Workbook
Name Average_emission_factor: '[1]Electricity emissions'!$H$38
Name BIDR: [2]Conversions!$E$76

Sheet About
A1: BASoBC BAU Amount Spent on Building Components
A2: Source:
A3: 1. BASoBC for US model | B3: Amount Spent on Components(Sheets:Commercial, Residential) | D3: Urban vs. Rural Residential Households
B4: Energy Information Administration | D4: Energy Information Administration
B5: 2015 | D5: 2013
B6: National Energy Modeling System 2015 Output Data | D6: Residential Energy Consumption Survey (RECS)
B7: Available upon request from EIA (no download link) | D7: http://www.eia.gov/consumption/residential/data/2009/
D8: Table HC2.1
A10: 2.Population | B10: HK Population Estimates (History data) | D10: HK Population Projections for 2017-2066 | F10: U.S. Historical Population (2014 and before) | H10: U.S. Population Projections (2015+)
B11: Census and Statistics Department, HK | D11: Census and Statistics Department, HK | F11: U.S. Census Bureau | H11: U.S. Census Bureau
B12: 2022 | D12: 2023 | F12: 2015 | H12: 2014
B13: Table 1.1 Mid Year Population by Age Group and Sex | D13: Table 150-11001 : Projected Mid-Year Population by Sex and Age Group | F13: Population Estimates: National Totals (Vintage 2015) | H13: National Population Projectons
B14: https://www.censtatd.gov.hk/en/data/stat_report/product/B1130303/att/B11303032022AN22B0100.pdf | D14: https://www.censtatd.gov.hk/en/web_table.html?id=150-11001 | F14: https://www.census.gov/popest/data/national/totals/2015/index.html | H14: https://www.census.gov/population/projections/files/summary/NP2014-T1.xls
D15: Annex Page | H15: Table 1
A17: 3. Energy Consumption | B17: HK Residential BAU Components Energy Use (Resi Ener HK) | D17: HK Commercial BAU Components Energy Use (Cmrc Ener HK) | F17: US Residential BAU Components Energy Use (Resi Ener US) | H17: US Commercial BAU Components Energy Use (Cmrc Ener US)
B18: InputData for HK EPS Model | D18: InputData for HK EPS Model | F18: InputData for HK EPS Model | H18: InputData for HK EPS Model
B19: bldg-BCEU | D19: bldg-BCEU | F19: bldg-BCEU | H19: bldg-BCEU
B20: Sheet: Residential_Final | D20: Sheet: Commercial_Final | F20: Copied from different sheets(colored darkblue) | H20: Copied from different sheets(colored darkblue)
A22: 4.Building Area | B22: HK Residential Area History Data | D22: HK Residential Area Prediction | F22: HK Commercial Area Prediction
B23: Census and Statistics Department, HK | D23: Census and Statistics Department, HK | F23: Rating and Valuation Department
B24: 2019 | D24: 2023 | F24: 2023
B25: Table 005 : Statistics on Domestic Households | D25: Table E485 : Hong Kong Domestic Household Projections | F25: Hong Kong Property Review 2023 - Preliminary Findings
B26: https://www.censtatd.gov.hk/en/scode190.html | D26: https://www.censtatd.gov.hk/en/web_table.html?id=150-12001k/hkstat/sub/sp190.jsp?productCode=D5320185 | F26: https://www.rvd.gov.hk/doc/en/HKPR2023_Preliminary_Findings_Eng.pdf
B28: US Residential Building Area (AEO T4) | D28: US Commercial Building Area (AEO T5)
B29: EIA | D29: EIA
B30: 2017 | D30: 2017
B31: Annual Energy Outlook 2017 | D31: Annual Energy Outlook 2017
B32: https://www.eia.gov/outlooks/aeo/excel/aeotab_4.xlsx | D32: https://www.eia.gov/outlooks/aeo/excel/aeotab_5.xlsx
B33: 4. Residential Sector Key Indicators and Consumption | D33: 5. Commercial Sector Key Indicators and Consumption
A35: 5. Urban vs Rural(HK) | B35: Building 2016 Data
B36: From Xiaoqian Jiang
B37: 2017
B38: From Excel "Copy of HK 2016 end use energy consumption rough 20190226 (added the building waste) revised2 lawrence.xlsx", Sheet"Building"
A40: 6.GDP | B40: HK National Income(GDP_Histo_census) | D40: U.S. GDP ,historical and projection (sheet: US Data) | F40: U.S. GDP (for checking the GDP from the left souce) | H40: U.S. GDP (also for checking)
B41: Census and Statistics Department, HK | D41: From Wenyi XI | F41: IIASA SSP database | H41: EIU Countrydata
B42: 2019 | D42: 2019 | F42: 2019 | H42: 2018
B43: Table 030: National Income | D43: Excel:"scaling-factors" | F43: SSP2 Scenario GDP projections | H43: Long term GDP projections for US
B44: https://www.censtatd.gov.hk/gb/?param=b5uniS&url=http://www.censtatd.gov.hk/hkstat/sub/sp250_tc.jsp?tableID=030&ID=0&productType=8 | F44: https://tntcat.iiasa.ac.at/SspDb/dsd?Action=htmlpage&page=about | H44: http://country.eiu.com/article.aspx?articleid=1647186748&Country=United%20States&topic=Economy&subtopic=Long-term+outlook&subsubtopic=Summary
B45: "Download longer data series" at the bottom of the page
A47: 7.CPI | B47: US CPI(1990-2018) | D47: US CPI(Only future estimation is used)
B48: U.S. Bureau of Labor Statistics | D48: EIU Country Data
B49: 2017 | D49: Export table in 2019-04-04
B50: Historical CPI-U, February 2019 | D50: LCPI
B51: https://www.bls.gov/cpi/tables/supplemental-files/historical-cpi-u-201902.pdf | D51: https://eiu.bvdinfo.com
B52: Page 4
A54: Note: Updated 19/04/04, according to Roman's advice on scaling factors and HK's status
A55: Method:
A56: We do not have data for HK, so we scale U.S. data by the average of the ratios
A57: of HK-to-US ①building floor area and ② (urban/rural) BAU Components Energy Use (from BCEU inputdata sheet)
A59: For the breakdown between urban and rural investment:
A60: 1.The US total residential investment is first scaled, and then distributed to urban/rural accourding to
A61: the ratio of total household units of HK urban/rural households in 2016. We suppose that the share of
A62: total household unit ratio between urban/rural are always the same as those in 2016. The same goes for commercial sector.
A63: I use US total residential investment, not US urban/rural residential investment, for scaling, because I think
A64: US and HK have different urbanization level and the ratio between urban and rural investment scales should not be fixed at the first step.
A65: Another reason is that we only have future projection of total residential building area for scaling.
A66: Also, note that, for the scaling factor, the (Ratio of Urban/rural specific per capita energy use multiplied by Total Residential Building Area) is taken,
... A80: We adjust 2013 dollars to 2018 dollars using the following conversion factor:
A81: 1.078 | B81: Please see sheet "US CPI" for full US CPI information
A84: note by Roman:
A85: Our energy use per capita for some building end uses compared to US values rises significantly.
A87: E.g. the ratio of energy use for lighting per capita rises from 0.39 in 2014 to 1.42 in 2050.
A88: Part of the reason might be that the US BAU builds in some assumptions on efficiency increases that we are missing for HK might have to think about how to add that.
A90: The sheet "scaling factor" is quite interesting for benchmarking with US values, in particular rows 70-87 on ratios of different energy end uses per capita.
A92: For the scaling, we might want to just use the ratio HK/US of total energy end-uses for the amount spent on components.
A94: note by Wing on 300823:
A95: did not update item 2: population, because the population folder from trans has updated, can directly use that

Sheet CPI
A1: Year | B1: CPI-U | C1: Multiply by to get 2018 Dollars
A2: 1990 | B2: 130.7 | C2: =B$30/B2 -> 1.9212471
A3: 1991 | B3: 136.2 | C3: =B$30/B3 -> 1.8436637 | G3: Historical Data | H3: From U.S. Bureau of Labor Statistics
A4: 1992 | B4: 140.3 | C4: =B$30/B4 -> 1.7897862 | G4: Estimation | H4: From EIU Countrydata Database
A5: 1993 | B5: 144.5 | C5: =B$30/B5 -> 1.7377647
A6: 1994 | B6: 148.2 | C6: =B$30/B6 -> 1.6943792
A7: 1995 | B7: 152.4 | C7: =B$30/B7 -> 1.6476837
A8: 1996 | B8: 156.9 | C8: =B$30/B8 -> 1.600427
A9: 1997 | B9: 160.5 | C9: =B$30/B9 -> 1.5645296
A10: 1998 | B10: 163 | C10: =B$30/B10 -> 1.5405337
A11: 1999 | B11: 166.6 | C11: =B$30/B11 -> 1.5072449
A12: 2000 | B12: 172.2 | C12: =B$30/B12 -> 1.4582288
A13: 2001 | B13: 177.1 | C13: =B$30/B13 -> 1.4178826
A14: 2002 | B14: 179.9 | C14: =B$30/B14 -> 1.3958143
A15: 2003 | B15: 184 | C15: =B$30/B15 -> 1.364712
A16: 2004 | B16: 188.9 | C16: =B$30/B16 -> 1.3293118
... A30: 2018 | B30: 251.107 | C30: =B$30/B30 -> 1
A31: 2019 | B31: ='CPI-EIU'!F46 -> 256.5 | C31: =B$30/B31 -> 0.97897466
A32: 2020 | B32: ='CPI-EIU'!F47 -> 260.1 | C32: =B$30/B32 -> 0.96542484
A33: 2021 | B33: ='CPI-EIU'!F48 -> 265.8 | C33: =B$30/B33 -> 0.9447216
A34: 2022 | B34: ='CPI-EIU'!F49 -> 271.3 | C34: =B$30/B34 -> 0.92556948
A35: 2023 | B35: ='CPI-EIU'!F50 -> 276.3 | C35: =B$30/B35 -> 0.90882012
A36: 2024 | B36: ='CPI-EIU'!F51 -> 280.9 | C36: =B$30/B36 -> 0.89393734
A37: 2025 | B37: ='CPI-EIU'!F52 -> 285.7 | C37: =B$30/B37 -> 0.87891845
A38: 2026 | B38: ='CPI-EIU'!F53 -> 290.6 | C38: =B$30/B38 -> 0.86409842
A39: 2027 | B39: ='CPI-EIU'!F54 -> 295.6 | C39: =B$30/B39 -> 0.84948241
A40: 2028 | B40: ='CPI-EIU'!F55 -> 300.7 | C40: =B$30/B40 -> 0.83507483
A41: 2029 | B41: ='CPI-EIU'!F56 -> 306 | C41: =B$30/B41 -> 0.82061111
A42: 2030 | B42: ='CPI-EIU'!F57 -> 311.5 | C42: =B$30/B42 -> 0.80612199
... A62: 2050 | B62: ='CPI-EIU'!F77 -> 458.6 | C62: =B$30/B62 -> 0.54755124

Sheet CPI-EIU
A4: United States of America
A6: Year | C6: Unit | F6: LCPI
A7: 1980 | F7: 82.383
A8: 1981 | F8: 90.933
A9: 1982 | F9: 96.533
A10: 1983 | F10: 99.583
A11: 1984 | F11: 103.933
A12: 1985 | F12: 107.6
A13: 1986 | F13: 109.692
A14: 1987 | F14: 113.617
A15: 1988 | F15: 118.275
A16: 1989 | F16: 123.942
A17: 1990 | F17: 130.658
A18: 1991 | F18: 136.167
... A77: 2050 | F77: 458.6
B79: Actual | E79: Forecast
A82: Consumer price index (av) - LCPI

Sheet Commercial
B2: Billions of 2013$
B4: Capital Invest: total installed capital cost of major end-use equipment paid by consumer (excludes federal or utility incentives)
B5: Subsidy Invest: federal equipment subsidies (e.g., investment tax credits for solar water heaters and ground-source heat pumps)
B7: Sum of Amount | E7: Year
B8: Division | C8: EndUse | D8: Label | E8: 2004 | F8: 2005 | G8: 2006 | H8: 2007 | I8: 2008 | J8: 2009 | K8: 2010 | L8: 2011 | M8: 2012 | N8: 2013 | O8: 2014 | P8: 2015 | Q8: 2016 | R8: 2017 | S8: 2018 | T8: 2019 | U8: 2020 | V8: 2021 | W8: 2022 | X8: 2023 | Y8: 2024 | Z8: 2025 | AA8: 2026 | AB8: 2027 | AC8: 2028 | AD8: 2029 | AE8: 2030 | AF8: 2031 | AG8: 2032 | AH8: 2033 | AI8: 2034 | AJ8: 2035 | AK8: 2036 | AL8: 2037 | AM8: 2038 | AN8: 2039 | AO8: 2040
B9: 1 New England | C9: 1 Heating | D9: Capital Invest | E9: 0.355 | F9: 0.377 | G9: 0.389 | H9: 0.38 | I9: 0.406 | J9: 0.339 | K9: 0.323 | L9: 0.317 | M9: 0.324 | N9: 0.317 | O9: 0.313 | P9: 0.31 | Q9: 0.31 | R9: 0.321 | S9: 0.322 | T9: 0.322 | U9: 0.318 | V9: 0.317 | W9: 0.316 | X9: 0.314 | Y9: 0.311 | Z9: 0.31 | AA9: 0.308 | AB9: 0.307 | AC9: 0.305 | AD9: 0.304 | AE9: 0.304 | AF9: 0.302 | AG9: 0.303 | AH9: 0.303 | AI9: 0.303 | AJ9: 0.304 | AK9: 0.306 | AL9: 0.305 | AM9: 0.305 | AN9: 0.304 | AO9: 0.302
D10: Subsidy Invest | E10: 0 | F10: 0 | G10: 0 | H10: 0 | I10: 0.012 | J10: 0.011 | K10: 0.01 | L10: 0.01 | M10: 0.01 | N10: 0.009 | O10: 0.009 | P10: 0.009 | Q10: 0.009 | R10: 0 | S10: 0 | T10: 0 | U10: 0 | V10: 0 | W10: 0 | X10: 0 | Y10: 0 | Z10: 0 | AA10: 0 | AB10: 0 | AC10: 0 | AD10: 0 | AE10: 0 | AF10: 0 | AG10: 0 | AH10: 0 | AI10: 0 | AJ10: 0 | AK10: 0 | AL10: 0 | AM10: 0 | AN10: 0 | AO10: 0
C11: 1 Heating Total | E11: 0.355 | F11: 0.377 | G11: 0.389 | H11: 0.38 | I11: 0.418 | J11: 0.35 | K11: 0.333 | L11: 0.327 | M11: 0.334 | N11: 0.326 | O11: 0.322 | P11: 0.319 | Q11: 0.319 | R11: 0.321 | S11: 0.322 | T11: 0.322 | U11: 0.318 | V11: 0.317 | W11: 0.316 | X11: 0.314 | Y11: 0.311 | Z11: 0.31 | AA11: 0.308 | AB11: 0.307 | AC11: 0.305 | AD11: 0.304 | AE11: 0.304 | AF11: 0.302 | AG11: 0.303 | AH11: 0.303 | AI11: 0.303 | AJ11: 0.304 | AK11: 0.306 | AL11: 0.305 | AM11: 0.305 | AN11: 0.304 | AO11: 0.302
C12: 2 Cooling | D12: Capital Invest | E12: 0.273 | F12: 0.231 | G12: 0.235 | H12: 0.234 | I12: 0.233 | J12: 0.231 | K12: 0.29 | L12: 0.279 | M12: 0.285 | N12: 0.272 | O12: 0.285 | P12: 0.277 | Q12: 0.277 | R12: 0.28 | S12: 0.28 | T12: 0.279 | U12: 0.278 | V12: 0.277 | W12: 0.276 | X12: 0.274 | Y12: 0.272 | Z12: 0.271 | AA12: 0.27 | AB12: 0.268 | AC12: 0.268 | AD12: 0.267 | AE12: 0.266 | AF12: 0.266 | AG12: 0.267 | AH12: 0.267 | AI12: 0.268 | AJ12: 0.269 | AK12: 0.27 | AL12: 0.269 | AM12: 0.269 | AN12: 0.267 | AO12: 0.266
D13: Subsidy Invest | E13: 0 | F13: 0 | G13: 0 | H13: 0 | I13: 0 | J13: 0 | K13: 0 | L13: 0 | M13: 0 | N13: 0 | O13: 0 | P13: 0 | Q13: 0 | R13: 0 | S13: 0 | T13: 0 | U13: 0 | V13: 0 | W13: 0 | X13: 0 | Y13: 0 | Z13: 0 | AA13: 0 | AB13: 0 | AC13: 0 | AD13: 0 | AE13: 0 | AF13: 0 | AG13: 0 | AH13: 0 | AI13: 0 | AJ13: 0 | AK13: 0 | AL13: 0 | AM13: 0 | AN13: 0 | AO13: 0
C14: 2 Cooling Total | E14: 0.273 | F14: 0.231 | G14: 0.235 | H14: 0.234 | I14: 0.233 | J14: 0.231 | K14: 0.29 | L14: 0.279 | M14: 0.285 | N14: 0.272 | O14: 0.285 | P14: 0.277 | Q14: 0.277 | R14: 0.28 | S14: 0.28 | T14: 0.279 | U14: 0.278 | V14: 0.277 | W14: 0.276 | X14: 0.274 | Y14: 0.272 | Z14: 0.271 | AA14: 0.27 | AB14: 0.268 | AC14: 0.268 | AD14: 0.267 | AE14: 0.266 | AF14: 0.266 | AG14: 0.267 | AH14: 0.267 | AI14: 0.268 | AJ14: 0.269 | AK14: 0.27 | AL14: 0.269 | AM14: 0.269 | AN14: 0.267 | AO14: 0.266
C15: 3 Water Heating | D15: Capital Invest | E15: 0.026 | F15: 0.027 | G15: 0.031 | H15: 0.031 | I15: 0.036 | J15: 0.033 | K15: 0.032 | L15: 0.031 | M15: 0.032 | N15: 0.033 | O15: 0.032 | P15: 0.032 | Q15: 0.031 | R15: 0.031 | S15: 0.031 | T15: 0.032 | U15: 0.033 | V15: 0.034 | W15: 0.034 | X15: 0.035 | Y15: 0.036 | Z15: 0.036 | AA15: 0.036 | AB15: 0.036 | AC15: 0.036 | AD15: 0.037 | AE15: 0.036 | AF15: 0.037 | AG15: 0.037 | AH15: 0.038 | AI15: 0.038 | AJ15: 0.039 | AK15: 0.039 | AL15: 0.039 | AM15: 0.04 | AN15: 0.04 | AO15: 0.04
D16: Subsidy Invest | E16: 0 | F16: 0 | G16: 0.003 | H16: 0.003 | I16: 0.007 | J16: 0.006 | K16: 0.006 | L16: 0.005 | M16: 0.005 | N16: 0.005 | O16: 0.005 | P16: 0.005 | Q16: 0.004 | R16: 0.001 | S16: 0.001 | T16: 0.001 | U16: 0.001 | V16: 0.001 | W16: 0.001 | X16: 0.001 | Y16: 0.001 | Z16: 0.001 | AA16: 0.001 | AB16: 0.001 | AC16: 0.001 | AD16: 0.001 | AE16: 0.001 | AF16: 0.001 | AG16: 0.001 | AH16: 0.001 | AI16: 0.001 | AJ16: 0.001 | AK16: 0.001 | AL16: 0.001 | AM16: 0.001 | AN16: 0.001 | AO16: 0.001
C17: 3 Water Heating Total | E17: 0.026 | F17: 0.027 | G17: 0.034 | H17: 0.034 | I17: 0.043 | J17: 0.039 | K17: 0.038 | L17: 0.036 | M17: 0.037 | N17: 0.038 | O17: 0.037 | P17: 0.037 | Q17: 0.035 | R17: 0.032 | S17: 0.032 | T17: 0.033 | U17: 0.034 | V17: 0.035 | W17: 0.035 | X17: 0.036 | Y17: 0.037 | Z17: 0.037 | AA17: 0.037 | AB17: 0.037 | AC17: 0.037 | AD17: 0.038 | AE17: 0.037 | AF17: 0.038 | AG17: 0.038 | AH17: 0.039 | AI17: 0.039 | AJ17: 0.04 | AK17: 0.04 | AL17: 0.04 | AM17: 0.041 | AN17: 0.041 | AO17: 0.041
C18: 4 Ventilation | D18: Capital Invest | E18: 0.723 | F18: 0.732 | G18: 0.762 | H18: 0.744 | I18: 0.775 | J18: 0.743 | K18: 0.717 | L18: 0.695 | M18: 0.721 | N18: 0.709 | O18: 0.716 | P18: 0.727 | Q18: 0.733 | R18: 0.749 | S18: 0.76 | T18: 0.775 | U18: 0.782 | V18: 0.789 | W18: 0.794 | X18: 0.796 | Y18: 0.798 | Z18: 0.8 | AA18: 0.801 | AB18: 0.802 | AC18: 0.804 | AD18: 0.809 | AE18: 0.814 | AF18: 0.823 | AG18: 0.836 | AH18: 0.849 | AI18: 0.865 | AJ18: 0.882 | AK18: 0.9 | AL18: 0.912 | AM18: 0.922 | AN18: 0.928 | AO18: 0.934
D19: Subsidy Invest | E19: 0 | F19: 0 | G19: 0 | H19: 0 | I19: 0 | J19: 0 | K19: 0 | L19: 0 | M19: 0 | N19: 0 | O19: 0 | P19: 0 | Q19: 0 | R19: 0 | S19: 0 | T19: 0 | U19: 0 | V19: 0 | W19: 0 | X19: 0 | Y19: 0 | Z19: 0 | AA19: 0 | AB19: 0 | AC19: 0 | AD19: 0 | AE19: 0 | AF19: 0 | AG19: 0 | AH19: 0 | AI19: 0 | AJ19: 0 | AK19: 0 | AL19: 0 | AM19: 0 | AN19: 0 | AO19: 0
C20: 4 Ventilation Total | E20: 0.723 | F20: 0.732 | G20: 0.762 | H20: 0.744 | I20: 0.775 | J20: 0.743 | K20: 0.717 | L20: 0.695 | M20: 0.721 | N20: 0.709 | O20: 0.716 | P20: 0.727 | Q20: 0.733 | R20: 0.749 | S20: 0.76 | T20: 0.775 | U20: 0.782 | V20: 0.789 | W20: 0.794 | X20: 0.796 | Y20: 0.798 | Z20: 0.8 | AA20: 0.801 | AB20: 0.802 | AC20: 0.804 | AD20: 0.809 | AE20: 0.814 | AF20: 0.823 | AG20: 0.836 | AH20: 0.849 | AI20: 0.865 | AJ20: 0.882 | AK20: 0.9 | AL20: 0.912 | AM20: 0.922 | AN20: 0.928 | AO20: 0.934
C21: 5 Cooking | D21: Capital Invest | E21: 0.017 | F21: 0.017 | G21: 0.018 | H21: 0.018 | I21: 0.019 | J21: 0.018 | K21: 0.018 | L21: 0.018 | M21: 0.018 | N21: 0.017 | O21: 0.017 | P21: 0.017 | Q21: 0.017 | R21: 0.018 | S21: 0.018 | T21: 0.018 | U21: 0.018 | V21: 0.019 | W21: 0.019 | X21: 0.019 | Y21: 0.019 | Z21: 0.019 | AA21: 0.019 | AB21: 0.019 | AC21: 0.019 | AD21: 0.019 | AE21: 0.019 | AF21: 0.02 | AG21: 0.02 | AH21: 0.02 | AI21: 0.02 | AJ21: 0.02 | AK21: 0.021 | AL21: 0.021 | AM21: 0.021 | AN21: 0.021 | AO21: 0.021
D22: Subsidy Invest | E22: 0 | F22: 0 | G22: 0 | H22: 0 | I22: 0 | J22: 0 | K22: 0 | L22: 0 | M22: 0 | N22: 0 | O22: 0 | P22: 0 | Q22: 0 | R22: 0 | S22: 0 | T22: 0 | U22: 0 | V22: 0 | W22: 0 | X22: 0 | Y22: 0 | Z22: 0 | AA22: 0 | AB22: 0 | AC22: 0 | AD22: 0 | AE22: 0 | AF22: 0 | AG22: 0 | AH22: 0 | AI22: 0 | AJ22: 0 | AK22: 0 | AL22: 0 | AM22: 0 | AN22: 0 | AO22: 0
C23: 5 Cooking Total | E23: 0.017 | F23: 0.017 | G23: 0.018 | H23: 0.018 | I23: 0.019 | J23: 0.018 | K23: 0.018 | L23: 0.018 | M23: 0.018 | N23: 0.017 | O23: 0.017 | P23: 0.017 | Q23: 0.017 | R23: 0.018 | S23: 0.018 | T23: 0.018 | U23: 0.018 | V23: 0.019 | W23: 0.019 | X23: 0.019 | Y23: 0.019 | Z23: 0.019 | AA23: 0.019 | AB23: 0.019 | AC23: 0.019 | AD23: 0.019 | AE23: 0.019 | AF23: 0.02 | AG23: 0.02 | AH23: 0.02 | AI23: 0.02 | AJ23: 0.02 | AK23: 0.021 | AL23: 0.021 | AM23: 0.021 | AN23: 0.021 | AO23: 0.021
C24: 6 Lighting | D24: Capital Invest | E24: 0.062 | F24: 0.066 | G24: 0.073 | H24: 0.066 | I24: 0.089 | J24: 0.083 | K24: 0.079 | L24: 0.072 | M24: 0.072 | N24: 0.066 | O24: 0.064 | P24: 0.062 | Q24: 0.059 | R24: 0.06 | S24: 0.061 | T24: 0.063 | U24: 0.071 | V24: 0.072 | W24: 0.073 | X24: 0.073 | Y24: 0.073 | Z24: 0.073 | AA24: 0.073 | AB24: 0.073 | AC24: 0.073 | AD24: 0.074 | AE24: 0.073 | AF24: 0.072 | AG24: 0.073 | AH24: 0.073 | AI24: 0.074 | AJ24: 0.075 | AK24: 0.076 | AL24: 0.076 | AM24: 0.077 | AN24: 0.078 | AO24: 0.079
D25: Subsidy Invest | E25: 0 | F25: 0 | G25: 0 | H25: 0 | I25: 0 | J25: 0 | K25: 0 | L25: 0 | M25: 0 | N25: 0 | O25: 0 | P25: 0 | Q25: 0 | R25: 0 | S25: 0 | T25: 0 | U25: 0 | V25: 0 | W25: 0 | X25: 0 | Y25: 0 | Z25: 0 | AA25: 0 | AB25: 0 | AC25: 0 | AD25: 0 | AE25: 0 | AF25: 0 | AG25: 0 | AH25: 0 | AI25: 0 | AJ25: 0 | AK25: 0 | AL25: 0 | AM25: 0 | AN25: 0 | AO25: 0
C26: 6 Lighting Total | E26: 0.062 | F26: 0.066 | G26: 0.073 | H26: 0.066 | I26: 0.089 | J26: 0.083 | K26: 0.079 | L26: 0.072 | M26: 0.072 | N26: 0.066 | O26: 0.064 | P26: 0.062 | Q26: 0.059 | R26: 0.06 | S26: 0.061 | T26: 0.063 | U26: 0.071 | V26: 0.072 | W26: 0.073 | X26: 0.073 | Y26: 0.073 | Z26: 0.073 | AA26: 0.073 | AB26: 0.073 | AC26: 0.073 | AD26: 0.074 | AE26: 0.073 | AF26: 0.072 | AG26: 0.073 | AH26: 0.073 | AI26: 0.074 | AJ26: 0.075 | AK26: 0.076 | AL26: 0.076 | AM26: 0.077 | AN26: 0.078 | AO26: 0.079
C27: 7 Refrigeration | D27: Capital Invest | E27: 1.259 | F27: 1.315 | G27: 1.337 | H27: 1.33 | I27: 1.362 | J27: 1.464 | K27: 2.103 | L27: 2.013 | M27: 2.139 | N27: 2.038 | O27: 2.012 | P27: 2.008 | Q27: 2.011 | R27: 2.111 | S27: 2.114 | T27: 2.113 | U27: 2.112 | V27: 2.113 | W27: 2.113 | X27: 2.114 | Y27: 2.119 | Z27: 2.128 | AA27: 2.136 | AB27: 2.145 | AC27: 2.156 | AD27: 2.168 | AE27: 2.18 | AF27: 2.192 | AG27: 2.208 | AH27: 2.224 | AI27: 2.245 | AJ27: 2.269 | AK27: 2.289 | AL27: 2.307 | AM27: 2.321 | AN27: 2.329 | AO27: 2.334
D28: Subsidy Invest | E28: 0 | F28: 0 | G28: 0 | H28: 0 | I28: 0 | J28: 0 | K28: 0 | L28: 0 | M28: 0 | N28: 0 | O28: 0 | P28: 0 | Q28: 0 | R28: 0 | S28: 0 | T28: 0 | U28: 0 | V28: 0 | W28: 0 | X28: 0 | Y28: 0 | Z28: 0 | AA28: 0 | AB28: 0 | AC28: 0 | AD28: 0 | AE28: 0 | AF28: 0 | AG28: 0 | AH28: 0 | AI28: 0 | AJ28: 0 | AK28: 0 | AL28: 0 | AM28: 0 | AN28: 0 | AO28: 0
C29: 7 Refrigeration Total | E29: 1.259 | F29: 1.315 | G29: 1.337 | H29: 1.33 | I29: 1.362 | J29: 1.464 | K29: 2.103 | L29: 2.013 | M29: 2.139 | N29: 2.038 | O29: 2.012 | P29: 2.008 | Q29: 2.011 | R29: 2.111 | S29: 2.114 | T29: 2.113 | U29: 2.112 | V29: 2.113 | W29: 2.113 | X29: 2.114 | Y29: 2.119 | Z29: 2.128 | AA29: 2.136 | AB29: 2.145 | AC29: 2.156 | AD29: 2.168 | AE29: 2.18 | AF29: 2.192 | AG29: 2.208 | AH29: 2.224 | AI29: 2.245 | AJ29: 2.269 | AK29: 2.289 | AL29: 2.307 | AM29: 2.321 | AN29: 2.329 | AO29: 2.334
B30: 1 New England Total | E30: 2.715 | F30: 2.765 | G30: 2.848 | H30: 2.806 | I30: 2.939 | J30: 2.928 | K30: 3.578 | L30: 3.44 | M30: 3.606 | N30: 3.466 | O30: 3.453 | P30: 3.447 | Q30: 3.451 | R30: 3.571 | S30: 3.587 | T30: 3.603 | U30: 3.613 | V30: 3.622 | W30: 3.626 | X30: 3.626 | Y30: 3.629 | Z30: 3.638 | AA30: 3.644 | AB30: 3.651 | AC30: 3.662 | AD30: 3.679 | AE30: 3.693 | AF30: 3.713 | AG30: 3.745 | AH30: 3.775 | AI30: 3.814 | AJ30: 3.859 | AK30: 3.902 | AL30: 3.93 | AM30: 3.956 | AN30: 3.968 | AO30: 3.977
B31: 2 Middle Atlantic | C31: 1 Heating | D31: Capital Invest | E31: 1.049 | F31: 1.067 | G31: 1.075 | H31: 1.067 | I31: 1.128 | J31: 1.021 | K31: 0.961 | L31: 0.942 | M31: 0.932 | N31: 0.914 | O31: 0.898 | P31: 0.894 | Q31: 0.894 | R31: 0.911 | S31: 0.909 | T31: 0.908 | U31: 0.896 | V31: 0.893 | W31: 0.887 | X31: 0.878 | Y31: 0.869 | Z31: 0.862 | AA31: 0.856 | AB31: 0.849 | AC31: 0.843 | AD31: 0.838 | AE31: 0.833 | AF31: 0.827 | AG31: 0.827 | AH31: 0.824 | AI31: 0.821 | AJ31: 0.82 | AK31: 0.821 | AL31: 0.817 | AM31: 0.814 | AN31: 0.809 | AO31: 0.804
D32: Subsidy Invest | E32: 0 | F32: 0 | G32: 0 | H32: 0 | I32: 0.024 | J32: 0.022 | K32: 0.02 | L32: 0.019 | M32: 0.019 | N32: 0.017 | O32: 0.017 | P32: 0.017 | Q32: 0.016 | R32: 0 | S32: 0 | T32: 0 | U32: 0 | V32: 0 | W32: 0 | X32: 0 | Y32: 0 | Z32: 0 | AA32: 0 | AB32: 0 | AC32: 0 | AD32: 0 | AE32: 0 | AF32: 0 | AG32: 0 | AH32: 0 | AI32: 0 | AJ32: 0 | AK32: 0 | AL32: 0 | AM32: 0 | AN32: 0 | AO32: 0
C33: 1 Heating Total | E33: 1.049 | F33: 1.067 | G33: 1.075 | H33: 1.067 | I33: 1.152 | J33: 1.043 | K33: 0.981 | L33: 0.961 | M33: 0.951 | N33: 0.931 | O33: 0.915 | P33: 0.911 | Q33: 0.91 | R33: 0.911 | S33: 0.909 | T33: 0.908 | U33: 0.896 | V33: 0.893 | W33: 0.887 | X33: 0.878 | Y33: 0.869 | Z33: 0.862 | AA33: 0.856 | AB33: 0.849 | AC33: 0.843 | AD33: 0.838 | AE33: 0.833 | AF33: 0.827 | AG33: 0.827 | AH33: 0.824 | AI33: 0.821 | AJ33: 0.82 | AK33: 0.821 | AL33: 0.817 | AM33: 0.814 | AN33: 0.809 | AO33: 0.804
C34: 2 Cooling | D34: Capital Invest | E34: 0.916 | F34: 0.74 | G34: 0.752 | H34: 0.759 | I34: 0.751 | J34: 0.753 | K34: 0.763 | L34: 0.758 | M34: 0.745 | N34: 0.768 | O34: 0.776 | P34: 0.762 | Q34: 0.761 | R34: 0.764 | S34: 0.764 | T34: 0.764 | U34: 0.76 | V34: 0.757 | W34: 0.754 | X34: 0.748 | Y34: 0.742 | Z34: 0.738 | AA34: 0.734 | AB34: 0.729 | AC34: 0.726 | AD34: 0.723 | AE34: 0.721 | AF34: 0.72 | AG34: 0.722 | AH34: 0.725 | AI34: 0.728 | AJ34: 0.733 | AK34: 0.739 | AL34: 0.742 | AM34: 0.744 | AN34: 0.744 | AO34: 0.744
D35: Subsidy Invest | E35: 0 | F35: 0 | G35: 0 | H35: 0 | I35: 0 | J35: 0 | K35: 0 | L35: 0 | M35: 0 | N35: 0 | O35: 0 | P35: 0 | Q35: 0 | R35: 0 | S35: 0 | T35: 0 | U35: 0 | V35: 0 | W35: 0 | X35: 0 | Y35: 0 | Z35: 0 | AA35: 0 | AB35: 0 | AC35: 0 | AD35: 0 | AE35: 0 | AF35: 0 | AG35: 0 | AH35: 0 | AI35: 0 | AJ35: 0 | AK35: 0 | AL35: 0 | AM35: 0 | AN35: 0 | AO35: 0
C36: 2 Cooling Total | E36: 0.916 | F36: 0.74 | G36: 0.752 | H36: 0.759 | I36: 0.751 | J36: 0.753 | K36: 0.763 | L36: 0.758 | M36: 0.745 | N36: 0.768 | O36: 0.776 | P36: 0.762 | Q36: 0.761 | R36: 0.764 | S36: 0.764 | T36: 0.764 | U36: 0.76 | V36: 0.757 | W36: 0.754 | X36: 0.748 | Y36: 0.742 | Z36: 0.738 | AA36: 0.734 | AB36: 0.729 | AC36: 0.726 | AD36: 0.723 | AE36: 0.721 | AF36: 0.72 | AG36: 0.722 | AH36: 0.725 | AI36: 0.728 | AJ36: 0.733 | AK36: 0.739 | AL36: 0.742 | AM36: 0.744 | AN36: 0.744 | AO36: 0.744
C37: 3 Water Heating | D37: Capital Invest | E37: 0.084 | F37: 0.085 | G37: 0.09 | H37: 0.092 | I37: 0.099 | J37: 0.097 | K37: 0.093 | L37: 0.091 | M37: 0.091 | N37: 0.094 | O37: 0.09 | P37: 0.091 | Q37: 0.091 | R37: 0.091 | S37: 0.092 | T37: 0.093 | U37: 0.095 | V37: 0.096 | W37: 0.096 | X37: 0.097 | Y37: 0.097 | Z37: 0.098 | AA37: 0.098 | AB37: 0.098 | AC37: 0.098 | AD37: 0.098 | AE37: 0.099 | AF37: 0.1 | AG37: 0.101 | AH37: 0.102 | AI37: 0.102 | AJ37: 0.103 | AK37: 0.105 | AL37: 0.107 | AM37: 0.108 | AN37: 0.108 | AO37: 0.109
D38: Subsidy Invest | E38: 0 | F38: 0 | G38: 0.004 | H38: 0.004 | I38: 0.007 | J38: 0.007 | K38: 0.007 | L38: 0.007 | M38: 0.007 | N38: 0.006 | O38: 0.005 | P38: 0.005 | Q38: 0.005 | R38: 0.001 | S38: 0.001 | T38: 0.001 | U38: 0.001 | V38: 0.001 | W38: 0.001 | X38: 0.001 | Y38: 0.001 | Z38: 0.001 | AA38: 0.001 | AB38: 0.001 | AC38: 0.001 | AD38: 0.001 | AE38: 0.001 | AF38: 0.001 | AG38: 0.001 | AH38: 0.001 | AI38: 0.001 | AJ38: 0.001 | AK38: 0.001 | AL38: 0.001 | AM38: 0.001 | AN38: 0.001 | AO38: 0.001
C39: 3 Water Heating Total | E39: 0.084 | F39: 0.085 | G39: 0.094 | H39: 0.096 | I39: 0.106 | J39: 0.104 | K39: 0.1 | L39: 0.098 | M39: 0.098 | N39: 0.1 | O39: 0.095 | P39: 0.096 | Q39: 0.096 | R39: 0.092 | S39: 0.093 | T39: 0.094 | U39: 0.096 | V39: 0.097 | W39: 0.097 | X39: 0.098 | Y39: 0.098 | Z39: 0.099 | AA39: 0.099 | AB39: 0.099 | AC39: 0.099 | AD39: 0.099 | AE39: 0.1 | AF39: 0.101 | AG39: 0.102 | AH39: 0.103 | AI39: 0.103 | AJ39: 0.104 | AK39: 0.106 | AL39: 0.108 | AM39: 0.109 | AN39: 0.109 | AO39: 0.11
C40: 4 Ventilation | D40: Capital Invest | E40: 3.15 | F40: 3.119 | G40: 3.169 | H40: 3.214 | I40: 3.278 | J40: 3.208 | K40: 3.07 | L40: 3.012 | M40: 3.014 | N40: 2.976 | O40: 2.97 | P40: 3.009 | Q40: 3.046 | R40: 3.093 | S40: 3.124 | T40: 3.156 | U40: 3.172 | V40: 3.193 | W40: 3.207 | X40: 3.21 | Y40: 3.219 | Z40: 3.226 | AA40: 3.234 | AB40: 3.238 | AC40: 3.252 | AD40: 3.266 | AE40: 3.282 | AF40: 3.308 | AG40: 3.352 | AH40: 3.401 | AI40: 3.45 | AJ40: 3.506 | AK40: 3.566 | AL40: 3.61 | AM40: 3.648 | AN40: 3.677 | AO40: 3.702
D41: Subsidy Invest | E41: 0 | F41: 0 | G41: 0 | H41: 0 | I41: 0 | J41: 0 | K41: 0 | L41: 0 | M41: 0 | N41: 0 | O41: 0 | P41: 0 | Q41: 0 | R41: 0 | S41: 0 | T41: 0 | U41: 0 | V41: 0 | W41: 0 | X41: 0 | Y41: 0 | Z41: 0 | AA41: 0 | AB41: 0 | AC41: 0 | AD41: 0 | AE41: 0 | AF41: 0 | AG41: 0 | AH41: 0 | AI41: 0 | AJ41: 0 | AK41: 0 | AL41: 0 | AM41: 0 | AN41: 0 | AO41: 0
C42: 4 Ventilation Total | E42: 3.15 | F42: 3.119 | G42: 3.169 | H42: 3.214 | I42: 3.278 | J42: 3.208 | K42: 3.07 | L42: 3.012 | M42: 3.014 | N42: 2.976 | O42: 2.97 | P42: 3.009 | Q42: 3.046 | R42: 3.093 | S42: 3.124 | T42: 3.156 | U42: 3.172 | V42: 3.193 | W42: 3.207 | X42: 3.21 | Y42: 3.219 | Z42: 3.226 | AA42: 3.234 | AB42: 3.238 | AC42: 3.252 | AD42: 3.266 | AE42: 3.282 | AF42: 3.308 | AG42: 3.352 | AH42: 3.401 | AI42: 3.45 | AJ42: 3.506 | AK42: 3.566 | AL42: 3.61 | AM42: 3.648 | AN42: 3.677 | AO42: 3.702
C43: 5 Cooking | D43: Capital Invest | E43: 0.072 | F43: 0.073 | G43: 0.073 | H43: 0.074 | I43: 0.079 | J43: 0.074 | K43: 0.072 | L43: 0.071 | M43: 0.07 | N43: 0.071 | O43: 0.067 | P43: 0.068 | Q43: 0.068 | R43: 0.069 | S43: 0.07 | T43: 0.07 | U43: 0.071 | V43: 0.074 | W43: 0.074 | X43: 0.074 | Y43: 0.075 | Z43: 0.075 | AA43: 0.075 | AB43: 0.076 | AC43: 0.076 | AD43: 0.077 | AE43: 0.077 | AF43: 0.077 | AG43: 0.078 | AH43: 0.078 | AI43: 0.079 | AJ43: 0.079 | AK43: 0.08 | AL43: 0.081 | AM43: 0.081 | AN43: 0.082 | AO43: 0.082
D44: Subsidy Invest | E44: 0 | F44: 0 | G44: 0 | H44: 0 | I44: 0 | J44: 0 | K44: 0 | L44: 0 | M44: 0 | N44: 0 | O44: 0 | P44: 0 | Q44: 0 | R44: 0 | S44: 0 | T44: 0 | U44: 0 | V44: 0 | W44: 0 | X44: 0 | Y44: 0 | Z44: 0 | AA44: 0 | AB44: 0 | AC44: 0 | AD44: 0 | AE44: 0 | AF44: 0 | AG44: 0 | AH44: 0 | AI44: 0 | AJ44: 0 | AK44: 0 | AL44: 0 | AM44: 0 | AN44: 0 | AO44: 0
C45: 5 Cooking Total | E45: 0.072 | F45: 0.073 | G45: 0.073 | H45: 0.074 | I45: 0.079 | J45: 0.074 | K45: 0.072 | L45: 0.071 | M45: 0.07 | N45: 0.071 | O45: 0.067 | P45: 0.068 | Q45: 0.068 | R45: 0.069 | S45: 0.07 | T45: 0.07 | U45: 0.071 | V45: 0.074 | W45: 0.074 | X45: 0.074 | Y45: 0.075 | Z45: 0.075 | AA45: 0.075 | AB45: 0.076 | AC45: 0.076 | AD45: 0.077 | AE45: 0.077 | AF45: 0.077 | AG45: 0.078 | AH45: 0.078 | AI45: 0.079 | AJ45: 0.079 | AK45: 0.08 | AL45: 0.081 | AM45: 0.081 | AN45: 0.082 | AO45: 0.082
C46: 6 Lighting | D46: Capital Invest | E46: 0.209 | F46: 0.207 | G46: 0.219 | H46: 0.204 | I46: 0.274 | J46: 0.262 | K46: 0.256 | L46: 0.233 | M46: 0.224 | N46: 0.212 | O46: 0.192 | P46: 0.191 | Q46: 0.192 | R46: 0.193 | S46: 0.195 | T46: 0.199 | U46: 0.217 | V46: 0.22 | W46: 0.223 | X46: 0.223 | Y46: 0.223 | Z46: 0.225 | AA46: 0.228 | AB46: 0.227 | AC46: 0.227 | AD46: 0.227 | AE46: 0.225 | AF46: 0.224 | AG46: 0.226 | AH46: 0.228 | AI46: 0.229 | AJ46: 0.231 | AK46: 0.233 | AL46: 0.235 | AM46: 0.239 | AN46: 0.24 | AO46: 0.243
D47: Subsidy Invest | E47: 0 | F47: 0 | G47: 0 | H47: 0 | I47: 0 | J47: 0 | K47: 0 | L47: 0 | M47: 0 | N47: 0 | O47: 0 | P47: 0 | Q47: 0 | R47: 0 | S47: 0 | T47: 0 | U47: 0 | V47: 0 | W47: 0 | X47: 0 | Y47: 0 | Z47: 0 | AA47: 0 | AB47: 0 | AC47: 0 | AD47: 0 | AE47: 0 | AF47: 0 | AG47: 0 | AH47: 0 | AI47: 0 | AJ47: 0 | AK47: 0 | AL47: 0 | AM47: 0 | AN47: 0 | AO47: 0
C48: 6 Lighting Total | E48: 0.209 | F48: 0.207 | G48: 0.219 | H48: 0.204 | I48: 0.274 | J48: 0.262 | K48: 0.256 | L48: 0.233 | M48: 0.224 | N48: 0.212 | O48: 0.192 | P48: 0.191 | Q48: 0.192 | R48: 0.193 | S48: 0.195 | T48: 0.199 | U48: 0.217 | V48: 0.22 | W48: 0.223 | X48: 0.223 | Y48: 0.223 | Z48: 0.225 | AA48: 0.228 | AB48: 0.227 | AC48: 0.227 | AD48: 0.227 | AE48: 0.225 | AF48: 0.224 | AG48: 0.226 | AH48: 0.228 | AI48: 0.229 | AJ48: 0.231 | AK48: 0.233 | AL48: 0.235 | AM48: 0.239 | AN48: 0.24 | AO48: 0.243
C49: 7 Refrigeration | D49: Capital Invest | E49: 2.403 | F49: 2.443 | G49: 2.486 | H49: 2.5 | I49: 2.56 | J49: 2.749 | K49: 3.794 | L49: 3.665 | M49: 3.782 | N49: 3.681 | O49: 3.647 | P49: 3.639 | Q49: 3.633 | R49: 3.795 | S49: 3.789 | T49: 3.78 | U49: 3.764 | V49: 3.757 | W49: 3.749 | X49: 3.742 | Y49: 3.742 | Z49: 3.754 | AA49: 3.765 | AB49: 3.774 | AC49: 3.789 | AD49: 3.805 | AE49: 3.818 | AF49: 3.828 | AG49: 3.849 | AH49: 3.865 | AI49: 3.886 | AJ49: 3.915 | AK49: 3.952 | AL49: 3.978 | AM49: 3.999 | AN49: 4.011 | AO49: 4.021
D50: Subsidy Invest | E50: 0 | F50: 0 | G50: 0 | H50: 0 | I50: 0 | J50: 0 | K50: 0 | L50: 0 | M50: 0 | N50: 0 | O50: 0 | P50: 0 | Q50: 0 | R50: 0 | S50: 0 | T50: 0 | U50: 0 | V50: 0 | W50: 0 | X50: 0 | Y50: 0 | Z50: 0 | AA50: 0 | AB50: 0 | AC50: 0 | AD50: 0 | AE50: 0 | AF50: 0 | AG50: 0 | AH50: 0 | AI50: 0 | AJ50: 0 | AK50: 0 | AL50: 0 | AM50: 0 | AN50: 0 | AO50: 0
C51: 7 Refrigeration Total | E51: 2.403 | F51: 2.443 | G51: 2.486 | H51: 2.5 | I51: 2.56 | J51: 2.749 | K51: 3.794 | L51: 3.665 | M51: 3.782 | N51: 3.681 | O51: 3.647 | P51: 3.639 | Q51: 3.633 | R51: 3.795 | S51: 3.789 | T51: 3.78 | U51: 3.764 | V51: 3.757 | W51: 3.749 | X51: 3.742 | Y51: 3.742 | Z51: 3.754 | AA51: 3.765 | AB51: 3.774 | AC51: 3.789 | AD51: 3.805 | AE51: 3.818 | AF51: 3.828 | AG51: 3.849 | AH51: 3.865 | AI51: 3.886 | AJ51: 3.915 | AK51: 3.952 | AL51: 3.978 | AM51: 3.999 | AN51: 4.011 | AO51: 4.021
B52: 2 Middle Atlantic Total | E52: 7.883 | F52: 7.734 | G52: 7.868 | H52: 7.914 | I52: 8.2 | J52: 8.193 | K52: 9.036 | L52: 8.798 | M52: 8.884 | N52: 8.739 | O52: 8.662 | P52: 8.676 | Q52: 8.706 | R52: 8.917 | S52: 8.944 | T52: 8.971 | U52: 8.976 | V52: 8.991 | W52: 8.991 | X52: 8.973 | Y52: 8.968 | Z52: 8.979 | AA52: 8.991 | AB52: 8.992 | AC52: 9.012 | AD52: 9.035 | AE52: 9.056 | AF52: 9.085 | AG52: 9.156 | AH52: 9.224 | AI52: 9.296 | AJ52: 9.388 | AK52: 9.497 | AL52: 9.571 | AM52: 9.634 | AN52: 9.672 | AO52: 9.706
B53: 3 East North Central | C53: 1 Heating | D53: Capital Invest | E53: 1.795 | F53: 1.891 | G53: 1.965 | H53: 1.924 | I53: 2.007 | J53: 1.807 | K53: 1.701 | L53: 1.613 | M53: 1.605 | N53: 1.6 | O53: 1.623 | P53: 1.638 | Q53: 1.648 | R53: 1.685 | S53: 1.693 | T53: 1.699 | U53: 1.697 | V53: 1.701 | W53: 1.694 | X53: 1.682 | Y53: 1.67 | Z53: 1.665 | AA53: 1.666 | AB53: 1.651 | AC53: 1.644 | AD53: 1.64 | AE53: 1.635 | AF53: 1.635 | AG53: 1.65 | AH53: 1.677 | AI53: 1.683 | AJ53: 1.693 | AK53: 1.71 | AL53: 1.715 | AM53: 1.731 | AN53: 1.745 | AO53: 1.759
D54: Subsidy Invest | E54: 0 | F54: 0 | G54: 0 | H54: 0 | I54: 0.029 | J54: 0.026 | K54: 0.024 | L54: 0.022 | M54: 0.022 | N54: 0.021 | O54: 0.021 | P54: 0.021 | Q54: 0.021 | R54: 0 | S54: 0 | T54: 0 | U54: 0 | V54: 0 | W54: 0 | X54: 0 | Y54: 0 | Z54: 0 | AA54: 0 | AB54: 0 | AC54: 0 | AD54: 0 | AE54: 0 | AF54: 0 | AG54: 0 | AH54: 0 | AI54: 0 | AJ54: 0 | AK54: 0 | AL54: 0 | AM54: 0 | AN54: 0 | AO54: 0
C55: 1 Heating Total | E55: 1.795 | F55: 1.891 | G55: 1.965 | H55: 1.924 | I55: 2.036 | J55: 1.833 | K55: 1.725 | L55: 1.635 | M55: 1.627 | N55: 1.621 | O55: 1.644 | P55: 1.659 | Q55: 1.669 | R55: 1.685 | S55: 1.693 | T55: 1.699 | U55: 1.697 | V55: 1.701 | W55: 1.694 | X55: 1.682 | Y55: 1.67 | Z55: 1.665 | AA55: 1.666 | AB55: 1.651 | AC55: 1.644 | AD55: 1.64 | AE55: 1.635 | AF55: 1.635 | AG55: 1.65 | AH55: 1.677 | AI55: 1.683 | AJ55: 1.693 | AK55: 1.71 | AL55: 1.715 | AM55: 1.731 | AN55: 1.745 | AO55: 1.759
C56: 2 Cooling | D56: Capital Invest | E56: 0.718 | F56: 0.637 | G56: 0.655 | H56: 0.645 | I56: 0.663 | J56: 0.631 | K56: 0.612 | L56: 0.591 | M56: 0.58 | N56: 0.618 | O56: 0.616 | P56: 0.613 | Q56: 0.616 | R56: 0.621 | S56: 0.623 | T56: 0.624 | U56: 0.622 | V56: 0.62 | W56: 0.617 | X56: 0.612 | Y56: 0.607 | Z56: 0.604 | AA56: 0.601 | AB56: 0.598 | AC56: 0.595 | AD56: 0.593 | AE56: 0.591 | AF56: 0.591 | AG56: 0.593 | AH56: 0.595 | AI56: 0.599 | AJ56: 0.604 | AK56: 0.61 | AL56: 0.613 | AM56: 0.614 | AN56: 0.613 | AO56: 0.612
D57: Subsidy Invest | E57: 0 | F57: 0 | G57: 0 | H57: 0 | I57: 0 | J57: 0 | K57: 0 | L57: 0 | M57: 0 | N57: 0 | O57: 0 | P57: 0 | Q57: 0 | R57: 0 | S57: 0 | T57: 0 | U57: 0 | V57: 0 | W57: 0 | X57: 0 | Y57: 0 | Z57: 0 | AA57: 0 | AB57: 0 | AC57: 0 | AD57: 0 | AE57: 0 | AF57: 0 | AG57: 0 | AH57: 0 | AI57: 0 | AJ57: 0 | AK57: 0 | AL57: 0 | AM57: 0 | AN57: 0 | AO57: 0
C58: 2 Cooling Total | E58: 0.718 | F58: 0.637 | G58: 0.655 | H58: 0.645 | I58: 0.663 | J58: 0.631 | K58: 0.612 | L58: 0.591 | M58: 0.58 | N58: 0.618 | O58: 0.616 | P58: 0.613 | Q58: 0.616 | R58: 0.621 | S58: 0.623 | T58: 0.624 | U58: 0.622 | V58: 0.62 | W58: 0.617 | X58: 0.612 | Y58: 0.607 | Z58: 0.604 | AA58: 0.601 | AB58: 0.598 | AC58: 0.595 | AD58: 0.593 | AE58: 0.591 | AF58: 0.591 | AG58: 0.593 | AH58: 0.595 | AI58: 0.599 | AJ58: 0.604 | AK58: 0.61 | AL58: 0.613 | AM58: 0.614 | AN58: 0.613 | AO58: 0.612
C59: 3 Water Heating | D59: Capital Invest | E59: 0.09 | F59: 0.09 | G59: 0.096 | H59: 0.1 | I59: 0.108 | J59: 0.103 | K59: 0.099 | L59: 0.099 | M59: 0.097 | N59: 0.101 | O59: 0.101 | P59: 0.103 | Q59: 0.103 | R59: 0.105 | S59: 0.106 | T59: 0.107 | U59: 0.109 | V59: 0.11 | W59: 0.111 | X59: 0.112 | Y59: 0.112 | Z59: 0.113 | AA59: 0.114 | AB59: 0.114 | AC59: 0.114 | AD59: 0.115 | AE59: 0.118 | AF59: 0.12 | AG59: 0.122 | AH59: 0.124 | AI59: 0.125 | AJ59: 0.127 | AK59: 0.129 | AL59: 0.131 | AM59: 0.131 | AN59: 0.133 | AO59: 0.134
D60: Subsidy Invest | E60: 0 | F60: 0 | G60: 0.002 | H60: 0.002 | I60: 0.007 | J60: 0.007 | K60: 0.007 | L60: 0.007 | M60: 0.007 | N60: 0.004 | O60: 0.004 | P60: 0.004 | Q60: 0.004 | R60: 0.001 | S60: 0.001 | T60: 0.001 | U60: 0.001 | V60: 0.001 | W60: 0.001 | X60: 0.001 | Y60: 0.001 | Z60: 0.001 | AA60: 0.001 | AB60: 0.001 | AC60: 0.001 | AD60: 0.001 | AE60: 0.001 | AF60: 0.001 | AG60: 0.001 | AH60: 0.001 | AI60: 0.001 | AJ60: 0.001 | AK60: 0.001 | AL60: 0.001 | AM60: 0.001 | AN60: 0.001 | AO60: 0.001
C61: 3 Water Heating Total | E61: 0.09 | F61: 0.09 | G61: 0.098 | H61: 0.102 | I61: 0.115 | J61: 0.11 | K61: 0.106 | L61: 0.106 | M61: 0.104 | N61: 0.105 | O61: 0.105 | P61: 0.107 | Q61: 0.107 | R61: 0.106 | S61: 0.107 | T61: 0.108 | U61: 0.11 | V61: 0.111 | W61: 0.112 | X61: 0.113 | Y61: 0.113 | Z61: 0.114 | AA61: 0.115 | AB61: 0.115 | AC61: 0.115 | AD61: 0.116 | AE61: 0.119 | AF61: 0.121 | AG61: 0.123 | AH61: 0.125 | AI61: 0.126 | AJ61: 0.128 | AK61: 0.13 | AL61: 0.132 | AM61: 0.132 | AN61: 0.134 | AO61: 0.135
C62: 4 Ventilation | D62: Capital Invest | E62: 4.45 | F62: 4.503 | G62: 4.706 | H62: 4.706 | I62: 4.825 | J62: 4.634 | K62: 4.448 | L62: 4.223 | M62: 4.22 | N62: 4.295 | O62: 4.364 | P62: 4.463 | Q62: 4.553 | R62: 4.664 | S62: 4.743 | T62: 4.81 | U62: 4.852 | V62: 4.893 | W62: 4.918 | X62: 4.922 | Y62: 4.928 | Z62: 4.949 | AA62: 4.97 | AB62: 4.991 | AC62: 5.014 | AD62: 5.048 | AE62: 5.086 | AF62: 5.14 | AG62: 5.223 | AH62: 5.307 | AI62: 5.396 | AJ62: 5.497 | AK62: 5.608 | AL62: 5.692 | AM62: 5.767 | AN62: 5.831 | AO62: 5.886
D63: Subsidy Invest | E63: 0 | F63: 0 | G63: 0 | H63: 0 | I63: 0 | J63: 0 | K63: 0 | L63: 0 | M63: 0 | N63: 0 | O63: 0 | P63: 0 | Q63: 0 | R63: 0 | S63: 0 | T63: 0 | U63: 0 | V63: 0 | W63: 0 | X63: 0 | Y63: 0 | Z63: 0 | AA63: 0 | AB63: 0 | AC63: 0 | AD63: 0 | AE63: 0 | AF63: 0 | AG63: 0 | AH63: 0 | AI63: 0 | AJ63: 0 | AK63: 0 | AL63: 0 | AM63: 0 | AN63: 0 | AO63: 0
C64: 4 Ventilation Total | E64: 4.45 | F64: 4.503 | G64: 4.706 | H64: 4.706 | I64: 4.825 | J64: 4.634 | K64: 4.448 | L64: 4.223 | M64: 4.22 | N64: 4.295 | O64: 4.364 | P64: 4.463 | Q64: 4.553 | R64: 4.664 | S64: 4.743 | T64: 4.81 | U64: 4.852 | V64: 4.893 | W64: 4.918 | X64: 4.922 | Y64: 4.928 | Z64: 4.949 | AA64: 4.97 | AB64: 4.991 | AC64: 5.014 | AD64: 5.048 | AE64: 5.086 | AF64: 5.14 | AG64: 5.223 | AH64: 5.307 | AI64: 5.396 | AJ64: 5.497 | AK64: 5.608 | AL64: 5.692 | AM64: 5.767 | AN64: 5.831 | AO64: 5.886
C65: 5 Cooking | D65: Capital Invest | E65: 0.067 | F65: 0.071 | G65: 0.073 | H65: 0.073 | I65: 0.075 | J65: 0.071 | K65: 0.068 | L65: 0.066 | M65: 0.066 | N65: 0.066 | O65: 0.069 | P65: 0.068 | Q65: 0.069 | R65: 0.07 | S65: 0.07 | T65: 0.071 | U65: 0.074 | V65: 0.074 | W65: 0.074 | X65: 0.075 | Y65: 0.075 | Z65: 0.076 | AA65: 0.077 | AB65: 0.077 | AC65: 0.078 | AD65: 0.078 | AE65: 0.079 | AF65: 0.08 | AG65: 0.08 | AH65: 0.081 | AI65: 0.081 | AJ65: 0.082 | AK65: 0.083 | AL65: 0.084 | AM65: 0.085 | AN65: 0.085 | AO65: 0.086
D66: Subsidy Invest | E66: 0 | F66: 0 | G66: 0 | H66: 0 | I66: 0 | J66: 0 | K66: 0 | L66: 0 | M66: 0 | N66: 0 | O66: 0 | P66: 0 | Q66: 0 | R66: 0 | S66: 0 | T66: 0 | U66: 0 | V66: 0 | W66: 0 | X66: 0 | Y66: 0 | Z66: 0 | AA66: 0 | AB66: 0 | AC66: 0 | AD66: 0 | AE66: 0 | AF66: 0 | AG66: 0 | AH66: 0 | AI66: 0 | AJ66: 0 | AK66: 0 | AL66: 0 | AM66: 0 | AN66: 0 | AO66: 0
C67: 5 Cooking Total | E67: 0.067 | F67: 0.071 | G67: 0.073 | H67: 0.073 | I67: 0.075 | J67: 0.071 | K67: 0.068 | L67: 0.066 | M67: 0.066 | N67: 0.066 | O67: 0.069 | P67: 0.068 | Q67: 0.069 | R67: 0.07 | S67: 0.07 | T67: 0.071 | U67: 0.074 | V67: 0.074 | W67: 0.074 | X67: 0.075 | Y67: 0.075 | Z67: 0.076 | AA67: 0.077 | AB67: 0.077 | AC67: 0.078 | AD67: 0.078 | AE67: 0.079 | AF67: 0.08 | AG67: 0.08 | AH67: 0.081 | AI67: 0.081 | AJ67: 0.082 | AK67: 0.083 | AL67: 0.084 | AM67: 0.085 | AN67: 0.085 | AO67: 0.086
C68: 6 Lighting | D68: Capital Invest | E68: 0.233 | F68: 0.237 | G68: 0.251 | H68: 0.232 | I68: 0.294 | J68: 0.273 | K68: 0.269 | L68: 0.251 | M68: 0.247 | N68: 0.241 | O68: 0.235 | P68: 0.237 | Q68: 0.239 | R68: 0.244 | S68: 0.246 | T68: 0.25 | U68: 0.267 | V68: 0.271 | W68: 0.273 | X68: 0.273 | Y68: 0.273 | Z68: 0.276 | AA68: 0.277 | AB68: 0.279 | AC68: 0.28 | AD68: 0.281 | AE68: 0.283 | AF68: 0.285 | AG68: 0.288 | AH68: 0.291 | AI68: 0.294 | AJ68: 0.298 | AK68: 0.303 | AL68: 0.306 | AM68: 0.309 | AN68: 0.312 | AO68: 0.314
D69: Subsidy Invest | E69: 0 | F69: 0 | G69: 0 | H69: 0 | I69: 0 | J69: 0 | K69: 0 | L69: 0 | M69: 0 | N69: 0 | O69: 0 | P69: 0 | Q69: 0 | R69: 0 | S69: 0 | T69: 0 | U69: 0 | V69: 0 | W69: 0 | X69: 0 | Y69: 0 | Z69: 0 | AA69: 0 | AB69: 0 | AC69: 0 | AD69: 0 | AE69: 0 | AF69: 0 | AG69: 0 | AH69: 0 | AI69: 0 | AJ69: 0 | AK69: 0 | AL69: 0 | AM69: 0 | AN69: 0 | AO69: 0
C70: 6 Lighting Total | E70: 0.233 | F70: 0.237 | G70: 0.251 | H70: 0.232 | I70: 0.294 | J70: 0.273 | K70: 0.269 | L70: 0.251 | M70: 0.247 | N70: 0.241 | O70: 0.235 | P70: 0.237 | Q70: 0.239 | R70: 0.244 | S70: 0.246 | T70: 0.25 | U70: 0.267 | V70: 0.271 | W70: 0.273 | X70: 0.273 | Y70: 0.273 | Z70: 0.276 | AA70: 0.277 | AB70: 0.279 | AC70: 0.28 | AD70: 0.281 | AE70: 0.283 | AF70: 0.285 | AG70: 0.288 | AH70: 0.291 | AI70: 0.294 | AJ70: 0.298 | AK70: 0.303 | AL70: 0.306 | AM70: 0.309 | AN70: 0.312 | AO70: 0.314
C71: 7 Refrigeration | D71: Capital Invest | E71: 3.365 | F71: 3.461 | G71: 3.59 | H71: 3.62 | I71: 3.67 | J71: 3.918 | K71: 5.549 | L71: 5.324 | M71: 5.468 | N71: 5.407 | O71: 5.389 | P71: 5.412 | Q71: 5.433 | R71: 5.743 | S71: 5.759 | T71: 5.766 | U71: 5.762 | V71: 5.768 | W71: 5.771 | X71: 5.774 | Y71: 5.788 | Z71: 5.82 | AA71: 5.851 | AB71: 5.882 | AC71: 5.917 | AD71: 5.957 | AE71: 5.991 | AF71: 6.027 | AG71: 6.078 | AH71: 6.125 | AI71: 6.183 | AJ71: 6.256 | AK71: 6.341 | AL71: 6.403 | AM71: 6.452 | AN71: 6.485 | AO71: 6.508
D72: Subsidy Invest | E72: 0 | F72: 0 | G72: 0 | H72: 0 | I72: 0 | J72: 0 | K72: 0 | L72: 0 | M72: 0 | N72: 0 | O72: 0 | P72: 0 | Q72: 0 | R72: 0 | S72: 0 | T72: 0 | U72: 0 | V72: 0 | W72: 0 | X72: 0 | Y72: 0 | Z72: 0 | AA72: 0 | AB72: 0 | AC72: 0 | AD72: 0 | AE72: 0 | AF72: 0 | AG72: 0 | AH72: 0 | AI72: 0 | AJ72: 0 | AK72: 0 | AL72: 0 | AM72: 0 | AN72: 0 | AO72: 0
C73: 7 Refrigeration Total | E73: 3.365 | F73: 3.461 | G73: 3.59 | H73: 3.62 | I73: 3.67 | J73: 3.918 | K73: 5.549 | L73: 5.324 | M73: 5.468 | N73: 5.407 | O73: 5.389 | P73: 5.412 | Q73: 5.433 | R73: 5.743 | S73: 5.759 | T73: 5.766 | U73: 5.762 | V73: 5.768 | W73: 5.771 | X73: 5.774 | Y73: 5.788 | Z73: 5.82 | AA73: 5.851 | AB73: 5.882 | AC73: 5.917 | AD73: 5.957 | AE73: 5.991 | AF73: 6.027 | AG73: 6.078 | AH73: 6.125 | AI73: 6.183 | AJ73: 6.256 | AK73: 6.341 | AL73: 6.403 | AM73: 6.452 | AN73: 6.485 | AO73: 6.508
B74: 3 East North Central Total | E74: 10.718 | F74: 10.89 | G74: 11.338 | H74: 11.302 | I74: 11.678 | J74: 11.47 | K74: 12.777 | L74: 12.196 | M74: 12.312 | N74: 12.353 | O74: 12.422 | P74: 12.559 | Q74: 12.686 | R74: 13.133 | S74: 13.241 | T74: 13.328 | U74: 13.384 | V74: 13.438 | W74: 13.459 | X74: 13.451 | Y74: 13.454 | Z74: 13.504 | AA74: 13.557 | AB74: 13.593 | AC74: 13.643 | AD74: 13.713 | AE74: 13.784 | AF74: 13.879 | AG74: 14.035 | AH74: 14.201 | AI74: 14.362 | AJ74: 14.558 | AK74: 14.785 | AL74: 14.945 | AM74: 15.09 | AN74: 15.205 | AO74: 15.3
B75: 4 West North Central | C75: 1 Heating | D75: Capital Invest | E75: 0.733 | F75: 0.759 | G75: 0.763 | H75: 0.759 | I75: 0.773 | J75: 0.737 | K75: 0.683 | L75: 0.66 | M75: 0.652 | N75: 0.642 | O75: 0.646 | P75: 0.653 | Q75: 0.655 | R75: 0.676 | S75: 0.679 | T75: 0.682 | U75: 0.687 | V75: 0.687 | W75: 0.685 | X75: 0.684 | Y75: 0.68 | Z75: 0.679 | AA75: 0.68 | AB75: 0.679 | AC75: 0.676 | AD75: 0.676 | AE75: 0.675 | AF75: 0.677 | AG75: 0.682 | AH75: 0.684 | AI75: 0.691 | AJ75: 0.694 | AK75: 0.702 | AL75: 0.704 | AM75: 0.711 | AN75: 0.72 | AO75: 0.72
D76: Subsidy Invest | E76: 0 | F76: 0 | G76: 0 | H76: 0 | I76: 0.02 | J76: 0.02 | K76: 0.017 | L76: 0.016 | M76: 0.016 | N76: 0.015 | O76: 0.015 | P76: 0.015 | Q76: 0.015 | R76: 0 | S76: 0 | T76: 0 | U76: 0 | V76: 0 | W76: 0 | X76: 0 | Y76: 0 | Z76: 0 | AA76: 0 | AB76: 0 | AC76: 0 | AD76: 0 | AE76: 0 | AF76: 0 | AG76: 0 | AH76: 0 | AI76: 0 | AJ76: 0 | AK76: 0 | AL76: 0 | AM76: 0 | AN76: 0 | AO76: 0
C77: 1 Heating Total | E77: 0.733 | F77: 0.759 | G77: 0.763 | H77: 0.759 | I77: 0.793 | J77: 0.757 | K77: 0.7 | L77: 0.676 | M77: 0.668 | N77: 0.657 | O77: 0.661 | P77: 0.668 | Q77: 0.67 | R77: 0.676 | S77: 0.679 | T77: 0.682 | U77: 0.687 | V77: 0.687 | W77: 0.685 | X77: 0.684 | Y77: 0.68 | Z77: 0.679 | AA77: 0.68 | AB77: 0.679 | AC77: 0.676 | AD77: 0.676 | AE77: 0.675 | AF77: 0.677 | AG77: 0.682 | AH77: 0.684 | AI77: 0.691 | AJ77: 0.694 | AK77: 0.702 | AL77: 0.704 | AM77: 0.711 | AN77: 0.72 | AO77: 0.72
C78: 2 Cooling | D78: Capital Invest | E78: 0.357 | F78: 0.311 | G78: 0.311 | H78: 0.312 | I78: 0.315 | J78: 0.312 | K78: 0.304 | L78: 0.292 | M78: 0.287 | N78: 0.305 | O78: 0.304 | P78: 0.302 | Q78: 0.302 | R78: 0.303 | S78: 0.303 | T78: 0.302 | U78: 0.3 | V78: 0.299 | W78: 0.296 | X78: 0.294 | Y78: 0.291 | Z78: 0.289 | AA78: 0.287 | AB78: 0.284 | AC78: 0.282 | AD78: 0.281 | AE78: 0.28 | AF78: 0.279 | AG78: 0.28 | AH78: 0.28 | AI78: 0.28 | AJ78: 0.281 | AK78: 0.283 | AL78: 0.283 | AM78: 0.282 | AN78: 0.281 | AO78: 0.279
D79: Subsidy Invest | E79: 0 | F79: 0 | G79: 0 | H79: 0 | I79: 0 | J79: 0 | K79: 0 | L79: 0 | M79: 0 | N79: 0 | O79: 0 | P79: 0 | Q79: 0 | R79: 0 | S79: 0 | T79: 0 | U79: 0 | V79: 0 | W79: 0 | X79: 0 | Y79: 0 | Z79: 0 | AA79: 0 | AB79: 0 | AC79: 0 | AD79: 0 | AE79: 0 | AF79: 0 | AG79: 0 | AH79: 0 | AI79: 0 | AJ79: 0 | AK79: 0 | AL79: 0 | AM79: 0 | AN79: 0 | AO79: 0
C80: 2 Cooling Total | E80: 0.357 | F80: 0.311 | G80: 0.311 | H80: 0.312 | I80: 0.315 | J80: 0.312 | K80: 0.304 | L80: 0.292 | M80: 0.287 | N80: 0.305 | O80: 0.304 | P80: 0.302 | Q80: 0.302 | R80: 0.303 | S80: 0.303 | T80: 0.302 | U80: 0.3 | V80: 0.299 | W80: 0.296 | X80: 0.294 | Y80: 0.291 | Z80: 0.289 | AA80: 0.287 | AB80: 0.284 | AC80: 0.282 | AD80: 0.281 | AE80: 0.28 | AF80: 0.279 | AG80: 0.28 | AH80: 0.28 | AI80: 0.28 | AJ80: 0.281 | AK80: 0.283 | AL80: 0.283 | AM80: 0.282 | AN80: 0.281 | AO80: 0.279
C81: 3 Water Heating | D81: Capital Invest | E81: 0.036 | F81: 0.036 | G81: 0.038 | H81: 0.039 | I81: 0.041 | J81: 0.041 | K81: 0.039 | L81: 0.038 | M81: 0.038 | N81: 0.04 | O81: 0.04 | P81: 0.04 | Q81: 0.04 | R81: 0.04 | S81: 0.041 | T81: 0.041 | U81: 0.043 | V81: 0.043 | W81: 0.043 | X81: 0.044 | Y81: 0.044 | Z81: 0.044 | AA81: 0.044 | AB81: 0.044 | AC81: 0.044 | AD81: 0.044 | AE81: 0.046 | AF81: 0.046 | AG81: 0.047 | AH81: 0.048 | AI81: 0.048 | AJ81: 0.049 | AK81: 0.05 | AL81: 0.05 | AM81: 0.051 | AN81: 0.051 | AO81: 0.051
D82: Subsidy Invest | E82: 0 | F82: 0 | G82: 0 | H82: 0 | I82: 0.002 | J82: 0.001 | K82: 0.002 | L82: 0.002 | M82: 0.002 | N82: 0.002 | O82: 0.002 | P82: 0.002 | Q82: 0.002 | R82: 0 | S82: 0 | T82: 0 | U82: 0 | V82: 0 | W82: 0 | X82: 0 | Y82: 0 | Z82: 0 | AA82: 0 | AB82: 0 | AC82: 0 | AD82: 0 | AE82: 0 | AF82: 0 | AG82: 0 | AH82: 0 | AI82: 0.001 | AJ82: 0.001 | AK82: 0.001 | AL82: 0.001 | AM82: 0.001 | AN82: 0.001 | AO82: 0.001
C83: 3 Water Heating Total | E83: 0.036 | F83: 0.036 | G83: 0.038 | H83: 0.039 | I83: 0.043 | J83: 0.042 | K83: 0.041 | L83: 0.04 | M83: 0.04 | N83: 0.042 | O83: 0.042 | P83: 0.042 | Q83: 0.042 | R83: 0.04 | S83: 0.041 | T83: 0.041 | U83: 0.043 | V83: 0.043 | W83: 0.043 | X83: 0.044 | Y83: 0.044 | Z83: 0.044 | AA83: 0.044 | AB83: 0.044 | AC83: 0.044 | AD83: 0.044 | AE83: 0.046 | AF83: 0.046 | AG83: 0.047 | AH83: 0.048 | AI83: 0.049 | AJ83: 0.05 | AK83: 0.051 | AL83: 0.051 | AM83: 0.052 | AN83: 0.052 | AO83: 0.052
C84: 4 Ventilation | D84: Capital Invest | E84: 1.281 | F84: 1.285 | G84: 1.296 | H84: 1.326 | I84: 1.33 | J84: 1.35 | K84: 1.288 | L84: 1.253 | M84: 1.256 | N84: 1.241 | O84: 1.251 | P84: 1.27 | Q84: 1.287 | R84: 1.312 | S84: 1.329 | T84: 1.343 | U84: 1.349 | V84: 1.357 | W84: 1.364 | X84: 1.367 | Y84: 1.369 | Z84: 1.374 | AA84: 1.38 | AB84: 1.385 | AC84: 1.393 | AD84: 1.404 | AE84: 1.413 | AF84: 1.427 | AG84: 1.447 | AH84: 1.466 | AI84: 1.486 | AJ84: 1.509 | AK84: 1.535 | AL84: 1.553 | AM84: 1.568 | AN84: 1.58 | AO84: 1.59
D85: Subsidy Invest | E85: 0 | F85: 0 | G85: 0 | H85: 0 | I85: 0 | J85: 0 | K85: 0 | L85: 0 | M85: 0 | N85: 0 | O85: 0 | P85: 0 | Q85: 0 | R85: 0 | S85: 0 | T85: 0 | U85: 0 | V85: 0 | W85: 0 | X85: 0 | Y85: 0 | Z85: 0 | AA85: 0 | AB85: 0 | AC85: 0 | AD85: 0 | AE85: 0 | AF85: 0 | AG85: 0 | AH85: 0 | AI85: 0 | AJ85: 0 | AK85: 0 | AL85: 0 | AM85: 0 | AN85: 0 | AO85: 0
C86: 4 Ventilation Total | E86: 1.281 | F86: 1.285 | G86: 1.296 | H86: 1.326 | I86: 1.33 | J86: 1.35 | K86: 1.288 | L86: 1.253 | M86: 1.256 | N86: 1.241 | O86: 1.251 | P86: 1.27 | Q86: 1.287 | R86: 1.312 | S86: 1.329 | T86: 1.343 | U86: 1.349 | V86: 1.357 | W86: 1.364 | X86: 1.367 | Y86: 1.369 | Z86: 1.374 | AA86: 1.38 | AB86: 1.385 | AC86: 1.393 | AD86: 1.404 | AE86: 1.413 | AF86: 1.427 | AG86: 1.447 | AH86: 1.466 | AI86: 1.486 | AJ86: 1.509 | AK86: 1.535 | AL86: 1.553 | AM86: 1.568 | AN86: 1.58 | AO86: 1.59
C87: 5 Cooking | D87: Capital Invest | E87: 0.025 | F87: 0.027 | G87: 0.027 | H87: 0.027 | I87: 0.027 | J87: 0.026 | K87: 0.024 | L87: 0.024 | M87: 0.024 | N87: 0.024 | O87: 0.024 | P87: 0.025 | Q87: 0.025 | R87: 0.025 | S87: 0.026 | T87: 0.026 | U87: 0.026 | V87: 0.027 | W87: 0.027 | X87: 0.027 | Y87: 0.028 | Z87: 0.028 | AA87: 0.028 | AB87: 0.028 | AC87: 0.028 | AD87: 0.029 | AE87: 0.029 | AF87: 0.029 | AG87: 0.029 | AH87: 0.03 | AI87: 0.03 | AJ87: 0.03 | AK87: 0.031 | AL87: 0.031 | AM87: 0.031 | AN87: 0.031 | AO87: 0.031
D88: Subsidy Invest | E88: 0 | F88: 0 | G88: 0 | H88: 0 | I88: 0 | J88: 0 | K88: 0 | L88: 0 | M88: 0 | N88: 0 | O88: 0 | P88: 0 | Q88: 0 | R88: 0 | S88: 0 | T88: 0 | U88: 0 | V88: 0 | W88: 0 | X88: 0 | Y88: 0 | Z88: 0 | AA88: 0 | AB88: 0 | AC88: 0 | AD88: 0 | AE88: 0 | AF88: 0 | AG88: 0 | AH88: 0 | AI88: 0 | AJ88: 0 | AK88: 0 | AL88: 0 | AM88: 0 | AN88: 0 | AO88: 0
C89: 5 Cooking Total | E89: 0.025 | F89: 0.027 | G89: 0.027 | H89: 0.027 | I89: 0.027 | J89: 0.026 | K89: 0.024 | L89: 0.024 | M89: 0.024 | N89: 0.024 | O89: 0.024 | P89: 0.025 | Q89: 0.025 | R89: 0.025 | S89: 0.026 | T89: 0.026 | U89: 0.026 | V89: 0.027 | W89: 0.027 | X89: 0.027 | Y89: 0.028 | Z89: 0.028 | AA89: 0.028 | AB89: 0.028 | AC89: 0.028 | AD89: 0.029 | AE89: 0.029 | AF89: 0.029 | AG89: 0.029 | AH89: 0.03 | AI89: 0.03 | AJ89: 0.03 | AK89: 0.031 | AL89: 0.031 | AM89: 0.031 | AN89: 0.031 | AO89: 0.031
C90: 6 Lighting | D90: Capital Invest | E90: 0.084 | F90: 0.083 | G90: 0.087 | H90: 0.08 | I90: 0.094 | J90: 0.096 | K90: 0.095 | L90: 0.089 | M90: 0.09 | N90: 0.089 | O90: 0.084 | P90: 0.084 | Q90: 0.084 | R90: 0.085 | S90: 0.086 | T90: 0.086 | U90: 0.088 | V90: 0.089 | W90: 0.089 | X90: 0.089 | Y90: 0.09 | Z90: 0.09 | AA90: 0.09 | AB90: 0.091 | AC90: 0.091 | AD90: 0.091 | AE90: 0.093 | AF90: 0.093 | AG90: 0.094 | AH90: 0.095 | AI90: 0.096 | AJ90: 0.097 | AK90: 0.099 | AL90: 0.099 | AM90: 0.1 | AN90: 0.101 | AO90: 0.101
D91: Subsidy Invest | E91: 0 | F91: 0 | G91: 0 | H91: 0 | I91: 0 | J91: 0 | K91: 0 | L91: 0 | M91: 0 | N91: 0 | O91: 0 | P91: 0 | Q91: 0 | R91: 0 | S91: 0 | T91: 0 | U91: 0 | V91: 0 | W91: 0 | X91: 0 | Y91: 0 | Z91: 0 | AA91: 0 | AB91: 0 | AC91: 0 | AD91: 0 | AE91: 0 | AF91: 0 | AG91: 0 | AH91: 0 | AI91: 0 | AJ91: 0 | AK91: 0 | AL91: 0 | AM91: 0 | AN91: 0 | AO91: 0
C92: 6 Lighting Total | E92: 0.084 | F92: 0.083 | G92: 0.087 | H92: 0.08 | I92: 0.094 | J92: 0.096 | K92: 0.095 | L92: 0.089 | M92: 0.09 | N92: 0.089 | O92: 0.084 | P92: 0.084 | Q92: 0.084 | R92: 0.085 | S92: 0.086 | T92: 0.086 | U92: 0.088 | V92: 0.089 | W92: 0.089 | X92: 0.089 | Y92: 0.09 | Z92: 0.09 | AA92: 0.09 | AB92: 0.091 | AC92: 0.091 | AD92: 0.091 | AE92: 0.093 | AF92: 0.093 | AG92: 0.094 | AH92: 0.095 | AI92: 0.096 | AJ92: 0.097 | AK92: 0.099 | AL92: 0.099 | AM92: 0.1 | AN92: 0.101 | AO92: 0.101
C93: 7 Refrigeration | D93: Capital Invest | E93: 1.725 | F93: 1.796 | G93: 1.816 | H93: 1.811 | I93: 1.79 | J93: 1.965 | K93: 2.706 | L93: 2.584 | M93: 2.669 | N93: 2.62 | O93: 2.611 | P93: 2.621 | Q93: 2.631 | R93: 2.768 | S93: 2.773 | T93: 2.772 | U93: 2.767 | V93: 2.766 | W93: 2.765 | X93: 2.764 | Y93: 2.77 | Z93: 2.785 | AA93: 2.8 | AB93: 2.814 | AC93: 2.831 | AD93: 2.85 | AE93: 2.866 | AF93: 2.88 | AG93: 2.902 | AH93: 2.92 | AI93: 2.945 | AJ93: 2.976 | AK93: 3.014 | AL93: 3.042 | AM93: 3.064 | AN93: 3.078 | AO93: 3.087
D94: Subsidy Invest | E94: 0 | F94: 0 | G94: 0 | H94: 0 | I94: 0 | J94: 0 | K94: 0 | L94: 0 | M94: 0 | N94: 0 | O94: 0 | P94: 0 | Q94: 0 | R94: 0 | S94: 0 | T94: 0 | U94: 0 | V94: 0 | W94: 0 | X94: 0 | Y94: 0 | Z94: 0 | AA94: 0 | AB94: 0 | AC94: 0 | AD94: 0 | AE94: 0 | AF94: 0 | AG94: 0 | AH94: 0 | AI94: 0 | AJ94: 0 | AK94: 0 | AL94: 0 | AM94: 0 | AN94: 0 | AO94: 0
C95: 7 Refrigeration Total | E95: 1.725 | F95: 1.796 | G95: 1.816 | H95: 1.811 | I95: 1.79 | J95: 1.965 | K95: 2.706 | L95: 2.584 | M95: 2.669 | N95: 2.62 | O95: 2.611 | P95: 2.621 | Q95: 2.631 | R95: 2.768 | S95: 2.773 | T95: 2.772 | U95: 2.767 | V95: 2.766 | W95: 2.765 | X95: 2.764 | Y95: 2.77 | Z95: 2.785 | AA95: 2.8 | AB95: 2.814 | AC95: 2.831 | AD95: 2.85 | AE95: 2.866 | AF95: 2.88 | AG95: 2.902 | AH95: 2.92 | AI95: 2.945 | AJ95: 2.976 | AK95: 3.014 | AL95: 3.042 | AM95: 3.064 | AN95: 3.078 | AO95: 3.087
B96: 4 West North Central Total | E96: 4.241 | F96: 4.297 | G96: 4.338 | H96: 4.354 | I96: 4.392 | J96: 4.548 | K96: 5.158 | L96: 4.958 | M96: 5.034 | N96: 4.978 | O96: 4.977 | P96: 5.012 | Q96: 5.041 | R96: 5.209 | S96: 5.237 | T96: 5.252 | U96: 5.26 | V96: 5.268 | W96: 5.269 | X96: 5.269 | Y96: 5.272 | Z96: 5.289 | AA96: 5.309 | AB96: 5.325 | AC96: 5.345 | AD96: 5.375 | AE96: 5.402 | AF96: 5.431 | AG96: 5.481 | AH96: 5.523 | AI96: 5.577 | AJ96: 5.637 | AK96: 5.715 | AL96: 5.763 | AM96: 5.808 | AN96: 5.843 | AO96: 5.86
B97: 5 South Atlantic | C97: 1 Heating | D97: Capital Invest | E97: 1.859 | F97: 1.923 | G97: 1.987 | H97: 2.013 | I97: 2.034 | J97: 1.898 | K97: 1.708 | L97: 1.612 | M97: 1.627 | N97: 1.584 | O97: 1.614 | P97: 1.644 | Q97: 1.663 | R97: 1.723 | S97: 1.737 | T97: 1.749 | U97: 1.748 | V97: 1.747 | W97: 1.751 | X97: 1.752 | Y97: 1.742 | Z97: 1.745 | AA97: 1.744 | AB97: 1.741 | AC97: 1.742 | AD97: 1.746 | AE97: 1.735 | AF97: 1.746 | AG97: 1.761 | AH97: 1.766 | AI97: 1.773 | AJ97: 1.786 | AK97: 1.833 | AL97: 1.86 | AM97: 1.867 | AN97: 1.878 | AO97: 1.888
D98: Subsidy Invest | E98: 0 | F98: 0 | G98: 0 | H98: 0 | I98: 0.05 | J98: 0.047 | K98: 0.04 | L98: 0.037 | M98: 0.037 | N98: 0.035 | O98: 0.035 | P98: 0.035 | Q98: 0.035 | R98: 0 | S98: 0 | T98: 0 | U98: 0 | V98: 0 | W98: 0 | X98: 0 | Y98: 0 | Z98: 0 | AA98: 0 | AB98: 0 | AC98: 0 | AD98: 0 | AE98: 0 | AF98: 0 | AG98: 0 | AH98: 0 | AI98: 0 | AJ98: 0 | AK98: 0 | AL98: 0 | AM98: 0 | AN98: 0 | AO98: 0
C99: 1 Heating Total | E99: 1.859 | F99: 1.923 | G99: 1.987 | H99: 2.013 | I99: 2.084 | J99: 1.945 | K99: 1.748 | L99: 1.649 | M99: 1.664 | N99: 1.619 | O99: 1.649 | P99: 1.679 | Q99: 1.698 | R99: 1.723 | S99: 1.737 | T99: 1.749 | U99: 1.748 | V99: 1.747 | W99: 1.751 | X99: 1.752 | Y99: 1.742 | Z99: 1.745 | AA99: 1.744 | AB99: 1.741 | AC99: 1.742 | AD99: 1.746 | AE99: 1.735 | AF99: 1.746 | AG99: 1.761 | AH99: 1.766 | AI99: 1.773 | AJ99: 1.786 | AK99: 1.833 | AL99: 1.86 | AM99: 1.867 | AN99: 1.878 | AO99: 1.888
C100: 2 Cooling | D100: Capital Invest | E100: 3.401 | F100: 2.307 | G100: 2.353 | H100: 2.398 | I100: 2.46 | J100: 2.357 | K100: 2.226 | L100: 2.111 | M100: 2.102 | N100: 2.24 | O100: 2.231 | P100: 2.226 | Q100: 2.241 | R100: 2.272 | S100: 2.284 | T100: 2.288 | U100: 2.274 | V100: 2.267 | W100: 2.254 | X100: 2.234 | Y100: 2.215 | Z100: 2.207 | AA100: 2.195 | AB100: 2.182 | AC100: 2.173 | AD100: 2.167 | AE100: 2.162 | AF100: 2.159 | AG100: 2.17 | AH100: 2.178 | AI100: 2.188 | AJ100: 2.205 | AK100: 2.226 | AL100: 2.228 | AM100: 2.227 | AN100: 2.218 | AO100: 2.204
D101: Subsidy Invest | E101: 0 | F101: 0 | G101: 0 | H101: 0 | I101: 0 | J101: 0 | K101: 0 | L101: 0 | M101: 0 | N101: 0 | O101: 0 | P101: 0 | Q101: 0 | R101: 0 | S101: 0 | T101: 0 | U101: 0 | V101: 0 | W101: 0 | X101: 0 | Y101: 0 | Z101: 0 | AA101: 0 | AB101: 0 | AC101: 0 | AD101: 0 | AE101: 0 | AF101: 0 | AG101: 0 | AH101: 0 | AI101: 0 | AJ101: 0 | AK101: 0 | AL101: 0 | AM101: 0 | AN101: 0 | AO101: 0
C102: 2 Cooling Total | E102: 3.401 | F102: 2.307 | G102: 2.353 | H102: 2.398 | I102: 2.46 | J102: 2.357 | K102: 2.226 | L102: 2.111 | M102: 2.102 | N102: 2.24 | O102: 2.231 | P102: 2.226 | Q102: 2.241 | R102: 2.272 | S102: 2.284 | T102: 2.288 | U102: 2.274 | V102: 2.267 | W102: 2.254 | X102: 2.234 | Y102: 2.215 | Z102: 2.207 | AA102: 2.195 | AB102: 2.182 | AC102: 2.173 | AD102: 2.167 | AE102: 2.162 | AF102: 2.159 | AG102: 2.17 | AH102: 2.178 | AI102: 2.188 | AJ102: 2.205 | AK102: 2.226 | AL102: 2.228 | AM102: 2.227 | AN102: 2.218 | AO102: 2.204
C103: 3 Water Heating | D103: Capital Invest | E103: 0.142 | F103: 0.143 | G103: 0.154 | H103: 0.161 | I103: 0.177 | J103: 0.182 | K103: 0.171 | L103: 0.166 | M103: 0.169 | N103: 0.172 | O103: 0.181 | P103: 0.174 | Q103: 0.176 | R103: 0.172 | S103: 0.174 | T103: 0.177 | U103: 0.181 | V103: 0.184 | W103: 0.188 | X103: 0.191 | Y103: 0.194 | Z103: 0.195 | AA103: 0.196 | AB103: 0.198 | AC103: 0.199 | AD103: 0.201 | AE103: 0.205 | AF103: 0.208 | AG103: 0.211 | AH103: 0.214 | AI103: 0.217 | AJ103: 0.221 | AK103: 0.225 | AL103: 0.228 | AM103: 0.231 | AN103: 0.232 | AO103: 0.24
...

Sheet Residential
B2: Displays Investment and Subsidy on the Shell and Investment Tables -- note total expenditures on equipment or shell = consumer investment ("Investment") + subsidy.
B3: i.e., total investment = totinvest + totsubsidy
I5: YEAR
B6: CDIV | C6: BLDG | D6: ENDUSE | E6: Filled Column Name | F6: FUEL | G6: EQPTYPE | H6: Data | I6: 2010 | J6: 2011 | K6: 2012 | L6: 2013 | M6: 2014 | N6: 2015 | O6: 2016 | P6: 2017 | Q6: 2018 | R6: 2019 | S6: 2020 | T6: 2021 | U6: 2022 | V6: 2023 | W6: 2024 | X6: 2025 | Y6: 2026 | Z6: 2027 | AA6: 2028 | AB6: 2029 | AC6: 2030 | AD6: 2031 | AE6: 2032 | AF6: 2033 | AG6: 2034 | AH6: 2035 | AI6: 2036 | AJ6: 2037 | AK6: 2038 | AL6: 2039 | AM6: 2040
B7: 1 New England | C7: Single Family | D7: Refrigeration | E7: =IF(D7="",E6,D7) -> Refrigeration | F7: Electricity | G7: RefBF#1 | H7: Sum of TOTSUBSIDY | I7: 0 | J7: 0 | K7: 0 | L7: 0 | M7: 0 | N7: 0 | O7: 0 | P7: 0 | Q7: 0 | R7: 0 | S7: 0 | T7: 0 | U7: 0 | V7: 0 | W7: 0 | X7: 0 | Y7: 0 | Z7: 0 | AA7: 0 | AB7: 0 | AC7: 0 | AD7: 0 | AE7: 0 | AF7: 0 | AG7: 0 | AH7: 0 | AI7: 0 | AJ7: 0 | AK7: 0 | AL7: 0 | AM7: 0
B8: 2 New England | C8: Single Family | D8: Refrigeration | E8: =IF(D8="",E7,D8) -> Refrigeration | F8: Electricity | H8: Sum of TOTPURCHASE | I8: 7641 | J8: 8277 | K8: 9322 | L8: 9515 | M8: 16192 | N8: 18638 | O8: 21440 | P8: 23650 | Q8: 22661 | R8: 21330 | S8: 20392 | T8: 19560 | U8: 19123 | V8: 18742 | W8: 18631 | X8: 18254 | Y8: 18246 | Z8: 18296 | AA8: 17978 | AB8: 18077 | AC8: 18041 | AD8: 18148 | AE8: 17803 | AF8: 17644 | AG8: 17295 | AH8: 16890 | AI8: 16364 | AJ8: 16912 | AK8: 16969 | AL8: 16848 | AM8: 16886
B9: 3 New England | C9: Single Family | D9: Refrigeration | E9: =IF(D9="",E8,D9) -> Refrigeration | F9: Electricity | H9: Sum of TOTINVEST | I9: 7106539 | J9: 7698489 | K9: 8670550 | L9: 8849066 | M9: 15868566 | N9: 18265744 | O9: 21012184 | P9: 23177772 | Q9: 22209051 | R9: 20903899 | S9: 19985670 | T9: 19170027 | U9: 18741917 | V9: 18368449 | W9: 18259277 | X9: 17890627 | Y9: 17882375 | Z9: 17931390 | AA9: 17619678 | AB9: 17715945 | AC9: 17681312 | AD9: 17785703 | AE9: 17448370 | AF9: 17292400 | AG9: 16950256 | AH9: 16552681 | AI9: 16037627 | AJ9: 16574633 | AK9: 16630497 | AL9: 16511926 | AM9: 16549458
B10: 4 New England | C10: Single Family | D10: Refrigeration | E10: =IF(D10="",E9,D10) -> Refrigeration | F10: Electricity | G10: RefBF#2 | H10: Sum of TOTSUBSIDY | I10: 0 | J10: 0 | K10: 0 | L10: 0 | M10: 0 | N10: 0 | O10: 0 | P10: 0 | Q10: 0 | R10: 0 | S10: 0 | T10: 0 | U10: 0 | V10: 0 | W10: 0 | X10: 0 | Y10: 0 | Z10: 0 | AA10: 0 | AB10: 0 | AC10: 0 | AD10: 0 | AE10: 0 | AF10: 0 | AG10: 0 | AH10: 0 | AI10: 0 | AJ10: 0 | AK10: 0 | AL10: 0 | AM10: 0
B11: 5 New England | C11: Single Family | D11: Refrigeration | E11: =IF(D11="",E10,D11) -> Refrigeration | F11: Electricity | H11: Sum of TOTPURCHASE | I11: 48537 | J11: 47630 | K11: 50302 | L11: 53524 | M11: 49460 | N11: 51317 | O11: 53089 | P11: 56065 | Q11: 56839 | R11: 57422 | S11: 58129 | T11: 58577 | U11: 59160 | V11: 60044 | W11: 60634 | X11: 61227 | Y11: 61552 | Z11: 61566 | AA11: 61503 | AB11: 61443 | AC11: 61470 | AD11: 61124 | AE11: 60410 | AF11: 59803 | AG11: 58923 | AH11: 57614 | AI11: 56047 | AJ11: 57376 | AK11: 58932 | AL11: 60278 | AM11: 61406
B12: 6 New England | C12: Single Family | D12: Refrigeration | E12: =IF(D12="",E11,D12) -> Refrigeration | F12: Electricity | H12: Sum of TOTINVEST | I12: 48537800 | J12: 47631566 | K12: 50303211 | L12: 53524902 | M12: 49461022 | N12: 51318107 | O12: 53090386 | P12: 56066387 | Q12: 56839291 | R12: 57423022 | S12: 58130268 | T12: 58578720 | U12: 59161552 | V12: 60045224 | W12: 60635246 | X12: 61228121 | Y12: 61552603 | Z12: 61566808 | AA12: 61503654 | AB12: 61444409 | AC12: 61471848 | AD12: 61124636 | AE12: 60410271 | AF12: 59803728 | AG12: 58924256 | AH12: 57615525 | AI12: 56047545 | AJ12: 57377648 | AK12: 58933707 | AL12: 60279583 | AM12: 61406659
B13: 7 New England | C13: Single Family | D13: Refrigeration | E13: =IF(D13="",E12,D13) -> Refrigeration | F13: Electricity | G13: RefSF#1 | H13: Sum of TOTSUBSIDY | I13: 0 | J13: 0 | K13: 0 | L13: 0 | M13: 0 | N13: 0 | O13: 0 | P13: 0 | Q13: 0 | R13: 0 | S13: 0 | T13: 0 | U13: 0 | V13: 0 | W13: 0 | X13: 0 | Y13: 0 | Z13: 0 | AA13: 0 | AB13: 0 | AC13: 0 | AD13: 0 | AE13: 0 | AF13: 0 | AG13: 0 | AH13: 0 | AI13: 0 | AJ13: 0 | AK13: 0 | AL13: 0 | AM13: 0
B14: 8 New England | C14: Single Family | D14: Refrigeration | E14: =IF(D14="",E13,D14) -> Refrigeration | F14: Electricity | H14: Sum of TOTPURCHASE | I14: 5969 | J14: 6469 | K14: 7288 | L14: 7436 | M14: 40275 | N14: 45498 | O14: 51154 | P14: 55843 | Q14: 54228 | R14: 51833 | S14: 50116 | T14: 48495 | U14: 47663 | V14: 46960 | W14: 46785 | X14: 46023 | Y14: 46035 | Z14: 46147 | AA14: 45435 | AB14: 45649 | AC14: 45573 | AD14: 45777 | AE14: 44950 | AF14: 44541 | AG14: 43687 | AH14: 42669 | AI14: 41361 | AJ14: 42698 | AK14: 42959 | AL14: 42681 | AM14: 42778
B15: 9 New England | C15: Single Family | D15: Refrigeration | E15: =IF(D15="",E14,D15) -> Refrigeration | F15: Electricity | H15: Sum of TOTINVEST | I15: 6746147 | J15: 7310906 | K15: 8237360 | L15: 8404614 | M15: 47122359 | N15: 53233937 | O15: 59851761 | P15: 65337419 | Q15: 63448254 | R15: 60645844 | S15: 58636743 | T15: 56739854 | U15: 55767337 | V15: 54944606 | W15: 54739233 | X15: 53847841 | Y15: 53861670 | Z15: 53992513 | AA15: 53160446 | AB15: 53409935 | AC15: 53321047 | AD15: 53560148 | AE15: 52592075 | AF15: 52114937 | AG15: 51115676 | AH15: 49924401 | AI15: 48394100 | AJ15: 49957719 | AK15: 50263408 | AL15: 49937693 | AM15: 50051741
B16: 10 New England | C16: Single Family | D16: Refrigeration | E16: =IF(D16="",E15,D16) -> Refrigeration | F16: Electricity | G16: RefSF#2 | H16: Sum of TOTSUBSIDY | I16: 0 | J16: 0 | K16: 0 | L16: 0 | M16: 0 | N16: 0 | O16: 0 | P16: 0 | Q16: 0 | R16: 0 | S16: 0 | T16: 0 | U16: 0 | V16: 0 | W16: 0 | X16: 0 | Y16: 0 | Z16: 0 | AA16: 0 | AB16: 0 | AC16: 0 | AD16: 0 | AE16: 0 | AF16: 0 | AG16: 0 | AH16: 0 | AI16: 0 | AJ16: 0 | AK16: 0 | AL16: 0 | AM16: 0
B17: 11 New England | C17: Single Family | D17: Refrigeration | E17: =IF(D17="",E16,D17) -> Refrigeration | F17: Electricity | H17: Sum of TOTPURCHASE | I17: 50208 | J17: 49439 | K17: 52336 | L17: 55601 | M17: 25377 | N17: 24456 | O17: 23375 | P17: 23872 | Q17: 25272 | R17: 26918 | S17: 28406 | T17: 29643 | U17: 30620 | V17: 31826 | W17: 32481 | X17: 33459 | Y17: 33763 | Z17: 33715 | AA17: 34045 | AB17: 33872 | AC17: 33939 | AD17: 33495 | AE17: 33263 | AF17: 32905 | AG17: 32530 | AH17: 31835 | AI17: 31049 | AJ17: 31591 | AK17: 32942 | AL17: 34445 | AM17: 35513
B18: 12 New England | C18: Single Family | D18: Refrigeration | E18: =IF(D18="",E17,D18) -> Refrigeration | F18: Electricity | H18: Sum of TOTINVEST | I18: 58744763 | J18: 57844425 | K18: 61233928 | L18: 65054706 | M18: 35021529 | N18: 33751387 | O18: 32258938 | P18: 32945042 | Q18: 34875787 | R18: 37148882 | S18: 39201580 | T18: 40909227 | U18: 42257760 | V18: 43921730 | W18: 44824465 | X18: 46174899 | Y18: 46594751 | Z18: 46529042 | AA18: 46984353 | AB18: 46743883 | AC18: 46837836 | AD18: 46223664 | AE18: 45904647 | AF18: 45410770 | AG18: 44893926 | AH18: 43933124 | AI18: 42848983 | AJ18: 43596456 | AK18: 45461919 | AL18: 47536440 | AM18: 49010152
B19: 13 New England | C19: Single Family | D19: Refrigeration | E19: =IF(D19="",E18,D19) -> Refrigeration | F19: Electricity | G19: RefTF#1 | H19: Sum of TOTSUBSIDY | I19: 0 | J19: 0 | K19: 0 | L19: 0 | M19: 0 | N19: 0 | O19: 0 | P19: 0 | Q19: 0 | R19: 0 | S19: 0 | T19: 0 | U19: 0 | V19: 0 | W19: 0 | X19: 0 | Y19: 0 | Z19: 0 | AA19: 0 | AB19: 0 | AC19: 0 | AD19: 0 | AE19: 0 | AF19: 0 | AG19: 0 | AH19: 0 | AI19: 0 | AJ19: 0 | AK19: 0 | AL19: 0 | AM19: 0
B20: 14 New England | C20: Single Family | D20: Refrigeration | E20: =IF(D20="",E19,D20) -> Refrigeration | F20: Electricity | H20: Sum of TOTPURCHASE | I20: 12395 | J20: 9192 | K20: 10593 | L20: 10652 | M20: 90886 | N20: 98724 | O20: 107161 | P20: 115466 | Q20: 114056 | R20: 111589 | S20: 110117 | T20: 108578 | U20: 108112 | V20: 108075 | W20: 108398 | X20: 108050 | Y20: 108355 | Z20: 108497 | AA20: 107622 | AB20: 107813 | AC20: 107751 | AD20: 107673 | AE20: 106078 | AF20: 105064 | AG20: 103290 | AH20: 100941 | AI20: 98025 | AJ20: 100759 | AK20: 102464 | AL20: 103295 | AM20: 104385
B21: 15 New England | C21: Single Family | D21: Refrigeration | E21: =IF(D21="",E20,D21) -> Refrigeration | F21: Electricity | H21: Sum of TOTINVEST | I21: 6570190 | J21: 4872550 | K21: 5614349 | L21: 5645999 | M21: 58167696 | N21: 63184200 | O21: 68584258 | P21: 73899346 | Q21: 72996754 | R21: 71417518 | S21: 70475828 | T21: 69490601 | U21: 69192543 | V21: 69168761 | W21: 69375333 | X21: 69152165 | Y21: 69347694 | Z21: 69438250 | AA21: 68878761 | AB21: 69001286 | AC21: 68961234 | AD21: 68911414 | AE21: 67890891 | AF21: 67241238 | AG21: 66106089 | AH21: 64602620 | AI21: 62736773 | AJ21: 64486344 | AK21: 65577097 | AL21: 66109194 | AM21: 66806897
B22: 16 New England | C22: Single Family | D22: Refrigeration | E22: =IF(D22="",E21,D22) -> Refrigeration | F22: Electricity | G22: RefTF#2 | H22: Sum of TOTSUBSIDY | I22: 0 | J22: 0 | K22: 0 | L22: 0 | M22: 0 | N22: 0 | O22: 0 | P22: 0 | Q22: 0 | R22: 0 | S22: 0 | T22: 0 | U22: 0 | V22: 0 | W22: 0 | X22: 0 | Y22: 0 | Z22: 0 | AA22: 0 | AB22: 0 | AC22: 0 | AD22: 0 | AE22: 0 | AF22: 0 | AG22: 0 | AH22: 0 | AI22: 0 | AJ22: 0 | AK22: 0 | AL22: 0 | AM22: 0
B23: 17 New England | C23: Single Family | D23: Refrigeration | E23: =IF(D23="",E22,D23) -> Refrigeration | F23: Electricity | H23: Sum of TOTPURCHASE | I23: 52693 | J23: 35293 | K23: 38057 | L23: 39952 | M23: 24317 | N23: 25195 | O23: 26061 | P23: 27530 | Q23: 27900 | R23: 28189 | S23: 28550 | T23: 28789 | U23: 29092 | V23: 29548 | W23: 29849 | X23: 30163 | Y23: 30328 | Z23: 30332 | AA23: 30315 | AB23: 30280 | AC23: 30296 | AD23: 30115 | AE23: 29769 | AF23: 29469 | AG23: 29040 | AH23: 28396 | AI23: 27627 | AJ23: 28275 | AK23: 29060 | AL23: 29835 | AM23: 30460
B24: 18 New England | C24: Single Family | D24: Refrigeration | E24: =IF(D24="",E23,D24) -> Refrigeration | F24: Electricity | H24: Sum of TOTINVEST | I24: 33723842 | J24: 22587672 | K24: 24356898 | L24: 25569733 | M24: 19453713 | N24: 20157305 | O24: 20849660 | P24: 22025093 | Q24: 22320892 | R24: 22552062 | S24: 22840451 | T24: 23032104 | U24: 23274475 | V24: 23639089 | W24: 23879883 | X24: 24131330 | Y24: 24262833 | Z24: 24266824 | AA24: 24252692 | AB24: 24225076 | AC24: 24237447 | AD24: 24093179 | AE24: 23816242 | AF24: 23576422 | AG24: 23232940 | AH24: 22717720 | AI24: 22101855 | AJ24: 22620585 | AK24: 23249063 | AL24: 23869179 | AM24: 24369094
B25: 19 New England | C25: Single Family | D25: Refrigeration | E25: =IF(D25="",E24,D25) -> Refrigeration | F25: Electricity | G25: RefTF#3 | H25: Sum of TOTSUBSIDY | I25: 4726838 | J25: 13466458 | K25: 14120400 | L25: 15094907 | M25: 0 | N25: 0 | O25: 0 | P25: 0 | Q25: 0 | R25: 0 | S25: 0 | T25: 0 | U25: 0 | V25: 0 | W25: 0 | X25: 0 | Y25: 0 | Z25: 0 | AA25: 0 | AB25: 0 | AC25: 0 | AD25: 0 | AE25: 0 | AF25: 0 | AG25: 0 | AH25: 0 | AI25: 0 | AJ25: 0 | AK25: 0 | AL25: 0 | AM25: 0
B26: 20 New England | C26: Single Family | D26: Refrigeration | E26: =IF(D26="",E25,D26) -> Refrigeration | F26: Electricity | H26: Sum of TOTPURCHASE | I26: 47267 | J26: 67331 | K26: 70601 | L26: 75473 | M26: 16102 | N26: 15991 | O26: 15837 | P26: 16434 | Q26: 17043 | R26: 17726 | S26: 18377 | T26: 18910 | U26: 19364 | V26: 19951 | W26: 20284 | X26: 20752 | Y26: 20915 | Z26: 20897 | AA26: 21026 | AB26: 20947 | AC26: 20978 | AD26: 20756 | AE26: 20579 | AF26: 20362 | AG26: 20108 | AH26: 19672 | AI26: 19170 | AJ26: 19544 | AK26: 20280 | AL26: 21124 | AM26: 21740
B27: 21 New England | C27: Single Family | D27: Refrigeration | E27: =IF(D27="",E26,D27) -> Refrigeration | F27: Electricity | H27: Sum of TOTINVEST | I27: 37814717 | J27: 59252418 | K27: 62129760 | L27: 66417593 | M27: 14170394 | N27: 14072334 | O27: 13937270 | P27: 14463015 | Q27: 14999293 | R27: 15599860 | S27: 16173149 | T27: 16641469 | U27: 17041615 | V27: 17557802 | W27: 17851260 | X27: 18262908 | Y27: 18405666 | Z27: 18389813 | AA27: 18503654 | AB27: 18434177 | AC27: 18461750 | AD27: 18265331 | AE27: 18110078 | AF27: 17919548 | AG27: 17695871 | AH27: 17312488 | AI27: 16870838 | AJ27: 17199974 | AK27: 17847856 | AL27: 18589902 | AM27: 19131718
B28: 22 New England | C28: Single Family | D28: Cooling | E28: =IF(D28="",E27,D28) -> Cooling | F28: Electricity | G28: CT_AIR#1 | H28: Sum of TOTSUBSIDY | I28: 0 | J28: 0 | K28: 0 | L28: 0 | M28: 0 | N28: 0 | O28: 0 | P28: 0 | Q28: 0 | R28: 0 | S28: 0 | T28: 0 | U28: 0 | V28: 0 | W28: 0 | X28: 0 | Y28: 0 | Z28: 0 | AA28: 0 | AB28: 0 | AC28: 0 | AD28: 0 | AE28: 0 | AF28: 0 | AG28: 0 | AH28: 0 | AI28: 0 | AJ28: 0 | AK28: 0 | AL28: 0 | AM28: 0
B29: 23 New England | C29: Single Family | D29: Cooling | E29: =IF(D29="",E28,D29) -> Cooling | F29: Electricity | H29: Sum of TOTPURCHASE | I29: 22254 | J29: 49768 | K29: 53717 | L29: 56009 | M29: 38471 | N29: 40976 | O29: 43875 | P29: 48472 | Q29: 48636 | R29: 48247 | S29: 47974 | T29: 47327 | U29: 46959 | V29: 47038 | W29: 47036 | X29: 47158 | Y29: 47283 | Z29: 47303 | AA29: 46507 | AB29: 46214 | AC29: 45608 | AD29: 44253 | AE29: 45143 | AF29: 46206 | AG29: 47071 | AH29: 47848 | AI29: 48330 | AJ29: 48818 | AK29: 48814 | AL29: 48702 | AM29: 48783
B30: 24 New England | C30: Single Family | D30: Cooling | E30: =IF(D30="",E29,D30) -> Cooling | F30: Electricity | H30: Sum of TOTINVEST | I30: 37832347 | J30: 84608767 | K30: 91320638 | L30: 95217437 | M30: 65403420 | N30: 69659933 | O30: 74588578 | P30: 82403952 | Q30: 82682896 | R30: 82020312 | S30: 81557980 | T30: 80456438 | U30: 79831972 | V30: 79965356 | W30: 79962086 | X30: 80171486 | Y30: 80382804 | Z30: 80415866 | AA30: 79063114 | AB30: 78564992 | AC30: 77534424 | AD30: 75230450 | AE30: 76745696 | AF30: 78552862 | AG30: 80021869 | AH30: 81343775 | AI30: 82162557 | AJ30: 82992508 | AK30: 82985931 | AL30: 82795979 | AM30: 82933594
B31: 25 New England | C31: Single Family | D31: Cooling | E31: =IF(D31="",E30,D31) -> Cooling | F31: Electricity | G31: CT_AIR#2 | H31: Sum of TOTSUBSIDY | I31: 0 | J31: 0 | K31: 0 | L31: 0 | M31: 0 | N31: 0 | O31: 0 | P31: 0 | Q31: 0 | R31: 0 | S31: 0 | T31: 0 | U31: 0 | V31: 0 | W31: 0 | X31: 0 | Y31: 0 | Z31: 0 | AA31: 0 | AB31: 0 | AC31: 0 | AD31: 0 | AE31: 0 | AF31: 0 | AG31: 0 | AH31: 0 | AI31: 0 | AJ31: 0 | AK31: 0 | AL31: 0 | AM31: 0
B32: 26 New England | C32: Single Family | D32: Cooling | E32: =IF(D32="",E31,D32) -> Cooling | F32: Electricity | H32: Sum of TOTPURCHASE | I32: 22954 | J32: 0 | K32: 0 | L32: 0 | M32: 19975 | N32: 21273 | O32: 22772 | P32: 24465 | Q32: 24485 | R32: 24662 | S32: 24837 | T32: 25093 | U32: 25336 | V32: 25865 | W32: 26184 | X32: 26457 | Y32: 26680 | Z32: 27056 | AA32: 27290 | AB32: 27277 | AC32: 27017 | AD32: 26237 | AE32: 27555 | AF32: 28692 | AG32: 29700 | AH32: 30494 | AI32: 31127 | AJ32: 31520 | AK32: 32192 | AL32: 32686 | AM32: 33081
B33: 27 New England | C33: Single Family | D33: Cooling | E33: =IF(D33="",E32,D33) -> Cooling | F33: Electricity | H33: Sum of TOTINVEST | I33: 41891684 | J33: 0 | K33: 0 | L33: 0 | M33: 37952576 | N33: 40419676 | O33: 43267468 | P33: 46484712 | Q33: 46522100 | R33: 46858356 | S33: 47191012 | T33: 47677744 | U33: 48139504 | V33: 49145228 | W33: 49750296 | X33: 50268464 | Y33: 50693012 | Z33: 51408148 | AA33: 51852300 | AB33: 51826828 | AC33: 51333524 | AD33: 49851680 | AE33: 52355352 | AF33: 54516108 | AG33: 56431748 | AH33: 57938696 | AI33: 59143124 | AJ33: 59889428 | AK33: 61164988 | AL33: 62104516 | AM33: 62854900
B34: 28 New England | C34: Single Family | D34: Cooling | E34: =IF(D34="",E33,D34) -> Cooling | F34: Electricity | G34: CT_AIR#3 | H34: Sum of TOTSUBSIDY | I34: 5646 | J34: 128 | K34: 2187 | L34: 8506 | M34: 0 | N34: 0 | O34: 0 | P34: 0 | Q34: 0 | R34: 0 | S34: 0 | T34: 0 | U34: 0 | V34: 0 | W34: 0 | X34: 0 | Y34: 0 | Z34: 0 | AA34: 0 | AB34: 0 | AC34: 0 | AD34: 0 | AE34: 0 | AF34: 0 | AG34: 0 | AH34: 0 | AI34: 0 | AJ34: 0 | AK34: 0 | AL34: 0 | AM34: 0
B35: 29 New England | C35: Single Family | D35: Cooling | E35: =IF(D35="",E34,D35) -> Cooling | F35: Electricity | H35: Sum of TOTPURCHASE | I35: 6 | J35: 0 | K35: 12 | L35: 47 | M35: 14 | N35: 14 | O35: 17 | P35: 23 | Q35: 27 | R35: 29 | S35: 31 | T35: 34 | U35: 36 | V35: 40 | W35: 44 | X35: 49 | Y35: 54 | Z35: 59 | AA35: 61 | AB35: 66 | AC35: 68 | AD35: 72 | AE35: 73 | AF35: 77 | AG35: 81 | AH35: 85 | AI35: 89 | AJ35: 91 | AK35: 95 | AL35: 97 | AM35: 95
B36: 30 New England | C36: Single Family | D36: Cooling | E36: =IF(D36="",E35,D36) -> Cooling | F36: Electricity | H36: Sum of TOTINVEST | I36: 27986 | J36: 3256 | K36: 55302 | L36: 215036 | M36: 65623 | N36: 66144 | O36: 79626 | P36: 106755 | Q36: 123487 | R36: 135681 | S36: 145408 | T36: 155092 | U36: 167902 | V36: 183492 | W36: 200490 | X36: 225457 | Y36: 249294 | Z36: 269591 | AA36: 281942 | AB36: 301586 | AC36: 312714 | AD36: 329309 | AE36: 334245 | AF36: 351133 | AG36: 370491 | AH36: 391173 | AI36: 405154 | AJ36: 417252 | AK36: 433704 | AL36: 441501 | AM36: 435067
B37: 31 New England | C37: Single Family | D37: Cooling | E37: =IF(D37="",E36,D37) -> Cooling | F37: Electricity | G37: CT_AIR#4 | H37: Sum of TOTSUBSIDY | I37: 1088995 | J37: 12209 | K37: 25941 | L37: 63211 | M37: 0 | N37: 0 | O37: 0 | P37: 0 | Q37: 0 | R37: 0 | S37: 0 | T37: 0 | U37: 0 | V37: 0 | W37: 0 | X37: 0 | Y37: 0 | Z37: 0 | AA37: 0 | AB37: 0 | AC37: 0 | AD37: 0 | AE37: 0 | AF37: 0 | AG37: 0 | AH37: 0 | AI37: 0 | AJ37: 0 | AK37: 0 | AL37: 0 | AM37: 0
B38: 32 New England | C38: Single Family | D38: Cooling | E38: =IF(D38="",E37,D38) -> Cooling | F38: Electricity | H38: Sum of TOTPURCHASE | I38: 720 | J38: 42 | K38: 116 | L38: 325 | M38: 94 | N38: 112 | O38: 131 | P38: 161 | Q38: 188 | R38: 213 | S38: 242 | T38: 261 | U38: 285 | V38: 313 | W38: 343 | X38: 385 | Y38: 422 | Z38: 450 | AA38: 464 | AB38: 488 | AC38: 522 | AD38: 545 | AE38: 551 | AF38: 578 | AG38: 608 | AH38: 642 | AI38: 663 | AJ38: 682 | AK38: 717 | AL38: 739 | AM38: 775
B39: 33 New England | C39: Single Family | D39: Cooling | E39: =IF(D39="",E38,D39) -> Cooling | F39: Electricity | H39: Sum of TOTINVEST | I39: 3281026 | J39: 192668 | K39: 533419 | L39: 1484459 | M39: 434025 | N39: 513136 | O39: 598459 | P39: 737053 | Q39: 861272 | R39: 971738 | S39: 1104053 | T39: 1195194 | U39: 1302828 | V39: 1429228 | W39: 1561565 | X39: 1756364 | Y39: 1924352 | Z39: 2051486 | AA39: 2113720 | AB39: 2221917 | AC39: 2381253 | AD39: 2480946 | AE39: 2511575 | AF39: 2634854 | AG39: 2770319 | AH39: 2926128 | AI39: 3022314 | AJ39: 3109767 | AK39: 3266187 | AL39: 3365957 | AM39: 3527816
B40: 34 New England | C40: Single Family | D40: Cooling | E40: =IF(D40="",E39,D40) -> Cooling | F40: Electricity | G40: ELEC_HP1 | H40: Sum of TOTSUBSIDY | I40: 0 | J40: 0 | K40: 0 | L40: 0 | M40: 0 | N40: 0 | O40: 0 | P40: 0 | Q40: 0 | R40: 0 | S40: 0 | T40: 0 | U40: 0 | V40: 0 | W40: 0 | X40: 0 | Y40: 0 | Z40: 0 | AA40: 0 | AB40: 0 | AC40: 0 | AD40: 0 | AE40: 0 | AF40: 0 | AG40: 0 | AH40: 0 | AI40: 0 | AJ40: 0 | AK40: 0 | AL40: 0 | AM40: 0
B41: 35 New England | C41: Single Family | D41: Cooling | E41: =IF(D41="",E40,D41) -> Cooling | F41: Electricity | H41: Sum of TOTPURCHASE | I41: 906 | J41: 6191 | K41: 6523 | L41: 6509 | M41: 8406 | N41: 8545 | O41: 8780 | P41: 9102 | Q41: 9490 | R41: 10010 | S41: 10227 | T41: 10674 | U41: 11159 | V41: 11549 | W41: 12027 | X41: 12633 | Y41: 13305 | Z41: 13952 | AA41: 14603 | AB41: 15230 | AC41: 18257 | AD41: 18437 | AE41: 18597 | AF41: 18817 | AG41: 18981 | AH41: 19241 | AI41: 19675 | AJ41: 20086 | AK41: 20370 | AL41: 20490 | AM41: 21943
B42: 36 New England | C42: Single Family | D42: Cooling | E42: =IF(D42="",E41,D42) -> Cooling | F42: Electricity | H42: Sum of TOTINVEST | I42: 0 | J42: 0 | K42: 0 | L42: 0 | M42: 0 | N42: 0 | O42: 0 | P42: 0 | Q42: 0 | R42: 0 | S42: 0 | T42: 0 | U42: 0 | V42: 0 | W42: 0 | X42: 0 | Y42: 0 | Z42: 0 | AA42: 0 | AB42: 0 | AC42: 0 | AD42: 0 | AE42: 0 | AF42: 0 | AG42: 0 | AH42: 0 | AI42: 0 | AJ42: 0 | AK42: 0 | AL42: 0 | AM42: 0
B43: 37 New England | C43: Single Family | D43: Cooling | E43: =IF(D43="",E42,D43) -> Cooling | F43: Electricity | G43: ELEC_HP2 | H43: Sum of TOTSUBSIDY | I43: 4297678 | J43: 1176715 | K43: 1198179 | L43: 1263758 | M43: 0 | N43: 0 | O43: 0 | P43: 0 | Q43: 0 | R43: 0 | S43: 0 | T43: 0 | U43: 0 | V43: 0 | W43: 0 | X43: 0 | Y43: 0 | Z43: 0 | AA43: 0 | AB43: 0 | AC43: 0 | AD43: 0 | AE43: 0 | AF43: 0 | AG43: 0 | AH43: 0 | AI43: 0 | AJ43: 0 | AK43: 0 | AL43: 0 | AM43: 0
B44: 38 New England | C44: Single Family | D44: Cooling | E44: =IF(D44="",E43,D44) -> Cooling | F44: Electricity | H44: Sum of TOTPURCHASE | I44: 8682 | J44: 7844 | K44: 7987 | L44: 8425 | M44: 6982 | N44: 6777 | O44: 6785 | P44: 6989 | Q44: 7305 | R44: 7746 | S44: 8300 | T44: 8695 | U44: 9091 | V44: 9416 | W44: 9793 | X44: 10297 | Y44: 10829 | Z44: 11324 | AA44: 11848 | AB44: 12325 | AC44: 10570 | AD44: 10633 | AE44: 10719 | AF44: 10824 | AG44: 10904 | AH44: 11038 | AI44: 11276 | AJ44: 11484 | AK44: 11663 | AL44: 11830 | AM44: 11172
B45: 39 New England | C45: Single Family | D45: Cooling | E45: =IF(D45="",E44,D45) -> Cooling | F45: Electricity | H45: Sum of TOTINVEST | I45: 0 | J45: 0 | K45: 0 | L45: 0 | M45: 0 | N45: 0 | O45: 0 | P45: 0 | Q45: 0 | R45: 0 | S45: 0 | T45: 0 | U45: 0 | V45: 0 | W45: 0 | X45: 0 | Y45: 0 | Z45: 0 | AA45: 0 | AB45: 0 | AC45: 0 | AD45: 0 | AE45: 0 | AF45: 0 | AG45: 0 | AH45: 0 | AI45: 0 | AJ45: 0 | AK45: 0 | AL45: 0 | AM45: 0
B46: 40 New England | C46: Single Family | D46: Cooling | E46: =IF(D46="",E45,D46) -> Cooling | F46: Electricity | G46: ELEC_HP3 | H46: Sum of TOTSUBSIDY | I46: 0 | J46: 0 | K46: 0 | L46: 0 | M46: 0 | N46: 0 | O46: 0 | P46: 0 | Q46: 0 | R46: 0 | S46: 0 | T46: 0 | U46: 0 | V46: 0 | W46: 0 | X46: 0 | Y46: 0 | Z46: 0 | AA46: 0 | AB46: 0 | AC46: 0 | AD46: 0 | AE46: 0 | AF46: 0 | AG46: 0 | AH46: 0 | AI46: 0 | AJ46: 0 | AK46: 0 | AL46: 0 | AM46: 0
B47: 41 New England | C47: Single Family | D47: Cooling | E47: =IF(D47="",E46,D47) -> Cooling | F47: Electricity | H47: Sum of TOTPURCHASE | I47: 0 | J47: 0 | K47: 0 | L47: 0 | M47: 0 | N47: 0 | O47: 0 | P47: 0 | Q47: 0 | R47: 0 | S47: 0 | T47: 0 | U47: 0 | V47: 0 | W47: 0 | X47: 0 | Y47: 0 | Z47: 0 | AA47: 0 | AB47: 0 | AC47: 0 | AD47: 0 | AE47: 0 | AF47: 0 | AG47: 0 | AH47: 0 | AI47: 0 | AJ47: 0 | AK47: 0 | AL47: 0 | AM47: 0
B48: 42 New England | C48: Single Family | D48: Cooling | E48: =IF(D48="",E47,D48) -> Cooling | F48: Electricity | H48: Sum of TOTINVEST | I48: 0 | J48: 0 | K48: 0 | L48: 0 | M48: 0 | N48: 0 | O48: 0 | P48: 0 | Q48: 0 | R48: 0 | S48: 0 | T48: 0 | U48: 0 | V48: 0 | W48: 0 | X48: 0 | Y48: 0 | Z48: 0 | AA48: 0 | AB48: 0 | AC48: 0 | AD48: 0 | AE48: 0 | AF48: 0 | AG48: 0 | AH48: 0 | AI48: 0 | AJ48: 0 | AK48: 0 | AL48: 0 | AM48: 0
B49: 43 New England | C49: Single Family | D49: Cooling | E49: =IF(D49="",E48,D49) -> Cooling | F49: Electricity | G49: ELEC_HP4 | H49: Sum of TOTSUBSIDY | I49: 4516469 | J49: 281885 | K49: 273949 | L49: 311662 | M49: 0 | N49: 0 | O49: 0 | P49: 0 | Q49: 0 | R49: 0 | S49: 0 | T49: 0 | U49: 0 | V49: 0 | W49: 0 | X49: 0 | Y49: 0 | Z49: 0 | AA49: 0 | AB49: 0 | AC49: 0 | AD49: 0 | AE49: 0 | AF49: 0 | AG49: 0 | AH49: 0 | AI49: 0 | AJ49: 0 | AK49: 0 | AL49: 0 | AM49: 0
B50: 44 New England | C50: Single Family | D50: Cooling | E50: =IF(D50="",E49,D50) -> Cooling | F50: Electricity | H50: Sum of TOTPURCHASE | I50: 6691 | J50: 1879 | K50: 1826 | L50: 2077 | M50: 1737 | N50: 1583 | O50: 1529 | P50: 1561 | Q50: 1638 | R50: 1749 | S50: 2063 | T50: 2181 | U50: 2281 | V50: 2367 | W50: 2454 | X50: 2587 | Y50: 2711 | Z50: 2816 | AA50: 2943 | AB50: 3042 | AC50: 2933 | AD50: 2930 | AE50: 2950 | AF50: 2968 | AG50: 2983 | AH50: 3012 | AI50: 3071 | AJ50: 3115 | AK50: 3172 | AL50: 3274 | AM50: 2869
B51: 45 New England | C51: Single Family | D51: Cooling | E51: =IF(D51="",E50,D51) -> Cooling | F51: Electricity | H51: Sum of TOTINVEST | I51: 0 | J51: 0 | K51: 0 | L51: 0 | M51: 0 | N51: 0 | O51: 0 | P51: 0 | Q51: 0 | R51: 0 | S51: 0 | T51: 0 | U51: 0 | V51: 0 | W51: 0 | X51: 0 | Y51: 0 | Z51: 0 | AA51: 0 | AB51: 0 | AC51: 0 | AD51: 0 | AE51: 0 | AF51: 0 | AG51: 0 | AH51: 0 | AI51: 0 | AJ51: 0 | AK51: 0 | AL51: 0 | AM51: 0
B52: 46 New England | C52: Single Family | D52: Cooling | E52: =IF(D52="",E51,D52) -> Cooling | F52: Electricity | G52: ELECSTV1 | H52: Sum of TOTSUBSIDY | I52: 0 | J52: 0 | K52: 0 | L52: 0 | M52: 0 | N52: 0 | O52: 0 | P52: 0 | Q52: 0 | R52: 0 | S52: 0 | T52: 0 | U52: 0 | V52: 0 | W52: 0 | X52: 0 | Y52: 0 | Z52: 0 | AA52: 0 | AB52: 0 | AC52: 0 | AD52: 0 | AE52: 0 | AF52: 0 | AG52: 0 | AH52: 0 | AI52: 0 | AJ52: 0 | AK52: 0 | AL52: 0 | AM52: 0
B53: 47 New England | C53: Single Family | D53: Cooling | E53: =IF(D53="",E52,D53) -> Cooling | F53: Electricity | H53: Sum of TOTPURCHASE | I53: 0 | J53: 0 | K53: 0 | L53: 0 | M53: 0 | N53: 0 | O53: 0 | P53: 0 | Q53: 0 | R53: 0 | S53: 0 | T53: 0 | U53: 0 | V53: 0 | W53: 0 | X53: 0 | Y53: 0 | Z53: 0 | AA53: 0 | AB53: 0 | AC53: 0 | AD53: 0 | AE53: 0 | AF53: 0 | AG53: 0 | AH53: 0 | AI53: 0 | AJ53: 0 | AK53: 0 | AL53: 0 | AM53: 0
B54: 48 New England | C54: Single Family | D54: Cooling | E54: =IF(D54="",E53,D54) -> Cooling | F54: Electricity | H54: Sum of TOTINVEST | I54: 0 | J54: 0 | K54: 0 | L54: 0 | M54: 0 | N54: 0 | O54: 0 | P54: 0 | Q54: 0 | R54: 0 | S54: 0 | T54: 0 | U54: 0 | V54: 0 | W54: 0 | X54: 0 | Y54: 0 | Z54: 0 | AA54: 0 | AB54: 0 | AC54: 0 | AD54: 0 | AE54: 0 | AF54: 0 | AG54: 0 | AH54: 0 | AI54: 0 | AJ54: 0 | AK54: 0 | AL54: 0 | AM54: 0
B55: 49 New England | C55: Single Family | D55: Cooling | E55: =IF(D55="",E54,D55) -> Cooling | F55: Electricity | G55: ELECSTV2 | H55: Sum of TOTSUBSIDY | I55: 0 | J55: 0 | K55: 0 | L55: 0 | M55: 0 | N55: 0 | O55: 0 | P55: 0 | Q55: 0 | R55: 0 | S55: 0 | T55: 0 | U55: 0 | V55: 0 | W55: 0 | X55: 0 | Y55: 0 | Z55: 0 | AA55: 0 | AB55: 0 | AC55: 0 | AD55: 0 | AE55: 0 | AF55: 0 | AG55: 0 | AH55: 0 | AI55: 0 | AJ55: 0 | AK55: 0 | AL55: 0 | AM55: 0
B56: 50 New England | C56: Single Family | D56: Cooling | E56: =IF(D56="",E55,D56) -> Cooling | F56: Electricity | H56: Sum of TOTPURCHASE | I56: 87126 | J56: 82303 | K56: 82144 | L56: 87524 | M56: 90345 | N56: 97842 | O56: 104447 | P56: 111099 | Q56: 115383 | R56: 118166 | S56: 121700 | T56: 124980 | U56: 128111 | V56: 142963 | W56: 158898 | X56: 179859 | Y56: 204229 | Z56: 189902 | AA56: 167532 | AB56: 147912 | AC56: 124177 | AD56: 94124 | AE56: 100028 | AF56: 104426 | AG56: 109168 | AH56: 114398 | AI56: 119395 | AJ56: 124138 | AK56: 128674 | AL56: 133285 | AM56: 139109
B57: 51 New England | C57: Single Family | D57: Cooling | E57: =IF(D57="",E56,D57) -> Cooling | F57: Electricity | H57: Sum of TOTINVEST | I57: 26138121 | J57: 24690953 | K57: 24643374 | L57: 26257443 | M57: 27103629 | N57: 29352928 | O57: 31334258 | P57: 33329949 | Q57: 34615281 | R57: 35449925 | S57: 36510451 | T57: 37494124 | U57: 38433734 | V57: 42889194 | W57: 47669617 | X57: 53957989 | Y57: 61269013 | Z57: 56970870 | AA57: 50259984 | AB57: 44374021 | AC57: 37253374 | AD57: 28237442 | AE57: 30008680 | AF57: 31328031 | AG57: 32750592 | AH57: 34319467 | AI57: 35818707 | AJ57: 37241705 | AK57: 38602453 | AL57: 39985556 | AM57: 41733155
B58: 52 New England | C58: Single Family | D58: Cooling | E58: =IF(D58="",E57,D58) -> Cooling | F58: Electricity | G58: GEO_HP1 | H58: Sum of TOTSUBSIDY | I58: 392655 | J58: 427853 | K58: 443979 | L58: 486106 | M58: 536270 | N58: 549911 | O58: 588205 | P58: 0 | Q58: 0 | R58: 0 | S58: 0 | T58: 0 | U58: 0 | V58: 0 | W58: 0 | X58: 0 | Y58: 0 | Z58: 0 | AA58: 0 | AB58: 0 | AC58: 0 | AD58: 0 | AE58: 0 | AF58: 0 | AG58: 0 | AH58: 0 | AI58: 0 | AJ58: 0 | AK58: 0 | AL58: 0 | AM58: 0
B59: 53 New England | C59: Single Family | D59: Cooling | E59: =IF(D59="",E58,D59) -> Cooling | F59: Electricity | H59: Sum of TOTPURCHASE | I59: 1412 | J59: 852 | K59: 889 | L59: 1161 | M59: 1193 | N59: 1377 | O59: 1534 | P59: 1511 | Q59: 1392 | R59: 1259 | S59: 1175 | T59: 1071 | U59: 1006 | V59: 965 | W59: 941 | X59: 939 | Y59: 941 | Z59: 943 | AA59: 942 | AB59: 955 | AC59: 971 | AD59: 985 | AE59: 993 | AF59: 1007 | AG59: 1019 | AH59: 1032 | AI59: 1039 | AJ59: 1041 | AK59: 1042 | AL59: 1037 | AM59: 1031
B60: 54 New England | C60: Single Family | D60: Cooling | E60: =IF(D60="",E59,D60) -> Cooling | F60: Electricity | H60: Sum of TOTINVEST | I60: 0 | J60: 0 | K60: 0 | L60: 0 | M60: 0 | N60: 0 | O60: 0 | P60: 0 | Q60: 0 | R60: 0 | S60: 0 | T60: 0 | U60: 0 | V60: 0 | W60: 0 | X60: 0 | Y60: 0 | Z60: 0 | AA60: 0 | AB60: 0 | AC60: 0 | AD60: 0 | AE60: 0 | AF60: 0 | AG60: 0 | AH60: 0 | AI60: 0 | AJ60: 0 | AK60: 0 | AL60: 0 | AM60: 0
B61: 55 New England | C61: Single Family | D61: Cooling | E61: =IF(D61="",E60,D61) -> Cooling | F61: Electricity | G61: GEO_HP2 | H61: Sum of TOTSUBSIDY | I61: 1968 | J61: 1609 | K61: 1446 | L61: 2052 | M61: 2425 | N61: 2073 | O61: 1976 | P61: 0 | Q61: 0 | R61: 0 | S61: 0 | T61: 0 | U61: 0 | V61: 0 | W61: 0 | X61: 0 | Y61: 0 | Z61: 0 | AA61: 0 | AB61: 0 | AC61: 0 | AD61: 0 | AE61: 0 | AF61: 0 | AG61: 0 | AH61: 0 | AI61: 0 | AJ61: 0 | AK61: 0 | AL61: 0 | AM61: 0
B62: 56 New England | C62: Single Family | D62: Cooling | E62: =IF(D62="",E61,D62) -> Cooling | F62: Electricity | H62: Sum of TOTPURCHASE | I62: 0 | J62: 0 | K62: 0 | L62: 0 | M62: 0 | N62: 0 | O62: 0 | P62: 2 | Q62: 2 | R62: 2 | S62: 3 | T62: 3 | U62: 3 | V62: 3 | W62: 3 | X62: 3 | Y62: 4 | Z62: 4 | AA62: 4 | AB62: 4 | AC62: 4 | AD62: 5 | AE62: 5 | AF62: 5 | AG62: 5 | AH62: 5 | AI62: 5 | AJ62: 5 | AK62: 5 | AL62: 5 | AM62: 5
B63: 57 New England | C63: Single Family | D63: Cooling | E63: =IF(D63="",E62,D63) -> Cooling | F63: Electricity | H63: Sum of TOTINVEST | I63: 0 | J63: 0 | K63: 0 | L63: 0 | M63: 0 | N63: 0 | O63: 0 | P63: 0 | Q63: 0 | R63: 0 | S63: 0 | T63: 0 | U63: 0 | V63: 0 | W63: 0 | X63: 0 | Y63: 0 | Z63: 0 | AA63: 0 | AB63: 0 | AC63: 0 | AD63: 0 | AE63: 0 | AF63: 0 | AG63: 0 | AH63: 0 | AI63: 0 | AJ63: 0 | AK63: 0 | AL63: 0 | AM63: 0
B64: 58 New England | C64: Single Family | D64: Cooling | E64: =IF(D64="",E63,D64) -> Cooling | F64: Electricity | G64: RM_AIR#1 | H64: Sum of TOTSUBSIDY | I64: 0 | J64: 0 | K64: 0 | L64: 0 | M64: 0 | N64: 0 | O64: 0 | P64: 0 | Q64: 0 | R64: 0 | S64: 0 | T64: 0 | U64: 0 | V64: 0 | W64: 0 | X64: 0 | Y64: 0 | Z64: 0 | AA64: 0 | AB64: 0 | AC64: 0 | AD64: 0 | AE64: 0 | AF64: 0 | AG64: 0 | AH64: 0 | AI64: 0 | AJ64: 0 | AK64: 0 | AL64: 0 | AM64: 0
B65: 59 New England | C65: Single Family | D65: Cooling | E65: =IF(D65="",E64,D65) -> Cooling | F65: Electricity | H65: Sum of TOTPURCHASE | I65: 97082 | J65: 96173 | K65: 107608 | L65: 119355 | M65: 127708 | N65: 135455 | O65: 149229 | P65: 163380 | Q65: 179360 | R65: 172582 | S65: 169574 | T65: 161168 | U65: 157907 | V65: 154876 | W65: 146198 | X65: 137450 | Y65: 127505 | Z65: 138946 | AA65: 147596 | AB65: 154889 | AC65: 163048 | AD65: 166119 | AE65: 166588 | AF65: 165585 | AG65: 163141 | AH65: 160151 | AI65: 157023 | AJ65: 154758 | AK65: 152737 | AL65: 152008 | AM65: 152733
B66: 60 New England | C66: Single Family | D66: Cooling | E66: =IF(D66="",E65,D66) -> Cooling | F66: Electricity | H66: Sum of TOTINVEST | I66: 27668486 | J66: 27409332 | K66: 30668571 | L66: 34016478 | M66: 36397002 | N66: 38604963 | O66: 42530590 | P66: 46563543 | Q66: 51117894 | R66: 49186133 | S66: 48328772 | T66: 45933204 | U66: 45003786 | V66: 44139855 | W66: 41666757 | X66: 39173298 | Y66: 36339360 | Z66: 39599921 | AA66: 42065246 | AB66: 44143496 | AC66: 46469003 | AD66: 47343963 | AE66: 47477711 | AF66: 47191863 | AG66: 46495689 | AH66: 45643387 | AI66: 44751857 | AJ66: 44106247 | AK66: 43530344 | AL66: 43322716 | AM66: 43529241
B67: 61 New England | C67: Single Family | D67: Cooling | E67: =IF(D67="",E66,D67) -> Cooling | F67: Electricity | G67: RM_AIR#2 | H67: Sum of TOTSUBSIDY | I67: 0 | J67: 0 | K67: 0 | L67: 0 | M67: 0 | N67: 0 | O67: 0 | P67: 0 | Q67: 0 | R67: 0 | S67: 0 | T67: 0 | U67: 0 | V67: 0 | W67: 0 | X67: 0 | Y67: 0 | Z67: 0 | AA67: 0 | AB67: 0 | AC67: 0 | AD67: 0 | AE67: 0 | AF67: 0 | AG67: 0 | AH67: 0 | AI67: 0 | AJ67: 0 | AK67: 0 | AL67: 0 | AM67: 0
B68: 62 New England | C68: Single Family | D68: Cooling | E68: =IF(D68="",E67,D68) -> Cooling | F68: Electricity | H68: Sum of TOTPURCHASE | I68: 92105 | J68: 90337 | K68: 101092 | L68: 111674 | M68: 118511 | N68: 126405 | O68: 139581 | P68: 152694 | Q68: 168019 | R68: 162072 | S68: 159661 | T68: 152104 | U68: 149324 | V68: 146773 | W68: 138764 | X68: 130757 | Y68: 121454 | Z68: 132523 | AA68: 141117 | AB68: 148132 | AC68: 156613 | AD68: 159620 | AE68: 160234 | AF68: 159433 | AG68: 157317 | AH68: 154570 | AI68: 151653 | AJ68: 149374 | AK68: 147890 | AL68: 147483 | AM68: 148407
B69: 63 New England | C69: Single Family | D69: Cooling | E69: =IF(D69="",E68,D69) -> Cooling | F69: Electricity | H69: Sum of TOTINVEST | I69: 28092268 | J69: 27553238 | K69: 30833617 | L69: 34060847 | M69: 36146249 | N69: 38554004 | O69: 42572545 | P69: 46572058 | Q69: 51246178 | R69: 49432149 | S69: 48696881 | T69: 46392038 | U69: 45544274 | V69: 44765895 | W69: 42323320 | X69: 39881157 | Y69: 37043938 | Z69: 40419696 | AA69: 43041064 | AB69: 45180440 | AC69: 47767060 | AD69: 48684374 | AE69: 48871663 | AF69: 48627266 | AG69: 47982172 | AH69: 47144133 | AI69: 46254311 | AJ69: 45559197 | AK69: 45106769 | AL69: 44982892 | AM69: 45264529
B70: 64 New England | C70: Single Family | D70: Cooling | E70: =IF(D70="",E69,D70) -> Cooling | F70: Electricity | G70: RM_AIR#3 | H70: Sum of TOTSUBSIDY | I70: 0 | J70: 0 | K70: 0 | L70: 0 | M70: 0 | N70: 0 | O70: 0 | P70: 0 | Q70: 0 | R70: 0 | S70: 0 | T70: 0 | U70: 0 | V70: 0 | W70: 0 | X70: 0 | Y70: 0 | Z70: 0 | AA70: 0 | AB70: 0 | AC70: 0 | AD70: 0 | AE70: 0 | AF70: 0 | AG70: 0 | AH70: 0 | AI70: 0 | AJ70: 0 | AK70: 0 | AL70: 0 | AM70: 0
B71: 65 New England | C71: Single Family | D71: Cooling | E71: =IF(D71="",E70,D71) -> Cooling | F71: Electricity | H71: Sum of TOTPURCHASE | I71: 42513 | J71: 41462 | K71: 46402 | L71: 51141 | M71: 54019 | N71: 57801 | O71: 63910 | P71: 69882 | Q71: 76997 | R71: 74376 | S71: 57854 | T71: 55230 | U71: 54315 | V71: 53488 | W71: 50638 | X71: 48028 | Y71: 44680 | Z71: 48929 | AA71: 52597 | AB71: 55126 | AC71: 50828 | AD71: 51738 | AE71: 52071 | AF71: 51943 | AG71: 51526 | AH71: 50710 | AI71: 49775 | AJ71: 48695 | AK71: 48880 | AL71: 49131 | AM71: 49675
B72: 66 New England | C72: Single Family | D72: Cooling | E72: =IF(D72="",E71,D72) -> Cooling | F72: Electricity | H72: Sum of TOTINVEST | I72: 19769071 | J72: 19280370 | K72: 21577414 | L72: 23780909 | M72: 25119443 | N72: 26877896 | O72: 29718310 | P72: 32495417 | Q72: 35803953 | R72: 34585276 | S72: 29795319 | T72: 28443706 | U72: 27972938 | V72: 27546645 | W72: 26079076 | X72: 24735023 | Y72: 23010785 | Z72: 25199270 | AA72: 27087844 | AB72: 28390481 | AC72: 27955797 | AD72: 28456682 | AE72: 28639149 | AF72: 28569242 | AG72: 28339756 | AH72: 27890943 | AI72: 27376760 | AJ72: 26782626 | AK72: 26884394 | AL72: 27022431 | AM72: 27321771
B73: 67 New England | C73: Single Family | D73: Cooling | E73: =IF(D73="",E72,D73) -> Cooling | F73: Natural Gas | G73: NG_HP | H73: Sum of TOTSUBSIDY | I73: 0 | J73: 0 | K73: 0 | L73: 0 | M73: 0 | N73: 0 | O73: 0 | P73: 0 | Q73: 0 | R73: 0 | S73: 0 | T73: 0 | U73: 0 | V73: 0 | W73: 0 | X73: 0 | Y73: 0 | Z73: 0 | AA73: 0 | AB73: 0 | AC73: 0 | AD73: 0 | AE73: 0 | AF73: 0 | AG73: 0 | AH73: 0 | AI73: 0 | AJ73: 0 | AK73: 0 | AL73: 0 | AM73: 0
B74: 68 New England | C74: Single Family | D74: Cooling | E74: =IF(D74="",E73,D74) -> Cooling | F74: Natural Gas | H74: Sum of TOTPURCHASE | I74: 0 | J74: 8 | K74: 11 | L74: 0 | M74: 0 | N74: 0 | O74: 0 | P74: 0 | Q74: 0 | R74: 0 | S74: 0 | T74: 1 | U74: 1 | V74: 1 | W74: 1 | X74: 1 | Y74: 1 | Z74: 1 | AA74: 1 | AB74: 1 | AC74: 1 | AD74: 1 | AE74: 1 | AF74: 1 | AG74: 1 | AH74: 1 | AI74: 1 | AJ74: 1 | AK74: 1 | AL74: 1 | AM74: 1
B75: 69 New England | C75: Single Family | D75: Cooling | E75: =IF(D75="",E74,D75) -> Cooling | F75: Natural Gas | H75: Sum of TOTINVEST | I75: 0 | J75: 0 | K75: 0 | L75: 0 | M75: 0 | N75: 0 | O75: 0 | P75: 0 | Q75: 0 | R75: 0 | S75: 0 | T75: 0 | U75: 0 | V75: 0 | W75: 0 | X75: 0 | Y75: 0 | Z75: 0 | AA75: 0 | AB75: 0 | AC75: 0 | AD75: 0 | AE75: 0 | AF75: 0 | AG75: 0 | AH75: 0 | AI75: 0 | AJ75: 0 | AK75: 0 | AL75: 0 | AM75: 0
B76: 70 New England | C76: Single Family | D76: Cooling | E76: =IF(D76="",E75,D76) -> Cooling | F76: Natural Gas | G76: NG_STV1 | H76: Sum of TOTSUBSIDY | I76: 0 | J76: 0 | K76: 0 | L76: 0 | M76: 0 | N76: 0 | O76: 0 | P76: 0 | Q76: 0 | R76: 0 | S76: 0 | T76: 0 | U76: 0 | V76: 0 | W76: 0 | X76: 0 | Y76: 0 | Z76: 0 | AA76: 0 | AB76: 0 | AC76: 0 | AD76: 0 | AE76: 0 | AF76: 0 | AG76: 0 | AH76: 0 | AI76: 0 | AJ76: 0 | AK76: 0 | AL76: 0 | AM76: 0
B77: 71 New England | C77: Single Family | D77: Cooling | E77: =IF(D77="",E76,D77) -> Cooling | F77: Natural Gas | H77: Sum of TOTPURCHASE | I77: 24724 | J77: 24484 | K77: 25761 | L77: 28858 | M77: 30151 | N77: 31857 | O77: 33108 | P77: 34906 | Q77: 35669 | R77: 35862 | S77: 36918 | T77: 37956 | U77: 38185 | V77: 38406 | W77: 39029 | X77: 40297 | Y77: 42185 | Z77: 38653 | AA77: 36350 | AB77: 35054 | AC77: 33670 | AD77: 30925 | AE77: 33138 | AF77: 34766 | AG77: 36204 | AH77: 37468 | AI77: 38467 | AJ77: 39268 | AK77: 39885 | AL77: 40270 | AM77: 40751
B78: 72 New England | C78: Single Family | D78: Cooling | E78: =IF(D78="",E77,D78) -> Cooling | F78: Natural Gas | H78: Sum of TOTINVEST | I78: 7417349 | J78: 7345340 | K78: 7728485 | L78: 8657763 | M78: 9045754 | N78: 9557277 | O78: 9932603 | P78: 10472087 | Q78: 10701020 | R78: 10758716 | S78: 11075729 | T78: 11387145 | U78: 11455662 | V78: 11522045 | W78: 11708996 | X78: 12089440 | Y78: 12655842 | Z78: 11596256 | AA78: 10905375 | AB78: 10516512 | AC78: 10101370 | AD78: 9277805 | AE78: 9941755 | AF78: 10430339 | AG78: 10861578 | AH78: 11240781 | AI78: 11540377 | AJ78: 11780662 | AK78: 11965677 | AL78: 12081108 | AM78: 12225729
B79: 73 New England | C79: Single Family | D79: Cooling | E79: =IF(D79="",E78,D79) -> Cooling | F79: Natural Gas | G79: NG_STV2 | H79: Sum of TOTSUBSIDY | I79: 0 | J79: 0 | K79: 0 | L79: 0 | M79: 0 | N79: 0 | O79: 0 | P79: 0 | Q79: 0 | R79: 0 | S79: 0 | T79: 0 | U79: 0 | V79: 0 | W79: 0 | X79: 0 | Y79: 0 | Z79: 0 | AA79: 0 | AB79: 0 | AC79: 0 | AD79: 0 | AE79: 0 | AF79: 0 | AG79: 0 | AH79: 0 | AI79: 0 | AJ79: 0 | AK79: 0 | AL79: 0 | AM79: 0
B80: 74 New England | C80: Single Family | D80: Cooling | E80: =IF(D80="",E79,D80) -> Cooling | F80: Natural Gas | H80: Sum of TOTPURCHASE | I80: 11915 | J80: 11732 | K80: 12301 | L80: 13756 | M80: 14244 | N80: 15015 | O80: 15612 | P80: 16519 | Q80: 16914 | R80: 17072 | S80: 17626 | T80: 18169 | U80: 18311 | V80: 18446 | W80: 18769 | X80: 19404 | Y80: 20326 | Z80: 18619 | AA80: 17498 | AB80: 16868 | AC80: 16201 | AD80: 14886 | AE80: 15966 | AF80: 16770 | AG80: 17477 | AH80: 18172 | AI80: 18772 | AJ80: 19344 | AK80: 19877 | AL80: 20349 | AM80: 20796
B81: 75 New England | C81: Single Family | D81: Cooling | E81: =IF(D81="",E80,D81) -> Cooling | F81: Natural Gas | H81: Sum of TOTINVEST | I81: 4170624 | J81: 4106560 | K81: 4305599 | L81: 4814951 | M81: 4986052 | N81: 5255604 | O81: 5464435 | P81: 5781890 | Q81: 5920030 | R81: 5975446 | S81: 6169783 | T81: 6359466 | U81: 6409039 | V81: 6456499 | W81: 6569345 | X81: 6791798 | Y81: 7114440 | Z81: 6517252 | AA81: 6124463 | AB81: 5904380 | AC81: 5670604 | AD81: 5210681 | AE81: 5588544 | AF81: 5869892 | AG81: 6117396 | AH81: 6360732 | AI81: 6570592 | AJ81: 6770455 | AK81: 6957569 | AL81: 7122490 | AM81: 7279055
B82: 76 New England | C82: Single Family | D82: Cooling | E82: =IF(D82="",E81,D82) -> Cooling | F82: LPG | G82: LPG_STV1 | H82: Sum of TOTSUBSIDY | I82: 0 | J82: 0 | K82: 0 | L82: 0 | M82: 0 | N82: 0 | O82: 0 | P82: 0 | Q82: 0 | R82: 0 | S82: 0 | T82: 0 | U82: 0 | V82: 0 | W82: 0 | X82: 0 | Y82: 0 | Z82: 0 | AA82: 0 | AB82: 0 | AC82: 0 | AD82: 0 | AE82: 0 | AF82: 0 | AG82: 0 | AH82: 0 | AI82: 0 | AJ82: 0 | AK82: 0 | AL82: 0 | AM82: 0
B83: 77 New England | C83: Single Family | D83: Cooling | E83: =IF(D83="",E82,D83) -> Cooling | F83: LPG | H83: Sum of TOTPURCHASE | I83: 10195 | J83: 9959 | K83: 12571 | L83: 9714 | M83: 9989 | N83: 10698 | O83: 11093 | P83: 11741 | Q83: 12032 | R83: 12140 | S83: 12542 | T83: 12922 | U83: 13031 | V83: 13130 | W83: 13368 | X83: 13842 | Y83: 14519 | Z83: 13419 | AA83: 12733 | AB83: 12399 | AC83: 11993 | AD83: 10989 | AE83: 11394 | AF83: 11482 | AG83: 11549 | AH83: 11771 | AI83: 12061 | AJ83: 12361 | AK83: 12628 | AL83: 12820 | AM83: 13018
B84: 78 New England | C84: Single Family | D84: Cooling | E84: =IF(D84="",E83,D84) -> Cooling | F84: LPG | H84: Sum of TOTINVEST | I84: 3058530 | J84: 2987946 | K84: 3771878 | L84: 2914686 | M84: 2997100 | N84: 3209702 | O84: 3328159 | P84: 3522414 | Q84: 3609956 | R84: 3642389 | S84: 3762850 | T84: 3876610 | U84: 3909597 | V84: 3939537 | W84: 4010716 | X84: 4152675 | Y84: 4356037 | Z84: 4025904 | AA84: 3820284 | AB84: 3719964 | AC84: 3598175 | AD84: 3296975 | AE84: 3418406 | AF84: 3444810 | AG84: 3464998 | AH84: 3531661 | AI84: 3618615 | AJ84: 3708761 | AK84: 3788841 | AL84: 3846174 | AM84: 3905932
B85: 79 New England | C85: Single Family | D85: Cooling | E85: =IF(D85="",E84,D85) -> Cooling | F85: LPG | G85: LPG_STV2 | H85: Sum of TOTSUBSIDY | I85: 0 | J85: 0 | K85: 0 | L85: 0 | M85: 0 | N85: 0 | O85: 0 | P85: 0 | Q85: 0 | R85: 0 | S85: 0 | T85: 0 | U85: 0 | V85: 0 | W85: 0 | X85: 0 | Y85: 0 | Z85: 0 | AA85: 0 | AB85: 0 | AC85: 0 | AD85: 0 | AE85: 0 | AF85: 0 | AG85: 0 | AH85: 0 | AI85: 0 | AJ85: 0 | AK85: 0 | AL85: 0 | AM85: 0
B86: 80 New England | C86: Single Family | D86: Cooling | E86: =IF(D86="",E85,D86) -> Cooling | F86: LPG | H86: Sum of TOTPURCHASE | I86: 5289 | J86: 5175 | K86: 6488 | L86: 4991 | M86: 5147 | N86: 5412 | O86: 5652 | P86: 5995 | Q86: 6150 | R86: 6213 | S86: 6421 | T86: 6619 | U86: 6679 | V86: 6736 | W86: 6863 | X86: 7111 | Y86: 7467 | Z86: 6907 | AA86: 6558 | AB86: 6392 | AC86: 6188 | AD86: 5677 | AE86: 5894 | AF86: 5946 | AG86: 5988 | AH86: 6110 | AI86: 6268 | AJ86: 6430 | AK86: 6577 | AL86: 6687 | AM86: 6817
B87: 81 New England | C87: Single Family | D87: Cooling | E87: =IF(D87="",E86,D87) -> Cooling | F87: LPG | H87: Sum of TOTINVEST | I87: 1851528 | J87: 1811465 | K87: 2271387 | L87: 1747269 | M87: 1801588 | N87: 1894653 | O87: 1978582 | P87: 2098914 | Q87: 2153119 | R87: 2174676 | S87: 2247583 | T87: 2316900 | U87: 2337942 | V87: 2358039 | W87: 2402421 | X87: 2489348 | Y87: 2613952 | Z87: 2417697 | AA87: 2295853 | AB87: 2237565 | AC87: 2166216 | AD87: 1987165 | AE87: 2063170 | AF87: 2081457 | AG87: 2096064 | AH87: 2138877 | AI87: 2194124 | AJ87: 2251081 | AK87: 2302275 | AL87: 2340680 | AM87: 2386184
B88: 82 New England | C88: Single Family | D88: Clothes Washing | E88: =IF(D88="",E87,D88) -> Clothes Washing | F88: Electricity | G88: CW#2 | H88: Sum of TOTSUBSIDY | I88: 0 | J88: 0 | K88: 0 | L88: 0 | M88: 0 | N88: 0 | O88: 0 | P88: 0 | Q88: 0 | R88: 0 | S88: 0 | T88: 0 | U88: 0 | V88: 0 | W88: 0 | X88: 0 | Y88: 0 | Z88: 0 | AA88: 0 | AB88: 0 | AC88: 0 | AD88: 0 | AE88: 0 | AF88: 0 | AG88: 0 | AH88: 0 | AI88: 0 | AJ88: 0 | AK88: 0 | AL88: 0 | AM88: 0
B89: 83 New England | C89: Single Family | D89: Clothes Washing | E89: =IF(D89="",E88,D89) -> Clothes Washing | F89: Electricity | H89: Sum of TOTPURCHASE | I89: 537 | J89: 520 | K89: 533 | L89: 556 | M89: 157165 | N89: 161072 | O89: 164189 | P89: 167958 | Q89: 140180 | R89: 149096 | S89: 266911 | T89: 285168 | U89: 269514 | V89: 259535 | W89: 255474 | X89: 254370 | Y89: 251866 | Z89: 242833 | AA89: 225442 | AB89: 239301 | AC89: 248779 | AD89: 255176 | AE89: 259646 | AF89: 264749 | AG89: 269415 | AH89: 273209 | AI89: 275136 | AJ89: 275347 | AK89: 273788 | AL89: 270508 | AM89: 267195
B90: 84 New England | C90: Single Family | D90: Clothes Washing | E90: =IF(D90="",E89,D90) -> Clothes Washing | F90: Electricity | H90: Sum of TOTINVEST | I90: 338641 | J90: 328067 | K90: 336772 | L90: 351198 | M90: 99014425 | N90: 101476242 | O90: 103439659 | P90: 105814296 | Q90: 96724608 | R90: 102876592 | S90: 184168902 | T90: 196766798 | U90: 185965238 | V90: 179080256 | W90: 176277562 | X90: 175515930 | Y90: 173788670 | Z90: 167555982 | AA90: 155555526 | AB90: 165118752 | AC90: 171658676 | AD90: 176072020 | AE90: 179156010 | AF90: 182678068 | AG90: 185896598 | AH90: 188514368 | AI90: 189844228 | AJ90: 189990518 | AK90: 188914364 | AL90: 186651608 | AM90: 184365318
B91: 85 New England | C91: Single Family | D91: Clothes Washing | E91: =IF(D91="",E90,D91) -> Clothes Washing | F91: Electricity | G91: CW#3 | H91: Sum of TOTSUBSIDY | I91: 52123078 | J91: 51177520 | K91: 52993023 | L91: 54709797 | M91: 0 | N91: 0 | O91: 0 | P91: 0 | Q91: 0 | R91: 0 | S91: 0 | T91: 0 | U91: 0 | V91: 0 | W91: 0 | X91: 0 | Y91: 0 | Z91: 0 | AA91: 0 | AB91: 0 | AC91: 0 | AD91: 0 | AE91: 0 | AF91: 0 | AG91: 0 | AH91: 0 | AI91: 0 | AJ91: 0 | AK91: 0 | AL91: 0 | AM91: 0
B92: 86 New England | C92: Single Family | D92: Clothes Washing | E92: =IF(D92="",E91,D92) -> Clothes Washing | F92: Electricity | H92: Sum of TOTPURCHASE | I92: 208492 | J92: 204709 | K92: 211971 | L92: 218838 | M92: 64940 | N92: 68287 | O92: 71437 | P92: 73807 | Q92: 108339 | R92: 106055 | S92: 309 | T92: 348 | U92: 341 | V92: 341 | W92: 342 | X92: 352 | Y92: 351 | Z92: 337 | AA92: 319 | AB92: 336 | AC92: 351 | AD92: 356 | AE92: 365 | AF92: 372 | AG92: 381 | AH92: 387 | AI92: 391 | AJ92: 388 | AK92: 404 | AL92: 437 | AM92: 452
B93: 87 New England | C93: Single Family | D93: Clothes Washing | E93: =IF(D93="",E92,D93) -> Clothes Washing | F93: Electricity | H93: Sum of TOTINVEST | I93: 135520004 | J93: 133061548 | K93: 137781862 | L93: 142245469 | M93: 42211500 | N93: 44387724 | O93: 46435086 | P93: 47975190 | Q93: 70421341 | R93: 68936195 | S93: 306227 | T93: 345673 | U93: 338918 | V93: 339136 | W93: 339494 | X93: 349485 | Y93: 348139 | Z93: 334816 | AA93: 316846 | AB93: 334122 | AC93: 348639 | AD93: 353189 | AE93: 362418 | AF93: 369132 | AG93: 377960 | AH93: 383981 | AI93: 388276 | AJ93: 384325 | AK93: 401146 | AL93: 433656 | AM93: 448638
B94: 88 New England | C94: Single Family | D94: Clothes Drying | E94: =IF(D94="",E93,D94) -> Clothes Drying | F94: Electricity | G94: ELECDRY1 | H94: Sum of TOTSUBSIDY | I94: 0 | J94: 0 | K94: 0 | L94: 0 | M94: 0 | N94: 0 | O94: 0 | P94: 0 | Q94: 0 | R94: 0 | S94: 0 | T94: 0 | U94: 0 | V94: 0 | W94: 0 | X94: 0 | Y94: 0 | Z94: 0 | AA94: 0 | AB94: 0 | AC94: 0 | AD94: 0 | AE94: 0 | AF94: 0 | AG94: 0 | AH94: 0 | AI94: 0 | AJ94: 0 | AK94: 0 | AL94: 0 | AM94: 0
B95: 89 New England | C95: Single Family | D95: Clothes Drying | E95: =IF(D95="",E94,D95) -> Clothes Drying | F95: Electricity | H95: Sum of TOTPURCHASE | I95: 156823 | J95: 153111 | K95: 159716 | L95: 166031 | M95: 169859 | N95: 180567 | O95: 190986 | P95: 202542 | Q95: 211799 | R95: 220293 | S95: 233539 | T95: 247148 | U95: 236798 | V95: 229831 | W95: 224372 | X95: 221810 | Y95: 220215 | Z95: 217752 | AA95: 212805 | AB95: 205013 | AC95: 194919 | AD95: 206900 | AE95: 215692 | AF95: 223837 | AG95: 230810 | AH95: 236759 | AI95: 241083 | AJ95: 244111 | AK95: 245692 | AL95: 245531 | AM95: 244739
B96: 90 New England | C96: Single Family | D96: Clothes Drying | E96: =IF(D96="",E95,D96) -> Clothes Drying | F96: Electricity | H96: Sum of TOTINVEST | I96: 62729511 | J96: 61244685 | K96: 63886552 | L96: 66412989 | M96: 67943884 | N96: 90283814 | O96: 95493464 | P96: 101271673 | Q96: 105899952 | R96: 110147042 | S96: 128447078 | T96: 135931982 | U96: 130239284 | V96: 126407106 | W96: 123404809 | X96: 121996522 | Y96: 121118946 | Z96: 119764318 | AA96: 117043145 | AB96: 112757863 | AC96: 107206040 | AD96: 113795345 | AE96: 118631335 | AF96: 123110739 | AG96: 126946023 | AH96: 130218313 | AI96: 132596099 | AJ96: 134261367 | AK96: 135131150 | AL96: 135042692 | AM96: 134607223
B97: 91 New England | C97: Single Family | D97: Clothes Drying | E97: =IF(D97="",E96,D97) -> Clothes Drying | F97: Electricity | G97: ELECDRY2 | H97: Sum of TOTSUBSIDY | I97: 0 | J97: 0 | K97: 0 | L97: 0 | M97: 0 | N97: 0 | O97: 0 | P97: 0 | Q97: 0 | R97: 0 | S97: 0 | T97: 0 | U97: 0 | V97: 0 | W97: 0 | X97: 0 | Y97: 0 | Z97: 0 | AA97: 0 | AB97: 0 | AC97: 0 | AD97: 0 | AE97: 0 | AF97: 0 | AG97: 0 | AH97: 0 | AI97: 0 | AJ97: 0 | AK97: 0 | AL97: 0 | AM97: 0
B98: 92 New England | C98: Single Family | D98: Clothes Drying | E98: =IF(D98="",E97,D98) -> Clothes Drying | F98: Electricity | H98: Sum of TOTPURCHASE | I98: 0 | J98: 0 | K98: 0 | L98: 0 | M98: 0 | N98: 67 | O98: 64 | P98: 66 | Q98: 72 | R98: 81 | S98: 9 | T98: 11 | U98: 11 | V98: 12 | W98: 12 | X98: 14 | Y98: 14 | Z98: 14 | AA98: 14 | AB98: 13 | AC98: 12 | AD98: 13 | AE98: 13 | AF98: 14 | AG98: 15 | AH98: 15 | AI98: 16 | AJ98: 15 | AK98: 17 | AL98: 22 | AM98: 24
B99: 93 New England | C99: Single Family | D99: Clothes Drying | E99: =IF(D99="",E98,D99) -> Clothes Drying | F99: Electricity | H99: Sum of TOTINVEST | I99: 288 | J99: 271 | K99: 276 | L99: 296 | M99: 311 | N99: 40663 | O99: 39194 | P99: 40113 | Q99: 44086 | R99: 48856 | S99: 7031 | T99: 8477 | U99: 8861 | V99: 9419 | W99: 9570 | X99: 10238 | Y99: 10312 | Z99: 10136 | AA99: 10365 | AB99: 9831 | AC99: 9430 | AD99: 9719 | AE99: 10337 | AF99: 10698 | AG99: 11194 | AH99: 11533 | AI99: 11858 | AJ99: 11698 | AK99: 13094 | AL99: 15829 | AM99: 17402
B100: 94 New England | C100: Single Family | D100: Clothes Drying | E100: =IF(D100="",E99,D100) -> Clothes Drying | F100: Natural Gas | G100: NG_DRY1 | H100: Sum of TOTSUBSIDY | I100: 0 | J100: 0 | K100: 0 | L100: 0 | M100: 0 | N100: 0 | O100: 0 | P100: 0 | Q100: 0 | R100: 0 | S100: 0 | T100: 0 | U100: 0 | V100: 0 | W100: 0 | X100: 0 | Y100: 0 | Z100: 0 | AA100: 0 | AB100: 0 | AC100: 0 | AD100: 0 | AE100: 0 | AF100: 0 | AG100: 0 | AH100: 0 | AI100: 0 | AJ100: 0 | AK100: 0 | AL100: 0 | AM100: 0
B101: 95 New England | C101: Single Family | D101: Clothes Drying | E101: =IF(D101="",E100,D101) -> Clothes Drying | H101: Sum of TOTPURCHASE | I101: 17317 | J101: 17701 | K101: 18030 | L101: 18402 | M101: 18883 | N101: 20357 | O101: 21220 | P101: 21708 | Q101: 22403 | R101: 23321 | S101: 24715 | T101: 26297 | U101: 25076 | V101: 24161 | W101: 23301 | X101: 22715 | Y101: 22439 | Z101: 22021 | AA101: 21389 | AB101: 20365 | AC101: 19018 | AD101: 20288 | AE101: 21271 | AF101: 22038 | AG101: 22653 | AH101: 23135 | AI101: 23486 | AJ101: 23684 | AK101: 23752 | AL101: 23659 | AM101: 23433
B102: 96 New England | C102: Single Family | D102: Clothes Drying | E102: =IF(D102="",E101,D102) -> Clothes Drying | H102: Sum of TOTINVEST | I102: 7360028 | J102: 7523639 | K102: 7662973 | L102: 7821413 | M102: 8025626 | N102: 9161381 | O102: 9549040 | P102: 9768906 | Q102: 10081969 | R102: 10495164 | S102: 11122431 | T102: 11834330 | U102: 11284617 | V102: 10872822 | W102: 10485933 | X102: 10222375 | Y102: 10097696 | Z102: 9909893 | AA102: 9625764 | AB102: 9164532 | AC102: 8558709 | AD102: 9130178 | AE102: 9572152 | AF102: 9917475 | AG102: 10194366 | AH102: 10410993 | AI102: 10569203 | AJ102: 10658395 | AK102: 10688599 | AL102: 10647184 | AM102: 10545254
...

Sheet RECS HC2.1
A1: Preliminary Release: March 28, 2011
A2: Final Release: April 2013
A3: Table HC2.1 Structural and Geographic Characteristics of U.S. Homes, By Housing Unit Type, 2009
A4: Million Housing Units, Final
C5: Housing Unit Type
C7: Single-Family Units | E7: Apartments in Buildings With
B8: Total U.S.1 (millions)
A9: Structural and Geographic Characteristics | E9: 2 to 4 Units | F9: 5 or More Units | G9: Mobile Homes
C10: Detached | D10: Attached
A12: Total Homes | B12: 113.6 | C12: 71.8 | D12: 6.7 | E12: 9 | F12: 19.1 | G12: 6.9
A14: Census Region and Division
A15: Northeast | B15: 20.8 | C15: 10.9 | D15: 1.8 | E15: 3.1 | F15: 4.4 | G15: 0.5
A16: New England | B16: 5.5 | C16: 3.1 | D16: 0.3 | E16: 1 | F16: 1 | G16: 0.1
A17: Middle Atlantic | B17: 15.3 | C17: 7.8 | D17: 1.5 | E17: 2.1 | F17: 3.4 | G17: 0.4
A18: Midwest | B18: 25.9 | C18: 18 | D18: 1.2 | E18: 1.9 | F18: 3.7 | G18: 1.1
A19: East North Central | B19: 17.9 | C19: 12.3 | D19: 0.8 | E19: 1.5 | F19: 2.7 | G19: 0.6
A20: West North Central | B20: 8.1 | C20: 5.7 | D20: 0.4 | E20: 0.4 | F20: 1 | G20: 0.5
A21: South | B21: 42.1 | C21: 27.6 | D21: 2.1 | E21: 2.2 | F21: 6.2 | G21: 3.9
A22: South Atlantic | B22: 22.2 | C22: 13.8 | D22: 1.3 | E22: 1.1 | F22: 3.5 | G22: 2.4
A23: East South Central | B23: 7.1 | C23: 5.2 | D23: 0.2 | E23: 0.3 | F23: 0.7 | G23: 0.7
A24: West South Central | B24: 12.8 | C24: 8.5 | D24: 0.6 | E24: 0.8 | F24: 2 | G24: 0.9
A25: West | B25: 24.8 | C25: 15.4 | D25: 1.5 | E25: 1.7 | F25: 4.7 | G25: 1.4
A26: Mountain | B26: 7.9 | C26: 5.5 | D26: 0.5 | E26: 0.3 | F26: 0.9 | G26: 0.7
... A29: Pacific | B29: 16.9 | C29: 9.9 | D29: 1 | E29: 1.4 | F29: 3.8 | G29: 0.8
A31: Urban and Rural2
A32: Urban | B32: 88.1 | C32: 51.3 | D32: 6.3 | E32: 8.5 | F32: 18.5 | G32: 3.5
A33: Rural | B33: 25.5 | C33: 20.5 | D33: 0.4 | E33: 0.5 | F33: 0.7 | G33: 3.5
A35: Metropolitan and Micropolitan
A36: Statistical Area
A37: In metropolitan statistical area | B37: 94 | C37: 57.3 | D37: 6.2 | E37: 7.9 | F37: 18.1 | G37: 4.5
A38: In micropolitan statistical area | B38: 12.4 | C38: 9.1 | D38: 0.4 | E38: 0.7 | F38: 0.7 | G38: 1.4
A39: Not in metropolitan or micropolitan
A40: statistical area | B40: 7.2 | C40: 5.4 | D40: 0.1 | E40: 0.3 | F40: 0.2 | G40: 1.1
A42: Climate Region3
A43: Very Cold/Cold | B43: 38.8 | C43: 25.1 | D43: 2.4 | E43: 3.9 | F43: 5.8 | G43: 1.6
A44: Mixed-Humid | B44: 35.4 | C44: 22.1 | D44: 2.3 | E44: 2.4 | F44: 6.2 | G44: 2.4
A45: Mixed-Dry/Hot-Dry | B45: 14.1 | C45: 8.8 | D45: 0.7 | E45: 1 | F45: 2.8 | G45: 0.8
A46: Hot-Humid | B46: 19.1 | C46: 12.2 | D46: 0.9 | E46: 1.2 | F46: 2.8 | G46: 2
A47: Marine | B47: 6.3 | C47: 3.6 | D47: 0.5 | E47: 0.5 | F47: 1.5 | G47: 0.2
A49: Year of Construction
A50: Before 1940 | B50: 14.4 | C50: 9 | D50: 1.1 | E50: 2.3 | F50: 2 | G50: Q
A51: 1940 to 1949 | B51: 5.2 | C51: 3.7 | D51: 0.2 | E51: 0.6 | F51: 0.7 | G51: Q
A52: 1950 to 1959 | B52: 13.5 | C52: 10.3 | D52: 0.6 | E52: 1.2 | F52: 1.3 | G52: 0.1
A53: 1960 to 1969 | B53: 13.3 | C53: 8.7 | D53: 0.5 | E53: 1.2 | F53: 2.6 | G53: 0.4
A54: 1970 to 1979 | B54: 18.3 | C54: 9.8 | D54: 1.1 | E54: 1.5 | F54: 4.1 | G54: 1.8
A55: 1980 to 1989 | B55: 17 | C55: 9.2 | D55: 1.4 | E55: 1.1 | F55: 3.5 | G55: 1.8
A56: 1990 to 1999 | B56: 16.4 | C56: 10.4 | D56: 0.8 | E56: 0.8 | F56: 2.5 | G56: 2
A57: 2000 to 2009 | B57: 15.6 | C57: 10.8 | D57: 1 | E57: 0.4 | F57: 2.4 | G57: 0.9
A59: Number of Stories or
A60: Levels in Housing Unit
A61: 1 Story | B61: 78.7 | C61: 43.4 | D61: 2.8 | E61: 7.8 | F61: 17.8 | G61: 6.9
A62: 2 Stories | B62: 32 | C62: 26.1 | D62: 3.5 | E62: 1.2 | F62: 1.2 | G62: N
A63: 3 or More Stories | B63: 1.7 | C63: 1.2 | D63: 0.4 | E63: Q | F63: Q | G63: N
A64: Split-Level | B64: 1.2 | C64: 1.2 | D64: Q | E64: N | F64: N | G64: N
A66: Number of Floors in Apartment
A67: Buildings With 5 or More Units
A68: 1 or 2 Floors | B68: 8.7 | C68: N | D68: N | E68: N | F68: 8.7 | G68: N
A69: 3 or 4 Floors | B69: 7.2 | C69: N | D69: N | E69: N | F69: 7.2 | G69: N
A70: 5 to 10 Floors | B70: 1.9 | C70: N | D70: N | E70: N | F70: 1.9 | G70: N
A71: 11 to 20 Floors | B71: 0.9 | C71: N | D71: N | E71: N | F71: 0.9 | G71: N
A72: More than 20 Floors | B72: 0.4 | C72: N | D72: N | E72: N | F72: 0.4 | G72: N
A73: Not in Apartment Building
A74: With 5 or More Units | B74: 94.5 | C74: 71.8 | D74: 6.7 | E74: 9 | F74: N | G74: 6.9
A76: Major Outside Wall Construction
A77: Siding (Aluminum, Vinyl, Steel) | B77: 41 | C77: 27.8 | D77: 2.1 | E77: 2.2 | F77: 2.8 | G77: 6.1
A78: Brick | B78: 30.2 | C78: 15.5 | D78: 2.3 | E78: 3.4 | F78: 9 | G78: N
A79: Wood | B79: 19.8 | C79: 14.2 | D79: 1.1 | E79: 1.8 | F79: 2.1 | G79: 0.6
A80: Stucco | B80: 14.5 | C80: 9.2 | D80: 1 | E80: 1.1 | F80: 3.3 | G80: N
A81: Concrete/Concrete Block | B81: 4.5 | C81: 2.6 | D81: 0.2 | E81: 0.2 | F81: 1.4 | G81: Q
A82: Composition (Shingle) | B82: 1.6 | C82: 1.2 | D82: 0.1 | E82: 0.1 | F82: Q | G82: Q
A83: Stone | B83: 1.3 | C83: 0.9 | D83: Q | E83: Q | F83: 0.3 | G83: N
A84: Other | B84: 0.7 | C84: 0.5 | D84: N | E84: Q | F84: Q | G84: Q
A86: Major Roofing Material
A87: Composition Shingles | B87: 54.1 | C87: 43.4 | D87: 3.9 | E87: 4.9 | F87: N | G87: 1.8
A88: Asphalt | B88: 18.6 | C88: 14.6 | D88: 1.4 | E88: 1.9 | F88: N | G88: 0.6
A89: Metal | B89: 8.3 | C89: 4.1 | D89: 0.1 | E89: 0.2 | F89: N | G89: 3.9
A90: Wood Shingles/Shakes | B90: 6.6 | C90: 4.6 | D90: 0.5 | E90: 1.1 | F90: N | G90: 0.4
A91: Ceramic or Clay Tiles | B91: 3.3 | C91: 2.7 | D91: 0.3 | E91: 0.3 | F91: N | G91: Q
A92: Concrete Tiles | B92: 1.3 | C92: 1 | D92: 0.1 | E92: 0.1 | F92: N | G92: Q
A93: Slate or Synthetic Slate | B93: 1.3 | C93: 0.9 | D93: 0.1 | E93: 0.2 | F93: N | G93: Q
A94: Other | B94: 1.2 | C94: 0.5 | D94: 0.2 | E94: 0.3 | F94: N | G94: 0.2
A95: Not Asked (Apartments in Buildings
A96: With 5 or More Units) | B96: 19.1 | C96: N | D96: N | E96: N | F96: 19.1 | G96: N
A98: Foundation/Basement of Single-Family
A99: Units and Apartments in Buildings With
A100: 2 to 4 Units (more than one may apply)
A101: Basement | B101: 34.9 | C101: 29.2 | D101: 3 | E101: 2.7 | F101: N | G101: N
A102: Crawlspace | B102: 26.1 | C102: 24.1 | D102: 1.1 | E102: 0.9 | F102: N | G102: N
A103: Concrete Slab | B103: 40.7 | C103: 33.3 | D103: 3.5 | E103: 3.9 | F103: N | G103: N
A104: Not Asked (Mobile Homes and Apartments
A105: in Buildings With 5 or More Units) | B105: 26.1 | C105: N | D105: N | E105: N | F105: 19.1 | G105: 6.9
A107: Total Number of Rooms
A108: (Excluding Bathrooms)
A109: 1 or 2 | B109: 4.1 | C109: Q | D109: Q | E109: 0.7 | F109: 3.1 | G109: 0.2
A110: 3. | B110: 8.7 | C110: 0.6 | D110: 0.4 | E110: 1.6 | F110: 5.5 | G110: 0.5
A111: 4. | B111: 16.9 | C111: 4.2 | D111: 1.5 | E111: 3.1 | F111: 6.1 | G111: 1.9
A112: 5. | B112: 21.1 | C112: 11.4 | D112: 1.7 | E112: 2.2 | F112: 3.3 | G112: 2.5
A113: 6. | B113: 22 | C113: 17.5 | D113: 1.5 | E113: 1 | F113: 0.8 | G113: 1.1
A114: 7 | B114: 16.4 | C114: 14.5 | D114: 1 | E114: 0.2 | F114: 0.2 | G114: 0.5
A115: 8. | B115: 11.8 | C115: 11 | D115: 0.4 | E115: Q | F115: Q | G115: 0.3
...

Sheet Calculations
A1: Residential
A2: Capital Expenditures in 2013 USD (total cost of components) | B2: 2014 | C2: 2015 | D2: 2016 | E2: 2017 | F2: 2018 | G2: 2019 | H2: 2020 | I2: 2021 | J2: 2022 | K2: 2023 | L2: 2024 | M2: 2025 | N2: 2026 | O2: 2027 | P2: 2028 | Q2: 2029 | R2: 2030 | S2: 2031 | T2: 2032 | U2: 2033 | V2: 2034 | W2: 2035 | X2: 2036 | Y2: 2037 | Z2: 2038 | AA2: 2039 | AB2: 2040 | AC2: 2041 | AD2: 2042 | AE2: 2043 | AF2: 2044 | AG2: 2045 | AH2: 2046 | AI2: 2047 | AJ2: 2048 | AK2: 2049 | AL2: 2050
A3: Heating | B3: =SUMIFS(Residential!M$7:M$7701,Residential!$E$7:$E$7701,"Heating",Residential!$H$7:$H$7701,"Sum of TOTINVEST") -> 9667720853 | C3: =SUMIFS(Residential!N$7:N$7701,Residential!$E$7:$E$7701,"Heating",Residential!$H$7:$H$7701,"Sum of TOTINVEST") -> 10050593045 | D3: =SUMIFS(Residential!O$7:O$7701,Residential!$E$7:$E$7701,"Heating",Residential!$H$7:$H$7701,"Sum of TOTINVEST") -> 10474442706 | E3: =SUMIFS(Residential!P$7:P$7701,Residential!$E$7:$E$7701,"Heating",Residential!$H$7:$H$7701,"Sum of TOTINVEST") -> 11268459465 | F3: =SUMIFS(Residential!Q$7:Q$7701,Residential!$E$7:$E$7701,"Heating",Residential!$H$7:$H$7701,"Sum of TOTINVEST") -> 11523907673 | G3: =SUMIFS(Residential!R$7:R$7701,Residential!$E$7:$E$7701,"Heating",Residential!$H$7:$H$7701,"Sum of TOTINVEST") -> 11767252466 | H3: =SUMIFS(Residential!S$7:S$7701,Residential!$E$7:$E$7701,"Heating",Residential!$H$7:$H$7701,"Sum of TOTINVEST") -> 12079708291 | I3: =SUMIFS(Residential!T$7:T$7701,Residential!$E$7:$E$7701,"Heating",Residential!$H$7:$H$7701,"Sum of TOTINVEST") -> 11938293473 | ... AB3: =SUMIFS(Residential!AM$7:AM$7701,Residential!$E$7:$E$7701,"Heating",Residential!$H$7:$H$7701,"Sum of TOTINVEST") -> 13264868416 | AC3: =TREND($P3:$AB3,$P$2:$AB$2,AC$2) -> 1.3194396e+10 | AD3: =TREND($P3:$AB3,$P$2:$AB$2,AD$2) -> 1.3273872e+10 | AE3: =TREND($P3:$AB3,$P$2:$AB$2,AE$2) -> 1.3353348e+10 | AF3: =TREND($P3:$AB3,$P$2:$AB$2,AF$2) -> 1.3432824e+10 | AG3: =TREND($P3:$AB3,$P$2:$AB$2,AG$2) -> 1.35123e+10 | AH3: =TREND($P3:$AB3,$P$2:$AB$2,AH$2) -> 1.3591775e+10 | AI3: =TREND($P3:$AB3,$P$2:$AB$2,AI$2) -> 1.3671251e+10 | AJ3: =TREND($P3:$AB3,$P$2:$AB$2,AJ$2) -> 1.3750727e+10 | ... AL3: =TREND($P3:$AB3,$P$2:$AB$2,AL$2) -> 1.3909679e+10
A4: Cooling and Ventilation | B4: =SUMIFS(Residential!M$7:M$7701,Residential!$E$7:$E$7701,"Cooling",Residential!$H$7:$H$7701,"Sum of TOTINVEST") -> 10937041372 | C4: =SUMIFS(Residential!N$7:N$7701,Residential!$E$7:$E$7701,"Cooling",Residential!$H$7:$H$7701,"Sum of TOTINVEST") -> 11697373294 | D4: =SUMIFS(Residential!O$7:O$7701,Residential!$E$7:$E$7701,"Cooling",Residential!$H$7:$H$7701,"Sum of TOTINVEST") -> 12495065905 | E4: =SUMIFS(Residential!P$7:P$7701,Residential!$E$7:$E$7701,"Cooling",Residential!$H$7:$H$7701,"Sum of TOTINVEST") -> 13483327925 | F4: =SUMIFS(Residential!Q$7:Q$7701,Residential!$E$7:$E$7701,"Cooling",Residential!$H$7:$H$7701,"Sum of TOTINVEST") -> 13722922776 | G4: =SUMIFS(Residential!R$7:R$7701,Residential!$E$7:$E$7701,"Cooling",Residential!$H$7:$H$7701,"Sum of TOTINVEST") -> 13742684670 | H4: =SUMIFS(Residential!S$7:S$7701,Residential!$E$7:$E$7701,"Cooling",Residential!$H$7:$H$7701,"Sum of TOTINVEST") -> 13741481995 | I4: =SUMIFS(Residential!T$7:T$7701,Residential!$E$7:$E$7701,"Cooling",Residential!$H$7:$H$7701,"Sum of TOTINVEST") -> 13675658941 | ... AB4: =SUMIFS(Residential!AM$7:AM$7701,Residential!$E$7:$E$7701,"Cooling",Residential!$H$7:$H$7701,"Sum of TOTINVEST") -> 15582119604 | AC4: =TREND($P4:$AB4,$P$2:$AB$2,AC$2) -> 1.5632483e+10 | AD4: =TREND($P4:$AB4,$P$2:$AB$2,AD$2) -> 1.5797578e+10 | AE4: =TREND($P4:$AB4,$P$2:$AB$2,AE$2) -> 1.5962672e+10 | AF4: =TREND($P4:$AB4,$P$2:$AB$2,AF$2) -> 1.6127766e+10 | AG4: =TREND($P4:$AB4,$P$2:$AB$2,AG$2) -> 1.6292861e+10 | AH4: =TREND($P4:$AB4,$P$2:$AB$2,AH$2) -> 1.6457955e+10 | AI4: =TREND($P4:$AB4,$P$2:$AB$2,AI$2) -> 1.662305e+10 | AJ4: =TREND($P4:$AB4,$P$2:$AB$2,AJ$2) -> 1.6788144e+10 | ... AL4: =TREND($P4:$AB4,$P$2:$AB$2,AL$2) -> 1.7118333e+10
A5: Envelope | B5: 0 | C5: 0 | D5: 0 | E5: 0 | F5: 0 | G5: 0 | H5: 0 | I5: 0 | J5: 0 | K5: 0 | L5: 0 | M5: 0 | N5: 0 | O5: 0 | P5: 0 | Q5: 0 | R5: 0 | S5: 0 | T5: 0 | U5: 0 | V5: 0 | W5: 0 | X5: 0 | Y5: 0 | Z5: 0 | AA5: 0 | AB5: 0 | AC5: =TREND($P5:$AB5,$P$2:$AB$2,AC$2) -> 0 | AD5: =TREND($P5:$AB5,$P$2:$AB$2,AD$2) -> 0 | AE5: =TREND($P5:$AB5,$P$2:$AB$2,AE$2) -> 0 | AF5: =TREND($P5:$AB5,$P$2:$AB$2,AF$2) -> 0 | AG5: =TREND($P5:$AB5,$P$2:$AB$2,AG$2) -> 0 | AH5: =TREND($P5:$AB5,$P$2:$AB$2,AH$2) -> 0 | AI5: =TREND($P5:$AB5,$P$2:$AB$2,AI$2) -> 0 | AJ5: =TREND($P5:$AB5,$P$2:$AB$2,AJ$2) -> 0 | ... AL5: =TREND($P5:$AB5,$P$2:$AB$2,AL$2) -> 0
A6: Lighting | B6: =SUMIFS(Residential!M$7:M$7701,Residential!$E$7:$E$7701,"Lighting",Residential!$H$7:$H$7701,"Sum of TOTINVEST") -> 5670571439 | C6: =SUMIFS(Residential!N$7:N$7701,Residential!$E$7:$E$7701,"Lighting",Residential!$H$7:$H$7701,"Sum of TOTINVEST") -> 5261095781 | D6: =SUMIFS(Residential!O$7:O$7701,Residential!$E$7:$E$7701,"Lighting",Residential!$H$7:$H$7701,"Sum of TOTINVEST") -> 5289787910 | E6: =SUMIFS(Residential!P$7:P$7701,Residential!$E$7:$E$7701,"Lighting",Residential!$H$7:$H$7701,"Sum of TOTINVEST") -> 5402620127 | F6: =SUMIFS(Residential!Q$7:Q$7701,Residential!$E$7:$E$7701,"Lighting",Residential!$H$7:$H$7701,"Sum of TOTINVEST") -> 5523361877 | G6: =SUMIFS(Residential!R$7:R$7701,Residential!$E$7:$E$7701,"Lighting",Residential!$H$7:$H$7701,"Sum of TOTINVEST") -> 5609671925 | H6: =SUMIFS(Residential!S$7:S$7701,Residential!$E$7:$E$7701,"Lighting",Residential!$H$7:$H$7701,"Sum of TOTINVEST") -> 8480695965 | I6: =SUMIFS(Residential!T$7:T$7701,Residential!$E$7:$E$7701,"Lighting",Residential!$H$7:$H$7701,"Sum of TOTINVEST") -> 6999952890 | ... AB6: =SUMIFS(Residential!AM$7:AM$7701,Residential!$E$7:$E$7701,"Lighting",Residential!$H$7:$H$7701,"Sum of TOTINVEST") -> 2716481490 | AC6: =TREND($P6:$AB6,$P$2:$AB$2,AC$2) -> 2.3861552e+09 | AD6: =TREND($P6:$AB6,$P$2:$AB$2,AD$2) -> 2.201026e+09 | AE6: =TREND($P6:$AB6,$P$2:$AB$2,AE$2) -> 2.0158967e+09 | AF6: =TREND($P6:$AB6,$P$2:$AB$2,AF$2) -> 1.8307675e+09 | AG6: =TREND($P6:$AB6,$P$2:$AB$2,AG$2) -> 1.6456382e+09 | AH6: =TREND($P6:$AB6,$P$2:$AB$2,AH$2) -> 1.460509e+09 | AI6: =TREND($P6:$AB6,$P$2:$AB$2,AI$2) -> 1.2753797e+09 | AJ6: =TREND($P6:$AB6,$P$2:$AB$2,AJ$2) -> 1.0902505e+09 | ... AL6: =TREND($P6:$AB6,$P$2:$AB$2,AL$2) -> 7.1999197e+08
A7: Appliances | B7: =SUM(SUMIFS(Residential!M$7:M$7701,Residential!$E$7:$E$7701,"Refrigeration",Residential!$H$7:$H$7701,"Sum of TOTINVEST"),SUMIFS(Residential!M$7:M$7701,Residential!$E$7:$E$7701,"Clothes Washing",Residential!$H$7:$H$7701,"Sum of TOTINVEST"),SUMIFS(Residential!M$7:M$7701,Residential!$E$7:$E$7701,"Clothes Drying",Residential!$H$7:$H$7701,"Sum of TOTINVEST"),SUMIFS(Residential!M$7:M$7701,Residential!$E$7:$E$7701,"Dish Washing",Residential!$H$7:$H$7701,"Sum of TOTINVEST"),SUMIFS(Residential!M$7:M$7701,Residential!$E$7:$E$7701,"Freezing",Residential!$H$7:$H$7701,"Sum of TOTINVEST"),SUMIFS(Residential!M$7:M$7701,Residential!$E$7:$E$7701,"Water Heating",Residential!$H$7:$H$7701,"Sum of TOTINVEST")) -> 23388251953 | C7: =SUM(SUMIFS(Residential!N$7:N$7701,Residential!$E$7:$E$7701,"Refrigeration",Residential!$H$7:$H$7701,"Sum of TOTINVEST"),SUMIFS(Residential!N$7:N$7701,Residential!$E$7:$E$7701,"Clothes Washing",Residential!$H$7:$H$7701,"Sum of TOTINVEST"),SUMIFS(Residential!N$7:N$7701,Residential!$E$7:$E$7701,"Clothes Drying",Residential!$H$7:$H$7701,"Sum of TOTINVEST"),SUMIFS(Residential!N$7:N$7701,Residential!$E$7:$E$7701,"Dish Washing",Residential!$H$7:$H$7701,"Sum of TOTINVEST"),SUMIFS(Residential!N$7:N$7701,Residential!$E$7:$E$7701,"Freezing",Residential!$H$7:$H$7701,"Sum of TOTINVEST"),SUMIFS(Residential!N$7:N$7701,Residential!$E$7:$E$7701,"Water Heating",Residential!$H$7:$H$7701,"Sum of TOTINVEST")) -> 25866249860 | D7: =SUM(SUMIFS(Residential!O$7:O$7701,Residential!$E$7:$E$7701,"Refrigeration",Residential!$H$7:$H$7701,"Sum of TOTINVEST"),SUMIFS(Residential!O$7:O$7701,Residential!$E$7:$E$7701,"Clothes Washing",Residential!$H$7:$H$7701,"Sum of TOTINVEST"),SUMIFS(Residential!O$7:O$7701,Residential!$E$7:$E$7701,"Clothes Drying",Residential!$H$7:$H$7701,"Sum of TOTINVEST"),SUMIFS(Residential!O$7:O$7701,Residential!$E$7:$E$7701,"Dish Washing",Residential!$H$7:$H$7701,"Sum of TOTINVEST"),SUMIFS(Residential!O$7:O$7701,Residential!$E$7:$E$7701,"Freezing",Residential!$H$7:$H$7701,"Sum of TOTINVEST"),SUMIFS(Residential!O$7:O$7701,Residential!$E$7:$E$7701,"Water Heating",Residential!$H$7:$H$7701,"Sum of TOTINVEST")) -> 26850048637 | E7: =SUM(SUMIFS(Residential!P$7:P$7701,Residential!$E$7:$E$7701,"Refrigeration",Residential!$H$7:$H$7701,"Sum of TOTINVEST"),SUMIFS(Residential!P$7:P$7701,Residential!$E$7:$E$7701,"Clothes Washing",Residential!$H$7:$H$7701,"Sum of TOTINVEST"),SUMIFS(Residential!P$7:P$7701,Residential!$E$7:$E$7701,"Clothes Drying",Residential!$H$7:$H$7701,"Sum of TOTINVEST"),SUMIFS(Residential!P$7:P$7701,Residential!$E$7:$E$7701,"Dish Washing",Residential!$H$7:$H$7701,"Sum of TOTINVEST"),SUMIFS(Residential!P$7:P$7701,Residential!$E$7:$E$7701,"Freezing",Residential!$H$7:$H$7701,"Sum of TOTINVEST"),SUMIFS(Residential!P$7:P$7701,Residential!$E$7:$E$7701,"Water Heating",Residential!$H$7:$H$7701,"Sum of TOTINVEST")) -> 27404889208 | F7: =SUM(SUMIFS(Residential!Q$7:Q$7701,Residential!$E$7:$E$7701,"Refrigeration",Residential!$H$7:$H$7701,"Sum of TOTINVEST"),SUMIFS(Residential!Q$7:Q$7701,Residential!$E$7:$E$7701,"Clothes Washing",Residential!$H$7:$H$7701,"Sum of TOTINVEST"),SUMIFS(Residential!Q$7:Q$7701,Residential!$E$7:$E$7701,"Clothes Drying",Residential!$H$7:$H$7701,"Sum of TOTINVEST"),SUMIFS(Residential!Q$7:Q$7701,Residential!$E$7:$E$7701,"Dish Washing",Residential!$H$7:$H$7701,"Sum of TOTINVEST"),SUMIFS(Residential!Q$7:Q$7701,Residential!$E$7:$E$7701,"Freezing",Residential!$H$7:$H$7701,"Sum of TOTINVEST"),SUMIFS(Residential!Q$7:Q$7701,Residential!$E$7:$E$7701,"Water Heating",Residential!$H$7:$H$7701,"Sum of TOTINVEST")) -> 28206878048 | G7: =SUM(SUMIFS(Residential!R$7:R$7701,Residential!$E$7:$E$7701,"Refrigeration",Residential!$H$7:$H$7701,"Sum of TOTINVEST"),SUMIFS(Residential!R$7:R$7701,Residential!$E$7:$E$7701,"Clothes Washing",Residential!$H$7:$H$7701,"Sum of TOTINVEST"),SUMIFS(Residential!R$7:R$7701,Residential!$E$7:$E$7701,"Clothes Drying",Residential!$H$7:$H$7701,"Sum of TOTINVEST"),SUMIFS(Residential!R$7:R$7701,Residential!$E$7:$E$7701,"Dish Washing",Residential!$H$7:$H$7701,"Sum of TOTINVEST"),SUMIFS(Residential!R$7:R$7701,Residential!$E$7:$E$7701,"Freezing",Residential!$H$7:$H$7701,"Sum of TOTINVEST"),SUMIFS(Residential!R$7:R$7701,Residential!$E$7:$E$7701,"Water Heating",Residential!$H$7:$H$7701,"Sum of TOTINVEST")) -> 28734740282 | H7: =SUM(SUMIFS(Residential!S$7:S$7701,Residential!$E$7:$E$7701,"Refrigeration",Residential!$H$7:$H$7701,"Sum of TOTINVEST"),SUMIFS(Residential!S$7:S$7701,Residential!$E$7:$E$7701,"Clothes Washing",Residential!$H$7:$H$7701,"Sum of TOTINVEST"),SUMIFS(Residential!S$7:S$7701,Residential!$E$7:$E$7701,"Clothes Drying",Residential!$H$7:$H$7701,"Sum of TOTINVEST"),SUMIFS(Residential!S$7:S$7701,Residential!$E$7:$E$7701,"Dish Washing",Residential!$H$7:$H$7701,"Sum of TOTINVEST"),SUMIFS(Residential!S$7:S$7701,Residential!$E$7:$E$7701,"Freezing",Residential!$H$7:$H$7701,"Sum of TOTINVEST"),SUMIFS(Residential!S$7:S$7701,Residential!$E$7:$E$7701,"Water Heating",Residential!$H$7:$H$7701,"Sum of TOTINVEST")) -> 29972648917 | I7: =SUM(SUMIFS(Residential!T$7:T$7701,Residential!$E$7:$E$7701,"Refrigeration",Residential!$H$7:$H$7701,"Sum of TOTINVEST"),SUMIFS(Residential!T$7:T$7701,Residential!$E$7:$E$7701,"Clothes Washing",Residential!$H$7:$H$7701,"Sum of TOTINVEST"),SUMIFS(Residential!T$7:T$7701,Residential!$E$7:$E$7701,"Clothes Drying",Residential!$H$7:$H$7701,"Sum of TOTINVEST"),SUMIFS(Residential!T$7:T$7701,Residential!$E$7:$E$7701,"Dish Washing",Residential!$H$7:$H$7701,"Sum of TOTINVEST"),SUMIFS(Residential!T$7:T$7701,Residential!$E$7:$E$7701,"Freezing",Residential!$H$7:$H$7701,"Sum of TOTINVEST"),SUMIFS(Residential!T$7:T$7701,Residential!$E$7:$E$7701,"Water Heating",Residential!$H$7:$H$7701,"Sum of TOTINVEST")) -> 30654580643 | ... AB7: =SUM(SUMIFS(Residential!AM$7:AM$7701,Residential!$E$7:$E$7701,"Refrigeration",Residential!$H$7:$H$7701,"Sum of TOTINVEST"),SUMIFS(Residential!AM$7:AM$7701,Residential!$E$7:$E$7701,"Clothes Washing",Residential!$H$7:$H$7701,"Sum of TOTINVEST"),SUMIFS(Residential!AM$7:AM$7701,Residential!$E$7:$E$7701,"Clothes Drying",Residential!$H$7:$H$7701,"Sum of TOTINVEST"),SUMIFS(Residential!AM$7:AM$7701,Residential!$E$7:$E$7701,"Dish Washing",Residential!$H$7:$H$7701,"Sum of TOTINVEST"),SUMIFS(Residential!AM$7:AM$7701,Residential!$E$7:$E$7701,"Freezing",Residential!$H$7:$H$7701,"Sum of TOTINVEST"),SUMIFS(Residential!AM$7:AM$7701,Residential!$E$7:$E$7701,"Water Heating",Residential!$H$7:$H$7701,"Sum of TOTINVEST")) -> 32796459922 | AC7: =TREND($P7:$AB7,$P$2:$AB$2,AC$2) -> 3.3315982e+10 | AD7: =TREND($P7:$AB7,$P$2:$AB$2,AD$2) -> 3.3616314e+10 | AE7: =TREND($P7:$AB7,$P$2:$AB$2,AE$2) -> 3.3916646e+10 | AF7: =TREND($P7:$AB7,$P$2:$AB$2,AF$2) -> 3.4216978e+10 | AG7: =TREND($P7:$AB7,$P$2:$AB$2,AG$2) -> 3.451731e+10 | AH7: =TREND($P7:$AB7,$P$2:$AB$2,AH$2) -> 3.4817643e+10 | AI7: =TREND($P7:$AB7,$P$2:$AB$2,AI$2) -> 3.5117975e+10 | AJ7: =TREND($P7:$AB7,$P$2:$AB$2,AJ$2) -> 3.5418307e+10 | ... AL7: =TREND($P7:$AB7,$P$2:$AB$2,AL$2) -> 3.6018971e+10
A8: Other | B8: 0 | C8: 0 | D8: 0 | E8: 0 | F8: 0 | G8: 0 | H8: 0 | I8: 0 | J8: 0 | K8: 0 | L8: 0 | M8: 0 | N8: 0 | O8: 0 | P8: 0 | Q8: 0 | R8: 0 | S8: 0 | T8: 0 | U8: 0 | V8: 0 | W8: 0 | X8: 0 | Y8: 0 | Z8: 0 | AA8: 0 | AB8: 0 | AC8: =TREND($P8:$AB8,$P$2:$AB$2,AC$2) -> 0 | AD8: =TREND($P8:$AB8,$P$2:$AB$2,AD$2) -> 0 | AE8: =TREND($P8:$AB8,$P$2:$AB$2,AE$2) -> 0 | AF8: =TREND($P8:$AB8,$P$2:$AB$2,AF$2) -> 0 | AG8: =TREND($P8:$AB8,$P$2:$AB$2,AG$2) -> 0 | AH8: =TREND($P8:$AB8,$P$2:$AB$2,AH$2) -> 0 | AI8: =TREND($P8:$AB8,$P$2:$AB$2,AI$2) -> 0 | AJ8: =TREND($P8:$AB8,$P$2:$AB$2,AJ$2) -> 0 | ... AL8: =TREND($P8:$AB8,$P$2:$AB$2,AL$2) -> 0
A10: Urban Residential
A11: Capital Expenditures in 2013 USD (total cost of components) | B11: 2014 | C11: 2015 | D11: 2016 | E11: 2017 | F11: 2018 | G11: 2019 | H11: 2020 | I11: 2021 | J11: 2022 | K11: 2023 | L11: 2024 | M11: 2025 | N11: 2026 | O11: 2027 | P11: 2028 | Q11: 2029 | R11: 2030 | S11: 2031 | T11: 2032 | U11: 2033 | V11: 2034 | W11: 2035 | X11: 2036 | Y11: 2037 | Z11: 2038 | AA11: 2039 | AB11: 2040 | AC11: 2041 | AD11: 2042 | AE11: 2043 | AF11: 2044 | AG11: 2045 | AH11: 2046 | AI11: 2047 | AJ11: 2048 | AK11: 2049 | AL11: 2050
A12: Heating | B12: =B3*('RECS HC2.1'!$B$32/SUM('RECS HC2.1'!$B$32:$B$33)) -> 7.4975899e+09 | C12: =C3*('RECS HC2.1'!$B$32/SUM('RECS HC2.1'!$B$32:$B$33)) -> 7.794518e+09 | D12: =D3*('RECS HC2.1'!$B$32/SUM('RECS HC2.1'!$B$32:$B$33)) -> 8.1232254e+09 | E12: =E3*('RECS HC2.1'!$B$32/SUM('RECS HC2.1'!$B$32:$B$33)) -> 8.7390077e+09 | F12: =F3*('RECS HC2.1'!$B$32/SUM('RECS HC2.1'!$B$32:$B$33)) -> 8.937115e+09 | G12: =G3*('RECS HC2.1'!$B$32/SUM('RECS HC2.1'!$B$32:$B$33)) -> 9.1258358e+09 | H12: =H3*('RECS HC2.1'!$B$32/SUM('RECS HC2.1'!$B$32:$B$33)) -> 9.3681541e+09 | I12: =I3*('RECS HC2.1'!$B$32/SUM('RECS HC2.1'!$B$32:$B$33)) -> 9.2584829e+09 | ... AL12: =AL3*('RECS HC2.1'!$B$32/SUM('RECS HC2.1'!$B$32:$B$33)) -> 1.0787348e+10
A13: Cooling and Ventilation | B13: =B4*('RECS HC2.1'!$B$32/SUM('RECS HC2.1'!$B$32:$B$33)) -> 8.4819837e+09 | C13: =C4*('RECS HC2.1'!$B$32/SUM('RECS HC2.1'!$B$32:$B$33)) -> 9.0716425e+09 | D13: =D4*('RECS HC2.1'!$B$32/SUM('RECS HC2.1'!$B$32:$B$33)) -> 9.6902756e+09 | E13: =E4*('RECS HC2.1'!$B$32/SUM('RECS HC2.1'!$B$32:$B$33)) -> 1.0456701e+10 | F13: =F4*('RECS HC2.1'!$B$32/SUM('RECS HC2.1'!$B$32:$B$33)) -> 1.0642513e+10 | G13: =G4*('RECS HC2.1'!$B$32/SUM('RECS HC2.1'!$B$32:$B$33)) -> 1.0657839e+10 | H13: =H4*('RECS HC2.1'!$B$32/SUM('RECS HC2.1'!$B$32:$B$33)) -> 1.0656906e+10 | I13: =I4*('RECS HC2.1'!$B$32/SUM('RECS HC2.1'!$B$32:$B$33)) -> 1.0605859e+10 | ... AL13: =AL4*('RECS HC2.1'!$B$32/SUM('RECS HC2.1'!$B$32:$B$33)) -> 1.327575e+10
A14: Envelope | B14: =B5*('RECS HC2.1'!$B$32/SUM('RECS HC2.1'!$B$32:$B$33)) -> 0 | C14: =C5*('RECS HC2.1'!$B$32/SUM('RECS HC2.1'!$B$32:$B$33)) -> 0 | D14: =D5*('RECS HC2.1'!$B$32/SUM('RECS HC2.1'!$B$32:$B$33)) -> 0 | E14: =E5*('RECS HC2.1'!$B$32/SUM('RECS HC2.1'!$B$32:$B$33)) -> 0 | F14: =F5*('RECS HC2.1'!$B$32/SUM('RECS HC2.1'!$B$32:$B$33)) -> 0 | G14: =G5*('RECS HC2.1'!$B$32/SUM('RECS HC2.1'!$B$32:$B$33)) -> 0 | H14: =H5*('RECS HC2.1'!$B$32/SUM('RECS HC2.1'!$B$32:$B$33)) -> 0 | I14: =I5*('RECS HC2.1'!$B$32/SUM('RECS HC2.1'!$B$32:$B$33)) -> 0 | ... AL14: =AL5*('RECS HC2.1'!$B$32/SUM('RECS HC2.1'!$B$32:$B$33)) -> 0
A15: Lighting | B15: =B6*('RECS HC2.1'!$B$32/SUM('RECS HC2.1'!$B$32:$B$33)) -> 4.3976879e+09 | C15: =C6*('RECS HC2.1'!$B$32/SUM('RECS HC2.1'!$B$32:$B$33)) -> 4.080128e+09 | D15: =D6*('RECS HC2.1'!$B$32/SUM('RECS HC2.1'!$B$32:$B$33)) -> 4.1023795e+09 | E15: =E6*('RECS HC2.1'!$B$32/SUM('RECS HC2.1'!$B$32:$B$33)) -> 4.1898841e+09 | F15: =F6*('RECS HC2.1'!$B$32/SUM('RECS HC2.1'!$B$32:$B$33)) -> 4.2835227e+09 | G15: =G6*('RECS HC2.1'!$B$32/SUM('RECS HC2.1'!$B$32:$B$33)) -> 4.3504586e+09 | H15: =H6*('RECS HC2.1'!$B$32/SUM('RECS HC2.1'!$B$32:$B$33)) -> 6.5770186e+09 | I15: =I6*('RECS HC2.1'!$B$32/SUM('RECS HC2.1'!$B$32:$B$33)) -> 5.4286606e+09 | ... AL15: =AL6*('RECS HC2.1'!$B$32/SUM('RECS HC2.1'!$B$32:$B$33)) -> 5.5837406e+08
A16: Appliances | B16: =B7*('RECS HC2.1'!$B$32/SUM('RECS HC2.1'!$B$32:$B$33)) -> 1.8138248e+10 | C16: =C7*('RECS HC2.1'!$B$32/SUM('RECS HC2.1'!$B$32:$B$33)) -> 2.0060005e+10 | D16: =D7*('RECS HC2.1'!$B$32/SUM('RECS HC2.1'!$B$32:$B$33)) -> 2.0822969e+10 | E16: =E7*('RECS HC2.1'!$B$32/SUM('RECS HC2.1'!$B$32:$B$33)) -> 2.1253264e+10 | F16: =F7*('RECS HC2.1'!$B$32/SUM('RECS HC2.1'!$B$32:$B$33)) -> 2.1875228e+10 | G16: =G7*('RECS HC2.1'!$B$32/SUM('RECS HC2.1'!$B$32:$B$33)) -> 2.2284601e+10 | H16: =H7*('RECS HC2.1'!$B$32/SUM('RECS HC2.1'!$B$32:$B$33)) -> 2.3244634e+10 | I16: =I7*('RECS HC2.1'!$B$32/SUM('RECS HC2.1'!$B$32:$B$33)) -> 2.3773491e+10 | ... AL16: =AL7*('RECS HC2.1'!$B$32/SUM('RECS HC2.1'!$B$32:$B$33)) -> 2.7933727e+10
A17: Other | B17: =B8*('RECS HC2.1'!$B$32/SUM('RECS HC2.1'!$B$32:$B$33)) -> 0 | C17: =C8*('RECS HC2.1'!$B$32/SUM('RECS HC2.1'!$B$32:$B$33)) -> 0 | D17: =D8*('RECS HC2.1'!$B$32/SUM('RECS HC2.1'!$B$32:$B$33)) -> 0 | E17: =E8*('RECS HC2.1'!$B$32/SUM('RECS HC2.1'!$B$32:$B$33)) -> 0 | F17: =F8*('RECS HC2.1'!$B$32/SUM('RECS HC2.1'!$B$32:$B$33)) -> 0 | G17: =G8*('RECS HC2.1'!$B$32/SUM('RECS HC2.1'!$B$32:$B$33)) -> 0 | H17: =H8*('RECS HC2.1'!$B$32/SUM('RECS HC2.1'!$B$32:$B$33)) -> 0 | I17: =I8*('RECS HC2.1'!$B$32/SUM('RECS HC2.1'!$B$32:$B$33)) -> 0 | ... AL17: =AL8*('RECS HC2.1'!$B$32/SUM('RECS HC2.1'!$B$32:$B$33)) -> 0
A19: Rural Residential
A20: Capital Expenditures in 2013 USD (total cost of components) | B20: 2014 | C20: 2015 | D20: 2016 | E20: 2017 | F20: 2018 | G20: 2019 | H20: 2020 | I20: 2021 | J20: 2022 | K20: 2023 | L20: 2024 | M20: 2025 | N20: 2026 | O20: 2027 | P20: 2028 | Q20: 2029 | R20: 2030 | S20: 2031 | T20: 2032 | U20: 2033 | V20: 2034 | W20: 2035 | X20: 2036 | Y20: 2037 | Z20: 2038 | AA20: 2039 | AB20: 2040 | AC20: 2041 | AD20: 2042 | AE20: 2043 | AF20: 2044 | AG20: 2045 | AH20: 2046 | AI20: 2047 | AJ20: 2048 | AK20: 2049 | AL20: 2050
A21: Heating | B21: =B3*('RECS HC2.1'!$B$33/SUM('RECS HC2.1'!$B$32:$B$33)) -> 2.170131e+09 | C21: =C3*('RECS HC2.1'!$B$33/SUM('RECS HC2.1'!$B$32:$B$33)) -> 2.256075e+09 | D21: =D3*('RECS HC2.1'!$B$33/SUM('RECS HC2.1'!$B$32:$B$33)) -> 2.3512173e+09 | E21: =E3*('RECS HC2.1'!$B$33/SUM('RECS HC2.1'!$B$32:$B$33)) -> 2.5294517e+09 | F21: =F3*('RECS HC2.1'!$B$33/SUM('RECS HC2.1'!$B$32:$B$33)) -> 2.5867927e+09 | G21: =G3*('RECS HC2.1'!$B$33/SUM('RECS HC2.1'!$B$32:$B$33)) -> 2.6414167e+09 | H21: =H3*('RECS HC2.1'!$B$33/SUM('RECS HC2.1'!$B$32:$B$33)) -> 2.7115542e+09 | I21: =I3*('RECS HC2.1'!$B$33/SUM('RECS HC2.1'!$B$32:$B$33)) -> 2.6798106e+09 | ... AL21: =AL3*('RECS HC2.1'!$B$33/SUM('RECS HC2.1'!$B$32:$B$33)) -> 3.1223311e+09
A22: Cooling and Ventilation | B22: =B4*('RECS HC2.1'!$B$33/SUM('RECS HC2.1'!$B$32:$B$33)) -> 2.4550577e+09 | C22: =C4*('RECS HC2.1'!$B$33/SUM('RECS HC2.1'!$B$32:$B$33)) -> 2.6257308e+09 | D22: =D4*('RECS HC2.1'!$B$33/SUM('RECS HC2.1'!$B$32:$B$33)) -> 2.8047903e+09 | E22: =E4*('RECS HC2.1'!$B$33/SUM('RECS HC2.1'!$B$32:$B$33)) -> 3.0266273e+09 | F22: =F4*('RECS HC2.1'!$B$33/SUM('RECS HC2.1'!$B$32:$B$33)) -> 3.0804096e+09 | G22: =G4*('RECS HC2.1'!$B$33/SUM('RECS HC2.1'!$B$32:$B$33)) -> 3.0848456e+09 | H22: =H4*('RECS HC2.1'!$B$33/SUM('RECS HC2.1'!$B$32:$B$33)) -> 3.0845756e+09 | I22: =I4*('RECS HC2.1'!$B$33/SUM('RECS HC2.1'!$B$32:$B$33)) -> 3.0698002e+09 | ... AL22: =AL4*('RECS HC2.1'!$B$33/SUM('RECS HC2.1'!$B$32:$B$33)) -> 3.8425836e+09
A23: Envelope | B23: =B5*('RECS HC2.1'!$B$33/SUM('RECS HC2.1'!$B$32:$B$33)) -> 0 | C23: =C5*('RECS HC2.1'!$B$33/SUM('RECS HC2.1'!$B$32:$B$33)) -> 0 | D23: =D5*('RECS HC2.1'!$B$33/SUM('RECS HC2.1'!$B$32:$B$33)) -> 0 | E23: =E5*('RECS HC2.1'!$B$33/SUM('RECS HC2.1'!$B$32:$B$33)) -> 0 | F23: =F5*('RECS HC2.1'!$B$33/SUM('RECS HC2.1'!$B$32:$B$33)) -> 0 | G23: =G5*('RECS HC2.1'!$B$33/SUM('RECS HC2.1'!$B$32:$B$33)) -> 0 | H23: =H5*('RECS HC2.1'!$B$33/SUM('RECS HC2.1'!$B$32:$B$33)) -> 0 | I23: =I5*('RECS HC2.1'!$B$33/SUM('RECS HC2.1'!$B$32:$B$33)) -> 0 | ... AL23: =AL5*('RECS HC2.1'!$B$33/SUM('RECS HC2.1'!$B$32:$B$33)) -> 0
A24: Lighting | B24: =B6*('RECS HC2.1'!$B$33/SUM('RECS HC2.1'!$B$32:$B$33)) -> 1.2728836e+09 | C24: =C6*('RECS HC2.1'!$B$33/SUM('RECS HC2.1'!$B$32:$B$33)) -> 1.1809678e+09 | D24: =D6*('RECS HC2.1'!$B$33/SUM('RECS HC2.1'!$B$32:$B$33)) -> 1.1874084e+09 | E24: =E6*('RECS HC2.1'!$B$33/SUM('RECS HC2.1'!$B$32:$B$33)) -> 1.212736e+09 | F24: =F6*('RECS HC2.1'!$B$33/SUM('RECS HC2.1'!$B$32:$B$33)) -> 1.2398392e+09 | G24: =G6*('RECS HC2.1'!$B$33/SUM('RECS HC2.1'!$B$32:$B$33)) -> 1.2592133e+09 | H24: =H6*('RECS HC2.1'!$B$33/SUM('RECS HC2.1'!$B$32:$B$33)) -> 1.9036774e+09 | I24: =I6*('RECS HC2.1'!$B$33/SUM('RECS HC2.1'!$B$32:$B$33)) -> 1.5712922e+09 | ... AL24: =AL6*('RECS HC2.1'!$B$33/SUM('RECS HC2.1'!$B$32:$B$33)) -> 1.6161792e+08
A25: Appliances | B25: =B7*('RECS HC2.1'!$B$33/SUM('RECS HC2.1'!$B$32:$B$33)) -> 5.2500037e+09 | C25: =C7*('RECS HC2.1'!$B$33/SUM('RECS HC2.1'!$B$32:$B$33)) -> 5.8062445e+09 | D25: =D7*('RECS HC2.1'!$B$33/SUM('RECS HC2.1'!$B$32:$B$33)) -> 6.0270796e+09 | E25: =E7*('RECS HC2.1'!$B$33/SUM('RECS HC2.1'!$B$32:$B$33)) -> 6.1516257e+09 | F25: =F7*('RECS HC2.1'!$B$33/SUM('RECS HC2.1'!$B$32:$B$33)) -> 6.3316496e+09 | G25: =G7*('RECS HC2.1'!$B$33/SUM('RECS HC2.1'!$B$32:$B$33)) -> 6.4501398e+09 | H25: =H7*('RECS HC2.1'!$B$33/SUM('RECS HC2.1'!$B$32:$B$33)) -> 6.7280154e+09 | I25: =I7*('RECS HC2.1'!$B$33/SUM('RECS HC2.1'!$B$32:$B$33)) -> 6.8810898e+09 | ... AL25: =AL7*('RECS HC2.1'!$B$33/SUM('RECS HC2.1'!$B$32:$B$33)) -> 8.0852443e+09
A26: Other | B26: =B8*('RECS HC2.1'!$B$33/SUM('RECS HC2.1'!$B$32:$B$33)) -> 0 | C26: =C8*('RECS HC2.1'!$B$33/SUM('RECS HC2.1'!$B$32:$B$33)) -> 0 | D26: =D8*('RECS HC2.1'!$B$33/SUM('RECS HC2.1'!$B$32:$B$33)) -> 0 | E26: =E8*('RECS HC2.1'!$B$33/SUM('RECS HC2.1'!$B$32:$B$33)) -> 0 | F26: =F8*('RECS HC2.1'!$B$33/SUM('RECS HC2.1'!$B$32:$B$33)) -> 0 | G26: =G8*('RECS HC2.1'!$B$33/SUM('RECS HC2.1'!$B$32:$B$33)) -> 0 | H26: =H8*('RECS HC2.1'!$B$33/SUM('RECS HC2.1'!$B$32:$B$33)) -> 0 | I26: =I8*('RECS HC2.1'!$B$33/SUM('RECS HC2.1'!$B$32:$B$33)) -> 0 | ... AL26: =AL8*('RECS HC2.1'!$B$33/SUM('RECS HC2.1'!$B$32:$B$33)) -> 0
A28: Commercial
A29: Capital Expenditures in 2013 USD (total cost of components) | B29: 2014 | C29: 2015 | D29: 2016 | E29: 2017 | F29: 2018 | G29: 2019 | H29: 2020 | I29: 2021 | J29: 2022 | K29: 2023 | L29: 2024 | M29: 2025 | N29: 2026 | O29: 2027 | P29: 2028 | Q29: 2029 | R29: 2030 | S29: 2031 | T29: 2032 | U29: 2033 | V29: 2034 | W29: 2035 | X29: 2036 | Y29: 2037 | Z29: 2038 | AA29: 2039 | AB29: 2040 | AC29: 2041 | AD29: 2042 | AE29: 2043 | AF29: 2044 | AG29: 2045 | AH29: 2046 | AI29: 2047 | AJ29: 2048 | AK29: 2049 | AL29: 2050
A30: Heating | B30: =SUM(Commercial!O11,Commercial!O33,Commercial!O55,Commercial!O77,Commercial!O99,Commercial!O121,Commercial!O143,Commercial!O165,Commercial!O187)*10^9 -> 7620000000 | C30: =SUM(Commercial!P11,Commercial!P33,Commercial!P55,Commercial!P77,Commercial!P99,Commercial!P121,Commercial!P143,Commercial!P165,Commercial!P187)*10^9 -> 7705000000 | D30: =SUM(Commercial!Q11,Commercial!Q33,Commercial!Q55,Commercial!Q77,Commercial!Q99,Commercial!Q121,Commercial!Q143,Commercial!Q165,Commercial!Q187)*10^9 -> 7757000000 | E30: =SUM(Commercial!R11,Commercial!R33,Commercial!R55,Commercial!R77,Commercial!R99,Commercial!R121,Commercial!R143,Commercial!R165,Commercial!R187)*10^9 -> 7841000000 | F30: =SUM(Commercial!S11,Commercial!S33,Commercial!S55,Commercial!S77,Commercial!S99,Commercial!S121,Commercial!S143,Commercial!S165,Commercial!S187)*10^9 -> 7886000000 | G30: =SUM(Commercial!T11,Commercial!T33,Commercial!T55,Commercial!T77,Commercial!T99,Commercial!T121,Commercial!T143,Commercial!T165,Commercial!T187)*10^9 -> 7924000000 | H30: =SUM(Commercial!U11,Commercial!U33,Commercial!U55,Commercial!U77,Commercial!U99,Commercial!U121,Commercial!U143,Commercial!U165,Commercial!U187)*10^9 -> 7908000000 | I30: =SUM(Commercial!V11,Commercial!V33,Commercial!V55,Commercial!V77,Commercial!V99,Commercial!V121,Commercial!V143,Commercial!V165,Commercial!V187)*10^9 -> 7910000000 | ... AB30: =SUM(Commercial!AO11,Commercial!AO33,Commercial!AO55,Commercial!AO77,Commercial!AO99,Commercial!AO121,Commercial!AO143,Commercial!AO165,Commercial!AO187)*10^9 -> 8096000000 | AC30: =TREND($P30:$AB30,$P$29:$AB$29,AC$29) -> 8.1339615e+09 | AD30: =TREND($P30:$AB30,$P$29:$AB$29,AD$29) -> 8.1723736e+09 | AE30: =TREND($P30:$AB30,$P$29:$AB$29,AE$29) -> 8.2107857e+09 | AF30: =TREND($P30:$AB30,$P$29:$AB$29,AF$29) -> 8.2491978e+09 | AG30: =TREND($P30:$AB30,$P$29:$AB$29,AG$29) -> 8.2876099e+09 | AH30: =TREND($P30:$AB30,$P$29:$AB$29,AH$29) -> 8.326022e+09 | AI30: =TREND($P30:$AB30,$P$29:$AB$29,AI$29) -> 8.3644341e+09 | AJ30: =TREND($P30:$AB30,$P$29:$AB$29,AJ$29) -> 8.4028462e+09 | ... AL30: =TREND($P30:$AB30,$P$29:$AB$29,AL$29) -> 8.4796703e+09
A31: Cooling and Ventilation | B31: =SUM(Commercial!O14,Commercial!O20,Commercial!O36,Commercial!O42,Commercial!O58,Commercial!O64,Commercial!O80,Commercial!O86,Commercial!O102,Commercial!O108,Commercial!O124,Commercial!O130,Commercial!O146,Commercial!O152,Commercial!O168,Commercial!O174,Commercial!O190,Commercial!O196)*10^9 -> 32204000000 | C31: =SUM(Commercial!P14,Commercial!P20,Commercial!P36,Commercial!P42,Commercial!P58,Commercial!P64,Commercial!P80,Commercial!P86,Commercial!P102,Commercial!P108,Commercial!P124,Commercial!P130,Commercial!P146,Commercial!P152,Commercial!P168,Commercial!P174,Commercial!P190,Commercial!P196)*10^9 -> 32856000000 | D31: =SUM(Commercial!Q14,Commercial!Q20,Commercial!Q36,Commercial!Q42,Commercial!Q58,Commercial!Q64,Commercial!Q80,Commercial!Q86,Commercial!Q102,Commercial!Q108,Commercial!Q124,Commercial!Q130,Commercial!Q146,Commercial!Q152,Commercial!Q168,Commercial!Q174,Commercial!Q190,Commercial!Q196)*10^9 -> 33433000000 | E31: =SUM(Commercial!R14,Commercial!R20,Commercial!R36,Commercial!R42,Commercial!R58,Commercial!R64,Commercial!R80,Commercial!R86,Commercial!R102,Commercial!R108,Commercial!R124,Commercial!R130,Commercial!R146,Commercial!R152,Commercial!R168,Commercial!R174,Commercial!R190,Commercial!R196)*10^9 -> 3.4194e+10 | F31: =SUM(Commercial!S14,Commercial!S20,Commercial!S36,Commercial!S42,Commercial!S58,Commercial!S64,Commercial!S80,Commercial!S86,Commercial!S102,Commercial!S108,Commercial!S124,Commercial!S130,Commercial!S146,Commercial!S152,Commercial!S168,Commercial!S174,Commercial!S190,Commercial!S196)*10^9 -> 34705000000 | G31: =SUM(Commercial!T14,Commercial!T20,Commercial!T36,Commercial!T42,Commercial!T58,Commercial!T64,Commercial!T80,Commercial!T86,Commercial!T102,Commercial!T108,Commercial!T124,Commercial!T130,Commercial!T146,Commercial!T152,Commercial!T168,Commercial!T174,Commercial!T190,Commercial!T196)*10^9 -> 3.5128e+10 | H31: =SUM(Commercial!U14,Commercial!U20,Commercial!U36,Commercial!U42,Commercial!U58,Commercial!U64,Commercial!U80,Commercial!U86,Commercial!U102,Commercial!U108,Commercial!U124,Commercial!U130,Commercial!U146,Commercial!U152,Commercial!U168,Commercial!U174,Commercial!U190,Commercial!U196)*10^9 -> 35342000000 | I31: =SUM(Commercial!V14,Commercial!V20,Commercial!V36,Commercial!V42,Commercial!V58,Commercial!V64,Commercial!V80,Commercial!V86,Commercial!V102,Commercial!V108,Commercial!V124,Commercial!V130,Commercial!V146,Commercial!V152,Commercial!V168,Commercial!V174,Commercial!V190,Commercial!V196)*10^9 -> 3.5574e+10 | ... AB31: =SUM(Commercial!AO14,Commercial!AO20,Commercial!AO36,Commercial!AO42,Commercial!AO58,Commercial!AO64,Commercial!AO80,Commercial!AO86,Commercial!AO102,Commercial!AO108,Commercial!AO124,Commercial!AO130,Commercial!AO146,Commercial!AO152,Commercial!AO168,Commercial!AO174,Commercial!AO190,Commercial!AO196)*10^9 -> 4.1105e+10 | AC31: =TREND($P31:$AB31,$P$29:$AB$29,AC$29) -> 4.1905308e+10 | AD31: =TREND($P31:$AB31,$P$29:$AB$29,AD$29) -> 4.2406791e+10 | AE31: =TREND($P31:$AB31,$P$29:$AB$29,AE$29) -> 4.2908275e+10 | AF31: =TREND($P31:$AB31,$P$29:$AB$29,AF$29) -> 4.3409758e+10 | AG31: =TREND($P31:$AB31,$P$29:$AB$29,AG$29) -> 4.3911242e+10 | AH31: =TREND($P31:$AB31,$P$29:$AB$29,AH$29) -> 4.4412725e+10 | AI31: =TREND($P31:$AB31,$P$29:$AB$29,AI$29) -> 4.4914209e+10 | AJ31: =TREND($P31:$AB31,$P$29:$AB$29,AJ$29) -> 4.5415692e+10 | ... AL31: =TREND($P31:$AB31,$P$29:$AB$29,AL$29) -> 4.6418659e+10
A32: Envelope | B32: 0 | C32: 0 | D32: 0 | E32: 0 | F32: 0 | G32: 0 | H32: 0 | I32: 0 | J32: 0 | K32: 0 | L32: 0 | M32: 0 | N32: 0 | O32: 0 | P32: 0 | Q32: 0 | R32: 0 | S32: 0 | T32: 0 | U32: 0 | V32: 0 | W32: 0 | X32: 0 | Y32: 0 | Z32: 0 | AA32: 0 | AB32: 0 | AC32: =TREND($P32:$AB32,$P$29:$AB$29,AC$29) -> 0 | AD32: =TREND($P32:$AB32,$P$29:$AB$29,AD$29) -> 0 | AE32: =TREND($P32:$AB32,$P$29:$AB$29,AE$29) -> 0 | AF32: =TREND($P32:$AB32,$P$29:$AB$29,AF$29) -> 0 | AG32: =TREND($P32:$AB32,$P$29:$AB$29,AG$29) -> 0 | AH32: =TREND($P32:$AB32,$P$29:$AB$29,AH$29) -> 0 | AI32: =TREND($P32:$AB32,$P$29:$AB$29,AI$29) -> 0 | AJ32: =TREND($P32:$AB32,$P$29:$AB$29,AJ$29) -> 0 | ... AL32: =TREND($P32:$AB32,$P$29:$AB$29,AL$29) -> 0
A33: Lighting | B33: =SUM(Commercial!O26,Commercial!O48,Commercial!O70,Commercial!O92,Commercial!O114,Commercial!O136,Commercial!O158,Commercial!O180,Commercial!O202)*10^9 -> 1.464e+09 | C33: =SUM(Commercial!P26,Commercial!P48,Commercial!P70,Commercial!P92,Commercial!P114,Commercial!P136,Commercial!P158,Commercial!P180,Commercial!P202)*10^9 -> 1.476e+09 | D33: =SUM(Commercial!Q26,Commercial!Q48,Commercial!Q70,Commercial!Q92,Commercial!Q114,Commercial!Q136,Commercial!Q158,Commercial!Q180,Commercial!Q202)*10^9 -> 1492000000 | E33: =SUM(Commercial!R26,Commercial!R48,Commercial!R70,Commercial!R92,Commercial!R114,Commercial!R136,Commercial!R158,Commercial!R180,Commercial!R202)*10^9 -> 1523000000 | F33: =SUM(Commercial!S26,Commercial!S48,Commercial!S70,Commercial!S92,Commercial!S114,Commercial!S136,Commercial!S158,Commercial!S180,Commercial!S202)*10^9 -> 1546000000 | G33: =SUM(Commercial!T26,Commercial!T48,Commercial!T70,Commercial!T92,Commercial!T114,Commercial!T136,Commercial!T158,Commercial!T180,Commercial!T202)*10^9 -> 1573000000 | H33: =SUM(Commercial!U26,Commercial!U48,Commercial!U70,Commercial!U92,Commercial!U114,Commercial!U136,Commercial!U158,Commercial!U180,Commercial!U202)*10^9 -> 1.68e+09 | I33: =SUM(Commercial!V26,Commercial!V48,Commercial!V70,Commercial!V92,Commercial!V114,Commercial!V136,Commercial!V158,Commercial!V180,Commercial!V202)*10^9 -> 1710000000 | ... AB33: =SUM(Commercial!AO26,Commercial!AO48,Commercial!AO70,Commercial!AO92,Commercial!AO114,Commercial!AO136,Commercial!AO158,Commercial!AO180,Commercial!AO202)*10^9 -> 2036000000 | AC33: =TREND($P33:$AB33,$P$29:$AB$29,AC$29) -> 2.0645769e+09 | AD33: =TREND($P33:$AB33,$P$29:$AB$29,AD$29) -> 2.0880659e+09 | AE33: =TREND($P33:$AB33,$P$29:$AB$29,AE$29) -> 2.1115549e+09 | AF33: =TREND($P33:$AB33,$P$29:$AB$29,AF$29) -> 2.135044e+09 | AG33: =TREND($P33:$AB33,$P$29:$AB$29,AG$29) -> 2.158533e+09 | AH33: =TREND($P33:$AB33,$P$29:$AB$29,AH$29) -> 2.182022e+09 | AI33: =TREND($P33:$AB33,$P$29:$AB$29,AI$29) -> 2.205511e+09 | AJ33: =TREND($P33:$AB33,$P$29:$AB$29,AJ$29) -> 2229000000 | ... AL33: =TREND($P33:$AB33,$P$29:$AB$29,AL$29) -> 2.275978e+09
A34: Appliances | B34: =SUM(Commercial!O17,Commercial!O23,Commercial!O29,Commercial!O39,Commercial!O45,Commercial!O51,Commercial!O61,Commercial!O67,Commercial!O73,Commercial!O83,Commercial!O89,Commercial!O95,Commercial!O105,Commercial!O111,Commercial!O117,Commercial!O127,Commercial!O133,Commercial!O139,Commercial!O149,Commercial!O155,Commercial!O161,Commercial!O171,Commercial!O177,Commercial!O183,Commercial!O193,Commercial!O199,Commercial!O205)*10^9 -> 35715000000 | C34: =SUM(Commercial!P17,Commercial!P23,Commercial!P29,Commercial!P39,Commercial!P45,Commercial!P51,Commercial!P61,Commercial!P67,Commercial!P73,Commercial!P83,Commercial!P89,Commercial!P95,Commercial!P105,Commercial!P111,Commercial!P117,Commercial!P127,Commercial!P133,Commercial!P139,Commercial!P149,Commercial!P155,Commercial!P161,Commercial!P171,Commercial!P177,Commercial!P183,Commercial!P193,Commercial!P199,Commercial!P205)*10^9 -> 36038000000 | D34: =SUM(Commercial!Q17,Commercial!Q23,Commercial!Q29,Commercial!Q39,Commercial!Q45,Commercial!Q51,Commercial!Q61,Commercial!Q67,Commercial!Q73,Commercial!Q83,Commercial!Q89,Commercial!Q95,Commercial!Q105,Commercial!Q111,Commercial!Q117,Commercial!Q127,Commercial!Q133,Commercial!Q139,Commercial!Q149,Commercial!Q155,Commercial!Q161,Commercial!Q171,Commercial!Q177,Commercial!Q183,Commercial!Q193,Commercial!Q199,Commercial!Q205)*10^9 -> 36381000000 | E34: =SUM(Commercial!R17,Commercial!R23,Commercial!R29,Commercial!R39,Commercial!R45,Commercial!R51,Commercial!R61,Commercial!R67,Commercial!R73,Commercial!R83,Commercial!R89,Commercial!R95,Commercial!R105,Commercial!R111,Commercial!R117,Commercial!R127,Commercial!R133,Commercial!R139,Commercial!R149,Commercial!R155,Commercial!R161,Commercial!R171,Commercial!R177,Commercial!R183,Commercial!R193,Commercial!R199,Commercial!R205)*10^9 -> 3.856e+10 | F34: =SUM(Commercial!S17,Commercial!S23,Commercial!S29,Commercial!S39,Commercial!S45,Commercial!S51,Commercial!S61,Commercial!S67,Commercial!S73,Commercial!S83,Commercial!S89,Commercial!S95,Commercial!S105,Commercial!S111,Commercial!S117,Commercial!S127,Commercial!S133,Commercial!S139,Commercial!S149,Commercial!S155,Commercial!S161,Commercial!S171,Commercial!S177,Commercial!S183,Commercial!S193,Commercial!S199,Commercial!S205)*10^9 -> 3.8813e+10 | G34: =SUM(Commercial!T17,Commercial!T23,Commercial!T29,Commercial!T39,Commercial!T45,Commercial!T51,Commercial!T61,Commercial!T67,Commercial!T73,Commercial!T83,Commercial!T89,Commercial!T95,Commercial!T105,Commercial!T111,Commercial!T117,Commercial!T127,Commercial!T133,Commercial!T139,Commercial!T149,Commercial!T155,Commercial!T161,Commercial!T171,Commercial!T177,Commercial!T183,Commercial!T193,Commercial!T199,Commercial!T205)*10^9 -> 38961000000 | H34: =SUM(Commercial!U17,Commercial!U23,Commercial!U29,Commercial!U39,Commercial!U45,Commercial!U51,Commercial!U61,Commercial!U67,Commercial!U73,Commercial!U83,Commercial!U89,Commercial!U95,Commercial!U105,Commercial!U111,Commercial!U117,Commercial!U127,Commercial!U133,Commercial!U139,Commercial!U149,Commercial!U155,Commercial!U161,Commercial!U171,Commercial!U177,Commercial!U183,Commercial!U193,Commercial!U199,Commercial!U205)*10^9 -> 39061000000 | I34: =SUM(Commercial!V17,Commercial!V23,Commercial!V29,Commercial!V39,Commercial!V45,Commercial!V51,Commercial!V61,Commercial!V67,Commercial!V73,Commercial!V83,Commercial!V89,Commercial!V95,Commercial!V105,Commercial!V111,Commercial!V117,Commercial!V127,Commercial!V133,Commercial!V139,Commercial!V149,Commercial!V155,Commercial!V161,Commercial!V171,Commercial!V177,Commercial!V183,Commercial!V193,Commercial!V199,Commercial!V205)*10^9 -> 3.9186e+10 | ... AB34: =SUM(Commercial!AO17,Commercial!AO23,Commercial!AO29,Commercial!AO39,Commercial!AO45,Commercial!AO51,Commercial!AO61,Commercial!AO67,Commercial!AO73,Commercial!AO83,Commercial!AO89,Commercial!AO95,Commercial!AO105,Commercial!AO111,Commercial!AO117,Commercial!AO127,Commercial!AO133,Commercial!AO139,Commercial!AO149,Commercial!AO155,Commercial!AO161,Commercial!AO171,Commercial!AO177,Commercial!AO183,Commercial!AO193,Commercial!AO199,Commercial!AO205)*10^9 -> 45720000000 | AC34: =TREND($P34:$AB34,$P$29:$AB$29,AC$29) -> 4.6378192e+10 | AD34: =TREND($P34:$AB34,$P$29:$AB$29,AD$29) -> 4.6833176e+10 | AE34: =TREND($P34:$AB34,$P$29:$AB$29,AE$29) -> 4.7288159e+10 | AF34: =TREND($P34:$AB34,$P$29:$AB$29,AF$29) -> 4.7743143e+10 | AG34: =TREND($P34:$AB34,$P$29:$AB$29,AG$29) -> 4.8198126e+10 | AH34: =TREND($P34:$AB34,$P$29:$AB$29,AH$29) -> 4.865311e+10 | AI34: =TREND($P34:$AB34,$P$29:$AB$29,AI$29) -> 4.9108093e+10 | AJ34: =TREND($P34:$AB34,$P$29:$AB$29,AJ$29) -> 4.9563077e+10 | ... AL34: =TREND($P34:$AB34,$P$29:$AB$29,AL$29) -> 5.0473044e+10
A35: Other | B35: 0 | C35: 0 | D35: 0 | E35: 0 | F35: 0 | G35: 0 | H35: 0 | I35: 0 | J35: 0 | K35: 0 | L35: 0 | M35: 0 | N35: 0 | O35: 0 | P35: 0 | Q35: 0 | R35: 0 | S35: 0 | T35: 0 | U35: 0 | V35: 0 | W35: 0 | X35: 0 | Y35: 0 | Z35: 0 | AA35: 0 | AB35: 0 | AC35: =TREND($P35:$AB35,$P$29:$AB$29,AC$29) -> 0 | AD35: =TREND($P35:$AB35,$P$29:$AB$29,AD$29) -> 0 | AE35: =TREND($P35:$AB35,$P$29:$AB$29,AE$29) -> 0 | AF35: =TREND($P35:$AB35,$P$29:$AB$29,AF$29) -> 0 | AG35: =TREND($P35:$AB35,$P$29:$AB$29,AG$29) -> 0 | AH35: =TREND($P35:$AB35,$P$29:$AB$29,AH$29) -> 0 | AI35: =TREND($P35:$AB35,$P$29:$AB$29,AI$29) -> 0 | AJ35: =TREND($P35:$AB35,$P$29:$AB$29,AJ$29) -> 0 | ... AL35: =TREND($P35:$AB35,$P$29:$AB$29,AL$29) -> 0

Sheet US data
A1: China
B2: 2010 | C2: 2011 | D2: 2012 | E2: 2013 | F2: 2014 | G2: 2015 | H2: 2016 | I2: 2017 | J2: 2018 | K2: 2019 | L2: 2020 | M2: 2021 | N2: 2022 | O2: 2023 | P2: 2024 | Q2: 2025 | R2: 2026 | S2: 2027 | T2: 2028 | U2: 2029 | V2: 2030 | W2: 2031 | X2: 2032 | Y2: 2033 | Z2: 2034 | AA2: 2035 | AB2: 2036 | AC2: 2037 | AD2: 2038 | AE2: 2039 | AF2: 2040 | AG2: 2041 | AH2: 2042 | AI2: 2043 | AJ2: 2044 | AK2: 2045 | AL2: 2046 | AM2: 2047 | AN2: 2048 | AO2: 2049 | AP2: 2050
A3: Population (persons) | B3: 1337705000 | C3: 1344130000 | D3: 1350695000 | E3: 1357380000 | F3: 1364270000 | G3: 1371220000 | H3: 1377507000 | I3: 1383288000 | J3: 1388513000 | K3: 1393152000 | L3: 1397198000 | M3: 1400662000 | N3: 1403545000 | O3: 1405871000 | P3: 1407670000 | Q3: 1408977000 | R3: 1409831000 | S3: 1410269000 | T3: 1410323000 | U3: 1410014000 | V3: 1409352000 | W3: 1408336000 | X3: 1406964000 | Y3: 1405249000 | Z3: 1403218000 | AA3: 1400923000 | AB3: 1398401000 | AC3: 1395671000 | AD3: 1392746000 | AE3: 1389626000 | AF3: 1386300000 | AG3: 1382738000 | AH3: 1378912000 | AI3: 1374808000 | AJ3: 1370404000 | AK3: 1365674000 | AL3: 1360605000 | AM3: 1355187000 | AN3: 1349423000 | AO3: 1343330000 | AP3: 1336607000
A4: GDP (USD) | B4: ='[3]GDP data(not used)'!B7 -> 5.9424646e+12 | C4: ='[3]GDP data(not used)'!C7 -> 6.4059769e+12 | D4: ='[3]GDP data(not used)'!D7 -> 6.9056431e+12 | E4: ='[3]GDP data(not used)'!E7 -> 7.4442832e+12 | F4: ='[3]GDP data(not used)'!F7 -> 8.0249373e+12 | G4: ='[3]GDP data(not used)'!G7 -> 8.6508824e+12 | H4: ='[3]GDP data(not used)'!H7 -> 9.2131898e+12 | I4: ='[3]GDP data(not used)'!I7 -> 9.8120471e+12 | ... AP4: ='[3]GDP data(not used)'!AP7 -> 3.6557391e+13
A5: Per Capita GDP (USD/person) | B5: =B4/B3 -> 4442.2833 | C5: =C4/C3 -> 4765.8909 | D5: =D4/D3 -> 5112.6591 | E5: =E4/E3 -> 5484.303 | F5: =F4/F3 -> 5882.2208 | G5: =G4/G3 -> 6308.8946 | H5: =H4/H3 -> 6688.3071 | I5: =I4/I3 -> 7093.2786 | ... AP5: =AP4/AP3 -> 27350.89
A7: U.S. Projections
B8: 2010 | C8: 2011 | D8: 2012 | E8: 2013 | F8: 2014 | G8: 2015 | H8: 2016 | I8: 2017 | J8: 2018 | K8: 2019 | L8: 2020 | M8: 2021 | N8: 2022 | O8: 2023 | P8: 2024 | Q8: 2025 | R8: 2026 | S8: 2027 | T8: 2028 | U8: 2029 | V8: 2030 | W8: 2031 | X8: 2032 | Y8: 2033 | Z8: 2034 | AA8: 2035 | AB8: 2036 | AC8: 2037 | AD8: 2038 | AE8: 2039 | AF8: 2040 | AG8: 2041 | AH8: 2042 | AI8: 2043 | AJ8: 2044 | AK8: 2045 | AL8: 2046 | AM8: 2047 | AN8: 2048 | AO8: 2049 | AP8: 2050
A9: Population (people) | B9: 309346863 | C9: 311718857 | D9: 314102623 | E9: 316427395 | F9: 318907401 | G9: 321369000 | H9: 323996000 | I9: 326626000 | J9: 329256000 | K9: 331884000 | L9: 334503000 | M9: 337109000 | N9: 339698000 | O9: 342267000 | P9: 344814000 | Q9: 347335000 | R9: 349826000 | S9: 352281000 | T9: 354698000 | U9: 357073000 | V9: 359402000 | W9: 361685000 | X9: 363920000 | Y9: 366106000 | Z9: 368246000 | AA9: 370338000 | AB9: 372390000 | AC9: 374401000 | AD9: 376375000 | AE9: 378313000 | AF9: 380219000 | AG9: 382096000 | AH9: 383949000 | AI9: 385779000 | AJ9: 387593000 | AK9: 389394000 | AL9: 391187000 | AM9: 392973000 | AN9: 394756000 | AO9: 396540000 | AP9: 398328000
A10: GDP (US$) | B10: 13595600000000 | C10: 13846800000000 | D10: 14231600000000 | E10: 14499000000000 | F10: 14898400000000 | G10: 15423300000000 | H10: 15928700000000 | I10: 16401200000000 | J10: 16854400000000 | K10: 17299300000000 | L10: 17743000000000 | M10: 18189100000000 | N10: 18639500000000 | O10: 19095200000000 | P10: 19557000000000 | Q10: 20025600000000 | R10: 20502000000000 | S10: 20987100000000 | T10: 21481300000000 | U10: 21981200000000 | V10: 22482200000000 | W10: 22983800000000 | X10: 23485700000000 | Y10: 23987600000000 | Z10: 24488800000000 | AA10: 24988800000000 | AB10: 25487200000000 | AC10: 25983700000000 | AD10: 26478500000000 | AE10: 26971200000000 | AF10: 27461800000000 | AG10: 27950700000000 | AH10: 28438300000000 | AI10: 28925400000000 | AJ10: 29412100000000 | AK10: 29898900000000 | AL10: 30386000000000 | AM10: 30873700000000 | AN10: 31362300000000 | AO10: 31851700000000 | AP10: 32341600000000
A11: Per Capita GDP | B11: 43950 | C11: 44421 | D11: 45309 | E11: 45821 | F11: 46717 | G11: 47993 | H11: 49163 | I11: 50214 | J11: 51189 | K11: 52125 | L11: 53043 | M11: 53956 | N11: 54871 | O11: 55790 | P11: 56717 | Q11: 57655 | R11: 58606 | S11: 59575 | T11: 60562 | U11: 61559 | V11: 62555 | W11: 63547 | X11: 64535 | Y11: 65521 | Z11: 66501 | AA11: 67476 | AB11: 68442 | AC11: 69401 | AD11: 70351 | AE11: 71293 | AF11: 72226 | AG11: 73151 | AH11: 74068 | AI11: 74979 | AJ11: 75884 | AK11: 76783 | AL11: 77676 | AM11: 78565 | AN11: 79447 | AO11: 80324 | AP11: 81193
A13: Ratio of China to U.S.
B14: 2010 | C14: 2011 | D14: 2012 | E14: 2013 | F14: 2014 | G14: 2015 | H14: 2016 | I14: 2017 | J14: 2018 | K14: 2019 | L14: 2020 | M14: 2021 | N14: 2022 | O14: 2023 | P14: 2024 | Q14: 2025 | R14: 2026 | S14: 2027 | T14: 2028 | U14: 2029 | V14: 2030 | W14: 2031 | X14: 2032 | Y14: 2033 | Z14: 2034 | AA14: 2035 | AB14: 2036 | AC14: 2037 | AD14: 2038 | AE14: 2039 | AF14: 2040 | AG14: 2041 | AH14: 2042 | AI14: 2043 | AJ14: 2044 | AK14: 2045 | AL14: 2046 | AM14: 2047 | AN14: 2048 | AO14: 2049 | AP14: 2050
A15: Population (people) | B15: =B3/B9 -> 4.3242882 | C15: =C3/C9 -> 4.3119945 | D15: =D3/D9 -> 4.300171 | E15: =E3/E9 -> 4.2897044 | F15: =F3/F9 -> 4.2779503 | G15: =G3/G9 -> 4.2668086 | H15: =H3/H9 -> 4.2516173 | I15: =I3/I9 -> 4.2350823 | ... AP15: =AP3/AP9 -> 3.3555437
A16: GDP (US$) | B16: =B4/B10 -> 0.43708734 | C16: =C4/C10 -> 0.4626323 | D16: =D4/D10 -> 0.48523308 | E16: =E4/E10 -> 0.51343425 | F16: =F4/F10 -> 0.53864424 | G16: =G4/G10 -> 0.56089698 | H16: =H4/H10 -> 0.57840186 | I16: =I4/I10 -> 0.59825178 | ... AP16: =AP4/AP10 -> 1.130352
A17: Per Capita GDP | B17: =B5/B11 -> 0.10107584 | C17: =C5/C11 -> 0.10728914 | D17: =D5/D11 -> 0.11283981 | E17: =E5/E11 -> 0.11968973 | F17: =F5/F11 -> 0.12591178 | G17: =G5/G11 -> 0.13145447 | H17: =H5/H11 -> 0.13604351 | I17: =I5/I11 -> 0.14126097 | ... AP17: =AP5/AP11 -> 0.33686266

Sheet AEO T4
B1: ref2017.d120816a | C1: 2015 | D1: 2016 | E1: 2017 | F1: 2018 | G1: 2019 | H1: 2020 | I1: 2021 | J1: 2022 | K1: 2023 | L1: 2024 | M1: 2025 | N1: 2026 | O1: 2027 | P1: 2028 | Q1: 2029 | R1: 2030 | S1: 2031 | T1: 2032 | U1: 2033 | V1: 2034 | W1: 2035 | X1: 2036 | Y1: 2037 | Z1: 2038 | AA1: 2039 | AB1: 2040 | AC1: 2041 | AD1: 2042 | AE1: 2043 | AF1: 2044 | AG1: 2045 | AH1: 2046 | AI1: 2047 | AJ1: 2048 | AK1: 2049 | AL1: 2050
C3: Report | D3: Annual Energy Outlook 2017
C4: Scenario | D4: ref2017 | G4: Reference case
C5: Datekey | D5: d120816a
C6: Release Date | E6: January 2017
A10: RKI000 | B10: 4. Residential Sector Key Indicators and Consumption
B11: (quadrillion Btu, unless otherwise noted)
AM12: 2016-
B13: Key Indicators and Consumption | C13: 2015 | D13: 2016 | E13: 2017 | F13: 2018 | G13: 2019 | H13: 2020 | I13: 2021 | J13: 2022 | K13: 2023 | L13: 2024 | M13: 2025 | N13: 2026 | O13: 2027 | P13: 2028 | Q13: 2029 | R13: 2030 | S13: 2031 | T13: 2032 | U13: 2033 | V13: 2034 | W13: 2035 | X13: 2036 | Y13: 2037 | Z13: 2038 | AA13: 2039 | AB13: 2040 | AC13: 2041 | AD13: 2042 | AE13: 2043 | AF13: 2044 | AG13: 2045 | AH13: 2046 | AI13: 2047 | AJ13: 2048 | AK13: 2049 | AL13: 2050 | AM13: 2050
B15: Key Indicators
B16: Households (millions)
A17: RKI000:ba_Single-Family | B17: Single-Family | C17: 80.548882 | D17: 81.10302 | E17: 81.82338 | F17: 82.645271 | G17: 83.465591 | H17: 84.301651 | I17: 85.147186 | J17: 86.01313 | K17: 86.889809 | L17: 87.77227 | M17: 88.648026 | N17: 89.503479 | O17: 90.324585 | P17: 91.099731 | Q17: 91.856583 | R17: 92.619987 | S17: 93.361687 | T17: 94.051025 | U17: 94.733063 | V17: 95.449333 | W17: 96.199455 | X17: 96.957245 | Y17: 97.713737 | Z17: 98.475151 | AA17: 99.23101 | AB17: 99.989937 | AC17: 100.75047 | AD17: 101.50308 | AE17: 102.26664 | AF17: 103.0535 | AG17: 103.86337 | AH17: 104.68725 | AI17: 105.51291 | AJ17: 106.32539 | AK17: 107.12827 | AL17: 107.92848 | AM17: 0.00844
A18: RKI000:ba_Multifamily | B18: Multifamily | C18: 28.870884 | D18: 29.110094 | E18: 29.380239 | F18: 29.680817 | G18: 30.01416 | H18: 30.373581 | I18: 30.756231 | J18: 31.153685 | K18: 31.553375 | L18: 31.957239 | M18: 32.351425 | N18: 32.732346 | O18: 33.110371 | P18: 33.49255 | Q18: 33.875225 | R18: 34.257374 | S18: 34.636684 | T18: 35.013767 | U18: 35.396408 | V18: 35.785557 | W18: 36.181156 | X18: 36.573303 | Y18: 36.961632 | Z18: 37.346928 | AA18: 37.722347 | AB18: 38.090382 | AC18: 38.449062 | AD18: 38.806965 | AE18: 39.162479 | AF18: 39.514824 | AG18: 39.860397 | AH18: 40.201298 | AI18: 40.538223 | AJ18: 40.868778 | AK18: 41.197083 | AL18: 41.520844 | AM18: 0.010499
A19: RKI000:ba_MobileHomes | B19: Mobile Homes | C19: 5.965145 | D19: 5.842867 | E19: 5.742257 | F19: 5.664587 | G19: 5.591901 | H19: 5.524901 | I19: 5.472419 | J19: 5.436611 | K19: 5.408078 | L19: 5.385289 | M19: 5.3637 | N19: 5.333962 | O19: 5.294229 | P19: 5.248191 | Q19: 5.200993 | R19: 5.152752 | S19: 5.102839 | T19: 5.051295 | U19: 5.002883 | V19: 4.961352 | W19: 4.926433 | X19: 4.895687 | Y19: 4.867416 | Z19: 4.845345 | AA19: 4.827591 | AB19: 4.811014 | AC19: 4.794406 | AD19: 4.778117 | AE19: 4.760415 | AF19: 4.740447 | AG19: 4.715725 | AH19: 4.68894 | AI19: 4.660537 | AJ19: 4.629189 | AK19: 4.597032 | AL19: 4.56343 | AM19: -0.007243
A20: RKI000:ba_Total | B20: Total | C20: 115.38492 | D20: 116.05598 | E20: 116.94588 | F20: 117.99068 | G20: 119.07166 | H20: 120.20013 | I20: 121.37584 | J20: 122.60342 | K20: 123.85126 | L20: 125.1148 | M20: 126.36315 | N20: 127.56979 | O20: 128.72919 | P20: 129.84047 | Q20: 130.9328 | R20: 132.03012 | S20: 133.10121 | T20: 134.11609 | U20: 135.13235 | V20: 136.19624 | W20: 137.30705 | X20: 138.42624 | Y20: 139.54279 | Z20: 140.66744 | AA20: 141.78095 | AB20: 142.89134 | AC20: 143.99393 | AD20: 145.08817 | AE20: 146.18955 | AF20: 147.30878 | AG20: 148.43948 | AH20: 149.57748 | AI20: 150.71167 | AJ20: 151.82336 | AK20: 152.92238 | AL20: 154.01276 | AM20: 0.008357
A22: RKI000:ca_AverageHouseS | B22: Average House Square Footage | C22: 1695.0878 | D22: 1703.2651 | E22: 1711.6783 | F22: 1720.0626 | G22: 1728.099 | H22: 1735.8943 | I22: 1743.3932 | J22: 1750.6895 | K22: 1757.9084 | L22: 1765.0195 | M22: 1772.1107 | N22: 1779.2067 | O22: 1786.1916 | P22: 1792.9419 | Q22: 1799.5736 | R22: 1806.2012 | S22: 1812.7317 | T22: 1819.0262 | U22: 1825.199 | V22: 1831.3966 | W22: 1837.626 | X22: 1843.8593 | Y22: 1850.0693 | Z22: 1856.2556 | AA22: 1862.4346 | AB22: 1868.646 | AC22: 1874.9025 | AD22: 1881.1038 | AE22: 1887.3536 | AF22: 1893.7168 | AG22: 1900.2357 | AH22: 1906.8367 | AI22: 1913.4568 | AJ22: 1920.0542 | AK22: 1926.6034 | AL22: 1933.1583 | AM22: 0.003731
B24: Energy Intensity
B25: (million Btu per household)
A26: RKI000:da_DeliveredEner | B26: Delivered Energy Consumption | C26: 95.092171 | D26: 91.514305 | E26: 93.235954 | F26: 93.20533 | G26: 92.119431 | H26: 90.596268 | I26: 89.305229 | J26: 88.062706 | K26: 86.945023 | L26: 85.989021 | M26: 85.068665 | N26: 84.170921 | O26: 83.288025 | P26: 82.493507 | Q26: 81.758041 | R26: 81.003342 | S26: 80.306366 | T26: 79.661469 | U26: 79.07061 | V26: 78.507645 | W26: 77.900688 | X26: 77.31575 | Y26: 76.757065 | Z26: 76.239441 | AA26: 75.742729 | AB26: 75.246231 | AC26: 74.741257 | AD26: 74.238434 | AE26: 73.729492 | AF26: 73.223419 | AG26: 72.72551 | AH26: 72.229294 | AI26: 71.727997 | AJ26: 71.198563 | AK26: 70.677345 | AL26: 70.151375 | AM26: -0.007788
A27: RKI000:da_TotalEnergyCo | B27: Total Energy Consumption | C27: 178.03015 | D27: 172.3932 | E27: 173.36307 | F27: 172.74106 | G27: 171.11243 | H27: 168.35864 | I27: 165.76492 | J27: 163.26141 | K27: 161.14697 | L27: 159.12972 | M27: 157.0602 | N27: 154.86238 | O27: 153.01291 | P27: 151.35422 | Q27: 149.92725 | R27: 148.44684 | S27: 147.19064 | T27: 145.94107 | U27: 145.06276 | V27: 143.89093 | W27: 142.56427 | X27: 141.70538 | Y27: 140.52081 | Z27: 139.61462 | AA27: 138.74222 | AB27: 137.95392 | AC27: 137.00166 | AD27: 136.08182 | AE27: 135.21374 | AF27: 134.20184 | AG27: 133.0312 | AH27: 131.96632 | AI27: 130.84097 | AJ27: 129.76594 | AK27: 128.76866 | AL27: 127.43207 | AM27: -0.008849
B28: (thousand Btu per square foot)
A29: RKI000:ea_DeliveredEner | B29: Delivered Energy Consumption | C29: 56.098671 | D29: 53.728748 | E29: 54.470486 | F29: 54.187172 | G29: 53.306805 | H29: 52.189968 | I29: 51.224949 | J29: 50.301727 | K29: 49.459358 | L29: 48.718452 | M29: 48.004147 | N29: 47.308121 | O29: 46.62883 | P29: 46.010139 | Q29: 45.431896 | R29: 44.847355 | S29: 44.301296 | T29: 43.793468 | U29: 43.32164 | V29: 42.867638 | W29: 42.392025 | X29: 41.93148 | Y29: 41.48875 | Z29: 41.071629 | AA29: 40.668667 | AB29: 40.267784 | AC29: 39.864079 | AD29: 39.465355 | AE29: 39.06501 | AF29: 38.666508 | AG29: 38.271835 | AH29: 37.87912 | AI29: 37.48608 | AJ29: 37.081539 | AK29: 36.684948 | AL29: 36.288479 | AM29: -0.011476
A30: RKI000:ea_TotalEnergyCo | B30: Total Energy Consumption | C30: 105.0271 | D30: 101.21337 | E30: 101.2825 | F30: 100.42718 | G30: 99.017723 | H30: 96.986687 | I30: 95.081779 | J30: 93.255501 | K30: 91.669716 | L30: 90.157478 | M30: 88.628883 | N30: 87.040131 | O30: 85.66433 | P30: 84.416687 | Q30: 83.312653 | R30: 82.187325 | S30: 81.19825 | T30: 80.230324 | U30: 79.477783 | V30: 78.568962 | W30: 77.580673 | X30: 76.852608 | Y30: 75.954346 | Z30: 75.213036 | AA30: 74.495087 | AB30: 73.825607 | AC30: 73.07135 | AD30: 72.341469 | AE30: 71.641975 | AF30: 70.866905 | AG30: 70.007744 | AH30: 69.20694 | AI30: 68.379372 | AJ30: 67.584518 | AK30: 66.837143 | AL30: 65.919106 | AM30: -0.012533
B32: Delivered Energy Consumption by Fuel
B33: Purchased Electricity
A34: RKI000:fa_SpaceHeating | B34: Space Heating | C34: 0.331095 | D34: 0.327905 | E34: 0.349864 | F34: 0.360698 | G34: 0.359427 | H34: 0.35678 | I34: 0.354556 | J34: 0.351704 | K34: 0.349147 | L34: 0.347889 | M34: 0.346378 | N34: 0.344521 | O34: 0.342983 | P34: 0.341653 | Q34: 0.340396 | R34: 0.339176 | S34: 0.337991 | T34: 0.336796 | U34: 0.335669 | V34: 0.334739 | W34: 0.333526 | X34: 0.332407 | Y34: 0.331335 | Z34: 0.330215 | AA34: 0.329147 | AB34: 0.328134 | AC34: 0.327134 | AD34: 0.32601 | AE34: 0.324843 | AF34: 0.323649 | AG34: 0.322493 | AH34: 0.321251 | AI34: 0.320117 | AJ34: 0.318898 | AK34: 0.31769 | AL34: 0.3165 | AM34: -0.001041
A35: RKI000:fa_SpaceCooling | B35: Space Cooling | C35: 0.794241 | D35: 0.843365 | E35: 0.734594 | F35: 0.76137 | G35: 0.762741 | H35: 0.761492 | I35: 0.761669 | J35: 0.760511 | K35: 0.760795 | L35: 0.763733 | M35: 0.766355 | N35: 0.769149 | O35: 0.772869 | P35: 0.777587 | Q35: 0.782814 | R35: 0.787987 | S35: 0.794111 | T35: 0.799816 | U35: 0.805894 | V35: 0.812054 | W35: 0.81797 | X35: 0.823585 | Y35: 0.828776 | Z35: 0.834249 | AA35: 0.839338 | AB35: 0.843899 | AC35: 0.848227 | AD35: 0.852276 | AE35: 0.855443 | AF35: 0.858159 | AG35: 0.860597 | AH35: 0.862771 | AI35: 0.864408 | AJ35: 0.86468 | AK35: 0.864275 | AL35: 0.863426 | AM35: 0.000692
A36: RKI000:fa_WaterHeating | B36: Water Heating | C36: 0.450959 | D36: 0.455588 | E36: 0.459874 | F36: 0.463842 | G36: 0.466237 | H36: 0.466061 | I36: 0.466631 | J36: 0.466397 | K36: 0.466415 | L36: 0.467595 | M36: 0.468658 | N36: 0.46926 | O36: 0.470007 | P36: 0.470921 | Q36: 0.471731 | R36: 0.472078 | S36: 0.472246 | T36: 0.472215 | U36: 0.471744 | V36: 0.470985 | W36: 0.469734 | X36: 0.468383 | Y36: 0.467286 | Z36: 0.466714 | AA36: 0.466841 | AB36: 0.467631 | AC36: 0.46911 | AD36: 0.470964 | AE36: 0.472968 | AF36: 0.475037 | AG36: 0.477081 | AH36: 0.479117 | AI36: 0.481072 | AJ36: 0.482834 | AK36: 0.484493 | AL36: 0.486022 | AM36: 0.001904
A37: RKI000:fa_Refrigeration | B37: Refrigeration | C37: 0.355201 | D37: 0.35081 | E37: 0.346875 | F37: 0.343662 | G37: 0.340835 | H37: 0.338432 | I37: 0.336455 | J37: 0.334212 | K37: 0.332347 | L37: 0.330892 | M37: 0.329846 | N37: 0.329135 | O37: 0.328747 | P37: 0.328678 | Q37: 0.329 | R37: 0.32979 | S37: 0.330945 | T37: 0.332402 | U37: 0.334299 | V37: 0.336792 | W37: 0.339898 | X37: 0.343507 | Y37: 0.347132 | Z37: 0.350793 | AA37: 0.354434 | AB37: 0.358071 | AC37: 0.361684 | AD37: 0.365255 | AE37: 0.368825 | AF37: 0.37242 | AG37: 0.376024 | AH37: 0.379613 | AI37: 0.383152 | AJ37: 0.386586 | AK37: 0.389937 | AL37: 0.39322 | AM37: 0.003362
A38: RKI000:fa_Cooking | B38: Cooking | C38: 0.107912 | D38: 0.108876 | E38: 0.110093 | F38: 0.111487 | G38: 0.112918 | H38: 0.1144 | I38: 0.115934 | J38: 0.117524 | K38: 0.119134 | L38: 0.120757 | M38: 0.122359 | N38: 0.123909 | O38: 0.1254 | P38: 0.126833 | Q38: 0.128242 | R38: 0.129656 | S38: 0.131037 | T38: 0.132353 | U38: 0.133671 | V38: 0.135043 | W38: 0.13647 | X38: 0.137907 | Y38: 0.13934 | Z38: 0.140783 | AA38: 0.142213 | AB38: 0.143639 | AC38: 0.145055 | AD38: 0.146462 | AE38: 0.147877 | AF38: 0.149312 | AG38: 0.150759 | AH38: 0.152214 | AI38: 0.153665 | AJ38: 0.155088 | AK38: 0.156497 | AL38: 0.157896 | AM38: 0.010993
A39: RKI000:fa_ClothesDryers | B39: Clothes Dryers | C39: 0.204635 | D39: 0.206883 | E39: 0.209296 | F39: 0.212039 | G39: 0.214057 | H39: 0.215143 | I39: 0.216217 | J39: 0.21703 | K39: 0.218042 | L39: 0.219747 | M39: 0.221473 | N39: 0.223056 | O39: 0.224778 | P39: 0.226697 | Q39: 0.228736 | R39: 0.230917 | S39: 0.233149 | T39: 0.235399 | U39: 0.23778 | V39: 0.24031 | W39: 0.242833 | X39: 0.245391 | Y39: 0.248003 | Z39: 0.250667 | AA39: 0.253331 | AB39: 0.256003 | AC39: 0.258678 | AD39: 0.261266 | AE39: 0.263761 | AF39: 0.266211 | AG39: 0.268628 | AH39: 0.271044 | AI39: 0.273422 | AJ39: 0.275691 | AK39: 0.277913 | AL39: 0.280083 | AM39: 0.00895
A40: RKI000:fa_Freezers | B40: Freezers | C40: 0.07543 | D40: 0.074619 | E40: 0.073888 | F40: 0.073192 | G40: 0.072462 | H40: 0.071706 | I40: 0.070935 | J40: 0.070168 | K40: 0.069453 | L40: 0.068787 | M40: 0.068159 | N40: 0.067552 | O40: 0.066966 | P40: 0.0664 | Q40: 0.065872 | R40: 0.065407 | S40: 0.064986 | T40: 0.064596 | U40: 0.064264 | V40: 0.064015 | W40: 0.063865 | X40: 0.063791 | Y40: 0.0638 | Z40: 0.063906 | AA40: 0.064104 | AB40: 0.064395 | AC40: 0.064768 | AD40: 0.065146 | AE40: 0.065538 | AF40: 0.065951 | AG40: 0.066383 | AH40: 0.06683 | AI40: 0.067283 | AJ40: 0.067733 | AK40: 0.068182 | AL40: 0.068633 | AM40: -0.002456
A41: RKI000:fa_Lighting | B41: Lighting | C41: 0.448123 | D41: 0.441566 | E41: 0.435892 | F41: 0.434207 | G41: 0.424534 | H41: 0.373465 | I41: 0.342323 | J41: 0.318797 | K41: 0.303977 | L41: 0.294402 | M41: 0.287885 | N41: 0.282972 | O41: 0.279133 | P41: 0.276178 | Q41: 0.273961 | R41: 0.264825 | S41: 0.25764 | T41: 0.252522 | U41: 0.249772 | V41: 0.249398 | W41: 0.249332 | X41: 0.249677 | Y41: 0.250358 | Z41: 0.251256 | AA41: 0.252238 | AB41: 0.248426 | AC41: 0.245436 | AD41: 0.243001 | AE41: 0.241185 | AF41: 0.240336 | AG41: 0.240358 | AH41: 0.2406 | AI41: 0.240962 | AJ41: 0.241355 | AK41: 0.241794 | AL41: 0.242266 | AM41: -0.017501
A42: RKI000:fa_ClothesWasher | B42: Clothes Washers 1/ | C42: 0.026497 | D42: 0.025667 | E42: 0.024887 | F42: 0.023776 | G42: 0.02266 | H42: 0.021433 | I42: 0.020162 | J42: 0.019082 | K42: 0.018184 | L42: 0.017458 | M42: 0.016899 | N42: 0.016508 | O42: 0.016292 | P42: 0.016259 | Q42: 0.016195 | R42: 0.016114 | S42: 0.01603 | T42: 0.015958 | U42: 0.015923 | V42: 0.015941 | W42: 0.016011 | X42: 0.016119 | Y42: 0.016252 | Z42: 0.0164 | AA42: 0.016553 | AB42: 0.016707 | AC42: 0.016862 | AD42: 0.017015 | AE42: 0.01717 | AF42: 0.017327 | AG42: 0.017485 | AH42: 0.017645 | AI42: 0.017804 | AJ42: 0.01796 | AK42: 0.018114 | AL42: 0.018267 | AM42: -0.009953
A43: RKI000:fa_Dishwashers | B43: Dishwashers 1/ | C43: 0.094424 | D43: 0.094505 | E43: 0.094796 | F43: 0.095229 | G43: 0.095648 | H43: 0.096045 | I43: 0.09644 | J43: 0.097098 | K43: 0.098031 | L43: 0.099282 | M43: 0.100798 | N43: 0.102534 | O43: 0.104483 | P43: 0.106602 | Q43: 0.108585 | R43: 0.110437 | S43: 0.112132 | T43: 0.11367 | U43: 0.115158 | V43: 0.116683 | W43: 0.118256 | X43: 0.119853 | Y43: 0.121467 | Z43: 0.123111 | AA43: 0.124761 | AB43: 0.126427 | AC43: 0.128099 | AD43: 0.129763 | AE43: 0.13143 | AF43: 0.133109 | AG43: 0.134785 | AH43: 0.136453 | AI43: 0.138095 | AJ43: 0.139687 | AK43: 0.141238 | AL43: 0.142754 | AM43: 0.012205
A44: RKI000:fa_ColorTelevisi | B44: Televisions and Related Equipment 2/ | C44: 0.288212 | D44: 0.282494 | E44: 0.2774 | F44: 0.273162 | G44: 0.26852 | H44: 0.263822 | I44: 0.259875 | J44: 0.256199 | K44: 0.253304 | L44: 0.251986 | M44: 0.251491 | N44: 0.251538 | O44: 0.252468 | P44: 0.25441 | Q44: 0.257082 | R44: 0.260393 | S44: 0.264374 | T44: 0.268873 | U44: 0.273967 | V44: 0.279572 | W44: 0.285348 | X44: 0.291337 | Y44: 0.297421 | Z44: 0.303437 | AA44: 0.309231 | AB44: 0.314683 | AC44: 0.317851 | AD44: 0.320415 | AE44: 0.322613 | AF44: 0.324784 | AG44: 0.326932 | AH44: 0.329083 | AI44: 0.331172 | AJ44: 0.333129 | AK44: 0.335039 | AL44: 0.336865 | AM44: 0.005191
A45: RKI000:fa_PersonalCompu | B45: Computers and Related Equipment 3/ | C45: 0.111117 | D45: 0.107827 | E45: 0.104646 | F45: 0.101712 | G45: 0.098496 | H45: 0.095143 | I45: 0.091913 | J45: 0.088654 | K45: 0.085554 | L45: 0.082878 | M45: 0.08035 | N45: 0.077899 | O45: 0.07563 | P45: 0.073536 | Q45: 0.071573 | R45: 0.069687 | S45: 0.067884 | T45: 0.066139 | U45: 0.064451 | V45: 0.062801 | W45: 0.06113 | X45: 0.059417 | Y45: 0.057759 | Z45: 0.056146 | AA45: 0.054541 | AB45: 0.052936 | AC45: 0.051434 | AD45: 0.049901 | AE45: 0.048327 | AF45: 0.046734 | AG45: 0.045077 | AH45: 0.043361 | AI45: 0.041551 | AJ45: 0.039626 | AK45: 0.03757 | AL45: 0.035389 | AM45: -0.032238
... A48: RKI000:fa_DeliveredEner | B48: Delivered Energy | C48: 4.776403 | D48: 4.810625 | E48: 4.780662 | F48: 4.835242 | G48: 4.828907 | H48: 4.773632 | I48: 4.744377 | J48: 4.719576 | K48: 4.706628 | L48: 4.710382 | M48: 4.717607 | N48: 4.724288 | O48: 4.736067 | P48: 4.754208 | Q48: 4.773802 | R48: 4.784884 | S48: 4.799917 | T48: 4.817743 | U48: 4.841113 | V48: 4.869628 | W48: 4.898304 | X48: 4.927637 | Y48: 4.957467 | Z48: 4.989327 | AA48: 5.020275 | AB48: 5.045135 | AC48: 5.065891 | AD48: 5.086051 | AE48: 5.104714 | AF48: 5.122814 | AG48: 5.140799 | AH48: 5.157453 | AI48: 5.17076 | AJ48: 5.179155 | AK48: 5.18572 | AL48: 5.189838 | AM48: 0.002234
B50: Natural Gas
A51: RKI000:ga_SpaceHeating | B51: Space Heating | C51: 3.018605 | D51: 2.81811 | E51: 3.022673 | F51: 3.069636 | G51: 3.05641 | H51: 3.045718 | I51: 3.036772 | J51: 3.030123 | K51: 3.024146 | L51: 3.018647 | M51: 3.01191 | N51: 3.003914 | O51: 2.991818 | P51: 2.979888 | Q51: 2.969606 | R51: 2.962548 | S51: 2.956111 | T51: 2.949076 | U51: 2.943504 | V51: 2.938931 | W51: 2.931776 | X51: 2.925297 | Y51: 2.919778 | Z51: 2.915329 | AA51: 2.910455 | AB51: 2.906943 | AC51: 2.902937 | AD51: 2.897179 | AE51: 2.890561 | AF51: 2.884018 | AG51: 2.877572 | AH51: 2.871458 | AI51: 2.865892 | AJ51: 2.859157 | AK51: 2.853049 | AL51: 2.846776 | AM51: 0.000298
A52: RKI000:ga_SpaceCooling | B52: Space Cooling | C52: 0.023169 | D52: 0.023783 | E52: 0.021051 | F52: 0.021517 | G52: 0.021521 | H52: 0.021344 | I52: 0.021161 | J52: 0.020983 | K52: 0.020806 | L52: 0.02061 | M52: 0.020399 | N52: 0.020189 | O52: 0.019967 | P52: 0.019774 | Q52: 0.019613 | R52: 0.019473 | S52: 0.019365 | T52: 0.019263 | U52: 0.019174 | V52: 0.019089 | W52: 0.018999 | X52: 0.018918 | Y52: 0.018831 | Z52: 0.01877 | AA52: 0.018718 | AB52: 0.018684 | AC52: 0.018653 | AD52: 0.018624 | AE52: 0.018595 | AF52: 0.018567 | AG52: 0.018545 | AH52: 0.018529 | AI52: 0.018515 | AJ52: 0.018493 | AK52: 0.018481 | AL52: 0.018464 | AM52: -0.007419
A53: RKI000:ga_WaterHeating | B53: Water Heating | C53: 1.207743 | D53: 1.213621 | E53: 1.214271 | F53: 1.215633 | G53: 1.218808 | H53: 1.222553 | I53: 1.228735 | J53: 1.236829 | K53: 1.246045 | L53: 1.255363 | M53: 1.262286 | N53: 1.268111 | O53: 1.270109 | P53: 1.271725 | Q53: 1.273584 | R53: 1.27574 | S53: 1.276583 | T53: 1.275915 | U53: 1.274368 | V53: 1.271778 | W53: 1.26755 | X53: 1.263039 | Y53: 1.258974 | Z53: 1.256536 | AA53: 1.255713 | AB53: 1.257376 | AC53: 1.2609 | AD53: 1.265479 | AE53: 1.270765 | AF53: 1.276758 | AG53: 1.283196 | AH53: 1.289961 | AI53: 1.296887 | AJ53: 1.303247 | AK53: 1.309684 | AL53: 1.315959 | AM53: 0.002384
A54: RKI000:ga_Cooking | B54: Cooking | C54: 0.208441 | D54: 0.208378 | E54: 0.208584 | F54: 0.208978 | G54: 0.209398 | H54: 0.209852 | I54: 0.210332 | J54: 0.21087 | K54: 0.211446 | L54: 0.212049 | M54: 0.212653 | N54: 0.21323 | O54: 0.213857 | P54: 0.214522 | Q54: 0.215274 | R54: 0.216151 | S54: 0.217106 | T54: 0.217986 | U54: 0.218863 | V54: 0.219801 | W54: 0.2208 | X54: 0.221816 | Y54: 0.222833 | Z54: 0.223865 | AA54: 0.224891 | AB54: 0.225923 | AC54: 0.226957 | AD54: 0.227982 | AE54: 0.229024 | AF54: 0.230099 | AG54: 0.231202 | AH54: 0.23232 | AI54: 0.233432 | AJ54: 0.234513 | AK54: 0.235571 | AL54: 0.236617 | AM54: 0.003745
A55: RKI000:ga_ClothesDryers | B55: Clothes Dryers | C55: 0.051087 | D55: 0.051545 | E55: 0.051764 | F55: 0.052008 | G55: 0.052271 | H55: 0.052599 | I55: 0.052932 | J55: 0.053309 | K55: 0.053703 | L55: 0.054085 | M55: 0.054437 | N55: 0.054769 | O55: 0.054929 | P55: 0.055131 | Q55: 0.055414 | R55: 0.055795 | S55: 0.056174 | T55: 0.056556 | U55: 0.056973 | V55: 0.05741 | W55: 0.057825 | X55: 0.058256 | Y55: 0.058704 | Z55: 0.059178 | AA55: 0.059646 | AB55: 0.060134 | AC55: 0.060619 | AD55: 0.061077 | AE55: 0.061514 | AF55: 0.061951 | AG55: 0.062392 | AH55: 0.062844 | AI55: 0.0633 | AJ55: 0.06373 | AK55: 0.064165 | AL55: 0.064593 | AM55: 0.006659
A56: RKI000:ga_OtherNatGas | B56: Other Uses 5/ | C56: 0.248127 | D56: 0.248469 | E56: 0.247135 | F56: 0.245532 | G56: 0.244021 | H56: 0.242715 | I56: 0.241399 | J56: 0.240171 | K56: 0.23899 | L56: 0.23777 | M56: 0.236485 | N56: 0.2352 | O56: 0.233416 | P56: 0.231774 | Q56: 0.230359 | R56: 0.229213 | S56: 0.228111 | T56: 0.227085 | U56: 0.226154 | V56: 0.225161 | W56: 0.223946 | X56: 0.222784 | Y56: 0.221713 | Z56: 0.220743 | AA56: 0.219778 | AB56: 0.21892 | AC56: 0.21806 | AD56: 0.217127 | AE56: 0.216112 | AF56: 0.21507 | AG56: 0.214016 | AH56: 0.212987 | AI56: 0.212001 | AJ56: 0.210979 | AK56: 0.210008 | AL56: 0.209026 | AM56: -0.005071
A57: RKI000:ga_DeliveredEner | B57: Delivered Energy | C57: 4.757174 | D57: 4.563908 | E57: 4.765479 | F57: 4.813304 | G57: 4.802428 | H57: 4.794781 | I57: 4.79133 | J57: 4.792284 | K57: 4.795135 | L57: 4.798526 | M57: 4.79817 | N57: 4.795413 | O57: 4.784097 | P57: 4.772815 | Q57: 4.763848 | R57: 4.758921 | S57: 4.753451 | T57: 4.745883 | U57: 4.739036 | V57: 4.732169 | W57: 4.720896 | X57: 4.710109 | Y57: 4.700832 | Z57: 4.694421 | AA57: 4.689201 | AB57: 4.68798 | AC57: 4.688127 | AD57: 4.687469 | AE57: 4.68657 | AF57: 4.686465 | AG57: 4.686924 | AH57: 4.688098 | AI57: 4.690028 | AJ57: 4.690119 | AK57: 4.690958 | AL57: 4.691435 | AM57: 0.000811
B59: Distillate Fuel Oil
A60: RKI000:ha_SpaceHeating | B60: Space Heating | C60: 0.463082 | D60: 0.381017 | E60: 0.460043 | F60: 0.437505 | G60: 0.424531 | H60: 0.41386 | I60: 0.404445 | J60: 0.395824 | K60: 0.387578 | L60: 0.379716 | M60: 0.371775 | N60: 0.363962 | O60: 0.356564 | P60: 0.349576 | Q60: 0.342729 | R60: 0.335616 | S60: 0.328618 | T60: 0.3217 | U60: 0.315563 | V60: 0.309764 | W60: 0.304188 | X60: 0.298425 | Y60: 0.293046 | Z60: 0.287975 | AA60: 0.282993 | AB60: 0.2782 | AC60: 0.27361 | AD60: 0.269117 | AE60: 0.264725 | AF60: 0.260354 | AG60: 0.256091 | AH60: 0.251756 | AI60: 0.247373 | AJ60: 0.243134 | AK60: 0.239004 | AL60: 0.234875 | AM60: -0.014128
A61: RKI000:ha_WaterHeating | B61: Water Heating | C61: 0.044641 | D61: 0.043057 | E61: 0.040292 | F61: 0.03706 | G61: 0.034129 | H61: 0.0317 | I61: 0.029709 | J61: 0.028076 | K61: 0.026785 | L61: 0.025834 | M61: 0.024839 | N61: 0.023861 | O61: 0.022926 | P61: 0.022048 | Q61: 0.02121 | R61: 0.020391 | S61: 0.019598 | T61: 0.018832 | U61: 0.018129 | V61: 0.017456 | W61: 0.016817 | X61: 0.016193 | Y61: 0.015621 | Z61: 0.015102 | AA61: 0.014627 | AB61: 0.014206 | AC61: 0.013839 | AD61: 0.013517 | AE61: 0.013228 | AF61: 0.012963 | AG61: 0.012719 | AH61: 0.012488 | AI61: 0.012266 | AJ61: 0.012061 | AK61: 0.011869 | AL61: 0.011686 | AM61: -0.03763
A62: RKI000:Other_ha_ha | B62: Other Uses 6/ | C62: 0.00705 | D62: 0.007281 | E62: 0.007295 | F62: 0.007178 | G62: 0.007051 | H62: 0.006972 | I62: 0.006915 | J62: 0.006868 | K62: 0.006823 | L62: 0.006779 | M62: 0.006731 | N62: 0.006684 | O62: 0.006643 | P62: 0.006608 | Q62: 0.006573 | R62: 0.006533 | S62: 0.006489 | T62: 0.006444 | U62: 0.00641 | V62: 0.006376 | W62: 0.006343 | X62: 0.006303 | Y62: 0.006268 | Z62: 0.006236 | AA62: 0.006203 | AB62: 0.00617 | AC62: 0.00614 | AD62: 0.006114 | AE62: 0.006088 | AF62: 0.006061 | AG62: 0.006035 | AH62: 0.006006 | AI62: 0.005976 | AJ62: 0.005948 | AK62: 0.005921 | AL62: 0.005892 | AM62: -0.006204
A63: RKI000:ha_DeliveredEner | B63: Delivered Energy | C63: 0.514773 | D63: 0.431354 | E63: 0.507631 | F63: 0.481744 | G63: 0.465711 | H63: 0.452532 | I63: 0.44107 | J63: 0.430768 | K63: 0.421187 | L63: 0.412329 | M63: 0.403345 | N63: 0.394507 | O63: 0.386133 | P63: 0.378232 | Q63: 0.370512 | R63: 0.362539 | S63: 0.354705 | T63: 0.346976 | U63: 0.340102 | V63: 0.333596 | W63: 0.327347 | X63: 0.320921 | Y63: 0.314935 | Z63: 0.309314 | AA63: 0.303823 | AB63: 0.298575 | AC63: 0.29359 | AD63: 0.288747 | AE63: 0.284041 | AF63: 0.279378 | AG63: 0.274844 | AH63: 0.270251 | AI63: 0.265616 | AJ63: 0.261144 | AK63: 0.256794 | AL63: 0.252453 | AM63: -0.015632
B65: Propane
A66: RKI000:ia_SpaceHeating | B66: Space Heating | C66: 0.341401 | D66: 0.299716 | E66: 0.32496 | F66: 0.326645 | G66: 0.321761 | H66: 0.317796 | I66: 0.31451 | J66: 0.310488 | K66: 0.306342 | L66: 0.302754 | M66: 0.299765 | N66: 0.296874 | O66: 0.293845 | P66: 0.290861 | Q66: 0.288088 | R66: 0.285417 | S66: 0.28234 | T66: 0.279063 | U66: 0.276201 | V66: 0.273603 | W66: 0.271222 | X66: 0.268648 | Y66: 0.266185 | Z66: 0.263612 | AA66: 0.260864 | AB66: 0.258301 | AC66: 0.255804 | AD66: 0.253456 | AE66: 0.25114 | AF66: 0.248897 | AG66: 0.246767 | AH66: 0.244607 | AI66: 0.242415 | AJ66: 0.240148 | AK66: 0.237975 | AL66: 0.235788 | AM66: -0.007031
A67: RKI000:ia_WaterHeating | B67: Water Heating | C67: 0.060069 | D67: 0.059111 | E67: 0.057686 | F67: 0.05566 | G67: 0.053911 | H67: 0.052448 | I67: 0.051315 | J67: 0.050314 | K67: 0.049471 | L67: 0.048832 | M67: 0.048126 | N67: 0.047367 | O67: 0.046506 | P67: 0.045599 | Q67: 0.044694 | R67: 0.043765 | S67: 0.042763 | T67: 0.041725 | U67: 0.040736 | V67: 0.039782 | W67: 0.038884 | X67: 0.037994 | Y67: 0.037168 | Z67: 0.036408 | AA67: 0.035708 | AB67: 0.035123 | AC67: 0.034627 | AD67: 0.034218 | AE67: 0.033866 | AF67: 0.033564 | AG67: 0.03331 | AH67: 0.033079 | AI67: 0.032862 | AJ67: 0.032649 | AK67: 0.032461 | AL67: 0.032288 | AM67: -0.017629
A68: RKI000:ia_Cooking | B68: Cooking | C68: 0.02822 | D68: 0.027886 | E68: 0.027591 | F68: 0.027326 | G68: 0.027069 | H68: 0.026817 | I68: 0.026573 | J68: 0.026348 | K68: 0.026133 | L68: 0.025924 | M68: 0.025714 | N68: 0.02549 | O68: 0.02529 | P68: 0.02511 | Q68: 0.024956 | R68: 0.024832 | S68: 0.02474 | T68: 0.024635 | U68: 0.02453 | V68: 0.024433 | W68: 0.024344 | X68: 0.024255 | Y68: 0.024165 | Z68: 0.024079 | AA68: 0.023992 | AB68: 0.023905 | AC68: 0.023814 | AD68: 0.023722 | AE68: 0.023628 | AF68: 0.023536 | AG68: 0.023445 | AH68: 0.023358 | AI68: 0.023279 | AJ68: 0.023204 | AK68: 0.023135 | AL68: 0.023071 | AM68: -0.00556
A69: RKI000:ia_OtherUses | B69: Other Uses 6/ | C69: 0.043472 | D69: 0.045084 | E69: 0.046261 | F69: 0.046886 | G69: 0.04753 | H69: 0.048302 | I69: 0.049156 | J69: 0.049955 | K69: 0.050737 | L69: 0.051561 | M69: 0.052445 | N69: 0.053335 | O69: 0.054176 | P69: 0.054999 | Q69: 0.055834 | R69: 0.056662 | S69: 0.057415 | T69: 0.058119 | U69: 0.058876 | V69: 0.059667 | W69: 0.060501 | X69: 0.061307 | Y69: 0.062129 | Z69: 0.062942 | AA69: 0.063721 | AB69: 0.064533 | AC69: 0.06536 | AD69: 0.066215 | AE69: 0.067079 | AF69: 0.067964 | AG69: 0.068881 | AH69: 0.069803 | AI69: 0.070717 | AJ69: 0.07161 | AK69: 0.07252 | AL69: 0.073424 | AM69: 0.014448
A70: RKI000:ia_DeliveredEner | B70: Delivered Energy | C70: 0.473162 | D70: 0.431797 | E70: 0.456497 | F70: 0.456517 | G70: 0.450271 | H70: 0.445362 | I70: 0.441554 | J70: 0.437106 | K70: 0.432684 | L70: 0.429072 | M70: 0.42605 | N70: 0.423066 | O70: 0.419817 | P70: 0.416569 | Q70: 0.413573 | R70: 0.410677 | S70: 0.407258 | T70: 0.403542 | U70: 0.400343 | V70: 0.397485 | W70: 0.39495 | X70: 0.392204 | Y70: 0.389648 | Z70: 0.387041 | AA70: 0.384285 | AB70: 0.381862 | AC70: 0.379606 | AD70: 0.377611 | AE70: 0.375713 | AF70: 0.373961 | AG70: 0.372403 | AH70: 0.370847 | AI70: 0.369273 | AJ70: 0.367611 | AK70: 0.366091 | AL70: 0.36457 | AM70: -0.004965
A72: RKI000:ja_MarketedRenew | B72: Marketed Renewables (wood) 7/ | C72: 0.440932 | D72: 0.373338 | E72: 0.382023 | F72: 0.399918 | G72: 0.411374 | H72: 0.41363 | I72: 0.411704 | J72: 0.407837 | K72: 0.403628 | L72: 0.399409 | M72: 0.395798 | N72: 0.392024 | O72: 0.387317 | P72: 0.381188 | Q72: 0.37527 | R72: 0.370244 | S72: 0.366117 | T72: 0.362504 | U72: 0.357335 | V72: 0.35266 | W72: 0.348059 | X72: 0.345057 | Y72: 0.341559 | Z72: 0.337991 | AA72: 0.335112 | AB72: 0.332439 | AC72: 0.329152 | AD72: 0.325441 | AE72: 0.321761 | AF72: 0.318272 | AG72: 0.314918 | AH72: 0.311896 | AI72: 0.309358 | AJ72: 0.306477 | AK72: 0.303598 | AL72: 0.301033 | AM72: -0.006311
A73: RKI000:ja_OtherFuels | B73: Kerosene | C73: 0.009758 | D73: 0.009758 | E73: 0.011269 | F73: 0.010637 | G73: 0.010123 | H73: 0.009748 | I73: 0.009464 | J73: 0.009216 | K73: 0.008989 | L73: 0.008781 | M73: 0.008574 | N73: 0.008368 | O73: 0.008168 | P73: 0.007984 | Q73: 0.007804 | R73: 0.007617 | S73: 0.007427 | T73: 0.007237 | U73: 0.007069 | V73: 0.006909 | W73: 0.006757 | X73: 0.0066 | Y73: 0.006454 | Z73: 0.006315 | AA73: 0.006178 | AB73: 0.006045 | AC73: 0.00592 | AD73: 0.005799 | AE73: 0.005681 | AF73: 0.005564 | AG73: 0.005449 | AH73: 0.005332 | AI73: 0.005213 | AJ73: 0.005098 | AK73: 0.004986 | AL73: 0.004875 | AM73: -0.020203
B75: Delivered Energy Consumption by End Use
A76: RKI000:ka_SpaceHeating | B76: Space Heating | C76: 4.604874 | D76: 4.209844 | E76: 4.550833 | F76: 4.605039 | G76: 4.583626 | H76: 4.55753 | I76: 4.53145 | J76: 4.505191 | K76: 4.479831 | L76: 4.457197 | M76: 4.4342 | N76: 4.409664 | O76: 4.380695 | P76: 4.351151 | Q76: 4.323893 | R76: 4.300618 | S76: 4.278604 | T76: 4.256376 | U76: 4.235342 | V76: 4.216606 | W76: 4.195526 | X76: 4.176435 | Y76: 4.158358 | Z76: 4.141437 | AA76: 4.124749 | AB76: 4.110062 | AC76: 4.094557 | AD76: 4.077002 | AE76: 4.058712 | AF76: 4.040754 | AG76: 4.023289 | AH76: 4.006301 | AI76: 3.990368 | AJ76: 3.972912 | AK76: 3.956301 | AL76: 3.939848 | AM76: -0.001948
A77: RKI000:ka_SpaceCooling | B77: Space Cooling | C77: 0.81741 | D77: 0.867148 | E77: 0.755645 | F77: 0.782887 | G77: 0.784262 | H77: 0.782837 | I77: 0.78283 | J77: 0.781494 | K77: 0.781601 | L77: 0.784343 | M77: 0.786754 | N77: 0.789338 | O77: 0.792837 | P77: 0.797361 | Q77: 0.802426 | R77: 0.80746 | S77: 0.813477 | T77: 0.819079 | U77: 0.825068 | V77: 0.831143 | W77: 0.836969 | X77: 0.842503 | Y77: 0.847606 | Z77: 0.853019 | AA77: 0.858057 | AB77: 0.862583 | AC77: 0.86688 | AD77: 0.8709 | AE77: 0.874038 | AF77: 0.876727 | AG77: 0.879142 | AH77: 0.8813 | AI77: 0.882924 | AJ77: 0.883173 | AK77: 0.882756 | AL77: 0.88189 | AM77: 0.000496
A78: RKI000:ka_WaterHeating | B78: Water Heating | C78: 1.763412 | D78: 1.771377 | E78: 1.772123 | F78: 1.772195 | G78: 1.773084 | H78: 1.772762 | I78: 1.77639 | J78: 1.781616 | K78: 1.788717 | L78: 1.797625 | M78: 1.803908 | N78: 1.808599 | O78: 1.809548 | P78: 1.810293 | Q78: 1.811218 | R78: 1.811974 | S78: 1.81119 | T78: 1.808687 | U78: 1.804977 | V78: 1.800001 | W78: 1.792986 | X78: 1.785609 | Y78: 1.77905 | Z78: 1.774759 | AA78: 1.772888 | AB78: 1.774335 | AC78: 1.778477 | AD78: 1.784178 | AE78: 1.790826 | AF78: 1.798323 | AG78: 1.806307 | AH78: 1.814646 | AI78: 1.823087 | AJ78: 1.83079 | AK78: 1.838508 | AL78: 1.845955 | AM78: 0.001214
A79: RKI000:ka_Refrigeration | B79: Refrigeration | C79: 0.355201 | D79: 0.35081 | E79: 0.346875 | F79: 0.343662 | G79: 0.340835 | H79: 0.338432 | I79: 0.336455 | J79: 0.334212 | K79: 0.332347 | L79: 0.330892 | M79: 0.329846 | N79: 0.329135 | O79: 0.328747 | P79: 0.328678 | Q79: 0.329 | R79: 0.32979 | S79: 0.330945 | T79: 0.332402 | U79: 0.334299 | V79: 0.336792 | W79: 0.339898 | X79: 0.343507 | Y79: 0.347132 | Z79: 0.350793 | AA79: 0.354434 | AB79: 0.358071 | AC79: 0.361684 | AD79: 0.365255 | AE79: 0.368825 | AF79: 0.37242 | AG79: 0.376024 | AH79: 0.379613 | AI79: 0.383152 | AJ79: 0.386586 | AK79: 0.389937 | AL79: 0.39322 | AM79: 0.003362
A80: RKI000:ka_Cooking | B80: Cooking | C80: 0.344572 | D80: 0.345141 | E80: 0.346268 | F80: 0.347791 | G80: 0.349385 | H80: 0.351068 | I80: 0.352839 | J80: 0.354743 | K80: 0.356713 | L80: 0.358731 | M80: 0.360726 | N80: 0.362629 | O80: 0.364548 | P80: 0.366466 | Q80: 0.368472 | R80: 0.370639 | S80: 0.372883 | T80: 0.374974 | U80: 0.377063 | V80: 0.379277 | W80: 0.381614 | X80: 0.383978 | Y80: 0.386339 | Z80: 0.388727 | AA80: 0.391096 | AB80: 0.393466 | AC80: 0.395827 | AD80: 0.398166 | AE80: 0.400529 | AF80: 0.402947 | AG80: 0.405406 | AH80: 0.407893 | AI80: 0.410376 | AJ80: 0.412805 | AK80: 0.415203 | AL80: 0.417583 | AM80: 0.00562
A81: RKI000:ka_ClothesDryers | B81: Clothes Dryers | C81: 0.255722 | D81: 0.258429 | E81: 0.261059 | F81: 0.264047 | G81: 0.266328 | H81: 0.267741 | I81: 0.269148 | J81: 0.270339 | K81: 0.271744 | L81: 0.273832 | M81: 0.27591 | N81: 0.277825 | O81: 0.279707 | P81: 0.281828 | Q81: 0.28415 | R81: 0.286712 | S81: 0.289323 | T81: 0.291956 | U81: 0.294752 | V81: 0.29772 | W81: 0.300659 | X81: 0.303647 | Y81: 0.306707 | Z81: 0.309845 | AA81: 0.312977 | AB81: 0.316137 | AC81: 0.319297 | AD81: 0.322343 | AE81: 0.325275 | AF81: 0.328163 | AG81: 0.331021 | AH81: 0.333887 | AI81: 0.336722 | AJ81: 0.339422 | AK81: 0.342078 | AL81: 0.344677 | AM81: 0.008506
A82: RKI000:ka_Freezers | B82: Freezers | C82: 0.07543 | D82: 0.074619 | E82: 0.073888 | F82: 0.073192 | G82: 0.072462 | H82: 0.071706 | I82: 0.070935 | J82: 0.070168 | K82: 0.069453 | L82: 0.068787 | M82: 0.068159 | N82: 0.067552 | O82: 0.066966 | P82: 0.0664 | Q82: 0.065872 | R82: 0.065407 | S82: 0.064986 | T82: 0.064596 | U82: 0.064264 | V82: 0.064015 | W82: 0.063865 | X82: 0.063791 | Y82: 0.0638 | Z82: 0.063906 | AA82: 0.064104 | AB82: 0.064395 | AC82: 0.064768 | AD82: 0.065146 | AE82: 0.065538 | AF82: 0.065951 | AG82: 0.066383 | AH82: 0.06683 | AI82: 0.067283 | AJ82: 0.067733 | AK82: 0.068182 | AL82: 0.068633 | AM82: -0.002456
A83: RKI000:ka_Lighting | B83: Lighting | C83: 0.448123 | D83: 0.441566 | E83: 0.435892 | F83: 0.434207 | G83: 0.424534 | H83: 0.373465 | I83: 0.342323 | J83: 0.318797 | K83: 0.303977 | L83: 0.294402 | M83: 0.287885 | N83: 0.282972 | O83: 0.279133 | P83: 0.276178 | Q83: 0.273961 | R83: 0.264825 | S83: 0.25764 | T83: 0.252522 | U83: 0.249772 | V83: 0.249398 | W83: 0.249332 | X83: 0.249677 | Y83: 0.250358 | Z83: 0.251256 | AA83: 0.252238 | AB83: 0.248426 | AC83: 0.245436 | AD83: 0.243001 | AE83: 0.241185 | AF83: 0.240336 | AG83: 0.240358 | AH83: 0.2406 | AI83: 0.240962 | AJ83: 0.241355 | AK83: 0.241794 | AL83: 0.242266 | AM83: -0.017501
A84: RKI000:ka_ClothesWasher | B84: Clothes Washers 1/ | C84: 0.026497 | D84: 0.025667 | E84: 0.024887 | F84: 0.023776 | G84: 0.02266 | H84: 0.021433 | I84: 0.020162 | J84: 0.019082 | K84: 0.018184 | L84: 0.017458 | M84: 0.016899 | N84: 0.016508 | O84: 0.016292 | P84: 0.016259 | Q84: 0.016195 | R84: 0.016114 | S84: 0.01603 | T84: 0.015958 | U84: 0.015923 | V84: 0.015941 | W84: 0.016011 | X84: 0.016119 | Y84: 0.016252 | Z84: 0.0164 | AA84: 0.016553 | AB84: 0.016707 | AC84: 0.016862 | AD84: 0.017015 | AE84: 0.01717 | AF84: 0.017327 | AG84: 0.017485 | AH84: 0.017645 | AI84: 0.017804 | AJ84: 0.01796 | AK84: 0.018114 | AL84: 0.018267 | AM84: -0.009953
A85: RKI000:ka_Dishwashers | B85: Dishwashers 1/ | C85: 0.094424 | D85: 0.094505 | E85: 0.094796 | F85: 0.095229 | G85: 0.095648 | H85: 0.096045 | I85: 0.09644 | J85: 0.097098 | K85: 0.098031 | L85: 0.099282 | M85: 0.100798 | N85: 0.102534 | O85: 0.104483 | P85: 0.106602 | Q85: 0.108585 | R85: 0.110437 | S85: 0.112132 | T85: 0.11367 | U85: 0.115158 | V85: 0.116683 | W85: 0.118256 | X85: 0.119853 | Y85: 0.121467 | Z85: 0.123111 | AA85: 0.124761 | AB85: 0.126427 | AC85: 0.128099 | AD85: 0.129763 | AE85: 0.13143 | AF85: 0.133109 | AG85: 0.134785 | AH85: 0.136453 | AI85: 0.138095 | AJ85: 0.139687 | AK85: 0.141238 | AL85: 0.142754 | AM85: 0.012205
A86: RKI000:ka_ColorTelevisi | B86: Televisions and Related Equipment 2/ | C86: 0.288212 | D86: 0.282494 | E86: 0.2774 | F86: 0.273162 | G86: 0.26852 | H86: 0.263822 | I86: 0.259875 | J86: 0.256199 | K86: 0.253304 | L86: 0.251986 | M86: 0.251491 | N86: 0.251538 | O86: 0.252468 | P86: 0.25441 | Q86: 0.257082 | R86: 0.260393 | S86: 0.264374 | T86: 0.268873 | U86: 0.273967 | V86: 0.279572 | W86: 0.285348 | X86: 0.291337 | Y86: 0.297421 | Z86: 0.303437 | AA86: 0.309231 | AB86: 0.314683 | AC86: 0.317851 | AD86: 0.320415 | AE86: 0.322613 | AF86: 0.324784 | AG86: 0.326932 | AH86: 0.329083 | AI86: 0.331172 | AJ86: 0.333129 | AK86: 0.335039 | AL86: 0.336865 | AM86: 0.005191
A87: RKI000:ka_PersonalCompu | B87: Computers and Related Equipment 3/ | C87: 0.111117 | D87: 0.107827 | E87: 0.104646 | F87: 0.101712 | G87: 0.098496 | H87: 0.095143 | I87: 0.091913 | J87: 0.088654 | K87: 0.085554 | L87: 0.082878 | M87: 0.08035 | N87: 0.077899 | O87: 0.07563 | P87: 0.073536 | Q87: 0.071573 | R87: 0.069687 | S87: 0.067884 | T87: 0.066139 | U87: 0.064451 | V87: 0.062801 | W87: 0.06113 | X87: 0.059417 | Y87: 0.057759 | Z87: 0.056146 | AA87: 0.054541 | AB87: 0.052936 | AC87: 0.051434 | AD87: 0.049901 | AE87: 0.048327 | AF87: 0.046734 | AG87: 0.045077 | AH87: 0.043361 | AI87: 0.041551 | AJ87: 0.039626 | AK87: 0.03757 | AL87: 0.035389 | AM87: -0.032238
... A92: RKI000:la_ElectricityRe | B92: Electricity Related Losses | C92: 9.569791 | D92: 9.386479 | E92: 9.370535 | F92: 9.384474 | G92: 9.405828 | H92: 9.347047 | I92: 9.280358 | J92: 9.219619 | K92: 9.190005 | L92: 9.150984 | M92: 9.097077 | N92: 9.018094 | O92: 8.975627 | P92: 8.940907 | Q92: 8.925586 | R92: 8.904574 | S92: 8.902377 | T92: 8.889162 | U92: 8.917674 | V92: 8.904959 | W92: 8.878765 | X92: 8.913216 | Y92: 8.897772 | Z92: 8.914825 | AA92: 8.932128 | AB92: 8.960385 | AC92: 8.96512 | AD92: 8.972742 | AE92: 8.988356 | AF92: 8.982656 | AG92: 8.951747 | AH92: 8.935314 | AI92: 8.909016 | AJ92: 8.891896 | AK92: 8.883463 | AL92: 8.821958 | AM92: -0.001823
B94: Total Energy Consumption by End Use
A95: RKI000:ma_SpaceHeating | B95: Space Heating | C95: 5.268241 | D95: 4.849652 | E95: 5.236599 | F95: 5.305098 | G95: 5.283724 | H95: 5.256125 | I95: 5.224988 | J95: 5.19224 | K95: 5.161564 | L95: 5.13305 | M95: 5.102129 | N95: 5.067314 | O95: 5.030704 | P95: 4.993675 | Q95: 4.960332 | R95: 4.931818 | S95: 4.905473 | T95: 4.877793 | U95: 4.853668 | V95: 4.828734 | W95: 4.800081 | X95: 4.777699 | Y95: 4.753046 | Z95: 4.731459 | AA95: 4.710371 | AB95: 4.692842 | AC95: 4.673488 | AD95: 4.652143 | AE95: 4.630694 | AF95: 4.608259 | AG95: 4.584851 | AH95: 4.56287 | AI95: 4.541918 | AJ95: 4.520416 | AK95: 4.500524 | AL95: 4.477851 | AM95: -0.002343
A96: RKI000:ma_SpaceCooling | B96: Space Cooling | C96: 2.408715 | D96: 2.512719 | E96: 2.195516 | F96: 2.260591 | G96: 2.269943 | H96: 2.273883 | I96: 2.272711 | J96: 2.26714 | K96: 2.267104 | L96: 2.268068 | M96: 2.264536 | N96: 2.257549 | O96: 2.257551 | P96: 2.259714 | Q96: 2.266055 | R96: 2.273887 | S96: 2.28631 | T96: 2.294811 | U96: 2.309582 | V96: 2.316123 | W96: 2.319637 | X96: 2.332221 | Y96: 2.335111 | Z96: 2.343639 | AA96: 2.351417 | AB96: 2.361386 | AC96: 2.36799 | AD96: 2.374475 | AE96: 2.380298 | AF96: 2.381475 | AG96: 2.377711 | AH96: 2.376056 | AI96: 2.372265 | AJ96: 2.367709 | AK96: 2.363313 | AL96: 2.349587 | AM96: -0.001972
A97: RKI000:ma_WaterHeating | B97: Water Heating | C97: 2.666933 | D97: 2.66032 | E97: 2.673518 | F97: 2.672441 | G97: 2.681228 | H97: 2.685337 | I97: 2.689156 | J97: 2.692715 | K97: 2.699424 | L97: 2.706035 | M97: 2.707633 | N97: 2.70436 | O97: 2.700288 | P97: 2.69592 | Q97: 2.693214 | R97: 2.6905 | S97: 2.687063 | T97: 2.679965 | U97: 2.673964 | V97: 2.661279 | W97: 2.644436 | X97: 2.63283 | Y97: 2.617745 | Z97: 2.608674 | AA97: 2.603496 | AB97: 2.604869 | AC97: 2.608663 | AD97: 2.615046 | AE97: 2.623626 | AF97: 2.631282 | AG97: 2.637054 | AH97: 2.644719 | AI97: 2.651956 | AJ97: 2.659749 | AK97: 2.668476 | AL97: 2.672121 | AM97: 0.00013
A98: RKI000:ma_Refrigeration | B98: Refrigeration | C98: 1.066866 | D98: 1.03531 | E98: 1.026782 | F98: 1.010659 | G98: 1.004718 | H98: 1.001102 | I98: 0.994586 | J98: 0.98709 | K98: 0.981278 | L98: 0.973725 | M98: 0.965898 | N98: 0.957413 | O98: 0.951776 | P98: 0.946801 | Q98: 0.944132 | R98: 0.943524 | S98: 0.944748 | T98: 0.945714 | U98: 0.950103 | V98: 0.952675 | W98: 0.956005 | X98: 0.964849 | Y98: 0.970172 | Z98: 0.977582 | AA98: 0.985046 | AB98: 0.99402 | AC98: 1.001758 | AD98: 1.009633 | AE98: 1.01825 | AF98: 1.025445 | AG98: 1.030799 | AH98: 1.037295 | AI98: 1.043307 | AJ98: 1.0503 | AK98: 1.057924 | AL98: 1.061636 | AM98: 0.000739
A99: RKI000:ma_Cooking | B99: Cooking | C99: 0.560779 | D99: 0.557579 | E99: 0.56206 | F99: 0.56417 | G99: 0.569328 | H99: 0.57507 | I99: 0.579614 | J99: 0.584325 | K99: 0.58933 | L99: 0.593329 | M99: 0.596674 | N99: 0.599156 | O99: 0.602201 | P99: 0.604991 | Q99: 0.608247 | R99: 0.611926 | S99: 0.615917 | T99: 0.619178 | U99: 0.623294 | V99: 0.626227 | W99: 0.628982 | X99: 0.633426 | Y99: 0.63643 | Z99: 0.640275 | AA99: 0.644123 | AB99: 0.648575 | AC99: 0.652532 | AD99: 0.656552 | AE99: 0.66091 | AF99: 0.664759 | AG99: 0.667925 | AH99: 0.671605 | AI99: 0.675134 | AJ99: 0.67907 | AK99: 0.683292 | AL99: 0.685982 | AM99: 0.006114
A100: RKI000:ma_ClothesDryers | B100: Clothes Dryers | C100: 0.665719 | D100: 0.662099 | E100: 0.671298 | F100: 0.675583 | G100: 0.683272 | H100: 0.689003 | I100: 0.692084 | J100: 0.694303 | K100: 0.697485 | L100: 0.70074 | M100: 0.702981 | N100: 0.703612 | O100: 0.705698 | P100: 0.708162 | Q100: 0.711818 | R100: 0.716443 | S100: 0.721743 | T100: 0.726288 | U100: 0.732759 | V100: 0.73717 | W100: 0.740824 | X100: 0.747515 | Y100: 0.751828 | Z100: 0.757731 | AA100: 0.763706 | AB100: 0.770811 | AC100: 0.777081 | AD100: 0.783265 | AE100: 0.789703 | AF100: 0.794954 | AG100: 0.798787 | AH100: 0.803472 | AI100: 0.807818 | AJ100: 0.812746 | AK100: 0.818159 | AL100: 0.820776 | AM100: 0.006339
A101: RKI000:ma_Freezers | B101: Freezers | C101: 0.226559 | D101: 0.220215 | E101: 0.218715 | F101: 0.215245 | G101: 0.213605 | H101: 0.212111 | I101: 0.209688 | J101: 0.207241 | K101: 0.205063 | L101: 0.202423 | M101: 0.199592 | N101: 0.196501 | O101: 0.193877 | P101: 0.191275 | Q101: 0.189032 | R101: 0.18713 | S101: 0.185516 | T101: 0.183781 | U101: 0.182644 | V101: 0.181079 | W101: 0.179627 | X101: 0.179177 | Y101: 0.178311 | Z101: 0.178093 | AA101: 0.178157 | AB101: 0.178765 | AC101: 0.179388 | AD101: 0.180074 | AE101: 0.180936 | AF101: 0.181593 | AG101: 0.181977 | AH101: 0.182612 | AI101: 0.183209 | AJ101: 0.184022 | AK101: 0.184983 | AL101: 0.1853 | AM101: -0.005064
