Workbook
Name Fraction_coal: [1]About!$C$50
Name Percent_rural: [1]About!$A$77
Name Percent_urban: [1]About!$A$76
Name quadrillion: [1]About!$B$79
Name Table4: #REF!
Name Table5: #REF!

Sheet About
A1: ICpUEfEBE Incremental Cost per Unit Energy for Electrified Building Equipment
A3: Sources: | B3: Cost of technologies except commerial heat pumps | D3: Commercial heating and water heating heat pump costs
B4: EIA | D4: NREL
B5: 2018 | D5: 2018
B6: Updated Buildings Sector Appliance and Equipment Costs and Efficiencies | D6: Electrification Futures Study Technology Report Figure Data
B7: https://www.eia.gov/analysis/studies/buildings/equipcosts/pdf/full.pdf | D7: https://data.nrel.gov/system/files/93/EFS_70485_figure_data.xlsx
B8: p. 9, 12, 29, 46, 51, 54, 58, 90, 92, 120, 123 | D8: Tables 22 and 23
B10: Residential building equipment stock and average annual energy consumption | D10: Commercial building equipment load factors
B11: EIA | D11: NREL
B12: 2021 | D12: 2018
B13: AEO 2021 | D13: Electrification Futures Study: End-Use Electric Technology Cost and Performance Projections through 2050
B14: https://www.eia.gov/outlooks/aeo/tables_side.php | D14: https://www.nrel.gov/docs/fy18osti/70485.pdf
B15: Tables 4 and 21 | D15: P.90
A17: Notes:
A18: All policy-driven electrification in the EPS is assumed to rely on heat pumps,
A19: not electric resistance heating
A21: Methodology:
A22: For residential buildings, we calculate the average energy used by equipment
A23: of different types, which allows us to find a $/BTU value. We then estimate
A24: the cost of switching to heat pump equipment based on the data from EIA
A25: and annual energy consumption.
A27: For commercial buildings, we lack data on annual energy use, but the NREL
A28: report provides data on annual heating and water heating utilization rates
A29: and the costs are normalized to $/(kBTU/hr) input, so we standardize the costs
A30: from EIA and then estimate the cost per BTU shifted using the annual load factors.
... A52: 2017 to 2012 USD
A53: 0.9366596
A54: 2016 to 2012 USD
A55: 0.95661377

Sheet EIA Costs
A1: Residential Gas Fired Furnaces
A2: DATA | B2: 2009 | C2: 2015 | D2: 2017 | H2: 2020 | J2: 2030 | L2: 2040 | N2: 2050 | P2: 2060
B3: Installed Base | C3: Installed Base | D3: Current Standard | E3: Typical | F3: ENERGY STAR (South) | G3: High | H3: Typical | I3: High | J3: Typical | K3: High | L3: Typical | M3: High | N3: Typical | O3: High | P3: Typical | Q3: High
A4: Typical Input Capacity (kBtu/h) | B4: 80 | C4: 80 | D4: 80 | E4: 80 | F4: 80 | G4: 80 | H4: 80 | I4: 80 | J4: 80 | K4: 80 | L4: 80 | M4: 80 | N4: 80 | O4: 80 | P4: 80 | Q4: 80
A5: AFUE (%) | B5: 80 | C5: 80 | D5: 80 | E5: 80 | F5: 90 | G5: 99 | H5: 80 | I5: 99 | J5: 80 | K5: 99 | L5: 80 | M5: 99 | N5: 80 | O5: 99 | P5: 80 | Q5: 99
A6: Electric Consumption (kWh/yr)* | B6: 548 | C6: 522 | D6: 470 | E6: 470 | F6: 408 | G6: 418 | H6: 329 | I6: 334 | J6: 329 | K6: 334 | L6: 329 | M6: 334 | N6: 329 | O6: 334 | P6: 329 | Q6: 334
A7: Average Life (yrs)** | B7: 16 | C7: 16 | D7: 16 | E7: 16 | F7: 16 | G7: 16 | H7: 16 | I7: 16 | J7: 16 | K7: 16 | L7: 16 | M7: 16 | N7: 16 | O7: 16 | P7: 16 | Q7: 16
B8: 27 | C8: 27 | D8: 27 | E8: 27 | F8: 27 | G8: 27 | H8: 27 | I8: 27 | J8: 27 | K8: 27 | L8: 27 | M8: 27 | N8: 27 | O8: 27 | P8: 27 | Q8: 27
A9: Retail Equipment Cost (2017$) | B9: 840 | C9: 860 | D9: 890 | E9: 890 | F9: 1150 | G9: 1620 | H9: 1080 | I9: 1620 | J9: 1080 | K9: 1620 | L9: 1080 | M9: 1620 | N9: 1080 | O9: 1620 | P9: 1080 | Q9: 1620
A10: Total Installed Cost (2017$) | B10: 2000 | C10: 2020 | D10: 2050 | E10: 2050 | F10: 2560 | G10: 3040 | H10: 2240 | I10: 3040 | J10: 2240 | K10: 3040 | L10: 2240 | M10: 3040 | N10: 2240 | O10: 3040 | P10: 2240 | Q10: 3040
A11: Annual Maintenance Cost (2017$) | B11: 40 | C11: 40 | D11: 40 | E11: 40 | F11: 40 | G11: 40 | H11: 40 | I11: 40 | J11: 40 | K11: 40 | L11: 40 | M11: 40 | N11: 40 | O11: 40 | P11: 40 | Q11: 40
A13: Residential Oil Fired Furnaces
A14: DATA | B14: 2009 | C14: 2015 | D14: 2017 | H14: 2020 | J14: 2030 | L14: 2040 | N14: 2050 | P14: 2060
B15: Installed Base | C15: Installed Base | D15: Current Standard | E15: Typical | F15: ENERGY STAR | G15: High | H15: Typical | I15: High Typical | K15: High | L15: Typical | M15: High | N15: Typical | O15: High | P15: Typical | Q15: High
A16: Typical Input Capacity (kBtu/h) | B16: 105 | C16: 105 | D16: 105 | E16: 105 | F16: 105 | G16: 105 | H16: 105 | I16: 105 | J16: 105 | K16: 105 | L16: 105 | M16: 105 | N16: 105 | O16: 105 | P16: 105 | Q16: 105
A17: AFUE (%) | B17: 80 | C17: 83 | D17: 83 | E17: 83 | F17: 85 | G17: 97 | H17: 83 | I17: 97 | J17: 84 | K17: 97 | L17: 84 | M17: 97 | N17: 84 | O17: 97 | P17: 84 | Q17: 97
A18: Electric Consumption (kWh/yr)* | B18: 490 | C18: 477 | D18: 477 | E18: 477 | F18: 466 | G18: 410 | H18: 477 | I18: 410 | J18: 472 | K18: 410 | L18: 472 | M18: 410 | N18: 472 | O18: 410 | P18: 472 | Q18: 410
A19: Average Life (yrs)** | B19: 20 | C19: 20 | D19: 20 | E19: 20 | F19: 20 | G19: 20 | H19: 20 | I19: 20 | J19: 20 | K19: 20 | L19: 20 | M19: 20 | N19: 20 | O19: 20 | P19: 20 | Q19: 20
B20: 33 | C20: 33 | D20: 33 | E20: 33 | F20: 33 | G20: 33 | H20: 33 | I20: 33 | J20: 33 | K20: 33 | L20: 33 | M20: 33 | N20: 33 | O20: 33 | P20: 33 | Q20: 33
A21: Retail Equipment Cost (2017$) | B21: 2150 | C21: 2200 | D21: 2200 | E21: 2200 | F21: 2250 | G21: 2700 | H21: 2200 | I21: 2700 | J21: 2250 | K21: 2700 | L21: 2250 | M21: 2700 | N21: 2250 | O21: 2700 | P21: 2250 | Q21: 2700
B22: 2350 | C22: 2900 | D22: 2900 | E22: 2900 | F22: 2950 | G22: 3450 | H22: 2900 | I22: 3450 | J22: 2950 | K22: 3450 | L22: 2950 | M22: 3450 | N22: 2950 | O22: 3450 | P22: 2950 | Q22: 3450
A23: Total Installed Cost (2017$) | B23: 2700 | C23: 2750 | D23: 2750 | E23: 2750 | F23: 2950 | G23: 4350 | H23: 2750 | I23: 4350 | J23: 2750 | K23: 4350 | L23: 2750 | M23: 4350 | N23: 2750 | O23: 4350 | P23: 2750 | Q23: 4350
B24: 3400 | C24: 5500 | D24: 5500 | E24: 5500 | F24: 5750 | G24: 8550 | H24: 5500 | I24: 8550 | J24: 5700 | K24: 8550 | L24: 5700 | M24: 8550 | N24: 5700 | O24: 8550 | P24: 5700 | Q24: 8550
A25: Annual Maintenance Cost (2017$) | B25: 70 | C25: 70 | D25: 70 | E25: 70 | F25: 70 | G25: 200 | H25: 70 | I25: 200 | J25: 70 | K25: 200 | L25: 70 | M25: 200 | N25: 70 | O25: 200 | P25: 70 | Q25: 200
A27: Residential Wood Pellet Stoves
A28: DATA | B28: 2009 | C28: 2015 | D28: 2017 | F28: 2020 | H28: 2030 | J28: 2040 | L28: 2050 | N28: 2060
B29: Installed Base | C29: Installed Base | D29: Typical | E29: High | F29: Typical | G29: High | H29: Typical | I29: High | J29: Typical | K29: High | L29: Typical | M29: High | N29: Typical | O29: High
A30: Typical Capacity (kBtu/h) | B30: 50 | C30: 50 | D30: 50 | E30: 50 | F30: 50 | G30: 50 | H30: 50 | I30: 50 | J30: 50 | K30: 50 | L30: 50 | M30: 50 | N30: 50 | O30: 50
A31: Efficiency (HHV) | B31: 65 | C31: 70 | D31: 76 | E31: 87 | F31: 76 | G31: 87 | H31: 77 | I31: 87 | J31: 78 | K31: 88 | L31: 79 | M31: 89 | N31: 79 | O31: 89
A32: Annual Electricity Consumption (kWh) | B32: 600 | C32: 600 | D32: 600 | E32: 600 | F32: 600 | G32: 600 | H32: 600 | I32: 600 | J32: 600 | K32: 600 | L32: 600 | M32: 600 | N32: 600 | O32: 600
A33: Average Life (yrs) | B33: 12 | C33: 12 | D33: 12 | E33: 12 | F33: 12 | G33: 12 | H33: 12 | I33: 12 | J33: 12 | K33: 12 | L33: 12 | M33: 12 | N33: 12 | O33: 12
B34: 25 | C34: 25 | D34: 25 | E34: 25 | F34: 25 | G34: 25 | H34: 25 | I34: 25 | J34: 25 | K34: 25 | L34: 25 | M34: 25 | N34: 25 | O34: 25
A35: Retail Equipment Cost (2017$) | B35: 3300 | C35: 3300 | D35: 3300 | E35: 4000 | F35: 3300 | G35: 4000 | H35: 3400 | I35: 4000 | J35: 3500 | K35: 4100 | L35: 3600 | M35: 4200 | N35: 3600 | O35: 4200
A36: Total Installed Cost (2017$) | B36: 4700 | C36: 4700 | D36: 4700 | E36: 5400 | F36: 4700 | G36: 5400 | H36: 4800 | I36: 5400 | J36: 4900 | K36: 5500 | L36: 5000 | M36: 5600 | N36: 5000 | O36: 5600
A37: Annual Maintenance Cost (2017$) | B37: 260 | C37: 260 | D37: 260 | E37: 260 | F37: 260 | G37: 260 | H37: 260 | I37: 260 | J37: 260 | K37: 260 | L37: 260 | M37: 260 | N37: 260 | O37: 260
A39: Residential Air Source Heat Pumps
A40: DATA | B40: 2009 | C40: 2015 | D40: 2017 | H40: 2020 | J40: 2030** | L40: 2040 | N40: 2050 | P40: 2060
B41: Installed Base | C41: Installed Base | D41: Current Standard | E41: Typical | F41: ENERGY STAR | G41: High | H41: Typical | I41: High | J41: Typical | K41: High | L41: Typical | M41: High | N41: Typical | O41: High | P41: Typical | Q41: High
A42: Typical Capacity (kBtu/h) | B42: 36 | C42: 36 | D42: 36 | E42: 36 | F42: 36 | G42: 36 | H42: 36 | I42: 36 | J42: 36 | K42: 36 | L42: 36 | M42: 36 | N42: 36 | O42: 36 | P42: 36 | Q42: 36
A43: SEER (Cooling)* | B43: 12 | C43: 13.1 | D43: 14 | E43: 15.3 | F43: 15 | G43: 19 | H43: 15.3 | I43: 19 | J43: 15.8 | K43: 19 | L43: 15.8 | M43: 19 | N43: 15.8 | O43: 19 | P43: 15.8 | Q43: 19
A44: HSPF (Heating)* | B44: 7 .0 | C44: 7.9 | D44: 8.2 | E44: 8.6 | F44: 8.5 | G44: 9 | H44: 8.6 | I44: 9 | J44: 8.8 | K44: 9 | L44: 8.8 | M44: 9 | N44: 8.8 | O44: 9 | P44: 8.8 | Q44: 9
A45: Average Life (yrs) | B45: 9 | C45: 9 | D45: 9 | E45: 9 | F45: 9 | G45: 9 | H45: 9 | I45: 9 | J45: 9 | K45: 9 | L45: 9 | M45: 9 | N45: 9 | O45: 9 | P45: 9 | Q45: 9
B46: 22 | C46: 22 | D46: 22 | E46: 22 | F46: 22 | G46: 22 | H46: 22 | I46: 22 | J46: 22 | K46: 22 | L46: 22 | M46: 22 | N46: 22 | O46: 22 | P46: 22 | Q46: 22
A47: Retail Equipment Cost (2017$)* | B47: 2550 | C47: 2800 | D47: 3350 | E47: 3600 | F47: 3500 | G47: 4550 | H47: 3600 | I47: 4550 | J47: 3700 | K47: 4550 | L47: 3700 | M47: 4550 | N47: 3700 | O47: 4550 | P47: 3700 | Q47: 4550
A48: Total Installed Cost (2017$)* | B48: 3000 | C48: 3250 | D48: 4850 | E48: 5100 | F48: 4950 | G48: 6100 | H48: 5100 | I48: 6100 | J48: 5150 | K48: 6100 | L48: 5150 | M48: 6100 | N48: 5150 | O48: 6100 | P48: 5150 | Q48: 6100
A49: Annual Maintenance Cost (2017$) | B49: 20 | C49: 20 | D49: 20 | E49: 20 | F49: 20 | G49: 20 | H49: 20 | I49: 20 | J49: 20 | K49: 20 | L49: 20 | M49: 20 | N49: 20 | O49: 20 | P49: 20 | Q49: 20
B50: 125 | C50: 125 | D50: 125 | E50: 125 | F50: 125 | G50: 125 | H50: 125 | I50: 125 | J50: 125 | K50: 125 | L50: 125 | M50: 125 | N50: 125 | O50: 125 | P50: 125 | Q50: 125
A52: Residential Gas Water Heater
B53: 2009 | C53: 2015 | D53: 2017 | H53: 2020 | J53: 2030 | L53: 2040 | N53: 2050 | P53: 2060
B54: Installed Base | C54: Installed Base | D54: Current Standard | E54: Typical | F54: ENERGY STAR | G54: High | H54: Typical | I54: High | J54: Typical | K54: High | L54: Typical | M54: High | N54: Typical | O54: High | P54: Typical | Q54: High
A55: Typical Capacity (gal) | B55: 40 | C55: 40 | D55: 40 | E55: 40 | F55: 40 | G55: 40 | H55: 40 | I55: 40 | J55: 40 | K55: 40 | L55: 40 | M55: 40 | N55: 40 | O55: 40 | P55: 40 | Q55: 40
A56: Uniform Energy Factor (UEF)* | B56: 0.58 | C56: 0.58 | D56: 0.61 | E56: 0.63 | F56: 0.66 | G56: 0.81 | H56: 0.63 | I56: 0.81 | J56: 0.63 | K56: 0.81 | L56: 0.63 | M56: 0.81 | N56: 0.63 | O56: 0.81 | P56: 0.63 | Q56: 0.81
A57: Average Life (yrs) | B57: 6 | C57: 6 | D57: 6 | E57: 6 | F57: 6 | G57: 6 | H57: 6 | I57: 6 | J57: 6 | K57: 6 | L57: 6 | M57: 6 | N57: 6 | O57: 6 | P57: 6 | Q57: 6
B58: 20 | C58: 20 | D58: 20 | E58: 20 | F58: 20 | G58: 20 | H58: 20 | I58: 20 | J58: 20 | K58: 20 | L58: 20 | M58: 20 | N58: 20 | O58: 20 | P58: 20 | Q58: 20
A59: Retail Equipment Cost (2017$) | B59: 500 | C59: 500 | D59: 700 | E59: 750 | F59: 800 | G59: 1850 | H59: 750 | I59: 1850 | J59: 750 | K59: 1850 | L59: 750 | M59: 1850 | N59: 750 | O59: 1850 | P59: 750 | Q59: 1850
B60: 550 | C60: 550 | D60: 1000 | E60: 1200 | F60: 1350 | G60: 2100 | H60: 1200 | I60: 2100 | J60: 1200 | K60: 2100 | L60: 1200 | M60: 2100 | N60: 1200 | O60: 2100 | P60: 1200 | Q60: 2100
A61: Total Installed Cost (2017$)** | B61: 1050 | C61: 1050 | D61: 1350 | E61: 1400 | F61: 1500 | G61: 2450 | H61: 1400 | I61: 2450 | J61: 1400 | K61: 2450 | L61: 1400 | M61: 2450 | N61: 1400 | O61: 2450 | P61: 1400 | Q61: 2450
B62: 1050 | C62: 1050 | D62: 2300 | E62: 2450 | F62: 2550 | G62: 3700 | H62: 2450 | I62: 3700 | J62: 2450 | K62: 3700 | L62: 2450 | M62: 3700 | N62: 2450 | O62: 3700 | P62: 2450 | Q62: 3700
A63: Annual Maintenance Cost (2017$)*** | B63: - | C63: - | D63: - | E63: - | F63: - | G63: - | H63: - | I63: - | J63: - | K63: - | L63: - | M63: - | N63: - | O63: - | P63: - | Q63: -
A66: Residential Oil Water Heater
A67: DATA | B67: 2009 | C67: 2015 | E67: 2017 | G67: 2020 | I67: 2030 | K67: 2040 | M67: 2050 | O67: 2060
B68: Installed Base | C68: =AVERAGE('EIA Costs'!D136:D137) -> 5225 | D68: Current Standard | E68: Typical | F68: High | G68: Typical | H68: High | I68: Typical | J68: High | K68: Typical | L68: High | M68: Typical | N68: High | O68: Typical | P68: High
A69: Typical Capacity (gal) | B69: 30 | C69: 32 | D69: 32 | E69: 32 | F69: 32 | G69: 32 | H69: 32 | I69: 32 | J69: 32 | K69: 32 | L69: 32 | M69: 32 | N69: 32 | O69: 32 | P69: 32
A70: Uniform Energy Factor (UEF)* | B70: 0.51 | C70: 0.51 | D70: 0.64 | E70: 0.67 | F70: 0.69 | G70: 0.67 | H70: 0.69 | I70: 0.67 | J70: 0.69 | K70: 0.67 | L70: 0.69 | M70: 0.67 | N70: 0.69 | O70: 0.67 | P70: 0.69
A71: Average Life (yrs) | B71: 6 | C71: 6 | D71: 6 | E71: 6 | F71: 6 | G71: 6 | H71: 6 | I71: 6 | J71: 6 | K71: 6 | L71: 6 | M71: 6 | N71: 6 | O71: 6 | P71: 6
B72: 20 | C72: 20 | D72: 20 | E72: 20 | F72: 20 | G72: 20 | H72: 20 | I72: 20 | J72: 20 | K72: 20 | L72: 20 | M72: 20 | N72: 20 | O72: 20 | P72: 20
A73: Retail Equipment Cost (2017$) | B73: 1350 | C73: 1350 | D73: 1500 | E73: 1600 | F73: 1600 | G73: 1600 | H73: 1600 | I73: 1600 | J73: 1600 | K73: 1600 | L73: 1600 | M73: 1600 | N73: 1600 | O73: 1600 | P73: 1600
B74: 1450 | C74: 1450 | D74: 1900 | E74: 2050 | F74: 2050 | G74: 2050 | H74: 2050 | I74: 2050 | J74: 2050 | K74: 2050 | L74: 2050 | M74: 2050 | N74: 2050 | O74: 2050 | P74: 2050
A75: Total Installed Cost (2017$) | B75: 2000 | C75: 2000 | D75: 2100 | E75: 2250 | F75: 2200 | G75: 2250 | H75: 2200 | I75: 2250 | J75: 2200 | K75: 2250 | L75: 2200 | M75: 2250 | N75: 2200 | O75: 2250 | P75: 2200
B76: 2100 | C76: 2100 | D76: 2700 | E76: 2850 | F76: 2850 | G76: 2850 | H76: 2850 | I76: 2850 | J76: 2850 | K76: 2850 | L76: 2850 | M76: 2850 | N76: 2850 | O76: 2850 | P76: 2850
A77: Annual Maintenance Cost (2017$) | B77: 180 | C77: 180 | D77: 180 | E77: 180 | F77: 180 | G77: 180 | H77: 180 | I77: 180 | J77: 180 | K77: 180 | L77: 180 | M77: 180 | N77: 180 | O77: 180 | P77: 180
A79: Residential Heat Pump Water Heater
A80: DATA | B80: 2009 | C80: 2015 | E80: 2017 | G80: 2020 | I80: 2030 | K80: 2040 | M80: 2050 | O80: 2060
B81: Installed Base | C81: Installed Base | D81: Typical | E81: ENERGY STAR | F81: High | G81: Typical | H81: High | I81: Typical | J81: High | K81: Typical | L81: High | M81: Typical | N81: High | O81: Typical | P81: High
A82: Typical Capacity (gal) | B82: 50 | C82: 50 | D82: 50 | E82: 50 | F82: 50 | G82: 50 | H82: 50 | I82: 50 | J82: 50 | K82: 50 | L82: 50 | M82: 50 | N82: 50 | O82: 50 | P82: 50
A83: Uniform Energy Factor (UEF)* | B83: 2.05 | C83: 2.05 | D83: 3.28 | E83: 2 | F83: 3.55 | G83: 3.28 | H83: 3.55 | I83: 3.28 | J83: 3.55 | K83: 3.28 | L83: 3.55 | M83: 3.28 | N83: 3.55 | O83: 3.28 | P83: 3.55
A84: Average Life (yrs) | B84: 6 | C84: 6 | D84: 6 | E84: 6 | F84: 6 | G84: 6 | H84: 6 | I84: 6 | J84: 6 | K84: 6 | L84: 6 | M84: 6 | N84: 6 | O84: 6 | P84: 6
B85: 20 | C85: 20 | D85: 20 | E85: 20 | F85: 20 | G85: 20 | H85: 20 | I85: 20 | J85: 20 | K85: 20 | L85: 20 | M85: 20 | N85: 20 | O85: 20 | P85: 20
A86: Retail Equipment Cost (2017$) | B86: 1550 | C86: 1100 | D86: 1200 | E86: 1050 | F86: 1200 | G86: 1200 | H86: 1200 | I86: 1200 | J86: 1200 | K86: 1200 | L86: 1200 | M86: 1200 | N86: 1200 | O86: 1200 | P86: 1200
B87: 1900 | C87: 1400 | D87: 1500 | E87: 1350 | F87: 2300 | G87: 1500 | H87: 2300 | I87: 1500 | J87: 2300 | K87: 1500 | L87: 2300 | M87: 1500 | N87: 2300 | O87: 1500 | P87: 2300
A88: Total Installed Cost (2017$) | B88: 1700 | C88: 1450 | D88: 1600 | E88: 1400 | F88: 1600 | G88: 1600 | H88: 1600 | I88: 1600 | J88: 1600 | K88: 1600 | L88: 1600 | M88: 1600 | N88: 1600 | O88: 1600 | P88: 1600
B89: 2450 | C89: 2500 | D89: 2550 | E89: 2400 | F89: 3350 | G89: 2550 | H89: 3350 | I89: 2550 | J89: 3350 | K89: 2550 | L89: 3350 | M89: 2550 | N89: 3350 | O89: 2550 | P89: 3350
A90: Annual Maintenance Cost (2017$) | B90: 20 | C90: 20 | D90: 20 | E90: 20 | F90: 20 | G90: 20 | H90: 20 | I90: 20 | J90: 20 | K90: 20 | L90: 20 | M90: 20 | N90: 20 | O90: 20 | P90: 20
A93: Commercial Gas Furnace
A94: DATA | B94: 2012 | D94: 2017 | F94: 2020 | H94: 2030 | J94: 2040 | L94: 2050 | N94: 2060
B95: Installed Base | C95: Current Standard | D95: Typical | E95: High | F95: Typical | G95: High | H95: Typical | I95: High | J95: Typical | K95: High | L95: Typical | M95: High | N95: Typical | O95: High
A96: Typical Input Capacity (kBtu/h) | B96: 400 | C96: 400 | D96: 400 | E96: 400 | F96: 400 | G96: 400 | H96: 400 | I96: 400 | J96: 400 | K96: 400 | L96: 400 | M96: 400 | N96: 400 | O96: 400
A97: Thermal Efficiency (%)* | B97: 80 | C97: 80 | D97: 80 | E97: 95 | F97: 80 | G97: 95 | H97: 81 | I97: 95 | J97: 81 | K97: 95 | L97: 81 | M97: 95 | N97: 81 | O97: 95
A98: Average Life (yrs) | B98: 23 | C98: 23 | D98: 23 | E98: 23 | F98: 23 | G98: 23 | H98: 23 | I98: 23 | J98: 23 | K98: 23 | L98: 23 | M98: 23 | N98: 23 | O98: 23
A99: Retail Equipment Cost (2017$) | B99: 1050 | C99: 1050 | D99: 1050 | E99: 2450 | F99: 1050 | G99: 2450 | H99: 1050 | I99: 2450 | J99: 1050 | K99: 2450 | L99: 1050 | M99: 2450 | N99: 1050 | O99: 2450
A100: Total Installed Cost (2017$) | B100: 2150 | C100: 2150 | D100: 2150 | E100: 3950 | F100: 2150 | G100: 3950 | H100: 2200 | I100: 3950 | J100: 2200 | K100: 3950 | L100: 2200 | M100: 3950 | N100: 2200 | O100: 3950
A101: Annual Maintenance Cost (2017$)** | B101: 170 | C101: 170 | D101: 170 | E101: 180 | F101: 170 | G101: 180 | H101: 170 | I101: 180 | J101: 170 | K101: 180 | L101: 170 | M101: 180 | N101: 170 | O101: 180
A104: Commercial Oil Furnace
A105: DATA | B105: 2012 | C105: 2017 | F105: 2020 | G105: 2030** | H105: 2040 | I105: 2050 | J105: 2060
B106: Installed Base | C106: Current Standard | D106: Typical | E106: High | F106: Typical | G106: Typical | H106: Typical | I106: Typical | J106: Typical
A107: Typical Input Capacity (kBtu/h) | B107: 400 | C107: 400 | D107: 400 | E107: 400 | F107: 400 | G107: 400 | H107: 400 | I107: 400 | J107: 400
A108: Thermal Efficiency (%)* | B108: 81 | C108: 81 | D108: 82 | E108: 85 | F108: 82 | G108: 82 | H108: 82 | I108: 82 | J108: 82
A109: Average Life (yrs) | B109: 23 | C109: 23 | D109: 23 | E109: 23 | F109: 23 | G109: 23 | H109: 23 | I109: 23 | J109: 23
A110: Retail Equipment Cost (2017$) | B110: 4650 | C110: 4650 | D110: 4700 | E110: 5050 | F110: 4700 | G110: 4700 | H110: 4700 | I110: 4700 | J110: 4700
A111: Total Installed Cost (2017$) | B111: 6550 | C111: 6550 | D111: 6600 | E111: 6750 | F111: 6600 | G111: 6600 | H111: 6600 | I111: 6600 | J111: 6600
...

Sheet EIA AEO Table 4
B1: highogs.d120120a | C1: 2020 | D1: 2021 | E1: 2022 | F1: 2023 | G1: 2024 | H1: 2025 | I1: 2026 | J1: 2027 | K1: 2028 | L1: 2029 | M1: 2030 | N1: 2031 | O1: 2032 | P1: 2033 | Q1: 2034 | R1: 2035 | S1: 2036 | T1: 2037 | U1: 2038 | V1: 2039 | W1: 2040 | X1: 2041 | Y1: 2042 | Z1: 2043 | AA1: 2044 | AB1: 2045 | AC1: 2046 | AD1: 2047 | AE1: 2048 | AF1: 2049 | AG1: 2050
C3: Report | D3: Annual Energy Outlook 2021
C4: Scenario | D4: ref2021 | G4: Reference case
C5: Datekey | D5: d113020a
C6: Release Date | E6: January 2021
A10: RKI000 | B10: 4. Residential Sector Key Indicators and Consumption | AR10: Compound
B11: (quadrillion Btu, unless otherwise noted) | AR11: Growth
AH12: 2051-2060年数据用2020-2050年增速计算 | AR12: 2020-2050
B13: Key Indicators and Consumption | C13: 2020 | D13: 2021 | E13: 2022 | F13: 2023 | G13: 2024 | H13: 2025 | I13: 2026 | J13: 2027 | K13: 2028 | L13: 2029 | M13: 2030 | N13: 2031 | O13: 2032 | P13: 2033 | Q13: 2034 | R13: 2035 | S13: 2036 | T13: 2037 | U13: 2038 | V13: 2039 | W13: 2040 | X13: 2041 | Y13: 2042 | Z13: 2043 | AA13: 2044 | AB13: 2045 | AC13: 2046 | AD13: 2047 | AE13: 2048 | AF13: 2049 | AG13: 2050 | AH13: 2051 | AI13: 2052 | AJ13: 2053 | AK13: 2054 | AL13: 2055 | AM13: 2056 | AN13: 2057 | AO13: 2058 | AP13: 2059 | AQ13: 2060 | AR13: (percent)
B15: Key Indicators
B16: Households (millions)
A17: RKI000:ba_Single-Family | B17: Single-Family | C17: 84.750443 | D17: 85.593651 | E17: 86.439354 | F17: 87.273476 | G17: 88.112289 | H17: 88.984467 | I17: 89.856285 | J17: 90.700256 | K17: 91.51667 | L17: 92.31514 | M17: 93.093277 | N17: 93.847504 | O17: 94.588799 | P17: 95.310699 | Q17: 96.006424 | R17: 96.697853 | S17: 97.37767 | T17: 98.047127 | U17: 98.708321 | V17: 99.360046 | W17: 100.01558 | X17: 100.67042 | Y17: 101.32133 | Z17: 101.97403 | AA17: 102.632 | AB17: 103.29288 | AC17: 103.95903 | AD17: 104.62138 | AE17: 105.2791 | AF17: 105.93704 | AG17: 106.59597 | AH17: =AG17*(1+$AR17) -> 107.41399 | AI17: =AH17*(1+$AR17) -> 108.23828 | AJ17: =AI17*(1+$AR17) -> 109.0689 | AK17: =AJ17*(1+$AR17) -> 109.9059 | AL17: =AK17*(1+$AR17) -> 110.74932 | AM17: =AL17*(1+$AR17) -> 111.59921 | AN17: =AM17*(1+$AR17) -> 112.45562 | AO17: =AN17*(1+$AR17) -> 113.3186 | ... AQ17: =AP17*(1+$AR17) -> 115.06449 | AR17: 0.007674
A18: RKI000:ba_Multifamily | B18: Multifamily | C18: 31.968704 | D18: 32.227837 | E18: 32.484608 | F18: 32.738888 | G18: 33.007179 | H18: 33.292564 | I18: 33.572525 | J18: 33.83012 | K18: 34.072906 | L18: 34.306412 | M18: 34.532425 | N18: 34.747349 | O18: 34.956161 | P18: 35.154221 | Q18: 35.343121 | R18: 35.533417 | S18: 35.72086 | T18: 35.907597 | U18: 36.095905 | V18: 36.288265 | W18: 36.482738 | X18: 36.677246 | Y18: 36.872318 | Z18: 37.067024 | AA18: 37.256569 | AB18: 37.445789 | AC18: 37.632339 | AD18: 37.817364 | AE18: 38.004612 | AF18: 38.195267 | AG18: 38.390739 | AH18: =AG18*(1+$AR18) -> 38.625729 | AI18: =AH18*(1+$AR18) -> 38.862157 | AJ18: =AI18*(1+$AR18) -> 39.100032 | AK18: =AJ18*(1+$AR18) -> 39.339363 | AL18: =AK18*(1+$AR18) -> 39.58016 | AM18: =AL18*(1+$AR18) -> 39.82243 | AN18: =AM18*(1+$AR18) -> 40.066183 | AO18: =AN18*(1+$AR18) -> 40.311428 | ... AQ18: =AP18*(1+$AR18) -> 40.806431 | AR18: 0.006121
A19: RKI000:ba_MobileHomes | B19: Mobile Homes | C19: 6.663464 | D19: 6.648326 | E19: 6.634981 | F19: 6.627098 | G19: 6.630111 | H19: 6.643839 | I19: 6.664732 | J19: 6.675515 | K19: 6.675215 | L19: 6.664383 | M19: 6.643749 | N19: 6.616388 | O19: 6.58721 | P19: 6.557878 | Q19: 6.529199 | R19: 6.505653 | S19: 6.485949 | T19: 6.466928 | U19: 6.447885 | V19: 6.43115 | W19: 6.419676 | X19: 6.411514 | Y19: 6.40536 | Z19: 6.400518 | AA19: 6.396067 | AB19: 6.392113 | AC19: 6.388073 | AD19: 6.381184 | AE19: 6.37248 | AF19: 6.363905 | AG19: 6.35391 | AH19: =AG19*(1+$AR19) -> 6.3438454 | AI19: =AH19*(1+$AR19) -> 6.3337968 | AJ19: =AI19*(1+$AR19) -> 6.323764 | AK19: =AJ19*(1+$AR19) -> 6.3137472 | AL19: =AK19*(1+$AR19) -> 6.3037462 | AM19: =AL19*(1+$AR19) -> 6.2937611 | AN19: =AM19*(1+$AR19) -> 6.2837918 | AO19: =AN19*(1+$AR19) -> 6.2738382 | ... AQ19: =AP19*(1+$AR19) -> 6.2539784 | AR19: -0.001584
A20: RKI000:ba_Total | B20: Total | C20: 123.38261 | D20: 124.46981 | E20: 125.55894 | F20: 126.63946 | G20: 127.74958 | H20: 128.92087 | I20: 130.09354 | J20: 131.2059 | K20: 132.26479 | L20: 133.28593 | M20: 134.26945 | N20: 135.21124 | O20: 136.13216 | P20: 137.0228 | Q20: 137.87875 | R20: 138.73691 | S20: 139.58447 | T20: 140.42166 | U20: 141.25212 | V20: 142.07947 | W20: 142.918 | X20: 143.75919 | Y20: 144.59901 | Z20: 145.44156 | AA20: 146.28465 | AB20: 147.1308 | AC20: 147.97945 | AD20: 148.81992 | AE20: 149.65619 | AF20: 150.49622 | AG20: 151.34062 | AH20: =AG20*(1+$AR20) -> 152.37443 | AI20: =AH20*(1+$AR20) -> 153.4153 | AJ20: =AI20*(1+$AR20) -> 154.46328 | AK20: =AJ20*(1+$AR20) -> 155.51842 | AL20: =AK20*(1+$AR20) -> 156.58076 | AM20: =AL20*(1+$AR20) -> 157.65037 | AN20: =AM20*(1+$AR20) -> 158.72728 | AO20: =AN20*(1+$AR20) -> 159.81154 | ... AQ20: =AP20*(1+$AR20) -> 162.00235 | AR20: 0.006831
A22: RKI000:ca_AverageHouseS | B22: Average House Square Footage | C22: 1789.3104 | D22: 1795.358 | E22: 1801.3766 | F22: 1807.3268 | G22: 1813.0863 | H22: 1818.6857 | I22: 1824.2563 | J22: 1829.9603 | K22: 1835.7445 | L22: 1841.579 | M22: 1847.4465 | N22: 1853.3517 | O22: 1859.2565 | P22: 1865.1763 | Q22: 1871.0797 | R22: 1876.913 | S22: 1882.7009 | T22: 1888.4429 | U22: 1894.134 | V22: 1899.7411 | W22: 1905.2928 | X22: 1910.8062 | Y22: 1916.274 | Z22: 1921.7234 | AA22: 1927.2003 | AB22: 1932.6646 | AC22: 1938.1436 | AD22: 1943.6198 | AE22: 1949.0584 | AF22: 1954.4558 | AG22: 1959.8108 | AH22: =AG22*(1+$AR22) -> 1965.7667 | AI22: =AH22*(1+$AR22) -> 1971.7406 | AJ22: =AI22*(1+$AR22) -> 1977.7327 | AK22: =AJ22*(1+$AR22) -> 1983.7431 | AL22: =AK22*(1+$AR22) -> 1989.7717 | AM22: =AL22*(1+$AR22) -> 1995.8186 | AN22: =AM22*(1+$AR22) -> 2001.8839 | AO22: =AN22*(1+$AR22) -> 2007.9676 | ... AQ22: =AP22*(1+$AR22) -> 2020.1906 | AR22: 0.003039
B24: Energy Intensity
B25: (million Btu per household)
A26: RKI000:da_DeliveredEner | B26: Gross End-use Consumption 1/ | C26: 92.738052 | D26: 91.586494 | E26: 91.932487 | F26: 91.31826 | G26: 90.823273 | H26: 90.223351 | I26: 89.61335 | J26: 88.99015 | K26: 88.42942 | L26: 87.893829 | M26: 87.318878 | N26: 86.789642 | O26: 86.329742 | P26: 85.926926 | Q26: 85.607529 | R26: 85.342171 | S26: 85.099846 | T26: 84.88208 | U26: 84.683701 | V26: 84.499214 | W26: 84.319466 | X26: 84.135582 | Y26: 83.962128 | Z26: 83.800156 | AA26: 83.656654 | AB26: 83.525162 | AC26: 83.412842 | AD26: 83.307243 | AE26: 83.24379 | AF26: 83.194534 | AG26: 83.15329 | AH26: =AG26*(1+$AR26) -> 82.851444 | AI26: =AH26*(1+$AR26) -> 82.550693 | AJ26: =AI26*(1+$AR26) -> 82.251034 | AK26: =AJ26*(1+$AR26) -> 81.952463 | AL26: =AK26*(1+$AR26) -> 81.654975 | AM26: =AL26*(1+$AR26) -> 81.358568 | AN26: =AM26*(1+$AR26) -> 81.063236 | AO26: =AN26*(1+$AR26) -> 80.768976 | ... AQ26: =AP26*(1+$AR26) -> 80.183658 | AR26: -0.00363
A27: RKI000:da_TotalEnergyCo | B27: Delivered Energy Consumption | C27: 92.104782 | D27: 90.867767 | E27: 91.143921 | F27: 90.463226 | G27: 89.904442 | H27: 89.241905 | I27: 88.56897 | J27: 87.883224 | K27: 87.260002 | L27: 86.662102 | M27: 86.023964 | N27: 85.430344 | O27: 84.905266 | P27: 84.436523 | Q27: 84.050179 | R27: 83.717567 | S27: 83.407295 | T27: 83.12088 | U27: 82.852921 | V27: 82.598061 | W27: 82.347038 | X27: 82.090897 | Y27: 81.843887 | Z27: 81.606949 | AA27: 81.386993 | AB27: 81.177185 | AC27: 80.98513 | AD27: 80.798256 | AE27: 80.651489 | AF27: 80.517357 | AG27: 80.389618 | AH27: =AG27*(1+$AR27) -> 80.025935 | AI27: =AH27*(1+$AR27) -> 79.663898 | AJ27: =AI27*(1+$AR27) -> 79.303499 | AK27: =AJ27*(1+$AR27) -> 78.94473 | AL27: =AK27*(1+$AR27) -> 78.587584 | AM27: =AL27*(1+$AR27) -> 78.232053 | AN27: =AM27*(1+$AR27) -> 77.878132 | AO27: =AN27*(1+$AR27) -> 77.525811 | ... AQ27: =AP27*(1+$AR27) -> 76.825944 | AR27: -0.004524
B28: (thousand Btu per square foot) | AH28: =AG28*(1+$AR28) -> 0 | AI28: =AH28*(1+$AR28) -> 0 | AJ28: =AI28*(1+$AR28) -> 0 | AK28: =AJ28*(1+$AR28) -> 0 | AL28: =AK28*(1+$AR28) -> 0 | AM28: =AL28*(1+$AR28) -> 0 | AN28: =AM28*(1+$AR28) -> 0 | AO28: =AN28*(1+$AR28) -> 0 | ... AQ28: =AP28*(1+$AR28) -> 0
A29: RKI000:ea_DeliveredEner | B29: Gross End-use Consumption 1/ | C29: 51.828938 | D29: 51.012939 | E29: 51.034573 | F29: 50.526699 | G29: 50.093189 | H29: 49.609097 | I29: 49.123222 | J29: 48.629551 | K29: 48.170876 | L29: 47.727428 | M29: 47.264633 | N29: 46.82848 | O29: 46.432404 | P29: 46.069065 | Q29: 45.75301 | R29: 45.469433 | S29: 45.200935 | T29: 44.948185 | U29: 44.708401 | V29: 44.479332 | W29: 44.255383 | X29: 44.03146 | Y29: 43.815304 | Z29: 43.606773 | AA29: 43.408386 | AB29: 43.217617 | AC29: 43.037495 | AD29: 42.861904 | AE29: 42.709747 | AF29: 42.566597 | AG29: 42.429241 | AH29: =AG29*(1+$AR29) -> 42.147171 | AI29: =AH29*(1+$AR29) -> 41.866977 | AJ29: =AI29*(1+$AR29) -> 41.588645 | AK29: =AJ29*(1+$AR29) -> 41.312164 | AL29: =AK29*(1+$AR29) -> 41.037521 | AM29: =AL29*(1+$AR29) -> 40.764703 | AN29: =AM29*(1+$AR29) -> 40.4937 | AO29: =AN29*(1+$AR29) -> 40.224497 | ... AQ29: =AP29*(1+$AR29) -> 39.69145 | AR29: -0.006648
A30: RKI000:ea_TotalEnergyCo | B30: Delivered Energy Consumption | C30: 51.475014 | D30: 50.612617 | E30: 50.596817 | F30: 50.053608 | G30: 49.586411 | H30: 49.06945 | I30: 48.550724 | J30: 48.024662 | K30: 47.533848 | L30: 47.058586 | M30: 46.563709 | N30: 46.095051 | O30: 45.666248 | P30: 45.269997 | Q30: 44.920685 | R30: 44.603863 | S30: 44.301933 | T30: 44.015564 | U30: 43.741848 | V30: 43.478588 | W30: 43.220146 | X30: 42.961391 | Y30: 42.709908 | Z30: 42.4655 | AA30: 42.230686 | AB30: 42.002731 | AC30: 41.784897 | AD30: 41.571022 | AE30: 41.379719 | AF30: 41.196815 | AG30: 41.01907 | AH30: =AG30*(1+$AR30) -> 40.709786 | AI30: =AH30*(1+$AR30) -> 40.402834 | AJ30: =AI30*(1+$AR30) -> 40.098197 | AK30: =AJ30*(1+$AR30) -> 39.795857 | AL30: =AK30*(1+$AR30) -> 39.495796 | AM30: =AL30*(1+$AR30) -> 39.197998 | AN30: =AM30*(1+$AR30) -> 38.902445 | AO30: =AN30*(1+$AR30) -> 38.60912 | ... AQ30: =AP30*(1+$AR30) -> 38.02909 | AR30: -0.00754
B32: Energy Consumption by Fuel
B33: Electricity 1/
A34: RKI000:fa_SpaceHeating | B34: Space Heating | C34: 0.648984 | D34: 0.698291 | E34: 0.706468 | F34: 0.702827 | G34: 0.701007 | H34: 0.69955 | I34: 0.697172 | J34: 0.693818 | K34: 0.690231 | L34: 0.68634 | M34: 0.68221 | N34: 0.677813 | O34: 0.673331 | P34: 0.669098 | Q34: 0.665025 | R34: 0.661573 | S34: 0.658052 | T34: 0.654504 | U34: 0.650834 | V34: 0.647063 | W34: 0.643497 | X34: 0.639746 | Y34: 0.635992 | Z34: 0.63249 | AA34: 0.628953 | AB34: 0.625267 | AC34: 0.621895 | AD34: 0.618506 | AE34: 0.615298 | AF34: 0.61255 | AG34: 0.609983 | AH34: =AG34*(1+$AR34) -> 0.608724 | AI34: =AH34*(1+$AR34) -> 0.60746759 | AJ34: =AI34*(1+$AR34) -> 0.60621378 | AK34: =AJ34*(1+$AR34) -> 0.60496255 | AL34: =AK34*(1+$AR34) -> 0.60371391 | AM34: =AL34*(1+$AR34) -> 0.60246784 | AN34: =AM34*(1+$AR34) -> 0.60122435 | AO34: =AN34*(1+$AR34) -> 0.59998342 | ... AQ34: =AP34*(1+$AR34) -> 0.59750925 | AR34: -0.002064
A35: RKI000:fa_SpaceCooling | B35: Space Cooling | C35: 0.805383 | D35: 0.7663 | E35: 0.862066 | F35: 0.87731 | G35: 0.893665 | H35: 0.910851 | I35: 0.927645 | J35: 0.943833 | K35: 0.959908 | L35: 0.975957 | M35: 0.991661 | N35: 1.00764 | O35: 1.024417 | P35: 1.041983 | Q35: 1.060664 | R35: 1.0811 | S35: 1.10211 | T35: 1.124333 | U35: 1.146319 | V35: 1.168238 | W35: 1.190837 | X35: 1.213056 | Y35: 1.236301 | Z35: 1.259563 | AA35: 1.283829 | AB35: 1.307854 | AC35: 1.33271 | AD35: 1.357816 | AE35: 1.384607 | AF35: 1.411898 | AG35: 1.440232 | AH35: =AG35*(1+$AR35) -> 1.4684087 | AI35: =AH35*(1+$AR35) -> 1.4971366 | AJ35: =AI35*(1+$AR35) -> 1.5264266 | AK35: =AJ35*(1+$AR35) -> 1.5562896 | AL35: =AK35*(1+$AR35) -> 1.5867369 | AM35: =AL35*(1+$AR35) -> 1.6177798 | AN35: =AM35*(1+$AR35) -> 1.6494301 | AO35: =AN35*(1+$AR35) -> 1.6816995 | ... AQ35: =AP35*(1+$AR35) -> 1.7481447 | AR35: 0.019564
A36: RKI000:fa_WaterHeating | B36: Water Heating | C36: 0.607547 | D36: 0.610144 | E36: 0.613074 | F36: 0.61509 | G36: 0.617846 | H36: 0.620172 | I36: 0.621656 | J36: 0.622656 | K36: 0.623322 | L36: 0.6239 | M36: 0.624483 | N36: 0.625003 | O36: 0.625859 | P36: 0.627114 | Q36: 0.628819 | R36: 0.631185 | S36: 0.633851 | T36: 0.636678 | U36: 0.639551 | V36: 0.642161 | W36: 0.644696 | X36: 0.647135 | Y36: 0.649634 | Z36: 0.65233 | AA36: 0.655174 | AB36: 0.658088 | AC36: 0.661325 | AD36: 0.664806 | AE36: 0.668643 | AF36: 0.672985 | AG36: 0.677571 | AH36: =AG36*(1+$AR36) -> 0.68003939 | AI36: =AH36*(1+$AR36) -> 0.68251677 | AJ36: =AI36*(1+$AR36) -> 0.68500318 | AK36: =AJ36*(1+$AR36) -> 0.68749865 | AL36: =AK36*(1+$AR36) -> 0.69000321 | AM36: =AL36*(1+$AR36) -> 0.69251689 | AN36: =AM36*(1+$AR36) -> 0.69503973 | AO36: =AN36*(1+$AR36) -> 0.69757176 | ... AQ36: =AP36*(1+$AR36) -> 0.70266352 | AR36: 0.003643
A37: RKI000:fa_Refrigeration | B37: Refrigeration | C37: 0.297571 | D37: 0.295346 | E37: 0.293794 | F37: 0.292089 | G37: 0.290616 | H37: 0.289474 | I37: 0.288541 | J37: 0.287696 | K37: 0.286959 | L37: 0.286376 | M37: 0.28598 | N37: 0.285826 | O37: 0.285965 | P37: 0.286393 | Q37: 0.287106 | R37: 0.288174 | S37: 0.289567 | T37: 0.291258 | U37: 0.293256 | V37: 0.295533 | W37: 0.298126 | X37: 0.301018 | Y37: 0.30418 | Z37: 0.307324 | AA37: 0.31044 | AB37: 0.31352 | AC37: 0.316558 | AD37: 0.319522 | AE37: 0.322411 | AF37: 0.325241 | AG37: 0.328011 | AH37: =AG37*(1+$AR37) -> 0.32907769 | AI37: =AH37*(1+$AR37) -> 0.33014785 | AJ37: =AI37*(1+$AR37) -> 0.33122149 | AK37: =AJ37*(1+$AR37) -> 0.33229863 | AL37: =AK37*(1+$AR37) -> 0.33337926 | AM37: =AL37*(1+$AR37) -> 0.33446341 | AN37: =AM37*(1+$AR37) -> 0.33555109 | AO37: =AN37*(1+$AR37) -> 0.3366423 | ... AQ37: =AP37*(1+$AR37) -> 0.33883538 | AR37: 0.003252
A38: RKI000:fa_Cooking | B38: Cooking | C38: 0.055007 | D38: 0.055161 | E38: 0.05546 | F38: 0.05575 | G38: 0.056045 | H38: 0.056357 | I38: 0.056663 | J38: 0.056938 | K38: 0.057183 | L38: 0.057389 | M38: 0.057556 | N38: 0.057676 | O38: 0.057755 | P38: 0.057841 | Q38: 0.057947 | R38: 0.058089 | S38: 0.058269 | T38: 0.058488 | U38: 0.058698 | V38: 0.058899 | W38: 0.059098 | X38: 0.05929 | Y38: 0.059473 | Z38: 0.059649 | AA38: 0.059818 | AB38: 0.05998 | AC38: 0.060139 | AD38: 0.06029 | AE38: 0.06044 | AF38: 0.060595 | AG38: 0.060756 | AH38: =AG38*(1+$AR38) -> 0.060957649 | AI38: =AH38*(1+$AR38) -> 0.061159968 | AJ38: =AI38*(1+$AR38) -> 0.061362958 | AK38: =AJ38*(1+$AR38) -> 0.061566621 | AL38: =AK38*(1+$AR38) -> 0.061770961 | AM38: =AL38*(1+$AR38) -> 0.061975979 | AN38: =AM38*(1+$AR38) -> 0.062181677 | AO38: =AN38*(1+$AR38) -> 0.062388058 | ... AQ38: =AP38*(1+$AR38) -> 0.062802877 | AR38: 0.003319
A39: RKI000:fa_ClothesDryers | B39: Clothes Dryers | C39: 0.21642 | D39: 0.220336 | E39: 0.224132 | F39: 0.227692 | G39: 0.231622 | H39: 0.235607 | I39: 0.239343 | J39: 0.242757 | K39: 0.246061 | L39: 0.249326 | M39: 0.252545 | N39: 0.255598 | O39: 0.258678 | P39: 0.261852 | Q39: 0.265235 | R39: 0.268841 | S39: 0.27257 | T39: 0.276244 | U39: 0.279829 | V39: 0.283363 | W39: 0.286891 | X39: 0.29037 | Y39: 0.293837 | Z39: 0.29735 | AA39: 0.300874 | AB39: 0.304347 | AC39: 0.307894 | AD39: 0.311491 | AE39: 0.315186 | AF39: 0.319055 | AG39: 0.322998 | AH39: =AG39*(1+$AR39) -> 0.32733812 | AI39: =AH39*(1+$AR39) -> 0.33173657 | AJ39: =AI39*(1+$AR39) -> 0.33619411 | AK39: =AJ39*(1+$AR39) -> 0.34071155 | AL39: =AK39*(1+$AR39) -> 0.34528969 | AM39: =AL39*(1+$AR39) -> 0.34992935 | AN39: =AM39*(1+$AR39) -> 0.35463135 | AO39: =AN39*(1+$AR39) -> 0.35939653 | ... AQ39: =AP39*(1+$AR39) -> 0.36911984 | AR39: 0.013437
A40: RKI000:fa_Freezers | B40: Freezers | C40: 0.069181 | D40: 0.068847 | E40: 0.068698 | F40: 0.068526 | G40: 0.06834 | H40: 0.068157 | I40: 0.067953 | J40: 0.067707 | K40: 0.067461 | L40: 0.067224 | M40: 0.066995 | N40: 0.066774 | O40: 0.06657 | P40: 0.066383 | Q40: 0.066214 | R40: 0.066077 | S40: 0.065975 | T40: 0.065902 | U40: 0.065862 | V40: 0.065855 | W40: 0.065888 | X40: 0.065966 | Y40: 0.066082 | Z40: 0.066247 | AA40: 0.066465 | AB40: 0.066737 | AC40: 0.067063 | AD40: 0.067429 | AE40: 0.06779 | AF40: 0.068152 | AG40: 0.068514 | AH40: =AG40*(1+$AR40) -> 0.06849187 | AI40: =AH40*(1+$AR40) -> 0.068469747 | AJ40: =AI40*(1+$AR40) -> 0.068447631 | AK40: =AJ40*(1+$AR40) -> 0.068425523 | AL40: =AK40*(1+$AR40) -> 0.068403421 | AM40: =AL40*(1+$AR40) -> 0.068381327 | AN40: =AM40*(1+$AR40) -> 0.06835924 | AO40: =AN40*(1+$AR40) -> 0.06833716 | ... AQ40: =AP40*(1+$AR40) -> 0.068293021 | AR40: -0.000323
A41: RKI000:fa_Lighting | B41: Lighting | C41: 0.211245 | D41: 0.204658 | E41: 0.202521 | F41: 0.20193 | G41: 0.202401 | H41: 0.201491 | I41: 0.200873 | J41: 0.200838 | K41: 0.201379 | L41: 0.202196 | M41: 0.200463 | N41: 0.199204 | O41: 0.198392 | P41: 0.197965 | Q41: 0.197945 | R41: 0.198286 | S41: 0.198748 | T41: 0.199251 | U41: 0.199757 | V41: 0.200288 | W41: 0.197496 | X41: 0.195328 | Y41: 0.193641 | Z41: 0.192433 | AA41: 0.191624 | AB41: 0.191038 | AC41: 0.190629 | AD41: 0.190303 | AE41: 0.190083 | AF41: 0.190014 | AG41: 0.190188 | AH41: =AG41*(1+$AR41) -> 0.18952348 | AI41: =AH41*(1+$AR41) -> 0.18886129 | AJ41: =AI41*(1+$AR41) -> 0.18820141 | AK41: =AJ41*(1+$AR41) -> 0.18754383 | AL41: =AK41*(1+$AR41) -> 0.18688855 | AM41: =AL41*(1+$AR41) -> 0.18623556 | AN41: =AM41*(1+$AR41) -> 0.18558486 | AO41: =AN41*(1+$AR41) -> 0.18493642 | ... AQ41: =AP41*(1+$AR41) -> 0.18364635 | AR41: -0.003494
A42: RKI000:fa_ClothesWasher | B42: Clothes Washers 2/ | C42: 0.036779 | D42: 0.037026 | E42: 0.037375 | F42: 0.037721 | G42: 0.038075 | H42: 0.038449 | I42: 0.038824 | J42: 0.03918 | K42: 0.039523 | L42: 0.039855 | M42: 0.040193 | N42: 0.040519 | O42: 0.040839 | P42: 0.041152 | Q42: 0.041455 | R42: 0.041759 | S42: 0.04206 | T42: 0.042358 | U42: 0.042653 | V42: 0.042945 | W42: 0.04324 | X42: 0.043535 | Y42: 0.043829 | Z42: 0.044122 | AA42: 0.044416 | AB42: 0.044709 | AC42: 0.045004 | AD42: 0.045295 | AE42: 0.045585 | AF42: 0.045875 | AG42: 0.046168 | AH42: =AG42*(1+$AR42) -> 0.0465192 | AI42: =AH42*(1+$AR42) -> 0.046873072 | AJ42: =AI42*(1+$AR42) -> 0.047229635 | AK42: =AJ42*(1+$AR42) -> 0.047588911 | AL42: =AK42*(1+$AR42) -> 0.04795092 | AM42: =AL42*(1+$AR42) -> 0.048315682 | AN42: =AM42*(1+$AR42) -> 0.04868322 | AO42: =AN42*(1+$AR42) -> 0.049053553 | ... AQ42: =AP42*(1+$AR42) -> 0.049802692 | AR42: 0.007607
A43: RKI000:fa_Dishwashers | B43: Dishwashers 2/ | C43: 0.026617 | D43: 0.026992 | E43: 0.027431 | F43: 0.027859 | G43: 0.028283 | H43: 0.028709 | I43: 0.029123 | J43: 0.029508 | K43: 0.029918 | L43: 0.03036 | M43: 0.03083 | N43: 0.03133 | O43: 0.031868 | P43: 0.032445 | Q43: 0.033062 | R43: 0.033677 | S43: 0.034289 | T43: 0.034896 | U43: 0.035501 | V43: 0.036103 | W43: 0.036706 | X43: 0.037309 | Y43: 0.03791 | Z43: 0.03851 | AA43: 0.03911 | AB43: 0.03971 | AC43: 0.040309 | AD43: 0.040905 | AE43: 0.041499 | AF43: 0.042093 | AG43: 0.042686 | AH43: =AG43*(1+$AR43) -> 0.043363427 | AI43: =AH43*(1+$AR43) -> 0.044051604 | AJ43: =AI43*(1+$AR43) -> 0.044750703 | AK43: =AJ43*(1+$AR43) -> 0.045460897 | AL43: =AK43*(1+$AR43) -> 0.046182361 | AM43: =AL43*(1+$AR43) -> 0.046915276 | AN43: =AM43*(1+$AR43) -> 0.047659821 | AO43: =AN43*(1+$AR43) -> 0.048416182 | ... AQ43: =AP43*(1+$AR43) -> 0.049965106 | AR43: 0.01587
A44: RKI000:fa_ColorTelevisi | B44: Televisions and Related Equipment 3/ | C44: 0.20913 | D44: 0.205162 | E44: 0.202737 | F44: 0.200828 | G44: 0.199926 | H44: 0.199812 | I44: 0.20026 | J44: 0.201233 | K44: 0.20279 | L44: 0.20499 | M44: 0.207745 | N44: 0.210879 | O44: 0.214516 | P44: 0.218628 | Q44: 0.223129 | R44: 0.228027 | S44: 0.233134 | T44: 0.23827 | U44: 0.243305 | V44: 0.248126 | W44: 0.252637 | X44: 0.256616 | Y44: 0.260069 | Z44: 0.263242 | AA44: 0.266345 | AB44: 0.26934 | AC44: 0.272296 | AD44: 0.275205 | AE44: 0.27813 | AF44: 0.281099 | AG44: 0.284057 | AH44: =AG44*(1+$AR44) -> 0.28697142 | AI44: =AH44*(1+$AR44) -> 0.28991575 | AJ44: =AI44*(1+$AR44) -> 0.29289029 | AK44: =AJ44*(1+$AR44) -> 0.29589534 | AL44: =AK44*(1+$AR44) -> 0.29893123 | AM44: =AL44*(1+$AR44) -> 0.30199826 | AN44: =AM44*(1+$AR44) -> 0.30509676 | AO44: =AN44*(1+$AR44) -> 0.30822706 | ... AQ44: =AP44*(1+$AR44) -> 0.31458432 | AR44: 0.01026
A45: RKI000:fa_PersonalCompu | B45: Computers and Related Equipment 4/ | C45: 0.086663 | D45: 0.083815 | E45: 0.081571 | F45: 0.079481 | G45: 0.077709 | H45: 0.076122 | I45: 0.074639 | J45: 0.073224 | K45: 0.071899 | L45: 0.07067 | M45: 0.069487 | N45: 0.068284 | O45: 0.0671 | P45: 0.06591 | Q45: 0.064687 | R45: 0.063421 | S45: 0.062059 | T45: 0.060712 | U45: 0.059373 | V45: 0.058027 | W45: 0.056675 | X45: 0.055295 | Y45: 0.053887 | Z45: 0.052461 | AA45: 0.051003 | AB45: 0.049484 | AC45: 0.047905 | AD45: 0.046248 | AE45: 0.044522 | AF45: 0.042687 | AG45: 0.040729 | AH45: =AG45*(1+$AR45) -> 0.039716681 | AI45: =AH45*(1+$AR45) -> 0.038729523 | AJ45: =AI45*(1+$AR45) -> 0.0377669 | AK45: =AJ45*(1+$AR45) -> 0.036828204 | AL45: =AK45*(1+$AR45) -> 0.035912839 | AM45: =AL45*(1+$AR45) -> 0.035020225 | AN45: =AM45*(1+$AR45) -> 0.034149798 | AO45: =AN45*(1+$AR45) -> 0.033301004 | ... AQ45: =AP45*(1+$AR45) -> 0.031666184 | AR45: -0.024855
... A50: RKI000:fa_PurchasedElec | B50: Purchased Electricity | C50: 5.052812 | D50: 5.085637 | E50: 5.095811 | F50: 5.116436 | G50: 5.142391 | H50: 5.170817 | I50: 5.205887 | J50: 5.237628 | K50: 5.270442 | L50: 5.303538 | M50: 5.333761 | N50: 5.36293 | O50: 5.394765 | P50: 5.428938 | Q50: 5.470158 | R50: 5.515707 | S50: 5.562729 | T50: 5.610796 | U50: 5.65801 | V50: 5.705455 | W50: 5.750833 | X50: 5.795556 | Y50: 5.841669 | Z50: 5.888741 | AA50: 5.936951 | AB50: 5.985407 | AC50: 6.035119 | AD50: 6.084916 | AE50: 6.139284 | AF50: 6.195721 | AG50: 6.253851 | AH50: =AG50*(1+$AR50) -> 6.298466 | AI50: =AH50*(1+$AR50) -> 6.3433992 | AJ50: =AI50*(1+$AR50) -> 6.388653 | AK50: =AJ50*(1+$AR50) -> 6.4342297 | AL50: =AK50*(1+$AR50) -> 6.4801315 | AM50: =AL50*(1+$AR50) -> 6.5263607 | AN50: =AM50*(1+$AR50) -> 6.5729198 | AO50: =AN50*(1+$AR50) -> 6.619811 | ... AQ50: =AP50*(1+$AR50) -> 6.7145994 | AR50: 0.007134
B52: Natural Gas
A53: RKI000:ga_SpaceHeating | B53: Space Heating | C53: 3.527198 | D53: 3.406817 | E53: 3.538172 | F53: 3.535602 | G53: 3.539818 | H53: 3.535704 | I53: 3.522943 | J53: 3.505328 | K53: 3.488243 | L53: 3.469637 | M53: 3.44763 | N53: 3.428068 | O53: 3.411065 | P53: 3.395152 | Q53: 3.380025 | R53: 3.367227 | S53: 3.35518 | T53: 3.343377 | U53: 3.333029 | V53: 3.323643 | W53: 3.315649 | X53: 3.307149 | Y53: 3.298006 | Z53: 3.288577 | AA53: 3.279139 | AB53: 3.269643 | AC53: 3.260687 | AD53: 3.251623 | AE53: 3.243194 | AF53: 3.234245 | AG53: 3.224808 | AH53: =AG53*(1+$AR53) -> 3.2151884 | AI53: =AH53*(1+$AR53) -> 3.2055975 | AJ53: =AI53*(1+$AR53) -> 3.1960352 | AK53: =AJ53*(1+$AR53) -> 3.1865014 | AL53: =AK53*(1+$AR53) -> 3.1769961 | AM53: =AL53*(1+$AR53) -> 3.1675191 | AN53: =AM53*(1+$AR53) -> 3.1580704 | AO53: =AN53*(1+$AR53) -> 3.1486499 | ... AQ53: =AP53*(1+$AR53) -> 3.129893 | AR53: -0.002983
A54: RKI000:ga_SpaceCooling | B54: Space Cooling | C54: 0.058618 | D54: 0.055422 | E54: 0.060292 | F54: 0.060192 | G54: 0.060163 | H54: 0.060023 | I54: 0.059796 | J54: 0.059542 | K54: 0.059324 | L54: 0.059101 | M54: 0.05881 | N54: 0.058535 | O54: 0.058282 | P54: 0.058023 | Q54: 0.057819 | R54: 0.057719 | S54: 0.057717 | T54: 0.05785 | U54: 0.058006 | V54: 0.058187 | W54: 0.058388 | X54: 0.058543 | Y54: 0.058715 | Z54: 0.058861 | AA54: 0.059042 | AB54: 0.059194 | AC54: 0.059373 | AD54: 0.059533 | AE54: 0.059739 | AF54: 0.05993 | AG54: 0.060134 | AH54: =AG54*(1+$AR54) -> 0.060185234 | AI54: =AH54*(1+$AR54) -> 0.060236512 | AJ54: =AI54*(1+$AR54) -> 0.060287833 | AK54: =AJ54*(1+$AR54) -> 0.060339199 | AL54: =AK54*(1+$AR54) -> 0.060390608 | AM54: =AL54*(1+$AR54) -> 0.060442061 | AN54: =AM54*(1+$AR54) -> 0.060493557 | AO54: =AN54*(1+$AR54) -> 0.060545098 | ... AQ54: =AP54*(1+$AR54) -> 0.06064831 | AR54: 0.000852
A55: RKI000:ga_WaterHeating | B55: Water Heating | C55: 1.007279 | D55: 1.004169 | E55: 1.007347 | F55: 1.014073 | G55: 1.023789 | H55: 1.033103 | I55: 1.041576 | J55: 1.049033 | K55: 1.056876 | L55: 1.064852 | M55: 1.070652 | N55: 1.076483 | O55: 1.082882 | P55: 1.089521 | Q55: 1.095863 | R55: 1.10233 | S55: 1.108471 | T55: 1.114128 | U55: 1.119485 | V55: 1.124763 | W55: 1.130038 | X55: 1.135069 | Y55: 1.139977 | Z55: 1.145107 | AA55: 1.150508 | AB55: 1.156279 | AC55: 1.16249 | AD55: 1.168953 | AE55: 1.175813 | AF55: 1.18275 | AG55: 1.189524 | AH55: =AG55*(1+$AR55) -> 1.1961366 | AI55: =AH55*(1+$AR55) -> 1.2027859 | AJ55: =AI55*(1+$AR55) -> 1.2094722 | AK55: =AJ55*(1+$AR55) -> 1.2161956 | AL55: =AK55*(1+$AR55) -> 1.2229565 | AM55: =AL55*(1+$AR55) -> 1.2297549 | AN55: =AM55*(1+$AR55) -> 1.2365911 | AO55: =AN55*(1+$AR55) -> 1.2434653 | ... AQ55: =AP55*(1+$AR55) -> 1.2573286 | AR55: 0.005559
A56: RKI000:ga_Cooking | B56: Cooking | C56: 0.103456 | D56: 0.103327 | E56: 0.103488 | F56: 0.103641 | G56: 0.103815 | H56: 0.10403 | I56: 0.10424 | J56: 0.104418 | K56: 0.104596 | L56: 0.104837 | M56: 0.105138 | N56: 0.105513 | O56: 0.105978 | P56: 0.10654 | Q56: 0.107144 | R56: 0.10781 | S56: 0.108522 | T56: 0.109274 | U56: 0.110047 | V56: 0.110843 | W56: 0.11167 | X56: 0.112526 | Y56: 0.113409 | Z56: 0.114322 | AA56: 0.115263 | AB56: 0.116226 | AC56: 0.117205 | AD56: 0.118188 | AE56: 0.119165 | AF56: 0.120132 | AG56: 0.121081 | AH56: =AG56*(1+$AR56) -> 0.12171752 | AI56: =AH56*(1+$AR56) -> 0.12235739 | AJ56: =AI56*(1+$AR56) -> 0.12300062 | AK56: =AJ56*(1+$AR56) -> 0.12364724 | AL56: =AK56*(1+$AR56) -> 0.12429725 | AM56: =AL56*(1+$AR56) -> 0.12495068 | AN56: =AM56*(1+$AR56) -> 0.12560755 | AO56: =AN56*(1+$AR56) -> 0.12626787 | ... AQ56: =AP56*(1+$AR56) -> 0.12759894 | AR56: 0.005257
A57: RKI000:ga_ClothesDryers | B57: Clothes Dryers | C57: 0.039427 | D57: 0.039794 | E57: 0.040383 | F57: 0.041098 | G57: 0.041912 | H57: 0.042688 | I57: 0.043422 | J57: 0.044122 | K57: 0.044799 | L57: 0.04545 | M57: 0.045976 | N57: 0.046544 | O57: 0.047158 | P57: 0.047801 | Q57: 0.048443 | R57: 0.049087 | S57: 0.049716 | T57: 0.050362 | U57: 0.051031 | V57: 0.051721 | W57: 0.052427 | X57: 0.053131 | Y57: 0.053831 | Z57: 0.054534 | AA57: 0.055235 | AB57: 0.055935 | AC57: 0.056636 | AD57: 0.057333 | AE57: 0.058035 | AF57: 0.058729 | AG57: 0.059408 | AH57: =AG57*(1+$AR57) -> 0.060225454 | AI57: =AH57*(1+$AR57) -> 0.061054156 | AJ57: =AI57*(1+$AR57) -> 0.061894262 | AK57: =AJ57*(1+$AR57) -> 0.062745927 | AL57: =AK57*(1+$AR57) -> 0.063609311 | AM57: =AL57*(1+$AR57) -> 0.064484575 | AN57: =AM57*(1+$AR57) -> 0.065371882 | AO57: =AN57*(1+$AR57) -> 0.066271399 | ... AQ57: =AP57*(1+$AR57) -> 0.068107736 | AR57: 0.01376
A58: RKI000:ga_OtherNatGas | B58: Other Uses 6/ | C58: 0.233372 | D58: 0.231855 | E58: 0.231502 | F58: 0.231786 | G58: 0.232411 | H58: 0.232655 | I58: 0.232517 | J58: 0.232038 | K58: 0.231477 | L58: 0.23081 | M58: 0.229433 | N58: 0.228332 | O58: 0.227513 | P58: 0.226939 | Q58: 0.22645 | R58: 0.226059 | S58: 0.225705 | T58: 0.225355 | U58: 0.225028 | V58: 0.224728 | W58: 0.224433 | X58: 0.224098 | Y58: 0.223732 | Z58: 0.223368 | AA58: 0.223001 | AB58: 0.222637 | AC58: 0.222293 | AD58: 0.221954 | AE58: 0.22166 | AF58: 0.221362 | AG58: 0.221026 | AH58: =AG58*(1+$AR58) -> 0.22062594 | AI58: =AH58*(1+$AR58) -> 0.22022661 | AJ58: =AI58*(1+$AR58) -> 0.219828 | AK58: =AJ58*(1+$AR58) -> 0.21943011 | AL58: =AK58*(1+$AR58) -> 0.21903294 | AM58: =AL58*(1+$AR58) -> 0.21863649 | AN58: =AM58*(1+$AR58) -> 0.21824076 | AO58: =AN58*(1+$AR58) -> 0.21784575 | ... AQ58: =AP58*(1+$AR58) -> 0.21705786 | AR58: -0.00181
A59: RKI000:ga_DeliveredEner | B59: Delivered Energy | C59: 4.96935 | D59: 4.841384 | E59: 4.981184 | F59: 4.986392 | G59: 5.001907 | H59: 5.008203 | I59: 5.004495 | J59: 4.99448 | K59: 4.985316 | L59: 4.974687 | M59: 4.95764 | N59: 4.943475 | O59: 4.932878 | P59: 4.923977 | Q59: 4.915745 | R59: 4.910232 | S59: 4.905311 | T59: 4.900348 | U59: 4.896626 | V59: 4.893885 | W59: 4.892605 | X59: 4.890516 | Y59: 4.88767 | Z59: 4.884768 | AA59: 4.882187 | AB59: 4.879915 | AC59: 4.878683 | AD59: 4.877585 | AE59: 4.877605 | AF59: 4.877148 | AG59: 4.87598 | AH59: =AG59*(1+$AR59) -> 4.8728984 | AI59: =AH59*(1+$AR59) -> 4.8698187 | AJ59: =AI59*(1+$AR59) -> 4.866741 | AK59: =AJ59*(1+$AR59) -> 4.8636652 | AL59: =AK59*(1+$AR59) -> 4.8605914 | AM59: =AL59*(1+$AR59) -> 4.8575195 | AN59: =AM59*(1+$AR59) -> 4.8544495 | AO59: =AN59*(1+$AR59) -> 4.8513815 | ... AQ59: =AP59*(1+$AR59) -> 4.8452513 | AR59: -0.000632
B61: Distillate Fuel Oil 7/
A62: RKI000:ha_SpaceHeating | B62: Space Heating | C62: 0.372664 | D62: 0.399955 | E62: 0.399688 | F62: 0.389283 | G62: 0.379513 | H62: 0.371232 | I62: 0.363199 | J62: 0.355843 | K62: 0.349209 | L62: 0.343014 | M62: 0.337038 | N62: 0.331464 | O62: 0.326065 | P62: 0.320905 | Q62: 0.315898 | R62: 0.311373 | S62: 0.307099 | T62: 0.302775 | U62: 0.298363 | V62: 0.294289 | W62: 0.290039 | X62: 0.285819 | Y62: 0.281613 | Z62: 0.277426 | AA62: 0.273195 | AB62: 0.268874 | AC62: 0.264632 | AD62: 0.260426 | AE62: 0.256324 | AF62: 0.252154 | AG62: 0.247963 | AH62: =AG62*(1+$AR62) -> 0.24461848 | AI62: =AH62*(1+$AR62) -> 0.24131906 | AJ62: =AI62*(1+$AR62) -> 0.23806415 | AK62: =AJ62*(1+$AR62) -> 0.23485314 | AL62: =AK62*(1+$AR62) -> 0.23168544 | AM62: =AL62*(1+$AR62) -> 0.22856047 | AN62: =AM62*(1+$AR62) -> 0.22547764 | AO62: =AN62*(1+$AR62) -> 0.2224364 | ... AQ62: =AP62*(1+$AR62) -> 0.21647642 | AR62: -0.013488
A63: RKI000:ha_WaterHeating | B63: Water Heating | C63: 0.048759 | D63: 0.047108 | E63: 0.045228 | F63: 0.043108 | G63: 0.041235 | H63: 0.039721 | I63: 0.038404 | J63: 0.037331 | K63: 0.036495 | L63: 0.035866 | M63: 0.035412 | N63: 0.034932 | O63: 0.034422 | P63: 0.033898 | Q63: 0.03336 | R63: 0.032838 | S63: 0.032329 | T63: 0.031798 | U63: 0.031244 | V63: 0.030722 | W63: 0.030176 | X63: 0.029644 | Y63: 0.029136 | Z63: 0.028658 | AA63: 0.028199 | AB63: 0.02775 | AC63: 0.02733 | AD63: 0.026935 | AE63: 0.026564 | AF63: 0.026194 | AG63: 0.025829 | AH63: =AG63*(1+$AR63) -> 0.025287702 | AI63: =AH63*(1+$AR63) -> 0.024757747 | AJ63: =AI63*(1+$AR63) -> 0.024238899 | AK63: =AJ63*(1+$AR63) -> 0.023730925 | AL63: =AK63*(1+$AR63) -> 0.023233596 | AM63: =AL63*(1+$AR63) -> 0.022746689 | AN63: =AM63*(1+$AR63) -> 0.022269987 | AO63: =AN63*(1+$AR63) -> 0.021803275 | ... AQ63: =AP63*(1+$AR63) -> 0.020898988 | AR63: -0.020957
A64: RKI000:Other_ha_ha | B64: Other Uses 8/ | C64: 0.007851 | D64: 0.007902 | E64: 0.007891 | F64: 0.007813 | G64: 0.007739 | H64: 0.007688 | I64: 0.00764 | J64: 0.007599 | K64: 0.007566 | L64: 0.007536 | M64: 0.007505 | N64: 0.007479 | O64: 0.007454 | P64: 0.00743 | Q64: 0.007408 | R64: 0.007392 | S64: 0.00738 | T64: 0.007363 | U64: 0.007342 | V64: 0.007326 | W64: 0.007302 | X64: 0.007279 | Y64: 0.007256 | Z64: 0.007236 | AA64: 0.007214 | AB64: 0.00719 | AC64: 0.007168 | AD64: 0.007148 | AE64: 0.007131 | AF64: 0.007112 | AG64: 0.007092 | AH64: =AG64*(1+$AR64) -> 0.007068029 | AI64: =AH64*(1+$AR64) -> 0.0070441391 | AJ64: =AI64*(1+$AR64) -> 0.0070203299 | AK64: =AJ64*(1+$AR64) -> 0.0069966012 | AL64: =AK64*(1+$AR64) -> 0.0069729527 | AM64: =AL64*(1+$AR64) -> 0.0069493841 | AN64: =AM64*(1+$AR64) -> 0.0069258952 | AO64: =AN64*(1+$AR64) -> 0.0069024857 | ... AQ64: =AP64*(1+$AR64) -> 0.0068559037 | AR64: -0.00338
A65: RKI000:ha_DeliveredEner | B65: Delivered Energy | C65: 0.429274 | D65: 0.454966 | E65: 0.452806 | F65: 0.440204 | G65: 0.428487 | H65: 0.418641 | I65: 0.409243 | J65: 0.400773 | K65: 0.39327 | L65: 0.386416 | M65: 0.379955 | N65: 0.373876 | O65: 0.367941 | P65: 0.362233 | Q65: 0.356666 | R65: 0.351603 | S65: 0.346807 | T65: 0.341936 | U65: 0.336949 | V65: 0.332337 | W65: 0.327518 | X65: 0.322742 | Y65: 0.318006 | Z65: 0.313319 | AA65: 0.308608 | AB65: 0.303814 | AC65: 0.299129 | AD65: 0.294509 | AE65: 0.290019 | AF65: 0.28546 | AG65: 0.280897 | AH65: =AG65*(1+$AR65) -> 0.27695405 | AI65: =AH65*(1+$AR65) -> 0.27306644 | AJ65: =AI65*(1+$AR65) -> 0.26923341 | AK65: =AJ65*(1+$AR65) -> 0.26545418 | AL65: =AK65*(1+$AR65) -> 0.261728 | AM65: =AL65*(1+$AR65) -> 0.25805413 | AN65: =AM65*(1+$AR65) -> 0.25443182 | AO65: =AN65*(1+$AR65) -> 0.25086036 | ... AQ65: =AP65*(1+$AR65) -> 0.24386714 | AR65: -0.014037
AH66: =AG66*(1+$AR66) -> 0 | AI66: =AH66*(1+$AR66) -> 0 | AJ66: =AI66*(1+$AR66) -> 0 | AK66: =AJ66*(1+$AR66) -> 0 | AL66: =AK66*(1+$AR66) -> 0 | AM66: =AL66*(1+$AR66) -> 0 | AN66: =AM66*(1+$AR66) -> 0 | AO66: =AN66*(1+$AR66) -> 0 | ... AQ66: =AP66*(1+$AR66) -> 0
B67: Propane | AH67: =AG67*(1+$AR67) -> 0 | AI67: =AH67*(1+$AR67) -> 0 | AJ67: =AI67*(1+$AR67) -> 0 | AK67: =AJ67*(1+$AR67) -> 0 | AL67: =AK67*(1+$AR67) -> 0 | AM67: =AL67*(1+$AR67) -> 0 | AN67: =AM67*(1+$AR67) -> 0 | AO67: =AN67*(1+$AR67) -> 0 | ... AQ67: =AP67*(1+$AR67) -> 0
A68: RKI000:ia_SpaceHeating | B68: Space Heating | C68: 0.300826 | D68: 0.319245 | E68: 0.316427 | F68: 0.313786 | G68: 0.311282 | H68: 0.308732 | I68: 0.306312 | J68: 0.303989 | K68: 0.301527 | L68: 0.298858 | M68: 0.295637 | N68: 0.292482 | O68: 0.289513 | P68: 0.28679 | Q68: 0.284197 | R68: 0.281868 | S68: 0.27961 | T68: 0.277262 | U68: 0.274919 | V68: 0.272692 | W68: 0.270642 | X68: 0.268655 | Y68: 0.266657 | Z68: 0.26476 | AA68: 0.262848 | AB68: 0.260929 | AC68: 0.258979 | AD68: 0.25697 | AE68: 0.254948 | AF68: 0.252907 | AG68: 0.250867 | AH68: =AG68*(1+$AR68) -> 0.24935302 | AI68: =AH68*(1+$AR68) -> 0.24784817 | AJ68: =AI68*(1+$AR68) -> 0.24635241 | AK68: =AJ68*(1+$AR68) -> 0.24486567 | AL68: =AK68*(1+$AR68) -> 0.24338791 | AM68: =AL68*(1+$AR68) -> 0.24191906 | AN68: =AM68*(1+$AR68) -> 0.24045908 | AO68: =AN68*(1+$AR68) -> 0.23900791 | ... AQ68: =AP68*(1+$AR68) -> 0.23613179 | AR68: -0.006035
A69: RKI000:ia_WaterHeating | B69: Water Heating | C69: 0.065346 | D69: 0.063722 | E69: 0.062055 | F69: 0.060465 | G69: 0.059105 | H69: 0.057937 | I69: 0.056967 | J69: 0.056138 | K69: 0.055393 | L69: 0.054729 | M69: 0.054049 | N69: 0.053271 | O69: 0.052457 | P69: 0.051632 | Q69: 0.050781 | R69: 0.049942 | S69: 0.049103 | T69: 0.048235 | U69: 0.047364 | V69: 0.046527 | W69: 0.045739 | X69: 0.044994 | Y69: 0.044292 | Z69: 0.043656 | AA69: 0.043064 | AB69: 0.042516 | AC69: 0.041997 | AD69: 0.041497 | AE69: 0.041015 | AF69: 0.040548 | AG69: 0.040094 | AH69: =AG69*(1+$AR69) -> 0.039446482 | AI69: =AH69*(1+$AR69) -> 0.038809421 | AJ69: =AI69*(1+$AR69) -> 0.038182649 | AK69: =AJ69*(1+$AR69) -> 0.037565999 | AL69: =AK69*(1+$AR69) -> 0.036959308 | AM69: =AL69*(1+$AR69) -> 0.036362416 | AN69: =AM69*(1+$AR69) -> 0.035775163 | AO69: =AN69*(1+$AR69) -> 0.035197394 | ... AQ69: =AP69*(1+$AR69) -> 0.034069698 | AR69: -0.01615
A70: RKI000:ia_Cooking | B70: Cooking | C70: 0.017067 | D70: 0.016859 | E70: 0.016696 | F70: 0.016528 | G70: 0.016358 | H70: 0.016189 | I70: 0.01601 | J70: 0.015815 | K70: 0.015609 | L70: 0.015392 | M70: 0.015163 | N70: 0.014927 | O70: 0.014685 | P70: 0.01448 | Q70: 0.014313 | R70: 0.014186 | S70: 0.014101 | T70: 0.014056 | U70: 0.014005 | V70: 0.01395 | W70: 0.01389 | X70: 0.013826 | Y70: 0.013758 | Z70: 0.013687 | AA70: 0.013616 | AB70: 0.013546 | AC70: 0.01348 | AD70: 0.013417 | AE70: 0.013359 | AF70: 0.013304 | AG70: 0.01325 | AH70: =AG70*(1+$AR70) -> 0.013138687 | AI70: =AH70*(1+$AR70) -> 0.013028309 | AJ70: =AI70*(1+$AR70) -> 0.012918858 | AK70: =AJ70*(1+$AR70) -> 0.012810326 | AL70: =AK70*(1+$AR70) -> 0.012702707 | AM70: =AL70*(1+$AR70) -> 0.012595992 | AN70: =AM70*(1+$AR70) -> 0.012490173 | AO70: =AN70*(1+$AR70) -> 0.012385243 | ... AQ70: =AP70*(1+$AR70) -> 0.01217802 | AR70: -0.008401
A71: RKI000:ia_OtherUses | B71: Other Uses 9/ | C71: 0.071942 | D71: 0.074219 | E71: 0.076272 | F71: 0.078184 | G71: 0.080132 | H71: 0.082117 | I71: 0.08416 | J71: 0.086215 | K71: 0.088203 | L71: 0.090113 | M71: 0.091786 | N71: 0.093445 | O71: 0.095152 | P71: 0.096924 | Q71: 0.098706 | R71: 0.100542 | S71: 0.102393 | T71: 0.104196 | U71: 0.105976 | V71: 0.107785 | W71: 0.109637 | X71: 0.11151 | Y71: 0.113397 | Z71: 0.115342 | AA71: 0.117306 | AB71: 0.119287 | AC71: 0.121262 | AD71: 0.123226 | AE71: 0.125186 | AF71: 0.127143 | AG71: 0.129101 | AH71: =AG71*(1+$AR71) -> 0.13164197 | AI71: =AH71*(1+$AR71) -> 0.13423294 | AJ71: =AI71*(1+$AR71) -> 0.13687492 | AK71: =AJ71*(1+$AR71) -> 0.13956889 | AL71: =AK71*(1+$AR71) -> 0.14231588 | AM71: =AL71*(1+$AR71) -> 0.14511694 | AN71: =AM71*(1+$AR71) -> 0.14797314 | AO71: =AN71*(1+$AR71) -> 0.15088554 | ... AQ71: =AP71*(1+$AR71) -> 0.15688345 | AR71: 0.019682
A72: RKI000:ia_DeliveredEner | B72: Delivered Energy | C72: 0.45518 | D72: 0.474045 | E72: 0.47145 | F72: 0.468962 | G72: 0.466877 | H72: 0.464974 | I72: 0.46345 | J72: 0.462157 | K72: 0.460731 | L72: 0.459092 | M72: 0.456636 | N72: 0.454125 | O72: 0.451806 | P72: 0.449826 | Q72: 0.447996 | R72: 0.446539 | S72: 0.445206 | T72: 0.443749 | U72: 0.442264 | V72: 0.440953 | W72: 0.439908 | X72: 0.438985 | Y72: 0.438105 | Z72: 0.437445 | AA72: 0.436834 | AB72: 0.436278 | AC72: 0.435718 | AD72: 0.435111 | AE72: 0.434508 | AF72: 0.433901 | AG72: 0.433312 | AH72: =AG72*(1+$AR72) -> 0.43260137 | AI72: =AH72*(1+$AR72) -> 0.4318919 | AJ72: =AI72*(1+$AR72) -> 0.4311836 | AK72: =AJ72*(1+$AR72) -> 0.43047646 | AL72: =AK72*(1+$AR72) -> 0.42977048 | AM72: =AL72*(1+$AR72) -> 0.42906565 | AN72: =AM72*(1+$AR72) -> 0.42836199 | AO72: =AN72*(1+$AR72) -> 0.42765947 | ... AQ72: =AP72*(1+$AR72) -> 0.4262579 | AR72: -0.00164
AH73: =AG73*(1+$AR73) -> 0 | AI73: =AH73*(1+$AR73) -> 0 | AJ73: =AI73*(1+$AR73) -> 0 | AK73: =AJ73*(1+$AR73) -> 0 | AL73: =AK73*(1+$AR73) -> 0 | AM73: =AL73*(1+$AR73) -> 0 | AN73: =AM73*(1+$AR73) -> 0 | AO73: =AN73*(1+$AR73) -> 0 | ... AQ73: =AP73*(1+$AR73) -> 0
A74: RKI000:ja_MarketedRenew | B74: Marketed Renewables (wood) 10/ | C74: 0.457513 | D74: 0.454262 | E74: 0.442685 | F74: 0.44422 | G74: 0.445592 | H74: 0.442511 | I74: 0.439175 | J74: 0.43576 | K74: 0.431667 | L74: 0.427109 | M74: 0.422399 | N74: 0.416737 | O74: 0.410947 | P74: 0.404757 | Q74: 0.398165 | R74: 0.390633 | S74: 0.38231 | T74: 0.375142 | U74: 0.369302 | V74: 0.362859 | W74: 0.358009 | X74: 0.353523 | Y74: 0.349097 | Z74: 0.344771 | AA74: 0.341088 | AB74: 0.33825 | AC74: 0.335486 | AD74: 0.332267 | AE74: 0.328579 | AF74: 0.325327 | AG74: 0.322186 | AH74: =AG74*(1+$AR74) -> 0.31844188 | AI74: =AH74*(1+$AR74) -> 0.31474126 | AJ74: =AI74*(1+$AR74) -> 0.31108366 | AK74: =AJ74*(1+$AR74) -> 0.30746855 | AL74: =AK74*(1+$AR74) -> 0.30389546 | AM74: =AL74*(1+$AR74) -> 0.30036389 | AN74: =AM74*(1+$AR74) -> 0.29687336 | AO74: =AN74*(1+$AR74) -> 0.2934234 | ... AQ74: =AP74*(1+$AR74) -> 0.28664328 | AR74: -0.011621
B76: Energy Consumption by End Use 1/
A77: RKI000:ka_SpaceHeating | B77: Space Heating | C77: 5.307185 | D77: 5.27857 | E77: 5.40344 | F77: 5.385718 | G77: 5.377212 | H77: 5.357728 | I77: 5.328801 | J77: 5.294736 | K77: 5.260876 | L77: 5.224958 | M77: 5.184915 | N77: 5.146564 | O77: 5.110921 | P77: 5.076702 | Q77: 5.043309 | R77: 5.012675 | S77: 4.982251 | T77: 4.95306 | U77: 4.926447 | V77: 4.900547 | W77: 4.877836 | X77: 4.854891 | Y77: 4.831365 | Z77: 4.808023 | AA77: 4.785222 | AB77: 4.762963 | AC77: 4.741679 | AD77: 4.719794 | AE77: 4.698342 | AF77: 4.677184 | AG77: 4.655806 | AH77: =AG77*(1+$AR77) -> 4.63553 | AI77: =AH77*(1+$AR77) -> 4.6153422 | AJ77: =AI77*(1+$AR77) -> 4.5952424 | AK77: =AJ77*(1+$AR77) -> 4.5752301 | AL77: =AK77*(1+$AR77) -> 4.555305 | AM77: =AL77*(1+$AR77) -> 4.5354667 | AN77: =AM77*(1+$AR77) -> 4.5157147 | AO77: =AN77*(1+$AR77) -> 4.4960488 | ... AQ77: =AP77*(1+$AR77) -> 4.4569734 | AR77: -0.004355
A78: RKI000:ka_SpaceCooling | B78: Space Cooling | C78: 0.864001 | D78: 0.821723 | E78: 0.922358 | F78: 0.937503 | G78: 0.953828 | H78: 0.970874 | I78: 0.987441 | J78: 1.003375 | K78: 1.019232 | L78: 1.035058 | M78: 1.050471 | N78: 1.066175 | O78: 1.082699 | P78: 1.100006 | Q78: 1.118483 | R78: 1.138818 | S78: 1.159827 | T78: 1.182183 | U78: 1.204325 | V78: 1.226425 | W78: 1.249226 | X78: 1.271599 | Y78: 1.295016 | Z78: 1.318424 | AA78: 1.342871 | AB78: 1.367048 | AC78: 1.392083 | AD78: 1.417349 | AE78: 1.444345 | AF78: 1.471828 | AG78: 1.500366 | AH78: =AG78*(1+$AR78) -> 1.5282233 | AI78: =AH78*(1+$AR78) -> 1.5565978 | AJ78: =AI78*(1+$AR78) -> 1.5854992 | AK78: =AJ78*(1+$AR78) -> 1.6149371 | AL78: =AK78*(1+$AR78) -> 1.6449217 | AM78: =AL78*(1+$AR78) -> 1.6754629 | AN78: =AM78*(1+$AR78) -> 1.7065713 | AO78: =AN78*(1+$AR78) -> 1.7382572 | ... AQ78: =AP78*(1+$AR78) -> 1.8034048 | AR78: 0.018567
A79: RKI000:ka_WaterHeating | B79: Water Heating | C79: 1.728931 | D79: 1.725143 | E79: 1.727704 | F79: 1.732736 | G79: 1.741975 | H79: 1.750933 | I79: 1.758603 | J79: 1.765158 | K79: 1.772085 | L79: 1.779346 | M79: 1.784596 | N79: 1.789688 | O79: 1.79562 | P79: 1.802165 | Q79: 1.808823 | R79: 1.816295 | S79: 1.823754 | T79: 1.830839 | U79: 1.837644 | V79: 1.844173 | W79: 1.850649 | X79: 1.856842 | Y79: 1.863041 | Z79: 1.86975 | AA79: 1.876945 | AB79: 1.884634 | AC79: 1.893142 | AD79: 1.902191 | AE79: 1.912034 | AF79: 1.922478 | AG79: 1.933017 | AH79: =AG79*(1+$AR79) -> 1.9402194 | AI79: =AH79*(1+$AR79) -> 1.9474487 | AJ79: =AI79*(1+$AR79) -> 1.9547049 | AK79: =AJ79*(1+$AR79) -> 1.9619881 | AL79: =AK79*(1+$AR79) -> 1.9692985 | AM79: =AL79*(1+$AR79) -> 1.9766361 | AN79: =AM79*(1+$AR79) -> 1.984001 | AO79: =AN79*(1+$AR79) -> 1.9913934 | ... AQ79: =AP79*(1+$AR79) -> 2.0062609 | AR79: 0.003726
A80: RKI000:ka_Refrigeration | B80: Refrigeration | C80: 0.297571 | D80: 0.295346 | E80: 0.293794 | F80: 0.292089 | G80: 0.290616 | H80: 0.289474 | I80: 0.288541 | J80: 0.287696 | K80: 0.286959 | L80: 0.286376 | M80: 0.28598 | N80: 0.285826 | O80: 0.285965 | P80: 0.286393 | Q80: 0.287106 | R80: 0.288174 | S80: 0.289567 | T80: 0.291258 | U80: 0.293256 | V80: 0.295533 | W80: 0.298126 | X80: 0.301018 | Y80: 0.30418 | Z80: 0.307324 | AA80: 0.31044 | AB80: 0.31352 | AC80: 0.316558 | AD80: 0.319522 | AE80: 0.322411 | AF80: 0.325241 | AG80: 0.328011 | AH80: =AG80*(1+$AR80) -> 0.32907769 | AI80: =AH80*(1+$AR80) -> 0.33014785 | AJ80: =AI80*(1+$AR80) -> 0.33122149 | AK80: =AJ80*(1+$AR80) -> 0.33229863 | AL80: =AK80*(1+$AR80) -> 0.33337926 | AM80: =AL80*(1+$AR80) -> 0.33446341 | AN80: =AM80*(1+$AR80) -> 0.33555109 | AO80: =AN80*(1+$AR80) -> 0.3366423 | ... AQ80: =AP80*(1+$AR80) -> 0.33883538 | AR80: 0.003252
A81: RKI000:ka_Cooking | B81: Cooking | C81: 0.17553 | D81: 0.175348 | E81: 0.175644 | F81: 0.175919 | G81: 0.176218 | H81: 0.176576 | I81: 0.176914 | J81: 0.177171 | K81: 0.177388 | L81: 0.177618 | M81: 0.177857 | N81: 0.178115 | O81: 0.178418 | P81: 0.178861 | Q81: 0.179404 | R81: 0.180086 | S81: 0.180891 | T81: 0.181818 | U81: 0.18275 | V81: 0.183692 | W81: 0.184658 | X81: 0.185641 | Y81: 0.18664 | Z81: 0.187659 | AA81: 0.188696 | AB81: 0.189752 | AC81: 0.190824 | AD81: 0.191895 | AE81: 0.192964 | AF81: 0.19403 | AG81: 0.195087 | AH81: =AG81*(1+$AR81) -> 0.19577527 | AI81: =AH81*(1+$AR81) -> 0.19646596 | AJ81: =AI81*(1+$AR81) -> 0.19715909 | AK81: =AJ81*(1+$AR81) -> 0.19785467 | AL81: =AK81*(1+$AR81) -> 0.1985527 | AM81: =AL81*(1+$AR81) -> 0.1992532 | AN81: =AM81*(1+$AR81) -> 0.19995616 | AO81: =AN81*(1+$AR81) -> 0.20066161 | ... AQ81: =AP81*(1+$AR81) -> 0.20207997 | AR81: 0.003528
A82: RKI000:ka_ClothesDryers | B82: Clothes Dryers | C82: 0.255846 | D82: 0.26013 | E82: 0.264514 | F82: 0.26879 | G82: 0.273535 | H82: 0.278295 | I82: 0.282766 | J82: 0.28688 | K82: 0.290861 | L82: 0.294776 | M82: 0.298522 | N82: 0.302141 | O82: 0.305836 | P82: 0.309653 | Q82: 0.313678 | R82: 0.317928 | S82: 0.322286 | T82: 0.326606 | U82: 0.33086 | V82: 0.335084 | W82: 0.339318 | X82: 0.343501 | Y82: 0.347668 | Z82: 0.351884 | AA82: 0.356109 | AB82: 0.360281 | AC82: 0.36453 | AD82: 0.368824 | AE82: 0.373221 | AF82: 0.377784 | AG82: 0.382406 | AH82: =AG82*(1+$AR82) -> 0.38756351 | AI82: =AH82*(1+$AR82) -> 0.39279058 | AJ82: =AI82*(1+$AR82) -> 0.39808815 | AK82: =AJ82*(1+$AR82) -> 0.40345716 | AL82: =AK82*(1+$AR82) -> 0.40889859 | AM82: =AL82*(1+$AR82) -> 0.4144134 | AN82: =AM82*(1+$AR82) -> 0.4200026 | AO82: =AN82*(1+$AR82) -> 0.42566717 | ... AQ82: =AP82*(1+$AR82) -> 0.43722655 | AR82: 0.013487
A83: RKI000:ka_Freezers | B83: Freezers | C83: 0.069181 | D83: 0.068847 | E83: 0.068698 | F83: 0.068526 | G83: 0.06834 | H83: 0.068157 | I83: 0.067953 | J83: 0.067707 | K83: 0.067461 | L83: 0.067224 | M83: 0.066995 | N83: 0.066774 | O83: 0.06657 | P83: 0.066383 | Q83: 0.066214 | R83: 0.066077 | S83: 0.065975 | T83: 0.065902 | U83: 0.065862 | V83: 0.065855 | W83: 0.065888 | X83: 0.065966 | Y83: 0.066082 | Z83: 0.066247 | AA83: 0.066465 | AB83: 0.066737 | AC83: 0.067063 | AD83: 0.067429 | AE83: 0.06779 | AF83: 0.068152 | AG83: 0.068514 | AH83: =AG83*(1+$AR83) -> 0.06849187 | AI83: =AH83*(1+$AR83) -> 0.068469747 | AJ83: =AI83*(1+$AR83) -> 0.068447631 | AK83: =AJ83*(1+$AR83) -> 0.068425523 | AL83: =AK83*(1+$AR83) -> 0.068403421 | AM83: =AL83*(1+$AR83) -> 0.068381327 | AN83: =AM83*(1+$AR83) -> 0.06835924 | AO83: =AN83*(1+$AR83) -> 0.06833716 | ... AQ83: =AP83*(1+$AR83) -> 0.068293021 | AR83: -0.000323
A84: RKI000:ka_Lighting | B84: Lighting | C84: 0.211245 | D84: 0.204658 | E84: 0.202521 | F84: 0.20193 | G84: 0.202401 | H84: 0.201491 | I84: 0.200873 | J84: 0.200838 | K84: 0.201379 | L84: 0.202196 | M84: 0.200463 | N84: 0.199204 | O84: 0.198392 | P84: 0.197965 | Q84: 0.197945 | R84: 0.198286 | S84: 0.198748 | T84: 0.199251 | U84: 0.199757 | V84: 0.200288 | W84: 0.197496 | X84: 0.195328 | Y84: 0.193641 | Z84: 0.192433 | AA84: 0.191624 | AB84: 0.191038 | AC84: 0.190629 | AD84: 0.190303 | AE84: 0.190083 | AF84: 0.190014 | AG84: 0.190188 | AH84: =AG84*(1+$AR84) -> 0.18952348 | AI84: =AH84*(1+$AR84) -> 0.18886129 | AJ84: =AI84*(1+$AR84) -> 0.18820141 | AK84: =AJ84*(1+$AR84) -> 0.18754383 | AL84: =AK84*(1+$AR84) -> 0.18688855 | AM84: =AL84*(1+$AR84) -> 0.18623556 | AN84: =AM84*(1+$AR84) -> 0.18558486 | AO84: =AN84*(1+$AR84) -> 0.18493642 | ... AQ84: =AP84*(1+$AR84) -> 0.18364635 | AR84: -0.003494
A85: RKI000:ka_ClothesWasher | B85: Clothes Washers 2/ | C85: 0.036779 | D85: 0.037026 | E85: 0.037375 | F85: 0.037721 | G85: 0.038075 | H85: 0.038449 | I85: 0.038824 | J85: 0.03918 | K85: 0.039523 | L85: 0.039855 | M85: 0.040193 | N85: 0.040519 | O85: 0.040839 | P85: 0.041152 | Q85: 0.041455 | R85: 0.041759 | S85: 0.04206 | T85: 0.042358 | U85: 0.042653 | V85: 0.042945 | W85: 0.04324 | X85: 0.043535 | Y85: 0.043829 | Z85: 0.044122 | AA85: 0.044416 | AB85: 0.044709 | AC85: 0.045004 | AD85: 0.045295 | AE85: 0.045585 | AF85: 0.045875 | AG85: 0.046168 | AH85: =AG85*(1+$AR85) -> 0.0465192 | AI85: =AH85*(1+$AR85) -> 0.046873072 | AJ85: =AI85*(1+$AR85) -> 0.047229635 | AK85: =AJ85*(1+$AR85) -> 0.047588911 | AL85: =AK85*(1+$AR85) -> 0.04795092 | AM85: =AL85*(1+$AR85) -> 0.048315682 | AN85: =AM85*(1+$AR85) -> 0.04868322 | AO85: =AN85*(1+$AR85) -> 0.049053553 | ... AQ85: =AP85*(1+$AR85) -> 0.049802692 | AR85: 0.007607
A86: RKI000:ka_Dishwashers | B86: Dishwashers 2/ | C86: 0.026617 | D86: 0.026992 | E86: 0.027431 | F86: 0.027859 | G86: 0.028283 | H86: 0.028709 | I86: 0.029123 | J86: 0.029508 | K86: 0.029918 | L86: 0.03036 | M86: 0.03083 | N86: 0.03133 | O86: 0.031868 | P86: 0.032445 | Q86: 0.033062 | R86: 0.033677 | S86: 0.034289 | T86: 0.034896 | U86: 0.035501 | V86: 0.036103 | W86: 0.036706 | X86: 0.037309 | Y86: 0.03791 | Z86: 0.03851 | AA86: 0.03911 | AB86: 0.03971 | AC86: 0.040309 | AD86: 0.040905 | AE86: 0.041499 | AF86: 0.042093 | AG86: 0.042686 | AH86: =AG86*(1+$AR86) -> 0.043363427 | AI86: =AH86*(1+$AR86) -> 0.044051604 | AJ86: =AI86*(1+$AR86) -> 0.044750703 | AK86: =AJ86*(1+$AR86) -> 0.045460897 | AL86: =AK86*(1+$AR86) -> 0.046182361 | AM86: =AL86*(1+$AR86) -> 0.046915276 | AN86: =AM86*(1+$AR86) -> 0.047659821 | AO86: =AN86*(1+$AR86) -> 0.048416182 | ... AQ86: =AP86*(1+$AR86) -> 0.049965106 | AR86: 0.01587
A87: RKI000:ka_ColorTelevisi | B87: Televisions and Related Equipment 3/ | C87: 0.20913 | D87: 0.205162 | E87: 0.202737 | F87: 0.200828 | G87: 0.199926 | H87: 0.199812 | I87: 0.20026 | J87: 0.201233 | K87: 0.20279 | L87: 0.20499 | M87: 0.207745 | N87: 0.210879 | O87: 0.214516 | P87: 0.218628 | Q87: 0.223129 | R87: 0.228027 | S87: 0.233134 | T87: 0.23827 | U87: 0.243305 | V87: 0.248126 | W87: 0.252637 | X87: 0.256616 | Y87: 0.260069 | Z87: 0.263242 | AA87: 0.266345 | AB87: 0.26934 | AC87: 0.272296 | AD87: 0.275205 | AE87: 0.27813 | AF87: 0.281099 | AG87: 0.284057 | AH87: =AG87*(1+$AR87) -> 0.28697142 | AI87: =AH87*(1+$AR87) -> 0.28991575 | AJ87: =AI87*(1+$AR87) -> 0.29289029 | AK87: =AJ87*(1+$AR87) -> 0.29589534 | AL87: =AK87*(1+$AR87) -> 0.29893123 | AM87: =AL87*(1+$AR87) -> 0.30199826 | AN87: =AM87*(1+$AR87) -> 0.30509676 | AO87: =AN87*(1+$AR87) -> 0.30822706 | ... AQ87: =AP87*(1+$AR87) -> 0.31458432 | AR87: 0.01026
A88: RKI000:ka_PersonalCompu | B88: Computers and Related Equipment 4/ | C88: 0.086663 | D88: 0.083815 | E88: 0.081571 | F88: 0.079481 | G88: 0.077709 | H88: 0.076122 | I88: 0.074639 | J88: 0.073224 | K88: 0.071899 | L88: 0.07067 | M88: 0.069487 | N88: 0.068284 | O88: 0.0671 | P88: 0.06591 | Q88: 0.064687 | R88: 0.063421 | S88: 0.062059 | T88: 0.060712 | U88: 0.059373 | V88: 0.058027 | W88: 0.056675 | X88: 0.055295 | Y88: 0.053887 | Z88: 0.052461 | AA88: 0.051003 | AB88: 0.049484 | AC88: 0.047905 | AD88: 0.046248 | AE88: 0.044522 | AF88: 0.042687 | AG88: 0.040729 | AH88: =AG88*(1+$AR88) -> 0.039716681 | AI88: =AH88*(1+$AR88) -> 0.038729523 | AJ88: =AI88*(1+$AR88) -> 0.0377669 | AK88: =AJ88*(1+$AR88) -> 0.036828204 | AL88: =AK88*(1+$AR88) -> 0.035912839 | AM88: =AL88*(1+$AR88) -> 0.035020225 | AN88: =AM88*(1+$AR88) -> 0.034149798 | AO88: =AN88*(1+$AR88) -> 0.033301004 | ... AQ88: =AP88*(1+$AR88) -> 0.031666184 | AR88: -0.024855
... A95: RKI000:la_ElectricityRe | B95: Electricity Related Losses | C95: 9.423895 | D95: 9.476621 | E95: 9.489174 | F95: 9.257663 | G95: 9.044497 | H95: 8.781025 | I95: 8.504918 | J95: 8.31342 | K95: 8.230984 | L95: 8.17648 | M95: 8.19232 | N95: 8.185059 | O95: 8.164425 | P95: 8.170115 | Q95: 8.173469 | R95: 8.198778 | S95: 8.224853 | T95: 8.23952 | U95: 8.258127 | V95: 8.292449 | W95: 8.330718 | X95: 8.36727 | Y95: 8.40609 | Z95: 8.423908 | AA95: 8.409726 | AB95: 8.439298 | AC95: 8.472725 | AD95: 8.503682 | AE95: 8.533015 | AF95: 8.585814 | AG95: 8.639295 | AH95: =AG95*(1+$AR95) -> 8.6143015 | AI95: =AH95*(1+$AR95) -> 8.5893803 | AJ95: =AI95*(1+$AR95) -> 8.5645313 | AK95: =AJ95*(1+$AR95) -> 8.5397541 | AL95: =AK95*(1+$AR95) -> 8.5150486 | AM95: =AL95*(1+$AR95) -> 8.4904145 | AN95: =AM95*(1+$AR95) -> 8.4658518 | AO95: =AN95*(1+$AR95) -> 8.4413601 | ... AQ95: =AP95*(1+$AR95) -> 8.392589 | AR95: -0.002893
B97: Total Energy Consumption by End Use 1/
A98: RKI000:ma_SpaceHeating | B98: Space Heating | C98: 6.51761 | D98: 6.579794 | E98: 6.719017 | F98: 6.657437 | G98: 6.610179 | H98: 6.545724 | I98: 6.467808 | J98: 6.396029 | K98: 6.338858 | L98: 6.283124 | M98: 6.23278 | N98: 6.181098 | O98: 6.129976 | P98: 6.083678 | Q98: 6.037023 | R98: 5.996106 | S98: 5.955264 | T98: 5.914248 | U98: 5.876412 | V98: 5.841048 | W98: 5.810057 | X98: 5.778563 | Y98: 5.746598 | Z98: 5.712856 | AA98: 5.676187 | AB98: 5.644627 | AC98: 5.614811 | AD98: 5.584211 | AE98: 5.553601 | AF98: 5.526089 | AG98: 5.498514 | AH98: =AG98*(1+$AR98) -> 5.4674364 | AI98: =AH98*(1+$AR98) -> 5.4365344 | AJ98: =AI98*(1+$AR98) -> 5.4058072 | AK98: =AJ98*(1+$AR98) -> 5.3752535 | AL98: =AK98*(1+$AR98) -> 5.3448726 | AM98: =AL98*(1+$AR98) -> 5.3146634 | AN98: =AM98*(1+$AR98) -> 5.2846249 | AO98: =AN98*(1+$AR98) -> 5.2547562 | ... AQ98: =AP98*(1+$AR98) -> 5.1955243 | AR98: -0.005652
A99: RKI000:ma_SpaceCooling | B99: Space Cooling | C99: 2.366128 | D99: 2.249679 | E99: 2.527688 | F99: 2.524938 | G99: 2.525652 | H99: 2.517709 | I99: 2.502984 | J99: 2.501515 | K99: 2.518388 | L99: 2.53974 | M99: 2.573649 | N99: 2.604116 | O99: 2.633105 | P99: 2.668165 | Q99: 2.703381 | R99: 2.745875 | S99: 2.789436 | T99: 2.833351 | U99: 2.877506 | V99: 2.924451 | W99: 2.97437 | X99: 3.023025 | Y99: 3.074131 | Z99: 3.12034 | AA99: 3.161524 | AB99: 3.2112 | AC99: 3.26319 | AD99: 3.315017 | AE99: 3.368937 | AF99: 3.428514 | AG99: 3.490087 | AH99: =AG99*(1+$AR99) -> 3.5355977 | AI99: =AH99*(1+$AR99) -> 3.5817019 | AJ99: =AI99*(1+$AR99) -> 3.6284073 | AK99: =AJ99*(1+$AR99) -> 3.6757218 | AL99: =AK99*(1+$AR99) -> 3.7236532 | AM99: =AL99*(1+$AR99) -> 3.7722096 | AN99: =AM99*(1+$AR99) -> 3.8213992 | AO99: =AN99*(1+$AR99) -> 3.8712303 | ... AQ99: =AP99*(1+$AR99) -> 3.9728502 | AR99: 0.01304
A100: RKI000:ma_WaterHeating | B100: Water Heating | C100: 2.862072 | D100: 2.862111 | E100: 2.869363 | F100: 2.845701 | G100: 2.828674 | H100: 2.804127 | I100: 2.774236 | J100: 2.753495 | K100: 2.745571 | L100: 2.741243 | M100: 2.743793 | N100: 2.743618 | O100: 2.742828 | P100: 2.745957 | Q100: 2.748435 | R100: 2.754554 | S100: 2.760983 | T100: 2.76585 | U100: 2.771141 | V100: 2.77755 | W100: 2.784608 | X100: 2.791183 | Y100: 2.797906 | Z100: 2.802966 | AA100: 2.805055 | AB100: 2.812578 | AC100: 2.821633 | AD100: 2.831316 | AE100: 2.841442 | AF100: 2.855138 | AG100: 2.8691 | AH100: =AG100*(1+$AR100) -> 2.8693353 | AI100: =AH100*(1+$AR100) -> 2.8695706 | AJ100: =AI100*(1+$AR100) -> 2.8698059 | AK100: =AJ100*(1+$AR100) -> 2.8700412 | AL100: =AK100*(1+$AR100) -> 2.8702765 | AM100: =AL100*(1+$AR100) -> 2.8705119 | AN100: =AM100*(1+$AR100) -> 2.8707473 | AO100: =AN100*(1+$AR100) -> 2.8709827 | ... AQ100: =AP100*(1+$AR100) -> 2.8714535 | AR100: 8.2e-05
A101: RKI000:ma_Refrigeration | B101: Refrigeration | C101: 0.852572 | D101: 0.845705 | E101: 0.840893 | F101: 0.820605 | G101: 0.801767 | H101: 0.781067 | I101: 0.759946 | J101: 0.744354 | K101: 0.735123 | L101: 0.727896 | M101: 0.725242 | N101: 0.722077 | O101: 0.71876 | P101: 0.717409 | Q101: 0.716114 | R101: 0.716546 | S101: 0.717728 | T101: 0.718993 | U101: 0.721295 | V101: 0.725087 | W101: 0.730016 | X101: 0.735631 | Y101: 0.741915 | Z101: 0.746978 | AA101: 0.750205 | AB101: 0.755602 | AC101: 0.761002 | AD101: 0.766082 | AE101: 0.77056 | AF101: 0.775979 | AG101: 0.781167 | AH101: =AG101*(1+$AR101) -> 0.77889302 | AI101: =AH101*(1+$AR101) -> 0.77662567 | AJ101: =AI101*(1+$AR101) -> 0.77436491 | AK101: =AJ101*(1+$AR101) -> 0.77211073 | AL101: =AK101*(1+$AR101) -> 0.76986312 | AM101: =AL101*(1+$AR101) -> 0.76762205 | AN101: =AM101*(1+$AR101) -> 0.7653875 | AO101: =AN101*(1+$AR101) -> 0.76315946 | ... AQ101: =AP101*(1+$AR101) -> 0.75872281 | AR101: -0.002911
A102: RKI000:ma_Cooking | B102: Cooking | C102: 0.278124 | D102: 0.278138 | E102: 0.278921 | F102: 0.276796 | G102: 0.274794 | H102: 0.272284 | I102: 0.269488 | J102: 0.267548 | K102: 0.266694 | L102: 0.266098 | M102: 0.266262 | N102: 0.266145 | O102: 0.265827 | P102: 0.265911 | Q102: 0.265992 | R102: 0.266436 | S102: 0.267049 | T102: 0.267712 | U102: 0.268426 | V102: 0.269301 | W102: 0.270272 | X102: 0.271245 | Y102: 0.272225 | Z102: 0.272992 | AA102: 0.273433 | AB102: 0.274328 | AC102: 0.275257 | AD102: 0.276157 | AE102: 0.276976 | AF102: 0.278005 | AG102: 0.279024 | AH102: =AG102*(1+$AR102) -> 0.27905413 | AI102: =AH102*(1+$AR102) -> 0.27908427 | AJ102: =AI102*(1+$AR102) -> 0.27911441 | AK102: =AJ102*(1+$AR102) -> 0.27914456 | AL102: =AK102*(1+$AR102) -> 0.27917471 | AM102: =AL102*(1+$AR102) -> 0.27920486 | AN102: =AM102*(1+$AR102) -> 0.27923501 | AO102: =AN102*(1+$AR102) -> 0.27926517 | ... AQ102: =AP102*(1+$AR102) -> 0.27932549 | AR102: 0.000108
A103: RKI000:ma_ClothesDryers | B103: Clothes Dryers | C103: 0.659492 | D103: 0.670714 | E103: 0.68189 | F103: 0.680783 | G103: 0.680924 | H103: 0.67841 | I103: 0.673794 | J103: 0.672206 | K103: 0.675152 | L103: 0.679175 | M103: 0.686429 | N103: 0.692255 | O103: 0.697333 | P103: 0.703734 | Q103: 0.710006 | R103: 0.717561 | S103: 0.725316 | T103: 0.73229 | U103: 0.739302 | V103: 0.74695 | W103: 0.754931 | X103: 0.76274 | Y103: 0.770518 | Z103: 0.77727 | AA103: 0.782322 | AB103: 0.789428 | AC103: 0.79681 | AD103: 0.80416 | AE103: 0.811327 | AF103: 0.819947 | AG103: 0.828637 | AH103: =AG103*(1+$AR103) -> 0.83496696 | AI103: =AH103*(1+$AR103) -> 0.84134527 | AJ103: =AI103*(1+$AR103) -> 0.84777231 | AK103: =AJ103*(1+$AR103) -> 0.85424844 | AL103: =AK103*(1+$AR103) -> 0.86077404 | AM103: =AL103*(1+$AR103) -> 0.8673495 | AN103: =AM103*(1+$AR103) -> 0.87397518 | AO103: =AN103*(1+$AR103) -> 0.88065148 | ... AQ103: =AP103*(1+$AR103) -> 0.89415746 | AR103: 0.007639
A104: RKI000:ma_Freezers | B104: Freezers | C104: 0.198212 | D104: 0.197138 | E104: 0.196626 | F104: 0.192518 | G104: 0.188539 | H104: 0.183903 | I104: 0.178972 | J104: 0.175177 | K104: 0.172821 | L104: 0.170865 | M104: 0.169898 | N104: 0.16869 | O104: 0.167319 | P104: 0.166287 | Q104: 0.165155 | R104: 0.164302 | S104: 0.163528 | T104: 0.162685 | U104: 0.161996 | V104: 0.161575 | W104: 0.161339 | X104: 0.161208 | Y104: 0.161178 | Z104: 0.161019 | AA104: 0.160618 | AB104: 0.16084 | AC104: 0.161218 | AD104: 0.161666 | AE104: 0.162018 | AF104: 0.162601 | AG104: 0.163167 | AH104: =AG104*(1+$AR104) -> 0.16211229 | AI104: =AH104*(1+$AR104) -> 0.16106439 | AJ104: =AI104*(1+$AR104) -> 0.16002327 | AK104: =AJ104*(1+$AR104) -> 0.15898888 | AL104: =AK104*(1+$AR104) -> 0.15796118 | AM104: =AL104*(1+$AR104) -> 0.15694012 | AN104: =AM104*(1+$AR104) -> 0.15592566 | AO104: =AN104*(1+$AR104) -> 0.15491775 | ... AQ104: =AP104*(1+$AR104) -> 0.15292145 | AR104: -0.006464
A105: RKI000:ma_Lighting | B105: Lighting | C105: 0.605238 | D105: 0.586025 | E105: 0.579653 | F105: 0.56731 | G105: 0.558393 | H105: 0.543669 | I105: 0.529051 | J105: 0.519626 | K105: 0.515887 | L105: 0.513932 | M105: 0.508372 | N105: 0.503246 | O105: 0.498649 | P105: 0.495897 | Q105: 0.493726 | R105: 0.493039 | S105: 0.492623 | T105: 0.491866 | U105: 0.491324 | V105: 0.491405 | W105: 0.483605 | X105: 0.477345 | Y105: 0.472304 | Z105: 0.467726 | AA105: 0.463076 | AB105: 0.460413 | AC105: 0.458271 | AD105: 0.456269 | AE105: 0.454297 | AF105: 0.453345 | AG105: 0.452938 | AH105: =AG105*(1+$AR105) -> 0.44858255 | AI105: =AH105*(1+$AR105) -> 0.44426898 | AJ105: =AI105*(1+$AR105) -> 0.43999689 | AK105: =AJ105*(1+$AR105) -> 0.43576588 | AL105: =AK105*(1+$AR105) -> 0.43157555 | AM105: =AL105*(1+$AR105) -> 0.42742552 | AN105: =AM105*(1+$AR105) -> 0.4233154 | AO105: =AN105*(1+$AR105) -> 0.4192448 | ... AQ105: =AP105*(1+$AR105) -> 0.41122065 | AR105: -0.009616
A106: RKI000:ma_ClothesWasher | B106: Clothes Washers 2/ | C106: 0.105377 | D106: 0.106022 | E106: 0.106973 | F106: 0.105974 | G106: 0.105045 | H106: 0.103745 | I106: 0.102253 | J106: 0.101371 | K106: 0.101248 | L106: 0.101302 | M106: 0.101929 | N106: 0.102362 | O106: 0.102648 | P106: 0.103085 | Q106: 0.1034 | R106: 0.103835 | S106: 0.104252 | T106: 0.104564 | U106: 0.104909 | V106: 0.105366 | W106: 0.105882 | X106: 0.106392 | Y106: 0.106901 | Z106: 0.107243 | AA106: 0.107334 | AB106: 0.107752 | AC106: 0.108188 | AD106: 0.108599 | AE106: 0.108947 | AF106: 0.109452 | AG106: 0.109949 | AH106: =AG106*(1+$AR106) -> 0.1101048 | AI106: =AH106*(1+$AR106) -> 0.11026082 | AJ106: =AI106*(1+$AR106) -> 0.11041706 | AK106: =AJ106*(1+$AR106) -> 0.11057352 | AL106: =AK106*(1+$AR106) -> 0.1107302 | AM106: =AL106*(1+$AR106) -> 0.1108871 | AN106: =AM106*(1+$AR106) -> 0.11104423 | AO106: =AN106*(1+$AR106) -> 0.11120158 | ... AQ106: =AP106*(1+$AR106) -> 0.11151695 | AR106: 0.001417
A107: RKI000:ma_Dishwashers | B107: Dishwashers 2/ | C107: 0.076259 | D107: 0.077291 | E107: 0.078512 | F107: 0.078269 | G107: 0.078028 | H107: 0.077464 | I107: 0.076702 | J107: 0.076345 | K107: 0.076644 | L107: 0.077167 | M107: 0.078184 | N107: 0.079149 | O107: 0.0801 | P107: 0.081274 | Q107: 0.082464 | R107: 0.083738 | S107: 0.084989 | T107: 0.086144 | U107: 0.087318 | V107: 0.088578 | W107: 0.089883 | X107: 0.091177 | Y107: 0.092465 | Z107: 0.093603 | AA107: 0.094513 | AB107: 0.095703 | AC107: 0.096902 | AD107: 0.098074 | AE107: 0.099183 | AF107: 0.100428 | AG107: 0.101659 | AH107: =AG107*(1+$AR107) -> 0.10263787 | AI107: =AH107*(1+$AR107) -> 0.10362617 | AJ107: =AI107*(1+$AR107) -> 0.10462399 | AK107: =AJ107*(1+$AR107) -> 0.10563142 | AL107: =AK107*(1+$AR107) -> 0.10664854 | AM107: =AL107*(1+$AR107) -> 0.10767546 | AN107: =AM107*(1+$AR107) -> 0.10871227 | AO107: =AN107*(1+$AR107) -> 0.10975906 | ... AQ107: =AP107*(1+$AR107) -> 0.11188297 | AR107: 0.009629
A108: RKI000:ma_ColorTelevisi | B108: Televisions and Related Equipment 3/ | C108: 0.59918 | D108: 0.587468 | E108: 0.58027 | F108: 0.564214 | G108: 0.551567 | H108: 0.539138 | I108: 0.527435 | J108: 0.520648 | K108: 0.5195 | L108: 0.521034 | M108: 0.52684 | N108: 0.532739 | O108: 0.539176 | P108: 0.547658 | Q108: 0.556541 | R108: 0.566991 | S108: 0.577853 | T108: 0.588187 | U108: 0.598436 | V108: 0.608776 | W108: 0.618627 | X108: 0.627121 | Y108: 0.634326 | Z108: 0.639832 | AA108: 0.643646 | AB108: 0.649126 | AC108: 0.654596 | AD108: 0.659827 | AE108: 0.664728 | AF108: 0.670661 | AG108: 0.67649 | AH108: =AG108*(1+$AR108) -> 0.67923181 | AI108: =AH108*(1+$AR108) -> 0.68198474 | AJ108: =AI108*(1+$AR108) -> 0.68474882 | AK108: =AJ108*(1+$AR108) -> 0.68752411 | AL108: =AK108*(1+$AR108) -> 0.69031065 | AM108: =AL108*(1+$AR108) -> 0.69310848 | AN108: =AM108*(1+$AR108) -> 0.69591764 | AO108: =AN108*(1+$AR108) -> 0.6987382 | ... AQ108: =AP108*(1+$AR108) -> 0.70441365 | AR108: 0.004053
A109: RKI000:ma_PersonalCompu | B109: Computers and Related Equipment 4/ | C109: 0.248299 | D109: 0.239998 | E109: 0.233472 | F109: 0.223297 | G109: 0.214388 | H109: 0.205396 | I109: 0.19658 | J109: 0.189453 | K109: 0.184189 | L109: 0.179624 | M109: 0.176218 | N109: 0.172504 | O109: 0.168653 | P109: 0.165104 | Q109: 0.161346 | R109: 0.157697 | S109: 0.153821 | T109: 0.149873 | U109: 0.146035 | V109: 0.142369 | W109: 0.138778 | X109: 0.135132 | Y109: 0.131433 | Z109: 0.127512 | AA109: 0.123253 | AB109: 0.119258 | AC109: 0.115164 | AD109: 0.110884 | AE109: 0.106407 | AF109: 0.101846 | AG109: 0.096998 | AH109: =AG109*(1+$AR109) -> 0.094006 | AI109: =AH109*(1+$AR109) -> 0.091106291 | AJ109: =AI109*(1+$AR109) -> 0.088296026 | AK109: =AJ109*(1+$AR109) -> 0.085572447 | AL109: =AK109*(1+$AR109) -> 0.082932879 | AM109: =AL109*(1+$AR109) -> 0.080374731 | AN109: =AM109*(1+$AR109) -> 0.077895493 | AO109: =AN109*(1+$AR109) -> 0.075492728 | ... AQ109: =AP109*(1+$AR109) -> 0.07090726 | AR109: -0.030846
... A111: RKI000:ma_OtherUses | B111: Other Uses 11/ | C111: 5.419452 | D111: 5.52211 | E111: 5.28011 | F111: 5.239892 | G111: 5.197499 | H111: 5.140347 | I111: 5.095592 | J111: 5.075119 | K111: 5.092853 | L111: 5.118895 | M111: 5.170038 | N111: 5.209659 | O111: 5.244733 | P111: 5.288115 | Q111: 5.337711 | R111: 5.393492 | S111: 5.449284 | T111: 5.499146 | U111: 5.549902 | V111: 5.608432 | W111: 5.671052 | X111: 5.732939 | Y111: 5.795694 | Z111: 5.85097 | AA111: 5.892901 | AB111: 5.953435 | AC111: 6.014259 | AD111: 6.073659 | AE111: 6.136003 | AF111: 6.207915 | AG111: 6.279944 | AH111: =AG111*(1+$AR111) -> 6.3108664 | AI111: =AH111*(1+$AR111) -> 6.3419412 | AJ111: =AI111*(1+$AR111) -> 6.3731689 | AK111: =AJ111*(1+$AR111) -> 6.4045504 | AL111: =AK111*(1+$AR111) -> 6.4360864 | AM111: =AL111*(1+$AR111) -> 6.4677776 | AN111: =AM111*(1+$AR111) -> 6.499625 | AO111: =AN111*(1+$AR111) -> 6.5316291 | ... AQ111: =AP111*(1+$AR111) -> 6.596111 | AR111: 0.004924
A112: RKI000:ma_Total | B112: Total Gross End-use Consumption | C112: 21.012035 | D112: 21.043247 | E112: 21.216682 | F112: 21.01828 | G112: 20.85379 | H112: 20.627789 | I112: 20.385229 | J112: 20.220219 | K112: 20.168884 | L112: 20.144857 | M112: 20.183903 | N112: 20.20079 | O112: 20.210455 | P112: 20.251713 | Q112: 20.2981 | R112: 20.374268 | S112: 20.453152 | T112: 20.522358 | U112: 20.597715 | V112: 20.691055 | W112: 20.79027 | X112: 20.887352 | Y112: 20.98815 | Z112: 21.068726 | AA112: 21.118212 | AB112: 21.216028 | AC112: 21.321001 | AD112: 21.42382 | AE112: 21.530754 | AF112: 21.665205 | AG112: 21.802176 | AR112: 0.001231
A113: RKI000:ma_OwnGeneration | B113: Generation for Own Use | C113: 0.078134 | D113: 0.08946 | E113: 0.099012 | F113: 0.108281 | G113: 0.11738 | H113: 0.126529 | I113: 0.135867 | J113: 0.145236 | K113: 0.154673 | L113: 0.164172 | M113: 0.173867 | N113: 0.183793 | O113: 0.193917 | P113: 0.204219 | Q113: 0.214726 | R113: 0.225393 | S113: 0.236254 | T113: 0.247311 | U113: 0.258601 | V113: 0.270115 | W113: 0.281895 | X113: 0.293942 | Y113: 0.306295 | Z113: 0.318983 | AA113: 0.332017 | AB113: 0.34546 | AC113: 0.359251 | AD113: 0.373388 | AE113: 0.387954 | AF113: 0.402906 | AG113: 0.418256 | AH113: =AG113*(1+$AR113) -> 0.44231199 | AI113: =AH113*(1+$AR113) -> 0.46775157 | AJ113: =AI113*(1+$AR113) -> 0.4946543 | AK113: =AJ113*(1+$AR113) -> 0.52310434 | AL113: =AK113*(1+$AR113) -> 0.55319069 | AM113: =AL113*(1+$AR113) -> 0.58500745 | AN113: =AM113*(1+$AR113) -> 0.61865415 | AO113: =AN113*(1+$AR113) -> 0.65423605 | ... AQ113: =AP113*(1+$AR113) -> 0.73165702 | AR113: 0.057515
A114: RKI000:ma_TtllOwnUseGen | B114: Total Net Own-use Generation | C114: 20.933901 | D114: 20.953787 | E114: 21.11767 | F114: 20.91 | G114: 20.73641 | H114: 20.501259 | I114: 20.249361 | J114: 20.074984 | K114: 20.014212 | L114: 19.980686 | M114: 20.010036 | N114: 20.016998 | O114: 20.016539 | P114: 20.047495 | Q114: 20.083374 | R114: 20.148874 | S114: 20.216898 | T114: 20.275047 | U114: 20.339113 | V114: 20.42094 | W114: 20.508375 | X114: 20.59341 | Y114: 20.681854 | Z114: 20.749743 | AA114: 20.786196 | AB114: 20.870569 | AC114: 20.96175 | AD114: 21.050432 | AE114: 21.142799 | AF114: 21.262299 | AG114: 21.383919 | AH114: =AG114*(1+$AR114) -> 21.39908 | AI114: =AH114*(1+$AR114) -> 21.414252 | AJ114: =AI114*(1+$AR114) -> 21.429435 | AK114: =AJ114*(1+$AR114) -> 21.444628 | AL114: =AK114*(1+$AR114) -> 21.459833 | AM114: =AL114*(1+$AR114) -> 21.475048 | AN114: =AM114*(1+$AR114) -> 21.490273 | AO114: =AN114*(1+$AR114) -> 21.50551 | ... AQ114: =AP114*(1+$AR114) -> 21.536016 | AR114: 0.000709
B116: Nonmarketed Renewables 12/
A117: RKI000:na_GeothermalHea | B117: Geothermal Heat Pumps | C117: 0.013036 | D117: 0.015201 | E117: 0.017725 | F117: 0.018765 | G117: 0.020128 | H117: 0.020978 | I117: 0.022219 | J117: 0.02329 | K117: 0.024472 | L117: 0.025659 | M117: 0.02686 | N117: 0.027926 | O117: 0.028994 | P117: 0.030059 | Q117: 0.031076 | R117: 0.032084 | S117: 0.0331 | T117: 0.034097 | U117: 0.035104 | V117: 0.03615 | W117: 0.037255 | X117: 0.038368 | Y117: 0.039507 | Z117: 0.040661 | AA117: 0.041816 | AB117: 0.043009 | AC117: 0.044202 | AD117: 0.045451 | AE117: 0.046683 | AF117: 0.047979 | AG117: 0.049258 | AH117: =AG117*(1+$AR117) -> 0.05148988 | AI117: =AH117*(1+$AR117) -> 0.053822886 | AJ117: =AI117*(1+$AR117) -> 0.056261601 | AK117: =AJ117*(1+$AR117) -> 0.058810815 | AL117: =AK117*(1+$AR117) -> 0.061475533 | AM117: =AL117*(1+$AR117) -> 0.064260989 | AN117: =AM117*(1+$AR117) -> 0.067172654 | AO117: =AN117*(1+$AR117) -> 0.070216247 | ... AQ117: =AP117*(1+$AR117) -> 0.076723397 | AR117: 0.04531
A118: RKI000:na_SolarHotWater | B118: Solar Hot Water Heating | C118: 0.041923 | D118: 0.0459 | E118: 0.045856 | F118: 0.045132 | G118: 0.044743 | H118: 0.043871 | I118: 0.043569 | J118: 0.043343 | K118: 0.043447 | L118: 0.043559 | M118: 0.044141 | N118: 0.044365 | O118: 0.044488 | P118: 0.044635 | Q118: 0.044823 | R118: 0.044966 | S118: 0.045067 | T118: 0.045217 | U118: 0.045376 | V118: 0.045571 | W118: 0.045716 | X118: 0.04592 | Y118: 0.046134 | Z118: 0.046332 | AA118: 0.046519 | AB118: 0.046729 | AC118: 0.046861 | AD118: 0.046873 | AE118: 0.046947 | AF118: 0.047069 | AG118: 0.046927 | AH118: =AG118*(1+$AR118) -> 0.047103727 | AI118: =AH118*(1+$AR118) -> 0.04728112 | AJ118: =AI118*(1+$AR118) -> 0.04745918 | AK118: =AJ118*(1+$AR118) -> 0.047637912 | AL118: =AK118*(1+$AR118) -> 0.047817316 | AM118: =AL118*(1+$AR118) -> 0.047997396 | AN118: =AM118*(1+$AR118) -> 0.048178154 | AO118: =AN118*(1+$AR118) -> 0.048359593 | ... AQ118: =AP118*(1+$AR118) -> 0.048724524 | AR118: 0.003766
A119: RKI000:na_SolarPhotovol | B119: Solar Photovoltaic | C119: 0.225073 | D119: 0.259677 | E119: 0.288641 | F119: 0.312461 | G119: 0.337018 | H119: 0.359239 | I119: 0.383723 | J119: 0.409686 | K119: 0.436777 | L119: 0.46326 | M119: 0.496 | N119: 0.523722 | O119: 0.55119 | P119: 0.579765 | Q119: 0.609985 | R119: 0.640008 | S119: 0.669855 | T119: 0.700877 | U119: 0.731649 | V119: 0.764556 | W119: 0.797295 | X119: 0.831853 | Y119: 0.867645 | Z119: 0.903495 | AA119: 0.940947 | AB119: 0.980271 | AC119: 1.018873 | AD119: 1.055044 | AE119: 1.093461 | AF119: 1.133643 | AG119: 1.168608 | AH119: =AG119*(1+$AR119) -> 1.2345642 | AI119: =AH119*(1+$AR119) -> 1.304243 | AJ119: =AI119*(1+$AR119) -> 1.3778545 | AK119: =AJ119*(1+$AR119) -> 1.4556206 | AL119: =AK119*(1+$AR119) -> 1.5377759 | AM119: =AL119*(1+$AR119) -> 1.6245679 | AN119: =AM119*(1+$AR119) -> 1.7162585 | AO119: =AN119*(1+$AR119) -> 1.8131242 | ... AQ119: =AP119*(1+$AR119) -> 2.0235653 | AR119: 0.05644
A120: RKI000:na_WindHuffPuff | B120: Wind | C120: 0.000173 | D120: 0.000174 | E120: 0.000173 | F120: 0.000169 | G120: 0.000167 | H120: 0.000162 | I120: 0.00016 | J120: 0.000159 | K120: 0.000158 | L120: 0.000158 | M120: 0.000158 | N120: 0.000158 | O120: 0.000157 | P120: 0.000157 | Q120: 0.000157 | R120: 0.000156 | S120: 0.000156 | T120: 0.000156 | U120: 0.000155 | V120: 0.000155 | W120: 0.000156 | X120: 0.000158 | Y120: 0.00016 | Z120: 0.000161 | AA120: 0.000163 | AB120: 0.000165 | AC120: 0.000166 | AD120: 0.000168 | AE120: 0.000169 | AF120: 0.000171 | AG120: 0.000173 | AH120: =AG120*(1+$AR120) -> 0.00017300277 | AI120: =AH120*(1+$AR120) -> 0.00017300554 | AJ120: =AI120*(1+$AR120) -> 0.0001730083 | AK120: =AJ120*(1+$AR120) -> 0.00017301107 | AL120: =AK120*(1+$AR120) -> 0.00017301384 | AM120: =AL120*(1+$AR120) -> 0.00017301661 | AN120: =AM120*(1+$AR120) -> 0.00017301938 | AO120: =AN120*(1+$AR120) -> 0.00017302215 | ... AQ120: =AP120*(1+$AR120) -> 0.00017302768 | AR120: 1.6e-05
A121: RKI000:na_Total | B121: Total | C121: 0.280204 | D121: 0.320951 | E121: 0.352396 | F121: 0.376527 | G121: 0.402057 | H121: 0.42425 | I121: 0.449671 | J121: 0.476478 | K121: 0.504854 | L121: 0.532635 | M121: 0.56716 | N121: 0.59617 | O121: 0.62483 | P121: 0.654616 | Q121: 0.686041 | R121: 0.717214 | S121: 0.748178 | T121: 0.780346 | U121: 0.812283 | V121: 0.846432 | W121: 0.880422 | X121: 0.916299 | Y121: 0.953445 | Z121: 0.990649 | AA121: 1.029446 | AB121: 1.070174 | AC121: 1.110102 | AD121: 1.147535 | AE121: 1.18726 | AF121: 1.228862 | AG121: 1.264965 | AH121: =AG121*(1+$AR121) -> 1.3301436 | AI121: =AH121*(1+$AR121) -> 1.3986806 | AJ121: =AI121*(1+$AR121) -> 1.470749 | AK121: =AJ121*(1+$AR121) -> 1.5465308 | AL121: =AK121*(1+$AR121) -> 1.6262173 | AM121: =AL121*(1+$AR121) -> 1.7100098 | AN121: =AM121*(1+$AR121) -> 1.7981198 | AO121: =AN121*(1+$AR121) -> 1.8907697 | ... AQ121: =AP121*(1+$AR121) -> 2.0906372 | AR121: 0.051526
B123: Heating Degree Days
A124: RKI000:hdd_NewEngland | B124: New England | C124: 5958 | D124: 6244 | E124: 6198 | F124: 6187 | G124: 6176 | H124: 6165 | I124: 6153 | J124: 6142 | K124: 6130 | L124: 6118 | M124: 6107 | N124: 6095 | O124: 6083 | P124: 6071 | Q124: 6059 | R124: 6048 | S124: 6036 | T124: 6024 | U124: 6012 | V124: 6000 | W124: 5988 | X124: 5976 | Y124: 5964 | Z124: 5952 | AA124: 5940 | AB124: 5929 | AC124: 5917 | AD124: 5905 | AE124: 5893 | AF124: 5881 | AG124: 5869 | AH124: =AG124*(1+$AR124) -> 5866.0538 | AI124: =AH124*(1+$AR124) -> 5863.109 | AJ124: =AI124*(1+$AR124) -> 5860.1657 | AK124: =AJ124*(1+$AR124) -> 5857.2239 | AL124: =AK124*(1+$AR124) -> 5854.2836 | AM124: =AL124*(1+$AR124) -> 5851.3447 | AN124: =AM124*(1+$AR124) -> 5848.4074 | AO124: =AN124*(1+$AR124) -> 5845.4715 | ... AQ124: =AP124*(1+$AR124) -> 5839.6041 | AR124: -0.000502
A125: RKI000:hdd_MiddleAtlant | B125: Middle Atlantic | C125: 5371 | D125: 5595 | E125: 5569 | F125: 5558 | G125: 5548 | H125: 5538 | I125: 5528 | J125: 5517 | K125: 5507 | L125: 5497 | M125: 5487 | N125: 5477 | O125: 5467 | P125: 5457 | Q125: 5446 | R125: 5436 | S125: 5426 | T125: 5416 | U125: 5406 | V125: 5396 | W125: 5386 | X125: 5376 | Y125: 5366 | Z125: 5355 | AA125: 5345 | AB125: 5335 | AC125: 5325 | AD125: 5315 | AE125: 5305 | AF125: 5295 | AG125: 5285 | AH125: =AG125*(1+$AR125) -> 5282.1567 | AI125: =AH125*(1+$AR125) -> 5279.3149 | AJ125: =AI125*(1+$AR125) -> 5276.4746 | AK125: =AJ125*(1+$AR125) -> 5273.6359 | AL125: =AK125*(1+$AR125) -> 5270.7986 | AM125: =AL125*(1+$AR125) -> 5267.9629 | AN125: =AM125*(1+$AR125) -> 5265.1288 | AO125: =AN125*(1+$AR125) -> 5262.2961 | ... AQ125: =AP125*(1+$AR125) -> 5256.6354 | AR125: -0.000538
...

Sheet EIA AEO Table 21
A1: Table 21. Residential Sector Equipment Stock and Efficiency, and Distributed Generation
A2: https://www.eia.gov/outlooks/aeo/data/browser/#/?id=30-AEO2021&region=0-0&cases=highogs&start=2019&end=2050&f=A&sourcekey=0
A3: Wed Mar 03 2021 12:12:30 GMT-0800 (Pacific Standard Time)
A4: Source: U.S. Energy Information Administration | AK4: 2051-2060年数据用2050年增速计算得到
B5: full name | C5: api key | D5: units | E5: 2019 | F5: 2020 | G5: 2021 | H5: 2022 | I5: 2023 | J5: 2024 | K5: 2025 | L5: 2026 | M5: 2027 | N5: 2028 | O5: 2029 | P5: 2030 | Q5: 2031 | R5: 2032 | S5: 2033 | T5: 2034 | U5: 2035 | V5: 2036 | W5: 2037 | X5: 2038 | Y5: 2039 | Z5: 2040 | AA5: 2041 | AB5: 2042 | AC5: 2043 | AD5: 2044 | AE5: 2045 | AF5: 2046 | AG5: 2047 | AH5: 2048 | AI5: 2049 | AJ5: 2050 | AK5: 2051 | AL5: 2052 | AM5: 2053 | AN5: 2054 | AO5: 2055 | AP5: 2056 | AQ5: 2057 | AR5: 2058 | AS5: 2059 | AT5: 2060 | AU5: 年增速 | AV5: Growth (2020-2050)
A6: Equipment Stock (million units) | C6: 30-AEO2021.2.
A7: Main Space Heaters | C7: 30-AEO2021.3.
A8: Electric Heat Pumps | B8: Residential Equipment: Equipment Stock: Main Space Heaters: Electric Heat Pumps: High oil and gas supply | C8: 30-AEO2021.4.highogs-d120120a | D8: millions | F8: 12.588214 | G8: 12.817233 | H8: 13.044524 | I8: 13.267048 | J8: 13.49545 | K8: 13.736792 | L8: 13.979751 | M8: 14.211932 | N8: 14.434669 | O8: 14.650879 | P8: 14.860855 | Q8: 15.063206 | R8: 15.261859 | S8: 15.455095 | T8: 15.642369 | U8: 15.83092 | V8: 16.018835 | W8: 16.206322 | X8: 16.391668 | Y8: 16.575872 | Z8: 16.761606 | AA8: 16.947832 | AB8: 17.134937 | AC8: 17.323729 | AD8: 17.513716 | AE8: 17.705347 | AF8: 17.898474 | AG8: 18.091597 | AH8: 18.28528 | AI8: 18.480938 | AJ8: 18.678591 | AK8: =AJ8*(1+$AU8) -> 18.878358 | AL8: =AK8*(1+$AU8) -> 19.080261 | AM8: =AL8*(1+$AU8) -> 19.284324 | AN8: =AM8*(1+$AU8) -> 19.490569 | AO8: =AN8*(1+$AU8) -> 19.69902 | AP8: =AO8*(1+$AU8) -> 19.909701 | AQ8: =AP8*(1+$AU8) -> 20.122634 | AR8: =AQ8*(1+$AU8) -> 20.337845 | ... AT8: =AS8*(1+$AU8) -> 20.775196 | AU8: =AJ8/AI8-1 -> 0.010694966 | AV8: 0.013
A9: Electric Other | B9: Residential Equipment: Equipment Stock: Main Space Heaters: Electric Other: High oil and gas supply | C9: 30-AEO2021.5.highogs-d120120a | D9: millions | F9: 30.217646 | G9: 30.352442 | H9: 30.489107 | I9: 30.626911 | J9: 30.775251 | K9: 30.93782 | L9: 31.102098 | M9: 31.252998 | N9: 31.392506 | O9: 31.52371 | P9: 31.647842 | Q9: 31.763769 | R9: 31.876602 | S9: 31.984751 | T9: 32.088398 | U9: 32.195225 | V9: 32.302486 | W9: 32.409527 | X9: 32.517002 | Y9: 32.626743 | Z9: 32.740696 | AA9: 32.856911 | AB9: 32.974445 | AC9: 33.093201 | AD9: 33.21143 | AE9: 33.330669 | AF9: 33.450096 | AG9: 33.567921 | AH9: 33.685921 | AI9: 33.805984 | AJ9: 33.927921 | AK9: =AJ9*(1+$AU9) -> 34.050298 | AL9: =AK9*(1+$AU9) -> 34.173116 | AM9: =AL9*(1+$AU9) -> 34.296377 | AN9: =AM9*(1+$AU9) -> 34.420083 | AO9: =AN9*(1+$AU9) -> 34.544235 | AP9: =AO9*(1+$AU9) -> 34.668835 | AQ9: =AP9*(1+$AU9) -> 34.793884 | AR9: =AQ9*(1+$AU9) -> 34.919385 | ... AT9: =AS9*(1+$AU9) -> 35.171745 | AU9: =AJ9/AI9-1 -> 0.003606965 | AV9: 0.004
A10: Natural Gas Heat Pumps | B10: Residential Equipment: Equipment Stock: Main Space Heaters: Natural Gas Heat Pumps: High oil and gas supply | C10: 30-AEO2021.6.highogs-d120120a | D10: millions | F10: 1.311724 | G10: 1.309614 | H10: 1.307512 | I10: 1.305418 | J10: 1.303333 | K10: 1.301256 | L10: 1.299187 | M10: 1.297126 | N10: 1.295073 | O10: 1.293028 | P10: 1.29099 | Q10: 1.288961 | R10: 1.286939 | S10: 1.284924 | T10: 1.282917 | U10: 1.280917 | V10: 1.278925 | W10: 1.27694 | X10: 1.274962 | Y10: 1.272991 | Z10: 1.271027 | AA10: 1.26907 | AB10: 1.26712 | AC10: 1.265176 | AD10: 1.263239 | AE10: 1.261309 | AF10: 1.259386 | AG10: 1.257469 | AH10: 1.255558 | AI10: 1.253654 | AJ10: 1.251756 | AK10: =AJ10*(1+$AU10) -> 1.2498609 | AL10: =AK10*(1+$AU10) -> 1.2479686 | AM10: =AL10*(1+$AU10) -> 1.2460792 | AN10: =AM10*(1+$AU10) -> 1.2441927 | AO10: =AN10*(1+$AU10) -> 1.242309 | AP10: =AO10*(1+$AU10) -> 1.2404282 | AQ10: =AP10*(1+$AU10) -> 1.2385502 | AR10: =AQ10*(1+$AU10) -> 1.2366751 | ... AT10: =AS10*(1+$AU10) -> 1.2329333 | AU10: =AJ10/AI10-1 -> -0.0015139744 | AV10: -0.002
A11: Natural Gas Other | B11: Residential Equipment: Equipment Stock: Main Space Heaters: Natural Gas Other: High oil and gas supply | C11: 30-AEO2021.7.highogs-d120120a | D11: millions | F11: 60.555111 | G11: 61.300755 | H11: 62.047543 | I11: 62.788345 | J11: 63.539452 | K11: 64.319839 | L11: 65.096298 | M11: 65.83799 | N11: 66.549057 | O11: 67.237877 | P11: 67.903763 | Q11: 68.544914 | R11: 69.171463 | S11: 69.777695 | T11: 70.360138 | U11: 70.938538 | V11: 71.50589 | W11: 72.063133 | X11: 72.615173 | Y11: 73.162819 | Z11: 73.714096 | AA11: 74.264648 | AB11: 74.813858 | AC11: 75.364723 | AD11: 75.916847 | AE11: 76.470596 | AF11: 77.026077 | AG11: 77.577576 | AH11: 78.126053 | AI11: 78.675049 | AJ11: 79.225029 | AK11: =AJ11*(1+$AU11) -> 79.778854 | AL11: =AK11*(1+$AU11) -> 80.33655 | AM11: =AL11*(1+$AU11) -> 80.898145 | AN11: =AM11*(1+$AU11) -> 81.463665 | AO11: =AN11*(1+$AU11) -> 82.033139 | AP11: =AO11*(1+$AU11) -> 82.606594 | AQ11: =AP11*(1+$AU11) -> 83.184057 | AR11: =AQ11*(1+$AU11) -> 83.765558 | ... AT11: =AS11*(1+$AU11) -> 84.940782 | AU11: =AJ11/AI11-1 -> 0.0069905263 | AV11: 0.009
A12: Distillate Fuel Oil | B12: Residential Equipment: Equipment Stock: Main Space Heaters: Distillate Fuel Oil: High oil and gas supply | C12: 30-AEO2021.8.highogs-d120120a | D12: millions | F12: 5.548133 | G12: 5.496151 | H12: 5.445325 | I12: 5.39556 | J12: 5.346739 | K12: 5.298432 | L12: 5.250475 | M12: 5.204051 | N12: 5.159433 | O12: 5.116981 | P12: 5.076789 | Q12: 5.038133 | R12: 5.001117 | S12: 4.96543 | T12: 4.93077 | U12: 4.897096 | V12: 4.864147 | W12: 4.832564 | X12: 4.802089 | Y12: 4.772426 | Z12: 4.743561 | AA12: 4.714861 | AB12: 4.684665 | AC12: 4.653028 | AD12: 4.620164 | AE12: 4.586325 | AF12: 4.551681 | AG12: 4.515605 | AH12: 4.478509 | AI12: 4.440822 | AJ12: 4.402934 | AK12: =AJ12*(1+$AU12) -> 4.3653693 | AL12: =AK12*(1+$AU12) -> 4.328125 | AM12: =AL12*(1+$AU12) -> 4.2911985 | AN12: =AM12*(1+$AU12) -> 4.254587 | AO12: =AN12*(1+$AU12) -> 4.218288 | AP12: =AO12*(1+$AU12) -> 4.1822986 | AQ12: =AP12*(1+$AU12) -> 4.1466162 | AR12: =AQ12*(1+$AU12) -> 4.1112383 | ... AT12: =AS12*(1+$AU12) -> 4.0413854 | AU12: =AJ12/AI12-1 -> -0.0085317538 | AV12: -0.008
A13: Propane | B13: Residential Equipment: Equipment Stock: Main Space Heaters: Propane: High oil and gas supply | C13: 30-AEO2021.9.highogs-d120120a | D13: millions | F13: 5.19486 | G13: 5.207179 | H13: 5.218678 | I13: 5.23048 | J13: 5.243737 | K13: 5.259387 | L13: 5.276538 | M13: 5.292049 | N13: 5.305241 | O13: 5.316492 | P13: 5.325163 | Q13: 5.332108 | R13: 5.338496 | S13: 5.344443 | T13: 5.349902 | U13: 5.356181 | V13: 5.362693 | W13: 5.368529 | X13: 5.373667 | Y13: 5.378528 | Z13: 5.383961 | AA13: 5.389707 | AB13: 5.394711 | AC13: 5.399234 | AD13: 5.4032 | AE13: 5.406765 | AF13: 5.409881 | AG13: 5.412031 | AH13: 5.413425 | AI13: 5.414567 | AJ13: 5.415322 | AK13: =AJ13*(1+$AU13) -> 5.4160771 | AL13: =AK13*(1+$AU13) -> 5.4168323 | AM13: =AL13*(1+$AU13) -> 5.4175876 | AN13: =AM13*(1+$AU13) -> 5.4183431 | AO13: =AN13*(1+$AU13) -> 5.4190986 | AP13: =AO13*(1+$AU13) -> 5.4198542 | AQ13: =AP13*(1+$AU13) -> 5.4206099 | AR13: =AQ13*(1+$AU13) -> 5.4213658 | ... AT13: =AS13*(1+$AU13) -> 5.4228778 | AU13: =AJ13/AI13-1 -> 0.00013943867 | AV13: 0.001
A14: Kerosene | B14: Residential Equipment: Equipment Stock: Main Space Heaters: Kerosene: High oil and gas supply | C14: 30-AEO2021.10.highogs-d120120a | D14: millions | F14: 0.002897 | G14: 0.005475 | H14: 0.008003 | I14: 0.01057 | J14: 0.013306 | K14: 0.016211 | L14: 0.019194 | M14: 0.021853 | N14: 0.024175 | O14: 0.026187 | P14: 0.027912 | Q14: 0.029431 | R14: 0.030854 | S14: 0.032223 | T14: 0.033555 | U14: 0.034948 | V14: 0.036373 | W14: 0.037762 | X14: 0.0391 | Y14: 0.040437 | Z14: 0.041835 | AA14: 0.043241 | AB14: 0.044628 | AC14: 0.045982 | AD14: 0.047285 | AE14: 0.04854 | AF14: 0.049738 | AG14: 0.050831 | AH14: 0.051844 | AI14: 0.052813 | AJ14: 0.053714 | AK14: =AJ14*(1+$AU14) -> 0.054630371 | AL14: =AK14*(1+$AU14) -> 0.055562376 | AM14: =AL14*(1+$AU14) -> 0.056510281 | AN14: =AM14*(1+$AU14) -> 0.057474357 | AO14: =AN14*(1+$AU14) -> 0.058454881 | AP14: =AO14*(1+$AU14) -> 0.059452132 | AQ14: =AP14*(1+$AU14) -> 0.060466397 | AR14: =AQ14*(1+$AU14) -> 0.061497966 | ... AT14: =AS14*(1+$AU14) -> 0.063614199 | AU14: =AJ14/AI14-1 -> 0.017060194 | AV14: 0.102
A15: Wood Stoves | B15: Residential Equipment: Equipment Stock: Main Space Heaters: Wood Stoves: High oil and gas supply | C15: 30-AEO2021.11.highogs-d120120a | D15: millions | F15: 3.344913 | G15: 3.319362 | H15: 3.294424 | I15: 3.270416 | J15: 3.247226 | K15: 3.223904 | L15: 3.200468 | M15: 3.176886 | N15: 3.153061 | O15: 3.128717 | P15: 3.103658 | Q15: 3.077978 | R15: 3.051444 | S15: 3.024014 | T15: 2.995715 | U15: 2.966784 | V15: 2.937014 | W15: 2.908106 | X15: 2.880246 | Y15: 2.853318 | Z15: 2.826585 | AA15: 2.80106 | AB15: 2.776755 | AC15: 2.753703 | AD15: 2.731991 | AE15: 2.711658 | AF15: 2.692641 | AG15: 2.673467 | AH15: 2.654179 | AI15: 2.634693 | AJ15: 2.614983 | AK15: =AJ15*(1+$AU15) -> 2.5954204 | AL15: =AK15*(1+$AU15) -> 2.5760042 | AM15: =AL15*(1+$AU15) -> 2.5567333 | AN15: =AM15*(1+$AU15) -> 2.5376065 | AO15: =AN15*(1+$AU15) -> 2.5186228 | AP15: =AO15*(1+$AU15) -> 2.4997811 | AQ15: =AP15*(1+$AU15) -> 2.4810804 | AR15: =AQ15*(1+$AU15) -> 2.4625196 | ... AT15: =AS15*(1+$AU15) -> 2.4258134 | AU15: =AJ15/AI15-1 -> -0.0074809475 | AV15: -0.008
A16: Geothermal Heat Pumps | B16: Residential Equipment: Equipment Stock: Main Space Heaters: Geothermal Heat Pumps: High oil and gas supply | C16: 30-AEO2021.12.highogs-d120120a | D16: millions | F16: 0.659973 | G16: 0.716466 | H16: 0.772579 | I16: 0.827264 | J16: 0.881329 | K16: 0.937041 | L16: 0.992897 | M16: 1.047697 | N16: 1.101563 | O16: 1.155224 | P16: 1.208774 | Q16: 1.261961 | R16: 1.315501 | S16: 1.369143 | T16: 1.422559 | U16: 1.476487 | V16: 1.530798 | W16: 1.583866 | X16: 1.635591 | Y16: 1.686028 | Z16: 1.73649 | AA16: 1.785776 | AB16: 1.833722 | AC16: 1.88055 | AD16: 1.926325 | AE16: 1.970899 | AF16: 2.014432 | AG16: 2.057983 | AH16: 2.101467 | AI16: 2.145185 | AJ16: 2.189195 | AK16: =AJ16*(1+$AU16) -> 2.2341079 | AL16: =AK16*(1+$AU16) -> 2.2799422 | AM16: =AL16*(1+$AU16) -> 2.3267169 | AN16: =AM16*(1+$AU16) -> 2.3744511 | AO16: =AN16*(1+$AU16) -> 2.4231647 | AP16: =AO16*(1+$AU16) -> 2.4728776 | AQ16: =AP16*(1+$AU16) -> 2.5236105 | AR16: =AQ16*(1+$AU16) -> 2.5753841 | ... AT16: =AS16*(1+$AU16) -> 2.6821398 | AU16: =AJ16/AI16-1 -> 0.020515713 | AV16: 0.041
A17: Total | B17: Residential Equipment: Equipment Stock: Main Space Heaters: Total: High oil and gas supply | C17: 30-AEO2021.13.highogs-d120120a | D17: millions | F17: 119.42348 | G17: 120.52468 | H17: 121.6277 | I17: 122.72201 | J17: 123.84583 | K17: 125.03069 | L17: 126.2169 | M17: 127.34258 | N17: 128.41479 | O17: 129.4491 | P17: 130.44574 | Q17: 131.40045 | R17: 132.33427 | S17: 133.23772 | T17: 134.10632 | U17: 134.9771 | V17: 135.83714 | W17: 136.68675 | X17: 137.52949 | Y17: 138.36917 | Z17: 139.21986 | AA17: 140.0731 | AB17: 140.92485 | AC17: 141.77933 | AD17: 142.6342 | AE17: 143.49211 | AF17: 144.35242 | AG17: 145.20448 | AH17: 146.05225 | AI17: 146.9037 | AJ17: 147.75946 | AK17: =AJ17*(1+$AU17) -> 148.6202 | AL17: =AK17*(1+$AU17) -> 149.48596 | AM17: =AL17*(1+$AU17) -> 150.35676 | AN17: =AM17*(1+$AU17) -> 151.23263 | AO17: =AN17*(1+$AU17) -> 152.11361 | AP17: =AO17*(1+$AU17) -> 152.99972 | AQ17: =AP17*(1+$AU17) -> 153.89099 | AR17: =AQ17*(1+$AU17) -> 154.78745 | ... AT17: =AS17*(1+$AU17) -> 156.59607 | AU17: =AJ17/AI17-1 -> 0.0058252991 | AV17: 0.007
A18: Space Cooling (million units) | C18: 30-AEO2021.15.
A19: Electric Heat Pumps | B19: Residential Equipment: Equipment Stock: Space Cooling: Electric Heat Pumps: High oil and gas supply | C19: 30-AEO2021.16.highogs-d120120a | D19: millions | F19: 12.58821 | G19: 12.817232 | H19: 13.044521 | I19: 13.267052 | J19: 13.495453 | K19: 13.736794 | L19: 13.979755 | M19: 14.211934 | N19: 14.434671 | O19: 14.650883 | P19: 14.860855 | Q19: 15.063212 | R19: 15.261856 | S19: 15.455102 | T19: 15.642369 | U19: 15.830916 | V19: 16.018831 | W19: 16.20632 | X19: 16.391672 | Y19: 16.575872 | Z19: 16.761606 | AA19: 16.947832 | AB19: 17.13493 | AC19: 17.323732 | AD19: 17.513723 | AE19: 17.705347 | AF19: 17.898479 | AG19: 18.0916 | AH19: 18.28528 | AI19: 18.480938 | AJ19: 18.678596 | AK19: =AJ19*(1+$AU19) -> 18.878368 | AL19: =AK19*(1+$AU19) -> 19.080277 | AM19: =AL19*(1+$AU19) -> 19.284345 | AN19: =AM19*(1+$AU19) -> 19.490595 | AO19: =AN19*(1+$AU19) -> 19.699052 | AP19: =AO19*(1+$AU19) -> 19.909738 | AQ19: =AP19*(1+$AU19) -> 20.122677 | AR19: =AQ19*(1+$AU19) -> 20.337894 | ... AT19: =AS19*(1+$AU19) -> 20.775258 | AU19: =AJ19/AI19-1 -> 0.010695236 | AV19: 0.013
A20: Natural Gas Heat Pumps | B20: Residential Equipment: Equipment Stock: Space Cooling: Natural Gas Heat Pumps: High oil and gas supply | C20: 30-AEO2021.17.highogs-d120120a | D20: millions | F20: 1.311724 | G20: 1.309614 | H20: 1.307512 | I20: 1.305418 | J20: 1.303333 | K20: 1.301256 | L20: 1.299187 | M20: 1.297126 | N20: 1.295073 | O20: 1.293028 | P20: 1.29099 | Q20: 1.288961 | R20: 1.286939 | S20: 1.284924 | T20: 1.282917 | U20: 1.280917 | V20: 1.278925 | W20: 1.27694 | X20: 1.274962 | Y20: 1.272991 | Z20: 1.271027 | AA20: 1.26907 | AB20: 1.26712 | AC20: 1.265176 | AD20: 1.263239 | AE20: 1.261309 | AF20: 1.259386 | AG20: 1.257469 | AH20: 1.255558 | AI20: 1.253654 | AJ20: 1.251756 | AK20: =AJ20*(1+$AU20) -> 1.2498609 | AL20: =AK20*(1+$AU20) -> 1.2479686 | AM20: =AL20*(1+$AU20) -> 1.2460792 | AN20: =AM20*(1+$AU20) -> 1.2441927 | AO20: =AN20*(1+$AU20) -> 1.242309 | AP20: =AO20*(1+$AU20) -> 1.2404282 | AQ20: =AP20*(1+$AU20) -> 1.2385502 | AR20: =AQ20*(1+$AU20) -> 1.2366751 | ... AT20: =AS20*(1+$AU20) -> 1.2329333 | AU20: =AJ20/AI20-1 -> -0.0015139744 | AV20: -0.002
A21: Geothermal Heat Pumps | B21: Residential Equipment: Equipment Stock: Space Cooling: Geothermal Heat Pumps: High oil and gas supply | C21: 30-AEO2021.18.highogs-d120120a | D21: millions | F21: 0.659973 | G21: 0.716466 | H21: 0.772579 | I21: 0.827264 | J21: 0.881329 | K21: 0.93704 | L21: 0.992898 | M21: 1.047698 | N21: 1.101564 | O21: 1.155224 | P21: 1.208774 | Q21: 1.26196 | R21: 1.315501 | S21: 1.369144 | T21: 1.422559 | U21: 1.476488 | V21: 1.530799 | W21: 1.583866 | X21: 1.635591 | Y21: 1.686028 | Z21: 1.73649 | AA21: 1.785776 | AB21: 1.833722 | AC21: 1.880549 | AD21: 1.926325 | AE21: 1.970899 | AF21: 2.014432 | AG21: 2.057982 | AH21: 2.101467 | AI21: 2.145186 | AJ21: 2.189197 | AK21: =AJ21*(1+$AU21) -> 2.2341109 | AL21: =AK21*(1+$AU21) -> 2.2799463 | AM21: =AL21*(1+$AU21) -> 2.3267221 | AN21: =AM21*(1+$AU21) -> 2.3744575 | AO21: =AN21*(1+$AU21) -> 2.4231723 | AP21: =AO21*(1+$AU21) -> 2.4728865 | AQ21: =AP21*(1+$AU21) -> 2.5236207 | AR21: =AQ21*(1+$AU21) -> 2.5753957 | ... AT21: =AS21*(1+$AU21) -> 2.6821542 | AU21: =AJ21/AI21-1 -> 0.02051617 | AV21: 0.041
A22: Central Air Conditioners | B22: Residential Equipment: Equipment Stock: Space Cooling: Central Air Conditioners: High oil and gas supply | C22: 30-AEO2021.19.highogs-d120120a | D22: millions | F22: 62.428101 | G22: 63.953739 | H22: 65.478302 | I22: 66.994934 | J22: 68.527229 | K22: 70.095711 | L22: 71.662971 | M22: 73.190346 | N22: 74.681778 | O22: 76.147041 | P22: 77.586067 | Q22: 78.996407 | R22: 80.391296 | S22: 81.764877 | T22: 83.114212 | U22: 84.46244 | V22: 85.801651 | W22: 87.13192 | X22: 88.455452 | Y22: 89.774467 | Z22: 91.098305 | AA22: 92.421654 | AB22: 93.741837 | AC22: 95.061737 | AD22: 96.380211 | AE22: 97.698593 | AF22: 99.016754 | AG22: 100.32771 | AH22: 101.63374 | AI22: 102.93985 | AJ22: 104.24644 | AK22: =AJ22*(1+$AU22) -> 105.56961 | AL22: =AK22*(1+$AU22) -> 106.90957 | AM22: =AL22*(1+$AU22) -> 108.26655 | AN22: =AM22*(1+$AU22) -> 109.64074 | AO22: =AN22*(1+$AU22) -> 111.03238 | AP22: =AO22*(1+$AU22) -> 112.44169 | AQ22: =AP22*(1+$AU22) -> 113.86888 | AR22: =AQ22*(1+$AU22) -> 115.31419 | ... AT22: =AS22*(1+$AU22) -> 118.26006 | AU22: =AJ22/AI22-1 -> 0.012692723 | AV22: 0.017
A23: Room Air Conditioners | B23: Residential Equipment: Equipment Stock: Space Cooling: Room Air Conditioners: High oil and gas supply | C23: 30-AEO2021.20.highogs-d120120a | D23: millions | F23: 57.979027 | G23: 57.968586 | H23: 57.959606 | I23: 57.95211 | J23: 57.951488 | K23: 57.960857 | L23: 57.973194 | M23: 57.977226 | N23: 57.973316 | O23: 57.963169 | P23: 57.946999 | Q23: 57.925327 | R23: 57.901684 | S23: 57.875652 | T23: 57.847012 | U23: 57.82074 | V23: 57.795208 | W23: 57.769428 | X23: 57.743534 | Y23: 57.718586 | Z23: 57.696892 | AA23: 57.677017 | AB23: 57.658131 | AC23: 57.640438 | AD23: 57.62347 | AE23: 57.607464 | AF23: 57.592182 | AG23: 57.575733 | AH23: 57.558784 | AI23: 57.54269 | AJ23: 57.527027 | AK23: =AJ23*(1+$AU23) -> 57.511368 | AL23: =AK23*(1+$AU23) -> 57.495714 | AM23: =AL23*(1+$AU23) -> 57.480064 | AN23: =AM23*(1+$AU23) -> 57.464418 | AO23: =AN23*(1+$AU23) -> 57.448776 | AP23: =AO23*(1+$AU23) -> 57.433138 | AQ23: =AP23*(1+$AU23) -> 57.417505 | AR23: =AQ23*(1+$AU23) -> 57.401876 | ... AT23: =AS23*(1+$AU23) -> 57.370631 | AU23: =AJ23/AI23-1 -> -0.00027219791 | AV23: 0
A24: Total | B24: Residential Equipment: Equipment Stock: Space Cooling: Total: High oil and gas supply | C24: 30-AEO2021.21.highogs-d120120a | D24: millions | F24: 134.96704 | G24: 136.76564 | H24: 138.56251 | I24: 140.34677 | J24: 142.15883 | K24: 144.03166 | L24: 145.90801 | M24: 147.72433 | N24: 149.4864 | O24: 151.20935 | P24: 152.89368 | Q24: 154.53587 | R24: 156.15727 | S24: 157.7497 | T24: 159.30907 | U24: 160.87151 | V24: 162.42541 | W24: 163.96848 | X24: 165.5012 | Y24: 167.02794 | Z24: 168.56433 | AA24: 170.10135 | AB24: 171.63574 | AC24: 173.17163 | AD24: 174.70697 | AE24: 176.24361 | AF24: 177.78124 | AG24: 179.3105 | AH24: 180.83482 | AI24: 182.36232 | AJ24: 183.89302 | AK24: =AJ24*(1+$AU24) -> 185.43657 | AL24: =AK24*(1+$AU24) -> 186.99308 | AM24: =AL24*(1+$AU24) -> 188.56265 | AN24: =AM24*(1+$AU24) -> 190.14539 | AO24: =AN24*(1+$AU24) -> 191.74142 | AP24: =AO24*(1+$AU24) -> 193.35085 | AQ24: =AP24*(1+$AU24) -> 194.97378 | AR24: =AQ24*(1+$AU24) -> 196.61034 | ... AT24: =AS24*(1+$AU24) -> 199.92478 | AU24: =AJ24/AI24-1 -> 0.0083937351 | AV24: 0.01
A25: Water Heaters (million units) | C25: 30-AEO2021.23.
A26: Electric | B26: Residential Equipment: Equipment Stock: Water Heaters: Electric: High oil and gas supply | C26: 30-AEO2021.24.highogs-d120120a | D26: millions | F26: 59.144028 | G26: 59.619999 | H26: 60.176491 | I26: 60.701748 | J26: 61.2099 | K26: 61.717579 | L26: 62.202168 | M26: 62.647766 | N26: 63.054695 | O26: 63.432339 | P26: 63.788673 | Q26: 64.143646 | R26: 64.507957 | S26: 64.874107 | T26: 65.239677 | U26: 65.619102 | V26: 66.004692 | W26: 66.394569 | X26: 66.788284 | Y26: 67.176643 | Z26: 67.565285 | AA26: 67.950615 | AB26: 68.332207 | AC26: 68.711609 | AD26: 69.088249 | AE26: 69.464256 | AF26: 69.840889 | AG26: 70.214859 | AH26: 70.589462 | AI26: 70.970284 | AJ26: 71.357269 | AK26: =AJ26*(1+$AU26) -> 71.746364 | AL26: =AK26*(1+$AU26) -> 72.137581 | AM26: =AL26*(1+$AU26) -> 72.530931 | AN26: =AM26*(1+$AU26) -> 72.926426 | AO26: =AN26*(1+$AU26) -> 73.324077 | AP26: =AO26*(1+$AU26) -> 73.723897 | AQ26: =AP26*(1+$AU26) -> 74.125897 | AR26: =AQ26*(1+$AU26) -> 74.530089 | ... AT26: =AS26*(1+$AU26) -> 75.345096 | AU26: =AJ26/AI26-1 -> 0.0054527751 | AV26: 0.006
A27: Natural Gas | B27: Residential Equipment: Equipment Stock: Water Heaters: Natural Gas: High oil and gas supply | C27: 30-AEO2021.25.highogs-d120120a | D27: millions | F27: 60.065723 | G27: 60.660275 | H27: 61.304443 | I27: 61.960426 | J27: 62.648998 | K27: 63.384193 | L27: 64.132782 | M27: 64.852921 | N27: 65.551575 | O27: 66.234795 | P27: 66.894508 | Q27: 67.521645 | R27: 68.124603 | S27: 68.699837 | T27: 69.24427 | U27: 69.778008 | V27: 70.294899 | W27: 70.797226 | X27: 71.288422 | Y27: 71.778992 | Z27: 72.277077 | AA27: 72.777733 | AB27: 73.277695 | AC27: 73.779533 | AD27: 74.282188 | AE27: 74.786438 | AF27: 75.290825 | AG27: 75.789009 | AH27: 76.281776 | AI27: 76.771454 | AJ27: 77.258736 | AK27: =AJ27*(1+$AU27) -> 77.749111 | AL27: =AK27*(1+$AU27) -> 78.242598 | AM27: =AL27*(1+$AU27) -> 78.739218 | AN27: =AM27*(1+$AU27) -> 79.23899 | AO27: =AN27*(1+$AU27) -> 79.741933 | AP27: =AO27*(1+$AU27) -> 80.24807 | AQ27: =AP27*(1+$AU27) -> 80.757418 | AR27: =AQ27*(1+$AU27) -> 81.27 | ... AT27: =AS27*(1+$AU27) -> 82.304944 | AU27: =AJ27/AI27-1 -> 0.0063471769 | AV27: 0.008
A28: Distillate Fuel Oil | B28: Residential Equipment: Equipment Stock: Water Heaters: Distillate Fuel Oil: High oil and gas supply | C28: 30-AEO2021.26.highogs-d120120a | D28: millions | F28: 2.645688 | G28: 2.600587 | H28: 2.557136 | I28: 2.513456 | J28: 2.472345 | K28: 2.435079 | L28: 2.399654 | M28: 2.36718 | N28: 2.337591 | O28: 2.310858 | P28: 2.286937 | Q28: 2.261104 | R28: 2.233402 | S28: 2.20452 | T28: 2.174745 | U28: 2.144583 | V28: 2.11454 | W28: 2.084679 | X28: 2.05522 | Y28: 2.026759 | Z28: 1.998826 | AA28: 1.971788 | AB28: 1.945657 | AC28: 1.920432 | AD28: 1.895941 | AE28: 1.871992 | AF28: 1.848593 | AG28: 1.825595 | AH28: 1.802938 | AI28: 1.780446 | AJ28: 1.758198 | AK28: =AJ28*(1+$AU28) -> 1.736228 | AL28: =AK28*(1+$AU28) -> 1.7145325 | AM28: =AL28*(1+$AU28) -> 1.6931082 | AN28: =AM28*(1+$AU28) -> 1.6719515 | AO28: =AN28*(1+$AU28) -> 1.6510593 | AP28: =AO28*(1+$AU28) -> 1.630428 | AQ28: =AP28*(1+$AU28) -> 1.6100546 | AR28: =AQ28*(1+$AU28) -> 1.5899358 | ... AT28: =AS28*(1+$AU28) -> 1.5504492 | AU28: =AJ28/AI28-1 -> -0.012495745 | AV28: -0.014
A29: Propane | B29: Residential Equipment: Equipment Stock: Water Heaters: Propane: High oil and gas supply | C29: 30-AEO2021.27.highogs-d120120a | D29: millions | F29: 4.054796 | G29: 3.961836 | H29: 3.878141 | I29: 3.804585 | J29: 3.742667 | K29: 3.69157 | L29: 3.649184 | M29: 3.611273 | N29: 3.577413 | O29: 3.547936 | P29: 3.522523 | Q29: 3.491105 | R29: 3.455376 | S29: 3.416478 | T29: 3.375241 | U29: 3.333834 | V29: 3.292641 | W29: 3.251569 | X29: 3.211201 | Y29: 3.172485 | Z29: 3.136445 | AA29: 3.102795 | AB29: 3.07125 | AC29: 3.041861 | AD29: 3.014236 | AE29: 2.988221 | AF29: 2.963415 | AG29: 2.939012 | AH29: 2.914999 | AI29: 2.891638 | AJ29: 2.868669 | AK29: =AJ29*(1+$AU29) -> 2.8458824 | AL29: =AK29*(1+$AU29) -> 2.8232769 | AM29: =AL29*(1+$AU29) -> 2.8008509 | AN29: =AM29*(1+$AU29) -> 2.778603 | AO29: =AN29*(1+$AU29) -> 2.7565319 | AP29: =AO29*(1+$AU29) -> 2.7346361 | AQ29: =AP29*(1+$AU29) -> 2.7129142 | AR29: =AQ29*(1+$AU29) -> 2.6913648 | ... AT29: =AS29*(1+$AU29) -> 2.6487783 | AU29: =AJ29/AI29-1 -> -0.0079432488 | AV29: -0.011
A30: Solar Thermal | B30: Residential Equipment: Equipment Stock: Water Heaters: Solar Thermal: High oil and gas supply | C30: 30-AEO2021.28.highogs-d120120a | D30: millions | F30: 1.619339 | G30: 1.767752 | H30: 1.777033 | I30: 1.787264 | J30: 1.79747 | K30: 1.808034 | L30: 1.819156 | M30: 1.830038 | N30: 1.840685 | O30: 1.851122 | P30: 1.861841 | Q30: 1.872775 | R30: 1.883872 | S30: 1.894988 | T30: 1.906009 | U30: 1.916758 | V30: 1.927217 | W30: 1.937276 | X30: 1.946888 | Y30: 1.956742 | Z30: 1.96678 | AA30: 1.976967 | AB30: 1.987235 | AC30: 1.997509 | AD30: 2.007803 | AE30: 2.0181 | AF30: 2.028332 | AG30: 2.038509 | AH30: 2.048583 | AI30: 2.058523 | AJ30: 2.068366 | AK30: =AJ30*(1+$AU30) -> 2.0782561 | AL30: =AK30*(1+$AU30) -> 2.0881934 | AM30: =AL30*(1+$AU30) -> 2.0981783 | AN30: =AM30*(1+$AU30) -> 2.1082109 | AO30: =AN30*(1+$AU30) -> 2.1182915 | AP30: =AO30*(1+$AU30) -> 2.1284203 | AQ30: =AP30*(1+$AU30) -> 2.1385975 | AR30: =AQ30*(1+$AU30) -> 2.1488234 | ... AT30: =AS30*(1+$AU30) -> 2.1694221 | AU30: =AJ30/AI30-1 -> 0.0047815837 | AV30: 0.008
A31: Total | B31: Residential Equipment: Equipment Stock: Water Heaters: Total: High oil and gas supply | C31: 30-AEO2021.29.highogs-d120120a | D31: millions | F31: 127.52957 | G31: 128.61044 | H31: 129.69325 | I31: 130.76747 | J31: 131.87138 | K31: 133.03645 | L31: 134.20294 | M31: 135.30917 | N31: 136.36194 | O31: 137.37705 | P31: 138.35449 | Q31: 139.29027 | R31: 140.20522 | S31: 141.08992 | T31: 141.93994 | U31: 142.79228 | V31: 143.63399 | W31: 144.46533 | X31: 145.29001 | Y31: 146.11162 | Z31: 146.94441 | AA31: 147.77991 | AB31: 148.61403 | AC31: 149.45094 | AD31: 150.28841 | AE31: 151.12901 | AF31: 151.97205 | AG31: 152.80699 | AH31: 153.63776 | AI31: 154.47232 | AJ31: 155.31122 | AK31: =AJ31*(1+$AU31) -> 156.15467 | AL31: =AK31*(1+$AU31) -> 157.0027 | AM31: =AL31*(1+$AU31) -> 157.85534 | AN31: =AM31*(1+$AU31) -> 158.71261 | AO31: =AN31*(1+$AU31) -> 159.57454 | AP31: =AO31*(1+$AU31) -> 160.44114 | AQ31: =AP31*(1+$AU31) -> 161.31245 | AR31: =AQ31*(1+$AU31) -> 162.1885 | ... AT31: =AS31*(1+$AU31) -> 163.95489 | AU31: =AJ31/AI31-1 -> 0.005430727 | AV31: 0.007
A32: Cooking Equipment (million units) | C32: 30-AEO2021.31.
A33: Electric | B33: Residential Equipment: Equipment Stock: Cooking Equipment: Electric: High oil and gas supply | C33: 30-AEO2021.32.highogs-d120120a | D33: millions | F33: 96.368851 | G33: 96.942863 | H33: 97.507462 | I33: 98.056366 | J33: 98.616669 | K33: 99.209564 | L33: 99.791199 | M33: 100.31636 | N33: 100.78964 | O33: 101.19668 | P33: 101.53636 | Q33: 101.79644 | R33: 101.98789 | S33: 102.18788 | T33: 102.41907 | U33: 102.71017 | V33: 103.06227 | W33: 103.47982 | X33: 103.88201 | Y33: 104.27118 | Z33: 104.65609 | AA33: 105.03009 | AB33: 105.38992 | AC33: 105.73807 | AD33: 106.07283 | AE33: 106.39809 | AF33: 106.71592 | AG33: 107.02323 | AH33: 107.32764 | AI33: 107.63994 | AJ33: 107.96524 | AK33: =AJ33*(1+$AU33) -> 108.29153 | AL33: =AK33*(1+$AU33) -> 108.6188 | AM33: =AL33*(1+$AU33) -> 108.94706 | AN33: =AM33*(1+$AU33) -> 109.27631 | AO33: =AN33*(1+$AU33) -> 109.60656 | AP33: =AO33*(1+$AU33) -> 109.9378 | AQ33: =AP33*(1+$AU33) -> 110.27005 | AR33: =AQ33*(1+$AU33) -> 110.6033 | ... AT33: =AS33*(1+$AU33) -> 111.27282 | AU33: =AJ33/AI33-1 -> 0.0030221311 | AV33: 0.004
A34: Natural Gas | B34: Residential Equipment: Equipment Stock: Cooking Equipment: Natural Gas: High oil and gas supply | C34: 30-AEO2021.33.highogs-d120120a | D34: millions | F34: 47.877865 | G34: 48.362202 | H34: 48.858322 | I34: 49.361767 | J34: 49.882469 | K34: 50.43058 | L34: 50.992687 | M34: 51.556805 | N34: 52.125301 | O34: 52.727886 | P34: 53.365761 | Q34: 54.045799 | R34: 54.776047 | S34: 55.464073 | T34: 56.082935 | U34: 56.639286 | V34: 57.11982 | W34: 57.520824 | X34: 57.932938 | Y34: 58.357018 | Z34: 58.798096 | AA34: 59.254616 | AB34: 59.725677 | AC34: 60.212387 | AD34: 60.713413 | AE34: 61.226475 | AF34: 61.748219 | AG34: 62.271156 | AH34: 62.791275 | AI34: 63.305855 | AJ34: 63.811348 | AK34: =AJ34*(1+$AU34) -> 64.320877 | AL34: =AK34*(1+$AU34) -> 64.834475 | AM34: =AL34*(1+$AU34) -> 65.352174 | AN34: =AM34*(1+$AU34) -> 65.874007 | AO34: =AN34*(1+$AU34) -> 66.400006 | AP34: =AO34*(1+$AU34) -> 66.930206 | AQ34: =AP34*(1+$AU34) -> 67.464639 | AR34: =AQ34*(1+$AU34) -> 68.00334 | ... AT34: =AS34*(1+$AU34) -> 69.09368 | AU34: =AJ34/AI34-1 -> 0.0079849328 | AV34: 0.01
A35: Propane | B35: Residential Equipment: Equipment Stock: Cooking Equipment: Propane: High oil and gas supply | C35: 30-AEO2021.34.highogs-d120120a | D35: millions | F35: 7.18522 | G35: 7.171827 | H35: 7.158296 | I35: 7.144682 | J35: 7.132236 | K35: 7.12113 | L35: 7.108913 | M35: 7.090971 | N35: 7.067329 | O35: 7.038247 | P35: 7.003797 | Q35: 6.965244 | R35: 6.924439 | S35: 6.887216 | T35: 6.85351 | U35: 6.824679 | V35: 6.80035 | W35: 6.779766 | X35: 6.756999 | Y35: 6.73224 | Z35: 6.706143 | AA35: 6.678343 | AB35: 6.648904 | AC35: 6.618482 | AD35: 6.587785 | AE35: 6.557754 | AF35: 6.529152 | AG35: 6.501891 | AH35: 6.47621 | AI35: 6.452127 | AJ35: 6.428639 | AK35: =AJ35*(1+$AU35) -> 6.4052365 | AL35: =AK35*(1+$AU35) -> 6.3819192 | AM35: =AL35*(1+$AU35) -> 6.3586868 | AN35: =AM35*(1+$AU35) -> 6.3355389 | AO35: =AN35*(1+$AU35) -> 6.3124754 | AP35: =AO35*(1+$AU35) -> 6.2894957 | AQ35: =AP35*(1+$AU35) -> 6.2665998 | AR35: =AQ35*(1+$AU35) -> 6.2437872 | ... AT35: =AS35*(1+$AU35) -> 6.1984108 | AU35: =AJ35/AI35-1 -> -0.0036403499 | AV35: -0.004
A36: Total | B36: Residential Equipment: Equipment Stock: Cooking Equipment: Total: High oil and gas supply | C36: 30-AEO2021.35.highogs-d120120a | D36: millions | F36: 151.43195 | G36: 152.4769 | H36: 153.52408 | I36: 154.56282 | J36: 155.63138 | K36: 156.76126 | L36: 157.89281 | M36: 158.96414 | N36: 159.98225 | O36: 160.96281 | P36: 161.90593 | Q36: 162.80748 | R36: 163.68837 | S36: 164.53917 | T36: 165.35551 | U36: 166.17413 | V36: 166.98245 | W36: 167.78041 | X36: 168.57194 | Y36: 169.36044 | Z36: 170.16034 | AA36: 170.96304 | AB36: 171.76451 | AC36: 172.56895 | AD36: 173.37402 | AE36: 174.18233 | AF36: 174.9933 | AG36: 175.79628 | AH36: 176.59514 | AI36: 177.39793 | AJ36: 178.20522 | AK36: =AJ36*(1+$AU36) -> 179.01617 | AL36: =AK36*(1+$AU36) -> 179.83081 | AM36: =AL36*(1+$AU36) -> 180.64917 | AN36: =AM36*(1+$AU36) -> 181.47124 | AO36: =AN36*(1+$AU36) -> 182.29706 | AP36: =AO36*(1+$AU36) -> 183.12664 | AQ36: =AP36*(1+$AU36) -> 183.95999 | AR36: =AQ36*(1+$AU36) -> 184.79713 | ... AT36: =AS36*(1+$AU36) -> 186.48286 | AU36: =AJ36/AI36-1 -> 0.0045506787 | AV36: 0.005
A37: Clothes Dryers (million units) | C37: 30-AEO2021.37.
A38: Electric | B38: Residential Equipment: Equipment Stock: Clothes Dryers: Electric: High oil and gas supply | C38: 30-AEO2021.38.highogs-d120120a | D38: millions | F38: 82.851837 | G38: 84.434746 | H38: 86.008148 | I38: 87.561714 | J38: 89.123634 | K38: 90.742928 | L38: 92.341606 | M38: 93.879135 | N38: 95.373093 | O38: 96.835007 | P38: 98.266113 | Q38: 99.661926 | R38: 101.04254 | S38: 102.4024 | T38: 103.77617 | U38: 105.16342 | V38: 106.55422 | W38: 107.92213 | X38: 109.27143 | Y38: 110.60932 | Z38: 111.9482 | AA38: 113.28167 | AB38: 114.60757 | AC38: 115.9321 | AD38: 117.2557 | AE38: 118.58108 | AF38: 119.90953 | AG38: 121.2308 | AH38: 122.54816 | AI38: 123.86906 | AJ38: 125.1927 | AK38: =AJ38*(1+$AU38) -> 126.53049 | AL38: =AK38*(1+$AU38) -> 127.88258 | AM38: =AL38*(1+$AU38) -> 129.24911 | AN38: =AM38*(1+$AU38) -> 130.63025 | AO38: =AN38*(1+$AU38) -> 132.02614 | AP38: =AO38*(1+$AU38) -> 133.43696 | AQ38: =AP38*(1+$AU38) -> 134.86284 | AR38: =AQ38*(1+$AU38) -> 136.30397 | ... AT38: =AS38*(1+$AU38) -> 139.23258 | AU38: =AJ38/AI38-1 -> 0.010685849 | AV38: 0.014
A39: Natural Gas | B39: Residential Equipment: Equipment Stock: Clothes Dryers: Natural Gas: High oil and gas supply | C39: 30-AEO2021.39.highogs-d120120a | D39: millions | F39: 19.328499 | G39: 19.644548 | H39: 19.971266 | I39: 20.307354 | J39: 20.658833 | K39: 21.032396 | L39: 21.427053 | M39: 21.8396 | N39: 22.242754 | O39: 22.63986 | P39: 23.029221 | Q39: 23.41106 | R39: 23.785479 | S39: 24.148891 | T39: 24.497536 | U39: 24.831118 | V39: 25.146399 | W39: 25.470278 | X39: 25.802156 | Y39: 26.140812 | Z39: 26.486872 | AA39: 26.837982 | AB39: 27.191841 | AC39: 27.547499 | AD39: 27.903585 | AE39: 28.25894 | AF39: 28.612516 | AG39: 28.962561 | AH39: 29.309134 | AI39: 29.653179 | AJ39: 29.995754 | AK39: =AJ39*(1+$AU39) -> 30.342287 | AL39: =AK39*(1+$AU39) -> 30.692823 | AM39: =AL39*(1+$AU39) -> 31.047408 | AN39: =AM39*(1+$AU39) -> 31.406091 | AO39: =AN39*(1+$AU39) -> 31.768917 | AP39: =AO39*(1+$AU39) -> 32.135934 | AQ39: =AP39*(1+$AU39) -> 32.507192 | AR39: =AQ39*(1+$AU39) -> 32.882738 | ... AT39: =AS39*(1+$AU39) -> 33.646897 | AU39: =AJ39/AI39-1 -> 0.011552724 | AV39: 0.015
A40: Total | B40: Residential Equipment: Equipment Stock: Clothes Dryers: Total: High oil and gas supply | C40: 30-AEO2021.40.highogs-d120120a | D40: millions | F40: 102.18034 | G40: 104.07929 | H40: 105.97942 | I40: 107.86906 | J40: 109.78247 | K40: 111.77532 | L40: 113.76866 | M40: 115.71873 | N40: 117.61584 | O40: 119.47487 | P40: 121.29533 | Q40: 123.07298 | R40: 124.82802 | S40: 126.55128 | T40: 128.27371 | U40: 129.99454 | V40: 131.70062 | W40: 133.39241 | X40: 135.07359 | Y40: 136.75014 | Z40: 138.43507 | AA40: 140.11966 | AB40: 141.79941 | AC40: 143.4796 | AD40: 145.15929 | AE40: 146.84001 | AF40: 148.52205 | AG40: 150.19336 | AH40: 151.85728 | AI40: 153.52223 | AJ40: 155.18846 | AK40: =AJ40*(1+$AU40) -> 156.87277 | AL40: =AK40*(1+$AU40) -> 158.57537 | AM40: =AL40*(1+$AU40) -> 160.29644 | AN40: =AM40*(1+$AU40) -> 162.03619 | AO40: =AN40*(1+$AU40) -> 163.79483 | AP40: =AO40*(1+$AU40) -> 165.57255 | AQ40: =AP40*(1+$AU40) -> 167.36956 | AR40: =AQ40*(1+$AU40) -> 169.18608 | ... AT40: =AS40*(1+$AU40) -> 172.87848 | AU40: =AJ40/AI40-1 -> 0.01085334 | AV40: 0.014
A41: Other Appliances (million units) | C41: 30-AEO2021.42.
A42: Refrigerators | B42: Residential Equipment: Equipment Stock: Other Appliances: Refrigerators: High oil and gas supply | C42: 30-AEO2021.43.highogs-d120120a | D42: millions | F42: 168.42892 | G42: 170.03853 | H42: 171.65152 | I42: 173.25046 | J42: 174.88527 | K42: 176.60463 | L42: 178.3268 | M42: 179.96771 | N42: 181.53455 | O42: 183.04887 | P42: 184.51003 | Q42: 185.91237 | R42: 187.2852 | S42: 188.61539 | T42: 189.89516 | U42: 191.17584 | V42: 192.44002 | W42: 193.68768 | X42: 194.92362 | Y42: 196.1515 | Z42: 197.39432 | AA42: 198.64011 | AB42: 199.88269 | AC42: 201.12915 | AD42: 202.37878 | AE42: 203.63318 | AF42: 204.8925 | AG42: 206.14032 | AH42: 207.38039 | AI42: 208.62447 | AJ42: 209.87308 | AK42: =AJ42*(1+$AU42) -> 211.12916 | AL42: =AK42*(1+$AU42) -> 212.39276 | AM42: =AL42*(1+$AU42) -> 213.66393 | AN42: =AM42*(1+$AU42) -> 214.9427 | AO42: =AN42*(1+$AU42) -> 216.22912 | AP42: =AO42*(1+$AU42) -> 217.52325 | AQ42: =AP42*(1+$AU42) -> 218.82512 | AR42: =AQ42*(1+$AU42) -> 220.13478 | ... AT42: =AS42*(1+$AU42) -> 222.77767 | AU42: =AJ42/AI42-1 -> 0.0059849692 | AV42: 0.007
A43: Freezers | B43: Residential Equipment: Equipment Stock: Other Appliances: Freezers: High oil and gas supply | C43: 30-AEO2021.44.highogs-d120120a | D43: millions | F43: 44.426056 | G43: 44.797699 | H43: 45.170856 | I43: 45.542194 | J43: 45.923038 | K43: 46.325333 | L43: 46.731335 | M43: 47.1171 | N43: 47.482719 | O43: 47.832832 | P43: 48.167053 | Q43: 48.485764 | R43: 48.797119 | S43: 49.099205 | T43: 49.389946 | U43: 49.682034 | V43: 49.971329 | W43: 50.256351 | X43: 50.537724 | Y43: 50.816631 | Z43: 51.100376 | AA43: 51.385639 | AB43: 51.670338 | AC43: 51.956215 | AD43: 52.243725 | AE43: 52.532379 | AF43: 52.822529 | AG43: 53.108795 | AH43: 53.391727 | AI43: 53.67474 | AJ43: 53.957195 | AK43: =AJ43*(1+$AU43) -> 54.241136 | AL43: =AK43*(1+$AU43) -> 54.526572 | AM43: =AL43*(1+$AU43) -> 54.81351 | AN43: =AM43*(1+$AU43) -> 55.101957 | AO43: =AN43*(1+$AU43) -> 55.391923 | AP43: =AO43*(1+$AU43) -> 55.683414 | AQ43: =AP43*(1+$AU43) -> 55.976439 | AR43: =AQ43*(1+$AU43) -> 56.271007 | ... AT43: =AS43*(1+$AU43) -> 56.8648 | AU43: =AJ43/AI43-1 -> 0.005262345 | AV43: 0.006
A44: Stock Average Equipment Efficiency | C44: 30-AEO2021.46.
A45: Main Space Heaters | C45: 30-AEO2021.47.
A46: Electric Heat Pumps (HSPF) | B46: Residential Equipment: Stock Average Efficiency: Main Space Heaters: Electric Heat Pumps: High oil and gas supply | C46: 30-AEO2021.48.highogs-d120120a | D46: HSPF | F46: 8.111535 | G46: 8.148027 | H46: 8.185239 | I46: 8.238631 | J46: 8.288433 | K46: 8.335285 | L46: 8.378555 | M46: 8.418251 | N46: 8.454421 | O46: 8.487426 | P46: 8.517176 | Q46: 8.543756 | R46: 8.567197 | S46: 8.587339 | T46: 8.604119 | U46: 8.617334 | V46: 8.626498 | W46: 8.631158 | X46: 8.635331 | Y46: 8.638949 | Z46: 8.641977 | AA46: 8.644416 | AB46: 8.646279 | AC46: 8.647627 | AD46: 8.648523 | AE46: 8.649054 | AF46: 8.649296 | AG46: 8.649323 | AH46: 8.649201 | AI46: 8.648991 | AJ46: 8.648719 | AK46: =AJ46*(1+$AU46) -> 8.648447 | AL46: =AK46*(1+$AU46) -> 8.648175 | AM46: =AL46*(1+$AU46) -> 8.6479031 | AN46: =AM46*(1+$AU46) -> 8.6476311 | AO46: =AN46*(1+$AU46) -> 8.6473591 | AP46: =AO46*(1+$AU46) -> 8.6470872 | AQ46: =AP46*(1+$AU46) -> 8.6468152 | AR46: =AQ46*(1+$AU46) -> 8.6465433 | ... AT46: =AS46*(1+$AU46) -> 8.6459995 | AU46: =AJ46/AI46-1 -> -3.1448755e-05 | AV46: 0.002
A47: Natural Gas Heat Pumps (GCOP) | B47: Residential Equipment: Stock Average Efficiency: Main Space Heaters: Natural Gas Heat Pumps: High oil and gas supply | C47: 30-AEO2021.49.highogs-d120120a | D47: GCOP | F47: 1.3 | G47: 1.3 | H47: 1.3 | I47: 1.3 | J47: 1.3 | K47: 1.3 | L47: 1.3 | M47: 1.3 | N47: 1.3 | O47: 1.3 | P47: 1.3 | Q47: 1.3 | R47: 1.3 | S47: 1.3 | T47: 1.3 | U47: 1.3 | V47: 1.3 | W47: 1.3 | X47: 1.3 | Y47: 1.3 | Z47: 1.3 | AA47: 1.3 | AB47: 1.3 | AC47: 1.3 | AD47: 1.3 | AE47: 1.3 | AF47: 1.3 | AG47: 1.3 | AH47: 1.3 | AI47: 1.3 | AJ47: 1.3 | AK47: =AJ47*(1+$AU47) -> 1.3 | AL47: =AK47*(1+$AU47) -> 1.3 | AM47: =AL47*(1+$AU47) -> 1.3 | AN47: =AM47*(1+$AU47) -> 1.3 | AO47: =AN47*(1+$AU47) -> 1.3 | AP47: =AO47*(1+$AU47) -> 1.3 | AQ47: =AP47*(1+$AU47) -> 1.3 | AR47: =AQ47*(1+$AU47) -> 1.3 | ... AT47: =AS47*(1+$AU47) -> 1.3 | AU47: =AJ47/AI47-1 -> 0 | AV47: 0
A48: Geothermal Heat Pumps (COP) | B48: Residential Equipment: Stock Average Efficiency: Main Space Heaters: Geothermal Heat Pumps: High oil and gas supply | C48: 30-AEO2021.50.highogs-d120120a | D48: COP | F48: 3.404802 | G48: 3.456838 | H48: 3.485908 | I48: 3.511074 | J48: 3.533869 | K48: 3.551336 | L48: 3.566935 | M48: 3.580438 | N48: 3.592196 | O48: 3.602517 | P48: 3.611648 | Q48: 3.619861 | R48: 3.62734 | S48: 3.634226 | T48: 3.640664 | U48: 3.646663 | V48: 3.652185 | W48: 3.657249 | X48: 3.661824 | Y48: 3.66599 | Z48: 3.66963 | AA48: 3.672833 | AB48: 3.675541 | AC48: 3.677655 | AD48: 3.679239 | AE48: 3.680244 | AF48: 3.680633 | AG48: 3.681017 | AH48: 3.681348 | AI48: 3.681579 | AJ48: 3.68171 | AK48: =AJ48*(1+$AU48) -> 3.681841 | AL48: =AK48*(1+$AU48) -> 3.681972 | AM48: =AL48*(1+$AU48) -> 3.682103 | AN48: =AM48*(1+$AU48) -> 3.682234 | AO48: =AN48*(1+$AU48) -> 3.6823651 | AP48: =AO48*(1+$AU48) -> 3.6824961 | AQ48: =AP48*(1+$AU48) -> 3.6826271 | AR48: =AQ48*(1+$AU48) -> 3.6827582 | ... AT48: =AS48*(1+$AU48) -> 3.6830203 | AU48: =AJ48/AI48-1 -> 3.5582558e-05 | AV48: 0.003
A49: Natural Gas Furnace (AFUE) | B49: Residential Equipment: Stock Average Efficiency: Main Space Heaters: Natural Gas Furnace: High oil and gas supply | C49: 30-AEO2021.51.highogs-d120120a | D49: AFUE | F49: 0.820036 | G49: 0.824161 | H49: 0.828208 | I49: 0.832364 | J49: 0.836489 | K49: 0.840623 | L49: 0.844793 | M49: 0.848654 | N49: 0.852221 | O49: 0.85548 | P49: 0.858432 | Q49: 0.861098 | R49: 0.863464 | S49: 0.865548 | T49: 0.86734 | U49: 0.868847 | V49: 0.87007 | W49: 0.871033 | X49: 0.871727 | Y49: 0.872156 | Z49: 0.872312 | AA49: 0.872207 | AB49: 0.872118 | AC49: 0.87204 | AD49: 0.871973 | AE49: 0.871911 | AF49: 0.87185 | AG49: 0.871789 | AH49: 0.871723 | AI49: 0.87165 | AJ49: 0.871576 | AK49: =AJ49*(1+$AU49) -> 0.87150201 | AL49: =AK49*(1+$AU49) -> 0.87142802 | AM49: =AL49*(1+$AU49) -> 0.87135404 | AN49: =AM49*(1+$AU49) -> 0.87128006 | AO49: =AN49*(1+$AU49) -> 0.87120609 | AP49: =AO49*(1+$AU49) -> 0.87113213 | AQ49: =AP49*(1+$AU49) -> 0.87105818 | AR49: =AQ49*(1+$AU49) -> 0.87098423 | ... AT49: =AS49*(1+$AU49) -> 0.87083635 | AU49: =AJ49/AI49-1 -> -8.4896461e-05 | AV49: 0.002
A50: Distillate Furnace (AFUE) | B50: Residential Equipment: Stock Average Efficiency: Main Space Heaters: Distillate Furnace: High oil and gas supply | C50: 30-AEO2021.52.highogs-d120120a | D50: AFUE | F50: 0.833806 | G50: 0.834607 | H50: 0.835419 | I50: 0.83625 | J50: 0.837084 | K50: 0.837921 | L50: 0.83879 | M50: 0.839622 | N50: 0.840402 | O50: 0.84113 | P50: 0.841793 | Q50: 0.842399 | R50: 0.84294 | S50: 0.843423 | T50: 0.843849 | U50: 0.844213 | V50: 0.844513 | W50: 0.84476 | X50: 0.84495 | Y50: 0.845077 | Z50: 0.845144 | AA50: 0.845157 | AB50: 0.84517 | AC50: 0.845182 | AD50: 0.845195 | AE50: 0.845207 | AF50: 0.845216 | AG50: 0.845218 | AH50: 0.845212 | AI50: 0.845201 | AJ50: 0.845183 | AK50: =AJ50*(1+$AU50) -> 0.845165 | AL50: =AK50*(1+$AU50) -> 0.845147 | AM50: =AL50*(1+$AU50) -> 0.845129 | AN50: =AM50*(1+$AU50) -> 0.845111 | AO50: =AN50*(1+$AU50) -> 0.84509301 | AP50: =AO50*(1+$AU50) -> 0.84507501 | AQ50: =AP50*(1+$AU50) -> 0.84505701 | AR50: =AQ50*(1+$AU50) -> 0.84503901 | ... AT50: =AS50*(1+$AU50) -> 0.84500302 | AU50: =AJ50/AI50-1 -> -2.1296709e-05 | AV50: 0
A51: Space Cooling | C51: 30-AEO2021.54.
A52: Electric Heat Pumps (SEER) | B52: Residential Equipment: Stock Average Efficiency: Space Cooling: Electric Heat Pumps: High oil and gas supply | C52: 30-AEO2021.55.highogs-d120120a | D52: SEER | F52: 13.797462 | G52: 13.926193 | H52: 14.057533 | I52: 14.24401 | J52: 14.417166 | K52: 14.578956 | L52: 14.728313 | M52: 14.865371 | N52: 14.990281 | O52: 15.104233 | P52: 15.206942 | Q52: 15.298712 | R52: 15.379595 | S52: 15.449061 | T52: 15.506894 | U52: 15.552299 | V52: 15.58355 | W52: 15.599044 | X52: 15.613103 | Y52: 15.625437 | Z52: 15.635885 | AA52: 15.644399 | AB52: 15.65105 | AC52: 15.655994 | AD52: 15.659428 | AE52: 15.661617 | AF52: 15.662818 | AG52: 15.663286 | AH52: 15.663247 | AI52: 15.662853 | AJ52: 15.662251 | AK52: =AJ52*(1+$AU52) -> 15.661649 | AL52: =AK52*(1+$AU52) -> 15.661047 | AM52: =AL52*(1+$AU52) -> 15.660445 | AN52: =AM52*(1+$AU52) -> 15.659843 | AO52: =AN52*(1+$AU52) -> 15.659241 | AP52: =AO52*(1+$AU52) -> 15.658639 | AQ52: =AP52*(1+$AU52) -> 15.658038 | AR52: =AQ52*(1+$AU52) -> 15.657436 | ... AT52: =AS52*(1+$AU52) -> 15.656232 | AU52: =AJ52/AI52-1 -> -3.8434888e-05 | AV52: 0.004
A53: Natural Gas Heat Pumps (GCOP) | B53: Residential Equipment: Stock Average Efficiency: Space Cooling: Natural Gas Heat Pumps: High oil and gas supply | C53: 30-AEO2021.56.highogs-d120120a | D53: GCOP | F53: 0.605712 | G53: 0.611056 | H53: 0.617004 | I53: 0.623586 | J53: 0.629972 | K53: 0.636158 | L53: 0.642119 | M53: 0.647926 | N53: 0.653643 | O53: 0.659434 | P53: 0.665412 | Q53: 0.67168 | R53: 0.67818 | S53: 0.684598 | T53: 0.690423 | U53: 0.69506 | V53: 0.698055 | W53: 0.699287 | X53: 0.699812 | Y53: 0.699968 | Z53: 0.699997 | AA53: 0.7 | AB53: 0.7 | AC53: 0.7 | AD53: 0.7 | AE53: 0.7 | AF53: 0.7 | AG53: 0.7 | AH53: 0.7 | AI53: 0.7 | AJ53: 0.7 | AK53: =AJ53*(1+$AU53) -> 0.7 | AL53: =AK53*(1+$AU53) -> 0.7 | AM53: =AL53*(1+$AU53) -> 0.7 | AN53: =AM53*(1+$AU53) -> 0.7 | AO53: =AN53*(1+$AU53) -> 0.7 | AP53: =AO53*(1+$AU53) -> 0.7 | AQ53: =AP53*(1+$AU53) -> 0.7 | AR53: =AQ53*(1+$AU53) -> 0.7 | ... AT53: =AS53*(1+$AU53) -> 0.7 | AU53: =AJ53/AI53-1 -> 0 | AV53: 0.005
A54: Geothermal Heat Pumps (EER) | B54: Residential Equipment: Stock Average Efficiency: Space Cooling: Geothermal Heat Pumps: High oil and gas supply | C54: 30-AEO2021.57.highogs-d120120a | D54: EER | F54: 15.371568 | G54: 15.734037 | H54: 15.935176 | I54: 16.106571 | J54: 16.263645 | K54: 16.384064 | L54: 16.490524 | M54: 16.582977 | N54: 16.663639 | O54: 16.734409 | P54: 16.796885 | Q54: 16.852787 | R54: 16.9034 | S54: 16.949652 | T54: 16.992464 | U54: 17.032129 | V54: 17.068327 | W54: 17.101297 | X54: 17.130928 | Y54: 17.157759 | Z54: 17.181078 | AA54: 17.201529 | AB54: 17.218733 | AC54: 17.232082 | AD54: 17.242004 | AE54: 17.248192 | AF54: 17.250374 | AG54: 17.252562 | AH54: 17.254446 | AI54: 17.255705 | AJ54: 17.256344 | AK54: =AJ54*(1+$AU54) -> 17.256983 | AL54: =AK54*(1+$AU54) -> 17.257622 | AM54: =AL54*(1+$AU54) -> 17.258261 | AN54: =AM54*(1+$AU54) -> 17.2589 | AO54: =AN54*(1+$AU54) -> 17.259539 | AP54: =AO54*(1+$AU54) -> 17.260178 | AQ54: =AP54*(1+$AU54) -> 17.260818 | AR54: =AQ54*(1+$AU54) -> 17.261457 | ... AT54: =AS54*(1+$AU54) -> 17.262735 | AU54: =AJ54/AI54-1 -> 3.7031231e-05 | AV54: 0.004
A55: Central Air Conditioners (SEER) | B55: Residential Equipment: Stock Average Efficiency: Space Cooling: Central Air Conditioners: High oil and gas supply | C55: 30-AEO2021.58.highogs-d120120a | D55: SEER | F55: 13.228506 | G55: 13.367886 | H55: 13.5061 | I55: 13.697567 | J55: 13.876314 | K55: 14.041323 | L55: 14.191576 | M55: 14.327323 | N55: 14.448998 | O55: 14.558713 | P55: 14.656015 | Q55: 14.740971 | R55: 14.814637 | S55: 14.878531 | T55: 14.932228 | U55: 14.976406 | V55: 15.010351 | W55: 15.032672 | X55: 15.054671 | Y55: 15.075858 | Z55: 15.095746 | AA55: 15.113917 | AB55: 15.130078 | AC55: 15.144073 | AD55: 15.155849 | AE55: 15.165525 | AF55: 15.173274 | AG55: 15.17935 | AH55: 15.184054 | AI55: 15.187647 | AJ55: 15.190414 | AK55: =AJ55*(1+$AU55) -> 15.193182 | AL55: =AK55*(1+$AU55) -> 15.19595 | AM55: =AL55*(1+$AU55) -> 15.198718 | AN55: =AM55*(1+$AU55) -> 15.201487 | AO55: =AN55*(1+$AU55) -> 15.204257 | AP55: =AO55*(1+$AU55) -> 15.207027 | AQ55: =AP55*(1+$AU55) -> 15.209797 | AR55: =AQ55*(1+$AU55) -> 15.212568 | ... AT55: =AS55*(1+$AU55) -> 15.218112 | AU55: =AJ55/AI55-1 -> 0.00018218754 | AV55: 0.005
A56: Room Air Conditioners (EER) | B56: Residential Equipment: Stock Average Efficiency: Space Cooling: Room Air Conditioners: High oil and gas supply | C56: 30-AEO2021.59.highogs-d120120a | D56: EER | F56: 11.152912 | G56: 11.219048 | H56: 11.291065 | I56: 11.36786 | J56: 11.450334 | K56: 11.525957 | L56: 11.591891 | M56: 11.647797 | N56: 11.694968 | O56: 11.732699 | P56: 11.783393 | Q56: 11.819624 | R56: 11.84202 | S56: 11.865673 | T56: 11.890105 | U56: 11.914655 | V56: 11.938442 | W56: 11.960458 | X56: 11.979723 | Y56: 11.995473 | Z56: 12.021017 | AA56: 12.042463 | AB56: 12.060704 | AC56: 12.076612 | AD56: 12.091027 | AE56: 12.104455 | AF56: 12.117017 | AG56: 12.128483 | AH56: 12.138476 | AI56: 12.146648 | AJ56: 12.152834 | AK56: =AJ56*(1+$AU56) -> 12.159023 | AL56: =AK56*(1+$AU56) -> 12.165215 | AM56: =AL56*(1+$AU56) -> 12.171411 | AN56: =AM56*(1+$AU56) -> 12.17761 | AO56: =AN56*(1+$AU56) -> 12.183811 | AP56: =AO56*(1+$AU56) -> 12.190016 | AQ56: =AP56*(1+$AU56) -> 12.196224 | AR56: =AQ56*(1+$AU56) -> 12.202436 | ... AT56: =AS56*(1+$AU56) -> 12.214868 | AU56: =AJ56/AI56-1 -> 0.0005092763 | AV56: 0.003
A57: Water Heaters | C57: 30-AEO2021.61.
A58: Electric (EF) | B58: Residential Equipment: Stock Average Efficiency: Water Heaters: Electric: High oil and gas supply | C58: 30-AEO2021.62.highogs-d120120a | D58: EF | F58: 0.906938 | G58: 0.912209 | H58: 0.917537 | I58: 0.922826 | J58: 0.928107 | K58: 0.933387 | L58: 0.938625 | M58: 0.943368 | N58: 0.94764 | O58: 0.951441 | P58: 0.954797 | Q58: 0.957712 | R58: 0.96019 | S58: 0.962247 | T58: 0.963881 | U58: 0.965093 | V58: 0.965901 | W58: 0.966295 | X58: 0.96629 | Y58: 0.966287 | Z58: 0.966284 | AA58: 0.966282 | AB58: 0.96628 | AC58: 0.966279 | AD58: 0.966277 | AE58: 0.966276 | AF58: 0.966274 | AG58: 0.966273 | AH58: 0.966272 | AI58: 0.96627 | AJ58: 0.966269 | AK58: =AJ58*(1+$AU58) -> 0.966268 | AL58: =AK58*(1+$AU58) -> 0.966267 | AM58: =AL58*(1+$AU58) -> 0.966266 | AN58: =AM58*(1+$AU58) -> 0.966265 | AO58: =AN58*(1+$AU58) -> 0.966264 | AP58: =AO58*(1+$AU58) -> 0.966263 | AQ58: =AP58*(1+$AU58) -> 0.966262 | AR58: =AQ58*(1+$AU58) -> 0.966261 | ... AT58: =AS58*(1+$AU58) -> 0.966259 | AU58: =AJ58/AI58-1 -> -1.0349074e-06 | AV58: 0.002
A59: Natural Gas (EF) | B59: Residential Equipment: Stock Average Efficiency: Water Heaters: Natural Gas: High oil and gas supply | C59: 30-AEO2021.63.highogs-d120120a | D59: EF | F59: 0.608571 | G59: 0.613722 | H59: 0.618254 | I59: 0.622173 | J59: 0.625473 | K59: 0.62819 | L59: 0.630332 | M59: 0.631928 | N59: 0.632941 | O59: 0.633409 | P59: 0.633409 | Q59: 0.633416 | R59: 0.633432 | S59: 0.633454 | T59: 0.633481 | U59: 0.63351 | V59: 0.633541 | W59: 0.633573 | X59: 0.633605 | Y59: 0.633637 | Z59: 0.633667 | AA59: 0.633696 | AB59: 0.633725 | AC59: 0.633751 | AD59: 0.633776 | AE59: 0.633799 | AF59: 0.63382 | AG59: 0.633838 | AH59: 0.633853 | AI59: 0.633866 | AJ59: 0.633879 | AK59: =AJ59*(1+$AU59) -> 0.633892 | AL59: =AK59*(1+$AU59) -> 0.633905 | AM59: =AL59*(1+$AU59) -> 0.633918 | AN59: =AM59*(1+$AU59) -> 0.633931 | AO59: =AN59*(1+$AU59) -> 0.633944 | AP59: =AO59*(1+$AU59) -> 0.63395701 | AQ59: =AP59*(1+$AU59) -> 0.63397001 | AR59: =AQ59*(1+$AU59) -> 0.63398301 | ... AT59: =AS59*(1+$AU59) -> 0.63400901 | AU59: =AJ59/AI59-1 -> 2.0509067e-05 | AV59: 0.001
A60: Distillate Fuel Oil (EF) | B60: Residential Equipment: Stock Average Efficiency: Water Heaters: Distillate Fuel Oil: High oil and gas supply | C60: 30-AEO2021.64.highogs-d120120a | D60: EF | F60: 0.582561 | G60: 0.597952 | H60: 0.61217 | I60: 0.625005 | J60: 0.63619 | K60: 0.645622 | L60: 0.653363 | M60: 0.659288 | N60: 0.663328 | O60: 0.665386 | P60: 0.665416 | Q60: 0.665449 | R60: 0.665487 | S60: 0.665527 | T60: 0.665569 | U60: 0.66561 | V60: 0.665648 | W60: 0.665686 | X60: 0.665724 | Y60: 0.665757 | Z60: 0.665792 | AA60: 0.665824 | AB60: 0.665854 | AC60: 0.665882 | AD60: 0.665909 | AE60: 0.665936 | AF60: 0.665961 | AG60: 0.665985 | AH60: 0.666007 | AI60: 0.66603 | AJ60: 0.666053 | AK60: =AJ60*(1+$AU60) -> 0.666076 | AL60: =AK60*(1+$AU60) -> 0.666099 | AM60: =AL60*(1+$AU60) -> 0.666122 | AN60: =AM60*(1+$AU60) -> 0.66614501 | AO60: =AN60*(1+$AU60) -> 0.66616801 | AP60: =AO60*(1+$AU60) -> 0.66619102 | AQ60: =AP60*(1+$AU60) -> 0.66621402 | AR60: =AQ60*(1+$AU60) -> 0.66623703 | ... AT60: =AS60*(1+$AU60) -> 0.66628304 | AU60: =AJ60/AI60-1 -> 3.4532979e-05 | AV60: 0.004
A61: Propane (EF) | B61: Residential Equipment: Stock Average Efficiency: Water Heaters: Propane: High oil and gas supply | C61: 30-AEO2021.65.highogs-d120120a | D61: EF | F61: 0.599473 | G61: 0.603086 | H61: 0.606431 | I61: 0.609429 | J61: 0.612014 | K61: 0.614186 | L61: 0.615945 | M61: 0.617278 | N61: 0.618165 | O61: 0.618599 | P61: 0.618585 | Q61: 0.618579 | R61: 0.618582 | S61: 0.618597 | T61: 0.618624 | U61: 0.61866 | V61: 0.618707 | W61: 0.618769 | X61: 0.618845 | Y61: 0.61893 | Z61: 0.619023 | AA61: 0.619123 | AB61: 0.619228 | AC61: 0.619332 | AD61: 0.619439 | AE61: 0.619546 | AF61: 0.619654 | AG61: 0.619765 | AH61: 0.619877 | AI61: 0.619992 | AJ61: 0.62011 | AK61: =AJ61*(1+$AU61) -> 0.62022802 | AL61: =AK61*(1+$AU61) -> 0.62034607 | AM61: =AL61*(1+$AU61) -> 0.62046413 | AN61: =AM61*(1+$AU61) -> 0.62058222 | AO61: =AN61*(1+$AU61) -> 0.62070034 | AP61: =AO61*(1+$AU61) -> 0.62081847 | AQ61: =AP61*(1+$AU61) -> 0.62093663 | AR61: =AQ61*(1+$AU61) -> 0.62105481 | ... AT61: =AS61*(1+$AU61) -> 0.62129124 | AU61: =AJ61/AI61-1 -> 0.00019032504 | AV61: 0.001
A62: Other Appliances (kilowatthours per year) | C62: 30-AEO2021.67.
A63: Refrigerators | B63: Residential Equipment: Stock Average Efficiency: Other Appliances: Refrigerators: High oil and gas supply | C63: 30-AEO2021.68.highogs-d120120a | D63: kWh | F63: 621.62353 | G63: 612.01746 | H63: 602.28351 | I63: 592.46655 | J63: 583.16315 | K63: 574.37079 | L63: 566.11255 | M63: 558.39551 | N63: 551.1908 | O63: 544.47058 | P63: 538.25568 | Q63: 532.6206 | R63: 527.52893 | S63: 522.97797 | T63: 518.96454 | U63: 515.45685 | V63: 512.45496 | W63: 509.93149 | X63: 507.91202 | Y63: 506.37027 | Z63: 505.33246 | AA63: 504.82309 | AB63: 504.8302 | AC63: 504.83661 | AD63: 504.84296 | AE63: 504.84894 | AF63: 504.85556 | AG63: 504.86337 | AH63: 504.87289 | AI63: 504.8848 | AJ63: 504.89883 | AK63: =AJ63*(1+$AU63) -> 504.91287 | AL63: =AK63*(1+$AU63) -> 504.92691 | AM63: =AL63*(1+$AU63) -> 504.94095 | AN63: =AM63*(1+$AU63) -> 504.95499 | AO63: =AN63*(1+$AU63) -> 504.96903 | AP63: =AO63*(1+$AU63) -> 504.98307 | AQ63: =AP63*(1+$AU63) -> 504.99711 | AR63: =AQ63*(1+$AU63) -> 505.01115 | ... AT63: =AS63*(1+$AU63) -> 505.03924 | AU63: =AJ63/AI63-1 -> 2.7804363e-05 | AV63: -0.007
A64: Freezers | B64: Residential Equipment: Stock Average Efficiency: Other Appliances: Freezers: High oil and gas supply | C64: 30-AEO2021.69.highogs-d120120a | D64: kWh | F64: 458.33588 | G64: 453.5516 | H64: 448.81262 | I64: 444.02313 | J64: 439.13892 | K64: 434.15997 | L64: 429.10785 | M64: 424.04935 | N64: 419.25418 | O64: 414.70547 | P64: 410.41049 | Q64: 406.34891 | R64: 402.49783 | S64: 398.87881 | T64: 395.50369 | U64: 392.3512 | V64: 389.46231 | W64: 386.81314 | X64: 384.4151 | Y64: 382.25317 | Z64: 380.31238 | AA64: 378.63962 | AB64: 377.2121 | AC64: 376.06656 | AD64: 375.2218 | AE64: 374.67923 | AF64: 374.43268 | AG64: 374.43494 | AH64: 374.43723 | AI64: 374.43997 | AJ64: 374.44287 | AK64: =AJ64*(1+$AU64) -> 374.44577 | AL64: =AK64*(1+$AU64) -> 374.44867 | AM64: =AL64*(1+$AU64) -> 374.45157 | AN64: =AM64*(1+$AU64) -> 374.45447 | AO64: =AN64*(1+$AU64) -> 374.45737 | AP64: =AO64*(1+$AU64) -> 374.46027 | AQ64: =AP64*(1+$AU64) -> 374.46316 | AR64: =AQ64*(1+$AU64) -> 374.46606 | ... AT64: =AS64*(1+$AU64) -> 374.47186 | AU64: =AJ64/AI64-1 -> 7.742229e-06 | AV64: -0.007
A65: Building Shell Efficiency Index | C65: 30-AEO2021.71.
A66: Space Heating | C66: 30-AEO2021.72.
A67: Pre-2015 Homes | B67: Residential Equipment: Building Shell Efficiency Index: Space Heating: Pre-2015 Homes: High oil and gas supply | C67: 30-AEO2021.73.highogs-d120120a | D67: 2015=1.00 | F67: 0.968571 | G67: 0.962195 | H67: 0.955582 | I67: 0.949151 | J67: 0.943134 | K67: 0.936788 | L67: 0.93005 | M67: 0.923079 | N67: 0.916107 | O67: 0.90907 | P67: 0.901684 | Q67: 0.89444 | R67: 0.887384 | S67: 0.880476 | T67: 0.873658 | U67: 0.866962 | V67: 0.860326 | W67: 0.853676 | X67: 0.84703 | Y67: 0.840425 | Z67: 0.833814 | AA67: 0.827163 | AB67: 0.82049 | AC67: 0.813841 | AD67: 0.807191 | AE67: 0.80053 | AF67: 0.793907 | AG67: 0.787308 | AH67: 0.780779 | AI67: 0.774272 | AJ67: 0.767739 | AK67: =AJ67*(1+$AU67) -> 0.76126112 | AL67: =AK67*(1+$AU67) -> 0.7548379 | AM67: =AL67*(1+$AU67) -> 0.74846888 | AN67: =AM67*(1+$AU67) -> 0.7421536 | AO67: =AN67*(1+$AU67) -> 0.7358916 | AP67: =AO67*(1+$AU67) -> 0.72968244 | AQ67: =AP67*(1+$AU67) -> 0.72352567 | AR67: =AQ67*(1+$AU67) -> 0.71742084 | ... AT67: =AS67*(1+$AU67) -> 0.7053653 | AU67: =AJ67/AI67-1 -> -0.0084376033 | AV67: -0.008
A68: New Construction | B68: Residential Equipment: Building Shell Efficiency Index: Space Heating: New Construction: High oil and gas supply | C68: 30-AEO2021.74.highogs-d120120a | D68: 2015=1.00 | F68: 0.876126 | G68: 0.860731 | H68: 0.861051 | I68: 0.839112 | J68: 0.840975 | K68: 0.849549 | L68: 0.847296 | M68: 0.844043 | N68: 0.842346 | O68: 0.840842 | P68: 0.839463 | Q68: 0.837842 | R68: 0.83629 | S68: 0.834089 | T68: 0.832987 | U68: 0.832546 | V68: 0.831627 | W68: 0.83117 | X68: 0.831116 | Y68: 0.831876 | Z68: 0.830613 | AA68: 0.829312 | AB68: 0.828532 | AC68: 0.826976 | AD68: 0.823783 | AE68: 0.822167 | AF68: 0.819808 | AG68: 0.818721 | AH68: 0.81884 | AI68: 0.818812 | AJ68: 0.819035 | AK68: =AJ68*(1+$AU68) -> 0.81925806 | AL68: =AK68*(1+$AU68) -> 0.81948118 | AM68: =AL68*(1+$AU68) -> 0.81970436 | AN68: =AM68*(1+$AU68) -> 0.81992761 | AO68: =AN68*(1+$AU68) -> 0.82015091 | AP68: =AO68*(1+$AU68) -> 0.82037428 | AQ68: =AP68*(1+$AU68) -> 0.8205977 | AR68: =AQ68*(1+$AU68) -> 0.82082119 | ... AT68: =AS68*(1+$AU68) -> 0.82126834 | AU68: =AJ68/AI68-1 -> 0.00027234579 | AV68: -0.002
A69: All Homes | B69: Residential Equipment: Building Shell Efficiency Index: Space Heating: All Homes: High oil and gas supply | C69: 30-AEO2021.75.highogs-d120120a | D69: 2015=1.00 | F69: 0.962651 | G69: 0.955521 | H69: 0.94833 | I69: 0.941222 | J69: 0.934641 | K69: 0.927968 | L69: 0.921074 | M69: 0.914127 | N69: 0.907337 | O69: 0.900631 | P69: 0.893765 | Q69: 0.88715 | R69: 0.880805 | S69: 0.874683 | T69: 0.868742 | U69: 0.862995 | V69: 0.857387 | W69: 0.851859 | X69: 0.846424 | Y69: 0.841116 | Z69: 0.835877 | AA69: 0.830681 | AB69: 0.825547 | AC69: 0.820499 | AD69: 0.815506 | AE69: 0.81057 | AF69: 0.805722 | AG69: 0.800958 | AH69: 0.79632 | AI69: 0.79177 | AJ69: 0.787274 | AK69: =AJ69*(1+$AU69) -> 0.78280353 | AL69: =AK69*(1+$AU69) -> 0.77835845 | AM69: =AL69*(1+$AU69) -> 0.7739386 | AN69: =AM69*(1+$AU69) -> 0.76954386 | AO69: =AN69*(1+$AU69) -> 0.76517407 | AP69: =AO69*(1+$AU69) -> 0.76082909 | AQ69: =AP69*(1+$AU69) -> 0.75650878 | AR69: =AQ69*(1+$AU69) -> 0.75221301 | ... AT69: =AS69*(1+$AU69) -> 0.74369451 | AU69: =AJ69/AI69-1 -> -0.0056784167 | AV69: -0.007
A70: Space Cooling | C70: 30-AEO2021.77.
A71: Pre-2015 Homes | B71: Residential Equipment: Building Shell Efficiency Index: Space Cooling: Pre-2015 Homes: High oil and gas supply | C71: 30-AEO2021.78.highogs-d120120a | D71: 2015=1.00 | F71: 0.98903 | G71: 0.986797 | H71: 0.984451 | I71: 0.98215 | J71: 0.979987 | K71: 0.97771 | L71: 0.975284 | M71: 0.972761 | N71: 0.970241 | O71: 0.967699 | P71: 0.965038 | Q71: 0.962423 | R71: 0.959869 | S71: 0.957359 | T71: 0.954884 | U71: 0.952455 | V71: 0.950051 | W71: 0.947639 | X71: 0.945221 | Y71: 0.942821 | Z71: 0.940406 | AA71: 0.937965 | AB71: 0.935515 | AC71: 0.933067 | AD71: 0.930615 | AE71: 0.928151 | AF71: 0.925701 | AG71: 0.923265 | AH71: 0.920855 | AI71: 0.918445 | AJ71: 0.916023 | AK71: =AJ71*(1+$AU71) -> 0.91360739 | AL71: =AK71*(1+$AU71) -> 0.91119814 | AM71: =AL71*(1+$AU71) -> 0.90879525 | AN71: =AM71*(1+$AU71) -> 0.9063987 | AO71: =AN71*(1+$AU71) -> 0.90400847 | AP71: =AO71*(1+$AU71) -> 0.90162454 | AQ71: =AP71*(1+$AU71) -> 0.8992469 | AR71: =AQ71*(1+$AU71) -> 0.89687552 | ... AT71: =AS71*(1+$AU71) -> 0.89215152 | AU71: =AJ71/AI71-1 -> -0.0026370659 | AV71: -0.003
A72: New Construction | B72: Residential Equipment: Building Shell Efficiency Index: Space Cooling: New Construction: High oil and gas supply | C72: 30-AEO2021.79.highogs-d120120a | D72: 2015=1.00 | F72: 0.990509 | G72: 0.983555 | H72: 0.983457 | I72: 0.977568 | J72: 0.979438 | K72: 0.984205 | L72: 0.983688 | M72: 0.981513 | N72: 0.980007 | O72: 0.978529 | P72: 0.977208 | Q72: 0.975998 | R72: 0.975184 | S72: 0.974275 | T72: 0.97414 | U72: 0.974631 | V72: 0.974859 | W72: 0.974992 | X72: 0.975273 | Y72: 0.976324 | Z72: 0.976343 | AA72: 0.9762 | AB72: 0.97628 | AC72: 0.975767 | AD72: 0.974184 | AE72: 0.973526 | AF72: 0.972333 | AG72: 0.971717 | AH72: 0.971882 | AI72: 0.97206 | AJ72: 0.972266 | AK72: =AJ72*(1+$AU72) -> 0.97247204 | AL72: =AK72*(1+$AU72) -> 0.97267813 | AM72: =AL72*(1+$AU72) -> 0.97288426 | AN72: =AM72*(1+$AU72) -> 0.97309044 | AO72: =AN72*(1+$AU72) -> 0.97329666 | AP72: =AO72*(1+$AU72) -> 0.97350292 | AQ72: =AP72*(1+$AU72) -> 0.97370922 | AR72: =AQ72*(1+$AU72) -> 0.97391557 | ... AT72: =AS72*(1+$AU72) -> 0.9743284 | AU72: =AJ72/AI72-1 -> 0.00021192107 | AV72: -0.001
A73: All Homes | B73: Residential Equipment: Building Shell Efficiency Index: Space Cooling: All Homes: High oil and gas supply | C73: 30-AEO2021.80.highogs-d120120a | D73: 2015=1.00 | F73: 0.989177 | G73: 0.987004 | H73: 0.984764 | I73: 0.982549 | J73: 0.980518 | K73: 0.978465 | L73: 0.976309 | M73: 0.974079 | N73: 0.971872 | O73: 0.969662 | P73: 0.967369 | Q73: 0.965134 | R73: 0.962973 | S73: 0.960868 | T73: 0.958813 | U73: 0.956825 | V73: 0.95488 | W73: 0.952949 | X73: 0.951035 | Y73: 0.949162 | Z73: 0.947297 | AA73: 0.945429 | AB73: 0.943573 | AC73: 0.941732 | AD73: 0.939896 | AE73: 0.938064 | AF73: 0.936252 | AG73: 0.934462 | AH73: 0.932708 | AI73: 0.930972 | AJ73: 0.929241 | AK73: =AJ73*(1+$AU73) -> 0.92751322 | AL73: =AK73*(1+$AU73) -> 0.92578865 | AM73: =AL73*(1+$AU73) -> 0.92406729 | AN73: =AM73*(1+$AU73) -> 0.92234913 | AO73: =AN73*(1+$AU73) -> 0.92063416 | AP73: =AO73*(1+$AU73) -> 0.91892238 | AQ73: =AP73*(1+$AU73) -> 0.91721378 | AR73: =AQ73*(1+$AU73) -> 0.91550837 | ... AT73: =AS73*(1+$AU73) -> 0.91210704 | AU73: =AJ73/AI73-1 -> -0.001859347 | AV73: -0.002
A74: Distributed Generation and | C74: 30-AEO2021.82.
A75: Combined Heat and Power | C75: 30-AEO2021.83.
A76: Generating Capacity (gigawatts) | C76: 30-AEO2021.84.
A77: Natural Gas Fuel Cells | B77: Residential: Combined Heat and Power: Generating Capacity: Fuel Cells: High oil and gas supply | C77: 30-AEO2021.85.highogs-d120120a | D77: GW | F77: 0 | G77: 0 | H77: 0 | I77: 0 | J77: 0 | K77: 0 | L77: 0 | M77: 0 | N77: 0 | O77: 0 | P77: 0 | Q77: 0 | R77: 0 | S77: 0 | T77: 2e-06 | U77: 5e-06 | V77: 1.1e-05 | W77: 2.1e-05 | X77: 4.2e-05 | Y77: 7.9e-05 | Z77: 0.000148 | AA77: 0.000273 | AB77: 0.000399 | AC77: 0.000525 | AD77: 0.000653 | AE77: 0.000781 | AF77: 0.00091 | AG77: 0.00104 | AH77: 0.00117 | AI77: 0.001301 | AJ77: 0.001433 | AK77: =AJ77*(1+$AU77) -> 0.0015783928 | AL77: =AK77*(1+$AU77) -> 0.0017385372 | AM77: =AL77*(1+$AU77) -> 0.0019149299 | AN77: =AM77*(1+$AU77) -> 0.0021092194 | AO77: =AN77*(1+$AU77) -> 0.0023232217 | AP77: =AO77*(1+$AU77) -> 0.0025589368 | AQ77: =AP77*(1+$AU77) -> 0.0028185675 | AR77: =AQ77*(1+$AU77) -> 0.0031045406 | ... AT77: =AS77*(1+$AU77) -> 0.0037664753 | AU77: =AJ77/AI77-1 -> 0.10146042 | AV77: - -
A78: Solar Photovoltaic | B78: Residential: Combined Heat and Power: Generating Capacity: Solar Photovoltaic: High oil and gas supply | C78: 30-AEO2021.86.highogs-d120120a | D78: GW | F78: 18.318205 | G78: 21.089043 | H78: 23.519173 | I78: 25.89143 | J78: 28.221027 | K78: 30.570915 | L78: 32.975586 | M78: 35.38728 | N78: 37.822853 | O78: 40.271053 | P78: 42.775265 | Q78: 45.335365 | R78: 47.952148 | S78: 50.609779 | T78: 53.324265 | U78: 56.072327 | V78: 58.87286 | W78: 61.71526 | X78: 64.619888 | Y78: 67.572464 | Z78: 70.595703 | AA78: 73.678421 | AB78: 76.830017 | AC78: 80.069023 | AD78: 83.38549 | AE78: 86.808281 | AF78: 90.307793 | AG78: 93.88311 | AH78: 97.568703 | AI78: 101.33858 | AJ78: 105.19511 | AK78: =AJ78*(1+$AU78) -> 109.19839 | AL78: =AK78*(1+$AU78) -> 113.35403 | AM78: =AL78*(1+$AU78) -> 117.6678 | AN78: =AM78*(1+$AU78) -> 122.14575 | AO78: =AN78*(1+$AU78) -> 126.7941 | AP78: =AO78*(1+$AU78) -> 131.61936 | AQ78: =AP78*(1+$AU78) -> 136.62824 | AR78: =AQ78*(1+$AU78) -> 141.82774 | ... AT78: =AS78*(1+$AU78) -> 152.82788 | AU78: =AJ78/AI78-1 -> 0.038055811 | AV78: 0.06
A79: Wind | B79: Residential: Combined Heat and Power: Generating Capacity: Wind: High oil and gas supply | C79: 30-AEO2021.87.highogs-d120120a | D79: GW | F79: 0.014232 | G79: 0.014232 | H79: 0.014232 | I79: 0.014232 | J79: 0.014232 | K79: 0.014232 | L79: 0.014232 | M79: 0.014232 | N79: 0.014232 | O79: 0.014232 | P79: 0.014232 | Q79: 0.014232 | R79: 0.014233 | S79: 0.014233 | T79: 0.014236 | U79: 0.014242 | V79: 0.014254 | W79: 0.014275 | X79: 0.014316 | Y79: 0.01439 | Z79: 0.014528 | AA79: 0.014778 | AB79: 0.01503 | AC79: 0.015283 | AD79: 0.015538 | AE79: 0.015795 | AF79: 0.016053 | AG79: 0.016312 | AH79: 0.016573 | AI79: 0.016835 | AJ79: 0.017098 | AK79: =AJ79*(1+$AU79) -> 0.017365109 | AL79: =AK79*(1+$AU79) -> 0.01763639 | AM79: =AL79*(1+$AU79) -> 0.01791191 | AN79: =AM79*(1+$AU79) -> 0.018191733 | AO79: =AN79*(1+$AU79) -> 0.018475928 | AP79: =AO79*(1+$AU79) -> 0.018764563 | AQ79: =AP79*(1+$AU79) -> 0.019057707 | AR79: =AQ79*(1+$AU79) -> 0.019355431 | ... AT79: =AS79*(1+$AU79) -> 0.019964904 | AU79: =AJ79/AI79-1 -> 0.015622216 | AV79: 0.006
A80: Total | B80: Residential: Combined Heat and Power: Generating Capacity: Total: High oil and gas supply | C80: 30-AEO2021.88.highogs-d120120a | D80: GW | F80: 18.332438 | G80: 21.103275 | H80: 23.533405 | I80: 25.905663 | J80: 28.23526 | K80: 30.585148 | L80: 32.989819 | M80: 35.401512 | N80: 37.837086 | O80: 40.285286 | P80: 42.789497 | Q80: 45.349598 | R80: 47.966381 | S80: 50.624012 | T80: 53.338505 | U80: 56.086571 | V80: 58.887123 | W80: 61.729557 | X80: 64.634239 | Y80: 67.586929 | Z80: 70.610374 | AA80: 73.693474 | AB80: 76.845444 | AC80: 80.084831 | AD80: 83.401688 | AE80: 86.824852 | AF80: 90.324753 | AG80: 93.900459 | AH80: 97.586441 | AI80: 101.35673 | AJ80: 105.21364 | AK80: =AJ80*(1+$AU80) -> 109.21731 | AL80: =AK80*(1+$AU80) -> 113.37334 | AM80: =AL80*(1+$AU80) -> 117.68752 | AN80: =AM80*(1+$AU80) -> 122.16586 | AO80: =AN80*(1+$AU80) -> 126.81462 | AP80: =AO80*(1+$AU80) -> 131.64027 | AQ80: =AP80*(1+$AU80) -> 136.64956 | AR80: =AQ80*(1+$AU80) -> 141.84946 | ... AT80: =AS80*(1+$AU80) -> 152.8504 | AU80: =AJ80/AI80-1 -> 0.038052827 | AV80: 0.06
A81: Net Generation (billion kilowatthours) | C81: 30-AEO2021.89.
A82: Natural Gas Fuel Cells | B82: Residential: Combined Heat and Power: Net Generation: Fuel Cells: High oil and gas supply | C82: 30-AEO2021.90.highogs-d120120a | D82: billion kWh | F82: 0 | G82: 0 | H82: 0 | I82: 0 | J82: 0 | K82: 0 | L82: 0 | M82: 0 | N82: 0 | O82: 0 | P82: 0 | Q82: 0 | R82: 0 | S82: 1e-06 | T82: 5e-06 | U82: 1.4e-05 | V82: 3e-05 | W82: 6e-05 | X82: 0.000117 | Y82: 0.00022 | Z82: 0.000412 | AA82: 0.000762 | AB82: 0.001113 | AC82: 0.001466 | AD82: 0.001822 | AE82: 0.002179 | AF82: 0.00254 | AG82: 0.002902 | AH82: 0.003265 | AI82: 0.00363 | AJ82: 0.003998 | AK82: =AJ82*(1+$AU82) -> 0.0044033069 | AL82: =AK82*(1+$AU82) -> 0.0048497027 | AM82: =AL82*(1+$AU82) -> 0.005341353 | AN82: =AM82*(1+$AU82) -> 0.0058828456 | AO82: =AN82*(1+$AU82) -> 0.0064792332 | AP82: =AO82*(1+$AU82) -> 0.0071360811 | AQ82: =AP82*(1+$AU82) -> 0.0078595185 | AR82: =AQ82*(1+$AU82) -> 0.0086562962 | ... AT82: =AS82*(1+$AU82) -> 0.010500366 | AU82: =AJ82/AI82-1 -> 0.10137741 | AV82: - -
A83: Solar Photovoltaic | B83: Residential: Combined Heat and Power: Net Generation: Solar Photovoltaic: High oil and gas supply | C83: 30-AEO2021.91.highogs-d120120a | D83: billion kWh | F83: 27.109547 | G83: 31.223125 | H83: 34.792332 | I83: 38.271561 | J83: 41.684376 | K83: 45.130352 | L83: 48.664413 | M83: 52.210365 | N83: 55.79567 | O83: 59.401932 | P83: 63.098839 | Q83: 66.885788 | R83: 70.764771 | S83: 74.710365 | T83: 78.74807 | U83: 82.841064 | V83: 87.019829 | W83: 91.267044 | X83: 95.615387 | Y83: 100.04205 | Z83: 104.58385 | AA83: 109.22242 | AB83: 113.97292 | AC83: 118.86551 | AD83: 123.8839 | AE83: 129.07486 | AF83: 134.39053 | AG83: 139.8293 | AH83: 145.44684 | AI83: 151.201 | AJ83: 157.09554 | AK83: =AJ83*(1+$AU83) -> 163.21986 | AL83: =AK83*(1+$AU83) -> 169.58295 | AM83: =AL83*(1+$AU83) -> 176.19409 | AN83: =AM83*(1+$AU83) -> 183.06297 | AO83: =AN83*(1+$AU83) -> 190.19963 | AP83: =AO83*(1+$AU83) -> 197.61452 | AQ83: =AP83*(1+$AU83) -> 205.31846 | AR83: =AQ83*(1+$AU83) -> 213.32275 | ... AT83: =AS83*(1+$AU83) -> 230.27962 | AU83: =AJ83/AI83-1 -> 0.038984735 | AV83: 0.06
A84: Wind | B84: Residential: Combined Heat and Power: Net Generation: Wind: High oil and gas supply | C84: 30-AEO2021.92.highogs-d120120a | D84: billion kWh | F84: 0.018546 | G84: 0.018546 | H84: 0.018546 | I84: 0.018546 | J84: 0.018546 | K84: 0.018546 | L84: 0.018546 | M84: 0.018546 | N84: 0.018546 | O84: 0.018546 | P84: 0.018546 | Q84: 0.018546 | R84: 0.018546 | S84: 0.018547 | T84: 0.01855 | U84: 0.018556 | V84: 0.018568 | W84: 0.01859 | X84: 0.018632 | Y84: 0.018708 | Z84: 0.018849 | AA84: 0.019106 | AB84: 0.019364 | AC84: 0.019624 | AD84: 0.019885 | AE84: 0.020148 | AF84: 0.020413 | AG84: 0.020678 | AH84: 0.020944 | AI84: 0.021211 | AJ84: 0.02148 | AK84: =AJ84*(1+$AU84) -> 0.021752411 | AL84: =AK84*(1+$AU84) -> 0.022028278 | AM84: =AL84*(1+$AU84) -> 0.022307643 | AN84: =AM84*(1+$AU84) -> 0.02259055 | AO84: =AN84*(1+$AU84) -> 0.022877046 | AP84: =AO84*(1+$AU84) -> 0.023167175 | AQ84: =AP84*(1+$AU84) -> 0.023460983 | AR84: =AQ84*(1+$AU84) -> 0.023758518 | ... AT84: =AS84*(1+$AU84) -> 0.024364955 | AU84: =AJ84/AI84-1 -> 0.012682099 | AV84: 0.005
A85: Total | B85: Residential: Combined Heat and Power: Net Generation: Total: High oil and gas supply | C85: 30-AEO2021.93.highogs-d120120a | D85: billion kWh | F85: 27.128092 | G85: 31.241671 | H85: 34.810879 | I85: 38.290108 | J85: 41.702923 | K85: 45.148899 | L85: 48.682961 | M85: 52.228912 | N85: 55.814217 | O85: 59.420479 | P85: 63.117386 | Q85: 66.904335 | R85: 70.783318 | S85: 74.728912 | T85: 78.766624 | U85: 82.859634 | V85: 87.038429 | W85: 91.285698 | X85: 95.634132 | Y85: 100.06098 | Z85: 104.60311 | AA85: 109.24229 | AB85: 113.9934 | AC85: 118.8866 | AD85: 123.90561 | AE85: 129.09718 | AF85: 134.41348 | AG85: 139.85288 | AH85: 145.47105 | AI85: 151.22584 | AJ85: 157.12102 | AK85: =AJ85*(1+$AU85) -> 163.246 | AL85: =AK85*(1+$AU85) -> 169.60975 | AM85: =AL85*(1+$AU85) -> 176.22157 | AN85: =AM85*(1+$AU85) -> 183.09114 | AO85: =AN85*(1+$AU85) -> 190.2285 | AP85: =AO85*(1+$AU85) -> 197.6441 | AQ85: =AP85*(1+$AU85) -> 205.34877 | AR85: =AQ85*(1+$AU85) -> 213.3538 | ... AT85: =AS85*(1+$AU85) -> 230.31218 | AU85: =AJ85/AI85-1 -> 0.038982569 | AV85: 0.06
A86: Disposition | C86: 30-AEO2021.94.
A87: Sales to the Grid | B87: Residential: Combined Heat and Power: Net Generation: Sales to the Grid: High oil and gas supply | C87: 30-AEO2021.95.highogs-d120120a | D87: billion kWh | F87: 4.228242 | G87: 5.022388 | H87: 5.792233 | I87: 6.554812 | J87: 7.300874 | K87: 8.065323 | L87: 8.862534 | M87: 9.662756 | N87: 10.482135 | O87: 11.304471 | P87: 12.159818 | Q87: 13.037743 | R87: 13.949456 | S87: 14.875851 | T87: 15.834056 | U87: 16.800795 | V87: 17.796278 | W87: 18.802971 | X87: 19.842371 | Y87: 20.894855 | Z87: 21.984423 | AA87: 23.09285 | AB87: 24.223326 | AC87: 25.398026 | AD87: 26.597134 | AE87: 27.848694 | AF87: 29.122913 | AG87: 30.419254 | AH87: 31.76824 | AI87: 33.140976 | AJ87: 34.537109 | AK87: =AJ87*(1+$AU87) -> 35.992057 | AL87: =AK87*(1+$AU87) -> 37.508298 | AM87: =AL87*(1+$AU87) -> 39.088413 | AN87: =AM87*(1+$AU87) -> 40.735095 | AO87: =AN87*(1+$AU87) -> 42.451146 | AP87: =AO87*(1+$AU87) -> 44.239489 | AQ87: =AP87*(1+$AU87) -> 46.10317 | AR87: =AQ87*(1+$AU87) -> 48.045363 | ... AT87: =AS87*(1+$AU87) -> 52.178652 | AU87: =AJ87/AI87-1 -> 0.042127094 | AV87: 0.073
A88: Generation for Own Use | B88: Residential: Combined Heat and Power: Net Generation: Generation for Own Use: High oil and gas supply | C88: 30-AEO2021.96.highogs-d120120a | D88: billion kWh | F88: 22.899849 | G88: 26.219282 | H88: 29.018644 | I88: 31.735296 | J88: 34.402046 | K88: 37.083572 | L88: 39.820427 | M88: 42.566154 | N88: 45.332077 | O88: 48.116009 | P88: 50.957565 | Q88: 53.866592 | R88: 56.833858 | S88: 59.853062 | T88: 62.932571 | U88: 66.058838 | V88: 69.242149 | W88: 72.482727 | X88: 75.791763 | Y88: 79.166122 | Z88: 82.61869 | AA88: 86.149437 | AB88: 89.770073 | AC88: 93.488571 | AD88: 97.308487 | AE88: 101.24849 | AF88: 105.29058 | AG88: 109.43363 | AH88: 113.70281 | AI88: 118.08487 | AJ88: 122.58391 | AK88: =AJ88*(1+$AU88) -> 127.25436 | AL88: =AK88*(1+$AU88) -> 132.10276 | AM88: =AL88*(1+$AU88) -> 137.13588 | AN88: =AM88*(1+$AU88) -> 142.36076 | AO88: =AN88*(1+$AU88) -> 147.78471 | AP88: =AO88*(1+$AU88) -> 153.41532 | AQ88: =AP88*(1+$AU88) -> 159.26045 | AR88: =AQ88*(1+$AU88) -> 165.32828 | ... AT88: =AS88*(1+$AU88) -> 178.1663 | AU88: =AJ88/AI88-1 -> 0.038100047 | AV88: 0.058
A89: Energy Input (trillion Btu) | C89: 30-AEO2021.97.
A90: Natural Gas Fuel Cells | B90: Residential: Combined Heat and Power: Energy Input: Fuel Cells: High oil and gas supply | C90: 30-AEO2021.98.highogs-d120120a | D90: trillion Btu | F90: 0 | G90: 0 | H90: 0 | I90: 0 | J90: 0 | K90: 0 | L90: 0 | M90: 0 | N90: 0 | O90: 0 | P90: 0 | Q90: 0 | R90: 3e-06 | S90: 9e-06 | T90: 4.2e-05 | U90: 0.000104 | V90: 0.000228 | W90: 0.000458 | X90: 0.000892 | Y90: 0.001677 | Z90: 0.003131 | AA90: 0.005778 | AB90: 0.008428 | AC90: 0.011089 | AD90: 0.01376 | AE90: 0.016443 | AF90: 0.019143 | AG90: 0.021843 | AH90: 0.024548 | AI90: 0.027264 | AJ90: 0.029989 | AK90: =AJ90*(1+$AU90) -> 0.03298636 | AL90: =AK90*(1+$AU90) -> 0.036283302 | AM90: =AL90*(1+$AU90) -> 0.039909769 | AN90: =AM90*(1+$AU90) -> 0.043898697 | AO90: =AN90*(1+$AU90) -> 0.048286312 | AP90: =AO90*(1+$AU90) -> 0.053112464 | AQ90: =AP90*(1+$AU90) -> 0.058420983 | AR90: =AQ90*(1+$AU90) -> 0.064260082 | ... AT90: =AS90*(1+$AU90) -> 0.07774744 | AU90: =AJ90/AI90-1 -> 0.09994865 | AV90: - -
A91: Solar Photovoltaic | B91: Residential: Combined Heat and Power: Energy Input: Solar Photovoltaic: High oil and gas supply | C91: 30-AEO2021.99.highogs-d120120a | D91: trillion Btu | F91: 225.07347 | G91: 259.67685 | H91: 288.64123 | I91: 312.46149 | J91: 337.01807 | K91: 359.23889 | L91: 383.72302 | M91: 409.68619 | N91: 436.77734 | O91: 463.25958 | P91: 495.99994 | Q91: 523.7218 | R91: 551.19031 | S91: 579.76514 | T91: 609.98492 | U91: 640.00781 | V91: 669.85529 | W91: 700.87677 | X91: 731.6488 | Y91: 764.55615 | Z91: 797.29492 | AA91: 831.85315 | AB91: 867.64453 | AC91: 903.49524 | AD91: 940.94727 | AE91: 980.27063 | AF91: 1018.873 | AG91: 1055.0437 | AH91: 1093.4607 | AI91: 1133.6433 | AJ91: 1168.6075 | AK91: =AJ91*(1+$AU91) -> 1204.6502 | AL91: =AK91*(1+$AU91) -> 1241.8044 | AM91: =AL91*(1+$AU91) -> 1280.1046 | AN91: =AM91*(1+$AU91) -> 1319.586 | AO91: =AN91*(1+$AU91) -> 1360.2852 | AP91: =AO91*(1+$AU91) -> 1402.2396 | AQ91: =AP91*(1+$AU91) -> 1445.488 | AR91: =AQ91*(1+$AU91) -> 1490.0702 | ... AT91: =AS91*(1+$AU91) -> 1583.4022 | AU91: =AJ91/AI91-1 -> 0.030842358 | AV91: 0.056
A92: Wind | B92: Residential: Combined Heat and Power: Energy Input: Wind: High oil and gas supply | C92: 30-AEO2021.100.highogs-d120120a | D92: trillion Btu | F92: 0.172512 | G92: 0.17376 | H92: 0.172883 | I92: 0.16903 | J92: 0.167234 | K92: 0.162235 | L92: 0.160124 | M92: 0.158755 | N92: 0.158329 | O92: 0.157956 | P92: 0.158237 | Q92: 0.157662 | R92: 0.157162 | S92: 0.156938 | T92: 0.156596 | U92: 0.156063 | V92: 0.155596 | W92: 0.155527 | X92: 0.155225 | Y92: 0.155492 | Z92: 0.156289 | AA92: 0.157906 | AB92: 0.159605 | AC92: 0.161311 | AD92: 0.162893 | AE92: 0.164593 | AF92: 0.166055 | AG92: 0.167643 | AH92: 0.169039 | AI92: 0.171113 | AJ92: 0.172595 | AK92: =AJ92*(1+$AU92) -> 0.17408984 | AL92: =AK92*(1+$AU92) -> 0.17559762 | AM92: =AL92*(1+$AU92) -> 0.17711846 | AN92: =AM92*(1+$AU92) -> 0.17865247 | AO92: =AN92*(1+$AU92) -> 0.18019977 | AP92: =AO92*(1+$AU92) -> 0.18176047 | AQ92: =AP92*(1+$AU92) -> 0.18333469 | AR92: =AQ92*(1+$AU92) -> 0.18492254 | ... AT92: =AS92*(1+$AU92) -> 0.18813962 | AU92: =AJ92/AI92-1 -> 0.0086609434 | AV92: 0
A93: Total | B93: Residential: Combined Heat and Power: Energy Input: Total: High oil and gas supply | C93: 30-AEO2021.101.highogs-d120120a | D93: trillion Btu | F93: 225.24599 | G93: 259.85062 | H93: 288.81412 | I93: 312.63052 | J93: 337.1853 | K93: 359.40112 | L93: 383.88315 | M93: 409.84494 | N93: 436.93567 | O93: 463.41754 | P93: 496.15817 | Q93: 523.87946 | R93: 551.34747 | S93: 579.92206 | T93: 610.1416 | U93: 640.164 | V93: 670.01111 | W93: 701.03272 | X93: 731.80493 | Y93: 764.71332 | Z93: 797.45435 | AA93: 832.01685 | AB93: 867.81256 | AC93: 903.66766 | AD93: 941.1239 | AE93: 980.45166 | AF93: 1019.0583 | AG93: 1055.2332 | AH93: 1093.6543 | AI93: 1133.8417 | AJ93: 1168.8102 | AK93: =AJ93*(1+$AU93) -> 1204.8571 | AL93: =AK93*(1+$AU93) -> 1242.0158 | AM93: =AL93*(1+$AU93) -> 1280.3205 | AN93: =AM93*(1+$AU93) -> 1319.8065 | AO93: =AN93*(1+$AU93) -> 1360.5103 | AP93: =AO93*(1+$AU93) -> 1402.4694 | AQ93: =AP93*(1+$AU93) -> 1445.7226 | AR93: =AQ93*(1+$AU93) -> 1490.3098 | ... AT93: =AS93*(1+$AU93) -> 1583.6518 | AU93: =AJ93/AI93-1 -> 0.030840731 | AV93: 0.056

Sheet NREL EF Table 22
A1: Figure 22. Installed unit costs (left) and performance projections (right) for commercial air-source heat pumps
A2: Figure Notes: | B2: Installed costs include both capital and installation costs.
A4: Year | B4: Technology | C4: EFS Case | D4: Installed Cost ($/kBtu/hr) | E4: Efficiency (COP)
A5: 2015 | B5: Air Source Heat Pump | C5: Moderate Advancement | D5: 96 | E5: 3.3
A6: 2015 | B6: Air Source Heat Pump | C6: Rapid Advancement | D6: 96 | E6: 3.3
A7: 2015 | B7: Air Source Heat Pump | C7: Slow Advancement | D7: 96 | E7: 3.3
A8: 2015 | B8: Cold Climate Air Source Heat Pump | C8: Moderate Advancement | D8: 96 | E8: 1.5
A9: 2015 | B9: Cold Climate Air Source Heat Pump | C9: Rapid Advancement | D9: 96 | E9: 1.5
A10: 2015 | B10: Cold Climate Air Source Heat Pump | C10: Slow Advancement | D10: 96 | E10: 1.5
A11: 2020 | B11: Air Source Heat Pump | C11: Moderate Advancement | D11: 85 | E11: 3.75
A12: 2020 | B12: Air Source Heat Pump | C12: Rapid Advancement | D12: 80 | E12: 4
A13: 2020 | B13: Air Source Heat Pump | C13: Slow Advancement | D13: 92.873543 | E13: 3.4
A14: 2020 | B14: Cold Climate Air Source Heat Pump | C14: Moderate Advancement | D14: 85 | E14: 2
A15: 2020 | B15: Cold Climate Air Source Heat Pump | C15: Rapid Advancement | D15: 80 | E15: 2.5
A16: 2020 | B16: Cold Climate Air Source Heat Pump | C16: Slow Advancement | D16: 92.873543 | E16: 1.75
... A34: 2050 | B34: Cold Climate Air Source Heat Pump | C34: Slow Advancement | D34: 76.140668 | E34: 2.75
A35: 2060 | B35: Air Source Heat Pump | C35: Moderate Advancement | D35: 60.296369 | E35: 4.25 | G35: 假定2060年与2050年保持一致
A36: 2060 | B36: Air Source Heat Pump | C36: Rapid Advancement | D36: 57.6 | E36: 5
A37: 2060 | B37: Air Source Heat Pump | C37: Slow Advancement | D37: 76.140668 | E37: 3.7
A38: 2060 | B38: Cold Climate Air Source Heat Pump | C38: Moderate Advancement | D38: 60.296369 | E38: 3
A39: 2060 | B39: Cold Climate Air Source Heat Pump | C39: Rapid Advancement | D39: 57.6 | E39: 3
A40: 2060 | B40: Cold Climate Air Source Heat Pump | C40: Slow Advancement | D40: 76.140668 | E40: 2.75

Sheet NREL EF Table 23
A1: Figure 23. Installed costs (left) and performance projections (right) for commercial HPWHs
A2: Figure Notes: | B2: Installed costs include both capital and installation costs.
A4: Year | B4: Technology | C4: EFS Case | D4: Installed Cost ($/kBtu/hr) | E4: Efficiency (COP)
A5: 2015 | B5: Heat Pump Water Heater | C5: Moderate Advancement | D5: 310 | E5: 2.45
A6: 2015 | B6: Heat Pump Water Heater | C6: Rapid Advancement | D6: 310 | E6: 2.45
A7: 2015 | B7: Heat Pump Water Heater | C7: Slow Advancement | D7: 310 | E7: 2.45
A8: 2020 | B8: Heat Pump Water Heater | C8: Moderate Advancement | D8: 287.51781 | E8: 3
A9: 2020 | B9: Heat Pump Water Heater | C9: Rapid Advancement | D9: 281.0389 | E9: 3
A10: 2020 | B10: Heat Pump Water Heater | C10: Slow Advancement | D10: 302.85283 | E10: 3
A11: 2030 | B11: Heat Pump Water Heater | C11: Moderate Advancement | D11: 247.32663 | E11: 3.25
A12: 2030 | B12: Heat Pump Water Heater | C12: Rapid Advancement | D12: 219.56945 | E12: 3.6
A13: 2030 | B13: Heat Pump Water Heater | C13: Slow Advancement | D13: 289.04903 | E13: 3
A14: 2040 | B14: Heat Pump Water Heater | C14: Moderate Advancement | D14: 212.75364 | E14: 3.35
A15: 2040 | B15: Heat Pump Water Heater | C15: Rapid Advancement | D15: 180 | E15: 3.85
A16: 2040 | B16: Heat Pump Water Heater | C16: Slow Advancement | D16: 275.8744 | E16: 3
... A19: 2050 | B19: Heat Pump Water Heater | C19: Slow Advancement | D19: 263.5 | E19: 3
A20: 2060 | B20: Heat Pump Water Heater | C20: Moderate Advancement | D20: 184.45 | E20: 3.43 | G20: 假定2060年与2050年保持一致
A21: 2060 | B21: Heat Pump Water Heater | C21: Rapid Advancement | D21: 158.1 | E21: 3.92
A22: 2060 | B22: Heat Pump Water Heater | C22: Slow Advancement | D22: 263.5 | E22: 3

Sheet Calculations
A1: Residential Equipment
A2: Heating
A3: Heating Energy Consumption per Unit per Year by Fuel (btu/unit) | B3: 2019 | C3: 2020 | D3: 2021 | E3: 2022 | F3: 2023 | G3: 2024 | H3: 2025 | I3: 2026 | J3: 2027 | K3: 2028 | L3: 2029 | M3: 2030 | N3: 2031 | O3: 2032 | P3: 2033 | Q3: 2034 | R3: 2035 | S3: 2036 | T3: 2037 | U3: 2038 | V3: 2039 | W3: 2040 | X3: 2041 | Y3: 2042 | Z3: 2043 | AA3: 2044 | AB3: 2045 | AC3: 2046 | AD3: 2047 | AE3: 2048 | AF3: 2049 | AG3: 2050 | AH3: 2051 | AI3: 2052 | AJ3: 2053 | AK3: 2054 | AL3: 2055 | AM3: 2056 | AN3: 2057 | AO3: 2058 | AP3: 2059 | AQ3: 2060 | AS3: 时间序列更新到2060年
A4: natural gas | C4: ='EIA AEO Table 4'!C53/SUM('EIA AEO Table 21'!F10:F11)*10^15/10^6 -> 57012744 | D4: ='EIA AEO Table 4'!D53/SUM('EIA AEO Table 21'!G10:G11)*10^15/10^6 -> 54412984 | E4: ='EIA AEO Table 4'!E53/SUM('EIA AEO Table 21'!H10:H11)*10^15/10^6 -> 55846720 | F4: ='EIA AEO Table 4'!F53/SUM('EIA AEO Table 21'!I10:I11)*10^15/10^6 -> 55162965 | G4: ='EIA AEO Table 4'!G53/SUM('EIA AEO Table 21'!J10:J11)*10^15/10^6 -> 54590777 | H4: ='EIA AEO Table 4'!H53/SUM('EIA AEO Table 21'!K10:K11)*10^15/10^6 -> 53880600 | I4: ='EIA AEO Table 4'!I53/SUM('EIA AEO Table 21'!L10:L11)*10^15/10^6 -> 53059978 | J4: ='EIA AEO Table 4'!J53/SUM('EIA AEO Table 21'!M10:M11)*10^15/10^6 -> 52213033 | ... AQ4: ='EIA AEO Table 4'!AQ53/SUM('EIA AEO Table 21'!AT10:AT11)*10^15/10^6 -> 36320739
A5: oil | C5: ='EIA AEO Table 4'!C62/'EIA AEO Table 21'!F12*10^15/10^6 -> 67169262 | D5: ='EIA AEO Table 4'!D62/'EIA AEO Table 21'!G12*10^15/10^6 -> 72770017 | E5: ='EIA AEO Table 4'!E62/'EIA AEO Table 21'!H12*10^15/10^6 -> 73400210 | F5: ='EIA AEO Table 4'!F62/'EIA AEO Table 21'!I12*10^15/10^6 -> 72148767 | G5: ='EIA AEO Table 4'!G62/'EIA AEO Table 21'!J12*10^15/10^6 -> 70980274 | H5: ='EIA AEO Table 4'!H62/'EIA AEO Table 21'!K12*10^15/10^6 -> 70064502 | I5: ='EIA AEO Table 4'!I62/'EIA AEO Table 21'!L12*10^15/10^6 -> 69174503 | J5: ='EIA AEO Table 4'!J62/'EIA AEO Table 21'!M12*10^15/10^6 -> 68378077 | ... AQ5: ='EIA AEO Table 4'!AQ62/'EIA AEO Table 21'!AT12*10^15/10^6 -> 53564904
A6: biomass | C6: ='EIA AEO Table 4'!C74/'EIA AEO Table 21'!F15*10^15/10^6 -> 1.3677874e+08 | D6: ='EIA AEO Table 4'!D74/'EIA AEO Table 21'!G15*10^15/10^6 -> 1.368522e+08 | E6: ='EIA AEO Table 4'!E74/'EIA AEO Table 21'!H15*10^15/10^6 -> 1.3437402e+08 | F6: ='EIA AEO Table 4'!F74/'EIA AEO Table 21'!I15*10^15/10^6 -> 1.3582981e+08 | G6: ='EIA AEO Table 4'!G74/'EIA AEO Table 21'!J15*10^15/10^6 -> 1.3722236e+08 | H6: ='EIA AEO Table 4'!H74/'EIA AEO Table 21'!K15*10^15/10^6 -> 1.3725936e+08 | I6: ='EIA AEO Table 4'!I74/'EIA AEO Table 21'!L15*10^15/10^6 -> 1.3722212e+08 | J6: ='EIA AEO Table 4'!J74/'EIA AEO Table 21'!M15*10^15/10^6 -> 1.3716577e+08 | ... AQ6: ='EIA AEO Table 4'!AQ74/'EIA AEO Table 21'!AT15*10^15/10^6 -> 1.1816378e+08
A8: Incremental Equipment Cost | B8: 2017 | C8: 2020 | D8: 2030 | E8: 2040 | F8: 2050 | G8: 2060
A9: natural gas (2017 USD) | B9: ='EIA Costs'!E48-'EIA Costs'!E10 -> 3050 | C9: ='EIA Costs'!H48-'EIA Costs'!H10 -> 2860 | D9: ='EIA Costs'!J48-'EIA Costs'!J10 -> 2910 | E9: ='EIA Costs'!L48-'EIA Costs'!L10 -> 2910 | F9: ='EIA Costs'!N48-'EIA Costs'!N10 -> 2910 | G9: ='EIA Costs'!P48-'EIA Costs'!P10 -> 2910
A10: oil (2017 USD) | B10: ='EIA Costs'!E48-AVERAGE('EIA Costs'!E23:E24) -> 975 | C10: ='EIA Costs'!H48-AVERAGE('EIA Costs'!H23:H24) -> 975 | D10: ='EIA Costs'!J48-AVERAGE('EIA Costs'!J23:J24) -> 925 | E10: ='EIA Costs'!L48-AVERAGE('EIA Costs'!L23:L24) -> 925 | F10: ='EIA Costs'!N48-AVERAGE('EIA Costs'!N23:N24) -> 925 | G10: ='EIA Costs'!P48-AVERAGE('EIA Costs'!P23:P24) -> 925
A11: biomass (2017 USD) | B11: ='EIA Costs'!E48-'EIA Costs'!D36 -> 400 | C11: ='EIA Costs'!H48-'EIA Costs'!F36 -> 400 | D11: ='EIA Costs'!J48-'EIA Costs'!H36 -> 350 | E11: ='EIA Costs'!L48-'EIA Costs'!J36 -> 250 | F11: ='EIA Costs'!N48-'EIA Costs'!L36 -> 150 | G11: ='EIA Costs'!P48-'EIA Costs'!N36 -> 150
A13: Annualized Incremental Equipment Cost | B13: 2019 | C13: 2020 | D13: 2021 | E13: 2022 | F13: 2023 | G13: 2024 | H13: 2025 | I13: 2026 | J13: 2027 | K13: 2028 | L13: 2029 | M13: 2030 | N13: 2031 | O13: 2032 | P13: 2033 | Q13: 2034 | R13: 2035 | S13: 2036 | T13: 2037 | U13: 2038 | V13: 2039 | W13: 2040 | X13: 2041 | Y13: 2042 | Z13: 2043 | AA13: 2044 | AB13: 2045 | AC13: 2046 | AD13: 2047 | AE13: 2048 | AF13: 2049 | AG13: 2050 | AH13: 2051 | AI13: 2052 | AJ13: 2053 | AK13: 2054 | AL13: 2055 | AM13: 2056 | AN13: 2057 | AO13: 2058 | AP13: 2059 | AQ13: 2060
A14: natural gas (2012 USD) | B14: =(TREND($B$9:$C$9,$B$8:$C$8,B$13))*(About!$A$53) -> 2738.1682 | C14: =(TREND($B$9:$C$9,$B$8:$C$8,C$13))*(About!$A$53) -> 2678.8464 | D14: =(TREND($C$9:$D$9,$C$8:$D$8,D$13))*(About!$A$53) -> 2683.5297 | E14: =(TREND($C$9:$D$9,$C$8:$D$8,E$13))*(About!$A$53) -> 2688.213 | F14: =(TREND($C$9:$D$9,$C$8:$D$8,F$13))*(About!$A$53) -> 2692.8963 | G14: =(TREND($C$9:$D$9,$C$8:$D$8,G$13))*(About!$A$53) -> 2697.5796 | H14: =(TREND($C$9:$D$9,$C$8:$D$8,H$13))*(About!$A$53) -> 2702.2629 | I14: =(TREND($C$9:$D$9,$C$8:$D$8,I$13))*(About!$A$53) -> 2706.9462 | J14: =(TREND($C$9:$D$9,$C$8:$D$8,J$13))*(About!$A$53) -> 2711.6295 | K14: =(TREND($C$9:$D$9,$C$8:$D$8,K$13))*(About!$A$53) -> 2716.3128 | ... M14: =(TREND($C$9:$D$9,$C$8:$D$8,M$13))*(About!$A$53) -> 2725.6794 | N14: =(TREND($D$9:$F$9,$D$8:$F$8,N$13))*(About!$A$53) -> 2725.6794 | O14: =(TREND($D$9:$F$9,$D$8:$F$8,O$13))*(About!$A$53) -> 2725.6794 | P14: =(TREND($D$9:$F$9,$D$8:$F$8,P$13))*(About!$A$53) -> 2725.6794 | Q14: =(TREND($D$9:$F$9,$D$8:$F$8,Q$13))*(About!$A$53) -> 2725.6794 | R14: =(TREND($D$9:$F$9,$D$8:$F$8,R$13))*(About!$A$53) -> 2725.6794 | S14: =(TREND($D$9:$F$9,$D$8:$F$8,S$13))*(About!$A$53) -> 2725.6794 | T14: =(TREND($D$9:$F$9,$D$8:$F$8,T$13))*(About!$A$53) -> 2725.6794 | U14: =(TREND($D$9:$F$9,$D$8:$F$8,U$13))*(About!$A$53) -> 2725.6794 | ... AQ14: =(TREND($D$9:$F$9,$D$8:$F$8,AQ$13))*(About!$A$53) -> 2725.6794
A15: oil (2012 USD) | B15: =(TREND($B$10:$C$10,$B$8:$C$8,B$13))*(About!$A$53) -> 913.24311 | C15: =(TREND($B$10:$C$10,$B$8:$C$8,C$13))*(About!$A$53) -> 913.24311 | D15: =(TREND($C$10:$D$10,$C$8:$D$8,D$13))*(About!$A$53) -> 908.55981 | E15: =(TREND($C$10:$D$10,$C$8:$D$8,E$13))*(About!$A$53) -> 903.87651 | F15: =(TREND($C$10:$D$10,$C$8:$D$8,F$13))*(About!$A$53) -> 899.19321 | G15: =(TREND($C$10:$D$10,$C$8:$D$8,G$13))*(About!$A$53) -> 894.50991 | H15: =(TREND($C$10:$D$10,$C$8:$D$8,H$13))*(About!$A$53) -> 889.82662 | I15: =(TREND($C$10:$D$10,$C$8:$D$8,I$13))*(About!$A$53) -> 885.14332 | J15: =(TREND($C$10:$D$10,$C$8:$D$8,J$13))*(About!$A$53) -> 880.46002 | K15: =(TREND($C$10:$D$10,$C$8:$D$8,K$13))*(About!$A$53) -> 875.77672 | ... M15: =(TREND($C$10:$D$10,$C$8:$D$8,M$13))*(About!$A$53) -> 866.41013 | N15: =(TREND($D$10:$F$10,$D$8:$F$8,N$13))*(About!$A$53) -> 866.41013 | O15: =(TREND($D$10:$F$10,$D$8:$F$8,O$13))*(About!$A$53) -> 866.41013 | P15: =(TREND($D$10:$F$10,$D$8:$F$8,P$13))*(About!$A$53) -> 866.41013 | Q15: =(TREND($D$10:$F$10,$D$8:$F$8,Q$13))*(About!$A$53) -> 866.41013 | R15: =(TREND($D$10:$F$10,$D$8:$F$8,R$13))*(About!$A$53) -> 866.41013 | S15: =(TREND($D$10:$F$10,$D$8:$F$8,S$13))*(About!$A$53) -> 866.41013 | T15: =(TREND($D$10:$F$10,$D$8:$F$8,T$13))*(About!$A$53) -> 866.41013 | U15: =(TREND($D$10:$F$10,$D$8:$F$8,U$13))*(About!$A$53) -> 866.41013 | ... AQ15: =(TREND($D$10:$F$10,$D$8:$F$8,AQ$13))*(About!$A$53) -> 866.41013
A16: biomass (2012 USD) | B16: =(TREND($B$11:$C$11,$B$8:$C$8,B$13))*(About!$A$53) -> 374.66384 | C16: =(TREND($B$11:$C$11,$B$8:$C$8,C$13))*(About!$A$53) -> 374.66384 | D16: =(TREND($C$11:$D$11,$C$8:$D$8,D$13))*(About!$A$53) -> 369.98054 | E16: =(TREND($C$11:$D$11,$C$8:$D$8,E$13))*(About!$A$53) -> 365.29724 | F16: =(TREND($C$11:$D$11,$C$8:$D$8,F$13))*(About!$A$53) -> 360.61394 | G16: =(TREND($C$11:$D$11,$C$8:$D$8,G$13))*(About!$A$53) -> 355.93065 | H16: =(TREND($C$11:$D$11,$C$8:$D$8,H$13))*(About!$A$53) -> 351.24735 | I16: =(TREND($C$11:$D$11,$C$8:$D$8,I$13))*(About!$A$53) -> 346.56405 | J16: =(TREND($C$11:$D$11,$C$8:$D$8,J$13))*(About!$A$53) -> 341.88075 | K16: =(TREND($C$11:$D$11,$C$8:$D$8,K$13))*(About!$A$53) -> 337.19745 | ... M16: =(TREND($C$11:$D$11,$C$8:$D$8,M$13))*(About!$A$53) -> 327.83086 | N16: =(TREND($D$11:$F$11,$D$8:$F$8,N$13))*(About!$A$53) -> 318.46426 | O16: =(TREND($D$11:$F$11,$D$8:$F$8,O$13))*(About!$A$53) -> 309.09767 | P16: =(TREND($D$11:$F$11,$D$8:$F$8,P$13))*(About!$A$53) -> 299.73107 | Q16: =(TREND($D$11:$F$11,$D$8:$F$8,Q$13))*(About!$A$53) -> 290.36447 | R16: =(TREND($D$11:$F$11,$D$8:$F$8,R$13))*(About!$A$53) -> 280.99788 | S16: =(TREND($D$11:$F$11,$D$8:$F$8,S$13))*(About!$A$53) -> 271.63128 | T16: =(TREND($D$11:$F$11,$D$8:$F$8,T$13))*(About!$A$53) -> 262.26469 | U16: =(TREND($D$11:$F$11,$D$8:$F$8,U$13))*(About!$A$53) -> 252.89809 | ... AQ16: =(TREND($D$11:$F$11,$D$8:$F$8,AQ$13))*(About!$A$53) -> 46.83298
A18: Annualized Incremental Cost per BTU Shifted | B18: 2019 | C18: 2020 | D18: 2021 | E18: 2022 | F18: 2023 | G18: 2024 | H18: 2025 | I18: 2026 | J18: 2027 | K18: 2028 | L18: 2029 | M18: 2030 | N18: 2031 | O18: 2032 | P18: 2033 | Q18: 2034 | R18: 2035 | S18: 2036 | T18: 2037 | U18: 2038 | V18: 2039 | W18: 2040 | X18: 2041 | Y18: 2042 | Z18: 2043 | AA18: 2044 | AB18: 2045 | AC18: 2046 | AD18: 2047 | AE18: 2048 | AF18: 2049 | AG18: 2050 | AH18: 2051 | AI18: 2052 | AJ18: 2053 | AK18: 2054 | AL18: 2055 | AM18: 2056 | AN18: 2057 | AO18: 2058 | AP18: 2059 | AQ18: 2060
A19: natural gas | C19: =C14/C4 -> 4.6986801e-05 | D19: =D14/D4 -> 4.931782e-05 | E19: =E14/E4 -> 4.8135558e-05 | F19: =F14/F4 -> 4.8817107e-05 | G19: =G14/G4 -> 4.9414568e-05 | H19: =H14/H4 -> 5.0152799e-05 | I19: =I14/I4 -> 5.1016723e-05 | J19: =J14/J4 -> 5.193396e-05 | ... AQ19: =AQ14/AQ4 -> 7.5044712e-05
A20: oil | C20: =C15/C5 -> 1.3596146e-05 | D20: =D15/D5 -> 1.2485359e-05 | E20: =E15/E5 -> 1.2314359e-05 | F20: =F15/F5 -> 1.2463043e-05 | G20: =G15/G5 -> 1.2602232e-05 | H20: =H15/H5 -> 1.2700106e-05 | I20: =I15/I5 -> 1.2795803e-05 | J20: =J15/J5 -> 1.287635e-05 | ... AQ20: =AQ15/AQ5 -> 1.6174959e-05
A21: biomass | C21: =C16/C6 -> 2.7391964e-06 | D21: =D16/D6 -> 2.7035045e-06 | E21: =E16/E6 -> 2.7185109e-06 | F21: =F16/F6 -> 2.6548954e-06 | G21: =G16/G6 -> 2.5938241e-06 | H21: =H16/H6 -> 2.5590047e-06 | I21: =I16/I6 -> 2.5255699e-06 | J21: =J16/J6 -> 2.4924641e-06 | ... AQ21: =AQ16/AQ6 -> 3.9633956e-07
A23: Appliances (water heaters)
A24: Appliances Energy Consumption per Unit per Year by Fuel (btu/unit) | B24: 2019 | C24: 2020 | D24: 2021 | E24: 2022 | F24: 2023 | G24: 2024 | H24: 2025 | I24: 2026 | J24: 2027 | K24: 2028 | L24: 2029 | M24: 2030 | N24: 2031 | O24: 2032 | P24: 2033 | Q24: 2034 | R24: 2035 | S24: 2036 | T24: 2037 | U24: 2038 | V24: 2039 | W24: 2040 | X24: 2041 | Y24: 2042 | Z24: 2043 | AA24: 2044 | AB24: 2045 | AC24: 2046 | AD24: 2047 | AE24: 2048 | AF24: 2049 | AG24: 2050 | AH24: 2051 | AI24: 2052 | AJ24: 2053 | AK24: 2054 | AL24: 2055 | AM24: 2056 | AN24: 2057 | AO24: 2058 | AP24: 2059 | AQ24: 2060
A25: natural gas | C25: ='EIA AEO Table 4'!C55/'EIA AEO Table 21'!F27*10^15/10^6 -> 16769614 | D25: ='EIA AEO Table 4'!D55/'EIA AEO Table 21'!G27*10^15/10^6 -> 16553980 | E25: ='EIA AEO Table 4'!E55/'EIA AEO Table 21'!H27*10^15/10^6 -> 16431876 | F25: ='EIA AEO Table 4'!F55/'EIA AEO Table 21'!I27*10^15/10^6 -> 16366463 | G25: ='EIA AEO Table 4'!G55/'EIA AEO Table 21'!J27*10^15/10^6 -> 16341666 | H25: ='EIA AEO Table 4'!H55/'EIA AEO Table 21'!K27*10^15/10^6 -> 16299064 | I25: ='EIA AEO Table 4'!I55/'EIA AEO Table 21'!L27*10^15/10^6 -> 16240930 | J25: ='EIA AEO Table 4'!J55/'EIA AEO Table 21'!M27*10^15/10^6 -> 16175571 | ... AQ25: ='EIA AEO Table 4'!AQ55/'EIA AEO Table 21'!AT27*10^15/10^6 -> 15276465
A26: oil | C26: ='EIA AEO Table 4'!C63/'EIA AEO Table 21'!F28*10^15/10^6 -> 18429611 | D26: ='EIA AEO Table 4'!D63/'EIA AEO Table 21'!G28*10^15/10^6 -> 18114372 | E26: ='EIA AEO Table 4'!E63/'EIA AEO Table 21'!H28*10^15/10^6 -> 17686975 | F26: ='EIA AEO Table 4'!F63/'EIA AEO Table 21'!I28*10^15/10^6 -> 17150887 | G26: ='EIA AEO Table 4'!G63/'EIA AEO Table 21'!J28*10^15/10^6 -> 16678498 | H26: ='EIA AEO Table 4'!H63/'EIA AEO Table 21'!K28*10^15/10^6 -> 16311996 | I26: ='EIA AEO Table 4'!I63/'EIA AEO Table 21'!L28*10^15/10^6 -> 16003974 | J26: ='EIA AEO Table 4'!J63/'EIA AEO Table 21'!M28*10^15/10^6 -> 15770241 | ... AQ26: ='EIA AEO Table 4'!AQ63/'EIA AEO Table 21'!AT28*10^15/10^6 -> 13479312
A28: Incremental Equipment Cost | B28: 2017 | C28: 2020 | D28: 2030 | E28: 2040 | F28: 2050 | G28: 2060
A29: natural gas (2017 USD) | B29: =AVERAGE('EIA Costs'!D88:D89)-AVERAGE('EIA Costs'!E61:E62) -> 150 | C29: =AVERAGE('EIA Costs'!G88:G89)-AVERAGE('EIA Costs'!H61:H62) -> 150 | D29: =AVERAGE('EIA Costs'!I88:I89)-AVERAGE('EIA Costs'!J61:J62) -> 150 | E29: =AVERAGE('EIA Costs'!K88:K89)-AVERAGE('EIA Costs'!L61:L62) -> 150 | F29: =AVERAGE('EIA Costs'!M88:M89)-AVERAGE('EIA Costs'!N61:N62) -> 150 | G29: =AVERAGE('EIA Costs'!O88:O89)-AVERAGE('EIA Costs'!P61:P62) -> 150
A30: oil (2017 USD) | B30: =AVERAGE('EIA Costs'!D88:D89)-AVERAGE('EIA Costs'!E75:E76) -> -475 | C30: =AVERAGE('EIA Costs'!G88:G89)-AVERAGE('EIA Costs'!G75:G76) -> -475 | D30: =AVERAGE('EIA Costs'!I88:I89)-AVERAGE('EIA Costs'!I75:I76) -> -475 | E30: =AVERAGE('EIA Costs'!K88:K89)-AVERAGE('EIA Costs'!K75:K76) -> -475 | F30: =AVERAGE('EIA Costs'!M88:M89)-AVERAGE('EIA Costs'!M75:M76) -> -475 | G30: =AVERAGE('EIA Costs'!O88:O89)-AVERAGE('EIA Costs'!O75:O76) -> -475
A32: Annualized Incremental Equipment Cost | B32: 2019 | C32: 2020 | D32: 2021 | E32: 2022 | F32: 2023 | G32: 2024 | H32: 2025 | I32: 2026 | J32: 2027 | K32: 2028 | L32: 2029 | M32: 2030 | N32: 2031 | O32: 2032 | P32: 2033 | Q32: 2034 | R32: 2035 | S32: 2036 | T32: 2037 | U32: 2038 | V32: 2039 | W32: 2040 | X32: 2041 | Y32: 2042 | Z32: 2043 | AA32: 2044 | AB32: 2045 | AC32: 2046 | AD32: 2047 | AE32: 2048 | AF32: 2049 | AG32: 2050 | AH32: 2051 | AI32: 2052 | AJ32: 2053 | AK32: 2054 | AL32: 2055 | AM32: 2056 | AN32: 2057 | AO32: 2058 | AP32: 2059 | AQ32: 2060
A33: natural gas (2012 USD) | B33: =TREND($B$29:$C$29,$B$28:$C$28,B$32) -> 150 | C33: =TREND($B$29:$C$29,$B$28:$C$28,C$32) -> 150 | D33: =TREND($C$29:$D$29,$C$28:$D$28,D$32) -> 150 | E33: =TREND($C$29:$D$29,$C$28:$D$28,E$32) -> 150 | F33: =TREND($C$29:$D$29,$C$28:$D$28,F$32) -> 150 | G33: =TREND($C$29:$D$29,$C$28:$D$28,G$32) -> 150 | H33: =TREND($C$29:$D$29,$C$28:$D$28,H$32) -> 150 | I33: =TREND($C$29:$D$29,$C$28:$D$28,I$32) -> 150 | J33: =TREND($C$29:$D$29,$C$28:$D$28,J$32) -> 150 | K33: =TREND($C$29:$D$29,$C$28:$D$28,K$32) -> 150 | ... M33: =TREND($C$29:$D$29,$C$28:$D$28,M$32) -> 150 | N33: =TREND($D$29:$F$29,$D$28:$F$28,N$32) -> 150 | O33: =TREND($D$29:$F$29,$D$28:$F$28,O$32) -> 150 | P33: =TREND($D$29:$F$29,$D$28:$F$28,P$32) -> 150 | Q33: =TREND($D$29:$F$29,$D$28:$F$28,Q$32) -> 150 | R33: =TREND($D$29:$F$29,$D$28:$F$28,R$32) -> 150 | S33: =TREND($D$29:$F$29,$D$28:$F$28,S$32) -> 150 | T33: =TREND($D$29:$F$29,$D$28:$F$28,T$32) -> 150 | U33: =TREND($D$29:$F$29,$D$28:$F$28,U$32) -> 150 | ... AQ33: =TREND($D$29:$F$29,$D$28:$F$28,AQ$32) -> 150
A34: oil (2012 USD) | B34: =TREND($B$30:$C$30,$B$28:$C$28,B$32) -> -475 | C34: =TREND($B$30:$C$30,$B$28:$C$28,C$32) -> -475 | D34: =TREND($C$30:$D$30,$C$28:$D$28,D$32) -> -475 | E34: =TREND($C$30:$D$30,$C$28:$D$28,E$32) -> -475 | F34: =TREND($C$30:$D$30,$C$28:$D$28,F$32) -> -475 | G34: =TREND($C$30:$D$30,$C$28:$D$28,G$32) -> -475 | H34: =TREND($C$30:$D$30,$C$28:$D$28,H$32) -> -475 | I34: =TREND($C$30:$D$30,$C$28:$D$28,I$32) -> -475 | J34: =TREND($C$30:$D$30,$C$28:$D$28,J$32) -> -475 | K34: =TREND($C$30:$D$30,$C$28:$D$28,K$32) -> -475 | ... M34: =TREND($C$30:$D$30,$C$28:$D$28,M$32) -> -475 | N34: =TREND($D$30:$F$30,$D$28:$F$28,N$32) -> -475 | O34: =TREND($D$30:$F$30,$D$28:$F$28,O$32) -> -475 | P34: =TREND($D$30:$F$30,$D$28:$F$28,P$32) -> -475 | Q34: =TREND($D$30:$F$30,$D$28:$F$28,Q$32) -> -475 | R34: =TREND($D$30:$F$30,$D$28:$F$28,R$32) -> -475 | S34: =TREND($D$30:$F$30,$D$28:$F$28,S$32) -> -475 | T34: =TREND($D$30:$F$30,$D$28:$F$28,T$32) -> -475 | U34: =TREND($D$30:$F$30,$D$28:$F$28,U$32) -> -475 | ... AQ34: =TREND($D$30:$F$30,$D$28:$F$28,AQ$32) -> -475
A36: Annualized Incremental Cost per BTU Shifted | B36: 2019 | C36: 2020 | D36: 2021 | E36: 2022 | F36: 2023 | G36: 2024 | H36: 2025 | I36: 2026 | J36: 2027 | K36: 2028 | L36: 2029 | M36: 2030 | N36: 2031 | O36: 2032 | P36: 2033 | Q36: 2034 | R36: 2035 | S36: 2036 | T36: 2037 | U36: 2038 | V36: 2039 | W36: 2040 | X36: 2041 | Y36: 2042 | Z36: 2043 | AA36: 2044 | AB36: 2045 | AC36: 2046 | AD36: 2047 | AE36: 2048 | AF36: 2049 | AG36: 2050 | AH36: 2051 | AI36: 2052 | AJ36: 2053 | AK36: 2054 | AL36: 2055 | AM36: 2056 | AN36: 2057 | AO36: 2058 | AP36: 2059 | AQ36: 2060
A37: natural gas | C37: =C33/C25 -> 8.9447496e-06 | D37: =D33/D25 -> 9.0612648e-06 | E37: =E33/E25 -> 9.1285986e-06 | F37: =F33/F25 -> 9.1650837e-06 | G37: =G33/G25 -> 9.1789907e-06 | H37: =H33/H25 -> 9.2029826e-06 | I37: =I33/I25 -> 9.2359245e-06 | J37: =J33/J25 -> 9.2732432e-06 | ... AQ37: =AQ33/AQ25 -> 9.8190258e-06
A38: oil | C38: =C34/C26 -> -2.577374e-05 | D38: =D34/D26 -> -2.6222273e-05 | E38: =E34/E26 -> -2.6855921e-05 | F38: =F34/F26 -> -2.769536e-05 | G38: =G34/G26 -> -2.8479784e-05 | H38: =H34/H26 -> -2.9119673e-05 | I38: =I34/I26 -> -2.9680128e-05 | J38: =J34/J26 -> -3.0120021e-05 | ... AQ38: =AQ34/AQ26 -> -3.5239188e-05
A40: Commercial Equipment
A41: Heating
A42: Utilization Assumption
A43: space heating | B43: 0.08
A44: water heating | B44: 0.25
A47: Installed Cost ($/kBTU/hr) | B47: 2015 | C47: 2017 | D47: 2020 | E47: 2030 | F47: 2040 | G47: 2050 | H47: 2060
A48: natural gas (2017 USD) | C48: ='EIA Costs'!D100/'EIA Costs'!D96 -> 5.375 | D48: ='EIA Costs'!F100/'EIA Costs'!F96 -> 5.375 | E48: ='EIA Costs'!H100/'EIA Costs'!H96 -> 5.5 | F48: ='EIA Costs'!J100/'EIA Costs'!J96 -> 5.5 | G48: ='EIA Costs'!L100/'EIA Costs'!L96 -> 5.5 | H48: ='EIA Costs'!N100/'EIA Costs'!N96 -> 5.5
A49: oil (2017 USD) | C49: ='EIA Costs'!D111/'EIA Costs'!D107 -> 16.5 | D49: ='EIA Costs'!F111/'EIA Costs'!F107 -> 16.5 | E49: ='EIA Costs'!G111/'EIA Costs'!G107 -> 16.5 | F49: ='EIA Costs'!H111/'EIA Costs'!H107 -> 16.5 | G49: ='EIA Costs'!I111/'EIA Costs'!I107 -> 16.5 | H49: ='EIA Costs'!J111/'EIA Costs'!J107 -> 16.5
A50: ASHP (2016 USD) | B50: ='NREL EF Table 22'!D5 -> 96 | D50: ='NREL EF Table 22'!D11 -> 85 | E50: ='NREL EF Table 22'!D17 -> 73 | F50: ='NREL EF Table 22'!D23 -> 65 | G50: ='NREL EF Table 22'!D29 -> 60.296369 | H50: ='NREL EF Table 22'!D35 -> 60.296369
A52: Annualized Installed Cost ($/kBTU/hr) | B52: 2019 | C52: 2020 | D52: 2021 | E52: 2022 | F52: 2023 | G52: 2024 | H52: 2025 | I52: 2026 | J52: 2027 | K52: 2028 | L52: 2029 | M52: 2030 | N52: 2031 | O52: 2032 | P52: 2033 | Q52: 2034 | R52: 2035 | S52: 2036 | T52: 2037 | U52: 2038 | V52: 2039 | W52: 2040 | X52: 2041 | Y52: 2042 | Z52: 2043 | AA52: 2044 | AB52: 2045 | AC52: 2046 | AD52: 2047 | AE52: 2048 | AF52: 2049 | AG52: 2050 | AH52: 2051 | AI52: 2052 | AJ52: 2053 | AK52: 2054 | AL52: 2055 | AM52: 2056 | AN52: 2057 | AO52: 2058 | AP52: 2059 | AQ52: 2060
A53: natural gas (2012 USD) | B53: =(TREND($C$48:$D$48,$C$47:$D$47,B$32))*(About!$A$53) -> 5.0345453 | C53: =(TREND($C$48:$D$48,$C$47:$D$47,C$32))*(About!$A$53) -> 5.0345453 | D53: =(TREND($D$48:$E$48,$D$47:$E$47,D$32))*(About!$A$53) -> 5.0462536 | E53: =(TREND($D$48:$E$48,$D$47:$E$47,E$32))*(About!$A$53) -> 5.0579618 | F53: =(TREND($D$48:$E$48,$D$47:$E$47,F$32))*(About!$A$53) -> 5.0696701 | G53: =(TREND($D$48:$E$48,$D$47:$E$47,G$32))*(About!$A$53) -> 5.0813783 | H53: =(TREND($D$48:$E$48,$D$47:$E$47,H$32))*(About!$A$53) -> 5.0930865 | I53: =(TREND($D$48:$E$48,$D$47:$E$47,I$32))*(About!$A$53) -> 5.1047948 | J53: =(TREND($D$48:$E$48,$D$47:$E$47,J$32))*(About!$A$53) -> 5.116503 | K53: =(TREND($D$48:$E$48,$D$47:$E$47,K$32))*(About!$A$53) -> 5.1282113 | ... M53: =(TREND($D$48:$E$48,$D$47:$E$47,M$32))*(About!$A$53) -> 5.1516278 | N53: =(TREND($E$48:$G$48,$E$47:$G$47,N$32))*(About!$A$53) -> 5.1516278 | O53: =(TREND($E$48:$G$48,$E$47:$G$47,O$32))*(About!$A$53) -> 5.1516278 | P53: =(TREND($E$48:$G$48,$E$47:$G$47,P$32))*(About!$A$53) -> 5.1516278 | Q53: =(TREND($E$48:$G$48,$E$47:$G$47,Q$32))*(About!$A$53) -> 5.1516278 | R53: =(TREND($E$48:$G$48,$E$47:$G$47,R$32))*(About!$A$53) -> 5.1516278 | S53: =(TREND($E$48:$G$48,$E$47:$G$47,S$32))*(About!$A$53) -> 5.1516278 | T53: =(TREND($E$48:$G$48,$E$47:$G$47,T$32))*(About!$A$53) -> 5.1516278 | U53: =(TREND($E$48:$G$48,$E$47:$G$47,U$32))*(About!$A$53) -> 5.1516278 | ... AQ53: =(TREND($E$48:$G$48,$E$47:$G$47,AQ$32))*(About!$A$53) -> 5.1516278
A54: oil (2012 USD) | B54: =(TREND($C$49:$D$49,$C$47:$D$47,B$32))*(About!$A$53) -> 15.454883 | C54: =(TREND($C$49:$D$49,$C$47:$D$47,C$32))*(About!$A$53) -> 15.454883 | D54: =(TREND($D$49:$E$49,$D$47:$E$47,D$32))*(About!$A$53) -> 15.454883 | E54: =(TREND($D$49:$E$49,$D$47:$E$47,E$32))*(About!$A$53) -> 15.454883 | F54: =(TREND($D$49:$E$49,$D$47:$E$47,F$32))*(About!$A$53) -> 15.454883 | G54: =(TREND($D$49:$E$49,$D$47:$E$47,G$32))*(About!$A$53) -> 15.454883 | H54: =(TREND($D$49:$E$49,$D$47:$E$47,H$32))*(About!$A$53) -> 15.454883 | I54: =(TREND($D$49:$E$49,$D$47:$E$47,I$32))*(About!$A$53) -> 15.454883 | J54: =(TREND($D$49:$E$49,$D$47:$E$47,J$32))*(About!$A$53) -> 15.454883 | K54: =(TREND($D$49:$E$49,$D$47:$E$47,K$32))*(About!$A$53) -> 15.454883 | ... M54: =(TREND($D$49:$E$49,$D$47:$E$47,M$32))*(About!$A$53) -> 15.454883 | N54: =(TREND($E$49:$G$49,$E$47:$G$47,N$32))*(About!$A$53) -> 15.454883 | O54: =(TREND($E$49:$G$49,$E$47:$G$47,O$32))*(About!$A$53) -> 15.454883 | P54: =(TREND($E$49:$G$49,$E$47:$G$47,P$32))*(About!$A$53) -> 15.454883 | Q54: =(TREND($E$49:$G$49,$E$47:$G$47,Q$32))*(About!$A$53) -> 15.454883 | R54: =(TREND($E$49:$G$49,$E$47:$G$47,R$32))*(About!$A$53) -> 15.454883 | S54: =(TREND($E$49:$G$49,$E$47:$G$47,S$32))*(About!$A$53) -> 15.454883 | T54: =(TREND($E$49:$G$49,$E$47:$G$47,T$32))*(About!$A$53) -> 15.454883 | U54: =(TREND($E$49:$G$49,$E$47:$G$47,U$32))*(About!$A$53) -> 15.454883 | ... AQ54: =(TREND($E$49:$G$49,$E$47:$G$47,AQ$32))*(About!$A$53) -> 15.454883
A55: ASHP (2012 USD) | B55: =((B50-D50)/(B47-D47)*(B52-C52)*(About!$A$55))+C55 -> 83.41672 | C55: =(TREND($D$50:$E$50,$D$47:$E$47,C$32))*(About!$A$55) -> 81.31217 | D55: =(TREND($D$50:$E$50,$D$47:$E$47,D$32))*(About!$A$55) -> 80.164234 | E55: =(TREND($D$50:$E$50,$D$47:$E$47,E$32))*(About!$A$55) -> 79.016297 | F55: =(TREND($D$50:$E$50,$D$47:$E$47,F$32))*(About!$A$55) -> 77.868361 | G55: =(TREND($D$50:$E$50,$D$47:$E$47,G$32))*(About!$A$55) -> 76.720424 | H55: =(TREND($D$50:$E$50,$D$47:$E$47,H$32))*(About!$A$55) -> 75.572487 | I55: =(TREND($D$50:$E$50,$D$47:$E$47,I$32))*(About!$A$55) -> 74.424551 | J55: =(TREND($D$50:$E$50,$D$47:$E$47,J$32))*(About!$A$55) -> 73.276614 | ... M55: =(TREND($D$50:$E$50,$D$47:$E$47,M$32))*(About!$A$55) -> 69.832805 | N55: =(TREND($E$50:$G$50,$E$47:$G$47,N$32))*(About!$A$55) -> 68.699623 | O55: =(TREND($E$50:$G$50,$E$47:$G$47,O$32))*(About!$A$55) -> 68.091999 | P55: =(TREND($E$50:$G$50,$E$47:$G$47,P$32))*(About!$A$55) -> 67.484376 | Q55: =(TREND($E$50:$G$50,$E$47:$G$47,Q$32))*(About!$A$55) -> 66.876753 | R55: =(TREND($E$50:$G$50,$E$47:$G$47,R$32))*(About!$A$55) -> 66.269129 | S55: =(TREND($E$50:$G$50,$E$47:$G$47,S$32))*(About!$A$55) -> 65.661506 | T55: =(TREND($E$50:$G$50,$E$47:$G$47,T$32))*(About!$A$55) -> 65.053882 | U55: =(TREND($E$50:$G$50,$E$47:$G$47,U$32))*(About!$A$55) -> 64.446259 | ... AQ55: =(TREND($E$50:$G$50,$E$47:$G$47,AQ$32))*(About!$A$55) -> 51.078544
A57: Annualized Incremental Capital Cost per BTU Shifted | B57: 2019 | C57: 2020 | D57: 2021 | E57: 2022 | F57: 2023 | G57: 2024 | H57: 2025 | I57: 2026 | J57: 2027 | K57: 2028 | L57: 2029 | M57: 2030 | N57: 2031 | O57: 2032 | P57: 2033 | Q57: 2034 | R57: 2035 | S57: 2036 | T57: 2037 | U57: 2038 | V57: 2039 | W57: 2040 | X57: 2041 | Y57: 2042 | Z57: 2043 | AA57: 2044 | AB57: 2045 | AC57: 2046 | AD57: 2047 | AE57: 2048 | AF57: 2049 | AG57: 2050 | AH57: 2051 | AI57: 2052 | AJ57: 2053 | AK57: 2054 | AL57: 2055 | AM57: 2056 | AN57: 2057 | AO57: 2058 | AP57: 2059 | AQ57: 2060
A58: natural gas | B58: =(B55-B53)/(8760*10^3*$B$43) -> 0.00011184671 | C58: =(C55-C53)/(8760*10^3*$B$43) -> 0.00010884364 | D58: =(D55-D53)/(8760*10^3*$B$43) -> 0.0001071889 | E58: =(E55-E53)/(8760*10^3*$B$43) -> 0.00010553415 | F58: =(F55-F53)/(8760*10^3*$B$43) -> 0.00010387941 | G58: =(G55-G53)/(8760*10^3*$B$43) -> 0.00010222467 | H58: =(H55-H53)/(8760*10^3*$B$43) -> 0.00010056992 | I58: =(I55-I53)/(8760*10^3*$B$43) -> 9.8915177e-05 | ... AQ58: =(AQ55-AQ53)/(8760*10^3*$B$43) -> 6.5534983e-05
A59: oil | B59: =(B55-B54)/(8760*10^3*$B$43) -> 9.6977507e-05 | C59: =(C55-C54)/(8760*10^3*$B$43) -> 9.3974439e-05 | D59: =(D55-D54)/(8760*10^3*$B$43) -> 9.2336402e-05 | E59: =(E55-E54)/(8760*10^3*$B$43) -> 9.0698364e-05 | F59: =(F55-F54)/(8760*10^3*$B$43) -> 8.9060327e-05 | G59: =(G55-G54)/(8760*10^3*$B$43) -> 8.742229e-05 | H59: =(H55-H54)/(8760*10^3*$B$43) -> 8.5784252e-05 | I59: =(I55-I54)/(8760*10^3*$B$43) -> 8.4146215e-05 | ... AQ59: =(AQ55-AQ54)/(8760*10^3*$B$43) -> 5.0832849e-05
A61: Appliances (water heaters)
A62: Utilization Assumption
A63: space heating | B63: 0.08
A64: water heating | B64: 0.25
A67: Installed Cost ($/kBTU/hr) | B67: 2015 | C67: 2017 | D67: 2020 | E67: 2030 | F67: 2040 | G67: 2050 | H67: 2060
A68: natural gas (2017 USD) | C68: =AVERAGE('EIA Costs'!D134:D135)/'EIA Costs'!D131 -> 19.472362 | D68: =AVERAGE('EIA Costs'!G134:G135)/'EIA Costs'!G131 -> 19.472362 | E68: =AVERAGE('EIA Costs'!I134:I135)/'EIA Costs'!I131 -> 19.472362 | F68: =AVERAGE('EIA Costs'!K134:K135)/'EIA Costs'!K131 -> 19.472362 | G68: =AVERAGE('EIA Costs'!M134:M135)/'EIA Costs'!M131 -> 19.472362 | H68: =AVERAGE('EIA Costs'!O134:O135)/'EIA Costs'!O131 -> 19.472362
A69: oil (2017 USD) | C69: ='EIA Costs'!D148/'EIA Costs'!D144 -> 17.333333 | D69: ='EIA Costs'!F148/'EIA Costs'!F144 -> 17.333333 | E69: ='EIA Costs'!H148/'EIA Costs'!H144 -> 17.333333 | F69: ='EIA Costs'!J148/'EIA Costs'!J144 -> 17.333333 | G69: ='EIA Costs'!L148/'EIA Costs'!L144 -> 17.333333 | H69: ='EIA Costs'!N148/'EIA Costs'!N144 -> 17.333333
A70: ASHP (2016 USD) | B70: ='NREL EF Table 23'!D5 -> 310 | D70: ='NREL EF Table 23'!D8 -> 287.51781 | E70: ='NREL EF Table 23'!D11 -> 247.32663 | F70: ='NREL EF Table 23'!D14 -> 212.75364 | G70: ='NREL EF Table 23'!D17 -> 184.45 | H70: ='NREL EF Table 23'!D20 -> 184.45
A72: Annualized Installed Cost ($/kBTU/hr) | B72: 2019 | C72: 2020 | D72: 2021 | E72: 2022 | F72: 2023 | G72: 2024 | H72: 2025 | I72: 2026 | J72: 2027 | K72: 2028 | L72: 2029 | M72: 2030 | N72: 2031 | O72: 2032 | P72: 2033 | Q72: 2034 | R72: 2035 | S72: 2036 | T72: 2037 | U72: 2038 | V72: 2039 | W72: 2040 | X72: 2041 | Y72: 2042 | Z72: 2043 | AA72: 2044 | AB72: 2045 | AC72: 2046 | AD72: 2047 | AE72: 2048 | AF72: 2049 | AG72: 2050 | AH72: 2051 | AI72: 2052 | AJ72: 2053 | AK72: 2054 | AL72: 2055 | AM72: 2056 | AN72: 2057 | AO72: 2058 | AP72: 2059 | AQ72: 2060
A73: natural gas (2012 USD) | B73: =(TREND($C$68:$D$68,$C$67:$D$67,B$32))*(About!$A$53) -> 18.238975 | C73: =(TREND($C$68:$D$68,$C$67:$D$67,C$32))*(About!$A$53) -> 18.238975 | D73: =(TREND($D$68:$E$68,$D$67:$E$67,D$32))*(About!$A$53) -> 18.238975 | E73: =(TREND($D$68:$E$68,$D$67:$E$67,E$32))*(About!$A$53) -> 18.238975 | F73: =(TREND($D$68:$E$68,$D$67:$E$67,F$32))*(About!$A$53) -> 18.238975 | G73: =(TREND($D$68:$E$68,$D$67:$E$67,G$32))*(About!$A$53) -> 18.238975 | H73: =(TREND($D$68:$E$68,$D$67:$E$67,H$32))*(About!$A$53) -> 18.238975 | I73: =(TREND($D$68:$E$68,$D$67:$E$67,I$32))*(About!$A$53) -> 18.238975 | J73: =(TREND($D$68:$E$68,$D$67:$E$67,J$32))*(About!$A$53) -> 18.238975 | K73: =(TREND($D$68:$E$68,$D$67:$E$67,K$32))*(About!$A$53) -> 18.238975 | ... M73: =(TREND($D$68:$E$68,$D$67:$E$67,M$32))*(About!$A$53) -> 18.238975 | N73: =(TREND($E$68:$G$68,$E$67:$G$67,N$32))*(About!$A$53) -> 18.238975 | O73: =(TREND($E$68:$G$68,$E$67:$G$67,O$32))*(About!$A$53) -> 18.238975 | P73: =(TREND($E$68:$G$68,$E$67:$G$67,P$32))*(About!$A$53) -> 18.238975 | Q73: =(TREND($E$68:$G$68,$E$67:$G$67,Q$32))*(About!$A$53) -> 18.238975 | R73: =(TREND($E$68:$G$68,$E$67:$G$67,R$32))*(About!$A$53) -> 18.238975 | S73: =(TREND($E$68:$G$68,$E$67:$G$67,S$32))*(About!$A$53) -> 18.238975 | T73: =(TREND($E$68:$G$68,$E$67:$G$67,T$32))*(About!$A$53) -> 18.238975 | U73: =(TREND($E$68:$G$68,$E$67:$G$67,U$32))*(About!$A$53) -> 18.238975 | ... AQ73: =(TREND($E$68:$G$68,$E$67:$G$67,AQ$32))*(About!$A$53) -> 18.238975
A74: oil (2012 USD) | B74: =(TREND($C$69:$D$69,$C$67:$D$67,B$32))*(About!$A$53) -> 16.235433 | C74: =(TREND($C$69:$D$69,$C$67:$D$67,C$32))*(About!$A$53) -> 16.235433 | D74: =(TREND($D$69:$E$69,$D$67:$E$67,D$32))*(About!$A$53) -> 16.235433 | E74: =(TREND($D$69:$E$69,$D$67:$E$67,E$32))*(About!$A$53) -> 16.235433 | F74: =(TREND($D$69:$E$69,$D$67:$E$67,F$32))*(About!$A$53) -> 16.235433 | G74: =(TREND($D$69:$E$69,$D$67:$E$67,G$32))*(About!$A$53) -> 16.235433 | H74: =(TREND($D$69:$E$69,$D$67:$E$67,H$32))*(About!$A$53) -> 16.235433 | I74: =(TREND($D$69:$E$69,$D$67:$E$67,I$32))*(About!$A$53) -> 16.235433 | J74: =(TREND($D$69:$E$69,$D$67:$E$67,J$32))*(About!$A$53) -> 16.235433 | K74: =(TREND($D$69:$E$69,$D$67:$E$67,K$32))*(About!$A$53) -> 16.235433 | ... M74: =(TREND($D$69:$E$69,$D$67:$E$67,M$32))*(About!$A$53) -> 16.235433 | N74: =(TREND($E$69:$G$69,$E$67:$G$67,N$32))*(About!$A$53) -> 16.235433 | O74: =(TREND($E$69:$G$69,$E$67:$G$67,O$32))*(About!$A$53) -> 16.235433 | P74: =(TREND($E$69:$G$69,$E$67:$G$67,P$32))*(About!$A$53) -> 16.235433 | Q74: =(TREND($E$69:$G$69,$E$67:$G$67,Q$32))*(About!$A$53) -> 16.235433 | R74: =(TREND($E$69:$G$69,$E$67:$G$67,R$32))*(About!$A$53) -> 16.235433 | S74: =(TREND($E$69:$G$69,$E$67:$G$67,S$32))*(About!$A$53) -> 16.235433 | T74: =(TREND($E$69:$G$69,$E$67:$G$67,T$32))*(About!$A$53) -> 16.235433 | U74: =(TREND($E$69:$G$69,$E$67:$G$67,U$32))*(About!$A$53) -> 16.235433 | ... AQ74: =(TREND($E$69:$G$69,$E$67:$G$67,AQ$32))*(About!$A$53) -> 16.235433
