Workbook

Sheet About
A1: BESP BAU EV Subsidy Percentage
A3: Sources: | B3: Federal Tax Credit Methodology
B4: Ernst and Young
B5: 2019
B6: Federal revenue estimates for potential changes to the plug-in electric drive vehicle tax credit
B7: https://www.afpm.org/sites/default/files/issue_resources/EV-Tax-May2019.pdf
B9: Historial Sales by Manufacturer
B10: Argonne National Laboratory
B11: 2022
B12: Data provided on request
B14: State Rebate Amounts
B15: EnergySage
B16: 2021
B17: Electric car tax credits and incentives
B18: https://www.energysage.com/electric-vehicles/costs-and-benefits-evs/ev-tax-credits/
B20: Tesla
B21: 2022
B22: Electric Vehicle & Solar Incentives
B23: https://www.tesla.com/support/incentives
A26: Notes
A27: The U.S. only has BAU subsidies for passenger LDVs, not other vehicle types.
A28: We account for both federal and state-level subsidies for EVs but not for
A29: charging equipment.
A31: For assumptions governing EV tax credit phase-out, see the "Data" tab.
A33: 2020 to 2012 USD (see cpi.xlsx) | B33: 0.88711067

Sheet Summary - HK
A1: Federal EV Subsidy Amount
A2: 2020 | B2: 2021 | C2: 2022 | D2: 2023 | E2: 2024 | F2: 2025 | G2: 2026 | H2: 2027 | I2: 2028 | J2: 2029 | K2: 2030 | L2: 2031 | M2: 2032 | N2: 2033 | O2: 2034 | P2: 2035 | Q2: 2036 | R2: 2037 | S2: 2038 | T2: 2039 | U2: 2040 | V2: 2041 | W2: 2042 | X2: 2043 | Y2: 2044 | Z2: 2045 | AA2: 2046 | AB2: 2047 | AC2: 2048 | AD2: 2049 | AE2: 2050
A3: ='Baseline Calculations'!C104 -> 1066.1677 | B3: ='Baseline Calculations'!D104 -> 1856.0233 | C3: ='Baseline Calculations'!E104 -> 1578.301 | D3: ='Baseline Calculations'!F104 -> 1230.8383 | E3: ='Baseline Calculations'!G104 -> 626.81537 | F3: ='Baseline Calculations'!H104 -> 144.46747 | G3: ='Baseline Calculations'!I104 -> 33.447892 | H3: ='Baseline Calculations'!J104 -> 33.447892 | ... AE3: ='Baseline Calculations'!AG104 -> 9.0924722
A5: State EV Subsidy Amounts
A6: This list only includes rebates on the EV itself, not on charging equipment.
A7: It also omits states that do not offer a rebate but do exempt EVs from sales, use, or excise taxes.
A8: State Rebates + Tax Credits Updated 8/11/2021
A9: TC | C9: https://www.energysage.com/electric-vehicles/costs-and-benefits-evs/ev-tax-credits/
A10: Rebates | C10: https://www.tesla.com/support/incentives
A11: Note: Could be an optimistic estimate
A12: State | B12: Population, millions (June 2022) | C12: Category | D12: 2020 | E12: =D12+1 -> 2021 | F12: =E12+1 -> 2022 | G12: =F12+1 -> 2023 | H12: =G12+1 -> 2024 | I12: =H12+1 -> 2025 | J12: =I12+1 -> 2026
A13: CO | B13: 5.685 | C13: LDV | D13: 4750 | E13: 4750 | F13: 3000 | G13: 3000 | H13: 2400 | I13: 2400 | J13: 2400 | K13: Note: average of cars and truck subsidies, which are different
A14: CT | B14: 3.571 | C14: LDV | D14: 2250 | E14: 2250 | F14: 2250 | G14: 2250 | H14: 2250 | I14: 2250 | J14: 2250 | R14: https://afdc.energy.gov/laws/11609
A15: DE | B15: 0.968 | C15: LDV | D15: 2500 | E15: 2500 | F15: 2500 | G15: 2500 | H15: 2500 | I15: 2500 | J15: 2500
A16: NY | B16: 8.38 | C16: LDV | D16: 2000 | E16: 2000 | F16: 2000 | G16: 2000 | H16: 2000 | I16: 2000 | J16: 2000 | K16: Subsidy goes up to 2000 based on battery
A17: TX | B17: 28.64 | C17: LDV | D17: 2500 | E17: 0 | F17: 0 | G17: 0 | H17: 0 | I17: 0 | J17: 0 | K17: Note: only 1 year program
A18: CA | B18: 39.35 | C18: LDV | D18: 2500 | E18: 2500 | F18: 2500 | G18: 2500 | H18: 2500 | I18: 2500 | J18: 2500
A19: LA | B19: 4.665 | C19: LDV | D19: 1500 | E19: 1500 | F19: 1500 | G19: 1500 | H19: 1500 | I19: 1500 | J19: 1500
A20: ME | B20: 1.341 | C20: LDV | D20: 2000 | E20: 2000 | F20: 2000 | G20: 2000 | H20: 2000 | I20: 2000 | J20: 2000
A21: MD | B21: 6.038 | C21: LDV | D21: 2500 | E21: 2500 | F21: 2500 | G21: 2500 | H21: 2500 | I21: 2500 | J21: 2500
A22: MA | B22: 6.873 | C22: LDV | D22: 2500 | E22: 2500 | F22: 2500 | G22: 2500 | H22: 2500 | I22: 2500 | J22: 2500
A23: NJ | B23: 8.885 | C23: LDV | D23: 5000 | E23: 5000 | F23: 5000 | G23: 5000 | H23: 5000 | I23: 5000 | J23: 5000
A24: OR | B24: 4.176 | C24: LDV | D24: 2500 | E24: 2500 | F24: 2500 | G24: 2500 | H24: 2500 | I24: 2500 | J24: 2500
A25: VT | B25: 0.624 | C25: LDV | D25: 4000 | E25: 4000 | F25: 4000 | G25: 4000 | H25: 4000 | I25: 4000 | J25: 4000 | K25: Note: Up to 4000
A26: Rest of country | B26: =B27-SUM(B13:B25) -> 210.304 | D26: 0 | E26: 0 | F26: 0 | G26: 0 | H26: 0 | I26: 0 | J26: 0
A27: USA | B27: 329.5
A29: Note: Pennsylvania offers a $1750 rebate, but only to the first 250 qualified applicants.
A31: Pop-Weighted State Avg Tax Credit
C32: 2020 | D32: 2021 | E32: 2022 | F32: 2023 | G32: 2024 | H32: 2025 | I32: 2026 | J32: 2027 | K32: 2028 | L32: 2029 | M32: 2030 | N32: 2031 | O32: 2032 | P32: 2033 | Q32: 2034 | R32: 2035 | S32: 2036 | T32: 2037 | U32: 2038 | V32: 2039 | W32: 2040 | X32: 2041 | Y32: 2042 | Z32: 2043 | AA32: 2044 | AB32: 2045 | AC32: 2046 | AD32: 2047 | AE32: 2048 | AF32: 2049 | AG32: 2050
C33: =SUMPRODUCT(D13:D26,$B$13:$B$26)/SUM($B$13:$B$26) -> 981.82549 | D33: =SUMPRODUCT(E13:E26,$B$13:$B$26)/SUM($B$13:$B$26) -> 764.52656 | E33: =SUMPRODUCT(F13:F26,$B$13:$B$26)/SUM($B$13:$B$26) -> 734.33308 | F33: =SUMPRODUCT(G13:G26,$B$13:$B$26)/SUM($B$13:$B$26) -> 734.33308 | G33: =SUMPRODUCT(H13:H26,$B$13:$B$26)/SUM($B$13:$B$26) -> 723.98103 | H33: =SUMPRODUCT(I13:I26,$B$13:$B$26)/SUM($B$13:$B$26) -> 723.98103 | I33: =SUMPRODUCT(J13:J26,$B$13:$B$26)/SUM($B$13:$B$26) -> 723.98103 | J33: =I33 -> 723.98103 | K33: =J33 -> 723.98103 | L33: =K33 -> 723.98103 | M33: =L33 -> 723.98103 | N33: =M33 -> 723.98103 | O33: =N33 -> 723.98103 | P33: =O33 -> 723.98103 | Q33: =P33 -> 723.98103 | ... AG33: =AF33 -> 723.98103
A35: Total Tax Credit (2012$)
C36: 2020 | D36: 2021 | E36: 2022 | F36: 2023 | G36: 2024 | H36: 2025 | I36: 2026 | J36: 2027 | K36: 2028 | L36: 2029 | M36: 2030 | N36: 2031 | O36: 2032 | P36: 2033 | Q36: 2034 | R36: 2035 | S36: 2036 | T36: 2037 | U36: 2038 | V36: 2039 | W36: 2040 | X36: 2041 | Y36: 2042 | Z36: 2043 | AA36: 2044 | AB36: 2045 | AC36: 2046 | AD36: 2047 | AE36: 2048 | AF36: 2049 | AG36: 2050
C37: =(A3+$C$33)*About!$B$33 -> 1816.7966 | D37: =(B3+$C$33)*About!$B$33 -> 2517.486 | E37: =(C3+$C$33)*About!$B$33 -> 2271.1155 | F37: =(D3+$C$33)*About!$B$33 -> 1962.8777 | G37: =(E3+$C$33)*About!$B$33 -> 1427.0425 | H37: =(F3+$C$33)*About!$B$33 -> 999.1465 | I37: =(G3+$C$33)*About!$B$33 -> 900.65985 | J37: =(H3+$C$33)*About!$B$33 -> 900.65985 | ... AG37: =(AE3+$C$33)*About!$B$33 -> 879.0539
A39: Time (Year) | C39: 2020 | D39: 2021 | E39: 2022 | F39: 2023 | G39: 2024 | H39: 2025 | I39: 2026 | J39: 2027 | K39: 2028 | L39: 2029 | M39: 2030 | N39: 2031 | O39: 2032 | P39: 2033 | Q39: 2034 | R39: 2035 | S39: 2036 | T39: 2037 | U39: 2038 | V39: 2039 | W39: 2040 | X39: 2041 | Y39: 2042 | Z39: 2043 | AA39: 2044 | AB39: 2045 | AC39: 2046 | AD39: 2047 | AE39: 2048 | AF39: 2049 | AG39: 2050
A40: New Vehicle Price after RnD[LDVs,passenger,battery electric vehicle] : MostRecentRun | C40: 49824 | D40: 46173.6 | E40: 43530.5 | F40: 41513.3 | G40: 39946.3 | H40: 38679.5 | I40: 37326.7 | J40: 36099.2 | K40: 34664.5 | L40: 33628.9 | M40: 32666.3 | N40: 32118.8 | O40: 31643.2 | P40: 31237.2 | Q40: 30885.3 | R40: 30578 | S40: 30305.7 | T40: 30065.9 | U40: 29852.9 | V40: 29660.9 | W40: 29486.9 | X40: 29330.6 | Y40: 29189.2 | Z40: 29060.4 | AA40: 28942.9 | AB40: 28835.1 | AC40: 28735.8 | AD40: 28643.9 | AE40: 28558.5 | AF40: 28478.6 | AG40: 28404.1
A42: Approximate EV Subsidy Percentage
C43: 2020 | D43: 2021 | E43: 2022 | F43: 2023 | G43: 2024 | H43: 2025 | I43: 2026 | J43: 2027 | K43: 2028 | L43: 2029 | M43: 2030 | N43: 2031 | O43: 2032 | P43: 2033 | Q43: 2034 | R43: 2035 | S43: 2036 | T43: 2037 | U43: 2038 | V43: 2039 | W43: 2040 | X43: 2041 | Y43: 2042 | Z43: 2043 | AA43: 2044 | AB43: 2045 | AC43: 2046 | AD43: 2047 | AE43: 2048 | AF43: 2049 | AG43: 2050
C44: =C37/C40 -> 0.036464286 | D44: =D37/D40 -> 0.054522194 | E44: =E37/E40 -> 0.052172971 | F44: =F37/F40 -> 0.047283104 | G44: =G37/G40 -> 0.035724021 | H44: =H37/H40 -> 0.025831422 | I44: =I37/I40 -> 0.024129105 | J44: =J37/J40 -> 0.024949579 | ... AG44: =AG37/AG40 -> 0.030948134
A46: Government EV Subsidy (First Registration Tax Scheme)
C47: 2018 | D47: 2019 | E47: 2020 | F47: 2021 | G47: 2022 | H47: 2023 | I47: 2024
C48: $97,500 | D48: $97,500 | E48: $97,500 | F48: $97,500 | G48: $97,500 | H48: $97,500 | I48: $97,500
A51: Government EV Subsidy (One-for-One Replacement Scheme) | B51: allows old PCs to be scrapped and de-registered and registered with a new EV for a higher FRT concession)
C53: 2018 | D53: 2019 | E53: 2020 | F53: 2021 | G53: 2022 | H53: 2023 | I53: 2024
C54: $287,500 | D54: $287,500 | E54: $287,500 | F54: $287,500 | G54: $287,500 | H54: $287,500 | I54: $287,500
A57: New Vehicle Price after RnD[LDVs,passenger,battery electric vehicle] : MostRecentRun
A61: Approximate EV Subsidy Percentage | C61: 2018 | D61: 2019 | E61: 2020 | F61: 2021 | G61: 2022 | H61: 2023 | I61: 2024

Sheet Summary - US
A1: Federal EV Subsidy Amount
A2: 2020 | B2: 2021 | C2: 2022 | D2: 2023 | E2: 2024 | F2: 2025 | G2: 2026 | H2: 2027 | I2: 2028 | J2: 2029 | K2: 2030 | L2: 2031 | M2: 2032 | N2: 2033 | O2: 2034 | P2: 2035 | Q2: 2036 | R2: 2037 | S2: 2038 | T2: 2039 | U2: 2040 | V2: 2041 | W2: 2042 | X2: 2043 | Y2: 2044 | Z2: 2045 | AA2: 2046 | AB2: 2047 | AC2: 2048 | AD2: 2049 | AE2: 2050
A3: ='Baseline Calculations'!C104 -> 1066.1677 | B3: ='Baseline Calculations'!D104 -> 1856.0233 | C3: ='Baseline Calculations'!E104 -> 1578.301 | D3: ='Baseline Calculations'!F104 -> 1230.8383 | E3: ='Baseline Calculations'!G104 -> 626.81537 | F3: ='Baseline Calculations'!H104 -> 144.46747 | G3: ='Baseline Calculations'!I104 -> 33.447892 | H3: ='Baseline Calculations'!J104 -> 33.447892 | ... AE3: ='Baseline Calculations'!AG104 -> 9.0924722
A5: State EV Subsidy Amounts
A6: This list only includes rebates on the EV itself, not on charging equipment.
A7: It also omits states that do not offer a rebate but do exempt EVs from sales, use, or excise taxes.
A8: State Rebates + Tax Credits Updated 8/11/2021
A9: TC | C9: https://www.energysage.com/electric-vehicles/costs-and-benefits-evs/ev-tax-credits/
A10: Rebates | C10: https://www.tesla.com/support/incentives
A11: Note: Could be an optimistic estimate
A12: State | B12: Population, millions (June 2022) | C12: Category | D12: 2020 | E12: =D12+1 -> 2021 | F12: =E12+1 -> 2022 | G12: =F12+1 -> 2023 | H12: =G12+1 -> 2024 | I12: =H12+1 -> 2025 | J12: =I12+1 -> 2026
A13: CO | B13: 5.685 | C13: LDV | D13: 4750 | E13: 4750 | F13: 3000 | G13: 3000 | H13: 2400 | I13: 2400 | J13: 2400 | K13: Note: average of cars and truck subsidies, which are different
A14: CT | B14: 3.571 | C14: LDV | D14: 2250 | E14: 2250 | F14: 2250 | G14: 2250 | H14: 2250 | I14: 2250 | J14: 2250 | R14: https://afdc.energy.gov/laws/11609
A15: DE | B15: 0.968 | C15: LDV | D15: 2500 | E15: 2500 | F15: 2500 | G15: 2500 | H15: 2500 | I15: 2500 | J15: 2500
A16: NY | B16: 8.38 | C16: LDV | D16: 2000 | E16: 2000 | F16: 2000 | G16: 2000 | H16: 2000 | I16: 2000 | J16: 2000 | K16: Subsidy goes up to 2000 based on battery
A17: TX | B17: 28.64 | C17: LDV | D17: 2500 | E17: 0 | F17: 0 | G17: 0 | H17: 0 | I17: 0 | J17: 0 | K17: Note: only 1 year program
A18: CA | B18: 39.35 | C18: LDV | D18: 2500 | E18: 2500 | F18: 2500 | G18: 2500 | H18: 2500 | I18: 2500 | J18: 2500
A19: LA | B19: 4.665 | C19: LDV | D19: 1500 | E19: 1500 | F19: 1500 | G19: 1500 | H19: 1500 | I19: 1500 | J19: 1500
A20: ME | B20: 1.341 | C20: LDV | D20: 2000 | E20: 2000 | F20: 2000 | G20: 2000 | H20: 2000 | I20: 2000 | J20: 2000
A21: MD | B21: 6.038 | C21: LDV | D21: 2500 | E21: 2500 | F21: 2500 | G21: 2500 | H21: 2500 | I21: 2500 | J21: 2500
A22: MA | B22: 6.873 | C22: LDV | D22: 2500 | E22: 2500 | F22: 2500 | G22: 2500 | H22: 2500 | I22: 2500 | J22: 2500
A23: NJ | B23: 8.885 | C23: LDV | D23: 5000 | E23: 5000 | F23: 5000 | G23: 5000 | H23: 5000 | I23: 5000 | J23: 5000
A24: OR | B24: 4.176 | C24: LDV | D24: 2500 | E24: 2500 | F24: 2500 | G24: 2500 | H24: 2500 | I24: 2500 | J24: 2500
A25: VT | B25: 0.624 | C25: LDV | D25: 4000 | E25: 4000 | F25: 4000 | G25: 4000 | H25: 4000 | I25: 4000 | J25: 4000 | K25: Note: Up to 4000
A26: Rest of country | B26: =B27-SUM(B13:B25) -> 210.304 | D26: 0 | E26: 0 | F26: 0 | G26: 0 | H26: 0 | I26: 0 | J26: 0
A27: USA | B27: 329.5
A29: Note: Pennsylvania offers a $1750 rebate, but only to the first 250 qualified applicants.
A31: Pop-Weighted State Avg Tax Credit
C32: 2020 | D32: 2021 | E32: 2022 | F32: 2023 | G32: 2024 | H32: 2025 | I32: 2026 | J32: 2027 | K32: 2028 | L32: 2029 | M32: 2030 | N32: 2031 | O32: 2032 | P32: 2033 | Q32: 2034 | R32: 2035 | S32: 2036 | T32: 2037 | U32: 2038 | V32: 2039 | W32: 2040 | X32: 2041 | Y32: 2042 | Z32: 2043 | AA32: 2044 | AB32: 2045 | AC32: 2046 | AD32: 2047 | AE32: 2048 | AF32: 2049 | AG32: 2050
C33: =SUMPRODUCT(D13:D26,$B$13:$B$26)/SUM($B$13:$B$26) -> 981.82549 | D33: =SUMPRODUCT(E13:E26,$B$13:$B$26)/SUM($B$13:$B$26) -> 764.52656 | E33: =SUMPRODUCT(F13:F26,$B$13:$B$26)/SUM($B$13:$B$26) -> 734.33308 | F33: =SUMPRODUCT(G13:G26,$B$13:$B$26)/SUM($B$13:$B$26) -> 734.33308 | G33: =SUMPRODUCT(H13:H26,$B$13:$B$26)/SUM($B$13:$B$26) -> 723.98103 | H33: =SUMPRODUCT(I13:I26,$B$13:$B$26)/SUM($B$13:$B$26) -> 723.98103 | I33: =SUMPRODUCT(J13:J26,$B$13:$B$26)/SUM($B$13:$B$26) -> 723.98103 | J33: =I33 -> 723.98103 | K33: =J33 -> 723.98103 | L33: =K33 -> 723.98103 | M33: =L33 -> 723.98103 | N33: =M33 -> 723.98103 | O33: =N33 -> 723.98103 | P33: =O33 -> 723.98103 | Q33: =P33 -> 723.98103 | ... AG33: =AF33 -> 723.98103
A35: Total Tax Credit (2012$)
C36: 2020 | D36: 2021 | E36: 2022 | F36: 2023 | G36: 2024 | H36: 2025 | I36: 2026 | J36: 2027 | K36: 2028 | L36: 2029 | M36: 2030 | N36: 2031 | O36: 2032 | P36: 2033 | Q36: 2034 | R36: 2035 | S36: 2036 | T36: 2037 | U36: 2038 | V36: 2039 | W36: 2040 | X36: 2041 | Y36: 2042 | Z36: 2043 | AA36: 2044 | AB36: 2045 | AC36: 2046 | AD36: 2047 | AE36: 2048 | AF36: 2049 | AG36: 2050
C37: =(A3+$C$33)*About!$B$33 -> 1816.7966 | D37: =(B3+$C$33)*About!$B$33 -> 2517.486 | E37: =(C3+$C$33)*About!$B$33 -> 2271.1155 | F37: =(D3+$C$33)*About!$B$33 -> 1962.8777 | G37: =(E3+$C$33)*About!$B$33 -> 1427.0425 | H37: =(F3+$C$33)*About!$B$33 -> 999.1465 | I37: =(G3+$C$33)*About!$B$33 -> 900.65985 | J37: =(H3+$C$33)*About!$B$33 -> 900.65985 | ... AG37: =(AE3+$C$33)*About!$B$33 -> 879.0539
A39: Time (Year) | C39: 2020 | D39: 2021 | E39: 2022 | F39: 2023 | G39: 2024 | H39: 2025 | I39: 2026 | J39: 2027 | K39: 2028 | L39: 2029 | M39: 2030 | N39: 2031 | O39: 2032 | P39: 2033 | Q39: 2034 | R39: 2035 | S39: 2036 | T39: 2037 | U39: 2038 | V39: 2039 | W39: 2040 | X39: 2041 | Y39: 2042 | Z39: 2043 | AA39: 2044 | AB39: 2045 | AC39: 2046 | AD39: 2047 | AE39: 2048 | AF39: 2049 | AG39: 2050
A40: New Vehicle Price after RnD[LDVs,passenger,battery electric vehicle] : MostRecentRun | C40: 49824 | D40: 46173.6 | E40: 43530.5 | F40: 41513.3 | G40: 39946.3 | H40: 38679.5 | I40: 37326.7 | J40: 36099.2 | K40: 34664.5 | L40: 33628.9 | M40: 32666.3 | N40: 32118.8 | O40: 31643.2 | P40: 31237.2 | Q40: 30885.3 | R40: 30578 | S40: 30305.7 | T40: 30065.9 | U40: 29852.9 | V40: 29660.9 | W40: 29486.9 | X40: 29330.6 | Y40: 29189.2 | Z40: 29060.4 | AA40: 28942.9 | AB40: 28835.1 | AC40: 28735.8 | AD40: 28643.9 | AE40: 28558.5 | AF40: 28478.6 | AG40: 28404.1
A42: Approximate EV Subsidy Percentage
C43: 2020 | D43: 2021 | E43: 2022 | F43: 2023 | G43: 2024 | H43: 2025 | I43: 2026 | J43: 2027 | K43: 2028 | L43: 2029 | M43: 2030 | N43: 2031 | O43: 2032 | P43: 2033 | Q43: 2034 | R43: 2035 | S43: 2036 | T43: 2037 | U43: 2038 | V43: 2039 | W43: 2040 | X43: 2041 | Y43: 2042 | Z43: 2043 | AA43: 2044 | AB43: 2045 | AC43: 2046 | AD43: 2047 | AE43: 2048 | AF43: 2049 | AG43: 2050
C44: =C37/C40 -> 0.036464286 | D44: =D37/D40 -> 0.054522194 | E44: =E37/E40 -> 0.052172971 | F44: =F37/F40 -> 0.047283104 | G44: =G37/G40 -> 0.035724021 | H44: =H37/H40 -> 0.025831422 | I44: =I37/I40 -> 0.024129105 | J44: =J37/J40 -> 0.024949579 | ... AG44: =AG37/AG40 -> 0.030948134

Sheet Baseline Calculations
D1: Projected Cumulative Sales
B2: 2020 | C2: 2021 | D2: 2022 | E2: 2023 | F2: 2024 | G2: 2025 | H2: 2026 | I2: 2027 | J2: 2028 | K2: 2029 | L2: 2030 | M2: 2031 | N2: 2032 | O2: 2033 | P2: 2034 | Q2: 2035 | R2: 2036 | S2: 2037 | T2: 2038 | U2: 2039 | V2: 2040 | W2: 2041 | X2: 2042 | Y2: 2043 | Z2: 2044 | AA2: 2045 | AB2: 2046 | AC2: 2047 | AD2: 2048 | AE2: 2049 | AF2: 2050
A3: Tesla | B3: =SUM('PEV Sales by Manufacturer'!D4:M4) -> 687269 | C3: =SUM('PEV Sales by Manufacturer'!D4:N4) -> 1008187 | D3: =C3+D32+D56 -> 1775770.6 | E3: =D3+E32+E56 -> 2893800.1 | F3: =E3+F32+F56 -> 4437118.6 | G3: =F3+G32+G56 -> 6399691.3 | H3: =G3+H32+H56 -> 8714085.8 | I3: =H3+I32+I56 -> 11395467 | J3: =I3+J32+J56 -> 14460255 | K3: =J3+K32+K56 -> 17883738 | ... AF3: =AE3+AF32+AF56 -> 1.4609994e+08
A4: GM (Cadillac and Chevrolet) | B4: =SUM('PEV Sales by Manufacturer'!D5:M5) -> 246675 | C4: =SUM('PEV Sales by Manufacturer'!D5:N5) -> 271520 | D4: =C4+D33+D57 -> 330946.81 | E4: =D4+E33+E57 -> 417505.81 | F4: =E4+F33+F57 -> 536991.86 | G4: =F4+G33+G57 -> 688934.15 | H4: =G4+H33+H57 -> 868108.02 | I4: =H4+I33+I57 -> 1075681.8 | J4: =I4+J33+J57 -> 1312920.8 | K4: =J4+K33+K57 -> 1577912.5 | ... AF4: =AE4+AF33+AF57 -> 11500099
A5: Nissan | B5: =SUM('PEV Sales by Manufacturer'!D6:M6) -> 151452 | C5: =SUM('PEV Sales by Manufacturer'!D6:N6) -> 165691 | D5: =C5+D34+D58 -> 199748.37 | E5: =D5+E34+E58 -> 249354.88 | F5: =E5+F34+F58 -> 317831.29 | G5: =F5+G34+G58 -> 404909.83 | H5: =G5+H34+H58 -> 507598.57 | I5: =H5+I34+I58 -> 626570.33 | J5: =I5+J34+J58 -> 762553.73 | K5: =J5+K34+K58 -> 914452.29 | ... AF5: =AE5+AF34+AF58 -> 6603352.5
A6: Toyota | B6: =SUM('PEV Sales by Manufacturer'!D7:M7) -> 135451 | C6: =SUM('PEV Sales by Manufacturer'!D7:N7) -> 188218 | D6: =C6+D35+D59 -> 319773.88 | E6: =D6+E35+E59 -> 512815.07 | F6: =E6+F35+F59 -> 781733.99 | G6: =F6+G35+G59 -> 1113667.8 | H6: =G6+H35+H59 -> 1483791.5 | I6: =H6+I35+I59 -> 1875885.4 | J6: =I6+J35+J59 -> 2273077.7 | K6: =J6+K35+K59 -> 2673237.5 | ... AF6: =AE6+AF35+AF59 -> 10157425
A7: Ford | B7: =SUM('PEV Sales by Manufacturer'!D8:M8) -> 126312 | C7: =SUM('PEV Sales by Manufacturer'!D8:N8) -> 159546 | D7: =C7+D36+D60 -> 239645.49 | E7: =D7+E36+E60 -> 356477.09 | F7: =E7+F36+F60 -> 518029.24 | G7: =F7+G36+G60 -> 722324.26 | H7: =G7+H36+H60 -> 960813.52 | I7: =H7+I36+I60 -> 1232935 | J7: =I7+J36+J60 -> 1538158.9 | K7: =J7+K36+K60 -> 1874146.3 | ... AF7: =AE7+AF36+AF60 -> 13602590
A8: BMW N. America | B8: =SUM('PEV Sales by Manufacturer'!D9:M9) -> 109611 | C8: =SUM('PEV Sales by Manufacturer'!D9:N9) -> 132675 | D8: =C8+D37+D61 -> 189823.87 | E8: =D8+E37+E61 -> 273592.3 | F8: =E8+F37+F61 -> 390133.3 | G8: =F8+G37+G61 -> 534608.6 | H8: =G8+H37+H61 -> 697074.75 | I8: =H8+I37+I61 -> 871678.1 | J8: =I8+J37+J61 -> 1052336.8 | K8: =J8+K37+K61 -> 1237991.9 | ... AF8: =AE8+AF37+AF61 -> 5407332.1
A9: FCA (Chrysler and Fiat) | B9: =SUM('PEV Sales by Manufacturer'!D10:M10) -> 37707 | C9: =SUM('PEV Sales by Manufacturer'!D10:N10) -> 86430 | D9: =C9+D38+D62 -> 207903.59 | E9: =D9+E38+E62 -> 386150.34 | F9: =E9+F38+F62 -> 634459.63 | G9: =F9+G38+G62 -> 940954.39 | H9: =G9+H38+H62 -> 1282712.3 | I9: =H9+I38+I62 -> 1644756.6 | J9: =I9+J38+J62 -> 2011508.5 | K9: =J9+K38+K62 -> 2381000.6 | ... AF9: =AE9+AF38+AF62 -> 9291608.6
A10: Honda | B10: =SUM('PEV Sales by Manufacturer'!D11:M11) -> 39002 | C10: =SUM('PEV Sales by Manufacturer'!D11:N11) -> 41317 | D10: =C10+D39+D63 -> 47088.534 | E10: =D10+E39+E63 -> 55557.485 | F10: =E10+F39+F63 -> 67355.24 | G10: =F10+G39+G63 -> 81917.702 | H10: =G10+H39+H63 -> 98156.013 | I10: =H10+I39+I63 -> 115358.92 | J10: =I10+J39+J63 -> 132786.62 | K10: =J10+K39+K63 -> 150345.56 | ... AF10: =AE10+AF39+AF63 -> 478950.39
A11: Audi | B11: =SUM('PEV Sales by Manufacturer'!D12:M12) -> 26628 | C11: =SUM('PEV Sales by Manufacturer'!D12:N12) -> 46647 | D11: =C11+D40+D64 -> 95435.2 | E11: =D11+E40+E64 -> 166739.1 | F11: =E11+F40+F64 -> 265581.04 | G11: =F11+G40+G64 -> 389572.71 | H11: =G11+H40+H64 -> 532179.46 | I11: =H11+I40+I64 -> 691175.69 | J11: =I11+J40+J64 -> 864268.75 | K11: =J11+K40+K64 -> 1050244.6 | ... AF11: =AE11+AF40+AF64 -> 6743860
A12: Hyundai | B12: =SUM('PEV Sales by Manufacturer'!D13:M13) -> 25223 | C12: =SUM('PEV Sales by Manufacturer'!D13:N13) -> 42236 | D12: =C12+D41+D65 -> 83552.19 | E12: =D12+E41+E65 -> 143897.6 | F12: =E12+F41+F65 -> 227483.4 | G12: =F12+G41+G65 -> 332604.35 | H12: =G12+H41+H65 -> 454082.46 | I12: =H12+I41+I65 -> 590537.77 | J12: =I12+J41+J65 -> 740556.77 | K12: =J12+K41+K65 -> 903054.89 | ... AF12: =AE12+AF41+AF65 -> 6113364.9
A13: Kia | B13: =SUM('PEV Sales by Manufacturer'!D14:M14) -> 24512 | C13: =SUM('PEV Sales by Manufacturer'!D14:N14) -> 39129 | D13: =C13+D42+D66 -> 74688.211 | E13: =D13+E42+E66 -> 126641.29 | F13: =E13+F42+F66 -> 198630.44 | G13: =F13+G42+G66 -> 289053.5 | H13: =G13+H42+H66 -> 393303.1 | I13: =H13+I42+I66 -> 509977.56 | J13: =I13+J42+J66 -> 637636.48 | K13: =J13+K42+K66 -> 775370.34 | ... AF13: =AE13+AF42+AF66 -> 5094893
A14: Volvo | B14: =SUM('PEV Sales by Manufacturer'!D15:M15) -> 19669 | C14: =SUM('PEV Sales by Manufacturer'!D15:N15) -> 45138 | D14: =C14+D43+D67 -> 107636.74 | E14: =D14+E43+E67 -> 199090.45 | F14: =E14+F43+F67 -> 326055.93 | G14: =F14+G43+G67 -> 484543.48 | H14: =G14+H43+H67 -> 665138.64 | I14: =H14+I43+I67 -> 863510.35 | J14: =I14+J43+J67 -> 1075173.5 | K14: =J14+K43+K67 -> 1298738.3 | ... AF14: =AE14+AF43+AF67 -> 7452768.6
... A24: Mazda | B24: =SUM('PEV Sales by Manufacturer'!D25:M25) -> 0 | C24: =SUM('PEV Sales by Manufacturer'!D25:N25) -> 116 | D24: =C24+D53+D77 -> 393.45311 | E24: =D24+E53+E77 -> 797.57947 | F24: =E24+F53+F77 -> 1355.4321 | G24: =F24+G53+G77 -> 2064.8296 | H24: =G24+H53+H77 -> 2901.3977 | I24: =H24+I53+I77 -> 3870.6178 | J24: =I24+J53+J77 -> 4978.4255 | K24: =J24+K53+K77 -> 6215.8883 | ... AF24: =AE24+AF53+AF77 -> 52561.308
A26: BAU Projected Sales in EPS
A27: Time (Year) | B27: 2020 | C27: 2021 | D27: 2022 | E27: 2023 | F27: 2024 | G27: 2025 | H27: 2026 | I27: 2027 | J27: 2028 | K27: 2029 | L27: 2030 | M27: 2031 | N27: 2032 | O27: 2033 | P27: 2034 | Q27: 2035 | R27: 2036 | S27: 2037 | T27: 2038 | U27: 2039 | V27: 2040 | W27: 2041 | X27: 2042 | Y27: 2043 | Z27: 2044 | AA27: 2045 | AB27: 2046 | AC27: 2047 | AD27: 2048 | AE27: 2049 | AF27: 2050
A28: New Vehicles[LDVs,passenger,battery electric vehicle] : MostRecentRun | B28: 349182 | C28: 603744 | D28: 1098920 | E28: 1600640 | F28: 2209510 | G28: 2809740 | H28: 3313430 | I28: 3838830 | J28: 4387740 | K28: 4901270 | L28: 5460140 | M28: 5896040 | N28: 6271520 | O28: 6625100 | P28: 6942390 | Q28: 7274900 | R28: 7567320 | S28: 7866920 | T28: 8176700 | U28: 8461000 | V28: 8757100 | W28: 9060000 | X28: 9346980 | Y28: 9657430 | Z28: 9970180 | AA28: 10265600 | AB28: 10577800 | AC28: 10885700 | AD28: 11185100 | AE28: 11495700 | AF28: 11818600
A29: New Vehicles[LDVs,passenger,plugin hybrid vehicle] : MostRecentRun | B29: 86889 | C29: 248313 | D29: 434007 | E29: 636849 | F29: 887172 | G29: 1095060 | H29: 1221050 | I29: 1293530 | J29: 1310350 | K29: 1320140 | L29: 1310940 | M29: 1306520 | N29: 1289590 | O29: 1270880 | P29: 1252620 | Q29: 1235240 | R29: 1219780 | S29: 1204400 | T29: 1191940 | U29: 1177850 | V29: 1166230 | W29: 1155260 | X29: 1143250 | Y29: 1133420 | Z29: 1123340 | AA29: 1112470 | AB29: 1102060 | AC29: 1091130 | AD29: 1079340 | AE29: 1067910 | AF29: 1056400
A31: Projected Annual BEV Sales by Manufacturer | B31: 2020 | C31: 2021 | D31: 2022 | E31: 2023 | F31: 2024 | G31: 2025 | H31: 2026 | I31: 2027 | J31: 2028 | K31: 2029 | L31: 2030 | M31: 2031 | N31: 2032 | O31: 2033 | P31: 2034 | Q31: 2035 | R31: 2036 | S31: 2037 | T31: 2038 | U31: 2039 | V31: 2040 | W31: 2041 | X31: 2042 | Y31: 2043 | Z31: 2044 | AA31: 2045 | AB31: 2046 | AC31: 2047 | AD31: 2048 | AE31: 2049 | AF31: 2050
A32: Tesla | B32: ='PEV Sales by Manufacturer'!M31 -> 183829 | C32: ='PEV Sales by Manufacturer'!N31 -> 320918 | D32: =D$28*'PEV Sales by Manufacturer'!$S31 -> 767583.59 | E32: =E$28*'PEV Sales by Manufacturer'!$S31 -> 1118029.5 | F32: =F$28*'PEV Sales by Manufacturer'!$S31 -> 1543318.5 | G32: =G$28*'PEV Sales by Manufacturer'!$S31 -> 1962572.6 | H32: =H$28*'PEV Sales by Manufacturer'!$S31 -> 2314394.6 | I32: =I$28*'PEV Sales by Manufacturer'!$S31 -> 2681380.7 | J32: =J$28*'PEV Sales by Manufacturer'!$S31 -> 3064788.3 | K32: =K$28*'PEV Sales by Manufacturer'!$S31 -> 3423483.4 | ... AF32: =AF$28*'PEV Sales by Manufacturer'!$S31 -> 8255162.7
A33: GM (Cadillac and Chevrolet) | B33: ='PEV Sales by Manufacturer'!M32 -> 20754 | C33: ='PEV Sales by Manufacturer'!N32 -> 24829 | D33: =D$28*'PEV Sales by Manufacturer'!$S32 -> 59386.924 | E33: =E$28*'PEV Sales by Manufacturer'!$S32 -> 86500.46 | F33: =F$28*'PEV Sales by Manufacturer'!$S32 -> 119404.51 | G33: =G$28*'PEV Sales by Manufacturer'!$S32 -> 151841.64 | H33: =H$28*'PEV Sales by Manufacturer'!$S32 -> 179061.64 | I33: =I$28*'PEV Sales by Manufacturer'!$S32 -> 207454.87 | J33: =J$28*'PEV Sales by Manufacturer'!$S32 -> 237118.61 | K33: =K$28*'PEV Sales by Manufacturer'!$S32 -> 264870.37 | ... AF33: =AF$28*'PEV Sales by Manufacturer'!$S32 -> 638690.99
A34: Nissan | B34: ='PEV Sales by Manufacturer'!M33 -> 9564 | C34: ='PEV Sales by Manufacturer'!N33 -> 14239 | D34: =D$28*'PEV Sales by Manufacturer'!$S33 -> 34057.369 | E34: =E$28*'PEV Sales by Manufacturer'!$S33 -> 49606.511 | F34: =F$28*'PEV Sales by Manufacturer'!$S33 -> 68476.41 | G34: =G$28*'PEV Sales by Manufacturer'!$S33 -> 87078.542 | H34: =H$28*'PEV Sales by Manufacturer'!$S33 -> 102688.74 | I34: =I$28*'PEV Sales by Manufacturer'!$S33 -> 118971.76 | J34: =J$28*'PEV Sales by Manufacturer'!$S33 -> 135983.4 | K34: =K$28*'PEV Sales by Manufacturer'!$S33 -> 151898.56 | ... AF34: =AF$28*'PEV Sales by Manufacturer'!$S33 -> 366278.18
A35: Toyota | B35: ='PEV Sales by Manufacturer'!M34 -> 0 | C35: ='PEV Sales by Manufacturer'!N34 -> 0 | D35: =D$28*'PEV Sales by Manufacturer'!$S34 -> 0 | E35: =E$28*'PEV Sales by Manufacturer'!$S34 -> 0 | F35: =F$28*'PEV Sales by Manufacturer'!$S34 -> 0 | G35: =G$28*'PEV Sales by Manufacturer'!$S34 -> 0 | H35: =H$28*'PEV Sales by Manufacturer'!$S34 -> 0 | I35: =I$28*'PEV Sales by Manufacturer'!$S34 -> 0 | J35: =J$28*'PEV Sales by Manufacturer'!$S34 -> 0 | K35: =K$28*'PEV Sales by Manufacturer'!$S34 -> 0 | ... AF35: =AF$28*'PEV Sales by Manufacturer'!$S34 -> 0
A36: Ford | B36: ='PEV Sales by Manufacturer'!M35 -> 3 | C36: ='PEV Sales by Manufacturer'!N35 -> 27221 | D36: =D$28*'PEV Sales by Manufacturer'!$S35 -> 65108.198 | E36: =E$28*'PEV Sales by Manufacturer'!$S35 -> 94833.825 | F36: =F$28*'PEV Sales by Manufacturer'!$S35 -> 130907.81 | G36: =G$28*'PEV Sales by Manufacturer'!$S35 -> 166469.91 | H36: =H$28*'PEV Sales by Manufacturer'!$S35 -> 196312.25 | I36: =I$28*'PEV Sales by Manufacturer'!$S35 -> 227440.86 | J36: =J$28*'PEV Sales by Manufacturer'!$S35 -> 259962.37 | K36: =K$28*'PEV Sales by Manufacturer'!$S35 -> 290387.71 | ... AF36: =AF$28*'PEV Sales by Manufacturer'!$S35 -> 700221.81
A37: BMW N. America | B37: ='PEV Sales by Manufacturer'!M36 -> 2640 | C37: ='PEV Sales by Manufacturer'!N36 -> 3485 | D37: =D$28*'PEV Sales by Manufacturer'!$S36 -> 8335.5524 | E37: =E$28*'PEV Sales by Manufacturer'!$S36 -> 12141.21 | F37: =F$28*'PEV Sales by Manufacturer'!$S36 -> 16759.624 | G37: =G$28*'PEV Sales by Manufacturer'!$S36 -> 21312.502 | H37: =H$28*'PEV Sales by Manufacturer'!$S36 -> 25133.103 | I37: =I$28*'PEV Sales by Manufacturer'!$S36 -> 29118.379 | J37: =J$28*'PEV Sales by Manufacturer'!$S36 -> 33281.983 | K37: =K$28*'PEV Sales by Manufacturer'!$S36 -> 37177.222 | ... AF37: =AF$28*'PEV Sales by Manufacturer'!$S36 -> 89646.707
A38: FCA (Chrysler and Fiat) | B38: ='PEV Sales by Manufacturer'!M37 -> 70 | C38: ='PEV Sales by Manufacturer'!N37 -> 0 | D38: =D$28*'PEV Sales by Manufacturer'!$S37 -> 0 | E38: =E$28*'PEV Sales by Manufacturer'!$S37 -> 0 | F38: =F$28*'PEV Sales by Manufacturer'!$S37 -> 0 | G38: =G$28*'PEV Sales by Manufacturer'!$S37 -> 0 | H38: =H$28*'PEV Sales by Manufacturer'!$S37 -> 0 | I38: =I$28*'PEV Sales by Manufacturer'!$S37 -> 0 | J38: =J$28*'PEV Sales by Manufacturer'!$S37 -> 0 | K38: =K$28*'PEV Sales by Manufacturer'!$S37 -> 0 | ... AF38: =AF$28*'PEV Sales by Manufacturer'!$S37 -> 0
A39: Honda | B39: ='PEV Sales by Manufacturer'!M38 -> 45 | C39: ='PEV Sales by Manufacturer'!N38 -> 1 | D39: =D$28*'PEV Sales by Manufacturer'!$S38 -> 2.3918371 | E39: =E$28*'PEV Sales by Manufacturer'!$S38 -> 3.4838479 | F39: =F$28*'PEV Sales by Manufacturer'!$S38 -> 4.8090744 | G39: =G$28*'PEV Sales by Manufacturer'!$S38 -> 6.1154956 | H39: =H$28*'PEV Sales by Manufacturer'!$S38 -> 7.2117942 | I39: =I$28*'PEV Sales by Manufacturer'!$S38 -> 8.3553454 | J39: =J$28*'PEV Sales by Manufacturer'!$S38 -> 9.5500668 | K39: =K$28*'PEV Sales by Manufacturer'!$S38 -> 10.667783 | ... AF39: =AF$28*'PEV Sales by Manufacturer'!$S38 -> 25.723589
A40: Audi | B40: ='PEV Sales by Manufacturer'!M39 -> 7202 | C40: ='PEV Sales by Manufacturer'!N39 -> 11076 | D40: =D$28*'PEV Sales by Manufacturer'!$S39 -> 26491.988 | E40: =E$28*'PEV Sales by Manufacturer'!$S39 -> 38587.1 | F40: =F$28*'PEV Sales by Manufacturer'!$S39 -> 53265.308 | G40: =G$28*'PEV Sales by Manufacturer'!$S39 -> 67735.229 | H40: =H$28*'PEV Sales by Manufacturer'!$S39 -> 79877.833 | I40: =I$28*'PEV Sales by Manufacturer'!$S39 -> 92543.805 | J40: =J$28*'PEV Sales by Manufacturer'!$S39 -> 105776.54 | K40: =K$28*'PEV Sales by Manufacturer'!$S39 -> 118156.36 | ... AF40: =AF$28*'PEV Sales by Manufacturer'!$S39 -> 284914.47
A41: Hyundai | B41: ='PEV Sales by Manufacturer'!M40 -> 4556 | C41: ='PEV Sales by Manufacturer'!N40 -> 10855 | D41: =D$28*'PEV Sales by Manufacturer'!$S40 -> 25963.392 | E41: =E$28*'PEV Sales by Manufacturer'!$S40 -> 37817.169 | F41: =F$28*'PEV Sales by Manufacturer'!$S40 -> 52202.503 | G41: =G$28*'PEV Sales by Manufacturer'!$S40 -> 66383.705 | H41: =H$28*'PEV Sales by Manufacturer'!$S40 -> 78284.026 | I41: =I$28*'PEV Sales by Manufacturer'!$S40 -> 90697.274 | J41: =J$28*'PEV Sales by Manufacturer'!$S40 -> 103665.98 | K41: =K$28*'PEV Sales by Manufacturer'!$S40 -> 115798.78 | ... AF41: =AF$28*'PEV Sales by Manufacturer'!$S40 -> 279229.56
A42: Kia | B42: ='PEV Sales by Manufacturer'!M41 -> 2848 | C42: ='PEV Sales by Manufacturer'!N41 -> 8717 | D42: =D$28*'PEV Sales by Manufacturer'!$S41 -> 20849.644 | E42: =E$28*'PEV Sales by Manufacturer'!$S41 -> 30368.702 | F42: =F$28*'PEV Sales by Manufacturer'!$S41 -> 41920.702 | G42: =G$28*'PEV Sales by Manufacturer'!$S41 -> 53308.775 | H42: =H$28*'PEV Sales by Manufacturer'!$S41 -> 62865.21 | I42: =I$28*'PEV Sales by Manufacturer'!$S41 -> 72833.545 | J42: =J$28*'PEV Sales by Manufacturer'!$S41 -> 83247.932 | K42: =K$28*'PEV Sales by Manufacturer'!$S41 -> 92991.06 | ... AF42: =AF$28*'PEV Sales by Manufacturer'!$S41 -> 224232.52
A43: Volvo | B43: ='PEV Sales by Manufacturer'!M42 -> 135 | C43: ='PEV Sales by Manufacturer'!N42 -> 9863 | D43: =D$28*'PEV Sales by Manufacturer'!$S42 -> 23590.69 | E43: =E$28*'PEV Sales by Manufacturer'!$S42 -> 34361.192 | F43: =F$28*'PEV Sales by Manufacturer'!$S42 -> 47431.901 | G43: =G$28*'PEV Sales by Manufacturer'!$S42 -> 60317.133 | H43: =H$28*'PEV Sales by Manufacturer'!$S42 -> 71129.926 | I43: =I$28*'PEV Sales by Manufacturer'!$S42 -> 82408.771 | J43: =J$28*'PEV Sales by Manufacturer'!$S42 -> 94192.309 | K43: =K$28*'PEV Sales by Manufacturer'!$S42 -> 105216.34 | ... AF43: =AF$28*'PEV Sales by Manufacturer'!$S42 -> 253711.76
... A53: Mazda | B53: ='PEV Sales by Manufacturer'!M52 -> 0 | C53: ='PEV Sales by Manufacturer'!N52 -> 116 | D53: =D$28*'PEV Sales by Manufacturer'!$S52 -> 277.45311 | E53: =E$28*'PEV Sales by Manufacturer'!$S52 -> 404.12636 | F53: =F$28*'PEV Sales by Manufacturer'!$S52 -> 557.85263 | G53: =G$28*'PEV Sales by Manufacturer'!$S52 -> 709.39749 | H53: =H$28*'PEV Sales by Manufacturer'!$S52 -> 836.56813 | I53: =I$28*'PEV Sales by Manufacturer'!$S52 -> 969.22006 | J53: =J$28*'PEV Sales by Manufacturer'!$S52 -> 1107.8078 | K53: =K$28*'PEV Sales by Manufacturer'!$S52 -> 1237.4628 | ... AF53: =AF$28*'PEV Sales by Manufacturer'!$S52 -> 2983.9363
A55: Projected Annual PHEV Sales by Manufacturer | B55: 2020 | C55: 2021 | D55: 2022 | E55: 2023 | F55: 2024 | G55: 2025 | H55: 2026 | I55: 2027 | J55: 2028 | K55: 2029 | L55: 2030 | M55: 2031 | N55: 2032 | O55: 2033 | P55: 2034 | Q55: 2035 | R55: 2036 | S55: 2037 | T55: 2038 | U55: 2039 | V55: 2040 | W55: 2041 | X55: 2042 | Y55: 2043 | Z55: 2044 | AA55: 2045 | AB55: 2046 | AC55: 2047 | AD55: 2048 | AE55: 2049 | AF55: 2050
A56: Tesla | B56: ='PEV Sales by Manufacturer'!M58 -> 0 | C56: ='PEV Sales by Manufacturer'!N58 -> 0 | D56: =D$29*'PEV Sales by Manufacturer'!$S58 -> 0 | E56: =E$29*'PEV Sales by Manufacturer'!$S58 -> 0 | F56: =F$29*'PEV Sales by Manufacturer'!$S58 -> 0 | G56: =G$29*'PEV Sales by Manufacturer'!$S58 -> 0 | H56: =H$29*'PEV Sales by Manufacturer'!$S58 -> 0 | I56: =I$29*'PEV Sales by Manufacturer'!$S58 -> 0 | J56: =J$29*'PEV Sales by Manufacturer'!$S58 -> 0 | K56: =K$29*'PEV Sales by Manufacturer'!$S58 -> 0 | ... AF56: =AF$29*'PEV Sales by Manufacturer'!$S58 -> 0
A57: GM (Cadillac and Chevrolet) | B57: ='PEV Sales by Manufacturer'!M59 -> 81 | C57: ='PEV Sales by Manufacturer'!N59 -> 16 | D57: =D$29*'PEV Sales by Manufacturer'!$S59 -> 39.890349 | E57: =E$29*'PEV Sales by Manufacturer'!$S59 -> 58.533915 | F57: =F$29*'PEV Sales by Manufacturer'!$S59 -> 81.541544 | G57: =G$29*'PEV Sales by Manufacturer'!$S59 -> 100.6489 | H57: =H$29*'PEV Sales by Manufacturer'!$S59 -> 112.22886 | I57: =I$29*'PEV Sales by Manufacturer'!$S59 -> 118.89062 | J57: =J$29*'PEV Sales by Manufacturer'!$S59 -> 120.43658 | K57: =K$29*'PEV Sales by Manufacturer'!$S59 -> 121.3364 | ... AF57: =AF$29*'PEV Sales by Manufacturer'!$S59 -> 97.095588
A58: Nissan | B58: ='PEV Sales by Manufacturer'!M60 -> 0 | C58: ='PEV Sales by Manufacturer'!N60 -> 0 | D58: =D$29*'PEV Sales by Manufacturer'!$S60 -> 0 | E58: =E$29*'PEV Sales by Manufacturer'!$S60 -> 0 | F58: =F$29*'PEV Sales by Manufacturer'!$S60 -> 0 | G58: =G$29*'PEV Sales by Manufacturer'!$S60 -> 0 | H58: =H$29*'PEV Sales by Manufacturer'!$S60 -> 0 | I58: =I$29*'PEV Sales by Manufacturer'!$S60 -> 0 | J58: =J$29*'PEV Sales by Manufacturer'!$S60 -> 0 | K58: =K$29*'PEV Sales by Manufacturer'!$S60 -> 0 | ... AF58: =AF$29*'PEV Sales by Manufacturer'!$S60 -> 0
A59: Toyota | B59: ='PEV Sales by Manufacturer'!M61 -> 17898 | C59: ='PEV Sales by Manufacturer'!N61 -> 52767 | D59: =D$29*'PEV Sales by Manufacturer'!$S61 -> 131555.88 | E59: =E$29*'PEV Sales by Manufacturer'!$S61 -> 193041.19 | F59: =F$29*'PEV Sales by Manufacturer'!$S61 -> 268918.92 | G59: =G$29*'PEV Sales by Manufacturer'!$S61 -> 331933.77 | H59: =H$29*'PEV Sales by Manufacturer'!$S61 -> 370123.77 | I59: =I$29*'PEV Sales by Manufacturer'!$S61 -> 392093.85 | J59: =J$29*'PEV Sales by Manufacturer'!$S61 -> 397192.32 | K59: =K$29*'PEV Sales by Manufacturer'!$S61 -> 400159.85 | ... AF59: =AF$29*'PEV Sales by Manufacturer'!$S61 -> 320215.18
A60: Ford | B60: ='PEV Sales by Manufacturer'!M62 -> 5565 | C60: ='PEV Sales by Manufacturer'!N62 -> 6013 | D60: =D$29*'PEV Sales by Manufacturer'!$S62 -> 14991.292 | E60: =E$29*'PEV Sales by Manufacturer'!$S62 -> 21997.777 | F60: =F$29*'PEV Sales by Manufacturer'!$S62 -> 30644.332 | G60: =G$29*'PEV Sales by Manufacturer'!$S62 -> 37825.114 | H60: =H$29*'PEV Sales by Manufacturer'!$S62 -> 42177.009 | I60: =I$29*'PEV Sales by Manufacturer'!$S62 -> 44680.583 | J60: =J$29*'PEV Sales by Manufacturer'!$S62 -> 45261.573 | K60: =K$29*'PEV Sales by Manufacturer'!$S62 -> 45599.735 | ... AF60: =AF$29*'PEV Sales by Manufacturer'!$S62 -> 36489.736
A61: BMW N. America | B61: ='PEV Sales by Manufacturer'!M63 -> 7999 | C61: ='PEV Sales by Manufacturer'!N63 -> 19579 | D61: =D$29*'PEV Sales by Manufacturer'!$S63 -> 48813.322 | E61: =E$29*'PEV Sales by Manufacturer'!$S63 -> 71627.221 | F61: =F$29*'PEV Sales by Manufacturer'!$S63 -> 99781.368 | G61: =G$29*'PEV Sales by Manufacturer'!$S63 -> 123162.8 | H61: =H$29*'PEV Sales by Manufacturer'!$S63 -> 137333.05 | I61: =I$29*'PEV Sales by Manufacturer'!$S63 -> 145484.97 | J61: =J$29*'PEV Sales by Manufacturer'!$S63 -> 147376.74 | K61: =K$29*'PEV Sales by Manufacturer'!$S63 -> 148477.83 | ... AF61: =AF$29*'PEV Sales by Manufacturer'!$S63 -> 118814.66
A62: FCA (Chrysler and Fiat) | B62: ='PEV Sales by Manufacturer'!M64 -> 5596 | C62: ='PEV Sales by Manufacturer'!N64 -> 48723 | D62: =D$29*'PEV Sales by Manufacturer'!$S64 -> 121473.59 | E62: =E$29*'PEV Sales by Manufacturer'!$S64 -> 178246.75 | F62: =F$29*'PEV Sales by Manufacturer'!$S64 -> 248309.29 | G62: =G$29*'PEV Sales by Manufacturer'!$S64 -> 306494.76 | H62: =H$29*'PEV Sales by Manufacturer'!$S64 -> 341757.92 | I62: =I$29*'PEV Sales by Manufacturer'!$S64 -> 362044.25 | J62: =J$29*'PEV Sales by Manufacturer'!$S64 -> 366751.97 | K62: =K$29*'PEV Sales by Manufacturer'!$S64 -> 369492.08 | ... AF62: =AF$29*'PEV Sales by Manufacturer'!$S64 -> 295674.27
A63: Honda | B63: ='PEV Sales by Manufacturer'!M65 -> 3939 | C63: ='PEV Sales by Manufacturer'!N65 -> 2314 | D63: =D$29*'PEV Sales by Manufacturer'!$S65 -> 5769.1418 | E63: =E$29*'PEV Sales by Manufacturer'!$S65 -> 8465.4675 | F63: =F$29*'PEV Sales by Manufacturer'!$S65 -> 11792.946 | G63: =G$29*'PEV Sales by Manufacturer'!$S65 -> 14556.347 | H63: =H$29*'PEV Sales by Manufacturer'!$S65 -> 16231.099 | I63: =I$29*'PEV Sales by Manufacturer'!$S65 -> 17194.557 | J63: =J$29*'PEV Sales by Manufacturer'!$S65 -> 17418.141 | K63: =K$29*'PEV Sales by Manufacturer'!$S65 -> 17548.276 | ... AF63: =AF$29*'PEV Sales by Manufacturer'!$S65 -> 14042.449
A64: Audi | B64: ='PEV Sales by Manufacturer'!M66 -> 4468 | C64: ='PEV Sales by Manufacturer'!N66 -> 8943 | D64: =D$29*'PEV Sales by Manufacturer'!$S66 -> 22296.212 | E64: =E$29*'PEV Sales by Manufacturer'!$S66 -> 32716.8 | F64: =F$29*'PEV Sales by Manufacturer'!$S66 -> 45576.627 | G64: =G$29*'PEV Sales by Manufacturer'!$S66 -> 56256.443 | H64: =H$29*'PEV Sales by Manufacturer'!$S66 -> 62728.919 | I64: =I$29*'PEV Sales by Manufacturer'!$S66 -> 66452.429 | J64: =J$29*'PEV Sales by Manufacturer'!$S66 -> 67316.521 | K64: =K$29*'PEV Sales by Manufacturer'!$S66 -> 67819.462 | ... AF64: =AF$29*'PEV Sales by Manufacturer'!$S66 -> 54270.365
A65: Hyundai | B65: ='PEV Sales by Manufacturer'!M67 -> 4237 | C65: ='PEV Sales by Manufacturer'!N67 -> 6158 | D65: =D$29*'PEV Sales by Manufacturer'!$S67 -> 15352.798 | E65: =E$29*'PEV Sales by Manufacturer'!$S67 -> 22528.241 | F65: =F$29*'PEV Sales by Manufacturer'!$S67 -> 31383.302 | G65: =G$29*'PEV Sales by Manufacturer'!$S67 -> 38737.244 | H65: =H$29*'PEV Sales by Manufacturer'!$S67 -> 43194.083 | I65: =I$29*'PEV Sales by Manufacturer'!$S67 -> 45758.029 | J65: =J$29*'PEV Sales by Manufacturer'!$S67 -> 46353.029 | K65: =K$29*'PEV Sales by Manufacturer'!$S67 -> 46699.346 | ... AF65: =AF$29*'PEV Sales by Manufacturer'!$S67 -> 37369.665
A66: Kia | B66: ='PEV Sales by Manufacturer'!M68 -> 2454 | C66: ='PEV Sales by Manufacturer'!N68 -> 5900 | D66: =D$29*'PEV Sales by Manufacturer'!$S68 -> 14709.566 | E66: =E$29*'PEV Sales by Manufacturer'!$S68 -> 21584.381 | F66: =F$29*'PEV Sales by Manufacturer'!$S68 -> 30068.444 | G66: =G$29*'PEV Sales by Manufacturer'!$S68 -> 37114.281 | H66: =H$29*'PEV Sales by Manufacturer'!$S68 -> 41384.392 | I66: =I$29*'PEV Sales by Manufacturer'!$S68 -> 43840.918 | J66: =J$29*'PEV Sales by Manufacturer'!$S68 -> 44410.989 | K66: =K$29*'PEV Sales by Manufacturer'!$S68 -> 44742.796 | ... AF66: =AF$29*'PEV Sales by Manufacturer'!$S68 -> 35803.998
A67: Volvo | B67: ='PEV Sales by Manufacturer'!M69 -> 7106 | C67: ='PEV Sales by Manufacturer'!N69 -> 15606 | D67: =D$29*'PEV Sales by Manufacturer'!$S69 -> 38908.049 | E67: =E$29*'PEV Sales by Manufacturer'!$S69 -> 57092.518 | F67: =F$29*'PEV Sales by Manufacturer'!$S69 -> 79533.584 | G67: =G$29*'PEV Sales by Manufacturer'!$S69 -> 98170.418 | H67: =H$29*'PEV Sales by Manufacturer'!$S69 -> 109465.22 | I67: =I$29*'PEV Sales by Manufacturer'!$S69 -> 115962.94 | J67: =J$29*'PEV Sales by Manufacturer'!$S69 -> 117470.83 | K67: =K$29*'PEV Sales by Manufacturer'!$S69 -> 118348.49 | ... AF67: =AF$29*'PEV Sales by Manufacturer'!$S69 -> 94704.609
... A77: Mazda | B77: ='PEV Sales by Manufacturer'!M79 -> 0 | C77: ='PEV Sales by Manufacturer'!N79 -> 0 | D77: =D$29*'PEV Sales by Manufacturer'!$S79 -> 0 | E77: =E$29*'PEV Sales by Manufacturer'!$S79 -> 0 | F77: =F$29*'PEV Sales by Manufacturer'!$S79 -> 0 | G77: =G$29*'PEV Sales by Manufacturer'!$S79 -> 0 | H77: =H$29*'PEV Sales by Manufacturer'!$S79 -> 0 | I77: =I$29*'PEV Sales by Manufacturer'!$S79 -> 0 | J77: =J$29*'PEV Sales by Manufacturer'!$S79 -> 0 | K77: =K$29*'PEV Sales by Manufacturer'!$S79 -> 0 | ... AF77: =AF$29*'PEV Sales by Manufacturer'!$S79 -> 0
A79: Projected BEV Credit By Manufacturer | C79: 2020 | D79: 2021 | E79: 2022 | F79: 2023 | G79: 2024 | H79: 2025 | I79: 2026 | J79: 2027 | K79: 2028 | L79: 2029 | M79: 2030 | N79: 2031 | O79: 2032 | P79: 2033 | Q79: 2034 | R79: 2035 | S79: 2036 | T79: 2037 | U79: 2038 | V79: 2039 | W79: 2040 | X79: 2041 | Y79: 2042 | Z79: 2043 | AA79: 2044 | AB79: 2045 | AC79: 2046 | AD79: 2047 | AE79: 2048 | AF79: 2049 | AG79: 2050
A80: Tesla | C80: =IF(B3<200000,7500,0) -> 0 | D80: =IF(C3<200000,7500,IF(B3<200000,7500*0.375,0)) -> 0 | E80: =IF(D3<200000,7500,IF(C3<200000,7500*0.375,0)) -> 0 | F80: =IF(E3<200000,7500,IF(D3<200000,7500*0.375,0)) -> 0 | G80: =IF(F3<200000,7500,IF(E3<200000,7500*0.375,0)) -> 0 | H80: =IF(G3<200000,7500,IF(F3<200000,7500*0.375,0)) -> 0 | I80: =IF(H3<200000,7500,IF(G3<200000,7500*0.375,0)) -> 0 | J80: =IF(I3<200000,7500,IF(H3<200000,7500*0.375,0)) -> 0 | K80: =IF(J3<200000,7500,IF(I3<200000,7500*0.375,0)) -> 0 | ... AG80: =IF(AF3<200000,7500,IF(AE3<200000,7500*0.375,0)) -> 0
A81: GM (Cadillac and Chevrolet) | C81: =IF(B4<200000,7500,0) -> 0 | D81: =IF(C4<200000,7500,IF(B4<200000,7500*0.375,0)) -> 0 | E81: =IF(D4<200000,7500,IF(C4<200000,7500*0.375,0)) -> 0 | F81: =IF(E4<200000,7500,IF(D4<200000,7500*0.375,0)) -> 0 | G81: =IF(F4<200000,7500,IF(E4<200000,7500*0.375,0)) -> 0 | H81: =IF(G4<200000,7500,IF(F4<200000,7500*0.375,0)) -> 0 | I81: =IF(H4<200000,7500,IF(G4<200000,7500*0.375,0)) -> 0 | J81: =IF(I4<200000,7500,IF(H4<200000,7500*0.375,0)) -> 0 | K81: =IF(J4<200000,7500,IF(I4<200000,7500*0.375,0)) -> 0 | ... AG81: =IF(AF4<200000,7500,IF(AE4<200000,7500*0.375,0)) -> 0
A82: Nissan | C82: =IF(B5<200000,7500,0) -> 7500 | D82: =IF(C5<200000,7500,IF(B5<200000,7500*0.375,0)) -> 7500 | E82: =IF(D5<200000,7500,IF(C5<200000,7500*0.375,0)) -> 7500 | F82: =IF(E5<200000,7500,IF(D5<200000,7500*0.375,0)) -> 2812.5 | G82: =IF(F5<200000,7500,IF(E5<200000,7500*0.375,0)) -> 0 | H82: =IF(G5<200000,7500,IF(F5<200000,7500*0.375,0)) -> 0 | I82: =IF(H5<200000,7500,IF(G5<200000,7500*0.375,0)) -> 0 | J82: =IF(I5<200000,7500,IF(H5<200000,7500*0.375,0)) -> 0 | K82: =IF(J5<200000,7500,IF(I5<200000,7500*0.375,0)) -> 0 | ... AG82: =IF(AF5<200000,7500,IF(AE5<200000,7500*0.375,0)) -> 0
A83: Toyota | C83: =IF(B6<200000,7500,0) -> 7500 | D83: =IF(C6<200000,7500,IF(B6<200000,7500*0.375,0)) -> 7500 | E83: =IF(D6<200000,7500,IF(C6<200000,7500*0.375,0)) -> 2812.5 | F83: =IF(E6<200000,7500,IF(D6<200000,7500*0.375,0)) -> 0 | G83: =IF(F6<200000,7500,IF(E6<200000,7500*0.375,0)) -> 0 | H83: =IF(G6<200000,7500,IF(F6<200000,7500*0.375,0)) -> 0 | I83: =IF(H6<200000,7500,IF(G6<200000,7500*0.375,0)) -> 0 | J83: =IF(I6<200000,7500,IF(H6<200000,7500*0.375,0)) -> 0 | K83: =IF(J6<200000,7500,IF(I6<200000,7500*0.375,0)) -> 0 | ... AG83: =IF(AF6<200000,7500,IF(AE6<200000,7500*0.375,0)) -> 0
A84: Ford | C84: =IF(B7<200000,7500,0) -> 7500 | D84: =IF(C7<200000,7500,IF(B7<200000,7500*0.375,0)) -> 7500 | E84: =IF(D7<200000,7500,IF(C7<200000,7500*0.375,0)) -> 2812.5 | F84: =IF(E7<200000,7500,IF(D7<200000,7500*0.375,0)) -> 0 | G84: =IF(F7<200000,7500,IF(E7<200000,7500*0.375,0)) -> 0 | H84: =IF(G7<200000,7500,IF(F7<200000,7500*0.375,0)) -> 0 | I84: =IF(H7<200000,7500,IF(G7<200000,7500*0.375,0)) -> 0 | J84: =IF(I7<200000,7500,IF(H7<200000,7500*0.375,0)) -> 0 | K84: =IF(J7<200000,7500,IF(I7<200000,7500*0.375,0)) -> 0 | ... AG84: =IF(AF7<200000,7500,IF(AE7<200000,7500*0.375,0)) -> 0
A85: BMW N. America | C85: =IF(B8<200000,7500,0) -> 7500 | D85: =IF(C8<200000,7500,IF(B8<200000,7500*0.375,0)) -> 7500 | E85: =IF(D8<200000,7500,IF(C8<200000,7500*0.375,0)) -> 7500 | F85: =IF(E8<200000,7500,IF(D8<200000,7500*0.375,0)) -> 2812.5 | G85: =IF(F8<200000,7500,IF(E8<200000,7500*0.375,0)) -> 0 | H85: =IF(G8<200000,7500,IF(F8<200000,7500*0.375,0)) -> 0 | I85: =IF(H8<200000,7500,IF(G8<200000,7500*0.375,0)) -> 0 | J85: =IF(I8<200000,7500,IF(H8<200000,7500*0.375,0)) -> 0 | K85: =IF(J8<200000,7500,IF(I8<200000,7500*0.375,0)) -> 0 | ... AG85: =IF(AF8<200000,7500,IF(AE8<200000,7500*0.375,0)) -> 0
A86: FCA (Chrysler and Fiat) | C86: =IF(B9<200000,7500,0) -> 7500 | D86: =IF(C9<200000,7500,IF(B9<200000,7500*0.375,0)) -> 7500 | E86: =IF(D9<200000,7500,IF(C9<200000,7500*0.375,0)) -> 2812.5 | F86: =IF(E9<200000,7500,IF(D9<200000,7500*0.375,0)) -> 0 | G86: =IF(F9<200000,7500,IF(E9<200000,7500*0.375,0)) -> 0 | H86: =IF(G9<200000,7500,IF(F9<200000,7500*0.375,0)) -> 0 | I86: =IF(H9<200000,7500,IF(G9<200000,7500*0.375,0)) -> 0 | J86: =IF(I9<200000,7500,IF(H9<200000,7500*0.375,0)) -> 0 | K86: =IF(J9<200000,7500,IF(I9<200000,7500*0.375,0)) -> 0 | ... AG86: =IF(AF9<200000,7500,IF(AE9<200000,7500*0.375,0)) -> 0
A87: Honda | C87: =IF(B10<200000,7500,0) -> 7500 | D87: =IF(C10<200000,7500,IF(B10<200000,7500*0.375,0)) -> 7500 | E87: =IF(D10<200000,7500,IF(C10<200000,7500*0.375,0)) -> 7500 | F87: =IF(E10<200000,7500,IF(D10<200000,7500*0.375,0)) -> 7500 | G87: =IF(F10<200000,7500,IF(E10<200000,7500*0.375,0)) -> 7500 | H87: =IF(G10<200000,7500,IF(F10<200000,7500*0.375,0)) -> 7500 | I87: =IF(H10<200000,7500,IF(G10<200000,7500*0.375,0)) -> 7500 | J87: =IF(I10<200000,7500,IF(H10<200000,7500*0.375,0)) -> 7500 | K87: =IF(J10<200000,7500,IF(I10<200000,7500*0.375,0)) -> 7500 | ... AG87: =IF(AF10<200000,7500,IF(AE10<200000,7500*0.375,0)) -> 0
A88: Audi | C88: =IF(B11<200000,7500,0) -> 7500 | D88: =IF(C11<200000,7500,IF(B11<200000,7500*0.375,0)) -> 7500 | E88: =IF(D11<200000,7500,IF(C11<200000,7500*0.375,0)) -> 7500 | F88: =IF(E11<200000,7500,IF(D11<200000,7500*0.375,0)) -> 7500 | G88: =IF(F11<200000,7500,IF(E11<200000,7500*0.375,0)) -> 2812.5 | H88: =IF(G11<200000,7500,IF(F11<200000,7500*0.375,0)) -> 0 | I88: =IF(H11<200000,7500,IF(G11<200000,7500*0.375,0)) -> 0 | J88: =IF(I11<200000,7500,IF(H11<200000,7500*0.375,0)) -> 0 | K88: =IF(J11<200000,7500,IF(I11<200000,7500*0.375,0)) -> 0 | ... AG88: =IF(AF11<200000,7500,IF(AE11<200000,7500*0.375,0)) -> 0
A89: Hyundai | C89: =IF(B12<200000,7500,0) -> 7500 | D89: =IF(C12<200000,7500,IF(B12<200000,7500*0.375,0)) -> 7500 | E89: =IF(D12<200000,7500,IF(C12<200000,7500*0.375,0)) -> 7500 | F89: =IF(E12<200000,7500,IF(D12<200000,7500*0.375,0)) -> 7500 | G89: =IF(F12<200000,7500,IF(E12<200000,7500*0.375,0)) -> 2812.5 | H89: =IF(G12<200000,7500,IF(F12<200000,7500*0.375,0)) -> 0 | I89: =IF(H12<200000,7500,IF(G12<200000,7500*0.375,0)) -> 0 | J89: =IF(I12<200000,7500,IF(H12<200000,7500*0.375,0)) -> 0 | K89: =IF(J12<200000,7500,IF(I12<200000,7500*0.375,0)) -> 0 | ... AG89: =IF(AF12<200000,7500,IF(AE12<200000,7500*0.375,0)) -> 0
A90: Kia | C90: =IF(B13<200000,7500,0) -> 7500 | D90: =IF(C13<200000,7500,IF(B13<200000,7500*0.375,0)) -> 7500 | E90: =IF(D13<200000,7500,IF(C13<200000,7500*0.375,0)) -> 7500 | F90: =IF(E13<200000,7500,IF(D13<200000,7500*0.375,0)) -> 7500 | G90: =IF(F13<200000,7500,IF(E13<200000,7500*0.375,0)) -> 7500 | H90: =IF(G13<200000,7500,IF(F13<200000,7500*0.375,0)) -> 2812.5 | I90: =IF(H13<200000,7500,IF(G13<200000,7500*0.375,0)) -> 0 | J90: =IF(I13<200000,7500,IF(H13<200000,7500*0.375,0)) -> 0 | K90: =IF(J13<200000,7500,IF(I13<200000,7500*0.375,0)) -> 0 | ... AG90: =IF(AF13<200000,7500,IF(AE13<200000,7500*0.375,0)) -> 0
A91: Volvo | C91: =IF(B14<200000,7500,0) -> 7500 | D91: =IF(C14<200000,7500,IF(B14<200000,7500*0.375,0)) -> 7500 | E91: =IF(D14<200000,7500,IF(C14<200000,7500*0.375,0)) -> 7500 | F91: =IF(E14<200000,7500,IF(D14<200000,7500*0.375,0)) -> 7500 | G91: =IF(F14<200000,7500,IF(E14<200000,7500*0.375,0)) -> 2812.5 | H91: =IF(G14<200000,7500,IF(F14<200000,7500*0.375,0)) -> 0 | I91: =IF(H14<200000,7500,IF(G14<200000,7500*0.375,0)) -> 0 | J91: =IF(I14<200000,7500,IF(H14<200000,7500*0.375,0)) -> 0 | K91: =IF(J14<200000,7500,IF(I14<200000,7500*0.375,0)) -> 0 | ... AG91: =IF(AF14<200000,7500,IF(AE14<200000,7500*0.375,0)) -> 0
... A101: Mazda | C101: =IF(B24<200000,7500,0) -> 7500 | D101: =IF(C24<200000,7500,IF(B24<200000,7500*0.375,0)) -> 7500 | E101: =IF(D24<200000,7500,IF(C24<200000,7500*0.375,0)) -> 7500 | F101: =IF(E24<200000,7500,IF(D24<200000,7500*0.375,0)) -> 7500 | G101: =IF(F24<200000,7500,IF(E24<200000,7500*0.375,0)) -> 7500 | H101: =IF(G24<200000,7500,IF(F24<200000,7500*0.375,0)) -> 7500 | I101: =IF(H24<200000,7500,IF(G24<200000,7500*0.375,0)) -> 7500 | J101: =IF(I24<200000,7500,IF(H24<200000,7500*0.375,0)) -> 7500 | K101: =IF(J24<200000,7500,IF(I24<200000,7500*0.375,0)) -> 7500 | ... AG101: =IF(AF24<200000,7500,IF(AE24<200000,7500*0.375,0)) -> 7500
A103: Weighted Average Credit | C103: 2020 | D103: 2021 | E103: 2022 | F103: 2023 | G103: 2024 | H103: 2025 | I103: 2026 | J103: 2027 | K103: 2028 | L103: 2029 | M103: 2030 | N103: 2031 | O103: 2032 | P103: 2033 | Q103: 2034 | R103: 2035 | S103: 2036 | T103: 2037 | U103: 2038 | V103: 2039 | W103: 2040 | X103: 2041 | Y103: 2042 | Z103: 2043 | AA103: 2044 | AB103: 2045 | AC103: 2046 | AD103: 2047 | AE103: 2048 | AF103: 2049 | AG103: 2050
C104: =SUMPRODUCT(C80:C101,B32:B53)/SUM(B32:B53) -> 1066.1677 | D104: =SUMPRODUCT(D80:D101,C32:C53)/SUM(C32:C53) -> 1856.0233 | E104: =SUMPRODUCT(E80:E101,D32:D53)/SUM(D32:D53) -> 1578.301 | F104: =SUMPRODUCT(F80:F101,E32:E53)/SUM(E32:E53) -> 1230.8383 | G104: =SUMPRODUCT(G80:G101,F32:F53)/SUM(F32:F53) -> 626.81537 | H104: =SUMPRODUCT(H80:H101,G32:G53)/SUM(G32:G53) -> 144.46747 | I104: =SUMPRODUCT(I80:I101,H32:H53)/SUM(H32:H53) -> 33.447892 | J104: =SUMPRODUCT(J80:J101,I32:I53)/SUM(I32:I53) -> 33.447892 | ... AG104: =SUMPRODUCT(AG80:AG101,AF32:AF53)/SUM(AF32:AF53) -> 9.0924722

Sheet Baseline Calculations - HK
D1: Projected Cumulative Sales
B2: 2020 | C2: 2021 | D2: 2022 | E2: 2023 | F2: 2024 | G2: 2025 | H2: 2026 | I2: 2027 | J2: 2028 | K2: 2029 | L2: 2030 | M2: 2031 | N2: 2032 | O2: 2033 | P2: 2034 | Q2: 2035 | R2: 2036 | S2: 2037 | T2: 2038 | U2: 2039 | V2: 2040 | W2: 2041 | X2: 2042 | Y2: 2043 | Z2: 2044 | AA2: 2045 | AB2: 2046 | AC2: 2047 | AD2: 2048 | AE2: 2049 | AF2: 2050
A3: Tesla | B3: =SUM('PEV Sales by Manufacturer'!D4:M4) -> 687269 | C3: =SUM('PEV Sales by Manufacturer'!D4:N4) -> 1008187 | D3: =C3+D32+D56 -> 1775770.6 | E3: =D3+E32+E56 -> 2893800.1 | F3: =E3+F32+F56 -> 4437118.6 | G3: =F3+G32+G56 -> 6399691.3 | H3: =G3+H32+H56 -> 8714085.8 | I3: =H3+I32+I56 -> 11395467 | J3: =I3+J32+J56 -> 14460255 | K3: =J3+K32+K56 -> 17883738 | ... AF3: =AE3+AF32+AF56 -> 1.4609994e+08
A4: GM (Cadillac and Chevrolet) | B4: =SUM('PEV Sales by Manufacturer'!D5:M5) -> 246675 | C4: =SUM('PEV Sales by Manufacturer'!D5:N5) -> 271520 | D4: =C4+D33+D57 -> 330946.81 | E4: =D4+E33+E57 -> 417505.81 | F4: =E4+F33+F57 -> 536991.86 | G4: =F4+G33+G57 -> 688934.15 | H4: =G4+H33+H57 -> 868108.02 | I4: =H4+I33+I57 -> 1075681.8 | J4: =I4+J33+J57 -> 1312920.8 | K4: =J4+K33+K57 -> 1577912.5 | ... AF4: =AE4+AF33+AF57 -> 11500099
A5: Nissan | B5: =SUM('PEV Sales by Manufacturer'!D6:M6) -> 151452 | C5: =SUM('PEV Sales by Manufacturer'!D6:N6) -> 165691 | D5: =C5+D34+D58 -> 199748.37 | E5: =D5+E34+E58 -> 249354.88 | F5: =E5+F34+F58 -> 317831.29 | G5: =F5+G34+G58 -> 404909.83 | H5: =G5+H34+H58 -> 507598.57 | I5: =H5+I34+I58 -> 626570.33 | J5: =I5+J34+J58 -> 762553.73 | K5: =J5+K34+K58 -> 914452.29 | ... AF5: =AE5+AF34+AF58 -> 6603352.5
A6: Toyota | B6: =SUM('PEV Sales by Manufacturer'!D7:M7) -> 135451 | C6: =SUM('PEV Sales by Manufacturer'!D7:N7) -> 188218 | D6: =C6+D35+D59 -> 319773.88 | E6: =D6+E35+E59 -> 512815.07 | F6: =E6+F35+F59 -> 781733.99 | G6: =F6+G35+G59 -> 1113667.8 | H6: =G6+H35+H59 -> 1483791.5 | I6: =H6+I35+I59 -> 1875885.4 | J6: =I6+J35+J59 -> 2273077.7 | K6: =J6+K35+K59 -> 2673237.5 | ... AF6: =AE6+AF35+AF59 -> 10157425
A7: Ford | B7: =SUM('PEV Sales by Manufacturer'!D8:M8) -> 126312 | C7: =SUM('PEV Sales by Manufacturer'!D8:N8) -> 159546 | D7: =C7+D36+D60 -> 239645.49 | E7: =D7+E36+E60 -> 356477.09 | F7: =E7+F36+F60 -> 518029.24 | G7: =F7+G36+G60 -> 722324.26 | H7: =G7+H36+H60 -> 960813.52 | I7: =H7+I36+I60 -> 1232935 | J7: =I7+J36+J60 -> 1538158.9 | K7: =J7+K36+K60 -> 1874146.3 | ... AF7: =AE7+AF36+AF60 -> 13602590
A8: BMW N. America | B8: =SUM('PEV Sales by Manufacturer'!D9:M9) -> 109611 | C8: =SUM('PEV Sales by Manufacturer'!D9:N9) -> 132675 | D8: =C8+D37+D61 -> 189823.87 | E8: =D8+E37+E61 -> 273592.3 | F8: =E8+F37+F61 -> 390133.3 | G8: =F8+G37+G61 -> 534608.6 | H8: =G8+H37+H61 -> 697074.75 | I8: =H8+I37+I61 -> 871678.1 | J8: =I8+J37+J61 -> 1052336.8 | K8: =J8+K37+K61 -> 1237991.9 | ... AF8: =AE8+AF37+AF61 -> 5407332.1
A9: FCA (Chrysler and Fiat) | B9: =SUM('PEV Sales by Manufacturer'!D10:M10) -> 37707 | C9: =SUM('PEV Sales by Manufacturer'!D10:N10) -> 86430 | D9: =C9+D38+D62 -> 207903.59 | E9: =D9+E38+E62 -> 386150.34 | F9: =E9+F38+F62 -> 634459.63 | G9: =F9+G38+G62 -> 940954.39 | H9: =G9+H38+H62 -> 1282712.3 | I9: =H9+I38+I62 -> 1644756.6 | J9: =I9+J38+J62 -> 2011508.5 | K9: =J9+K38+K62 -> 2381000.6 | ... AF9: =AE9+AF38+AF62 -> 9291608.6
A10: Honda | B10: =SUM('PEV Sales by Manufacturer'!D11:M11) -> 39002 | C10: =SUM('PEV Sales by Manufacturer'!D11:N11) -> 41317 | D10: =C10+D39+D63 -> 47088.534 | E10: =D10+E39+E63 -> 55557.485 | F10: =E10+F39+F63 -> 67355.24 | G10: =F10+G39+G63 -> 81917.702 | H10: =G10+H39+H63 -> 98156.013 | I10: =H10+I39+I63 -> 115358.92 | J10: =I10+J39+J63 -> 132786.62 | K10: =J10+K39+K63 -> 150345.56 | ... AF10: =AE10+AF39+AF63 -> 478950.39
A11: Audi | B11: =SUM('PEV Sales by Manufacturer'!D12:M12) -> 26628 | C11: =SUM('PEV Sales by Manufacturer'!D12:N12) -> 46647 | D11: =C11+D40+D64 -> 95435.2 | E11: =D11+E40+E64 -> 166739.1 | F11: =E11+F40+F64 -> 265581.04 | G11: =F11+G40+G64 -> 389572.71 | H11: =G11+H40+H64 -> 532179.46 | I11: =H11+I40+I64 -> 691175.69 | J11: =I11+J40+J64 -> 864268.75 | K11: =J11+K40+K64 -> 1050244.6 | ... AF11: =AE11+AF40+AF64 -> 6743860
A12: Hyundai | B12: =SUM('PEV Sales by Manufacturer'!D13:M13) -> 25223 | C12: =SUM('PEV Sales by Manufacturer'!D13:N13) -> 42236 | D12: =C12+D41+D65 -> 83552.19 | E12: =D12+E41+E65 -> 143897.6 | F12: =E12+F41+F65 -> 227483.4 | G12: =F12+G41+G65 -> 332604.35 | H12: =G12+H41+H65 -> 454082.46 | I12: =H12+I41+I65 -> 590537.77 | J12: =I12+J41+J65 -> 740556.77 | K12: =J12+K41+K65 -> 903054.89 | ... AF12: =AE12+AF41+AF65 -> 6113364.9
A13: Kia | B13: =SUM('PEV Sales by Manufacturer'!D14:M14) -> 24512 | C13: =SUM('PEV Sales by Manufacturer'!D14:N14) -> 39129 | D13: =C13+D42+D66 -> 74688.211 | E13: =D13+E42+E66 -> 126641.29 | F13: =E13+F42+F66 -> 198630.44 | G13: =F13+G42+G66 -> 289053.5 | H13: =G13+H42+H66 -> 393303.1 | I13: =H13+I42+I66 -> 509977.56 | J13: =I13+J42+J66 -> 637636.48 | K13: =J13+K42+K66 -> 775370.34 | ... AF13: =AE13+AF42+AF66 -> 5094893
A14: Volvo | B14: =SUM('PEV Sales by Manufacturer'!D15:M15) -> 19669 | C14: =SUM('PEV Sales by Manufacturer'!D15:N15) -> 45138 | D14: =C14+D43+D67 -> 107636.74 | E14: =D14+E43+E67 -> 199090.45 | F14: =E14+F43+F67 -> 326055.93 | G14: =F14+G43+G67 -> 484543.48 | H14: =G14+H43+H67 -> 665138.64 | I14: =H14+I43+I67 -> 863510.35 | J14: =I14+J43+J67 -> 1075173.5 | K14: =J14+K43+K67 -> 1298738.3 | ... AF14: =AE14+AF43+AF67 -> 7452768.6
... A24: Mazda | B24: =SUM('PEV Sales by Manufacturer'!D25:M25) -> 0 | C24: =SUM('PEV Sales by Manufacturer'!D25:N25) -> 116 | D24: =C24+D53+D77 -> 393.45311 | E24: =D24+E53+E77 -> 797.57947 | F24: =E24+F53+F77 -> 1355.4321 | G24: =F24+G53+G77 -> 2064.8296 | H24: =G24+H53+H77 -> 2901.3977 | I24: =H24+I53+I77 -> 3870.6178 | J24: =I24+J53+J77 -> 4978.4255 | K24: =J24+K53+K77 -> 6215.8883 | ... AF24: =AE24+AF53+AF77 -> 52561.308
A26: BAU Projected Sales in EPS
A27: Time (Year) | B27: 2020 | C27: 2021 | D27: 2022 | E27: 2023 | F27: 2024 | G27: 2025 | H27: 2026 | I27: 2027 | J27: 2028 | K27: 2029 | L27: 2030 | M27: 2031 | N27: 2032 | O27: 2033 | P27: 2034 | Q27: 2035 | R27: 2036 | S27: 2037 | T27: 2038 | U27: 2039 | V27: 2040 | W27: 2041 | X27: 2042 | Y27: 2043 | Z27: 2044 | AA27: 2045 | AB27: 2046 | AC27: 2047 | AD27: 2048 | AE27: 2049 | AF27: 2050
A28: New Vehicles[LDVs,passenger,battery electric vehicle] : MostRecentRun | B28: 349182 | C28: 603744 | D28: 1098920 | E28: 1600640 | F28: 2209510 | G28: 2809740 | H28: 3313430 | I28: 3838830 | J28: 4387740 | K28: 4901270 | L28: 5460140 | M28: 5896040 | N28: 6271520 | O28: 6625100 | P28: 6942390 | Q28: 7274900 | R28: 7567320 | S28: 7866920 | T28: 8176700 | U28: 8461000 | V28: 8757100 | W28: 9060000 | X28: 9346980 | Y28: 9657430 | Z28: 9970180 | AA28: 10265600 | AB28: 10577800 | AC28: 10885700 | AD28: 11185100 | AE28: 11495700 | AF28: 11818600
A29: New Vehicles[LDVs,passenger,plugin hybrid vehicle] : MostRecentRun | B29: 86889 | C29: 248313 | D29: 434007 | E29: 636849 | F29: 887172 | G29: 1095060 | H29: 1221050 | I29: 1293530 | J29: 1310350 | K29: 1320140 | L29: 1310940 | M29: 1306520 | N29: 1289590 | O29: 1270880 | P29: 1252620 | Q29: 1235240 | R29: 1219780 | S29: 1204400 | T29: 1191940 | U29: 1177850 | V29: 1166230 | W29: 1155260 | X29: 1143250 | Y29: 1133420 | Z29: 1123340 | AA29: 1112470 | AB29: 1102060 | AC29: 1091130 | AD29: 1079340 | AE29: 1067910 | AF29: 1056400
A31: Projected Annual BEV Sales by Manufacturer | B31: 2020 | C31: 2021 | D31: 2022 | E31: 2023 | F31: 2024 | G31: 2025 | H31: 2026 | I31: 2027 | J31: 2028 | K31: 2029 | L31: 2030 | M31: 2031 | N31: 2032 | O31: 2033 | P31: 2034 | Q31: 2035 | R31: 2036 | S31: 2037 | T31: 2038 | U31: 2039 | V31: 2040 | W31: 2041 | X31: 2042 | Y31: 2043 | Z31: 2044 | AA31: 2045 | AB31: 2046 | AC31: 2047 | AD31: 2048 | AE31: 2049 | AF31: 2050
A32: Tesla | B32: ='PEV Sales by Manufacturer'!M31 -> 183829 | C32: ='PEV Sales by Manufacturer'!N31 -> 320918 | D32: =D$28*'PEV Sales by Manufacturer'!$S31 -> 767583.59 | E32: =E$28*'PEV Sales by Manufacturer'!$S31 -> 1118029.5 | F32: =F$28*'PEV Sales by Manufacturer'!$S31 -> 1543318.5 | G32: =G$28*'PEV Sales by Manufacturer'!$S31 -> 1962572.6 | H32: =H$28*'PEV Sales by Manufacturer'!$S31 -> 2314394.6 | I32: =I$28*'PEV Sales by Manufacturer'!$S31 -> 2681380.7 | J32: =J$28*'PEV Sales by Manufacturer'!$S31 -> 3064788.3 | K32: =K$28*'PEV Sales by Manufacturer'!$S31 -> 3423483.4 | ... AF32: =AF$28*'PEV Sales by Manufacturer'!$S31 -> 8255162.7
A33: GM (Cadillac and Chevrolet) | B33: ='PEV Sales by Manufacturer'!M32 -> 20754 | C33: ='PEV Sales by Manufacturer'!N32 -> 24829 | D33: =D$28*'PEV Sales by Manufacturer'!$S32 -> 59386.924 | E33: =E$28*'PEV Sales by Manufacturer'!$S32 -> 86500.46 | F33: =F$28*'PEV Sales by Manufacturer'!$S32 -> 119404.51 | G33: =G$28*'PEV Sales by Manufacturer'!$S32 -> 151841.64 | H33: =H$28*'PEV Sales by Manufacturer'!$S32 -> 179061.64 | I33: =I$28*'PEV Sales by Manufacturer'!$S32 -> 207454.87 | J33: =J$28*'PEV Sales by Manufacturer'!$S32 -> 237118.61 | K33: =K$28*'PEV Sales by Manufacturer'!$S32 -> 264870.37 | ... AF33: =AF$28*'PEV Sales by Manufacturer'!$S32 -> 638690.99
A34: Nissan | B34: ='PEV Sales by Manufacturer'!M33 -> 9564 | C34: ='PEV Sales by Manufacturer'!N33 -> 14239 | D34: =D$28*'PEV Sales by Manufacturer'!$S33 -> 34057.369 | E34: =E$28*'PEV Sales by Manufacturer'!$S33 -> 49606.511 | F34: =F$28*'PEV Sales by Manufacturer'!$S33 -> 68476.41 | G34: =G$28*'PEV Sales by Manufacturer'!$S33 -> 87078.542 | H34: =H$28*'PEV Sales by Manufacturer'!$S33 -> 102688.74 | I34: =I$28*'PEV Sales by Manufacturer'!$S33 -> 118971.76 | J34: =J$28*'PEV Sales by Manufacturer'!$S33 -> 135983.4 | K34: =K$28*'PEV Sales by Manufacturer'!$S33 -> 151898.56 | ... AF34: =AF$28*'PEV Sales by Manufacturer'!$S33 -> 366278.18
A35: Toyota | B35: ='PEV Sales by Manufacturer'!M34 -> 0 | C35: ='PEV Sales by Manufacturer'!N34 -> 0 | D35: =D$28*'PEV Sales by Manufacturer'!$S34 -> 0 | E35: =E$28*'PEV Sales by Manufacturer'!$S34 -> 0 | F35: =F$28*'PEV Sales by Manufacturer'!$S34 -> 0 | G35: =G$28*'PEV Sales by Manufacturer'!$S34 -> 0 | H35: =H$28*'PEV Sales by Manufacturer'!$S34 -> 0 | I35: =I$28*'PEV Sales by Manufacturer'!$S34 -> 0 | J35: =J$28*'PEV Sales by Manufacturer'!$S34 -> 0 | K35: =K$28*'PEV Sales by Manufacturer'!$S34 -> 0 | ... AF35: =AF$28*'PEV Sales by Manufacturer'!$S34 -> 0
A36: Ford | B36: ='PEV Sales by Manufacturer'!M35 -> 3 | C36: ='PEV Sales by Manufacturer'!N35 -> 27221 | D36: =D$28*'PEV Sales by Manufacturer'!$S35 -> 65108.198 | E36: =E$28*'PEV Sales by Manufacturer'!$S35 -> 94833.825 | F36: =F$28*'PEV Sales by Manufacturer'!$S35 -> 130907.81 | G36: =G$28*'PEV Sales by Manufacturer'!$S35 -> 166469.91 | H36: =H$28*'PEV Sales by Manufacturer'!$S35 -> 196312.25 | I36: =I$28*'PEV Sales by Manufacturer'!$S35 -> 227440.86 | J36: =J$28*'PEV Sales by Manufacturer'!$S35 -> 259962.37 | K36: =K$28*'PEV Sales by Manufacturer'!$S35 -> 290387.71 | ... AF36: =AF$28*'PEV Sales by Manufacturer'!$S35 -> 700221.81
A37: BMW N. America | B37: ='PEV Sales by Manufacturer'!M36 -> 2640 | C37: ='PEV Sales by Manufacturer'!N36 -> 3485 | D37: =D$28*'PEV Sales by Manufacturer'!$S36 -> 8335.5524 | E37: =E$28*'PEV Sales by Manufacturer'!$S36 -> 12141.21 | F37: =F$28*'PEV Sales by Manufacturer'!$S36 -> 16759.624 | G37: =G$28*'PEV Sales by Manufacturer'!$S36 -> 21312.502 | H37: =H$28*'PEV Sales by Manufacturer'!$S36 -> 25133.103 | I37: =I$28*'PEV Sales by Manufacturer'!$S36 -> 29118.379 | J37: =J$28*'PEV Sales by Manufacturer'!$S36 -> 33281.983 | K37: =K$28*'PEV Sales by Manufacturer'!$S36 -> 37177.222 | ... AF37: =AF$28*'PEV Sales by Manufacturer'!$S36 -> 89646.707
A38: FCA (Chrysler and Fiat) | B38: ='PEV Sales by Manufacturer'!M37 -> 70 | C38: ='PEV Sales by Manufacturer'!N37 -> 0 | D38: =D$28*'PEV Sales by Manufacturer'!$S37 -> 0 | E38: =E$28*'PEV Sales by Manufacturer'!$S37 -> 0 | F38: =F$28*'PEV Sales by Manufacturer'!$S37 -> 0 | G38: =G$28*'PEV Sales by Manufacturer'!$S37 -> 0 | H38: =H$28*'PEV Sales by Manufacturer'!$S37 -> 0 | I38: =I$28*'PEV Sales by Manufacturer'!$S37 -> 0 | J38: =J$28*'PEV Sales by Manufacturer'!$S37 -> 0 | K38: =K$28*'PEV Sales by Manufacturer'!$S37 -> 0 | ... AF38: =AF$28*'PEV Sales by Manufacturer'!$S37 -> 0
A39: Honda | B39: ='PEV Sales by Manufacturer'!M38 -> 45 | C39: ='PEV Sales by Manufacturer'!N38 -> 1 | D39: =D$28*'PEV Sales by Manufacturer'!$S38 -> 2.3918371 | E39: =E$28*'PEV Sales by Manufacturer'!$S38 -> 3.4838479 | F39: =F$28*'PEV Sales by Manufacturer'!$S38 -> 4.8090744 | G39: =G$28*'PEV Sales by Manufacturer'!$S38 -> 6.1154956 | H39: =H$28*'PEV Sales by Manufacturer'!$S38 -> 7.2117942 | I39: =I$28*'PEV Sales by Manufacturer'!$S38 -> 8.3553454 | J39: =J$28*'PEV Sales by Manufacturer'!$S38 -> 9.5500668 | K39: =K$28*'PEV Sales by Manufacturer'!$S38 -> 10.667783 | ... AF39: =AF$28*'PEV Sales by Manufacturer'!$S38 -> 25.723589
A40: Audi | B40: ='PEV Sales by Manufacturer'!M39 -> 7202 | C40: ='PEV Sales by Manufacturer'!N39 -> 11076 | D40: =D$28*'PEV Sales by Manufacturer'!$S39 -> 26491.988 | E40: =E$28*'PEV Sales by Manufacturer'!$S39 -> 38587.1 | F40: =F$28*'PEV Sales by Manufacturer'!$S39 -> 53265.308 | G40: =G$28*'PEV Sales by Manufacturer'!$S39 -> 67735.229 | H40: =H$28*'PEV Sales by Manufacturer'!$S39 -> 79877.833 | I40: =I$28*'PEV Sales by Manufacturer'!$S39 -> 92543.805 | J40: =J$28*'PEV Sales by Manufacturer'!$S39 -> 105776.54 | K40: =K$28*'PEV Sales by Manufacturer'!$S39 -> 118156.36 | ... AF40: =AF$28*'PEV Sales by Manufacturer'!$S39 -> 284914.47
A41: Hyundai | B41: ='PEV Sales by Manufacturer'!M40 -> 4556 | C41: ='PEV Sales by Manufacturer'!N40 -> 10855 | D41: =D$28*'PEV Sales by Manufacturer'!$S40 -> 25963.392 | E41: =E$28*'PEV Sales by Manufacturer'!$S40 -> 37817.169 | F41: =F$28*'PEV Sales by Manufacturer'!$S40 -> 52202.503 | G41: =G$28*'PEV Sales by Manufacturer'!$S40 -> 66383.705 | H41: =H$28*'PEV Sales by Manufacturer'!$S40 -> 78284.026 | I41: =I$28*'PEV Sales by Manufacturer'!$S40 -> 90697.274 | J41: =J$28*'PEV Sales by Manufacturer'!$S40 -> 103665.98 | K41: =K$28*'PEV Sales by Manufacturer'!$S40 -> 115798.78 | ... AF41: =AF$28*'PEV Sales by Manufacturer'!$S40 -> 279229.56
A42: Kia | B42: ='PEV Sales by Manufacturer'!M41 -> 2848 | C42: ='PEV Sales by Manufacturer'!N41 -> 8717 | D42: =D$28*'PEV Sales by Manufacturer'!$S41 -> 20849.644 | E42: =E$28*'PEV Sales by Manufacturer'!$S41 -> 30368.702 | F42: =F$28*'PEV Sales by Manufacturer'!$S41 -> 41920.702 | G42: =G$28*'PEV Sales by Manufacturer'!$S41 -> 53308.775 | H42: =H$28*'PEV Sales by Manufacturer'!$S41 -> 62865.21 | I42: =I$28*'PEV Sales by Manufacturer'!$S41 -> 72833.545 | J42: =J$28*'PEV Sales by Manufacturer'!$S41 -> 83247.932 | K42: =K$28*'PEV Sales by Manufacturer'!$S41 -> 92991.06 | ... AF42: =AF$28*'PEV Sales by Manufacturer'!$S41 -> 224232.52
A43: Volvo | B43: ='PEV Sales by Manufacturer'!M42 -> 135 | C43: ='PEV Sales by Manufacturer'!N42 -> 9863 | D43: =D$28*'PEV Sales by Manufacturer'!$S42 -> 23590.69 | E43: =E$28*'PEV Sales by Manufacturer'!$S42 -> 34361.192 | F43: =F$28*'PEV Sales by Manufacturer'!$S42 -> 47431.901 | G43: =G$28*'PEV Sales by Manufacturer'!$S42 -> 60317.133 | H43: =H$28*'PEV Sales by Manufacturer'!$S42 -> 71129.926 | I43: =I$28*'PEV Sales by Manufacturer'!$S42 -> 82408.771 | J43: =J$28*'PEV Sales by Manufacturer'!$S42 -> 94192.309 | K43: =K$28*'PEV Sales by Manufacturer'!$S42 -> 105216.34 | ... AF43: =AF$28*'PEV Sales by Manufacturer'!$S42 -> 253711.76
... A53: Mazda | B53: ='PEV Sales by Manufacturer'!M52 -> 0 | C53: ='PEV Sales by Manufacturer'!N52 -> 116 | D53: =D$28*'PEV Sales by Manufacturer'!$S52 -> 277.45311 | E53: =E$28*'PEV Sales by Manufacturer'!$S52 -> 404.12636 | F53: =F$28*'PEV Sales by Manufacturer'!$S52 -> 557.85263 | G53: =G$28*'PEV Sales by Manufacturer'!$S52 -> 709.39749 | H53: =H$28*'PEV Sales by Manufacturer'!$S52 -> 836.56813 | I53: =I$28*'PEV Sales by Manufacturer'!$S52 -> 969.22006 | J53: =J$28*'PEV Sales by Manufacturer'!$S52 -> 1107.8078 | K53: =K$28*'PEV Sales by Manufacturer'!$S52 -> 1237.4628 | ... AF53: =AF$28*'PEV Sales by Manufacturer'!$S52 -> 2983.9363
A55: Projected Annual PHEV Sales by Manufacturer | B55: 2020 | C55: 2021 | D55: 2022 | E55: 2023 | F55: 2024 | G55: 2025 | H55: 2026 | I55: 2027 | J55: 2028 | K55: 2029 | L55: 2030 | M55: 2031 | N55: 2032 | O55: 2033 | P55: 2034 | Q55: 2035 | R55: 2036 | S55: 2037 | T55: 2038 | U55: 2039 | V55: 2040 | W55: 2041 | X55: 2042 | Y55: 2043 | Z55: 2044 | AA55: 2045 | AB55: 2046 | AC55: 2047 | AD55: 2048 | AE55: 2049 | AF55: 2050
A56: Tesla | B56: ='PEV Sales by Manufacturer'!M58 -> 0 | C56: ='PEV Sales by Manufacturer'!N58 -> 0 | D56: =D$29*'PEV Sales by Manufacturer'!$S58 -> 0 | E56: =E$29*'PEV Sales by Manufacturer'!$S58 -> 0 | F56: =F$29*'PEV Sales by Manufacturer'!$S58 -> 0 | G56: =G$29*'PEV Sales by Manufacturer'!$S58 -> 0 | H56: =H$29*'PEV Sales by Manufacturer'!$S58 -> 0 | I56: =I$29*'PEV Sales by Manufacturer'!$S58 -> 0 | J56: =J$29*'PEV Sales by Manufacturer'!$S58 -> 0 | K56: =K$29*'PEV Sales by Manufacturer'!$S58 -> 0 | ... AF56: =AF$29*'PEV Sales by Manufacturer'!$S58 -> 0
A57: GM (Cadillac and Chevrolet) | B57: ='PEV Sales by Manufacturer'!M59 -> 81 | C57: ='PEV Sales by Manufacturer'!N59 -> 16 | D57: =D$29*'PEV Sales by Manufacturer'!$S59 -> 39.890349 | E57: =E$29*'PEV Sales by Manufacturer'!$S59 -> 58.533915 | F57: =F$29*'PEV Sales by Manufacturer'!$S59 -> 81.541544 | G57: =G$29*'PEV Sales by Manufacturer'!$S59 -> 100.6489 | H57: =H$29*'PEV Sales by Manufacturer'!$S59 -> 112.22886 | I57: =I$29*'PEV Sales by Manufacturer'!$S59 -> 118.89062 | J57: =J$29*'PEV Sales by Manufacturer'!$S59 -> 120.43658 | K57: =K$29*'PEV Sales by Manufacturer'!$S59 -> 121.3364 | ... AF57: =AF$29*'PEV Sales by Manufacturer'!$S59 -> 97.095588
A58: Nissan | B58: ='PEV Sales by Manufacturer'!M60 -> 0 | C58: ='PEV Sales by Manufacturer'!N60 -> 0 | D58: =D$29*'PEV Sales by Manufacturer'!$S60 -> 0 | E58: =E$29*'PEV Sales by Manufacturer'!$S60 -> 0 | F58: =F$29*'PEV Sales by Manufacturer'!$S60 -> 0 | G58: =G$29*'PEV Sales by Manufacturer'!$S60 -> 0 | H58: =H$29*'PEV Sales by Manufacturer'!$S60 -> 0 | I58: =I$29*'PEV Sales by Manufacturer'!$S60 -> 0 | J58: =J$29*'PEV Sales by Manufacturer'!$S60 -> 0 | K58: =K$29*'PEV Sales by Manufacturer'!$S60 -> 0 | ... AF58: =AF$29*'PEV Sales by Manufacturer'!$S60 -> 0
A59: Toyota | B59: ='PEV Sales by Manufacturer'!M61 -> 17898 | C59: ='PEV Sales by Manufacturer'!N61 -> 52767 | D59: =D$29*'PEV Sales by Manufacturer'!$S61 -> 131555.88 | E59: =E$29*'PEV Sales by Manufacturer'!$S61 -> 193041.19 | F59: =F$29*'PEV Sales by Manufacturer'!$S61 -> 268918.92 | G59: =G$29*'PEV Sales by Manufacturer'!$S61 -> 331933.77 | H59: =H$29*'PEV Sales by Manufacturer'!$S61 -> 370123.77 | I59: =I$29*'PEV Sales by Manufacturer'!$S61 -> 392093.85 | J59: =J$29*'PEV Sales by Manufacturer'!$S61 -> 397192.32 | K59: =K$29*'PEV Sales by Manufacturer'!$S61 -> 400159.85 | ... AF59: =AF$29*'PEV Sales by Manufacturer'!$S61 -> 320215.18
A60: Ford | B60: ='PEV Sales by Manufacturer'!M62 -> 5565 | C60: ='PEV Sales by Manufacturer'!N62 -> 6013 | D60: =D$29*'PEV Sales by Manufacturer'!$S62 -> 14991.292 | E60: =E$29*'PEV Sales by Manufacturer'!$S62 -> 21997.777 | F60: =F$29*'PEV Sales by Manufacturer'!$S62 -> 30644.332 | G60: =G$29*'PEV Sales by Manufacturer'!$S62 -> 37825.114 | H60: =H$29*'PEV Sales by Manufacturer'!$S62 -> 42177.009 | I60: =I$29*'PEV Sales by Manufacturer'!$S62 -> 44680.583 | J60: =J$29*'PEV Sales by Manufacturer'!$S62 -> 45261.573 | K60: =K$29*'PEV Sales by Manufacturer'!$S62 -> 45599.735 | ... AF60: =AF$29*'PEV Sales by Manufacturer'!$S62 -> 36489.736
A61: BMW N. America | B61: ='PEV Sales by Manufacturer'!M63 -> 7999 | C61: ='PEV Sales by Manufacturer'!N63 -> 19579 | D61: =D$29*'PEV Sales by Manufacturer'!$S63 -> 48813.322 | E61: =E$29*'PEV Sales by Manufacturer'!$S63 -> 71627.221 | F61: =F$29*'PEV Sales by Manufacturer'!$S63 -> 99781.368 | G61: =G$29*'PEV Sales by Manufacturer'!$S63 -> 123162.8 | H61: =H$29*'PEV Sales by Manufacturer'!$S63 -> 137333.05 | I61: =I$29*'PEV Sales by Manufacturer'!$S63 -> 145484.97 | J61: =J$29*'PEV Sales by Manufacturer'!$S63 -> 147376.74 | K61: =K$29*'PEV Sales by Manufacturer'!$S63 -> 148477.83 | ... AF61: =AF$29*'PEV Sales by Manufacturer'!$S63 -> 118814.66
A62: FCA (Chrysler and Fiat) | B62: ='PEV Sales by Manufacturer'!M64 -> 5596 | C62: ='PEV Sales by Manufacturer'!N64 -> 48723 | D62: =D$29*'PEV Sales by Manufacturer'!$S64 -> 121473.59 | E62: =E$29*'PEV Sales by Manufacturer'!$S64 -> 178246.75 | F62: =F$29*'PEV Sales by Manufacturer'!$S64 -> 248309.29 | G62: =G$29*'PEV Sales by Manufacturer'!$S64 -> 306494.76 | H62: =H$29*'PEV Sales by Manufacturer'!$S64 -> 341757.92 | I62: =I$29*'PEV Sales by Manufacturer'!$S64 -> 362044.25 | J62: =J$29*'PEV Sales by Manufacturer'!$S64 -> 366751.97 | K62: =K$29*'PEV Sales by Manufacturer'!$S64 -> 369492.08 | ... AF62: =AF$29*'PEV Sales by Manufacturer'!$S64 -> 295674.27
A63: Honda | B63: ='PEV Sales by Manufacturer'!M65 -> 3939 | C63: ='PEV Sales by Manufacturer'!N65 -> 2314 | D63: =D$29*'PEV Sales by Manufacturer'!$S65 -> 5769.1418 | E63: =E$29*'PEV Sales by Manufacturer'!$S65 -> 8465.4675 | F63: =F$29*'PEV Sales by Manufacturer'!$S65 -> 11792.946 | G63: =G$29*'PEV Sales by Manufacturer'!$S65 -> 14556.347 | H63: =H$29*'PEV Sales by Manufacturer'!$S65 -> 16231.099 | I63: =I$29*'PEV Sales by Manufacturer'!$S65 -> 17194.557 | J63: =J$29*'PEV Sales by Manufacturer'!$S65 -> 17418.141 | K63: =K$29*'PEV Sales by Manufacturer'!$S65 -> 17548.276 | ... AF63: =AF$29*'PEV Sales by Manufacturer'!$S65 -> 14042.449
A64: Audi | B64: ='PEV Sales by Manufacturer'!M66 -> 4468 | C64: ='PEV Sales by Manufacturer'!N66 -> 8943 | D64: =D$29*'PEV Sales by Manufacturer'!$S66 -> 22296.212 | E64: =E$29*'PEV Sales by Manufacturer'!$S66 -> 32716.8 | F64: =F$29*'PEV Sales by Manufacturer'!$S66 -> 45576.627 | G64: =G$29*'PEV Sales by Manufacturer'!$S66 -> 56256.443 | H64: =H$29*'PEV Sales by Manufacturer'!$S66 -> 62728.919 | I64: =I$29*'PEV Sales by Manufacturer'!$S66 -> 66452.429 | J64: =J$29*'PEV Sales by Manufacturer'!$S66 -> 67316.521 | K64: =K$29*'PEV Sales by Manufacturer'!$S66 -> 67819.462 | ... AF64: =AF$29*'PEV Sales by Manufacturer'!$S66 -> 54270.365
A65: Hyundai | B65: ='PEV Sales by Manufacturer'!M67 -> 4237 | C65: ='PEV Sales by Manufacturer'!N67 -> 6158 | D65: =D$29*'PEV Sales by Manufacturer'!$S67 -> 15352.798 | E65: =E$29*'PEV Sales by Manufacturer'!$S67 -> 22528.241 | F65: =F$29*'PEV Sales by Manufacturer'!$S67 -> 31383.302 | G65: =G$29*'PEV Sales by Manufacturer'!$S67 -> 38737.244 | H65: =H$29*'PEV Sales by Manufacturer'!$S67 -> 43194.083 | I65: =I$29*'PEV Sales by Manufacturer'!$S67 -> 45758.029 | J65: =J$29*'PEV Sales by Manufacturer'!$S67 -> 46353.029 | K65: =K$29*'PEV Sales by Manufacturer'!$S67 -> 46699.346 | ... AF65: =AF$29*'PEV Sales by Manufacturer'!$S67 -> 37369.665
A66: Kia | B66: ='PEV Sales by Manufacturer'!M68 -> 2454 | C66: ='PEV Sales by Manufacturer'!N68 -> 5900 | D66: =D$29*'PEV Sales by Manufacturer'!$S68 -> 14709.566 | E66: =E$29*'PEV Sales by Manufacturer'!$S68 -> 21584.381 | F66: =F$29*'PEV Sales by Manufacturer'!$S68 -> 30068.444 | G66: =G$29*'PEV Sales by Manufacturer'!$S68 -> 37114.281 | H66: =H$29*'PEV Sales by Manufacturer'!$S68 -> 41384.392 | I66: =I$29*'PEV Sales by Manufacturer'!$S68 -> 43840.918 | J66: =J$29*'PEV Sales by Manufacturer'!$S68 -> 44410.989 | K66: =K$29*'PEV Sales by Manufacturer'!$S68 -> 44742.796 | ... AF66: =AF$29*'PEV Sales by Manufacturer'!$S68 -> 35803.998
A67: Volvo | B67: ='PEV Sales by Manufacturer'!M69 -> 7106 | C67: ='PEV Sales by Manufacturer'!N69 -> 15606 | D67: =D$29*'PEV Sales by Manufacturer'!$S69 -> 38908.049 | E67: =E$29*'PEV Sales by Manufacturer'!$S69 -> 57092.518 | F67: =F$29*'PEV Sales by Manufacturer'!$S69 -> 79533.584 | G67: =G$29*'PEV Sales by Manufacturer'!$S69 -> 98170.418 | H67: =H$29*'PEV Sales by Manufacturer'!$S69 -> 109465.22 | I67: =I$29*'PEV Sales by Manufacturer'!$S69 -> 115962.94 | J67: =J$29*'PEV Sales by Manufacturer'!$S69 -> 117470.83 | K67: =K$29*'PEV Sales by Manufacturer'!$S69 -> 118348.49 | ... AF67: =AF$29*'PEV Sales by Manufacturer'!$S69 -> 94704.609
... A77: Mazda | B77: ='PEV Sales by Manufacturer'!M79 -> 0 | C77: ='PEV Sales by Manufacturer'!N79 -> 0 | D77: =D$29*'PEV Sales by Manufacturer'!$S79 -> 0 | E77: =E$29*'PEV Sales by Manufacturer'!$S79 -> 0 | F77: =F$29*'PEV Sales by Manufacturer'!$S79 -> 0 | G77: =G$29*'PEV Sales by Manufacturer'!$S79 -> 0 | H77: =H$29*'PEV Sales by Manufacturer'!$S79 -> 0 | I77: =I$29*'PEV Sales by Manufacturer'!$S79 -> 0 | J77: =J$29*'PEV Sales by Manufacturer'!$S79 -> 0 | K77: =K$29*'PEV Sales by Manufacturer'!$S79 -> 0 | ... AF77: =AF$29*'PEV Sales by Manufacturer'!$S79 -> 0
A79: Projected BEV Credit By Manufacturer | C79: 2020 | D79: 2021 | E79: 2022 | F79: 2023 | G79: 2024 | H79: 2025 | I79: 2026 | J79: 2027 | K79: 2028 | L79: 2029 | M79: 2030 | N79: 2031 | O79: 2032 | P79: 2033 | Q79: 2034 | R79: 2035 | S79: 2036 | T79: 2037 | U79: 2038 | V79: 2039 | W79: 2040 | X79: 2041 | Y79: 2042 | Z79: 2043 | AA79: 2044 | AB79: 2045 | AC79: 2046 | AD79: 2047 | AE79: 2048 | AF79: 2049 | AG79: 2050
A80: Tesla | C80: =IF(B3<200000,7500,0) -> 0 | D80: =IF(C3<200000,7500,IF(B3<200000,7500*0.375,0)) -> 0 | E80: =IF(D3<200000,7500,IF(C3<200000,7500*0.375,0)) -> 0 | F80: =IF(E3<200000,7500,IF(D3<200000,7500*0.375,0)) -> 0 | G80: =IF(F3<200000,7500,IF(E3<200000,7500*0.375,0)) -> 0 | H80: =IF(G3<200000,7500,IF(F3<200000,7500*0.375,0)) -> 0 | I80: =IF(H3<200000,7500,IF(G3<200000,7500*0.375,0)) -> 0 | J80: =IF(I3<200000,7500,IF(H3<200000,7500*0.375,0)) -> 0 | K80: =IF(J3<200000,7500,IF(I3<200000,7500*0.375,0)) -> 0 | ... AG80: =IF(AF3<200000,7500,IF(AE3<200000,7500*0.375,0)) -> 0
A81: GM (Cadillac and Chevrolet) | C81: =IF(B4<200000,7500,0) -> 0 | D81: =IF(C4<200000,7500,IF(B4<200000,7500*0.375,0)) -> 0 | E81: =IF(D4<200000,7500,IF(C4<200000,7500*0.375,0)) -> 0 | F81: =IF(E4<200000,7500,IF(D4<200000,7500*0.375,0)) -> 0 | G81: =IF(F4<200000,7500,IF(E4<200000,7500*0.375,0)) -> 0 | H81: =IF(G4<200000,7500,IF(F4<200000,7500*0.375,0)) -> 0 | I81: =IF(H4<200000,7500,IF(G4<200000,7500*0.375,0)) -> 0 | J81: =IF(I4<200000,7500,IF(H4<200000,7500*0.375,0)) -> 0 | K81: =IF(J4<200000,7500,IF(I4<200000,7500*0.375,0)) -> 0 | ... AG81: =IF(AF4<200000,7500,IF(AE4<200000,7500*0.375,0)) -> 0
A82: Nissan | C82: =IF(B5<200000,7500,0) -> 7500 | D82: =IF(C5<200000,7500,IF(B5<200000,7500*0.375,0)) -> 7500 | E82: =IF(D5<200000,7500,IF(C5<200000,7500*0.375,0)) -> 7500 | F82: =IF(E5<200000,7500,IF(D5<200000,7500*0.375,0)) -> 2812.5 | G82: =IF(F5<200000,7500,IF(E5<200000,7500*0.375,0)) -> 0 | H82: =IF(G5<200000,7500,IF(F5<200000,7500*0.375,0)) -> 0 | I82: =IF(H5<200000,7500,IF(G5<200000,7500*0.375,0)) -> 0 | J82: =IF(I5<200000,7500,IF(H5<200000,7500*0.375,0)) -> 0 | K82: =IF(J5<200000,7500,IF(I5<200000,7500*0.375,0)) -> 0 | ... AG82: =IF(AF5<200000,7500,IF(AE5<200000,7500*0.375,0)) -> 0
A83: Toyota | C83: =IF(B6<200000,7500,0) -> 7500 | D83: =IF(C6<200000,7500,IF(B6<200000,7500*0.375,0)) -> 7500 | E83: =IF(D6<200000,7500,IF(C6<200000,7500*0.375,0)) -> 2812.5 | F83: =IF(E6<200000,7500,IF(D6<200000,7500*0.375,0)) -> 0 | G83: =IF(F6<200000,7500,IF(E6<200000,7500*0.375,0)) -> 0 | H83: =IF(G6<200000,7500,IF(F6<200000,7500*0.375,0)) -> 0 | I83: =IF(H6<200000,7500,IF(G6<200000,7500*0.375,0)) -> 0 | J83: =IF(I6<200000,7500,IF(H6<200000,7500*0.375,0)) -> 0 | K83: =IF(J6<200000,7500,IF(I6<200000,7500*0.375,0)) -> 0 | ... AG83: =IF(AF6<200000,7500,IF(AE6<200000,7500*0.375,0)) -> 0
A84: Ford | C84: =IF(B7<200000,7500,0) -> 7500 | D84: =IF(C7<200000,7500,IF(B7<200000,7500*0.375,0)) -> 7500 | E84: =IF(D7<200000,7500,IF(C7<200000,7500*0.375,0)) -> 2812.5 | F84: =IF(E7<200000,7500,IF(D7<200000,7500*0.375,0)) -> 0 | G84: =IF(F7<200000,7500,IF(E7<200000,7500*0.375,0)) -> 0 | H84: =IF(G7<200000,7500,IF(F7<200000,7500*0.375,0)) -> 0 | I84: =IF(H7<200000,7500,IF(G7<200000,7500*0.375,0)) -> 0 | J84: =IF(I7<200000,7500,IF(H7<200000,7500*0.375,0)) -> 0 | K84: =IF(J7<200000,7500,IF(I7<200000,7500*0.375,0)) -> 0 | ... AG84: =IF(AF7<200000,7500,IF(AE7<200000,7500*0.375,0)) -> 0
A85: BMW N. America | C85: =IF(B8<200000,7500,0) -> 7500 | D85: =IF(C8<200000,7500,IF(B8<200000,7500*0.375,0)) -> 7500 | E85: =IF(D8<200000,7500,IF(C8<200000,7500*0.375,0)) -> 7500 | F85: =IF(E8<200000,7500,IF(D8<200000,7500*0.375,0)) -> 2812.5 | G85: =IF(F8<200000,7500,IF(E8<200000,7500*0.375,0)) -> 0 | H85: =IF(G8<200000,7500,IF(F8<200000,7500*0.375,0)) -> 0 | I85: =IF(H8<200000,7500,IF(G8<200000,7500*0.375,0)) -> 0 | J85: =IF(I8<200000,7500,IF(H8<200000,7500*0.375,0)) -> 0 | K85: =IF(J8<200000,7500,IF(I8<200000,7500*0.375,0)) -> 0 | ... AG85: =IF(AF8<200000,7500,IF(AE8<200000,7500*0.375,0)) -> 0
A86: FCA (Chrysler and Fiat) | C86: =IF(B9<200000,7500,0) -> 7500 | D86: =IF(C9<200000,7500,IF(B9<200000,7500*0.375,0)) -> 7500 | E86: =IF(D9<200000,7500,IF(C9<200000,7500*0.375,0)) -> 2812.5 | F86: =IF(E9<200000,7500,IF(D9<200000,7500*0.375,0)) -> 0 | G86: =IF(F9<200000,7500,IF(E9<200000,7500*0.375,0)) -> 0 | H86: =IF(G9<200000,7500,IF(F9<200000,7500*0.375,0)) -> 0 | I86: =IF(H9<200000,7500,IF(G9<200000,7500*0.375,0)) -> 0 | J86: =IF(I9<200000,7500,IF(H9<200000,7500*0.375,0)) -> 0 | K86: =IF(J9<200000,7500,IF(I9<200000,7500*0.375,0)) -> 0 | ... AG86: =IF(AF9<200000,7500,IF(AE9<200000,7500*0.375,0)) -> 0
A87: Honda | C87: =IF(B10<200000,7500,0) -> 7500 | D87: =IF(C10<200000,7500,IF(B10<200000,7500*0.375,0)) -> 7500 | E87: =IF(D10<200000,7500,IF(C10<200000,7500*0.375,0)) -> 7500 | F87: =IF(E10<200000,7500,IF(D10<200000,7500*0.375,0)) -> 7500 | G87: =IF(F10<200000,7500,IF(E10<200000,7500*0.375,0)) -> 7500 | H87: =IF(G10<200000,7500,IF(F10<200000,7500*0.375,0)) -> 7500 | I87: =IF(H10<200000,7500,IF(G10<200000,7500*0.375,0)) -> 7500 | J87: =IF(I10<200000,7500,IF(H10<200000,7500*0.375,0)) -> 7500 | K87: =IF(J10<200000,7500,IF(I10<200000,7500*0.375,0)) -> 7500 | ... AG87: =IF(AF10<200000,7500,IF(AE10<200000,7500*0.375,0)) -> 0
A88: Audi | C88: =IF(B11<200000,7500,0) -> 7500 | D88: =IF(C11<200000,7500,IF(B11<200000,7500*0.375,0)) -> 7500 | E88: =IF(D11<200000,7500,IF(C11<200000,7500*0.375,0)) -> 7500 | F88: =IF(E11<200000,7500,IF(D11<200000,7500*0.375,0)) -> 7500 | G88: =IF(F11<200000,7500,IF(E11<200000,7500*0.375,0)) -> 2812.5 | H88: =IF(G11<200000,7500,IF(F11<200000,7500*0.375,0)) -> 0 | I88: =IF(H11<200000,7500,IF(G11<200000,7500*0.375,0)) -> 0 | J88: =IF(I11<200000,7500,IF(H11<200000,7500*0.375,0)) -> 0 | K88: =IF(J11<200000,7500,IF(I11<200000,7500*0.375,0)) -> 0 | ... AG88: =IF(AF11<200000,7500,IF(AE11<200000,7500*0.375,0)) -> 0
A89: Hyundai | C89: =IF(B12<200000,7500,0) -> 7500 | D89: =IF(C12<200000,7500,IF(B12<200000,7500*0.375,0)) -> 7500 | E89: =IF(D12<200000,7500,IF(C12<200000,7500*0.375,0)) -> 7500 | F89: =IF(E12<200000,7500,IF(D12<200000,7500*0.375,0)) -> 7500 | G89: =IF(F12<200000,7500,IF(E12<200000,7500*0.375,0)) -> 2812.5 | H89: =IF(G12<200000,7500,IF(F12<200000,7500*0.375,0)) -> 0 | I89: =IF(H12<200000,7500,IF(G12<200000,7500*0.375,0)) -> 0 | J89: =IF(I12<200000,7500,IF(H12<200000,7500*0.375,0)) -> 0 | K89: =IF(J12<200000,7500,IF(I12<200000,7500*0.375,0)) -> 0 | ... AG89: =IF(AF12<200000,7500,IF(AE12<200000,7500*0.375,0)) -> 0
A90: Kia | C90: =IF(B13<200000,7500,0) -> 7500 | D90: =IF(C13<200000,7500,IF(B13<200000,7500*0.375,0)) -> 7500 | E90: =IF(D13<200000,7500,IF(C13<200000,7500*0.375,0)) -> 7500 | F90: =IF(E13<200000,7500,IF(D13<200000,7500*0.375,0)) -> 7500 | G90: =IF(F13<200000,7500,IF(E13<200000,7500*0.375,0)) -> 7500 | H90: =IF(G13<200000,7500,IF(F13<200000,7500*0.375,0)) -> 2812.5 | I90: =IF(H13<200000,7500,IF(G13<200000,7500*0.375,0)) -> 0 | J90: =IF(I13<200000,7500,IF(H13<200000,7500*0.375,0)) -> 0 | K90: =IF(J13<200000,7500,IF(I13<200000,7500*0.375,0)) -> 0 | ... AG90: =IF(AF13<200000,7500,IF(AE13<200000,7500*0.375,0)) -> 0
A91: Volvo | C91: =IF(B14<200000,7500,0) -> 7500 | D91: =IF(C14<200000,7500,IF(B14<200000,7500*0.375,0)) -> 7500 | E91: =IF(D14<200000,7500,IF(C14<200000,7500*0.375,0)) -> 7500 | F91: =IF(E14<200000,7500,IF(D14<200000,7500*0.375,0)) -> 7500 | G91: =IF(F14<200000,7500,IF(E14<200000,7500*0.375,0)) -> 2812.5 | H91: =IF(G14<200000,7500,IF(F14<200000,7500*0.375,0)) -> 0 | I91: =IF(H14<200000,7500,IF(G14<200000,7500*0.375,0)) -> 0 | J91: =IF(I14<200000,7500,IF(H14<200000,7500*0.375,0)) -> 0 | K91: =IF(J14<200000,7500,IF(I14<200000,7500*0.375,0)) -> 0 | ... AG91: =IF(AF14<200000,7500,IF(AE14<200000,7500*0.375,0)) -> 0
... A101: Mazda | C101: =IF(B24<200000,7500,0) -> 7500 | D101: =IF(C24<200000,7500,IF(B24<200000,7500*0.375,0)) -> 7500 | E101: =IF(D24<200000,7500,IF(C24<200000,7500*0.375,0)) -> 7500 | F101: =IF(E24<200000,7500,IF(D24<200000,7500*0.375,0)) -> 7500 | G101: =IF(F24<200000,7500,IF(E24<200000,7500*0.375,0)) -> 7500 | H101: =IF(G24<200000,7500,IF(F24<200000,7500*0.375,0)) -> 7500 | I101: =IF(H24<200000,7500,IF(G24<200000,7500*0.375,0)) -> 7500 | J101: =IF(I24<200000,7500,IF(H24<200000,7500*0.375,0)) -> 7500 | K101: =IF(J24<200000,7500,IF(I24<200000,7500*0.375,0)) -> 7500 | ... AG101: =IF(AF24<200000,7500,IF(AE24<200000,7500*0.375,0)) -> 7500
A103: Weighted Average Credit | C103: 2020 | D103: 2021 | E103: 2022 | F103: 2023 | G103: 2024 | H103: 2025 | I103: 2026 | J103: 2027 | K103: 2028 | L103: 2029 | M103: 2030 | N103: 2031 | O103: 2032 | P103: 2033 | Q103: 2034 | R103: 2035 | S103: 2036 | T103: 2037 | U103: 2038 | V103: 2039 | W103: 2040 | X103: 2041 | Y103: 2042 | Z103: 2043 | AA103: 2044 | AB103: 2045 | AC103: 2046 | AD103: 2047 | AE103: 2048 | AF103: 2049 | AG103: 2050
C104: =SUMPRODUCT(C80:C101,B32:B53)/SUM(B32:B53) -> 1066.1677 | D104: =SUMPRODUCT(D80:D101,C32:C53)/SUM(C32:C53) -> 1856.0233 | E104: =SUMPRODUCT(E80:E101,D32:D53)/SUM(D32:D53) -> 1578.301 | F104: =SUMPRODUCT(F80:F101,E32:E53)/SUM(E32:E53) -> 1230.8383 | G104: =SUMPRODUCT(G80:G101,F32:F53)/SUM(F32:F53) -> 626.81537 | H104: =SUMPRODUCT(H80:H101,G32:G53)/SUM(G32:G53) -> 144.46747 | I104: =SUMPRODUCT(I80:I101,H32:H53)/SUM(H32:H53) -> 33.447892 | J104: =SUMPRODUCT(J80:J101,I32:I53)/SUM(I32:I53) -> 33.447892 | ... AG104: =SUMPRODUCT(AG80:AG101,AF32:AF53)/SUM(AF32:AF53) -> 9.0924722

Sheet PEV Sales by Manufacturer
A1: Data summarized by Argonne National Laboratory, 6/22/2022, contact yzhou@anl.gov
A2: PEV
A3: Manufacturer | D3: 2011 | E3: 2012 | F3: 2013 | G3: 2014 | H3: 2015 | I3: 2016 | J3: 2017 | K3: 2018 | L3: 2019 | M3: 2020 | N3: 2021 | O3: 2022* | Q3: Total | R3: Percentage of Total, 2021
A4: Tesla | E4: 2400 | F4: 19400 | G4: 16750 | H4: 26408 | I4: 49800 | J4: 49970 | K4: 161123 | L4: 177589 | M4: 183829 | N4: 320918 | O4: 180520 | Q4: 1188707 | R4: =N4/$N$27 -> 0.50655853
A5: GM (Cadillac and Chevrolet) | D5: 7671 | E5: 23461 | F5: 23660 | G5: 21260 | H5: 19046 | I5: 28887 | J5: 43891 | K5: 36594 | L5: 21370 | M5: 20835 | N5: 24845 | O5: 3680 | Q5: 275200 | R5: =N5/$N$27 -> 0.039217017
A6: Nissan | D6: 9674 | E6: 9819 | F6: 22610 | G6: 30200 | H6: 17269 | I6: 14006 | J6: 11230 | K6: 14715 | L6: 12365 | M6: 9564 | N6: 14239 | O6: 7037 | Q6: 172728 | R6: =N6/$N$27 -> 0.022475794
A7: Toyota | E7: 12941 | F7: 13093 | G7: 14448 | H7: 4209 | I7: 2474 | J7: 20936 | K7: 27596 | L7: 21856 | M7: 17898 | N7: 52767 | O7: 13578 | Q7: 201796 | R7: =N7/$N$27 -> 0.083290978
A8: Ford | E8: 3057 | F8: 14981 | G8: 21947 | H8: 18923 | I8: 24796 | J8: 19589 | K8: 9216 | L8: 8235 | M8: 5568 | N8: 33234 | O8: 23819 | Q8: 183365 | R8: =N8/$N$27 -> 0.052458778
A9: BMW N. America | E9: 673 | F9: 0 | G9: 6647 | H9: 14181 | I9: 16117 | J9: 21195 | K9: 26092 | L9: 14067 | M9: 10639 | N9: 23064 | O9: 7611 | Q9: 140286 | R9: =N9/$N$27 -> 0.036405767
A10: FCA (Chrysler and Fiat) | F10: 260 | G10: 1503 | H10: 3477 | I10: 3737 | J10: 6317 | K10: 9897 | L10: 6850 | M10: 5666 | N10: 48723 | O10: 30098 | Q10: 116528 | R10: =N10/$N$27 -> 0.076907657
A11: Honda | E11: 93 | F11: 1095 | G11: 856 | H11: 66 | I11: 0 | J11: 2024 | K11: 19550 | L11: 11334 | M11: 3984 | N11: 2315 | O11: 2 | Q11: 41319 | R11: =N11/$N$27 -> 0.0036541515
A12: Audi | I12: 4280 | J12: 2877 | K12: 2391 | L12: 5410 | M12: 11670 | N12: 20019 | O12: 9704 | Q12: 56351 | R12: =N12/$N$27 -> 0.031599335
A13: Hyundai | H13: 15 | I13: 3000 | J13: 2686 | K13: 2684 | L13: 8045 | M13: 8793 | N13: 17013 | O13: 17215 | Q13: 59451 | R13: =N13/$N$27 -> 0.026854462
A14: Kia | G14: 359 | H14: 1015 | I14: 1728 | J14: 3669 | K14: 5670 | L14: 6769 | M14: 5302 | N14: 14617 | O14: 19481 | Q14: 58610 | R14: =N14/$N$27 -> 0.023072455
A15: Volvo | H15: 86 | I15: 2015 | J15: 2826 | K15: 3818 | L15: 3683 | M15: 7241 | N15: 25469 | O15: 13813 | Q15: 58951 | R15: =N15/$N$27 -> 0.040201981
A16: Porsche | F16: 51 | G16: 991 | H16: 1570 | I16: 2504 | J16: 1592 | K16: 2152 | L16: 2705 | M16: 6935 | N16: 11931 | O16: 4760 | Q16: 35191 | R16: =N16/$N$27 -> 0.018832692
A17: Volkswagon | G17: 357 | H17: 4232 | I17: 3937 | J17: 3534 | K17: 1354 | L17: 4863 | M17: 767 | N17: 16775 | O17: 3820 | Q17: 39639 | R17: =N17/$N$27 -> 0.026478787
A18: Merdeces-Benz | G18: 774 | H18: 2024 | I18: 1584 | J18: 2690 | K18: 2336 | L18: 5389 | M18: 1236 | N18: 507 | O18: 3280 | Q18: 19820 | R18: =N18/$N$27 -> 0.00080028286
A19: Mitsubishi | D19: 76 | E19: 588 | F19: 1029 | G19: 196 | H19: 115 | I19: 94 | J19: 105 | K19: 4166 | L19: 2810 | M19: 1964 | N19: 2250 | O19: 1158 | Q19: 14551 | R19: =N19/$N$27 -> 0.0035515512
A20: Smart USA | D20: 342 | E20: 139 | F20: 923 | G20: 2594 | H20: 1387 | I20: 657 | J20: 544 | K20: 1198 | L20: 680 | M20: 0 | N20: 0 | O20: 0 | Q20: 8464 | R20: =N20/$N$27 -> 0
A21: Jaguar Land Rover | K21: 393 | L21: 3002 | M21: 3129 | N21: 1665 | O21: 251 | Q21: 8440 | R21: =N21/$N$27 -> 0.0026281479
A22: Subaru | K22: 0 | L22: 2591 | M22: 2514 | N22: 2618 | O22: 947 | Q22: 8670 | R22: =N22/$N$27 -> 0.0041324271
A23: Rivian | N23: 376 | O23: 3551 | Q23: 3927 | R23: =N23/$N$27 -> 0.00059350366
A24: Lucid | N24: 65 | O24: 600 | Q24: 665 | R24: =N24/$N$27 -> 0.00010260037
A25: Mazda | N25: 116 | O25: 293 | Q25: 409 | R25: =N25/$N$27 -> 0.00018310219
A27: Total | D27: 17763 | E27: 53171 | F27: 97102 | G27: 118882 | H27: 114023 | I27: 159616 | J27: 195675 | K27: 330945 | L27: 319613 | M27: 307534 | N27: 633526 | O27: 345218 | Q27: 2693068
A29: BEV Only
A30: Manufacturer | D30: 2011 | E30: 2012 | F30: 2013 | G30: 2014 | H30: 2015 | I30: 2016 | J30: 2017 | K30: 2018 | L30: 2019 | M30: 2020 | N30: 2021 | O30: 2022* | Q30: Total | S30: Percentage of 2021 Sales
A31: Tesla | E31: 2400 | F31: 19400 | G31: 16750 | H31: 26408 | I31: 49800 | J31: 49970 | K31: 161123 | L31: 177589 | M31: 183829 | N31: 320918 | O31: 180520 | Q31: =SUM(D31:O31) -> 1188707 | S31: =N31/$N$54 -> 0.69848905
A32: GM (Cadillac and Chevrolet) | D32: 0 | E32: 0 | F32: 560 | G32: 1145 | H32: 2629 | I32: 3614 | J32: 23320 | K32: 18026 | L32: 16418 | M32: 20754 | N32: 24829 | O32: 3680 | Q32: =SUM(D32:O32) -> 114975 | S32: =N32/$N$54 -> 0.054041171
A33: Nissan | D33: 9674 | E33: 9819 | F33: 22610 | G33: 30200 | H33: 17269 | I33: 14006 | J33: 11230 | K33: 14715 | L33: 12365 | M33: 9564 | N33: 14239 | O33: 7037 | Q33: =SUM(D33:O33) -> 172728 | S33: =N33/$N$54 -> 0.030991673
A34: Toyota | E34: 192 | F34: 1005 | G34: 1184 | H34: 18 | I34: 0 | J34: 0 | K34: 1 | L34: 0 | M34: 0 | N34: 0 | O34: 199 | Q34: =SUM(D34:O34) -> 2599 | S34: =N34/$N$54 -> 0
A35: Ford | E35: 683 | F35: 1738 | G35: 1964 | H35: 1582 | I35: 901 | J35: 1817 | K35: 560 | L35: 0 | M35: 3 | N35: 27221 | O35: 18763 | Q35: =SUM(D35:O35) -> 55232 | S35: =N35/$N$54 -> 0.059247441
A36: BMW N. America | E36: 673 | F36: 0 | G36: 6092 | H36: 11024 | I36: 7625 | J36: 6276 | K36: 6117 | L36: 4854 | M36: 2640 | N36: 3485 | O36: 2392 | Q36: =SUM(D36:O36) -> 51178 | S36: =N36/$N$54 -> 0.0075852222
A37: FCA (Chrysler and Fiat) | F37: 260 | G37: 1503 | H37: 3477 | I37: 3737 | J37: 3336 | K37: 1022 | L37: 604 | M37: 70 | N37: 0 | O37: 0 | Q37: =SUM(D37:O37) -> 14009 | S37: =N37/$N$54 -> 0
A38: Honda | E38: 93 | F38: 569 | G38: 407 | H38: 2 | I38: 0 | J38: 1121 | K38: 948 | L38: 576 | M38: 45 | N38: 1 | O38: 0 | Q38: =SUM(D38:O38) -> 3762 | S38: =N38/$N$54 -> 2.1765343e-06
A39: Audi | I39: 0 | J39: 0 | K39: 0 | L39: 5369 | M39: 7202 | N39: 11076 | O39: 5530 | Q39: =SUM(D39:O39) -> 29177 | S39: =N39/$N$54 -> 0.024107294
A40: Hyundai | H40: 0 | I40: 0 | J40: 432 | K40: 474 | L40: 5244 | M40: 4556 | N40: 10855 | O40: 13030 | Q40: =SUM(D40:O40) -> 34591 | S40: =N40/$N$54 -> 0.02362628
A41: Kia | G41: 359 | H41: 1015 | I41: 1728 | J41: 2157 | K41: 996 | L41: 2528 | M41: 2848 | N41: 8717 | O41: 15261 | Q41: =SUM(D41:O41) -> 35609 | S41: =N41/$N$54 -> 0.01897285
A42: Volvo | H42: 0 | I42: 0 | J42: 0 | K42: 0 | L42: 0 | M42: 135 | N42: 9863 | O42: 7331 | Q42: =SUM(D42:O42) -> 17329 | S42: =N42/$N$54 -> 0.021467158
A43: Porsche | F43: 0 | G43: 0 | H43: 0 | I43: 0 | J43: 0 | K43: 0 | L43: 130 | M43: 4414 | N43: 9419 | O43: 3895 | Q43: =SUM(D43:O43) -> 17858 | S43: =N43/$N$54 -> 0.020500777
A44: Volkswagon | G44: 357 | H44: 4232 | I44: 3937 | J44: 3534 | K44: 1354 | L44: 4863 | M44: 767 | N44: 16775 | O44: 3820 | Q44: =SUM(D44:O44) -> 39639 | S44: =N44/$N$54 -> 0.036511364
A45: Merdeces-Benz | G45: 774 | H45: 1906 | I45: 632 | J45: 744 | K45: 135 | L45: 8 | M45: 0 | N45: 429 | O45: 3280 | Q45: =SUM(D45:O45) -> 7908 | S45: =N45/$N$54 -> 0.00093373324
A46: Mitsubishi | D46: 76 | E46: 588 | F46: 1029 | G46: 196 | H46: 115 | I46: 94 | J46: 6 | K46: 0 | L46: 0 | M46: 0 | N46: 0 | O46: 0 | Q46: =SUM(D46:O46) -> 2104 | S46: =N46/$N$54 -> 0
A47: Smart USA | D47: 342 | E47: 139 | F47: 923 | G47: 2594 | H47: 1387 | I47: 657 | J47: 544 | K47: 1198 | L47: 680 | M47: 0 | N47: 0 | O47: 0 | Q47: =SUM(D47:O47) -> 8464 | S47: =N47/$N$54 -> 0
A48: Jaguar Land Rover | K48: 393 | L48: 2594 | M48: 1658 | N48: 1062 | O48: 251 | Q48: =SUM(D48:O48) -> 5958 | S48: =N48/$N$54 -> 0.0023114795
A49: Subaru | N49: 0 | O49: 0 | Q49: =SUM(D49:O49) -> 0 | S49: =N49/$N$54 -> 0
A50: Rivian | N50: 376 | O50: 3551 | Q50: =SUM(D50:O50) -> 3927 | S50: =N50/$N$54 -> 0.00081837691
A51: Lucid | N51: 65 | O51: 600 | Q51: =SUM(D51:O51) -> 665 | S51: =N51/$N$54 -> 0.00014147473
A52: Mazda | N52: 116 | O52: 293 | Q52: =SUM(D52:O52) -> 409 | S52: =N52/$N$54 -> 0.00025247798
A54: Total | D54: =SUM(D31:D52) -> 10092 | E54: =SUM(E31:E52) -> 14587 | F54: =SUM(F31:F52) -> 48094 | G54: =SUM(G31:G52) -> 63525 | H54: =SUM(H31:H52) -> 71064 | I54: =SUM(I31:I52) -> 86731 | J54: =SUM(J31:J52) -> 104487 | K54: =SUM(K31:K52) -> 207062 | ... O54: =SUM(O31:O52) -> 269433
A56: PHEV Only
A57: Manufacturer | D57: 2011 | E57: 2012 | F57: 2013 | G57: 2014 | H57: 2015 | I57: 2016 | J57: 2017 | K57: 2018 | L57: 2019 | M57: 2020 | N57: 2021 | O57: 2022* | Q57: Total | S57: Percentage of 2021 Sales
A58: Tesla | D58: =D4-D31 -> 0 | E58: =E4-E31 -> 0 | F58: =F4-F31 -> 0 | G58: =G4-G31 -> 0 | H58: =H4-H31 -> 0 | I58: =I4-I31 -> 0 | J58: =J4-J31 -> 0 | K58: =K4-K31 -> 0 | ... O58: =O4-O31 -> 0 | Q58: =SUM(D58:O58) -> 0 | S58: =N58/$N$81 -> 0
A59: GM (Cadillac and Chevrolet) | D59: =D5-D32 -> 7671 | E59: =E5-E32 -> 23461 | F59: =F5-F32 -> 23100 | G59: =G5-G32 -> 20115 | H59: =H5-H32 -> 16417 | I59: =I5-I32 -> 25273 | J59: =J5-J32 -> 20571 | K59: =K5-K32 -> 18568 | ... O59: =O5-O32 -> 0 | Q59: =SUM(D59:O59) -> 160225 | S59: =N59/$N$81 -> 9.1911765e-05
A60: Nissan | D60: =D6-D33 -> 0 | E60: =E6-E33 -> 0 | F60: =F6-F33 -> 0 | G60: =G6-G33 -> 0 | H60: =H6-H33 -> 0 | I60: =I6-I33 -> 0 | J60: =J6-J33 -> 0 | K60: =K6-K33 -> 0 | ... O60: =O6-O33 -> 0 | Q60: =SUM(D60:O60) -> 0 | S60: =N60/$N$81 -> 0
A61: Toyota | D61: =D7-D34 -> 0 | E61: =E7-E34 -> 12749 | F61: =F7-F34 -> 12088 | G61: =G7-G34 -> 13264 | H61: =H7-H34 -> 4191 | I61: =I7-I34 -> 2474 | J61: =J7-J34 -> 20936 | K61: =K7-K34 -> 27595 | ... O61: =O7-O34 -> 13379 | Q61: =SUM(D61:O61) -> 199197 | S61: =N61/$N$81 -> 0.30311926
A62: Ford | D62: =D8-D35 -> 0 | E62: =E8-E35 -> 2374 | F62: =F8-F35 -> 13243 | G62: =G8-G35 -> 19983 | H62: =H8-H35 -> 17341 | I62: =I8-I35 -> 23895 | J62: =J8-J35 -> 17772 | K62: =K8-K35 -> 8656 | ... O62: =O8-O35 -> 5056 | Q62: =SUM(D62:O62) -> 128133 | S62: =N62/$N$81 -> 0.03454159
A63: BMW N. America | D63: =D9-D36 -> 0 | E63: =E9-E36 -> 0 | F63: =F9-F36 -> 0 | G63: =G9-G36 -> 555 | H63: =H9-H36 -> 3157 | I63: =I9-I36 -> 8492 | J63: =J9-J36 -> 14919 | K63: =K9-K36 -> 19975 | ... O63: =O9-O36 -> 5219 | Q63: =SUM(D63:O63) -> 89108 | S63: =N63/$N$81 -> 0.11247128
A64: FCA (Chrysler and Fiat) | D64: =D10-D37 -> 0 | E64: =E10-E37 -> 0 | F64: =F10-F37 -> 0 | G64: =G10-G37 -> 0 | H64: =H10-H37 -> 0 | I64: =I10-I37 -> 0 | J64: =J10-J37 -> 2981 | K64: =K10-K37 -> 8875 | ... O64: =O10-O37 -> 30098 | Q64: =SUM(D64:O64) -> 102519 | S64: =N64/$N$81 -> 0.27988856
A65: Honda | D65: =D11-D38 -> 0 | E65: =E11-E38 -> 0 | F65: =F11-F38 -> 526 | G65: =G11-G38 -> 449 | H65: =H11-H38 -> 64 | I65: =I11-I38 -> 0 | J65: =J11-J38 -> 903 | K65: =K11-K38 -> 18602 | ... O65: =O11-O38 -> 2 | Q65: =SUM(D65:O65) -> 37557 | S65: =N65/$N$81 -> 0.013292739
A66: Audi | D66: =D12-D39 -> 0 | E66: =E12-E39 -> 0 | F66: =F12-F39 -> 0 | G66: =G12-G39 -> 0 | H66: =H12-H39 -> 0 | I66: =I12-I39 -> 4280 | J66: =J12-J39 -> 2877 | K66: =K12-K39 -> 2391 | ... O66: =O12-O39 -> 4174 | Q66: =SUM(D66:O66) -> 27174 | S66: =N66/$N$81 -> 0.051372932
A67: Hyundai | D67: =D13-D40 -> 0 | E67: =E13-E40 -> 0 | F67: =F13-F40 -> 0 | G67: =G13-G40 -> 0 | H67: =H13-H40 -> 15 | I67: =I13-I40 -> 3000 | J67: =J13-J40 -> 2254 | K67: =K13-K40 -> 2210 | ... O67: =O13-O40 -> 4185 | Q67: =SUM(D67:O67) -> 24860 | S67: =N67/$N$81 -> 0.03537454
A68: Kia | D68: =D14-D41 -> 0 | E68: =E14-E41 -> 0 | F68: =F14-F41 -> 0 | G68: =G14-G41 -> 0 | H68: =H14-H41 -> 0 | I68: =I14-I41 -> 0 | J68: =J14-J41 -> 1512 | K68: =K14-K41 -> 4674 | ... O68: =O14-O41 -> 4220 | Q68: =SUM(D68:O68) -> 23001 | S68: =N68/$N$81 -> 0.033892463
A69: Volvo | D69: =D15-D42 -> 0 | E69: =E15-E42 -> 0 | F69: =F15-F42 -> 0 | G69: =G15-G42 -> 0 | H69: =H15-H42 -> 86 | I69: =I15-I42 -> 2015 | J69: =J15-J42 -> 2826 | K69: =K15-K42 -> 3818 | ... O69: =O15-O42 -> 6482 | Q69: =SUM(D69:O69) -> 41622 | S69: =N69/$N$81 -> 0.089648437
... A79: Mazda | D79: =D25-D52 -> 0 | E79: =E25-E52 -> 0 | F79: =F25-F52 -> 0 | G79: =G25-G52 -> 0 | H79: =H25-H52 -> 0 | I79: =I25-I52 -> 0 | J79: =J25-J52 -> 0 | K79: =K25-K52 -> 0 | ... O79: =O25-O52 -> 0 | Q79: =SUM(D79:O79) -> 0 | S79: =N79/$N$81 -> 0
A81: Total | D81: =SUM(D58:D79) -> 7671 | E81: =SUM(E58:E79) -> 38584 | F81: =SUM(F58:F79) -> 49008 | G81: =SUM(G58:G79) -> 55357 | H81: =SUM(H58:H79) -> 42959 | I81: =SUM(I58:I79) -> 72885 | J81: =SUM(J58:J79) -> 91188 | K81: =SUM(K58:K79) -> 123883 | ... O81: =SUM(O58:O79) -> 75785

Sheet PEV Sales by Manufacturer - HK
A1: Data summarized by Argonne National Laboratory, 6/22/2022, contact yzhou@anl.gov
A2: PEV
A3: Manufacturer | D3: 2011 | E3: 2012 | F3: 2013 | G3: 2014 | H3: 2015 | I3: 2016 | J3: 2017 | K3: 2018 | L3: 2019 | M3: 2020 | N3: 2021 | O3: 2022* | Q3: Total | R3: Percentage of Total, 2021
A4: Tesla | E4: 2400 | F4: 19400 | G4: 16750 | H4: 26408 | I4: 49800 | J4: 49970 | K4: 161123 | L4: 177589 | M4: 183829 | N4: 320918 | O4: 180520 | Q4: 1188707 | R4: =N4/$N$27 -> 0.50655853
A5: GM (Cadillac and Chevrolet) | D5: 7671 | E5: 23461 | F5: 23660 | G5: 21260 | H5: 19046 | I5: 28887 | J5: 43891 | K5: 36594 | L5: 21370 | M5: 20835 | N5: 24845 | O5: 3680 | Q5: 275200 | R5: =N5/$N$27 -> 0.039217017
A6: Nissan | D6: 9674 | E6: 9819 | F6: 22610 | G6: 30200 | H6: 17269 | I6: 14006 | J6: 11230 | K6: 14715 | L6: 12365 | M6: 9564 | N6: 14239 | O6: 7037 | Q6: 172728 | R6: =N6/$N$27 -> 0.022475794
A7: Toyota | E7: 12941 | F7: 13093 | G7: 14448 | H7: 4209 | I7: 2474 | J7: 20936 | K7: 27596 | L7: 21856 | M7: 17898 | N7: 52767 | O7: 13578 | Q7: 201796 | R7: =N7/$N$27 -> 0.083290978
A8: Ford | E8: 3057 | F8: 14981 | G8: 21947 | H8: 18923 | I8: 24796 | J8: 19589 | K8: 9216 | L8: 8235 | M8: 5568 | N8: 33234 | O8: 23819 | Q8: 183365 | R8: =N8/$N$27 -> 0.052458778
A9: BMW N. America | E9: 673 | F9: 0 | G9: 6647 | H9: 14181 | I9: 16117 | J9: 21195 | K9: 26092 | L9: 14067 | M9: 10639 | N9: 23064 | O9: 7611 | Q9: 140286 | R9: =N9/$N$27 -> 0.036405767
A10: FCA (Chrysler and Fiat) | F10: 260 | G10: 1503 | H10: 3477 | I10: 3737 | J10: 6317 | K10: 9897 | L10: 6850 | M10: 5666 | N10: 48723 | O10: 30098 | Q10: 116528 | R10: =N10/$N$27 -> 0.076907657
A11: Honda | E11: 93 | F11: 1095 | G11: 856 | H11: 66 | I11: 0 | J11: 2024 | K11: 19550 | L11: 11334 | M11: 3984 | N11: 2315 | O11: 2 | Q11: 41319 | R11: =N11/$N$27 -> 0.0036541515
A12: Audi | I12: 4280 | J12: 2877 | K12: 2391 | L12: 5410 | M12: 11670 | N12: 20019 | O12: 9704 | Q12: 56351 | R12: =N12/$N$27 -> 0.031599335
A13: Hyundai | H13: 15 | I13: 3000 | J13: 2686 | K13: 2684 | L13: 8045 | M13: 8793 | N13: 17013 | O13: 17215 | Q13: 59451 | R13: =N13/$N$27 -> 0.026854462
A14: Kia | G14: 359 | H14: 1015 | I14: 1728 | J14: 3669 | K14: 5670 | L14: 6769 | M14: 5302 | N14: 14617 | O14: 19481 | Q14: 58610 | R14: =N14/$N$27 -> 0.023072455
A15: Volvo | H15: 86 | I15: 2015 | J15: 2826 | K15: 3818 | L15: 3683 | M15: 7241 | N15: 25469 | O15: 13813 | Q15: 58951 | R15: =N15/$N$27 -> 0.040201981
A16: Porsche | F16: 51 | G16: 991 | H16: 1570 | I16: 2504 | J16: 1592 | K16: 2152 | L16: 2705 | M16: 6935 | N16: 11931 | O16: 4760 | Q16: 35191 | R16: =N16/$N$27 -> 0.018832692
A17: Volkswagon | G17: 357 | H17: 4232 | I17: 3937 | J17: 3534 | K17: 1354 | L17: 4863 | M17: 767 | N17: 16775 | O17: 3820 | Q17: 39639 | R17: =N17/$N$27 -> 0.026478787
A18: Merdeces-Benz | G18: 774 | H18: 2024 | I18: 1584 | J18: 2690 | K18: 2336 | L18: 5389 | M18: 1236 | N18: 507 | O18: 3280 | Q18: 19820 | R18: =N18/$N$27 -> 0.00080028286
A19: Mitsubishi | D19: 76 | E19: 588 | F19: 1029 | G19: 196 | H19: 115 | I19: 94 | J19: 105 | K19: 4166 | L19: 2810 | M19: 1964 | N19: 2250 | O19: 1158 | Q19: 14551 | R19: =N19/$N$27 -> 0.0035515512
A20: Smart USA | D20: 342 | E20: 139 | F20: 923 | G20: 2594 | H20: 1387 | I20: 657 | J20: 544 | K20: 1198 | L20: 680 | M20: 0 | N20: 0 | O20: 0 | Q20: 8464 | R20: =N20/$N$27 -> 0
A21: Jaguar Land Rover | K21: 393 | L21: 3002 | M21: 3129 | N21: 1665 | O21: 251 | Q21: 8440 | R21: =N21/$N$27 -> 0.0026281479
A22: Subaru | K22: 0 | L22: 2591 | M22: 2514 | N22: 2618 | O22: 947 | Q22: 8670 | R22: =N22/$N$27 -> 0.0041324271
A23: Rivian | N23: 376 | O23: 3551 | Q23: 3927 | R23: =N23/$N$27 -> 0.00059350366
A24: Lucid | N24: 65 | O24: 600 | Q24: 665 | R24: =N24/$N$27 -> 0.00010260037
A25: Mazda | N25: 116 | O25: 293 | Q25: 409 | R25: =N25/$N$27 -> 0.00018310219
A27: Total | D27: 17763 | E27: 53171 | F27: 97102 | G27: 118882 | H27: 114023 | I27: 159616 | J27: 195675 | K27: 330945 | L27: 319613 | M27: 307534 | N27: 633526 | O27: 345218 | Q27: 2693068
A29: BEV Only
A30: Manufacturer | D30: 2011 | E30: 2012 | F30: 2013 | G30: 2014 | H30: 2015 | I30: 2016 | J30: 2017 | K30: 2018 | L30: 2019 | M30: 2020 | N30: 2021 | O30: 2022* | Q30: Total | S30: Percentage of 2021 Sales
A31: Tesla | E31: 2400 | F31: 19400 | G31: 16750 | H31: 26408 | I31: 49800 | J31: 49970 | K31: 161123 | L31: 177589 | M31: 183829 | N31: 320918 | O31: 180520 | Q31: =SUM(D31:O31) -> 1188707 | S31: =N31/$N$54 -> 0.69848905
A32: GM (Cadillac and Chevrolet) | D32: 0 | E32: 0 | F32: 560 | G32: 1145 | H32: 2629 | I32: 3614 | J32: 23320 | K32: 18026 | L32: 16418 | M32: 20754 | N32: 24829 | O32: 3680 | Q32: =SUM(D32:O32) -> 114975 | S32: =N32/$N$54 -> 0.054041171
A33: Nissan | D33: 9674 | E33: 9819 | F33: 22610 | G33: 30200 | H33: 17269 | I33: 14006 | J33: 11230 | K33: 14715 | L33: 12365 | M33: 9564 | N33: 14239 | O33: 7037 | Q33: =SUM(D33:O33) -> 172728 | S33: =N33/$N$54 -> 0.030991673
A34: Toyota | E34: 192 | F34: 1005 | G34: 1184 | H34: 18 | I34: 0 | J34: 0 | K34: 1 | L34: 0 | M34: 0 | N34: 0 | O34: 199 | Q34: =SUM(D34:O34) -> 2599 | S34: =N34/$N$54 -> 0
A35: Ford | E35: 683 | F35: 1738 | G35: 1964 | H35: 1582 | I35: 901 | J35: 1817 | K35: 560 | L35: 0 | M35: 3 | N35: 27221 | O35: 18763 | Q35: =SUM(D35:O35) -> 55232 | S35: =N35/$N$54 -> 0.059247441
A36: BMW N. America | E36: 673 | F36: 0 | G36: 6092 | H36: 11024 | I36: 7625 | J36: 6276 | K36: 6117 | L36: 4854 | M36: 2640 | N36: 3485 | O36: 2392 | Q36: =SUM(D36:O36) -> 51178 | S36: =N36/$N$54 -> 0.0075852222
A37: FCA (Chrysler and Fiat) | F37: 260 | G37: 1503 | H37: 3477 | I37: 3737 | J37: 3336 | K37: 1022 | L37: 604 | M37: 70 | N37: 0 | O37: 0 | Q37: =SUM(D37:O37) -> 14009 | S37: =N37/$N$54 -> 0
A38: Honda | E38: 93 | F38: 569 | G38: 407 | H38: 2 | I38: 0 | J38: 1121 | K38: 948 | L38: 576 | M38: 45 | N38: 1 | O38: 0 | Q38: =SUM(D38:O38) -> 3762 | S38: =N38/$N$54 -> 2.1765343e-06
A39: Audi | I39: 0 | J39: 0 | K39: 0 | L39: 5369 | M39: 7202 | N39: 11076 | O39: 5530 | Q39: =SUM(D39:O39) -> 29177 | S39: =N39/$N$54 -> 0.024107294
A40: Hyundai | H40: 0 | I40: 0 | J40: 432 | K40: 474 | L40: 5244 | M40: 4556 | N40: 10855 | O40: 13030 | Q40: =SUM(D40:O40) -> 34591 | S40: =N40/$N$54 -> 0.02362628
A41: Kia | G41: 359 | H41: 1015 | I41: 1728 | J41: 2157 | K41: 996 | L41: 2528 | M41: 2848 | N41: 8717 | O41: 15261 | Q41: =SUM(D41:O41) -> 35609 | S41: =N41/$N$54 -> 0.01897285
A42: Volvo | H42: 0 | I42: 0 | J42: 0 | K42: 0 | L42: 0 | M42: 135 | N42: 9863 | O42: 7331 | Q42: =SUM(D42:O42) -> 17329 | S42: =N42/$N$54 -> 0.021467158
A43: Porsche | F43: 0 | G43: 0 | H43: 0 | I43: 0 | J43: 0 | K43: 0 | L43: 130 | M43: 4414 | N43: 9419 | O43: 3895 | Q43: =SUM(D43:O43) -> 17858 | S43: =N43/$N$54 -> 0.020500777
A44: Volkswagon | G44: 357 | H44: 4232 | I44: 3937 | J44: 3534 | K44: 1354 | L44: 4863 | M44: 767 | N44: 16775 | O44: 3820 | Q44: =SUM(D44:O44) -> 39639 | S44: =N44/$N$54 -> 0.036511364
A45: Merdeces-Benz | G45: 774 | H45: 1906 | I45: 632 | J45: 744 | K45: 135 | L45: 8 | M45: 0 | N45: 429 | O45: 3280 | Q45: =SUM(D45:O45) -> 7908 | S45: =N45/$N$54 -> 0.00093373324
A46: Mitsubishi | D46: 76 | E46: 588 | F46: 1029 | G46: 196 | H46: 115 | I46: 94 | J46: 6 | K46: 0 | L46: 0 | M46: 0 | N46: 0 | O46: 0 | Q46: =SUM(D46:O46) -> 2104 | S46: =N46/$N$54 -> 0
A47: Smart USA | D47: 342 | E47: 139 | F47: 923 | G47: 2594 | H47: 1387 | I47: 657 | J47: 544 | K47: 1198 | L47: 680 | M47: 0 | N47: 0 | O47: 0 | Q47: =SUM(D47:O47) -> 8464 | S47: =N47/$N$54 -> 0
A48: Jaguar Land Rover | K48: 393 | L48: 2594 | M48: 1658 | N48: 1062 | O48: 251 | Q48: =SUM(D48:O48) -> 5958 | S48: =N48/$N$54 -> 0.0023114795
A49: Subaru | N49: 0 | O49: 0 | Q49: =SUM(D49:O49) -> 0 | S49: =N49/$N$54 -> 0
A50: Rivian | N50: 376 | O50: 3551 | Q50: =SUM(D50:O50) -> 3927 | S50: =N50/$N$54 -> 0.00081837691
A51: Lucid | N51: 65 | O51: 600 | Q51: =SUM(D51:O51) -> 665 | S51: =N51/$N$54 -> 0.00014147473
A52: Mazda | N52: 116 | O52: 293 | Q52: =SUM(D52:O52) -> 409 | S52: =N52/$N$54 -> 0.00025247798
A54: Total | D54: =SUM(D31:D52) -> 10092 | E54: =SUM(E31:E52) -> 14587 | F54: =SUM(F31:F52) -> 48094 | G54: =SUM(G31:G52) -> 63525 | H54: =SUM(H31:H52) -> 71064 | I54: =SUM(I31:I52) -> 86731 | J54: =SUM(J31:J52) -> 104487 | K54: =SUM(K31:K52) -> 207062 | ... O54: =SUM(O31:O52) -> 269433
A56: PHEV Only
A57: Manufacturer | D57: 2011 | E57: 2012 | F57: 2013 | G57: 2014 | H57: 2015 | I57: 2016 | J57: 2017 | K57: 2018 | L57: 2019 | M57: 2020 | N57: 2021 | O57: 2022* | Q57: Total | S57: Percentage of 2021 Sales
A58: Tesla | D58: =D4-D31 -> 0 | E58: =E4-E31 -> 0 | F58: =F4-F31 -> 0 | G58: =G4-G31 -> 0 | H58: =H4-H31 -> 0 | I58: =I4-I31 -> 0 | J58: =J4-J31 -> 0 | K58: =K4-K31 -> 0 | ... O58: =O4-O31 -> 0 | Q58: =SUM(D58:O58) -> 0 | S58: =N58/$N$81 -> 0
A59: GM (Cadillac and Chevrolet) | D59: =D5-D32 -> 7671 | E59: =E5-E32 -> 23461 | F59: =F5-F32 -> 23100 | G59: =G5-G32 -> 20115 | H59: =H5-H32 -> 16417 | I59: =I5-I32 -> 25273 | J59: =J5-J32 -> 20571 | K59: =K5-K32 -> 18568 | ... O59: =O5-O32 -> 0 | Q59: =SUM(D59:O59) -> 160225 | S59: =N59/$N$81 -> 9.1911765e-05
A60: Nissan | D60: =D6-D33 -> 0 | E60: =E6-E33 -> 0 | F60: =F6-F33 -> 0 | G60: =G6-G33 -> 0 | H60: =H6-H33 -> 0 | I60: =I6-I33 -> 0 | J60: =J6-J33 -> 0 | K60: =K6-K33 -> 0 | ... O60: =O6-O33 -> 0 | Q60: =SUM(D60:O60) -> 0 | S60: =N60/$N$81 -> 0
A61: Toyota | D61: =D7-D34 -> 0 | E61: =E7-E34 -> 12749 | F61: =F7-F34 -> 12088 | G61: =G7-G34 -> 13264 | H61: =H7-H34 -> 4191 | I61: =I7-I34 -> 2474 | J61: =J7-J34 -> 20936 | K61: =K7-K34 -> 27595 | ... O61: =O7-O34 -> 13379 | Q61: =SUM(D61:O61) -> 199197 | S61: =N61/$N$81 -> 0.30311926
A62: Ford | D62: =D8-D35 -> 0 | E62: =E8-E35 -> 2374 | F62: =F8-F35 -> 13243 | G62: =G8-G35 -> 19983 | H62: =H8-H35 -> 17341 | I62: =I8-I35 -> 23895 | J62: =J8-J35 -> 17772 | K62: =K8-K35 -> 8656 | ... O62: =O8-O35 -> 5056 | Q62: =SUM(D62:O62) -> 128133 | S62: =N62/$N$81 -> 0.03454159
A63: BMW N. America | D63: =D9-D36 -> 0 | E63: =E9-E36 -> 0 | F63: =F9-F36 -> 0 | G63: =G9-G36 -> 555 | H63: =H9-H36 -> 3157 | I63: =I9-I36 -> 8492 | J63: =J9-J36 -> 14919 | K63: =K9-K36 -> 19975 | ... O63: =O9-O36 -> 5219 | Q63: =SUM(D63:O63) -> 89108 | S63: =N63/$N$81 -> 0.11247128
A64: FCA (Chrysler and Fiat) | D64: =D10-D37 -> 0 | E64: =E10-E37 -> 0 | F64: =F10-F37 -> 0 | G64: =G10-G37 -> 0 | H64: =H10-H37 -> 0 | I64: =I10-I37 -> 0 | J64: =J10-J37 -> 2981 | K64: =K10-K37 -> 8875 | ... O64: =O10-O37 -> 30098 | Q64: =SUM(D64:O64) -> 102519 | S64: =N64/$N$81 -> 0.27988856
A65: Honda | D65: =D11-D38 -> 0 | E65: =E11-E38 -> 0 | F65: =F11-F38 -> 526 | G65: =G11-G38 -> 449 | H65: =H11-H38 -> 64 | I65: =I11-I38 -> 0 | J65: =J11-J38 -> 903 | K65: =K11-K38 -> 18602 | ... O65: =O11-O38 -> 2 | Q65: =SUM(D65:O65) -> 37557 | S65: =N65/$N$81 -> 0.013292739
A66: Audi | D66: =D12-D39 -> 0 | E66: =E12-E39 -> 0 | F66: =F12-F39 -> 0 | G66: =G12-G39 -> 0 | H66: =H12-H39 -> 0 | I66: =I12-I39 -> 4280 | J66: =J12-J39 -> 2877 | K66: =K12-K39 -> 2391 | ... O66: =O12-O39 -> 4174 | Q66: =SUM(D66:O66) -> 27174 | S66: =N66/$N$81 -> 0.051372932
A67: Hyundai | D67: =D13-D40 -> 0 | E67: =E13-E40 -> 0 | F67: =F13-F40 -> 0 | G67: =G13-G40 -> 0 | H67: =H13-H40 -> 15 | I67: =I13-I40 -> 3000 | J67: =J13-J40 -> 2254 | K67: =K13-K40 -> 2210 | ... O67: =O13-O40 -> 4185 | Q67: =SUM(D67:O67) -> 24860 | S67: =N67/$N$81 -> 0.03537454
A68: Kia | D68: =D14-D41 -> 0 | E68: =E14-E41 -> 0 | F68: =F14-F41 -> 0 | G68: =G14-G41 -> 0 | H68: =H14-H41 -> 0 | I68: =I14-I41 -> 0 | J68: =J14-J41 -> 1512 | K68: =K14-K41 -> 4674 | ... O68: =O14-O41 -> 4220 | Q68: =SUM(D68:O68) -> 23001 | S68: =N68/$N$81 -> 0.033892463
A69: Volvo | D69: =D15-D42 -> 0 | E69: =E15-E42 -> 0 | F69: =F15-F42 -> 0 | G69: =G15-G42 -> 0 | H69: =H15-H42 -> 86 | I69: =I15-I42 -> 2015 | J69: =J15-J42 -> 2826 | K69: =K15-K42 -> 3818 | ... O69: =O15-O42 -> 6482 | Q69: =SUM(D69:O69) -> 41622 | S69: =N69/$N$81 -> 0.089648437
... A79: Mazda | D79: =D25-D52 -> 0 | E79: =E25-E52 -> 0 | F79: =F25-F52 -> 0 | G79: =G25-G52 -> 0 | H79: =H25-H52 -> 0 | I79: =I25-I52 -> 0 | J79: =J25-J52 -> 0 | K79: =K25-K52 -> 0 | ... O79: =O25-O52 -> 0 | Q79: =SUM(D79:O79) -> 0 | S79: =N79/$N$81 -> 0
A81: Total | D81: =SUM(D58:D79) -> 7671 | E81: =SUM(E58:E79) -> 38584 | F81: =SUM(F58:F79) -> 49008 | G81: =SUM(G58:G79) -> 55357 | H81: =SUM(H58:H79) -> 42959 | I81: =SUM(I58:I79) -> 72885 | J81: =SUM(J58:J79) -> 91188 | K81: =SUM(K58:K79) -> 123883 | ... O81: =SUM(O58:O79) -> 75785
A85: NOTE Hong Kong doesn't have the exact number so the numbers were taken by how many of the cars were registered throughout the year
D87: 2021 | E87: 2022 | F87: TOTAL | G87: % of total 2021 Sales
A88: Audi | D88: =3+2+2+3+1+2+2+3+4+2+15 -> 39
A89: Euauto | D89: 0
A90: Nissan | D90: =15+21+38+26+19+25+19+14+17+16+24+23 -> 257
A91: Honda | D91: 0
A92: Tesla | D92: =131+409+425+534+867+500+806+623+816+704+1437+735 -> 7987
A93: BMW | D93: 0
A94: Renault | D94: 0
A95: Lotus | D95: 0
A96: BYD | D96: 1
A97: ORA | D97: 0 | L97: r
A98: Tazzari | D98: 0
A99: Maxus | D99: 0
A100: MG | D100: 0
A101: Mercedes-Benz | D101: =5+5+7+12+4+2+54+30+102+228 -> 449
A102: Volkswagon | D102: =1+4+7+7+3+2+4+7+3+2+4+1 -> 45
A103: Hyundai | D103: =23+13+24+18+28+23+24+8+20+23+18+23 -> 245
A104: Jaguar | D104: 1
A105: KIA | D105: =18+11+31+17+19+21+25+8+16+12+11+10 -> 199
A106: JOYLONG | D106: 0
A107: Porsche
A108: Mini
A109: Lexus
A110: Polestar
A111: Volvo
A112: DFSK
A113: Peugot

Sheet BESP-passengers
A1: Subsidy Percentage (dimensionless) | B1: 2020 | C1: 2021 | D1: 2022 | E1: 2023 | F1: 2024 | G1: 2025 | H1: 2026 | I1: 2027 | J1: 2028 | K1: 2029 | L1: 2030 | M1: 2031 | N1: 2032 | O1: 2033 | P1: 2034 | Q1: 2035 | R1: 2036 | S1: 2037 | T1: 2038 | U1: 2039 | V1: 2040 | W1: 2041 | X1: 2042 | Y1: 2043 | Z1: 2044 | AA1: 2045 | AB1: 2046 | AC1: 2047 | AD1: 2048 | AE1: 2049 | AF1: 2050
A2: LDVs | B2: ='Summary - US'!C44 -> 0.036464286 | C2: ='Summary - US'!D44 -> 0.054522194 | D2: ='Summary - US'!E44 -> 0.052172971 | E2: ='Summary - US'!F44 -> 0.047283104 | F2: ='Summary - US'!G44 -> 0.035724021 | G2: ='Summary - US'!H44 -> 0.025831422 | H2: ='Summary - US'!I44 -> 0.024129105 | I2: ='Summary - US'!J44 -> 0.024949579 | ... AF2: ='Summary - US'!AG44 -> 0.030948134
A3: HDVs | B3: 0 | C3: 0 | D3: 0 | E3: 0 | F3: 0 | G3: 0 | H3: 0 | I3: 0 | J3: 0 | K3: 0 | L3: 0 | M3: 0 | N3: 0 | O3: 0 | P3: 0 | Q3: 0 | R3: 0 | S3: 0 | T3: 0 | U3: 0 | V3: 0 | W3: 0 | X3: 0 | Y3: 0 | Z3: 0 | AA3: 0 | AB3: 0 | AC3: 0 | AD3: 0 | AE3: 0 | AF3: 0
A4: aircraft | B4: 0 | C4: 0 | D4: 0 | E4: 0 | F4: 0 | G4: 0 | H4: 0 | I4: 0 | J4: 0 | K4: 0 | L4: 0 | M4: 0 | N4: 0 | O4: 0 | P4: 0 | Q4: 0 | R4: 0 | S4: 0 | T4: 0 | U4: 0 | V4: 0 | W4: 0 | X4: 0 | Y4: 0 | Z4: 0 | AA4: 0 | AB4: 0 | AC4: 0 | AD4: 0 | AE4: 0 | AF4: 0
A5: rail | B5: 0 | C5: 0 | D5: 0 | E5: 0 | F5: 0 | G5: 0 | H5: 0 | I5: 0 | J5: 0 | K5: 0 | L5: 0 | M5: 0 | N5: 0 | O5: 0 | P5: 0 | Q5: 0 | R5: 0 | S5: 0 | T5: 0 | U5: 0 | V5: 0 | W5: 0 | X5: 0 | Y5: 0 | Z5: 0 | AA5: 0 | AB5: 0 | AC5: 0 | AD5: 0 | AE5: 0 | AF5: 0
A6: ships | B6: 0 | C6: 0 | D6: 0 | E6: 0 | F6: 0 | G6: 0 | H6: 0 | I6: 0 | J6: 0 | K6: 0 | L6: 0 | M6: 0 | N6: 0 | O6: 0 | P6: 0 | Q6: 0 | R6: 0 | S6: 0 | T6: 0 | U6: 0 | V6: 0 | W6: 0 | X6: 0 | Y6: 0 | Z6: 0 | AA6: 0 | AB6: 0 | AC6: 0 | AD6: 0 | AE6: 0 | AF6: 0
A7: motorbikes | B7: 0 | C7: 0 | D7: 0 | E7: 0 | F7: 0 | G7: 0 | H7: 0 | I7: 0 | J7: 0 | K7: 0 | L7: 0 | M7: 0 | N7: 0 | O7: 0 | P7: 0 | Q7: 0 | R7: 0 | S7: 0 | T7: 0 | U7: 0 | V7: 0 | W7: 0 | X7: 0 | Y7: 0 | Z7: 0 | AA7: 0 | AB7: 0 | AC7: 0 | AD7: 0 | AE7: 0 | AF7: 0

Sheet BESP-freight
A1: Subsidy Percentage (dimensionless) | B1: 2020 | C1: 2021 | D1: 2022 | E1: 2023 | F1: 2024 | G1: 2025 | H1: 2026 | I1: 2027 | J1: 2028 | K1: 2029 | L1: 2030 | M1: 2031 | N1: 2032 | O1: 2033 | P1: 2034 | Q1: 2035 | R1: 2036 | S1: 2037 | T1: 2038 | U1: 2039 | V1: 2040 | W1: 2041 | X1: 2042 | Y1: 2043 | Z1: 2044 | AA1: 2045 | AB1: 2046 | AC1: 2047 | AD1: 2048 | AE1: 2049 | AF1: 2050
A2: LDVs | B2: 0 | C2: 0 | D2: 0 | E2: 0 | F2: 0 | G2: 0 | H2: 0 | I2: 0 | J2: 0 | K2: 0 | L2: 0 | M2: 0 | N2: 0 | O2: 0 | P2: 0 | Q2: 0 | R2: 0 | S2: 0 | T2: 0 | U2: 0 | V2: 0 | W2: 0 | X2: 0 | Y2: 0 | Z2: 0 | AA2: 0 | AB2: 0 | AC2: 0 | AD2: 0 | AE2: 0 | AF2: 0
A3: HDVs | B3: 0 | C3: 0 | D3: 0 | E3: 0 | F3: 0 | G3: 0 | H3: 0 | I3: 0 | J3: 0 | K3: 0 | L3: 0 | M3: 0 | N3: 0 | O3: 0 | P3: 0 | Q3: 0 | R3: 0 | S3: 0 | T3: 0 | U3: 0 | V3: 0 | W3: 0 | X3: 0 | Y3: 0 | Z3: 0 | AA3: 0 | AB3: 0 | AC3: 0 | AD3: 0 | AE3: 0 | AF3: 0
A4: aircraft | B4: 0 | C4: 0 | D4: 0 | E4: 0 | F4: 0 | G4: 0 | H4: 0 | I4: 0 | J4: 0 | K4: 0 | L4: 0 | M4: 0 | N4: 0 | O4: 0 | P4: 0 | Q4: 0 | R4: 0 | S4: 0 | T4: 0 | U4: 0 | V4: 0 | W4: 0 | X4: 0 | Y4: 0 | Z4: 0 | AA4: 0 | AB4: 0 | AC4: 0 | AD4: 0 | AE4: 0 | AF4: 0
A5: rail | B5: 0 | C5: 0 | D5: 0 | E5: 0 | F5: 0 | G5: 0 | H5: 0 | I5: 0 | J5: 0 | K5: 0 | L5: 0 | M5: 0 | N5: 0 | O5: 0 | P5: 0 | Q5: 0 | R5: 0 | S5: 0 | T5: 0 | U5: 0 | V5: 0 | W5: 0 | X5: 0 | Y5: 0 | Z5: 0 | AA5: 0 | AB5: 0 | AC5: 0 | AD5: 0 | AE5: 0 | AF5: 0
A6: ships | B6: 0 | C6: 0 | D6: 0 | E6: 0 | F6: 0 | G6: 0 | H6: 0 | I6: 0 | J6: 0 | K6: 0 | L6: 0 | M6: 0 | N6: 0 | O6: 0 | P6: 0 | Q6: 0 | R6: 0 | S6: 0 | T6: 0 | U6: 0 | V6: 0 | W6: 0 | X6: 0 | Y6: 0 | Z6: 0 | AA6: 0 | AB6: 0 | AC6: 0 | AD6: 0 | AE6: 0 | AF6: 0
A7: motorbikes | B7: 0 | C7: 0 | D7: 0 | E7: 0 | F7: 0 | G7: 0 | H7: 0 | I7: 0 | J7: 0 | K7: 0 | L7: 0 | M7: 0 | N7: 0 | O7: 0 | P7: 0 | Q7: 0 | R7: 0 | S7: 0 | T7: 0 | U7: 0 | V7: 0 | W7: 0 | X7: 0 | Y7: 0 | Z7: 0 | AA7: 0 | AB7: 0 | AC7: 0 | AD7: 0 | AE7: 0 | AF7: 0
