Workbook

Sheet About
A1: GRA Government Revenue Accounting
A3: Source: | B3: none needed
B4: Government revenue handling is one of the design decisions a model user should make
B5: when designing a policy package.
A7: Notes
A8: This variable sets how government compensates for positive or negative cash flows caused by the
A9: policy package - for example, by raising or lowering spending or taxes. This is important because
A10: the consequences of a policy such as a tax or subsidy can depend strongly on how government
A11: obtains the necessary funds to pay for a program or how government puts revenue from a tax
A12: to use.
A14: This variable allows government to use the following different mechanisms to account for
A15: cash flow changes caused by policies. Each mechanism affects government cash flows whether
A16: those flows are positive or negative. For example, a change in spending on programs can be
A17: either an increase in spending or a decrease in spending, depending on whether the policy
A18: increased or decreased government money.
A20: 1 | B20: Change in spending on regular government programs (e.g. according to BAU budget allocations)
A21: 2 | B21: Change in deficit spending
A22: 3 | B22: Change in taxes on or rebates/dividends to households
A23: 4 | B23: Change in payroll taxes (affecting businesses and workers)
A24: 5 | B24: Change in corporate income taxes
A26: How To Assign Weights
A27: Government can use any mixture of these five strategies by assigning weights
A28: to the values in this variable. Weights must be between 0 and 10 (inclusive) and must
A29: use integer values, reflecting the step size of these levers in the web app.
A30: For example, if 25% of a carbon tax is to be rebated to households as a climate dividend
A31: and 75% is to be used to offset payroll taxes, one correct set of weightings is: [0, 0, 1, 3, 0].
A32: Another correct set of weights that would produce identical results is: [0, 0, 2, 6, 0].
A33: Weights do not need to sum to 10. For example, [0, 3, 5, 5, 7] is a valid set of weights
A34: and would assign 3/20 (or 15%) to deficit spending, 5/20 (or 25%) to change in
A35: taxes/rebates on households, etc.
A37: (Weights are used rather than percentages that must add to 100% because the GRA control
A38: settings are exposed in the web app, and a user must be able to adjust one setting without
... A50: interest, which further increases debt, etc.

Sheet Set Values Here
A1: These levers need to be split into five variables (not subscripts of one variable) in order to
A2: allow separate policy implementation schedules for each lever. However, it's easiest to
A3: set the priorities when they are all visible on one sheet. Therefore, set the priorities on
A4: this sheet, and the blue tabs read the priorities from this sheet.
A6: Set weights below. Use only integers from 0 to 10.
A7: Government Cash Flow Type | B7: Regular Spending | C7: Deficit Spending | D7: Household Taxes | E7: Payroll Taxes | F7: Corporate Taxes
A8: carbon tax revenue | B8: 0 | C8: 5 | D8: 5 | E8: 5 | F8: 0
A9: fuel tax revenue | B9: 0 | C9: 5 | D9: 0 | E9: 0 | F9: 5
A10: EV subsidy | B10: 0 | C10: 5 | D10: 0 | E10: 0 | F10: 0
A11: elec gen subsidy | B11: 0 | C11: 5 | D11: 0 | E11: 0 | F11: 0
A12: elec cap construction subsidy | B12: 0 | C12: 5 | D12: 0 | E12: 0 | F12: 0
A13: distributed solar subsidy | B13: 0 | C13: 5 | D13: 0 | E13: 0 | F13: 0
A14: fuel subsidy | B14: 0 | C14: 5 | D14: 0 | E14: 0 | F14: 0
A15: national debt interest | B15: 5 | C15: 0 | D15: 5 | E15: 0 | F15: 0
A16: remainder | B16: 5 | C16: 5 | D16: 5 | E16: 0 | F16: 0
A19: Percentages of Govt Cash Flow Changes Handled via Each Mechanism
A20: This is only to help you set weights correctly. Do not edit the formulas below. Edit the weights above.
A21: Government Cash Flow Type | B21: Regular Spending | C21: Deficit Spending | D21: Household Taxes | E21: Payroll Taxes | F21: Corporate Taxes
A22: carbon tax revenue | B22: =IFERROR(B8/SUM($B8:$F8),1/COUNT($B8:$F8)) -> 0 | C22: =IFERROR(C8/SUM($B8:$F8),1/COUNT($B8:$F8)) -> 0.33333333 | D22: =IFERROR(D8/SUM($B8:$F8),1/COUNT($B8:$F8)) -> 0.33333333 | E22: =IFERROR(E8/SUM($B8:$F8),1/COUNT($B8:$F8)) -> 0.33333333 | F22: =IFERROR(F8/SUM($B8:$F8),1/COUNT($B8:$F8)) -> 0
A23: fuel tax revenue | B23: =IFERROR(B9/SUM($B9:$F9),1/COUNT($B9:$F9)) -> 0 | C23: =IFERROR(C9/SUM($B9:$F9),1/COUNT($B9:$F9)) -> 0.5 | D23: =IFERROR(D9/SUM($B9:$F9),1/COUNT($B9:$F9)) -> 0 | E23: =IFERROR(E9/SUM($B9:$F9),1/COUNT($B9:$F9)) -> 0 | F23: =IFERROR(F9/SUM($B9:$F9),1/COUNT($B9:$F9)) -> 0.5
A24: EV subsidy | B24: =IFERROR(B10/SUM($B10:$F10),1/COUNT($B10:$F10)) -> 0 | C24: =IFERROR(C10/SUM($B10:$F10),1/COUNT($B10:$F10)) -> 1 | D24: =IFERROR(D10/SUM($B10:$F10),1/COUNT($B10:$F10)) -> 0 | E24: =IFERROR(E10/SUM($B10:$F10),1/COUNT($B10:$F10)) -> 0 | F24: =IFERROR(F10/SUM($B10:$F10),1/COUNT($B10:$F10)) -> 0
A25: elec gen subsidy | B25: =IFERROR(B11/SUM($B11:$F11),1/COUNT($B11:$F11)) -> 0 | C25: =IFERROR(C11/SUM($B11:$F11),1/COUNT($B11:$F11)) -> 1 | D25: =IFERROR(D11/SUM($B11:$F11),1/COUNT($B11:$F11)) -> 0 | E25: =IFERROR(E11/SUM($B11:$F11),1/COUNT($B11:$F11)) -> 0 | F25: =IFERROR(F11/SUM($B11:$F11),1/COUNT($B11:$F11)) -> 0
A26: elec cap construction subsidy | B26: =IFERROR(B12/SUM($B12:$F12),1/COUNT($B12:$F12)) -> 0 | C26: =IFERROR(C12/SUM($B12:$F12),1/COUNT($B12:$F12)) -> 1 | D26: =IFERROR(D12/SUM($B12:$F12),1/COUNT($B12:$F12)) -> 0 | E26: =IFERROR(E12/SUM($B12:$F12),1/COUNT($B12:$F12)) -> 0 | F26: =IFERROR(F12/SUM($B12:$F12),1/COUNT($B12:$F12)) -> 0
A27: distributed solar subsidy | B27: =IFERROR(B13/SUM($B13:$F13),1/COUNT($B13:$F13)) -> 0 | C27: =IFERROR(C13/SUM($B13:$F13),1/COUNT($B13:$F13)) -> 1 | D27: =IFERROR(D13/SUM($B13:$F13),1/COUNT($B13:$F13)) -> 0 | E27: =IFERROR(E13/SUM($B13:$F13),1/COUNT($B13:$F13)) -> 0 | F27: =IFERROR(F13/SUM($B13:$F13),1/COUNT($B13:$F13)) -> 0
A28: fuel subsidy | B28: =IFERROR(B14/SUM($B14:$F14),1/COUNT($B14:$F14)) -> 0 | C28: =IFERROR(C14/SUM($B14:$F14),1/COUNT($B14:$F14)) -> 1 | D28: =IFERROR(D14/SUM($B14:$F14),1/COUNT($B14:$F14)) -> 0 | E28: =IFERROR(E14/SUM($B14:$F14),1/COUNT($B14:$F14)) -> 0 | F28: =IFERROR(F14/SUM($B14:$F14),1/COUNT($B14:$F14)) -> 0
A29: national debt interest | B29: =IFERROR(B15/SUM($B15:$F15),1/COUNT($B15:$F15)) -> 0.5 | C29: =IFERROR(C15/SUM($B15:$F15),1/COUNT($B15:$F15)) -> 0 | D29: =IFERROR(D15/SUM($B15:$F15),1/COUNT($B15:$F15)) -> 0.5 | E29: =IFERROR(E15/SUM($B15:$F15),1/COUNT($B15:$F15)) -> 0 | F29: =IFERROR(F15/SUM($B15:$F15),1/COUNT($B15:$F15)) -> 0
A30: remainder | B30: =IFERROR(B16/SUM($B16:$F16),1/COUNT($B16:$F16)) -> 0.33333333 | C30: =IFERROR(C16/SUM($B16:$F16),1/COUNT($B16:$F16)) -> 0.33333333 | D30: =IFERROR(D16/SUM($B16:$F16),1/COUNT($B16:$F16)) -> 0.33333333 | E30: =IFERROR(E16/SUM($B16:$F16),1/COUNT($B16:$F16)) -> 0 | F30: =IFERROR(F16/SUM($B16:$F16),1/COUNT($B16:$F16)) -> 0

Sheet GRA-carbontax
A1: Unit: dimensionless (relative weight) | B1: carbon tax revenue
A2: Regular Spending | B2: {=TRANSPOSE('Set Values Here'!B8:F8)} -> 0
A3: Deficit Spending | B3: 5
A4: Household Taxes | B4: 5
A5: Payroll Taxes | B5: 5
A6: Corporate Taxes | B6: 0

Sheet GRA-fueltax
A1: Unit: dimensionless (relative weight) | B1: fuel tax revenue
A2: Regular Spending | B2: {=TRANSPOSE('Set Values Here'!B9:F9)} -> 0
A3: Deficit Spending | B3: 5
A4: Household Taxes | B4: 0
A5: Payroll Taxes | B5: 0
A6: Corporate Taxes | B6: 5

Sheet GRA-evsubsidy
A1: Unit: dimensionless (relative weight) | B1: EV subsidy
A2: Regular Spending | B2: {=TRANSPOSE('Set Values Here'!B10:F10)} -> 0
A3: Deficit Spending | B3: 5
A4: Household Taxes | B4: 0
A5: Payroll Taxes | B5: 0
A6: Corporate Taxes | B6: 0

Sheet GRA-elecgensubsidy
A1: Unit: dimensionless (relative weight) | B1: elec gen subsidy
A2: Regular Spending | B2: {=TRANSPOSE('Set Values Here'!B11:F11)} -> 0
A3: Deficit Spending | B3: 5
A4: Household Taxes | B4: 0
A5: Payroll Taxes | B5: 0
A6: Corporate Taxes | B6: 0

Sheet GRA-eleccapconstsubsidy
A1: Unit: dimensionless (relative weight) | B1: elec cap construction subsidy
A2: Regular Spending | B2: {=TRANSPOSE('Set Values Here'!B12:F12)} -> 0
A3: Deficit Spending | B3: 5
A4: Household Taxes | B4: 0
A5: Payroll Taxes | B5: 0
A6: Corporate Taxes | B6: 0

Sheet GRA-distsolarsubsidy
A1: Unit: dimensionless (relative weight) | B1: distributed solar subsidy
A2: Regular Spending | B2: {=TRANSPOSE('Set Values Here'!B13:F13)} -> 0
A3: Deficit Spending | B3: 5
A4: Household Taxes | B4: 0
A5: Payroll Taxes | B5: 0
A6: Corporate Taxes | B6: 0

Sheet GRA-fuelsubsidy
A1: Unit: dimensionless (relative weight) | B1: fuel subsidy
A2: Regular Spending | B2: {=TRANSPOSE('Set Values Here'!B14:F14)} -> 0
A3: Deficit Spending | B3: 5
A4: Household Taxes | B4: 0
A5: Payroll Taxes | B5: 0
A6: Corporate Taxes | B6: 0

Sheet GRA-ntnldebtinterest
A1: Unit: dimensionless (relative weight) | B1: national debt interest
A2: Regular Spending | B2: {=TRANSPOSE('Set Values Here'!B15:F15)} -> 5
A3: Deficit Spending | B3: 0
A4: Household Taxes | B4: 5
A5: Payroll Taxes | B5: 0
A6: Corporate Taxes | B6: 0

Sheet GRA-remainder
A1: Unit: dimensionless (relative weight) | B1: remainder
A2: Regular Spending | B2: {=TRANSPOSE('Set Values Here'!B16:F16)} -> 5
A3: Deficit Spending | B3: 5
A4: Household Taxes | B4: 5
A5: Payroll Taxes | B5: 0
A6: Corporate Taxes | B6: 0
