Workbook

Sheet About
A1: DLIM Domestic Leontief Inverse Matrix
A3: Source: | B3: Most Data
B4: OECD
B5: 2018
B6: Input-Output Tables 2018 Edition (ISIC Rev. 4)
B7: https://stats.oecd.org/Index.aspx?DataSetCode=IOTSI4_2018
B8: Variable: LEONTFD
B10: ISIC Code Splits
B11: U.S. Bureau of Economic Analysis
B12: 2012
B13: Input-Output Accounts Data
B14: https://www.bea.gov/industry/input-output-accounts-data
B15: "'Industry-by-Industry Domestic Requirements" table, 405-industry breakdown
B16: "Use of Commodities by Industry" table, 405-industry breakdown
A18: Notes
A19: OECD Stat directly provides Leontief inverse matrices, both total and domestic-only, for
A20: 64 countries and regions.
A22: A domestic-only Leontief matrix filters out payments to foreign suppliers from the respending
A23: calculations. This type of Leontief matrix must be multiplied by a change in domestic (not total)
A24: output by ISIC code, as it does not filter the direct output changes by which it is multiplied.
A25: Conversely, a "Total" Leontief matrix must be multiplied by a change in total (not domestic)
A26: output by ISIC code, as it cannot restore imports that were removed from the direct output changes
A27: by which it is multiplied.
A29: Splitting OECD Joined ISIC Codes
A30: The OECD tables group several industries that are broken out in the EPS.
A31: Therefore, we calculate these rows and columns using a separate data source.
... A76: before creating a Leontief Inverse Matrix.

Sheet OECD LEONTFD
A1: =DotStatQuery(B1) -> #NAME? | B1: Sorry, the query is too large to fit into the Excel cell. You will not be able to update your table with the .Stat Populator.
A2: Dataset: Input-Output Tables (IOTs) 2018 ed.
A3: Variable | C3: LEONTFD: Leontief inverse matrix (domestic)
A4: Country | C4: HKG: Hong Kong, China
A5: Time | C5: 2015
A6: Unit | C6: Index
A7: To: (sector in column) | C7: D01T03: Agriculture, forestry and fishing | D7: D05T06: Mining and extraction of energy producing products | E7: D07T08: Mining and quarrying of non-energy producing products | F7: D09: Mining support service activities | G7: D10T12: Food products, beverages and tobacco | H7: D13T15: Textiles, wearing apparel, leather and related products | I7: D16: Wood and products of wood and cork | J7: D17T18: Paper products and printing | K7: D19: Coke and refined petroleum products | L7: D20T21: Chemicals and pharmaceutical products | M7: D22: Rubber and plastic products | N7: D23: Other non-metallic mineral products | O7: D24: Basic metals | P7: D25: Fabricated metal products | Q7: D26: Computer, electronic and optical products | R7: D27: Electrical equipment | S7: D28: Machinery and equipment, nec | T7: D29: Motor vehicles, trailers and semi-trailers | U7: D30: Other transport equipment | V7: D31T33: Other manufacturing; repair and installation of machinery and equipment | W7: D35T39: Electricity, gas, water supply, sewerage, waste and remediation services | X7: D41T43: Construction | Y7: D45T47: Wholesale and retail trade; repair of motor vehicles | Z7: D49T53: Transportation and storage | AA7: D55T56: Accomodation and food services | AB7: D58T60: Publishing, audiovisual and broadcasting activities | AC7: D61: Telecommunications | AD7: D62T63: IT and other information services | AE7: D64T66: Financial and insurance activities | AF7: D68: Real estate activities | AG7: D69T82: Other business sector services | AH7: D84: Public admin. and defence; compulsory social security | AI7: D85: Education | AJ7: D86T88: Human health and social work | AK7: D90T96: Arts, entertainment, recreation and other service activities | AL7: D97T98: Private households with employed persons
A8: From: (sector in row)
A9: DOM_01T03: Agriculture, forestry and fishing | C9: 1.03 | D9: 0.001 | E9: 0.001 | F9: 0.001 | G9: 0.028 | H9: 0.002 | I9: 0.003 | J9: 0.001 | K9: 0.001 | L9: 0.002 | M9: 0.001 | N9: 0.001 | O9: 0.001 | P9: 0 | Q9: 0 | R9: 0 | S9: 0 | T9: 0 | U9: 0 | V9: 0 | W9: 0.001 | X9: 0 | Y9: 0.001 | Z9: 0 | AA9: 0.009 | AB9: 0 | AC9: 0 | AD9: 0 | AE9: 0 | AF9: 0 | AG9: 0 | AH9: 0.001 | AI9: 0.001 | AJ9: 0.001 | AK9: 0.002 | AL9: 0
A10: DOM_05T06: Mining and extraction of energy producing products | C10: 0.001 | D10: 1.004 | E10: 0.003 | F10: 0.005 | G10: 0 | H10: 0.001 | I10: 0.001 | J10: 0.001 | K10: 0.034 | L10: 0.002 | M10: 0.001 | N10: 0.002 | O10: 0.002 | P10: 0 | Q10: 0 | R10: 0 | S10: 0 | T10: 0 | U10: 0 | V10: 0 | W10: 0.004 | X10: 0.001 | Y10: 0 | Z10: 0.002 | AA10: 0 | AB10: 0 | AC10: 0 | AD10: 0 | AE10: 0 | AF10: 0 | AG10: 0.001 | AH10: 0 | AI10: 0 | AJ10: 0 | AK10: 0 | AL10: 0
A11: DOM_07T08: Mining and quarrying of non-energy producing products | C11: 0.003 | D11: 0.008 | E11: 1.142 | F11: 0.026 | G11: 0.001 | H11: 0.002 | I11: 0.004 | J11: 0.007 | K11: 0.005 | L11: 0.03 | M11: 0.006 | N11: 0.166 | O11: 0.024 | P11: 0.002 | Q11: 0.001 | R11: 0.001 | S11: 0.003 | T11: 0.002 | U11: 0.002 | V11: 0.005 | W11: 0.003 | X11: 0.036 | Y11: 0.001 | Z11: 0.001 | AA11: 0 | AB11: 0 | AC11: 0 | AD11: 0 | AE11: 0 | AF11: 0.002 | AG11: 0.001 | AH11: 0.002 | AI11: 0.001 | AJ11: 0.001 | AK11: 0.001 | AL11: 0
A12: DOM_09: Mining support service activities | C12: 0.002 | D12: 0.01 | E12: 0.006 | F12: 1.016 | G12: 0 | H12: 0 | I12: 0 | J12: 0 | K12: 0.001 | L12: 0 | M12: 0 | N12: 0.001 | O12: 0 | P12: 0 | Q12: 0 | R12: 0 | S12: 0 | T12: 0 | U12: 0 | V12: 0 | W12: 0 | X12: 0.001 | Y12: 0 | Z12: 0 | AA12: 0 | AB12: 0 | AC12: 0 | AD12: 0 | AE12: 0 | AF12: 0 | AG12: 0 | AH12: 0 | AI12: 0 | AJ12: 0 | AK12: 0 | AL12: 0
A13: DOM_10T12: Food products, beverages and tobacco | C13: 0.274 | D13: 0.012 | E13: 0.012 | F13: 0.016 | G13: 1.43 | H13: 0.049 | I13: 0.032 | J13: 0.032 | K13: 0.017 | L13: 0.073 | M13: 0.02 | N13: 0.013 | O13: 0.006 | P13: 0.004 | Q13: 0.006 | R13: 0.003 | S13: 0.006 | T13: 0.006 | U13: 0.007 | V13: 0.009 | W13: 0.01 | X13: 0.01 | Y13: 0.018 | Z13: 0.008 | AA13: 0.317 | AB13: 0.011 | AC13: 0.004 | AD13: 0.006 | AE13: 0.004 | AF13: 0.002 | AG13: 0.014 | AH13: 0.032 | AI13: 0.024 | AJ13: 0.046 | AK13: 0.064 | AL13: 0
A14: DOM_13T15: Textiles, wearing apparel, leather and related products | C14: 0.013 | D14: 0.02 | E14: 0.015 | F14: 0.025 | G14: 0.015 | H14: 1.221 | I14: 0.04 | J14: 0.01 | K14: 0.01 | L14: 0.011 | M14: 0.017 | N14: 0.011 | O14: 0.009 | P14: 0.006 | Q14: 0.01 | R14: 0.006 | S14: 0.01 | T14: 0.017 | U14: 0.017 | V14: 0.032 | W14: 0.008 | X14: 0.01 | Y14: 0.015 | Z14: 0.008 | AA14: 0.011 | AB14: 0.014 | AC14: 0.006 | AD14: 0.008 | AE14: 0.003 | AF14: 0.001 | AG14: 0.014 | AH14: 0.01 | AI14: 0.005 | AJ14: 0.015 | AK14: 0.016 | AL14: 0
A15: DOM_16: Wood and of products of wood and cork (except furniture) | C15: 0.002 | D15: 0.011 | E15: 0.005 | F15: 0.005 | G15: 0.001 | H15: 0.002 | I15: 1.36 | J15: 0.016 | K15: 0.002 | L15: 0.003 | M15: 0.005 | N15: 0.008 | O15: 0.001 | P15: 0.002 | Q15: 0.002 | R15: 0.001 | S15: 0.002 | T15: 0.004 | U15: 0.006 | V15: 0.046 | W15: 0.003 | X15: 0.03 | Y15: 0.001 | Z15: 0.001 | AA15: 0.001 | AB15: 0.001 | AC15: 0.001 | AD15: 0.001 | AE15: 0 | AF15: 0.003 | AG15: 0.002 | AH15: 0.001 | AI15: 0.001 | AJ15: 0.001 | AK15: 0.002 | AL15: 0
A16: DOM_17T18: Paper products and printing | C16: 0 | D16: 0 | E16: 0 | F16: 0 | G16: 0 | H16: 0 | I16: 0.001 | J16: 1.006 | K16: 0 | L16: 0 | M16: 0 | N16: 0 | O16: 0 | P16: 0 | Q16: 0 | R16: 0 | S16: 0 | T16: 0 | U16: 0 | V16: 0 | W16: 0 | X16: 0 | Y16: 0 | Z16: 0 | AA16: 0 | AB16: 0.002 | AC16: 0 | AD16: 0 | AE16: 0 | AF16: 0 | AG16: 0 | AH16: 0 | AI16: 0 | AJ16: 0 | AK16: 0 | AL16: 0
A17: DOM_19: Coke and refined petroleum products | C17: 0.03 | D17: 0.053 | E17: 0.082 | F17: 0.066 | G17: 0.008 | H17: 0.013 | I17: 0.033 | J17: 0.018 | K17: 1.154 | L17: 0.051 | M17: 0.02 | N17: 0.05 | O17: 0.03 | P17: 0.006 | Q17: 0.008 | R17: 0.004 | S17: 0.009 | T17: 0.008 | U17: 0.007 | V17: 0.009 | W17: 0.035 | X17: 0.024 | Y17: 0.008 | Z17: 0.05 | AA17: 0.006 | AB17: 0.008 | AC17: 0.005 | AD17: 0.006 | AE17: 0.004 | AF17: 0.003 | AG17: 0.017 | AH17: 0.01 | AI17: 0.006 | AJ17: 0.008 | AK17: 0.009 | AL17: 0
A18: DOM_20T21: Chemicals and pharmaceutical products | C18: 0.014 | D18: 0.02 | E18: 0.021 | F18: 0.015 | G18: 0.005 | H18: 0.035 | I18: 0.04 | J18: 0.03 | K18: 0.041 | L18: 1.118 | M18: 0.136 | N18: 0.025 | O18: 0.013 | P18: 0.005 | Q18: 0.009 | R18: 0.005 | S18: 0.007 | T18: 0.01 | U18: 0.009 | V18: 0.011 | W18: 0.006 | X18: 0.009 | Y18: 0.002 | Z18: 0.003 | AA18: 0.002 | AB18: 0.004 | AC18: 0.001 | AD18: 0.001 | AE18: 0.001 | AF18: 0.001 | AG18: 0.004 | AH18: 0.004 | AI18: 0.003 | AJ18: 0.036 | AK18: 0.006 | AL18: 0
A19: DOM_22: Rubber and plastics products | C19: 0.002 | D19: 0.005 | E19: 0.004 | F19: 0.004 | G19: 0.003 | H19: 0.004 | I19: 0.006 | J19: 0.005 | K19: 0.002 | L19: 0.004 | M19: 1.031 | N19: 0.004 | O19: 0.001 | P19: 0.001 | Q19: 0.005 | R19: 0.002 | S19: 0.004 | T19: 0.009 | U19: 0.003 | V19: 0.004 | W19: 0.001 | X19: 0.006 | Y19: 0.001 | Z19: 0.001 | AA19: 0.001 | AB19: 0.001 | AC19: 0.001 | AD19: 0 | AE19: 0 | AF19: 0 | AG19: 0.001 | AH19: 0.001 | AI19: 0 | AJ19: 0.001 | AK19: 0.001 | AL19: 0
A20: DOM_23: Other non-metallic mineral products | C20: 0 | D20: 0.001 | E20: 0.005 | F20: 0.002 | G20: 0.001 | H20: 0 | I20: 0.004 | J20: 0 | K20: 0 | L20: 0.001 | M20: 0.002 | N20: 1.022 | O20: 0.001 | P20: 0.001 | Q20: 0.002 | R20: 0 | S20: 0.001 | T20: 0.001 | U20: 0.001 | V20: 0.001 | W20: 0.001 | X20: 0.015 | Y20: 0 | Z20: 0 | AA20: 0 | AB20: 0 | AC20: 0 | AD20: 0 | AE20: 0 | AF20: 0.001 | AG20: 0 | AH20: 0 | AI20: 0 | AJ20: 0 | AK20: 0 | AL20: 0
... A45: TOTAL: Total | C45: 1.746 | D45: 2.07 | E45: 2.063 | F45: 2.054 | G45: 1.889 | H45: 1.754 | I45: 2.48 | J45: 1.624 | K45: 1.738 | L45: 1.78 | M45: 1.689 | N45: 1.879 | O45: 1.587 | P45: 1.282 | Q45: 1.571 | R45: 1.213 | S45: 1.478 | T45: 1.547 | U45: 1.374 | V45: 1.431 | W45: 1.613 | X45: 1.733 | Y45: 1.436 | Z45: 1.444 | AA45: 1.653 | AB45: 1.62 | AC45: 1.423 | AD45: 1.427 | AE45: 1.432 | AF45: 1.228 | AG45: 1.687 | AH45: 1.377 | AI45: 1.29 | AJ45: 1.432 | AK45: 1.538 | AL45: 1
A46: Data extracted on 18 Jan 2024 09:29 UTC (GMT) from OECD.Stat

Sheet DLIM
B1: ISIC 01T03 | C1: ISIC 05 | D1: ISIC 06 | E1: ISIC 07T08 | F1: ISIC 09 | G1: ISIC 10T12 | H1: ISIC 13T15 | I1: ISIC 16 | J1: ISIC 17T18 | K1: ISIC 19 | L1: ISIC 20 | M1: ISIC 21 | N1: ISIC 22 | O1: ISIC 231 | P1: ISIC 239 | Q1: ISIC 241 | R1: ISIC 242 | S1: ISIC 25 | T1: ISIC 26 | U1: ISIC 27 | V1: ISIC 28 | W1: ISIC 29 | X1: ISIC 30 | Y1: ISIC 31T33 | Z1: ISIC 351 | AA1: ISIC 352T353 | AB1: ISIC 36T39 | AC1: ISIC 41T43 | AD1: ISIC 45T47 | AE1: ISIC 49T53 | AF1: ISIC 55T56 | AG1: ISIC 58T60 | AH1: ISIC 61 | AI1: ISIC 62T63 | AJ1: ISIC 64T66 | AK1: ISIC 68 | AL1: ISIC 69T82 | AM1: ISIC 84 | AN1: ISIC 85 | AO1: ISIC 86T88 | AP1: ISIC 90T96 | AQ1: ISIC 97T98
A2: ISIC 01T03 | B2: ='OECD LEONTFD'!C9 -> 1.03 | C2: ='Weighted Avg BEA Multipliers'!E472 -> 0.00035354395 | D2: ='Weighted Avg BEA Multipliers'!F472 -> 0.00022726856 | E2: ='OECD LEONTFD'!E9 -> 0.001 | F2: ='OECD LEONTFD'!F9 -> 0.001 | G2: ='OECD LEONTFD'!G9 -> 0.028 | H2: ='OECD LEONTFD'!H9 -> 0.002 | I2: ='OECD LEONTFD'!I9 -> 0.003 | J2: ='OECD LEONTFD'!J9 -> 0.001 | K2: ='OECD LEONTFD'!K9 -> 0.001 | L2: ='Weighted Avg BEA Multipliers'!N472 -> 0.011445709 | M2: ='Weighted Avg BEA Multipliers'!O472 -> 0.0021397938 | N2: ='OECD LEONTFD'!M9 -> 0.001 | O2: ='Weighted Avg BEA Multipliers'!Q472 -> 0.00048540449 | P2: ='Weighted Avg BEA Multipliers'!R472 -> 0.00093341524 | Q2: ='Weighted Avg BEA Multipliers'!S472 -> 0.00044179799 | R2: ='Weighted Avg BEA Multipliers'!T472 -> 0.00026023 | S2: ='OECD LEONTFD'!P9 -> 0 | T2: ='OECD LEONTFD'!Q9 -> 0 | U2: ='OECD LEONTFD'!R9 -> 0 | V2: ='OECD LEONTFD'!S9 -> 0 | W2: ='OECD LEONTFD'!T9 -> 0 | X2: ='OECD LEONTFD'!U9 -> 0 | Y2: ='OECD LEONTFD'!V9 -> 0 | Z2: ='Weighted Avg BEA Multipliers'!AB472 -> 0.00022348092 | AA2: ='Weighted Avg BEA Multipliers'!AC472 -> 0.00010431067 | AB2: ='Weighted Avg BEA Multipliers'!AD472 -> 0.00036695052 | AC2: ='OECD LEONTFD'!X9 -> 0 | AD2: ='OECD LEONTFD'!Y9 -> 0.001 | AE2: ='OECD LEONTFD'!Z9 -> 0 | AF2: ='OECD LEONTFD'!AA9 -> 0.009 | AG2: ='OECD LEONTFD'!AB9 -> 0 | AH2: ='OECD LEONTFD'!AC9 -> 0 | AI2: ='OECD LEONTFD'!AD9 -> 0 | AJ2: ='OECD LEONTFD'!AE9 -> 0 | ... AQ2: ='OECD LEONTFD'!AL9 -> 0
A3: ISIC 05 | B3: ='Weighted Avg BEA Multipliers'!D473 -> 0.0026402269 | C3: ='Weighted Avg BEA Multipliers'!E473 -> 1.08927 | D3: ='Weighted Avg BEA Multipliers'!F473 -> 0.0019034 | E3: ='Weighted Avg BEA Multipliers'!G473 -> 0.0057258045 | F3: ='Weighted Avg BEA Multipliers'!H473 -> 0.0009259352 | G3: ='Weighted Avg BEA Multipliers'!I473 -> 0.0044641371 | H3: ='Weighted Avg BEA Multipliers'!J473 -> 0.0037795621 | I3: ='Weighted Avg BEA Multipliers'!K473 -> 0.0023969017 | ... AQ3: ='Weighted Avg BEA Multipliers'!AS473 -> 0
A4: ISIC 06 | B4: ='Weighted Avg BEA Multipliers'!D474 -> 0.013743178 | C4: ='Weighted Avg BEA Multipliers'!E474 -> 0.0243075 | D4: ='Weighted Avg BEA Multipliers'!F474 -> 1.08943 | E4: ='Weighted Avg BEA Multipliers'!G474 -> 0.030401592 | F4: ='Weighted Avg BEA Multipliers'!H474 -> 0.01000578 | G4: ='Weighted Avg BEA Multipliers'!I474 -> 0.013314126 | H4: ='Weighted Avg BEA Multipliers'!J474 -> 0.015175169 | I4: ='Weighted Avg BEA Multipliers'!K474 -> 0.013443327 | ... AQ4: ='Weighted Avg BEA Multipliers'!AS474 -> 0
A5: ISIC 07T08 | B5: ='OECD LEONTFD'!C11 -> 0.003 | C5: ='Weighted Avg BEA Multipliers'!E475 -> 0.0031371967 | D5: ='Weighted Avg BEA Multipliers'!F475 -> 0.000430351 | E5: ='OECD LEONTFD'!E11 -> 1.142 | F5: ='OECD LEONTFD'!F11 -> 0.026 | G5: ='OECD LEONTFD'!G11 -> 0.001 | H5: ='OECD LEONTFD'!H11 -> 0.002 | I5: ='OECD LEONTFD'!I11 -> 0.004 | J5: ='OECD LEONTFD'!J11 -> 0.007 | K5: ='OECD LEONTFD'!K11 -> 0.005 | L5: ='Weighted Avg BEA Multipliers'!N475 -> 0.0030763197 | M5: ='Weighted Avg BEA Multipliers'!O475 -> 0.00014922534 | N5: ='OECD LEONTFD'!M11 -> 0.006 | O5: ='Weighted Avg BEA Multipliers'!Q475 -> 0.0045476308 | P5: ='Weighted Avg BEA Multipliers'!R475 -> 0.015960324 | Q5: ='Weighted Avg BEA Multipliers'!S475 -> 0.013433242 | R5: ='Weighted Avg BEA Multipliers'!T475 -> 0.017955051 | S5: ='OECD LEONTFD'!P11 -> 0.002 | T5: ='OECD LEONTFD'!Q11 -> 0.001 | U5: ='OECD LEONTFD'!R11 -> 0.001 | V5: ='OECD LEONTFD'!S11 -> 0.003 | W5: ='OECD LEONTFD'!T11 -> 0.002 | X5: ='OECD LEONTFD'!U11 -> 0.002 | Y5: ='OECD LEONTFD'!V11 -> 0.005 | Z5: ='Weighted Avg BEA Multipliers'!AB475 -> 0.00046307766 | AA5: ='Weighted Avg BEA Multipliers'!AC475 -> 0.00015519656 | AB5: ='Weighted Avg BEA Multipliers'!AD475 -> 0.00083755886 | AC5: ='OECD LEONTFD'!X11 -> 0.036 | AD5: ='OECD LEONTFD'!Y11 -> 0.001 | AE5: ='OECD LEONTFD'!Z11 -> 0.001 | AF5: ='OECD LEONTFD'!AA11 -> 0 | AG5: ='OECD LEONTFD'!AB11 -> 0 | AH5: ='OECD LEONTFD'!AC11 -> 0 | AI5: ='OECD LEONTFD'!AD11 -> 0 | AJ5: ='OECD LEONTFD'!AE11 -> 0 | ... AQ5: ='OECD LEONTFD'!AL11 -> 0
A6: ISIC 09 | B6: ='OECD LEONTFD'!C12 -> 0.002 | C6: ='Weighted Avg BEA Multipliers'!E476 -> 0.012285152 | D6: ='Weighted Avg BEA Multipliers'!F476 -> 0.03117161 | E6: ='OECD LEONTFD'!E12 -> 0.006 | F6: ='OECD LEONTFD'!F12 -> 1.016 | G6: ='OECD LEONTFD'!G12 -> 0 | H6: ='OECD LEONTFD'!H12 -> 0 | I6: ='OECD LEONTFD'!I12 -> 0 | J6: ='OECD LEONTFD'!J12 -> 0 | K6: ='OECD LEONTFD'!K12 -> 0.001 | L6: ='Weighted Avg BEA Multipliers'!N476 -> 0.0019003888 | M6: ='Weighted Avg BEA Multipliers'!O476 -> 0.0002180874 | N6: ='OECD LEONTFD'!M12 -> 0 | O6: ='Weighted Avg BEA Multipliers'!Q476 -> 0.0011593057 | P6: ='Weighted Avg BEA Multipliers'!R476 -> 0.0020320267 | Q6: ='Weighted Avg BEA Multipliers'!S476 -> 0.0019424567 | R6: ='Weighted Avg BEA Multipliers'!T476 -> 0.0018622353 | S6: ='OECD LEONTFD'!P12 -> 0 | T6: ='OECD LEONTFD'!Q12 -> 0 | U6: ='OECD LEONTFD'!R12 -> 0 | V6: ='OECD LEONTFD'!S12 -> 0 | W6: ='OECD LEONTFD'!T12 -> 0 | X6: ='OECD LEONTFD'!U12 -> 0 | Y6: ='OECD LEONTFD'!V12 -> 0 | Z6: ='Weighted Avg BEA Multipliers'!AB476 -> 0.0016405896 | AA6: ='Weighted Avg BEA Multipliers'!AC476 -> 0.00519324 | AB6: ='Weighted Avg BEA Multipliers'!AD476 -> 0.00039759986 | AC6: ='OECD LEONTFD'!X12 -> 0.001 | AD6: ='OECD LEONTFD'!Y12 -> 0 | AE6: ='OECD LEONTFD'!Z12 -> 0 | AF6: ='OECD LEONTFD'!AA12 -> 0 | AG6: ='OECD LEONTFD'!AB12 -> 0 | AH6: ='OECD LEONTFD'!AC12 -> 0 | AI6: ='OECD LEONTFD'!AD12 -> 0 | AJ6: ='OECD LEONTFD'!AE12 -> 0 | ... AQ6: ='OECD LEONTFD'!AL12 -> 0
A7: ISIC 10T12 | B7: ='OECD LEONTFD'!C13 -> 0.274 | C7: ='Weighted Avg BEA Multipliers'!E477 -> 4.8390044e-05 | D7: ='Weighted Avg BEA Multipliers'!F477 -> 3.5728165e-05 | E7: ='OECD LEONTFD'!E13 -> 0.012 | F7: ='OECD LEONTFD'!F13 -> 0.016 | G7: ='OECD LEONTFD'!G13 -> 1.43 | H7: ='OECD LEONTFD'!H13 -> 0.049 | I7: ='OECD LEONTFD'!I13 -> 0.032 | J7: ='OECD LEONTFD'!J13 -> 0.032 | K7: ='OECD LEONTFD'!K13 -> 0.017 | L7: ='Weighted Avg BEA Multipliers'!N477 -> 0.00039934201 | M7: ='Weighted Avg BEA Multipliers'!O477 -> 0.00073157925 | N7: ='OECD LEONTFD'!M13 -> 0.02 | O7: ='Weighted Avg BEA Multipliers'!Q477 -> 6.416523e-05 | P7: ='Weighted Avg BEA Multipliers'!R477 -> 9.254891e-05 | Q7: ='Weighted Avg BEA Multipliers'!S477 -> 0.00018007689 | R7: ='Weighted Avg BEA Multipliers'!T477 -> 4.5765354e-05 | S7: ='OECD LEONTFD'!P13 -> 0.004 | T7: ='OECD LEONTFD'!Q13 -> 0.006 | U7: ='OECD LEONTFD'!R13 -> 0.003 | V7: ='OECD LEONTFD'!S13 -> 0.006 | W7: ='OECD LEONTFD'!T13 -> 0.006 | X7: ='OECD LEONTFD'!U13 -> 0.007 | Y7: ='OECD LEONTFD'!V13 -> 0.009 | Z7: ='Weighted Avg BEA Multipliers'!AB477 -> 4.7515498e-05 | AA7: ='Weighted Avg BEA Multipliers'!AC477 -> 4.2581032e-05 | AB7: ='Weighted Avg BEA Multipliers'!AD477 -> 8.6533041e-05 | AC7: ='OECD LEONTFD'!X13 -> 0.01 | AD7: ='OECD LEONTFD'!Y13 -> 0.018 | AE7: ='OECD LEONTFD'!Z13 -> 0.008 | AF7: ='OECD LEONTFD'!AA13 -> 0.317 | AG7: ='OECD LEONTFD'!AB13 -> 0.011 | AH7: ='OECD LEONTFD'!AC13 -> 0.004 | AI7: ='OECD LEONTFD'!AD13 -> 0.006 | AJ7: ='OECD LEONTFD'!AE13 -> 0.004 | ... AQ7: ='OECD LEONTFD'!AL13 -> 0
A8: ISIC 13T15 | B8: ='OECD LEONTFD'!C14 -> 0.013 | C8: ='Weighted Avg BEA Multipliers'!E478 -> 8.3947041e-05 | D8: ='Weighted Avg BEA Multipliers'!F478 -> 3.2868661e-05 | E8: ='OECD LEONTFD'!E14 -> 0.015 | F8: ='OECD LEONTFD'!F14 -> 0.025 | G8: ='OECD LEONTFD'!G14 -> 0.015 | H8: ='OECD LEONTFD'!H14 -> 1.221 | I8: ='OECD LEONTFD'!I14 -> 0.04 | J8: ='OECD LEONTFD'!J14 -> 0.01 | K8: ='OECD LEONTFD'!K14 -> 0.01 | L8: ='Weighted Avg BEA Multipliers'!N478 -> 0.00014256418 | M8: ='Weighted Avg BEA Multipliers'!O478 -> 5.3661775e-05 | N8: ='OECD LEONTFD'!M14 -> 0.017 | O8: ='Weighted Avg BEA Multipliers'!Q478 -> 0.00012484643 | P8: ='Weighted Avg BEA Multipliers'!R478 -> 0.00058237112 | Q8: ='Weighted Avg BEA Multipliers'!S478 -> 0.00013648352 | R8: ='Weighted Avg BEA Multipliers'!T478 -> 7.6744028e-05 | S8: ='OECD LEONTFD'!P14 -> 0.006 | T8: ='OECD LEONTFD'!Q14 -> 0.01 | U8: ='OECD LEONTFD'!R14 -> 0.006 | V8: ='OECD LEONTFD'!S14 -> 0.01 | W8: ='OECD LEONTFD'!T14 -> 0.017 | X8: ='OECD LEONTFD'!U14 -> 0.017 | Y8: ='OECD LEONTFD'!V14 -> 0.032 | Z8: ='Weighted Avg BEA Multipliers'!AB478 -> 2.7894273e-05 | AA8: ='Weighted Avg BEA Multipliers'!AC478 -> 2.9689394e-05 | AB8: ='Weighted Avg BEA Multipliers'!AD478 -> 0.00034328169 | AC8: ='OECD LEONTFD'!X14 -> 0.01 | AD8: ='OECD LEONTFD'!Y14 -> 0.015 | AE8: ='OECD LEONTFD'!Z14 -> 0.008 | AF8: ='OECD LEONTFD'!AA14 -> 0.011 | AG8: ='OECD LEONTFD'!AB14 -> 0.014 | AH8: ='OECD LEONTFD'!AC14 -> 0.006 | AI8: ='OECD LEONTFD'!AD14 -> 0.008 | AJ8: ='OECD LEONTFD'!AE14 -> 0.003 | ... AQ8: ='OECD LEONTFD'!AL14 -> 0
A9: ISIC 16 | B9: ='OECD LEONTFD'!C15 -> 0.002 | C9: ='Weighted Avg BEA Multipliers'!E479 -> 0.00097287326 | D9: ='Weighted Avg BEA Multipliers'!F479 -> 0.00020176302 | E9: ='OECD LEONTFD'!E15 -> 0.005 | F9: ='OECD LEONTFD'!F15 -> 0.005 | G9: ='OECD LEONTFD'!G15 -> 0.001 | H9: ='OECD LEONTFD'!H15 -> 0.002 | I9: ='OECD LEONTFD'!I15 -> 1.36 | J9: ='OECD LEONTFD'!J15 -> 0.016 | K9: ='OECD LEONTFD'!K15 -> 0.002 | L9: ='Weighted Avg BEA Multipliers'!N479 -> 0.00060753085 | M9: ='Weighted Avg BEA Multipliers'!O479 -> 0.00021991061 | N9: ='OECD LEONTFD'!M15 -> 0.005 | O9: ='Weighted Avg BEA Multipliers'!Q479 -> 0.0012505455 | P9: ='Weighted Avg BEA Multipliers'!R479 -> 0.0019075598 | Q9: ='Weighted Avg BEA Multipliers'!S479 -> 0.00098361309 | R9: ='Weighted Avg BEA Multipliers'!T479 -> 0.0013599078 | S9: ='OECD LEONTFD'!P15 -> 0.002 | T9: ='OECD LEONTFD'!Q15 -> 0.002 | U9: ='OECD LEONTFD'!R15 -> 0.001 | V9: ='OECD LEONTFD'!S15 -> 0.002 | W9: ='OECD LEONTFD'!T15 -> 0.004 | X9: ='OECD LEONTFD'!U15 -> 0.006 | Y9: ='OECD LEONTFD'!V15 -> 0.046 | Z9: ='Weighted Avg BEA Multipliers'!AB479 -> 0.0003975535 | AA9: ='Weighted Avg BEA Multipliers'!AC479 -> 0.00017855317 | AB9: ='Weighted Avg BEA Multipliers'!AD479 -> 0.00035079213 | AC9: ='OECD LEONTFD'!X15 -> 0.03 | AD9: ='OECD LEONTFD'!Y15 -> 0.001 | AE9: ='OECD LEONTFD'!Z15 -> 0.001 | AF9: ='OECD LEONTFD'!AA15 -> 0.001 | AG9: ='OECD LEONTFD'!AB15 -> 0.001 | AH9: ='OECD LEONTFD'!AC15 -> 0.001 | AI9: ='OECD LEONTFD'!AD15 -> 0.001 | AJ9: ='OECD LEONTFD'!AE15 -> 0 | ... AQ9: ='OECD LEONTFD'!AL15 -> 0
A10: ISIC 17T18 | B10: ='OECD LEONTFD'!C16 -> 0 | C10: ='Weighted Avg BEA Multipliers'!E480 -> 0.0011755592 | D10: ='Weighted Avg BEA Multipliers'!F480 -> 0.00069282355 | E10: ='OECD LEONTFD'!E16 -> 0 | F10: ='OECD LEONTFD'!F16 -> 0 | G10: ='OECD LEONTFD'!G16 -> 0 | H10: ='OECD LEONTFD'!H16 -> 0 | I10: ='OECD LEONTFD'!I16 -> 0.001 | J10: ='OECD LEONTFD'!J16 -> 1.006 | K10: ='OECD LEONTFD'!K16 -> 0 | L10: ='Weighted Avg BEA Multipliers'!N480 -> 0.0037505594 | M10: ='Weighted Avg BEA Multipliers'!O480 -> 0.0031215902 | N10: ='OECD LEONTFD'!M16 -> 0 | O10: ='Weighted Avg BEA Multipliers'!Q480 -> 0.0061699358 | P10: ='Weighted Avg BEA Multipliers'!R480 -> 0.00329503 | Q10: ='Weighted Avg BEA Multipliers'!S480 -> 0.0043331966 | R10: ='Weighted Avg BEA Multipliers'!T480 -> 0.0028407013 | S10: ='OECD LEONTFD'!P16 -> 0 | T10: ='OECD LEONTFD'!Q16 -> 0 | U10: ='OECD LEONTFD'!R16 -> 0 | V10: ='OECD LEONTFD'!S16 -> 0 | W10: ='OECD LEONTFD'!T16 -> 0 | X10: ='OECD LEONTFD'!U16 -> 0 | Y10: ='OECD LEONTFD'!V16 -> 0 | Z10: ='Weighted Avg BEA Multipliers'!AB480 -> 0.00058671539 | AA10: ='Weighted Avg BEA Multipliers'!AC480 -> 0.00058980351 | AB10: ='Weighted Avg BEA Multipliers'!AD480 -> 0.001422224 | AC10: ='OECD LEONTFD'!X16 -> 0 | AD10: ='OECD LEONTFD'!Y16 -> 0 | AE10: ='OECD LEONTFD'!Z16 -> 0 | AF10: ='OECD LEONTFD'!AA16 -> 0 | AG10: ='OECD LEONTFD'!AB16 -> 0.002 | AH10: ='OECD LEONTFD'!AC16 -> 0 | AI10: ='OECD LEONTFD'!AD16 -> 0 | AJ10: ='OECD LEONTFD'!AE16 -> 0 | ... AQ10: ='OECD LEONTFD'!AL16 -> 0
A11: ISIC 19 | B11: ='OECD LEONTFD'!C17 -> 0.03 | C11: ='Weighted Avg BEA Multipliers'!E481 -> 0.060065732 | D11: ='Weighted Avg BEA Multipliers'!F481 -> 0.022708045 | E11: ='OECD LEONTFD'!E17 -> 0.082 | F11: ='OECD LEONTFD'!F17 -> 0.066 | G11: ='OECD LEONTFD'!G17 -> 0.008 | H11: ='OECD LEONTFD'!H17 -> 0.013 | I11: ='OECD LEONTFD'!I17 -> 0.033 | J11: ='OECD LEONTFD'!J17 -> 0.018 | K11: ='OECD LEONTFD'!K17 -> 1.154 | L11: ='Weighted Avg BEA Multipliers'!N481 -> 0.10586097 | M11: ='Weighted Avg BEA Multipliers'!O481 -> 0.013940628 | N11: ='OECD LEONTFD'!M17 -> 0.02 | O11: ='Weighted Avg BEA Multipliers'!Q481 -> 0.033651967 | P11: ='Weighted Avg BEA Multipliers'!R481 -> 0.038328871 | Q11: ='Weighted Avg BEA Multipliers'!S481 -> 0.036553834 | R11: ='Weighted Avg BEA Multipliers'!T481 -> 0.022056971 | S11: ='OECD LEONTFD'!P17 -> 0.006 | T11: ='OECD LEONTFD'!Q17 -> 0.008 | U11: ='OECD LEONTFD'!R17 -> 0.004 | V11: ='OECD LEONTFD'!S17 -> 0.009 | W11: ='OECD LEONTFD'!T17 -> 0.008 | X11: ='OECD LEONTFD'!U17 -> 0.007 | Y11: ='OECD LEONTFD'!V17 -> 0.009 | Z11: ='Weighted Avg BEA Multipliers'!AB481 -> 0.038776857 | AA11: ='Weighted Avg BEA Multipliers'!AC481 -> 0.0092523058 | AB11: ='Weighted Avg BEA Multipliers'!AD481 -> 0.025155287 | AC11: ='OECD LEONTFD'!X17 -> 0.024 | AD11: ='OECD LEONTFD'!Y17 -> 0.008 | AE11: ='OECD LEONTFD'!Z17 -> 0.05 | AF11: ='OECD LEONTFD'!AA17 -> 0.006 | AG11: ='OECD LEONTFD'!AB17 -> 0.008 | AH11: ='OECD LEONTFD'!AC17 -> 0.005 | AI11: ='OECD LEONTFD'!AD17 -> 0.006 | AJ11: ='OECD LEONTFD'!AE17 -> 0.004 | ... AQ11: ='OECD LEONTFD'!AL17 -> 0
A12: ISIC 20 | B12: ='Weighted Avg BEA Multipliers'!D482 -> 0.0073918355 | C12: ='Weighted Avg BEA Multipliers'!E482 -> 0.0036617919 | D12: ='Weighted Avg BEA Multipliers'!F482 -> 0.003173782 | E12: ='Weighted Avg BEA Multipliers'!G482 -> 0.0061211696 | F12: ='Weighted Avg BEA Multipliers'!H482 -> 0.0026872515 | G12: ='Weighted Avg BEA Multipliers'!I482 -> 0.0086131234 | H12: ='Weighted Avg BEA Multipliers'!J482 -> 0.023532605 | I12: ='Weighted Avg BEA Multipliers'!K482 -> 0.0070279062 | ... AQ12: ='Weighted Avg BEA Multipliers'!AS482 -> 0
A13: ISIC 21 | B13: ='Weighted Avg BEA Multipliers'!D483 -> 0.00079814151 | C13: ='Weighted Avg BEA Multipliers'!E483 -> 1.3889469e-05 | D13: ='Weighted Avg BEA Multipliers'!F483 -> 8.2287732e-06 | E13: ='Weighted Avg BEA Multipliers'!G483 -> 2.1035717e-05 | F13: ='Weighted Avg BEA Multipliers'!H483 -> 1.463426e-05 | G13: ='Weighted Avg BEA Multipliers'!I483 -> 0.00047078027 | H13: ='Weighted Avg BEA Multipliers'!J483 -> 4.4867472e-05 | I13: ='Weighted Avg BEA Multipliers'!K483 -> 0.00013963272 | ... AQ13: ='Weighted Avg BEA Multipliers'!AS483 -> 0
A14: ISIC 22 | B14: ='OECD LEONTFD'!C19 -> 0.002 | C14: ='Weighted Avg BEA Multipliers'!E484 -> 0.0020630093 | D14: ='Weighted Avg BEA Multipliers'!F484 -> 0.00064982598 | E14: ='OECD LEONTFD'!E19 -> 0.004 | F14: ='OECD LEONTFD'!F19 -> 0.004 | G14: ='OECD LEONTFD'!G19 -> 0.003 | H14: ='OECD LEONTFD'!H19 -> 0.004 | I14: ='OECD LEONTFD'!I19 -> 0.006 | J14: ='OECD LEONTFD'!J19 -> 0.005 | K14: ='OECD LEONTFD'!K19 -> 0.002 | L14: ='Weighted Avg BEA Multipliers'!N484 -> 0.0042839434 | M14: ='Weighted Avg BEA Multipliers'!O484 -> 0.002758145 | N14: ='OECD LEONTFD'!M19 -> 1.031 | O14: ='Weighted Avg BEA Multipliers'!Q484 -> 0.004173762 | P14: ='Weighted Avg BEA Multipliers'!R484 -> 0.0040823381 | Q14: ='Weighted Avg BEA Multipliers'!S484 -> 0.0021917177 | R14: ='Weighted Avg BEA Multipliers'!T484 -> 0.001571186 | S14: ='OECD LEONTFD'!P19 -> 0.001 | T14: ='OECD LEONTFD'!Q19 -> 0.005 | U14: ='OECD LEONTFD'!R19 -> 0.002 | V14: ='OECD LEONTFD'!S19 -> 0.004 | W14: ='OECD LEONTFD'!T19 -> 0.009 | X14: ='OECD LEONTFD'!U19 -> 0.003 | Y14: ='OECD LEONTFD'!V19 -> 0.004 | Z14: ='Weighted Avg BEA Multipliers'!AB484 -> 0.00053201899 | AA14: ='Weighted Avg BEA Multipliers'!AC484 -> 0.00038799534 | AB14: ='Weighted Avg BEA Multipliers'!AD484 -> 0.0014438811 | AC14: ='OECD LEONTFD'!X19 -> 0.006 | AD14: ='OECD LEONTFD'!Y19 -> 0.001 | AE14: ='OECD LEONTFD'!Z19 -> 0.001 | AF14: ='OECD LEONTFD'!AA19 -> 0.001 | AG14: ='OECD LEONTFD'!AB19 -> 0.001 | AH14: ='OECD LEONTFD'!AC19 -> 0.001 | AI14: ='OECD LEONTFD'!AD19 -> 0 | AJ14: ='OECD LEONTFD'!AE19 -> 0 | ... AQ14: ='OECD LEONTFD'!AL19 -> 0
A15: ISIC 231 | B15: ='Weighted Avg BEA Multipliers'!D485 -> 0.00045576164 | C15: ='Weighted Avg BEA Multipliers'!E485 -> 0.0001691 | D15: ='Weighted Avg BEA Multipliers'!F485 -> 0.0001226 | E15: ='Weighted Avg BEA Multipliers'!G485 -> 0.00020333799 | F15: ='Weighted Avg BEA Multipliers'!H485 -> 0.00018517648 | G15: ='Weighted Avg BEA Multipliers'!I485 -> 0.0052564122 | H15: ='Weighted Avg BEA Multipliers'!J485 -> 0.0019710091 | I15: ='Weighted Avg BEA Multipliers'!K485 -> 0.0020262942 | ... AQ15: ='Weighted Avg BEA Multipliers'!AS485 -> 0
A16: ISIC 239 | B16: ='Weighted Avg BEA Multipliers'!D486 -> 0.00016508363 | C16: ='Weighted Avg BEA Multipliers'!E486 -> 0.0005374531 | D16: ='Weighted Avg BEA Multipliers'!F486 -> 0.00031293118 | E16: ='Weighted Avg BEA Multipliers'!G486 -> 0.00070986614 | F16: ='Weighted Avg BEA Multipliers'!H486 -> 0.00040121696 | G16: ='Weighted Avg BEA Multipliers'!I486 -> 0.0001467997 | H16: ='Weighted Avg BEA Multipliers'!J486 -> 0.00012835261 | I16: ='Weighted Avg BEA Multipliers'!K486 -> 0.00059090674 | ... AQ16: ='Weighted Avg BEA Multipliers'!AS486 -> 0
A17: ISIC 241 | B17: ='Weighted Avg BEA Multipliers'!D487 -> 0.0017905589 | C17: ='Weighted Avg BEA Multipliers'!E487 -> 0.0061225663 | D17: ='Weighted Avg BEA Multipliers'!F487 -> 0.010847028 | E17: ='Weighted Avg BEA Multipliers'!G487 -> 0.012659595 | F17: ='Weighted Avg BEA Multipliers'!H487 -> 0.0052851986 | G17: ='Weighted Avg BEA Multipliers'!I487 -> 0.0034720234 | H17: ='Weighted Avg BEA Multipliers'!J487 -> 0.0042326015 | I17: ='Weighted Avg BEA Multipliers'!K487 -> 0.0069278629 | ... AQ17: ='Weighted Avg BEA Multipliers'!AS487 -> 0
A18: ISIC 242 | B18: ='Weighted Avg BEA Multipliers'!D488 -> 0.00023665584 | C18: ='Weighted Avg BEA Multipliers'!E488 -> 0.00053333216 | D18: ='Weighted Avg BEA Multipliers'!F488 -> 0.00048998175 | E18: ='Weighted Avg BEA Multipliers'!G488 -> 0.00061785833 | F18: ='Weighted Avg BEA Multipliers'!H488 -> 0.0004682479 | G18: ='Weighted Avg BEA Multipliers'!I488 -> 0.0025664241 | H18: ='Weighted Avg BEA Multipliers'!J488 -> 0.00036653095 | I18: ='Weighted Avg BEA Multipliers'!K488 -> 0.00091787669 | ... AQ18: ='Weighted Avg BEA Multipliers'!AS488 -> 0
A19: ISIC 25 | B19: ='OECD LEONTFD'!C22 -> 0 | C19: ='Weighted Avg BEA Multipliers'!E489 -> 0.0016006963 | D19: ='Weighted Avg BEA Multipliers'!F489 -> 0.0018839264 | E19: ='OECD LEONTFD'!E22 -> 0.001 | F19: ='OECD LEONTFD'!F22 -> 0.001 | G19: ='OECD LEONTFD'!G22 -> 0 | H19: ='OECD LEONTFD'!H22 -> 0 | I19: ='OECD LEONTFD'!I22 -> 0.002 | J19: ='OECD LEONTFD'!J22 -> 0 | K19: ='OECD LEONTFD'!K22 -> 0 | L19: ='Weighted Avg BEA Multipliers'!N489 -> 0.0019514917 | M19: ='Weighted Avg BEA Multipliers'!O489 -> 0.00030849987 | N19: ='OECD LEONTFD'!M22 -> 0.001 | O19: ='Weighted Avg BEA Multipliers'!Q489 -> 0.0021242907 | P19: ='Weighted Avg BEA Multipliers'!R489 -> 0.0032473687 | Q19: ='Weighted Avg BEA Multipliers'!S489 -> 0.0054401042 | R19: ='Weighted Avg BEA Multipliers'!T489 -> 0.004059456 | S19: ='OECD LEONTFD'!P22 -> 1.002 | T19: ='OECD LEONTFD'!Q22 -> 0.001 | U19: ='OECD LEONTFD'!R22 -> 0 | V19: ='OECD LEONTFD'!S22 -> 0.002 | W19: ='OECD LEONTFD'!T22 -> 0.002 | X19: ='OECD LEONTFD'!U22 -> 0.001 | Y19: ='OECD LEONTFD'!V22 -> 0.001 | Z19: ='Weighted Avg BEA Multipliers'!AB489 -> 0.00044786765 | AA19: ='Weighted Avg BEA Multipliers'!AC489 -> 0.00073460885 | AB19: ='Weighted Avg BEA Multipliers'!AD489 -> 0.0025920701 | AC19: ='OECD LEONTFD'!X22 -> 0.002 | AD19: ='OECD LEONTFD'!Y22 -> 0 | AE19: ='OECD LEONTFD'!Z22 -> 0 | AF19: ='OECD LEONTFD'!AA22 -> 0 | AG19: ='OECD LEONTFD'!AB22 -> 0 | AH19: ='OECD LEONTFD'!AC22 -> 0 | AI19: ='OECD LEONTFD'!AD22 -> 0 | AJ19: ='OECD LEONTFD'!AE22 -> 0 | ... AQ19: ='OECD LEONTFD'!AL22 -> 0
A20: ISIC 26 | B20: ='OECD LEONTFD'!C23 -> 0.001 | C20: ='Weighted Avg BEA Multipliers'!E490 -> 0.00020746635 | D20: ='Weighted Avg BEA Multipliers'!F490 -> 0.00014001358 | E20: ='OECD LEONTFD'!E23 -> 0.002 | F20: ='OECD LEONTFD'!F23 -> 0.003 | G20: ='OECD LEONTFD'!G23 -> 0 | H20: ='OECD LEONTFD'!H23 -> 0.001 | I20: ='OECD LEONTFD'!I23 -> 0.002 | J20: ='OECD LEONTFD'!J23 -> 0.002 | K20: ='OECD LEONTFD'!K23 -> 0.001 | L20: ='Weighted Avg BEA Multipliers'!N490 -> 0.00080928569 | M20: ='Weighted Avg BEA Multipliers'!O490 -> 0.00012078361 | N20: ='OECD LEONTFD'!M23 -> 0.002 | O20: ='Weighted Avg BEA Multipliers'!Q490 -> 0.0011022202 | P20: ='Weighted Avg BEA Multipliers'!R490 -> 0.00090920837 | Q20: ='Weighted Avg BEA Multipliers'!S490 -> 0.00065263018 | R20: ='Weighted Avg BEA Multipliers'!T490 -> 0.001225647 | S20: ='OECD LEONTFD'!P23 -> 0.001 | T20: ='OECD LEONTFD'!Q23 -> 1.1 | U20: ='OECD LEONTFD'!R23 -> 0.004 | V20: ='OECD LEONTFD'!S23 -> 0.006 | W20: ='OECD LEONTFD'!T23 -> 0.006 | X20: ='OECD LEONTFD'!U23 -> 0.003 | Y20: ='OECD LEONTFD'!V23 -> 0.002 | Z20: ='Weighted Avg BEA Multipliers'!AB490 -> 7.4960734e-05 | AA20: ='Weighted Avg BEA Multipliers'!AC490 -> 7.9689758e-05 | AB20: ='Weighted Avg BEA Multipliers'!AD490 -> 0.00041158355 | AC20: ='OECD LEONTFD'!X23 -> 0.002 | AD20: ='OECD LEONTFD'!Y23 -> 0.001 | AE20: ='OECD LEONTFD'!Z23 -> 0.001 | AF20: ='OECD LEONTFD'!AA23 -> 0.001 | AG20: ='OECD LEONTFD'!AB23 -> 0.002 | AH20: ='OECD LEONTFD'!AC23 -> 0.01 | AI20: ='OECD LEONTFD'!AD23 -> 0.006 | AJ20: ='OECD LEONTFD'!AE23 -> 0.001 | ... AQ20: ='OECD LEONTFD'!AL23 -> 0
A21: ISIC 27 | B21: ='OECD LEONTFD'!C24 -> 0.001 | C21: ='Weighted Avg BEA Multipliers'!E491 -> 0.00011552758 | D21: ='Weighted Avg BEA Multipliers'!F491 -> 0.00011759371 | E21: ='OECD LEONTFD'!E24 -> 0.004 | F21: ='OECD LEONTFD'!F24 -> 0.004 | G21: ='OECD LEONTFD'!G24 -> 0.001 | H21: ='OECD LEONTFD'!H24 -> 0.001 | I21: ='OECD LEONTFD'!I24 -> 0.003 | J21: ='OECD LEONTFD'!J24 -> 0.002 | K21: ='OECD LEONTFD'!K24 -> 0.002 | L21: ='Weighted Avg BEA Multipliers'!N491 -> 0.00016310068 | M21: ='Weighted Avg BEA Multipliers'!O491 -> 4.0447786e-05 | N21: ='OECD LEONTFD'!M24 -> 0.003 | O21: ='Weighted Avg BEA Multipliers'!Q491 -> 0.00027939343 | P21: ='Weighted Avg BEA Multipliers'!R491 -> 0.00015065807 | Q21: ='Weighted Avg BEA Multipliers'!S491 -> 0.00041634698 | R21: ='Weighted Avg BEA Multipliers'!T491 -> 0.0013445855 | S21: ='OECD LEONTFD'!P24 -> 0.002 | T21: ='OECD LEONTFD'!Q24 -> 0.022 | U21: ='OECD LEONTFD'!R24 -> 1.023 | V21: ='OECD LEONTFD'!S24 -> 0.014 | W21: ='OECD LEONTFD'!T24 -> 0.014 | X21: ='OECD LEONTFD'!U24 -> 0.007 | Y21: ='OECD LEONTFD'!V24 -> 0.003 | Z21: ='Weighted Avg BEA Multipliers'!AB491 -> 9.5767037e-05 | AA21: ='Weighted Avg BEA Multipliers'!AC491 -> 6.3517369e-05 | AB21: ='Weighted Avg BEA Multipliers'!AD491 -> 0.0002685632 | AC21: ='OECD LEONTFD'!X24 -> 0.012 | AD21: ='OECD LEONTFD'!Y24 -> 0.001 | AE21: ='OECD LEONTFD'!Z24 -> 0.001 | AF21: ='OECD LEONTFD'!AA24 -> 0.001 | AG21: ='OECD LEONTFD'!AB24 -> 0.001 | AH21: ='OECD LEONTFD'!AC24 -> 0.003 | AI21: ='OECD LEONTFD'!AD24 -> 0.002 | AJ21: ='OECD LEONTFD'!AE24 -> 0 | ... AQ21: ='OECD LEONTFD'!AL24 -> 0
A22: ISIC 28 | B22: ='OECD LEONTFD'!C25 -> 0.002 | C22: ='Weighted Avg BEA Multipliers'!E492 -> 0.0017958815 | D22: ='Weighted Avg BEA Multipliers'!F492 -> 0.0007153966 | E22: ='OECD LEONTFD'!E25 -> 0.01 | F22: ='OECD LEONTFD'!F25 -> 0.015 | G22: ='OECD LEONTFD'!G25 -> 0.001 | H22: ='OECD LEONTFD'!H25 -> 0.002 | I22: ='OECD LEONTFD'!I25 -> 0.004 | J22: ='OECD LEONTFD'!J25 -> 0.003 | K22: ='OECD LEONTFD'!K25 -> 0.002 | L22: ='Weighted Avg BEA Multipliers'!N492 -> 0.00026613648 | M22: ='Weighted Avg BEA Multipliers'!O492 -> 4.853261e-05 | N22: ='OECD LEONTFD'!M25 -> 0.002 | O22: ='Weighted Avg BEA Multipliers'!Q492 -> 0.00022507237 | P22: ='Weighted Avg BEA Multipliers'!R492 -> 0.00023821033 | Q22: ='Weighted Avg BEA Multipliers'!S492 -> 0.00050787413 | R22: ='Weighted Avg BEA Multipliers'!T492 -> 0.00035941281 | S22: ='OECD LEONTFD'!P25 -> 0.002 | T22: ='OECD LEONTFD'!Q25 -> 0.002 | U22: ='OECD LEONTFD'!R25 -> 0.001 | V22: ='OECD LEONTFD'!S25 -> 1.02 | W22: ='OECD LEONTFD'!T25 -> 0.007 | X22: ='OECD LEONTFD'!U25 -> 0.007 | Y22: ='OECD LEONTFD'!V25 -> 0.002 | Z22: ='Weighted Avg BEA Multipliers'!AB492 -> 0.00017106672 | AA22: ='Weighted Avg BEA Multipliers'!AC492 -> 0.00016021804 | AB22: ='Weighted Avg BEA Multipliers'!AD492 -> 0.00085774693 | AC22: ='OECD LEONTFD'!X25 -> 0.004 | AD22: ='OECD LEONTFD'!Y25 -> 0.001 | AE22: ='OECD LEONTFD'!Z25 -> 0.001 | AF22: ='OECD LEONTFD'!AA25 -> 0 | AG22: ='OECD LEONTFD'!AB25 -> 0 | AH22: ='OECD LEONTFD'!AC25 -> 0 | AI22: ='OECD LEONTFD'!AD25 -> 0 | AJ22: ='OECD LEONTFD'!AE25 -> 0 | ... AQ22: ='OECD LEONTFD'!AL25 -> 0
A23: ISIC 29 | B23: ='OECD LEONTFD'!C26 -> 0.001 | C23: ='Weighted Avg BEA Multipliers'!E493 -> 0.00053780033 | D23: ='Weighted Avg BEA Multipliers'!F493 -> 0.0001966581 | E23: ='OECD LEONTFD'!E26 -> 0.004 | F23: ='OECD LEONTFD'!F26 -> 0.004 | G23: ='OECD LEONTFD'!G26 -> 0.001 | H23: ='OECD LEONTFD'!H26 -> 0.001 | I23: ='OECD LEONTFD'!I26 -> 0.004 | J23: ='OECD LEONTFD'!J26 -> 0.001 | K23: ='OECD LEONTFD'!K26 -> 0.001 | L23: ='Weighted Avg BEA Multipliers'!N493 -> 0.00027873548 | M23: ='Weighted Avg BEA Multipliers'!O493 -> 8.5801045e-05 | N23: ='OECD LEONTFD'!M26 -> 0.002 | O23: ='Weighted Avg BEA Multipliers'!Q493 -> 0.00035797055 | P23: ='Weighted Avg BEA Multipliers'!R493 -> 0.00049138317 | Q23: ='Weighted Avg BEA Multipliers'!S493 -> 0.0013908673 | R23: ='Weighted Avg BEA Multipliers'!T493 -> 0.00034280753 | S23: ='OECD LEONTFD'!P26 -> 0.001 | T23: ='OECD LEONTFD'!Q26 -> 0.001 | U23: ='OECD LEONTFD'!R26 -> 0.001 | V23: ='OECD LEONTFD'!S26 -> 0.005 | W23: ='OECD LEONTFD'!T26 -> 1.113 | X23: ='OECD LEONTFD'!U26 -> 0.002 | Y23: ='OECD LEONTFD'!V26 -> 0.001 | Z23: ='Weighted Avg BEA Multipliers'!AB493 -> 8.2545019e-05 | AA23: ='Weighted Avg BEA Multipliers'!AC493 -> 7.8661737e-05 | AB23: ='Weighted Avg BEA Multipliers'!AD493 -> 0.0011674874 | AC23: ='OECD LEONTFD'!X26 -> 0.002 | AD23: ='OECD LEONTFD'!Y26 -> 0.004 | AE23: ='OECD LEONTFD'!Z26 -> 0.003 | AF23: ='OECD LEONTFD'!AA26 -> 0.001 | AG23: ='OECD LEONTFD'!AB26 -> 0.001 | AH23: ='OECD LEONTFD'!AC26 -> 0.001 | AI23: ='OECD LEONTFD'!AD26 -> 0.001 | AJ23: ='OECD LEONTFD'!AE26 -> 0 | ... AQ23: ='OECD LEONTFD'!AL26 -> 0
A24: ISIC 30 | B24: ='OECD LEONTFD'!C27 -> 0.001 | C24: ='Weighted Avg BEA Multipliers'!E494 -> 0.0001137889 | D24: ='Weighted Avg BEA Multipliers'!F494 -> 2.7788818e-05 | E24: ='OECD LEONTFD'!E27 -> 0 | F24: ='OECD LEONTFD'!F27 -> 0 | G24: ='OECD LEONTFD'!G27 -> 0 | H24: ='OECD LEONTFD'!H27 -> 0 | I24: ='OECD LEONTFD'!I27 -> 0 | J24: ='OECD LEONTFD'!J27 -> 0 | K24: ='OECD LEONTFD'!K27 -> 0 | L24: ='Weighted Avg BEA Multipliers'!N494 -> 3.4596057e-05 | M24: ='Weighted Avg BEA Multipliers'!O494 -> 8.7361854e-06 | N24: ='OECD LEONTFD'!M27 -> 0 | O24: ='Weighted Avg BEA Multipliers'!Q494 -> 5.6719701e-05 | P24: ='Weighted Avg BEA Multipliers'!R494 -> 5.7203362e-05 | Q24: ='Weighted Avg BEA Multipliers'!S494 -> 0.00021402426 | R24: ='Weighted Avg BEA Multipliers'!T494 -> 3.2848821e-05 | S24: ='OECD LEONTFD'!P27 -> 0 | T24: ='OECD LEONTFD'!Q27 -> 0 | U24: ='OECD LEONTFD'!R27 -> 0 | V24: ='OECD LEONTFD'!S27 -> 0 | W24: ='OECD LEONTFD'!T27 -> 0 | X24: ='OECD LEONTFD'!U27 -> 1.021 | Y24: ='OECD LEONTFD'!V27 -> 0 | Z24: ='Weighted Avg BEA Multipliers'!AB494 -> 4.2190161e-05 | AA24: ='Weighted Avg BEA Multipliers'!AC494 -> 1.6617532e-05 | AB24: ='Weighted Avg BEA Multipliers'!AD494 -> 3.7731154e-05 | AC24: ='OECD LEONTFD'!X27 -> 0 | AD24: ='OECD LEONTFD'!Y27 -> 0 | AE24: ='OECD LEONTFD'!Z27 -> 0.002 | AF24: ='OECD LEONTFD'!AA27 -> 0 | AG24: ='OECD LEONTFD'!AB27 -> 0 | AH24: ='OECD LEONTFD'!AC27 -> 0 | AI24: ='OECD LEONTFD'!AD27 -> 0 | AJ24: ='OECD LEONTFD'!AE27 -> 0 | ... AQ24: ='OECD LEONTFD'!AL27 -> 0
A25: ISIC 31T33 | B25: ='OECD LEONTFD'!C28 -> 0.001 | C25: ='Weighted Avg BEA Multipliers'!E495 -> 0.00043596239 | D25: ='Weighted Avg BEA Multipliers'!F495 -> 0.00029847403 | E25: ='OECD LEONTFD'!E28 -> 0.001 | F25: ='OECD LEONTFD'!F28 -> 0.001 | G25: ='OECD LEONTFD'!G28 -> 0.003 | H25: ='OECD LEONTFD'!H28 -> 0.002 | I25: ='OECD LEONTFD'!I28 -> 0.002 | J25: ='OECD LEONTFD'!J28 -> 0.004 | K25: ='OECD LEONTFD'!K28 -> 0 | L25: ='Weighted Avg BEA Multipliers'!N495 -> 0.0009299995 | M25: ='Weighted Avg BEA Multipliers'!O495 -> 0.00038375538 | N25: ='OECD LEONTFD'!M28 -> 0.001 | O25: ='Weighted Avg BEA Multipliers'!Q495 -> 0.0011721956 | P25: ='Weighted Avg BEA Multipliers'!R495 -> 0.0010637019 | Q25: ='Weighted Avg BEA Multipliers'!S495 -> 0.0010085308 | R25: ='Weighted Avg BEA Multipliers'!T495 -> 0.00075036502 | S25: ='OECD LEONTFD'!P28 -> 0 | T25: ='OECD LEONTFD'!Q28 -> 0 | U25: ='OECD LEONTFD'!R28 -> 0 | V25: ='OECD LEONTFD'!S28 -> 0.001 | W25: ='OECD LEONTFD'!T28 -> 0.001 | X25: ='OECD LEONTFD'!U28 -> 0.001 | Y25: ='OECD LEONTFD'!V28 -> 1.002 | Z25: ='Weighted Avg BEA Multipliers'!AB495 -> 0.00024495313 | AA25: ='Weighted Avg BEA Multipliers'!AC495 -> 0.00034327994 | AB25: ='Weighted Avg BEA Multipliers'!AD495 -> 0.0026707233 | AC25: ='OECD LEONTFD'!X28 -> 0.001 | AD25: ='OECD LEONTFD'!Y28 -> 0 | AE25: ='OECD LEONTFD'!Z28 -> 0 | AF25: ='OECD LEONTFD'!AA28 -> 0.001 | AG25: ='OECD LEONTFD'!AB28 -> 0.001 | AH25: ='OECD LEONTFD'!AC28 -> 0 | AI25: ='OECD LEONTFD'!AD28 -> 0 | AJ25: ='OECD LEONTFD'!AE28 -> 0 | ... AQ25: ='OECD LEONTFD'!AL28 -> 0
A26: ISIC 351 | B26: ='Weighted Avg BEA Multipliers'!D496 -> 0.014465011 | C26: ='Weighted Avg BEA Multipliers'!E496 -> 0.0295842 | D26: ='Weighted Avg BEA Multipliers'!F496 -> 0.0137376 | E26: ='Weighted Avg BEA Multipliers'!G496 -> 0.047963592 | F26: ='Weighted Avg BEA Multipliers'!H496 -> 0.0048063029 | G26: ='Weighted Avg BEA Multipliers'!I496 -> 0.020639786 | H26: ='Weighted Avg BEA Multipliers'!J496 -> 0.02940217 | I26: ='Weighted Avg BEA Multipliers'!K496 -> 0.029479147 | ... AQ26: ='Weighted Avg BEA Multipliers'!AS496 -> 0
A27: ISIC 352T353 | B27: ='Weighted Avg BEA Multipliers'!D497 -> 0.0072812674 | C27: ='Weighted Avg BEA Multipliers'!E497 -> 0.0021629 | D27: ='Weighted Avg BEA Multipliers'!F497 -> 0.0028386 | E27: ='Weighted Avg BEA Multipliers'!G497 -> 0.0072437037 | F27: ='Weighted Avg BEA Multipliers'!H497 -> 0.0011110647 | G27: ='Weighted Avg BEA Multipliers'!I497 -> 0.0062433237 | H27: ='Weighted Avg BEA Multipliers'!J497 -> 0.0054971923 | I27: ='Weighted Avg BEA Multipliers'!K497 -> 0.0041364979 | ... AQ27: ='Weighted Avg BEA Multipliers'!AS497 -> 0
A28: ISIC 36T39 | B28: ='Weighted Avg BEA Multipliers'!D498 -> 0.0025254014 | C28: ='Weighted Avg BEA Multipliers'!E498 -> 0.0041167778 | D28: ='Weighted Avg BEA Multipliers'!F498 -> 0.0048645842 | E28: ='Weighted Avg BEA Multipliers'!G498 -> 0.0043939941 | F28: ='Weighted Avg BEA Multipliers'!H498 -> 0.0030532597 | G28: ='Weighted Avg BEA Multipliers'!I498 -> 0.0036674741 | H28: ='Weighted Avg BEA Multipliers'!J498 -> 0.0034480994 | I28: ='Weighted Avg BEA Multipliers'!K498 -> 0.0032139013 | ... AQ28: ='Weighted Avg BEA Multipliers'!AS498 -> 0
A29: ISIC 41T43 | B29: ='OECD LEONTFD'!C30 -> 0.007 | C29: ='Weighted Avg BEA Multipliers'!E499 -> 0.0036870845 | D29: ='Weighted Avg BEA Multipliers'!F499 -> 0.0012603734 | E29: ='OECD LEONTFD'!E30 -> 0.027 | F29: ='OECD LEONTFD'!F30 -> 0.028 | G29: ='OECD LEONTFD'!G30 -> 0.003 | H29: ='OECD LEONTFD'!H30 -> 0.006 | I29: ='OECD LEONTFD'!I30 -> 0.017 | J29: ='OECD LEONTFD'!J30 -> 0.009 | K29: ='OECD LEONTFD'!K30 -> 0.011 | L29: ='Weighted Avg BEA Multipliers'!N499 -> 0.0017360658 | M29: ='Weighted Avg BEA Multipliers'!O499 -> 0.00058217776 | N29: ='OECD LEONTFD'!M30 -> 0.008 | O29: ='Weighted Avg BEA Multipliers'!Q499 -> 0.0019127665 | P29: ='Weighted Avg BEA Multipliers'!R499 -> 0.0020527366 | Q29: ='Weighted Avg BEA Multipliers'!S499 -> 0.0019592694 | R29: ='Weighted Avg BEA Multipliers'!T499 -> 0.0014092481 | S29: ='OECD LEONTFD'!P30 -> 0.004 | T29: ='OECD LEONTFD'!Q30 -> 0.005 | U29: ='OECD LEONTFD'!R30 -> 0.002 | V29: ='OECD LEONTFD'!S30 -> 0.006 | W29: ='OECD LEONTFD'!T30 -> 0.005 | X29: ='OECD LEONTFD'!U30 -> 0.003 | Y29: ='OECD LEONTFD'!V30 -> 0.005 | Z29: ='Weighted Avg BEA Multipliers'!AB499 -> 0.0046834165 | AA29: ='Weighted Avg BEA Multipliers'!AC499 -> 0.0015327566 | AB29: ='Weighted Avg BEA Multipliers'!AD499 -> 0.0011292778 | AC29: ='OECD LEONTFD'!X30 -> 1.115 | AD29: ='OECD LEONTFD'!Y30 -> 0.006 | AE29: ='OECD LEONTFD'!Z30 -> 0.006 | AF29: ='OECD LEONTFD'!AA30 -> 0.004 | AG29: ='OECD LEONTFD'!AB30 -> 0.005 | AH29: ='OECD LEONTFD'!AC30 -> 0.009 | AI29: ='OECD LEONTFD'!AD30 -> 0.004 | AJ29: ='OECD LEONTFD'!AE30 -> 0.004 | ... AQ29: ='OECD LEONTFD'!AL30 -> 0
A30: ISIC 45T47 | B30: ='OECD LEONTFD'!C31 -> 0.168 | C30: ='Weighted Avg BEA Multipliers'!E500 -> 0.004640983 | D30: ='Weighted Avg BEA Multipliers'!F500 -> 0.0019476673 | E30: ='OECD LEONTFD'!E31 -> 0.171 | F30: ='OECD LEONTFD'!F31 -> 0.182 | G30: ='OECD LEONTFD'!G31 -> 0.236 | H30: ='OECD LEONTFD'!H31 -> 0.169 | I30: ='OECD LEONTFD'!I31 -> 0.404 | J30: ='OECD LEONTFD'!J31 -> 0.104 | K30: ='OECD LEONTFD'!K31 -> 0.135 | L30: ='Weighted Avg BEA Multipliers'!N500 -> 0.0081993582 | M30: ='Weighted Avg BEA Multipliers'!O500 -> 0.0059061112 | N30: ='OECD LEONTFD'!M31 -> 0.113 | O30: ='Weighted Avg BEA Multipliers'!Q500 -> 0.0058505657 | P30: ='Weighted Avg BEA Multipliers'!R500 -> 0.0054245734 | Q30: ='Weighted Avg BEA Multipliers'!S500 -> 0.01141489 | R30: ='Weighted Avg BEA Multipliers'!T500 -> 0.0085038659 | S30: ='OECD LEONTFD'!P31 -> 0.089 | T30: ='OECD LEONTFD'!Q31 -> 0.11 | U30: ='OECD LEONTFD'!R31 -> 0.082 | V30: ='OECD LEONTFD'!S31 -> 0.147 | W30: ='OECD LEONTFD'!T31 -> 0.134 | X30: ='OECD LEONTFD'!U31 -> 0.097 | Y30: ='OECD LEONTFD'!V31 -> 0.128 | Z30: ='Weighted Avg BEA Multipliers'!AB500 -> 0.0015073034 | AA30: ='Weighted Avg BEA Multipliers'!AC500 -> 0.0010742262 | AB30: ='Weighted Avg BEA Multipliers'!AD500 -> 0.0030731854 | AC30: ='OECD LEONTFD'!X31 -> 0.133 | AD30: ='OECD LEONTFD'!Y31 -> 1.191 | AE30: ='OECD LEONTFD'!Z31 -> 0.09 | AF30: ='OECD LEONTFD'!AA31 -> 0.159 | AG30: ='OECD LEONTFD'!AB31 -> 0.174 | AH30: ='OECD LEONTFD'!AC31 -> 0.082 | AI30: ='OECD LEONTFD'!AD31 -> 0.103 | AJ30: ='OECD LEONTFD'!AE31 -> 0.029 | ... AQ30: ='OECD LEONTFD'!AL31 -> 0
A31: ISIC 49T53 | B31: ='OECD LEONTFD'!C32 -> 0.026 | C31: ='Weighted Avg BEA Multipliers'!E501 -> 0.008224352 | D31: ='Weighted Avg BEA Multipliers'!F501 -> 0.0035527366 | E31: ='OECD LEONTFD'!E32 -> 0.101 | F31: ='OECD LEONTFD'!F32 -> 0.122 | G31: ='OECD LEONTFD'!G32 -> 0.022 | H31: ='OECD LEONTFD'!H32 -> 0.028 | I31: ='OECD LEONTFD'!I32 -> 0.068 | J31: ='OECD LEONTFD'!J32 -> 0.047 | K31: ='OECD LEONTFD'!K32 -> 0.043 | L31: ='Weighted Avg BEA Multipliers'!N501 -> 0.010157017 | M31: ='Weighted Avg BEA Multipliers'!O501 -> 0.0039118209 | N31: ='OECD LEONTFD'!M32 -> 0.041 | O31: ='Weighted Avg BEA Multipliers'!Q501 -> 0.014475468 | P31: ='Weighted Avg BEA Multipliers'!R501 -> 0.016363018 | Q31: ='Weighted Avg BEA Multipliers'!S501 -> 0.018867352 | R31: ='Weighted Avg BEA Multipliers'!T501 -> 0.013550617 | S31: ='OECD LEONTFD'!P32 -> 0.014 | T31: ='OECD LEONTFD'!Q32 -> 0.058 | U31: ='OECD LEONTFD'!R32 -> 0.009 | V31: ='OECD LEONTFD'!S32 -> 0.028 | W31: ='OECD LEONTFD'!T32 -> 0.023 | X31: ='OECD LEONTFD'!U32 -> 0.022 | Y31: ='OECD LEONTFD'!V32 -> 0.022 | Z31: ='Weighted Avg BEA Multipliers'!AB501 -> 0.0078474047 | AA31: ='Weighted Avg BEA Multipliers'!AC501 -> 0.0049009467 | AB31: ='Weighted Avg BEA Multipliers'!AD501 -> 0.0074264982 | AC31: ='OECD LEONTFD'!X32 -> 0.053 | AD31: ='OECD LEONTFD'!Y32 -> 0.029 | AE31: ='OECD LEONTFD'!Z32 -> 1.074 | AF31: ='OECD LEONTFD'!AA32 -> 0.019 | AG31: ='OECD LEONTFD'!AB32 -> 0.069 | AH31: ='OECD LEONTFD'!AC32 -> 0.035 | AI31: ='OECD LEONTFD'!AD32 -> 0.044 | AJ31: ='OECD LEONTFD'!AE32 -> 0.024 | ... AQ31: ='OECD LEONTFD'!AL32 -> 0
A32: ISIC 55T56 | B32: ='OECD LEONTFD'!C33 -> 0.002 | C32: ='Weighted Avg BEA Multipliers'!E502 -> 0.0012620637 | D32: ='Weighted Avg BEA Multipliers'!F502 -> 0.0010472053 | E32: ='OECD LEONTFD'!E33 -> 0.006 | F32: ='OECD LEONTFD'!F33 -> 0.014 | G32: ='OECD LEONTFD'!G33 -> 0.002 | H32: ='OECD LEONTFD'!H33 -> 0.003 | I32: ='OECD LEONTFD'!I33 -> 0.008 | J32: ='OECD LEONTFD'!J33 -> 0.004 | K32: ='OECD LEONTFD'!K33 -> 0.003 | L32: ='Weighted Avg BEA Multipliers'!N502 -> 0.0014422221 | M32: ='Weighted Avg BEA Multipliers'!O502 -> 0.00087531674 | N32: ='OECD LEONTFD'!M33 -> 0.004 | O32: ='Weighted Avg BEA Multipliers'!Q502 -> 0.002600068 | P32: ='Weighted Avg BEA Multipliers'!R502 -> 0.002964328 | Q32: ='Weighted Avg BEA Multipliers'!S502 -> 0.0030217047 | R32: ='Weighted Avg BEA Multipliers'!T502 -> 0.0018633807 | S32: ='OECD LEONTFD'!P33 -> 0.002 | T32: ='OECD LEONTFD'!Q33 -> 0.003 | U32: ='OECD LEONTFD'!R33 -> 0.001 | V32: ='OECD LEONTFD'!S33 -> 0.003 | W32: ='OECD LEONTFD'!T33 -> 0.003 | X32: ='OECD LEONTFD'!U33 -> 0.004 | Y32: ='OECD LEONTFD'!V33 -> 0.002 | Z32: ='Weighted Avg BEA Multipliers'!AB502 -> 0.0028574402 | AA32: ='Weighted Avg BEA Multipliers'!AC502 -> 0.0024128822 | AB32: ='Weighted Avg BEA Multipliers'!AD502 -> 0.0043578938 | AC32: ='OECD LEONTFD'!X33 -> 0.004 | AD32: ='OECD LEONTFD'!Y33 -> 0.004 | AE32: ='OECD LEONTFD'!Z33 -> 0.005 | AF32: ='OECD LEONTFD'!AA33 -> 1.003 | AG32: ='OECD LEONTFD'!AB33 -> 0.005 | AH32: ='OECD LEONTFD'!AC33 -> 0.002 | AI32: ='OECD LEONTFD'!AD33 -> 0.006 | AJ32: ='OECD LEONTFD'!AE33 -> 0.004 | ... AQ32: ='OECD LEONTFD'!AL33 -> 0
A33: ISIC 58T60 | B33: ='OECD LEONTFD'!C34 -> 0.003 | C33: ='Weighted Avg BEA Multipliers'!E503 -> 0.00070406259 | D33: ='Weighted Avg BEA Multipliers'!F503 -> 0.00087983943 | E33: ='OECD LEONTFD'!E34 -> 0.004 | F33: ='OECD LEONTFD'!F34 -> 0.004 | G33: ='OECD LEONTFD'!G34 -> 0.004 | H33: ='OECD LEONTFD'!H34 -> 0.003 | I33: ='OECD LEONTFD'!I34 -> 0.007 | J33: ='OECD LEONTFD'!J34 -> 0.014 | K33: ='OECD LEONTFD'!K34 -> 0.005 | L33: ='Weighted Avg BEA Multipliers'!N503 -> 0.00076180824 | M33: ='Weighted Avg BEA Multipliers'!O503 -> 0.0015166397 | N33: ='OECD LEONTFD'!M34 -> 0.004 | O33: ='Weighted Avg BEA Multipliers'!Q503 -> 0.00087082367 | P33: ='Weighted Avg BEA Multipliers'!R503 -> 0.00095973146 | Q33: ='Weighted Avg BEA Multipliers'!S503 -> 0.00092466783 | R33: ='Weighted Avg BEA Multipliers'!T503 -> 0.00070005885 | S33: ='OECD LEONTFD'!P34 -> 0.002 | T33: ='OECD LEONTFD'!Q34 -> 0.005 | U33: ='OECD LEONTFD'!R34 -> 0.001 | V33: ='OECD LEONTFD'!S34 -> 0.003 | W33: ='OECD LEONTFD'!T34 -> 0.003 | X33: ='OECD LEONTFD'!U34 -> 0.002 | Y33: ='OECD LEONTFD'!V34 -> 0.003 | Z33: ='Weighted Avg BEA Multipliers'!AB503 -> 0.00068808523 | AA33: ='Weighted Avg BEA Multipliers'!AC503 -> 0.00093861492 | AB33: ='Weighted Avg BEA Multipliers'!AD503 -> 0.00098919786 | AC33: ='OECD LEONTFD'!X34 -> 0.004 | AD33: ='OECD LEONTFD'!Y34 -> 0.005 | AE33: ='OECD LEONTFD'!Z34 -> 0.003 | AF33: ='OECD LEONTFD'!AA34 -> 0.003 | AG33: ='OECD LEONTFD'!AB34 -> 1.087 | AH33: ='OECD LEONTFD'!AC34 -> 0.013 | AI33: ='OECD LEONTFD'!AD34 -> 0.014 | AJ33: ='OECD LEONTFD'!AE34 -> 0.005 | ... AQ33: ='OECD LEONTFD'!AL34 -> 0
A34: ISIC 61 | B34: ='OECD LEONTFD'!C35 -> 0.004 | C34: ='Weighted Avg BEA Multipliers'!E504 -> 0.0032787871 | D34: ='Weighted Avg BEA Multipliers'!F504 -> 0.0031680007 | E34: ='OECD LEONTFD'!E35 -> 0.011 | F34: ='OECD LEONTFD'!F35 -> 0.013 | G34: ='OECD LEONTFD'!G35 -> 0.003 | H34: ='OECD LEONTFD'!H35 -> 0.007 | I34: ='OECD LEONTFD'!I35 -> 0.012 | J34: ='OECD LEONTFD'!J35 -> 0.007 | K34: ='OECD LEONTFD'!K35 -> 0.006 | L34: ='Weighted Avg BEA Multipliers'!N504 -> 0.00257378 | M34: ='Weighted Avg BEA Multipliers'!O504 -> 0.0031589718 | N34: ='OECD LEONTFD'!M35 -> 0.007 | O34: ='Weighted Avg BEA Multipliers'!Q504 -> 0.0039005617 | P34: ='Weighted Avg BEA Multipliers'!R504 -> 0.0044618168 | Q34: ='Weighted Avg BEA Multipliers'!S504 -> 0.0038392476 | R34: ='Weighted Avg BEA Multipliers'!T504 -> 0.0028075878 | S34: ='OECD LEONTFD'!P35 -> 0.003 | T34: ='OECD LEONTFD'!Q35 -> 0.007 | U34: ='OECD LEONTFD'!R35 -> 0.002 | V34: ='OECD LEONTFD'!S35 -> 0.006 | W34: ='OECD LEONTFD'!T35 -> 0.005 | X34: ='OECD LEONTFD'!U35 -> 0.004 | Y34: ='OECD LEONTFD'!V35 -> 0.004 | Z34: ='Weighted Avg BEA Multipliers'!AB504 -> 0.0035017566 | AA34: ='Weighted Avg BEA Multipliers'!AC504 -> 0.0028642505 | AB34: ='Weighted Avg BEA Multipliers'!AD504 -> 0.0055137235 | AC34: ='OECD LEONTFD'!X35 -> 0.006 | AD34: ='OECD LEONTFD'!Y35 -> 0.006 | AE34: ='OECD LEONTFD'!Z35 -> 0.007 | AF34: ='OECD LEONTFD'!AA35 -> 0.004 | AG34: ='OECD LEONTFD'!AB35 -> 0.018 | AH34: ='OECD LEONTFD'!AC35 -> 1.109 | AI34: ='OECD LEONTFD'!AD35 -> 0.016 | AJ34: ='OECD LEONTFD'!AE35 -> 0.01 | ... AQ34: ='OECD LEONTFD'!AL35 -> 0
A35: ISIC 62T63 | B35: ='OECD LEONTFD'!C36 -> 0.002 | C35: ='Weighted Avg BEA Multipliers'!E505 -> 0.0017580418 | D35: ='Weighted Avg BEA Multipliers'!F505 -> 0.0031120665 | E35: ='OECD LEONTFD'!E36 -> 0.006 | F35: ='OECD LEONTFD'!F36 -> 0.006 | G35: ='OECD LEONTFD'!G36 -> 0.003 | H35: ='OECD LEONTFD'!H36 -> 0.004 | I35: ='OECD LEONTFD'!I36 -> 0.008 | J35: ='OECD LEONTFD'!J36 -> 0.006 | K35: ='OECD LEONTFD'!K36 -> 0.006 | L35: ='Weighted Avg BEA Multipliers'!N505 -> 0.0018681741 | M35: ='Weighted Avg BEA Multipliers'!O505 -> 0.0024096243 | N35: ='OECD LEONTFD'!M36 -> 0.005 | O35: ='Weighted Avg BEA Multipliers'!Q505 -> 0.0031599722 | P35: ='Weighted Avg BEA Multipliers'!R505 -> 0.0032622859 | Q35: ='Weighted Avg BEA Multipliers'!S505 -> 0.0026682217 | R35: ='Weighted Avg BEA Multipliers'!T505 -> 0.0021926603 | S35: ='OECD LEONTFD'!P36 -> 0.002 | T35: ='OECD LEONTFD'!Q36 -> 0.007 | U35: ='OECD LEONTFD'!R36 -> 0.002 | V35: ='OECD LEONTFD'!S36 -> 0.004 | W35: ='OECD LEONTFD'!T36 -> 0.004 | X35: ='OECD LEONTFD'!U36 -> 0.002 | Y35: ='OECD LEONTFD'!V36 -> 0.003 | Z35: ='Weighted Avg BEA Multipliers'!AB505 -> 0.0022622014 | AA35: ='Weighted Avg BEA Multipliers'!AC505 -> 0.0030934146 | AB35: ='Weighted Avg BEA Multipliers'!AD505 -> 0.0032840922 | AC35: ='OECD LEONTFD'!X36 -> 0.005 | AD35: ='OECD LEONTFD'!Y36 -> 0.004 | AE35: ='OECD LEONTFD'!Z36 -> 0.005 | AF35: ='OECD LEONTFD'!AA36 -> 0.002 | AG35: ='OECD LEONTFD'!AB36 -> 0.013 | AH35: ='OECD LEONTFD'!AC36 -> 0.012 | AI35: ='OECD LEONTFD'!AD36 -> 1.044 | AJ35: ='OECD LEONTFD'!AE36 -> 0.01 | ... AQ35: ='OECD LEONTFD'!AL36 -> 0
A36: ISIC 64T66 | B36: ='OECD LEONTFD'!C37 -> 0.078 | C36: ='Weighted Avg BEA Multipliers'!E506 -> 0.0078961847 | D36: ='Weighted Avg BEA Multipliers'!F506 -> 0.0083567583 | E36: ='OECD LEONTFD'!E37 -> 0.155 | F36: ='OECD LEONTFD'!F37 -> 0.166 | G36: ='OECD LEONTFD'!G37 -> 0.044 | H36: ='OECD LEONTFD'!H37 -> 0.087 | I36: ='OECD LEONTFD'!I37 -> 0.181 | J36: ='OECD LEONTFD'!J37 -> 0.097 | K36: ='OECD LEONTFD'!K37 -> 0.103 | L36: ='Weighted Avg BEA Multipliers'!N506 -> 0.0051531083 | M36: ='Weighted Avg BEA Multipliers'!O506 -> 0.003676114 | N36: ='OECD LEONTFD'!M37 -> 0.095 | O36: ='Weighted Avg BEA Multipliers'!Q506 -> 0.0089828445 | P36: ='Weighted Avg BEA Multipliers'!R506 -> 0.0093666114 | Q36: ='Weighted Avg BEA Multipliers'!S506 -> 0.0071484624 | R36: ='Weighted Avg BEA Multipliers'!T506 -> 0.0075003286 | S36: ='OECD LEONTFD'!P37 -> 0.036 | T36: ='OECD LEONTFD'!Q37 -> 0.065 | U36: ='OECD LEONTFD'!R37 -> 0.022 | V36: ='OECD LEONTFD'!S37 -> 0.064 | W36: ='OECD LEONTFD'!T37 -> 0.062 | X36: ='OECD LEONTFD'!U37 -> 0.055 | Y36: ='OECD LEONTFD'!V37 -> 0.051 | Z36: ='Weighted Avg BEA Multipliers'!AB506 -> 0.0059160994 | AA36: ='Weighted Avg BEA Multipliers'!AC506 -> 0.011396811 | AB36: ='Weighted Avg BEA Multipliers'!AD506 -> 0.0071022565 | AC36: ='OECD LEONTFD'!X37 -> 0.093 | AD36: ='OECD LEONTFD'!Y37 -> 0.061 | AE36: ='OECD LEONTFD'!Z37 -> 0.074 | AF36: ='OECD LEONTFD'!AA37 -> 0.038 | AG36: ='OECD LEONTFD'!AB37 -> 0.06 | AH36: ='OECD LEONTFD'!AC37 -> 0.048 | AI36: ='OECD LEONTFD'!AD37 -> 0.056 | AJ36: ='OECD LEONTFD'!AE37 -> 1.275 | ... AQ36: ='OECD LEONTFD'!AL37 -> 0
A37: ISIC 68 | B37: ='OECD LEONTFD'!C38 -> 0.003 | C37: ='Weighted Avg BEA Multipliers'!E507 -> 0.0051939573 | D37: ='Weighted Avg BEA Multipliers'!F507 -> 0.0047951833 | E37: ='OECD LEONTFD'!E38 -> 0.005 | F37: ='OECD LEONTFD'!F38 -> 0.004 | G37: ='OECD LEONTFD'!G38 -> 0.003 | H37: ='OECD LEONTFD'!H38 -> 0.005 | I37: ='OECD LEONTFD'!I38 -> 0.008 | J37: ='OECD LEONTFD'!J38 -> 0.005 | K37: ='OECD LEONTFD'!K38 -> 0.004 | L37: ='Weighted Avg BEA Multipliers'!N507 -> 0.007571106 | M37: ='Weighted Avg BEA Multipliers'!O507 -> 0.0041015911 | N37: ='OECD LEONTFD'!M38 -> 0.005 | O37: ='Weighted Avg BEA Multipliers'!Q507 -> 0.0067028348 | P37: ='Weighted Avg BEA Multipliers'!R507 -> 0.0070450685 | Q37: ='Weighted Avg BEA Multipliers'!S507 -> 0.0069297603 | R37: ='Weighted Avg BEA Multipliers'!T507 -> 0.0056498962 | S37: ='OECD LEONTFD'!P38 -> 0.002 | T37: ='OECD LEONTFD'!Q38 -> 0.003 | U37: ='OECD LEONTFD'!R38 -> 0.001 | V37: ='OECD LEONTFD'!S38 -> 0.003 | W37: ='OECD LEONTFD'!T38 -> 0.004 | X37: ='OECD LEONTFD'!U38 -> 0.002 | Y37: ='OECD LEONTFD'!V38 -> 0.003 | Z37: ='Weighted Avg BEA Multipliers'!AB507 -> 0.0046115452 | AA37: ='Weighted Avg BEA Multipliers'!AC507 -> 0.006740697 | AB37: ='Weighted Avg BEA Multipliers'!AD507 -> 0.011399677 | AC37: ='OECD LEONTFD'!X38 -> 0.005 | AD37: ='OECD LEONTFD'!Y38 -> 0.007 | AE37: ='OECD LEONTFD'!Z38 -> 0.003 | AF37: ='OECD LEONTFD'!AA38 -> 0.006 | AG37: ='OECD LEONTFD'!AB38 -> 0.006 | AH37: ='OECD LEONTFD'!AC38 -> 0.005 | AI37: ='OECD LEONTFD'!AD38 -> 0.005 | AJ37: ='OECD LEONTFD'!AE38 -> 0.004 | ... AQ37: ='OECD LEONTFD'!AL38 -> 0
A38: ISIC 69T82 | B38: ='OECD LEONTFD'!C39 -> 0.029 | C38: ='Weighted Avg BEA Multipliers'!E508 -> 0.014461791 | D38: ='Weighted Avg BEA Multipliers'!F508 -> 0.015063558 | E38: ='OECD LEONTFD'!E39 -> 0.11 | F38: ='OECD LEONTFD'!F39 -> 0.157 | G38: ='OECD LEONTFD'!G39 -> 0.028 | H38: ='OECD LEONTFD'!H39 -> 0.036 | I38: ='OECD LEONTFD'!I39 -> 0.076 | J38: ='OECD LEONTFD'!J39 -> 0.055 | K38: ='OECD LEONTFD'!K39 -> 0.046 | L38: ='Weighted Avg BEA Multipliers'!N508 -> 0.0098413299 | M38: ='Weighted Avg BEA Multipliers'!O508 -> 0.010483138 | N38: ='OECD LEONTFD'!M39 -> 0.055 | O38: ='Weighted Avg BEA Multipliers'!Q508 -> 0.011471519 | P38: ='Weighted Avg BEA Multipliers'!R508 -> 0.012236422 | Q38: ='Weighted Avg BEA Multipliers'!S508 -> 0.0096771507 | R38: ='Weighted Avg BEA Multipliers'!T508 -> 0.0078905752 | S38: ='OECD LEONTFD'!P39 -> 0.018 | T38: ='OECD LEONTFD'!Q39 -> 0.087 | U38: ='OECD LEONTFD'!R39 -> 0.013 | V38: ='OECD LEONTFD'!S39 -> 0.036 | W38: ='OECD LEONTFD'!T39 -> 0.034 | X38: ='OECD LEONTFD'!U39 -> 0.029 | Y38: ='OECD LEONTFD'!V39 -> 0.028 | Z38: ='Weighted Avg BEA Multipliers'!AB508 -> 0.0083309385 | AA38: ='Weighted Avg BEA Multipliers'!AC508 -> 0.0096662516 | AB38: ='Weighted Avg BEA Multipliers'!AD508 -> 0.014337375 | AC38: ='OECD LEONTFD'!X39 -> 0.071 | AD38: ='OECD LEONTFD'!Y39 -> 0.031 | AE38: ='OECD LEONTFD'!Z39 -> 0.059 | AF38: ='OECD LEONTFD'!AA39 -> 0.024 | AG38: ='OECD LEONTFD'!AB39 -> 0.07 | AH38: ='OECD LEONTFD'!AC39 -> 0.037 | AI38: ='OECD LEONTFD'!AD39 -> 0.058 | AJ38: ='OECD LEONTFD'!AE39 -> 0.022 | ... AQ38: ='OECD LEONTFD'!AL39 -> 0
A39: ISIC 84 | B39: ='OECD LEONTFD'!C40 -> 0.003 | C39: ='Weighted Avg BEA Multipliers'!E509 -> 0.00067194945 | D39: ='Weighted Avg BEA Multipliers'!F509 -> 0.00098929021 | E39: ='OECD LEONTFD'!E40 -> 0.007 | F39: ='OECD LEONTFD'!F40 -> 0.008 | G39: ='OECD LEONTFD'!G40 -> 0.002 | H39: ='OECD LEONTFD'!H40 -> 0.004 | I39: ='OECD LEONTFD'!I40 -> 0.008 | J39: ='OECD LEONTFD'!J40 -> 0.005 | K39: ='OECD LEONTFD'!K40 -> 0.006 | L39: ='Weighted Avg BEA Multipliers'!N509 -> 0.0011651151 | M39: ='Weighted Avg BEA Multipliers'!O509 -> 0.0004271523 | N39: ='OECD LEONTFD'!M40 -> 0.005 | O39: ='Weighted Avg BEA Multipliers'!Q509 -> 0.0010458544 | P39: ='Weighted Avg BEA Multipliers'!R509 -> 0.0010968162 | Q39: ='Weighted Avg BEA Multipliers'!S509 -> 0.014470081 | R39: ='Weighted Avg BEA Multipliers'!T509 -> 0.00091039267 | S39: ='OECD LEONTFD'!P40 -> 0.002 | T39: ='OECD LEONTFD'!Q40 -> 0.003 | U39: ='OECD LEONTFD'!R40 -> 0.001 | V39: ='OECD LEONTFD'!S40 -> 0.003 | W39: ='OECD LEONTFD'!T40 -> 0.003 | X39: ='OECD LEONTFD'!U40 -> 0.002 | Y39: ='OECD LEONTFD'!V40 -> 0.002 | Z39: ='Weighted Avg BEA Multipliers'!AB509 -> 0.002896624 | AA39: ='Weighted Avg BEA Multipliers'!AC509 -> 0.00071969047 | AB39: ='Weighted Avg BEA Multipliers'!AD509 -> 0.0036146367 | AC39: ='OECD LEONTFD'!X40 -> 0.004 | AD39: ='OECD LEONTFD'!Y40 -> 0.002 | AE39: ='OECD LEONTFD'!Z40 -> 0.004 | AF39: ='OECD LEONTFD'!AA40 -> 0.002 | AG39: ='OECD LEONTFD'!AB40 -> 0.004 | AH39: ='OECD LEONTFD'!AC40 -> 0.003 | AI39: ='OECD LEONTFD'!AD40 -> 0.003 | AJ39: ='OECD LEONTFD'!AE40 -> 0.002 | ... AQ39: ='OECD LEONTFD'!AL40 -> 0
A40: ISIC 85 | B40: ='OECD LEONTFD'!C41 -> 0.002 | C40: ='Weighted Avg BEA Multipliers'!E510 -> 0.00010707564 | D40: ='Weighted Avg BEA Multipliers'!F510 -> 5.1550509e-05 | E40: ='OECD LEONTFD'!E41 -> 0.007 | F40: ='OECD LEONTFD'!F41 -> 0.006 | G40: ='OECD LEONTFD'!G41 -> 0.002 | H40: ='OECD LEONTFD'!H41 -> 0.004 | I40: ='OECD LEONTFD'!I41 -> 0.008 | J40: ='OECD LEONTFD'!J41 -> 0.006 | K40: ='OECD LEONTFD'!K41 -> 0.006 | L40: ='Weighted Avg BEA Multipliers'!N510 -> 0.00015801371 | M40: ='Weighted Avg BEA Multipliers'!O510 -> 4.7047142e-05 | N40: ='OECD LEONTFD'!M41 -> 0.005 | O40: ='Weighted Avg BEA Multipliers'!Q510 -> 0.0001223678 | P40: ='Weighted Avg BEA Multipliers'!R510 -> 0.00011809476 | Q40: ='Weighted Avg BEA Multipliers'!S510 -> 0.00022972076 | R40: ='Weighted Avg BEA Multipliers'!T510 -> 0.00011727959 | S40: ='OECD LEONTFD'!P41 -> 0.002 | T40: ='OECD LEONTFD'!Q41 -> 0.005 | U40: ='OECD LEONTFD'!R41 -> 0.001 | V40: ='OECD LEONTFD'!S41 -> 0.004 | W40: ='OECD LEONTFD'!T41 -> 0.004 | X40: ='OECD LEONTFD'!U41 -> 0.002 | Y40: ='OECD LEONTFD'!V41 -> 0.003 | Z40: ='Weighted Avg BEA Multipliers'!AB510 -> 0.00024803215 | AA40: ='Weighted Avg BEA Multipliers'!AC510 -> 0.00059614802 | AB40: ='Weighted Avg BEA Multipliers'!AD510 -> 8.7187473e-05 | AC40: ='OECD LEONTFD'!X41 -> 0.004 | AD40: ='OECD LEONTFD'!Y41 -> 0.004 | AE40: ='OECD LEONTFD'!Z41 -> 0.004 | AF40: ='OECD LEONTFD'!AA41 -> 0.002 | AG40: ='OECD LEONTFD'!AB41 -> 0.006 | AH40: ='OECD LEONTFD'!AC41 -> 0.005 | AI40: ='OECD LEONTFD'!AD41 -> 0.008 | AJ40: ='OECD LEONTFD'!AE41 -> 0.006 | ... AQ40: ='OECD LEONTFD'!AL41 -> 0
... A43: ISIC 97T98 | B43: ='OECD LEONTFD'!C44 -> 0 | C43: ='Weighted Avg BEA Multipliers'!E513 -> 0 | D43: ='Weighted Avg BEA Multipliers'!F513 -> 0 | E43: ='OECD LEONTFD'!E44 -> 0 | F43: ='OECD LEONTFD'!F44 -> 0 | G43: ='OECD LEONTFD'!G44 -> 0 | H43: ='OECD LEONTFD'!H44 -> 0 | I43: ='OECD LEONTFD'!I44 -> 0 | J43: ='OECD LEONTFD'!J44 -> 0 | K43: ='OECD LEONTFD'!K44 -> 0 | L43: ='Weighted Avg BEA Multipliers'!N513 -> 0 | M43: ='Weighted Avg BEA Multipliers'!O513 -> 0 | N43: ='OECD LEONTFD'!M44 -> 0 | O43: ='Weighted Avg BEA Multipliers'!Q513 -> 0 | P43: ='Weighted Avg BEA Multipliers'!R513 -> 0 | Q43: ='Weighted Avg BEA Multipliers'!S513 -> 0 | R43: ='Weighted Avg BEA Multipliers'!T513 -> 0 | S43: ='OECD LEONTFD'!P44 -> 0 | T43: ='OECD LEONTFD'!Q44 -> 0 | U43: ='OECD LEONTFD'!R44 -> 0 | V43: ='OECD LEONTFD'!S44 -> 0 | W43: ='OECD LEONTFD'!T44 -> 0 | X43: ='OECD LEONTFD'!U44 -> 0 | Y43: ='OECD LEONTFD'!V44 -> 0 | Z43: ='Weighted Avg BEA Multipliers'!AB513 -> 0 | AA43: ='Weighted Avg BEA Multipliers'!AC513 -> 0 | AB43: ='Weighted Avg BEA Multipliers'!AD513 -> 0 | AC43: ='OECD LEONTFD'!X44 -> 0 | AD43: ='OECD LEONTFD'!Y44 -> 0 | AE43: ='OECD LEONTFD'!Z44 -> 0 | AF43: ='OECD LEONTFD'!AA44 -> 0 | AG43: ='OECD LEONTFD'!AB44 -> 0 | AH43: ='OECD LEONTFD'!AC44 -> 0 | AI43: ='OECD LEONTFD'!AD44 -> 0 | AJ43: ='OECD LEONTFD'!AE44 -> 0 | ... AQ43: ='OECD LEONTFD'!AL44 -> 1

Sheet Weighted Avg BEA Multipliers
A1: The BEA provides a DLIM table broken down into 405 industry categories (NAICS codes).
A2: To consolidate these categories into ISIC Codes, we take output-weighted averages of each NAICS code within each ISIC code.
A3: To properly calculate the same-industry multipliers (along the diagonal), we take an output-weighted average only of cells
A4: along the diagonal in the NAICS table for NAICS codes within a given ISIC code, not all cells for NAICS codes within a given ISIC code.
A6: Data by NAICS Code
A7: NAICS Code | D7: ='BEA Use Table'!D$6 -> 1111A0 | E7: ='BEA Use Table'!E$6 -> 1111B0 | F7: ='BEA Use Table'!F$6 -> 111200 | G7: ='BEA Use Table'!G$6 -> 111300 | H7: ='BEA Use Table'!H$6 -> 111400 | I7: ='BEA Use Table'!I$6 -> 111900 | J7: ='BEA Use Table'!J$6 -> 112120 | K7: ='BEA Use Table'!K$6 -> 1121A0 | ... OR7: ='BEA Use Table'!OR$6 -> S00203
A8: Output | D8: ='BEA Use Table'!D$418 -> 42655 | E8: ='BEA Use Table'!E$418 -> 100350 | F8: ='BEA Use Table'!F$418 -> 14753 | G8: ='BEA Use Table'!G$418 -> 25763 | H8: ='BEA Use Table'!H$418 -> 18654 | I8: ='BEA Use Table'!I$418 -> 19518 | J8: ='BEA Use Table'!J$418 -> 36981 | K8: ='BEA Use Table'!K$418 -> 78410 | ... OR8: ='BEA Use Table'!OR$418 -> 241279
A9: Matching ISIC Code | D9: =INDEX('BEA Requirements Table'!$B$7:$B$411,MATCH(D$7,'BEA Requirements Table'!$A$7:$A$411,0)) -> ISIC 01T03 | E9: =INDEX('BEA Requirements Table'!$B$7:$B$411,MATCH(E$7,'BEA Requirements Table'!$A$7:$A$411,0)) -> ISIC 01T03 | F9: =INDEX('BEA Requirements Table'!$B$7:$B$411,MATCH(F$7,'BEA Requirements Table'!$A$7:$A$411,0)) -> ISIC 01T03 | G9: =INDEX('BEA Requirements Table'!$B$7:$B$411,MATCH(G$7,'BEA Requirements Table'!$A$7:$A$411,0)) -> ISIC 01T03 | H9: =INDEX('BEA Requirements Table'!$B$7:$B$411,MATCH(H$7,'BEA Requirements Table'!$A$7:$A$411,0)) -> ISIC 01T03 | I9: =INDEX('BEA Requirements Table'!$B$7:$B$411,MATCH(I$7,'BEA Requirements Table'!$A$7:$A$411,0)) -> ISIC 01T03 | J9: =INDEX('BEA Requirements Table'!$B$7:$B$411,MATCH(J$7,'BEA Requirements Table'!$A$7:$A$411,0)) -> ISIC 01T03 | K9: =INDEX('BEA Requirements Table'!$B$7:$B$411,MATCH(K$7,'BEA Requirements Table'!$A$7:$A$411,0)) -> ISIC 01T03 | ... OR9: =INDEX('BEA Requirements Table'!$B$7:$B$411,MATCH(OR$7,'BEA Requirements Table'!$A$7:$A$411,0)) -> ISIC 84
A10: Self-Multiplier (diagonal) | D10: =INDEX('BEA Requirements Table'!$D$7:$OR$411,MATCH(D$7,'BEA Requirements Table'!$A$7:$A$411,0),MATCH(D$7,'BEA Requirements Table'!$D$5:$OR$5,0)) -> 1.05453 | E10: =INDEX('BEA Requirements Table'!$D$7:$OR$411,MATCH(E$7,'BEA Requirements Table'!$A$7:$A$411,0),MATCH(E$7,'BEA Requirements Table'!$D$5:$OR$5,0)) -> 1.08337 | F10: =INDEX('BEA Requirements Table'!$D$7:$OR$411,MATCH(F$7,'BEA Requirements Table'!$A$7:$A$411,0),MATCH(F$7,'BEA Requirements Table'!$D$5:$OR$5,0)) -> 1.03093 | G10: =INDEX('BEA Requirements Table'!$D$7:$OR$411,MATCH(G$7,'BEA Requirements Table'!$A$7:$A$411,0),MATCH(G$7,'BEA Requirements Table'!$D$5:$OR$5,0)) -> 1.00484 | H10: =INDEX('BEA Requirements Table'!$D$7:$OR$411,MATCH(H$7,'BEA Requirements Table'!$A$7:$A$411,0),MATCH(H$7,'BEA Requirements Table'!$D$5:$OR$5,0)) -> 1.17022 | I10: =INDEX('BEA Requirements Table'!$D$7:$OR$411,MATCH(I$7,'BEA Requirements Table'!$A$7:$A$411,0),MATCH(I$7,'BEA Requirements Table'!$D$5:$OR$5,0)) -> 1.02678 | J10: =INDEX('BEA Requirements Table'!$D$7:$OR$411,MATCH(J$7,'BEA Requirements Table'!$A$7:$A$411,0),MATCH(J$7,'BEA Requirements Table'!$D$5:$OR$5,0)) -> 1.00122 | K10: =INDEX('BEA Requirements Table'!$D$7:$OR$411,MATCH(K$7,'BEA Requirements Table'!$A$7:$A$411,0),MATCH(K$7,'BEA Requirements Table'!$D$5:$OR$5,0)) -> 1.39968 | ... OR10: =INDEX('BEA Requirements Table'!$D$7:$OR$411,MATCH(OR$7,'BEA Requirements Table'!$A$7:$A$411,0),MATCH(OR$7,'BEA Requirements Table'!$D$5:$OR$5,0)) -> 1.0095
A12: Self-Multipliers (Diagonal) by ISIC Code
A13: ISIC Code | D13: ISIC 01T03 | E13: ISIC 05 | F13: ISIC 06 | G13: ISIC 07T08 | H13: ISIC 09 | I13: ISIC 10T12 | J13: ISIC 13T15 | K13: ISIC 16 | L13: ISIC 17T18 | M13: ISIC 19 | N13: ISIC 20 | O13: ISIC 21 | P13: ISIC 22 | Q13: ISIC 231 | R13: ISIC 239 | S13: ISIC 241 | T13: ISIC 242 | U13: ISIC 25 | V13: ISIC 26 | W13: ISIC 27 | X13: ISIC 28 | Y13: ISIC 29 | Z13: ISIC 30 | AA13: ISIC 31T33 | AB13: ISIC 351 | AC13: ISIC 352T353 | AD13: ISIC 36T39 | AE13: ISIC 41T43 | AF13: ISIC 45T47 | AG13: ISIC 49T53 | AH13: ISIC 55T56 | AI13: ISIC 58T60 | AJ13: ISIC 61 | AK13: ISIC 62T63 | AL13: ISIC 64T66 | AM13: ISIC 68 | AN13: ISIC 69T82 | AO13: ISIC 84 | AP13: ISIC 85 | AQ13: ISIC 86T88 | AR13: ISIC 90T96 | AS13: ISIC 97T98
A14: Weighted Avg Self-Multiplier | D14: {=SUMPRODUCT($D$8:$OR$8,$D$10:$OR$10*($D$9:$OR$9=D$13))/SUMIFS($D$8:$OR$8,$D$9:$OR$9,D$13)} -> 1.1278184 | E14: {=SUMPRODUCT($D$8:$OR$8,$D$10:$OR$10*($D$9:$OR$9=E$13))/SUMIFS($D$8:$OR$8,$D$9:$OR$9,E$13)} -> 1.08927 | F14: {=SUMPRODUCT($D$8:$OR$8,$D$10:$OR$10*($D$9:$OR$9=F$13))/SUMIFS($D$8:$OR$8,$D$9:$OR$9,F$13)} -> 1.08943 | G14: {=SUMPRODUCT($D$8:$OR$8,$D$10:$OR$10*($D$9:$OR$9=G$13))/SUMIFS($D$8:$OR$8,$D$9:$OR$9,G$13)} -> 1.0213291 | H14: {=SUMPRODUCT($D$8:$OR$8,$D$10:$OR$10*($D$9:$OR$9=H$13))/SUMIFS($D$8:$OR$8,$D$9:$OR$9,H$13)} -> 1.003311 | I14: {=SUMPRODUCT($D$8:$OR$8,$D$10:$OR$10*($D$9:$OR$9=I$13))/SUMIFS($D$8:$OR$8,$D$9:$OR$9,I$13)} -> 1.0933205 | J14: {=SUMPRODUCT($D$8:$OR$8,$D$10:$OR$10*($D$9:$OR$9=J$13))/SUMIFS($D$8:$OR$8,$D$9:$OR$9,J$13)} -> 1.0347452 | K14: {=SUMPRODUCT($D$8:$OR$8,$D$10:$OR$10*($D$9:$OR$9=K$13))/SUMIFS($D$8:$OR$8,$D$9:$OR$9,K$13)} -> 1.0844379 | ... AS14: {=SUMPRODUCT($D$8:$OR$8,$D$10:$OR$10*($D$9:$OR$9=AS$13))/SUMIFS($D$8:$OR$8,$D$9:$OR$9,AS$13)} -> 1
A16: Weighted Avg Multipliers by NAICS Row and ISIC Column
A17: NAICS Code | B17: Output | C17: Matching ISIC Code | D17: ISIC 01T03 | E17: ISIC 05 | F17: ISIC 06 | G17: ISIC 07T08 | H17: ISIC 09 | I17: ISIC 10T12 | J17: ISIC 13T15 | K17: ISIC 16 | L17: ISIC 17T18 | M17: ISIC 19 | N17: ISIC 20 | O17: ISIC 21 | P17: ISIC 22 | Q17: ISIC 231 | R17: ISIC 239 | S17: ISIC 241 | T17: ISIC 242 | U17: ISIC 25 | V17: ISIC 26 | W17: ISIC 27 | X17: ISIC 28 | Y17: ISIC 29 | Z17: ISIC 30 | AA17: ISIC 31T33 | AB17: ISIC 351 | AC17: ISIC 352T353 | AD17: ISIC 36T39 | AE17: ISIC 41T43 | AF17: ISIC 45T47 | AG17: ISIC 49T53 | AH17: ISIC 55T56 | AI17: ISIC 58T60 | AJ17: ISIC 61 | AK17: ISIC 62T63 | AL17: ISIC 64T66 | AM17: ISIC 68 | AN17: ISIC 69T82 | AO17: ISIC 84 | AP17: ISIC 85 | AQ17: ISIC 86T88 | AR17: ISIC 90T96 | AS17: ISIC 97T98
A18: 1111A0 | B18: {=TRANSPOSE(D8:OR8)} -> 42655 | C18: {=TRANSPOSE(D9:OR9)} -> ISIC 01T03 | D18: {=SUMPRODUCT('BEA Requirements Table'!$D7:$OR7,$D$8:$OR$8*($D$9:$OR$9=D$17))/SUMIFS($D$8:$OR$8,$D$9:$OR$9,D$17)} -> 0.11167834 | E18: {=SUMPRODUCT('BEA Requirements Table'!$D7:$OR7,$D$8:$OR$8*($D$9:$OR$9=E$17))/SUMIFS($D$8:$OR$8,$D$9:$OR$9,E$17)} -> 0.0001397 | F18: {=SUMPRODUCT('BEA Requirements Table'!$D7:$OR7,$D$8:$OR$8*($D$9:$OR$9=F$17))/SUMIFS($D$8:$OR$8,$D$9:$OR$9,F$17)} -> 0.0001007 | G18: {=SUMPRODUCT('BEA Requirements Table'!$D7:$OR7,$D$8:$OR$8*($D$9:$OR$9=G$17))/SUMIFS($D$8:$OR$8,$D$9:$OR$9,G$17)} -> 0.0001849258 | H18: {=SUMPRODUCT('BEA Requirements Table'!$D7:$OR7,$D$8:$OR$8*($D$9:$OR$9=H$17))/SUMIFS($D$8:$OR$8,$D$9:$OR$9,H$17)} -> 0.0001107445 | I18: {=SUMPRODUCT('BEA Requirements Table'!$D7:$OR7,$D$8:$OR$8*($D$9:$OR$9=I$17))/SUMIFS($D$8:$OR$8,$D$9:$OR$9,I$17)} -> 0.056364174 | J18: {=SUMPRODUCT('BEA Requirements Table'!$D7:$OR7,$D$8:$OR$8*($D$9:$OR$9=J$17))/SUMIFS($D$8:$OR$8,$D$9:$OR$9,J$17)} -> 0.00095564615 | K18: {=SUMPRODUCT('BEA Requirements Table'!$D7:$OR7,$D$8:$OR$8*($D$9:$OR$9=K$17))/SUMIFS($D$8:$OR$8,$D$9:$OR$9,K$17)} -> 0.0010346428 | ... AS18: {=SUMPRODUCT('BEA Requirements Table'!$D7:$OR7,$D$8:$OR$8*($D$9:$OR$9=AS$17))/SUMIFS($D$8:$OR$8,$D$9:$OR$9,AS$17)} -> 0
A19: 1111B0 | B19: 100350 | C19: ISIC 01T03 | D19: {=SUMPRODUCT('BEA Requirements Table'!$D8:$OR8,$D$8:$OR$8*($D$9:$OR$9=D$17))/SUMIFS($D$8:$OR$8,$D$9:$OR$9,D$17)} -> 0.29460649 | E19: {=SUMPRODUCT('BEA Requirements Table'!$D8:$OR8,$D$8:$OR$8*($D$9:$OR$9=E$17))/SUMIFS($D$8:$OR$8,$D$9:$OR$9,E$17)} -> 0.0007956 | F19: {=SUMPRODUCT('BEA Requirements Table'!$D8:$OR8,$D$8:$OR$8*($D$9:$OR$9=F$17))/SUMIFS($D$8:$OR$8,$D$9:$OR$9,F$17)} -> 0.0008532 | G19: {=SUMPRODUCT('BEA Requirements Table'!$D8:$OR8,$D$8:$OR$8*($D$9:$OR$9=G$17))/SUMIFS($D$8:$OR$8,$D$9:$OR$9,G$17)} -> 0.0020999794 | H19: {=SUMPRODUCT('BEA Requirements Table'!$D8:$OR8,$D$8:$OR$8*($D$9:$OR$9=H$17))/SUMIFS($D$8:$OR$8,$D$9:$OR$9,H$17)} -> 0.00088083936 | I19: {=SUMPRODUCT('BEA Requirements Table'!$D8:$OR8,$D$8:$OR$8*($D$9:$OR$9=I$17))/SUMIFS($D$8:$OR$8,$D$9:$OR$9,I$17)} -> 0.10346046 | J19: {=SUMPRODUCT('BEA Requirements Table'!$D8:$OR8,$D$8:$OR$8*($D$9:$OR$9=J$17))/SUMIFS($D$8:$OR$8,$D$9:$OR$9,J$17)} -> 0.0065270949 | K19: {=SUMPRODUCT('BEA Requirements Table'!$D8:$OR8,$D$8:$OR$8*($D$9:$OR$9=K$17))/SUMIFS($D$8:$OR$8,$D$9:$OR$9,K$17)} -> 0.0030200403 | ... AS19: {=SUMPRODUCT('BEA Requirements Table'!$D8:$OR8,$D$8:$OR$8*($D$9:$OR$9=AS$17))/SUMIFS($D$8:$OR$8,$D$9:$OR$9,AS$17)} -> 0
A20: 111200 | B20: 14753 | C20: ISIC 01T03 | D20: {=SUMPRODUCT('BEA Requirements Table'!$D9:$OR9,$D$8:$OR$8*($D$9:$OR$9=D$17))/SUMIFS($D$8:$OR$8,$D$9:$OR$9,D$17)} -> 0.033481599 | E20: {=SUMPRODUCT('BEA Requirements Table'!$D9:$OR9,$D$8:$OR$8*($D$9:$OR$9=E$17))/SUMIFS($D$8:$OR$8,$D$9:$OR$9,E$17)} -> 1.01e-05 | F20: {=SUMPRODUCT('BEA Requirements Table'!$D9:$OR9,$D$8:$OR$8*($D$9:$OR$9=F$17))/SUMIFS($D$8:$OR$8,$D$9:$OR$9,F$17)} -> 4.3e-06 | G20: {=SUMPRODUCT('BEA Requirements Table'!$D9:$OR9,$D$8:$OR$8*($D$9:$OR$9=G$17))/SUMIFS($D$8:$OR$8,$D$9:$OR$9,G$17)} -> 1.4808533e-05 | H20: {=SUMPRODUCT('BEA Requirements Table'!$D9:$OR9,$D$8:$OR$8*($D$9:$OR$9=H$17))/SUMIFS($D$8:$OR$8,$D$9:$OR$9,H$17)} -> 7.5801776e-06 | I20: {=SUMPRODUCT('BEA Requirements Table'!$D9:$OR9,$D$8:$OR$8*($D$9:$OR$9=I$17))/SUMIFS($D$8:$OR$8,$D$9:$OR$9,I$17)} -> 0.0021091811 | J20: {=SUMPRODUCT('BEA Requirements Table'!$D9:$OR9,$D$8:$OR$8*($D$9:$OR$9=J$17))/SUMIFS($D$8:$OR$8,$D$9:$OR$9,J$17)} -> 3.2489172e-05 | K20: {=SUMPRODUCT('BEA Requirements Table'!$D9:$OR9,$D$8:$OR$8*($D$9:$OR$9=K$17))/SUMIFS($D$8:$OR$8,$D$9:$OR$9,K$17)} -> 0.00025617884 | ... AS20: {=SUMPRODUCT('BEA Requirements Table'!$D9:$OR9,$D$8:$OR$8*($D$9:$OR$9=AS$17))/SUMIFS($D$8:$OR$8,$D$9:$OR$9,AS$17)} -> 0
A21: 111300 | B21: 25763 | C21: ISIC 01T03 | D21: {=SUMPRODUCT('BEA Requirements Table'!$D10:$OR10,$D$8:$OR$8*($D$9:$OR$9=D$17))/SUMIFS($D$8:$OR$8,$D$9:$OR$9,D$17)} -> 0.056695329 | E21: {=SUMPRODUCT('BEA Requirements Table'!$D10:$OR10,$D$8:$OR$8*($D$9:$OR$9=E$17))/SUMIFS($D$8:$OR$8,$D$9:$OR$9,E$17)} -> 1.03e-05 | F21: {=SUMPRODUCT('BEA Requirements Table'!$D10:$OR10,$D$8:$OR$8*($D$9:$OR$9=F$17))/SUMIFS($D$8:$OR$8,$D$9:$OR$9,F$17)} -> 5.2e-06 | G21: {=SUMPRODUCT('BEA Requirements Table'!$D10:$OR10,$D$8:$OR$8*($D$9:$OR$9=G$17))/SUMIFS($D$8:$OR$8,$D$9:$OR$9,G$17)} -> 1.0948383e-05 | H21: {=SUMPRODUCT('BEA Requirements Table'!$D10:$OR10,$D$8:$OR$8*($D$9:$OR$9=H$17))/SUMIFS($D$8:$OR$8,$D$9:$OR$9,H$17)} -> 1.0850991e-05 | I21: {=SUMPRODUCT('BEA Requirements Table'!$D10:$OR10,$D$8:$OR$8*($D$9:$OR$9=I$17))/SUMIFS($D$8:$OR$8,$D$9:$OR$9,I$17)} -> 0.010522246 | J21: {=SUMPRODUCT('BEA Requirements Table'!$D10:$OR10,$D$8:$OR$8*($D$9:$OR$9=J$17))/SUMIFS($D$8:$OR$8,$D$9:$OR$9,J$17)} -> 3.53703e-05 | K21: {=SUMPRODUCT('BEA Requirements Table'!$D10:$OR10,$D$8:$OR$8*($D$9:$OR$9=K$17))/SUMIFS($D$8:$OR$8,$D$9:$OR$9,K$17)} -> 0.00025224893 | ... AS21: {=SUMPRODUCT('BEA Requirements Table'!$D10:$OR10,$D$8:$OR$8*($D$9:$OR$9=AS$17))/SUMIFS($D$8:$OR$8,$D$9:$OR$9,AS$17)} -> 0
A22: 111400 | B22: 18654 | C22: ISIC 01T03 | D22: {=SUMPRODUCT('BEA Requirements Table'!$D11:$OR11,$D$8:$OR$8*($D$9:$OR$9=D$17))/SUMIFS($D$8:$OR$8,$D$9:$OR$9,D$17)} -> 0.049433059 | E22: {=SUMPRODUCT('BEA Requirements Table'!$D11:$OR11,$D$8:$OR$8*($D$9:$OR$9=E$17))/SUMIFS($D$8:$OR$8,$D$9:$OR$9,E$17)} -> 0.0001181 | F22: {=SUMPRODUCT('BEA Requirements Table'!$D11:$OR11,$D$8:$OR$8*($D$9:$OR$9=F$17))/SUMIFS($D$8:$OR$8,$D$9:$OR$9,F$17)} -> 8.19e-05 | G22: {=SUMPRODUCT('BEA Requirements Table'!$D11:$OR11,$D$8:$OR$8*($D$9:$OR$9=G$17))/SUMIFS($D$8:$OR$8,$D$9:$OR$9,G$17)} -> 0.00017582177 | H22: {=SUMPRODUCT('BEA Requirements Table'!$D11:$OR11,$D$8:$OR$8*($D$9:$OR$9=H$17))/SUMIFS($D$8:$OR$8,$D$9:$OR$9,H$17)} -> 0.00011213753 | I22: {=SUMPRODUCT('BEA Requirements Table'!$D11:$OR11,$D$8:$OR$8*($D$9:$OR$9=I$17))/SUMIFS($D$8:$OR$8,$D$9:$OR$9,I$17)} -> 0.0016638448 | J22: {=SUMPRODUCT('BEA Requirements Table'!$D11:$OR11,$D$8:$OR$8*($D$9:$OR$9=J$17))/SUMIFS($D$8:$OR$8,$D$9:$OR$9,J$17)} -> 0.00033249434 | K22: {=SUMPRODUCT('BEA Requirements Table'!$D11:$OR11,$D$8:$OR$8*($D$9:$OR$9=K$17))/SUMIFS($D$8:$OR$8,$D$9:$OR$9,K$17)} -> 0.00081033095 | ... AS22: {=SUMPRODUCT('BEA Requirements Table'!$D11:$OR11,$D$8:$OR$8*($D$9:$OR$9=AS$17))/SUMIFS($D$8:$OR$8,$D$9:$OR$9,AS$17)} -> 0
A23: 111900 | B23: 19518 | C23: ISIC 01T03 | D23: {=SUMPRODUCT('BEA Requirements Table'!$D12:$OR12,$D$8:$OR$8*($D$9:$OR$9=D$17))/SUMIFS($D$8:$OR$8,$D$9:$OR$9,D$17)} -> 0.047468672 | E23: {=SUMPRODUCT('BEA Requirements Table'!$D12:$OR12,$D$8:$OR$8*($D$9:$OR$9=E$17))/SUMIFS($D$8:$OR$8,$D$9:$OR$9,E$17)} -> 0.0003242 | F23: {=SUMPRODUCT('BEA Requirements Table'!$D12:$OR12,$D$8:$OR$8*($D$9:$OR$9=F$17))/SUMIFS($D$8:$OR$8,$D$9:$OR$9,F$17)} -> 4.85e-05 | G23: {=SUMPRODUCT('BEA Requirements Table'!$D12:$OR12,$D$8:$OR$8*($D$9:$OR$9=G$17))/SUMIFS($D$8:$OR$8,$D$9:$OR$9,G$17)} -> 0.00035064609 | H23: {=SUMPRODUCT('BEA Requirements Table'!$D12:$OR12,$D$8:$OR$8*($D$9:$OR$9=H$17))/SUMIFS($D$8:$OR$8,$D$9:$OR$9,H$17)} -> 0.00011197813 | I23: {=SUMPRODUCT('BEA Requirements Table'!$D12:$OR12,$D$8:$OR$8*($D$9:$OR$9=I$17))/SUMIFS($D$8:$OR$8,$D$9:$OR$9,I$17)} -> 0.011282704 | J23: {=SUMPRODUCT('BEA Requirements Table'!$D12:$OR12,$D$8:$OR$8*($D$9:$OR$9=J$17))/SUMIFS($D$8:$OR$8,$D$9:$OR$9,J$17)} -> 0.02644973 | K23: {=SUMPRODUCT('BEA Requirements Table'!$D12:$OR12,$D$8:$OR$8*($D$9:$OR$9=K$17))/SUMIFS($D$8:$OR$8,$D$9:$OR$9,K$17)} -> 0.011507855 | ... AS23: {=SUMPRODUCT('BEA Requirements Table'!$D12:$OR12,$D$8:$OR$8*($D$9:$OR$9=AS$17))/SUMIFS($D$8:$OR$8,$D$9:$OR$9,AS$17)} -> 0
A24: 112120 | B24: 36981 | C24: ISIC 01T03 | D24: {=SUMPRODUCT('BEA Requirements Table'!$D13:$OR13,$D$8:$OR$8*($D$9:$OR$9=D$17))/SUMIFS($D$8:$OR$8,$D$9:$OR$9,D$17)} -> 0.08145218 | E24: {=SUMPRODUCT('BEA Requirements Table'!$D13:$OR13,$D$8:$OR$8*($D$9:$OR$9=E$17))/SUMIFS($D$8:$OR$8,$D$9:$OR$9,E$17)} -> 3.76e-05 | F24: {=SUMPRODUCT('BEA Requirements Table'!$D13:$OR13,$D$8:$OR$8*($D$9:$OR$9=F$17))/SUMIFS($D$8:$OR$8,$D$9:$OR$9,F$17)} -> 2.27e-05 | G24: {=SUMPRODUCT('BEA Requirements Table'!$D13:$OR13,$D$8:$OR$8*($D$9:$OR$9=G$17))/SUMIFS($D$8:$OR$8,$D$9:$OR$9,G$17)} -> 3.8105538e-05 | H24: {=SUMPRODUCT('BEA Requirements Table'!$D13:$OR13,$D$8:$OR$8*($D$9:$OR$9=H$17))/SUMIFS($D$8:$OR$8,$D$9:$OR$9,H$17)} -> 5.4796581e-05 | I24: {=SUMPRODUCT('BEA Requirements Table'!$D13:$OR13,$D$8:$OR$8*($D$9:$OR$9=I$17))/SUMIFS($D$8:$OR$8,$D$9:$OR$9,I$17)} -> 0.056588641 | J24: {=SUMPRODUCT('BEA Requirements Table'!$D13:$OR13,$D$8:$OR$8*($D$9:$OR$9=J$17))/SUMIFS($D$8:$OR$8,$D$9:$OR$9,J$17)} -> 0.00011129828 | K24: {=SUMPRODUCT('BEA Requirements Table'!$D13:$OR13,$D$8:$OR$8*($D$9:$OR$9=K$17))/SUMIFS($D$8:$OR$8,$D$9:$OR$9,K$17)} -> 0.00050722726 | ... AS24: {=SUMPRODUCT('BEA Requirements Table'!$D13:$OR13,$D$8:$OR$8*($D$9:$OR$9=AS$17))/SUMIFS($D$8:$OR$8,$D$9:$OR$9,AS$17)} -> 0
A25: 1121A0 | B25: 78410 | C25: ISIC 01T03 | D25: {=SUMPRODUCT('BEA Requirements Table'!$D14:$OR14,$D$8:$OR$8*($D$9:$OR$9=D$17))/SUMIFS($D$8:$OR$8,$D$9:$OR$9,D$17)} -> 0.24867205 | E25: {=SUMPRODUCT('BEA Requirements Table'!$D14:$OR14,$D$8:$OR$8*($D$9:$OR$9=E$17))/SUMIFS($D$8:$OR$8,$D$9:$OR$9,E$17)} -> 8.58e-05 | F25: {=SUMPRODUCT('BEA Requirements Table'!$D14:$OR14,$D$8:$OR$8*($D$9:$OR$9=F$17))/SUMIFS($D$8:$OR$8,$D$9:$OR$9,F$17)} -> 5.36e-05 | G25: {=SUMPRODUCT('BEA Requirements Table'!$D14:$OR14,$D$8:$OR$8*($D$9:$OR$9=G$17))/SUMIFS($D$8:$OR$8,$D$9:$OR$9,G$17)} -> 7.8566958e-05 | H25: {=SUMPRODUCT('BEA Requirements Table'!$D14:$OR14,$D$8:$OR$8*($D$9:$OR$9=H$17))/SUMIFS($D$8:$OR$8,$D$9:$OR$9,H$17)} -> 9.8141284e-05 | I25: {=SUMPRODUCT('BEA Requirements Table'!$D14:$OR14,$D$8:$OR$8*($D$9:$OR$9=I$17))/SUMIFS($D$8:$OR$8,$D$9:$OR$9,I$17)} -> 0.111961 | J25: {=SUMPRODUCT('BEA Requirements Table'!$D14:$OR14,$D$8:$OR$8*($D$9:$OR$9=J$17))/SUMIFS($D$8:$OR$8,$D$9:$OR$9,J$17)} -> 0.0085939068 | K25: {=SUMPRODUCT('BEA Requirements Table'!$D14:$OR14,$D$8:$OR$8*($D$9:$OR$9=K$17))/SUMIFS($D$8:$OR$8,$D$9:$OR$9,K$17)} -> 0.0011581419 | ... AS25: {=SUMPRODUCT('BEA Requirements Table'!$D14:$OR14,$D$8:$OR$8*($D$9:$OR$9=AS$17))/SUMIFS($D$8:$OR$8,$D$9:$OR$9,AS$17)} -> 0
A26: 112300 | B26: 37700 | C26: ISIC 01T03 | D26: {=SUMPRODUCT('BEA Requirements Table'!$D15:$OR15,$D$8:$OR$8*($D$9:$OR$9=D$17))/SUMIFS($D$8:$OR$8,$D$9:$OR$9,D$17)} -> 0.092105172 | E26: {=SUMPRODUCT('BEA Requirements Table'!$D15:$OR15,$D$8:$OR$8*($D$9:$OR$9=E$17))/SUMIFS($D$8:$OR$8,$D$9:$OR$9,E$17)} -> 2.72e-05 | F26: {=SUMPRODUCT('BEA Requirements Table'!$D15:$OR15,$D$8:$OR$8*($D$9:$OR$9=F$17))/SUMIFS($D$8:$OR$8,$D$9:$OR$9,F$17)} -> 1.6e-05 | G26: {=SUMPRODUCT('BEA Requirements Table'!$D15:$OR15,$D$8:$OR$8*($D$9:$OR$9=G$17))/SUMIFS($D$8:$OR$8,$D$9:$OR$9,G$17)} -> 2.7208944e-05 | H26: {=SUMPRODUCT('BEA Requirements Table'!$D15:$OR15,$D$8:$OR$8*($D$9:$OR$9=H$17))/SUMIFS($D$8:$OR$8,$D$9:$OR$9,H$17)} -> 3.6119617e-05 | I26: {=SUMPRODUCT('BEA Requirements Table'!$D15:$OR15,$D$8:$OR$8*($D$9:$OR$9=I$17))/SUMIFS($D$8:$OR$8,$D$9:$OR$9,I$17)} -> 0.04318748 | J26: {=SUMPRODUCT('BEA Requirements Table'!$D15:$OR15,$D$8:$OR$8*($D$9:$OR$9=J$17))/SUMIFS($D$8:$OR$8,$D$9:$OR$9,J$17)} -> 0.00025514736 | K26: {=SUMPRODUCT('BEA Requirements Table'!$D15:$OR15,$D$8:$OR$8*($D$9:$OR$9=K$17))/SUMIFS($D$8:$OR$8,$D$9:$OR$9,K$17)} -> 0.00050768005 | ... AS26: {=SUMPRODUCT('BEA Requirements Table'!$D15:$OR15,$D$8:$OR$8*($D$9:$OR$9=AS$17))/SUMIFS($D$8:$OR$8,$D$9:$OR$9,AS$17)} -> 0
A27: 112A00 | B27: 39708 | C27: ISIC 01T03 | D27: {=SUMPRODUCT('BEA Requirements Table'!$D16:$OR16,$D$8:$OR$8*($D$9:$OR$9=D$17))/SUMIFS($D$8:$OR$8,$D$9:$OR$9,D$17)} -> 0.10385159 | E27: {=SUMPRODUCT('BEA Requirements Table'!$D16:$OR16,$D$8:$OR$8*($D$9:$OR$9=E$17))/SUMIFS($D$8:$OR$8,$D$9:$OR$9,E$17)} -> 7.66e-05 | F27: {=SUMPRODUCT('BEA Requirements Table'!$D16:$OR16,$D$8:$OR$8*($D$9:$OR$9=F$17))/SUMIFS($D$8:$OR$8,$D$9:$OR$9,F$17)} -> 3.18e-05 | G27: {=SUMPRODUCT('BEA Requirements Table'!$D16:$OR16,$D$8:$OR$8*($D$9:$OR$9=G$17))/SUMIFS($D$8:$OR$8,$D$9:$OR$9,G$17)} -> 5.8114684e-05 | H27: {=SUMPRODUCT('BEA Requirements Table'!$D16:$OR16,$D$8:$OR$8*($D$9:$OR$9=H$17))/SUMIFS($D$8:$OR$8,$D$9:$OR$9,H$17)} -> 4.872693e-05 | I27: {=SUMPRODUCT('BEA Requirements Table'!$D16:$OR16,$D$8:$OR$8*($D$9:$OR$9=I$17))/SUMIFS($D$8:$OR$8,$D$9:$OR$9,I$17)} -> 0.039660065 | J27: {=SUMPRODUCT('BEA Requirements Table'!$D16:$OR16,$D$8:$OR$8*($D$9:$OR$9=J$17))/SUMIFS($D$8:$OR$8,$D$9:$OR$9,J$17)} -> 0.013528182 | K27: {=SUMPRODUCT('BEA Requirements Table'!$D16:$OR16,$D$8:$OR$8*($D$9:$OR$9=K$17))/SUMIFS($D$8:$OR$8,$D$9:$OR$9,K$17)} -> 0.0023061151 | ... AS27: {=SUMPRODUCT('BEA Requirements Table'!$D16:$OR16,$D$8:$OR$8*($D$9:$OR$9=AS$17))/SUMIFS($D$8:$OR$8,$D$9:$OR$9,AS$17)} -> 0
A28: 113000 | B28: 15849 | C28: ISIC 01T03 | D28: {=SUMPRODUCT('BEA Requirements Table'!$D17:$OR17,$D$8:$OR$8*($D$9:$OR$9=D$17))/SUMIFS($D$8:$OR$8,$D$9:$OR$9,D$17)} -> 0.040087511 | E28: {=SUMPRODUCT('BEA Requirements Table'!$D17:$OR17,$D$8:$OR$8*($D$9:$OR$9=E$17))/SUMIFS($D$8:$OR$8,$D$9:$OR$9,E$17)} -> 0.0026828 | F28: {=SUMPRODUCT('BEA Requirements Table'!$D17:$OR17,$D$8:$OR$8*($D$9:$OR$9=F$17))/SUMIFS($D$8:$OR$8,$D$9:$OR$9,F$17)} -> 0.0001558 | G28: {=SUMPRODUCT('BEA Requirements Table'!$D17:$OR17,$D$8:$OR$8*($D$9:$OR$9=G$17))/SUMIFS($D$8:$OR$8,$D$9:$OR$9,G$17)} -> 0.00050720853 | H28: {=SUMPRODUCT('BEA Requirements Table'!$D17:$OR17,$D$8:$OR$8*($D$9:$OR$9=H$17))/SUMIFS($D$8:$OR$8,$D$9:$OR$9,H$17)} -> 0.00026714484 | I28: {=SUMPRODUCT('BEA Requirements Table'!$D17:$OR17,$D$8:$OR$8*($D$9:$OR$9=I$17))/SUMIFS($D$8:$OR$8,$D$9:$OR$9,I$17)} -> 0.0010194234 | J28: {=SUMPRODUCT('BEA Requirements Table'!$D17:$OR17,$D$8:$OR$8*($D$9:$OR$9=J$17))/SUMIFS($D$8:$OR$8,$D$9:$OR$9,J$17)} -> 0.0010747028 | K28: {=SUMPRODUCT('BEA Requirements Table'!$D17:$OR17,$D$8:$OR$8*($D$9:$OR$9=K$17))/SUMIFS($D$8:$OR$8,$D$9:$OR$9,K$17)} -> 0.16008748 | ... AS28: {=SUMPRODUCT('BEA Requirements Table'!$D17:$OR17,$D$8:$OR$8*($D$9:$OR$9=AS$17))/SUMIFS($D$8:$OR$8,$D$9:$OR$9,AS$17)} -> 0
A29: 114000 | B29: 7887 | C29: ISIC 01T03 | D29: {=SUMPRODUCT('BEA Requirements Table'!$D18:$OR18,$D$8:$OR$8*($D$9:$OR$9=D$17))/SUMIFS($D$8:$OR$8,$D$9:$OR$9,D$17)} -> 0.017200321 | E29: {=SUMPRODUCT('BEA Requirements Table'!$D18:$OR18,$D$8:$OR$8*($D$9:$OR$9=E$17))/SUMIFS($D$8:$OR$8,$D$9:$OR$9,E$17)} -> 5.2e-06 | F29: {=SUMPRODUCT('BEA Requirements Table'!$D18:$OR18,$D$8:$OR$8*($D$9:$OR$9=F$17))/SUMIFS($D$8:$OR$8,$D$9:$OR$9,F$17)} -> 2.5e-06 | G29: {=SUMPRODUCT('BEA Requirements Table'!$D18:$OR18,$D$8:$OR$8*($D$9:$OR$9=G$17))/SUMIFS($D$8:$OR$8,$D$9:$OR$9,G$17)} -> 4.2075841e-06 | H29: {=SUMPRODUCT('BEA Requirements Table'!$D18:$OR18,$D$8:$OR$8*($D$9:$OR$9=H$17))/SUMIFS($D$8:$OR$8,$D$9:$OR$9,H$17)} -> 6.0322624e-06 | I29: {=SUMPRODUCT('BEA Requirements Table'!$D18:$OR18,$D$8:$OR$8*($D$9:$OR$9=I$17))/SUMIFS($D$8:$OR$8,$D$9:$OR$9,I$17)} -> 0.00084031036 | J29: {=SUMPRODUCT('BEA Requirements Table'!$D18:$OR18,$D$8:$OR$8*($D$9:$OR$9=J$17))/SUMIFS($D$8:$OR$8,$D$9:$OR$9,J$17)} -> 1.0324652e-05 | K29: {=SUMPRODUCT('BEA Requirements Table'!$D18:$OR18,$D$8:$OR$8*($D$9:$OR$9=K$17))/SUMIFS($D$8:$OR$8,$D$9:$OR$9,K$17)} -> 7.3135378e-06 | ... AS29: {=SUMPRODUCT('BEA Requirements Table'!$D18:$OR18,$D$8:$OR$8*($D$9:$OR$9=AS$17))/SUMIFS($D$8:$OR$8,$D$9:$OR$9,AS$17)} -> 0
A30: 115000 | B30: 22530 | C30: ISIC 01T03 | D30: {=SUMPRODUCT('BEA Requirements Table'!$D19:$OR19,$D$8:$OR$8*($D$9:$OR$9=D$17))/SUMIFS($D$8:$OR$8,$D$9:$OR$9,D$17)} -> 0.10696281 | E30: {=SUMPRODUCT('BEA Requirements Table'!$D19:$OR19,$D$8:$OR$8*($D$9:$OR$9=E$17))/SUMIFS($D$8:$OR$8,$D$9:$OR$9,E$17)} -> 0.0005952 | F30: {=SUMPRODUCT('BEA Requirements Table'!$D19:$OR19,$D$8:$OR$8*($D$9:$OR$9=F$17))/SUMIFS($D$8:$OR$8,$D$9:$OR$9,F$17)} -> 0.0001213 | G30: {=SUMPRODUCT('BEA Requirements Table'!$D19:$OR19,$D$8:$OR$8*($D$9:$OR$9=G$17))/SUMIFS($D$8:$OR$8,$D$9:$OR$9,G$17)} -> 0.0003256584 | H30: {=SUMPRODUCT('BEA Requirements Table'!$D19:$OR19,$D$8:$OR$8*($D$9:$OR$9=H$17))/SUMIFS($D$8:$OR$8,$D$9:$OR$9,H$17)} -> 0.00015029542 | I30: {=SUMPRODUCT('BEA Requirements Table'!$D19:$OR19,$D$8:$OR$8*($D$9:$OR$9=I$17))/SUMIFS($D$8:$OR$8,$D$9:$OR$9,I$17)} -> 0.017493774 | J30: {=SUMPRODUCT('BEA Requirements Table'!$D19:$OR19,$D$8:$OR$8*($D$9:$OR$9=J$17))/SUMIFS($D$8:$OR$8,$D$9:$OR$9,J$17)} -> 0.0030481071 | K30: {=SUMPRODUCT('BEA Requirements Table'!$D19:$OR19,$D$8:$OR$8*($D$9:$OR$9=K$17))/SUMIFS($D$8:$OR$8,$D$9:$OR$9,K$17)} -> 0.030082597 | ... AS30: {=SUMPRODUCT('BEA Requirements Table'!$D19:$OR19,$D$8:$OR$8*($D$9:$OR$9=AS$17))/SUMIFS($D$8:$OR$8,$D$9:$OR$9,AS$17)} -> 0
A31: 211000 | B31: 348619 | C31: ISIC 06 | D31: {=SUMPRODUCT('BEA Requirements Table'!$D20:$OR20,$D$8:$OR$8*($D$9:$OR$9=D$17))/SUMIFS($D$8:$OR$8,$D$9:$OR$9,D$17)} -> 0.013743178 | E31: {=SUMPRODUCT('BEA Requirements Table'!$D20:$OR20,$D$8:$OR$8*($D$9:$OR$9=E$17))/SUMIFS($D$8:$OR$8,$D$9:$OR$9,E$17)} -> 0.0243075 | F31: {=SUMPRODUCT('BEA Requirements Table'!$D20:$OR20,$D$8:$OR$8*($D$9:$OR$9=F$17))/SUMIFS($D$8:$OR$8,$D$9:$OR$9,F$17)} -> 1.08943 | G31: {=SUMPRODUCT('BEA Requirements Table'!$D20:$OR20,$D$8:$OR$8*($D$9:$OR$9=G$17))/SUMIFS($D$8:$OR$8,$D$9:$OR$9,G$17)} -> 0.030401592 | H31: {=SUMPRODUCT('BEA Requirements Table'!$D20:$OR20,$D$8:$OR$8*($D$9:$OR$9=H$17))/SUMIFS($D$8:$OR$8,$D$9:$OR$9,H$17)} -> 0.01000578 | I31: {=SUMPRODUCT('BEA Requirements Table'!$D20:$OR20,$D$8:$OR$8*($D$9:$OR$9=I$17))/SUMIFS($D$8:$OR$8,$D$9:$OR$9,I$17)} -> 0.013314126 | J31: {=SUMPRODUCT('BEA Requirements Table'!$D20:$OR20,$D$8:$OR$8*($D$9:$OR$9=J$17))/SUMIFS($D$8:$OR$8,$D$9:$OR$9,J$17)} -> 0.015175169 | K31: {=SUMPRODUCT('BEA Requirements Table'!$D20:$OR20,$D$8:$OR$8*($D$9:$OR$9=K$17))/SUMIFS($D$8:$OR$8,$D$9:$OR$9,K$17)} -> 0.013443327 | ... AS31: {=SUMPRODUCT('BEA Requirements Table'!$D20:$OR20,$D$8:$OR$8*($D$9:$OR$9=AS$17))/SUMIFS($D$8:$OR$8,$D$9:$OR$9,AS$17)} -> 0
A32: 212100 | B32: 52499 | C32: ISIC 05 | D32: {=SUMPRODUCT('BEA Requirements Table'!$D21:$OR21,$D$8:$OR$8*($D$9:$OR$9=D$17))/SUMIFS($D$8:$OR$8,$D$9:$OR$9,D$17)} -> 0.0026402269 | E32: {=SUMPRODUCT('BEA Requirements Table'!$D21:$OR21,$D$8:$OR$8*($D$9:$OR$9=E$17))/SUMIFS($D$8:$OR$8,$D$9:$OR$9,E$17)} -> 1.08927 | F32: {=SUMPRODUCT('BEA Requirements Table'!$D21:$OR21,$D$8:$OR$8*($D$9:$OR$9=F$17))/SUMIFS($D$8:$OR$8,$D$9:$OR$9,F$17)} -> 0.0019034 | G32: {=SUMPRODUCT('BEA Requirements Table'!$D21:$OR21,$D$8:$OR$8*($D$9:$OR$9=G$17))/SUMIFS($D$8:$OR$8,$D$9:$OR$9,G$17)} -> 0.0057258045 | H32: {=SUMPRODUCT('BEA Requirements Table'!$D21:$OR21,$D$8:$OR$8*($D$9:$OR$9=H$17))/SUMIFS($D$8:$OR$8,$D$9:$OR$9,H$17)} -> 0.0009259352 | I32: {=SUMPRODUCT('BEA Requirements Table'!$D21:$OR21,$D$8:$OR$8*($D$9:$OR$9=I$17))/SUMIFS($D$8:$OR$8,$D$9:$OR$9,I$17)} -> 0.0044641371 | J32: {=SUMPRODUCT('BEA Requirements Table'!$D21:$OR21,$D$8:$OR$8*($D$9:$OR$9=J$17))/SUMIFS($D$8:$OR$8,$D$9:$OR$9,J$17)} -> 0.0037795621 | K32: {=SUMPRODUCT('BEA Requirements Table'!$D21:$OR21,$D$8:$OR$8*($D$9:$OR$9=K$17))/SUMIFS($D$8:$OR$8,$D$9:$OR$9,K$17)} -> 0.0023969017 | ... AS32: {=SUMPRODUCT('BEA Requirements Table'!$D21:$OR21,$D$8:$OR$8*($D$9:$OR$9=AS$17))/SUMIFS($D$8:$OR$8,$D$9:$OR$9,AS$17)} -> 0
A33: 212230 | B33: 13694 | C33: ISIC 07T08 | D33: {=SUMPRODUCT('BEA Requirements Table'!$D22:$OR22,$D$8:$OR$8*($D$9:$OR$9=D$17))/SUMIFS($D$8:$OR$8,$D$9:$OR$9,D$17)} -> 0.00018650044 | E33: {=SUMPRODUCT('BEA Requirements Table'!$D22:$OR22,$D$8:$OR$8*($D$9:$OR$9=E$17))/SUMIFS($D$8:$OR$8,$D$9:$OR$9,E$17)} -> 0.0002612 | F33: {=SUMPRODUCT('BEA Requirements Table'!$D22:$OR22,$D$8:$OR$8*($D$9:$OR$9=F$17))/SUMIFS($D$8:$OR$8,$D$9:$OR$9,F$17)} -> 0.0003822 | G33: {=SUMPRODUCT('BEA Requirements Table'!$D22:$OR22,$D$8:$OR$8*($D$9:$OR$9=G$17))/SUMIFS($D$8:$OR$8,$D$9:$OR$9,G$17)} -> 0.20587823 | H33: {=SUMPRODUCT('BEA Requirements Table'!$D22:$OR22,$D$8:$OR$8*($D$9:$OR$9=H$17))/SUMIFS($D$8:$OR$8,$D$9:$OR$9,H$17)} -> 0.00024526364 | I33: {=SUMPRODUCT('BEA Requirements Table'!$D22:$OR22,$D$8:$OR$8*($D$9:$OR$9=I$17))/SUMIFS($D$8:$OR$8,$D$9:$OR$9,I$17)} -> 0.00027123949 | J33: {=SUMPRODUCT('BEA Requirements Table'!$D22:$OR22,$D$8:$OR$8*($D$9:$OR$9=J$17))/SUMIFS($D$8:$OR$8,$D$9:$OR$9,J$17)} -> 0.00065440144 | K33: {=SUMPRODUCT('BEA Requirements Table'!$D22:$OR22,$D$8:$OR$8*($D$9:$OR$9=K$17))/SUMIFS($D$8:$OR$8,$D$9:$OR$9,K$17)} -> 0.00034090177 | ... AS33: {=SUMPRODUCT('BEA Requirements Table'!$D22:$OR22,$D$8:$OR$8*($D$9:$OR$9=AS$17))/SUMIFS($D$8:$OR$8,$D$9:$OR$9,AS$17)} -> 0
A34: 2122A0 | B34: 21814 | C34: ISIC 07T08 | D34: {=SUMPRODUCT('BEA Requirements Table'!$D23:$OR23,$D$8:$OR$8*($D$9:$OR$9=D$17))/SUMIFS($D$8:$OR$8,$D$9:$OR$9,D$17)} -> 0.00026700065 | E34: {=SUMPRODUCT('BEA Requirements Table'!$D23:$OR23,$D$8:$OR$8*($D$9:$OR$9=E$17))/SUMIFS($D$8:$OR$8,$D$9:$OR$9,E$17)} -> 0.0003714 | F34: {=SUMPRODUCT('BEA Requirements Table'!$D23:$OR23,$D$8:$OR$8*($D$9:$OR$9=F$17))/SUMIFS($D$8:$OR$8,$D$9:$OR$9,F$17)} -> 0.0005574 | G34: {=SUMPRODUCT('BEA Requirements Table'!$D23:$OR23,$D$8:$OR$8*($D$9:$OR$9=G$17))/SUMIFS($D$8:$OR$8,$D$9:$OR$9,G$17)} -> 0.32925314 | H34: {=SUMPRODUCT('BEA Requirements Table'!$D23:$OR23,$D$8:$OR$8*($D$9:$OR$9=H$17))/SUMIFS($D$8:$OR$8,$D$9:$OR$9,H$17)} -> 0.00029814019 | I34: {=SUMPRODUCT('BEA Requirements Table'!$D23:$OR23,$D$8:$OR$8*($D$9:$OR$9=I$17))/SUMIFS($D$8:$OR$8,$D$9:$OR$9,I$17)} -> 0.00031653196 | J34: {=SUMPRODUCT('BEA Requirements Table'!$D23:$OR23,$D$8:$OR$8*($D$9:$OR$9=J$17))/SUMIFS($D$8:$OR$8,$D$9:$OR$9,J$17)} -> 0.00051603516 | K34: {=SUMPRODUCT('BEA Requirements Table'!$D23:$OR23,$D$8:$OR$8*($D$9:$OR$9=K$17))/SUMIFS($D$8:$OR$8,$D$9:$OR$9,K$17)} -> 0.00044935204 | ... AS34: {=SUMPRODUCT('BEA Requirements Table'!$D23:$OR23,$D$8:$OR$8*($D$9:$OR$9=AS$17))/SUMIFS($D$8:$OR$8,$D$9:$OR$9,AS$17)} -> 0
A35: 212310 | B35: 15966 | C35: ISIC 07T08 | D35: {=SUMPRODUCT('BEA Requirements Table'!$D24:$OR24,$D$8:$OR$8*($D$9:$OR$9=D$17))/SUMIFS($D$8:$OR$8,$D$9:$OR$9,D$17)} -> 0.0021314728 | E35: {=SUMPRODUCT('BEA Requirements Table'!$D24:$OR24,$D$8:$OR$8*($D$9:$OR$9=E$17))/SUMIFS($D$8:$OR$8,$D$9:$OR$9,E$17)} -> 0.0111982 | F35: {=SUMPRODUCT('BEA Requirements Table'!$D24:$OR24,$D$8:$OR$8*($D$9:$OR$9=F$17))/SUMIFS($D$8:$OR$8,$D$9:$OR$9,F$17)} -> 0.0002978 | G35: {=SUMPRODUCT('BEA Requirements Table'!$D24:$OR24,$D$8:$OR$8*($D$9:$OR$9=G$17))/SUMIFS($D$8:$OR$8,$D$9:$OR$9,G$17)} -> 0.2428344 | H35: {=SUMPRODUCT('BEA Requirements Table'!$D24:$OR24,$D$8:$OR$8*($D$9:$OR$9=H$17))/SUMIFS($D$8:$OR$8,$D$9:$OR$9,H$17)} -> 0.00051561701 | I35: {=SUMPRODUCT('BEA Requirements Table'!$D24:$OR24,$D$8:$OR$8*($D$9:$OR$9=I$17))/SUMIFS($D$8:$OR$8,$D$9:$OR$9,I$17)} -> 0.00096098072 | J35: {=SUMPRODUCT('BEA Requirements Table'!$D24:$OR24,$D$8:$OR$8*($D$9:$OR$9=J$17))/SUMIFS($D$8:$OR$8,$D$9:$OR$9,J$17)} -> 0.00029361762 | K35: {=SUMPRODUCT('BEA Requirements Table'!$D24:$OR24,$D$8:$OR$8*($D$9:$OR$9=K$17))/SUMIFS($D$8:$OR$8,$D$9:$OR$9,K$17)} -> 0.00031675747 | ... AS35: {=SUMPRODUCT('BEA Requirements Table'!$D24:$OR24,$D$8:$OR$8*($D$9:$OR$9=AS$17))/SUMIFS($D$8:$OR$8,$D$9:$OR$9,AS$17)} -> 0
A36: 2123A0 | B36: 17038 | C36: ISIC 07T08 | D36: {=SUMPRODUCT('BEA Requirements Table'!$D25:$OR25,$D$8:$OR$8*($D$9:$OR$9=D$17))/SUMIFS($D$8:$OR$8,$D$9:$OR$9,D$17)} -> 0.0047946927 | E36: {=SUMPRODUCT('BEA Requirements Table'!$D25:$OR25,$D$8:$OR$8*($D$9:$OR$9=E$17))/SUMIFS($D$8:$OR$8,$D$9:$OR$9,E$17)} -> 0.001436 | F36: {=SUMPRODUCT('BEA Requirements Table'!$D25:$OR25,$D$8:$OR$8*($D$9:$OR$9=F$17))/SUMIFS($D$8:$OR$8,$D$9:$OR$9,F$17)} -> 0.0004306 | G36: {=SUMPRODUCT('BEA Requirements Table'!$D25:$OR25,$D$8:$OR$8*($D$9:$OR$9=G$17))/SUMIFS($D$8:$OR$8,$D$9:$OR$9,G$17)} -> 0.25347226 | H36: {=SUMPRODUCT('BEA Requirements Table'!$D25:$OR25,$D$8:$OR$8*($D$9:$OR$9=H$17))/SUMIFS($D$8:$OR$8,$D$9:$OR$9,H$17)} -> 0.00052239782 | I36: {=SUMPRODUCT('BEA Requirements Table'!$D25:$OR25,$D$8:$OR$8*($D$9:$OR$9=I$17))/SUMIFS($D$8:$OR$8,$D$9:$OR$9,I$17)} -> 0.0019089 | J36: {=SUMPRODUCT('BEA Requirements Table'!$D25:$OR25,$D$8:$OR$8*($D$9:$OR$9=J$17))/SUMIFS($D$8:$OR$8,$D$9:$OR$9,J$17)} -> 0.0010205434 | K36: {=SUMPRODUCT('BEA Requirements Table'!$D25:$OR25,$D$8:$OR$8*($D$9:$OR$9=K$17))/SUMIFS($D$8:$OR$8,$D$9:$OR$9,K$17)} -> 0.00098473567 | ... AS36: {=SUMPRODUCT('BEA Requirements Table'!$D25:$OR25,$D$8:$OR$8*($D$9:$OR$9=AS$17))/SUMIFS($D$8:$OR$8,$D$9:$OR$9,AS$17)} -> 0
A37: 213111 | B37: 32666 | C37: ISIC 09 | D37: {=SUMPRODUCT('BEA Requirements Table'!$D26:$OR26,$D$8:$OR$8*($D$9:$OR$9=D$17))/SUMIFS($D$8:$OR$8,$D$9:$OR$9,D$17)} -> 8.233732e-06 | E37: {=SUMPRODUCT('BEA Requirements Table'!$D26:$OR26,$D$8:$OR$8*($D$9:$OR$9=E$17))/SUMIFS($D$8:$OR$8,$D$9:$OR$9,E$17)} -> 0.0001456 | F37: {=SUMPRODUCT('BEA Requirements Table'!$D26:$OR26,$D$8:$OR$8*($D$9:$OR$9=F$17))/SUMIFS($D$8:$OR$8,$D$9:$OR$9,F$17)} -> 0.0003744 | G37: {=SUMPRODUCT('BEA Requirements Table'!$D26:$OR26,$D$8:$OR$8*($D$9:$OR$9=G$17))/SUMIFS($D$8:$OR$8,$D$9:$OR$9,G$17)} -> 0.00021835005 | H37: {=SUMPRODUCT('BEA Requirements Table'!$D26:$OR26,$D$8:$OR$8*($D$9:$OR$9=H$17))/SUMIFS($D$8:$OR$8,$D$9:$OR$9,H$17)} -> 0.2605028 | I37: {=SUMPRODUCT('BEA Requirements Table'!$D26:$OR26,$D$8:$OR$8*($D$9:$OR$9=I$17))/SUMIFS($D$8:$OR$8,$D$9:$OR$9,I$17)} -> 1.0919598e-05 | J37: {=SUMPRODUCT('BEA Requirements Table'!$D26:$OR26,$D$8:$OR$8*($D$9:$OR$9=J$17))/SUMIFS($D$8:$OR$8,$D$9:$OR$9,J$17)} -> 1.6812358e-05 | K37: {=SUMPRODUCT('BEA Requirements Table'!$D26:$OR26,$D$8:$OR$8*($D$9:$OR$9=K$17))/SUMIFS($D$8:$OR$8,$D$9:$OR$9,K$17)} -> 1.3996599e-05 | ... AS37: {=SUMPRODUCT('BEA Requirements Table'!$D26:$OR26,$D$8:$OR$8*($D$9:$OR$9=AS$17))/SUMIFS($D$8:$OR$8,$D$9:$OR$9,AS$17)} -> 0
A38: 21311A | B38: 92768 | C38: ISIC 09 | D38: {=SUMPRODUCT('BEA Requirements Table'!$D27:$OR27,$D$8:$OR$8*($D$9:$OR$9=D$17))/SUMIFS($D$8:$OR$8,$D$9:$OR$9,D$17)} -> 0.00076773325 | E38: {=SUMPRODUCT('BEA Requirements Table'!$D27:$OR27,$D$8:$OR$8*($D$9:$OR$9=E$17))/SUMIFS($D$8:$OR$8,$D$9:$OR$9,E$17)} -> 0.0165598 | F38: {=SUMPRODUCT('BEA Requirements Table'!$D27:$OR27,$D$8:$OR$8*($D$9:$OR$9=F$17))/SUMIFS($D$8:$OR$8,$D$9:$OR$9,F$17)} -> 0.0420161 | G38: {=SUMPRODUCT('BEA Requirements Table'!$D27:$OR27,$D$8:$OR$8*($D$9:$OR$9=G$17))/SUMIFS($D$8:$OR$8,$D$9:$OR$9,G$17)} -> 0.024786374 | H38: {=SUMPRODUCT('BEA Requirements Table'!$D27:$OR27,$D$8:$OR$8*($D$9:$OR$9=H$17))/SUMIFS($D$8:$OR$8,$D$9:$OR$9,H$17)} -> 0.74855572 | I38: {=SUMPRODUCT('BEA Requirements Table'!$D27:$OR27,$D$8:$OR$8*($D$9:$OR$9=I$17))/SUMIFS($D$8:$OR$8,$D$9:$OR$9,I$17)} -> 0.00073531283 | J38: {=SUMPRODUCT('BEA Requirements Table'!$D27:$OR27,$D$8:$OR$8*($D$9:$OR$9=J$17))/SUMIFS($D$8:$OR$8,$D$9:$OR$9,J$17)} -> 0.00085447939 | K38: {=SUMPRODUCT('BEA Requirements Table'!$D27:$OR27,$D$8:$OR$8*($D$9:$OR$9=K$17))/SUMIFS($D$8:$OR$8,$D$9:$OR$9,K$17)} -> 0.00073163378 | ... AS38: {=SUMPRODUCT('BEA Requirements Table'!$D27:$OR27,$D$8:$OR$8*($D$9:$OR$9=AS$17))/SUMIFS($D$8:$OR$8,$D$9:$OR$9,AS$17)} -> 0
A39: 221100 | B39: 339301 | C39: ISIC 351 | D39: {=SUMPRODUCT('BEA Requirements Table'!$D28:$OR28,$D$8:$OR$8*($D$9:$OR$9=D$17))/SUMIFS($D$8:$OR$8,$D$9:$OR$9,D$17)} -> 0.014465011 | E39: {=SUMPRODUCT('BEA Requirements Table'!$D28:$OR28,$D$8:$OR$8*($D$9:$OR$9=E$17))/SUMIFS($D$8:$OR$8,$D$9:$OR$9,E$17)} -> 0.0295842 | F39: {=SUMPRODUCT('BEA Requirements Table'!$D28:$OR28,$D$8:$OR$8*($D$9:$OR$9=F$17))/SUMIFS($D$8:$OR$8,$D$9:$OR$9,F$17)} -> 0.0137376 | G39: {=SUMPRODUCT('BEA Requirements Table'!$D28:$OR28,$D$8:$OR$8*($D$9:$OR$9=G$17))/SUMIFS($D$8:$OR$8,$D$9:$OR$9,G$17)} -> 0.047963592 | H39: {=SUMPRODUCT('BEA Requirements Table'!$D28:$OR28,$D$8:$OR$8*($D$9:$OR$9=H$17))/SUMIFS($D$8:$OR$8,$D$9:$OR$9,H$17)} -> 0.0048063029 | I39: {=SUMPRODUCT('BEA Requirements Table'!$D28:$OR28,$D$8:$OR$8*($D$9:$OR$9=I$17))/SUMIFS($D$8:$OR$8,$D$9:$OR$9,I$17)} -> 0.020639786 | J39: {=SUMPRODUCT('BEA Requirements Table'!$D28:$OR28,$D$8:$OR$8*($D$9:$OR$9=J$17))/SUMIFS($D$8:$OR$8,$D$9:$OR$9,J$17)} -> 0.02940217 | K39: {=SUMPRODUCT('BEA Requirements Table'!$D28:$OR28,$D$8:$OR$8*($D$9:$OR$9=K$17))/SUMIFS($D$8:$OR$8,$D$9:$OR$9,K$17)} -> 0.029479147 | ... AS39: {=SUMPRODUCT('BEA Requirements Table'!$D28:$OR28,$D$8:$OR$8*($D$9:$OR$9=AS$17))/SUMIFS($D$8:$OR$8,$D$9:$OR$9,AS$17)} -> 0
A40: 221200 | B40: 78708 | C40: ISIC 352T353 | D40: {=SUMPRODUCT('BEA Requirements Table'!$D29:$OR29,$D$8:$OR$8*($D$9:$OR$9=D$17))/SUMIFS($D$8:$OR$8,$D$9:$OR$9,D$17)} -> 0.0072812674 | E40: {=SUMPRODUCT('BEA Requirements Table'!$D29:$OR29,$D$8:$OR$8*($D$9:$OR$9=E$17))/SUMIFS($D$8:$OR$8,$D$9:$OR$9,E$17)} -> 0.0021629 | F40: {=SUMPRODUCT('BEA Requirements Table'!$D29:$OR29,$D$8:$OR$8*($D$9:$OR$9=F$17))/SUMIFS($D$8:$OR$8,$D$9:$OR$9,F$17)} -> 0.0028386 | G40: {=SUMPRODUCT('BEA Requirements Table'!$D29:$OR29,$D$8:$OR$8*($D$9:$OR$9=G$17))/SUMIFS($D$8:$OR$8,$D$9:$OR$9,G$17)} -> 0.0072437037 | H40: {=SUMPRODUCT('BEA Requirements Table'!$D29:$OR29,$D$8:$OR$8*($D$9:$OR$9=H$17))/SUMIFS($D$8:$OR$8,$D$9:$OR$9,H$17)} -> 0.0011110647 | I40: {=SUMPRODUCT('BEA Requirements Table'!$D29:$OR29,$D$8:$OR$8*($D$9:$OR$9=I$17))/SUMIFS($D$8:$OR$8,$D$9:$OR$9,I$17)} -> 0.0062433237 | J40: {=SUMPRODUCT('BEA Requirements Table'!$D29:$OR29,$D$8:$OR$8*($D$9:$OR$9=J$17))/SUMIFS($D$8:$OR$8,$D$9:$OR$9,J$17)} -> 0.0054971923 | K40: {=SUMPRODUCT('BEA Requirements Table'!$D29:$OR29,$D$8:$OR$8*($D$9:$OR$9=K$17))/SUMIFS($D$8:$OR$8,$D$9:$OR$9,K$17)} -> 0.0041364979 | ... AS40: {=SUMPRODUCT('BEA Requirements Table'!$D29:$OR29,$D$8:$OR$8*($D$9:$OR$9=AS$17))/SUMIFS($D$8:$OR$8,$D$9:$OR$9,AS$17)} -> 0
A41: 221300 | B41: 12583 | C41: ISIC 36T39 | D41: {=SUMPRODUCT('BEA Requirements Table'!$D30:$OR30,$D$8:$OR$8*($D$9:$OR$9=D$17))/SUMIFS($D$8:$OR$8,$D$9:$OR$9,D$17)} -> 0.00094486975 | E41: {=SUMPRODUCT('BEA Requirements Table'!$D30:$OR30,$D$8:$OR$8*($D$9:$OR$9=E$17))/SUMIFS($D$8:$OR$8,$D$9:$OR$9,E$17)} -> 0.0002776 | F41: {=SUMPRODUCT('BEA Requirements Table'!$D30:$OR30,$D$8:$OR$8*($D$9:$OR$9=F$17))/SUMIFS($D$8:$OR$8,$D$9:$OR$9,F$17)} -> 0.0012174 | G41: {=SUMPRODUCT('BEA Requirements Table'!$D30:$OR30,$D$8:$OR$8*($D$9:$OR$9=G$17))/SUMIFS($D$8:$OR$8,$D$9:$OR$9,G$17)} -> 0.00042791176 | H41: {=SUMPRODUCT('BEA Requirements Table'!$D30:$OR30,$D$8:$OR$8*($D$9:$OR$9=H$17))/SUMIFS($D$8:$OR$8,$D$9:$OR$9,H$17)} -> 0.00011252796 | I41: {=SUMPRODUCT('BEA Requirements Table'!$D30:$OR30,$D$8:$OR$8*($D$9:$OR$9=I$17))/SUMIFS($D$8:$OR$8,$D$9:$OR$9,I$17)} -> 0.00062023835 | J41: {=SUMPRODUCT('BEA Requirements Table'!$D30:$OR30,$D$8:$OR$8*($D$9:$OR$9=J$17))/SUMIFS($D$8:$OR$8,$D$9:$OR$9,J$17)} -> 0.0004890576 | K41: {=SUMPRODUCT('BEA Requirements Table'!$D30:$OR30,$D$8:$OR$8*($D$9:$OR$9=K$17))/SUMIFS($D$8:$OR$8,$D$9:$OR$9,K$17)} -> 0.00038478886 | ... AS41: {=SUMPRODUCT('BEA Requirements Table'!$D30:$OR30,$D$8:$OR$8*($D$9:$OR$9=AS$17))/SUMIFS($D$8:$OR$8,$D$9:$OR$9,AS$17)} -> 0
A42: 233210 | B42: 43893 | C42: ISIC 41T43 | D42: {=SUMPRODUCT('BEA Requirements Table'!$D31:$OR31,$D$8:$OR$8*($D$9:$OR$9=D$17))/SUMIFS($D$8:$OR$8,$D$9:$OR$9,D$17)} -> 0 | E42: {=SUMPRODUCT('BEA Requirements Table'!$D31:$OR31,$D$8:$OR$8*($D$9:$OR$9=E$17))/SUMIFS($D$8:$OR$8,$D$9:$OR$9,E$17)} -> 0 | F42: {=SUMPRODUCT('BEA Requirements Table'!$D31:$OR31,$D$8:$OR$8*($D$9:$OR$9=F$17))/SUMIFS($D$8:$OR$8,$D$9:$OR$9,F$17)} -> 0 | G42: {=SUMPRODUCT('BEA Requirements Table'!$D31:$OR31,$D$8:$OR$8*($D$9:$OR$9=G$17))/SUMIFS($D$8:$OR$8,$D$9:$OR$9,G$17)} -> 0 | H42: {=SUMPRODUCT('BEA Requirements Table'!$D31:$OR31,$D$8:$OR$8*($D$9:$OR$9=H$17))/SUMIFS($D$8:$OR$8,$D$9:$OR$9,H$17)} -> 0 | I42: {=SUMPRODUCT('BEA Requirements Table'!$D31:$OR31,$D$8:$OR$8*($D$9:$OR$9=I$17))/SUMIFS($D$8:$OR$8,$D$9:$OR$9,I$17)} -> 0 | J42: {=SUMPRODUCT('BEA Requirements Table'!$D31:$OR31,$D$8:$OR$8*($D$9:$OR$9=J$17))/SUMIFS($D$8:$OR$8,$D$9:$OR$9,J$17)} -> 0 | K42: {=SUMPRODUCT('BEA Requirements Table'!$D31:$OR31,$D$8:$OR$8*($D$9:$OR$9=K$17))/SUMIFS($D$8:$OR$8,$D$9:$OR$9,K$17)} -> 0 | ... AS42: {=SUMPRODUCT('BEA Requirements Table'!$D31:$OR31,$D$8:$OR$8*($D$9:$OR$9=AS$17))/SUMIFS($D$8:$OR$8,$D$9:$OR$9,AS$17)} -> 0
A43: 233262 | B43: 68219 | C43: ISIC 41T43 | D43: {=SUMPRODUCT('BEA Requirements Table'!$D32:$OR32,$D$8:$OR$8*($D$9:$OR$9=D$17))/SUMIFS($D$8:$OR$8,$D$9:$OR$9,D$17)} -> 0 | E43: {=SUMPRODUCT('BEA Requirements Table'!$D32:$OR32,$D$8:$OR$8*($D$9:$OR$9=E$17))/SUMIFS($D$8:$OR$8,$D$9:$OR$9,E$17)} -> 0 | F43: {=SUMPRODUCT('BEA Requirements Table'!$D32:$OR32,$D$8:$OR$8*($D$9:$OR$9=F$17))/SUMIFS($D$8:$OR$8,$D$9:$OR$9,F$17)} -> 0 | G43: {=SUMPRODUCT('BEA Requirements Table'!$D32:$OR32,$D$8:$OR$8*($D$9:$OR$9=G$17))/SUMIFS($D$8:$OR$8,$D$9:$OR$9,G$17)} -> 0 | H43: {=SUMPRODUCT('BEA Requirements Table'!$D32:$OR32,$D$8:$OR$8*($D$9:$OR$9=H$17))/SUMIFS($D$8:$OR$8,$D$9:$OR$9,H$17)} -> 0 | I43: {=SUMPRODUCT('BEA Requirements Table'!$D32:$OR32,$D$8:$OR$8*($D$9:$OR$9=I$17))/SUMIFS($D$8:$OR$8,$D$9:$OR$9,I$17)} -> 0 | J43: {=SUMPRODUCT('BEA Requirements Table'!$D32:$OR32,$D$8:$OR$8*($D$9:$OR$9=J$17))/SUMIFS($D$8:$OR$8,$D$9:$OR$9,J$17)} -> 0 | K43: {=SUMPRODUCT('BEA Requirements Table'!$D32:$OR32,$D$8:$OR$8*($D$9:$OR$9=K$17))/SUMIFS($D$8:$OR$8,$D$9:$OR$9,K$17)} -> 0 | ... AS43: {=SUMPRODUCT('BEA Requirements Table'!$D32:$OR32,$D$8:$OR$8*($D$9:$OR$9=AS$17))/SUMIFS($D$8:$OR$8,$D$9:$OR$9,AS$17)} -> 0
A44: 230301 | B44: 174351 | C44: ISIC 41T43 | D44: {=SUMPRODUCT('BEA Requirements Table'!$D33:$OR33,$D$8:$OR$8*($D$9:$OR$9=D$17))/SUMIFS($D$8:$OR$8,$D$9:$OR$9,D$17)} -> 0.014280078 | E44: {=SUMPRODUCT('BEA Requirements Table'!$D33:$OR33,$D$8:$OR$8*($D$9:$OR$9=E$17))/SUMIFS($D$8:$OR$8,$D$9:$OR$9,E$17)} -> 0.0225519 | F44: {=SUMPRODUCT('BEA Requirements Table'!$D33:$OR33,$D$8:$OR$8*($D$9:$OR$9=F$17))/SUMIFS($D$8:$OR$8,$D$9:$OR$9,F$17)} -> 0.0075243 | G44: {=SUMPRODUCT('BEA Requirements Table'!$D33:$OR33,$D$8:$OR$8*($D$9:$OR$9=G$17))/SUMIFS($D$8:$OR$8,$D$9:$OR$9,G$17)} -> 0.032048142 | H44: {=SUMPRODUCT('BEA Requirements Table'!$D33:$OR33,$D$8:$OR$8*($D$9:$OR$9=H$17))/SUMIFS($D$8:$OR$8,$D$9:$OR$9,H$17)} -> 0.015024282 | I44: {=SUMPRODUCT('BEA Requirements Table'!$D33:$OR33,$D$8:$OR$8*($D$9:$OR$9=I$17))/SUMIFS($D$8:$OR$8,$D$9:$OR$9,I$17)} -> 0.010152407 | J44: {=SUMPRODUCT('BEA Requirements Table'!$D33:$OR33,$D$8:$OR$8*($D$9:$OR$9=J$17))/SUMIFS($D$8:$OR$8,$D$9:$OR$9,J$17)} -> 0.0071157777 | K44: {=SUMPRODUCT('BEA Requirements Table'!$D33:$OR33,$D$8:$OR$8*($D$9:$OR$9=K$17))/SUMIFS($D$8:$OR$8,$D$9:$OR$9,K$17)} -> 0.0079073025 | ... AS44: {=SUMPRODUCT('BEA Requirements Table'!$D33:$OR33,$D$8:$OR$8*($D$9:$OR$9=AS$17))/SUMIFS($D$8:$OR$8,$D$9:$OR$9,AS$17)} -> 0
A45: 230302 | B45: 67878 | C45: ISIC 41T43 | D45: {=SUMPRODUCT('BEA Requirements Table'!$D34:$OR34,$D$8:$OR$8*($D$9:$OR$9=D$17))/SUMIFS($D$8:$OR$8,$D$9:$OR$9,D$17)} -> 0.00031844207 | E45: {=SUMPRODUCT('BEA Requirements Table'!$D34:$OR34,$D$8:$OR$8*($D$9:$OR$9=E$17))/SUMIFS($D$8:$OR$8,$D$9:$OR$9,E$17)} -> 0.0001047 | F45: {=SUMPRODUCT('BEA Requirements Table'!$D34:$OR34,$D$8:$OR$8*($D$9:$OR$9=F$17))/SUMIFS($D$8:$OR$8,$D$9:$OR$9,F$17)} -> 0.0002408 | G45: {=SUMPRODUCT('BEA Requirements Table'!$D34:$OR34,$D$8:$OR$8*($D$9:$OR$9=G$17))/SUMIFS($D$8:$OR$8,$D$9:$OR$9,G$17)} -> 0.00019452121 | H45: {=SUMPRODUCT('BEA Requirements Table'!$D34:$OR34,$D$8:$OR$8*($D$9:$OR$9=H$17))/SUMIFS($D$8:$OR$8,$D$9:$OR$9,H$17)} -> 5.4984347e-05 | I45: {=SUMPRODUCT('BEA Requirements Table'!$D34:$OR34,$D$8:$OR$8*($D$9:$OR$9=I$17))/SUMIFS($D$8:$OR$8,$D$9:$OR$9,I$17)} -> 0.00025471293 | J45: {=SUMPRODUCT('BEA Requirements Table'!$D34:$OR34,$D$8:$OR$8*($D$9:$OR$9=J$17))/SUMIFS($D$8:$OR$8,$D$9:$OR$9,J$17)} -> 0.00020202324 | K45: {=SUMPRODUCT('BEA Requirements Table'!$D34:$OR34,$D$8:$OR$8*($D$9:$OR$9=K$17))/SUMIFS($D$8:$OR$8,$D$9:$OR$9,K$17)} -> 0.00019799675 | ... AS45: {=SUMPRODUCT('BEA Requirements Table'!$D34:$OR34,$D$8:$OR$8*($D$9:$OR$9=AS$17))/SUMIFS($D$8:$OR$8,$D$9:$OR$9,AS$17)} -> 0
A46: 2332A0 | B46: 73715 | C46: ISIC 41T43 | D46: {=SUMPRODUCT('BEA Requirements Table'!$D35:$OR35,$D$8:$OR$8*($D$9:$OR$9=D$17))/SUMIFS($D$8:$OR$8,$D$9:$OR$9,D$17)} -> 7.6839091e-05 | E46: {=SUMPRODUCT('BEA Requirements Table'!$D35:$OR35,$D$8:$OR$8*($D$9:$OR$9=E$17))/SUMIFS($D$8:$OR$8,$D$9:$OR$9,E$17)} -> 0.0001213 | F46: {=SUMPRODUCT('BEA Requirements Table'!$D35:$OR35,$D$8:$OR$8*($D$9:$OR$9=F$17))/SUMIFS($D$8:$OR$8,$D$9:$OR$9,F$17)} -> 4.05e-05 | G46: {=SUMPRODUCT('BEA Requirements Table'!$D35:$OR35,$D$8:$OR$8*($D$9:$OR$9=G$17))/SUMIFS($D$8:$OR$8,$D$9:$OR$9,G$17)} -> 0.00017244485 | H46: {=SUMPRODUCT('BEA Requirements Table'!$D35:$OR35,$D$8:$OR$8*($D$9:$OR$9=H$17))/SUMIFS($D$8:$OR$8,$D$9:$OR$9,H$17)} -> 8.0854749e-05 | I46: {=SUMPRODUCT('BEA Requirements Table'!$D35:$OR35,$D$8:$OR$8*($D$9:$OR$9=I$17))/SUMIFS($D$8:$OR$8,$D$9:$OR$9,I$17)} -> 5.4629998e-05 | J46: {=SUMPRODUCT('BEA Requirements Table'!$D35:$OR35,$D$8:$OR$8*($D$9:$OR$9=J$17))/SUMIFS($D$8:$OR$8,$D$9:$OR$9,J$17)} -> 3.8270558e-05 | K46: {=SUMPRODUCT('BEA Requirements Table'!$D35:$OR35,$D$8:$OR$8*($D$9:$OR$9=K$17))/SUMIFS($D$8:$OR$8,$D$9:$OR$9,K$17)} -> 4.2526429e-05 | ... AS46: {=SUMPRODUCT('BEA Requirements Table'!$D35:$OR35,$D$8:$OR$8*($D$9:$OR$9=AS$17))/SUMIFS($D$8:$OR$8,$D$9:$OR$9,AS$17)} -> 0
A47: 233412 | B47: 26126 | C47: ISIC 41T43 | D47: {=SUMPRODUCT('BEA Requirements Table'!$D36:$OR36,$D$8:$OR$8*($D$9:$OR$9=D$17))/SUMIFS($D$8:$OR$8,$D$9:$OR$9,D$17)} -> 0 | E47: {=SUMPRODUCT('BEA Requirements Table'!$D36:$OR36,$D$8:$OR$8*($D$9:$OR$9=E$17))/SUMIFS($D$8:$OR$8,$D$9:$OR$9,E$17)} -> 0 | F47: {=SUMPRODUCT('BEA Requirements Table'!$D36:$OR36,$D$8:$OR$8*($D$9:$OR$9=F$17))/SUMIFS($D$8:$OR$8,$D$9:$OR$9,F$17)} -> 0 | G47: {=SUMPRODUCT('BEA Requirements Table'!$D36:$OR36,$D$8:$OR$8*($D$9:$OR$9=G$17))/SUMIFS($D$8:$OR$8,$D$9:$OR$9,G$17)} -> 0 | H47: {=SUMPRODUCT('BEA Requirements Table'!$D36:$OR36,$D$8:$OR$8*($D$9:$OR$9=H$17))/SUMIFS($D$8:$OR$8,$D$9:$OR$9,H$17)} -> 0 | I47: {=SUMPRODUCT('BEA Requirements Table'!$D36:$OR36,$D$8:$OR$8*($D$9:$OR$9=I$17))/SUMIFS($D$8:$OR$8,$D$9:$OR$9,I$17)} -> 0 | J47: {=SUMPRODUCT('BEA Requirements Table'!$D36:$OR36,$D$8:$OR$8*($D$9:$OR$9=J$17))/SUMIFS($D$8:$OR$8,$D$9:$OR$9,J$17)} -> 0 | K47: {=SUMPRODUCT('BEA Requirements Table'!$D36:$OR36,$D$8:$OR$8*($D$9:$OR$9=K$17))/SUMIFS($D$8:$OR$8,$D$9:$OR$9,K$17)} -> 0 | ... AS47: {=SUMPRODUCT('BEA Requirements Table'!$D36:$OR36,$D$8:$OR$8*($D$9:$OR$9=AS$17))/SUMIFS($D$8:$OR$8,$D$9:$OR$9,AS$17)} -> 0
A48: 2334A0 | B48: 165931 | C48: ISIC 41T43 | D48: {=SUMPRODUCT('BEA Requirements Table'!$D37:$OR37,$D$8:$OR$8*($D$9:$OR$9=D$17))/SUMIFS($D$8:$OR$8,$D$9:$OR$9,D$17)} -> 0.00017184144 | E48: {=SUMPRODUCT('BEA Requirements Table'!$D37:$OR37,$D$8:$OR$8*($D$9:$OR$9=E$17))/SUMIFS($D$8:$OR$8,$D$9:$OR$9,E$17)} -> 5.65e-05 | F48: {=SUMPRODUCT('BEA Requirements Table'!$D37:$OR37,$D$8:$OR$8*($D$9:$OR$9=F$17))/SUMIFS($D$8:$OR$8,$D$9:$OR$9,F$17)} -> 0.0001299 | G48: {=SUMPRODUCT('BEA Requirements Table'!$D37:$OR37,$D$8:$OR$8*($D$9:$OR$9=G$17))/SUMIFS($D$8:$OR$8,$D$9:$OR$9,G$17)} -> 0.00010498363 | H48: {=SUMPRODUCT('BEA Requirements Table'!$D37:$OR37,$D$8:$OR$8*($D$9:$OR$9=H$17))/SUMIFS($D$8:$OR$8,$D$9:$OR$9,H$17)} -> 2.965311e-05 | I48: {=SUMPRODUCT('BEA Requirements Table'!$D37:$OR37,$D$8:$OR$8*($D$9:$OR$9=I$17))/SUMIFS($D$8:$OR$8,$D$9:$OR$9,I$17)} -> 0.00013745006 | J48: {=SUMPRODUCT('BEA Requirements Table'!$D37:$OR37,$D$8:$OR$8*($D$9:$OR$9=J$17))/SUMIFS($D$8:$OR$8,$D$9:$OR$9,J$17)} -> 0.00010902936 | K48: {=SUMPRODUCT('BEA Requirements Table'!$D37:$OR37,$D$8:$OR$8*($D$9:$OR$9=K$17))/SUMIFS($D$8:$OR$8,$D$9:$OR$9,K$17)} -> 0.0001068446 | ... AS48: {=SUMPRODUCT('BEA Requirements Table'!$D37:$OR37,$D$8:$OR$8*($D$9:$OR$9=AS$17))/SUMIFS($D$8:$OR$8,$D$9:$OR$9,AS$17)} -> 0
A49: 233230 | B49: 37260 | C49: ISIC 41T43 | D49: {=SUMPRODUCT('BEA Requirements Table'!$D38:$OR38,$D$8:$OR$8*($D$9:$OR$9=D$17))/SUMIFS($D$8:$OR$8,$D$9:$OR$9,D$17)} -> 0 | E49: {=SUMPRODUCT('BEA Requirements Table'!$D38:$OR38,$D$8:$OR$8*($D$9:$OR$9=E$17))/SUMIFS($D$8:$OR$8,$D$9:$OR$9,E$17)} -> 0 | F49: {=SUMPRODUCT('BEA Requirements Table'!$D38:$OR38,$D$8:$OR$8*($D$9:$OR$9=F$17))/SUMIFS($D$8:$OR$8,$D$9:$OR$9,F$17)} -> 0 | G49: {=SUMPRODUCT('BEA Requirements Table'!$D38:$OR38,$D$8:$OR$8*($D$9:$OR$9=G$17))/SUMIFS($D$8:$OR$8,$D$9:$OR$9,G$17)} -> 0 | H49: {=SUMPRODUCT('BEA Requirements Table'!$D38:$OR38,$D$8:$OR$8*($D$9:$OR$9=H$17))/SUMIFS($D$8:$OR$8,$D$9:$OR$9,H$17)} -> 0 | I49: {=SUMPRODUCT('BEA Requirements Table'!$D38:$OR38,$D$8:$OR$8*($D$9:$OR$9=I$17))/SUMIFS($D$8:$OR$8,$D$9:$OR$9,I$17)} -> 0 | J49: {=SUMPRODUCT('BEA Requirements Table'!$D38:$OR38,$D$8:$OR$8*($D$9:$OR$9=J$17))/SUMIFS($D$8:$OR$8,$D$9:$OR$9,J$17)} -> 0 | K49: {=SUMPRODUCT('BEA Requirements Table'!$D38:$OR38,$D$8:$OR$8*($D$9:$OR$9=K$17))/SUMIFS($D$8:$OR$8,$D$9:$OR$9,K$17)} -> 0 | ... AS49: {=SUMPRODUCT('BEA Requirements Table'!$D38:$OR38,$D$8:$OR$8*($D$9:$OR$9=AS$17))/SUMIFS($D$8:$OR$8,$D$9:$OR$9,AS$17)} -> 0
A50: 2332D0 | B50: 85743 | C50: ISIC 41T43 | D50: {=SUMPRODUCT('BEA Requirements Table'!$D39:$OR39,$D$8:$OR$8*($D$9:$OR$9=D$17))/SUMIFS($D$8:$OR$8,$D$9:$OR$9,D$17)} -> 0 | E50: {=SUMPRODUCT('BEA Requirements Table'!$D39:$OR39,$D$8:$OR$8*($D$9:$OR$9=E$17))/SUMIFS($D$8:$OR$8,$D$9:$OR$9,E$17)} -> 0 | F50: {=SUMPRODUCT('BEA Requirements Table'!$D39:$OR39,$D$8:$OR$8*($D$9:$OR$9=F$17))/SUMIFS($D$8:$OR$8,$D$9:$OR$9,F$17)} -> 0 | G50: {=SUMPRODUCT('BEA Requirements Table'!$D39:$OR39,$D$8:$OR$8*($D$9:$OR$9=G$17))/SUMIFS($D$8:$OR$8,$D$9:$OR$9,G$17)} -> 0 | H50: {=SUMPRODUCT('BEA Requirements Table'!$D39:$OR39,$D$8:$OR$8*($D$9:$OR$9=H$17))/SUMIFS($D$8:$OR$8,$D$9:$OR$9,H$17)} -> 0 | I50: {=SUMPRODUCT('BEA Requirements Table'!$D39:$OR39,$D$8:$OR$8*($D$9:$OR$9=I$17))/SUMIFS($D$8:$OR$8,$D$9:$OR$9,I$17)} -> 0 | J50: {=SUMPRODUCT('BEA Requirements Table'!$D39:$OR39,$D$8:$OR$8*($D$9:$OR$9=J$17))/SUMIFS($D$8:$OR$8,$D$9:$OR$9,J$17)} -> 0 | K50: {=SUMPRODUCT('BEA Requirements Table'!$D39:$OR39,$D$8:$OR$8*($D$9:$OR$9=K$17))/SUMIFS($D$8:$OR$8,$D$9:$OR$9,K$17)} -> 0 | ... AS50: {=SUMPRODUCT('BEA Requirements Table'!$D39:$OR39,$D$8:$OR$8*($D$9:$OR$9=AS$17))/SUMIFS($D$8:$OR$8,$D$9:$OR$9,AS$17)} -> 0
A51: 233240 | B51: 93986 | C51: ISIC 41T43 | D51: {=SUMPRODUCT('BEA Requirements Table'!$D40:$OR40,$D$8:$OR$8*($D$9:$OR$9=D$17))/SUMIFS($D$8:$OR$8,$D$9:$OR$9,D$17)} -> 0 | E51: {=SUMPRODUCT('BEA Requirements Table'!$D40:$OR40,$D$8:$OR$8*($D$9:$OR$9=E$17))/SUMIFS($D$8:$OR$8,$D$9:$OR$9,E$17)} -> 0 | F51: {=SUMPRODUCT('BEA Requirements Table'!$D40:$OR40,$D$8:$OR$8*($D$9:$OR$9=F$17))/SUMIFS($D$8:$OR$8,$D$9:$OR$9,F$17)} -> 0 | G51: {=SUMPRODUCT('BEA Requirements Table'!$D40:$OR40,$D$8:$OR$8*($D$9:$OR$9=G$17))/SUMIFS($D$8:$OR$8,$D$9:$OR$9,G$17)} -> 0 | H51: {=SUMPRODUCT('BEA Requirements Table'!$D40:$OR40,$D$8:$OR$8*($D$9:$OR$9=H$17))/SUMIFS($D$8:$OR$8,$D$9:$OR$9,H$17)} -> 0 | I51: {=SUMPRODUCT('BEA Requirements Table'!$D40:$OR40,$D$8:$OR$8*($D$9:$OR$9=I$17))/SUMIFS($D$8:$OR$8,$D$9:$OR$9,I$17)} -> 0 | J51: {=SUMPRODUCT('BEA Requirements Table'!$D40:$OR40,$D$8:$OR$8*($D$9:$OR$9=J$17))/SUMIFS($D$8:$OR$8,$D$9:$OR$9,J$17)} -> 0 | K51: {=SUMPRODUCT('BEA Requirements Table'!$D40:$OR40,$D$8:$OR$8*($D$9:$OR$9=K$17))/SUMIFS($D$8:$OR$8,$D$9:$OR$9,K$17)} -> 0 | ... AS51: {=SUMPRODUCT('BEA Requirements Table'!$D40:$OR40,$D$8:$OR$8*($D$9:$OR$9=AS$17))/SUMIFS($D$8:$OR$8,$D$9:$OR$9,AS$17)} -> 0
A52: 233411 | B52: 122107 | C52: ISIC 41T43 | D52: {=SUMPRODUCT('BEA Requirements Table'!$D41:$OR41,$D$8:$OR$8*($D$9:$OR$9=D$17))/SUMIFS($D$8:$OR$8,$D$9:$OR$9,D$17)} -> 7.7292201e-08 | E52: {=SUMPRODUCT('BEA Requirements Table'!$D41:$OR41,$D$8:$OR$8*($D$9:$OR$9=E$17))/SUMIFS($D$8:$OR$8,$D$9:$OR$9,E$17)} -> 0 | F52: {=SUMPRODUCT('BEA Requirements Table'!$D41:$OR41,$D$8:$OR$8*($D$9:$OR$9=F$17))/SUMIFS($D$8:$OR$8,$D$9:$OR$9,F$17)} -> 1e-07 | G52: {=SUMPRODUCT('BEA Requirements Table'!$D41:$OR41,$D$8:$OR$8*($D$9:$OR$9=G$17))/SUMIFS($D$8:$OR$8,$D$9:$OR$9,G$17)} -> 2.3303947e-08 | H52: {=SUMPRODUCT('BEA Requirements Table'!$D41:$OR41,$D$8:$OR$8*($D$9:$OR$9=H$17))/SUMIFS($D$8:$OR$8,$D$9:$OR$9,H$17)} -> 0 | I52: {=SUMPRODUCT('BEA Requirements Table'!$D41:$OR41,$D$8:$OR$8*($D$9:$OR$9=I$17))/SUMIFS($D$8:$OR$8,$D$9:$OR$9,I$17)} -> 8.9644188e-08 | J52: {=SUMPRODUCT('BEA Requirements Table'!$D41:$OR41,$D$8:$OR$8*($D$9:$OR$9=J$17))/SUMIFS($D$8:$OR$8,$D$9:$OR$9,J$17)} -> 5.5007482e-08 | K52: {=SUMPRODUCT('BEA Requirements Table'!$D41:$OR41,$D$8:$OR$8*($D$9:$OR$9=K$17))/SUMIFS($D$8:$OR$8,$D$9:$OR$9,K$17)} -> 2.5507839e-08 | ... AS52: {=SUMPRODUCT('BEA Requirements Table'!$D41:$OR41,$D$8:$OR$8*($D$9:$OR$9=AS$17))/SUMIFS($D$8:$OR$8,$D$9:$OR$9,AS$17)} -> 0
A53: 2332C0 | B53: 114097 | C53: ISIC 41T43 | D53: {=SUMPRODUCT('BEA Requirements Table'!$D42:$OR42,$D$8:$OR$8*($D$9:$OR$9=D$17))/SUMIFS($D$8:$OR$8,$D$9:$OR$9,D$17)} -> 0 | E53: {=SUMPRODUCT('BEA Requirements Table'!$D42:$OR42,$D$8:$OR$8*($D$9:$OR$9=E$17))/SUMIFS($D$8:$OR$8,$D$9:$OR$9,E$17)} -> 0 | F53: {=SUMPRODUCT('BEA Requirements Table'!$D42:$OR42,$D$8:$OR$8*($D$9:$OR$9=F$17))/SUMIFS($D$8:$OR$8,$D$9:$OR$9,F$17)} -> 0 | G53: {=SUMPRODUCT('BEA Requirements Table'!$D42:$OR42,$D$8:$OR$8*($D$9:$OR$9=G$17))/SUMIFS($D$8:$OR$8,$D$9:$OR$9,G$17)} -> 0 | H53: {=SUMPRODUCT('BEA Requirements Table'!$D42:$OR42,$D$8:$OR$8*($D$9:$OR$9=H$17))/SUMIFS($D$8:$OR$8,$D$9:$OR$9,H$17)} -> 0 | I53: {=SUMPRODUCT('BEA Requirements Table'!$D42:$OR42,$D$8:$OR$8*($D$9:$OR$9=I$17))/SUMIFS($D$8:$OR$8,$D$9:$OR$9,I$17)} -> 0 | J53: {=SUMPRODUCT('BEA Requirements Table'!$D42:$OR42,$D$8:$OR$8*($D$9:$OR$9=J$17))/SUMIFS($D$8:$OR$8,$D$9:$OR$9,J$17)} -> 0 | K53: {=SUMPRODUCT('BEA Requirements Table'!$D42:$OR42,$D$8:$OR$8*($D$9:$OR$9=K$17))/SUMIFS($D$8:$OR$8,$D$9:$OR$9,K$17)} -> 0 | ... AS53: {=SUMPRODUCT('BEA Requirements Table'!$D42:$OR42,$D$8:$OR$8*($D$9:$OR$9=AS$17))/SUMIFS($D$8:$OR$8,$D$9:$OR$9,AS$17)} -> 0
A54: 321100 | B54: 23444 | C54: ISIC 16 | D54: {=SUMPRODUCT('BEA Requirements Table'!$D43:$OR43,$D$8:$OR$8*($D$9:$OR$9=D$17))/SUMIFS($D$8:$OR$8,$D$9:$OR$9,D$17)} -> 0.00061762567 | E54: {=SUMPRODUCT('BEA Requirements Table'!$D43:$OR43,$D$8:$OR$8*($D$9:$OR$9=E$17))/SUMIFS($D$8:$OR$8,$D$9:$OR$9,E$17)} -> 0.0022699 | F54: {=SUMPRODUCT('BEA Requirements Table'!$D43:$OR43,$D$8:$OR$8*($D$9:$OR$9=F$17))/SUMIFS($D$8:$OR$8,$D$9:$OR$9,F$17)} -> 0.00026 | G54: {=SUMPRODUCT('BEA Requirements Table'!$D43:$OR43,$D$8:$OR$8*($D$9:$OR$9=G$17))/SUMIFS($D$8:$OR$8,$D$9:$OR$9,G$17)} -> 0.00081107179 | H54: {=SUMPRODUCT('BEA Requirements Table'!$D43:$OR43,$D$8:$OR$8*($D$9:$OR$9=H$17))/SUMIFS($D$8:$OR$8,$D$9:$OR$9,H$17)} -> 0.00054069822 | I54: {=SUMPRODUCT('BEA Requirements Table'!$D43:$OR43,$D$8:$OR$8*($D$9:$OR$9=I$17))/SUMIFS($D$8:$OR$8,$D$9:$OR$9,I$17)} -> 0.0011120332 | J54: {=SUMPRODUCT('BEA Requirements Table'!$D43:$OR43,$D$8:$OR$8*($D$9:$OR$9=J$17))/SUMIFS($D$8:$OR$8,$D$9:$OR$9,J$17)} -> 0.00067737709 | K54: {=SUMPRODUCT('BEA Requirements Table'!$D43:$OR43,$D$8:$OR$8*($D$9:$OR$9=K$17))/SUMIFS($D$8:$OR$8,$D$9:$OR$9,K$17)} -> 0.41540759 | ... AS54: {=SUMPRODUCT('BEA Requirements Table'!$D43:$OR43,$D$8:$OR$8*($D$9:$OR$9=AS$17))/SUMIFS($D$8:$OR$8,$D$9:$OR$9,AS$17)} -> 0
A55: 321200 | B55: 17223 | C55: ISIC 16 | D55: {=SUMPRODUCT('BEA Requirements Table'!$D44:$OR44,$D$8:$OR$8*($D$9:$OR$9=D$17))/SUMIFS($D$8:$OR$8,$D$9:$OR$9,D$17)} -> 0.00019320348 | E55: {=SUMPRODUCT('BEA Requirements Table'!$D44:$OR44,$D$8:$OR$8*($D$9:$OR$9=E$17))/SUMIFS($D$8:$OR$8,$D$9:$OR$9,E$17)} -> 0.0002744 | F55: {=SUMPRODUCT('BEA Requirements Table'!$D44:$OR44,$D$8:$OR$8*($D$9:$OR$9=F$17))/SUMIFS($D$8:$OR$8,$D$9:$OR$9,F$17)} -> 0.0001153 | G55: {=SUMPRODUCT('BEA Requirements Table'!$D44:$OR44,$D$8:$OR$8*($D$9:$OR$9=G$17))/SUMIFS($D$8:$OR$8,$D$9:$OR$9,G$17)} -> 0.00032055254 | H55: {=SUMPRODUCT('BEA Requirements Table'!$D44:$OR44,$D$8:$OR$8*($D$9:$OR$9=H$17))/SUMIFS($D$8:$OR$8,$D$9:$OR$9,H$17)} -> 0.00019709323 | I55: {=SUMPRODUCT('BEA Requirements Table'!$D44:$OR44,$D$8:$OR$8*($D$9:$OR$9=I$17))/SUMIFS($D$8:$OR$8,$D$9:$OR$9,I$17)} -> 0.00019530804 | J55: {=SUMPRODUCT('BEA Requirements Table'!$D44:$OR44,$D$8:$OR$8*($D$9:$OR$9=J$17))/SUMIFS($D$8:$OR$8,$D$9:$OR$9,J$17)} -> 0.00013688471 | K55: {=SUMPRODUCT('BEA Requirements Table'!$D44:$OR44,$D$8:$OR$8*($D$9:$OR$9=K$17))/SUMIFS($D$8:$OR$8,$D$9:$OR$9,K$17)} -> 0.24798114 | ... AS55: {=SUMPRODUCT('BEA Requirements Table'!$D44:$OR44,$D$8:$OR$8*($D$9:$OR$9=AS$17))/SUMIFS($D$8:$OR$8,$D$9:$OR$9,AS$17)} -> 0
A56: 321910 | B56: 20581 | C56: ISIC 16 | D56: {=SUMPRODUCT('BEA Requirements Table'!$D45:$OR45,$D$8:$OR$8*($D$9:$OR$9=D$17))/SUMIFS($D$8:$OR$8,$D$9:$OR$9,D$17)} -> 0.00087758881 | E56: {=SUMPRODUCT('BEA Requirements Table'!$D45:$OR45,$D$8:$OR$8*($D$9:$OR$9=E$17))/SUMIFS($D$8:$OR$8,$D$9:$OR$9,E$17)} -> 0.0007222 | F56: {=SUMPRODUCT('BEA Requirements Table'!$D45:$OR45,$D$8:$OR$8*($D$9:$OR$9=F$17))/SUMIFS($D$8:$OR$8,$D$9:$OR$9,F$17)} -> 0.0002425 | G56: {=SUMPRODUCT('BEA Requirements Table'!$D45:$OR45,$D$8:$OR$8*($D$9:$OR$9=G$17))/SUMIFS($D$8:$OR$8,$D$9:$OR$9,G$17)} -> 0.0005781192 | H56: {=SUMPRODUCT('BEA Requirements Table'!$D45:$OR45,$D$8:$OR$8*($D$9:$OR$9=H$17))/SUMIFS($D$8:$OR$8,$D$9:$OR$9,H$17)} -> 0.0004958041 | I56: {=SUMPRODUCT('BEA Requirements Table'!$D45:$OR45,$D$8:$OR$8*($D$9:$OR$9=I$17))/SUMIFS($D$8:$OR$8,$D$9:$OR$9,I$17)} -> 0.00062005795 | J56: {=SUMPRODUCT('BEA Requirements Table'!$D45:$OR45,$D$8:$OR$8*($D$9:$OR$9=J$17))/SUMIFS($D$8:$OR$8,$D$9:$OR$9,J$17)} -> 0.0003772896 | K56: {=SUMPRODUCT('BEA Requirements Table'!$D45:$OR45,$D$8:$OR$8*($D$9:$OR$9=K$17))/SUMIFS($D$8:$OR$8,$D$9:$OR$9,K$17)} -> 0.28766926 | ... AS56: {=SUMPRODUCT('BEA Requirements Table'!$D45:$OR45,$D$8:$OR$8*($D$9:$OR$9=AS$17))/SUMIFS($D$8:$OR$8,$D$9:$OR$9,AS$17)} -> 0
A57: 3219A0 | B57: 19437 | C57: ISIC 16 | D57: {=SUMPRODUCT('BEA Requirements Table'!$D46:$OR46,$D$8:$OR$8*($D$9:$OR$9=D$17))/SUMIFS($D$8:$OR$8,$D$9:$OR$9,D$17)} -> 0.00081031924 | E57: {=SUMPRODUCT('BEA Requirements Table'!$D46:$OR46,$D$8:$OR$8*($D$9:$OR$9=E$17))/SUMIFS($D$8:$OR$8,$D$9:$OR$9,E$17)} -> 0.0002928 | F57: {=SUMPRODUCT('BEA Requirements Table'!$D46:$OR46,$D$8:$OR$8*($D$9:$OR$9=F$17))/SUMIFS($D$8:$OR$8,$D$9:$OR$9,F$17)} -> 0.000165 | G57: {=SUMPRODUCT('BEA Requirements Table'!$D46:$OR46,$D$8:$OR$8*($D$9:$OR$9=G$17))/SUMIFS($D$8:$OR$8,$D$9:$OR$9,G$17)} -> 0.00084004195 | H57: {=SUMPRODUCT('BEA Requirements Table'!$D46:$OR46,$D$8:$OR$8*($D$9:$OR$9=H$17))/SUMIFS($D$8:$OR$8,$D$9:$OR$9,H$17)} -> 0.0005442391 | I57: {=SUMPRODUCT('BEA Requirements Table'!$D46:$OR46,$D$8:$OR$8*($D$9:$OR$9=I$17))/SUMIFS($D$8:$OR$8,$D$9:$OR$9,I$17)} -> 0.00096651301 | J57: {=SUMPRODUCT('BEA Requirements Table'!$D46:$OR46,$D$8:$OR$8*($D$9:$OR$9=J$17))/SUMIFS($D$8:$OR$8,$D$9:$OR$9,J$17)} -> 0.0005706618 | K57: {=SUMPRODUCT('BEA Requirements Table'!$D46:$OR46,$D$8:$OR$8*($D$9:$OR$9=K$17))/SUMIFS($D$8:$OR$8,$D$9:$OR$9,K$17)} -> 0.25116861 | ... AS57: {=SUMPRODUCT('BEA Requirements Table'!$D46:$OR46,$D$8:$OR$8*($D$9:$OR$9=AS$17))/SUMIFS($D$8:$OR$8,$D$9:$OR$9,AS$17)} -> 0
A58: 327100 | B58: 7260 | C58: ISIC 239 | D58: {=SUMPRODUCT('BEA Requirements Table'!$D47:$OR47,$D$8:$OR$8*($D$9:$OR$9=D$17))/SUMIFS($D$8:$OR$8,$D$9:$OR$9,D$17)} -> 6.156324e-05 | E58: {=SUMPRODUCT('BEA Requirements Table'!$D47:$OR47,$D$8:$OR$8*($D$9:$OR$9=E$17))/SUMIFS($D$8:$OR$8,$D$9:$OR$9,E$17)} -> 0.0001332 | F58: {=SUMPRODUCT('BEA Requirements Table'!$D47:$OR47,$D$8:$OR$8*($D$9:$OR$9=F$17))/SUMIFS($D$8:$OR$8,$D$9:$OR$9,F$17)} -> 0.000142 | G58: {=SUMPRODUCT('BEA Requirements Table'!$D47:$OR47,$D$8:$OR$8*($D$9:$OR$9=G$17))/SUMIFS($D$8:$OR$8,$D$9:$OR$9,G$17)} -> 0.00018658115 | H58: {=SUMPRODUCT('BEA Requirements Table'!$D47:$OR47,$D$8:$OR$8*($D$9:$OR$9=H$17))/SUMIFS($D$8:$OR$8,$D$9:$OR$9,H$17)} -> 0.00011636555 | I58: {=SUMPRODUCT('BEA Requirements Table'!$D47:$OR47,$D$8:$OR$8*($D$9:$OR$9=I$17))/SUMIFS($D$8:$OR$8,$D$9:$OR$9,I$17)} -> 0.00014887722 | J58: {=SUMPRODUCT('BEA Requirements Table'!$D47:$OR47,$D$8:$OR$8*($D$9:$OR$9=J$17))/SUMIFS($D$8:$OR$8,$D$9:$OR$9,J$17)} -> 0.00010703683 | K58: {=SUMPRODUCT('BEA Requirements Table'!$D47:$OR47,$D$8:$OR$8*($D$9:$OR$9=K$17))/SUMIFS($D$8:$OR$8,$D$9:$OR$9,K$17)} -> 0.00019472376 | ... AS58: {=SUMPRODUCT('BEA Requirements Table'!$D47:$OR47,$D$8:$OR$8*($D$9:$OR$9=AS$17))/SUMIFS($D$8:$OR$8,$D$9:$OR$9,AS$17)} -> 0
A59: 327200 | B59: 23558 | C59: ISIC 231 | D59: {=SUMPRODUCT('BEA Requirements Table'!$D48:$OR48,$D$8:$OR$8*($D$9:$OR$9=D$17))/SUMIFS($D$8:$OR$8,$D$9:$OR$9,D$17)} -> 0.00045576164 | E59: {=SUMPRODUCT('BEA Requirements Table'!$D48:$OR48,$D$8:$OR$8*($D$9:$OR$9=E$17))/SUMIFS($D$8:$OR$8,$D$9:$OR$9,E$17)} -> 0.0001691 | F59: {=SUMPRODUCT('BEA Requirements Table'!$D48:$OR48,$D$8:$OR$8*($D$9:$OR$9=F$17))/SUMIFS($D$8:$OR$8,$D$9:$OR$9,F$17)} -> 0.0001226 | G59: {=SUMPRODUCT('BEA Requirements Table'!$D48:$OR48,$D$8:$OR$8*($D$9:$OR$9=G$17))/SUMIFS($D$8:$OR$8,$D$9:$OR$9,G$17)} -> 0.00020333799 | H59: {=SUMPRODUCT('BEA Requirements Table'!$D48:$OR48,$D$8:$OR$8*($D$9:$OR$9=H$17))/SUMIFS($D$8:$OR$8,$D$9:$OR$9,H$17)} -> 0.00018517648 | I59: {=SUMPRODUCT('BEA Requirements Table'!$D48:$OR48,$D$8:$OR$8*($D$9:$OR$9=I$17))/SUMIFS($D$8:$OR$8,$D$9:$OR$9,I$17)} -> 0.0052564122 | J59: {=SUMPRODUCT('BEA Requirements Table'!$D48:$OR48,$D$8:$OR$8*($D$9:$OR$9=J$17))/SUMIFS($D$8:$OR$8,$D$9:$OR$9,J$17)} -> 0.0019710091 | K59: {=SUMPRODUCT('BEA Requirements Table'!$D48:$OR48,$D$8:$OR$8*($D$9:$OR$9=K$17))/SUMIFS($D$8:$OR$8,$D$9:$OR$9,K$17)} -> 0.0020262942 | ... AS59: {=SUMPRODUCT('BEA Requirements Table'!$D48:$OR48,$D$8:$OR$8*($D$9:$OR$9=AS$17))/SUMIFS($D$8:$OR$8,$D$9:$OR$9,AS$17)} -> 0
A60: 327310 | B60: 5921 | C60: ISIC 239 | D60: {=SUMPRODUCT('BEA Requirements Table'!$D49:$OR49,$D$8:$OR$8*($D$9:$OR$9=D$17))/SUMIFS($D$8:$OR$8,$D$9:$OR$9,D$17)} -> 0.00011712888 | E60: {=SUMPRODUCT('BEA Requirements Table'!$D49:$OR49,$D$8:$OR$8*($D$9:$OR$9=E$17))/SUMIFS($D$8:$OR$8,$D$9:$OR$9,E$17)} -> 0.0003038 | F60: {=SUMPRODUCT('BEA Requirements Table'!$D49:$OR49,$D$8:$OR$8*($D$9:$OR$9=F$17))/SUMIFS($D$8:$OR$8,$D$9:$OR$9,F$17)} -> 0.0023851 | G60: {=SUMPRODUCT('BEA Requirements Table'!$D49:$OR49,$D$8:$OR$8*($D$9:$OR$9=G$17))/SUMIFS($D$8:$OR$8,$D$9:$OR$9,G$17)} -> 0.00032527314 | H60: {=SUMPRODUCT('BEA Requirements Table'!$D49:$OR49,$D$8:$OR$8*($D$9:$OR$9=H$17))/SUMIFS($D$8:$OR$8,$D$9:$OR$9,H$17)} -> 0.0021404299 | I60: {=SUMPRODUCT('BEA Requirements Table'!$D49:$OR49,$D$8:$OR$8*($D$9:$OR$9=I$17))/SUMIFS($D$8:$OR$8,$D$9:$OR$9,I$17)} -> 9.4181019e-05 | J60: {=SUMPRODUCT('BEA Requirements Table'!$D49:$OR49,$D$8:$OR$8*($D$9:$OR$9=J$17))/SUMIFS($D$8:$OR$8,$D$9:$OR$9,J$17)} -> 7.887051e-05 | K60: {=SUMPRODUCT('BEA Requirements Table'!$D49:$OR49,$D$8:$OR$8*($D$9:$OR$9=K$17))/SUMIFS($D$8:$OR$8,$D$9:$OR$9,K$17)} -> 9.2930116e-05 | ... AS60: {=SUMPRODUCT('BEA Requirements Table'!$D49:$OR49,$D$8:$OR$8*($D$9:$OR$9=AS$17))/SUMIFS($D$8:$OR$8,$D$9:$OR$9,AS$17)} -> 0
A61: 327320 | B61: 20848 | C61: ISIC 239 | D61: {=SUMPRODUCT('BEA Requirements Table'!$D50:$OR50,$D$8:$OR$8*($D$9:$OR$9=D$17))/SUMIFS($D$8:$OR$8,$D$9:$OR$9,D$17)} -> 0.0003646938 | E61: {=SUMPRODUCT('BEA Requirements Table'!$D50:$OR50,$D$8:$OR$8*($D$9:$OR$9=E$17))/SUMIFS($D$8:$OR$8,$D$9:$OR$9,E$17)} -> 0.0010194 | F61: {=SUMPRODUCT('BEA Requirements Table'!$D50:$OR50,$D$8:$OR$8*($D$9:$OR$9=F$17))/SUMIFS($D$8:$OR$8,$D$9:$OR$9,F$17)} -> 0.0002133 | G61: {=SUMPRODUCT('BEA Requirements Table'!$D50:$OR50,$D$8:$OR$8*($D$9:$OR$9=G$17))/SUMIFS($D$8:$OR$8,$D$9:$OR$9,G$17)} -> 0.00070664559 | H61: {=SUMPRODUCT('BEA Requirements Table'!$D50:$OR50,$D$8:$OR$8*($D$9:$OR$9=H$17))/SUMIFS($D$8:$OR$8,$D$9:$OR$9,H$17)} -> 0.00037138065 | I61: {=SUMPRODUCT('BEA Requirements Table'!$D50:$OR50,$D$8:$OR$8*($D$9:$OR$9=I$17))/SUMIFS($D$8:$OR$8,$D$9:$OR$9,I$17)} -> 0.00025416457 | J61: {=SUMPRODUCT('BEA Requirements Table'!$D50:$OR50,$D$8:$OR$8*($D$9:$OR$9=J$17))/SUMIFS($D$8:$OR$8,$D$9:$OR$9,J$17)} -> 0.00018217864 | K61: {=SUMPRODUCT('BEA Requirements Table'!$D50:$OR50,$D$8:$OR$8*($D$9:$OR$9=K$17))/SUMIFS($D$8:$OR$8,$D$9:$OR$9,K$17)} -> 0.00021138126 | ... AS61: {=SUMPRODUCT('BEA Requirements Table'!$D50:$OR50,$D$8:$OR$8*($D$9:$OR$9=AS$17))/SUMIFS($D$8:$OR$8,$D$9:$OR$9,AS$17)} -> 0
A62: 327330 | B62: 5693 | C62: ISIC 239 | D62: {=SUMPRODUCT('BEA Requirements Table'!$D51:$OR51,$D$8:$OR$8*($D$9:$OR$9=D$17))/SUMIFS($D$8:$OR$8,$D$9:$OR$9,D$17)} -> 8.5964958e-05 | E62: {=SUMPRODUCT('BEA Requirements Table'!$D51:$OR51,$D$8:$OR$8*($D$9:$OR$9=E$17))/SUMIFS($D$8:$OR$8,$D$9:$OR$9,E$17)} -> 0.0002106 | F62: {=SUMPRODUCT('BEA Requirements Table'!$D51:$OR51,$D$8:$OR$8*($D$9:$OR$9=F$17))/SUMIFS($D$8:$OR$8,$D$9:$OR$9,F$17)} -> 5.29e-05 | G62: {=SUMPRODUCT('BEA Requirements Table'!$D51:$OR51,$D$8:$OR$8*($D$9:$OR$9=G$17))/SUMIFS($D$8:$OR$8,$D$9:$OR$9,G$17)} -> 0.00015212998 | H62: {=SUMPRODUCT('BEA Requirements Table'!$D51:$OR51,$D$8:$OR$8*($D$9:$OR$9=H$17))/SUMIFS($D$8:$OR$8,$D$9:$OR$9,H$17)} -> 0.00011968783 | I62: {=SUMPRODUCT('BEA Requirements Table'!$D51:$OR51,$D$8:$OR$8*($D$9:$OR$9=I$17))/SUMIFS($D$8:$OR$8,$D$9:$OR$9,I$17)} -> 7.4042683e-05 | J62: {=SUMPRODUCT('BEA Requirements Table'!$D51:$OR51,$D$8:$OR$8*($D$9:$OR$9=J$17))/SUMIFS($D$8:$OR$8,$D$9:$OR$9,J$17)} -> 5.8724707e-05 | K62: {=SUMPRODUCT('BEA Requirements Table'!$D51:$OR51,$D$8:$OR$8*($D$9:$OR$9=K$17))/SUMIFS($D$8:$OR$8,$D$9:$OR$9,K$17)} -> 7.0287363e-05 | ... AS62: {=SUMPRODUCT('BEA Requirements Table'!$D51:$OR51,$D$8:$OR$8*($D$9:$OR$9=AS$17))/SUMIFS($D$8:$OR$8,$D$9:$OR$9,AS$17)} -> 0
A63: 327390 | B63: 8728 | C63: ISIC 239 | D63: {=SUMPRODUCT('BEA Requirements Table'!$D52:$OR52,$D$8:$OR$8*($D$9:$OR$9=D$17))/SUMIFS($D$8:$OR$8,$D$9:$OR$9,D$17)} -> 0.00010284512 | E63: {=SUMPRODUCT('BEA Requirements Table'!$D52:$OR52,$D$8:$OR$8*($D$9:$OR$9=E$17))/SUMIFS($D$8:$OR$8,$D$9:$OR$9,E$17)} -> 0.0001631 | F63: {=SUMPRODUCT('BEA Requirements Table'!$D52:$OR52,$D$8:$OR$8*($D$9:$OR$9=F$17))/SUMIFS($D$8:$OR$8,$D$9:$OR$9,F$17)} -> 6.69e-05 | G63: {=SUMPRODUCT('BEA Requirements Table'!$D52:$OR52,$D$8:$OR$8*($D$9:$OR$9=G$17))/SUMIFS($D$8:$OR$8,$D$9:$OR$9,G$17)} -> 0.0002168755 | H63: {=SUMPRODUCT('BEA Requirements Table'!$D52:$OR52,$D$8:$OR$8*($D$9:$OR$9=H$17))/SUMIFS($D$8:$OR$8,$D$9:$OR$9,H$17)} -> 0.00011073493 | I63: {=SUMPRODUCT('BEA Requirements Table'!$D52:$OR52,$D$8:$OR$8*($D$9:$OR$9=I$17))/SUMIFS($D$8:$OR$8,$D$9:$OR$9,I$17)} -> 9.9025621e-05 | J63: {=SUMPRODUCT('BEA Requirements Table'!$D52:$OR52,$D$8:$OR$8*($D$9:$OR$9=J$17))/SUMIFS($D$8:$OR$8,$D$9:$OR$9,J$17)} -> 6.8119279e-05 | K63: {=SUMPRODUCT('BEA Requirements Table'!$D52:$OR52,$D$8:$OR$8*($D$9:$OR$9=K$17))/SUMIFS($D$8:$OR$8,$D$9:$OR$9,K$17)} -> 8.3446747e-05 | ... AS63: {=SUMPRODUCT('BEA Requirements Table'!$D52:$OR52,$D$8:$OR$8*($D$9:$OR$9=AS$17))/SUMIFS($D$8:$OR$8,$D$9:$OR$9,AS$17)} -> 0
A64: 327400 | B64: 5979 | C64: ISIC 239 | D64: {=SUMPRODUCT('BEA Requirements Table'!$D53:$OR53,$D$8:$OR$8*($D$9:$OR$9=D$17))/SUMIFS($D$8:$OR$8,$D$9:$OR$9,D$17)} -> 0.00012632178 | E64: {=SUMPRODUCT('BEA Requirements Table'!$D53:$OR53,$D$8:$OR$8*($D$9:$OR$9=E$17))/SUMIFS($D$8:$OR$8,$D$9:$OR$9,E$17)} -> 0.0001982 | F64: {=SUMPRODUCT('BEA Requirements Table'!$D53:$OR53,$D$8:$OR$8*($D$9:$OR$9=F$17))/SUMIFS($D$8:$OR$8,$D$9:$OR$9,F$17)} -> 0.0001718 | G64: {=SUMPRODUCT('BEA Requirements Table'!$D53:$OR53,$D$8:$OR$8*($D$9:$OR$9=G$17))/SUMIFS($D$8:$OR$8,$D$9:$OR$9,G$17)} -> 0.0048256938 | H64: {=SUMPRODUCT('BEA Requirements Table'!$D53:$OR53,$D$8:$OR$8*($D$9:$OR$9=H$17))/SUMIFS($D$8:$OR$8,$D$9:$OR$9,H$17)} -> 0.0001715164 | I64: {=SUMPRODUCT('BEA Requirements Table'!$D53:$OR53,$D$8:$OR$8*($D$9:$OR$9=I$17))/SUMIFS($D$8:$OR$8,$D$9:$OR$9,I$17)} -> 0.00019240351 | J64: {=SUMPRODUCT('BEA Requirements Table'!$D53:$OR53,$D$8:$OR$8*($D$9:$OR$9=J$17))/SUMIFS($D$8:$OR$8,$D$9:$OR$9,J$17)} -> 0.00015848175 | K64: {=SUMPRODUCT('BEA Requirements Table'!$D53:$OR53,$D$8:$OR$8*($D$9:$OR$9=K$17))/SUMIFS($D$8:$OR$8,$D$9:$OR$9,K$17)} -> 0.00099309325 | ... AS64: {=SUMPRODUCT('BEA Requirements Table'!$D53:$OR53,$D$8:$OR$8*($D$9:$OR$9=AS$17))/SUMIFS($D$8:$OR$8,$D$9:$OR$9,AS$17)} -> 0
A65: 327910 | B65: 5287 | C65: ISIC 239 | D65: {=SUMPRODUCT('BEA Requirements Table'!$D54:$OR54,$D$8:$OR$8*($D$9:$OR$9=D$17))/SUMIFS($D$8:$OR$8,$D$9:$OR$9,D$17)} -> 7.341069e-05 | E65: {=SUMPRODUCT('BEA Requirements Table'!$D54:$OR54,$D$8:$OR$8*($D$9:$OR$9=E$17))/SUMIFS($D$8:$OR$8,$D$9:$OR$9,E$17)} -> 0.0001585 | F65: {=SUMPRODUCT('BEA Requirements Table'!$D54:$OR54,$D$8:$OR$8*($D$9:$OR$9=F$17))/SUMIFS($D$8:$OR$8,$D$9:$OR$9,F$17)} -> 0.0001703 | G65: {=SUMPRODUCT('BEA Requirements Table'!$D54:$OR54,$D$8:$OR$8*($D$9:$OR$9=G$17))/SUMIFS($D$8:$OR$8,$D$9:$OR$9,G$17)} -> 0.00015682754 | H65: {=SUMPRODUCT('BEA Requirements Table'!$D54:$OR54,$D$8:$OR$8*($D$9:$OR$9=H$17))/SUMIFS($D$8:$OR$8,$D$9:$OR$9,H$17)} -> 0.00013511593 | I65: {=SUMPRODUCT('BEA Requirements Table'!$D54:$OR54,$D$8:$OR$8*($D$9:$OR$9=I$17))/SUMIFS($D$8:$OR$8,$D$9:$OR$9,I$17)} -> 0.00011257114 | J65: {=SUMPRODUCT('BEA Requirements Table'!$D54:$OR54,$D$8:$OR$8*($D$9:$OR$9=J$17))/SUMIFS($D$8:$OR$8,$D$9:$OR$9,J$17)} -> 0.0003845888 | K65: {=SUMPRODUCT('BEA Requirements Table'!$D54:$OR54,$D$8:$OR$8*($D$9:$OR$9=K$17))/SUMIFS($D$8:$OR$8,$D$9:$OR$9,K$17)} -> 0.00076872552 | ... AS65: {=SUMPRODUCT('BEA Requirements Table'!$D54:$OR54,$D$8:$OR$8*($D$9:$OR$9=AS$17))/SUMIFS($D$8:$OR$8,$D$9:$OR$9,AS$17)} -> 0
A66: 327991 | B66: 3657 | C66: ISIC 239 | D66: {=SUMPRODUCT('BEA Requirements Table'!$D55:$OR55,$D$8:$OR$8*($D$9:$OR$9=D$17))/SUMIFS($D$8:$OR$8,$D$9:$OR$9,D$17)} -> 2.0246289e-05 | E66: {=SUMPRODUCT('BEA Requirements Table'!$D55:$OR55,$D$8:$OR$8*($D$9:$OR$9=E$17))/SUMIFS($D$8:$OR$8,$D$9:$OR$9,E$17)} -> 6.4e-05 | F66: {=SUMPRODUCT('BEA Requirements Table'!$D55:$OR55,$D$8:$OR$8*($D$9:$OR$9=F$17))/SUMIFS($D$8:$OR$8,$D$9:$OR$9,F$17)} -> 8.1e-06 | G66: {=SUMPRODUCT('BEA Requirements Table'!$D55:$OR55,$D$8:$OR$8*($D$9:$OR$9=G$17))/SUMIFS($D$8:$OR$8,$D$9:$OR$9,G$17)} -> 6.2103421e-05 | H66: {=SUMPRODUCT('BEA Requirements Table'!$D55:$OR55,$D$8:$OR$8*($D$9:$OR$9=H$17))/SUMIFS($D$8:$OR$8,$D$9:$OR$9,H$17)} -> 1.3882228e-05 | I66: {=SUMPRODUCT('BEA Requirements Table'!$D55:$OR55,$D$8:$OR$8*($D$9:$OR$9=I$17))/SUMIFS($D$8:$OR$8,$D$9:$OR$9,I$17)} -> 1.4138438e-05 | J66: {=SUMPRODUCT('BEA Requirements Table'!$D55:$OR55,$D$8:$OR$8*($D$9:$OR$9=J$17))/SUMIFS($D$8:$OR$8,$D$9:$OR$9,J$17)} -> 8.7002358e-06 | K66: {=SUMPRODUCT('BEA Requirements Table'!$D55:$OR55,$D$8:$OR$8*($D$9:$OR$9=K$17))/SUMIFS($D$8:$OR$8,$D$9:$OR$9,K$17)} -> 1.9749536e-05 | ... AS66: {=SUMPRODUCT('BEA Requirements Table'!$D55:$OR55,$D$8:$OR$8*($D$9:$OR$9=AS$17))/SUMIFS($D$8:$OR$8,$D$9:$OR$9,AS$17)} -> 0
A67: 327992 | B67: 3548 | C67: ISIC 239 | D67: {=SUMPRODUCT('BEA Requirements Table'!$D56:$OR56,$D$8:$OR$8*($D$9:$OR$9=D$17))/SUMIFS($D$8:$OR$8,$D$9:$OR$9,D$17)} -> 0.00018713413 | E67: {=SUMPRODUCT('BEA Requirements Table'!$D56:$OR56,$D$8:$OR$8*($D$9:$OR$9=E$17))/SUMIFS($D$8:$OR$8,$D$9:$OR$9,E$17)} -> 0.0030875 | F67: {=SUMPRODUCT('BEA Requirements Table'!$D56:$OR56,$D$8:$OR$8*($D$9:$OR$9=F$17))/SUMIFS($D$8:$OR$8,$D$9:$OR$9,F$17)} -> 0.0002553 | G67: {=SUMPRODUCT('BEA Requirements Table'!$D56:$OR56,$D$8:$OR$8*($D$9:$OR$9=G$17))/SUMIFS($D$8:$OR$8,$D$9:$OR$9,G$17)} -> 0.00067498252 | H67: {=SUMPRODUCT('BEA Requirements Table'!$D56:$OR56,$D$8:$OR$8*($D$9:$OR$9=H$17))/SUMIFS($D$8:$OR$8,$D$9:$OR$9,H$17)} -> 0.0014749385 | I67: {=SUMPRODUCT('BEA Requirements Table'!$D56:$OR56,$D$8:$OR$8*($D$9:$OR$9=I$17))/SUMIFS($D$8:$OR$8,$D$9:$OR$9,I$17)} -> 0.00015362369 | J67: {=SUMPRODUCT('BEA Requirements Table'!$D56:$OR56,$D$8:$OR$8*($D$9:$OR$9=J$17))/SUMIFS($D$8:$OR$8,$D$9:$OR$9,J$17)} -> 0.00012535674 | K67: {=SUMPRODUCT('BEA Requirements Table'!$D56:$OR56,$D$8:$OR$8*($D$9:$OR$9=K$17))/SUMIFS($D$8:$OR$8,$D$9:$OR$9,K$17)} -> 0.00019986044 | ... AS67: {=SUMPRODUCT('BEA Requirements Table'!$D56:$OR56,$D$8:$OR$8*($D$9:$OR$9=AS$17))/SUMIFS($D$8:$OR$8,$D$9:$OR$9,AS$17)} -> 0
A68: 327993 | B68: 4931 | C68: ISIC 239 | D68: {=SUMPRODUCT('BEA Requirements Table'!$D57:$OR57,$D$8:$OR$8*($D$9:$OR$9=D$17))/SUMIFS($D$8:$OR$8,$D$9:$OR$9,D$17)} -> 4.1382664e-05 | E68: {=SUMPRODUCT('BEA Requirements Table'!$D57:$OR57,$D$8:$OR$8*($D$9:$OR$9=E$17))/SUMIFS($D$8:$OR$8,$D$9:$OR$9,E$17)} -> 4.89e-05 | F68: {=SUMPRODUCT('BEA Requirements Table'!$D57:$OR57,$D$8:$OR$8*($D$9:$OR$9=F$17))/SUMIFS($D$8:$OR$8,$D$9:$OR$9,F$17)} -> 3.32e-05 | G68: {=SUMPRODUCT('BEA Requirements Table'!$D57:$OR57,$D$8:$OR$8*($D$9:$OR$9=G$17))/SUMIFS($D$8:$OR$8,$D$9:$OR$9,G$17)} -> 6.2167051e-05 | H68: {=SUMPRODUCT('BEA Requirements Table'!$D57:$OR57,$D$8:$OR$8*($D$9:$OR$9=H$17))/SUMIFS($D$8:$OR$8,$D$9:$OR$9,H$17)} -> 3.7340601e-05 | I68: {=SUMPRODUCT('BEA Requirements Table'!$D57:$OR57,$D$8:$OR$8*($D$9:$OR$9=I$17))/SUMIFS($D$8:$OR$8,$D$9:$OR$9,I$17)} -> 7.717451e-05 | J68: {=SUMPRODUCT('BEA Requirements Table'!$D57:$OR57,$D$8:$OR$8*($D$9:$OR$9=J$17))/SUMIFS($D$8:$OR$8,$D$9:$OR$9,J$17)} -> 4.2393366e-05 | K68: {=SUMPRODUCT('BEA Requirements Table'!$D57:$OR57,$D$8:$OR$8*($D$9:$OR$9=K$17))/SUMIFS($D$8:$OR$8,$D$9:$OR$9,K$17)} -> 0.0053584484 | ... AS68: {=SUMPRODUCT('BEA Requirements Table'!$D57:$OR57,$D$8:$OR$8*($D$9:$OR$9=AS$17))/SUMIFS($D$8:$OR$8,$D$9:$OR$9,AS$17)} -> 0
A69: 327999 | B69: 4129 | C69: ISIC 239 | D69: {=SUMPRODUCT('BEA Requirements Table'!$D58:$OR58,$D$8:$OR$8*($D$9:$OR$9=D$17))/SUMIFS($D$8:$OR$8,$D$9:$OR$9,D$17)} -> 7.9227894e-05 | E69: {=SUMPRODUCT('BEA Requirements Table'!$D58:$OR58,$D$8:$OR$8*($D$9:$OR$9=E$17))/SUMIFS($D$8:$OR$8,$D$9:$OR$9,E$17)} -> 0.0001799 | F69: {=SUMPRODUCT('BEA Requirements Table'!$D58:$OR58,$D$8:$OR$8*($D$9:$OR$9=F$17))/SUMIFS($D$8:$OR$8,$D$9:$OR$9,F$17)} -> 6.42e-05 | G69: {=SUMPRODUCT('BEA Requirements Table'!$D58:$OR58,$D$8:$OR$8*($D$9:$OR$9=G$17))/SUMIFS($D$8:$OR$8,$D$9:$OR$9,G$17)} -> 0.00013423071 | H69: {=SUMPRODUCT('BEA Requirements Table'!$D58:$OR58,$D$8:$OR$8*($D$9:$OR$9=H$17))/SUMIFS($D$8:$OR$8,$D$9:$OR$9,H$17)} -> 8.9201982e-05 | I69: {=SUMPRODUCT('BEA Requirements Table'!$D58:$OR58,$D$8:$OR$8*($D$9:$OR$9=I$17))/SUMIFS($D$8:$OR$8,$D$9:$OR$9,I$17)} -> 5.0374622e-05 | J69: {=SUMPRODUCT('BEA Requirements Table'!$D58:$OR58,$D$8:$OR$8*($D$9:$OR$9=J$17))/SUMIFS($D$8:$OR$8,$D$9:$OR$9,J$17)} -> 2.7814864e-05 | K69: {=SUMPRODUCT('BEA Requirements Table'!$D58:$OR58,$D$8:$OR$8*($D$9:$OR$9=K$17))/SUMIFS($D$8:$OR$8,$D$9:$OR$9,K$17)} -> 4.6648406e-05 | ... AS69: {=SUMPRODUCT('BEA Requirements Table'!$D58:$OR58,$D$8:$OR$8*($D$9:$OR$9=AS$17))/SUMIFS($D$8:$OR$8,$D$9:$OR$9,AS$17)} -> 0
... A73: 331313 | B73: 6506 | C73: ISIC 242 | D73: {=SUMPRODUCT('BEA Requirements Table'!$D62:$OR62,$D$8:$OR$8*($D$9:$OR$9=D$17))/SUMIFS($D$8:$OR$8,$D$9:$OR$9,D$17)} -> 8.9827627e-05 | E73: {=SUMPRODUCT('BEA Requirements Table'!$D62:$OR62,$D$8:$OR$8*($D$9:$OR$9=E$17))/SUMIFS($D$8:$OR$8,$D$9:$OR$9,E$17)} -> 0.000145 | F73: {=SUMPRODUCT('BEA Requirements Table'!$D62:$OR62,$D$8:$OR$8*($D$9:$OR$9=F$17))/SUMIFS($D$8:$OR$8,$D$9:$OR$9,F$17)} -> 0.0001394 | G73: {=SUMPRODUCT('BEA Requirements Table'!$D62:$OR62,$D$8:$OR$8*($D$9:$OR$9=G$17))/SUMIFS($D$8:$OR$8,$D$9:$OR$9,G$17)} -> 0.00020691591 | H73: {=SUMPRODUCT('BEA Requirements Table'!$D62:$OR62,$D$8:$OR$8*($D$9:$OR$9=H$17))/SUMIFS($D$8:$OR$8,$D$9:$OR$9,H$17)} -> 0.00013705195 | I73: {=SUMPRODUCT('BEA Requirements Table'!$D62:$OR62,$D$8:$OR$8*($D$9:$OR$9=I$17))/SUMIFS($D$8:$OR$8,$D$9:$OR$9,I$17)} -> 0.0015441708 | J73: {=SUMPRODUCT('BEA Requirements Table'!$D62:$OR62,$D$8:$OR$8*($D$9:$OR$9=J$17))/SUMIFS($D$8:$OR$8,$D$9:$OR$9,J$17)} -> 0.00012454663 | K73: {=SUMPRODUCT('BEA Requirements Table'!$D62:$OR62,$D$8:$OR$8*($D$9:$OR$9=K$17))/SUMIFS($D$8:$OR$8,$D$9:$OR$9,K$17)} -> 0.00052835364 | ... AS73: {=SUMPRODUCT('BEA Requirements Table'!$D62:$OR62,$D$8:$OR$8*($D$9:$OR$9=AS$17))/SUMIFS($D$8:$OR$8,$D$9:$OR$9,AS$17)} -> 0
A74: 33131B | B74: 25348 | C74: ISIC 242 | D74: {=SUMPRODUCT('BEA Requirements Table'!$D63:$OR63,$D$8:$OR$8*($D$9:$OR$9=D$17))/SUMIFS($D$8:$OR$8,$D$9:$OR$9,D$17)} -> 0.00027885814 | E74: {=SUMPRODUCT('BEA Requirements Table'!$D63:$OR63,$D$8:$OR$8*($D$9:$OR$9=E$17))/SUMIFS($D$8:$OR$8,$D$9:$OR$9,E$17)} -> 0.0004097 | F74: {=SUMPRODUCT('BEA Requirements Table'!$D63:$OR63,$D$8:$OR$8*($D$9:$OR$9=F$17))/SUMIFS($D$8:$OR$8,$D$9:$OR$9,F$17)} -> 0.0003475 | G74: {=SUMPRODUCT('BEA Requirements Table'!$D63:$OR63,$D$8:$OR$8*($D$9:$OR$9=G$17))/SUMIFS($D$8:$OR$8,$D$9:$OR$9,G$17)} -> 0.0005436609 | H74: {=SUMPRODUCT('BEA Requirements Table'!$D63:$OR63,$D$8:$OR$8*($D$9:$OR$9=H$17))/SUMIFS($D$8:$OR$8,$D$9:$OR$9,H$17)} -> 0.00048946855 | I74: {=SUMPRODUCT('BEA Requirements Table'!$D63:$OR63,$D$8:$OR$8*($D$9:$OR$9=I$17))/SUMIFS($D$8:$OR$8,$D$9:$OR$9,I$17)} -> 0.0092559288 | J74: {=SUMPRODUCT('BEA Requirements Table'!$D63:$OR63,$D$8:$OR$8*($D$9:$OR$9=J$17))/SUMIFS($D$8:$OR$8,$D$9:$OR$9,J$17)} -> 0.00041335677 | K74: {=SUMPRODUCT('BEA Requirements Table'!$D63:$OR63,$D$8:$OR$8*($D$9:$OR$9=K$17))/SUMIFS($D$8:$OR$8,$D$9:$OR$9,K$17)} -> 0.0014433761 | ... AS74: {=SUMPRODUCT('BEA Requirements Table'!$D63:$OR63,$D$8:$OR$8*($D$9:$OR$9=AS$17))/SUMIFS($D$8:$OR$8,$D$9:$OR$9,AS$17)} -> 0
A75: 331410 | B75: 14821 | C75: ISIC 242 | D75: {=SUMPRODUCT('BEA Requirements Table'!$D64:$OR64,$D$8:$OR$8*($D$9:$OR$9=D$17))/SUMIFS($D$8:$OR$8,$D$9:$OR$9,D$17)} -> 0.00019738231 | E75: {=SUMPRODUCT('BEA Requirements Table'!$D64:$OR64,$D$8:$OR$8*($D$9:$OR$9=E$17))/SUMIFS($D$8:$OR$8,$D$9:$OR$9,E$17)} -> 0.0003526 | F75: {=SUMPRODUCT('BEA Requirements Table'!$D64:$OR64,$D$8:$OR$8*($D$9:$OR$9=F$17))/SUMIFS($D$8:$OR$8,$D$9:$OR$9,F$17)} -> 0.0004568 | G75: {=SUMPRODUCT('BEA Requirements Table'!$D64:$OR64,$D$8:$OR$8*($D$9:$OR$9=G$17))/SUMIFS($D$8:$OR$8,$D$9:$OR$9,G$17)} -> 0.00050593192 | H75: {=SUMPRODUCT('BEA Requirements Table'!$D64:$OR64,$D$8:$OR$8*($D$9:$OR$9=H$17))/SUMIFS($D$8:$OR$8,$D$9:$OR$9,H$17)} -> 0.00030479952 | I75: {=SUMPRODUCT('BEA Requirements Table'!$D64:$OR64,$D$8:$OR$8*($D$9:$OR$9=I$17))/SUMIFS($D$8:$OR$8,$D$9:$OR$9,I$17)} -> 0.00040275552 | J75: {=SUMPRODUCT('BEA Requirements Table'!$D64:$OR64,$D$8:$OR$8*($D$9:$OR$9=J$17))/SUMIFS($D$8:$OR$8,$D$9:$OR$9,J$17)} -> 0.00038946328 | K75: {=SUMPRODUCT('BEA Requirements Table'!$D64:$OR64,$D$8:$OR$8*($D$9:$OR$9=K$17))/SUMIFS($D$8:$OR$8,$D$9:$OR$9,K$17)} -> 0.00063310688 | ... AS75: {=SUMPRODUCT('BEA Requirements Table'!$D64:$OR64,$D$8:$OR$8*($D$9:$OR$9=AS$17))/SUMIFS($D$8:$OR$8,$D$9:$OR$9,AS$17)} -> 0
A76: 331420 | B76: 23342 | C76: ISIC 242 | D76: {=SUMPRODUCT('BEA Requirements Table'!$D65:$OR65,$D$8:$OR$8*($D$9:$OR$9=D$17))/SUMIFS($D$8:$OR$8,$D$9:$OR$9,D$17)} -> 0.00029142823 | E76: {=SUMPRODUCT('BEA Requirements Table'!$D65:$OR65,$D$8:$OR$8*($D$9:$OR$9=E$17))/SUMIFS($D$8:$OR$8,$D$9:$OR$9,E$17)} -> 0.0007006 | F76: {=SUMPRODUCT('BEA Requirements Table'!$D65:$OR65,$D$8:$OR$8*($D$9:$OR$9=F$17))/SUMIFS($D$8:$OR$8,$D$9:$OR$9,F$17)} -> 0.0007059 | G76: {=SUMPRODUCT('BEA Requirements Table'!$D65:$OR65,$D$8:$OR$8*($D$9:$OR$9=G$17))/SUMIFS($D$8:$OR$8,$D$9:$OR$9,G$17)} -> 0.00065425037 | H76: {=SUMPRODUCT('BEA Requirements Table'!$D65:$OR65,$D$8:$OR$8*($D$9:$OR$9=H$17))/SUMIFS($D$8:$OR$8,$D$9:$OR$9,H$17)} -> 0.00038499809 | I76: {=SUMPRODUCT('BEA Requirements Table'!$D65:$OR65,$D$8:$OR$8*($D$9:$OR$9=I$17))/SUMIFS($D$8:$OR$8,$D$9:$OR$9,I$17)} -> 0.00051992285 | J76: {=SUMPRODUCT('BEA Requirements Table'!$D65:$OR65,$D$8:$OR$8*($D$9:$OR$9=J$17))/SUMIFS($D$8:$OR$8,$D$9:$OR$9,J$17)} -> 0.00041693937 | K76: {=SUMPRODUCT('BEA Requirements Table'!$D65:$OR65,$D$8:$OR$8*($D$9:$OR$9=K$17))/SUMIFS($D$8:$OR$8,$D$9:$OR$9,K$17)} -> 0.00098638408 | ... AS76: {=SUMPRODUCT('BEA Requirements Table'!$D65:$OR65,$D$8:$OR$8*($D$9:$OR$9=AS$17))/SUMIFS($D$8:$OR$8,$D$9:$OR$9,AS$17)} -> 0
A77: 331490 | B77: 22780 | C77: ISIC 242 | D77: {=SUMPRODUCT('BEA Requirements Table'!$D66:$OR66,$D$8:$OR$8*($D$9:$OR$9=D$17))/SUMIFS($D$8:$OR$8,$D$9:$OR$9,D$17)} -> 0.00026351361 | E77: {=SUMPRODUCT('BEA Requirements Table'!$D66:$OR66,$D$8:$OR$8*($D$9:$OR$9=E$17))/SUMIFS($D$8:$OR$8,$D$9:$OR$9,E$17)} -> 0.0008194 | F77: {=SUMPRODUCT('BEA Requirements Table'!$D66:$OR66,$D$8:$OR$8*($D$9:$OR$9=F$17))/SUMIFS($D$8:$OR$8,$D$9:$OR$9,F$17)} -> 0.0007272 | G77: {=SUMPRODUCT('BEA Requirements Table'!$D66:$OR66,$D$8:$OR$8*($D$9:$OR$9=G$17))/SUMIFS($D$8:$OR$8,$D$9:$OR$9,G$17)} -> 0.00095668142 | H77: {=SUMPRODUCT('BEA Requirements Table'!$D66:$OR66,$D$8:$OR$8*($D$9:$OR$9=H$17))/SUMIFS($D$8:$OR$8,$D$9:$OR$9,H$17)} -> 0.00090814656 | I77: {=SUMPRODUCT('BEA Requirements Table'!$D66:$OR66,$D$8:$OR$8*($D$9:$OR$9=I$17))/SUMIFS($D$8:$OR$8,$D$9:$OR$9,I$17)} -> 0.00051786669 | J77: {=SUMPRODUCT('BEA Requirements Table'!$D66:$OR66,$D$8:$OR$8*($D$9:$OR$9=J$17))/SUMIFS($D$8:$OR$8,$D$9:$OR$9,J$17)} -> 0.00045204242 | K77: {=SUMPRODUCT('BEA Requirements Table'!$D66:$OR66,$D$8:$OR$8*($D$9:$OR$9=K$17))/SUMIFS($D$8:$OR$8,$D$9:$OR$9,K$17)} -> 0.00087053952 | ... AS77: {=SUMPRODUCT('BEA Requirements Table'!$D66:$OR66,$D$8:$OR$8*($D$9:$OR$9=AS$17))/SUMIFS($D$8:$OR$8,$D$9:$OR$9,AS$17)} -> 0
A78: 331510 | B78: 18876 | C78: ISIC 241 | D78: {=SUMPRODUCT('BEA Requirements Table'!$D67:$OR67,$D$8:$OR$8*($D$9:$OR$9=D$17))/SUMIFS($D$8:$OR$8,$D$9:$OR$9,D$17)} -> 0.00034180514 | E78: {=SUMPRODUCT('BEA Requirements Table'!$D67:$OR67,$D$8:$OR$8*($D$9:$OR$9=E$17))/SUMIFS($D$8:$OR$8,$D$9:$OR$9,E$17)} -> 0.0014307 | F78: {=SUMPRODUCT('BEA Requirements Table'!$D67:$OR67,$D$8:$OR$8*($D$9:$OR$9=F$17))/SUMIFS($D$8:$OR$8,$D$9:$OR$9,F$17)} -> 0.0006536 | G78: {=SUMPRODUCT('BEA Requirements Table'!$D67:$OR67,$D$8:$OR$8*($D$9:$OR$9=G$17))/SUMIFS($D$8:$OR$8,$D$9:$OR$9,G$17)} -> 0.0014390291 | H78: {=SUMPRODUCT('BEA Requirements Table'!$D67:$OR67,$D$8:$OR$8*($D$9:$OR$9=H$17))/SUMIFS($D$8:$OR$8,$D$9:$OR$9,H$17)} -> 0.00056194033 | I78: {=SUMPRODUCT('BEA Requirements Table'!$D67:$OR67,$D$8:$OR$8*($D$9:$OR$9=I$17))/SUMIFS($D$8:$OR$8,$D$9:$OR$9,I$17)} -> 0.0005030744 | J78: {=SUMPRODUCT('BEA Requirements Table'!$D67:$OR67,$D$8:$OR$8*($D$9:$OR$9=J$17))/SUMIFS($D$8:$OR$8,$D$9:$OR$9,J$17)} -> 0.00034089049 | K78: {=SUMPRODUCT('BEA Requirements Table'!$D67:$OR67,$D$8:$OR$8*($D$9:$OR$9=K$17))/SUMIFS($D$8:$OR$8,$D$9:$OR$9,K$17)} -> 0.00075789856 | ... AS78: {=SUMPRODUCT('BEA Requirements Table'!$D67:$OR67,$D$8:$OR$8*($D$9:$OR$9=AS$17))/SUMIFS($D$8:$OR$8,$D$9:$OR$9,AS$17)} -> 0
A79: 331520 | B79: 12812 | C79: ISIC 242 | D79: {=SUMPRODUCT('BEA Requirements Table'!$D68:$OR68,$D$8:$OR$8*($D$9:$OR$9=D$17))/SUMIFS($D$8:$OR$8,$D$9:$OR$9,D$17)} -> 0.00019742368 | E79: {=SUMPRODUCT('BEA Requirements Table'!$D68:$OR68,$D$8:$OR$8*($D$9:$OR$9=E$17))/SUMIFS($D$8:$OR$8,$D$9:$OR$9,E$17)} -> 0.0005536 | F79: {=SUMPRODUCT('BEA Requirements Table'!$D68:$OR68,$D$8:$OR$8*($D$9:$OR$9=F$17))/SUMIFS($D$8:$OR$8,$D$9:$OR$9,F$17)} -> 0.0003384 | G79: {=SUMPRODUCT('BEA Requirements Table'!$D68:$OR68,$D$8:$OR$8*($D$9:$OR$9=G$17))/SUMIFS($D$8:$OR$8,$D$9:$OR$9,G$17)} -> 0.0006308494 | H79: {=SUMPRODUCT('BEA Requirements Table'!$D68:$OR68,$D$8:$OR$8*($D$9:$OR$9=H$17))/SUMIFS($D$8:$OR$8,$D$9:$OR$9,H$17)} -> 0.00030980998 | I79: {=SUMPRODUCT('BEA Requirements Table'!$D68:$OR68,$D$8:$OR$8*($D$9:$OR$9=I$17))/SUMIFS($D$8:$OR$8,$D$9:$OR$9,I$17)} -> 0.00028881109 | J79: {=SUMPRODUCT('BEA Requirements Table'!$D68:$OR68,$D$8:$OR$8*($D$9:$OR$9=J$17))/SUMIFS($D$8:$OR$8,$D$9:$OR$9,J$17)} -> 0.000243495 | K79: {=SUMPRODUCT('BEA Requirements Table'!$D68:$OR68,$D$8:$OR$8*($D$9:$OR$9=K$17))/SUMIFS($D$8:$OR$8,$D$9:$OR$9,K$17)} -> 0.00057098562 | ... AS79: {=SUMPRODUCT('BEA Requirements Table'!$D68:$OR68,$D$8:$OR$8*($D$9:$OR$9=AS$17))/SUMIFS($D$8:$OR$8,$D$9:$OR$9,AS$17)} -> 0
A80: 332114 | B80: 8341 | C80: ISIC 25 | D80: {=SUMPRODUCT('BEA Requirements Table'!$D69:$OR69,$D$8:$OR$8*($D$9:$OR$9=D$17))/SUMIFS($D$8:$OR$8,$D$9:$OR$9,D$17)} -> 0.00011488652 | E80: {=SUMPRODUCT('BEA Requirements Table'!$D69:$OR69,$D$8:$OR$8*($D$9:$OR$9=E$17))/SUMIFS($D$8:$OR$8,$D$9:$OR$9,E$17)} -> 0.000469 | F80: {=SUMPRODUCT('BEA Requirements Table'!$D69:$OR69,$D$8:$OR$8*($D$9:$OR$9=F$17))/SUMIFS($D$8:$OR$8,$D$9:$OR$9,F$17)} -> 0.0002229 | G80: {=SUMPRODUCT('BEA Requirements Table'!$D69:$OR69,$D$8:$OR$8*($D$9:$OR$9=G$17))/SUMIFS($D$8:$OR$8,$D$9:$OR$9,G$17)} -> 0.00047196437 | H80: {=SUMPRODUCT('BEA Requirements Table'!$D69:$OR69,$D$8:$OR$8*($D$9:$OR$9=H$17))/SUMIFS($D$8:$OR$8,$D$9:$OR$9,H$17)} -> 0.00023374894 | I80: {=SUMPRODUCT('BEA Requirements Table'!$D69:$OR69,$D$8:$OR$8*($D$9:$OR$9=I$17))/SUMIFS($D$8:$OR$8,$D$9:$OR$9,I$17)} -> 0.00030637753 | J80: {=SUMPRODUCT('BEA Requirements Table'!$D69:$OR69,$D$8:$OR$8*($D$9:$OR$9=J$17))/SUMIFS($D$8:$OR$8,$D$9:$OR$9,J$17)} -> 0.00018272143 | K80: {=SUMPRODUCT('BEA Requirements Table'!$D69:$OR69,$D$8:$OR$8*($D$9:$OR$9=K$17))/SUMIFS($D$8:$OR$8,$D$9:$OR$9,K$17)} -> 0.00040075885 | ... AS80: {=SUMPRODUCT('BEA Requirements Table'!$D69:$OR69,$D$8:$OR$8*($D$9:$OR$9=AS$17))/SUMIFS($D$8:$OR$8,$D$9:$OR$9,AS$17)} -> 0
A81: 33211A | B81: 14316 | C81: ISIC 25 | D81: {=SUMPRODUCT('BEA Requirements Table'!$D70:$OR70,$D$8:$OR$8*($D$9:$OR$9=D$17))/SUMIFS($D$8:$OR$8,$D$9:$OR$9,D$17)} -> 0.00019524962 | E81: {=SUMPRODUCT('BEA Requirements Table'!$D70:$OR70,$D$8:$OR$8*($D$9:$OR$9=E$17))/SUMIFS($D$8:$OR$8,$D$9:$OR$9,E$17)} -> 0.000929 | F81: {=SUMPRODUCT('BEA Requirements Table'!$D70:$OR70,$D$8:$OR$8*($D$9:$OR$9=F$17))/SUMIFS($D$8:$OR$8,$D$9:$OR$9,F$17)} -> 0.000527 | G81: {=SUMPRODUCT('BEA Requirements Table'!$D70:$OR70,$D$8:$OR$8*($D$9:$OR$9=G$17))/SUMIFS($D$8:$OR$8,$D$9:$OR$9,G$17)} -> 0.0016211514 | H81: {=SUMPRODUCT('BEA Requirements Table'!$D70:$OR70,$D$8:$OR$8*($D$9:$OR$9=H$17))/SUMIFS($D$8:$OR$8,$D$9:$OR$9,H$17)} -> 0.00040397608 | I81: {=SUMPRODUCT('BEA Requirements Table'!$D70:$OR70,$D$8:$OR$8*($D$9:$OR$9=I$17))/SUMIFS($D$8:$OR$8,$D$9:$OR$9,I$17)} -> 0.00025930693 | J81: {=SUMPRODUCT('BEA Requirements Table'!$D70:$OR70,$D$8:$OR$8*($D$9:$OR$9=J$17))/SUMIFS($D$8:$OR$8,$D$9:$OR$9,J$17)} -> 0.0002891552 | K81: {=SUMPRODUCT('BEA Requirements Table'!$D70:$OR70,$D$8:$OR$8*($D$9:$OR$9=K$17))/SUMIFS($D$8:$OR$8,$D$9:$OR$9,K$17)} -> 0.00071209604 | ... AS81: {=SUMPRODUCT('BEA Requirements Table'!$D70:$OR70,$D$8:$OR$8*($D$9:$OR$9=AS$17))/SUMIFS($D$8:$OR$8,$D$9:$OR$9,AS$17)} -> 0
A82: 332119 | B82: 11904 | C82: ISIC 25 | D82: {=SUMPRODUCT('BEA Requirements Table'!$D71:$OR71,$D$8:$OR$8*($D$9:$OR$9=D$17))/SUMIFS($D$8:$OR$8,$D$9:$OR$9,D$17)} -> 0.00022073975 | E82: {=SUMPRODUCT('BEA Requirements Table'!$D71:$OR71,$D$8:$OR$8*($D$9:$OR$9=E$17))/SUMIFS($D$8:$OR$8,$D$9:$OR$9,E$17)} -> 0.0003179 | F82: {=SUMPRODUCT('BEA Requirements Table'!$D71:$OR71,$D$8:$OR$8*($D$9:$OR$9=F$17))/SUMIFS($D$8:$OR$8,$D$9:$OR$9,F$17)} -> 0.0002031 | G82: {=SUMPRODUCT('BEA Requirements Table'!$D71:$OR71,$D$8:$OR$8*($D$9:$OR$9=G$17))/SUMIFS($D$8:$OR$8,$D$9:$OR$9,G$17)} -> 0.00030634148 | H82: {=SUMPRODUCT('BEA Requirements Table'!$D71:$OR71,$D$8:$OR$8*($D$9:$OR$9=H$17))/SUMIFS($D$8:$OR$8,$D$9:$OR$9,H$17)} -> 0.00018067717 | I82: {=SUMPRODUCT('BEA Requirements Table'!$D71:$OR71,$D$8:$OR$8*($D$9:$OR$9=I$17))/SUMIFS($D$8:$OR$8,$D$9:$OR$9,I$17)} -> 0.00039568352 | J82: {=SUMPRODUCT('BEA Requirements Table'!$D71:$OR71,$D$8:$OR$8*($D$9:$OR$9=J$17))/SUMIFS($D$8:$OR$8,$D$9:$OR$9,J$17)} -> 0.00035522591 | K82: {=SUMPRODUCT('BEA Requirements Table'!$D71:$OR71,$D$8:$OR$8*($D$9:$OR$9=K$17))/SUMIFS($D$8:$OR$8,$D$9:$OR$9,K$17)} -> 0.00065423302 | ... AS82: {=SUMPRODUCT('BEA Requirements Table'!$D71:$OR71,$D$8:$OR$8*($D$9:$OR$9=AS$17))/SUMIFS($D$8:$OR$8,$D$9:$OR$9,AS$17)} -> 0
A83: 332200 | B83: 9611 | C83: ISIC 25 | D83: {=SUMPRODUCT('BEA Requirements Table'!$D72:$OR72,$D$8:$OR$8*($D$9:$OR$9=D$17))/SUMIFS($D$8:$OR$8,$D$9:$OR$9,D$17)} -> 0.00077385592 | E83: {=SUMPRODUCT('BEA Requirements Table'!$D72:$OR72,$D$8:$OR$8*($D$9:$OR$9=E$17))/SUMIFS($D$8:$OR$8,$D$9:$OR$9,E$17)} -> 0.0003076 | F83: {=SUMPRODUCT('BEA Requirements Table'!$D72:$OR72,$D$8:$OR$8*($D$9:$OR$9=F$17))/SUMIFS($D$8:$OR$8,$D$9:$OR$9,F$17)} -> 0.0009812 | G83: {=SUMPRODUCT('BEA Requirements Table'!$D72:$OR72,$D$8:$OR$8*($D$9:$OR$9=G$17))/SUMIFS($D$8:$OR$8,$D$9:$OR$9,G$17)} -> 0.00038792026 | H83: {=SUMPRODUCT('BEA Requirements Table'!$D72:$OR72,$D$8:$OR$8*($D$9:$OR$9=H$17))/SUMIFS($D$8:$OR$8,$D$9:$OR$9,H$17)} -> 0.0010655413 | I83: {=SUMPRODUCT('BEA Requirements Table'!$D72:$OR72,$D$8:$OR$8*($D$9:$OR$9=I$17))/SUMIFS($D$8:$OR$8,$D$9:$OR$9,I$17)} -> 0.00050080121 | J83: {=SUMPRODUCT('BEA Requirements Table'!$D72:$OR72,$D$8:$OR$8*($D$9:$OR$9=J$17))/SUMIFS($D$8:$OR$8,$D$9:$OR$9,J$17)} -> 0.00012973156 | K83: {=SUMPRODUCT('BEA Requirements Table'!$D72:$OR72,$D$8:$OR$8*($D$9:$OR$9=K$17))/SUMIFS($D$8:$OR$8,$D$9:$OR$9,K$17)} -> 0.00026165329 | ... AS83: {=SUMPRODUCT('BEA Requirements Table'!$D72:$OR72,$D$8:$OR$8*($D$9:$OR$9=AS$17))/SUMIFS($D$8:$OR$8,$D$9:$OR$9,AS$17)} -> 0
A84: 332310 | B84: 40635 | C84: ISIC 25 | D84: {=SUMPRODUCT('BEA Requirements Table'!$D73:$OR73,$D$8:$OR$8*($D$9:$OR$9=D$17))/SUMIFS($D$8:$OR$8,$D$9:$OR$9,D$17)} -> 0.00078926119 | E84: {=SUMPRODUCT('BEA Requirements Table'!$D73:$OR73,$D$8:$OR$8*($D$9:$OR$9=E$17))/SUMIFS($D$8:$OR$8,$D$9:$OR$9,E$17)} -> 0.0011052 | F84: {=SUMPRODUCT('BEA Requirements Table'!$D73:$OR73,$D$8:$OR$8*($D$9:$OR$9=F$17))/SUMIFS($D$8:$OR$8,$D$9:$OR$9,F$17)} -> 0.0040737 | G84: {=SUMPRODUCT('BEA Requirements Table'!$D73:$OR73,$D$8:$OR$8*($D$9:$OR$9=G$17))/SUMIFS($D$8:$OR$8,$D$9:$OR$9,G$17)} -> 0.0019611037 | H84: {=SUMPRODUCT('BEA Requirements Table'!$D73:$OR73,$D$8:$OR$8*($D$9:$OR$9=H$17))/SUMIFS($D$8:$OR$8,$D$9:$OR$9,H$17)} -> 0.0012981467 | I84: {=SUMPRODUCT('BEA Requirements Table'!$D73:$OR73,$D$8:$OR$8*($D$9:$OR$9=I$17))/SUMIFS($D$8:$OR$8,$D$9:$OR$9,I$17)} -> 0.00079101123 | J84: {=SUMPRODUCT('BEA Requirements Table'!$D73:$OR73,$D$8:$OR$8*($D$9:$OR$9=J$17))/SUMIFS($D$8:$OR$8,$D$9:$OR$9,J$17)} -> 0.00075785197 | K84: {=SUMPRODUCT('BEA Requirements Table'!$D73:$OR73,$D$8:$OR$8*($D$9:$OR$9=K$17))/SUMIFS($D$8:$OR$8,$D$9:$OR$9,K$17)} -> 0.0038941776 | ... AS84: {=SUMPRODUCT('BEA Requirements Table'!$D73:$OR73,$D$8:$OR$8*($D$9:$OR$9=AS$17))/SUMIFS($D$8:$OR$8,$D$9:$OR$9,AS$17)} -> 0
A85: 332320 | B85: 36571 | C85: ISIC 25 | D85: {=SUMPRODUCT('BEA Requirements Table'!$D74:$OR74,$D$8:$OR$8*($D$9:$OR$9=D$17))/SUMIFS($D$8:$OR$8,$D$9:$OR$9,D$17)} -> 0.00061677396 | E85: {=SUMPRODUCT('BEA Requirements Table'!$D74:$OR74,$D$8:$OR$8*($D$9:$OR$9=E$17))/SUMIFS($D$8:$OR$8,$D$9:$OR$9,E$17)} -> 0.0009747 | F85: {=SUMPRODUCT('BEA Requirements Table'!$D74:$OR74,$D$8:$OR$8*($D$9:$OR$9=F$17))/SUMIFS($D$8:$OR$8,$D$9:$OR$9,F$17)} -> 0.0007925 | G85: {=SUMPRODUCT('BEA Requirements Table'!$D74:$OR74,$D$8:$OR$8*($D$9:$OR$9=G$17))/SUMIFS($D$8:$OR$8,$D$9:$OR$9,G$17)} -> 0.0014320673 | H85: {=SUMPRODUCT('BEA Requirements Table'!$D74:$OR74,$D$8:$OR$8*($D$9:$OR$9=H$17))/SUMIFS($D$8:$OR$8,$D$9:$OR$9,H$17)} -> 0.0051682463 | I85: {=SUMPRODUCT('BEA Requirements Table'!$D74:$OR74,$D$8:$OR$8*($D$9:$OR$9=I$17))/SUMIFS($D$8:$OR$8,$D$9:$OR$9,I$17)} -> 0.00073577562 | J85: {=SUMPRODUCT('BEA Requirements Table'!$D74:$OR74,$D$8:$OR$8*($D$9:$OR$9=J$17))/SUMIFS($D$8:$OR$8,$D$9:$OR$9,J$17)} -> 0.00059082848 | K85: {=SUMPRODUCT('BEA Requirements Table'!$D74:$OR74,$D$8:$OR$8*($D$9:$OR$9=K$17))/SUMIFS($D$8:$OR$8,$D$9:$OR$9,K$17)} -> 0.0069834249 | ... AS85: {=SUMPRODUCT('BEA Requirements Table'!$D74:$OR74,$D$8:$OR$8*($D$9:$OR$9=AS$17))/SUMIFS($D$8:$OR$8,$D$9:$OR$9,AS$17)} -> 0
A86: 332410 | B86: 7030 | C86: ISIC 25 | D86: {=SUMPRODUCT('BEA Requirements Table'!$D75:$OR75,$D$8:$OR$8*($D$9:$OR$9=D$17))/SUMIFS($D$8:$OR$8,$D$9:$OR$9,D$17)} -> 8.6647848e-05 | E86: {=SUMPRODUCT('BEA Requirements Table'!$D75:$OR75,$D$8:$OR$8*($D$9:$OR$9=E$17))/SUMIFS($D$8:$OR$8,$D$9:$OR$9,E$17)} -> 6.88e-05 | F86: {=SUMPRODUCT('BEA Requirements Table'!$D75:$OR75,$D$8:$OR$8*($D$9:$OR$9=F$17))/SUMIFS($D$8:$OR$8,$D$9:$OR$9,F$17)} -> 5.32e-05 | G86: {=SUMPRODUCT('BEA Requirements Table'!$D75:$OR75,$D$8:$OR$8*($D$9:$OR$9=G$17))/SUMIFS($D$8:$OR$8,$D$9:$OR$9,G$17)} -> 8.7620402e-05 | H86: {=SUMPRODUCT('BEA Requirements Table'!$D75:$OR75,$D$8:$OR$8*($D$9:$OR$9=H$17))/SUMIFS($D$8:$OR$8,$D$9:$OR$9,H$17)} -> 5.2188448e-05 | I86: {=SUMPRODUCT('BEA Requirements Table'!$D75:$OR75,$D$8:$OR$8*($D$9:$OR$9=I$17))/SUMIFS($D$8:$OR$8,$D$9:$OR$9,I$17)} -> 0.00011627747 | J86: {=SUMPRODUCT('BEA Requirements Table'!$D75:$OR75,$D$8:$OR$8*($D$9:$OR$9=J$17))/SUMIFS($D$8:$OR$8,$D$9:$OR$9,J$17)} -> 0.0001329737 | K86: {=SUMPRODUCT('BEA Requirements Table'!$D75:$OR75,$D$8:$OR$8*($D$9:$OR$9=K$17))/SUMIFS($D$8:$OR$8,$D$9:$OR$9,K$17)} -> 0.0001137503 | ... AS86: {=SUMPRODUCT('BEA Requirements Table'!$D75:$OR75,$D$8:$OR$8*($D$9:$OR$9=AS$17))/SUMIFS($D$8:$OR$8,$D$9:$OR$9,AS$17)} -> 0
A87: 332420 | B87: 9455 | C87: ISIC 25 | D87: {=SUMPRODUCT('BEA Requirements Table'!$D76:$OR76,$D$8:$OR$8*($D$9:$OR$9=D$17))/SUMIFS($D$8:$OR$8,$D$9:$OR$9,D$17)} -> 0.00015712401 | E87: {=SUMPRODUCT('BEA Requirements Table'!$D76:$OR76,$D$8:$OR$8*($D$9:$OR$9=E$17))/SUMIFS($D$8:$OR$8,$D$9:$OR$9,E$17)} -> 0.0001078 | F87: {=SUMPRODUCT('BEA Requirements Table'!$D76:$OR76,$D$8:$OR$8*($D$9:$OR$9=F$17))/SUMIFS($D$8:$OR$8,$D$9:$OR$9,F$17)} -> 7.8e-05 | G87: {=SUMPRODUCT('BEA Requirements Table'!$D76:$OR76,$D$8:$OR$8*($D$9:$OR$9=G$17))/SUMIFS($D$8:$OR$8,$D$9:$OR$9,G$17)} -> 0.00013166911 | H87: {=SUMPRODUCT('BEA Requirements Table'!$D76:$OR76,$D$8:$OR$8*($D$9:$OR$9=H$17))/SUMIFS($D$8:$OR$8,$D$9:$OR$9,H$17)} -> 9.2754955e-05 | I87: {=SUMPRODUCT('BEA Requirements Table'!$D76:$OR76,$D$8:$OR$8*($D$9:$OR$9=I$17))/SUMIFS($D$8:$OR$8,$D$9:$OR$9,I$17)} -> 0.00014294633 | J87: {=SUMPRODUCT('BEA Requirements Table'!$D76:$OR76,$D$8:$OR$8*($D$9:$OR$9=J$17))/SUMIFS($D$8:$OR$8,$D$9:$OR$9,J$17)} -> 0.00013971329 | K87: {=SUMPRODUCT('BEA Requirements Table'!$D76:$OR76,$D$8:$OR$8*($D$9:$OR$9=K$17))/SUMIFS($D$8:$OR$8,$D$9:$OR$9,K$17)} -> 0.00015339752 | ... AS87: {=SUMPRODUCT('BEA Requirements Table'!$D76:$OR76,$D$8:$OR$8*($D$9:$OR$9=AS$17))/SUMIFS($D$8:$OR$8,$D$9:$OR$9,AS$17)} -> 0
A88: 332430 | B88: 18845 | C88: ISIC 25 | D88: {=SUMPRODUCT('BEA Requirements Table'!$D77:$OR77,$D$8:$OR$8*($D$9:$OR$9=D$17))/SUMIFS($D$8:$OR$8,$D$9:$OR$9,D$17)} -> 0.00052177568 | E88: {=SUMPRODUCT('BEA Requirements Table'!$D77:$OR77,$D$8:$OR$8*($D$9:$OR$9=E$17))/SUMIFS($D$8:$OR$8,$D$9:$OR$9,E$17)} -> 0.0003183 | F88: {=SUMPRODUCT('BEA Requirements Table'!$D77:$OR77,$D$8:$OR$8*($D$9:$OR$9=F$17))/SUMIFS($D$8:$OR$8,$D$9:$OR$9,F$17)} -> 0.000252 | G88: {=SUMPRODUCT('BEA Requirements Table'!$D77:$OR77,$D$8:$OR$8*($D$9:$OR$9=G$17))/SUMIFS($D$8:$OR$8,$D$9:$OR$9,G$17)} -> 0.00037242226 | H88: {=SUMPRODUCT('BEA Requirements Table'!$D77:$OR77,$D$8:$OR$8*($D$9:$OR$9=H$17))/SUMIFS($D$8:$OR$8,$D$9:$OR$9,H$17)} -> 0.00021764703 | I88: {=SUMPRODUCT('BEA Requirements Table'!$D77:$OR77,$D$8:$OR$8*($D$9:$OR$9=I$17))/SUMIFS($D$8:$OR$8,$D$9:$OR$9,I$17)} -> 0.013708508 | J88: {=SUMPRODUCT('BEA Requirements Table'!$D77:$OR77,$D$8:$OR$8*($D$9:$OR$9=J$17))/SUMIFS($D$8:$OR$8,$D$9:$OR$9,J$17)} -> 0.0003465756 | K88: {=SUMPRODUCT('BEA Requirements Table'!$D77:$OR77,$D$8:$OR$8*($D$9:$OR$9=K$17))/SUMIFS($D$8:$OR$8,$D$9:$OR$9,K$17)} -> 0.00047149234 | ... AS88: {=SUMPRODUCT('BEA Requirements Table'!$D77:$OR77,$D$8:$OR$8*($D$9:$OR$9=AS$17))/SUMIFS($D$8:$OR$8,$D$9:$OR$9,AS$17)} -> 0
A89: 332500 | B89: 7282 | C89: ISIC 25 | D89: {=SUMPRODUCT('BEA Requirements Table'!$D78:$OR78,$D$8:$OR$8*($D$9:$OR$9=D$17))/SUMIFS($D$8:$OR$8,$D$9:$OR$9,D$17)} -> 0.00010876133 | E89: {=SUMPRODUCT('BEA Requirements Table'!$D78:$OR78,$D$8:$OR$8*($D$9:$OR$9=E$17))/SUMIFS($D$8:$OR$8,$D$9:$OR$9,E$17)} -> 0.0004201 | F89: {=SUMPRODUCT('BEA Requirements Table'!$D78:$OR78,$D$8:$OR$8*($D$9:$OR$9=F$17))/SUMIFS($D$8:$OR$8,$D$9:$OR$9,F$17)} -> 9.38e-05 | G89: {=SUMPRODUCT('BEA Requirements Table'!$D78:$OR78,$D$8:$OR$8*($D$9:$OR$9=G$17))/SUMIFS($D$8:$OR$8,$D$9:$OR$9,G$17)} -> 0.00019574742 | H89: {=SUMPRODUCT('BEA Requirements Table'!$D78:$OR78,$D$8:$OR$8*($D$9:$OR$9=H$17))/SUMIFS($D$8:$OR$8,$D$9:$OR$9,H$17)} -> 0.00011601627 | I89: {=SUMPRODUCT('BEA Requirements Table'!$D78:$OR78,$D$8:$OR$8*($D$9:$OR$9=I$17))/SUMIFS($D$8:$OR$8,$D$9:$OR$9,I$17)} -> 0.00011339295 | J89: {=SUMPRODUCT('BEA Requirements Table'!$D78:$OR78,$D$8:$OR$8*($D$9:$OR$9=J$17))/SUMIFS($D$8:$OR$8,$D$9:$OR$9,J$17)} -> 0.00036370994 | K89: {=SUMPRODUCT('BEA Requirements Table'!$D78:$OR78,$D$8:$OR$8*($D$9:$OR$9=K$17))/SUMIFS($D$8:$OR$8,$D$9:$OR$9,K$17)} -> 0.0037496631 | ... AS89: {=SUMPRODUCT('BEA Requirements Table'!$D78:$OR78,$D$8:$OR$8*($D$9:$OR$9=AS$17))/SUMIFS($D$8:$OR$8,$D$9:$OR$9,AS$17)} -> 0
A90: 332600 | B90: 8441 | C90: ISIC 25 | D90: {=SUMPRODUCT('BEA Requirements Table'!$D79:$OR79,$D$8:$OR$8*($D$9:$OR$9=D$17))/SUMIFS($D$8:$OR$8,$D$9:$OR$9,D$17)} -> 0.0017025111 | E90: {=SUMPRODUCT('BEA Requirements Table'!$D79:$OR79,$D$8:$OR$8*($D$9:$OR$9=E$17))/SUMIFS($D$8:$OR$8,$D$9:$OR$9,E$17)} -> 0.0003411 | F90: {=SUMPRODUCT('BEA Requirements Table'!$D79:$OR79,$D$8:$OR$8*($D$9:$OR$9=F$17))/SUMIFS($D$8:$OR$8,$D$9:$OR$9,F$17)} -> 0.0024023 | G90: {=SUMPRODUCT('BEA Requirements Table'!$D79:$OR79,$D$8:$OR$8*($D$9:$OR$9=G$17))/SUMIFS($D$8:$OR$8,$D$9:$OR$9,G$17)} -> 0.00066078848 | H90: {=SUMPRODUCT('BEA Requirements Table'!$D79:$OR79,$D$8:$OR$8*($D$9:$OR$9=H$17))/SUMIFS($D$8:$OR$8,$D$9:$OR$9,H$17)} -> 0.00039739338 | I90: {=SUMPRODUCT('BEA Requirements Table'!$D79:$OR79,$D$8:$OR$8*($D$9:$OR$9=I$17))/SUMIFS($D$8:$OR$8,$D$9:$OR$9,I$17)} -> 0.00085569738 | J90: {=SUMPRODUCT('BEA Requirements Table'!$D79:$OR79,$D$8:$OR$8*($D$9:$OR$9=J$17))/SUMIFS($D$8:$OR$8,$D$9:$OR$9,J$17)} -> 0.0014104742 | K90: {=SUMPRODUCT('BEA Requirements Table'!$D79:$OR79,$D$8:$OR$8*($D$9:$OR$9=K$17))/SUMIFS($D$8:$OR$8,$D$9:$OR$9,K$17)} -> 0.00034319197 | ... AS90: {=SUMPRODUCT('BEA Requirements Table'!$D79:$OR79,$D$8:$OR$8*($D$9:$OR$9=AS$17))/SUMIFS($D$8:$OR$8,$D$9:$OR$9,AS$17)} -> 0
A91: 332710 | B91: 39891 | C91: ISIC 25 | D91: {=SUMPRODUCT('BEA Requirements Table'!$D80:$OR80,$D$8:$OR$8*($D$9:$OR$9=D$17))/SUMIFS($D$8:$OR$8,$D$9:$OR$9,D$17)} -> 0.0011548967 | E91: {=SUMPRODUCT('BEA Requirements Table'!$D80:$OR80,$D$8:$OR$8*($D$9:$OR$9=E$17))/SUMIFS($D$8:$OR$8,$D$9:$OR$9,E$17)} -> 0.0022939 | F91: {=SUMPRODUCT('BEA Requirements Table'!$D80:$OR80,$D$8:$OR$8*($D$9:$OR$9=F$17))/SUMIFS($D$8:$OR$8,$D$9:$OR$9,F$17)} -> 0.0011921 | G91: {=SUMPRODUCT('BEA Requirements Table'!$D80:$OR80,$D$8:$OR$8*($D$9:$OR$9=G$17))/SUMIFS($D$8:$OR$8,$D$9:$OR$9,G$17)} -> 0.0036253334 | H91: {=SUMPRODUCT('BEA Requirements Table'!$D80:$OR80,$D$8:$OR$8*($D$9:$OR$9=H$17))/SUMIFS($D$8:$OR$8,$D$9:$OR$9,H$17)} -> 0.0014874788 | I91: {=SUMPRODUCT('BEA Requirements Table'!$D80:$OR80,$D$8:$OR$8*($D$9:$OR$9=I$17))/SUMIFS($D$8:$OR$8,$D$9:$OR$9,I$17)} -> 0.0032402627 | J91: {=SUMPRODUCT('BEA Requirements Table'!$D80:$OR80,$D$8:$OR$8*($D$9:$OR$9=J$17))/SUMIFS($D$8:$OR$8,$D$9:$OR$9,J$17)} -> 0.0066462558 | K91: {=SUMPRODUCT('BEA Requirements Table'!$D80:$OR80,$D$8:$OR$8*($D$9:$OR$9=K$17))/SUMIFS($D$8:$OR$8,$D$9:$OR$9,K$17)} -> 0.0054710402 | ... AS91: {=SUMPRODUCT('BEA Requirements Table'!$D80:$OR80,$D$8:$OR$8*($D$9:$OR$9=AS$17))/SUMIFS($D$8:$OR$8,$D$9:$OR$9,AS$17)} -> 0
A92: 332720 | B92: 28005 | C92: ISIC 25 | D92: {=SUMPRODUCT('BEA Requirements Table'!$D81:$OR81,$D$8:$OR$8*($D$9:$OR$9=D$17))/SUMIFS($D$8:$OR$8,$D$9:$OR$9,D$17)} -> 0.00054191265 | E92: {=SUMPRODUCT('BEA Requirements Table'!$D81:$OR81,$D$8:$OR$8*($D$9:$OR$9=E$17))/SUMIFS($D$8:$OR$8,$D$9:$OR$9,E$17)} -> 0.0089521 | F92: {=SUMPRODUCT('BEA Requirements Table'!$D81:$OR81,$D$8:$OR$8*($D$9:$OR$9=F$17))/SUMIFS($D$8:$OR$8,$D$9:$OR$9,F$17)} -> 0.0009016 | G92: {=SUMPRODUCT('BEA Requirements Table'!$D81:$OR81,$D$8:$OR$8*($D$9:$OR$9=G$17))/SUMIFS($D$8:$OR$8,$D$9:$OR$9,G$17)} -> 0.0038860399 | H92: {=SUMPRODUCT('BEA Requirements Table'!$D81:$OR81,$D$8:$OR$8*($D$9:$OR$9=H$17))/SUMIFS($D$8:$OR$8,$D$9:$OR$9,H$17)} -> 0.0011529373 | I92: {=SUMPRODUCT('BEA Requirements Table'!$D81:$OR81,$D$8:$OR$8*($D$9:$OR$9=I$17))/SUMIFS($D$8:$OR$8,$D$9:$OR$9,I$17)} -> 0.0012714154 | J92: {=SUMPRODUCT('BEA Requirements Table'!$D81:$OR81,$D$8:$OR$8*($D$9:$OR$9=J$17))/SUMIFS($D$8:$OR$8,$D$9:$OR$9,J$17)} -> 0.0024691689 | K92: {=SUMPRODUCT('BEA Requirements Table'!$D81:$OR81,$D$8:$OR$8*($D$9:$OR$9=K$17))/SUMIFS($D$8:$OR$8,$D$9:$OR$9,K$17)} -> 0.0033935017 | ... AS92: {=SUMPRODUCT('BEA Requirements Table'!$D81:$OR81,$D$8:$OR$8*($D$9:$OR$9=AS$17))/SUMIFS($D$8:$OR$8,$D$9:$OR$9,AS$17)} -> 0
A93: 332800 | B93: 27234 | C93: ISIC 25 | D93: {=SUMPRODUCT('BEA Requirements Table'!$D82:$OR82,$D$8:$OR$8*($D$9:$OR$9=D$17))/SUMIFS($D$8:$OR$8,$D$9:$OR$9,D$17)} -> 0.00088015686 | E93: {=SUMPRODUCT('BEA Requirements Table'!$D82:$OR82,$D$8:$OR$8*($D$9:$OR$9=E$17))/SUMIFS($D$8:$OR$8,$D$9:$OR$9,E$17)} -> 0.0023558 | F93: {=SUMPRODUCT('BEA Requirements Table'!$D82:$OR82,$D$8:$OR$8*($D$9:$OR$9=F$17))/SUMIFS($D$8:$OR$8,$D$9:$OR$9,F$17)} -> 0.0011023 | G93: {=SUMPRODUCT('BEA Requirements Table'!$D82:$OR82,$D$8:$OR$8*($D$9:$OR$9=G$17))/SUMIFS($D$8:$OR$8,$D$9:$OR$9,G$17)} -> 0.0069096814 | H93: {=SUMPRODUCT('BEA Requirements Table'!$D82:$OR82,$D$8:$OR$8*($D$9:$OR$9=H$17))/SUMIFS($D$8:$OR$8,$D$9:$OR$9,H$17)} -> 0.0013705746 | I93: {=SUMPRODUCT('BEA Requirements Table'!$D82:$OR82,$D$8:$OR$8*($D$9:$OR$9=I$17))/SUMIFS($D$8:$OR$8,$D$9:$OR$9,I$17)} -> 0.0029371676 | J93: {=SUMPRODUCT('BEA Requirements Table'!$D82:$OR82,$D$8:$OR$8*($D$9:$OR$9=J$17))/SUMIFS($D$8:$OR$8,$D$9:$OR$9,J$17)} -> 0.0072107351 | K93: {=SUMPRODUCT('BEA Requirements Table'!$D82:$OR82,$D$8:$OR$8*($D$9:$OR$9=K$17))/SUMIFS($D$8:$OR$8,$D$9:$OR$9,K$17)} -> 0.006264757 | ... AS93: {=SUMPRODUCT('BEA Requirements Table'!$D82:$OR82,$D$8:$OR$8*($D$9:$OR$9=AS$17))/SUMIFS($D$8:$OR$8,$D$9:$OR$9,AS$17)} -> 0
A94: 332913 | B94: 3524 | C94: ISIC 25 | D94: {=SUMPRODUCT('BEA Requirements Table'!$D83:$OR83,$D$8:$OR$8*($D$9:$OR$9=D$17))/SUMIFS($D$8:$OR$8,$D$9:$OR$9,D$17)} -> 6.7772025e-05 | E94: {=SUMPRODUCT('BEA Requirements Table'!$D83:$OR83,$D$8:$OR$8*($D$9:$OR$9=E$17))/SUMIFS($D$8:$OR$8,$D$9:$OR$9,E$17)} -> 9.13e-05 | F94: {=SUMPRODUCT('BEA Requirements Table'!$D83:$OR83,$D$8:$OR$8*($D$9:$OR$9=F$17))/SUMIFS($D$8:$OR$8,$D$9:$OR$9,F$17)} -> 3.93e-05 | G94: {=SUMPRODUCT('BEA Requirements Table'!$D83:$OR83,$D$8:$OR$8*($D$9:$OR$9=G$17))/SUMIFS($D$8:$OR$8,$D$9:$OR$9,G$17)} -> 0.00012444686 | H94: {=SUMPRODUCT('BEA Requirements Table'!$D83:$OR83,$D$8:$OR$8*($D$9:$OR$9=H$17))/SUMIFS($D$8:$OR$8,$D$9:$OR$9,H$17)} -> 7.4435132e-05 | I94: {=SUMPRODUCT('BEA Requirements Table'!$D83:$OR83,$D$8:$OR$8*($D$9:$OR$9=I$17))/SUMIFS($D$8:$OR$8,$D$9:$OR$9,I$17)} -> 6.6150315e-05 | J94: {=SUMPRODUCT('BEA Requirements Table'!$D83:$OR83,$D$8:$OR$8*($D$9:$OR$9=J$17))/SUMIFS($D$8:$OR$8,$D$9:$OR$9,J$17)} -> 4.8334325e-05 | K94: {=SUMPRODUCT('BEA Requirements Table'!$D83:$OR83,$D$8:$OR$8*($D$9:$OR$9=K$17))/SUMIFS($D$8:$OR$8,$D$9:$OR$9,K$17)} -> 0.0003833148 | ... AS94: {=SUMPRODUCT('BEA Requirements Table'!$D83:$OR83,$D$8:$OR$8*($D$9:$OR$9=AS$17))/SUMIFS($D$8:$OR$8,$D$9:$OR$9,AS$17)} -> 0
A95: 33291A | B95: 28427 | C95: ISIC 25 | D95: {=SUMPRODUCT('BEA Requirements Table'!$D84:$OR84,$D$8:$OR$8*($D$9:$OR$9=D$17))/SUMIFS($D$8:$OR$8,$D$9:$OR$9,D$17)} -> 0.00038441135 | E95: {=SUMPRODUCT('BEA Requirements Table'!$D84:$OR84,$D$8:$OR$8*($D$9:$OR$9=E$17))/SUMIFS($D$8:$OR$8,$D$9:$OR$9,E$17)} -> 0.0006008 | F95: {=SUMPRODUCT('BEA Requirements Table'!$D84:$OR84,$D$8:$OR$8*($D$9:$OR$9=F$17))/SUMIFS($D$8:$OR$8,$D$9:$OR$9,F$17)} -> 0.0059475 | G95: {=SUMPRODUCT('BEA Requirements Table'!$D84:$OR84,$D$8:$OR$8*($D$9:$OR$9=G$17))/SUMIFS($D$8:$OR$8,$D$9:$OR$9,G$17)} -> 0.00092150837 | H95: {=SUMPRODUCT('BEA Requirements Table'!$D84:$OR84,$D$8:$OR$8*($D$9:$OR$9=H$17))/SUMIFS($D$8:$OR$8,$D$9:$OR$9,H$17)} -> 0.00084529017 | I95: {=SUMPRODUCT('BEA Requirements Table'!$D84:$OR84,$D$8:$OR$8*($D$9:$OR$9=I$17))/SUMIFS($D$8:$OR$8,$D$9:$OR$9,I$17)} -> 0.00057883549 | J95: {=SUMPRODUCT('BEA Requirements Table'!$D84:$OR84,$D$8:$OR$8*($D$9:$OR$9=J$17))/SUMIFS($D$8:$OR$8,$D$9:$OR$9,J$17)} -> 0.00042895088 | K95: {=SUMPRODUCT('BEA Requirements Table'!$D84:$OR84,$D$8:$OR$8*($D$9:$OR$9=K$17))/SUMIFS($D$8:$OR$8,$D$9:$OR$9,K$17)} -> 0.00066368538 | ... AS95: {=SUMPRODUCT('BEA Requirements Table'!$D84:$OR84,$D$8:$OR$8*($D$9:$OR$9=AS$17))/SUMIFS($D$8:$OR$8,$D$9:$OR$9,AS$17)} -> 0
A96: 332991 | B96: 7014 | C96: ISIC 25 | D96: {=SUMPRODUCT('BEA Requirements Table'!$D85:$OR85,$D$8:$OR$8*($D$9:$OR$9=D$17))/SUMIFS($D$8:$OR$8,$D$9:$OR$9,D$17)} -> 8.9550396e-05 | E96: {=SUMPRODUCT('BEA Requirements Table'!$D85:$OR85,$D$8:$OR$8*($D$9:$OR$9=E$17))/SUMIFS($D$8:$OR$8,$D$9:$OR$9,E$17)} -> 0.0001889 | F96: {=SUMPRODUCT('BEA Requirements Table'!$D85:$OR85,$D$8:$OR$8*($D$9:$OR$9=F$17))/SUMIFS($D$8:$OR$8,$D$9:$OR$9,F$17)} -> 0.000584 | G96: {=SUMPRODUCT('BEA Requirements Table'!$D85:$OR85,$D$8:$OR$8*($D$9:$OR$9=G$17))/SUMIFS($D$8:$OR$8,$D$9:$OR$9,G$17)} -> 0.00023587843 | H96: {=SUMPRODUCT('BEA Requirements Table'!$D85:$OR85,$D$8:$OR$8*($D$9:$OR$9=H$17))/SUMIFS($D$8:$OR$8,$D$9:$OR$9,H$17)} -> 0.0001340285 | I96: {=SUMPRODUCT('BEA Requirements Table'!$D85:$OR85,$D$8:$OR$8*($D$9:$OR$9=I$17))/SUMIFS($D$8:$OR$8,$D$9:$OR$9,I$17)} -> 0.00012008306 | J96: {=SUMPRODUCT('BEA Requirements Table'!$D85:$OR85,$D$8:$OR$8*($D$9:$OR$9=J$17))/SUMIFS($D$8:$OR$8,$D$9:$OR$9,J$17)} -> 9.4618913e-05 | K96: {=SUMPRODUCT('BEA Requirements Table'!$D85:$OR85,$D$8:$OR$8*($D$9:$OR$9=K$17))/SUMIFS($D$8:$OR$8,$D$9:$OR$9,K$17)} -> 0.00025765427 | ... AS96: {=SUMPRODUCT('BEA Requirements Table'!$D85:$OR85,$D$8:$OR$8*($D$9:$OR$9=AS$17))/SUMIFS($D$8:$OR$8,$D$9:$OR$9,AS$17)} -> 0
A97: 332996 | B97: 8201 | C97: ISIC 25 | D97: {=SUMPRODUCT('BEA Requirements Table'!$D86:$OR86,$D$8:$OR$8*($D$9:$OR$9=D$17))/SUMIFS($D$8:$OR$8,$D$9:$OR$9,D$17)} -> 0.00012073273 | E97: {=SUMPRODUCT('BEA Requirements Table'!$D86:$OR86,$D$8:$OR$8*($D$9:$OR$9=E$17))/SUMIFS($D$8:$OR$8,$D$9:$OR$9,E$17)} -> 0.0002111 | F97: {=SUMPRODUCT('BEA Requirements Table'!$D86:$OR86,$D$8:$OR$8*($D$9:$OR$9=F$17))/SUMIFS($D$8:$OR$8,$D$9:$OR$9,F$17)} -> 0.0003102 | G97: {=SUMPRODUCT('BEA Requirements Table'!$D86:$OR86,$D$8:$OR$8*($D$9:$OR$9=G$17))/SUMIFS($D$8:$OR$8,$D$9:$OR$9,G$17)} -> 0.00026365079 | H97: {=SUMPRODUCT('BEA Requirements Table'!$D86:$OR86,$D$8:$OR$8*($D$9:$OR$9=H$17))/SUMIFS($D$8:$OR$8,$D$9:$OR$9,H$17)} -> 0.00017567471 | I97: {=SUMPRODUCT('BEA Requirements Table'!$D86:$OR86,$D$8:$OR$8*($D$9:$OR$9=I$17))/SUMIFS($D$8:$OR$8,$D$9:$OR$9,I$17)} -> 0.0001130425 | J97: {=SUMPRODUCT('BEA Requirements Table'!$D86:$OR86,$D$8:$OR$8*($D$9:$OR$9=J$17))/SUMIFS($D$8:$OR$8,$D$9:$OR$9,J$17)} -> 9.2133027e-05 | K97: {=SUMPRODUCT('BEA Requirements Table'!$D86:$OR86,$D$8:$OR$8*($D$9:$OR$9=K$17))/SUMIFS($D$8:$OR$8,$D$9:$OR$9,K$17)} -> 0.00015675469 | ... AS97: {=SUMPRODUCT('BEA Requirements Table'!$D86:$OR86,$D$8:$OR$8*($D$9:$OR$9=AS$17))/SUMIFS($D$8:$OR$8,$D$9:$OR$9,AS$17)} -> 0
A98: 33299A | B98: 13951 | C98: ISIC 25 | D98: {=SUMPRODUCT('BEA Requirements Table'!$D87:$OR87,$D$8:$OR$8*($D$9:$OR$9=D$17))/SUMIFS($D$8:$OR$8,$D$9:$OR$9,D$17)} -> 1.9446169e-05 | E98: {=SUMPRODUCT('BEA Requirements Table'!$D87:$OR87,$D$8:$OR$8*($D$9:$OR$9=E$17))/SUMIFS($D$8:$OR$8,$D$9:$OR$9,E$17)} -> 4.08e-05 | F98: {=SUMPRODUCT('BEA Requirements Table'!$D87:$OR87,$D$8:$OR$8*($D$9:$OR$9=F$17))/SUMIFS($D$8:$OR$8,$D$9:$OR$9,F$17)} -> 4.54e-05 | G98: {=SUMPRODUCT('BEA Requirements Table'!$D87:$OR87,$D$8:$OR$8*($D$9:$OR$9=G$17))/SUMIFS($D$8:$OR$8,$D$9:$OR$9,G$17)} -> 5.1913586e-05 | H98: {=SUMPRODUCT('BEA Requirements Table'!$D87:$OR87,$D$8:$OR$8*($D$9:$OR$9=H$17))/SUMIFS($D$8:$OR$8,$D$9:$OR$9,H$17)} -> 2.8986466e-05 | I98: {=SUMPRODUCT('BEA Requirements Table'!$D87:$OR87,$D$8:$OR$8*($D$9:$OR$9=I$17))/SUMIFS($D$8:$OR$8,$D$9:$OR$9,I$17)} -> 2.4107176e-05 | J98: {=SUMPRODUCT('BEA Requirements Table'!$D87:$OR87,$D$8:$OR$8*($D$9:$OR$9=J$17))/SUMIFS($D$8:$OR$8,$D$9:$OR$9,J$17)} -> 2.5146366e-05 | K98: {=SUMPRODUCT('BEA Requirements Table'!$D87:$OR87,$D$8:$OR$8*($D$9:$OR$9=K$17))/SUMIFS($D$8:$OR$8,$D$9:$OR$9,K$17)} -> 3.3195125e-05 | ... AS98: {=SUMPRODUCT('BEA Requirements Table'!$D87:$OR87,$D$8:$OR$8*($D$9:$OR$9=AS$17))/SUMIFS($D$8:$OR$8,$D$9:$OR$9,AS$17)} -> 0
A99: 332999 | B99: 14572 | C99: ISIC 25 | D99: {=SUMPRODUCT('BEA Requirements Table'!$D88:$OR88,$D$8:$OR$8*($D$9:$OR$9=D$17))/SUMIFS($D$8:$OR$8,$D$9:$OR$9,D$17)} -> 0.00032284085 | E99: {=SUMPRODUCT('BEA Requirements Table'!$D88:$OR88,$D$8:$OR$8*($D$9:$OR$9=E$17))/SUMIFS($D$8:$OR$8,$D$9:$OR$9,E$17)} -> 0.0004072 | F99: {=SUMPRODUCT('BEA Requirements Table'!$D88:$OR88,$D$8:$OR$8*($D$9:$OR$9=F$17))/SUMIFS($D$8:$OR$8,$D$9:$OR$9,F$17)} -> 0.0002684 | G99: {=SUMPRODUCT('BEA Requirements Table'!$D88:$OR88,$D$8:$OR$8*($D$9:$OR$9=G$17))/SUMIFS($D$8:$OR$8,$D$9:$OR$9,G$17)} -> 0.00073340014 | H99: {=SUMPRODUCT('BEA Requirements Table'!$D88:$OR88,$D$8:$OR$8*($D$9:$OR$9=H$17))/SUMIFS($D$8:$OR$8,$D$9:$OR$9,H$17)} -> 0.00039154621 | I99: {=SUMPRODUCT('BEA Requirements Table'!$D88:$OR88,$D$8:$OR$8*($D$9:$OR$9=I$17))/SUMIFS($D$8:$OR$8,$D$9:$OR$9,I$17)} -> 0.00066428987 | J99: {=SUMPRODUCT('BEA Requirements Table'!$D88:$OR88,$D$8:$OR$8*($D$9:$OR$9=J$17))/SUMIFS($D$8:$OR$8,$D$9:$OR$9,J$17)} -> 0.00053988898 | K99: {=SUMPRODUCT('BEA Requirements Table'!$D88:$OR88,$D$8:$OR$8*($D$9:$OR$9=K$17))/SUMIFS($D$8:$OR$8,$D$9:$OR$9,K$17)} -> 0.00060338687 | ... AS99: {=SUMPRODUCT('BEA Requirements Table'!$D88:$OR88,$D$8:$OR$8*($D$9:$OR$9=AS$17))/SUMIFS($D$8:$OR$8,$D$9:$OR$9,AS$17)} -> 0
A100: 333111 | B100: 34750 | C100: ISIC 28 | D100: {=SUMPRODUCT('BEA Requirements Table'!$D89:$OR89,$D$8:$OR$8*($D$9:$OR$9=D$17))/SUMIFS($D$8:$OR$8,$D$9:$OR$9,D$17)} -> 0.0031150457 | E100: {=SUMPRODUCT('BEA Requirements Table'!$D89:$OR89,$D$8:$OR$8*($D$9:$OR$9=E$17))/SUMIFS($D$8:$OR$8,$D$9:$OR$9,E$17)} -> 5.53e-05 | F100: {=SUMPRODUCT('BEA Requirements Table'!$D89:$OR89,$D$8:$OR$8*($D$9:$OR$9=F$17))/SUMIFS($D$8:$OR$8,$D$9:$OR$9,F$17)} -> 3.26e-05 | G100: {=SUMPRODUCT('BEA Requirements Table'!$D89:$OR89,$D$8:$OR$8*($D$9:$OR$9=G$17))/SUMIFS($D$8:$OR$8,$D$9:$OR$9,G$17)} -> 6.740968e-05 | H100: {=SUMPRODUCT('BEA Requirements Table'!$D89:$OR89,$D$8:$OR$8*($D$9:$OR$9=H$17))/SUMIFS($D$8:$OR$8,$D$9:$OR$9,H$17)} -> 3.4433425e-05 | I100: {=SUMPRODUCT('BEA Requirements Table'!$D89:$OR89,$D$8:$OR$8*($D$9:$OR$9=I$17))/SUMIFS($D$8:$OR$8,$D$9:$OR$9,I$17)} -> 0.001268132 | J100: {=SUMPRODUCT('BEA Requirements Table'!$D89:$OR89,$D$8:$OR$8*($D$9:$OR$9=J$17))/SUMIFS($D$8:$OR$8,$D$9:$OR$9,J$17)} -> 0.00016516878 | K100: {=SUMPRODUCT('BEA Requirements Table'!$D89:$OR89,$D$8:$OR$8*($D$9:$OR$9=K$17))/SUMIFS($D$8:$OR$8,$D$9:$OR$9,K$17)} -> 0.00043124378 | ... AS100: {=SUMPRODUCT('BEA Requirements Table'!$D89:$OR89,$D$8:$OR$8*($D$9:$OR$9=AS$17))/SUMIFS($D$8:$OR$8,$D$9:$OR$9,AS$17)} -> 0
A101: 333112 | B101: 7711 | C101: ISIC 28 | D101: {=SUMPRODUCT('BEA Requirements Table'!$D90:$OR90,$D$8:$OR$8*($D$9:$OR$9=D$17))/SUMIFS($D$8:$OR$8,$D$9:$OR$9,D$17)} -> 0.00035718965 | E101: {=SUMPRODUCT('BEA Requirements Table'!$D90:$OR90,$D$8:$OR$8*($D$9:$OR$9=E$17))/SUMIFS($D$8:$OR$8,$D$9:$OR$9,E$17)} -> 0.0002095 | F101: {=SUMPRODUCT('BEA Requirements Table'!$D90:$OR90,$D$8:$OR$8*($D$9:$OR$9=F$17))/SUMIFS($D$8:$OR$8,$D$9:$OR$9,F$17)} -> 0.0001562 | G101: {=SUMPRODUCT('BEA Requirements Table'!$D90:$OR90,$D$8:$OR$8*($D$9:$OR$9=G$17))/SUMIFS($D$8:$OR$8,$D$9:$OR$9,G$17)} -> 0.0001412706 | H101: {=SUMPRODUCT('BEA Requirements Table'!$D90:$OR90,$D$8:$OR$8*($D$9:$OR$9=H$17))/SUMIFS($D$8:$OR$8,$D$9:$OR$9,H$17)} -> 0.00018165728 | I101: {=SUMPRODUCT('BEA Requirements Table'!$D90:$OR90,$D$8:$OR$8*($D$9:$OR$9=I$17))/SUMIFS($D$8:$OR$8,$D$9:$OR$9,I$17)} -> 0.00011508322 | J101: {=SUMPRODUCT('BEA Requirements Table'!$D90:$OR90,$D$8:$OR$8*($D$9:$OR$9=J$17))/SUMIFS($D$8:$OR$8,$D$9:$OR$9,J$17)} -> 4.9224089e-05 | K101: {=SUMPRODUCT('BEA Requirements Table'!$D90:$OR90,$D$8:$OR$8*($D$9:$OR$9=K$17))/SUMIFS($D$8:$OR$8,$D$9:$OR$9,K$17)} -> 0.00010780863 | ... AS101: {=SUMPRODUCT('BEA Requirements Table'!$D90:$OR90,$D$8:$OR$8*($D$9:$OR$9=AS$17))/SUMIFS($D$8:$OR$8,$D$9:$OR$9,AS$17)} -> 0
A102: 333120 | B102: 40161 | C102: ISIC 28 | D102: {=SUMPRODUCT('BEA Requirements Table'!$D91:$OR91,$D$8:$OR$8*($D$9:$OR$9=D$17))/SUMIFS($D$8:$OR$8,$D$9:$OR$9,D$17)} -> 2.7739876e-05 | E102: {=SUMPRODUCT('BEA Requirements Table'!$D91:$OR91,$D$8:$OR$8*($D$9:$OR$9=E$17))/SUMIFS($D$8:$OR$8,$D$9:$OR$9,E$17)} -> 0.0010971 | F102: {=SUMPRODUCT('BEA Requirements Table'!$D91:$OR91,$D$8:$OR$8*($D$9:$OR$9=F$17))/SUMIFS($D$8:$OR$8,$D$9:$OR$9,F$17)} -> 0.0002392 | G102: {=SUMPRODUCT('BEA Requirements Table'!$D91:$OR91,$D$8:$OR$8*($D$9:$OR$9=G$17))/SUMIFS($D$8:$OR$8,$D$9:$OR$9,G$17)} -> 0.001366959 | H102: {=SUMPRODUCT('BEA Requirements Table'!$D91:$OR91,$D$8:$OR$8*($D$9:$OR$9=H$17))/SUMIFS($D$8:$OR$8,$D$9:$OR$9,H$17)} -> 0.00048983452 | I102: {=SUMPRODUCT('BEA Requirements Table'!$D91:$OR91,$D$8:$OR$8*($D$9:$OR$9=I$17))/SUMIFS($D$8:$OR$8,$D$9:$OR$9,I$17)} -> 1.9218968e-05 | J102: {=SUMPRODUCT('BEA Requirements Table'!$D91:$OR91,$D$8:$OR$8*($D$9:$OR$9=J$17))/SUMIFS($D$8:$OR$8,$D$9:$OR$9,J$17)} -> 1.4365083e-05 | K102: {=SUMPRODUCT('BEA Requirements Table'!$D91:$OR91,$D$8:$OR$8*($D$9:$OR$9=K$17))/SUMIFS($D$8:$OR$8,$D$9:$OR$9,K$17)} -> 1.3020543e-05 | ... AS102: {=SUMPRODUCT('BEA Requirements Table'!$D91:$OR91,$D$8:$OR$8*($D$9:$OR$9=AS$17))/SUMIFS($D$8:$OR$8,$D$9:$OR$9,AS$17)} -> 0
A103: 333130 | B103: 32768 | C103: ISIC 28 | D103: {=SUMPRODUCT('BEA Requirements Table'!$D92:$OR92,$D$8:$OR$8*($D$9:$OR$9=D$17))/SUMIFS($D$8:$OR$8,$D$9:$OR$9,D$17)} -> 9.9138703e-05 | E103: {=SUMPRODUCT('BEA Requirements Table'!$D92:$OR92,$D$8:$OR$8*($D$9:$OR$9=E$17))/SUMIFS($D$8:$OR$8,$D$9:$OR$9,E$17)} -> 0.0132818 | F103: {=SUMPRODUCT('BEA Requirements Table'!$D92:$OR92,$D$8:$OR$8*($D$9:$OR$9=F$17))/SUMIFS($D$8:$OR$8,$D$9:$OR$9,F$17)} -> 0.0034931 | G103: {=SUMPRODUCT('BEA Requirements Table'!$D92:$OR92,$D$8:$OR$8*($D$9:$OR$9=G$17))/SUMIFS($D$8:$OR$8,$D$9:$OR$9,G$17)} -> 0.0043360002 | H103: {=SUMPRODUCT('BEA Requirements Table'!$D92:$OR92,$D$8:$OR$8*($D$9:$OR$9=H$17))/SUMIFS($D$8:$OR$8,$D$9:$OR$9,H$17)} -> 0.0036596113 | I103: {=SUMPRODUCT('BEA Requirements Table'!$D92:$OR92,$D$8:$OR$8*($D$9:$OR$9=I$17))/SUMIFS($D$8:$OR$8,$D$9:$OR$9,I$17)} -> 0.00011689651 | J103: {=SUMPRODUCT('BEA Requirements Table'!$D92:$OR92,$D$8:$OR$8*($D$9:$OR$9=J$17))/SUMIFS($D$8:$OR$8,$D$9:$OR$9,J$17)} -> 0.00011927996 | K103: {=SUMPRODUCT('BEA Requirements Table'!$D92:$OR92,$D$8:$OR$8*($D$9:$OR$9=K$17))/SUMIFS($D$8:$OR$8,$D$9:$OR$9,K$17)} -> 9.2551074e-05 | ... AS103: {=SUMPRODUCT('BEA Requirements Table'!$D92:$OR92,$D$8:$OR$8*($D$9:$OR$9=AS$17))/SUMIFS($D$8:$OR$8,$D$9:$OR$9,AS$17)} -> 0
A104: 333242 | B104: 10289 | C104: ISIC 28 | D104: {=SUMPRODUCT('BEA Requirements Table'!$D93:$OR93,$D$8:$OR$8*($D$9:$OR$9=D$17))/SUMIFS($D$8:$OR$8,$D$9:$OR$9,D$17)} -> 1.7770583e-05 | E104: {=SUMPRODUCT('BEA Requirements Table'!$D93:$OR93,$D$8:$OR$8*($D$9:$OR$9=E$17))/SUMIFS($D$8:$OR$8,$D$9:$OR$9,E$17)} -> 2.14e-05 | F104: {=SUMPRODUCT('BEA Requirements Table'!$D93:$OR93,$D$8:$OR$8*($D$9:$OR$9=F$17))/SUMIFS($D$8:$OR$8,$D$9:$OR$9,F$17)} -> 2.01e-05 | G104: {=SUMPRODUCT('BEA Requirements Table'!$D93:$OR93,$D$8:$OR$8*($D$9:$OR$9=G$17))/SUMIFS($D$8:$OR$8,$D$9:$OR$9,G$17)} -> 2.5740764e-05 | H104: {=SUMPRODUCT('BEA Requirements Table'!$D93:$OR93,$D$8:$OR$8*($D$9:$OR$9=H$17))/SUMIFS($D$8:$OR$8,$D$9:$OR$9,H$17)} -> 2.621661e-05 | I104: {=SUMPRODUCT('BEA Requirements Table'!$D93:$OR93,$D$8:$OR$8*($D$9:$OR$9=I$17))/SUMIFS($D$8:$OR$8,$D$9:$OR$9,I$17)} -> 2.8164528e-05 | J104: {=SUMPRODUCT('BEA Requirements Table'!$D93:$OR93,$D$8:$OR$8*($D$9:$OR$9=J$17))/SUMIFS($D$8:$OR$8,$D$9:$OR$9,J$17)} -> 3.1294469e-05 | K104: {=SUMPRODUCT('BEA Requirements Table'!$D93:$OR93,$D$8:$OR$8*($D$9:$OR$9=K$17))/SUMIFS($D$8:$OR$8,$D$9:$OR$9,K$17)} -> 3.0837096e-05 | ... AS104: {=SUMPRODUCT('BEA Requirements Table'!$D93:$OR93,$D$8:$OR$8*($D$9:$OR$9=AS$17))/SUMIFS($D$8:$OR$8,$D$9:$OR$9,AS$17)} -> 0
A105: 33329A | B105: 22752 | C105: ISIC 28 | D105: {=SUMPRODUCT('BEA Requirements Table'!$D94:$OR94,$D$8:$OR$8*($D$9:$OR$9=D$17))/SUMIFS($D$8:$OR$8,$D$9:$OR$9,D$17)} -> 5.720669e-05 | E105: {=SUMPRODUCT('BEA Requirements Table'!$D94:$OR94,$D$8:$OR$8*($D$9:$OR$9=E$17))/SUMIFS($D$8:$OR$8,$D$9:$OR$9,E$17)} -> 0.0001273 | F105: {=SUMPRODUCT('BEA Requirements Table'!$D94:$OR94,$D$8:$OR$8*($D$9:$OR$9=F$17))/SUMIFS($D$8:$OR$8,$D$9:$OR$9,F$17)} -> 9.18e-05 | G105: {=SUMPRODUCT('BEA Requirements Table'!$D94:$OR94,$D$8:$OR$8*($D$9:$OR$9=G$17))/SUMIFS($D$8:$OR$8,$D$9:$OR$9,G$17)} -> 0.00018630988 | H105: {=SUMPRODUCT('BEA Requirements Table'!$D94:$OR94,$D$8:$OR$8*($D$9:$OR$9=H$17))/SUMIFS($D$8:$OR$8,$D$9:$OR$9,H$17)} -> 0.00020246439 | I105: {=SUMPRODUCT('BEA Requirements Table'!$D94:$OR94,$D$8:$OR$8*($D$9:$OR$9=I$17))/SUMIFS($D$8:$OR$8,$D$9:$OR$9,I$17)} -> 0.00034367458 | J105: {=SUMPRODUCT('BEA Requirements Table'!$D94:$OR94,$D$8:$OR$8*($D$9:$OR$9=J$17))/SUMIFS($D$8:$OR$8,$D$9:$OR$9,J$17)} -> 0.00017006113 | K105: {=SUMPRODUCT('BEA Requirements Table'!$D94:$OR94,$D$8:$OR$8*($D$9:$OR$9=K$17))/SUMIFS($D$8:$OR$8,$D$9:$OR$9,K$17)} -> 0.00011976453 | ... AS105: {=SUMPRODUCT('BEA Requirements Table'!$D94:$OR94,$D$8:$OR$8*($D$9:$OR$9=AS$17))/SUMIFS($D$8:$OR$8,$D$9:$OR$9,AS$17)} -> 0
A106: 333314 | B106: 5431 | C106: ISIC 28 | D106: {=SUMPRODUCT('BEA Requirements Table'!$D95:$OR95,$D$8:$OR$8*($D$9:$OR$9=D$17))/SUMIFS($D$8:$OR$8,$D$9:$OR$9,D$17)} -> 2.4188151e-06 | E106: {=SUMPRODUCT('BEA Requirements Table'!$D95:$OR95,$D$8:$OR$8*($D$9:$OR$9=E$17))/SUMIFS($D$8:$OR$8,$D$9:$OR$9,E$17)} -> 4.6e-06 | F106: {=SUMPRODUCT('BEA Requirements Table'!$D95:$OR95,$D$8:$OR$8*($D$9:$OR$9=F$17))/SUMIFS($D$8:$OR$8,$D$9:$OR$9,F$17)} -> 3.5e-06 | G106: {=SUMPRODUCT('BEA Requirements Table'!$D95:$OR95,$D$8:$OR$8*($D$9:$OR$9=G$17))/SUMIFS($D$8:$OR$8,$D$9:$OR$9,G$17)} -> 4.9294109e-06 | H106: {=SUMPRODUCT('BEA Requirements Table'!$D95:$OR95,$D$8:$OR$8*($D$9:$OR$9=H$17))/SUMIFS($D$8:$OR$8,$D$9:$OR$9,H$17)} -> 8.7781271e-06 | I106: {=SUMPRODUCT('BEA Requirements Table'!$D95:$OR95,$D$8:$OR$8*($D$9:$OR$9=I$17))/SUMIFS($D$8:$OR$8,$D$9:$OR$9,I$17)} -> 3.9999814e-06 | J106: {=SUMPRODUCT('BEA Requirements Table'!$D95:$OR95,$D$8:$OR$8*($D$9:$OR$9=J$17))/SUMIFS($D$8:$OR$8,$D$9:$OR$9,J$17)} -> 4.4336138e-06 | K106: {=SUMPRODUCT('BEA Requirements Table'!$D95:$OR95,$D$8:$OR$8*($D$9:$OR$9=K$17))/SUMIFS($D$8:$OR$8,$D$9:$OR$9,K$17)} -> 9.3736903e-06 | ... AS106: {=SUMPRODUCT('BEA Requirements Table'!$D95:$OR95,$D$8:$OR$8*($D$9:$OR$9=AS$17))/SUMIFS($D$8:$OR$8,$D$9:$OR$9,AS$17)} -> 0
...

Sheet BEA Requirements Table
A1: Industry-by-Industry Total Domestic Requirements Table, 2012
A2: Bureau of Economic Analysis
A4: Industry / Industry | D4: Oilseed farming | E4: Grain farming | F4: Vegetable and melon farming | G4: Fruit and tree nut farming | H4: Greenhouse, nursery, and floriculture production | I4: Other crop farming | J4: Dairy cattle and milk production | K4: Beef cattle ranching and farming, including feedlots and dual-purpose ranching and farming | L4: Poultry and egg production | M4: Animal production, except cattle and poultry and eggs | N4: Forestry and logging | O4: Fishing, hunting and trapping | P4: Support activities for agriculture and forestry | Q4: Oil and gas extraction | R4: Coal mining | S4: Copper, nickel, lead, and zinc mining | T4: Iron, gold, silver, and other metal ore mining | U4: Stone mining and quarrying | V4: Other nonmetallic mineral mining and quarrying | W4: Drilling oil and gas wells | X4: Other support activities for mining | Y4: Electric power generation, transmission, and distribution | Z4: Natural gas distribution | AA4: Water, sewage and other systems | AB4: Health care structures | AC4: Educational and vocational structures | AD4: Nonresidential maintenance and repair | AE4: Residential maintenance and repair | AF4: Office and commercial structures | AG4: Multifamily residential structures | AH4: Other residential structures | AI4: Manufacturing structures | AJ4: Other nonresidential structures | AK4: Power and communication structures | AL4: Single-family residential structures | AM4: Transportation structures and highways and streets | AN4: Sawmills and wood preservation | AO4: Veneer, plywood, and engineered wood product manufacturing | AP4: Millwork | AQ4: All other wood product manufacturing | AR4: Clay product and refractory manufacturing | AS4: Glass and glass product manufacturing | AT4: Cement manufacturing | AU4: Ready-mix concrete manufacturing | AV4: Concrete pipe, brick, and block manufacturing | AW4: Other concrete product manufacturing | AX4: Lime and gypsum product manufacturing | AY4: Abrasive product manufacturing | AZ4: Cut stone and stone product manufacturing | BA4: Ground or treated mineral and earth manufacturing | BB4: Mineral wool manufacturing | BC4: Miscellaneous nonmetallic mineral products | BD4: Iron and steel mills and ferroalloy manufacturing | BE4: Steel product manufacturing from purchased steel | BF4: Secondary smelting and alloying of aluminum | BG4: Alumina refining and primary aluminum production | BH4: Aluminum product manufacturing from purchased aluminum | BI4: Nonferrous Metal (except Aluminum) Smelting and Refining | BJ4: Copper rolling, drawing, extruding and alloying | BK4: Nonferrous metal (except copper and aluminum) rolling, drawing, extruding and alloying | BL4: Ferrous metal foundries | BM4: Nonferrous metal foundries | BN4: Custom roll forming | BO4: All other forging, stamping, and sintering | BP4: Metal crown, closure, and other metal stamping (except automotive) | BQ4: Cutlery and handtool manufacturing | BR4: Plate work and fabricated structural product manufacturing | BS4: Ornamental and architectural metal products manufacturing | BT4: Power boiler and heat exchanger manufacturing | BU4: Metal tank (heavy gauge) manufacturing | BV4: Metal can, box, and other metal container (light gauge) manufacturing | BW4: Hardware manufacturing | BX4: Spring and wire product manufacturing | BY4: Machine shops | BZ4: Turned product and screw, nut, and bolt manufacturing | CA4: Coating, engraving, heat treating and allied activities | CB4: Plumbing fixture fitting and trim manufacturing | CC4: Valve and fittings other than plumbing | CD4: Ball and roller bearing manufacturing | CE4: Fabricated pipe and pipe fitting manufacturing | CF4: Ammunition, arms, ordnance, and accessories manufacturing | CG4: Other fabricated metal manufacturing | CH4: Farm machinery and equipment manufacturing | CI4: Lawn and garden equipment manufacturing | CJ4: Construction machinery manufacturing | CK4: Mining and oil and gas field machinery manufacturing | CL4: Semiconductor machinery manufacturing | CM4: Other industrial machinery manufacturing | CN4: Optical instrument and lens manufacturing | CO4: Photographic and photocopying equipment manufacturing | CP4: Other commercial and service industry machinery manufacturing | CQ4: Heating equipment (except warm air furnaces) manufacturing | CR4: Air conditioning, refrigeration, and warm air heating equipment manufacturing | CS4: Industrial and commercial fan and blower and air purification equipment manufacturing | CT4: Industrial mold manufacturing | CU4: Special tool, die, jig, and fixture manufacturing | CV4: Machine tool manufacturing | CW4: Cutting and machine tool accessory, rolling mill, and other metalworking machinery manufacturing | CX4: Turbine and turbine generator set units manufacturing | CY4: Speed changer, industrial high-speed drive, and gear manufacturing | CZ4: Mechanical power transmission equipment manufacturing | DA4: Other engine equipment manufacturing | DB4: Air and gas compressor manufacturing | DC4: Pump and pumping equipment manufacturing | DD4: Material handling equipment manufacturing | DE4: Power-driven handtool manufacturing | DF4: Packaging machinery manufacturing | DG4: Industrial process furnace and oven manufacturing | DH4: Other general purpose machinery manufacturing | DI4: Fluid power process machinery | DJ4: Electronic computer manufacturing | DK4: Computer storage device manufacturing | DL4: Computer terminals and other computer peripheral equipment manufacturing | DM4: Telephone apparatus manufacturing | DN4: Broadcast and wireless communications equipment | DO4: Other communications equipment manufacturing | DP4: Semiconductor and related device manufacturing | DQ4: Printed circuit assembly (electronic assembly) manufacturing | DR4: Other electronic component manufacturing | DS4: Electromedical and electrotherapeutic apparatus manufacturing | DT4: Search, detection, and navigation instruments manufacturing | DU4: Automatic environmental control manufacturing | DV4: Industrial process variable instruments manufacturing | DW4: Totalizing fluid meter and counting device manufacturing | DX4: Electricity and signal testing instruments manufacturing | DY4: Analytical laboratory instrument manufacturing | DZ4: Irradiation apparatus manufacturing | EA4: Watch, clock, and other measuring and controlling device manufacturing | EB4: Audio and video equipment manufacturing | EC4: Manufacturing and reproducing magnetic and optical media | ED4: Electric lamp bulb and part manufacturing | EE4: Lighting fixture manufacturing | EF4: Small electrical appliance manufacturing | EG4: Household cooking appliance manufacturing | EH4: Household refrigerator and home freezer manufacturing | EI4: Household laundry equipment manufacturing | EJ4: Other major household appliance manufacturing | EK4: Power, distribution, and specialty transformer manufacturing | EL4: Motor and generator manufacturing | EM4: Switchgear and switchboard apparatus manufacturing | EN4: Relay and industrial control manufacturing | EO4: Storage battery manufacturing | EP4: Primary battery manufacturing | EQ4: Communication and energy wire and cable manufacturing | ER4: Wiring device manufacturing | ES4: Carbon and graphite product manufacturing | ET4: All other miscellaneous electrical equipment and component manufacturing | EU4: Automobile manufacturing | EV4: Light truck and utility vehicle manufacturing | EW4: Heavy duty truck manufacturing | EX4: Motor vehicle body manufacturing | EY4: Truck trailer manufacturing | EZ4: Motor home manufacturing | FA4: Travel trailer and camper manufacturing | FB4: Motor vehicle gasoline engine and engine parts manufacturing | FC4: Motor vehicle electrical and electronic equipment manufacturing | FD4: Motor vehicle transmission and power train parts manufacturing | FE4: Motor vehicle seating and interior trim manufacturing | FF4: Motor vehicle metal stamping | FG4: Other Motor Vehicle Parts Manufacturing | FH4: Motor vehicle steering, suspension component (except spring), and brake systems manufacturing | FI4: Aircraft manufacturing | FJ4: Aircraft engine and engine parts manufacturing | FK4: Other aircraft parts and auxiliary equipment manufacturing | FL4: Guided missile and space vehicle manufacturing | FM4: Propulsion units and parts for space vehicles and guided missiles | FN4: Railroad rolling stock manufacturing | FO4: Ship building and repairing | FP4: Boat building | FQ4: Motorcycle, bicycle, and parts manufacturing | FR4: Military armored vehicle, tank, and tank component manufacturing | FS4: All other transportation equipment manufacturing | FT4: Wood kitchen cabinet and countertop manufacturing | FU4: Upholstered household furniture manufacturing | FV4: Nonupholstered wood household furniture manufacturing | FW4: Institutional furniture manufacturing | FX4: Other household nonupholstered furniture | FY4: Showcase, partition, shelving, and locker manufacturing | FZ4: Office furniture and custom architectural woodwork and millwork manufacturing | GA4: Other furniture related product manufacturing | GB4: Surgical and medical instrument manufacturing | GC4: Surgical appliance and supplies manufacturing | GD4: Dental equipment and supplies manufacturing | GE4: Ophthalmic goods manufacturing | GF4: Dental laboratories | GG4: Jewelry and silverware manufacturing | GH4: Sporting and athletic goods manufacturing | GI4: Doll, toy, and game manufacturing | GJ4: Office supplies (except paper) manufacturing | GK4: Sign manufacturing | GL4: All other miscellaneous manufacturing | GM4: Dog and cat food manufacturing | GN4: Other animal food manufacturing | GO4: Flour milling and malt manufacturing | GP4: Wet corn milling | GQ4: Fats and oils refining and blending | GR4: Soybean and other oilseed processing | GS4: Breakfast cereal manufacturing | GT4: Sugar and confectionery product manufacturing | GU4: Frozen food manufacturing | GV4: Fruit and vegetable canning, pickling, and drying | GW4: Cheese manufacturing | GX4: Dry, condensed, and evaporated dairy product manufacturing | GY4: Fluid milk and butter manufacturing | GZ4: Ice cream and frozen dessert manufacturing | HA4: Poultry processing | HB4: Animal (except poultry) slaughtering, rendering, and processing | HC4: Seafood product preparation and packaging | HD4: Bread and bakery product manufacturing | HE4: Cookie, cracker, pasta, and tortilla manufacturing | HF4: Snack food manufacturing | HG4: Coffee and tea manufacturing | HH4: Flavoring syrup and concentrate manufacturing | HI4: Seasoning and dressing manufacturing | HJ4: All other food manufacturing | HK4: Soft drink and ice manufacturing | HL4: Breweries | HM4: Wineries | HN4: Distilleries | HO4: Tobacco product manufacturing | HP4: Fiber, yarn, and thread mills | HQ4: Fabric mills | HR4: Textile and fabric finishing and fabric coating mills | HS4: Carpet and rug mills | HT4: Curtain and linen mills | HU4: Other textile product mills | HV4: Apparel manufacturing | HW4: Leather and allied product manufacturing | HX4: Pulp mills | HY4: Paper mills | HZ4: Paperboard mills | IA4: Paperboard container manufacturing | IB4: Paper Bag and Coated and Treated Paper Manufacturing | IC4: Stationery product manufacturing | ID4: Sanitary paper product manufacturing | IE4: All other converted paper product manufacturing | IF4: Printing | IG4: Support activities for printing | IH4: Petroleum refineries | II4: Asphalt paving mixture and block manufacturing | IJ4: Asphalt shingle and coating materials manufacturing | IK4: Other petroleum and coal products manufacturing | IL4: Petrochemical manufacturing | IM4: Industrial gas manufacturing | IN4: Synthetic dye and pigment manufacturing | IO4: Other Basic Inorganic Chemical Manufacturing | IP4: Other basic organic chemical manufacturing | IQ4: Plastics material and resin manufacturing | IR4: Synthetic rubber and artificial and synthetic fibers and filaments manufacturing | IS4: Medicinal and botanical manufacturing | IT4: Pharmaceutical preparation manufacturing | IU4: In-vitro diagnostic substance manufacturing | IV4: Biological product (except diagnostic) manufacturing | IW4: Fertilizer manufacturing | IX4: Pesticide and other agricultural chemical manufacturing | IY4: Paint and coating manufacturing | IZ4: Adhesive manufacturing | JA4: Soap and cleaning compound manufacturing | JB4: Toilet preparation manufacturing | JC4: Printing ink manufacturing | JD4: All other chemical product and preparation manufacturing | JE4: Plastics packaging materials and unlaminated film and sheet manufacturing | JF4: Plastics pipe, pipe fitting, and unlaminated profile shape manufacturing | JG4: Laminated plastics plate, sheet (except packaging), and shape manufacturing | JH4: Polystyrene foam product manufacturing | JI4: Urethane and other foam product (except polystyrene) manufacturing | JJ4: Plastics bottle manufacturing | JK4: Other plastics product manufacturing | JL4: Tire manufacturing | JM4: Rubber and plastics hoses and belting manufacturing | JN4: Other rubber product manufacturing | JO4: Motor vehicle and motor vehicle parts and supplies | JP4: Professional and commercial equipment and supplies | JQ4: Household appliances and electrical and electronic goods | JR4: Machinery, equipment, and supplies | JS4: Other durable goods merchant wholesalers | JT4: Drugs and druggists’ sundries | JU4: Grocery and related product wholesalers | JV4: Petroleum and petroleum products | JW4: Other nondurable goods merchant wholesalers | JX4: Wholesale electronic markets and agents and brokers | JY4: Customs duties | JZ4: Motor vehicle and parts dealers | KA4: Food and beverage stores | KB4: General merchandise stores | KC4: Building material and garden equipment and supplies dealers | KD4: Health and personal care stores | KE4: Gasoline stations | KF4: Clothing and clothing accessories stores | KG4: Nonstore retailers | KH4: All other retail | KI4: Air transportation | KJ4: Rail transportation | KK4: Water transportation | KL4: Truck transportation | KM4: Transit and ground passenger transportation | KN4: Pipeline transportation | KO4: Scenic and sightseeing transportation and support activities for transportation | KP4: Couriers and messengers | KQ4: Warehousing and storage | KR4: Newspaper publishers | KS4: Periodical Publishers | KT4: Book publishers | KU4: Directory, mailing list, and other publishers | KV4: Software publishers | KW4: Motion picture and video industries | KX4: Sound recording industries | KY4: Radio and television broadcasting | KZ4: Cable and other subscription programming | LA4: Wired telecommunications carriers | LB4: Wireless telecommunications carriers (except satellite) | LC4: Satellite, telecommunications resellers, and all other telecommunications | LD4: Data processing, hosting, and related services | LE4: Internet publishing and broadcasting and Web search portals | LF4: News syndicates, libraries, archives and all other information services | LG4: Nondepository credit intermediation and related activities | LH4: Monetary authorities and depository credit intermediation | LI4: Other financial investment activities | LJ4: Securities and commodity contracts intermediation and brokerage | LK4: Direct life insurance carriers | LL4: Insurance carriers, except direct life | LM4: Insurance agencies, brokerages, and related activities | LN4: Funds, trusts, and other financial vehicles | LO4: Owner-occupied housing | LP4: Tenant-occupied housing | LQ4: Other real estate | LR4: Automotive equipment rental and leasing | LS4: Commercial and industrial machinery and equipment rental and leasing | LT4: General and consumer goods rental | LU4: Lessors of nonfinancial intangible assets | LV4: Legal services | LW4: Custom computer programming services | LX4: Computer systems design services | LY4: Other computer related services, including facilities management | LZ4: Accounting, tax preparation, bookkeeping, and payroll services | MA4: Architectural, engineering, and related services | MB4: Management consulting services | MC4: Environmental and other technical consulting services | MD4: Scientific research and development services | ME4: Advertising, public relations, and related services | MF4: Specialized design services | MG4: Photographic services | MH4: Veterinary services | MI4: All other miscellaneous professional, scientific, and technical services | MJ4: Management of companies and enterprises | MK4: Employment services | ML4: Services to buildings and dwellings | MM4: Office administrative services | MN4: Facilities support services | MO4: Business support services | MP4: Travel arrangement and reservation services | MQ4: Investigation and security services | MR4: Other support services | MS4: Waste management and remediation services | MT4: Elementary and secondary schools | MU4: Junior colleges, colleges, universities, and professional schools | MV4: Other educational services | MW4: Offices of physicians | MX4: Offices of dentists | MY4: Offices of other health practitioners | MZ4: Outpatient care centers | NA4: Medical and diagnostic laboratories | NB4: Home health care services | NC4: Other ambulatory health care services | ND4: Hospitals | NE4: Nursing and community care facilities | NF4: Residential mental health, substance abuse, and other residential care facilities | NG4: Individual and family services | NH4: Child day care services | NI4: Community food, housing, and other relief services, including rehabilitation services | NJ4: Performing arts companies | NK4: Spectator sports | NL4: Independent artists, writers, and performers | NM4: Promoters of performing arts and sports and agents for public figures | NN4: Museums, historical sites, zoos, and parks | NO4: Amusement parks and arcades | NP4: Gambling industries (except casino hotels) | NQ4: Other amusement and recreation industries | NR4: Accommodation | NS4: Full-service restaurants | NT4: Limited-service restaurants | NU4: All other food and drinking places | NV4: Automotive repair and maintenance | NW4: Electronic and precision equipment repair and maintenance | NX4: Commercial and industrial machinery and equipment repair and maintenance | NY4: Personal and household goods repair and maintenance | NZ4: Personal care services | OA4: Death care services | OB4: Dry-cleaning and laundry services | OC4: Other personal services | OD4: Religious organizations | OE4: Grantmaking, giving, and social advocacy organizations | OF4: Civic, social, professional, and similar organizations | OG4: Private households | OH4: Federal general government (defense) | OI4: Federal general government (nondefense) | OJ4: Postal service | OK4: Federal electric utilities | OL4: Other federal government enterprises | OM4: State and local government educational services | ON4: State and local government hospitals and health services | OO4: State and local government other services | OP4: State and local government passenger transit | OQ4: State and local government electric utilities | OR4: Other state and local government enterprises
