Workbook

Sheet About
A1: DRC Annual Cost per Unit Demand Response Capacity
A2: DRC Share of DR by Provider
A4: Source: | B4: EIA
B5: 2018
B6: Form 861 with data from 2016
B7: https://www.eia.gov/electricity/data/eia861/
B8: Demand_Response_2016.xlsx
A10: Notes
A11: Utilities pay to procure DR services. They often pay energy service companies (ESCOs),
A12: who themselves pass most of the payments on to the electricity consumers who are the
A13: suppliers of the DR. Other utilities may not use ESCOs and may pay the DR providers
A14: directly.
A16: Our data source provides the ultimate suppliers of the DR and the cost of that DR, but
A17: doesn't deal with the share taken by ESCOs. We do not model any share of the money
A18: taken by ESCOs and assign all of the cash flows from utilities to the ultimate DR providers
A19: (the "nonenergy industries" or "consumers" cash flow entities in the EPS).
A21: In the EPS, the "nonenergy industries" cash flow entity encompasses both industrial facilities and
A22: commercial buildings, so we calculate accordingly in this spreadsheet.
A24: We do not have any data on DR services provided by government buildings, so we
... A30: demand shifting they called upon.

Sheet Demand Response_States
A1: Utility Characteristics | E1: Cost Calculations | I1: Yearly Energy and Demand Savings | AC1: Program Costs | AM1: DSM Program
I2: Number of Customers Enrolled | N2: Energy Savings (MWh) | S2: Potential Peak Demand Savings (MW) | X2: Actual Peak Demand Savings (MW) | AC2: Customer Incentives (Thousand Dollars) | AH2: All Other Costs (Thousand Dollars) | AM2: Grid Connected
A3: Data Year | B3: Utility Number | C3: Utility Name | D3: State | E3: Residential Avg Cost ($/MW) | F3: Commercial Avg Cost ($/MW) | G3: Industrial Avg Cost ($/MW) | H3: Transportation Avg Cost ($/MW) | I3: Residential | J3: Commercial | K3: Industrial | L3: Transportation | M3: Total | N3: Residential | O3: Commercial | P3: Industrial | Q3: Transportation | R3: Total | S3: Residential | T3: Commercial | U3: Industrial | V3: Transportation | W3: Total | X3: Residential | Y3: Commercial | Z3: Industrial | AA3: Transportation | AB3: Total | AC3: Residential | AD3: Commercial | AE3: Industrial | AF3: Transportation | AG3: Total | AH3: Residential | AI3: Commercial | AJ3: Industrial | AK3: Transportation | AL3: Total | AM3: Water Heater
A4: 2016 | B4: 84 | C4: A & N Electric Coop | D4: MD | E4: =IFERROR(SUM(AC4,AH4)*10^3/S4,"") -> 2000 | F4: =IFERROR(SUM(AD4,AI4)*10^3/T4,"") | G4: =IFERROR(SUM(AE4,AJ4)*10^3/U4,"") | H4: =IFERROR(SUM(AF4,AK4)*10^3/V4,"") | I4: 35 | J4: 0 | K4: 0 | L4: 0 | M4: 35 | N4: 1 | O4: 0 | P4: 0 | Q4: 0 | R4: 1 | S4: 0.5 | T4: 0 | U4: 0 | V4: 0 | W4: 0.5 | X4: 0.4 | Y4: 0 | Z4: 0 | AA4: 0 | AB4: 0.4 | AC4: 0 | AD4: 0 | AE4: 0 | AF4: 0 | AG4: 0 | AH4: 1 | AI4: 0 | AJ4: 0 | AK4: 0 | AL4: 1 | AM4: .
A5: 2016 | B5: 84 | C5: A & N Electric Coop | D5: VA | E5: =IFERROR(SUM(AC5,AH5)*10^3/S5,"") -> 7500 | F5: =IFERROR(SUM(AD5,AI5)*10^3/T5,"") | G5: =IFERROR(SUM(AE5,AJ5)*10^3/U5,"") | H5: =IFERROR(SUM(AF5,AK5)*10^3/V5,"") | I5: 2471 | J5: 0 | K5: 0 | L5: 0 | M5: 2471 | N5: 110 | O5: 0 | P5: 0 | Q5: 0 | R5: 110 | S5: 2 | T5: 0 | U5: 0 | V5: 0 | W5: 2 | X5: 1 | Y5: 0 | Z5: 0 | AA5: 0 | AB5: 1 | AC5: 0 | AD5: 0 | AE5: 0 | AF5: 0 | AG5: 0 | AH5: 15 | AI5: 0 | AJ5: 0 | AK5: 0 | AL5: 15 | AM5: .
A6: 2016 | B6: 97 | C6: Adams Electric Coop | D6: IL | E6: =IFERROR(SUM(AC6,AH6)*10^3/S6,"") -> 19250 | F6: =IFERROR(SUM(AD6,AI6)*10^3/T6,"") -> 0 | G6: =IFERROR(SUM(AE6,AJ6)*10^3/U6,"") | H6: =IFERROR(SUM(AF6,AK6)*10^3/V6,"") | I6: 4263 | J6: 67 | K6: 0 | L6: 0 | M6: 4330 | N6: 0 | O6: 0 | P6: 0 | Q6: 0 | R6: 0 | S6: 4 | T6: 4 | U6: 0 | V6: 0 | W6: 8 | X6: 4 | Y6: 0 | Z6: 0 | AA6: 0 | AB6: 4 | AC6: 68 | AD6: 0 | AE6: 0 | AF6: 0 | AG6: 68 | AH6: 9 | AI6: 0 | AJ6: 0 | AK6: 0 | AL6: 9 | AM6: 43
A7: 2016 | B7: 108 | C7: Adams-Columbia Electric Coop | D7: WI | E7: =IFERROR(SUM(AC7,AH7)*10^3/S7,"") -> 18071.066 | F7: =IFERROR(SUM(AD7,AI7)*10^3/T7,"") | G7: =IFERROR(SUM(AE7,AJ7)*10^3/U7,"") -> 1537.2168 | H7: =IFERROR(SUM(AF7,AK7)*10^3/V7,"") | I7: 3906 | J7: 0 | K7: 951 | L7: 0 | M7: 4857 | N7: 1400 | O7: 0 | P7: 14681 | Q7: 0 | R7: 16081 | S7: 19.7 | T7: 0 | U7: 61.8 | V7: 0 | W7: 81.5 | X7: 5.9 | Y7: 0 | Z7: 9.9 | AA7: 0 | AB7: 15.8 | AC7: 295 | AD7: 0 | AE7: 1 | AF7: 0 | AG7: 296 | AH7: 61 | AI7: 0 | AJ7: 94 | AK7: 0 | AL7: 155 | AM7: 0
A8: 2016 | B8: 189 | C8: PowerSouth Energy Cooperative | D8: AL | E8: =IFERROR(SUM(AC8,AH8)*10^3/S8,"") -> 35933.333 | F8: =IFERROR(SUM(AD8,AI8)*10^3/T8,"") | G8: =IFERROR(SUM(AE8,AJ8)*10^3/U8,"") | H8: =IFERROR(SUM(AF8,AK8)*10^3/V8,"") | I8: 17284 | J8: 0 | K8: 0 | L8: 0 | M8: 17284 | N8: 0 | O8: 0 | P8: 0 | Q8: 0 | R8: 0 | S8: 15 | T8: 0 | U8: 0 | V8: 0 | W8: 15 | X8: 15 | Y8: 0 | Z8: 0 | AA8: 0 | AB8: 15 | AC8: 0 | AD8: 0 | AE8: 0 | AF8: 0 | AG8: 0 | AH8: 539 | AI8: 0 | AJ8: 0 | AK8: 0 | AL8: 539 | AM8: 2259
A9: 2016 | B9: 195 | C9: Alabama Power Co | D9: AL | E9: =IFERROR(SUM(AC9,AH9)*10^3/S9,"") -> 5986.0465 | F9: =IFERROR(SUM(AD9,AI9)*10^3/T9,"") -> 219428.57 | G9: =IFERROR(SUM(AE9,AJ9)*10^3/U9,"") -> 16704.205 | H9: =IFERROR(SUM(AF9,AK9)*10^3/V9,"") | I9: 12232 | J9: 63 | K9: 168 | L9: 0 | M9: 12463 | N9: 316 | O9: 2621 | P9: 2230 | Q9: 0 | R9: 5167 | S9: 215 | T9: 7 | U9: 1403 | V9: 0 | W9: 1625 | X9: 6.6 | Y9: 6 | Z9: 21.9 | AA9: 0 | AB9: 34.5 | AC9: 0 | AD9: 0 | AE9: 0 | AF9: 0 | AG9: 0 | AH9: 1287 | AI9: 1536 | AJ9: 23436 | AK9: 0 | AL9: 26259 | AM9: .
A10: 2016 | B10: 213 | C10: Alaska Electric Light&Power Co | D10: AK | E10: =IFERROR(SUM(AC10,AH10)*10^3/S10,"") -> 19200 | F10: =IFERROR(SUM(AD10,AI10)*10^3/T10,"") -> 76.923077 | G10: =IFERROR(SUM(AE10,AJ10)*10^3/U10,"") -> 0 | H10: =IFERROR(SUM(AF10,AK10)*10^3/V10,"") | I10: 2358 | J10: 44 | K10: 1 | L10: 0 | M10: 2403 | N10: 0 | O10: 0 | P10: 0 | Q10: 0 | R10: 0 | S10: 5 | T10: 13 | U10: 9 | V10: 0 | W10: 27 | X10: 0 | Y10: 13 | Z10: 9 | AA10: 0 | AB10: 22 | AC10: 65 | AD10: 1 | AE10: 0 | AF10: 0 | AG10: 66 | AH10: 31 | AI10: 0 | AJ10: 0 | AK10: 0 | AL10: 31 | AM10: 0
A11: 2016 | B11: 295 | C11: City of Alexandria - (MN) | D11: MN | E11: =IFERROR(SUM(AC11,AH11)*10^3/S11,"") -> 4777.7778 | F11: =IFERROR(SUM(AD11,AI11)*10^3/T11,"") | G11: =IFERROR(SUM(AE11,AJ11)*10^3/U11,"") | H11: =IFERROR(SUM(AF11,AK11)*10^3/V11,"") | I11: 2816 | J11: 0 | K11: 0 | L11: 0 | M11: 2816 | N11: 0 | O11: 0 | P11: 0 | Q11: 0 | R11: 0 | S11: 9 | T11: 0 | U11: 0 | V11: 0 | W11: 9 | X11: 3.7 | Y11: 0 | Z11: 0 | AA11: 0 | AB11: 3.7 | AC11: 5 | AD11: 0 | AE11: 0 | AF11: 0 | AG11: 5 | AH11: 38 | AI11: 0 | AJ11: 0 | AK11: 0 | AL11: 38 | AM11: 12
A12: 2016 | B12: 329 | C12: Allamakee-Clayton El Coop, Inc | D12: IA | E12: =IFERROR(SUM(AC12,AH12)*10^3/S12,"") -> 87142.857 | F12: =IFERROR(SUM(AD12,AI12)*10^3/T12,"") -> 89444.444 | G12: =IFERROR(SUM(AE12,AJ12)*10^3/U12,"") | H12: =IFERROR(SUM(AF12,AK12)*10^3/V12,"") | I12: 2659 | J12: 163 | K12: 0 | L12: 0 | M12: 2822 | N12: 0 | O12: 0 | P12: 0 | Q12: 0 | R12: 0 | S12: 4.9 | T12: 1.8 | U12: 0 | V12: 0 | W12: 6.7 | X12: 2.6 | Y12: 1 | Z12: 0 | AA12: 0 | AB12: 3.6 | AC12: 314 | AD12: 118 | AE12: 0 | AF12: 0 | AG12: 432 | AH12: 113 | AI12: 43 | AJ12: 0 | AK12: 0 | AL12: 156 | AM12: .
A13: 2016 | B13: 407 | C13: Altamaha Electric Member Corp | D13: GA | E13: =IFERROR(SUM(AC13,AH13)*10^3/S13,"") | F13: =IFERROR(SUM(AD13,AI13)*10^3/T13,"") | G13: =IFERROR(SUM(AE13,AJ13)*10^3/U13,"") -> 2027.027 | H13: =IFERROR(SUM(AF13,AK13)*10^3/V13,"") | I13: 0 | J13: 0 | K13: 203 | L13: 0 | M13: 203 | N13: 0 | O13: 0 | P13: 0 | Q13: 0 | R13: 0 | S13: 0 | T13: 0 | U13: 14.8 | V13: 0 | W13: 14.8 | X13: 0 | Y13: 0 | Z13: 14.8 | AA13: 0 | AB13: 14.8 | AC13: 0 | AD13: 0 | AE13: 0 | AF13: 0 | AG13: 0 | AH13: 0 | AI13: 0 | AJ13: 30 | AK13: 0 | AL13: 30 | AM13: .
A14: 2016 | B14: 590 | C14: City of Anaheim - (CA) | D14: CA | E14: =IFERROR(SUM(AC14,AH14)*10^3/S14,"") | F14: =IFERROR(SUM(AD14,AI14)*10^3/T14,"") -> 0 | G14: =IFERROR(SUM(AE14,AJ14)*10^3/U14,"") -> 0 | H14: =IFERROR(SUM(AF14,AK14)*10^3/V14,"") | I14: 0 | J14: 3 | K14: 11 | L14: 0 | M14: 14 | N14: 0 | O14: 0 | P14: 0 | Q14: 0 | R14: 0 | S14: 0 | T14: 5 | U14: 8 | V14: 0 | W14: 13 | X14: 0 | Y14: 0 | Z14: 0 | AA14: 0 | AB14: 0 | AC14: 0 | AD14: 0 | AE14: 0 | AF14: 0 | AG14: 0 | AH14: 0 | AI14: 0 | AJ14: 0 | AK14: 0 | AL14: 0 | AM14: .
A15: 2016 | B15: 733 | C15: Appalachian Power Co | D15: VA | E15: =IFERROR(SUM(AC15,AH15)*10^3/S15,"") -> 0 | F15: =IFERROR(SUM(AD15,AI15)*10^3/T15,"") | G15: =IFERROR(SUM(AE15,AJ15)*10^3/U15,"") -> 0 | H15: =IFERROR(SUM(AF15,AK15)*10^3/V15,"") | I15: 3406 | J15: 0 | K15: 5 | L15: 0 | M15: 3411 | N15: 0 | O15: 0 | P15: 0 | Q15: 0 | R15: 0 | S15: 3.4 | T15: 0 | U15: 33.5 | V15: 0 | W15: 36.9 | X15: 3.4 | Y15: 0 | Z15: 0 | AA15: 0 | AB15: 3.4 | AC15: 0 | AD15: 0 | AE15: 0 | AF15: 0 | AG15: 0 | AH15: 0 | AI15: 0 | AJ15: 0 | AK15: 0 | AL15: 0 | AM15: .
A16: 2016 | B16: 733 | C16: Appalachian Power Co | D16: WV | E16: =IFERROR(SUM(AC16,AH16)*10^3/S16,"") -> 0 | F16: =IFERROR(SUM(AD16,AI16)*10^3/T16,"") | G16: =IFERROR(SUM(AE16,AJ16)*10^3/U16,"") -> 0 | H16: =IFERROR(SUM(AF16,AK16)*10^3/V16,"") | I16: 1420 | J16: 0 | K16: 5 | L16: 0 | M16: 1425 | N16: 1 | O16: 0 | P16: 0 | Q16: 0 | R16: 1 | S16: 1.4 | T16: 0 | U16: 93.7 | V16: 0 | W16: 95.1 | X16: 1.4 | Y16: 0 | Z16: 0 | AA16: 0 | AB16: 1.4 | AC16: 0 | AD16: 0 | AE16: 0 | AF16: 0 | AG16: 0 | AH16: 0 | AI16: 0 | AJ16: 0 | AK16: 0 | AL16: 0 | AM16: .
A17: 2016 | B17: 803 | C17: Arizona Public Service Co | D17: AZ | E17: =IFERROR(SUM(AC17,AH17)*10^3/S17,"") -> 10313.024 | F17: =IFERROR(SUM(AD17,AI17)*10^3/T17,"") -> 0 | G17: =IFERROR(SUM(AE17,AJ17)*10^3/U17,"") | H17: =IFERROR(SUM(AF17,AK17)*10^3/V17,"") | I17: 573415 | J17: 903 | K17: 0 | L17: 0 | M17: 574318 | N17: 791576 | O17: 121808 | P17: 0 | Q17: 0 | R17: 913384 | S17: 178.9 | T17: 27.8 | U17: 0 | V17: 0 | W17: 206.7 | X17: 178.9 | Y17: 27.8 | Z17: 0 | AA17: 0 | AB17: 206.7 | AC17: 0 | AD17: 0 | AE17: 0 | AF17: 0 | AG17: 0 | AH17: 1845 | AI17: 0 | AJ17: 0 | AK17: 0 | AL17: 1845 | AM17: .
A18: 2016 | B18: 807 | C18: Arkansas Electric Coop Corp | D18: AR | E18: =IFERROR(SUM(AC18,AH18)*10^3/S18,"") | F18: =IFERROR(SUM(AD18,AI18)*10^3/T18,"") -> 43804.14 | G18: =IFERROR(SUM(AE18,AJ18)*10^3/U18,"") | H18: =IFERROR(SUM(AF18,AK18)*10^3/V18,"") | I18: 0 | J18: 8 | K18: 0 | L18: 0 | M18: 8 | N18: 0 | O18: 0 | P18: 0 | Q18: 0 | R18: 0 | S18: 0 | T18: 628 | U18: 0 | V18: 0 | W18: 628 | X18: 0 | Y18: 80 | Z18: 0 | AA18: 0 | AB18: 80 | AC18: 0 | AD18: 27509 | AE18: 0 | AF18: 0 | AG18: 27509 | AH18: 0 | AI18: 0 | AJ18: 0 | AK18: 0 | AL18: 0 | AM18: .
A19: 2016 | B19: 814 | C19: Entergy Arkansas Inc | D19: AR | E19: =IFERROR(SUM(AC19,AH19)*10^3/S19,"") -> 133451.96 | F19: =IFERROR(SUM(AD19,AI19)*10^3/T19,"") | G19: =IFERROR(SUM(AE19,AJ19)*10^3/U19,"") -> 210529.41 | H19: =IFERROR(SUM(AF19,AK19)*10^3/V19,"") | I19: 23613 | J19: 0 | K19: 1547 | L19: 0 | M19: 25160 | N19: 52172 | O19: 0 | P19: 0 | Q19: 0 | R19: 52172 | S19: 28.1 | T19: 0 | U19: 17 | V19: 0 | W19: 45.1 | X19: 28.1 | Y19: 0 | Z19: 17 | AA19: 0 | AB19: 45.1 | AC19: 764 | AD19: 0 | AE19: 331 | AF19: 0 | AG19: 1095 | AH19: 2986 | AI19: 0 | AJ19: 3248 | AK19: 0 | AL19: 6234 | AM19: .
A20: 2016 | B20: 828 | C20: City of Arlington - (MN) | D20: MN | E20: =IFERROR(SUM(AC20,AH20)*10^3/S20,"") | F20: =IFERROR(SUM(AD20,AI20)*10^3/T20,"") | G20: =IFERROR(SUM(AE20,AJ20)*10^3/U20,"") | H20: =IFERROR(SUM(AF20,AK20)*10^3/V20,"") | I20: 444 | J20: 33 | K20: 0 | L20: 0 | M20: 477 | N20: 0 | O20: 0 | P20: 0 | Q20: 0 | R20: 0 | S20: 0 | T20: 0 | U20: 0 | V20: 0 | W20: 0 | X20: 0 | Y20: 0 | Z20: 0 | AA20: 0 | AB20: 0 | AC20: 11 | AD20: 1 | AE20: 0 | AF20: 0 | AG20: 12 | AH20: 0 | AI20: 0 | AJ20: 0 | AK20: 0 | AL20: 0 | AM20: .
A21: 2016 | B21: 963 | C21: Atlantic City Electric Co | D21: NJ | E21: =IFERROR(SUM(AC21,AH21)*10^3/S21,"") -> 39316.406 | F21: =IFERROR(SUM(AD21,AI21)*10^3/T21,"") | G21: =IFERROR(SUM(AE21,AJ21)*10^3/U21,"") | H21: =IFERROR(SUM(AF21,AK21)*10^3/V21,"") | I21: 46449 | J21: 0 | K21: 0 | L21: 0 | M21: 46449 | N21: 205 | O21: 0 | P21: 0 | Q21: 0 | R21: 205 | S21: 51.2 | T21: 0 | U21: 0 | V21: 0 | W21: 51.2 | X21: 51.2 | Y21: 0 | Z21: 0 | AA21: 0 | AB21: 51.2 | AC21: 145 | AD21: 0 | AE21: 0 | AF21: 0 | AG21: 145 | AH21: 1868 | AI21: 0 | AJ21: 0 | AK21: 0 | AL21: 1868 | AM21: .
A22: 2016 | B22: 965 | C22: Atlantic Municipal Utilities | D22: IA | E22: =IFERROR(SUM(AC22,AH22)*10^3/S22,"") -> 26000 | F22: =IFERROR(SUM(AD22,AI22)*10^3/T22,"") -> 10000 | G22: =IFERROR(SUM(AE22,AJ22)*10^3/U22,"") | H22: =IFERROR(SUM(AF22,AK22)*10^3/V22,"") | I22: 327 | J22: 33 | K22: 0 | L22: 0 | M22: 360 | N22: 25 | O22: 14 | P22: 0 | Q22: 0 | R22: 39 | S22: 0.5 | T22: 0.1 | U22: 0 | V22: 0 | W22: 0.6 | X22: 0.5 | Y22: 0.1 | Z22: 0 | AA22: 0 | AB22: 0.6 | AC22: 8 | AD22: 1 | AE22: 0 | AF22: 0 | AG22: 9 | AH22: 5 | AI22: 0 | AJ22: 0 | AK22: 0 | AL22: 5 | AM22: .
A23: 2016 | B23: 1009 | C23: City of Austin - (MN) | D23: MN | E23: =IFERROR(SUM(AC23,AH23)*10^3/S23,"") -> 0 | F23: =IFERROR(SUM(AD23,AI23)*10^3/T23,"") -> 42500 | G23: =IFERROR(SUM(AE23,AJ23)*10^3/U23,"") | H23: =IFERROR(SUM(AF23,AK23)*10^3/V23,"") | I23: 6542 | J23: 2 | K23: 0 | L23: 0 | M23: 6544 | N23: 304 | O23: 6 | P23: 0 | Q23: 0 | R23: 310 | S23: 3.5 | T23: 0.4 | U23: 0 | V23: 0 | W23: 3.9 | X23: 3.5 | Y23: 0.4 | Z23: 0 | AA23: 0 | AB23: 3.9 | AC23: 0 | AD23: 17 | AE23: 0 | AF23: 0 | AG23: 17 | AH23: 0 | AI23: 0 | AJ23: 0 | AK23: 0 | AL23: 0 | AM23: .
A24: 2016 | B24: 1015 | C24: Austin Energy | D24: TX | E24: =IFERROR(SUM(AC24,AH24)*10^3/S24,"") -> 39359.606 | F24: =IFERROR(SUM(AD24,AI24)*10^3/T24,"") -> 28257.426 | G24: =IFERROR(SUM(AE24,AJ24)*10^3/U24,"") -> 29141.104 | H24: =IFERROR(SUM(AF24,AK24)*10^3/V24,"") | I24: 128501 | J24: 8825 | K24: 2942 | L24: 0 | M24: 140268 | N24: 61 | O24: 205 | P24: 68 | Q24: 0 | R24: 334 | S24: 60.9 | T24: 50.5 | U24: 16.3 | V24: 0 | W24: 127.7 | X24: 35.3 | Y24: 35.4 | Z24: 11.2 | AA24: 0 | AB24: 81.9 | AC24: 1383 | AD24: 357 | AE24: 119 | AF24: 0 | AG24: 1859 | AH24: 1014 | AI24: 1070 | AJ24: 356 | AK24: 0 | AL24: 2440 | AM24: 1973
A25: 2016 | B25: 1167 | C25: Baltimore Gas & Electric Co | D25: MD | E25: =IFERROR(SUM(AC25,AH25)*10^3/S25,"") -> 90851.401 | F25: =IFERROR(SUM(AD25,AI25)*10^3/T25,"") | G25: =IFERROR(SUM(AE25,AJ25)*10^3/U25,"") | H25: =IFERROR(SUM(AF25,AK25)*10^3/V25,"") | I25: 332684 | J25: 0 | K25: 0 | L25: 0 | M25: 332684 | N25: 2302 | O25: 0 | P25: 0 | Q25: 0 | R25: 2302 | S25: 378.2 | T25: 0 | U25: 0 | V25: 0 | W25: 378.2 | X25: 0 | Y25: 0 | Z25: 0 | AA25: 0 | AB25: 0 | AC25: 23366 | AD25: 0 | AE25: 0 | AF25: 0 | AG25: 23366 | AH25: 10994 | AI25: 0 | AJ25: 0 | AK25: 0 | AL25: 10994 | AM25: .
A26: 2016 | B26: 1233 | C26: City of Barnesville - (MN) | D26: MN | E26: =IFERROR(SUM(AC26,AH26)*10^3/S26,"") -> 21000 | F26: =IFERROR(SUM(AD26,AI26)*10^3/T26,"") | G26: =IFERROR(SUM(AE26,AJ26)*10^3/U26,"") | H26: =IFERROR(SUM(AF26,AK26)*10^3/V26,"") | I26: 872 | J26: 60 | K26: 0 | L26: 0 | M26: 932 | N26: 9 | O26: 0 | P26: 0 | Q26: 0 | R26: 9 | S26: 1 | T26: 0 | U26: 0 | V26: 0 | W26: 1 | X26: 1 | Y26: 0 | Z26: 0 | AA26: 0 | AB26: 1 | AC26: 11 | AD26: 0 | AE26: 0 | AF26: 0 | AG26: 11 | AH26: 10 | AI26: 0 | AJ26: 0 | AK26: 0 | AL26: 10 | AM26: .
A27: 2016 | B27: 1251 | C27: Barron Electric Coop | D27: WI | E27: =IFERROR(SUM(AC27,AH27)*10^3/S27,"") -> 8571.4286 | F27: =IFERROR(SUM(AD27,AI27)*10^3/T27,"") -> 8518.5185 | G27: =IFERROR(SUM(AE27,AJ27)*10^3/U27,"") | H27: =IFERROR(SUM(AF27,AK27)*10^3/V27,"") | I27: 6067 | J27: 359 | K27: 0 | L27: 0 | M27: 6426 | N27: 0 | O27: 0 | P27: 0 | Q27: 0 | R27: 0 | S27: 3.5 | T27: 10.8 | U27: 0 | V27: 0 | W27: 14.3 | X27: 1.6 | Y27: 4.9 | Z27: 0 | AA27: 0 | AB27: 6.5 | AC27: 8 | AD27: 24 | AE27: 0 | AF27: 0 | AG27: 32 | AH27: 22 | AI27: 68 | AJ27: 0 | AK27: 0 | AL27: 90 | AM27: .
A28: 2016 | B28: 1367 | C28: Bayfield Electric Coop, Inc | D28: WI | E28: =IFERROR(SUM(AC28,AH28)*10^3/S28,"") -> 26500 | F28: =IFERROR(SUM(AD28,AI28)*10^3/T28,"") | G28: =IFERROR(SUM(AE28,AJ28)*10^3/U28,"") | H28: =IFERROR(SUM(AF28,AK28)*10^3/V28,"") | I28: 1201 | J28: 6 | K28: 0 | L28: 0 | M28: 1207 | N28: 398 | O28: 0 | P28: 0 | Q28: 0 | R28: 398 | S28: 2 | T28: 0 | U28: 0 | V28: 0 | W28: 2 | X28: 2 | Y28: 0 | Z28: 0 | AA28: 0 | AB28: 2 | AC28: 44 | AD28: 0 | AE28: 0 | AF28: 0 | AG28: 44 | AH28: 9 | AI28: 0 | AJ28: 0 | AK28: 0 | AL28: 9 | AM28: .
A29: 2016 | B29: 1529 | C29: Beltrami Electric Coop, Inc | D29: MN | E29: =IFERROR(SUM(AC29,AH29)*10^3/S29,"") -> 1383.5061 | F29: =IFERROR(SUM(AD29,AI29)*10^3/T29,"") -> 0 | G29: =IFERROR(SUM(AE29,AJ29)*10^3/U29,"") | H29: =IFERROR(SUM(AF29,AK29)*10^3/V29,"") | I29: 7760 | J29: 28 | K29: 0 | L29: 0 | M29: 7788 | N29: 5002 | O29: 0 | P29: 0 | Q29: 0 | R29: 5002 | S29: 221.9 | T29: 3.9 | U29: 0 | V29: 0 | W29: 225.8 | X29: 27.4 | Y29: 3.9 | Z29: 0 | AA29: 0 | AB29: 31.3 | AC29: 35 | AD29: 0 | AE29: 0 | AF29: 0 | AG29: 35 | AH29: 272 | AI29: 0 | AJ29: 0 | AK29: 0 | AL29: 272 | AM29: 0
A30: 2016 | B30: 1573 | C30: City of Benson - (MN) | D30: MN | E30: =IFERROR(SUM(AC30,AH30)*10^3/S30,"") -> 2941.1765 | F30: =IFERROR(SUM(AD30,AI30)*10^3/T30,"") -> 0 | G30: =IFERROR(SUM(AE30,AJ30)*10^3/U30,"") | H30: =IFERROR(SUM(AF30,AK30)*10^3/V30,"") | I30: 966 | J30: 35 | K30: 0 | L30: 0 | M30: 1001 | N30: 0 | O30: 0 | P30: 0 | Q30: 0 | R30: 0 | S30: 3.4 | T30: 0.4 | U30: 0 | V30: 0 | W30: 3.8 | X30: 2.6 | Y30: 0.4 | Z30: 0 | AA30: 0 | AB30: 3 | AC30: 2 | AD30: 0 | AE30: 0 | AF30: 0 | AG30: 2 | AH30: 8 | AI30: 0 | AJ30: 0 | AK30: 0 | AL30: 8 | AM30: .
A31: 2016 | B31: 1613 | C31: Berkeley Electric Coop Inc | D31: SC | E31: =IFERROR(SUM(AC31,AH31)*10^3/S31,"") -> 5098.7654 | F31: =IFERROR(SUM(AD31,AI31)*10^3/T31,"") | G31: =IFERROR(SUM(AE31,AJ31)*10^3/U31,"") | H31: =IFERROR(SUM(AF31,AK31)*10^3/V31,"") | I31: 18250 | J31: 0 | K31: 0 | L31: 0 | M31: 18250 | N31: 0 | O31: 0 | P31: 0 | Q31: 0 | R31: 0 | S31: 81 | T31: 0 | U31: 0 | V31: 0 | W31: 81 | X31: 16.2 | Y31: 0 | Z31: 0 | AA31: 0 | AB31: 16.2 | AC31: 154 | AD31: 0 | AE31: 0 | AF31: 0 | AG31: 154 | AH31: 259 | AI31: 0 | AJ31: 0 | AK31: 0 | AL31: 259 | AM31: .
A32: 2016 | B32: 1769 | C32: Black Hills Electric Coop, Inc | D32: SD | E32: =IFERROR(SUM(AC32,AH32)*10^3/S32,"") | F32: =IFERROR(SUM(AD32,AI32)*10^3/T32,"") | G32: =IFERROR(SUM(AE32,AJ32)*10^3/U32,"") | H32: =IFERROR(SUM(AF32,AK32)*10^3/V32,"") | I32: 183 | J32: 8 | K32: 0 | L32: 0 | M32: 191 | N32: 0 | O32: 0 | P32: 0 | Q32: 0 | R32: 0 | S32: 0 | T32: 0 | U32: 0 | V32: 0 | W32: 0 | X32: 0 | Y32: 0 | Z32: 0 | AA32: 0 | AB32: 0 | AC32: 0 | AD32: 0 | AE32: 0 | AF32: 0 | AG32: 0 | AH32: 0 | AI32: 0 | AJ32: 0 | AK32: 0 | AL32: 0 | AM32: .
A33: 2016 | B33: 1883 | C33: Blue Earth Light & Water | D33: MN | E33: =IFERROR(SUM(AC33,AH33)*10^3/S33,"") -> 9500 | F33: =IFERROR(SUM(AD33,AI33)*10^3/T33,"") | G33: =IFERROR(SUM(AE33,AJ33)*10^3/U33,"") | H33: =IFERROR(SUM(AF33,AK33)*10^3/V33,"") | I33: 508 | J33: 0 | K33: 0 | L33: 0 | M33: 508 | N33: 27 | O33: 0 | P33: 0 | Q33: 0 | R33: 27 | S33: 4 | T33: 0 | U33: 0 | V33: 0 | W33: 4 | X33: 1 | Y33: 0 | Z33: 0 | AA33: 0 | AB33: 1 | AC33: 38 | AD33: 0 | AE33: 0 | AF33: 0 | AG33: 38 | AH33: 0 | AI33: 0 | AJ33: 0 | AK33: 0 | AL33: 0 | AM33: .
A34: 2016 | B34: 2182 | C34: City of Breckenridge- (MN) | D34: MN | E34: =IFERROR(SUM(AC34,AH34)*10^3/S34,"") -> 8000 | F34: =IFERROR(SUM(AD34,AI34)*10^3/T34,"") -> 22000 | G34: =IFERROR(SUM(AE34,AJ34)*10^3/U34,"") | H34: =IFERROR(SUM(AF34,AK34)*10^3/V34,"") | I34: 652 | J34: 90 | K34: 0 | L34: 0 | M34: 742 | N34: 1 | O34: 1 | P34: 0 | Q34: 0 | R34: 2 | S34: 1 | T34: 1 | U34: 0 | V34: 0 | W34: 2 | X34: 1 | Y34: 1 | Z34: 0 | AA34: 0 | AB34: 2 | AC34: 8 | AD34: 22 | AE34: 0 | AF34: 0 | AG34: 30 | AH34: 0 | AI34: 0 | AJ34: 0 | AK34: 0 | AL34: 0 | AM34: .
A35: 2016 | B35: 2192 | C35: Bremen Electric Light & Power Co | D35: IN | E35: =IFERROR(SUM(AC35,AH35)*10^3/S35,"") | F35: =IFERROR(SUM(AD35,AI35)*10^3/T35,"") | G35: =IFERROR(SUM(AE35,AJ35)*10^3/U35,"") -> 10000 | H35: =IFERROR(SUM(AF35,AK35)*10^3/V35,"") | I35: 0 | J35: 0 | K35: 1 | L35: 0 | M35: 1 | N35: 0 | O35: 0 | P35: 0 | Q35: 0 | R35: 0 | S35: 0 | T35: 0 | U35: 4.2 | V35: 0 | W35: 4.2 | X35: 0 | Y35: 0 | Z35: 3.5 | AA35: 0 | AB35: 3.5 | AC35: 0 | AD35: 0 | AE35: 42 | AF35: 0 | AG35: 42 | AH35: 0 | AI35: 0 | AJ35: 0 | AK35: 0 | AL35: 0 | AM35: .
A36: 2016 | B36: 2599 | C36: Burt County Public Power Dist | D36: NE | E36: =IFERROR(SUM(AC36,AH36)*10^3/S36,"") | F36: =IFERROR(SUM(AD36,AI36)*10^3/T36,"") | G36: =IFERROR(SUM(AE36,AJ36)*10^3/U36,"") -> 266.66667 | H36: =IFERROR(SUM(AF36,AK36)*10^3/V36,"") | I36: 0 | J36: 0 | K36: 359 | L36: 0 | M36: 359 | N36: 0 | O36: 0 | P36: 215 | Q36: 0 | R36: 215 | S36: 0 | T36: 0 | U36: 15 | V36: 0 | W36: 15 | X36: 0 | Y36: 0 | Z36: 3 | AA36: 0 | AB36: 3 | AC36: 0 | AD36: 0 | AE36: 0 | AF36: 0 | AG36: 0 | AH36: 0 | AI36: 0 | AJ36: 4 | AK36: 0 | AL36: 4 | AM36: .
A37: 2016 | B37: 2641 | C37: Butler Rural El Coop Assn, Inc - (KS) | D37: KS | E37: =IFERROR(SUM(AC37,AH37)*10^3/S37,"") -> 0 | F37: =IFERROR(SUM(AD37,AI37)*10^3/T37,"") -> 0 | G37: =IFERROR(SUM(AE37,AJ37)*10^3/U37,"") -> 0 | H37: =IFERROR(SUM(AF37,AK37)*10^3/V37,"") | I37: 6585 | J37: 776 | K37: 4 | L37: 0 | M37: 7365 | N37: 0 | O37: 0 | P37: 0 | Q37: 0 | R37: 0 | S37: 2.6 | T37: 0.4 | U37: 1 | V37: 0 | W37: 4 | X37: 1.8 | Y37: 0.2 | Z37: 0.5 | AA37: 0 | AB37: 2.5 | AC37: 0 | AD37: 0 | AE37: 0 | AF37: 0 | AG37: 0 | AH37: 0 | AI37: 0 | AJ37: 0 | AK37: 0 | AL37: 0 | AM37: .
A38: 2016 | B38: 2643 | C38: Butler Public Power District - (NE) | D38: NE | E38: =IFERROR(SUM(AC38,AH38)*10^3/S38,"") | F38: =IFERROR(SUM(AD38,AI38)*10^3/T38,"") | G38: =IFERROR(SUM(AE38,AJ38)*10^3/U38,"") -> 224.7191 | H38: =IFERROR(SUM(AF38,AK38)*10^3/V38,"") | I38: 0 | J38: 0 | K38: 741 | L38: 0 | M38: 741 | N38: 0 | O38: 0 | P38: 993 | Q38: 0 | R38: 993 | S38: 0 | T38: 0 | U38: 17.8 | V38: 0 | W38: 17.8 | X38: 0 | Y38: 0 | Z38: 8.3 | AA38: 0 | AB38: 8.3 | AC38: 0 | AD38: 0 | AE38: 0 | AF38: 0 | AG38: 0 | AH38: 0 | AI38: 0 | AJ38: 4 | AK38: 0 | AL38: 4 | AM38: .
A39: 2016 | B39: 2655 | C39: Butte Electric Coop, Inc | D39: SD | E39: =IFERROR(SUM(AC39,AH39)*10^3/S39,"") -> 1375 | F39: =IFERROR(SUM(AD39,AI39)*10^3/T39,"") | G39: =IFERROR(SUM(AE39,AJ39)*10^3/U39,"") | H39: =IFERROR(SUM(AF39,AK39)*10^3/V39,"") | I39: 1438 | J39: 0 | K39: 0 | L39: 0 | M39: 1438 | N39: 948 | O39: 0 | P39: 0 | Q39: 0 | R39: 948 | S39: 8 | T39: 0 | U39: 0 | V39: 0 | W39: 8 | X39: 3 | Y39: 0 | Z39: 0 | AA39: 0 | AB39: 3 | AC39: 3 | AD39: 0 | AE39: 0 | AF39: 0 | AG39: 3 | AH39: 8 | AI39: 0 | AJ39: 0 | AK39: 0 | AL39: 8 | AM39: 1438
A40: 2016 | B40: 2678 | C40: C & L Electric Coop Corp | D40: AR | E40: =IFERROR(SUM(AC40,AH40)*10^3/S40,"") | F40: =IFERROR(SUM(AD40,AI40)*10^3/T40,"") -> 17000 | G40: =IFERROR(SUM(AE40,AJ40)*10^3/U40,"") | H40: =IFERROR(SUM(AF40,AK40)*10^3/V40,"") | I40: 0 | J40: 83 | K40: 0 | L40: 0 | M40: 83 | N40: 0 | O40: 0 | P40: 0 | Q40: 0 | R40: 0 | S40: 0 | T40: 2 | U40: 0 | V40: 0 | W40: 2 | X40: 0 | Y40: 1 | Z40: 0 | AA40: 0 | AB40: 1 | AC40: 0 | AD40: 32 | AE40: 0 | AF40: 0 | AG40: 32 | AH40: 0 | AI40: 2 | AJ40: 0 | AK40: 0 | AL40: 2 | AM40: .
A41: 2016 | B41: 2985 | C41: Capital Electric Coop, Inc | D41: ND | E41: =IFERROR(SUM(AC41,AH41)*10^3/S41,"") -> 268750 | F41: =IFERROR(SUM(AD41,AI41)*10^3/T41,"") | G41: =IFERROR(SUM(AE41,AJ41)*10^3/U41,"") -> 48750 | H41: =IFERROR(SUM(AF41,AK41)*10^3/V41,"") | I41: 836 | J41: 10 | K41: 21 | L41: 0 | M41: 867 | N41: 0 | O41: 0 | P41: 0 | Q41: 0 | R41: 0 | S41: 0.8 | T41: 0 | U41: 1.6 | V41: 0 | W41: 2.4 | X41: 0.7 | Y41: 0 | Z41: 1.6 | AA41: 0 | AB41: 2.3 | AC41: 44 | AD41: 1 | AE41: 74 | AF41: 0 | AG41: 119 | AH41: 171 | AI41: 2 | AJ41: 4 | AK41: 0 | AL41: 177 | AM41: .
A42: 2016 | B42: 3046 | C42: Duke Energy Progress - (NC) | D42: NC | E42: =IFERROR(SUM(AC42,AH42)*10^3/S42,"") -> 957961.17 | F42: =IFERROR(SUM(AD42,AI42)*10^3/T42,"") -> 60625 | G42: =IFERROR(SUM(AE42,AJ42)*10^3/U42,"") -> 0 | H42: =IFERROR(SUM(AF42,AK42)*10^3/V42,"") | I42: 7252 | J42: 50 | K42: 52 | L42: 0 | M42: 7354 | N42: 0 | O42: 0 | P42: 0 | Q42: 0 | R42: 0 | S42: 10.3 | T42: 19.2 | U42: 140.6 | V42: 0 | W42: 170.1 | X42: 0 | Y42: 0 | Z42: 0 | AA42: 0 | AB42: 0 | AC42: 3096 | AD42: 767 | AE42: 0 | AF42: 0 | AG42: 3863 | AH42: 6771 | AI42: 397 | AJ42: 0 | AK42: 0 | AL42: 7168 | AM42: .
A43: 2016 | B43: 3046 | C43: Duke Energy Progress - (NC) | D43: SC | E43: =IFERROR(SUM(AC43,AH43)*10^3/S43,"") | F43: =IFERROR(SUM(AD43,AI43)*10^3/T43,"") -> 1015000 | G43: =IFERROR(SUM(AE43,AJ43)*10^3/U43,"") -> 0 | H43: =IFERROR(SUM(AF43,AK43)*10^3/V43,"") | I43: 0 | J43: 1 | K43: 20 | L43: 0 | M43: 21 | N43: 0 | O43: 0 | P43: 0 | Q43: 0 | R43: 0 | S43: 0 | T43: 0.2 | U43: 90.7 | V43: 0 | W43: 90.9 | X43: 0 | Y43: 0 | Z43: 0 | AA43: 0 | AB43: 0 | AC43: 540 | AD43: 134 | AE43: 0 | AF43: 0 | AG43: 674 | AH43: 1181 | AI43: 69 | AJ43: 0 | AK43: 0 | AL43: 1250 | AM43: .
A44: 2016 | B44: 3081 | C44: Carroll Electric Member Corp - (GA) | D44: GA | E44: =IFERROR(SUM(AC44,AH44)*10^3/S44,"") -> 78571.429 | F44: =IFERROR(SUM(AD44,AI44)*10^3/T44,"") | G44: =IFERROR(SUM(AE44,AJ44)*10^3/U44,"") -> 63000 | H44: =IFERROR(SUM(AF44,AK44)*10^3/V44,"") | I44: 4466 | J44: 0 | K44: 29 | L44: 0 | M44: 4495 | N44: 18 | O44: 0 | P44: 324 | Q44: 0 | R44: 342 | S44: 0.7 | T44: 0 | U44: 12 | V44: 0 | W44: 12.7 | X44: 0.7 | Y44: 0 | Z44: 12 | AA44: 0 | AB44: 12.7 | AC44: 55 | AD44: 0 | AE44: 756 | AF44: 0 | AG44: 811 | AH44: 0 | AI44: 0 | AJ44: 0 | AK44: 0 | AL44: 0 | AM44: .
A45: 2016 | B45: 3203 | C45: Cedar Falls Utilities | D45: IA | E45: =IFERROR(SUM(AC45,AH45)*10^3/S45,"") | F45: =IFERROR(SUM(AD45,AI45)*10^3/T45,"") | G45: =IFERROR(SUM(AE45,AJ45)*10^3/U45,"") | H45: =IFERROR(SUM(AF45,AK45)*10^3/V45,"") | I45: 485 | J45: 1 | K45: 0 | L45: 0 | M45: 486 | N45: 9 | O45: 7 | P45: 0 | Q45: 0 | R45: 16 | S45: 0 | T45: 0 | U45: 0 | V45: 0 | W45: 0 | X45: 0 | Y45: 0 | Z45: 0 | AA45: 0 | AB45: 0 | AC45: 0 | AD45: 1 | AE45: 0 | AF45: 0 | AG45: 1 | AH45: 6 | AI45: 1 | AJ45: 0 | AK45: 0 | AL45: 7 | AM45: .
A46: 2016 | B46: 3205 | C46: Cedar-Knox Public Power Dist | D46: NE | E46: =IFERROR(SUM(AC46,AH46)*10^3/S46,"") | F46: =IFERROR(SUM(AD46,AI46)*10^3/T46,"") | G46: =IFERROR(SUM(AE46,AJ46)*10^3/U46,"") | H46: =IFERROR(SUM(AF46,AK46)*10^3/V46,"") | I46: 148 | J46: 86 | K46: 0 | L46: 0 | M46: 234 | N46: 2855 | O46: 3271 | P46: 0 | Q46: 0 | R46: 6126 | S46: 0 | T46: 0 | U46: 0 | V46: 0 | W46: 0 | X46: 0 | Y46: 0 | Z46: 0 | AA46: 0 | AB46: 0 | AC46: 15 | AD46: 4 | AE46: 0 | AF46: 0 | AG46: 19 | AH46: 7 | AI46: 7 | AJ46: 0 | AK46: 0 | AL46: 14 | AM46: .
A47: 2016 | B47: 3222 | C47: Central Alabama Electric Coop | D47: AL | E47: =IFERROR(SUM(AC47,AH47)*10^3/S47,"") -> 7272.7273 | F47: =IFERROR(SUM(AD47,AI47)*10^3/T47,"") | G47: =IFERROR(SUM(AE47,AJ47)*10^3/U47,"") | H47: =IFERROR(SUM(AF47,AK47)*10^3/V47,"") | I47: 534 | J47: 0 | K47: 0 | L47: 0 | M47: 534 | N47: 6 | O47: 0 | P47: 0 | Q47: 0 | R47: 6 | S47: 5.5 | T47: 0 | U47: 0 | V47: 0 | W47: 5.5 | X47: 4.9 | Y47: 0 | Z47: 0 | AA47: 0 | AB47: 4.9 | AC47: 0 | AD47: 0 | AE47: 0 | AF47: 0 | AG47: 0 | AH47: 40 | AI47: 0 | AJ47: 0 | AK47: 0 | AL47: 40 | AM47: .
A48: 2016 | B48: 3248 | C48: Central Georgia El Member Corp | D48: GA | E48: =IFERROR(SUM(AC48,AH48)*10^3/S48,"") -> 26200 | F48: =IFERROR(SUM(AD48,AI48)*10^3/T48,"") | G48: =IFERROR(SUM(AE48,AJ48)*10^3/U48,"") | H48: =IFERROR(SUM(AF48,AK48)*10^3/V48,"") | I48: 4272 | J48: 0 | K48: 0 | L48: 0 | M48: 4272 | N48: 210 | O48: 0 | P48: 0 | Q48: 0 | R48: 210 | S48: 5 | T48: 0 | U48: 0 | V48: 0 | W48: 5 | X48: 3 | Y48: 0 | Z48: 0 | AA48: 0 | AB48: 3 | AC48: 89 | AD48: 0 | AE48: 0 | AF48: 0 | AG48: 89 | AH48: 42 | AI48: 0 | AJ48: 0 | AK48: 0 | AL48: 42 | AM48: 10
A49: 2016 | B49: 3249 | C49: Central Hudson Gas & Elec Corp | D49: NY | E49: =IFERROR(SUM(AC49,AH49)*10^3/S49,"") -> 0 | F49: =IFERROR(SUM(AD49,AI49)*10^3/T49,"") -> 0 | G49: =IFERROR(SUM(AE49,AJ49)*10^3/U49,"") -> 0 | H49: =IFERROR(SUM(AF49,AK49)*10^3/V49,"") | I49: 1395 | J49: 160 | K49: 18 | L49: 0 | M49: 1573 | N49: 9 | O49: 1 | P49: 130 | Q49: 0 | R49: 140 | S49: 1.9 | T49: 0.2 | U49: 7.7 | V49: 0 | W49: 9.8 | X49: 1.2 | Y49: 0.1 | Z49: 7.7 | AA49: 0 | AB49: 9 | AC49: 0 | AD49: 0 | AE49: 0 | AF49: 0 | AG49: 0 | AH49: 0 | AI49: 0 | AJ49: 0 | AK49: 0 | AL49: 0 | AM49: .
A50: 2016 | B50: 3258 | C50: Central Iowa Power Cooperative | D50: IA | E50: =IFERROR(SUM(AC50,AH50)*10^3/S50,"") | F50: =IFERROR(SUM(AD50,AI50)*10^3/T50,"") -> 0 | G50: =IFERROR(SUM(AE50,AJ50)*10^3/U50,"") -> 0 | H50: =IFERROR(SUM(AF50,AK50)*10^3/V50,"") | I50: 0 | J50: 7 | K50: 10 | L50: 0 | M50: 17 | N50: 0 | O50: 0 | P50: 0 | Q50: 0 | R50: 0 | S50: 0 | T50: 5 | U50: 4.6 | V50: 0 | W50: 9.6 | X50: 0 | Y50: 0 | Z50: 0 | AA50: 0 | AB50: 0 | AC50: 0 | AD50: 0 | AE50: 0 | AF50: 0 | AG50: 0 | AH50: 0 | AI50: 0 | AJ50: 0 | AK50: 0 | AL50: 0 | AM50: .
A51: 2016 | B51: 3278 | C51: AEP Texas Central Company | D51: TX | E51: =IFERROR(SUM(AC51,AH51)*10^3/S51,"") | F51: =IFERROR(SUM(AD51,AI51)*10^3/T51,"") -> 0 | G51: =IFERROR(SUM(AE51,AJ51)*10^3/U51,"") | H51: =IFERROR(SUM(AF51,AK51)*10^3/V51,"") | I51: 0 | J51: 42 | K51: 0 | L51: 0 | M51: 42 | N51: 0 | O51: 0 | P51: 0 | Q51: 0 | R51: 0 | S51: 0 | T51: 17.6 | U51: 0 | V51: 0 | W51: 17.6 | X51: 0 | Y51: 10.7 | Z51: 0 | AA51: 0 | AB51: 10.7 | AC51: 0 | AD51: 0 | AE51: 0 | AF51: 0 | AG51: 0 | AH51: 0 | AI51: 0 | AJ51: 0 | AK51: 0 | AL51: 0 | AM51: .
A52: 2016 | B52: 3279 | C52: Central Power Elec Coop, Inc | D52: ND | E52: =IFERROR(SUM(AC52,AH52)*10^3/S52,"") -> 18955.224 | F52: =IFERROR(SUM(AD52,AI52)*10^3/T52,"") -> 30526.316 | G52: =IFERROR(SUM(AE52,AJ52)*10^3/U52,"") | H52: =IFERROR(SUM(AF52,AK52)*10^3/V52,"") | I52: 0 | J52: 0 | K52: 0 | L52: 0 | M52: 0 | N52: 1400 | O52: 2329 | P52: 0 | Q52: 0 | R52: 3729 | S52: 6.7 | T52: 5.7 | U52: 0 | V52: 0 | W52: 12.4 | X52: 6.7 | Y52: 5.7 | Z52: 0 | AA52: 0 | AB52: 12.4 | AC52: 0 | AD52: 0 | AE52: 0 | AF52: 0 | AG52: 0 | AH52: 127 | AI52: 174 | AJ52: 14 | AK52: 0 | AL52: 315 | AM52: .
A53: 2016 | B53: 3293 | C53: Central Wisconsin Elec Coop | D53: WI | E53: =IFERROR(SUM(AC53,AH53)*10^3/S53,"") -> 58500 | F53: =IFERROR(SUM(AD53,AI53)*10^3/T53,"") -> 41800 | G53: =IFERROR(SUM(AE53,AJ53)*10^3/U53,"") | H53: =IFERROR(SUM(AF53,AK53)*10^3/V53,"") | I53: 1699 | J53: 132 | K53: 0 | L53: 0 | M53: 1831 | N53: 400 | O53: 300 | P53: 0 | Q53: 0 | R53: 700 | S53: 4 | T53: 5 | U53: 0 | V53: 0 | W53: 9 | X53: 2 | Y53: 2 | Z53: 0 | AA53: 0 | AB53: 4 | AC53: 234 | AD53: 209 | AE53: 0 | AF53: 0 | AG53: 443 | AH53: 0 | AI53: 0 | AJ53: 0 | AK53: 0 | AL53: 0 | AM53: .
A54: 2016 | B54: 3329 | C54: Borough of Chambersburg | D54: PA | E54: =IFERROR(SUM(AC54,AH54)*10^3/S54,"") | F54: =IFERROR(SUM(AD54,AI54)*10^3/T54,"") | G54: =IFERROR(SUM(AE54,AJ54)*10^3/U54,"") -> 4690000 | H54: =IFERROR(SUM(AF54,AK54)*10^3/V54,"") | I54: 0 | J54: 0 | K54: 5 | L54: 0 | M54: 5 | N54: 0 | O54: 0 | P54: 0 | Q54: 0 | R54: 0 | S54: 0 | T54: 0 | U54: 0.3 | V54: 0 | W54: 0.3 | X54: 0 | Y54: 0 | Z54: 0.3 | AA54: 0 | AB54: 0.3 | AC54: 0 | AD54: 0 | AE54: 0 | AF54: 0 | AG54: 0 | AH54: 0 | AI54: 0 | AJ54: 1407 | AK54: 0 | AL54: 1407 | AM54: .
A55: 2016 | B55: 3478 | C55: Cimarron Electric Coop | D55: OK | E55: =IFERROR(SUM(AC55,AH55)*10^3/S55,"") | F55: =IFERROR(SUM(AD55,AI55)*10^3/T55,"") -> 1000000 | G55: =IFERROR(SUM(AE55,AJ55)*10^3/U55,"") | H55: =IFERROR(SUM(AF55,AK55)*10^3/V55,"") | I55: 0 | J55: 300 | K55: 0 | L55: 0 | M55: 300 | N55: 0 | O55: 1 | P55: 0 | Q55: 0 | R55: 1 | S55: 0 | T55: 0.5 | U55: 0 | V55: 0 | W55: 0.5 | X55: 0 | Y55: 0.1 | Z55: 0 | AA55: 0 | AB55: 0.1 | AC55: 0 | AD55: 0 | AE55: 0 | AF55: 0 | AG55: 0 | AH55: 0 | AI55: 500 | AJ55: 0 | AK55: 0 | AL55: 500 | AM55: .
A56: 2016 | B56: 3498 | C56: Chippewa Valley Electric Coop | D56: WI | E56: =IFERROR(SUM(AC56,AH56)*10^3/S56,"") -> 61250 | F56: =IFERROR(SUM(AD56,AI56)*10^3/T56,"") | G56: =IFERROR(SUM(AE56,AJ56)*10^3/U56,"") | H56: =IFERROR(SUM(AF56,AK56)*10^3/V56,"") | I56: 3846 | J56: 51 | K56: 0 | L56: 0 | M56: 3897 | N56: 0 | O56: 0 | P56: 0 | Q56: 0 | R56: 0 | S56: 8 | T56: 0 | U56: 0 | V56: 0 | W56: 8 | X56: 4 | Y56: 0 | Z56: 0 | AA56: 0 | AB56: 4 | AC56: 437 | AD56: 1 | AE56: 0 | AF56: 0 | AG56: 438 | AH56: 53 | AI56: 0 | AJ56: 0 | AK56: 0 | AL56: 53 | AM56: 8
A57: 2016 | B57: 3502 | C57: Choctawhatche Elec Coop, Inc | D57: FL | E57: =IFERROR(SUM(AC57,AH57)*10^3/S57,"") -> 1375 | F57: =IFERROR(SUM(AD57,AI57)*10^3/T57,"") -> 100 | G57: =IFERROR(SUM(AE57,AJ57)*10^3/U57,"") | H57: =IFERROR(SUM(AF57,AK57)*10^3/V57,"") | I57: 42629 | J57: 6044 | K57: 0 | L57: 0 | M57: 48673 | N57: 0 | O57: 0 | P57: 0 | Q57: 0 | R57: 0 | S57: 32 | T57: 10 | U57: 0 | V57: 0 | W57: 42 | X57: 32 | Y57: 10 | Z57: 0 | AA57: 0 | AB57: 42 | AC57: 39 | AD57: 0 | AE57: 0 | AF57: 0 | AG57: 39 | AH57: 5 | AI57: 1 | AJ57: 0 | AK57: 0 | AL57: 6 | AM57: 553
A58: 2016 | B58: 3503 | C58: Choptank Electric Coop, Inc | D58: MD | E58: =IFERROR(SUM(AC58,AH58)*10^3/S58,"") | F58: =IFERROR(SUM(AD58,AI58)*10^3/T58,"") -> 162.16216 | G58: =IFERROR(SUM(AE58,AJ58)*10^3/U58,"") -> 0 | H58: =IFERROR(SUM(AF58,AK58)*10^3/V58,"") | I58: 0 | J58: 235 | K58: 9 | L58: 0 | M58: 244 | N58: 0 | O58: 0 | P58: 0 | Q58: 0 | R58: 0 | S58: 0 | T58: 55.5 | U58: 50.7 | V58: 0 | W58: 106.2 | X58: 0 | Y58: 34.6 | Z58: 38.5 | AA58: 0 | AB58: 73.1 | AC58: 0 | AD58: 0 | AE58: 0 | AF58: 0 | AG58: 0 | AH58: 0 | AI58: 9 | AJ58: 0 | AK58: 0 | AL58: 9 | AM58: 0
A59: 2016 | B59: 3542 | C59: Duke Energy Ohio Inc | D59: OH | E59: =IFERROR(SUM(AC59,AH59)*10^3/S59,"") -> 15752.212 | F59: =IFERROR(SUM(AD59,AI59)*10^3/T59,"") -> 112334.63 | G59: =IFERROR(SUM(AE59,AJ59)*10^3/U59,"") -> 0 | H59: =IFERROR(SUM(AF59,AK59)*10^3/V59,"") | I59: 45509 | J59: 21 | K59: 19 | L59: 0 | M59: 45549 | N59: 0 | O59: 0 | P59: 0 | Q59: 0 | R59: 0 | S59: 67.8 | T59: 25.7 | U59: 32.8 | V59: 0 | W59: 126.3 | X59: 0 | Y59: 0 | Z59: 0 | AA59: 0 | AB59: 0 | AC59: 490 | AD59: 2887 | AE59: 0 | AF59: 0 | AG59: 3377 | AH59: 578 | AI59: 0 | AJ59: 0 | AK59: 0 | AL59: 578 | AM59: .
A60: 2016 | B60: 3701 | C60: Clark Electric Coop - (WI) | D60: WI | E60: =IFERROR(SUM(AC60,AH60)*10^3/S60,"") -> 89000 | F60: =IFERROR(SUM(AD60,AI60)*10^3/T60,"") -> 85333.333 | G60: =IFERROR(SUM(AE60,AJ60)*10^3/U60,"") | H60: =IFERROR(SUM(AF60,AK60)*10^3/V60,"") | I60: 2337 | J60: 426 | K60: 0 | L60: 0 | M60: 2763 | N60: 0 | O60: 0 | P60: 0 | Q60: 0 | R60: 0 | S60: 1 | T60: 1.5 | U60: 0 | V60: 0 | W60: 2.5 | X60: 0.9 | Y60: 1.5 | Z60: 0 | AA60: 0 | AB60: 2.4 | AC60: 78 | AD60: 120 | AE60: 0 | AF60: 0 | AG60: 198 | AH60: 11 | AI60: 8 | AJ60: 0 | AK60: 0 | AL60: 19 | AM60: .
A61: 2016 | B61: 3755 | C61: Cleveland Electric Illum Co | D61: OH | E61: =IFERROR(SUM(AC61,AH61)*10^3/S61,"") -> 118666.67 | F61: =IFERROR(SUM(AD61,AI61)*10^3/T61,"") | G61: =IFERROR(SUM(AE61,AJ61)*10^3/U61,"") -> 47.443332 | H61: =IFERROR(SUM(AF61,AK61)*10^3/V61,"") | I61: 7090 | J61: 0 | K61: 4 | L61: 0 | M61: 7094 | N61: 36 | O61: 0 | P61: 0 | Q61: 0 | R61: 36 | S61: 4.5 | T61: 0 | U61: 189.7 | V61: 0 | W61: 194.2 | X61: 4.4 | Y61: 0 | Z61: 0 | AA61: 0 | AB61: 4.4 | AC61: 78 | AD61: 0 | AE61: 9 | AF61: 0 | AG61: 87 | AH61: 456 | AI61: 0 | AJ61: 0 | AK61: 0 | AL61: 456 | AM61: 0
A62: 2016 | B62: 3757 | C62: Clay Electric Cooperative, Inc | D62: FL | E62: =IFERROR(SUM(AC62,AH62)*10^3/S62,"") | F62: =IFERROR(SUM(AD62,AI62)*10^3/T62,"") | G62: =IFERROR(SUM(AE62,AJ62)*10^3/U62,"") | H62: =IFERROR(SUM(AF62,AK62)*10^3/V62,"") | I62: 0 | J62: 4 | K62: 0 | L62: 0 | M62: 4 | N62: 0 | O62: 0 | P62: 0 | Q62: 0 | R62: 0 | S62: 0 | T62: 0 | U62: 0 | V62: 0 | W62: 0 | X62: 0 | Y62: 0 | Z62: 0 | AA62: 0 | AB62: 0 | AC62: 0 | AD62: 0 | AE62: 0 | AF62: 0 | AG62: 0 | AH62: 0 | AI62: 0 | AJ62: 0 | AK62: 0 | AL62: 0 | AM62: .
A63: 2016 | B63: 3764 | C63: Clearwater-Polk Elec Coop Inc | D63: MN | E63: =IFERROR(SUM(AC63,AH63)*10^3/S63,"") -> 25000 | F63: =IFERROR(SUM(AD63,AI63)*10^3/T63,"") -> 0 | G63: =IFERROR(SUM(AE63,AJ63)*10^3/U63,"") | H63: =IFERROR(SUM(AF63,AK63)*10^3/V63,"") | I63: 1768 | J63: 6 | K63: 0 | L63: 0 | M63: 1774 | N63: 242 | O63: 13 | P63: 0 | Q63: 0 | R63: 255 | S63: 33 | T63: 0.5 | U63: 0 | V63: 0 | W63: 33.5 | X63: 8.9 | Y63: 0.5 | Z63: 0 | AA63: 0 | AB63: 9.4 | AC63: 814 | AD63: 0 | AE63: 0 | AF63: 0 | AG63: 814 | AH63: 11 | AI63: 0 | AJ63: 0 | AK63: 0 | AL63: 11 | AM63: 0
A64: 2016 | B64: 3844 | C64: Coastal Electric Coop, Inc | D64: SC | E64: =IFERROR(SUM(AC64,AH64)*10^3/S64,"") -> 8571.4286 | F64: =IFERROR(SUM(AD64,AI64)*10^3/T64,"") | G64: =IFERROR(SUM(AE64,AJ64)*10^3/U64,"") | H64: =IFERROR(SUM(AF64,AK64)*10^3/V64,"") | I64: 815 | J64: 0 | K64: 0 | L64: 0 | M64: 815 | N64: 8 | O64: 0 | P64: 0 | Q64: 0 | R64: 8 | S64: 0.7 | T64: 0 | U64: 0 | V64: 0 | W64: 0.7 | X64: 0.7 | Y64: 0 | Z64: 0 | AA64: 0 | AB64: 0.7 | AC64: 0 | AD64: 0 | AE64: 0 | AF64: 0 | AG64: 0 | AH64: 6 | AI64: 0 | AJ64: 0 | AK64: 0 | AL64: 6 | AM64: 10
A65: 2016 | B65: 3931 | C65: Coles-Moultrie Electric Coop | D65: IL | E65: =IFERROR(SUM(AC65,AH65)*10^3/S65,"") -> 0 | F65: =IFERROR(SUM(AD65,AI65)*10^3/T65,"") -> 0 | G65: =IFERROR(SUM(AE65,AJ65)*10^3/U65,"") -> 0 | H65: =IFERROR(SUM(AF65,AK65)*10^3/V65,"") | I65: 4593 | J65: 103 | K65: 8 | L65: 0 | M65: 4704 | N65: 0 | O65: 0 | P65: 0 | Q65: 0 | R65: 0 | S65: 0.5 | T65: 0.5 | U65: 0.5 | V65: 0 | W65: 1.5 | X65: 0 | Y65: 0 | Z65: 0 | AA65: 0 | AB65: 0 | AC65: 0 | AD65: 0 | AE65: 0 | AF65: 0 | AG65: 0 | AH65: 0 | AI65: 0 | AJ65: 0 | AK65: 0 | AL65: 0 | AM65: .
A66: 2016 | B66: 3989 | C66: City of Colorado Springs - (CO) | D66: CO | E66: =IFERROR(SUM(AC66,AH66)*10^3/S66,"") -> 395714.29 | F66: =IFERROR(SUM(AD66,AI66)*10^3/T66,"") | G66: =IFERROR(SUM(AE66,AJ66)*10^3/U66,"") | H66: =IFERROR(SUM(AF66,AK66)*10^3/V66,"") | I66: 1205 | J66: 0 | K66: 0 | L66: 0 | M66: 1205 | N66: 0 | O66: 0 | P66: 0 | Q66: 0 | R66: 0 | S66: 0.7 | T66: 0 | U66: 0 | V66: 0 | W66: 0.7 | X66: 0.2 | Y66: 0 | Z66: 0 | AA66: 0 | AB66: 0.2 | AC66: 11 | AD66: 0 | AE66: 0 | AF66: 0 | AG66: 11 | AH66: 266 | AI66: 0 | AJ66: 0 | AK66: 0 | AL66: 266 | AM66: .
A67: 2016 | B67: 4045 | C67: City of Columbia - (MO) | D67: MO | E67: =IFERROR(SUM(AC67,AH67)*10^3/S67,"") -> 8125 | F67: =IFERROR(SUM(AD67,AI67)*10^3/T67,"") -> 12000 | G67: =IFERROR(SUM(AE67,AJ67)*10^3/U67,"") -> 0 | H67: =IFERROR(SUM(AF67,AK67)*10^3/V67,"") | I67: 14387 | J67: 734 | K67: 11 | L67: 0 | M67: 15132 | N67: 0 | O67: 0 | P67: 0 | Q67: 0 | R67: 0 | S67: 24 | T67: 4 | U67: 3.4 | V67: 0 | W67: 31.4 | X67: 0 | Y67: 0 | Z67: 0 | AA67: 0 | AB67: 0 | AC67: 195 | AD67: 48 | AE67: 0 | AF67: 0 | AG67: 243 | AH67: 0 | AI67: 0 | AJ67: 0 | AK67: 0 | AL67: 0 | AM67: .
A68: 2016 | B68: 4065 | C68: City of Columbus - (OH) | D68: OH | E68: =IFERROR(SUM(AC68,AH68)*10^3/S68,"") | F68: =IFERROR(SUM(AD68,AI68)*10^3/T68,"") -> 0 | G68: =IFERROR(SUM(AE68,AJ68)*10^3/U68,"") -> 0 | H68: =IFERROR(SUM(AF68,AK68)*10^3/V68,"") | I68: 0 | J68: 3 | K68: 14 | L68: 0 | M68: 17 | N68: 0 | O68: 0 | P68: 0 | Q68: 0 | R68: 0 | S68: 0 | T68: 0.6 | U68: 12.3 | V68: 0 | W68: 12.9 | X68: 0 | Y68: 0 | Z68: 0 | AA68: 0 | AB68: 0 | AC68: 0 | AD68: 0 | AE68: 0 | AF68: 0 | AG68: 0 | AH68: 0 | AI68: 0 | AJ68: 0 | AK68: 0 | AL68: 0 | AM68: .
A69: 2016 | B69: 4110 | C69: Commonwealth Edison Co | D69: IL | E69: =IFERROR(SUM(AC69,AH69)*10^3/S69,"") -> 55887.612 | F69: =IFERROR(SUM(AD69,AI69)*10^3/T69,"") -> 155.68862 | G69: =IFERROR(SUM(AE69,AJ69)*10^3/U69,"") -> 65.138721 | H69: =IFERROR(SUM(AF69,AK69)*10^3/V69,"") | I69: 78300 | J69: 1740 | K69: 1460 | L69: 0 | M69: 81500 | N69: 157 | O69: 0 | P69: 0 | Q69: 0 | R69: 157 | S69: 78.3 | T69: 334 | U69: 829 | V69: 0 | W69: 1241.3 | X69: 78.3 | Y69: 0 | Z69: 0 | AA69: 0 | AB69: 78.3 | AC69: 2576 | AD69: 0 | AE69: 0 | AF69: 0 | AG69: 2576 | AH69: 1800 | AI69: 52 | AJ69: 54 | AK69: 0 | AL69: 1906 | AM69: .
A70: 2016 | B70: 4117 | C70: Community Electric Coop | D70: VA | E70: =IFERROR(SUM(AC70,AH70)*10^3/S70,"") -> 28333.333 | F70: =IFERROR(SUM(AD70,AI70)*10^3/T70,"") | G70: =IFERROR(SUM(AE70,AJ70)*10^3/U70,"") -> 26666.667 | H70: =IFERROR(SUM(AF70,AK70)*10^3/V70,"") | I70: 1571 | J70: 0 | K70: 3 | L70: 0 | M70: 1574 | N70: 0 | O70: 0 | P70: 0 | Q70: 0 | R70: 0 | S70: 1.8 | T70: 0 | U70: 3 | V70: 0 | W70: 4.8 | X70: 1 | Y70: 0 | Z70: 3 | AA70: 0 | AB70: 4 | AC70: 38 | AD70: 0 | AE70: 78 | AF70: 0 | AG70: 116 | AH70: 13 | AI70: 0 | AJ70: 2 | AK70: 0 | AL70: 15 | AM70: 0
A71: 2016 | B71: 4147 | C71: Town of Concord - (MA) | D71: MA | E71: =IFERROR(SUM(AC71,AH71)*10^3/S71,"") -> 294.11765 | F71: =IFERROR(SUM(AD71,AI71)*10^3/T71,"") -> 0 | G71: =IFERROR(SUM(AE71,AJ71)*10^3/U71,"") | H71: =IFERROR(SUM(AF71,AK71)*10^3/V71,"") | I71: 490 | J71: 6 | K71: 0 | L71: 0 | M71: 496 | N71: 0 | O71: 0 | P71: 0 | Q71: 0 | R71: 0 | S71: 6.8 | T71: 1 | U71: 0 | V71: 0 | W71: 7.8 | X71: 6.8 | Y71: 1 | Z71: 0 | AA71: 0 | AB71: 7.8 | AC71: 2 | AD71: 0 | AE71: 0 | AF71: 0 | AG71: 2 | AH71: 0 | AI71: 0 | AJ71: 0 | AK71: 0 | AL71: 0 | AM71: 5
A72: 2016 | B72: 4176 | C72: Connecticut Light & Power Co | D72: CT | E72: =IFERROR(SUM(AC72,AH72)*10^3/S72,"") | F72: =IFERROR(SUM(AD72,AI72)*10^3/T72,"") -> 42233.01 | G72: =IFERROR(SUM(AE72,AJ72)*10^3/U72,"") -> 16159.218 | H72: =IFERROR(SUM(AF72,AK72)*10^3/V72,"") | I72: 0 | J72: 66 | K72: 47 | L72: 0 | M72: 113 | N72: 0 | O72: 0 | P72: 0 | Q72: 0 | R72: 0 | S72: 0 | T72: 30.9 | U72: 71.6 | V72: 0 | W72: 102.5 | X72: 0 | Y72: 19.1 | Z72: 17 | AA72: 0 | AB72: 36.1 | AC72: 0 | AD72: 792 | AE72: 702 | AF72: 0 | AG72: 1494 | AH72: 859 | AI72: 513 | AJ72: 455 | AK72: 0 | AL72: 1827 | AM72: 0
A73: 2016 | B73: 4226 | C73: Consolidated Edison Co-NY Inc | D73: NY | E73: =IFERROR(SUM(AC73,AH73)*10^3/S73,"") -> 295285.71 | F73: =IFERROR(SUM(AD73,AI73)*10^3/T73,"") -> 229846.15 | G73: =IFERROR(SUM(AE73,AJ73)*10^3/U73,"") | H73: =IFERROR(SUM(AF73,AK73)*10^3/V73,"") | I73: 25920 | J73: 1078 | K73: 0 | L73: 0 | M73: 26998 | N73: 603 | O73: 2622 | P73: 0 | Q73: 0 | R73: 3225 | S73: 35 | T73: 195 | U73: 0 | V73: 0 | W73: 230 | X73: 25 | Y73: 180 | Z73: 0 | AA73: 0 | AB73: 205 | AC73: 348 | AD73: 43474 | AE73: 0 | AF73: 0 | AG73: 43822 | AH73: 9987 | AI73: 1346 | AJ73: 0 | AK73: 0 | AL73: 11333 | AM73: .
A74: 2016 | B74: 4254 | C74: Consumers Energy Co | D74: MI | E74: =IFERROR(SUM(AC74,AH74)*10^3/S74,"") | F74: =IFERROR(SUM(AD74,AI74)*10^3/T74,"") | G74: =IFERROR(SUM(AE74,AJ74)*10^3/U74,"") -> 60032.154 | H74: =IFERROR(SUM(AF74,AK74)*10^3/V74,"") | I74: 1545 | J74: 0 | K74: 17 | L74: 0 | M74: 1562 | N74: 0 | O74: 0 | P74: 0 | Q74: 0 | R74: 0 | S74: 0 | T74: 0 | U74: 62.2 | V74: 0 | W74: 62.2 | X74: 0 | Y74: 0 | Z74: 0 | AA74: 0 | AB74: 0 | AC74: 59 | AD74: 0 | AE74: 3734 | AF74: 0 | AG74: 3793 | AH74: 0 | AI74: 0 | AJ74: 0 | AK74: 0 | AL74: 0 | AM74: .
A75: 2016 | B75: 4362 | C75: Corn Belt Energy Corporation | D75: IL | E75: =IFERROR(SUM(AC75,AH75)*10^3/S75,"") | F75: =IFERROR(SUM(AD75,AI75)*10^3/T75,"") -> 239333.33 | G75: =IFERROR(SUM(AE75,AJ75)*10^3/U75,"") | H75: =IFERROR(SUM(AF75,AK75)*10^3/V75,"") | I75: 0 | J75: 59 | K75: 0 | L75: 0 | M75: 59 | N75: 0 | O75: 0 | P75: 0 | Q75: 0 | R75: 0 | S75: 0 | T75: 4.5 | U75: 0 | V75: 0 | W75: 4.5 | X75: 0 | Y75: 4.5 | Z75: 0 | AA75: 0 | AB75: 4.5 | AC75: 0 | AD75: 1077 | AE75: 0 | AF75: 0 | AG75: 1077 | AH75: 0 | AI75: 0 | AJ75: 0 | AK75: 0 | AL75: 0 | AM75: .
A76: 2016 | B76: 4363 | C76: Corn Belt Power Coop | D76: IA | E76: =IFERROR(SUM(AC76,AH76)*10^3/S76,"") -> 0 | F76: =IFERROR(SUM(AD76,AI76)*10^3/T76,"") | G76: =IFERROR(SUM(AE76,AJ76)*10^3/U76,"") -> 0 | H76: =IFERROR(SUM(AF76,AK76)*10^3/V76,"") | I76: 5888 | J76: 0 | K76: 3 | L76: 0 | M76: 5891 | N76: 0 | O76: 0 | P76: 0 | Q76: 0 | R76: 0 | S76: 67 | T76: 0 | U76: 42 | V76: 0 | W76: 109 | X76: 60.4 | Y76: 0 | Z76: 24.7 | AA76: 0 | AB76: 85.1 | AC76: 0 | AD76: 0 | AE76: 0 | AF76: 0 | AG76: 0 | AH76: 0 | AI76: 0 | AJ76: 0 | AK76: 0 | AL76: 0 | AM76: 292
A77: 2016 | B77: 4430 | C77: Covington Electric Coop, Inc | D77: AL | E77: =IFERROR(SUM(AC77,AH77)*10^3/S77,"") -> 0 | F77: =IFERROR(SUM(AD77,AI77)*10^3/T77,"") | G77: =IFERROR(SUM(AE77,AJ77)*10^3/U77,"") | H77: =IFERROR(SUM(AF77,AK77)*10^3/V77,"") | I77: 1954 | J77: 0 | K77: 0 | L77: 0 | M77: 1954 | N77: 0 | O77: 0 | P77: 0 | Q77: 0 | R77: 0 | S77: 1 | T77: 0 | U77: 0 | V77: 0 | W77: 1 | X77: 0 | Y77: 0 | Z77: 0 | AA77: 0 | AB77: 0 | AC77: 0 | AD77: 0 | AE77: 0 | AF77: 0 | AG77: 0 | AH77: 0 | AI77: 0 | AJ77: 0 | AK77: 0 | AL77: 0 | AM77: 225
A78: 2016 | B78: 4432 | C78: Coweta-Fayette El Member Corp | D78: GA | E78: =IFERROR(SUM(AC78,AH78)*10^3/S78,"") -> 7733.3333 | F78: =IFERROR(SUM(AD78,AI78)*10^3/T78,"") | G78: =IFERROR(SUM(AE78,AJ78)*10^3/U78,"") | H78: =IFERROR(SUM(AF78,AK78)*10^3/V78,"") | I78: 11610 | J78: 0 | K78: 0 | L78: 0 | M78: 11610 | N78: 277 | O78: 0 | P78: 0 | Q78: 0 | R78: 277 | S78: 15 | T78: 0 | U78: 0 | V78: 0 | W78: 15 | X78: 8 | Y78: 0 | Z78: 0 | AA78: 0 | AB78: 8 | AC78: 116 | AD78: 0 | AE78: 0 | AF78: 0 | AG78: 116 | AH78: 0 | AI78: 0 | AJ78: 0 | AK78: 0 | AL78: 0 | AM78: .
A79: 2016 | B79: 4509 | C79: Craighead Electric Coop Corp | D79: AR | E79: =IFERROR(SUM(AC79,AH79)*10^3/S79,"") | F79: =IFERROR(SUM(AD79,AI79)*10^3/T79,"") -> 30408.163 | G79: =IFERROR(SUM(AE79,AJ79)*10^3/U79,"") -> 27500 | H79: =IFERROR(SUM(AF79,AK79)*10^3/V79,"") | I79: 0 | J79: 600 | K79: 48 | L79: 0 | M79: 648 | N79: 0 | O79: 0 | P79: 0 | Q79: 0 | R79: 0 | S79: 0 | T79: 19.6 | U79: 1.2 | V79: 0 | W79: 20.8 | X79: 0 | Y79: 7.5 | Z79: 1.2 | AA79: 0 | AB79: 8.7 | AC79: 0 | AD79: 0 | AE79: 0 | AF79: 0 | AG79: 0 | AH79: 0 | AI79: 596 | AJ79: 33 | AK79: 0 | AL79: 629 | AM79: .
A80: 2016 | B80: 4538 | C80: Crisp County Power Comm | D80: GA | E80: =IFERROR(SUM(AC80,AH80)*10^3/S80,"") | F80: =IFERROR(SUM(AD80,AI80)*10^3/T80,"") | G80: =IFERROR(SUM(AE80,AJ80)*10^3/U80,"") -> 0 | H80: =IFERROR(SUM(AF80,AK80)*10^3/V80,"") | I80: 0 | J80: 0 | K80: 2 | L80: 0 | M80: 2 | N80: 0 | O80: 0 | P80: 0 | Q80: 0 | R80: 0 | S80: 0 | T80: 0 | U80: 12 | V80: 0 | W80: 12 | X80: 0 | Y80: 0 | Z80: 10 | AA80: 0 | AB80: 10 | AC80: 0 | AD80: 0 | AE80: 0 | AF80: 0 | AG80: 0 | AH80: 0 | AI80: 0 | AJ80: 0 | AK80: 0 | AL80: 0 | AM80: .
A81: 2016 | B81: 4675 | C81: Cuivre River Electric Coop Inc | D81: MO | E81: =IFERROR(SUM(AC81,AH81)*10^3/S81,"") -> 23000 | F81: =IFERROR(SUM(AD81,AI81)*10^3/T81,"") -> 0 | G81: =IFERROR(SUM(AE81,AJ81)*10^3/U81,"") | H81: =IFERROR(SUM(AF81,AK81)*10^3/V81,"") | I81: 432 | J81: 24 | K81: 0 | L81: 0 | M81: 456 | N81: 0 | O81: 0 | P81: 0 | Q81: 0 | R81: 0 | S81: 1 | T81: 8.8 | U81: 0 | V81: 0 | W81: 9.8 | X81: 1 | Y81: 5.9 | Z81: 0 | AA81: 0 | AB81: 6.9 | AC81: 20 | AD81: 0 | AE81: 0 | AF81: 0 | AG81: 20 | AH81: 3 | AI81: 0 | AJ81: 0 | AK81: 0 | AL81: 3 | AM81: .
A82: 2016 | B82: 4704 | C82: DS&O Electric Cooperative, Inc. | D82: KS | E82: =IFERROR(SUM(AC82,AH82)*10^3/S82,"") -> 50000 | F82: =IFERROR(SUM(AD82,AI82)*10^3/T82,"") -> 18888.889 | G82: =IFERROR(SUM(AE82,AJ82)*10^3/U82,"") | H82: =IFERROR(SUM(AF82,AK82)*10^3/V82,"") | I82: 124 | J82: 45 | K82: 0 | L82: 0 | M82: 169 | N82: 0 | O82: 0 | P82: 0 | Q82: 0 | R82: 0 | S82: 0.3 | T82: 1.8 | U82: 0 | V82: 0 | W82: 2.1 | X82: 0.3 | Y82: 1.5 | Z82: 0 | AA82: 0 | AB82: 1.8 | AC82: 5 | AD82: 24 | AE82: 0 | AF82: 0 | AG82: 29 | AH82: 10 | AI82: 10 | AJ82: 0 | AK82: 0 | AL82: 20 | AM82: .
A83: 2016 | B83: 4794 | C83: City of Danville - (VA) | D83: VA | E83: =IFERROR(SUM(AC83,AH83)*10^3/S83,"") | F83: =IFERROR(SUM(AD83,AI83)*10^3/T83,"") -> 11578.947 | G83: =IFERROR(SUM(AE83,AJ83)*10^3/U83,"") -> 11333.333 | H83: =IFERROR(SUM(AF83,AK83)*10^3/V83,"") | I83: 0 | J83: 3 | K83: 2 | L83: 0 | M83: 5 | N83: 0 | O83: 0 | P83: 0 | Q83: 0 | R83: 0 | S83: 0 | T83: 1.9 | U83: 3 | V83: 0 | W83: 4.9 | X83: 0 | Y83: 1.5 | Z83: 2.6 | AA83: 0 | AB83: 4.1 | AC83: 0 | AD83: 22 | AE83: 34 | AF83: 0 | AG83: 56 | AH83: 0 | AI83: 0 | AJ83: 0 | AK83: 0 | AL83: 0 | AM83: .
A84: 2016 | B84: 4911 | C84: Dawson Power District | D84: NE | E84: =IFERROR(SUM(AC84,AH84)*10^3/S84,"") | F84: =IFERROR(SUM(AD84,AI84)*10^3/T84,"") | G84: =IFERROR(SUM(AE84,AJ84)*10^3/U84,"") -> 1653.2721 | H84: =IFERROR(SUM(AF84,AK84)*10^3/V84,"") | I84: 0 | J84: 0 | K84: 4449 | L84: 0 | M84: 4449 | N84: 0 | O84: 0 | P84: 0 | Q84: 0 | R84: 0 | S84: 0 | T84: 0 | U84: 87.1 | V84: 0 | W84: 87.1 | X84: 0 | Y84: 0 | Z84: 59.1 | AA84: 0 | AB84: 59.1 | AC84: 0 | AD84: 0 | AE84: 0 | AF84: 0 | AG84: 0 | AH84: 0 | AI84: 0 | AJ84: 144 | AK84: 0 | AL84: 144 | AM84: .
A85: 2016 | B85: 5027 | C85: Delmarva Power | D85: DE | E85: =IFERROR(SUM(AC85,AH85)*10^3/S85,"") -> 132281.11 | F85: =IFERROR(SUM(AD85,AI85)*10^3/T85,"") | G85: =IFERROR(SUM(AE85,AJ85)*10^3/U85,"") | H85: =IFERROR(SUM(AF85,AK85)*10^3/V85,"") | I85: 248000 | J85: 0 | K85: 0 | L85: 0 | M85: 248000 | N85: 2083 | O85: 0 | P85: 0 | Q85: 0 | R85: 2083 | S85: 43.4 | T85: 0 | U85: 0 | V85: 0 | W85: 43.4 | X85: 43.4 | Y85: 0 | Z85: 0 | AA85: 0 | AB85: 43.4 | AC85: 575 | AD85: 0 | AE85: 0 | AF85: 0 | AG85: 575 | AH85: 5166 | AI85: 0 | AJ85: 0 | AK85: 0 | AL85: 5166 | AM85: .
A86: 2016 | B86: 5027 | C86: Delmarva Power | D86: MD | E86: =IFERROR(SUM(AC86,AH86)*10^3/S86,"") -> 136878.79 | F86: =IFERROR(SUM(AD86,AI86)*10^3/T86,"") -> 100851.06 | G86: =IFERROR(SUM(AE86,AJ86)*10^3/U86,"") | H86: =IFERROR(SUM(AF86,AK86)*10^3/V86,"") | I86: 165000 | J86: 755 | K86: 0 | L86: 0 | M86: 165755 | N86: 3780 | O86: 224 | P86: 0 | Q86: 0 | R86: 4004 | S86: 33 | T86: 4.7 | U86: 0 | V86: 0 | W86: 37.7 | X86: 33 | Y86: 4.7 | Z86: 0 | AA86: 0 | AB86: 37.7 | AC86: 1878 | AD86: 207 | AE86: 0 | AF86: 0 | AG86: 2085 | AH86: 2639 | AI86: 267 | AJ86: 0 | AK86: 0 | AL86: 2906 | AM86: .
A87: 2016 | B87: 5056 | C87: City of Denison - (IA) | D87: IA | E87: =IFERROR(SUM(AC87,AH87)*10^3/S87,"") -> 54000 | F87: =IFERROR(SUM(AD87,AI87)*10^3/T87,"") -> 26666.667 | G87: =IFERROR(SUM(AE87,AJ87)*10^3/U87,"") | H87: =IFERROR(SUM(AF87,AK87)*10^3/V87,"") | I87: 2431 | J87: 156 | K87: 19 | L87: 0 | M87: 2606 | N87: 27 | O87: 9 | P87: 0 | Q87: 0 | R87: 36 | S87: 1.5 | T87: 0.3 | U87: 0 | V87: 0 | W87: 1.8 | X87: 1.5 | Y87: 0.3 | Z87: 0 | AA87: 0 | AB87: 1.8 | AC87: 78 | AD87: 7 | AE87: 21 | AF87: 0 | AG87: 106 | AH87: 3 | AI87: 1 | AJ87: 2 | AK87: 0 | AL87: 6 | AM87: .
A88: 2016 | B88: 5070 | C88: Delaware Electric Cooperative | D88: DE | E88: =IFERROR(SUM(AC88,AH88)*10^3/S88,"") -> 39915.254 | F88: =IFERROR(SUM(AD88,AI88)*10^3/T88,"") -> 0 | G88: =IFERROR(SUM(AE88,AJ88)*10^3/U88,"") | H88: =IFERROR(SUM(AF88,AK88)*10^3/V88,"") | I88: 21862 | J88: 1117 | K88: 0 | L88: 0 | M88: 22979 | N88: 0 | O88: 0 | P88: 0 | Q88: 0 | R88: 0 | S88: 11.8 | T88: 15.2 | U88: 0 | V88: 0 | W88: 27 | X88: 9.8 | Y88: 14.2 | Z88: 0 | AA88: 0 | AB88: 24 | AC88: 433 | AD88: 0 | AE88: 0 | AF88: 0 | AG88: 433 | AH88: 38 | AI88: 0 | AJ88: 0 | AK88: 0 | AL88: 38 | AM88: .
A89: 2016 | B89: 5078 | C89: Denton County Elec Coop, Inc | D89: TX | E89: =IFERROR(SUM(AC89,AH89)*10^3/S89,"") -> 87846.154 | F89: =IFERROR(SUM(AD89,AI89)*10^3/T89,"") | G89: =IFERROR(SUM(AE89,AJ89)*10^3/U89,"") | H89: =IFERROR(SUM(AF89,AK89)*10^3/V89,"") | I89: 5802 | J89: 0 | K89: 0 | L89: 0 | M89: 5802 | N89: 16 | O89: 0 | P89: 0 | Q89: 0 | R89: 16 | S89: 13 | T89: 0 | U89: 0 | V89: 0 | W89: 13 | X89: 8 | Y89: 0 | Z89: 0 | AA89: 0 | AB89: 8 | AC89: 887 | AD89: 0 | AE89: 0 | AF89: 0 | AG89: 887 | AH89: 255 | AI89: 0 | AJ89: 0 | AK89: 0 | AL89: 255 | AM89: .
... A95: 2016 | B95: 5416 | C95: Duke Energy Carolinas, LLC | D95: SC | E95: =IFERROR(SUM(AC95,AH95)*10^3/S95,"") -> 33105.311 | F95: =IFERROR(SUM(AD95,AI95)*10^3/T95,"") -> 185728.16 | G95: =IFERROR(SUM(AE95,AJ95)*10^3/U95,"") -> 0 | H95: =IFERROR(SUM(AF95,AK95)*10^3/V95,"") | I95: 49318 | J95: 16 | K95: 42 | L95: 0 | M95: 49376 | N95: 0 | O95: 0 | P95: 0 | Q95: 0 | R95: 0 | S95: 111.1 | T95: 20.6 | U95: 134.5 | V95: 0 | W95: 266.2 | X95: 0 | Y95: 0 | Z95: 0 | AA95: 0 | AB95: 0 | AC95: 1651 | AD95: 3618 | AE95: 0 | AF95: 0 | AG95: 5269 | AH95: 2027 | AI95: 208 | AJ95: 0 | AK95: 0 | AL95: 2235 | AM95: .
A96: 2016 | B96: 5417 | C96: Dunn County Electric Coop | D96: WI | E96: =IFERROR(SUM(AC96,AH96)*10^3/S96,"") -> 14117.647 | F96: =IFERROR(SUM(AD96,AI96)*10^3/T96,"") -> 14335.664 | G96: =IFERROR(SUM(AE96,AJ96)*10^3/U96,"") | H96: =IFERROR(SUM(AF96,AK96)*10^3/V96,"") | I96: 3553 | J96: 361 | K96: 0 | L96: 0 | M96: 3914 | N96: 0 | O96: 0 | P96: 0 | Q96: 0 | R96: 0 | S96: 1.7 | T96: 14.3 | U96: 0 | V96: 0 | W96: 16 | X96: 0.7 | Y96: 5.5 | Z96: 0 | AA96: 0 | AB96: 6.2 | AC96: 13 | AD96: 113 | AE96: 0 | AF96: 0 | AG96: 126 | AH96: 11 | AI96: 92 | AJ96: 0 | AK96: 0 | AL96: 103 | AM96: 0
A97: 2016 | B97: 5480 | C97: Town of Danvers | D97: MA | E97: =IFERROR(SUM(AC97,AH97)*10^3/S97,"") -> 103333.33 | F97: =IFERROR(SUM(AD97,AI97)*10^3/T97,"") -> 71428.571 | G97: =IFERROR(SUM(AE97,AJ97)*10^3/U97,"") -> 140000 | H97: =IFERROR(SUM(AF97,AK97)*10^3/V97,"") | I97: 1230 | J97: 74 | K97: 5 | L97: 0 | M97: 1309 | N97: 3 | O97: 4 | P97: 1 | Q97: 0 | R97: 8 | S97: 0.3 | T97: 0.7 | U97: 0.2 | V97: 0 | W97: 1.2 | X97: 0.3 | Y97: 0.7 | Z97: 0.2 | AA97: 0 | AB97: 1.2 | AC97: 29 | AD97: 0 | AE97: 14 | AF97: 0 | AG97: 43 | AH97: 2 | AI97: 50 | AJ97: 14 | AK97: 0 | AL97: 66 | AM97: .
A98: 2016 | B98: 5552 | C98: East River Elec Pwr Coop, Inc | D98: SD | E98: =IFERROR(SUM(AC98,AH98)*10^3/S98,"") -> 41617.647 | F98: =IFERROR(SUM(AD98,AI98)*10^3/T98,"") | G98: =IFERROR(SUM(AE98,AJ98)*10^3/U98,"") -> 8428.5714 | H98: =IFERROR(SUM(AF98,AK98)*10^3/V98,"") | I98: 0 | J98: 0 | K98: 0 | L98: 0 | M98: 0 | N98: 0 | O98: 0 | P98: 0 | Q98: 0 | R98: 0 | S98: 34 | T98: 0 | U98: 42 | V98: 0 | W98: 76 | X98: 34 | Y98: 0 | Z98: 42 | AA98: 0 | AB98: 76 | AC98: 0 | AD98: 0 | AE98: 0 | AF98: 0 | AG98: 0 | AH98: 1415 | AI98: 0 | AJ98: 354 | AK98: 0 | AL98: 1769 | AM98: 609
A99: 2016 | B99: 5575 | C99: City of East Grand Forks - (MN) | D99: MN | E99: =IFERROR(SUM(AC99,AH99)*10^3/S99,"") -> 16000 | F99: =IFERROR(SUM(AD99,AI99)*10^3/T99,"") -> 12500 | G99: =IFERROR(SUM(AE99,AJ99)*10^3/U99,"") | H99: =IFERROR(SUM(AF99,AK99)*10^3/V99,"") | I99: 861 | J99: 68 | K99: 0 | L99: 0 | M99: 929 | N99: 785 | O99: 1185 | P99: 0 | Q99: 0 | R99: 1970 | S99: 4 | T99: 2 | U99: 0 | V99: 0 | W99: 6 | X99: 2 | Y99: 2 | Z99: 0 | AA99: 0 | AB99: 4 | AC99: 41 | AD99: 2 | AE99: 0 | AF99: 0 | AG99: 43 | AH99: 23 | AI99: 23 | AJ99: 0 | AK99: 0 | AL99: 46 | AM99: .
A100: 2016 | B100: 5580 | C100: East Kentucky Power Coop, Inc | D100: KY | E100: =IFERROR(SUM(AC100,AH100)*10^3/S100,"") -> 1032352.9 | F100: =IFERROR(SUM(AD100,AI100)*10^3/T100,"") | G100: =IFERROR(SUM(AE100,AJ100)*10^3/U100,"") -> 61842.105 | H100: =IFERROR(SUM(AF100,AK100)*10^3/V100,"") | I100: 2282 | J100: 0 | K100: 2 | L100: 0 | M100: 2284 | N100: 16 | O100: 0 | P100: 0 | Q100: 0 | R100: 16 | S100: 1.7 | T100: 0 | U100: 7.6 | V100: 0 | W100: 9.3 | X100: 1.7 | Y100: 0 | Z100: 7.6 | AA100: 0 | AB100: 9.3 | AC100: 580 | AD100: 0 | AE100: 470 | AF100: 0 | AG100: 1050 | AH100: 1175 | AI100: 0 | AJ100: 0 | AK100: 0 | AL100: 1175 | AM100: 865
A101: 2016 | B101: 5632 | C101: Eau Claire Electric Coop | D101: WI | E101: =IFERROR(SUM(AC101,AH101)*10^3/S101,"") -> 54800 | F101: =IFERROR(SUM(AD101,AI101)*10^3/T101,"") -> 55851.064 | G101: =IFERROR(SUM(AE101,AJ101)*10^3/U101,"") | H101: =IFERROR(SUM(AF101,AK101)*10^3/V101,"") | I101: 5274 | J101: 181 | K101: 0 | L101: 0 | M101: 5455 | N101: 0 | O101: 0 | P101: 0 | Q101: 0 | R101: 0 | S101: 2.5 | T101: 9.4 | U101: 0 | V101: 0 | W101: 11.9 | X101: 1.2 | Y101: 4.7 | Z101: 0 | AA101: 0 | AB101: 5.9 | AC101: 121 | AD101: 463 | AE101: 0 | AF101: 0 | AG101: 584 | AH101: 16 | AI101: 62 | AJ101: 0 | AK101: 0 | AL101: 78 | AM101: 37
A102: 2016 | B102: 5701 | C102: El Paso Electric Co | D102: NM | E102: =IFERROR(SUM(AC102,AH102)*10^3/S102,"") | F102: =IFERROR(SUM(AD102,AI102)*10^3/T102,"") | G102: =IFERROR(SUM(AE102,AJ102)*10^3/U102,"") | H102: =IFERROR(SUM(AF102,AK102)*10^3/V102,"") | I102: 0 | J102: 0 | K102: 3 | L102: 0 | M102: 3 | N102: 0 | O102: 0 | P102: 0 | Q102: 0 | R102: 0 | S102: 0 | T102: 0 | U102: 0 | V102: 0 | W102: 0 | X102: 0 | Y102: 0 | Z102: 0 | AA102: 0 | AB102: 0 | AC102: 0 | AD102: 0 | AE102: 0 | AF102: 0 | AG102: 0 | AH102: 0 | AI102: 0 | AJ102: 0 | AK102: 0 | AL102: 0 | AM102: .
A103: 2016 | B103: 5701 | C103: El Paso Electric Co | D103: TX | E103: =IFERROR(SUM(AC103,AH103)*10^3/S103,"") | F103: =IFERROR(SUM(AD103,AI103)*10^3/T103,"") -> 46250 | G103: =IFERROR(SUM(AE103,AJ103)*10^3/U103,"") -> 40000 | H103: =IFERROR(SUM(AF103,AK103)*10^3/V103,"") | I103: 0 | J103: 5 | K103: 12 | L103: 0 | M103: 17 | N103: 0 | O103: 10 | P103: 13 | Q103: 0 | R103: 23 | S103: 0 | T103: 3.2 | U103: 4.4 | V103: 0 | W103: 7.6 | X103: 0 | Y103: 3.2 | Z103: 4.4 | AA103: 0 | AB103: 7.6 | AC103: 0 | AD103: 148 | AE103: 176 | AF103: 0 | AG103: 324 | AH103: 0 | AI103: 0 | AJ103: 0 | AK103: 0 | AL103: 0 | AM103: .
A104: 2016 | B104: 5780 | C104: Elkhorn Rural Public Pwr Dist | D104: NE | E104: =IFERROR(SUM(AC104,AH104)*10^3/S104,"") | F104: =IFERROR(SUM(AD104,AI104)*10^3/T104,"") | G104: =IFERROR(SUM(AE104,AJ104)*10^3/U104,"") -> 3679.7753 | H104: =IFERROR(SUM(AF104,AK104)*10^3/V104,"") | I104: 0 | J104: 0 | K104: 1258 | L104: 0 | M104: 1258 | N104: 0 | O104: 0 | P104: 0 | Q104: 0 | R104: 0 | S104: 0 | T104: 0 | U104: 35.6 | V104: 0 | W104: 35.6 | X104: 0 | Y104: 0 | Z104: 35.6 | AA104: 0 | AB104: 35.6 | AC104: 0 | AD104: 0 | AE104: 0 | AF104: 0 | AG104: 0 | AH104: 0 | AI104: 0 | AJ104: 131 | AK104: 0 | AL104: 131 | AM104: .
A105: 2016 | B105: 5860 | C105: Empire District Electric Co | D105: MO | E105: =IFERROR(SUM(AC105,AH105)*10^3/S105,"") | F105: =IFERROR(SUM(AD105,AI105)*10^3/T105,"") | G105: =IFERROR(SUM(AE105,AJ105)*10^3/U105,"") -> 15000 | H105: =IFERROR(SUM(AF105,AK105)*10^3/V105,"") | I105: 0 | J105: 0 | K105: 2 | L105: 0 | M105: 2 | N105: 0 | O105: 0 | P105: 0 | Q105: 0 | R105: 0 | S105: 0 | T105: 0 | U105: 0.8 | V105: 0 | W105: 0.8 | X105: 0 | Y105: 0 | Z105: 0 | AA105: 0 | AB105: 0 | AC105: 0 | AD105: 0 | AE105: 12 | AF105: 0 | AG105: 12 | AH105: 0 | AI105: 0 | AJ105: 0 | AK105: 0 | AL105: 0 | AM105: .
...

Sheet Calculations
A1: Provider | B1: Average Cost ($/MW-yr) | C1: Share of DR
A2: residential | B2: =SUMPRODUCT('Demand Response_States'!E4:E430,'Demand Response_States'!S4:S430)/SUM('Demand Response_States'!S4:S430) -> 52676.668 | C2: =SUM('Demand Response_States'!S4:S430)/SUM('Demand Response_States'!$W4:$W430) -> 0.2927923
A3: commercial | B3: =SUMPRODUCT('Demand Response_States'!F4:F430,'Demand Response_States'!T4:T430)/SUM('Demand Response_States'!T4:T430) -> 46486.107 | C3: =SUM('Demand Response_States'!T4:T430)/SUM('Demand Response_States'!$W4:$W430) -> 0.30766811
A4: industrial | B4: =SUMPRODUCT('Demand Response_States'!G4:G430,'Demand Response_States'!U4:U430)/SUM('Demand Response_States'!U4:U430) -> 24022.777 | C4: =SUM('Demand Response_States'!U4:U430)/SUM('Demand Response_States'!$W4:$W430) -> 0.39914987
A6: In the EPS, the "industry" cash flow entity encompasses both industrial
A7: facilities and commercial buildings, so we combine these into a single
A8: entry:
A10: residential | B10: =B2 -> 52676.668 | C10: =C2 -> 0.2927923
A11: commercial & industrial | B11: =(B3*C3+B4*C4)/SUM(C3:C4) -> 33800.755 | C11: =SUM(C3:C4) -> 0.70681799

Sheet DRCo-ACpUDRC
B1: Cost ($/MW)
A2: government | B2: =Calculations!B11 -> 33800.755
A3: nonenergy industries | B3: =Calculations!B11 -> 33800.755
A4: labor and consumers | B4: =Calculations!B10 -> 52676.668
A5: foreign entities | B5: 0
A6: electricity suppliers | B6: =B$3 -> 33800.755
A7: coal suppliers | B7: =B$3 -> 33800.755
A8: natural gas and petroleum suppliers | B8: =B$3 -> 33800.755
A9: biomass and biofuel suppliers | B9: =B$3 -> 33800.755
A10: other energy suppliers | B10: =B$3 -> 33800.755

Sheet DRCo-SoDRbP
A1: % of DR (dimensionless) | B1: share
A2: government | B2: 0
A3: nonenergy industries | B3: =Calculations!C11 -> 0.70681799
A4: labor and consumers | B4: =Calculations!C10 -> 0.2927923
A5: foreign entities | B5: 0
A6: electricity suppliers | B6: 0
A7: coal suppliers | B7: 0
A8: natural gas and petroleum suppliers | B8: 0
A9: biomass and biofuel suppliers | B9: 0
A10: other energy suppliers | B10: 0
