Workbook
Name currency_conv: About!$A$49

Sheet About
A1: TNRbI Total Nonfuel Revenue by Industry
A3: Source: | B3: U.S. Energy Information Administration | I3: Census and Statistics Department
B4: 2019 | I4: Gross Domestic Product (GDP) by economic activity at current prices
B5: Annual Energy Outlook 2019 | I5: 2021
B6: https://www.eia.gov/outlooks/aeo/supplement/excel/suptab_24.xlsx | I6: https://www.censtatd.gov.hk/en/web_table.html?id=310-34101
B7: Table 24: Industrial Sector Macroeconomic Indicators | I7: Table 310-34101
A9: Notes | I9: Hong Kong Monetary Authority
A10: This variable should contain the total revenue each industry earns by | I10: Economic and Financial Data for Hong Kong
A11: selling its products, EXCEPT for fuels (natural gas, petroleum, coal) | I11: 2021
A12: as changes in fuel sales are accounted for separately in each sector. | I12: https://www.hkma.gov.hk/eng/data-publications-and-research/data-and-statistics/economic-financial-data-for-hong-kong/
A13: To also include the fuels here would be double-counting.
A15: As a result, we don't need AEO tables 11 and 12 (which provide
A16: petroleum production and prices), nor AEO table 13 (which
A17: provides natural gas production and prices). We only need the
A18: industrial sales figures from AEO table 24.
A20: We group the small amount earned from non-fuel petroleum- and
A21: coal-derived products in the "other industries" category
A22: because the elasticities calculated for the "natural gas and
A23: petroleum systems" and "mining" industries are dominated by
A24: the use of these products as fuels, which is probably too high for
A25: non-fuel products. Accordingly, it is more accurate to use the
A26: generalized "other industries" category elasticity.
... A48: conversion factor:
A49: =1.07*10^9 -> 1.07e+09 | B49: 2012 USD / billion 2009 USD

Sheet EIA 24
B1: ref2019.d111618a | C1: 2017 | D1: 2018 | E1: 2019 | F1: 2020 | G1: 2021 | H1: 2022 | I1: 2023 | J1: 2024 | K1: 2025 | L1: 2026 | M1: 2027 | N1: 2028 | O1: 2029 | P1: 2030 | Q1: 2031 | R1: 2032 | S1: 2033 | T1: 2034 | U1: 2035 | V1: 2036 | W1: 2037 | X1: 2038 | Y1: 2039 | Z1: 2040 | AA1: 2041 | AB1: 2042 | AC1: 2043 | AD1: 2044 | AE1: 2045 | AF1: 2046 | AG1: 2047 | AH1: 2048 | AI1: 2049 | AJ1: 2050
C3: Report | D3: Annual Energy Outlook 2019
C4: Scenario | D4: ref2019 | G4: Reference case
C5: Datekey | D5: d111618a
C6: Release Date | E6: January 2019
A10: ISM000 | B10: 24. Industrial Sector Macroeconomic Indicators
AK12: 2018-
B13: Indicators | C13: 2017 | D13: 2018 | E13: 2019 | F13: 2020 | G13: 2021 | H13: 2022 | I13: 2023 | J13: 2024 | K13: 2025 | L13: 2026 | M13: 2027 | N13: 2028 | O13: 2029 | P13: 2030 | Q13: 2031 | R13: 2032 | S13: 2033 | T13: 2034 | U13: 2035 | V13: 2036 | W13: 2037 | X13: 2038 | Y13: 2039 | Z13: 2040 | AA13: 2041 | AB13: 2042 | AC13: 2043 | AD13: 2044 | AE13: 2045 | AF13: 2046 | AG13: 2047 | AH13: 2048 | AI13: 2049 | AJ13: 2050 | AK13: 2050
A15: ISM000:ba_GDP(billionm_ | B15: Gross Domestic Product (million 2021 HK dollars) | C15: 17096.18 | D15: 17581.588 | E15: 18098.652 | F15: 18486.852 | G15: 18791.873 | H15: 19102.1 | I15: 19412.967 | J15: 19749.795 | K15: 20115.928 | L15: 20495.133 | M15: 20893.289 | N15: 21314.609 | O15: 21725.949 | P15: 22156.758 | Q15: 22591.58 | R15: 23014.096 | S15: 23459.133 | T15: 23909.533 | U15: 24347.9 | V15: 24789.902 | W15: 25245.342 | X15: 25713.199 | Y15: 26188.455 | Z15: 26674.789 | AA15: 27162.408 | AB15: 27671.131 | AC15: 28191.525 | AD15: 28717.711 | AE15: 29261.375 | AF15: 29800.648 | AG15: 30360.574 | AH15: 30909.953 | AI15: 31460.225 | AJ15: 32006.383 | AK15: 0.018898 | AL15: 29801 | AM15: 30361 | AN15: 30910 | AO15: 31460 | AP15: 32006 | AQ15: 0.019
A17: ISM000:ca_NonfarmEmploy | B17: Nonfarm Employment (millions) | C17: 146.47887 | D17: 148.82622 | E17: 150.34656 | F17: 151.7157 | G17: 152.523 | H17: 153.15376 | I17: 153.54065 | J17: 153.98824 | K17: 154.55675 | L17: 155.21475 | M17: 156.01364 | N17: 156.93599 | O17: 157.84306 | P17: 158.89725 | Q17: 159.82431 | R17: 160.81573 | S17: 161.79948 | T17: 162.83571 | U17: 163.81389 | V17: 164.75874 | W17: 165.6945 | X17: 166.655 | Y17: 167.62332 | Z17: 168.71918 | AA17: 169.57524 | AB17: 170.58575 | AC17: 171.61832 | AD17: 172.67293 | AE17: 173.76211 | AF17: 174.87563 | AG17: 175.99243 | AH17: 177.03633 | AI17: 178.0609 | AJ17: 179.15192 | AK17: 0.005812
B19: Value of Shipments (billion 2009 dollars)
B21: Nonmanufacturing Sector
A22: ISM000:ea_Agricultural | B22: Agriculture/Forestry/Fishing/Hunting | C22: 362.89963 | D22: 362.61444 | E22: 369.52792 | F22: 375.66763 | G22: 381.76007 | H22: 388.22049 | I22: 394.60315 | J22: 399.98019 | K22: 404.81665 | L22: 409.90182 | M22: 414.07797 | N22: 418.66849 | O22: 422.73752 | P22: 426.74454 | Q22: 431.62732 | R22: 436.52881 | S22: 441.44275 | T22: 446.13489 | U22: 450.88312 | V22: 455.56811 | W22: 460.33926 | X22: 465.07715 | Y22: 469.48776 | Z22: 473.86359 | AA22: 478.38061 | AB22: 483.12509 | AC22: 488.04758 | AD22: 493.20972 | AE22: 498.65073 | AF22: 504.27176 | AG22: 509.93637 | AH22: 515.85559 | AI22: 521.68811 | AJ22: 527.16083 | AK22: 0.011761
A23: ISM000:ea_Mining | B23: Mining | C23: 474.23843 | D23: 518.78442 | E23: 623.94904 | F23: 647.33569 | G23: 663.08765 | H23: 674.51099 | I23: 680.09302 | J23: 687.71899 | K23: 696.25238 | L23: 709.39893 | M23: 714.28015 | N23: 716.78125 | O23: 719.64673 | P23: 721.78748 | Q23: 726.67413 | R23: 727.94434 | S23: 730.02985 | T23: 731.82794 | U23: 732.95886 | V23: 735.26837 | W23: 736.53705 | X23: 739.59747 | Y23: 741.56659 | Z23: 743.54602 | AA23: 744.47595 | AB23: 744.68671 | AC23: 742.52417 | AD23: 742.61475 | AE23: 741.33685 | AF23: 740.75244 | AG23: 740.07312 | AH23: 739.87329 | AI23: 737.57916 | AJ23: 737.88379 | AK23: 0.01107
A24: ISM000:ea_Construction | B24: Construction | C24: 1225.132 | D24: 1264.616 | E24: 1311.53 | F24: 1342.675 | G24: 1353.322 | H24: 1368.673 | I24: 1380.24 | J24: 1389.927 | K24: 1403.29 | L24: 1417.254 | M24: 1432.236 | N24: 1454.27 | O24: 1471.766 | P24: 1490.767 | Q24: 1514.829 | R24: 1534.302 | S24: 1553.411 | T24: 1578.843 | U24: 1604.495 | V24: 1627.248 | W24: 1649.697 | X24: 1675.092 | Y24: 1694.702 | Z24: 1721.012 | AA24: 1751.698 | AB24: 1776.366 | AC24: 1805.5341 | AD24: 1837.296 | AE24: 1867.644 | AF24: 1902.1 | AG24: 1934.537 | AH24: 1963.129 | AI24: 1987.384 | AJ24: 2014.828 | AK24: 0.014662
B26: Manufacturing Sector
A27: ISM000:fa_FoodandKindre | B27: Food Products | C27: 722.18848 | D27: 736.98138 | E27: 751.71942 | F27: 768.45679 | G27: 783.52911 | H27: 796.78473 | I27: 810.76361 | J27: 826.20282 | K27: 840.4068 | L27: 853.97479 | M27: 871.36133 | N27: 887.8764 | O27: 903.25732 | P27: 918.47223 | Q27: 933.59161 | R27: 949.06818 | S27: 965.01251 | T27: 981.82281 | U27: 999.72113 | V27: 1018.107 | W27: 1036.306 | X27: 1055.0129 | Y27: 1074.004 | Z27: 1092.618 | AA27: 1110.3311 | AB27: 1128.266 | AC27: 1146.999 | AD27: 1166.564 | AE27: 1186.411 | AF27: 1206.986 | AG27: 1227.525 | AH27: 1249.327 | AI27: 1271.59 | AJ27: 1294.351 | AK27: 0.017756
A28: ISM000:fa_BeveragesandT | B28: Beverages and Tobacco Products | C28: 161.5509 | D28: 160.21519 | E28: 160.4308 | F28: 160.7433 | G28: 161.1636 | H28: 161.54739 | I28: 161.9308 | J28: 162.4493 | K28: 163.33501 | L28: 164.24091 | M28: 164.74409 | N28: 165.8503 | O28: 166.64909 | P28: 167.55119 | Q28: 168.62151 | R28: 169.8703 | S28: 171.2112 | T28: 172.659 | U28: 174.0769 | V28: 175.5479 | W28: 177.21651 | X28: 178.7892 | Y28: 180.44501 | Z28: 182.00391 | AA28: 183.8685 | AB28: 185.6286 | AC28: 187.3694 | AD28: 188.4783 | AE28: 189.7137 | AF28: 190.7475 | AG28: 191.97321 | AH28: 193.0829 | AI28: 194.1915 | AJ28: 195.2323 | AK28: 0.006196
A29: ISM000:fa_TextileMillPr | B29: Textile Mills and Products | C29: 70.193687 | D29: 70.376953 | E29: 68.607048 | F29: 66.336479 | G29: 64.307663 | H29: 63.131721 | I29: 62.069641 | J29: 60.939621 | K29: 60.04039 | L29: 59.140968 | M29: 57.337742 | N29: 56.543991 | O29: 55.44244 | P29: 54.28368 | Q29: 53.38131 | R29: 52.403858 | S29: 51.53772 | T29: 50.794312 | U29: 49.976761 | V29: 49.054939 | W29: 48.409801 | X29: 47.642639 | Y29: 46.698891 | Z29: 45.697929 | AA29: 44.78788 | AB29: 43.907379 | AC29: 43.24855 | AD29: 42.51897 | AE29: 42.140862 | AF29: 41.500149 | AG29: 41.106781 | AH29: 40.662159 | AI29: 40.213638 | AJ29: 39.703091 | AK29: -0.01773
A30: ISM000:fa_LumberandWood | B30: Wood Products | C30: 90.168892 | D30: 93.926689 | E30: 96.632019 | F30: 97.547394 | G30: 97.94265 | H30: 98.50795 | I30: 99.268097 | J30: 99.970688 | K30: 101.117 | L30: 102.1375 | M30: 101.6138 | N30: 101.1505 | O30: 101.4837 | P30: 102.0752 | Q30: 103.5264 | R30: 104.5062 | S30: 105.1427 | T30: 107.5022 | U30: 110.192 | V30: 112.1448 | W30: 113.9783 | X30: 116.1401 | Y30: 116.8653 | Z30: 118.3823 | AA30: 120.5424 | AB30: 121.9071 | AC30: 122.2316 | AD30: 123.7332 | AE30: 125.0826 | AF30: 126.9333 | AG30: 128.4897 | AH30: 129.38029 | AI30: 129.4743 | AJ30: 130.08 | AK30: 0.010228
A31: ISM000:fa_FurnitureandF | B31: Furniture and Related Products | C31: 71.82148 | D31: 72.511581 | E31: 74.572548 | F31: 74.519951 | G31: 74.162529 | H31: 74.956261 | I31: 76.302757 | J31: 77.808998 | K31: 79.369186 | L31: 80.790756 | M31: 81.606773 | N31: 82.623619 | O31: 83.446518 | P31: 83.987831 | Q31: 84.997543 | R31: 86.319717 | S31: 87.37265 | T31: 88.665871 | U31: 90.581703 | V31: 92.677292 | W31: 94.931602 | X31: 96.744911 | Y31: 98.005959 | Z31: 98.954033 | AA31: 99.683769 | AB31: 100.4962 | AC31: 101.4443 | AD31: 102.5086 | AE31: 104.0473 | AF31: 106.0047 | AG31: 108.2282 | AH31: 110.6935 | AI31: 113.2189 | AJ31: 115.5134 | AK31: 0.014658
A32: ISM000:fa_PaperandAllie | B32: Paper Products | C32: 166.9249 | D32: 167.4024 | E32: 167.7527 | F32: 167.5995 | G32: 168.3136 | H32: 169.8345 | I32: 171.4184 | J32: 173.1671 | K32: 175.13879 | L32: 177.02811 | M32: 178.01601 | N32: 179.68201 | O32: 180.67931 | P32: 181.6028 | Q32: 182.9041 | R32: 184.3197 | S32: 186.5743 | T32: 189.084 | U32: 191.80299 | V32: 194.5872 | W32: 197.5201 | X32: 200.1882 | Y32: 202.6956 | Z32: 204.8524 | AA32: 206.90871 | AB32: 208.9077 | AC32: 211.2323 | AD32: 213.7119 | AE32: 216.48019 | AF32: 219.051 | AG32: 221.78709 | AH32: 224.6299 | AI32: 227.47639 | AJ32: 230.10609 | AK32: 0.009991
A33: ISM000:fa_PrintingandPu | B33: Printing | C33: 80.733253 | D33: 79.572456 | E33: 78.361237 | F33: 77.256989 | G33: 76.760963 | H33: 76.649277 | I33: 76.764961 | J33: 77.032013 | K33: 77.403099 | L33: 77.753838 | M33: 77.960808 | N33: 78.240532 | O33: 78.361816 | P33: 78.47728 | Q33: 78.605728 | R33: 78.73288 | S33: 78.897552 | T33: 79.112183 | U33: 79.38546 | V33: 79.687889 | W33: 79.970261 | X33: 80.331863 | Y33: 80.704361 | Z33: 81.002327 | AA33: 81.234093 | AB33: 81.454033 | AC33: 81.732132 | AD33: 82.028252 | AE33: 82.348541 | AF33: 82.658882 | AG33: 82.967522 | AH33: 83.316269 | AI33: 83.685219 | AJ33: 84.045952 | AK33: 0.001711
A34: ISM000:fa_ChemicalandAl | B34: Chemical Manufacturing | C34: 720.88574 | D34: 746.0802 | E34: 786.0509 | F34: 802.65613 | G34: 827.37323 | H34: 849.51862 | I34: 869.1344 | J34: 891.36011 | K34: 912.52783 | L34: 931.92566 | M34: 956.94482 | N34: 977.96899 | O34: 998.81799 | P34: 1014.1586 | Q34: 1032.4705 | R34: 1050.4998 | S34: 1067.3884 | T34: 1079.8501 | U34: 1096.9585 | V34: 1116.3108 | W34: 1131.3572 | X34: 1152.411 | Y34: 1169.8191 | Z34: 1184.6204 | AA34: 1201.244 | AB34: 1218.3441 | AC34: 1230.6794 | AD34: 1247.9963 | AE34: 1267.3103 | AF34: 1285.1699 | AG34: 1303.6643 | AH34: 1326.3699 | AI34: 1344.1294 | AJ34: 1364.8359 | AK34: 0.019053
A35: ISM000:fa_BulkChemicals | B35: Bulk Chemicals | C35: 363.27762 | D35: 372.54971 | E35: 407.01526 | F35: 417.83719 | G35: 435.14813 | H35: 449.01062 | I35: 459.034 | J35: 470.87021 | K35: 479.74466 | L35: 486.33978 | M35: 499.13873 | N35: 507.04291 | O35: 516.83667 | P35: 521.03601 | Q35: 527.96069 | R35: 534.93414 | S35: 540.56073 | T35: 540.97046 | U35: 545.63074 | V35: 552.07416 | W35: 554.48499 | X35: 563.04749 | Y35: 567.85687 | Z35: 570.91248 | AA35: 575.94452 | AB35: 581.68872 | AC35: 582.09082 | AD35: 586.90485 | AE35: 590.09216 | AF35: 594.68433 | AG35: 599.2782 | AH35: 607.26862 | AI35: 609.6366 | AJ35: 614.66553 | AK35: 0.01577
A36: ISM000:fa_Inorganic | B36: Inorganic | C36: 40.983452 | D36: 41.330261 | E36: 41.2705 | F36: 41.09787 | G36: 40.759232 | H36: 40.57407 | I36: 40.66293 | J36: 40.92556 | K36: 41.25383 | L36: 41.557789 | M36: 41.805351 | N36: 42.06493 | O36: 42.225842 | P36: 42.231571 | Q36: 42.13176 | R36: 41.94931 | S36: 41.736191 | T36: 41.570572 | U36: 41.420052 | V36: 41.270741 | W36: 41.100422 | X36: 40.926022 | Y36: 40.712551 | Z36: 40.483952 | AA36: 40.241508 | AB36: 39.943401 | AC36: 39.683189 | AD36: 39.447762 | AE36: 39.201511 | AF36: 38.941849 | AG36: 38.686932 | AH36: 38.41494 | AI36: 38.129478 | AJ36: 37.839581 | AK36: -0.002754
A37: ISM000:fa_Organic | B37: Organic | C37: 192.24319 | D37: 197.9971 | E37: 224.9725 | F37: 228.0186 | G37: 240.0959 | H37: 249.2412 | I37: 254.2623 | J37: 261.25281 | K37: 265.61191 | L37: 268.1152 | M37: 277.08859 | N37: 280.83841 | O37: 288.1947 | P37: 290.2294 | Q37: 294.76321 | R37: 299.6254 | S37: 303.75159 | T37: 302.457 | U37: 305.85449 | V37: 311.4043 | W37: 311.9679 | X37: 318.7146 | Y37: 323.08139 | Z37: 326.19611 | AA37: 331.52911 | AB37: 338.1109 | AC37: 338.50659 | AD37: 343.056 | AE37: 345.854 | AF37: 349.94601 | AG37: 353.96719 | AH37: 361.38739 | AI37: 362.9718 | AJ37: 367.17859 | AK37: 0.019487
A38: ISM000:fa_Resins | B38: Resin, Synthetic Rubber, and Fibers | C38: 83.963051 | D38: 84.718231 | E38: 89.674492 | F38: 96.828949 | G38: 102.0571 | H38: 106.311 | I38: 110.3128 | J38: 113.909 | K38: 117.1831 | L38: 120.1439 | M38: 123.0199 | N38: 126.1295 | O38: 128.5527 | P38: 131.03101 | Q38: 133.5773 | R38: 135.89729 | S38: 137.6429 | T38: 139.39999 | U38: 140.7171 | V38: 141.6436 | W38: 143.5954 | X38: 145.4993 | Y38: 146.1801 | Z38: 146.45979 | AA38: 146.5012 | AB38: 146.06661 | AC38: 146.34489 | AD38: 146.7899 | AE38: 147.38789 | AF38: 148.10609 | AG38: 148.8183 | AH38: 149.48061 | AI38: 150.3 | AJ38: 151.22951 | AK38: 0.018273
... A60: ISM000:ha_TotalIndustri | B60: Total Industrial Value of Shipments | C60: 7444.4067 | D60: 7686.2876 | E60: 7987.1069 | F60: 8152.8706 | G60: 8276.1816 | H60: 8398.9766 | I60: 8524.0332 | J60: 8651.4619 | K60: 8802.5957 | L60: 8961.9629 | M60: 9111.3213 | N60: 9279.2227 | O60: 9426.7266 | P60: 9569.8477 | Q60: 9732.4912 | R60: 9890.1973 | S60: 10050.737 | T60: 10219.731 | U60: 10399.768 | V60: 10578.618 | W60: 10762.756 | X60: 10951.21 | Y60: 11125.877 | Z60: 11298.741 | AA60: 11474.664 | AB60: 11647.586 | AC60: 11829.552 | AD60: 12023.95 | AE60: 12232.412 | AF60: 12441.26 | AG60: 12657.642 | AH60: 12878.206 | AI60: 13090.664 | AJ60: 13311.65 | AK60: 0.017311
B62: Note: Totals may not equal sum of components due to independent rounding.
B63: Sources: 2017 and 2018: IHS Markit, Macroeconomic and Employment models, August 2018; and
B64: IHS Markit, Industry model, May 2018. Projections: U.S. Energy Information Administration, AEO2019 National Energy Modeling
B65: System run ref2019.d111618a.

Sheet hk gdp contribution
A1: https://www.censtatd.gov.hk/hkstat/sub/sp250.jsp?tableID=036&ID=0&productType=8 | K1: Source: Census and Statistical department
A2: Economic Activity | D2: 2018 | E2: 2019 | F2: 2020 | G2: 2021
A3: Agriculture, fishing, mining and quarrying | D3: 0.1 | E3: 0.1 | F3: 0.1 | G3: 0.1
A4: Manufacturing | D4: 1 | E4: 1.1 | F4: 1 | G4: 1
A5: Electricity, gas and water supply, and waste management | D5: 1.3 | E5: 1.2 | F5: 1.4 | G5: 1.3
A6: Construction | D6: 4.5 | E6: 4.2 | F6: 4.1 | G6: 4
A7: Services | D7: 93.1 | E7: 93.4 | F7: 93.4 | G7: 93.7
B8: Import/export, wholesale and retail trades | D8: 21.3 | E8: 19.5 | F8: 18.4 | G8: 19.4
C9: Import and export trade | D9: 17.2 | E9: 16.1 | F9: 15.9 | G9: 16.8
C10: Wholesale and retail trades | D10: 4.1 | E10: 3.4 | F10: 2.5 | G10: 2.6
B11: Accommodation and food services ^ | D11: 3.4 | E11: 2.8 | F11: 1.4 | G11: 1.7
B12: Transportation, storage, postal and courier services | D12: 5.9 | E12: 5.5 | F12: 4.5 | G12: 7.3
C13: Transportation and storage | D13: 5.5 | E13: 5.2 | F13: 4 | G13: 6.9
C14: Postal and courier services | D14: 0.3 | E14: 0.3 | F14: 0.4 | G14: 0.4
B15: Information and communications | D15: 3.4 | E15: 3.5 | F15: 3.7 | G15: 3.6
B16: Financing and insurance | D16: 19.8 | E16: 21.2 | F16: 23.4 | G16: 21.3
B17: Real estate, professional and business services | D17: 10.4 | E17: 10.1 | F17: 9.5 | G17: 9.1
C18: Real estate | D18: 4.6 | E18: 4.5 | F18: 4.2 | G18: 3.9
C19: Professional and business services | D19: 5.8 | E19: 5.6 | F19: 5.3 | G19: 5.3
B20: Public administration, social and personal services | D20: 18.5 | E20: 19.6 | F20: 20.7 | G20: 20.5
B21: Ownership of premises | D21: 10.5 | E21: 11.3 | F21: 11.8 | G21: 10.8
A22: GDP at basic prices | D22: 100 | E22: 100 | F22: 100 | G22: 100

Sheet HK GDP
A1: sourceL PCM | C1: (PCM was updated 21/08/23)
B2: GDP in 2021 HK$
B3: GDP | C3: Year-on-year change | D3: GDP per capita HK$
B4: HK$ million
A5: 2016^1 | B5: 2490598 | C5: 0.035 | D5: 349958.95
A6: 2017 | B6: 2659611 | C6: 0.035 | D6: 370791.18
A7: 2018 | B7: 2835429 | C7: 0.035 | D7: 392294.89
A8: 2019 | B8: 2845022 | C8: 0.035 | D8: 389121.37
A9: 2020 | B9: 2675793 | C9: 0.035 | D9: 362004.57
A10: 2021 | B10: 2867622 | C10: 0.035 | D10: 390969.06
A11: 2022 | B11: 2818046 | C11: 0.03 | D11: 391689.04
A12: 2023 | B12: 2902587 | C12: 0.03 | D12: 400395.54
A13: 2024 | B13: =B12*(1+C12) -> 2989664.6 | C13: 0.03 | D13: 410104.94
A14: 2025 | B14: =B13*(1+C13) -> 3079354.5 | C14: 0.03 | D14: 420464.38
A15: 2026 | B15: =B14*(1+C14) -> 3171735.2 | C15: 0.025 | D15: 430883.79
A16: 2027 | B16: =B15*(1+C15) -> 3251028.6 | C16: 0.025 | D16: 439132.41
A17: 2028 | B17: =B16*(1+C16) -> 3332304.3 | C17: 0.025 | D17: 447289.22
A18: 2029 | B18: =B17*(1+C17) -> 3415611.9 | C18: 0.025 | D18: 455560.76
A19: 2030 | B19: =B18*(1+C18) -> 3501002.2 | C19: 0.025 | D19: 464028.55
A20: 2031 | B20: =B19*(1+C19) -> 3588527.2 | C20: 0.025 | D20: 472803.03
A21: 2032 | B21: =B20*(1+C20) -> 3678240.4 | C21: 0.025 | D21: 481798.29
A22: 2033 | B22: =B21*(1+C21) -> 3770196.4 | C22: 0.025 | D22: 490994.17
A23: 2034 | B23: =B22*(1+C22) -> 3864451.3 | C23: 0.025 | D23: 500375.74
A24: 2035 | B24: =B23*(1+C23) -> 3961062.6 | C24: 0.025 | D24: 509848.39
... A38: 2049 | B38: =B37*(1+C37) -> 5596877.8 | C38: 0.025 | D38: 703744.31
A39: 2050 | B39: 6232620.9 | C39: 0.025 | D39: 785271.45
A40: 2050 | B40: 6232621 | C40: 0.025 | D40: 687434.06

Sheet calcualtion
A1: Nonfuel Revenue ($) | C1: 2017 | D1: 2018 | E1: 2019 | F1: 2020 | G1: 2021 | H1: 2022 | I1: 2023 | J1: 2024 | K1: 2025 | L1: 2026 | M1: 2027 | N1: 2028 | O1: 2029 | P1: 2030 | Q1: 2031 | R1: 2032 | S1: 2033 | T1: 2034 | U1: 2035 | V1: 2036 | W1: 2037 | X1: 2038 | Y1: 2039 | Z1: 2040 | AA1: 2041 | AB1: 2042 | AC1: 2043 | AD1: 2044 | AE1: 2045 | AF1: 2046 | AG1: 2047 | AH1: 2048 | AI1: 2049 | AJ1: 2050
A2: GDP | B2: 2021 HK$ million | C2: 2659611 | D2: 2835429 | E2: 2845022 | F2: 2675793 | G2: 2867622 | H2: 2818046 | I2: 2902587 | J2: 2989655 | K2: 3079355 | L2: 3171735 | M2: 3251029 | N2: 3332305 | O2: 3415612 | P2: 3501003 | Q2: 3588528 | R2: 3678241 | S2: 3770197 | T2: 3864452 | U2: 3961063 | V2: 4060090 | W2: 4161592 | X2: 4265632 | Y2: 4372273 | Z2: 4481579 | AA2: 4593619 | AB2: 4709459 | AC2: 4826171 | AD2: 4946825 | AE2: 5070496 | AF2: 5197258 | AG2: 5327190 | AH2: 5460369 | AI2: 5596879 | AJ2: 6232621
A3: percentage of agriculture | B3: % | C3: 0.1 | D3: 0.1 | E3: 0.1 | F3: 0.1 | G3: 0.1 | H3: 0.1 | I3: 0.1 | J3: 0.1 | K3: 0.1 | L3: 0.1 | M3: 0.1 | N3: 0.1 | O3: 0.1 | P3: 0.1 | Q3: 0.1 | R3: 0.1 | S3: 0.1 | T3: 0.1 | U3: 0.1 | V3: 0.1 | W3: 0.1 | X3: 0.1 | Y3: 0.1 | Z3: 0.1 | AA3: 0.1 | AB3: 0.1 | AC3: 0.1 | AD3: 0.1 | AE3: 0.1 | AF3: 0.1 | AG3: 0.1 | AH3: 0.1 | AI3: 0.1 | AJ3: 0.1
A4: percentage of industry | B4: % | C4: 1.1 | D4: =C4+($AJ$4-$C$4)/33 -> 1.069697 | E4: =D4+($AJ$4-$C$4)/33 -> 1.0393939 | F4: =E4+($AJ$4-$C$4)/33 -> 1.0090909 | G4: =F4+($AJ$4-$C$4)/33 -> 0.97878788 | H4: =G4+($AJ$4-$C$4)/33 -> 0.94848485 | I4: =H4+($AJ$4-$C$4)/33 -> 0.91818182 | J4: =I4+($AJ$4-$C$4)/33 -> 0.88787879 | K4: =J4+($AJ$4-$C$4)/33 -> 0.85757576 | ... AI4: =AH4+($AJ$4-$C$4)/33 -> 0.13030303 | AJ4: 0.1
A6: percentage of agriculture | B6: 2021 HK$ million | C6: =C2*C3/100 -> 2659.611 | D6: =D2*D3/100 -> 2835.429 | E6: =E2*E3/100 -> 2845.022 | F6: =F2*F3/100 -> 2675.793 | G6: =G2*G3/100 -> 2867.622 | H6: =H2*H3/100 -> 2818.046 | I6: =I2*I3/100 -> 2902.587 | J6: =J2*J3/100 -> 2989.655 | ... AJ6: =AJ2*AJ3/100 -> 6232.621
A7: percentage of industry | B7: 2021HK$ million | C7: =C2*C4/100 -> 29255.721 | D7: =D2*D4/100 -> 30330.498 | E7: =E2*E4/100 -> 29570.986 | F7: =F2*F4/100 -> 27001.184 | G7: =G2*G4/100 -> 28067.937 | H7: =H2*H4/100 -> 26728.739 | I7: =I2*I4/100 -> 26651.026 | J7: =J2*J4/100 -> 26544.513 | ... AJ7: =AJ2*AJ4/100 -> 6232.621
A9: percentage of agriculture | B9: 2016 million USD | C9: =C6/$B$15 -> 339.07607 | D9: =D6/$B$15 -> 361.49126 | E9: =E6/$B$15 -> 362.71428 | F9: =F6/$B$15 -> 341.13913 | G9: =G6/$B$15 -> 365.59557 | H9: =H6/$B$15 -> 359.27509 | I9: =I6/$B$15 -> 370.05329 | J9: =J6/$B$15 -> 381.15366 | ... AJ9: =AJ6/$B$15 -> 794.60216
A10: percentage of industry | B10: 2016 million USD | C10: =C7/$B$15 -> 3729.8368 | D10: =D7/$B$15 -> 3866.8611 | E10: =E7/$B$15 -> 3770.0302 | F10: =F7/$B$15 -> 3442.404 | G10: =G7/$B$15 -> 3578.4052 | H10: =H7/$B$15 -> 3407.6698 | I10: =I7/$B$15 -> 3397.762 | J10: =J7/$B$15 -> 3384.1825 | ... AJ10: =AJ7/$B$15 -> 794.60216
A12: percentage of agriculture | B12: 2012 value million USD | C12: =C9*$D$18 -> 257.69782 | D12: =D9*$D$18 -> 274.73336 | E12: =E9*$D$18 -> 275.66285 | F12: =F9*$D$18 -> 259.26574 | G12: =G9*$D$18 -> 277.85264 | H12: =H9*$D$18 -> 273.04907 | I12: =I9*$D$18 -> 281.2405 | J12: =J9*$D$18 -> 289.67679 | ... AJ12: =AJ9*$D$18 -> 603.89765
A13: percentage of industry | B13: 2012 value million USD | C13: =C10*$D$18 -> 2834.676 | D13: =D10*$D$18 -> 2938.8144 | E13: =E10*$D$18 -> 2865.223 | F13: =F10*$D$18 -> 2616.227 | G13: =G10*$D$18 -> 2719.5879 | H13: =H10*$D$18 -> 2589.829 | I13: =I10*$D$18 -> 2582.2991 | J13: =J10*$D$18 -> 2571.9787 | ... AJ13: =AJ10*$D$18 -> 603.89765
A15: 1 US Dollar = | B15: 7.8437 | C15: Hong Kong Dollars on 25/08/23
A16: https://www.exchange-rates.org/Rate/USD/HKD/12-30-2016
A18: 1.00 US Dollars of 2021 are worth 0.76 US Dollars of 2012. | D18: 0.76
A19: https://stats.areppim.com/calc/calc_usdlrxdeflator.php

Sheet TNRbI
A1: Nonfuel Revenue ($) | B1: 2017 | C1: 2018 | D1: 2019 | E1: 2020 | F1: 2021 | G1: 2022 | H1: 2023 | I1: 2024 | J1: 2025 | K1: 2026 | L1: 2027 | M1: 2028 | N1: 2029 | O1: 2030 | P1: 2031 | Q1: 2032 | R1: 2033 | S1: 2034 | T1: 2035 | U1: 2036 | V1: 2037 | W1: 2038 | X1: 2039 | Y1: 2040 | Z1: 2041 | AA1: 2042 | AB1: 2043 | AC1: 2044 | AD1: 2045 | AE1: 2046 | AF1: 2047 | AG1: 2048 | AH1: 2049 | AI1: 2050
A2: Cement and other carbonate use | B2: 0 | C2: 0 | D2: 0 | E2: 0 | F2: 0 | G2: 0 | H2: 0 | I2: 0 | J2: 0 | K2: 0 | L2: 0 | M2: 0 | N2: 0 | O2: 0 | P2: 0 | Q2: 0 | R2: 0 | S2: 0 | T2: 0 | U2: 0 | V2: 0 | W2: 0 | X2: 0 | Y2: 0 | Z2: 0 | AA2: 0 | AB2: 0 | AC2: 0 | AD2: 0 | AE2: 0 | AF2: 0 | AG2: 0 | AH2: 0 | AI2: 0
A3: Natural gas and petroleum systems | B3: 0 | C3: 0 | D3: 0 | E3: 0 | F3: 0 | G3: 0 | H3: 0 | I3: 0 | J3: 0 | K3: 0 | L3: 0 | M3: 0 | N3: 0 | O3: 0 | P3: 0 | Q3: 0 | R3: 0 | S3: 0 | T3: 0 | U3: 0 | V3: 0 | W3: 0 | X3: 0 | Y3: 0 | Z3: 0 | AA3: 0 | AB3: 0 | AC3: 0 | AD3: 0 | AE3: 0 | AF3: 0 | AG3: 0 | AH3: 0 | AI3: 0
A4: Iron and steel | B4: 0 | C4: 0 | D4: 0 | E4: 0 | F4: 0 | G4: 0 | H4: 0 | I4: 0 | J4: 0 | K4: 0 | L4: 0 | M4: 0 | N4: 0 | O4: 0 | P4: 0 | Q4: 0 | R4: 0 | S4: 0 | T4: 0 | U4: 0 | V4: 0 | W4: 0 | X4: 0 | Y4: 0 | Z4: 0 | AA4: 0 | AB4: 0 | AC4: 0 | AD4: 0 | AE4: 0 | AF4: 0 | AG4: 0 | AH4: 0 | AI4: 0
A5: Chemicals | B5: 0 | C5: 0 | D5: 0 | E5: 0 | F5: 0 | G5: 0 | H5: 0 | I5: 0 | J5: 0 | K5: 0 | L5: 0 | M5: 0 | N5: 0 | O5: 0 | P5: 0 | Q5: 0 | R5: 0 | S5: 0 | T5: 0 | U5: 0 | V5: 0 | W5: 0 | X5: 0 | Y5: 0 | Z5: 0 | AA5: 0 | AB5: 0 | AC5: 0 | AD5: 0 | AE5: 0 | AF5: 0 | AG5: 0 | AH5: 0 | AI5: 0
A6: Mining | B6: 0 | C6: 0 | D6: 0 | E6: 0 | F6: 0 | G6: 0 | H6: 0 | I6: 0 | J6: 0 | K6: 0 | L6: 0 | M6: 0 | N6: 0 | O6: 0 | P6: 0 | Q6: 0 | R6: 0 | S6: 0 | T6: 0 | U6: 0 | V6: 0 | W6: 0 | X6: 0 | Y6: 0 | Z6: 0 | AA6: 0 | AB6: 0 | AC6: 0 | AD6: 0 | AE6: 0 | AF6: 0 | AG6: 0 | AH6: 0 | AI6: 0
A7: Waste management | B7: 0 | C7: 0 | D7: 0 | E7: 0 | F7: 0 | G7: 0 | H7: 0 | I7: 0 | J7: 0 | K7: 0 | L7: 0 | M7: 0 | N7: 0 | O7: 0 | P7: 0 | Q7: 0 | R7: 0 | S7: 0 | T7: 0 | U7: 0 | V7: 0 | W7: 0 | X7: 0 | Y7: 0 | Z7: 0 | AA7: 0 | AB7: 0 | AC7: 0 | AD7: 0 | AE7: 0 | AF7: 0 | AG7: 0 | AH7: 0 | AI7: 0
A8: Agriculture | B8: =calcualtion!C12*1000000 -> 2.5769782e+08 | C8: =calcualtion!D12*1000000 -> 2.7473336e+08 | D8: =calcualtion!E12*1000000 -> 2.7566285e+08 | E8: =calcualtion!F12*1000000 -> 2.5926574e+08 | F8: =calcualtion!G12*1000000 -> 2.7785264e+08 | G8: =calcualtion!H12*1000000 -> 2.7304907e+08 | H8: =calcualtion!I12*1000000 -> 2.812405e+08 | I8: =calcualtion!J12*1000000 -> 2.8967679e+08 | ... AI8: =calcualtion!AJ12*1000000 -> 6.0389765e+08
A9: Other industries | B9: =calcualtion!C13*1000000 -> 2.834676e+09 | C9: =calcualtion!D13*1000000 -> 2.9388144e+09 | D9: =calcualtion!E13*1000000 -> 2.865223e+09 | E9: =calcualtion!F13*1000000 -> 2.616227e+09 | F9: =calcualtion!G13*1000000 -> 2.7195879e+09 | G9: =calcualtion!H13*1000000 -> 2.589829e+09 | H9: =calcualtion!I13*1000000 -> 2.5822991e+09 | I9: =calcualtion!J13*1000000 -> 2.5719787e+09 | ... AI9: =calcualtion!AJ13*1000000 -> 6.0389765e+08
