Workbook
Name gal_per_barrel: [1]About!$A$63

Sheet About
A1: BIFUbC BAU Industrial Fuel Use before CCS
A3: Sources: | B3: All Subscripts Except Waste Management
B4: Energy Information Administration
B5: 2021, 2022
B6: Annual Energy Outlook 2021 and 2022
B7: https://www.eia.gov/outlooks/aeo/tables_side.php
B8: See below for listing of which tables are used for which data
B10: 2020 Values
B11: provided on request from EIA
B12: indusa tab
B14: Waste Management
B15: Energy Information Administration
B16: 2021
B17: Miscellaneous Electric Load Consumption Characterization 2021 Update
B18: https://www.eia.gov/analysis/studies/demand/miscelectric/pdf/miscelectric.pdf
B21: Reallocating Portions of "Balance of Manufacturing" to Specific Industry Categories
B22: U.S. Bureau of Economic Analysis
B23: 2012
B24: Input-Output Accounts Data
B25: https://www.bea.gov/industry/input-output-accounts-data
B26: "Use of Commodities by Industry" table, 405-industry breakdown
A28: Note:
A29: The words "before CCS" in this variable name indicate that this is the fuel use by industry, excluding
A30: any fuel used to power the energy-intensive process of carbon capture and sequestration. If any CCS
A31: is performed by Industry in the BAU case, this is handled in CCS sector input variables, not here.
A33: EIA Data Source and Adjustments
A34: The AEO 2022 model was rebased to EIA's 2018 Manufacturing Energy Consumption Survey, which means there are some significant
A35: differences between consumption between AEO 2021 and AEO 2022. Rather than take 2020 values directly from AEO 2021, we use a file
A36: provided by the EIA which extends the 2018 MECS data back to year 2018.
A38: The following table provides a key to the AEO data sources available for each EPS Industry Category:
B40: EPS Industry Category | C40: AEO Data Source
B41: agriculture and forestry 01T03 | C41: Table 34
B42: coal mining 05 | C42: EIA indusa data set (contains more breakout than the regular AEO)
B43: oil and gas extraction 06 | C43: EIA indusa data set (contains more breakout than the regular AEO)
B44: other mining and quarrying 07T08 | C44: EIA indusa data set (contains more breakout than the regular AEO)
B45: food beverage and tobacco 10T12 | C45: Table 25 (only includes food, beverages and tobacco are part of "balance of manufacturing" in Table 33)
B46: textiles apparel and leather 13T15 | C46: AEO includes this in "balance of manufacturing" in Table 33.
B47: wood products 16 | C47: Table 33 (excludes furniture, which is part of "balance of manufacturing" in Table 33)
B48: pulp paper and printing 17T18 | C48: Table 26 (only includes pulp and paper, printing services are part of "balance of manufacturing" in Table 33)
B49: refined petroleum and coke 19 | C49: Table 24
B50: chemicals 20 | C50: Table 27
B51: rubber and plastic products 22 | C51: Table 33
... B65: construction 41T43 | C65: Table 34
A67: In general, the AEO provides data for industries that map well onto the EPS's Industry Categories.
A68: However, there are some differences. Since U.S. economic data (from the U.S. BEA or BLS) map
A69: perfectly onto the EPS's Industry Categories (for example, output, value added, and employment),
A70: we cannot allow the energy use to be grouped differently. Therefore, we make the following
A71: adjustments to align AEO energy use data with the BLS/BEA economic data and the EPS industry
A72: categories:
B73: Remove this from AEO's "Balance of Manufacturing" | C73: Add it to:
B74: beverages and tobacco | C74: food beverage and tobacco 10T12
B75: textiles, apparel, and leather | C75: textiles apparel and leather 13T15
B76: printing | C76: pulp paper and printing 17T18
B77: non-aluminum, nonferrous metals | C77: other metals 242
A79: Note that we do not need to separate furniture from "Balance of Manufacturing" because the BEA/BLS economic
A80: data also group furniture with their "other manufacturing" data
A82: This Variable Excludes All On-Site Energy Carrier Generation (Electricity, Heat, Hydrogen)
A83: This variable is for energy purchased and consumed by the Industry sector.
A84: Secondary energy, including electricity, heat, or hydrogen that is generated on-site and also consumed on-site
A85: (e.g. entirely within an industrial facility) should not be included in this variable.
A86: Any energy carrier (electricity, heat, hydrogen) demand entered here will be
A87: supplied by the electricity, district heat, or hydrogen supply sectors respectively.
A89: The "Renewables" rows in the U.S. source data are for on-site generation, including both
A90: electricity and non-electric energy from renewable sources. We do not include this line
A91: in electricity fuel use, because that total is used to calculate demand for electricity from
A92: the Electricity Supply sector (and therefore should exclude on-site generation).
... A117: Petroleum Fuels Mapping (based on closest BTU Content)
B118: Fuel Used in AEO | C118: Corresponding EPS Fuel
B119: Crude Oil | C119: Crude Oil
B120: Propane Heat and Power | C120: LPG/propane/butane
B121: Liquefied Petroleum Gas and Other Feedstocks | C121: LPG/propane/butane
B122: Motor Gasoline | C122: Petroleum Diesel
B123: Distillate Fuel Oil | C123: Petroleum Diesel
B124: Residual Fuel Oil | C124: Heavy or Residual Oil
B125: Petrochemical Feedstocks | C125: LPG/propane/butane
B126: Petroleum Coke | C126: Petroleum Diesel
B127: Asphalt and Road Oil | C127: Petroleum Diesel
B128: Miscellaneous Petroleum 3/ | C128: Heavy or Residual Oil

Sheet AEO T11 Petroleum 2022
B1: lowmacro.d011222a | C1: 2021 | D1: 2022 | E1: 2023 | F1: 2024 | G1: 2025 | H1: 2026 | I1: 2027 | J1: 2028 | K1: 2029 | L1: 2030 | M1: 2031 | N1: 2032 | O1: 2033 | P1: 2034 | Q1: 2035 | R1: 2036 | S1: 2037 | T1: 2038 | U1: 2039 | V1: 2040 | W1: 2041 | X1: 2042 | Y1: 2043 | Z1: 2044 | AA1: 2045 | AB1: 2046 | AC1: 2047 | AD1: 2048 | AE1: 2049 | AF1: 2050
A4: PSD000 | B4: 11. Petroleum and Other Liquids Supply and Disposition | AG4: Average
B5: (million barrels per day, unless otherwise noted) | AG5: Annual
AG6: Change
B7: Supply and Disposition | C7: 2021 | D7: 2022 | E7: 2023 | F7: 2024 | G7: 2025 | H7: 2026 | I7: 2027 | J7: 2028 | K7: 2029 | L7: 2030 | M7: 2031 | N7: 2032 | O7: 2033 | P7: 2034 | Q7: 2035 | R7: 2036 | S7: 2037 | T7: 2038 | U7: 2039 | V7: 2040 | W7: 2041 | X7: 2042 | Y7: 2043 | Z7: 2044 | AA7: 2045 | AB7: 2046 | AC7: 2047 | AD7: 2048 | AE7: 2049 | AF7: 2050 | AG7: 2021–2050
B9: Crude Oil
A10: PSD000:ba_DomesticCrude | B10: Domestic Crude Production 1/ | C10: 11.13137 | D10: 11.889478 | E10: 12.275469 | F10: 12.609236 | G10: 13.052148 | H10: 13.237693 | I10: 13.193173 | J10: 13.348814 | K10: 13.321289 | L10: 13.279312 | M10: 13.144327 | N10: 13.016207 | O10: 13.009095 | P10: 12.840246 | Q10: 12.759727 | R10: 12.67831 | S10: 12.545458 | T10: 12.455381 | U10: 12.459658 | V10: 12.500587 | W10: 12.419264 | X10: 12.381392 | Y10: 12.382156 | Z10: 12.307539 | AA10: 12.451011 | AB10: 12.532495 | AC10: 12.548349 | AD10: 12.492279 | AE10: 12.350566 | AF10: 12.663138 | AG10: 0.004456
A11: PSD000:ba_Alaska | B11: Alaska | C11: 0.440285 | D11: 0.413283 | E11: 0.394 | F11: 0.410075 | G11: 0.45657 | H11: 0.480052 | I11: 0.509854 | J11: 0.555656 | K11: 0.565951 | L11: 0.603593 | M11: 0.603082 | N11: 0.632631 | O11: 0.655834 | P11: 0.608421 | Q11: 0.562587 | R11: 0.523475 | S11: 0.489129 | T11: 0.457713 | U11: 0.427311 | V11: 0.399117 | W11: 0.372766 | X11: 0.387112 | Y11: 0.440329 | Z11: 0.49331 | AA11: 0.536112 | AB11: 0.537997 | AC11: 0.541833 | AD11: 0.604909 | AE11: 0.640281 | AF11: 0.704812 | AG11: 0.016357
A12: PSD000:ba_Lower48States | B12: Lower 48 States | C12: 10.691085 | D12: 11.476194 | E12: 11.881469 | F12: 12.199161 | G12: 12.595578 | H12: 12.757642 | I12: 12.683319 | J12: 12.793159 | K12: 12.755339 | L12: 12.675718 | M12: 12.541245 | N12: 12.383576 | O12: 12.353261 | P12: 12.231825 | Q12: 12.197142 | R12: 12.154836 | S12: 12.05633 | T12: 11.997668 | U12: 12.032348 | V12: 12.10147 | W12: 12.046497 | X12: 11.99428 | Y12: 11.941829 | Z12: 11.814229 | AA12: 11.914899 | AB12: 11.994498 | AC12: 12.006516 | AD12: 11.88737 | AE12: 11.710285 | AF12: 11.958327 | AG12: 0.00387
A13: PSD000:ba_NetImports | B13: Net Imports | C13: 3.23714 | D13: 4.19416 | E13: 4.152548 | F13: 3.877034 | G13: 3.537109 | H13: 3.305701 | I13: 3.298764 | J13: 3.111144 | K13: 3.134891 | L13: 3.133256 | M13: 3.141488 | N13: 3.378828 | O13: 3.304003 | P13: 3.387724 | Q13: 3.415774 | R13: 3.391183 | S13: 3.476847 | T13: 3.582338 | U13: 3.488359 | V13: 3.408924 | W13: 3.503948 | X13: 3.492462 | Y13: 3.525169 | Z13: 3.600249 | AA13: 3.368079 | AB13: 3.282752 | AC13: 3.169615 | AD13: 3.263203 | AE13: 3.406638 | AF13: 3.071324 | AG13: -0.001812
A14: PSD000:ba_GrossImports | B14: Gross Imports | C14: 6.263 | D14: 7.443 | E14: 7.518854 | F14: 7.215144 | G14: 6.878153 | H14: 6.604451 | I14: 6.609701 | J14: 6.468909 | K14: 6.427916 | L14: 6.403545 | M14: 6.487971 | N14: 6.648247 | O14: 6.573159 | P14: 6.718789 | Q14: 6.754125 | R14: 6.894927 | S14: 6.952014 | T14: 7.049026 | U14: 7.080949 | V14: 6.935089 | W14: 6.929074 | X14: 6.847743 | Y14: 6.697597 | Z14: 6.841123 | AA14: 6.528656 | AB14: 6.363351 | AC14: 6.282736 | AD14: 6.371989 | AE14: 6.519814 | AF14: 6.194175 | AG14: -0.000381
A15: PSD000:ba_Exports | B15: Exports | C15: 3.02586 | D15: 3.24884 | E15: 3.366306 | F15: 3.33811 | G15: 3.341043 | H15: 3.298751 | I15: 3.310937 | J15: 3.357765 | K15: 3.293025 | L15: 3.270289 | M15: 3.346483 | N15: 3.269419 | O15: 3.269156 | P15: 3.331066 | Q15: 3.338351 | R15: 3.503744 | S15: 3.475167 | T15: 3.466688 | U15: 3.59259 | V15: 3.526165 | W15: 3.425126 | X15: 3.355281 | Y15: 3.172428 | Z15: 3.240875 | AA15: 3.160577 | AB15: 3.080599 | AC15: 3.113122 | AD15: 3.108786 | AE15: 3.113176 | AF15: 3.122851 | AG15: 0.001089
A16: PSD000:ba_OtherCrudeSup | B16: Other Crude Supply 2/ | C16: 0.741 | D16: 0.203 | E16: 0.09795 | F16: 0.111 | G16: 0.05411 | H16: 0.10617 | I16: 0.10548 | J16: 0.07008 | K16: 0.06 | L16: 0.06 | M16: 0.06 | N16: 0 | O16: 0 | P16: 0 | Q16: 0 | R16: 0 | S16: 0 | T16: 0 | U16: 0 | V16: 0 | W16: 0 | X16: 0 | Y16: 0 | Z16: 0 | AA16: 0 | AB16: 0 | AC16: 0 | AD16: 0 | AE16: 0 | AF16: 0 | AG16: --
A17: PSD000:ba_TotalCrudeSup | B17: Total Crude Supply | C17: 15.109509 | D17: 16.286636 | E17: 16.525967 | F17: 16.597269 | G17: 16.643366 | H17: 16.649565 | I17: 16.597418 | J17: 16.530037 | K17: 16.51618 | L17: 16.472569 | M17: 16.345816 | N17: 16.395035 | O17: 16.313099 | P17: 16.22797 | Q17: 16.175501 | R17: 16.069494 | S17: 16.022305 | T17: 16.03772 | U17: 15.948017 | V17: 15.90951 | W17: 15.923212 | X17: 15.873854 | Y17: 15.907325 | Z17: 15.907787 | AA17: 15.81909 | AB17: 15.815247 | AC17: 15.717964 | AD17: 15.755483 | AE17: 15.757204 | AF17: 15.734463 | AG17: 0.001399
A19: PSD000:ca_NetProductImp | B19: Net Product Imports | C19: -3.404 | D19: -4.227 | E19: -4.772481 | F19: -5.014002 | G19: -5.141753 | H19: -5.107935 | I19: -5.031907 | J19: -5.008404 | K19: -5.134243 | L19: -5.219859 | M19: -5.125083 | N19: -5.179778 | O19: -5.092685 | P19: -5.112258 | Q19: -5.131105 | R19: -5.048989 | S19: -4.998381 | T19: -5.033622 | U19: -4.957439 | V19: -4.970531 | W19: -4.990724 | X19: -4.983805 | Y19: -5.049411 | Z19: -5.049631 | AA19: -5.000953 | AB19: -4.925579 | AC19: -4.780752 | AD19: -4.823569 | AE19: -4.789707 | AF19: -4.669329 | AG19: 0.010958
A20: PSD000:ca_GrossRefinedP | B20: Gross Refined Product Imports 3/ | C20: 1.045 | D20: 0.9 | E20: 0.540965 | F20: 0.536901 | G20: 0.573851 | H20: 0.625459 | I20: 0.64564 | J20: 0.644276 | K20: 0.628917 | L20: 0.637546 | M20: 0.635343 | N20: 0.65362 | O20: 0.653357 | P20: 0.653217 | Q20: 0.657973 | R20: 0.64936 | S20: 0.655096 | T20: 0.663124 | U20: 0.667046 | V20: 0.672157 | W20: 0.674622 | X20: 0.671073 | Y20: 0.676214 | Z20: 0.682098 | AA20: 0.690336 | AB20: 0.693412 | AC20: 0.707709 | AD20: 0.739248 | AE20: 0.7327 | AF20: 0.713065 | AG20: -0.013093
A21: PSD000:ca_UnfinishedOil | B21: Unfinished Oil Imports | C21: 0.601 | D21: 0.649 | E21: 0.632151 | F21: 0.646594 | G21: 0.64619 | H21: 0.599061 | I21: 0.597109 | J21: 0.595101 | K21: 0.584598 | L21: 0.582763 | M21: 0.589303 | N21: 0.579093 | O21: 0.577258 | P21: 0.575457 | Q21: 0.573956 | R21: 0.572121 | S21: 0.569918 | T21: 0.568292 | U21: 0.566248 | V21: 0.564759 | W21: 0.562567 | X21: 0.560732 | Y21: 0.558897 | Z21: 0.557062 | AA21: 0.555227 | AB21: 0.553392 | AC21: 0.551189 | AD21: 0.549354 | AE21: 0.54752 | AF21: 0.545685 | AG21: -0.003324
A22: PSD000:ca_BlendingCompo | B22: Blending Component Imports | C22: 0.53 | D22: 0.486 | E22: 0.602196 | F22: 0.628687 | G22: 0.639088 | H22: 0.613078 | I22: 0.563574 | J22: 0.524183 | K22: 0.49522 | L22: 0.474248 | M22: 0.438696 | N22: 0.430674 | O22: 0.411511 | P22: 0.396547 | Q22: 0.382388 | R22: 0.36969 | S22: 0.364156 | T22: 0.361914 | U22: 0.3574 | V22: 0.351959 | W22: 0.362047 | X22: 0.369328 | Y22: 0.36953 | Z22: 0.372241 | AA22: 0.377206 | AB22: 0.382094 | AC22: 0.385815 | AD22: 0.398275 | AE22: 0.402593 | AF22: 0.407672 | AG22: -0.009008
A23: PSD000:ca_Exports | B23: Exports | C23: 5.58 | D23: 6.262 | E23: 6.547793 | F23: 6.826184 | G23: 7.000882 | H23: 6.945532 | I23: 6.838229 | J23: 6.771964 | K23: 6.842978 | L23: 6.914416 | M23: 6.788424 | N23: 6.843165 | O23: 6.73481 | P23: 6.737479 | Q23: 6.745421 | R23: 6.640161 | S23: 6.587552 | T23: 6.626952 | U23: 6.548133 | V23: 6.559406 | W23: 6.589959 | X23: 6.584939 | Y23: 6.654051 | Z23: 6.661032 | AA23: 6.623722 | AB23: 6.554478 | AC23: 6.425466 | AD23: 6.510446 | AE23: 6.472519 | AF23: 6.335751 | AG23: 0.00439
A24: PSD000:ca_RefineryProce | B24: Refinery Processing Gain 4/ | C24: 0.96 | D24: 1.073 | E24: 1.000602 | F24: 0.964999 | G24: 0.975629 | H24: 0.988506 | I24: 0.966193 | J24: 0.980392 | K24: 0.989076 | L24: 1.004136 | M24: 0.997323 | N24: 1.004319 | O24: 1.008479 | P24: 1.033908 | Q24: 1.031711 | R24: 1.059599 | S24: 1.071261 | T24: 1.078428 | U24: 1.082535 | V24: 1.079149 | W24: 1.083481 | X24: 1.076755 | Y24: 1.067527 | Z24: 1.074581 | AA24: 1.065435 | AB24: 1.055148 | AC24: 1.050167 | AD24: 1.069102 | AE24: 1.078147 | AF24: 1.077413 | AG24: 0.003987
A25: PSD000:ProductStockDraw | B25: Product Stock Withdrawal | C25: 0.207 | D25: -0.116 | E25: 0 | F25: 0 | G25: 0 | H25: 0 | I25: 0 | J25: 0 | K25: 0 | L25: 0 | M25: 0 | N25: 0 | O25: 0 | P25: 0 | Q25: 0 | R25: 0 | S25: 0 | T25: 0 | U25: 0 | V25: 0 | W25: 0 | X25: 0 | Y25: 0 | Z25: 0 | AA25: 0 | AB25: 0 | AC25: 0 | AD25: 0 | AE25: 0 | AF25: 0 | AG25: --
A26: PSD000:ca_NaturalGasPla | B26: Natural Gas Plant Liquids | C26: 5.352244 | D26: 5.818853 | E26: 6.095093 | F26: 6.199161 | G26: 6.308229 | H26: 6.261226 | I26: 6.207613 | J26: 6.196386 | K26: 6.238307 | L26: 6.296646 | M26: 6.319704 | N26: 6.376586 | O26: 6.356655 | P26: 6.371484 | Q26: 6.396303 | R26: 6.344337 | S26: 6.319689 | T26: 6.321146 | U26: 6.362522 | V26: 6.400144 | W26: 6.414342 | X26: 6.498267 | Y26: 6.582048 | Z26: 6.570409 | AA26: 6.653749 | AB26: 6.681746 | AC26: 6.699253 | AD26: 6.707251 | AE26: 6.71034 | AF26: 6.747999 | AG26: 0.008023
A27: PSD000:from_Renewables | B27: Biofuels | C27: 1.070721 | D27: 1.155702 | E27: 1.136121 | F27: 1.134927 | G27: 1.134589 | H27: 1.133988 | I27: 1.132913 | J27: 1.131853 | K27: 1.130931 | L27: 1.130589 | M27: 1.130702 | N27: 1.130502 | O27: 1.130834 | P27: 1.130965 | Q27: 1.130826 | R27: 1.130789 | S27: 1.131159 | T27: 1.136443 | U27: 1.133184 | V27: 1.152908 | W27: 1.161384 | X27: 1.170208 | Y27: 1.178721 | Z27: 1.192037 | AA27: 1.202371 | AB27: 1.212905 | AC27: 1.225209 | AD27: 1.236486 | AE27: 1.251456 | AF27: 1.262136 | AG27: 0.005688
A28: PSD000:cb_TotalEthanol | B28: Ethanol (undenatured) | C28: 0.867395 | D28: 0.8941 | E28: 0.908598 | F28: 0.905286 | G28: 0.904918 | H28: 0.903162 | I28: 0.900128 | J28: 0.897371 | K28: 0.894905 | L28: 0.894096 | M28: 0.894649 | N28: 0.894581 | O28: 0.895917 | P28: 0.896592 | Q28: 0.896857 | R28: 0.896703 | S28: 0.897726 | T28: 0.899582 | U28: 0.902747 | V28: 0.907048 | W28: 0.910808 | X28: 0.915285 | Y28: 0.920009 | Z28: 0.925335 | AA28: 0.931836 | AB28: 0.939975 | AC28: 0.948851 | AD28: 0.95778 | AE28: 0.967349 | AF28: 0.978649 | AG28: 0.00417
A29: PSD000:ca_DomesticEthan | B29: Domestic Production | C29: 0.943897 | D29: 0.976075 | E29: 1.018353 | F29: 1.017787 | G29: 1.025995 | H29: 1.027261 | I29: 1.02733 | J29: 1.027758 | K29: 1.034911 | L29: 1.037597 | M29: 1.041743 | N29: 1.044947 | O29: 1.048755 | P29: 1.052864 | Q29: 1.059217 | R29: 1.063121 | S29: 1.068312 | T29: 1.074434 | U29: 1.090108 | V29: 1.090747 | W29: 1.100781 | X29: 1.108286 | Y29: 1.117845 | Z29: 1.137318 | AA29: 1.149122 | AB29: 1.162655 | AC29: 1.17697 | AD29: 1.191685 | AE29: 1.207161 | AF29: 1.226783 | AG29: 0.00908
A30: PSD000:ca_EthanolImport | B30: Net Imports | C30: -0.076502 | D30: -0.081975 | E30: -0.109756 | F30: -0.1125 | G30: -0.121077 | H30: -0.124098 | I30: -0.127202 | J30: -0.130387 | K30: -0.140006 | L30: -0.143501 | M30: -0.147094 | N30: -0.150366 | O30: -0.152838 | P30: -0.156272 | Q30: -0.16236 | R30: -0.166418 | S30: -0.170586 | T30: -0.174851 | U30: -0.187361 | V30: -0.1837 | W30: -0.189973 | X30: -0.193001 | Y30: -0.197836 | Z30: -0.211983 | AA30: -0.217286 | AB30: -0.22268 | AC30: -0.228118 | AD30: -0.233905 | AE30: -0.239811 | AF30: -0.248134 | AG30: 0.041409
A31: PSD000:ca_EthanolWithdr | B31: Stock Withdrawal | C31: 0 | D31: 0 | E31: 0 | F31: 0 | G31: 0 | H31: 0 | I31: 0 | J31: 0 | K31: 0 | L31: 0 | M31: 0 | N31: 0 | O31: 0 | P31: 0 | Q31: 0 | R31: 0 | S31: 0 | T31: 0 | U31: 0 | V31: 0 | W31: 0 | X31: 0 | Y31: 0 | Z31: 0 | AA31: 0 | AB31: 0 | AC31: 0 | AD31: 0 | AE31: 0 | AF31: 0 | AG31: --
A32: PSD000:cb_TotalBiodiesl | B32: Biodiesel | C32: 0.10957 | D32: 0.12343 | E32: 0.085491 | F32: 0.087156 | G32: 0.086575 | H32: 0.087775 | I32: 0.089271 | J32: 0.089958 | K32: 0.091673 | L32: 0.09195 | M32: 0.091554 | N32: 0.090458 | O32: 0.08909 | P32: 0.08837 | Q32: 0.087067 | R32: 0.087809 | S32: 0.088052 | T32: 0.090187 | U32: 0.090393 | V32: 0.102889 | W32: 0.105504 | X32: 0.108863 | Y32: 0.110526 | Z32: 0.116439 | AA32: 0.118634 | AB32: 0.119738 | AC32: 0.12037 | AD32: 0.121144 | AE32: 0.121403 | AF32: 0.122203 | AG32: --
A33: PSD000:cb_DomesticBiodi | B33: Domestic Production | C33: 0.112 | D33: 0.125859 | E33: 0.077513 | F33: 0.079138 | G33: 0.078517 | H33: 0.079676 | I33: 0.081133 | J33: 0.081779 | K33: 0.083453 | L33: 0.083689 | M33: 0.083251 | N33: 0.082114 | O33: 0.080704 | P33: 0.079942 | Q33: 0.078597 | R33: 0.079297 | S33: 0.079497 | T33: 0.081589 | U33: 0.081753 | V33: 0.094205 | W33: 0.096776 | X33: 0.100092 | Y33: 0.101712 | Z33: 0.10758 | AA33: 0.109731 | AB33: 0.110791 | AC33: 0.111378 | AD33: 0.112106 | AE33: 0.11232 | AF33: 0.113075 | AG33: 0.000329
A34: PSD000:cb_BiodieselImpo | B34: Net Imports | C34: -0.00243 | D34: -0.00243 | E34: 0.007978 | F34: 0.008018 | G34: 0.008058 | H34: 0.008098 | I34: 0.008139 | J34: 0.00818 | K34: 0.00822 | L34: 0.008262 | M34: 0.008303 | N34: 0.008344 | O34: 0.008386 | P34: 0.008428 | Q34: 0.00847 | R34: 0.008512 | S34: 0.008555 | T34: 0.008598 | U34: 0.008641 | V34: 0.008684 | W34: 0.008727 | X34: 0.008771 | Y34: 0.008815 | Z34: 0.008859 | AA34: 0.008903 | AB34: 0.008948 | AC34: 0.008993 | AD34: 0.009038 | AE34: 0.009083 | AF34: 0.009128 | AG34: --
A35: PSD000:cb_BiodieselWith | B35: Stock Withdrawal | C35: 0 | D35: 0 | E35: 0 | F35: 0 | G35: 0 | H35: 0 | I35: 0 | J35: 0 | K35: 0 | L35: 0 | M35: 0 | N35: 0 | O35: 0 | P35: 0 | Q35: 0 | R35: 0 | S35: 0 | T35: 0 | U35: 0 | V35: 0 | W35: 0 | X35: 0 | Y35: 0 | Z35: 0 | AA35: 0 | AB35: 0 | AC35: 0 | AD35: 0 | AE35: 0 | AF35: 0 | AG35: --
A36: PSD000:Other_BM-derived | B36: Other Biomass-derived Liquids 5/ | C36: 0.093755 | D36: 0.138173 | E36: 0.142032 | F36: 0.142485 | G36: 0.143096 | H36: 0.143051 | I36: 0.143513 | J36: 0.144524 | K36: 0.144353 | L36: 0.144542 | M36: 0.1445 | N36: 0.145463 | O36: 0.145827 | P36: 0.146004 | Q36: 0.146902 | R36: 0.146277 | S36: 0.145381 | T36: 0.146673 | U36: 0.140043 | V36: 0.142971 | W36: 0.145072 | X36: 0.146061 | Y36: 0.148185 | Z36: 0.150263 | AA36: 0.1519 | AB36: 0.153192 | AC36: 0.155988 | AD36: 0.157562 | AE36: 0.162704 | AF36: 0.161284 | AG36: 0.018882
A37: PSD000:Other_BM_Dome | B37: Domestic Production | C37: 0.069112 | D37: 0.100886 | E37: 0.107997 | F37: 0.108025 | G37: 0.108205 | H37: 0.107724 | I37: 0.107745 | J37: 0.108308 | K37: 0.107684 | L37: 0.107415 | M37: 0.106909 | N37: 0.107402 | O37: 0.10729 | P37: 0.106986 | Q37: 0.107396 | R37: 0.106277 | S37: 0.104881 | T37: 0.105667 | U37: 0.098524 | V37: 0.108887 | W37: 0.110561 | X37: 0.111119 | Y37: 0.112807 | Z37: 0.114442 | AA37: 0.115632 | AB37: 0.11647 | AC37: 0.118807 | AD37: 0.119916 | AE37: 0.124587 | AF37: 0.122691 | AG37: 0.019989
A38: PSD000:Other_BM_NetImp | B38: Net Imports | C38: 0.024644 | D38: 0.037287 | E38: 0.034035 | F38: 0.03446 | G38: 0.034891 | H38: 0.035327 | I38: 0.035769 | J38: 0.036216 | K38: 0.036668 | L38: 0.037127 | M38: 0.037591 | N38: 0.038061 | O38: 0.038536 | P38: 0.039018 | Q38: 0.039506 | R38: 0.04 | S38: 0.0405 | T38: 0.041006 | U38: 0.041519 | V38: 0.034084 | W38: 0.034511 | X38: 0.034942 | Y38: 0.035379 | Z38: 0.035821 | AA38: 0.036269 | AB38: 0.036722 | AC38: 0.037181 | AD38: 0.037646 | AE38: 0.038116 | AF38: 0.038593 | AG38: 0.015587
A39: PSD000:Other_BM_Stock | B39: Stock Withdrawal | C39: 0 | D39: 0 | E39: 0 | F39: 0 | G39: 0 | H39: 0 | I39: 0 | J39: 0 | K39: 0 | L39: 0 | M39: 0 | N39: 0 | O39: 0 | P39: 0 | Q39: 0 | R39: 0 | S39: 0 | T39: 0 | U39: 0 | V39: 0 | W39: 0 | X39: 0 | Y39: 0 | Z39: 0 | AA39: 0 | AB39: 0 | AC39: 0 | AD39: 0 | AE39: 0 | AF39: 0 | AG39: --
A40: PSD000:AllLiquidsfromGa | B40: Liquids from Gas | C40: 0 | D40: 0 | E40: 0 | F40: 0 | G40: 0 | H40: 0 | I40: 0 | J40: 0 | K40: 0 | L40: 0 | M40: 0 | N40: 0 | O40: 0 | P40: 0 | Q40: 0 | R40: 0 | S40: 0 | T40: 0 | U40: 0 | V40: 0 | W40: 0 | X40: 0 | Y40: 0 | Z40: 0 | AA40: 0 | AB40: 0 | AC40: 0 | AD40: 0 | AE40: 0 | AF40: 0 | AG40: --
A41: PSD000:ca_LiquidsfromCo | B41: Liquids from Coal | C41: 0 | D41: 0 | E41: 0 | F41: 0 | G41: 0 | H41: 0 | I41: 0 | J41: 0 | K41: 0 | L41: 0 | M41: 0 | N41: 0 | O41: 0 | P41: 0 | Q41: 0 | R41: 0 | S41: 0 | T41: 0 | U41: 0 | V41: 0 | W41: 0 | X41: 0 | Y41: 0 | Z41: 0 | AA41: 0 | AB41: 0 | AC41: 0 | AD41: 0 | AE41: 0 | AF41: 0 | AG41: --
A42: PSD000:ca_OtherOther | B42: Other 6/ | C42: 0.204 | D42: 0.204 | E42: 0.24125 | F42: 0.236141 | G42: 0.235012 | H42: 0.235472 | I42: 0.230299 | J42: 0.230071 | K42: 0.228028 | L42: 0.227871 | M42: 0.227135 | N42: 0.222182 | O42: 0.22186 | P42: 0.225621 | Q42: 0.224308 | R42: 0.228586 | S42: 0.230524 | T42: 0.231316 | U42: 0.230383 | V42: 0.226263 | W42: 0.22521 | X42: 0.222785 | Y42: 0.220057 | Z42: 0.222193 | AA42: 0.219587 | AB42: 0.216035 | AC42: 0.214285 | AD42: 0.217129 | AE42: 0.22031 | AF42: 0.218113 | AG42: 0.002309
A44: PSD000:da_TotalPrimaryS | B44: Total Primary Supply 7/ | C44: 19.499475 | D44: 20.195192 | E44: 20.226551 | F44: 20.118494 | G44: 20.155071 | H44: 20.160822 | I44: 20.10253 | J44: 20.060335 | K44: 19.968279 | L44: 19.911951 | M44: 19.895597 | N44: 19.948847 | O44: 19.938242 | P44: 19.877691 | Q44: 19.827545 | R44: 19.783815 | S44: 19.776556 | T44: 19.771431 | U44: 19.799202 | V44: 19.797443 | W44: 19.816906 | X44: 19.858063 | Y44: 19.906267 | Z44: 19.917377 | AA44: 19.959278 | AB44: 20.0555 | AC44: 20.126125 | AD44: 20.16188 | AE44: 20.227749 | AF44: 20.370794 | AG44: 0.001509
B47: Product Supplied
B48: by Fuel
A49: PSD000:ea_LiqPetGas | B49: Liquefied Petroleum Gases and Other 8/ | C49: 3.127 | D49: 3.323 | E49: 3.714857 | F49: 3.680768 | G49: 3.765748 | H49: 3.858406 | I49: 3.917768 | J49: 3.951531 | K49: 3.943332 | L49: 3.951994 | M49: 4.001838 | N49: 4.095806 | O49: 4.133923 | P49: 4.151421 | Q49: 4.170887 | R49: 4.185106 | S49: 4.206843 | T49: 4.227133 | U49: 4.255278 | V49: 4.270975 | W49: 4.286715 | X49: 4.317674 | Y49: 4.358402 | Z49: 4.359835 | AA49: 4.381007 | AB49: 4.428132 | AC49: 4.448447 | AD49: 4.430595 | AE49: 4.434793 | AF49: 4.487284 | AG49: 0.012532
A50: PSD000:ea_MotorGasoline | B50: Motor Gasoline 9/ | C50: 8.782 | D50: 8.973 | E50: 8.973271 | F50: 8.932969 | G50: 8.876821 | H50: 8.807067 | I50: 8.726618 | J50: 8.649973 | K50: 8.578621 | L50: 8.522937 | M50: 8.480564 | N50: 8.433201 | O50: 8.398709 | P50: 8.358372 | Q50: 8.314993 | R50: 8.277933 | S50: 8.251658 | T50: 8.232928 | U50: 8.227341 | V50: 8.22857 | W50: 8.232148 | X50: 8.241183 | Y50: 8.252725 | Z50: 8.271482 | AA50: 8.298276 | AB50: 8.339398 | AC50: 8.38658 | AD50: 8.433881 | AE50: 8.486462 | AF50: 8.553778 | AG50: -0.000908
A51: PSD000:ea_E85E85E85E85 | B51: of which: E85 10/ | C51: 0.021105 | D51: 0.02277 | E51: 0.023747 | F51: 0.023545 | G51: 0.023184 | H51: 0.022616 | I51: 0.021883 | J51: 0.021149 | K51: 0.020418 | L51: 0.019669 | M51: 0.018979 | N51: 0.018259 | O51: 0.017659 | P51: 0.017094 | Q51: 0.016612 | R51: 0.016222 | S51: 0.015916 | T51: 0.015688 | U51: 0.015643 | V51: 0.015554 | W51: 0.015564 | X51: 0.015407 | Y51: 0.015495 | Z51: 0.015814 | AA51: 0.015984 | AB51: 0.016179 | AC51: 0.016389 | AD51: 0.01665 | AE51: 0.016897 | AF51: 0.017232 | AG51: -0.006967
A52: PSD000:ea_JetFuel | B52: Jet Fuel 11/ | C52: 1.378 | D52: 1.603 | E52: 1.632198 | F52: 1.666027 | G52: 1.695105 | H52: 1.714869 | I52: 1.727475 | J52: 1.743383 | K52: 1.757344 | L52: 1.774232 | M52: 1.785162 | N52: 1.798758 | O52: 1.805781 | P52: 1.803751 | Q52: 1.808221 | R52: 1.813574 | S52: 1.822733 | T52: 1.831574 | U52: 1.844533 | V52: 1.858947 | W52: 1.869788 | X52: 1.883112 | Y52: 1.897106 | Z52: 1.909029 | AA52: 1.92523 | AB52: 1.94221 | AC52: 1.957966 | AD52: 1.972578 | AE52: 1.988608 | AF52: 2.010514 | AG52: 0.013111
A53: PSD000:ea_DistillateFue | B53: Distillate Fuel Oil 12/ | C53: 3.94 | D53: 4.066 | E53: 3.944513 | F53: 3.895084 | G53: 3.86677 | H53: 3.831583 | I53: 3.787262 | J53: 3.7549 | K53: 3.715634 | L53: 3.679131 | M53: 3.641455 | N53: 3.614773 | O53: 3.588087 | P53: 3.551691 | Q53: 3.520728 | R53: 3.493722 | S53: 3.471214 | T53: 3.453728 | U53: 3.44051 | V53: 3.429547 | W53: 3.41669 | X53: 3.407719 | Y53: 3.39998 | Z53: 3.386575 | AA53: 3.374169 | AB53: 3.371101 | AC53: 3.363438 | AD53: 3.350249 | AE53: 3.339895 | AF53: 3.341018 | AG53: -0.00567
A54: PSD000:eb_DieselAllSect | B54: of which: Diesel | C54: 3.662 | D54: 3.795 | E54: 3.543447 | F54: 3.501385 | G54: 3.478711 | H54: 3.450007 | I54: 3.412087 | J54: 3.384042 | K54: 3.347983 | L54: 3.315111 | M54: 3.281488 | N54: 3.256749 | O54: 3.232103 | P54: 3.199263 | Q54: 3.171939 | R54: 3.147967 | S54: 3.128216 | T54: 3.113036 | U54: 3.101505 | V54: 3.092648 | W54: 3.08211 | X54: 3.075501 | Y54: 3.070382 | Z54: 3.059787 | AA54: 3.050117 | AB54: 3.049247 | AC54: 3.043713 | AD54: 3.032522 | AE54: 3.023829 | AF54: 3.026226 | AG54: -0.006554
A55: PSD000:ea_ResidualFuel | B55: Residual Fuel Oil | C55: 0.28 | D55: 0.238 | E55: 0.259309 | F55: 0.25841 | G55: 0.259714 | H55: 0.257142 | I55: 0.251744 | J55: 0.249776 | K55: 0.2494 | L55: 0.248355 | M55: 0.247987 | N55: 0.251563 | O55: 0.25134 | P55: 0.25084 | Q55: 0.251208 | R55: 0.251025 | S55: 0.251245 | T55: 0.251036 | U55: 0.25181 | V55: 0.24298 | W55: 0.241256 | X55: 0.240722 | Y55: 0.236527 | Z55: 0.232377 | AA55: 0.230527 | AB55: 0.227666 | AC55: 0.227329 | AD55: 0.227457 | AE55: 0.226579 | AF55: 0.22716 | AG55: -0.007186
A56: PSD000:ea_Other | B56: Other 13/ | C56: 1.832 | D56: 1.946 | E56: 1.723729 | F56: 1.70463 | G56: 1.710884 | H56: 1.712569 | I56: 1.710115 | J56: 1.730677 | K56: 1.744265 | L56: 1.756167 | M56: 1.759861 | N56: 1.774837 | O56: 1.780883 | P56: 1.783613 | Q56: 1.78371 | R56: 1.786499 | S56: 1.797802 | T56: 1.800391 | U56: 1.805934 | V56: 1.791351 | W56: 1.795321 | X56: 1.792417 | Y56: 1.78564 | Z56: 1.783141 | AA56: 1.774966 | AB56: 1.771364 | AC56: 1.766835 | AD56: 1.772969 | AE56: 1.778128 | AF56: 1.778009 | AG56: -0.001031
B57: by Sector
A58: PSD000:fa_Residentialan | B58: Residential and Commercial | C58: 1.009218 | D58: 1.034456 | E58: 1.008523 | F58: 0.99852 | G58: 0.989504 | H58: 0.980614 | I58: 0.975585 | J58: 0.970425 | K58: 0.965274 | L58: 0.960575 | M58: 0.956035 | N58: 0.950797 | O58: 0.946334 | P58: 0.94258 | Q58: 0.939271 | R58: 0.936216 | S58: 0.933046 | T58: 0.929864 | U58: 0.927031 | V58: 0.923845 | W58: 0.920799 | X58: 0.917887 | Y58: 0.914663 | Z58: 0.911454 | AA58: 0.90886 | AB58: 0.906568 | AC58: 0.904783 | AD58: 0.903224 | AE58: 0.901578 | AF58: 0.900268 | AG58: -0.003931
A59: PSD000:fa_Industrial | B59: Industrial 14/ | C59: 5.244506 | D59: 5.372293 | E59: 5.584586 | F59: 5.538293 | G59: 5.636838 | H59: 5.738596 | I59: 5.800649 | J59: 5.860044 | K59: 5.871382 | L59: 5.89683 | M59: 5.954898 | N59: 6.074557 | O59: 6.127226 | P59: 6.148238 | Q59: 6.167869 | R59: 6.185688 | S59: 6.222788 | T59: 6.251523 | U59: 6.2917 | V59: 6.297082 | W59: 6.320348 | X59: 6.351971 | Y59: 6.388638 | Z59: 6.389232 | AA59: 6.403549 | AB59: 6.449202 | AC59: 6.466802 | AD59: 6.456789 | AE59: 6.468865 | AF59: 6.525923 | AG59: 0.007566
A60: PSD000:fa_Transportatio | B60: Transportation | C60: 13.078706 | D60: 13.509422 | E60: 13.72812 | F60: 13.677314 | G60: 13.625035 | H60: 13.541108 | I60: 13.426821 | J60: 13.331367 | K60: 13.233304 | L60: 13.157462 | M60: 13.089072 | N60: 13.026499 | O60: 12.967883 | P60: 12.891699 | Q60: 12.825808 | R60: 12.769456 | S60: 12.729765 | T60: 12.700137 | U60: 12.691615 | V60: 12.686998 | W60: 12.687475 | X60: 12.701134 | Y60: 12.716845 | Z60: 12.733018 | AA60: 12.764606 | AB60: 12.817345 | AC60: 12.872959 | AD60: 12.921991 | AE60: 12.978816 | AF60: 13.06673 | AG60: -3.2e-05
A61: PSD000:fa_ElectricPower | B61: Electric Power 15/ | C61: 0.053998 | D61: 0.051977 | E61: 0.051331 | F61: 0.048028 | G61: 0.04661 | H61: 0.044254 | I61: 0.041392 | J61: 0.039944 | K61: 0.039352 | L61: 0.03816 | M61: 0.036641 | N61: 0.036268 | O61: 0.036043 | P61: 0.035288 | Q61: 0.034407 | R61: 0.033765 | S61: 0.032898 | T61: 0.032107 | U61: 0.031774 | V61: 0.031247 | W61: 0.030191 | X61: 0.029019 | Y61: 0.027735 | Z61: 0.026483 | AA61: 0.025155 | AB61: 0.025035 | AC61: 0.024904 | AD61: 0.024869 | AE61: 0.024892 | AF61: 0.024986 | AG61: -0.026223
A62: PSD000:fa_balancesector | B62: Unspecified Sector 16/ | C62: 0.101697 | D62: 0.000666 | E62: -0.121739 | F62: -0.121543 | G62: -0.121535 | H62: -0.121193 | I62: -0.120465 | J62: -0.120004 | K62: -0.119371 | L62: -0.118923 | M62: -0.118372 | N62: -0.117961 | O62: -0.117469 | P62: -0.116683 | Q62: -0.116141 | R62: -0.115692 | S62: -0.115405 | T62: -0.115199 | U62: -0.115187 | V62: -0.115304 | W62: -0.115329 | X62: -0.115501 | Y62: -0.115733 | Z62: -0.115848 | AA62: -0.1161 | AB62: -0.116566 | AC62: -0.116941 | AD62: -0.117179 | AE62: -0.117504 | AF62: -0.118186 | AG62: --
A63: PSD000:fa_Total | B63: Total | C63: 19.339003 | D63: 20.149 | E63: 20.247879 | F63: 20.137888 | G63: 20.175043 | H63: 20.181641 | I63: 20.120983 | J63: 20.08024 | K63: 19.988594 | L63: 19.932816 | M63: 19.916866 | N63: 19.968939 | O63: 19.958723 | P63: 19.899687 | Q63: 19.849747 | R63: 19.807861 | S63: 19.801495 | T63: 19.796787 | U63: 19.825405 | V63: 19.822369 | W63: 19.841917 | X63: 19.882828 | Y63: 19.93038 | Z63: 19.942442 | AA63: 19.984179 | AB63: 20.079872 | AC63: 20.150595 | AD63: 20.187731 | AE63: 20.254463 | AF63: 20.397762 | AG63: 0.00184
A65: PSD000:ga_Discrepancy | B65: Discrepancy 17/ | C65: 0.160473 | D65: 0.046192 | E65: -0.021328 | F65: -0.019394 | G65: -0.019972 | H65: -0.020819 | I65: -0.018454 | J65: -0.019905 | K65: -0.020315 | L65: -0.020864 | M65: -0.021269 | N65: -0.020092 | O65: -0.020481 | P65: -0.021996 | Q65: -0.022202 | R65: -0.024046 | S65: -0.024939 | T65: -0.025356 | U65: -0.026203 | V65: -0.024925 | W65: -0.025011 | X65: -0.024765 | Y65: -0.024113 | Z65: -0.025064 | AA65: -0.0249 | AB65: -0.024372 | AC65: -0.024469 | AD65: -0.02585 | AE65: -0.026714 | AF65: -0.026968 | AG65: --
A67: PSD000:ha_DomesticRefin | B67: Domestic Refinery Distillation Capacity 18/ | C67: 18.124001 | D67: 18.129999 | E67: 18.592609 | F67: 18.665119 | G67: 18.737631 | H67: 18.810141 | I67: 18.810141 | J67: 18.810141 | K67: 18.810141 | L67: 18.810141 | M67: 18.810141 | N67: 18.810141 | O67: 18.810141 | P67: 18.810141 | Q67: 18.810141 | R67: 18.810141 | S67: 18.810141 | T67: 18.810141 | U67: 18.810141 | V67: 18.810141 | W67: 18.810141 | X67: 18.810141 | Y67: 18.810141 | Z67: 18.810141 | AA67: 18.810141 | AB67: 18.810141 | AC67: 18.810141 | AD67: 18.810141 | AE67: 18.810141 | AF67: 18.810141 | AG67: 0.001282
A68: PSD000:ha_CapacityUtili | B68: Capacity Utilization Rate (%) 19/ | C68: 86.334 | D68: 90.825996 | E68: 90.019287 | F68: 90.074989 | G68: 89.971771 | H68: 89.574478 | I68: 89.293961 | J68: 88.932365 | K68: 88.840218 | L68: 88.605263 | M68: 87.94313 | N68: 88.186844 | O68: 87.748222 | P68: 87.292671 | Q68: 87.011269 | R68: 86.444618 | S68: 86.190132 | T68: 86.269348 | U68: 85.789421 | V68: 85.58287 | W68: 85.652611 | X68: 85.387558 | Y68: 85.562599 | Z68: 85.562111 | AA68: 85.087646 | AB68: 85.064621 | AC68: 84.544197 | AD68: 84.741539 | AE68: 84.748459 | AF68: 84.624733 | AG68: -0.000689
A69: PSD000:total_gross_imp | B69: Total Gross Imports | C69: 8.477337 | D69: 9.523506 | E69: 9.33618 | F69: 9.069804 | G69: 8.780231 | H69: 8.485474 | I69: 8.45993 | J69: 8.276864 | K69: 8.18154 | L69: 8.143491 | M69: 8.197206 | N69: 8.358039 | O69: 8.262207 | P69: 8.391456 | Q69: 8.416417 | R69: 8.534611 | S69: 8.59024 | T69: 8.691959 | U69: 8.721804 | V69: 8.566731 | W69: 8.571548 | X69: 8.492589 | Y69: 8.346431 | Z69: 8.497204 | AA69: 8.196597 | AB69: 8.03792 | AC69: 7.973623 | AD69: 8.10555 | AE69: 8.249825 | AF69: 7.908318 | AG69: -0.002393
A70: PSD000:total_gross_exp | B70: Total Gross Exports | C70: 8.698484 | D70: 9.603465 | E70: 10.023854 | F70: 10.276794 | G70: 10.463002 | H70: 10.368382 | I70: 10.276368 | J70: 10.260115 | K70: 10.276009 | L70: 10.328207 | M70: 10.282001 | N70: 10.26295 | O70: 10.156804 | P70: 10.224817 | Q70: 10.246132 | R70: 10.310323 | S70: 10.233305 | T70: 10.268491 | U70: 10.328084 | V70: 10.269271 | W70: 10.205059 | X70: 10.133221 | Y70: 10.024317 | Z70: 10.113891 | AA70: 10.001585 | AB70: 9.857757 | AC70: 9.766706 | AD70: 9.853137 | AE70: 9.825506 | AF70: 9.706737 | AG70: 0.003789
A71: PSD000:total_net_import | B71: Total Net Imports | C71: -0.221148 | D71: -0.079959 | E71: -0.687675 | F71: -1.20699 | G71: -1.682772 | H71: -1.882908 | I71: -1.816438 | J71: -1.983251 | K71: -2.094469 | L71: -2.184716 | M71: -2.084795 | N71: -1.904911 | O71: -1.894597 | P71: -1.833362 | Q71: -1.829715 | R71: -1.775712 | S71: -1.643065 | T71: -1.576531 | U71: -1.60628 | V71: -1.702539 | W71: -1.633512 | X71: -1.640632 | Y71: -1.677886 | Z71: -1.616687 | AA71: -1.804988 | AB71: -1.819837 | AC71: -1.793082 | AD71: -1.747587 | AE71: -1.575681 | AF71: -1.798419 | AG71: 0.074946
A72: PSD000:ha_ImportShareof | B72: Net Import Share of Product Supplied (%) | C72: -1.134123 | D72: -0.395929 | E72: -3.399865 | F72: -5.999404 | G72: -8.349124 | H72: -9.339439 | I72: -9.035862 | J72: -9.886431 | K72: -10.48898 | L72: -10.971879 | M72: -10.478678 | N72: -9.548976 | O72: -9.502327 | P72: -9.223207 | Q72: -9.228146 | R72: -8.975577 | S72: -8.308146 | T72: -7.973784 | U72: -8.112856 | V72: -8.599792 | W72: -8.243016 | X72: -8.261791 | Y72: -8.428928 | Z72: -8.116961 | AA72: -9.043355 | AB72: -9.074008 | AC72: -8.909227 | AD72: -8.66778 | AE72: -7.789699 | AF72: -8.828415 | AG72: 0.073326
B73: Expenditures for Imported Crude Oil and
A74: PSD000:ha_PetroleumProd | B74: Petroleum Products (billion 2021 dollars) | C74: 155.21623 | D74: 185.37291 | E74: 173.63461 | F74: 181.41414 | G74: 177.80328 | H74: 173.57982 | I74: 178.32516 | J74: 176.64185 | K74: 177.43938 | L74: 178.46866 | M74: 183.11549 | N74: 189.599 | O74: 189.32494 | P74: 194.05011 | Q74: 195.36751 | R74: 200.26335 | S74: 202.39774 | T74: 207.81213 | U74: 208.35976 | V74: 212.51984 | W74: 215.29132 | X74: 214.89412 | Y74: 215.34541 | Z74: 223.54488 | AA74: 215.35455 | AB74: 214.21584 | AC74: 212.4077 | AD74: 214.62738 | AE74: 219.79674 | AF74: 208.10915 | AG74: 0.010163
B77: 1/ Includes lease condensate.
B78: 2/ Strategic petroleum reserve stock additions plus unaccounted for crude oil and crude oil stock withdrawals.
B79: 3/ Includes other hydrocarbons and alcohols.
B80: 4/ The volumetric amount by which total output is greater than input due to the processing of crude oil into products which, in total,
B81: have a lower specific gravity than the crude oil processed.
B82: 5/ Includes pyrolysis oils, biomass-derived Fischer-Tropsch liquids, biobutanol, and renewable feedstocks used for the
B83: on-site production of diesel and gasoline.
B84: 6/ Includes domestic sources of other blending components, other hydrocarbons, and ethers.
B85: 7/ Total crude supply, net product imports, refinery processing gain, product stock withdrawal, natural gas plant liquids, supply from
B86: renewable sources, liquids from gas, liquids from coal, and other supply.
B87: 8/ Includes ethane, natural gasoline, and refinery olefins.
B88: 9/ Includes ethanol and ethers blended into gasoline.
... B105: National Energy Modeling System run ref2022.d011222a. Projections: EIA, AEO2022 National Energy Modeling System run ref2022.d011222a.

Sheet AEO T11 Petroleum 2021
B1: ref2021.d113020a | C1: 2020 | D1: 2021 | E1: 2022 | F1: 2023 | G1: 2024 | H1: 2025 | I1: 2026 | J1: 2027 | K1: 2028 | L1: 2029 | M1: 2030 | N1: 2031 | O1: 2032 | P1: 2033 | Q1: 2034 | R1: 2035 | S1: 2036 | T1: 2037 | U1: 2038 | V1: 2039 | W1: 2040 | X1: 2041 | Y1: 2042 | Z1: 2043 | AA1: 2044 | AB1: 2045 | AC1: 2046 | AD1: 2047 | AE1: 2048 | AF1: 2049 | AG1: 2050 | AJ1: Difference between 2020 and 2021
C3: Report | D3: Annual Energy Outlook 2021
C4: Scenario | D4: ref2021 | G4: Reference case
C5: Datekey | D5: d113020a
C6: Release Date | E6: January 2021
A10: PSD000 | B10: 11. Petroleum and Other Liquids Supply and Disposition | AH10: Compound
B11: (million barrels per day, unless otherwise noted) | AH11: Growth
AH12: 2020-2050
B13: Supply and Disposition | C13: 2020 | D13: 2021 | E13: 2022 | F13: 2023 | G13: 2024 | H13: 2025 | I13: 2026 | J13: 2027 | K13: 2028 | L13: 2029 | M13: 2030 | N13: 2031 | O13: 2032 | P13: 2033 | Q13: 2034 | R13: 2035 | S13: 2036 | T13: 2037 | U13: 2038 | V13: 2039 | W13: 2040 | X13: 2041 | Y13: 2042 | Z13: 2043 | AA13: 2044 | AB13: 2045 | AC13: 2046 | AD13: 2047 | AE13: 2048 | AF13: 2049 | AG13: 2050 | AH13: (percent)
B15: Crude Oil
A16: PSD000:ba_DomesticCrude | B16: Domestic Crude Production 1/ | C16: 11.470048 | D16: 11.166155 | E16: 11.626638 | F16: 12.329649 | G16: 12.74404 | H16: 13.231529 | I16: 13.497977 | J16: 13.594147 | K16: 13.710074 | L16: 13.718638 | M16: 13.76896 | N16: 13.795834 | O16: 13.768938 | P16: 13.861969 | Q16: 13.883383 | R16: 13.763157 | S16: 13.566243 | T16: 13.451651 | U16: 13.348973 | V16: 13.283369 | W16: 13.173889 | X16: 13.118857 | Y16: 13.146461 | Z16: 13.310509 | AA16: 13.351305 | AB16: 13.223972 | AC16: 13.249136 | AD16: 13.294786 | AE16: 13.227971 | AF16: 13.159329 | AG16: 12.87295 | AH16: 0.003854 | AJ16: =C16/D16 -> 1.0272155
A17: PSD000:ba_Alaska | B17: Alaska | C17: 0.457568 | D17: 0.485528 | E17: 0.472 | F17: 0.553932 | G17: 0.57012 | H17: 0.574502 | I17: 0.600343 | J17: 0.638631 | K17: 0.620714 | L17: 0.597336 | M17: 0.56874 | N17: 0.57986 | O17: 0.630835 | P17: 0.671899 | Q17: 0.690727 | R17: 0.670324 | S17: 0.641218 | T17: 0.610044 | U17: 0.581141 | V17: 0.554657 | W17: 0.555257 | X17: 0.597369 | Y17: 0.60897 | Z17: 0.740398 | AA17: 0.791331 | AB17: 0.759136 | AC17: 0.730634 | AD17: 0.705085 | AE17: 0.680323 | AF17: 0.658361 | AG17: 0.617198 | AH17: 0.010025 | AJ17: =C17/D17 -> 0.94241321
A18: PSD000:ba_Lower48States | B18: Lower 48 States | C18: 11.01248 | D18: 10.680627 | E18: 11.154638 | F18: 11.775717 | G18: 12.173921 | H18: 12.657028 | I18: 12.897635 | J18: 12.955516 | K18: 13.08936 | L18: 13.121303 | M18: 13.200219 | N18: 13.215974 | O18: 13.138103 | P18: 13.190071 | Q18: 13.192656 | R18: 13.092833 | S18: 12.925025 | T18: 12.841607 | U18: 12.767832 | V18: 12.728712 | W18: 12.618632 | X18: 12.521488 | Y18: 12.537491 | Z18: 12.570111 | AA18: 12.559974 | AB18: 12.464836 | AC18: 12.518502 | AD18: 12.589702 | AE18: 12.547648 | AF18: 12.500969 | AG18: 12.255751 | AH18: 0.003572 | AJ18: =C18/D18 -> 1.0310706
A19: PSD000:ba_NetImports | B19: Net Imports | C19: 2.83 | D19: 4.5 | E19: 4.97122 | F19: 4.794863 | G19: 4.470877 | H19: 4.198047 | I19: 4.015316 | J19: 3.97385 | K19: 3.856572 | L19: 3.847551 | M19: 3.808479 | N19: 3.760889 | O19: 3.784652 | P19: 3.641997 | Q19: 3.609391 | R19: 3.708626 | S19: 3.935255 | T19: 4.045917 | U19: 4.142609 | V19: 4.127064 | W19: 4.259272 | X19: 4.304543 | Y19: 4.313911 | Z19: 4.110817 | AA19: 4.074094 | AB19: 4.18912 | AC19: 4.129763 | AD19: 4.11883 | AE19: 4.203545 | AF19: 4.232956 | AG19: 4.496002 | AH19: 0.01555 | AJ19: =C19/D19 -> 0.62888889
A20: PSD000:ba_GrossImports | B20: Gross Imports | C20: 6.053 | D20: 7.55 | E20: 7.787116 | F20: 7.747426 | G20: 7.818967 | H20: 7.530605 | I20: 7.532843 | J20: 7.236153 | K20: 7.035046 | L20: 7.19906 | M20: 6.94103 | N20: 7.047481 | O20: 6.85515 | P20: 6.740557 | Q20: 6.838348 | R20: 6.962935 | S20: 7.224354 | T20: 7.286689 | U20: 7.339459 | V20: 7.553651 | W20: 7.465834 | X20: 7.463062 | Y20: 7.529857 | Z20: 7.372736 | AA20: 7.244863 | AB20: 7.257197 | AC20: 7.153084 | AD20: 7.193253 | AE20: 7.311895 | AF20: 7.347315 | AG20: 7.624471 | AH20: 0.007723 | AJ20: =C20/D20 -> 0.80172185
A21: PSD000:ba_Exports | B21: Exports | C21: 3.223 | D21: 3.05 | E21: 2.815896 | F21: 2.952563 | G21: 3.34809 | H21: 3.332558 | I21: 3.517526 | J21: 3.262303 | K21: 3.178474 | L21: 3.351509 | M21: 3.132551 | N21: 3.286592 | O21: 3.070499 | P21: 3.09856 | Q21: 3.228958 | R21: 3.25431 | S21: 3.289099 | T21: 3.240773 | U21: 3.19685 | V21: 3.426587 | W21: 3.206562 | X21: 3.158519 | Y21: 3.215945 | Z21: 3.261918 | AA21: 3.170769 | AB21: 3.068078 | AC21: 3.023321 | AD21: 3.074423 | AE21: 3.10835 | AF21: 3.114359 | AG21: 3.128469 | AH21: -0.000992 | AJ21: =C21/D21 -> 1.0567213
A22: PSD000:ba_OtherCrudeSup | B22: Other Crude Supply 2/ | C22: 0.042 | D22: 0.296 | E22: 0.03425 | F22: 0.0774 | G22: 0.09563 | H22: 0.07192 | I22: 0 | J22: 0 | K22: 0 | L22: 0 | M22: 0 | N22: 0 | O22: 0 | P22: 0 | Q22: 0 | R22: 0 | S22: 0 | T22: 0 | U22: 0 | V22: 0 | W22: 0 | X22: 0 | Y22: 0 | Z22: 0 | AA22: 0 | AB22: 0 | AC22: 0 | AD22: 0 | AE22: 0 | AF22: 0 | AG22: 0 | AH22: -- | AJ22: =C22/D22 -> 0.14189189
A23: PSD000:ba_TotalCrudeSup | B23: Total Crude Supply | C23: 14.342048 | D23: 15.962154 | E23: 16.632109 | F23: 17.201912 | G23: 17.310549 | H23: 17.501497 | I23: 17.513294 | J23: 17.567997 | K23: 17.566647 | L23: 17.566189 | M23: 17.577438 | N23: 17.556723 | O23: 17.553589 | P23: 17.503967 | Q23: 17.492773 | R23: 17.471783 | S23: 17.501499 | T23: 17.497566 | U23: 17.491583 | V23: 17.410433 | W23: 17.433161 | X23: 17.423401 | Y23: 17.460373 | Z23: 17.421326 | AA23: 17.4254 | AB23: 17.413092 | AC23: 17.378899 | AD23: 17.413616 | AE23: 17.431517 | AF23: 17.392284 | AG23: 17.368952 | AH23: 0.006403 | AJ23: =C23/D23 -> 0.8985033
AJ24: =C24/D24 -> #DIV/0!
A25: PSD000:ca_NetProductImp | B25: Net Product Imports | C25: -3.217 | D25: -3.635 | E25: -4.651141 | F25: -5.329247 | G25: -5.400157 | H25: -5.549729 | I25: -5.638276 | J25: -5.733 | K25: -5.730247 | L25: -5.797076 | M25: -5.845665 | N25: -5.837363 | O25: -5.795742 | P25: -5.718789 | Q25: -5.692716 | R25: -5.612529 | S25: -5.613312 | T25: -5.574323 | U25: -5.532296 | V25: -5.450375 | W25: -5.456642 | X25: -5.385563 | Y25: -5.377039 | Z25: -5.283255 | AA25: -5.243139 | AB25: -5.137103 | AC25: -5.021393 | AD25: -4.954345 | AE25: -4.876846 | AF25: -4.742838 | AG25: -4.633424 | AH25: 0.012236 | AJ25: =C25/D25 -> 0.88500688
A26: PSD000:ca_GrossRefinedP | B26: Gross Refined Product Imports 3/ | C26: 0.974 | D26: 0.852 | E26: 0.657141 | F26: 0.658067 | G26: 0.651951 | H26: 0.638855 | I26: 0.72687 | J26: 0.723677 | K26: 0.712943 | L26: 0.701428 | M26: 0.735705 | N26: 0.71881 | O26: 0.716891 | P26: 0.716738 | Q26: 0.720995 | R26: 0.728537 | S26: 0.720787 | T26: 0.72819 | U26: 0.733582 | V26: 0.741212 | W26: 0.747285 | X26: 0.761693 | Y26: 0.761609 | Z26: 0.763732 | AA26: 0.765033 | AB26: 0.773424 | AC26: 0.758651 | AD26: 0.769778 | AE26: 0.79673 | AF26: 0.797911 | AG26: 0.762324 | AH26: -0.008135 | AJ26: =C26/D26 -> 1.1431925
A27: PSD000:ca_UnfinishedOil | B27: Unfinished Oil Imports | C27: 0.563 | D27: 0.698 | E27: 0.664354 | F27: 0.657648 | G27: 0.646594 | H27: 0.64619 | I27: 0.599429 | J27: 0.597477 | K27: 0.595157 | L27: 0.584598 | M27: 0.583131 | N27: 0.581296 | O27: 0.579093 | P27: 0.577258 | Q27: 0.575791 | R27: 0.573956 | S27: 0.572121 | T27: 0.555167 | U27: 0.55344 | V27: 0.566616 | W27: 0.564781 | X27: 0.547568 | Y27: 0.545365 | Z27: 0.558529 | AA27: 0.556694 | AB27: 0.554859 | AC27: 0.553024 | AD27: 0.551189 | AE27: 0.549354 | AF27: 0.54752 | AG27: 0.545685 | AH27: -0.001041 | AJ27: =C27/D27 -> 0.80659026
A28: PSD000:ca_BlendingCompo | B28: Blending Component Imports | C28: 0.359 | D28: 0.442 | E28: 0.598704 | F28: 0.6216 | G28: 0.635292 | H28: 0.64028 | I28: 0.610671 | J28: 0.564376 | K28: 0.525891 | L28: 0.496328 | M28: 0.477206 | N28: 0.448678 | O28: 0.426883 | P28: 0.40751 | Q28: 0.396023 | R28: 0.380087 | S28: 0.381256 | T28: 0.375105 | U28: 0.370709 | V28: 0.365776 | W28: 0.36375 | X28: 0.359704 | Y28: 0.359535 | Z28: 0.362024 | AA28: 0.363643 | AB28: 0.361096 | AC28: 0.362296 | AD28: 0.368013 | AE28: 0.375189 | AF28: 0.381407 | AG28: 0.386442 | AH28: 0.002458 | AJ28: =C28/D28 -> 0.81221719
A29: PSD000:ca_Exports | B29: Exports | C29: 5.113 | D29: 5.627 | E29: 6.57134 | F29: 7.266561 | G29: 7.333994 | H29: 7.475054 | I29: 7.575245 | J29: 7.61853 | K29: 7.564239 | L29: 7.579431 | M29: 7.641706 | N29: 7.586148 | O29: 7.518609 | P29: 7.420295 | Q29: 7.385525 | R29: 7.295109 | S29: 7.287476 | T29: 7.232786 | U29: 7.190026 | V29: 7.123981 | W29: 7.132459 | X29: 7.054527 | Y29: 7.043549 | Z29: 6.96754 | AA29: 6.928508 | AB29: 6.826482 | AC29: 6.695365 | AD29: 6.643326 | AE29: 6.59812 | AF29: 6.469676 | AG29: 6.327875 | AH29: 0.007131 | AJ29: =C29/D29 -> 0.9086547
A30: PSD000:ca_RefineryProce | B30: Refinery Processing Gain 4/ | C30: 0.963 | D30: 1.093 | E30: 1.011712 | F30: 1.006525 | G30: 0.96884 | H30: 0.988423 | I30: 1.003248 | J30: 0.990855 | K30: 1.001114 | L30: 1.014459 | M30: 1.010121 | N30: 1.013339 | O30: 1.018253 | P30: 1.022922 | Q30: 1.044129 | R30: 1.04602 | S30: 1.072378 | T30: 1.078819 | U30: 1.084642 | V30: 1.097418 | W30: 1.093501 | X30: 1.095632 | Y30: 1.099306 | Z30: 1.083379 | AA30: 1.078065 | AB30: 1.075419 | AC30: 1.078596 | AD30: 1.081911 | AE30: 1.082935 | AF30: 1.081192 | AG30: 1.088299 | AH30: 0.004086 | AJ30: =C30/D30 -> 0.8810613
A31: PSD000:ProductStockDraw | B31: Product Stock Withdrawal | C31: -0.083 | D31: 0.052 | E31: 0 | F31: 0 | G31: 0 | H31: 0 | I31: 0 | J31: 0 | K31: 0 | L31: 0 | M31: 0 | N31: 0 | O31: 0 | P31: 0 | Q31: 0 | R31: 0 | S31: 0 | T31: 0 | U31: 0 | V31: 0 | W31: 0 | X31: 0 | Y31: 0 | Z31: 0 | AA31: 0 | AB31: 0 | AC31: 0 | AD31: 0 | AE31: 0 | AF31: 0 | AG31: 0 | AH31: -- | AJ31: =C31/D31 -> -1.5961538
A32: PSD000:ca_NaturalGasPla | B32: Natural Gas Plant Liquids | C32: 5.02603 | D32: 5.200461 | E32: 5.481331 | F32: 5.755203 | G32: 5.85873 | H32: 5.885843 | I32: 5.962521 | J32: 6.001111 | K32: 5.988202 | L32: 6.040942 | M32: 6.1231 | N32: 6.15308 | O32: 6.126073 | P32: 6.131374 | Q32: 6.158622 | R32: 6.153062 | S32: 6.125976 | T32: 6.123695 | U32: 6.121618 | V32: 6.141864 | W32: 6.149165 | X32: 6.135815 | Y32: 6.171154 | Z32: 6.223928 | AA32: 6.263006 | AB32: 6.266887 | AC32: 6.247303 | AD32: 6.218316 | AE32: 6.216486 | AF32: 6.237903 | AG32: 6.25917 | AH32: 0.007341 | AJ32: =C32/D32 -> 0.96645855
A33: PSD000:from_Renewables | B33: Biofuels | C33: 0.967844 | D33: 1.097252 | E33: 1.104007 | F33: 1.120142 | G33: 1.122895 | H33: 1.126976 | I33: 1.130516 | J33: 1.133907 | K33: 1.137306 | L33: 1.140499 | M33: 1.144013 | N33: 1.14387 | O33: 1.144006 | P33: 1.144678 | Q33: 1.145682 | R33: 1.146916 | S33: 1.147554 | T33: 1.148103 | U33: 1.148892 | V33: 1.150137 | W33: 1.151594 | X33: 1.152909 | Y33: 1.154606 | Z33: 1.15653 | AA33: 1.162142 | AB33: 1.168497 | AC33: 1.175066 | AD33: 1.182199 | AE33: 1.189561 | AF33: 1.200335 | AG33: 1.211093 | AH33: 0.007502 | AJ33: =C33/D33 -> 0.88206173
A34: PSD000:cb_TotalEthanol | B34: Ethanol | C34: 0.801417 | D34: 0.883641 | E34: 0.873613 | F34: 0.875332 | G34: 0.873404 | H34: 0.874846 | I34: 0.874832 | J34: 0.874454 | K34: 0.874113 | L34: 0.873241 | M34: 0.873034 | N34: 0.873036 | O34: 0.87352 | P34: 0.875343 | Q34: 0.878042 | R34: 0.881248 | S34: 0.883171 | T34: 0.88528 | U34: 0.8878 | V34: 0.891139 | W34: 0.894868 | X34: 0.898296 | Y34: 0.902709 | Z34: 0.907862 | AA34: 0.913282 | AB34: 0.918505 | AC34: 0.924127 | AD34: 0.929622 | AE34: 0.935832 | AF34: 0.942592 | AG34: 0.949442 | AH34: 0.005666 | AJ34: =C34/D34 -> 0.90694864
A35: PSD000:ca_DomesticEthan | B35: Domestic Production | C35: 0.87759 | D35: 0.967299 | E35: 0.980691 | F35: 0.985088 | G35: 0.98918 | H35: 0.995922 | I35: 0.99893 | J35: 1.001656 | K35: 1.0045 | L35: 1.006883 | M35: 1.010012 | N35: 1.020131 | O35: 1.024293 | P35: 1.029881 | Q35: 1.036442 | R35: 1.043608 | S35: 1.049588 | T35: 1.055866 | U35: 1.062651 | V35: 1.070354 | W35: 1.078568 | X35: 1.086592 | Y35: 1.09571 | Z35: 1.105691 | AA35: 1.116048 | AB35: 1.131383 | AC35: 1.137161 | AD35: 1.15791 | AE35: 1.169819 | AF35: 1.182431 | AG35: 1.195287 | AH35: 0.010352 | AJ35: =C35/D35 -> 0.90725825
A36: PSD000:ca_EthanolImport | B36: Net Imports | C36: -0.076173 | D36: -0.083658 | E36: -0.107078 | F36: -0.109756 | G36: -0.115777 | H36: -0.121077 | I36: -0.124098 | J36: -0.127202 | K36: -0.130387 | L36: -0.133642 | M36: -0.136978 | N36: -0.147094 | O36: -0.150773 | P36: -0.154538 | Q36: -0.1584 | R36: -0.16236 | S36: -0.166418 | T36: -0.170586 | U36: -0.174851 | V36: -0.179214 | W36: -0.1837 | X36: -0.188296 | Y36: -0.193001 | Z36: -0.197829 | AA36: -0.202767 | AB36: -0.212879 | AC36: -0.213033 | AD36: -0.228288 | AE36: -0.233987 | AF36: -0.239839 | AG36: -0.245844 | AH36: 0.039829 | AJ36: =C36/D36 -> 0.91052858
A37: PSD000:ca_EthanolWithdr | B37: Stock Withdrawal | C37: 0 | D37: 0 | E37: 0 | F37: 0 | G37: 0 | H37: 0 | I37: 0 | J37: 0 | K37: 0 | L37: 0 | M37: 0 | N37: 0 | O37: 0 | P37: 0 | Q37: 0 | R37: 0 | S37: 0 | T37: 0 | U37: 0 | V37: 0 | W37: 0 | X37: 0 | Y37: 0 | Z37: 0 | AA37: 0 | AB37: 0 | AC37: 0 | AD37: 0 | AE37: 0 | AF37: 0 | AG37: 0 | AH37: -- | AJ37: =C37/D37 -> #DIV/0!
A38: PSD000:cb_TotalBiodiesl | B38: Biodiesel | C38: 0.116095 | D38: 0.13709 | E38: 0.132302 | F38: 0.135473 | G38: 0.135684 | H38: 0.135886 | I38: 0.136087 | J38: 0.136455 | K38: 0.136648 | L38: 0.136864 | M38: 0.13762 | N38: 0.137471 | O38: 0.137665 | P38: 0.137726 | Q38: 0.137942 | R38: 0.138158 | S38: 0.137691 | T38: 0.135528 | U38: 0.134295 | V38: 0.134471 | W38: 0.134646 | X38: 0.134823 | Y38: 0.135 | Z38: 0.134761 | AA38: 0.134934 | AB38: 0.135108 | AC38: 0.135501 | AD38: 0.135683 | AE38: 0.135865 | AF38: 0.139333 | AG38: 0.141751 | AH38: -- | AJ38: =C38/D38 -> 0.84685243
A39: PSD000:cb_DomesticBiodi | B39: Domestic Production | C39: 0.113 | D39: 0.133995 | E39: 0.122511 | F39: 0.127495 | G39: 0.127666 | H39: 0.127828 | I39: 0.127989 | J39: 0.128316 | K39: 0.128469 | L39: 0.128643 | M39: 0.129358 | N39: 0.129168 | O39: 0.12932 | P39: 0.12934 | Q39: 0.129514 | R39: 0.129688 | S39: 0.129179 | T39: 0.126973 | U39: 0.125698 | V39: 0.12583 | W39: 0.125962 | X39: 0.126095 | Y39: 0.126229 | Z39: 0.125946 | AA39: 0.126075 | AB39: 0.126205 | AC39: 0.126553 | AD39: 0.12669 | AE39: 0.126828 | AF39: 0.13025 | AG39: 0.132623 | AH39: 0.005352 | AJ39: =C39/D39 -> 0.84331505
A40: PSD000:cb_BiodieselImpo | B40: Net Imports | C40: 0.003095 | D40: 0.003095 | E40: 0.009791 | F40: 0.007978 | G40: 0.008018 | H40: 0.008058 | I40: 0.008098 | J40: 0.008139 | K40: 0.00818 | L40: 0.00822 | M40: 0.008262 | N40: 0.008303 | O40: 0.008344 | P40: 0.008386 | Q40: 0.008428 | R40: 0.00847 | S40: 0.008512 | T40: 0.008555 | U40: 0.008598 | V40: 0.008641 | W40: 0.008684 | X40: 0.008727 | Y40: 0.008771 | Z40: 0.008815 | AA40: 0.008859 | AB40: 0.008903 | AC40: 0.008948 | AD40: 0.008993 | AE40: 0.009038 | AF40: 0.009083 | AG40: 0.009128 | AH40: 0.036709 | AJ40: =C40/D40 -> 1
A41: PSD000:cb_BiodieselWith | B41: Stock Withdrawal | C41: 0 | D41: 0 | E41: 0 | F41: 0 | G41: 0 | H41: 0 | I41: 0 | J41: 0 | K41: 0 | L41: 0 | M41: 0 | N41: 0 | O41: 0 | P41: 0 | Q41: 0 | R41: 0 | S41: 0 | T41: 0 | U41: 0 | V41: 0 | W41: 0 | X41: 0 | Y41: 0 | Z41: 0 | AA41: 0 | AB41: 0 | AC41: 0 | AD41: 0 | AE41: 0 | AF41: 0 | AG41: 0 | AH41: -- | AJ41: =C41/D41 -> #DIV/0!
A42: PSD000:Other_BM-derived | B42: Other Biomass-derived Liquids 5/ | C42: 0.050332 | D42: 0.076521 | E42: 0.098092 | F42: 0.109337 | G42: 0.113808 | H42: 0.116244 | I42: 0.119597 | J42: 0.122998 | K42: 0.126544 | L42: 0.130394 | M42: 0.13336 | N42: 0.133363 | O42: 0.132822 | P42: 0.131609 | Q42: 0.129698 | R42: 0.127509 | S42: 0.126692 | T42: 0.127295 | U42: 0.126796 | V42: 0.124528 | W42: 0.122079 | X42: 0.11979 | Y42: 0.116897 | Z42: 0.113907 | AA42: 0.113926 | AB42: 0.114884 | AC42: 0.115437 | AD42: 0.116895 | AE42: 0.117864 | AF42: 0.11841 | AG42: 0.1199 | AH42: 0.029357 | AJ42: =C42/D42 -> 0.65775408
A43: PSD000:Other_BM_Dome | B43: Domestic Production | C43: 0.032683 | D43: 0.050489 | E43: 0.073741 | F43: 0.084682 | G43: 0.088845 | H43: 0.090969 | I43: 0.094006 | J43: 0.097087 | K43: 0.10031 | L43: 0.103831 | M43: 0.106465 | N43: 0.106131 | O43: 0.10525 | P43: 0.103692 | Q43: 0.101433 | R43: 0.098891 | S43: 0.097716 | T43: 0.097957 | U43: 0.097091 | V43: 0.094451 | W43: 0.091627 | X43: 0.093372 | Y43: 0.091584 | Z43: 0.088278 | AA43: 0.087977 | AB43: 0.088611 | AC43: 0.088836 | AD43: 0.089961 | AE43: 0.090593 | AF43: 0.090798 | AG43: 0.091943 | AH43: 0.035078 | AJ43: =C43/D43 -> 0.64732912
A44: PSD000:Other_BM_NetImp | B44: Net Imports | C44: 0.017648 | D44: 0.026031 | E44: 0.024351 | F44: 0.024655 | G44: 0.024963 | H44: 0.025275 | I44: 0.025591 | J44: 0.025911 | K44: 0.026235 | L44: 0.026563 | M44: 0.026895 | N44: 0.027231 | O44: 0.027572 | P44: 0.027916 | Q44: 0.028265 | R44: 0.028618 | S44: 0.028976 | T44: 0.029338 | U44: 0.029705 | V44: 0.030076 | W44: 0.030452 | X44: 0.026418 | Y44: 0.025312 | Z44: 0.025629 | AA44: 0.025949 | AB44: 0.026273 | AC44: 0.026602 | AD44: 0.026934 | AE44: 0.027271 | AF44: 0.027612 | AG44: 0.027957 | AH44: 0.015452 | AJ44: =C44/D44 -> 0.67796089
A45: PSD000:Other_BM_Stock | B45: Stock Withdrawal | C45: 0 | D45: 0 | E45: 0 | F45: 0 | G45: 0 | H45: 0 | I45: 0 | J45: 0 | K45: 0 | L45: 0 | M45: 0 | N45: 0 | O45: 0 | P45: 0 | Q45: 0 | R45: 0 | S45: 0 | T45: 0 | U45: 0 | V45: 0 | W45: 0 | X45: 0 | Y45: 0 | Z45: 0 | AA45: 0 | AB45: 0 | AC45: 0 | AD45: 0 | AE45: 0 | AF45: 0 | AG45: 0 | AH45: -- | AJ45: =C45/D45 -> #DIV/0!
A46: PSD000:AllLiquidsfromGa | B46: Liquids from Gas | C46: 0 | D46: 0 | E46: 0 | F46: 0 | G46: 0 | H46: 0 | I46: 0 | J46: 0 | K46: 0 | L46: 0 | M46: 0 | N46: 0 | O46: 0 | P46: 0 | Q46: 0 | R46: 0 | S46: 0 | T46: 0 | U46: 0 | V46: 0 | W46: 0 | X46: 0 | Y46: 0 | Z46: 0 | AA46: 0 | AB46: 0 | AC46: 0 | AD46: 0 | AE46: 0 | AF46: 0 | AG46: 0 | AH46: -- | AJ46: =C46/D46 -> #DIV/0!
A47: PSD000:ca_LiquidsfromCo | B47: Liquids from Coal | C47: 0 | D47: 0 | E47: 0 | F47: 0 | G47: 0 | H47: 0 | I47: 0 | J47: 0 | K47: 0 | L47: 0 | M47: 0 | N47: 0 | O47: 0 | P47: 0 | Q47: 0 | R47: 0 | S47: 0 | T47: 0 | U47: 0 | V47: 0 | W47: 0 | X47: 0 | Y47: 0 | Z47: 0 | AA47: 0 | AB47: 0 | AC47: 0 | AD47: 0 | AE47: 0 | AF47: 0 | AG47: 0 | AH47: -- | AJ47: =C47/D47 -> #DIV/0!
A48: PSD000:ca_OtherOther | B48: Other 6/ | C48: 0.209 | D48: 0.209 | E48: 0.242314 | F48: 0.246997 | G48: 0.247316 | H48: 0.246604 | I48: 0.246231 | J48: 0.241679 | K48: 0.243457 | L48: 0.242003 | M48: 0.233147 | N48: 0.233613 | O48: 0.23299 | P48: 0.232713 | Q48: 0.236295 | R48: 0.237347 | S48: 0.240781 | T48: 0.244333 | U48: 0.245359 | V48: 0.251578 | W48: 0.249325 | X48: 0.249354 | Y48: 0.249732 | Z48: 0.249564 | AA48: 0.25016 | AB48: 0.248147 | AC48: 0.251377 | AD48: 0.252945 | AE48: 0.25349 | AF48: 0.25469 | AG48: 0.258319 | AH48: 0.007087 | AJ48: =C48/D48 -> 1
AJ49: =C49/D49 -> #DIV/0!
A50: PSD000:da_TotalPrimaryS | B50: Total Primary Supply 7/ | C50: 18.207922 | D50: 19.978867 | E50: 19.820332 | F50: 20.001534 | G50: 20.108173 | H50: 20.199614 | I50: 20.217533 | J50: 20.202549 | K50: 20.206478 | L50: 20.207016 | M50: 20.242155 | N50: 20.26326 | O50: 20.279169 | P50: 20.316864 | Q50: 20.384787 | R50: 20.442598 | S50: 20.474876 | T50: 20.518192 | U50: 20.559797 | V50: 20.601055 | W50: 20.620106 | X50: 20.671547 | Y50: 20.758131 | Z50: 20.851471 | AA50: 20.935635 | AB50: 21.034939 | AC50: 21.109848 | AD50: 21.194641 | AE50: 21.297144 | AF50: 21.423565 | AG50: 21.55241 | AH50: 0.005637 | AJ50: =C50/D50 -> 0.91135909
AJ51: =C51/D51 -> #DIV/0!
AJ52: =C52/D52 -> #DIV/0!
B53: Product Supplied | AJ53: =C53/D53 -> #DIV/0!
B54: by Fuel | AJ54: =C54/D54 -> #DIV/0!
A55: PSD000:ea_LiqPetGas | B55: Liquefied Petroleum Gases and Other 8/ | C55: 2.989 | D55: 3.255 | E55: 3.609726 | F55: 3.705562 | G55: 3.807588 | H55: 3.895917 | I55: 3.951897 | J55: 3.993202 | K55: 4.04269 | L55: 4.096564 | M55: 4.164239 | N55: 4.227246 | O55: 4.27165 | P55: 4.323526 | Q55: 4.3839 | R55: 4.434229 | S55: 4.462133 | T55: 4.499022 | U55: 4.534411 | V55: 4.557205 | W55: 4.565302 | X55: 4.580216 | Y55: 4.621236 | Z55: 4.657368 | AA55: 4.679041 | AB55: 4.706604 | AC55: 4.725658 | AD55: 4.745313 | AE55: 4.770703 | AF55: 4.820659 | AG55: 4.864904 | AH55: 0.016369 | AJ55: =C55/D55 -> 0.91827957
A56: PSD000:ea_MotorGasoline | B56: Motor Gasoline 9/ | C56: 8.222 | D56: 8.975 | E56: 8.647271 | F56: 8.651978 | G56: 8.626451 | H56: 8.589529 | I56: 8.537522 | J56: 8.483031 | K56: 8.430394 | L56: 8.372775 | M56: 8.322585 | N56: 8.275581 | O56: 8.232552 | P56: 8.201967 | Q56: 8.17979 | R56: 8.162219 | S56: 8.143358 | T56: 8.126231 | U56: 8.11299 | V56: 8.106754 | W56: 8.104486 | X56: 8.104496 | Y56: 8.113137 | Z56: 8.128265 | AA56: 8.145515 | AB56: 8.161805 | AC56: 8.17985 | AD56: 8.199533 | AE56: 8.223298 | AF56: 8.251421 | AG56: 8.280221 | AH56: 0.000235 | AJ56: =C56/D56 -> 0.91610028
A57: PSD000:ea_E85E85E85E85 | B57: of which: E85 10/ | C57: 0.021506 | D57: 0.022221 | E57: 0.021036 | F57: 0.021706 | G57: 0.021522 | H57: 0.021154 | I57: 0.02077 | J57: 0.020333 | K57: 0.019779 | L57: 0.019327 | M57: 0.018831 | N57: 0.018512 | O57: 0.018144 | P57: 0.017908 | Q57: 0.017711 | R57: 0.017593 | S57: 0.017505 | T57: 0.017463 | U57: 0.017437 | V57: 0.017535 | W57: 0.017587 | X57: 0.017699 | Y57: 0.017864 | Z57: 0.018059 | AA57: 0.018291 | AB57: 0.018569 | AC57: 0.018755 | AD57: 0.019022 | AE57: 0.019294 | AF57: 0.019625 | AG57: 0.019969 | AH57: -0.002469 | AJ57: =C57/D57 -> 0.96782323
A58: PSD000:ea_JetFuel | B58: Jet Fuel 11/ | C58: 1.076 | D58: 1.542 | E58: 1.572167 | F58: 1.633723 | G58: 1.665057 | H58: 1.693854 | I58: 1.70277 | J58: 1.710599 | K58: 1.724974 | L58: 1.735477 | M58: 1.74995 | N58: 1.768529 | O58: 1.791543 | P58: 1.815627 | Q58: 1.839887 | R58: 1.863731 | S58: 1.882253 | T58: 1.898537 | U58: 1.91695 | V58: 1.936127 | W58: 1.958794 | X58: 1.980997 | Y58: 2.006128 | Z58: 2.032139 | AA58: 2.059608 | AB58: 2.085221 | AC58: 2.109635 | AD58: 2.131682 | AE58: 2.152062 | AF58: 2.170761 | AG58: 2.189618 | AH58: 0.023965 | AJ58: =C58/D58 -> 0.69779507
A59: PSD000:ea_DistillateFue | B59: Distillate Fuel Oil 12/ | C59: 3.752 | D59: 3.959 | E59: 3.865273 | F59: 3.874248 | G59: 3.888752 | H59: 3.923565 | I59: 3.920543 | J59: 3.911974 | K59: 3.894572 | L59: 3.876584 | M59: 3.850567 | N59: 3.843616 | O59: 3.826887 | P59: 3.813994 | Q59: 3.807055 | R59: 3.802737 | S59: 3.796126 | T59: 3.789049 | U59: 3.788571 | V59: 3.790232 | W59: 3.791813 | X59: 3.795066 | Y59: 3.815734 | Z59: 3.833811 | AA59: 3.854297 | AB59: 3.867991 | AC59: 3.885901 | AD59: 3.90179 | AE59: 3.920615 | AF59: 3.940897 | AG59: 3.96279 | AH59: 0.001824 | AJ59: =C59/D59 -> 0.94771407
A60: PSD000:eb_DieselAllSect | B60: of which: Diesel | C60: 3.456 | D60: 3.657 | E60: 3.432402 | F60: 3.448857 | G60: 3.469472 | H60: 3.509047 | I60: 3.509813 | J60: 3.505762 | K60: 3.492223 | L60: 3.47701 | M60: 3.453422 | N60: 3.449278 | O60: 3.434251 | P60: 3.422858 | Q60: 3.416938 | R60: 3.41386 | S60: 3.408481 | T60: 3.403135 | U60: 3.404889 | V60: 3.40744 | W60: 3.409968 | X60: 3.414116 | Y60: 3.435445 | Z60: 3.454095 | AA60: 3.474675 | AB60: 3.488708 | AC60: 3.506695 | AD60: 3.522471 | AE60: 3.540893 | AF60: 3.560535 | AG60: 3.581682 | AH60: 0.001191 | AJ60: =C60/D60 -> 0.94503692
A61: PSD000:ea_ResidualFuel | B61: Residual Fuel Oil | C61: 0.222 | D61: 0.251 | E61: 0.345624 | F61: 0.341309 | G61: 0.33371 | H61: 0.296118 | I61: 0.295799 | J61: 0.281907 | K61: 0.279161 | L61: 0.276551 | M61: 0.295443 | N61: 0.27819 | O61: 0.276926 | P61: 0.275384 | Q61: 0.274001 | R61: 0.272381 | S61: 0.270942 | T61: 0.272104 | U61: 0.268697 | V61: 0.268357 | W61: 0.257496 | X61: 0.263795 | Y61: 0.250871 | Z61: 0.249603 | AA61: 0.241339 | AB61: 0.245082 | AC61: 0.238866 | AD61: 0.235293 | AE61: 0.234301 | AF61: 0.233955 | AG61: 0.232535 | AH61: 0.001547 | AJ61: =C61/D61 -> 0.88446215
A62: PSD000:ea_Other | B62: Other 13/ | C62: 1.793 | D62: 1.902 | E62: 1.809897 | F62: 1.816249 | G62: 1.807728 | H62: 1.821579 | I62: 1.832354 | J62: 1.842665 | K62: 1.855776 | L62: 1.869629 | M62: 1.878015 | N62: 1.889208 | O62: 1.898826 | P62: 1.90594 | Q62: 1.921151 | R62: 1.928938 | S62: 1.942982 | T62: 1.957459 | U62: 1.962909 | V62: 1.969185 | W62: 1.968737 | X62: 1.973713 | Y62: 1.978284 | Z62: 1.977734 | AA62: 1.983579 | AB62: 1.995786 | AC62: 1.99847 | AD62: 2.010444 | AE62: 2.026478 | AF62: 2.036897 | AG62: 2.054795 | AH62: 0.004553 | AJ62: =C62/D62 -> 0.9426919
B63: by Sector | AJ63: =C63/D63 -> #DIV/0!
A64: PSD000:fa_Residentialan | B64: Residential and Commercial | C64: 0.973008 | D64: 1.020967 | E64: 1.025397 | F64: 1.018487 | G64: 1.0125 | H64: 1.008024 | I64: 1.001379 | J64: 0.99554 | K64: 0.989118 | L64: 0.98361 | M64: 0.977635 | N64: 0.972941 | O64: 0.968266 | P64: 0.964393 | Q64: 0.960889 | R64: 0.95787 | S64: 0.954872 | T64: 0.951809 | U64: 0.948629 | V64: 0.94609 | W64: 0.943079 | X64: 0.940291 | Y64: 0.937793 | Z64: 0.935353 | AA64: 0.933443 | AB64: 0.931899 | AC64: 0.929856 | AD64: 0.927902 | AE64: 0.926282 | AF64: 0.924856 | AG64: 0.923642 | AH64: -0.001734 | AJ64: =C64/D64 -> 0.95302591
A65: PSD000:fa_Industrial | B65: Industrial 14/ | C65: 5.030285 | D65: 5.33316 | E65: 5.629797 | F65: 5.743815 | G65: 5.852944 | H65: 5.972896 | I65: 6.053487 | J65: 6.119887 | K65: 6.192935 | L65: 6.271528 | M65: 6.359034 | N65: 6.445484 | O65: 6.510686 | P65: 6.580037 | Q65: 6.666644 | R65: 6.735588 | S65: 6.78666 | T65: 6.846908 | U65: 6.897853 | V65: 6.937009 | W65: 6.954561 | X65: 6.985662 | Y65: 7.043337 | Z65: 7.092395 | AA65: 7.133726 | AB65: 7.18644 | AC65: 7.220916 | AD65: 7.265339 | AE65: 7.320342 | AF65: 7.395383 | AG65: 7.472469 | AH65: 0.013279 | AJ65: =C65/D65 -> 0.94320909
A66: PSD000:fa_Transportatio | B66: Transportation | C66: 12.302353 | D66: 13.081482 | E66: 13.357647 | F66: 13.425238 | G66: 13.431393 | H66: 13.410588 | I66: 13.355597 | J66: 13.280526 | K66: 13.218669 | L66: 13.145129 | M66: 13.096184 | N66: 13.036627 | O66: 12.991385 | P66: 12.963189 | Q66: 12.948902 | R66: 12.941265 | S66: 12.92625 | T66: 12.91397 | U66: 12.909477 | V66: 12.916617 | W66: 12.920952 | X66: 12.945317 | Y66: 12.97907 | Z66: 13.028308 | AA66: 13.075641 | AB66: 13.125675 | AC66: 13.169308 | AD66: 13.213575 | AE66: 13.264289 | AF66: 13.318529 | AG66: 13.374049 | AH66: 0.002788 | AJ66: =C66/D66 -> 0.94044031
A67: PSD000:fa_ElectricPower | B67: Electric Power 15/ | C67: 0.069548 | D67: 0.054252 | E67: 0.05537 | F67: 0.051545 | G67: 0.048999 | H67: 0.046557 | I67: 0.044846 | J67: 0.042355 | K67: 0.040813 | L67: 0.040001 | M67: 0.039095 | N67: 0.037522 | O67: 0.037129 | P67: 0.036861 | Q67: 0.036754 | R67: 0.036245 | S67: 0.035847 | T67: 0.035025 | U67: 0.033509 | V67: 0.033052 | W67: 0.032673 | X67: 0.031489 | Y67: 0.030281 | Z67: 0.028884 | AA67: 0.027648 | AB67: 0.026181 | AC67: 0.026173 | AD67: 0.026314 | AE67: 0.026476 | AF67: 0.02661 | AG67: 0.026682 | AH67: -0.03143 | AJ67: =C67/D67 -> 1.2819435
A68: PSD000:fa_balancesector | B68: Unspecified Sector 16/ | C68: -0.207071 | D68: -0.214067 | E68: -0.215582 | F68: -0.216147 | G68: -0.216455 | H68: -0.217386 | I68: -0.216495 | J68: -0.215456 | K68: -0.214169 | L68: -0.212707 | M68: -0.210975 | N68: -0.210066 | O68: -0.208777 | P68: -0.207777 | Q68: -0.207077 | R68: -0.206529 | S68: -0.205897 | T68: -0.205304 | U68: -0.20502 | V68: -0.204847 | W68: -0.204721 | X68: -0.204647 | Y68: -0.205381 | Z68: -0.206045 | AA68: -0.206797 | AB68: -0.207256 | AC68: -0.207892 | AD68: -0.208486 | AE68: -0.209181 | AF68: -0.209929 | AG68: -0.210747 | AH68: 0.000587 | AJ68: =C68/D68 -> 0.96731864
A69: PSD000:fa_Total | B69: Total | C69: 18.054001 | D69: 19.884001 | E69: 19.849958 | F69: 20.023069 | G69: 20.129288 | H69: 20.220562 | I69: 20.240885 | J69: 20.223379 | K69: 20.227568 | L69: 20.227581 | M69: 20.260799 | N69: 20.28237 | O69: 20.298384 | P69: 20.336435 | Q69: 20.405785 | R69: 20.464235 | S69: 20.497795 | T69: 20.542404 | U69: 20.58453 | V69: 20.627859 | W69: 20.646627 | X69: 20.698284 | Y69: 20.785393 | Z69: 20.87892 | AA69: 20.963379 | AB69: 21.062489 | AC69: 21.138378 | AD69: 21.224056 | AE69: 21.327456 | AF69: 21.454592 | AG69: 21.584862 | AH69: 0.005972 | AJ69: =C69/D69 -> 0.90796621
AJ70: =C70/D70 -> #DIV/0!
A71: PSD000:ga_Discrepancy | B71: Discrepancy 17/ | C71: 0.153921 | D71: 0.094866 | E71: -0.029627 | F71: -0.021536 | G71: -0.021114 | H71: -0.020948 | I71: -0.023352 | J71: -0.02083 | K71: -0.02109 | L71: -0.020565 | M71: -0.018644 | N71: -0.01911 | O71: -0.019215 | P71: -0.019571 | Q71: -0.020998 | R71: -0.021637 | S71: -0.022919 | T71: -0.024212 | U71: -0.024733 | V71: -0.026804 | W71: -0.026522 | X71: -0.026737 | Y71: -0.027262 | Z71: -0.027449 | AA71: -0.027744 | AB71: -0.02755 | AC71: -0.02853 | AD71: -0.029415 | AE71: -0.030312 | AF71: -0.031027 | AG71: -0.032452 | AH71: -- | AJ71: =C71/D71 -> 1.6225096
AJ72: =C72/D72 -> #DIV/0!
A73: PSD000:ha_DomesticRefin | B73: Domestic Refinery Distillation Capacity 18/ | C73: 18.662001 | D73: 18.386 | E73: 18.757694 | F73: 18.944704 | G73: 19.018314 | H73: 19.091925 | I73: 19.091925 | J73: 19.091925 | K73: 19.091925 | L73: 19.091925 | M73: 19.091925 | N73: 19.091925 | O73: 19.091925 | P73: 19.091925 | Q73: 19.091925 | R73: 19.091925 | S73: 19.091925 | T73: 19.091925 | U73: 19.091925 | V73: 19.091925 | W73: 19.091925 | X73: 19.091925 | Y73: 19.091925 | Z73: 19.091925 | AA73: 19.091925 | AB73: 19.091925 | AC73: 19.091925 | AD73: 19.091925 | AE73: 19.091925 | AF73: 19.091925 | AG73: 19.091925 | AH73: 0.000759 | AJ73: =C73/D73 -> 1.0150115
A74: PSD000:ha_CapacityUtili | B74: Capacity Utilization Rate (percent) 19/ | C74: 79.660004 | D74: 88.108002 | E74: 89.901886 | F74: 91.956673 | G74: 92.152649 | H74: 92.796829 | I74: 92.777084 | J74: 93.060249 | K74: 93.049187 | L74: 93.028427 | M74: 93.084824 | N74: 92.973381 | O74: 92.953285 | P74: 92.690269 | Q74: 92.629242 | R74: 92.516243 | S74: 92.668831 | T74: 92.619003 | U74: 92.585068 | V74: 92.183327 | W74: 92.299553 | X74: 92.219131 | Y74: 92.409515 | Z74: 92.228302 | AA74: 92.246567 | AB74: 92.179283 | AC74: 91.998001 | AD74: 92.177353 | AE74: 92.268799 | AF74: 92.06118 | AG74: 91.93737 | AH74: 0.004789 | AJ74: =C74/D74 -> 0.9041177
A75: PSD000:total_gross_imp | B75: Total Gross Imports | C75: 7.994856 | D75: 9.588755 | E75: 9.741456 | F75: 9.717374 | G75: 9.785786 | H75: 9.489263 | I75: 9.503502 | J75: 9.155733 | K75: 8.903451 | L75: 9.016198 | M75: 8.772227 | N75: 8.8318 | O75: 8.613934 | P75: 8.478366 | Q75: 8.567851 | R75: 8.682604 | S75: 8.936007 | T75: 8.983045 | U75: 9.035492 | V75: 9.265973 | W75: 9.180787 | X75: 9.167173 | Y75: 9.23045 | Z75: 9.091464 | AA75: 8.965041 | AB75: 8.981753 | AC75: 8.862605 | AD75: 8.91816 | AE75: 9.069477 | AF75: 9.110847 | AG75: 9.356008 | AH75: 0.005254 | AJ75: =C75/D75 -> 0.83377414
A76: PSD000:total_gross_exp | B76: Total Gross Exports | C76: 8.437286 | D76: 8.778286 | E76: 9.494313 | F76: 10.328879 | G76: 10.797861 | H76: 10.928689 | I76: 11.21687 | J76: 11.008035 | K76: 10.873099 | L76: 11.064581 | M76: 10.911236 | N76: 11.019835 | O76: 10.739881 | P76: 10.673393 | Q76: 10.772882 | R76: 10.71178 | S76: 10.742992 | T76: 10.644144 | U76: 10.561727 | V76: 10.729782 | W76: 10.52272 | X76: 10.401341 | Y76: 10.452495 | Z76: 10.427288 | AA76: 10.302044 | AB76: 10.107439 | AC76: 9.93172 | AD76: 9.946036 | AE76: 9.940456 | AF76: 9.823874 | AG76: 9.702188 | AH76: 0.004667 | AJ76: =C76/D76 -> 0.96115415
A77: PSD000:total_net_import | B77: Total Net Imports | C77: -0.44243 | D77: 0.810469 | E77: 0.247143 | F77: -0.611506 | G77: -1.012075 | H77: -1.439426 | I77: -1.713368 | J77: -1.852302 | K77: -1.969648 | L77: -2.048383 | M77: -2.139009 | N77: -2.188035 | O77: -2.125947 | P77: -2.195027 | Q77: -2.205031 | R77: -2.029176 | S77: -1.806986 | T77: -1.661099 | U77: -1.526235 | V77: -1.463809 | W77: -1.341933 | X77: -1.234168 | Y77: -1.222045 | Z77: -1.335824 | AA77: -1.337003 | AB77: -1.125686 | AC77: -1.069115 | AD77: -1.027876 | AE77: -0.870979 | AF77: -0.713027 | AG77: -0.346181 | AH77: -0.008144 | AJ77: =C77/D77 -> -0.5458938
A78: PSD000:ha_ImportShareof | B78: Net Import Share of Product Supplied (percent) | C78: -2.429874 | D78: 4.05663 | E78: 1.246916 | F78: -3.057297 | G78: -5.033155 | H78: -7.126008 | I78: -8.474666 | J78: -9.168653 | K78: -9.747604 | L78: -10.136989 | M78: -10.5671 | N78: -10.79804 | O78: -10.483407 | P78: -10.803967 | Q78: -10.817046 | R78: -9.926208 | S78: -8.825379 | T78: -8.095737 | U78: -7.423394 | V78: -7.105503 | W78: -6.507888 | X78: -5.970377 | Y78: -5.88707 | Z78: -6.406375 | AA78: -6.386258 | AB78: -5.351501 | AC78: -5.064525 | AD78: -4.849699 | AE78: -4.089653 | AF78: -3.328236 | AG78: -1.606233 | AH78: -0.013704 | AJ78: =C78/D78 -> -0.59898832
B79: Expenditures for Imported Crude Oil and | AJ79: =C79/D79 -> #DIV/0!
A80: PSD000:ha_PetroleumProd | B80: Petroleum Products (billion 2020 dollars) | C80: 96.355621 | D80: 135.7948 | E80: 148.92793 | F80: 162.64175 | G80: 175.12064 | H80: 177.17503 | I80: 183.65756 | J80: 182.90169 | K80: 184.18112 | L80: 192.23349 | M80: 190.56842 | N80: 197.00211 | O80: 195.83057 | P80: 195.8746 | Q80: 200.00871 | R80: 205.55507 | S80: 216.18269 | T80: 219.23926 | U80: 225.37466 | V80: 232.8564 | W80: 239.92156 | X80: 243.74686 | Y80: 249.43391 | Z80: 249.93012 | AA80: 247.88382 | AB80: 246.64914 | AC80: 249.5916 | AD80: 253.13223 | AE80: 257.01791 | AF80: 259.24829 | AG80: 267.3085 | AH80: 0.034597 | AJ80: =C80/D80 -> 0.70956783
AJ81: =C81/D81 -> #DIV/0!
AJ82: =C82/D82 -> #DIV/0!
B83: 1/ Includes lease condensate. | AJ83: =C83/D83 -> #DIV/0!
B84: 2/ Strategic petroleum reserve stock additions plus unaccounted for crude oil and crude oil stock withdrawals. | AJ84: =C84/D84 -> #DIV/0!
B85: 3/ Includes other hydrocarbons and alcohols. | AJ85: =C85/D85 -> #DIV/0!
B86: 4/ The volumetric amount by which total output is greater than input due to the processing of crude oil into products which, in total, | AJ86: =C86/D86 -> #DIV/0!
B87: have a lower specific gravity than the crude oil processed. | AJ87: =C87/D87 -> #DIV/0!
B88: 5/ Includes pyrolysis oils, biomass-derived Fischer-Tropsch liquids, biobutanol, and renewable feedstocks used for the | AJ88: =C88/D88 -> #DIV/0!
B89: on-site production of diesel and gasoline. | AJ89: =C89/D89 -> #DIV/0!
B90: 6/ Includes domestic sources of other blending components, other hydrocarbons, and ethers. | AJ90: =C90/D90 -> #DIV/0!
B91: 7/ Total crude supply, net product imports, refinery processing gain, product stock withdrawal, natural gas plant liquids, supply from | AJ91: =C91/D91 -> #DIV/0!
B92: renewable sources, liquids from gas, liquids from coal, and other supply. | AJ92: =C92/D92 -> #DIV/0!
B93: 8/ Includes ethane, natural gasoline, and refinery olefins. | AJ93: =C93/D93 -> #DIV/0!
B94: 9/ Includes ethanol and ethers blended into gasoline. | AJ94: =C94/D94 -> #DIV/0!
... B111: National Energy Modeling System run ref2021.d113020a. Projections: EIA, AEO2021 National Energy Modeling System run ref2021.d113020a. | AJ111: =C111/D111 -> #DIV/0!
AJ112: =C112/D112 -> #DIV/0!
AJ113: =C113/D113 -> #DIV/0!
AJ114: =C114/D114 -> #DIV/0!
AJ115: =C115/D115 -> #DIV/0!
AJ116: =C116/D116 -> #DIV/0!
AJ117: =C117/D117 -> #DIV/0!
AJ118: =C118/D118 -> #DIV/0!
AJ119: =C119/D119 -> #DIV/0!
AJ120: =C120/D120 -> #DIV/0!
AJ121: =C121/D121 -> #DIV/0!
...

Sheet AEO T24 Refining 2022 Raw
A1: Table 24. Refining Industry Energy Consumption
A2: https://www.eia.gov/outlooks/aeo/data/browser/#/?id=35-AEO2022&cases=lowmacro&sourcekey=0
A3: Wed Jul 13 2022 09:47:36 GMT-0400 (Eastern Daylight Time)
A4: Source: U.S. Energy Information Administration
B5: full name | C5: api key | D5: units | E5: 2020 | F5: 2021 | G5: 2022 | H5: 2023 | I5: 2024 | J5: 2025 | K5: 2026 | L5: 2027 | M5: 2028 | N5: 2029 | O5: 2030 | P5: 2031 | Q5: 2032 | R5: 2033 | S5: 2034 | T5: 2035 | U5: 2036 | V5: 2037 | W5: 2038 | X5: 2039 | Y5: 2040 | Z5: 2041 | AA5: 2042 | AB5: 2043 | AC5: 2044 | AD5: 2045 | AE5: 2046 | AF5: 2047 | AG5: 2048 | AH5: 2049 | AI5: 2050 | AJ5: Growth (2021-2050)
A6: Value of Shipments (billion 2012 dollars) | B6: Refining Industry: Value of Shipments: Low economic growth | C6: 35-AEO2022.2.lowmacro-d011222a | D6: billion 2012 $ | F6: 746.87048 | G6: 840.716 | H6: 850.76227 | I6: 846.17731 | J6: 846.14966 | K6: 844.26404 | L6: 840.59943 | M6: 838.8761 | N6: 835.64575 | O6: 832.79443 | P6: 831.82013 | Q6: 833.64276 | R6: 833.2926 | S6: 831.01508 | T6: 828.73273 | U6: 827.11176 | V6: 826.83716 | W6: 826.18012 | X6: 827.33057 | Y6: 827.06683 | Z6: 827.62585 | AA6: 829.53912 | AB6: 831.72736 | AC6: 832.18103 | AD6: 834.06146 | AE6: 837.30823 | AF6: 839.42822 | AG6: 839.74255 | AH6: 842.51312 | AI6: 849.40979 | AJ6: 0.004
A7: Inputs to Distillation Units | C7: 35-AEO2022.3.
A8: (million barrels per day) | B8: Refining Industry: Inputs to Distillation Units: Low economic growth | C8: 35-AEO2022.4.lowmacro-d011222a | D8: MMb/d | F8: 15.710509 | G8: 16.935637 | H8: 17.158117 | I8: 17.243862 | J8: 17.289557 | K8: 17.248625 | L8: 17.194527 | M8: 17.125137 | N8: 17.100779 | O8: 17.055332 | P8: 16.935118 | Q8: 16.974129 | R8: 16.890358 | S8: 16.803427 | T8: 16.749456 | U8: 16.641615 | V8: 16.592222 | W8: 16.606012 | X8: 16.514265 | Y8: 16.474268 | Z8: 16.485779 | AA8: 16.434586 | AB8: 16.466223 | AC8: 16.464849 | AD8: 16.374317 | AE8: 16.368639 | AF8: 16.269154 | AG8: 16.304836 | AH8: 16.304724 | AI8: 16.280148 | AJ8: 0.001
A9: Total Energy Consumption (trillion Btu) | C9: 35-AEO2022.6.
A10: Residual Fuel Oil | B10: Refining Industry: Total Energy Use: Residual Fuel Oil: Low economic growth | C10: 35-AEO2022.7.lowmacro-d011222a | D10: trillion Btu | F10: 0.214 | G10: 0.214 | H10: 0 | I10: 0 | J10: 0 | K10: 0 | L10: 0 | M10: 0 | N10: 0 | O10: 0 | P10: 0 | Q10: 0 | R10: 0 | S10: 0 | T10: 0 | U10: 0 | V10: 0 | W10: 0 | X10: 0 | Y10: 0 | Z10: 0 | AA10: 0 | AB10: 0 | AC10: 0 | AD10: 0 | AE10: 0 | AF10: 0 | AG10: 0 | AH10: 0 | AI10: 0 | AJ10: - -
A11: Distillate Fuel Oil | B11: Refining Industry: Total Energy Use: Distillate Fuel Oil: Low economic growth | C11: 35-AEO2022.8.lowmacro-d011222a | D11: trillion Btu | F11: 1.625 | G11: 1.625 | H11: 0 | I11: 0 | J11: 0 | K11: 0 | L11: 0 | M11: 0 | N11: 0 | O11: 0 | P11: 0 | Q11: 0 | R11: 0 | S11: 0 | T11: 0 | U11: 0 | V11: 0 | W11: 0 | X11: 0 | Y11: 0 | Z11: 0 | AA11: 0 | AB11: 0 | AC11: 0 | AD11: 0 | AE11: 0 | AF11: 0 | AG11: 0 | AH11: 0 | AI11: 0 | AJ11: - -
A12: Liquefied Petroleum Gas Heat and Power | B12: Refining Industry: Total Energy Use: Liquefied Petroleum Gases: Low economic growth | C12: 35-AEO2022.9.lowmacro-d011222a | D12: trillion Btu | F12: 6.813 | G12: 6.813 | H12: 0 | I12: 0 | J12: 0 | K12: 0 | L12: 0 | M12: 0 | N12: 0 | O12: 0 | P12: 0 | Q12: 0 | R12: 0 | S12: 0 | T12: 0 | U12: 0 | V12: 0 | W12: 0 | X12: 0 | Y12: 0 | Z12: 0 | AA12: 0 | AB12: 0 | AC12: 0 | AD12: 0 | AE12: 0 | AF12: 0 | AG12: 0 | AH12: 0 | AI12: 0 | AJ12: - -
A13: Petroleum Coke | B13: Refining Industry: Total Energy Use: Petroleum Coke: Low economic growth | C13: 35-AEO2022.10.lowmacro-d011222a | D13: trillion Btu | F13: 457.229 | G13: 494.56598 | H13: 512.17004 | I13: 507.68442 | J13: 508.41577 | K13: 501.6297 | L13: 499.41949 | M13: 501.44247 | N13: 503.42487 | O13: 508.64514 | P13: 507.30545 | Q13: 510.25604 | R13: 510.57617 | S13: 511.58743 | T13: 510.87836 | U13: 510.53915 | V13: 508.83008 | W13: 508.80609 | X13: 509.01776 | Y13: 505.9101 | Z13: 506.77811 | AA13: 506.62024 | AB13: 508.24448 | AC13: 509.07855 | AD13: 510.58063 | AE13: 511.49094 | AF13: 511.26907 | AG13: 513.88257 | AH13: 517.29755 | AI13: 518.11548 | AJ13: 0.004
A14: Still Gas | B14: Refining Industry: Total Energy Use: Still Gas: Low economic growth | C14: 35-AEO2022.11.lowmacro-d011222a | D14: trillion Btu | F14: 1307.035 | G14: 1307.035 | H14: 1376.4792 | I14: 1370.5844 | J14: 1380.0272 | K14: 1384.7845 | L14: 1372.6489 | M14: 1386.3915 | N14: 1386.8704 | O14: 1389.0078 | P14: 1381.9146 | Q14: 1402.4971 | R14: 1398.6792 | S14: 1401.0201 | T14: 1406.3014 | U14: 1413.2411 | V14: 1434.525 | W14: 1435.3785 | X14: 1436.8918 | Y14: 1417.8949 | Z14: 1419.7549 | AA14: 1409.0181 | AB14: 1401.1478 | AC14: 1405.2753 | AD14: 1393.4462 | AE14: 1386.337 | AF14: 1375.0979 | AG14: 1388.4934 | AH14: 1397.1702 | AI14: 1386.0151 | AJ14: 0.002
A15: Other Petroleum | B15: Refining Industry: Total Energy Use: Other Petroleum: Low economic growth | C15: 35-AEO2022.12.lowmacro-d011222a | D15: trillion Btu | F15: 2.958 | G15: 2.958 | H15: 0 | I15: 0 | J15: 0.372267 | K15: 0.71969 | L15: 9.951056 | M15: 1.636055 | N15: 0 | O15: 0 | P15: 0 | Q15: 0.013138 | R15: 0 | S15: 0 | T15: 0.019257 | U15: 0.138091 | V15: 0.027799 | W15: 0.012505 | X15: 0.099726 | Y15: 0.032392 | Z15: 0.041556 | AA15: 0.077835 | AB15: 0.061223 | AC15: 0.011795 | AD15: 0.02569 | AE15: 0.039747 | AF15: 0.0126 | AG15: 0.039243 | AH15: 0.042319 | AI15: 0.037359 | AJ15: -0.14
A16: Petroleum and Other Liquids Subtotal | B16: Refining Industry: Total Energy Use: Petroleum Subtotal: Low economic growth | C16: 35-AEO2022.13.lowmacro-d011222a | D16: trillion Btu | F16: 1775.874 | G16: 1813.2111 | H16: 1888.6493 | I16: 1878.2688 | J16: 1888.8153 | K16: 1887.134 | L16: 1882.0194 | M16: 1889.4701 | N16: 1890.2952 | O16: 1897.653 | P16: 1889.22 | Q16: 1912.7664 | R16: 1909.2554 | S16: 1912.6075 | T16: 1917.199 | U16: 1923.9183 | V16: 1943.3829 | W16: 1944.197 | X16: 1946.0094 | Y16: 1923.8373 | Z16: 1926.5745 | AA16: 1915.7162 | AB16: 1909.4536 | AC16: 1914.3656 | AD16: 1904.0525 | AE16: 1897.8678 | AF16: 1886.3795 | AG16: 1902.4152 | AH16: 1914.5101 | AI16: 1904.168 | AJ16: 0.002
A17: Natural Gas | B17: Refining Industry: Total Energy Use: Natural Gas: Low economic growth | C17: 35-AEO2022.14.lowmacro-d011222a | D17: trillion Btu | F17: 1567.2632 | G17: 1576.2631 | H17: 1398.3788 | I17: 1360.6981 | J17: 1366.2755 | K17: 1393.6177 | L17: 1380.9757 | M17: 1389.9215 | N17: 1401.6855 | O17: 1410.05 | P17: 1412.5398 | Q17: 1371.0464 | R17: 1379.0742 | S17: 1406.8669 | T17: 1403.7351 | U17: 1439.798 | V17: 1443.9424 | W17: 1455.5973 | X17: 1459.7305 | Y17: 1459.2112 | Z17: 1457.2461 | AA17: 1460.7694 | AB17: 1463.6974 | AC17: 1482.3774 | AD17: 1484.8281 | AE17: 1477.1414 | AF17: 1490.5393 | AG17: 1521.3918 | AH17: 1539.7046 | AI17: 1557.6783 | AJ17: 0
A18: of which: Heat and Power | B18: Refining Industry: Total Energy Use: Natural Gas: Heat and Power: Low economic growth | C18: 35-AEO2022.15.lowmacro-d011222a | D18: trillion Btu | F18: 1376.2632 | G18: 1376.2631 | H18: 1195.0608 | I18: 1169.7944 | J18: 1176.6498 | K18: 1196.4496 | L18: 1187.5369 | M18: 1194.3967 | N18: 1205.7681 | O18: 1210.056 | P18: 1209.989 | Q18: 1180.3882 | R18: 1185.743 | S18: 1200.6757 | T18: 1197.2352 | U18: 1217.8516 | V18: 1215.5436 | W18: 1224.4225 | X18: 1226.9199 | Y18: 1235.1213 | Z18: 1234.569 | AA18: 1241.5365 | AB18: 1251.6686 | AC18: 1265.0332 | AD18: 1270.4662 | AE18: 1269.7192 | AF18: 1283.7209 | AG18: 1304.6792 | AH18: 1316.2902 | AI18: 1335.2708 | AJ18: -0.001
A19: of which: Feedstocks | B19: Refining Industry: Total Energy Use: Natural Gas: Feedstocks: Low economic growth | C19: 35-AEO2022.16.lowmacro-d011222a | D19: trillion Btu | F19: 191 | G19: 200 | H19: 203.31799 | I19: 190.90372 | J19: 189.62576 | K19: 197.16812 | L19: 193.4389 | M19: 195.5248 | N19: 195.91748 | O19: 199.99399 | P19: 202.55083 | Q19: 190.65814 | R19: 193.33115 | S19: 206.19127 | T19: 206.49988 | U19: 221.94636 | V19: 228.3988 | W19: 231.17477 | X19: 232.81056 | Y19: 224.0898 | Z19: 222.67714 | AA19: 219.23294 | AB19: 212.02879 | AC19: 217.34425 | AD19: 214.36197 | AE19: 207.42213 | AF19: 206.81836 | AG19: 216.71269 | AH19: 223.4144 | AI19: 222.40764 | AJ19: 0.005
A20: of which: Gas-to-Liquids Heat | B20: Refining Industry: Total Energy Use: Natural Gas: Gas-to-Liquids Heat: Low economic growth | C20: 35-AEO2022.17.lowmacro-d011222a | D20: trillion Btu | F20: 0 | G20: 0 | H20: 0 | I20: 0 | J20: 0 | K20: 0 | L20: 0 | M20: 0 | N20: 0 | O20: 0 | P20: 0 | Q20: 0 | R20: 0 | S20: 0 | T20: 0 | U20: 0 | V20: 0 | W20: 0 | X20: 0 | Y20: 0 | Z20: 0 | AA20: 0 | AB20: 0 | AC20: 0 | AD20: 0 | AE20: 0 | AF20: 0 | AG20: 0 | AH20: 0 | AI20: 0 | AJ20: - -
A21: Steam Coal | B21: Refining Industry: Total Energy Use: Steam Coal: Low economic growth | C21: 35-AEO2022.18.lowmacro-d011222a | D21: trillion Btu | F21: 24 | G21: 24 | H21: 0 | I21: 0 | J21: 0 | K21: 0 | L21: 0 | M21: 0 | N21: 0 | O21: 0 | P21: 0 | Q21: 0.044211 | R21: 0.587311 | S21: 0.587311 | T21: 4.129168 | U21: 6.791768 | V21: 10.297455 | W21: 13.768188 | X21: 24.259581 | Y21: 24.055048 | Z21: 30.481363 | AA21: 30.481363 | AB21: 30.481363 | AC21: 30.481363 | AD21: 30.472221 | AE21: 30.481363 | AF21: 30.481363 | AG21: 30.481363 | AH21: 30.481363 | AI21: 30.481363 | AJ21: 0.008
A22: Biofuels Heat and Coproducts | B22: Refining Industry: Total Energy Use: Biofuels Heat and Coproducts: Low economic growth | C22: 35-AEO2022.19.lowmacro-d011222a | D22: trillion Btu | F22: 941.45343 | G22: 933.54883 | H22: 902.31354 | I22: 902.28943 | J22: 910.22437 | K22: 911.72607 | L22: 911.99884 | M22: 912.42938 | N22: 919.52039 | O22: 922.16632 | P22: 925.97485 | Q22: 929.1579 | R22: 931.77387 | S22: 935.22247 | T22: 940.83124 | U22: 944.62891 | V22: 949.54382 | W22: 954.95795 | X22: 969.474 | Y22: 969.95734 | Z22: 978.94367 | AA22: 984.90363 | AB22: 992.83691 | AC22: 1009.6605 | AD22: 1019.3696 | AE22: 1030.2854 | AF22: 1042.0416 | AG22: 1054.1409 | AH22: 1066.8409 | AI22: 1083.0004 | AJ22: 0.005
A23: Purchased Electricity | B23: Refining Industry: Total Energy Use: Purchased Electricity: Low economic growth | C23: 35-AEO2022.20.lowmacro-d011222a | D23: trillion Btu | F23: 187.22299 | G23: 187.22299 | H23: 187.76643 | I23: 184.86105 | J23: 185.47809 | K23: 186.6109 | L23: 183.6449 | M23: 185.39218 | N23: 186.7728 | O23: 188.5428 | P23: 187.41983 | Q23: 191.95367 | R23: 191.76068 | S23: 194.25104 | T23: 193.53644 | U23: 196.57754 | V23: 197.63037 | W23: 198.64825 | X23: 199.39276 | Y23: 199.25093 | Z23: 200.21727 | AA23: 200.02982 | AB23: 200.91527 | AC23: 202.63843 | AD23: 202.20322 | AE23: 201.92714 | AF23: 202.16632 | AG23: 204.93985 | AH23: 207.32062 | AI23: 207.41142 | AJ23: 0.004
A24: Total | B24: Refining Industry: Total Energy Use: Total: Low economic growth | C24: 35-AEO2022.21.lowmacro-d011222a | D24: trillion Btu | F24: 4495.8135 | G24: 4534.2461 | H24: 4377.1079 | I24: 4326.1172 | J24: 4350.793 | K24: 4379.0889 | L24: 4358.6392 | M24: 4377.2129 | N24: 4398.2739 | O24: 4418.4121 | P24: 4415.1543 | Q24: 4404.9683 | R24: 4412.4517 | S24: 4449.5356 | T24: 4459.4307 | U24: 4511.7148 | V24: 4544.7969 | W24: 4567.1685 | X24: 4598.8662 | Y24: 4576.3115 | Z24: 4593.4629 | AA24: 4591.9004 | AB24: 4597.3848 | AC24: 4639.5234 | AD24: 4640.9258 | AE24: 4637.7031 | AF24: 4651.6084 | AG24: 4713.3691 | AH24: 4758.8579 | AI24: 4782.7393 | AJ24: 0.002
A25: Carbon Dioxide Emissions | C25: 35-AEO2022.24.
A26: (million metric tons carbon dioxide) | B26: Refining Industry: Carbon Dioxide Emissions: Low economic growth | C26: 35-AEO2022.25.lowmacro-d011222a | D26: MMmt CO2 | F26: 241.70407 | G26: 245.12738 | H26: 238.10994 | I26: 232.64516 | J26: 233.13074 | K26: 234.2005 | L26: 232.07024 | M26: 233.52861 | N26: 234.22252 | O26: 235.04095 | P26: 234.21455 | Q26: 233.83411 | R26: 234.32123 | S26: 235.57091 | T26: 235.3481 | U26: 237.81638 | V26: 239.53348 | W26: 240.60075 | X26: 242.01614 | Y26: 240.27261 | Z26: 241.00105 | AA26: 240.36909 | AB26: 240.12732 | AC26: 241.51883 | AD26: 240.81566 | AE26: 239.9462 | AF26: 239.82762 | AG26: 242.68574 | AH26: 244.67653 | AI26: 245.05357 | AJ26: 0
A27: Energy Related to Refining Activity Only | C27: 35-AEO2022.27.
A28: Energy Consumption | C28: 35-AEO2022.28.
A29: Residual Fuel Oil | B29: Refining Industry: Refinery Only Energy: Use: Residual Fuel Oil: Low economic growth | C29: 35-AEO2022.29.lowmacro-d011222a | D29: trillion Btu | F29: 0.214 | G29: 0.214 | H29: 0 | I29: 0 | J29: 0 | K29: 0 | L29: 0 | M29: 0 | N29: 0 | O29: 0 | P29: 0 | Q29: 0 | R29: 0 | S29: 0 | T29: 0 | U29: 0 | V29: 0 | W29: 0 | X29: 0 | Y29: 0 | Z29: 0 | AA29: 0 | AB29: 0 | AC29: 0 | AD29: 0 | AE29: 0 | AF29: 0 | AG29: 0 | AH29: 0 | AI29: 0 | AJ29: - -
A30: Distillate Fuel Oil | B30: Refining Industry: Refinery Only Energy: Use: Distillate Fuel Oil: Low economic growth | C30: 35-AEO2022.30.lowmacro-d011222a | D30: trillion Btu | F30: 1.625 | G30: 1.625 | H30: 0 | I30: 0 | J30: 0 | K30: 0 | L30: 0 | M30: 0 | N30: 0 | O30: 0 | P30: 0 | Q30: 0 | R30: 0 | S30: 0 | T30: 0 | U30: 0 | V30: 0 | W30: 0 | X30: 0 | Y30: 0 | Z30: 0 | AA30: 0 | AB30: 0 | AC30: 0 | AD30: 0 | AE30: 0 | AF30: 0 | AG30: 0 | AH30: 0 | AI30: 0 | AJ30: - -
A31: Liquefied Petroleum Gas Heat and Power | B31: Refining Industry: Refinery Only Energy: Use: Liquefied Petroleum Gases: Low economic growth | C31: 35-AEO2022.31.lowmacro-d011222a | D31: trillion Btu | F31: 6.813 | G31: 6.813 | H31: 0 | I31: 0 | J31: 0 | K31: 0 | L31: 0 | M31: 0 | N31: 0 | O31: 0 | P31: 0 | Q31: 0 | R31: 0 | S31: 0 | T31: 0 | U31: 0 | V31: 0 | W31: 0 | X31: 0 | Y31: 0 | Z31: 0 | AA31: 0 | AB31: 0 | AC31: 0 | AD31: 0 | AE31: 0 | AF31: 0 | AG31: 0 | AH31: 0 | AI31: 0 | AJ31: - -
A32: Petroleum Coke | B32: Refining Industry: Refinery Only Energy: Use: Petroleum Coke: Low economic growth | C32: 35-AEO2022.32.lowmacro-d011222a | D32: trillion Btu | F32: 454.61902 | G32: 491.70599 | H32: 512.17004 | I32: 507.68442 | J32: 508.41577 | K32: 501.6297 | L32: 499.41949 | M32: 501.44247 | N32: 503.42487 | O32: 508.64514 | P32: 507.30545 | Q32: 510.25604 | R32: 510.57617 | S32: 511.58743 | T32: 510.87836 | U32: 510.53915 | V32: 508.83008 | W32: 508.80609 | X32: 509.01776 | Y32: 505.9101 | Z32: 506.77811 | AA32: 506.62024 | AB32: 508.24448 | AC32: 509.07855 | AD32: 510.58063 | AE32: 511.49094 | AF32: 511.26907 | AG32: 513.88257 | AH32: 517.29755 | AI32: 518.11548 | AJ32: 0.005
A33: Still Gas | B33: Refining Industry: Refinery Only Energy: Use: Still Gas: Low economic growth | C33: 35-AEO2022.33.lowmacro-d011222a | D33: trillion Btu | F33: 1276.865 | G33: 1275.885 | H33: 1323.2778 | I33: 1318.073 | J33: 1326.8258 | K33: 1331.5831 | L33: 1319.4475 | M33: 1333.1901 | N33: 1333.6689 | O33: 1335.8064 | P33: 1328.7131 | Q33: 1351.6774 | R33: 1347.6113 | S33: 1349.8387 | T33: 1354.9116 | U33: 1361.7104 | V33: 1382.6962 | W33: 1383.4335 | X33: 1384.8945 | Y33: 1366.2391 | Z33: 1368.2394 | AA33: 1357.5138 | AB33: 1349.7498 | AC33: 1353.7228 | AD33: 1341.6931 | AE33: 1334.6233 | AF33: 1323.3475 | AG33: 1336.1302 | AH33: 1344.8271 | AI33: 1333.0242 | AJ33: 0.001
A34: Other Petroleum | B34: Refining Industry: Refinery Only Energy: Use: Other Petroleum: Low economic growth | C34: 35-AEO2022.34.lowmacro-d011222a | D34: trillion Btu | F34: 2.958 | G34: 2.958 | H34: 0 | I34: 0 | J34: 0.372267 | K34: 0.71969 | L34: 9.951056 | M34: 1.636055 | N34: 0 | O34: 0 | P34: 0 | Q34: 0.013138 | R34: 0 | S34: 0 | T34: 0.019257 | U34: 0.138091 | V34: 0.027799 | W34: 0.012505 | X34: 0.099726 | Y34: 0.032392 | Z34: 0.041556 | AA34: 0.077835 | AB34: 0.061223 | AC34: 0.011795 | AD34: 0.02569 | AE34: 0.039747 | AF34: 0.0126 | AG34: 0.039243 | AH34: 0.042319 | AI34: 0.037359 | AJ34: -0.14
A35: Petroleum and Other Liquids Subtotal | B35: Refining Industry: Refinery Only Energy: Use: Petroleum Subtotal: Low economic growth | C35: 35-AEO2022.35.lowmacro-d011222a | D35: trillion Btu | F35: 1743.094 | G35: 1779.201 | H35: 1835.4479 | I35: 1825.7574 | J35: 1835.6139 | K35: 1833.9326 | L35: 1828.818 | M35: 1836.2687 | N35: 1837.0938 | O35: 1844.4515 | P35: 1836.0186 | Q35: 1861.9465 | R35: 1858.1875 | S35: 1861.4261 | T35: 1865.8093 | U35: 1872.3877 | V35: 1891.5541 | W35: 1892.252 | X35: 1894.0121 | Y35: 1872.1815 | Z35: 1875.059 | AA35: 1864.2119 | AB35: 1858.0555 | AC35: 1862.8131 | AD35: 1852.2993 | AE35: 1846.1541 | AF35: 1834.6291 | AG35: 1850.052 | AH35: 1862.1671 | AI35: 1851.177 | AJ35: 0.002
A36: Natural Gas | B36: Refining Industry: Refinery Only Energy: Use: Natural Gas: Low economic growth | C36: 35-AEO2022.36.lowmacro-d011222a | D36: trillion Btu | F36: 858.72315 | G36: 857.25305 | H36: 551.43799 | I36: 529.18518 | J36: 529.53796 | K36: 548.72766 | L36: 539.75134 | M36: 546.42163 | N36: 554.59265 | O36: 557.69312 | P36: 555.9057 | Q36: 534.33868 | R36: 537.55603 | S36: 550.52112 | T36: 544.90601 | U36: 564.22528 | V36: 559.7583 | W36: 566.91125 | X36: 566.3078 | Y36: 575.64697 | Z36: 573.78314 | AA36: 578.16223 | AB36: 585.18103 | AC36: 590.72723 | AD36: 591.06335 | AE36: 585.5863 | AF36: 594.23023 | AG36: 607.37872 | AH36: 613.43616 | AI36: 622.67377 | AJ36: -0.011
A37: Steam Coal | B37: Refining Industry: Refinery Only Energy: Use: Steam Coal: Low economic growth | C37: 35-AEO2022.37.lowmacro-d011222a | D37: trillion Btu | F37: 0 | G37: 0 | H37: 0 | I37: 0 | J37: 0 | K37: 0 | L37: 0 | M37: 0 | N37: 0 | O37: 0 | P37: 0 | Q37: 0 | R37: 0 | S37: 0 | T37: 0 | U37: 0 | V37: 0 | W37: 0 | X37: 0 | Y37: 0 | Z37: 0 | AA37: 0 | AB37: 0 | AC37: 0 | AD37: 0 | AE37: 0 | AF37: 0 | AG37: 0 | AH37: 0 | AI37: 0 | AJ37: - -
A38: Purchased Electricity | B38: Refining Industry: Refinery Only Energy: Use: Purchased Electricity: Low economic growth | C38: 35-AEO2022.38.lowmacro-d011222a | D38: trillion Btu | F38: 150.22299 | G38: 150.22299 | H38: 146.39061 | I38: 143.5092 | J38: 143.77194 | K38: 144.84698 | L38: 141.87497 | M38: 143.60429 | N38: 144.68192 | O38: 146.33949 | P38: 145.05365 | Q38: 149.44209 | R38: 149.10196 | S38: 151.42042 | T38: 150.44222 | U38: 153.31632 | V38: 154.14926 | W38: 154.91486 | X38: 155.00134 | Y38: 154.84001 | Z38: 155.39178 | AA38: 154.89087 | AB38: 155.38863 | AC38: 156.29366 | AD38: 155.37083 | AE38: 154.5392 | AF38: 154.18634 | AG38: 156.35101 | AH38: 158.09168 | AI38: 157.37001 | AJ38: 0.002
A39: Total | B39: Refining Industry: Refinery Only Energy: Use: Total: Low economic growth | C39: 35-AEO2022.39.lowmacro-d011222a | D39: trillion Btu | F39: 2752.04 | G39: 2786.677 | H39: 2533.2764 | I39: 2498.4519 | J39: 2508.9238 | K39: 2527.5071 | L39: 2510.4443 | M39: 2526.2947 | N39: 2536.3684 | O39: 2548.4841 | P39: 2536.978 | Q39: 2545.7273 | R39: 2544.8457 | S39: 2563.3677 | T39: 2561.1575 | U39: 2589.9294 | V39: 2605.4617 | W39: 2614.0779 | X39: 2615.3213 | Y39: 2602.6687 | Z39: 2604.2339 | AA39: 2597.2649 | AB39: 2598.6252 | AC39: 2609.834 | AD39: 2598.7336 | AE39: 2586.2795 | AF39: 2583.0457 | AG39: 2613.7817 | AH39: 2633.6948 | AI39: 2631.2209 | AJ39: -0.002
A40: Carbon Dioxide Emissions | C40: 35-AEO2022.41.
A41: (million metric tons carbon dioxide) | B41: Refining Industry: Refinery Only Energy: Carbon Dioxide Emissions: Low economic growth | C41: 35-AEO2022.42.lowmacro-d011222a | D41: MMmt CO2 | F41: 194.19421 | G41: 196.98454 | H41: 184.56274 | I41: 180.5103 | J41: 180.76196 | K41: 181.43282 | L41: 179.63312 | M41: 180.95116 | N41: 181.47546 | O41: 182.08995 | P41: 181.08618 | Q41: 181.95428 | R41: 182.01772 | S41: 182.62331 | T41: 182.02245 | U41: 183.40593 | V41: 184.31232 | W41: 184.77695 | X41: 184.88017 | Y41: 183.73434 | Z41: 183.84285 | AA41: 183.24374 | AB41: 183.20239 | AC41: 183.81677 | AD41: 182.97263 | AE41: 182.19159 | AF41: 181.78348 | AG41: 183.63301 | AH41: 184.91869 | AI41: 184.71197 | AJ41: -0.002
A42: Energy Consumption per Unit of Refinery Input | C42: 35-AEO2022.45.
A43: (thousand Btu per barrel) | C43: 35-AEO2022.46.
A44: Residual Fuel Oil | B44: Refining Industry: Refinery Only Energy: Use per Unit of Refinery Input: Residual Fuel Oil: Low economic growth | C44: 35-AEO2022.47.lowmacro-d011222a | D44: thousand Btu/b | F44: 0.037319 | G44: 0.034619 | H44: 0 | I44: 0 | J44: 0 | K44: 0 | L44: 0 | M44: 0 | N44: 0 | O44: 0 | P44: 0 | Q44: 0 | R44: 0 | S44: 0 | T44: 0 | U44: 0 | V44: 0 | W44: 0 | X44: 0 | Y44: 0 | Z44: 0 | AA44: 0 | AB44: 0 | AC44: 0 | AD44: 0 | AE44: 0 | AF44: 0 | AG44: 0 | AH44: 0 | AI44: 0 | AJ44: - -
A45: Distillate Fuel Oil | B45: Refining Industry: Refinery Only Energy: Use per Unit of Refinery Input: Distillate Fuel Oil: Low economic growth | C45: 35-AEO2022.48.lowmacro-d011222a | D45: thousand Btu/b | F45: 0.283381 | G45: 0.262881 | H45: 0 | I45: 0 | J45: 0 | K45: 0 | L45: 0 | M45: 0 | N45: 0 | O45: 0 | P45: 0 | Q45: 0 | R45: 0 | S45: 0 | T45: 0 | U45: 0 | V45: 0 | W45: 0 | X45: 0 | Y45: 0 | Z45: 0 | AA45: 0 | AB45: 0 | AC45: 0 | AD45: 0 | AE45: 0 | AF45: 0 | AG45: 0 | AH45: 0 | AI45: 0 | AJ45: - -
A46: Liquefied Petroleum Gas Heat and Power | B46: Refining Industry: Refinery Only Energy: Use per Unit of Refinery Input: Liquefied Petroleum Gases: Low economic growth | C46: 35-AEO2022.49.lowmacro-d011222a | D46: thousand Btu/b | F46: 1.188106 | G46: 1.102158 | H46: 0 | I46: 0 | J46: 0 | K46: 0 | L46: 0 | M46: 0 | N46: 0 | O46: 0 | P46: 0 | Q46: 0 | R46: 0 | S46: 0 | T46: 0 | U46: 0 | V46: 0 | W46: 0 | X46: 0 | Y46: 0 | Z46: 0 | AA46: 0 | AB46: 0 | AC46: 0 | AD46: 0 | AE46: 0 | AF46: 0 | AG46: 0 | AH46: 0 | AI46: 0 | AJ46: - -
A47: Petroleum Coke | B47: Refining Industry: Refinery Only Energy: Use per Unit of Refinery Input: Petroleum Coke: Low economic growth | C47: 35-AEO2022.50.lowmacro-d011222a | D47: thousand Btu/b | F47: 79.280151 | G47: 79.544678 | H47: 81.780861 | I47: 80.661522 | J47: 80.56424 | K47: 79.677536 | L47: 79.57605 | M47: 80.22213 | N47: 80.653999 | O47: 81.707489 | P47: 82.070763 | Q47: 82.358376 | R47: 82.818779 | S47: 83.412109 | T47: 83.564903 | U47: 84.050575 | V47: 84.018585 | W47: 83.944855 | X47: 84.446342 | Y47: 84.134544 | Z47: 84.220055 | AA47: 84.456085 | AB47: 84.564056 | AC47: 84.709908 | AD47: 85.429581 | AE47: 85.61158 | AF47: 86.097733 | AG47: 86.348457 | AH47: 86.922874 | AI47: 87.191742 | AJ47: 0.003
A48: Still Gas | B48: Refining Industry: Refinery Only Energy: Use per Unit of Refinery Input: Still Gas: Low economic growth | C48: 35-AEO2022.51.lowmacro-d011222a | D48: thousand Btu/b | F48: 222.67007 | G48: 206.40355 | H48: 211.29466 | I48: 209.41705 | J48: 210.25058 | K48: 211.50514 | L48: 210.23694 | M48: 213.28737 | N48: 213.66791 | O48: 214.5806 | P48: 214.95628 | Q48: 218.16882 | R48: 218.59134 | S48: 220.08536 | T48: 221.6243 | U48: 224.17976 | V48: 228.31232 | W48: 228.24437 | X48: 229.75481 | Y48: 227.21016 | Z48: 227.38393 | AA48: 226.30421 | AB48: 224.57758 | AC48: 225.25743 | AD48: 224.49007 | AE48: 223.38463 | AF48: 222.85178 | AG48: 224.51196 | AH48: 225.97487 | AI48: 224.32971 | AJ48: 0
A49: Other Petroleum | B49: Refining Industry: Refinery Only Energy: Use per Unit of Refinery Input: Other Petroleum: Low economic growth | C49: 35-AEO2022.52.lowmacro-d011222a | D49: thousand Btu/b | F49: 0.51584 | G49: 0.478524 | H49: 0 | I49: 0 | J49: 0.05899 | K49: 0.114314 | L49: 1.585572 | M49: 0.26174 | N49: 0 | O49: 0 | P49: 0 | Q49: 0.002121 | R49: 0 | S49: 0 | T49: 0.00315 | U49: 0.022734 | V49: 0.00459 | W49: 0.002063 | X49: 0.016545 | Y49: 0.005387 | Z49: 0.006906 | AA49: 0.012975 | AB49: 0.010187 | AC49: 0.001963 | AD49: 0.004298 | AE49: 0.006653 | AF49: 0.002122 | AG49: 0.006594 | AH49: 0.007111 | AI49: 0.006287 | AJ49: -0.141
A50: Petroleum and Other Liquids Subtotal | B50: Refining Industry: Refinery Only Energy: Use per Unit of Refinery Input: Petroleum Subtotal: Low economic growth | C50: 35-AEO2022.53.lowmacro-d011222a | D50: thousand Btu/b | F50: 303.97488 | G50: 287.82642 | H50: 293.07553 | I50: 290.07858 | J50: 290.87381 | K50: 291.297 | L50: 291.39856 | M50: 293.77124 | N50: 294.3219 | O50: 296.28809 | P50: 297.02704 | Q50: 300.5293 | R50: 301.41013 | S50: 303.49747 | T50: 305.19235 | U50: 308.25308 | V50: 312.33548 | W50: 312.19128 | X50: 314.21768 | Y50: 311.3501 | Z50: 311.61087 | AA50: 310.77328 | AB50: 309.15182 | AC50: 309.9693 | AD50: 309.92395 | AE50: 309.00287 | AF50: 308.95166 | AG50: 310.867 | AH50: 312.90485 | AI50: 311.52774 | AJ50: 0.001
A51: Natural Gas | B51: Refining Industry: Refinery Only Energy: Use per Unit of Refinery Input: Natural Gas: Low economic growth | C51: 35-AEO2022.54.lowmacro-d011222a | D51: thousand Btu/b | F51: 149.7511 | G51: 138.68027 | H51: 88.05098 | I51: 84.077591 | J51: 83.911285 | K51: 87.158447 | L51: 86.002411 | M51: 87.418015 | N51: 88.851624 | O51: 89.586426 | P51: 89.933205 | Q51: 86.245461 | R51: 87.195091 | S51: 89.760078 | T51: 89.130844 | U51: 92.888977 | V51: 92.42791 | W51: 93.531281 | X51: 93.95079 | Y51: 95.732025 | Z51: 95.355438 | AA51: 96.382484 | AB51: 97.365112 | AC51: 98.29612 | AD51: 98.895828 | AE51: 98.013405 | AF51: 100.06839 | AG51: 102.05875 | AH51: 103.0773 | AI51: 104.78747 | AJ51: -0.012
A52: Steam Coal | B52: Refining Industry: Refinery Only Energy: Use per Unit of Refinery Input: Steam Coal: Low economic growth | C52: 35-AEO2022.55.lowmacro-d011222a | D52: thousand Btu/b | F52: 0 | G52: 0 | H52: 0 | I52: 0 | J52: 0 | K52: 0 | L52: 0 | M52: 0 | N52: 0 | O52: 0 | P52: 0 | Q52: 0 | R52: 0 | S52: 0 | T52: 0 | U52: 0 | V52: 0 | W52: 0 | X52: 0 | Y52: 0 | Z52: 0 | AA52: 0 | AB52: 0 | AC52: 0 | AD52: 0 | AE52: 0 | AF52: 0 | AG52: 0 | AH52: 0 | AI52: 0 | AJ52: - -
A53: Purchased Electricity | B53: Refining Industry: Refinery Only Energy: Use per Unit of Refinery Input: Purchased Electricity: Low economic growth | C53: 35-AEO2022.56.lowmacro-d011222a | D53: thousand Btu/b | F53: 26.197104 | G53: 24.302 | H53: 23.37495 | I53: 22.800919 | J53: 22.782293 | K53: 23.007113 | L53: 22.605946 | M53: 22.974205 | N53: 23.179577 | O53: 23.50761 | P53: 23.466461 | Q53: 24.120848 | R53: 24.18531 | S53: 24.688444 | T53: 24.60799 | U53: 25.24062 | V53: 25.453297 | W53: 25.55847 | X53: 25.714811 | Y53: 25.750414 | Z53: 25.824131 | AA53: 25.82107 | AB53: 25.854275 | AC53: 26.007029 | AD53: 25.996412 | AE53: 25.866236 | AF53: 25.964985 | AG53: 26.271894 | AH53: 26.564564 | AI53: 26.483217 | AJ53: 0
A54: Total | B54: Refining Industry: Refinery Only Energy: Use per Unit of Refinery Input: Total: Low economic growth | C54: 35-AEO2022.57.lowmacro-d011222a | D54: thousand Btu/b | F54: 479.9231 | G54: 450.80869 | H54: 404.50146 | I54: 396.95709 | J54: 397.56738 | K54: 401.46256 | L54: 400.00693 | M54: 404.16348 | N54: 406.35309 | O54: 409.38211 | P54: 410.4267 | Q54: 410.8956 | R54: 412.79053 | S54: 417.94598 | T54: 418.93118 | U54: 426.38269 | V54: 430.2167 | W54: 431.28104 | X54: 433.88327 | Y54: 432.83255 | Z54: 432.79044 | AA54: 432.97684 | AB54: 432.37122 | AC54: 434.27243 | AD54: 434.81616 | AE54: 432.88251 | AF54: 434.98505 | AG54: 439.19763 | AH54: 442.54672 | AI54: 442.79843 | AJ54: -0.003
A55: Combined Heat and Power | C55: 35-AEO2022.59.
A56: Generating Capacity (gigawatts) | C56: 35-AEO2022.60.
A57: Petroleum | B57: Refining Industry: Combined Heat and Power: Generating Capacity: Petroleum: Low economic growth | C57: 35-AEO2022.61.lowmacro-d011222a | D57: GW | F57: 0.1353 | G57: 0.1353 | H57: 0.1353 | I57: 0.1353 | J57: 0.1353 | K57: 0.1353 | L57: 0.1353 | M57: 0.1353 | N57: 0.1353 | O57: 0.1353 | P57: 0.1353 | Q57: 0.1353 | R57: 0.1353 | S57: 0.1353 | T57: 0.1353 | U57: 0.1353 | V57: 0.1353 | W57: 0.1353 | X57: 0.1353 | Y57: 0.1353 | Z57: 0.1353 | AA57: 0.1353 | AB57: 0.1353 | AC57: 0.1353 | AD57: 0.1353 | AE57: 0.1353 | AF57: 0.1353 | AG57: 0.1353 | AH57: 0.1353 | AI57: 0.1353 | AJ57: 0
A58: Natural Gas | B58: Refining Industry: Combined Heat and Power: Generating Capacity: Natural Gas: Low economic growth | C58: 35-AEO2022.62.lowmacro-d011222a | D58: GW | F58: 3.3355 | G58: 3.3355 | H58: 3.3355 | I58: 3.3355 | J58: 3.3355 | K58: 3.3355 | L58: 3.3355 | M58: 3.3355 | N58: 3.3355 | O58: 3.3355 | P58: 3.3355 | Q58: 3.3355 | R58: 3.3355 | S58: 3.3355 | T58: 3.3355 | U58: 3.3355 | V58: 3.3355 | W58: 3.3355 | X58: 3.3355 | Y58: 3.3355 | Z58: 3.3355 | AA58: 3.3355 | AB58: 3.3355 | AC58: 3.3355 | AD58: 3.3355 | AE58: 3.3355 | AF58: 3.3355 | AG58: 3.3355 | AH58: 3.3355 | AI58: 3.3355 | AJ58: 0
A59: Coal | B59: Refining Industry: Combined Heat and Power: Generating Capacity: Coal: Low economic growth | C59: 35-AEO2022.63.lowmacro-d011222a | D59: GW | F59: 0 | G59: 0 | H59: 0 | I59: 0 | J59: 0 | K59: 0 | L59: 0 | M59: 0 | N59: 0 | O59: 0 | P59: 0 | Q59: 0 | R59: 0 | S59: 0 | T59: 0 | U59: 0 | V59: 0 | W59: 0 | X59: 0 | Y59: 0 | Z59: 0 | AA59: 0 | AB59: 0 | AC59: 0 | AD59: 0 | AE59: 0 | AF59: 0 | AG59: 0 | AH59: 0 | AI59: 0 | AJ59: - -
A60: Other | B60: Refining Industry: Combined Heat and Power: Generating Capacity: Other: Low economic growth | C60: 35-AEO2022.64.lowmacro-d011222a | D60: GW | F60: 1.0951 | G60: 1.0951 | H60: 1.0951 | I60: 1.0951 | J60: 1.0951 | K60: 1.0951 | L60: 1.0951 | M60: 1.0951 | N60: 1.0951 | O60: 1.0951 | P60: 1.0951 | Q60: 1.0951 | R60: 1.0951 | S60: 1.0951 | T60: 1.0951 | U60: 1.0951 | V60: 1.0951 | W60: 1.0951 | X60: 1.0951 | Y60: 1.0951 | Z60: 1.0951 | AA60: 1.0951 | AB60: 1.0951 | AC60: 1.0951 | AD60: 1.0951 | AE60: 1.0951 | AF60: 1.0951 | AG60: 1.0951 | AH60: 1.0951 | AI60: 1.0951 | AJ60: 0
A61: Total | B61: Refining Industry: Combined Heat and Power: Generating Capacity: Total: Low economic growth | C61: 35-AEO2022.65.lowmacro-d011222a | D61: GW | F61: 4.5659 | G61: 4.5659 | H61: 4.5659 | I61: 4.5659 | J61: 4.5659 | K61: 4.5659 | L61: 4.5659 | M61: 4.5659 | N61: 4.5659 | O61: 4.5659 | P61: 4.5659 | Q61: 4.5659 | R61: 4.5659 | S61: 4.5659 | T61: 4.5659 | U61: 4.5659 | V61: 4.5659 | W61: 4.5659 | X61: 4.5659 | Y61: 4.5659 | Z61: 4.5659 | AA61: 4.5659 | AB61: 4.5659 | AC61: 4.5659 | AD61: 4.5659 | AE61: 4.5659 | AF61: 4.5659 | AG61: 4.5659 | AH61: 4.5659 | AI61: 4.5659 | AJ61: 0
A62: Net Generation (billion kilowatthours) | C62: 35-AEO2022.66.
A63: Petroleum | B63: Refining Industry: Combined Heat and Power: Net Generation: Petroleum: Low economic growth | C63: 35-AEO2022.67.lowmacro-d011222a | D63: BkWh | F63: 0.3593 | G63: 0.39106 | H63: 0 | I63: 0 | J63: 0 | K63: 0 | L63: 0 | M63: 0 | N63: 0 | O63: 0 | P63: 0 | Q63: 0 | R63: 0 | S63: 0 | T63: 0 | U63: 0 | V63: 0 | W63: 0 | X63: 0 | Y63: 0 | Z63: 0 | AA63: 0 | AB63: 0 | AC63: 0 | AD63: 0 | AE63: 0 | AF63: 0 | AG63: 0 | AH63: 0 | AI63: 0 | AJ63: - -
A64: Natural Gas | B64: Refining Industry: Combined Heat and Power: Net Generation: Natural Gas: Low economic growth | C64: 35-AEO2022.68.lowmacro-d011222a | D64: BkWh | F64: 24.35149 | G64: 25.159262 | H64: 24.43865 | I64: 24.121645 | J64: 24.43865 | K64: 24.43865 | L64: 24.43865 | M64: 24.43865 | N64: 24.43865 | O64: 24.43865 | P64: 24.43865 | Q64: 23.34457 | R64: 23.458542 | S64: 23.510744 | T64: 23.606461 | U64: 23.671148 | V64: 23.808113 | W64: 23.861492 | X64: 23.885506 | Y64: 23.728643 | Z64: 23.664204 | AA64: 23.659025 | AB64: 23.610271 | AC64: 23.681173 | AD64: 23.773306 | AE64: 23.755255 | AF64: 23.7721 | AG64: 24.053558 | AH64: 24.044323 | AI64: 24.341949 | AJ64: 0
A65: Coal | B65: Refining Industry: Combined Heat and Power: Net Generation: Coal: Low economic growth | C65: 35-AEO2022.69.lowmacro-d011222a | D65: BkWh | F65: 0 | G65: 0 | H65: 0 | I65: 0 | J65: 0 | K65: 0 | L65: 0 | M65: 0 | N65: 0 | O65: 0 | P65: 0 | Q65: 0 | R65: 0 | S65: 0 | T65: 0 | U65: 0 | V65: 0 | W65: 0 | X65: 0 | Y65: 0 | Z65: 0 | AA65: 0 | AB65: 0 | AC65: 0 | AD65: 0 | AE65: 0 | AF65: 0 | AG65: 0 | AH65: 0 | AI65: 0 | AJ65: - -
A66: Other | B66: Refining Industry: Combined Heat and Power: Net Generation: Other: Low economic growth | C66: 35-AEO2022.70.lowmacro-d011222a | D66: BkWh | F66: 4.80197 | G66: 4.99792 | H66: 6.109663 | I66: 6.030411 | J66: 6.109663 | K66: 6.109663 | L66: 6.109663 | M66: 6.109663 | N66: 6.109663 | O66: 6.109663 | P66: 6.109663 | Q66: 5.836143 | R66: 5.864635 | S66: 5.877686 | T66: 5.901615 | U66: 5.917787 | V66: 5.952028 | W66: 5.965373 | X66: 5.971376 | Y66: 5.932161 | Z66: 5.916051 | AA66: 5.914756 | AB66: 5.902568 | AC66: 5.920293 | AD66: 5.943326 | AE66: 5.938814 | AF66: 5.943025 | AG66: 6.01339 | AH66: 6.011081 | AI66: 6.085487 | AJ66: 0.008
A67: Total | B67: Refining Industry: Combined Heat and Power: Net Generation: Total: Low economic growth | C67: 35-AEO2022.71.lowmacro-d011222a | D67: BkWh | F67: 29.51276 | G67: 30.548241 | H67: 30.548313 | I67: 30.152056 | J67: 30.548313 | K67: 30.548313 | L67: 30.548313 | M67: 30.548313 | N67: 30.548313 | O67: 30.548313 | P67: 30.548313 | Q67: 29.180714 | R67: 29.323177 | S67: 29.38843 | T67: 29.508076 | U67: 29.588936 | V67: 29.760141 | W67: 29.826866 | X67: 29.856882 | Y67: 29.660805 | Z67: 29.580254 | AA67: 29.573782 | AB67: 29.51284 | AC67: 29.601467 | AD67: 29.716633 | AE67: 29.694069 | AF67: 29.715126 | AG67: 30.066948 | AH67: 30.055405 | AI67: 30.427437 | AJ67: 0.001
A68: Disposition | C68: 35-AEO2022.72.
A69: Sales to the Grid | B69: Refining Industry: Combined Heat and Power: Net Generation: Sales to the Grid: Low economic growth | C69: 35-AEO2022.73.lowmacro-d011222a | D69: BkWh | F69: 9.383711 | G69: 10.545921 | H69: 0 | I69: 0 | J69: 0 | K69: 0 | L69: 0 | M69: 0 | N69: 0 | O69: 0 | P69: 0 | Q69: 0 | R69: 0 | S69: 0 | T69: 0 | U69: 0 | V69: 0 | W69: 0 | X69: 0 | Y69: 0 | Z69: 0 | AA69: 0 | AB69: 0 | AC69: 0 | AD69: 0 | AE69: 0 | AF69: 0 | AG69: 0 | AH69: 0 | AI69: 0 | AJ69: - -
A70: Generation for Own Use | B70: Refining Industry: Combined Heat and Power: Net Generation: Generation for Own Use: Low economic growth | C70: 35-AEO2022.74.lowmacro-d011222a | D70: BkWh | F70: 20.129051 | G70: 20.002319 | H70: 30.548311 | I70: 30.152056 | J70: 30.548311 | K70: 30.548311 | L70: 30.548311 | M70: 30.548311 | N70: 30.548311 | O70: 30.548311 | P70: 30.548311 | Q70: 29.180712 | R70: 29.323177 | S70: 29.38843 | T70: 29.508076 | U70: 29.588936 | V70: 29.760139 | W70: 29.826864 | X70: 29.85688 | Y70: 29.660805 | Z70: 29.580256 | AA70: 29.57378 | AB70: 29.512836 | AC70: 29.601467 | AD70: 29.716633 | AE70: 29.694067 | AF70: 29.715126 | AG70: 30.066946 | AH70: 30.055405 | AI70: 30.427439 | AJ70: 0.014
A71: Energy Consumed at Ethanol Plants | C71: 35-AEO2022.82.
A72: (trillion Btu) | C72: 35-AEO2022.83.
A73: Natural Gas | B73: Refining Industry: Energy Consumed at Ethanol Plants: Natural Gas: Low economic growth | C73: 35-AEO2022.84.lowmacro-d011222a | D73: trillion Btu | F73: 368 | G73: 368 | H73: 430.81705 | I73: 430.56384 | J73: 434.306 | K73: 434.91617 | L73: 434.97967 | M73: 435.16934 | N73: 438.36966 | O73: 439.5571 | P73: 441.27744 | Q73: 442.77075 | R73: 443.9158 | S73: 445.42871 | T73: 446.7699 | U73: 447.50381 | V73: 448.47006 | W73: 449.73126 | X73: 452.62299 | Y73: 452.85113 | Z73: 454.72369 | AA73: 457.35724 | AB73: 460.89511 | AC73: 468.09613 | AD73: 472.39056 | AE73: 477.27792 | AF73: 482.48898 | AG73: 487.8479 | AH73: 493.48193 | AI73: 500.63315 | AJ73: 0.011
A74: Coal | B74: Refining Industry: Energy Consumed at Ethanol Plants: Coal: Low economic growth | C74: 35-AEO2022.85.lowmacro-d011222a | D74: trillion Btu | F74: 24 | G74: 24 | H74: 0 | I74: 0 | J74: 0 | K74: 0 | L74: 0 | M74: 0 | N74: 0 | O74: 0 | P74: 0 | Q74: 0.044211 | R74: 0.587311 | S74: 0.587311 | T74: 4.129168 | U74: 6.791768 | V74: 10.297455 | W74: 13.768188 | X74: 24.259581 | Y74: 24.055048 | Z74: 30.481363 | AA74: 30.481363 | AB74: 30.481363 | AC74: 30.481363 | AD74: 30.472221 | AE74: 30.481363 | AF74: 30.481363 | AG74: 30.481363 | AH74: 30.481363 | AI74: 30.481363 | AJ74: 0.008
A75: Electricity | B75: Refining Industry: Energy Consumed at Ethanol Plants: Electricity: Low economic growth | C75: 35-AEO2022.86.lowmacro-d011222a | D75: trillion Btu | F75: 37 | G75: 37 | H75: 41.375824 | I75: 41.351852 | J75: 41.70615 | K75: 41.763924 | L75: 41.769936 | M75: 41.787891 | N75: 42.090889 | O75: 42.203312 | P75: 42.366188 | Q75: 42.511578 | R75: 42.65873 | S75: 42.830612 | T75: 43.094223 | U75: 43.261223 | V75: 43.481102 | W75: 43.733391 | X75: 44.391418 | Y75: 44.410915 | Z75: 44.825485 | AA75: 45.138947 | AB75: 45.526638 | AC75: 46.344772 | AD75: 46.832386 | AE75: 47.387943 | AF75: 47.979988 | AG75: 48.588833 | AH75: 49.228935 | AI75: 50.041409 | AJ75: 0.01
A76: Total | B76: Refining Industry: Energy Consumed at Ethanol Plants: Total: Low economic growth | C76: 35-AEO2022.87.lowmacro-d011222a | D76: trillion Btu | F76: 429 | G76: 429 | H76: 472.19287 | I76: 471.91571 | J76: 476.01215 | K76: 476.68008 | L76: 476.7496 | M76: 476.95725 | N76: 480.46054 | O76: 481.76041 | P76: 483.64362 | Q76: 485.32654 | R76: 487.16183 | S76: 488.84662 | T76: 493.99329 | U76: 497.55682 | V76: 502.24863 | W76: 507.23285 | X76: 521.27399 | Y76: 521.31708 | Z76: 530.03052 | AA76: 532.97754 | AB76: 536.90308 | AC76: 544.92224 | AD76: 549.69519 | AE76: 555.14722 | AF76: 560.95032 | AG76: 566.91809 | AH76: 573.19226 | AI76: 581.15588 | AJ76: 0.011

Sheet AEO T24 Refining 2022
B1: ref2022.d011222a | C1: 2021 | D1: 2022 | E1: 2023 | F1: 2024 | G1: 2025 | H1: 2026 | I1: 2027 | J1: 2028 | K1: 2029 | L1: 2030 | M1: 2031 | N1: 2032 | O1: 2033 | P1: 2034 | Q1: 2035 | R1: 2036 | S1: 2037 | T1: 2038 | U1: 2039 | V1: 2040 | W1: 2041 | X1: 2042 | Y1: 2043 | Z1: 2044 | AA1: 2045 | AB1: 2046 | AC1: 2047 | AD1: 2048 | AE1: 2049 | AF1: 2050
A4: IRF000 | B4: 24. Refining Industry Energy Consumption | AG4: Average
AG5: Annual
B7: Shipments, Energy Consumption, and Emissions | C7: 2021 | D7: 2022 | E7: 2023 | F7: 2024 | G7: 2025 | H7: 2026 | I7: 2027 | J7: 2028 | K7: 2029 | L7: 2030 | M7: 2031 | N7: 2032 | O7: 2033 | P7: 2034 | Q7: 2035 | R7: 2036 | S7: 2037 | T7: 2038 | U7: 2039 | V7: 2040 | W7: 2041 | X7: 2042 | Y7: 2043 | Z7: 2044 | AA7: 2045 | AB7: 2046 | AC7: 2047 | AD7: 2048 | AE7: 2049 | AF7: 2050 | AG7: 2051
A9: IRF000:ba_ValueofShipme | B9: Value of Shipments (billion 2012 dollars) | C9: ='AEO T24 Refining 2022 Raw'!F6 -> 746.87048 | D9: ='AEO T24 Refining 2022 Raw'!G6 -> 840.716 | E9: ='AEO T24 Refining 2022 Raw'!H6 -> 850.76227 | F9: ='AEO T24 Refining 2022 Raw'!I6 -> 846.17731 | G9: ='AEO T24 Refining 2022 Raw'!J6 -> 846.14966 | H9: ='AEO T24 Refining 2022 Raw'!K6 -> 844.26404 | I9: ='AEO T24 Refining 2022 Raw'!L6 -> 840.59943 | J9: ='AEO T24 Refining 2022 Raw'!M6 -> 838.8761 | ... AG9: ='AEO T24 Refining 2022 Raw'!AJ6 -> 0.004
B10: Inputs to Distillation Units
A11: IRF000:ba_CrudeOilInput | B11: (million barrels per day) | C11: ='AEO T24 Refining 2022 Raw'!F8 -> 15.710509 | D11: ='AEO T24 Refining 2022 Raw'!G8 -> 16.935637 | E11: ='AEO T24 Refining 2022 Raw'!H8 -> 17.158117 | F11: ='AEO T24 Refining 2022 Raw'!I8 -> 17.243862 | G11: ='AEO T24 Refining 2022 Raw'!J8 -> 17.289557 | H11: ='AEO T24 Refining 2022 Raw'!K8 -> 17.248625 | I11: ='AEO T24 Refining 2022 Raw'!L8 -> 17.194527 | J11: ='AEO T24 Refining 2022 Raw'!M8 -> 17.125137 | ... AG11: ='AEO T24 Refining 2022 Raw'!AJ8 -> 0.001
B13: Total Energy Consumption (trillion Btu) 1/
A14: IRF000:ca_ResidualOil | B14: Residual Fuel Oil | C14: ='AEO T24 Refining 2022 Raw'!F10 -> 0.214 | D14: ='AEO T24 Refining 2022 Raw'!G10 -> 0.214 | E14: ='AEO T24 Refining 2022 Raw'!H10 -> 0 | F14: ='AEO T24 Refining 2022 Raw'!I10 -> 0 | G14: ='AEO T24 Refining 2022 Raw'!J10 -> 0 | H14: ='AEO T24 Refining 2022 Raw'!K10 -> 0 | I14: ='AEO T24 Refining 2022 Raw'!L10 -> 0 | J14: ='AEO T24 Refining 2022 Raw'!M10 -> 0 | ... AG14: ='AEO T24 Refining 2022 Raw'!AJ10 -> - -
A15: IRF000:ca_DistillateOil | B15: Distillate Fuel Oil | C15: ='AEO T24 Refining 2022 Raw'!F11 -> 1.625 | D15: ='AEO T24 Refining 2022 Raw'!G11 -> 1.625 | E15: ='AEO T24 Refining 2022 Raw'!H11 -> 0 | F15: ='AEO T24 Refining 2022 Raw'!I11 -> 0 | G15: ='AEO T24 Refining 2022 Raw'!J11 -> 0 | H15: ='AEO T24 Refining 2022 Raw'!K11 -> 0 | I15: ='AEO T24 Refining 2022 Raw'!L11 -> 0 | J15: ='AEO T24 Refining 2022 Raw'!M11 -> 0 | ... AG15: ='AEO T24 Refining 2022 Raw'!AJ11 -> - -
A16: IRF000:ca_LiquefiedPetr | B16: Liquefied Petroleum Gas Heat and Power 2/ | C16: ='AEO T24 Refining 2022 Raw'!F12 -> 6.813 | D16: ='AEO T24 Refining 2022 Raw'!G12 -> 6.813 | E16: ='AEO T24 Refining 2022 Raw'!H12 -> 0 | F16: ='AEO T24 Refining 2022 Raw'!I12 -> 0 | G16: ='AEO T24 Refining 2022 Raw'!J12 -> 0 | H16: ='AEO T24 Refining 2022 Raw'!K12 -> 0 | I16: ='AEO T24 Refining 2022 Raw'!L12 -> 0 | J16: ='AEO T24 Refining 2022 Raw'!M12 -> 0 | ... AG16: ='AEO T24 Refining 2022 Raw'!AJ12 -> - -
A17: IRF000:ca_PetroleumCoke | B17: Petroleum Coke | C17: ='AEO T24 Refining 2022 Raw'!F13 -> 457.229 | D17: ='AEO T24 Refining 2022 Raw'!G13 -> 494.56598 | E17: ='AEO T24 Refining 2022 Raw'!H13 -> 512.17004 | F17: ='AEO T24 Refining 2022 Raw'!I13 -> 507.68442 | G17: ='AEO T24 Refining 2022 Raw'!J13 -> 508.41577 | H17: ='AEO T24 Refining 2022 Raw'!K13 -> 501.6297 | I17: ='AEO T24 Refining 2022 Raw'!L13 -> 499.41949 | J17: ='AEO T24 Refining 2022 Raw'!M13 -> 501.44247 | ... AG17: ='AEO T24 Refining 2022 Raw'!AJ13 -> 0.004
A18: IRF000:ca_StillGas | B18: Still Gas | C18: ='AEO T24 Refining 2022 Raw'!F14 -> 1307.035 | D18: ='AEO T24 Refining 2022 Raw'!G14 -> 1307.035 | E18: ='AEO T24 Refining 2022 Raw'!H14 -> 1376.4792 | F18: ='AEO T24 Refining 2022 Raw'!I14 -> 1370.5844 | G18: ='AEO T24 Refining 2022 Raw'!J14 -> 1380.0272 | H18: ='AEO T24 Refining 2022 Raw'!K14 -> 1384.7845 | I18: ='AEO T24 Refining 2022 Raw'!L14 -> 1372.6489 | J18: ='AEO T24 Refining 2022 Raw'!M14 -> 1386.3915 | ... AG18: ='AEO T24 Refining 2022 Raw'!AJ14 -> 0.002
A19: IRF000:ca_OtherPetroleu | B19: Other Petroleum 3/ | C19: ='AEO T24 Refining 2022 Raw'!F15 -> 2.958 | D19: ='AEO T24 Refining 2022 Raw'!G15 -> 2.958 | E19: ='AEO T24 Refining 2022 Raw'!H15 -> 0 | F19: ='AEO T24 Refining 2022 Raw'!I15 -> 0 | G19: ='AEO T24 Refining 2022 Raw'!J15 -> 0.372267 | H19: ='AEO T24 Refining 2022 Raw'!K15 -> 0.71969 | I19: ='AEO T24 Refining 2022 Raw'!L15 -> 9.951056 | J19: ='AEO T24 Refining 2022 Raw'!M15 -> 1.636055 | ... AG19: ='AEO T24 Refining 2022 Raw'!AJ15 -> -0.14
A20: IRF000:ca_PetroleumSubt | B20: Petroleum and Other Liquids Subtotal | C20: ='AEO T24 Refining 2022 Raw'!F16 -> 1775.874 | D20: ='AEO T24 Refining 2022 Raw'!G16 -> 1813.2111 | E20: ='AEO T24 Refining 2022 Raw'!H16 -> 1888.6493 | F20: ='AEO T24 Refining 2022 Raw'!I16 -> 1878.2688 | G20: ='AEO T24 Refining 2022 Raw'!J16 -> 1888.8153 | H20: ='AEO T24 Refining 2022 Raw'!K16 -> 1887.134 | I20: ='AEO T24 Refining 2022 Raw'!L16 -> 1882.0194 | J20: ='AEO T24 Refining 2022 Raw'!M16 -> 1889.4701 | ... AG20: ='AEO T24 Refining 2022 Raw'!AJ16 -> 0.002
A21: IRF000:ca_NaturalGas | B21: Natural Gas | C21: ='AEO T24 Refining 2022 Raw'!F17 -> 1567.2632 | D21: ='AEO T24 Refining 2022 Raw'!G17 -> 1576.2631 | E21: ='AEO T24 Refining 2022 Raw'!H17 -> 1398.3788 | F21: ='AEO T24 Refining 2022 Raw'!I17 -> 1360.6981 | G21: ='AEO T24 Refining 2022 Raw'!J17 -> 1366.2755 | H21: ='AEO T24 Refining 2022 Raw'!K17 -> 1393.6177 | I21: ='AEO T24 Refining 2022 Raw'!L17 -> 1380.9757 | J21: ='AEO T24 Refining 2022 Raw'!M17 -> 1389.9215 | ... AG21: ='AEO T24 Refining 2022 Raw'!AJ17 -> 0
A22: IRF000:NatGas_owHeatPow | B22: of which: Heat and Power | C22: ='AEO T24 Refining 2022 Raw'!F18 -> 1376.2632 | D22: ='AEO T24 Refining 2022 Raw'!G18 -> 1376.2631 | E22: ='AEO T24 Refining 2022 Raw'!H18 -> 1195.0608 | F22: ='AEO T24 Refining 2022 Raw'!I18 -> 1169.7944 | G22: ='AEO T24 Refining 2022 Raw'!J18 -> 1176.6498 | H22: ='AEO T24 Refining 2022 Raw'!K18 -> 1196.4496 | I22: ='AEO T24 Refining 2022 Raw'!L18 -> 1187.5369 | J22: ='AEO T24 Refining 2022 Raw'!M18 -> 1194.3967 | ... AG22: ='AEO T24 Refining 2022 Raw'!AJ18 -> -0.001
A23: IRF000:NatGas_owFeed | B23: of which: Feedstocks | C23: ='AEO T24 Refining 2022 Raw'!F19 -> 191 | D23: ='AEO T24 Refining 2022 Raw'!G19 -> 200 | E23: ='AEO T24 Refining 2022 Raw'!H19 -> 203.31799 | F23: ='AEO T24 Refining 2022 Raw'!I19 -> 190.90372 | G23: ='AEO T24 Refining 2022 Raw'!J19 -> 189.62576 | H23: ='AEO T24 Refining 2022 Raw'!K19 -> 197.16812 | I23: ='AEO T24 Refining 2022 Raw'!L19 -> 193.4389 | J23: ='AEO T24 Refining 2022 Raw'!M19 -> 195.5248 | ... AG23: ='AEO T24 Refining 2022 Raw'!AJ19 -> 0.005
A24: IRF000:NatGas_owGTLHeat | B24: of which: Gas-to-Liquids Heat | C24: ='AEO T24 Refining 2022 Raw'!F20 -> 0 | D24: ='AEO T24 Refining 2022 Raw'!G20 -> 0 | E24: ='AEO T24 Refining 2022 Raw'!H20 -> 0 | F24: ='AEO T24 Refining 2022 Raw'!I20 -> 0 | G24: ='AEO T24 Refining 2022 Raw'!J20 -> 0 | H24: ='AEO T24 Refining 2022 Raw'!K20 -> 0 | I24: ='AEO T24 Refining 2022 Raw'!L20 -> 0 | J24: ='AEO T24 Refining 2022 Raw'!M20 -> 0 | ... AG24: ='AEO T24 Refining 2022 Raw'!AJ20 -> - -
A25: IRF000:ca_SteamCoal | B25: Steam Coal 4/ | C25: ='AEO T24 Refining 2022 Raw'!F21 -> 24 | D25: ='AEO T24 Refining 2022 Raw'!G21 -> 24 | E25: ='AEO T24 Refining 2022 Raw'!H21 -> 0 | F25: ='AEO T24 Refining 2022 Raw'!I21 -> 0 | G25: ='AEO T24 Refining 2022 Raw'!J21 -> 0 | H25: ='AEO T24 Refining 2022 Raw'!K21 -> 0 | I25: ='AEO T24 Refining 2022 Raw'!L21 -> 0 | J25: ='AEO T24 Refining 2022 Raw'!M21 -> 0 | ... AG25: ='AEO T24 Refining 2022 Raw'!AJ21 -> 0.008
... A28: IRF000:ca_Total | B28: Total | C28: ='AEO T24 Refining 2022 Raw'!F24 -> 4495.8135 | D28: ='AEO T24 Refining 2022 Raw'!G24 -> 4534.2461 | E28: ='AEO T24 Refining 2022 Raw'!H24 -> 4377.1079 | F28: ='AEO T24 Refining 2022 Raw'!I24 -> 4326.1172 | G28: ='AEO T24 Refining 2022 Raw'!J24 -> 4350.793 | H28: ='AEO T24 Refining 2022 Raw'!K24 -> 4379.0889 | I28: ='AEO T24 Refining 2022 Raw'!L24 -> 4358.6392 | J28: ='AEO T24 Refining 2022 Raw'!M24 -> 4377.2129 | ... AG28: ='AEO T24 Refining 2022 Raw'!AJ24 -> 0.002
B30: Carbon Dioxide Emissions 4/
A31: IRF000:ea_tonscarbon_dd | B31: (million metric tons carbon dioxide) | C31: ='AEO T24 Refining 2022 Raw'!F26 -> 241.70407 | D31: ='AEO T24 Refining 2022 Raw'!G26 -> 245.12738 | E31: ='AEO T24 Refining 2022 Raw'!H26 -> 238.10994 | F31: ='AEO T24 Refining 2022 Raw'!I26 -> 232.64516 | G31: ='AEO T24 Refining 2022 Raw'!J26 -> 233.13074 | H31: ='AEO T24 Refining 2022 Raw'!K26 -> 234.2005 | I31: ='AEO T24 Refining 2022 Raw'!L26 -> 232.07024 | J31: ='AEO T24 Refining 2022 Raw'!M26 -> 233.52861 | ... AG31: ='AEO T24 Refining 2022 Raw'!AJ26 -> 0
B33: Energy Related to Refining Activity Only
B34: Energy Consumption
A35: IRF000:da_ResidualOil | B35: Residual Fuel Oil | C35: ='AEO T24 Refining 2022 Raw'!F29 -> 0.214 | D35: ='AEO T24 Refining 2022 Raw'!G29 -> 0.214 | E35: ='AEO T24 Refining 2022 Raw'!H29 -> 0 | F35: ='AEO T24 Refining 2022 Raw'!I29 -> 0 | G35: ='AEO T24 Refining 2022 Raw'!J29 -> 0 | H35: ='AEO T24 Refining 2022 Raw'!K29 -> 0 | I35: ='AEO T24 Refining 2022 Raw'!L29 -> 0 | J35: ='AEO T24 Refining 2022 Raw'!M29 -> 0 | ... AG35: ='AEO T24 Refining 2022 Raw'!AJ29 -> - -
A36: IRF000:da_DistillateOil | B36: Distillate Fuel Oil | C36: ='AEO T24 Refining 2022 Raw'!F30 -> 1.625 | D36: ='AEO T24 Refining 2022 Raw'!G30 -> 1.625 | E36: ='AEO T24 Refining 2022 Raw'!H30 -> 0 | F36: ='AEO T24 Refining 2022 Raw'!I30 -> 0 | G36: ='AEO T24 Refining 2022 Raw'!J30 -> 0 | H36: ='AEO T24 Refining 2022 Raw'!K30 -> 0 | I36: ='AEO T24 Refining 2022 Raw'!L30 -> 0 | J36: ='AEO T24 Refining 2022 Raw'!M30 -> 0 | ... AG36: ='AEO T24 Refining 2022 Raw'!AJ30 -> - -
A37: IRF000:da_LiquefiedPetr | B37: Liquefied Petroleum Gas Heat and Power 2/ | C37: ='AEO T24 Refining 2022 Raw'!F31 -> 6.813 | D37: ='AEO T24 Refining 2022 Raw'!G31 -> 6.813 | E37: ='AEO T24 Refining 2022 Raw'!H31 -> 0 | F37: ='AEO T24 Refining 2022 Raw'!I31 -> 0 | G37: ='AEO T24 Refining 2022 Raw'!J31 -> 0 | H37: ='AEO T24 Refining 2022 Raw'!K31 -> 0 | I37: ='AEO T24 Refining 2022 Raw'!L31 -> 0 | J37: ='AEO T24 Refining 2022 Raw'!M31 -> 0 | ... AG37: ='AEO T24 Refining 2022 Raw'!AJ31 -> - -
A38: IRF000:da_PetroleumCoke | B38: Petroleum Coke | C38: ='AEO T24 Refining 2022 Raw'!F32 -> 454.61902 | D38: ='AEO T24 Refining 2022 Raw'!G32 -> 491.70599 | E38: ='AEO T24 Refining 2022 Raw'!H32 -> 512.17004 | F38: ='AEO T24 Refining 2022 Raw'!I32 -> 507.68442 | G38: ='AEO T24 Refining 2022 Raw'!J32 -> 508.41577 | H38: ='AEO T24 Refining 2022 Raw'!K32 -> 501.6297 | I38: ='AEO T24 Refining 2022 Raw'!L32 -> 499.41949 | J38: ='AEO T24 Refining 2022 Raw'!M32 -> 501.44247 | ... AG38: ='AEO T24 Refining 2022 Raw'!AJ32 -> 0.005
A39: IRF000:da_StillGas | B39: Still Gas | C39: ='AEO T24 Refining 2022 Raw'!F33 -> 1276.865 | D39: ='AEO T24 Refining 2022 Raw'!G33 -> 1275.885 | E39: ='AEO T24 Refining 2022 Raw'!H33 -> 1323.2778 | F39: ='AEO T24 Refining 2022 Raw'!I33 -> 1318.073 | G39: ='AEO T24 Refining 2022 Raw'!J33 -> 1326.8258 | H39: ='AEO T24 Refining 2022 Raw'!K33 -> 1331.5831 | I39: ='AEO T24 Refining 2022 Raw'!L33 -> 1319.4475 | J39: ='AEO T24 Refining 2022 Raw'!M33 -> 1333.1901 | ... AG39: ='AEO T24 Refining 2022 Raw'!AJ33 -> 0.001
A40: IRF000:da_OtherPetroleu | B40: Other Petroleum 3/ | C40: ='AEO T24 Refining 2022 Raw'!F34 -> 2.958 | D40: ='AEO T24 Refining 2022 Raw'!G34 -> 2.958 | E40: ='AEO T24 Refining 2022 Raw'!H34 -> 0 | F40: ='AEO T24 Refining 2022 Raw'!I34 -> 0 | G40: ='AEO T24 Refining 2022 Raw'!J34 -> 0.372267 | H40: ='AEO T24 Refining 2022 Raw'!K34 -> 0.71969 | I40: ='AEO T24 Refining 2022 Raw'!L34 -> 9.951056 | J40: ='AEO T24 Refining 2022 Raw'!M34 -> 1.636055 | ... AG40: ='AEO T24 Refining 2022 Raw'!AJ34 -> -0.14
A41: IRF000:da_PetroleumSubt | B41: Petroleum and Other Liquids Subtotal | C41: ='AEO T24 Refining 2022 Raw'!F35 -> 1743.094 | D41: ='AEO T24 Refining 2022 Raw'!G35 -> 1779.201 | E41: ='AEO T24 Refining 2022 Raw'!H35 -> 1835.4479 | F41: ='AEO T24 Refining 2022 Raw'!I35 -> 1825.7574 | G41: ='AEO T24 Refining 2022 Raw'!J35 -> 1835.6139 | H41: ='AEO T24 Refining 2022 Raw'!K35 -> 1833.9326 | I41: ='AEO T24 Refining 2022 Raw'!L35 -> 1828.818 | J41: ='AEO T24 Refining 2022 Raw'!M35 -> 1836.2687 | ... AG41: ='AEO T24 Refining 2022 Raw'!AJ35 -> 0.002
A42: IRF000:da_NaturalGas | B42: Natural Gas | C42: ='AEO T24 Refining 2022 Raw'!F36 -> 858.72315 | D42: ='AEO T24 Refining 2022 Raw'!G36 -> 857.25305 | E42: ='AEO T24 Refining 2022 Raw'!H36 -> 551.43799 | F42: ='AEO T24 Refining 2022 Raw'!I36 -> 529.18518 | G42: ='AEO T24 Refining 2022 Raw'!J36 -> 529.53796 | H42: ='AEO T24 Refining 2022 Raw'!K36 -> 548.72766 | I42: ='AEO T24 Refining 2022 Raw'!L36 -> 539.75134 | J42: ='AEO T24 Refining 2022 Raw'!M36 -> 546.42163 | ... AG42: ='AEO T24 Refining 2022 Raw'!AJ36 -> -0.011
A43: IRF000:da_SteamCoal | B43: Steam Coal | C43: ='AEO T24 Refining 2022 Raw'!F37 -> 0 | D43: ='AEO T24 Refining 2022 Raw'!G37 -> 0 | E43: ='AEO T24 Refining 2022 Raw'!H37 -> 0 | F43: ='AEO T24 Refining 2022 Raw'!I37 -> 0 | G43: ='AEO T24 Refining 2022 Raw'!J37 -> 0 | H43: ='AEO T24 Refining 2022 Raw'!K37 -> 0 | I43: ='AEO T24 Refining 2022 Raw'!L37 -> 0 | J43: ='AEO T24 Refining 2022 Raw'!M37 -> 0 | ... AG43: ='AEO T24 Refining 2022 Raw'!AJ37 -> - -
A44: IRF000:da_PurchasedElec | B44: Purchased Electricity | C44: ='AEO T24 Refining 2022 Raw'!F38 -> 150.22299 | D44: ='AEO T24 Refining 2022 Raw'!G38 -> 150.22299 | E44: ='AEO T24 Refining 2022 Raw'!H38 -> 146.39061 | F44: ='AEO T24 Refining 2022 Raw'!I38 -> 143.5092 | G44: ='AEO T24 Refining 2022 Raw'!J38 -> 143.77194 | H44: ='AEO T24 Refining 2022 Raw'!K38 -> 144.84698 | I44: ='AEO T24 Refining 2022 Raw'!L38 -> 141.87497 | J44: ='AEO T24 Refining 2022 Raw'!M38 -> 143.60429 | ... AG44: ='AEO T24 Refining 2022 Raw'!AJ38 -> 0.002
A45: IRF000:da_Total | B45: Total | C45: ='AEO T24 Refining 2022 Raw'!F39 -> 2752.04 | D45: ='AEO T24 Refining 2022 Raw'!G39 -> 2786.677 | E45: ='AEO T24 Refining 2022 Raw'!H39 -> 2533.2764 | F45: ='AEO T24 Refining 2022 Raw'!I39 -> 2498.4519 | G45: ='AEO T24 Refining 2022 Raw'!J39 -> 2508.9238 | H45: ='AEO T24 Refining 2022 Raw'!K39 -> 2527.5071 | I45: ='AEO T24 Refining 2022 Raw'!L39 -> 2510.4443 | J45: ='AEO T24 Refining 2022 Raw'!M39 -> 2526.2947 | ... AG45: ='AEO T24 Refining 2022 Raw'!AJ39 -> -0.002
B47: Carbon Dioxide Emissions 5/
A48: IRF000:da_tonscarbon_dd | B48: (million metric tons carbon dioxide) | C48: ='AEO T24 Refining 2022 Raw'!F41 -> 194.19421 | D48: ='AEO T24 Refining 2022 Raw'!G41 -> 196.98454 | E48: ='AEO T24 Refining 2022 Raw'!H41 -> 184.56274 | F48: ='AEO T24 Refining 2022 Raw'!I41 -> 180.5103 | G48: ='AEO T24 Refining 2022 Raw'!J41 -> 180.76196 | H48: ='AEO T24 Refining 2022 Raw'!K41 -> 181.43282 | I48: ='AEO T24 Refining 2022 Raw'!L41 -> 179.63312 | J48: ='AEO T24 Refining 2022 Raw'!M41 -> 180.95116 | ... AG48: ='AEO T24 Refining 2022 Raw'!AJ41 -> -0.002
B51: Energy Consumption per Unit of Refinery Input
B52: (thousand Btu per barrel)
A53: IRF000:db_ResidualOil | B53: Residual Fuel Oil | C53: ='AEO T24 Refining 2022 Raw'!F44 -> 0.037319 | D53: ='AEO T24 Refining 2022 Raw'!G44 -> 0.034619 | E53: ='AEO T24 Refining 2022 Raw'!H44 -> 0 | F53: ='AEO T24 Refining 2022 Raw'!I44 -> 0 | G53: ='AEO T24 Refining 2022 Raw'!J44 -> 0 | H53: ='AEO T24 Refining 2022 Raw'!K44 -> 0 | I53: ='AEO T24 Refining 2022 Raw'!L44 -> 0 | J53: ='AEO T24 Refining 2022 Raw'!M44 -> 0 | ... AG53: ='AEO T24 Refining 2022 Raw'!AJ44 -> - -
A54: IRF000:db_DistillateOil | B54: Distillate Fuel Oil | C54: ='AEO T24 Refining 2022 Raw'!F45 -> 0.283381 | D54: ='AEO T24 Refining 2022 Raw'!G45 -> 0.262881 | E54: ='AEO T24 Refining 2022 Raw'!H45 -> 0 | F54: ='AEO T24 Refining 2022 Raw'!I45 -> 0 | G54: ='AEO T24 Refining 2022 Raw'!J45 -> 0 | H54: ='AEO T24 Refining 2022 Raw'!K45 -> 0 | I54: ='AEO T24 Refining 2022 Raw'!L45 -> 0 | J54: ='AEO T24 Refining 2022 Raw'!M45 -> 0 | ... AG54: ='AEO T24 Refining 2022 Raw'!AJ45 -> - -
A55: IRF000:db_LiquefiedPetr | B55: Liquefied Petroleum Gas Heat and Power 2/ | C55: ='AEO T24 Refining 2022 Raw'!F46 -> 1.188106 | D55: ='AEO T24 Refining 2022 Raw'!G46 -> 1.102158 | E55: ='AEO T24 Refining 2022 Raw'!H46 -> 0 | F55: ='AEO T24 Refining 2022 Raw'!I46 -> 0 | G55: ='AEO T24 Refining 2022 Raw'!J46 -> 0 | H55: ='AEO T24 Refining 2022 Raw'!K46 -> 0 | I55: ='AEO T24 Refining 2022 Raw'!L46 -> 0 | J55: ='AEO T24 Refining 2022 Raw'!M46 -> 0 | ... AG55: ='AEO T24 Refining 2022 Raw'!AJ46 -> - -
A56: IRF000:db_PetroleumCoke | B56: Petroleum Coke | C56: ='AEO T24 Refining 2022 Raw'!F47 -> 79.280151 | D56: ='AEO T24 Refining 2022 Raw'!G47 -> 79.544678 | E56: ='AEO T24 Refining 2022 Raw'!H47 -> 81.780861 | F56: ='AEO T24 Refining 2022 Raw'!I47 -> 80.661522 | G56: ='AEO T24 Refining 2022 Raw'!J47 -> 80.56424 | H56: ='AEO T24 Refining 2022 Raw'!K47 -> 79.677536 | I56: ='AEO T24 Refining 2022 Raw'!L47 -> 79.57605 | J56: ='AEO T24 Refining 2022 Raw'!M47 -> 80.22213 | ... AG56: ='AEO T24 Refining 2022 Raw'!AJ47 -> 0.003
A57: IRF000:db_StillGas | B57: Still Gas | C57: ='AEO T24 Refining 2022 Raw'!F48 -> 222.67007 | D57: ='AEO T24 Refining 2022 Raw'!G48 -> 206.40355 | E57: ='AEO T24 Refining 2022 Raw'!H48 -> 211.29466 | F57: ='AEO T24 Refining 2022 Raw'!I48 -> 209.41705 | G57: ='AEO T24 Refining 2022 Raw'!J48 -> 210.25058 | H57: ='AEO T24 Refining 2022 Raw'!K48 -> 211.50514 | I57: ='AEO T24 Refining 2022 Raw'!L48 -> 210.23694 | J57: ='AEO T24 Refining 2022 Raw'!M48 -> 213.28737 | ... AG57: ='AEO T24 Refining 2022 Raw'!AJ48 -> 0
A58: IRF000:db_OtherPetroleu | B58: Other Petroleum 3/ | C58: ='AEO T24 Refining 2022 Raw'!F49 -> 0.51584 | D58: ='AEO T24 Refining 2022 Raw'!G49 -> 0.478524 | E58: ='AEO T24 Refining 2022 Raw'!H49 -> 0 | F58: ='AEO T24 Refining 2022 Raw'!I49 -> 0 | G58: ='AEO T24 Refining 2022 Raw'!J49 -> 0.05899 | H58: ='AEO T24 Refining 2022 Raw'!K49 -> 0.114314 | I58: ='AEO T24 Refining 2022 Raw'!L49 -> 1.585572 | J58: ='AEO T24 Refining 2022 Raw'!M49 -> 0.26174 | ... AG58: ='AEO T24 Refining 2022 Raw'!AJ49 -> -0.141
A59: IRF000:db_PetroleumSubt | B59: Petroleum and Other Liquids Subtotal | C59: ='AEO T24 Refining 2022 Raw'!F50 -> 303.97488 | D59: ='AEO T24 Refining 2022 Raw'!G50 -> 287.82642 | E59: ='AEO T24 Refining 2022 Raw'!H50 -> 293.07553 | F59: ='AEO T24 Refining 2022 Raw'!I50 -> 290.07858 | G59: ='AEO T24 Refining 2022 Raw'!J50 -> 290.87381 | H59: ='AEO T24 Refining 2022 Raw'!K50 -> 291.297 | I59: ='AEO T24 Refining 2022 Raw'!L50 -> 291.39856 | J59: ='AEO T24 Refining 2022 Raw'!M50 -> 293.77124 | ... AG59: ='AEO T24 Refining 2022 Raw'!AJ50 -> 0.001
A60: IRF000:db_NaturalGas | B60: Natural Gas | C60: ='AEO T24 Refining 2022 Raw'!F51 -> 149.7511 | D60: ='AEO T24 Refining 2022 Raw'!G51 -> 138.68027 | E60: ='AEO T24 Refining 2022 Raw'!H51 -> 88.05098 | F60: ='AEO T24 Refining 2022 Raw'!I51 -> 84.077591 | G60: ='AEO T24 Refining 2022 Raw'!J51 -> 83.911285 | H60: ='AEO T24 Refining 2022 Raw'!K51 -> 87.158447 | I60: ='AEO T24 Refining 2022 Raw'!L51 -> 86.002411 | J60: ='AEO T24 Refining 2022 Raw'!M51 -> 87.418015 | ... AG60: ='AEO T24 Refining 2022 Raw'!AJ51 -> -0.012
A61: IRF000:db_SteamCoal | B61: Steam Coal | C61: ='AEO T24 Refining 2022 Raw'!F52 -> 0 | D61: ='AEO T24 Refining 2022 Raw'!G52 -> 0 | E61: ='AEO T24 Refining 2022 Raw'!H52 -> 0 | F61: ='AEO T24 Refining 2022 Raw'!I52 -> 0 | G61: ='AEO T24 Refining 2022 Raw'!J52 -> 0 | H61: ='AEO T24 Refining 2022 Raw'!K52 -> 0 | I61: ='AEO T24 Refining 2022 Raw'!L52 -> 0 | J61: ='AEO T24 Refining 2022 Raw'!M52 -> 0 | ... AG61: ='AEO T24 Refining 2022 Raw'!AJ52 -> - -
A62: IRF000:db_PurchasedElec | B62: Purchased Electricity | C62: ='AEO T24 Refining 2022 Raw'!F53 -> 26.197104 | D62: ='AEO T24 Refining 2022 Raw'!G53 -> 24.302 | E62: ='AEO T24 Refining 2022 Raw'!H53 -> 23.37495 | F62: ='AEO T24 Refining 2022 Raw'!I53 -> 22.800919 | G62: ='AEO T24 Refining 2022 Raw'!J53 -> 22.782293 | H62: ='AEO T24 Refining 2022 Raw'!K53 -> 23.007113 | I62: ='AEO T24 Refining 2022 Raw'!L53 -> 22.605946 | J62: ='AEO T24 Refining 2022 Raw'!M53 -> 22.974205 | ... AG62: ='AEO T24 Refining 2022 Raw'!AJ53 -> 0
A63: IRF000:db_Total | B63: Total | C63: ='AEO T24 Refining 2022 Raw'!F54 -> 479.9231 | D63: ='AEO T24 Refining 2022 Raw'!G54 -> 450.80869 | E63: ='AEO T24 Refining 2022 Raw'!H54 -> 404.50146 | F63: ='AEO T24 Refining 2022 Raw'!I54 -> 396.95709 | G63: ='AEO T24 Refining 2022 Raw'!J54 -> 397.56738 | H63: ='AEO T24 Refining 2022 Raw'!K54 -> 401.46256 | I63: ='AEO T24 Refining 2022 Raw'!L54 -> 400.00693 | J63: ='AEO T24 Refining 2022 Raw'!M54 -> 404.16348 | ... AG63: ='AEO T24 Refining 2022 Raw'!AJ54 -> -0.003
B65: Combined Heat and Power
B66: Generating Capacity (gigawatts)
A67: IRF000:ga_Petroleum | B67: Petroleum | C67: ='AEO T24 Refining 2022 Raw'!F57 -> 0.1353 | D67: ='AEO T24 Refining 2022 Raw'!G57 -> 0.1353 | E67: ='AEO T24 Refining 2022 Raw'!H57 -> 0.1353 | F67: ='AEO T24 Refining 2022 Raw'!I57 -> 0.1353 | G67: ='AEO T24 Refining 2022 Raw'!J57 -> 0.1353 | H67: ='AEO T24 Refining 2022 Raw'!K57 -> 0.1353 | I67: ='AEO T24 Refining 2022 Raw'!L57 -> 0.1353 | J67: ='AEO T24 Refining 2022 Raw'!M57 -> 0.1353 | ... AG67: ='AEO T24 Refining 2022 Raw'!AJ57 -> 0
A68: IRF000:ga_NaturalGas | B68: Natural Gas | C68: ='AEO T24 Refining 2022 Raw'!F58 -> 3.3355 | D68: ='AEO T24 Refining 2022 Raw'!G58 -> 3.3355 | E68: ='AEO T24 Refining 2022 Raw'!H58 -> 3.3355 | F68: ='AEO T24 Refining 2022 Raw'!I58 -> 3.3355 | G68: ='AEO T24 Refining 2022 Raw'!J58 -> 3.3355 | H68: ='AEO T24 Refining 2022 Raw'!K58 -> 3.3355 | I68: ='AEO T24 Refining 2022 Raw'!L58 -> 3.3355 | J68: ='AEO T24 Refining 2022 Raw'!M58 -> 3.3355 | ... AG68: ='AEO T24 Refining 2022 Raw'!AJ58 -> 0
A69: IRF000:ga_Coal | B69: Coal | C69: ='AEO T24 Refining 2022 Raw'!F59 -> 0 | D69: ='AEO T24 Refining 2022 Raw'!G59 -> 0 | E69: ='AEO T24 Refining 2022 Raw'!H59 -> 0 | F69: ='AEO T24 Refining 2022 Raw'!I59 -> 0 | G69: ='AEO T24 Refining 2022 Raw'!J59 -> 0 | H69: ='AEO T24 Refining 2022 Raw'!K59 -> 0 | I69: ='AEO T24 Refining 2022 Raw'!L59 -> 0 | J69: ='AEO T24 Refining 2022 Raw'!M59 -> 0 | ... AG69: ='AEO T24 Refining 2022 Raw'!AJ59 -> - -
A70: IRF000:ga_Other | B70: Other 6/ | C70: ='AEO T24 Refining 2022 Raw'!F60 -> 1.0951 | D70: ='AEO T24 Refining 2022 Raw'!G60 -> 1.0951 | E70: ='AEO T24 Refining 2022 Raw'!H60 -> 1.0951 | F70: ='AEO T24 Refining 2022 Raw'!I60 -> 1.0951 | G70: ='AEO T24 Refining 2022 Raw'!J60 -> 1.0951 | H70: ='AEO T24 Refining 2022 Raw'!K60 -> 1.0951 | I70: ='AEO T24 Refining 2022 Raw'!L60 -> 1.0951 | J70: ='AEO T24 Refining 2022 Raw'!M60 -> 1.0951 | ... AG70: ='AEO T24 Refining 2022 Raw'!AJ60 -> 0
A71: IRF000:ga_Total | B71: Total | C71: ='AEO T24 Refining 2022 Raw'!F61 -> 4.5659 | D71: ='AEO T24 Refining 2022 Raw'!G61 -> 4.5659 | E71: ='AEO T24 Refining 2022 Raw'!H61 -> 4.5659 | F71: ='AEO T24 Refining 2022 Raw'!I61 -> 4.5659 | G71: ='AEO T24 Refining 2022 Raw'!J61 -> 4.5659 | H71: ='AEO T24 Refining 2022 Raw'!K61 -> 4.5659 | I71: ='AEO T24 Refining 2022 Raw'!L61 -> 4.5659 | J71: ='AEO T24 Refining 2022 Raw'!M61 -> 4.5659 | ... AG71: ='AEO T24 Refining 2022 Raw'!AJ61 -> 0
B72: Net Generation (billion kilowatthours)
A73: IRF000:ha_Petroleum | B73: Petroleum | C73: ='AEO T24 Refining 2022 Raw'!F63 -> 0.3593 | D73: ='AEO T24 Refining 2022 Raw'!G63 -> 0.39106 | E73: ='AEO T24 Refining 2022 Raw'!H63 -> 0 | F73: ='AEO T24 Refining 2022 Raw'!I63 -> 0 | G73: ='AEO T24 Refining 2022 Raw'!J63 -> 0 | H73: ='AEO T24 Refining 2022 Raw'!K63 -> 0 | I73: ='AEO T24 Refining 2022 Raw'!L63 -> 0 | J73: ='AEO T24 Refining 2022 Raw'!M63 -> 0 | ... AG73: ='AEO T24 Refining 2022 Raw'!AJ63 -> - -
A74: IRF000:ha_NaturalGas | B74: Natural Gas | C74: ='AEO T24 Refining 2022 Raw'!F64 -> 24.35149 | D74: ='AEO T24 Refining 2022 Raw'!G64 -> 25.159262 | E74: ='AEO T24 Refining 2022 Raw'!H64 -> 24.43865 | F74: ='AEO T24 Refining 2022 Raw'!I64 -> 24.121645 | G74: ='AEO T24 Refining 2022 Raw'!J64 -> 24.43865 | H74: ='AEO T24 Refining 2022 Raw'!K64 -> 24.43865 | I74: ='AEO T24 Refining 2022 Raw'!L64 -> 24.43865 | J74: ='AEO T24 Refining 2022 Raw'!M64 -> 24.43865 | ... AG74: ='AEO T24 Refining 2022 Raw'!AJ64 -> 0
A75: IRF000:ha_Coal | B75: Coal | C75: ='AEO T24 Refining 2022 Raw'!F65 -> 0 | D75: ='AEO T24 Refining 2022 Raw'!G65 -> 0 | E75: ='AEO T24 Refining 2022 Raw'!H65 -> 0 | F75: ='AEO T24 Refining 2022 Raw'!I65 -> 0 | G75: ='AEO T24 Refining 2022 Raw'!J65 -> 0 | H75: ='AEO T24 Refining 2022 Raw'!K65 -> 0 | I75: ='AEO T24 Refining 2022 Raw'!L65 -> 0 | J75: ='AEO T24 Refining 2022 Raw'!M65 -> 0 | ... AG75: ='AEO T24 Refining 2022 Raw'!AJ65 -> - -
A76: IRF000:ha_Other | B76: Other 6/ | C76: ='AEO T24 Refining 2022 Raw'!F66 -> 4.80197 | D76: ='AEO T24 Refining 2022 Raw'!G66 -> 4.99792 | E76: ='AEO T24 Refining 2022 Raw'!H66 -> 6.109663 | F76: ='AEO T24 Refining 2022 Raw'!I66 -> 6.030411 | G76: ='AEO T24 Refining 2022 Raw'!J66 -> 6.109663 | H76: ='AEO T24 Refining 2022 Raw'!K66 -> 6.109663 | I76: ='AEO T24 Refining 2022 Raw'!L66 -> 6.109663 | J76: ='AEO T24 Refining 2022 Raw'!M66 -> 6.109663 | ... AG76: ='AEO T24 Refining 2022 Raw'!AJ66 -> 0.008
A77: IRF000:ha_Total | B77: Total | C77: ='AEO T24 Refining 2022 Raw'!F67 -> 29.51276 | D77: ='AEO T24 Refining 2022 Raw'!G67 -> 30.548241 | E77: ='AEO T24 Refining 2022 Raw'!H67 -> 30.548313 | F77: ='AEO T24 Refining 2022 Raw'!I67 -> 30.152056 | G77: ='AEO T24 Refining 2022 Raw'!J67 -> 30.548313 | H77: ='AEO T24 Refining 2022 Raw'!K67 -> 30.548313 | I77: ='AEO T24 Refining 2022 Raw'!L67 -> 30.548313 | J77: ='AEO T24 Refining 2022 Raw'!M67 -> 30.548313 | ... AG77: ='AEO T24 Refining 2022 Raw'!AJ67 -> 0.001
B78: Disposition
A79: IRF000:ha_SalestotheGri | B79: Sales to the Grid | C79: ='AEO T24 Refining 2022 Raw'!F69 -> 9.383711 | D79: ='AEO T24 Refining 2022 Raw'!G69 -> 10.545921 | E79: ='AEO T24 Refining 2022 Raw'!H69 -> 0 | F79: ='AEO T24 Refining 2022 Raw'!I69 -> 0 | G79: ='AEO T24 Refining 2022 Raw'!J69 -> 0 | H79: ='AEO T24 Refining 2022 Raw'!K69 -> 0 | I79: ='AEO T24 Refining 2022 Raw'!L69 -> 0 | J79: ='AEO T24 Refining 2022 Raw'!M69 -> 0 | ... AG79: ='AEO T24 Refining 2022 Raw'!AJ69 -> - -
A80: IRF000:ha_Generationfor | B80: Generation for Own Use | C80: ='AEO T24 Refining 2022 Raw'!F70 -> 20.129051 | D80: ='AEO T24 Refining 2022 Raw'!G70 -> 20.002319 | E80: ='AEO T24 Refining 2022 Raw'!H70 -> 30.548311 | F80: ='AEO T24 Refining 2022 Raw'!I70 -> 30.152056 | G80: ='AEO T24 Refining 2022 Raw'!J70 -> 30.548311 | H80: ='AEO T24 Refining 2022 Raw'!K70 -> 30.548311 | I80: ='AEO T24 Refining 2022 Raw'!L70 -> 30.548311 | J80: ='AEO T24 Refining 2022 Raw'!M70 -> 30.548311 | ... AG80: ='AEO T24 Refining 2022 Raw'!AJ70 -> 0.014
B82: Energy Consumed at Ethanol Plants
B83: (trillion Btu)
A84: IRF000:ja_NaturalGas | B84: Natural Gas | C84: ='AEO T24 Refining 2022 Raw'!F73 -> 368 | D84: ='AEO T24 Refining 2022 Raw'!G73 -> 368 | E84: ='AEO T24 Refining 2022 Raw'!H73 -> 430.81705 | F84: ='AEO T24 Refining 2022 Raw'!I73 -> 430.56384 | G84: ='AEO T24 Refining 2022 Raw'!J73 -> 434.306 | H84: ='AEO T24 Refining 2022 Raw'!K73 -> 434.91617 | I84: ='AEO T24 Refining 2022 Raw'!L73 -> 434.97967 | J84: ='AEO T24 Refining 2022 Raw'!M73 -> 435.16934 | ... AG84: ='AEO T24 Refining 2022 Raw'!AJ73 -> 0.011
A85: IRF000:ja_Coal | B85: Coal | C85: ='AEO T24 Refining 2022 Raw'!F74 -> 24 | D85: ='AEO T24 Refining 2022 Raw'!G74 -> 24 | E85: ='AEO T24 Refining 2022 Raw'!H74 -> 0 | F85: ='AEO T24 Refining 2022 Raw'!I74 -> 0 | G85: ='AEO T24 Refining 2022 Raw'!J74 -> 0 | H85: ='AEO T24 Refining 2022 Raw'!K74 -> 0 | I85: ='AEO T24 Refining 2022 Raw'!L74 -> 0 | J85: ='AEO T24 Refining 2022 Raw'!M74 -> 0 | ... AG85: ='AEO T24 Refining 2022 Raw'!AJ74 -> 0.008
A86: IRF000:ja_Electricity | B86: Electricity | C86: ='AEO T24 Refining 2022 Raw'!F75 -> 37 | D86: ='AEO T24 Refining 2022 Raw'!G75 -> 37 | E86: ='AEO T24 Refining 2022 Raw'!H75 -> 41.375824 | F86: ='AEO T24 Refining 2022 Raw'!I75 -> 41.351852 | G86: ='AEO T24 Refining 2022 Raw'!J75 -> 41.70615 | H86: ='AEO T24 Refining 2022 Raw'!K75 -> 41.763924 | I86: ='AEO T24 Refining 2022 Raw'!L75 -> 41.769936 | J86: ='AEO T24 Refining 2022 Raw'!M75 -> 41.787891 | ... AG86: ='AEO T24 Refining 2022 Raw'!AJ75 -> 0.01
A87: IRF000:ja_Total | B87: Total | C87: ='AEO T24 Refining 2022 Raw'!F76 -> 429 | D87: ='AEO T24 Refining 2022 Raw'!G76 -> 429 | E87: ='AEO T24 Refining 2022 Raw'!H76 -> 472.19287 | F87: ='AEO T24 Refining 2022 Raw'!I76 -> 471.91571 | G87: ='AEO T24 Refining 2022 Raw'!J76 -> 476.01215 | H87: ='AEO T24 Refining 2022 Raw'!K76 -> 476.68008 | I87: ='AEO T24 Refining 2022 Raw'!L76 -> 476.7496 | J87: ='AEO T24 Refining 2022 Raw'!M76 -> 476.95725 | ... AG87: ='AEO T24 Refining 2022 Raw'!AJ76 -> 0.011
B89: 1/ Includes energy for combined heat and power plants that have a non-regulatory status, small on-site generating systems,
B90: consumption at ethanol plants, and (if adapted) consumption at coal-to-liquids (CTL) and gas-to-liquids (GTL) plants.
B91: 2/ Includes ethane, natural gasoline, and refinery olefins.
B92: 3/ Includes lubricants and miscellaneous petroleum products.
B93: 4/ Includes consumption at ethanol and coal-to-liquids (CTL) plants. Where CTL technology is adopted in these projections,
B94: the plants are assumed to produce oil products and to generate electricity.
B95: A portion of the coal use is attributed to feedstock use to produce the liquids. The feedstock portion
B96: is assumed to be equal to the Btu content of the liquids produced. The rest of the coal used in CTL plants is accounted for in
B97: industrial steam coal consumption, a portion of which is reflected in energy used for end-use sector combined heat and power.
B98: 5/ Includes emissions attributable to the fuels consumed to generate the purchased electricity, but not non-combustion
B99: emissions from industrial processes.
B100: 6/ Includes municipal waste, wood, and other biomass.
... B106: AEO2022 National Energy Modeling System run ref2022.d011222a. Projections: EIA, AEO2022 National Energy Modeling System run ref2022.d011222a.

Sheet AEO T24 Refining 2021
B1: ref2021.d113020a | C1: 2020 | D1: 2021 | E1: 2022 | F1: 2023 | G1: 2024 | H1: 2025 | I1: 2026 | J1: 2027 | K1: 2028 | L1: 2029 | M1: 2030 | N1: 2031 | O1: 2032 | P1: 2033 | Q1: 2034 | R1: 2035 | S1: 2036 | T1: 2037 | U1: 2038 | V1: 2039 | W1: 2040 | X1: 2041 | Y1: 2042 | Z1: 2043 | AA1: 2044 | AB1: 2045 | AC1: 2046 | AD1: 2047 | AE1: 2048 | AF1: 2049 | AG1: 2050 | AJ1: Difference between 2020 and 2021
C3: Report | D3: Annual Energy Outlook 2021
C4: Scenario | D4: ref2021 | G4: Reference case
C5: Datekey | D5: d113020a
C6: Release Date | E6: January 2021
A10: IRF000 | B10: 24. Refining Industry Energy Consumption | AH10: Compound
AH11: Growth
AH12: 2020-2050
B13: Shipments, Energy Consumption, and Emissions | C13: 2020 | D13: 2021 | E13: 2022 | F13: 2023 | G13: 2024 | H13: 2025 | I13: 2026 | J13: 2027 | K13: 2028 | L13: 2029 | M13: 2030 | N13: 2031 | O13: 2032 | P13: 2033 | Q13: 2034 | R13: 2035 | S13: 2036 | T13: 2037 | U13: 2038 | V13: 2039 | W13: 2040 | X13: 2041 | Y13: 2042 | Z13: 2043 | AA13: 2044 | AB13: 2045 | AC13: 2046 | AD13: 2047 | AE13: 2048 | AF13: 2049 | AG13: 2050 | AH13: (percent)
A15: IRF000:ba_ValueofShipme | B15: Value of Shipments (billion 2012 dollars) | C15: 735.55859 | D15: 814.97101 | E15: 818.17279 | F15: 825.38788 | G15: 830.2301 | H15: 834.67071 | I15: 831.61218 | J15: 831.19299 | K15: 832.04028 | L15: 832.85022 | M15: 832.18012 | N15: 833.53058 | O15: 834.6449 | P15: 836.50079 | Q15: 839.2157 | R15: 841.39368 | S15: 843.37311 | T15: 844.65961 | U15: 846.3352 | V15: 847.78052 | W15: 847.98718 | X15: 849.97467 | Y15: 853.47668 | Z15: 857.58331 | AA15: 861.1861 | AB15: 865.2486 | AC15: 868.92273 | AD15: 872.0694 | AE15: 875.10651 | AF15: 880.57617 | AG15: 887.51099 | AH15: 0.006279 | AJ15: =C15/'AEO T24 Refining 2022'!C9 -> 0.98485428
B16: Inputs to Distillation Units | AJ16: =C16/D16 -> #DIV/0!
A17: IRF000:ba_CrudeOilInput | B17: (million barrels per day) | C17: 14.905047 | D17: 16.660154 | E17: 17.296463 | F17: 17.85956 | G17: 17.957142 | H17: 18.147688 | I17: 18.112722 | J17: 18.165474 | K17: 18.161804 | L17: 18.150787 | M17: 18.16057 | N17: 18.13802 | O17: 18.132683 | P17: 18.081226 | Q17: 18.068563 | R17: 18.045738 | S17: 18.07362 | T17: 18.052732 | U17: 18.045023 | V17: 17.977049 | W17: 17.997942 | X17: 17.970968 | Y17: 18.005737 | Z17: 17.979855 | AA17: 17.982094 | AB17: 17.967951 | AC17: 17.931923 | AD17: 17.964806 | AE17: 17.980871 | AF17: 17.939804 | AG17: 17.914637 | AH17: 0.006149 | AJ17: =C17/D17 -> 0.89465241
AJ18: =C18/D18 -> #DIV/0!
B19: Total Energy Consumption (trillion Btu) 1/ | AJ19: =C19/D19 -> #DIV/0!
A20: IRF000:ca_ResidualOil | B20: Residual Fuel Oil | C20: 0.15 | D20: 0.161 | E20: 0 | F20: 0 | G20: 0 | H20: 0 | I20: 0 | J20: 0 | K20: 0 | L20: 0 | M20: 0 | N20: 0 | O20: 0 | P20: 0 | Q20: 0 | R20: 0 | S20: 0 | T20: 0 | U20: 0 | V20: 0 | W20: 0 | X20: 0 | Y20: 0 | Z20: 0 | AA20: 0 | AB20: 0 | AC20: 0 | AD20: 0 | AE20: 0 | AF20: 0 | AG20: 0 | AH20: -- | AJ20: =C20/D20 -> 0.93167702
A21: IRF000:ca_DistillateOil | B21: Distillate Fuel Oil | C21: 1.986 | D21: 2.147 | E21: 0 | F21: 0 | G21: 0 | H21: 0 | I21: 0 | J21: 0 | K21: 0 | L21: 0 | M21: 0 | N21: 0 | O21: 0 | P21: 0 | Q21: 0 | R21: 0 | S21: 0 | T21: 0 | U21: 0 | V21: 0 | W21: 0 | X21: 0 | Y21: 0 | Z21: 0 | AA21: 0 | AB21: 0 | AC21: 0 | AD21: 0 | AE21: 0 | AF21: 0 | AG21: 0 | AH21: -- | AJ21: =C21/D21 -> 0.92501164
A22: IRF000:ca_LiquefiedPetr | B22: Liquefied Petroleum Gas Heat and Power 2/ | C22: 7.159 | D22: 7.734 | E22: 0 | F22: 0 | G22: 0 | H22: 0 | I22: 0 | J22: 0 | K22: 0 | L22: 0 | M22: 0 | N22: 0 | O22: 0 | P22: 0 | Q22: 0 | R22: 0 | S22: 0 | T22: 0 | U22: 0 | V22: 0 | W22: 0 | X22: 0 | Y22: 0 | Z22: 0 | AA22: 0 | AB22: 0 | AC22: 0 | AD22: 0 | AE22: 0 | AF22: 0 | AG22: 0 | AH22: -- | AJ22: =C22/D22 -> 0.92565296
A23: IRF000:ca_PetroleumCoke | B23: Petroleum Coke | C23: 465.14301 | D23: 502.38397 | E23: 501.43607 | F23: 498.72119 | G23: 495.09537 | H23: 491.42127 | I23: 498.80359 | J23: 492.76923 | K23: 495.78485 | L23: 503.4339 | M23: 507.48554 | N23: 505.50427 | O23: 507.73166 | P23: 508.73926 | Q23: 512.8537 | R23: 511.80841 | S23: 511.08411 | T23: 510.2663 | U23: 510.20432 | V23: 510.0202 | W23: 510.15924 | X23: 510.79251 | Y23: 511.96027 | Z23: 513.88873 | AA23: 514.85346 | AB23: 512.99982 | AC23: 515.21576 | AD23: 516.62042 | AE23: 517.92828 | AF23: 516.72772 | AG23: 519.26306 | AH23: 0.003676 | AJ23: =C23/D23 -> 0.92587151
A24: IRF000:ca_StillGas | B24: Still Gas | C24: 1332.4979 | D24: 1439.1901 | E24: 1425.1088 | F24: 1440.1422 | G24: 1427.9835 | H24: 1452.4305 | I24: 1462.7539 | J24: 1469.9377 | K24: 1478.9086 | L24: 1489.9265 | M24: 1484.3157 | N24: 1489.8763 | O24: 1496.5669 | P24: 1493.2141 | Q24: 1504.4948 | R24: 1506.9012 | S24: 1525.1659 | T24: 1542.5576 | U24: 1541.0941 | V24: 1543.7809 | W24: 1545.3164 | X24: 1544.4895 | Y24: 1538.2808 | Z24: 1518.004 | AA24: 1512.1489 | AB24: 1520.3474 | AC24: 1505.2648 | AD24: 1509.17 | AE24: 1519.401 | AF24: 1515.8882 | AG24: 1526.6178 | AH24: 0.004544 | AJ24: =C24/D24 -> 0.92586654
A25: IRF000:ca_OtherPetroleu | B25: Other Petroleum 3/ | C25: 4.728 | D25: 5.105 | E25: 5.237201 | F25: 3.913398 | G25: 9.131416 | H25: 11.423477 | I25: 5.746054 | J25: 8.374808 | K25: 9.649928 | L25: 0.871765 | M25: 0.069692 | N25: 0.043026 | O25: 0.027881 | P25: 0.046244 | Q25: 0.04736 | R25: 0.015157 | S25: 0.106586 | T25: 0.078291 | U25: 0.033505 | V25: 0.034214 | W25: 0.09433 | X25: 0.120671 | Y25: 0.087701 | Z25: 0.085654 | AA25: 0.021703 | AB25: 0.030275 | AC25: 0.004302 | AD25: 0 | AE25: 0 | AF25: 0 | AG25: 0.006381 | AH25: -0.197692 | AJ25: =C25/D25 -> 0.92615083
A26: IRF000:ca_PetroleumSubt | B26: Petroleum and Other Liquids Subtotal | C26: 1811.6639 | D26: 1956.7209 | E26: 1931.782 | F26: 1942.7769 | G26: 1932.2103 | H26: 1955.2753 | I26: 1967.3036 | J26: 1971.0818 | K26: 1984.3433 | L26: 1994.2322 | M26: 1991.871 | N26: 1995.4236 | O26: 2004.3264 | P26: 2001.9996 | Q26: 2017.3958 | R26: 2018.7249 | S26: 2036.3566 | T26: 2052.9023 | U26: 2051.3318 | V26: 2053.8352 | W26: 2055.5698 | X26: 2055.4026 | Y26: 2050.3286 | Z26: 2031.9785 | AA26: 2027.0242 | AB26: 2033.3774 | AC26: 2020.4847 | AD26: 2025.7905 | AE26: 2037.3293 | AF26: 2032.616 | AG26: 2045.8872 | AH26: 0.004061 | AJ26: =C26/D26 -> 0.9258673
A27: IRF000:ca_NaturalGas | B27: Natural Gas | C27: 1468.803 | D27: 1559.728 | E27: 1349.9082 | F27: 1388.2887 | G27: 1387.8911 | H27: 1384.7472 | I27: 1403.2537 | J27: 1390.196 | K27: 1399.2916 | L27: 1415.8683 | M27: 1381.1156 | N27: 1390.1771 | O27: 1387.6399 | P27: 1395.5632 | Q27: 1416.3917 | R27: 1426.6912 | S27: 1452.746 | T27: 1472.8116 | U27: 1486.9662 | V27: 1530.7054 | W27: 1526.9989 | X27: 1532.9934 | Y27: 1551.311 | Z27: 1572.7869 | AA27: 1582.4199 | AB27: 1573.1882 | AC27: 1606.696 | AD27: 1630.9414 | AE27: 1646.9562 | AF27: 1661.1824 | AG27: 1683.6995 | AH27: 0.004562 | AJ27: =C27/D27 -> 0.94170455
A28: IRF000:NatGas_owHeatPow | B28: of which: Heat and Power | C28: 1253.803 | D28: 1324.728 | E28: 1149.9519 | F28: 1190.4327 | G28: 1190.516 | H28: 1191.7635 | I28: 1204.418 | J28: 1197.1542 | K28: 1202.827 | L28: 1216.7677 | M28: 1199.9783 | N28: 1207.4768 | O28: 1205.3958 | P28: 1211.483 | Q28: 1221.2948 | R28: 1228.0549 | S28: 1243.4431 | T28: 1252.9951 | U28: 1264.3149 | V28: 1291.4873 | W28: 1293.073 | X28: 1298.7517 | Y28: 1314.8842 | Z28: 1337.5476 | AA28: 1345.9098 | AB28: 1341.2783 | AC28: 1367.4011 | AD28: 1387.8154 | AE28: 1398.2571 | AF28: 1409.0624 | AG28: 1422.1135 | AH28: 0.004208 | AJ28: =C28/D28 -> 0.94646067
A29: IRF000:NatGas_owFeed | B29: of which: Feedstocks | C29: 215 | D29: 235 | E29: 199.95633 | F29: 197.85593 | G29: 197.37512 | H29: 192.98363 | I29: 198.83572 | J29: 193.04184 | K29: 196.46458 | L29: 199.10056 | M29: 181.13733 | N29: 182.70027 | O29: 182.24414 | P29: 184.08019 | Q29: 195.09688 | R29: 198.63623 | S29: 209.30287 | T29: 219.81656 | U29: 222.65118 | V29: 239.21808 | W29: 233.9259 | X29: 234.24175 | Y29: 236.42693 | Z29: 235.23923 | AA29: 236.51015 | AB29: 231.90997 | AC29: 239.29494 | AD29: 243.12602 | AE29: 248.69913 | AF29: 252.11998 | AG29: 261.586 | AH29: 0.006559 | AJ29: =C29/D29 -> 0.91489362
A30: IRF000:NatGas_owGTLHeat | B30: of which: Gas-to-Liquids Heat | C30: 0 | D30: 0 | E30: 0 | F30: 0 | G30: 0 | H30: 0 | I30: 0 | J30: 0 | K30: 0 | L30: 0 | M30: 0 | N30: 0 | O30: 0 | P30: 0 | Q30: 0 | R30: 0 | S30: 0 | T30: 0 | U30: 0 | V30: 0 | W30: 0 | X30: 0 | Y30: 0 | Z30: 0 | AA30: 0 | AB30: 0 | AC30: 0 | AD30: 0 | AE30: 0 | AF30: 0 | AG30: 0 | AH30: -- | AJ30: =C30/D30 -> #DIV/0!
A31: IRF000:ca_SteamCoal | B31: Steam Coal 4/ | C31: 24 | D31: 24 | E31: 0 | F31: 0 | G31: 0 | H31: 0 | I31: 0 | J31: 0 | K31: 0 | L31: 0 | M31: 0 | N31: 0 | O31: 0 | P31: 0 | Q31: 0 | R31: 0 | S31: 0 | T31: 0 | U31: 0.122591 | V31: 0.149576 | W31: 0.178443 | X31: 0.153959 | Y31: 5.231768 | Z31: 11.411824 | AA31: 18.228508 | AB31: 28.409792 | AC31: 30.051184 | AD31: 30.071499 | AE31: 30.07649 | AF31: 30.29249 | AG31: 30.24353 | AH31: 0.007737 | AJ31: =C31/D31 -> 1
A32: IRF000:ca_BiofuelsHeat | B32: Biofuels Heat and Coproducts | C32: 904.81 | D32: 881.07098 | E32: 870.69183 | F32: 876.05048 | G32: 879.00037 | H32: 885.42383 | I32: 888.24915 | J32: 890.47656 | K32: 892.77313 | L32: 895.17163 | M32: 899.6134 | N32: 909.2641 | O32: 912.55432 | P32: 917.70508 | Q32: 923.90314 | R32: 929.98041 | S32: 934.80102 | T32: 940.00677 | U32: 945.40228 | V32: 951.61133 | W32: 958.42664 | X32: 965.08875 | Y32: 973.15063 | Z32: 982.17548 | AA32: 991.48071 | AB32: 1005.4067 | AC32: 1010.2288 | AD32: 1027.6367 | AE32: 1037.3982 | AF32: 1047.9141 | AG32: 1058.575 | AH32: 0.005245 | AJ32: =C32/D32 -> 1.0269434
A33: IRF000:ca_PurchasedElec | B33: Purchased Electricity | C33: 183.73801 | D33: 195.48799 | E33: 185.37479 | F33: 190.03418 | G33: 187.78192 | H33: 190.02612 | I33: 192.10574 | J33: 190.69887 | K33: 192.87547 | L33: 195.44615 | M33: 197.79579 | N33: 198.35004 | O33: 199.33328 | P33: 199.65649 | Q33: 202.76285 | R33: 203.10559 | S33: 206.0314 | T33: 206.92932 | U33: 207.77951 | V33: 210.90242 | W33: 211.62976 | X33: 212.48975 | Y33: 214.19211 | Z33: 215.03107 | AA33: 215.73427 | AB33: 216.20517 | AC33: 218.04677 | AD33: 220.64041 | AE33: 222.83873 | AF33: 223.63184 | AG33: 226.52113 | AH33: 0.007002 | AJ33: =C33/D33 -> 0.93989409
A34: IRF000:ca_Total | B34: Total | C34: 4393.0146 | D34: 4617.0078 | E34: 4337.7568 | F34: 4397.1499 | G34: 4386.8838 | H34: 4415.4727 | I34: 4450.9121 | J34: 4442.4531 | K34: 4469.2832 | L34: 4500.7183 | M34: 4470.396 | N34: 4493.2148 | O34: 4503.854 | P34: 4514.9248 | Q34: 4560.4536 | R34: 4578.502 | S34: 4629.9351 | T34: 4672.6499 | U34: 4691.6021 | V34: 4747.2041 | W34: 4752.8037 | X34: 4766.1284 | Y34: 4794.2139 | Z34: 4813.3838 | AA34: 4834.8877 | AB34: 4856.5874 | AC34: 4885.5078 | AD34: 4935.0806 | AE34: 4974.5986 | AF34: 4995.6367 | AG34: 5044.9263 | AH34: 0.004623 | AJ34: =C34/D34 -> 0.95148521
AJ35: =C35/D35 -> #DIV/0!
B36: Carbon Dioxide Emissions 4/ | AJ36: =C36/D36 -> #DIV/0!
A37: IRF000:ea_tonscarbon_dd | B37: (million metric tons carbon dioxide) | C37: 234.85892 | D37: 252.34105 | E37: 236.63531 | F37: 237.61577 | G37: 235.01251 | H37: 235.02162 | I37: 237.54558 | J37: 236.26146 | K37: 237.7511 | L37: 239.6239 | M37: 237.67473 | N37: 238.15703 | O37: 238.50745 | P37: 238.75323 | Q37: 241.0802 | R37: 241.31613 | S37: 243.90274 | T37: 245.92856 | U37: 246.37122 | V37: 249.04507 | W37: 248.96466 | X37: 249.20947 | Y37: 250.48392 | Z37: 251.03728 | AA37: 251.90053 | AB37: 252.52086 | AC37: 253.65153 | AD37: 255.38687 | AE37: 257.14172 | AF37: 257.61212 | AG37: 259.87759 | AH37: 0.00338 | AJ37: =C37/D37 -> 0.93072022
AJ38: =C38/D38 -> #DIV/0!
B39: Energy Related to Refining Activity Only | AJ39: =C39/D39 -> #DIV/0!
B40: Energy Consumption | AJ40: =C40/D40 -> #DIV/0!
A41: IRF000:da_ResidualOil | B41: Residual Fuel Oil | C41: 0.15 | D41: 0.161 | E41: 0 | F41: 0 | G41: 0 | H41: 0 | I41: 0 | J41: 0 | K41: 0 | L41: 0 | M41: 0 | N41: 0 | O41: 0 | P41: 0 | Q41: 0 | R41: 0 | S41: 0 | T41: 0 | U41: 0 | V41: 0 | W41: 0 | X41: 0 | Y41: 0 | Z41: 0 | AA41: 0 | AB41: 0 | AC41: 0 | AD41: 0 | AE41: 0 | AF41: 0 | AG41: 0 | AH41: -- | AJ41: =C41/D41 -> 0.93167702
A42: IRF000:da_DistillateOil | B42: Distillate Fuel Oil | C42: 1.986 | D42: 2.147 | E42: 0 | F42: 0 | G42: 0 | H42: 0 | I42: 0 | J42: 0 | K42: 0 | L42: 0 | M42: 0 | N42: 0 | O42: 0 | P42: 0 | Q42: 0 | R42: 0 | S42: 0 | T42: 0 | U42: 0 | V42: 0 | W42: 0 | X42: 0 | Y42: 0 | Z42: 0 | AA42: 0 | AB42: 0 | AC42: 0 | AD42: 0 | AE42: 0 | AF42: 0 | AG42: 0 | AH42: -- | AJ42: =C42/D42 -> 0.92501164
A43: IRF000:da_LiquefiedPetr | B43: Liquefied Petroleum Gas Heat and Power 2/ | C43: 7.159 | D43: 7.734 | E43: 0 | F43: 0 | G43: 0 | H43: 0 | I43: 0 | J43: 0 | K43: 0 | L43: 0 | M43: 0 | N43: 0 | O43: 0 | P43: 0 | Q43: 0 | R43: 0 | S43: 0 | T43: 0 | U43: 0 | V43: 0 | W43: 0 | X43: 0 | Y43: 0 | Z43: 0 | AA43: 0 | AB43: 0 | AC43: 0 | AD43: 0 | AE43: 0 | AF43: 0 | AG43: 0 | AH43: -- | AJ43: =C43/D43 -> 0.92565296
A44: IRF000:da_PetroleumCoke | B44: Petroleum Coke | C44: 462.21301 | D44: 499.45398 | E44: 501.43607 | F44: 498.72119 | G44: 495.09537 | H44: 491.42127 | I44: 498.80359 | J44: 492.76923 | K44: 495.78485 | L44: 503.4339 | M44: 507.48554 | N44: 505.50427 | O44: 507.73166 | P44: 508.73926 | Q44: 512.8537 | R44: 511.80841 | S44: 511.08411 | T44: 510.2663 | U44: 510.20432 | V44: 510.0202 | W44: 510.15924 | X44: 510.79251 | Y44: 511.96027 | Z44: 513.88873 | AA44: 514.85346 | AB44: 512.99982 | AC44: 515.21576 | AD44: 516.62042 | AE44: 517.92828 | AF44: 516.72772 | AG44: 519.26306 | AH44: 0.003887 | AJ44: =C44/D44 -> 0.92543664
A45: IRF000:da_StillGas | B45: Still Gas | C45: 1298.8279 | D45: 1405.52 | E45: 1371.9137 | F45: 1386.7589 | G45: 1374.6002 | H45: 1399.0472 | I45: 1409.3706 | J45: 1416.5544 | K45: 1425.5253 | L45: 1436.5432 | M45: 1432.684 | N45: 1438.2548 | O45: 1444.9547 | P45: 1441.4835 | Q45: 1452.5747 | R45: 1454.7729 | S45: 1472.624 | T45: 1489.286 | U45: 1487.7108 | V45: 1490.3976 | W45: 1491.9331 | X45: 1491.1062 | Y45: 1484.8975 | Z45: 1464.6207 | AA45: 1458.7656 | AB45: 1466.9641 | AC45: 1451.8815 | AD45: 1455.7867 | AE45: 1466.0177 | AF45: 1462.5049 | AG45: 1473.2345 | AH45: 0.004209 | AJ45: =C45/D45 -> 0.92409063
A46: IRF000:da_OtherPetroleu | B46: Other Petroleum 3/ | C46: 4.728 | D46: 5.105 | E46: 5.237201 | F46: 3.913398 | G46: 9.131416 | H46: 11.423477 | I46: 5.746054 | J46: 8.374808 | K46: 9.649928 | L46: 0.871765 | M46: 0.069692 | N46: 0.043026 | O46: 0.027881 | P46: 0.046244 | Q46: 0.04736 | R46: 0.015157 | S46: 0.106586 | T46: 0.078291 | U46: 0.033505 | V46: 0.034214 | W46: 0.09433 | X46: 0.120671 | Y46: 0.087701 | Z46: 0.085654 | AA46: 0.021703 | AB46: 0.030275 | AC46: 0.004302 | AD46: 0 | AE46: 0 | AF46: 0 | AG46: 0.006381 | AH46: -0.197692 | AJ46: =C46/D46 -> 0.92615083
A47: IRF000:da_PetroleumSubt | B47: Petroleum and Other Liquids Subtotal | C47: 1775.064 | D47: 1920.121 | E47: 1878.5869 | F47: 1889.3936 | G47: 1878.827 | H47: 1901.892 | I47: 1913.9203 | J47: 1917.6985 | K47: 1930.96 | L47: 1940.8489 | M47: 1940.2391 | N47: 1943.802 | O47: 1952.7142 | P47: 1950.269 | Q47: 1965.4758 | R47: 1966.5964 | S47: 1983.8147 | T47: 1999.6305 | U47: 1997.9486 | V47: 2000.4519 | W47: 2002.1866 | X47: 2002.0194 | Y47: 1996.9453 | Z47: 1978.5952 | AA47: 1973.6409 | AB47: 1979.9941 | AC47: 1967.1014 | AD47: 1972.4072 | AE47: 1983.946 | AF47: 1979.2327 | AG47: 1992.5039 | AH47: 0.003859 | AJ47: =C47/D47 -> 0.92445424
A48: IRF000:da_NaturalGas | B48: Natural Gas | C48: 736.79297 | D48: 807.71802 | E48: 522.42212 | F48: 560.81763 | G48: 558.72717 | H48: 557.02759 | I48: 568.20557 | J48: 559.87012 | K48: 564.13562 | L48: 577.03967 | M48: 565.74793 | N48: 568.79926 | O48: 564.88428 | P48: 568.06506 | Q48: 574.23676 | R48: 577.27551 | S48: 588.9762 | T48: 593.17578 | U48: 601.57196 | V48: 625.96747 | W48: 624.55835 | X48: 627.29559 | Y48: 641.50122 | Z48: 662.4613 | AA48: 668.94458 | AB48: 661.50684 | AC48: 685.9986 | AD48: 698.79858 | AE48: 704.64929 | AF48: 710.91339 | AG48: 719.2608 | AH48: -0.000802 | AJ48: =C48/D48 -> 0.91219083
A49: IRF000:da_SteamCoal | B49: Steam Coal | C49: 0 | D49: 0 | E49: 0 | F49: 0 | G49: 0 | H49: 0 | I49: 0 | J49: 0 | K49: 0 | L49: 0 | M49: 0 | N49: 0 | O49: 0 | P49: 0 | Q49: 0 | R49: 0 | S49: 0 | T49: 0 | U49: 0 | V49: 0 | W49: 0 | X49: 0 | Y49: 0 | Z49: 0 | AA49: 0 | AB49: 0 | AC49: 0 | AD49: 0 | AE49: 0 | AF49: 0 | AG49: 0 | AH49: -- | AJ49: =C49/D49 -> #DIV/0!
A50: IRF000:da_PurchasedElec | B50: Purchased Electricity | C50: 146.73801 | D50: 158.48799 | E50: 145.56638 | F50: 150.0454 | G50: 147.58733 | H50: 149.5525 | I50: 151.49234 | J50: 149.98401 | K50: 152.02736 | L50: 154.49989 | M50: 156.70673 | N50: 156.83606 | O50: 157.64212 | P50: 157.735 | Q50: 160.56845 | R50: 160.62093 | S50: 163.31573 | T50: 163.95694 | U50: 164.53387 | V50: 167.34045 | W50: 167.72665 | X50: 168.2532 | Y50: 169.57719 | Z50: 169.95842 | AA50: 170.22926 | AB50: 170.06158 | AC50: 171.66635 | AD50: 173.3943 | AE50: 175.14574 | AF50: 175.41612 | AG50: 177.77255 | AH50: 0.006416 | AJ50: =C50/D50 -> 0.92586199
A51: IRF000:da_Total | B51: Total | C51: 2658.595 | D51: 2886.3269 | E51: 2546.5754 | F51: 2600.2566 | G51: 2585.1416 | H51: 2608.4719 | I51: 2633.6184 | J51: 2627.5527 | K51: 2647.123 | L51: 2672.3887 | M51: 2662.6938 | N51: 2669.4375 | O51: 2675.2407 | P51: 2676.0691 | Q51: 2700.281 | R51: 2704.4929 | S51: 2736.1067 | T51: 2756.7632 | U51: 2764.0544 | V51: 2793.7598 | W51: 2794.4717 | X51: 2797.5681 | Y51: 2808.0237 | Z51: 2811.0151 | AA51: 2812.8147 | AB51: 2811.5625 | AC51: 2824.7664 | AD51: 2844.6001 | AE51: 2863.741 | AF51: 2865.562 | AG51: 2889.5371 | AH51: 0.00278 | AJ51: =C51/D51 -> 0.92109974
AJ52: =C52/D52 -> #DIV/0!
B53: Carbon Dioxide Emissions 5/ | AJ53: =C53/D53 -> #DIV/0!
A54: IRF000:da_tonscarbon_dd | B54: (million metric tons carbon dioxide) | C54: 185.83943 | D54: 202.13274 | E54: 183.71982 | F54: 185.27573 | G54: 182.94714 | H54: 183.29549 | I54: 185.30402 | J54: 184.39504 | K54: 185.6297 | L54: 187.2945 | M54: 186.77225 | N54: 186.92531 | O54: 187.22972 | P54: 187.20258 | Q54: 188.73972 | R54: 188.64062 | S54: 190.4384 | T54: 191.58905 | U54: 191.74767 | V54: 193.38284 | W54: 193.40492 | X54: 193.47046 | Y54: 194.02159 | Z54: 193.94922 | AA54: 193.98445 | AB54: 193.73357 | AC54: 194.25157 | AD54: 195.3152 | AE54: 196.5056 | AF54: 196.49983 | AG54: 197.97943 | AH54: 0.002112 | AJ54: =C54/D54 -> 0.91939305
AJ55: =C55/D55 -> #DIV/0!
AJ56: =C56/D56 -> #DIV/0!
B57: Energy Consumption per Unit of Refinery Input | AJ57: =C57/D57 -> #DIV/0!
B58: (thousand Btu per barrel) | AJ58: =C58/D58 -> #DIV/0!
A59: IRF000:db_ResidualOil | B59: Residual Fuel Oil | C59: 0.027572 | D59: 0.026476 | E59: 0 | F59: 0 | G59: 0 | H59: 0 | I59: 0 | J59: 0 | K59: 0 | L59: 0 | M59: 0 | N59: 0 | O59: 0 | P59: 0 | Q59: 0 | R59: 0 | S59: 0 | T59: 0 | U59: 0 | V59: 0 | W59: 0 | X59: 0 | Y59: 0 | Z59: 0 | AA59: 0 | AB59: 0 | AC59: 0 | AD59: 0 | AE59: 0 | AF59: 0 | AG59: 0 | AH59: -- | AJ59: =C59/D59 -> 1.041396
A60: IRF000:db_DistillateOil | B60: Distillate Fuel Oil | C60: 0.365051 | D60: 0.353069 | E60: 0 | F60: 0 | G60: 0 | H60: 0 | I60: 0 | J60: 0 | K60: 0 | L60: 0 | M60: 0 | N60: 0 | O60: 0 | P60: 0 | Q60: 0 | R60: 0 | S60: 0 | T60: 0 | U60: 0 | V60: 0 | W60: 0 | X60: 0 | Y60: 0 | Z60: 0 | AA60: 0 | AB60: 0 | AC60: 0 | AD60: 0 | AE60: 0 | AF60: 0 | AG60: 0 | AH60: -- | AJ60: =C60/D60 -> 1.0339367
A61: IRF000:db_LiquefiedPetr | B61: Liquefied Petroleum Gas Heat and Power 2/ | C61: 1.31591 | D61: 1.271839 | E61: 0 | F61: 0 | G61: 0 | H61: 0 | I61: 0 | J61: 0 | K61: 0 | L61: 0 | M61: 0 | N61: 0 | O61: 0 | P61: 0 | Q61: 0 | R61: 0 | S61: 0 | T61: 0 | U61: 0 | V61: 0 | W61: 0 | X61: 0 | Y61: 0 | Z61: 0 | AA61: 0 | AB61: 0 | AC61: 0 | AD61: 0 | AE61: 0 | AF61: 0 | AG61: 0 | AH61: -- | AJ61: =C61/D61 -> 1.0346514
A62: IRF000:db_PetroleumCoke | B62: Petroleum Coke | C62: 84.960281 | D62: 82.134117 | E62: 79.426498 | F62: 76.505775 | G62: 75.536835 | H62: 74.189041 | I62: 75.448914 | J62: 74.31971 | K62: 74.789635 | L62: 75.989594 | M62: 76.559898 | N62: 76.355812 | O62: 76.714828 | P62: 77.085823 | Q62: 77.76371 | R62: 77.703384 | S62: 77.473717 | T62: 77.439232 | U62: 77.462914 | V62: 77.727753 | W62: 77.658684 | X62: 77.871796 | Y62: 77.899101 | Z62: 78.305099 | AA62: 78.442337 | AB62: 78.221436 | AC62: 78.717163 | AD62: 78.7873 | AE62: 78.916176 | AF62: 78.913483 | AG62: 79.412079 | AH62: -0.002249 | AJ62: =C62/D62 -> 1.0344091
A63: IRF000:db_StillGas | B63: Still Gas | C63: 238.7401 | D63: 231.13469 | E63: 217.30846 | F63: 212.73422 | G63: 209.72311 | H63: 211.21182 | I63: 213.18106 | J63: 213.64546 | K63: 215.0419 | L63: 216.83548 | M63: 216.13647 | N63: 217.24666 | O63: 218.32291 | P63: 218.41826 | Q63: 220.25307 | R63: 220.86542 | S63: 223.23068 | T63: 226.01761 | U63: 225.87503 | V63: 227.13855 | W63: 227.10861 | X63: 227.32344 | Y63: 225.93976 | Z63: 223.17531 | AA63: 222.25545 | AB63: 223.68047 | AC63: 221.82548 | AD63: 222.01504 | AE63: 223.37555 | AF63: 223.35042 | AG63: 225.3051 | AH63: -0.001929 | AJ63: =C63/D63 -> 1.0329047
A64: IRF000:db_OtherPetroleu | B64: Other Petroleum 3/ | C64: 0.869063 | D64: 0.839506 | E64: 0.829562 | F64: 0.600331 | G64: 1.393183 | H64: 1.724583 | I64: 0.869147 | J64: 1.263093 | K64: 1.455701 | L64: 0.131586 | M64: 0.010514 | N64: 0.006499 | O64: 0.004213 | P64: 0.007007 | Q64: 0.007181 | R64: 0.002301 | S64: 0.016157 | T64: 0.011882 | U64: 0.005087 | V64: 0.005214 | W64: 0.014359 | X64: 0.018397 | Y64: 0.013344 | Z64: 0.013052 | AA64: 0.003307 | AB64: 0.004616 | AC64: 0.000657 | AD64: 0 | AE64: 0 | AF64: 0 | AG64: 0.000976 | AH64: -0.202596 | AJ64: =C64/D64 -> 1.0352076
A65: IRF000:db_PetroleumSubt | B65: Petroleum and Other Liquids Subtotal | C65: 326.27795 | D65: 315.7597 | E65: 297.56451 | F65: 289.84033 | G65: 286.65314 | H65: 287.12546 | I65: 289.49912 | J65: 289.22827 | K65: 291.28723 | L65: 292.95666 | M65: 292.70691 | N65: 293.60898 | O65: 295.04193 | P65: 295.51111 | Q65: 298.02396 | R65: 298.57108 | S65: 300.72055 | T65: 303.46872 | U65: 303.34305 | V65: 304.87152 | W65: 304.78168 | X65: 305.21365 | Y65: 303.8522 | Z65: 301.49347 | AA65: 300.70108 | AB65: 301.90652 | AC65: 300.54334 | AD65: 300.80234 | AE65: 302.29172 | AF65: 302.26392 | AG65: 304.71814 | AH65: -0.002276 | AJ65: =C65/D65 -> 1.0333109
A66: IRF000:db_NaturalGas | B66: Natural Gas | C66: 135.43137 | D66: 132.82747 | E66: 82.750641 | F66: 86.031609 | G66: 85.245155 | H66: 84.093521 | I66: 85.94664 | J66: 84.439896 | K66: 85.100418 | L66: 87.099831 | M66: 85.349434 | N66: 85.916443 | O66: 85.350204 | P66: 86.075058 | Q66: 87.07119 | R66: 87.642677 | S66: 89.281143 | T66: 90.021774 | U66: 91.335007 | V66: 95.39827 | W66: 95.073021 | X66: 95.633026 | Y66: 97.609863 | Z66: 100.94422 | AA66: 101.91944 | AB66: 100.86556 | AC66: 104.81019 | AD66: 106.57041 | AE66: 107.36666 | AF66: 108.56908 | AG66: 109.99819 | AH66: -0.006909 | AJ66: =C66/D66 -> 1.0196036
A67: IRF000:db_SteamCoal | B67: Steam Coal | C67: 0 | D67: 0 | E67: 0 | F67: 0 | G67: 0 | H67: 0 | I67: 0 | J67: 0 | K67: 0 | L67: 0 | M67: 0 | N67: 0 | O67: 0 | P67: 0 | Q67: 0 | R67: 0 | S67: 0 | T67: 0 | U67: 0 | V67: 0 | W67: 0 | X67: 0 | Y67: 0 | Z67: 0 | AA67: 0 | AB67: 0 | AC67: 0 | AD67: 0 | AE67: 0 | AF67: 0 | AG67: 0 | AH67: -- | AJ67: =C67/D67 -> #DIV/0!
A68: IRF000:db_PurchasedElec | B68: Purchased Electricity | C68: 26.9722 | D68: 26.063004 | E68: 23.05743 | F68: 23.017548 | G68: 22.517437 | H68: 22.57769 | I68: 22.914696 | J68: 22.620665 | K68: 22.933477 | L68: 23.320606 | M68: 23.640972 | N68: 23.689898 | O68: 23.818661 | P68: 23.900518 | Q68: 24.346901 | R68: 24.385666 | S68: 24.756546 | T68: 24.882498 | U68: 24.980724 | V68: 25.502905 | W68: 25.532089 | X68: 25.650686 | Y68: 25.80261 | Z68: 25.897846 | AA68: 25.935886 | AB68: 25.930733 | AC68: 26.228018 | AD68: 26.443531 | AE68: 26.686768 | AF68: 26.78915 | AG68: 27.18716 | AH68: 0.000265 | AJ68: =C68/D68 -> 1.0348845
A69: IRF000:db_Total | B69: Total | C69: 488.68152 | D69: 474.65015 | E69: 403.37259 | F69: 398.8895 | G69: 394.41571 | H69: 393.79669 | I69: 398.36044 | J69: 396.28882 | K69: 399.32111 | L69: 403.37711 | M69: 401.6973 | N69: 403.21533 | O69: 404.21082 | P69: 405.48669 | Q69: 409.44205 | R69: 410.59943 | S69: 414.75824 | T69: 418.37299 | U69: 419.65875 | V69: 425.77267 | W69: 425.38678 | X69: 426.49737 | Y69: 427.26468 | Z69: 428.33554 | AA69: 428.5564 | AB69: 428.70282 | AC69: 431.58154 | AD69: 433.81628 | AE69: 436.34515 | AF69: 437.62216 | AG69: 441.9035 | AH69: -0.003348 | AJ69: =C69/D69 -> 1.0295615
AJ70: =C70/D70 -> #DIV/0!
B71: Combined Heat and Power | AJ71: =C71/D71 -> #DIV/0!
B72: Generating Capacity (gigawatts) | AJ72: =C72/D72 -> #DIV/0!
A73: IRF000:ga_Petroleum | B73: Petroleum | C73: 0.1353 | D73: 0.1353 | E73: 0.1353 | F73: 0.1353 | G73: 0.1353 | H73: 0.1353 | I73: 0.1353 | J73: 0.1353 | K73: 0.1353 | L73: 0.1353 | M73: 0.1353 | N73: 0.1353 | O73: 0.1353 | P73: 0.1353 | Q73: 0.1353 | R73: 0.1353 | S73: 0.1353 | T73: 0.1353 | U73: 0.1353 | V73: 0.1353 | W73: 0.1353 | X73: 0.1353 | Y73: 0.1353 | Z73: 0.1353 | AA73: 0.1353 | AB73: 0.1353 | AC73: 0.1353 | AD73: 0.1353 | AE73: 0.1353 | AF73: 0.1353 | AG73: 0.1353 | AH73: 0 | AJ73: =C73/D73 -> 1
A74: IRF000:ga_NaturalGas | B74: Natural Gas | C74: 3.2079 | D74: 3.2079 | E74: 3.2079 | F74: 3.2079 | G74: 3.2079 | H74: 3.2079 | I74: 3.2079 | J74: 3.2079 | K74: 3.2079 | L74: 3.2079 | M74: 3.2079 | N74: 3.2079 | O74: 3.2079 | P74: 3.2079 | Q74: 3.2079 | R74: 3.2079 | S74: 3.2079 | T74: 3.2079 | U74: 3.2079 | V74: 3.2079 | W74: 3.2079 | X74: 3.2079 | Y74: 3.2079 | Z74: 3.2079 | AA74: 3.2079 | AB74: 3.2079 | AC74: 3.2079 | AD74: 3.2079 | AE74: 3.2079 | AF74: 3.2079 | AG74: 3.2079 | AH74: 0 | AJ74: =C74/D74 -> 1
A75: IRF000:ga_Coal | B75: Coal | C75: 0 | D75: 0 | E75: 0 | F75: 0 | G75: 0 | H75: 0 | I75: 0 | J75: 0 | K75: 0 | L75: 0 | M75: 0 | N75: 0 | O75: 0 | P75: 0 | Q75: 0 | R75: 0 | S75: 0 | T75: 0 | U75: 0 | V75: 0 | W75: 0 | X75: 0 | Y75: 0 | Z75: 0 | AA75: 0 | AB75: 0 | AC75: 0 | AD75: 0 | AE75: 0 | AF75: 0 | AG75: 0 | AH75: -- | AJ75: =C75/D75 -> #DIV/0!
A76: IRF000:ga_Other | B76: Other 6/ | C76: 1.21695 | D76: 1.21695 | E76: 1.21695 | F76: 1.21695 | G76: 1.21695 | H76: 1.21695 | I76: 1.21695 | J76: 1.21695 | K76: 1.21695 | L76: 1.21695 | M76: 1.21695 | N76: 1.21695 | O76: 1.21695 | P76: 1.21695 | Q76: 1.21695 | R76: 1.21695 | S76: 1.21695 | T76: 1.21695 | U76: 1.21695 | V76: 1.21695 | W76: 1.21695 | X76: 1.21695 | Y76: 1.21695 | Z76: 1.21695 | AA76: 1.21695 | AB76: 1.21695 | AC76: 1.21695 | AD76: 1.21695 | AE76: 1.21695 | AF76: 1.21695 | AG76: 1.21695 | AH76: 0 | AJ76: =C76/D76 -> 1
A77: IRF000:ga_Total | B77: Total | C77: 4.56015 | D77: 4.56015 | E77: 4.56015 | F77: 4.56015 | G77: 4.56015 | H77: 4.56015 | I77: 4.56015 | J77: 4.56015 | K77: 4.56015 | L77: 4.56015 | M77: 4.56015 | N77: 4.56015 | O77: 4.56015 | P77: 4.56015 | Q77: 4.56015 | R77: 4.56015 | S77: 4.56015 | T77: 4.56015 | U77: 4.56015 | V77: 4.56015 | W77: 4.56015 | X77: 4.56015 | Y77: 4.56015 | Z77: 4.56015 | AA77: 4.56015 | AB77: 4.56015 | AC77: 4.56015 | AD77: 4.56015 | AE77: 4.56015 | AF77: 4.56015 | AG77: 4.56015 | AH77: 0 | AJ77: =C77/D77 -> 1
B78: Net Generation (billion kilowatthours) | AJ78: =C78/D78 -> #DIV/0!
A79: IRF000:ha_Petroleum | B79: Petroleum | C79: 0.39832 | D79: 0.39832 | E79: 0 | F79: 0 | G79: 0 | H79: 0 | I79: 0 | J79: 0 | K79: 0 | L79: 0 | M79: 0 | N79: 0 | O79: 0 | P79: 0 | Q79: 0 | R79: 0 | S79: 0 | T79: 0 | U79: 0 | V79: 0 | W79: 0 | X79: 0 | Y79: 0 | Z79: 0 | AA79: 0 | AB79: 0 | AC79: 0 | AD79: 0 | AE79: 0 | AF79: 0 | AG79: 0 | AH79: -- | AJ79: =C79/D79 -> 1
A80: IRF000:ha_NaturalGas | B80: Natural Gas | C80: 24.809412 | D80: 24.809412 | E80: 24.435719 | F80: 24.522161 | G80: 24.522161 | H80: 24.522161 | I80: 24.522161 | J80: 24.522161 | K80: 24.522161 | L80: 24.522161 | M80: 23.717573 | N80: 23.712896 | O80: 23.708588 | P80: 23.762985 | Q80: 23.849995 | R80: 23.94566 | S80: 24.135637 | T80: 24.470867 | U80: 24.522161 | V80: 24.522161 | W80: 24.522161 | X80: 24.522161 | Y80: 24.522161 | Z80: 24.522161 | AA80: 24.522161 | AB80: 24.522161 | AC80: 24.522161 | AD80: 24.522161 | AE80: 24.522161 | AF80: 24.522161 | AG80: 24.522161 | AH80: -0.000388 | AJ80: =C80/D80 -> 1
A81: IRF000:ha_Coal | B81: Coal | C81: 0 | D81: 0 | E81: 0 | F81: 0 | G81: 0 | H81: 0 | I81: 0 | J81: 0 | K81: 0 | L81: 0 | M81: 0 | N81: 0 | O81: 0 | P81: 0 | Q81: 0 | R81: 0 | S81: 0 | T81: 0 | U81: 0 | V81: 0 | W81: 0 | X81: 0 | Y81: 0 | Z81: 0 | AA81: 0 | AB81: 0 | AC81: 0 | AD81: 0 | AE81: 0 | AF81: 0 | AG81: 0 | AH81: -- | AJ81: =C81/D81 -> #DIV/0!
A82: IRF000:ha_Other | B82: Other 6/ | C82: 5.444911 | D82: 5.444911 | E82: 6.10893 | F82: 6.13054 | G82: 6.13054 | H82: 6.13054 | I82: 6.13054 | J82: 6.13054 | K82: 6.13054 | L82: 6.13054 | M82: 5.929393 | N82: 5.928224 | O82: 5.927147 | P82: 5.940746 | Q82: 5.962499 | R82: 5.986415 | S82: 6.033909 | T82: 6.117717 | U82: 6.13054 | V82: 6.13054 | W82: 6.13054 | X82: 6.13054 | Y82: 6.13054 | Z82: 6.13054 | AA82: 6.13054 | AB82: 6.13054 | AC82: 6.13054 | AD82: 6.13054 | AE82: 6.13054 | AF82: 6.13054 | AG82: 6.13054 | AH82: 0.003961 | AJ82: =C82/D82 -> 1
A83: IRF000:ha_Total | B83: Total | C83: 30.652641 | D83: 30.652641 | E83: 30.544647 | F83: 30.652702 | G83: 30.652702 | H83: 30.652702 | I83: 30.652702 | J83: 30.652702 | K83: 30.652702 | L83: 30.652702 | M83: 29.646967 | N83: 29.641121 | O83: 29.635735 | P83: 29.703732 | Q83: 29.812492 | R83: 29.932076 | S83: 30.169546 | T83: 30.588585 | U83: 30.652702 | V83: 30.652702 | W83: 30.652702 | X83: 30.652702 | Y83: 30.652702 | Z83: 30.652702 | AA83: 30.652702 | AB83: 30.652702 | AC83: 30.652702 | AD83: 30.652702 | AE83: 30.652702 | AF83: 30.652702 | AG83: 30.652702 | AH83: 0 | AJ83: =C83/D83 -> 1
B84: Disposition | AJ84: =C84/D84 -> #DIV/0!
A85: IRF000:ha_SalestotheGri | B85: Sales to the Grid | C85: 9.58069 | D85: 9.58069 | E85: 0 | F85: 0 | G85: 0 | H85: 0 | I85: 0 | J85: 0 | K85: 0 | L85: 0 | M85: 0 | N85: 0 | O85: 0 | P85: 0 | Q85: 0 | R85: 0 | S85: 0 | T85: 0 | U85: 0 | V85: 0 | W85: 0 | X85: 0 | Y85: 0 | Z85: 0 | AA85: 0 | AB85: 0 | AC85: 0 | AD85: 0 | AE85: 0 | AF85: 0 | AG85: 0 | AH85: -- | AJ85: =C85/D85 -> 1
A86: IRF000:ha_Generationfor | B86: Generation for Own Use | C86: 21.071953 | D86: 21.071953 | E86: 30.544647 | F86: 30.6527 | G86: 30.6527 | H86: 30.6527 | I86: 30.6527 | J86: 30.6527 | K86: 30.6527 | L86: 30.6527 | M86: 29.646967 | N86: 29.641119 | O86: 29.635735 | P86: 29.703732 | Q86: 29.812494 | R86: 29.932074 | S86: 30.169548 | T86: 30.588583 | U86: 30.6527 | V86: 30.6527 | W86: 30.6527 | X86: 30.6527 | Y86: 30.6527 | Z86: 30.6527 | AA86: 30.6527 | AB86: 30.6527 | AC86: 30.6527 | AD86: 30.6527 | AE86: 30.6527 | AF86: 30.6527 | AG86: 30.6527 | AH86: 0.012571 | AJ86: =C86/D86 -> 1
AJ87: =C87/D87 -> #DIV/0!
B88: Energy Consumed at Ethanol Plants | AJ88: =C88/D88 -> #DIV/0!
B89: (trillion Btu) | AJ89: =C89/D89 -> #DIV/0!
A90: IRF000:ja_NaturalGas | B90: Natural Gas | C90: 368 | D90: 368 | E90: 414.74948 | F90: 416.08212 | G90: 418.25586 | H90: 421.20303 | I90: 422.67941 | J90: 423.75107 | K90: 425.15845 | L90: 426.19507 | M90: 427.70346 | N90: 432.1915 | O90: 434.06284 | P90: 436.4957 | Q90: 439.3782 | R90: 442.26651 | S90: 444.29971 | T90: 446.73306 | U90: 449.21011 | V90: 451.98691 | W90: 454.98169 | X90: 457.92313 | Y90: 459.84992 | Z90: 461.55334 | AA90: 463.43222 | AB90: 466.23846 | AC90: 467.86957 | AD90: 475.48383 | AE90: 480.07483 | AF90: 484.61603 | AG90: 489.3197 | AH90: 0.009543 | AJ90: =C90/D90 -> 1
A91: IRF000:ja_Coal | B91: Coal | C91: 24 | D91: 24 | E91: 0 | F91: 0 | G91: 0 | H91: 0 | I91: 0 | J91: 0 | K91: 0 | L91: 0 | M91: 0 | N91: 0 | O91: 0 | P91: 0 | Q91: 0 | R91: 0 | S91: 0 | T91: 0 | U91: 0.122591 | V91: 0.149576 | W91: 0.178443 | X91: 0.153959 | Y91: 5.231768 | Z91: 11.411824 | AA91: 18.228508 | AB91: 28.409792 | AC91: 30.051184 | AD91: 30.071499 | AE91: 30.07649 | AF91: 30.29249 | AG91: 30.24353 | AH91: 0.007737 | AJ91: =C91/D91 -> 1
A92: IRF000:ja_Electricity | B92: Electricity | C92: 37 | D92: 37 | E92: 39.808418 | F92: 39.988785 | G92: 40.194592 | H92: 40.473621 | I92: 40.6134 | J92: 40.714863 | K92: 40.84811 | L92: 40.946255 | M92: 41.089066 | N92: 41.513985 | O92: 41.691158 | P92: 41.921494 | Q92: 42.194405 | R92: 42.484661 | S92: 42.71566 | T92: 42.972382 | U92: 43.245636 | V92: 43.561966 | W92: 43.903114 | X92: 44.236534 | Y92: 44.614914 | Z92: 45.072651 | AA92: 45.505005 | AB92: 46.143581 | AC92: 46.380421 | AD92: 47.246113 | AE92: 47.692993 | AF92: 48.215717 | AG92: 48.748581 | AH92: 0.009234 | AJ92: =C92/D92 -> 1
A93: IRF000:ja_Total | B93: Total | C93: 429 | D93: 429 | E93: 454.55789 | F93: 456.07092 | G93: 458.45044 | H93: 461.67667 | I93: 463.29282 | J93: 464.46594 | K93: 466.00656 | L93: 467.14133 | M93: 468.79254 | N93: 473.70547 | O93: 475.754 | P93: 478.41717 | Q93: 481.5726 | R93: 484.75116 | S93: 487.01538 | T93: 489.70544 | U93: 492.57834 | V93: 495.69842 | W93: 499.06323 | X93: 502.31363 | Y93: 509.69659 | Z93: 518.03784 | AA93: 527.16577 | AB93: 540.79181 | AC93: 544.30115 | AD93: 552.80145 | AE93: 557.8443 | AF93: 563.12421 | AG93: 568.31183 | AH93: 0.009418 | AJ93: =C93/D93 -> 1
AJ94: =C94/D94 -> #DIV/0!
B95: 1/ Includes energy for combined heat and power plants that have a non-regulatory status, small on-site generating systems, | AJ95: =C95/D95 -> #DIV/0!
B96: consumption at ethanol plants, and (if adapted) consumption at coal-to-liquids (CTL) and gas-to-liquids (GTL) plants. | AJ96: =C96/D96 -> #DIV/0!
B97: 2/ Includes ethane, natural gasoline, and refinery olefins. | AJ97: =C97/D97 -> #DIV/0!
B98: 3/ Includes lubricants and miscellaneous petroleum products. | AJ98: =C98/D98 -> #DIV/0!
B99: 4/ Includes consumption at ethanol and coal-to-liquids (CTL) plants. Where CTL technology is adopted in these projections, | AJ99: =C99/D99 -> #DIV/0!
B100: the plants are assumed to produce oil products and to generate electricity. | AJ100: =C100/D100 -> #DIV/0!
B101: A portion of the coal use is attributed to feedstock use to produce the liquids. The feedstock portion | AJ101: =C101/D101 -> #DIV/0!
B102: is assumed to be equal to the Btu content of the liquids produced. The rest of the coal used in CTL plants is accounted for in | AJ102: =C102/D102 -> #DIV/0!
B103: industrial steam coal consumption, a portion of which is reflected in energy used for end-use sector combined heat and power. | AJ103: =C103/D103 -> #DIV/0!
B104: 5/ Includes emissions attributable to the fuels consumed to generate the purchased electricity. | AJ104: =C104/D104 -> #DIV/0!
B105: 6/ Includes municipal waste, wood, and other biomass. | AJ105: =C105/D105 -> #DIV/0!
...

Sheet AEO T25 Food 2022 Raw
A1: Table 25. Food Industry Energy Consumption
A2: https://www.eia.gov/outlooks/aeo/data/browser/#/?id=36-AEO2022&cases=lowmacro&sourcekey=0
A3: Wed Jul 13 2022 09:59:00 GMT-0400 (Eastern Daylight Time)
A4: Source: U.S. Energy Information Administration
B5: full name | C5: api key | D5: units | E5: 2020 | F5: 2021 | G5: 2022 | H5: 2023 | I5: 2024 | J5: 2025 | K5: 2026 | L5: 2027 | M5: 2028 | N5: 2029 | O5: 2030 | P5: 2031 | Q5: 2032 | R5: 2033 | S5: 2034 | T5: 2035 | U5: 2036 | V5: 2037 | W5: 2038 | X5: 2039 | Y5: 2040 | Z5: 2041 | AA5: 2042 | AB5: 2043 | AC5: 2044 | AD5: 2045 | AE5: 2046 | AF5: 2047 | AG5: 2048 | AH5: 2049 | AI5: 2050 | AJ5: Growth (2021-2050)
A6: Value of Shipments (billion 2012 dollars) | B6: Food Industry: Value of Shipments: Low economic growth | C6: 36-AEO2022.2.lowmacro-d011222a | D6: billion 2012 $ | F6: 951.64435 | G6: 968.1377 | H6: 969.99872 | I6: 974.52918 | J6: 980.4978 | K6: 986.57391 | L6: 993.19183 | M6: 999.98218 | N6: 1005.9415 | O6: 1011.705 | P6: 1017.6683 | Q6: 1023.1825 | R6: 1027.4513 | S6: 1031.0057 | T6: 1034.582 | U6: 1038.2365 | V6: 1041.2788 | W6: 1044.4017 | X6: 1048.0537 | Y6: 1051.4875 | Z6: 1054.3187 | AA6: 1057.787 | AB6: 1061.2743 | AC6: 1064.614 | AD6: 1067.8418 | AE6: 1070.3273 | AF6: 1072.7795 | AG6: 1076.1705 | AH6: 1080.1558 | AI6: 1085.246 | AJ6: 0.005
A7: Energy Consumption (trillion Btu) | C7: 36-AEO2022.4.
A8: Residual Fuel Oil | B8: Food Industry: Energy Use: Residual Fuel Oil: Low economic growth | C8: 36-AEO2022.5.lowmacro-d011222a | D8: trillion Btu | F8: 0 | G8: 0 | H8: 0 | I8: 0 | J8: 0 | K8: 0 | L8: 0 | M8: 0 | N8: 0 | O8: 0 | P8: 0 | Q8: 0 | R8: 0 | S8: 0 | T8: 0 | U8: 0 | V8: 0 | W8: 0 | X8: 0 | Y8: 0 | Z8: 0 | AA8: 0 | AB8: 0 | AC8: 0 | AD8: 0 | AE8: 0 | AF8: 0 | AG8: 0 | AH8: 0 | AI8: 0 | AJ8: - -
A9: Distillate Fuel Oil | B9: Food Industry: Energy Use: Distillate Fuel Oil: Low economic growth | C9: 36-AEO2022.6.lowmacro-d011222a | D9: trillion Btu | F9: 5.627154 | G9: 5.260293 | H9: 5.331036 | I9: 5.121982 | J9: 5.125743 | K9: 5.169047 | L9: 5.212226 | M9: 5.232885 | N9: 5.24092 | O9: 5.252158 | P9: 5.256423 | Q9: 5.259318 | R9: 5.272373 | S9: 5.280777 | T9: 5.283544 | U9: 5.287021 | V9: 5.293893 | W9: 5.31083 | X9: 5.339373 | Y9: 5.343135 | Z9: 5.365616 | AA9: 5.398614 | AB9: 5.413135 | AC9: 5.423661 | AD9: 5.447029 | AE9: 5.451392 | AF9: 5.476696 | AG9: 5.510705 | AH9: 5.536191 | AI9: 5.575253 | AJ9: 0
A10: Propane | B10: Food Industry: Energy Use: Propane: Low economic growth | C10: 36-AEO2022.7.lowmacro-d011222a | D10: trillion Btu | F10: 2.192929 | G10: 2.270476 | H10: 1.946182 | I10: 1.37834 | J10: 1.174641 | K10: 1.05954 | L10: 0.978171 | M10: 1.005221 | N10: 1.029062 | O10: 1.033881 | P10: 1.03307 | Q10: 1.018098 | R10: 1.02714 | S10: 1.014497 | T10: 0.987038 | U10: 0.968649 | V10: 0.962958 | W10: 0.956875 | X10: 0.960653 | Y10: 0.9283 | Z10: 0.926457 | AA10: 0.922238 | AB10: 0.893382 | AC10: 0.872203 | AD10: 0.851638 | AE10: 0.833936 | AF10: 0.825785 | AG10: 0.822588 | AH10: 0.818329 | AI10: 0.819534 | AJ10: -0.033
A11: Other Petroleum | B11: Food Industry: Energy Use: Other Petroleum: Low economic growth | C11: 36-AEO2022.8.lowmacro-d011222a | D11: trillion Btu | F11: 0 | G11: 0 | H11: 0 | I11: 0 | J11: 0 | K11: 0 | L11: 0 | M11: 0 | N11: 0 | O11: 0 | P11: 0 | Q11: 0 | R11: 0 | S11: 0 | T11: 0 | U11: 0 | V11: 0 | W11: 0 | X11: 0 | Y11: 0 | Z11: 0 | AA11: 0 | AB11: 0 | AC11: 0 | AD11: 0 | AE11: 0 | AF11: 0 | AG11: 0 | AH11: 0 | AI11: 0 | AJ11: - -
A12: Petroleum and Other Liquids Subtotal | B12: Food Industry: Energy Use: Petroleum Subtotal: Low economic growth | C12: 36-AEO2022.9.lowmacro-d011222a | D12: trillion Btu | F12: 7.820084 | G12: 7.530768 | H12: 7.277218 | I12: 6.500322 | J12: 6.300385 | K12: 6.228588 | L12: 6.190397 | M12: 6.238106 | N12: 6.269981 | O12: 6.286039 | P12: 6.289493 | Q12: 6.277415 | R12: 6.299513 | S12: 6.295274 | T12: 6.270583 | U12: 6.25567 | V12: 6.256851 | W12: 6.267704 | X12: 6.300025 | Y12: 6.271435 | Z12: 6.292073 | AA12: 6.320852 | AB12: 6.306517 | AC12: 6.295864 | AD12: 6.298667 | AE12: 6.285328 | AF12: 6.302482 | AG12: 6.333293 | AH12: 6.354521 | AI12: 6.394787 | AJ12: -0.007
A13: Natural Gas | B13: Food Industry: Energy Use: Natural Gas: Low economic growth | C13: 36-AEO2022.10.lowmacro-d011222a | D13: trillion Btu | F13: 708.91211 | G13: 718.23315 | H13: 719.33472 | I13: 719.57544 | J13: 716.81726 | K13: 710.0921 | L13: 699.19678 | M13: 686.12933 | N13: 672.22479 | O13: 658.72064 | P13: 646.51367 | Q13: 631.74072 | R13: 617.66498 | S13: 604.65521 | T13: 592.90765 | U13: 582.3114 | V13: 575.75159 | W13: 572.86932 | X13: 570.36645 | Y13: 568.1283 | Z13: 565.69275 | AA13: 564.29028 | AB13: 563.90021 | AC13: 563.12457 | AD13: 562.73547 | AE13: 561.73499 | AF13: 560.73352 | AG13: 560.20044 | AH13: 559.91858 | AI13: 559.90125 | AJ13: -0.008
A14: Steam Coal | B14: Food Industry: Energy Use: Steam Coal: Low economic growth | C14: 36-AEO2022.11.lowmacro-d011222a | D14: trillion Btu | F14: 120.65002 | G14: 121.6443 | H14: 122.50738 | I14: 123.32153 | J14: 124.09146 | K14: 124.79425 | L14: 125.42467 | M14: 125.96892 | N14: 126.40067 | O14: 126.71386 | P14: 126.9089 | Q14: 126.97023 | R14: 126.89532 | S14: 126.74983 | T14: 126.60882 | U14: 126.47578 | V14: 126.34092 | W14: 126.20685 | X14: 126.07678 | Y14: 125.94997 | Z14: 125.82139 | AA14: 125.69995 | AB14: 125.58214 | AC14: 125.46759 | AD14: 125.35948 | AE14: 125.24904 | AF14: 125.14445 | AG14: 125.04241 | AH14: 124.94379 | AI14: 124.8584 | AJ14: 0.001
A15: Renewables | B15: Food Industry: Energy Use: Renewables: Low economic growth | C15: 36-AEO2022.12.lowmacro-d011222a | D15: trillion Btu | F15: 42.718613 | G15: 44.452999 | H15: 45.227348 | I15: 45.90411 | J15: 46.651237 | K15: 47.408489 | L15: 48.233803 | M15: 49.057999 | N15: 49.806713 | O15: 50.490818 | P15: 51.225452 | Q15: 51.913265 | R15: 52.413948 | S15: 52.843273 | T15: 53.283752 | U15: 53.721146 | V15: 54.097984 | W15: 54.495686 | X15: 54.929451 | Y15: 55.349358 | Z15: 55.734379 | AA15: 56.171242 | AB15: 56.609455 | AC15: 57.058678 | AD15: 57.542686 | AE15: 57.985077 | AF15: 58.453686 | AG15: 58.936592 | AH15: 59.437241 | AI15: 60.040871 | AJ15: 0.012
A16: Purchased Electricity | B16: Food Industry: Energy Use: Purchased Electricity: Low economic growth | C16: 36-AEO2022.13.lowmacro-d011222a | D16: trillion Btu | F16: 281.88214 | G16: 284.83514 | H16: 286.75903 | I16: 288.7792 | J16: 290.70258 | K16: 292.43246 | L16: 294.07028 | M16: 295.31125 | N16: 296.06628 | O16: 296.76987 | P16: 297.66632 | Q16: 298.4368 | R16: 298.88538 | S16: 298.95648 | T16: 299.32535 | U16: 299.62271 | V16: 299.88837 | W16: 300.14526 | X16: 300.57428 | Y16: 300.91956 | Z16: 301.31827 | AA16: 301.97232 | AB16: 302.87808 | AC16: 303.4639 | AD16: 303.83655 | AE16: 304.12579 | AF16: 304.21451 | AG16: 304.67517 | AH16: 305.31885 | AI16: 306.09189 | AJ16: 0.003
A17: Total | B17: Food Industry: Energy Use: Total: Low economic growth | C17: 36-AEO2022.14.lowmacro-d011222a | D17: trillion Btu | F17: 1161.9829 | G17: 1176.6963 | H17: 1181.1057 | I17: 1184.0806 | J17: 1184.563 | K17: 1180.9559 | L17: 1173.116 | M17: 1162.7056 | N17: 1150.7684 | O17: 1138.9812 | P17: 1128.6038 | Q17: 1115.3384 | R17: 1102.1592 | S17: 1089.5 | T17: 1078.3961 | U17: 1068.3867 | V17: 1062.3357 | W17: 1059.9849 | X17: 1058.2471 | Y17: 1056.6187 | Z17: 1054.8589 | AA17: 1054.4547 | AB17: 1055.2764 | AC17: 1055.4105 | AD17: 1055.7728 | AE17: 1055.3801 | AF17: 1054.8486 | AG17: 1055.188 | AH17: 1055.9729 | AI17: 1057.2872 | AJ17: -0.003
A18: Energy Consumption per Unit of Output | C18: 36-AEO2022.16.
A19: (thousand Btu per 2012 dollar shipments) | C19: 36-AEO2022.17.
A20: Residual Fuel Oil | B20: Food Industry: Energy Use per Unit of Output: Residual Fuel Oil: Low economic growth | C20: 36-AEO2022.18.lowmacro-d011222a | D20: thousand Btu/2012 $ | F20: 0 | G20: 0 | H20: 0 | I20: 0 | J20: 0 | K20: 0 | L20: 0 | M20: 0 | N20: 0 | O20: 0 | P20: 0 | Q20: 0 | R20: 0 | S20: 0 | T20: 0 | U20: 0 | V20: 0 | W20: 0 | X20: 0 | Y20: 0 | Z20: 0 | AA20: 0 | AB20: 0 | AC20: 0 | AD20: 0 | AE20: 0 | AF20: 0 | AG20: 0 | AH20: 0 | AI20: 0 | AJ20: - -
A21: Distillate Fuel Oil | B21: Food Industry: Energy Use per Unit of Output: Distillate Fuel Oil: Low economic growth | C21: 36-AEO2022.19.lowmacro-d011222a | D21: thousand Btu/2012 $ | F21: 0.005913 | G21: 0.005433 | H21: 0.005496 | I21: 0.005256 | J21: 0.005228 | K21: 0.005239 | L21: 0.005248 | M21: 0.005233 | N21: 0.00521 | O21: 0.005191 | P21: 0.005165 | Q21: 0.00514 | R21: 0.005132 | S21: 0.005122 | T21: 0.005107 | U21: 0.005092 | V21: 0.005084 | W21: 0.005085 | X21: 0.005095 | Y21: 0.005082 | Z21: 0.005089 | AA21: 0.005104 | AB21: 0.005101 | AC21: 0.005094 | AD21: 0.005101 | AE21: 0.005093 | AF21: 0.005105 | AG21: 0.005121 | AH21: 0.005125 | AI21: 0.005137 | AJ21: -0.005
A22: Propane | B22: Food Industry: Energy Use per Unit of Output: Propane: Low economic growth | C22: 36-AEO2022.20.lowmacro-d011222a | D22: thousand Btu/2012 $ | F22: 0.002304 | G22: 0.002345 | H22: 0.002006 | I22: 0.001414 | J22: 0.001198 | K22: 0.001074 | L22: 0.000985 | M22: 0.001005 | N22: 0.001023 | O22: 0.001022 | P22: 0.001015 | Q22: 0.000995 | R22: 0.001 | S22: 0.000984 | T22: 0.000954 | U22: 0.000933 | V22: 0.000925 | W22: 0.000916 | X22: 0.000917 | Y22: 0.000883 | Z22: 0.000879 | AA22: 0.000872 | AB22: 0.000842 | AC22: 0.000819 | AD22: 0.000798 | AE22: 0.000779 | AF22: 0.00077 | AG22: 0.000764 | AH22: 0.000758 | AI22: 0.000755 | AJ22: -0.038
A23: Other Petroleum | B23: Food Industry: Energy Use per Unit of Output: Other Petroleum: Low economic growth | C23: 36-AEO2022.21.lowmacro-d011222a | D23: thousand Btu/2012 $ | F23: 0 | G23: 0 | H23: 0 | I23: 0 | J23: 0 | K23: 0 | L23: 0 | M23: 0 | N23: 0 | O23: 0 | P23: 0 | Q23: 0 | R23: 0 | S23: 0 | T23: 0 | U23: 0 | V23: 0 | W23: 0 | X23: 0 | Y23: 0 | Z23: 0 | AA23: 0 | AB23: 0 | AC23: 0 | AD23: 0 | AE23: 0 | AF23: 0 | AG23: 0 | AH23: 0 | AI23: 0 | AJ23: - -
A24: Petroleum and Other Liquids Subtotal | B24: Food Industry: Energy Use per Unit of Output: Petroleum Subtotal: Low economic growth | C24: 36-AEO2022.22.lowmacro-d011222a | D24: thousand Btu/2012 $ | F24: 0.008217 | G24: 0.007779 | H24: 0.007502 | I24: 0.00667 | J24: 0.006426 | K24: 0.006313 | L24: 0.006233 | M24: 0.006238 | N24: 0.006233 | O24: 0.006213 | P24: 0.00618 | Q24: 0.006135 | R24: 0.006131 | S24: 0.006106 | T24: 0.006061 | U24: 0.006025 | V24: 0.006009 | W24: 0.006001 | X24: 0.006011 | Y24: 0.005964 | Z24: 0.005968 | AA24: 0.005976 | AB24: 0.005942 | AC24: 0.005914 | AD24: 0.005899 | AE24: 0.005872 | AF24: 0.005875 | AG24: 0.005885 | AH24: 0.005883 | AI24: 0.005892 | AJ24: -0.011
A25: Natural Gas | B25: Food Industry: Energy Use per Unit of Output: Natural Gas: Low economic growth | C25: 36-AEO2022.23.lowmacro-d011222a | D25: thousand Btu/2012 $ | F25: 0.744934 | G25: 0.741871 | H25: 0.741583 | I25: 0.738383 | J25: 0.731075 | K25: 0.719756 | L25: 0.70399 | M25: 0.686142 | N25: 0.668254 | O25: 0.6511 | P25: 0.635289 | Q25: 0.617427 | R25: 0.601162 | S25: 0.586471 | T25: 0.573089 | U25: 0.560866 | V25: 0.552927 | W25: 0.548514 | X25: 0.544215 | Y25: 0.540309 | Z25: 0.536548 | AA25: 0.533463 | AB25: 0.531343 | AC25: 0.528947 | AD25: 0.526984 | AE25: 0.524825 | AF25: 0.522692 | AG25: 0.52055 | AH25: 0.518368 | AI25: 0.515921 | AJ25: -0.013
A26: Steam Coal | B26: Food Industry: Energy Use per Unit of Output: Steam Coal: Low economic growth | C26: 36-AEO2022.24.lowmacro-d011222a | D26: thousand Btu/2012 $ | F26: 0.126781 | G26: 0.125648 | H26: 0.126296 | I26: 0.126545 | J26: 0.12656 | K26: 0.126493 | L26: 0.126284 | M26: 0.125971 | N26: 0.125654 | O26: 0.125248 | P26: 0.124706 | Q26: 0.124093 | R26: 0.123505 | S26: 0.122938 | T26: 0.122377 | U26: 0.121818 | V26: 0.121332 | W26: 0.120841 | X26: 0.120296 | Y26: 0.119783 | Z26: 0.119339 | AA26: 0.118833 | AB26: 0.118331 | AC26: 0.117853 | AD26: 0.117395 | AE26: 0.117019 | AF26: 0.116654 | AG26: 0.116192 | AH26: 0.115672 | AI26: 0.115051 | AJ26: -0.003
A27: Renewables | B27: Food Industry: Energy Use per Unit of Output: Renewables: Low economic growth | C27: 36-AEO2022.25.lowmacro-d011222a | D27: thousand Btu/2012 $ | F27: 0.044889 | G27: 0.045916 | H27: 0.046626 | I27: 0.047104 | J27: 0.047579 | K27: 0.048054 | L27: 0.048564 | M27: 0.049059 | N27: 0.049513 | O27: 0.049907 | P27: 0.050336 | Q27: 0.050737 | R27: 0.051014 | S27: 0.051254 | T27: 0.051503 | U27: 0.051743 | V27: 0.051953 | W27: 0.052179 | X27: 0.052411 | Y27: 0.052639 | Z27: 0.052863 | AA27: 0.053103 | AB27: 0.053341 | AC27: 0.053596 | AD27: 0.053887 | AE27: 0.054175 | AF27: 0.054488 | AG27: 0.054765 | AH27: 0.055027 | AI27: 0.055325 | AJ27: 0.007
A28: Purchased Electricity | B28: Food Industry: Energy Use per Unit of Output: Purchased Electricity: Low economic growth | C28: 36-AEO2022.26.lowmacro-d011222a | D28: thousand Btu/2012 $ | F28: 0.296205 | G28: 0.294209 | H28: 0.295628 | I28: 0.296327 | J28: 0.296485 | K28: 0.296412 | L28: 0.296086 | M28: 0.295317 | N28: 0.294318 | O28: 0.293336 | P28: 0.292498 | Q28: 0.291675 | R28: 0.2909 | S28: 0.289966 | T28: 0.28932 | U28: 0.288588 | V28: 0.288 | W28: 0.287385 | X28: 0.286793 | Y28: 0.286185 | Z28: 0.285794 | AA28: 0.285476 | AB28: 0.285391 | AC28: 0.285046 | AD28: 0.284533 | AE28: 0.284143 | AF28: 0.283576 | AG28: 0.28311 | AH28: 0.282662 | AI28: 0.282048 | AJ28: -0.002
A29: Total | B29: Food Industry: Energy Use per Unit of Output: Total: Low economic growth | C29: 36-AEO2022.27.lowmacro-d011222a | D29: thousand Btu/2012 $ | F29: 1.221026 | G29: 1.215423 | H29: 1.217636 | I29: 1.215028 | J29: 1.208124 | K29: 1.197027 | L29: 1.181157 | M29: 1.162726 | N29: 1.143971 | O29: 1.125804 | P29: 1.10901 | Q29: 1.090068 | R29: 1.072712 | S29: 1.056735 | T29: 1.04235 | U29: 1.02904 | V29: 1.020222 | W29: 1.014921 | X29: 1.009726 | Y29: 1.00488 | Z29: 1.000512 | AA29: 0.99685 | AB29: 0.994348 | AC29: 0.991355 | AD29: 0.988698 | AE29: 0.986035 | AF29: 0.983286 | AG29: 0.980502 | AH29: 0.977612 | AI29: 0.974237 | AJ29: -0.008
A30: Carbon Dioxide Emissions | C30: 36-AEO2022.29.
A31: (million metric tons carbon dioxide) | B31: Food Industry: Carbon Dioxide Emissions: Low economic growth | C31: 36-AEO2022.30.lowmacro-d011222a | D31: MMmt CO2 | F31: 84.659256 | G31: 84.432541 | H31: 83.172096 | I31: 80.253532 | J31: 79.190575 | K31: 78.534172 | L31: 77.286858 | M31: 76.849823 | N31: 75.901016 | O31: 74.654869 | P31: 73.685036 | Q31: 72.539032 | R31: 72.185402 | S31: 70.479309 | T31: 68.929382 | U31: 67.844734 | V31: 67.295563 | W31: 67.146736 | X31: 67.028603 | Y31: 66.761383 | Z31: 66.571747 | AA31: 66.451202 | AB31: 66.338867 | AC31: 66.178299 | AD31: 65.898499 | AE31: 65.746361 | AF31: 65.525658 | AG31: 65.367485 | AH31: 65.303795 | AI31: 65.428558 | AJ31: -0.009
A32: Combined Heat and Power | C32: 36-AEO2022.33.
A33: Generating Capacity (gigawatts) | C33: 36-AEO2022.34.
A34: Petroleum | B34: Food Industry: Combined Heat and Power: Generating Capacity: Petroleum: Low economic growth | C34: 36-AEO2022.35.lowmacro-d011222a | D34: GW | F34: 0.1007 | G34: 0.1007 | H34: 0.1007 | I34: 0.1007 | J34: 0.1007 | K34: 0.1007 | L34: 0.1007 | M34: 0.1007 | N34: 0.1007 | O34: 0.1007 | P34: 0.1007 | Q34: 0.1007 | R34: 0.1007 | S34: 0.1007 | T34: 0.1007 | U34: 0.1007 | V34: 0.1007 | W34: 0.1007 | X34: 0.1007 | Y34: 0.1007 | Z34: 0.1007 | AA34: 0.1007 | AB34: 0.1007 | AC34: 0.1007 | AD34: 0.1007 | AE34: 0.1007 | AF34: 0.1007 | AG34: 0.1007 | AH34: 0.1007 | AI34: 0.1007 | AJ34: 0
A35: Natural Gas | B35: Food Industry: Combined Heat and Power: Generating Capacity: Natural Gas: Low economic growth | C35: 36-AEO2022.36.lowmacro-d011222a | D35: GW | F35: 0.570334 | G35: 0.582906 | H35: 0.593123 | I35: 0.600868 | J35: 0.607955 | K35: 0.614551 | L35: 0.621011 | M35: 0.627203 | N35: 0.633211 | O35: 0.638965 | P35: 0.644644 | Q35: 0.648905 | R35: 0.65314 | S35: 0.657337 | T35: 0.661484 | U35: 0.665673 | V35: 0.669925 | W35: 0.674236 | X35: 0.678482 | Y35: 0.682881 | Z35: 0.687255 | AA35: 0.691688 | AB35: 0.696218 | AC35: 0.700807 | AD35: 0.705437 | AE35: 0.71013 | AF35: 0.714914 | AG35: 0.719763 | AH35: 0.724681 | AI35: 0.729722 | AJ35: 0.009
A36: Coal | B36: Food Industry: Combined Heat and Power: Generating Capacity: Coal: Low economic growth | C36: 36-AEO2022.37.lowmacro-d011222a | D36: GW | F36: 1.0235 | G36: 1.0235 | H36: 1.0235 | I36: 1.0235 | J36: 1.0235 | K36: 1.0235 | L36: 1.0235 | M36: 1.0235 | N36: 1.0235 | O36: 1.0235 | P36: 1.0235 | Q36: 1.0235 | R36: 1.0235 | S36: 1.0235 | T36: 1.0235 | U36: 1.0235 | V36: 1.0235 | W36: 1.0235 | X36: 1.0235 | Y36: 1.0235 | Z36: 1.0235 | AA36: 1.0235 | AB36: 1.0235 | AC36: 1.0235 | AD36: 1.0235 | AE36: 1.0235 | AF36: 1.0235 | AG36: 1.0235 | AH36: 1.0235 | AI36: 1.0235 | AJ36: 0
A37: Other | B37: Food Industry: Combined Heat and Power: Generating Capacity: Other: Low economic growth | C37: 36-AEO2022.38.lowmacro-d011222a | D37: GW | F37: 0.0636 | G37: 0.0659 | H37: 0.0659 | I37: 0.0659 | J37: 0.0659 | K37: 0.0659 | L37: 0.0659 | M37: 0.0659 | N37: 0.0659 | O37: 0.0659 | P37: 0.0659 | Q37: 0.0659 | R37: 0.0659 | S37: 0.0659 | T37: 0.0659 | U37: 0.0659 | V37: 0.0659 | W37: 0.0659 | X37: 0.0659 | Y37: 0.0659 | Z37: 0.0659 | AA37: 0.0659 | AB37: 0.0659 | AC37: 0.0659 | AD37: 0.0659 | AE37: 0.0659 | AF37: 0.0659 | AG37: 0.0659 | AH37: 0.0659 | AI37: 0.0659 | AJ37: 0.001
A38: Total | B38: Food Industry: Combined Heat and Power: Generating Capacity: Total: Low economic growth | C38: 36-AEO2022.39.lowmacro-d011222a | D38: GW | F38: 1.758134 | G38: 1.773006 | H38: 1.783223 | I38: 1.790968 | J38: 1.798055 | K38: 1.804651 | L38: 1.811112 | M38: 1.817302 | N38: 1.82331 | O38: 1.829065 | P38: 1.834744 | Q38: 1.839005 | R38: 1.84324 | S38: 1.847437 | T38: 1.851584 | U38: 1.855773 | V38: 1.860024 | W38: 1.864336 | X38: 1.868582 | Y38: 1.872981 | Z38: 1.877355 | AA38: 1.881788 | AB38: 1.886318 | AC38: 1.890907 | AD38: 1.895537 | AE38: 1.90023 | AF38: 1.905014 | AG38: 1.909863 | AH38: 1.914781 | AI38: 1.919822 | AJ38: 0.003
A39: Net Generation (billion kilowatthours) | C39: 36-AEO2022.40.
A40: Petroleum | B40: Food Industry: Combined Heat and Power: Net Generation: Petroleum: Low economic growth | C40: 36-AEO2022.41.lowmacro-d011222a | D40: BkWh | F40: 0.122866 | G40: 0.122866 | H40: 0.122866 | I40: 0.122866 | J40: 0.122866 | K40: 0.122866 | L40: 0.122866 | M40: 0.122866 | N40: 0.122866 | O40: 0.122866 | P40: 0.122866 | Q40: 0.122866 | R40: 0.122866 | S40: 0.122866 | T40: 0.122866 | U40: 0.122866 | V40: 0.122866 | W40: 0.122866 | X40: 0.122866 | Y40: 0.122866 | Z40: 0.122866 | AA40: 0.122866 | AB40: 0.122866 | AC40: 0.122866 | AD40: 0.122866 | AE40: 0.122866 | AF40: 0.122866 | AG40: 0.122866 | AH40: 0.122866 | AI40: 0.122866 | AJ40: 0
A41: Natural Gas | B41: Food Industry: Combined Heat and Power: Net Generation: Natural Gas: Low economic growth | C41: 36-AEO2022.42.lowmacro-d011222a | D41: BkWh | F41: 2.315639 | G41: 2.362228 | H41: 2.400343 | I41: 2.429334 | J41: 2.456003 | K41: 2.480944 | L41: 2.505451 | M41: 2.529023 | N41: 2.551973 | O41: 2.574018 | P41: 2.595834 | Q41: 2.612425 | R41: 2.628969 | S41: 2.645415 | T41: 2.661732 | U41: 2.67828 | V41: 2.695137 | W41: 2.712297 | X41: 2.729274 | Y41: 2.746914 | Z41: 2.76452 | AA41: 2.782422 | AB41: 2.800749 | AC41: 2.819367 | AD41: 2.838193 | AE41: 2.857302 | AF41: 2.876815 | AG41: 2.89663 | AH41: 2.916764 | AI41: 2.937438 | AJ41: 0.008
A42: Coal | B42: Food Industry: Combined Heat and Power: Net Generation: Coal: Low economic growth | C42: 36-AEO2022.43.lowmacro-d011222a | D42: BkWh | F42: 3.287625 | G42: 3.287625 | H42: 3.287625 | I42: 3.287625 | J42: 3.287625 | K42: 3.287625 | L42: 3.287625 | M42: 3.287625 | N42: 3.287625 | O42: 3.287625 | P42: 3.287625 | Q42: 3.287625 | R42: 3.287625 | S42: 3.287625 | T42: 3.287625 | U42: 3.287625 | V42: 3.287625 | W42: 3.287625 | X42: 3.287625 | Y42: 3.287625 | Z42: 3.287625 | AA42: 3.287625 | AB42: 3.287625 | AC42: 3.287625 | AD42: 3.287625 | AE42: 3.287625 | AF42: 3.287625 | AG42: 3.287625 | AH42: 3.287625 | AI42: 3.287625 | AJ42: 0
A43: Other | B43: Food Industry: Combined Heat and Power: Net Generation: Other: Low economic growth | C43: 36-AEO2022.44.lowmacro-d011222a | D43: BkWh | F43: 0.18137 | G43: 0.185414 | H43: 0.185414 | I43: 0.185414 | J43: 0.185414 | K43: 0.185414 | L43: 0.185414 | M43: 0.185414 | N43: 0.185414 | O43: 0.185414 | P43: 0.185414 | Q43: 0.185414 | R43: 0.185414 | S43: 0.185414 | T43: 0.185414 | U43: 0.185414 | V43: 0.185414 | W43: 0.185414 | X43: 0.185414 | Y43: 0.185414 | Z43: 0.185414 | AA43: 0.185414 | AB43: 0.185414 | AC43: 0.185414 | AD43: 0.185414 | AE43: 0.185414 | AF43: 0.185414 | AG43: 0.185414 | AH43: 0.185414 | AI43: 0.185414 | AJ43: 0.001
A44: Total | B44: Food Industry: Combined Heat and Power: Net Generation: Total: Low economic growth | C44: 36-AEO2022.45.lowmacro-d011222a | D44: BkWh | F44: 5.9075 | G44: 5.958132 | H44: 5.996248 | I44: 6.025239 | J44: 6.051908 | K44: 6.076849 | L44: 6.101356 | M44: 6.124928 | N44: 6.147878 | O44: 6.169923 | P44: 6.191739 | Q44: 6.208329 | R44: 6.224875 | S44: 6.24132 | T44: 6.257636 | U44: 6.274185 | V44: 6.291042 | W44: 6.308201 | X44: 6.325179 | Y44: 6.342819 | Z44: 6.360425 | AA44: 6.378325 | AB44: 6.396654 | AC44: 6.415272 | AD44: 6.434099 | AE44: 6.453207 | AF44: 6.47272 | AG44: 6.492535 | AH44: 6.512668 | AI44: 6.533342 | AJ44: 0.003
A45: Disposition | C45: 36-AEO2022.46.
A46: Sales to the Grid | B46: Food Industry: Combined Heat and Power: Net Generation: Sales to the Grid: Low economic growth | C46: 36-AEO2022.47.lowmacro-d011222a | D46: BkWh | F46: 0.116702 | G46: 0.118278 | H46: 0.11952 | I46: 0.120466 | J46: 0.121335 | K46: 0.122148 | L46: 0.122947 | M46: 0.123715 | N46: 0.124464 | O46: 0.125182 | P46: 0.125893 | Q46: 0.126434 | R46: 0.126974 | S46: 0.12751 | T46: 0.128042 | U46: 0.128581 | V46: 0.129131 | W46: 0.12969 | X46: 0.130244 | Y46: 0.130819 | Z46: 0.131393 | AA46: 0.131976 | AB46: 0.132574 | AC46: 0.133181 | AD46: 0.133794 | AE46: 0.134417 | AF46: 0.135053 | AG46: 0.135699 | AH46: 0.136356 | AI46: 0.13703 | AJ46: 0.006
A47: Generation for Own Use | B47: Food Industry: Combined Heat and Power: Net Generation: Generation for Own Use: Low economic growth | C47: 36-AEO2022.48.lowmacro-d011222a | D47: BkWh | F47: 5.790798 | G47: 5.839854 | H47: 5.876727 | I47: 5.904773 | J47: 5.930573 | K47: 5.954701 | L47: 5.978408 | M47: 6.001213 | N47: 6.023414 | O47: 6.044741 | P47: 6.065845 | Q47: 6.081895 | R47: 6.097902 | S47: 6.11381 | T47: 6.129594 | U47: 6.145604 | V47: 6.161911 | W47: 6.178511 | X47: 6.194935 | Y47: 6.212 | Z47: 6.229032 | AA47: 6.246349 | AB47: 6.264081 | AC47: 6.282091 | AD47: 6.300304 | AE47: 6.318789 | AF47: 6.337666 | AG47: 6.356835 | AH47: 6.376312 | AI47: 6.396313 | AJ47: 0.003

Sheet AEO T25 Food 2022
B1: ref2022.d011222a | C1: 2021 | D1: 2022 | E1: 2023 | F1: 2024 | G1: 2025 | H1: 2026 | I1: 2027 | J1: 2028 | K1: 2029 | L1: 2030 | M1: 2031 | N1: 2032 | O1: 2033 | P1: 2034 | Q1: 2035 | R1: 2036 | S1: 2037 | T1: 2038 | U1: 2039 | V1: 2040 | W1: 2041 | X1: 2042 | Y1: 2043 | Z1: 2044 | AA1: 2045 | AB1: 2046 | AC1: 2047 | AD1: 2048 | AE1: 2049 | AF1: 2050
C3: Report | D3: Annual Energy Outlook 2022
C4: Scenario | D4: ref2022 | G4: Reference
C5: Datekey | D5: d011222a
C6: Release Date | E6: March 2022
A10: IFD000 | B10: 25. Food Industry Energy Consumption | AG10: Average
AG11: Annual
AG12: Change
B13: Shipments & Energy Consumption | C13: 2021 | D13: 2022 | E13: 2023 | F13: 2024 | G13: 2025 | H13: 2026 | I13: 2027 | J13: 2028 | K13: 2029 | L13: 2030 | M13: 2031 | N13: 2032 | O13: 2033 | P13: 2034 | Q13: 2035 | R13: 2036 | S13: 2037 | T13: 2038 | U13: 2039 | V13: 2040 | W13: 2041 | X13: 2042 | Y13: 2043 | Z13: 2044 | AA13: 2045 | AB13: 2046 | AC13: 2047 | AD13: 2048 | AE13: 2049 | AF13: 2050 | AG13: 2051
A15: IFD000:ba_ValueofShipme | B15: Value of Shipments (billion 2012 dollars) | C15: ='AEO T25 Food 2022 Raw'!F6 -> 951.64435 | D15: ='AEO T25 Food 2022 Raw'!G6 -> 968.1377 | E15: ='AEO T25 Food 2022 Raw'!H6 -> 969.99872 | F15: ='AEO T25 Food 2022 Raw'!I6 -> 974.52918 | G15: ='AEO T25 Food 2022 Raw'!J6 -> 980.4978 | H15: ='AEO T25 Food 2022 Raw'!K6 -> 986.57391 | I15: ='AEO T25 Food 2022 Raw'!L6 -> 993.19183 | J15: ='AEO T25 Food 2022 Raw'!M6 -> 999.98218 | ... AG15: ='AEO T25 Food 2022 Raw'!AJ6 -> 0.005
B17: Energy Consumption (trillion Btu) 1/
A18: IFD000:ca_ResidualOil | B18: Residual Fuel Oil | C18: ='AEO T25 Food 2022 Raw'!F8 -> 0 | D18: ='AEO T25 Food 2022 Raw'!G8 -> 0 | E18: ='AEO T25 Food 2022 Raw'!H8 -> 0 | F18: ='AEO T25 Food 2022 Raw'!I8 -> 0 | G18: ='AEO T25 Food 2022 Raw'!J8 -> 0 | H18: ='AEO T25 Food 2022 Raw'!K8 -> 0 | I18: ='AEO T25 Food 2022 Raw'!L8 -> 0 | J18: ='AEO T25 Food 2022 Raw'!M8 -> 0 | ... AG18: ='AEO T25 Food 2022 Raw'!AJ8 -> - -
A19: IFD000:ca_DistillateOil | B19: Distillate Fuel Oil | C19: ='AEO T25 Food 2022 Raw'!F9 -> 5.627154 | D19: ='AEO T25 Food 2022 Raw'!G9 -> 5.260293 | E19: ='AEO T25 Food 2022 Raw'!H9 -> 5.331036 | F19: ='AEO T25 Food 2022 Raw'!I9 -> 5.121982 | G19: ='AEO T25 Food 2022 Raw'!J9 -> 5.125743 | H19: ='AEO T25 Food 2022 Raw'!K9 -> 5.169047 | I19: ='AEO T25 Food 2022 Raw'!L9 -> 5.212226 | J19: ='AEO T25 Food 2022 Raw'!M9 -> 5.232885 | ... AG19: ='AEO T25 Food 2022 Raw'!AJ9 -> 0
