Workbook
Name dollars_2019_2012: About!$A$105
Name dollars_2020_2012: About!$A$104
Name dollars_2021_2012: About!$A$103
Name lignite_multiplier: 'Hard Coal and Lig Multipliers'!$N$15
Name nonlignite_multiplier: 'Hard Coal and Lig Multipliers'!$N$16

Sheet About
A1: BFPaT BAU Pretax Fuel Price by Sector
A2: BFPaT BAU Fuel Tax by Sector
A4: Sources: | B4: most fuels and growth rates | D4: Tax on Petroleum Gasoline, Petroleum Diesel, Jet Fuel
B5: Energy Information Administration | D5: Energy Information Administration
B6: 2021 | D6: 2021
B7: Annual Energy Outlook 2021 | D7: Annual Energy Outlook 2021
B8: https://www.eia.gov/outlooks/aeo/tables_side.php | D8: https://www.eia.gov/outlooks/aeo/tables_side.php
B9: Table 3 (and Table 2 for industrial coal consumption fractions by coal type) | D9: Table 59
B11: biomass | D11: Tax on Non-Liquid Fuels
B12: Energy Information Administraton | D12: The Sales Tax Clearinghouse
B13: 2020 | D13: n/a
B14: State Energy Data System (SEDS): 1960-2018 (complete) | D14: FAQ
B15: https://www.eia.gov/state/seds/archive/seper2018.pdf | D15: https://thestc.com/FAQ.stm
B16: Tables ET3, ET4, ET5, and ET7 | D16: Question "What is the average sales tax nationally?"
B18: biofuel diesel | D18: Gas future prices
B19: DOE Alternative Fuels Data Center | D19: CME Group
B20: 2018 | D20: 2020
B21: Clean Cities Alternative Fuel Price Report: January 2018 | D21: Henry Hub Natural Gas Futures - Quotes
B22: https://afdc.energy.gov/files/u/publication/alternative_fuel_price_report_jan_2018.pdf | D22: https://www.cmegroup.com/trading/energy/natural-gas/natural-gas_quotes_globex.html
B23: Page 4, Table 3
B25: heat | D25: Historical Henry Hub Prices, Retail Prices, and Consumption by Sector
B26: Euroheat & Power | D26: EIA
B27: n/a | D27: 2020
B28: DHC & Statistics: United States | D28: Natural Gas: Data
B29: http://www.euroheat.org/United-States-156.aspx | D29: https://www.eia.gov/naturalgas/data.php; https://www.eia.gov/dnav/ng/ng_pri_sum_dcu_nus_a.htm
B30: "Average District Heating price in 2011" (using "Steam" rather than "Water" because most U.S. district heating systems use steam) | D30: Prices; Natural gas spot and futures prices; and Delivered to Consumers links
B32: hydrogen start year costs | D32: Historical Natural Gas Consumption by Sector
B33: California Energy Commission and California Air Resources Board | D33: Bloomberg New Energy Finance
B34: 2015 | D34: 2020
B35: Assessment of Time and Cost Needed to Attain 100 Hydrogen Refueling Stations in California | D35: Hydrogen Economy Outlook: Key Messages
B36: https://ww2.energy.ca.gov/2015publications/CEC-600-2015-016/CEC-600-2015-016.pdf | D36: https://data.bloomberglp.com/professional/sites/24/BNEF-Hydrogen-Economy-Outlook-Key-Messages-30-Mar-2020.pdf
B37: Page 57, Table 12 | D37: Page 5
B39: lignite and non-lignite price multipliers
B40: Energy Information Administration
B41: 2019
B42: Form EIA-923 detailed data
B43: https://www.eia.gov/electricity/data/eia923/
B44: Year 2018, Tab 5
A45: Notes
A47: Pre-Tax Prices
A48: This variable contains PRE-TAX fuel prices per unit energy, disaggregated by sector.
A50: BAU Fuel Taxes
A51: Separately, it also specifies the amount of BAU fuel tax per unit energy that is levied on each fuel.
A52: BAU fuel taxes include sales taxes, value-added taxes (VAT), and excise taxes, not carbon taxes.
A53: If there is a BAU Carbon Tax in the modeled region, its effect on fuel prices must not be included here.
A54: (A BAU carbon tax is specified separately in fuels/BCTR BAU Carbon Tax Rate.)
A56: BAU Fuel Subsidies
A57: All pre-tax fuel prices in this variable should incorporate the contribution of any BAU subsidies.
A58: This is because BAU subsidies are often applied far upstream of retail sales, such as subsidies for oil
A59: and gas drilling companies. Similarly, subsidies paid for electricity generation
... A102: We adjust dollars of the following years to 2012 dollars using the following conversion factors:
A103: 0.84730413 | B103: 2021 to 2012
A104: 0.88711067 | B104: 2020 to 2012
A105: 0.89805482 | B105: 2019 to 2012
A106: 0.914 | B106: 2018 to 2012; used for EIA AEO 2018 and DOE Clean Cities report
A107: 0.96868157 | B107: 2015 to 2012; used for CEC/CARB hydrogen report
A108: 1.022 | B108: 2011 to 2012; used for Euroheat and Power statistics
A109: See "cpi.xlsx" in the InputData folder for source information.
A112: Crude Oil Heat Content
A113: 5.719 | B113: million BTU / barrel (U.S.-produced crude)
A114: 6.063 | B114: million BTU / barrel (imported crude)
A115: Source: EIA AEO 2019, Appendix G, Conversion Factors
A117: For the United States EPS, we use West Texas Intermediate as our crude benchmark, as this is typical in the U.S.
A118: When adapting the EPS to other countries, using Brent crude (also available in AEO table 12) is advised, and
A119: the heat content used should be switched to the value for "imported" crude above.
A121: Municipal Solid Waste Prices
A122: Rather than costing money, companies usually pay a "tipping fee" to the processor for accepting their
A123: municipal solid waste. This would imply a negative fuel price. However, there may be extra expenses
A124: associated with sorting the waste so that only suitable MSW is combusted, while other items (such as
A125: electronics and batteries, which should not have been part of the MSW stream) don't get combusted.
A126: For simplicity, we assume that the added processing costs of dealing with MSW offset the tipping fees,
A127: resulting in a fuel cost of zero. (This assumes MSW power plants get all their profit from selling power,
A128: and they break even on the tipping fees.)
... A140: Other Conversions
A142: BTU per Gallon Liquid Fuels | D142: Source:
A143: gasoline | B143: 120476 | D143: EIA | E143: Energy Explained: Units and Calculators
A144: diesel | B144: 137452 | D144: 2017 | E144: https://www.eia.gov/energyexplained/index.cfm/index.cfm?page=about_energy_units
A145: heating oil | B145: 138500
A146: jet fuel | B146: 135000

Sheet AEO 2022 2
B1: ref2022.d011222a | C1: 2021 | D1: 2022 | E1: 2023 | F1: 2024 | G1: 2025 | H1: 2026 | I1: 2027 | J1: 2028 | K1: 2029 | L1: 2030 | M1: 2031 | N1: 2032 | O1: 2033 | P1: 2034 | Q1: 2035 | R1: 2036 | S1: 2037 | T1: 2038 | U1: 2039 | V1: 2040 | W1: 2041 | X1: 2042 | Y1: 2043 | Z1: 2044 | AA1: 2045 | AB1: 2046 | AC1: 2047 | AD1: 2048 | AE1: 2049 | AF1: 2050
C3: Report | D3: Annual Energy Outlook 2022
C4: Scenario | D4: ref2022 | G4: Reference
C5: Datekey | D5: d011222a
C6: Release Date | E6: March 2022
A10: QUA000 | B10: 2. Energy Consumption by Sector and Source | AG10: Average
B11: (quadrillion Btu, unless otherwise noted) | AG11: Annual
AG12: Change
B13: Sector and Source | C13: 2021 | D13: 2022 | E13: 2023 | F13: 2024 | G13: 2025 | H13: 2026 | I13: 2027 | J13: 2028 | K13: 2029 | L13: 2030 | M13: 2031 | N13: 2032 | O13: 2033 | P13: 2034 | Q13: 2035 | R13: 2036 | S13: 2037 | T13: 2038 | U13: 2039 | V13: 2040 | W13: 2041 | X13: 2042 | Y13: 2043 | Z13: 2044 | AA13: 2045 | AB13: 2046 | AC13: 2047 | AD13: 2048 | AE13: 2049 | AF13: 2050 | AG13: 2021–2050
B15: Residential
A16: QUA000:ca_LiquefiedPetr | B16: Propane | C16: 0.478688 | D16: 0.482703 | E16: 0.464288 | F16: 0.460531 | G16: 0.457639 | H16: 0.454679 | I16: 0.451559 | J16: 0.448273 | K16: 0.444886 | L16: 0.44168 | M16: 0.438529 | N16: 0.435397 | O16: 0.432479 | P16: 0.429935 | Q16: 0.427832 | R16: 0.426087 | S16: 0.424476 | T16: 0.422915 | U16: 0.421446 | V16: 0.42005 | W16: 0.418672 | X16: 0.417295 | Y16: 0.415866 | Z16: 0.414476 | AA16: 0.413321 | AB16: 0.412523 | AC16: 0.412023 | AD16: 0.411646 | AE16: 0.411273 | AF16: 0.410956 | AG16: -0.005247
A17: QUA000:ca_DistillateFue | B17: Distillate Fuel Oil 1/ | C17: 0.419546 | D17: 0.441378 | E17: 0.414719 | F17: 0.404789 | G17: 0.394743 | H17: 0.385008 | I17: 0.375941 | J17: 0.368066 | K17: 0.36113 | L17: 0.355018 | M17: 0.348935 | N17: 0.342917 | O17: 0.337075 | P17: 0.331558 | Q17: 0.326194 | R17: 0.320915 | S17: 0.315659 | T17: 0.31053 | U17: 0.305559 | V17: 0.300633 | W17: 0.295725 | X17: 0.290945 | Y17: 0.286024 | Z17: 0.281041 | AA17: 0.276311 | AB17: 0.271616 | AC17: 0.26707 | AD17: 0.262644 | AE17: 0.258195 | AF17: 0.253878 | AG17: -0.017172
A18: QUA000:ca_PetroleumSubt | B18: Petroleum and Other Liquids Subtotal | C18: 0.898234 | D18: 0.924081 | E18: 0.879007 | F18: 0.86532 | G18: 0.852382 | H18: 0.839687 | I18: 0.8275 | J18: 0.816339 | K18: 0.806015 | L18: 0.796699 | M18: 0.787464 | N18: 0.778314 | O18: 0.769554 | P18: 0.761493 | Q18: 0.754026 | R18: 0.747001 | S18: 0.740135 | T18: 0.733445 | U18: 0.727005 | V18: 0.720684 | W18: 0.714397 | X18: 0.70824 | Y18: 0.70189 | Z18: 0.695517 | AA18: 0.689632 | AB18: 0.684139 | AC18: 0.679093 | AD18: 0.674289 | AE18: 0.669469 | AF18: 0.664835 | AG18: -0.010322
A19: QUA000:ca_NaturalGas | B19: Natural Gas | C19: 5.007376 | D19: 5.070196 | E19: 4.99077 | F19: 5.003871 | G19: 5.018683 | H19: 5.024077 | I19: 5.023698 | J19: 5.014405 | K19: 4.998899 | L19: 4.983529 | M19: 4.969099 | N19: 4.951568 | O19: 4.934161 | P19: 4.920165 | Q19: 4.911035 | R19: 4.90425 | S19: 4.896574 | T19: 4.888241 | U19: 4.879435 | V19: 4.871953 | W19: 4.863002 | X19: 4.855389 | Y19: 4.849878 | Z19: 4.845332 | AA19: 4.840716 | AB19: 4.835385 | AC19: 4.829076 | AD19: 4.821843 | AE19: 4.813109 | AF19: 4.803506 | AG19: -0.001432
A20: QUA000:ca_RenewableEner | B20: Renewable Energy 2/ | C20: 0.463756 | D20: 0.48347 | E20: 0.450565 | F20: 0.445645 | G20: 0.442627 | H20: 0.439965 | I20: 0.436402 | J20: 0.431361 | K20: 0.425031 | L20: 0.417201 | M20: 0.409955 | N20: 0.403153 | O20: 0.395951 | P20: 0.388133 | Q20: 0.380095 | R20: 0.372198 | S20: 0.365149 | T20: 0.358661 | U20: 0.352049 | V20: 0.346263 | W20: 0.340993 | X20: 0.335841 | Y20: 0.331453 | Z20: 0.327786 | AA20: 0.323771 | AB20: 0.320077 | AC20: 0.315878 | AD20: 0.311247 | AE20: 0.306821 | AF20: 0.302059 | AG20: -0.014675
A21: QUA000:ca_Electricity | B21: Purchased Electricity | C21: 5.085111 | D21: 4.988574 | E21: 5.101863 | F21: 5.136075 | G21: 5.167903 | H21: 5.190618 | I21: 5.207037 | J21: 5.22809 | K21: 5.249576 | L21: 5.270422 | M21: 5.291863 | N21: 5.31704 | O21: 5.344032 | P21: 5.370875 | Q21: 5.406477 | R21: 5.448595 | S21: 5.494287 | T21: 5.540269 | U21: 5.586945 | V21: 5.627694 | W21: 5.668567 | X21: 5.710461 | Y21: 5.75561 | Z21: 5.803448 | AA21: 5.850867 | AB21: 5.903627 | AC21: 5.955761 | AD21: 6.009111 | AE21: 6.063807 | AF21: 6.124871 | AG21: 0.006436
A22: QUA000:ca_DeliveredEner | B22: Delivered Energy | C22: 11.454478 | D22: 11.466321 | E22: 11.422204 | F22: 11.450912 | G22: 11.481594 | H22: 11.494348 | I22: 11.494637 | J22: 11.490195 | K22: 11.47952 | L22: 11.467852 | M22: 11.458383 | N22: 11.450075 | O22: 11.4437 | P22: 11.440667 | Q22: 11.451631 | R22: 11.472043 | S22: 11.496145 | T22: 11.520617 | U22: 11.545433 | V22: 11.566592 | W22: 11.58696 | X22: 11.609931 | Y22: 11.63883 | Z22: 11.672083 | AA22: 11.704986 | AB22: 11.743228 | AC22: 11.779808 | AD22: 11.816492 | AE22: 11.853207 | AF22: 11.89527 | AG22: 0.001303
A23: QUA000:ca_ElectricityRe | B23: Electricity Related Losses | C23: 9.377542 | D23: 9.196331 | E23: 9.314765 | F23: 9.184469 | G23: 9.087095 | H23: 9.024928 | I23: 8.956861 | J23: 8.875485 | K23: 8.864312 | L23: 8.860741 | M23: 8.867586 | N23: 8.875726 | O23: 8.84233 | P23: 8.842175 | Q23: 8.850697 | R23: 8.882401 | S23: 8.918847 | T23: 8.951853 | U23: 9.000834 | V23: 9.040874 | W23: 9.082237 | X23: 9.119998 | Y23: 9.157075 | Z23: 9.203964 | AA23: 9.249299 | AB23: 9.290339 | AC23: 9.335984 | AD23: 9.39344 | AE23: 9.446524 | AF23: 9.518768 | AG23: 0.000516
A24: QUA000:ca_Total | B24: Total | C24: 20.83202 | D24: 20.662651 | E24: 20.736969 | F24: 20.635382 | G24: 20.568689 | H24: 20.519276 | I24: 20.451496 | J24: 20.365681 | K24: 20.343832 | L24: 20.328592 | M24: 20.32597 | N24: 20.325802 | O24: 20.28603 | P24: 20.282843 | Q24: 20.302326 | R24: 20.354445 | S24: 20.414993 | T24: 20.472469 | U24: 20.546267 | V24: 20.607466 | W24: 20.669197 | X24: 20.729929 | Y24: 20.795906 | Z24: 20.876047 | AA24: 20.954285 | AB24: 21.033567 | AC24: 21.115791 | AD24: 21.209932 | AE24: 21.29973 | AF24: 21.41404 | AG24: 0.000951
B26: Commercial
A27: QUA000:da_LiquefiedPetr | B27: Propane | C27: 0.17859 | D27: 0.18783 | E27: 0.186579 | F27: 0.184479 | G27: 0.18239 | H27: 0.180182 | I27: 0.18182 | J27: 0.18334 | K27: 0.18487 | L27: 0.18648 | M27: 0.188105 | N27: 0.189644 | O27: 0.191298 | P27: 0.193028 | Q27: 0.194755 | R27: 0.196456 | S27: 0.198034 | T27: 0.199594 | U27: 0.201224 | V27: 0.202767 | W27: 0.20432 | X27: 0.205891 | Y27: 0.207382 | Z27: 0.20892 | AA27: 0.210623 | AB27: 0.212427 | AC27: 0.214246 | AD27: 0.216022 | AE27: 0.217762 | AF27: 0.219574 | AG27: 0.007149
A28: QUA000:da_MotorGasoline | B28: Motor Gasoline 3/ | C28: 0.35056 | D28: 0.35151 | E28: 0.353471 | F28: 0.353966 | G28: 0.354745 | H28: 0.355503 | I28: 0.356187 | J28: 0.356588 | K28: 0.357041 | L28: 0.357326 | M28: 0.357812 | N28: 0.357763 | O28: 0.358197 | P28: 0.358654 | Q28: 0.359099 | R28: 0.359576 | S28: 0.360009 | T28: 0.360383 | U28: 0.360918 | V28: 0.361148 | W28: 0.36152 | X28: 0.361853 | Y28: 0.362139 | Z28: 0.362525 | AA28: 0.362952 | AB28: 0.363336 | AC28: 0.363789 | AD28: 0.36427 | AE28: 0.364716 | AF28: 0.365384 | AG28: 0.001429
A29: QUA000:da_Kerosene | B29: Kerosene | C29: 0.00185 | D29: 0.00174 | E29: 0.002293 | F29: 0.001994 | G29: 0.001895 | H29: 0.00178 | I29: 0.001731 | J29: 0.001694 | K29: 0.00167 | L29: 0.001676 | M29: 0.001625 | N29: 0.001531 | O29: 0.001523 | P29: 0.001517 | Q29: 0.001507 | R29: 0.001494 | S29: 0.001464 | T29: 0.001443 | U29: 0.001436 | V29: 0.001397 | W29: 0.001371 | X29: 0.00136 | Y29: 0.001324 | Z29: 0.001289 | AA29: 0.001286 | AB29: 0.001265 | AC29: 0.001267 | AD29: 0.001271 | AE29: 0.00126 | AF29: 0.001271 | AG29: -0.012861
A30: QUA000:da_DistillateFue | B30: Distillate Fuel Oil | C30: 0.31439 | D30: 0.32436 | E30: 0.322703 | F30: 0.320352 | G30: 0.31806 | H30: 0.315785 | I30: 0.316033 | J30: 0.315139 | K30: 0.313409 | L30: 0.311615 | M30: 0.309806 | N30: 0.307297 | O30: 0.305038 | P30: 0.303233 | Q30: 0.301571 | R30: 0.299843 | S30: 0.297911 | T30: 0.295842 | U30: 0.293922 | V30: 0.291693 | W30: 0.289451 | X30: 0.287349 | Y30: 0.285039 | Z30: 0.282571 | AA30: 0.280451 | AB30: 0.278366 | AC30: 0.276538 | AD30: 0.274924 | AE30: 0.273241 | AF30: 0.271715 | AG30: -0.005018
A31: QUA000:da_ResidualFuel | B31: Residual Fuel Oil | C31: 0.0019 | D31: 0.0019 | E31: 0.002376 | F31: 0.002199 | G31: 0.002339 | H31: 0.002517 | I31: 0.002365 | J31: 0.002365 | K31: 0.002377 | L31: 0.002376 | M31: 0.002383 | N31: 0.002373 | O31: 0.002384 | P31: 0.00239 | Q31: 0.00242 | R31: 0.00244 | S31: 0.002467 | T31: 0.002477 | U31: 0.002522 | V31: 0.002438 | W31: 0.00244 | X31: 0.002461 | Y31: 0.002443 | Z31: 0.002426 | AA31: 0.002446 | AB31: 0.002447 | AC31: 0.002469 | AD31: 0.002502 | AE31: 0.002518 | AF31: 0.002566 | AG31: 0.010417
A32: QUA000:da_PetroleumSubt | B32: Petroleum and Other Liquids Subtotal | C32: 0.84729 | D32: 0.86734 | E32: 0.867423 | F32: 0.86299 | G32: 0.859428 | H32: 0.855766 | I32: 0.858137 | J32: 0.859126 | K32: 0.859367 | L32: 0.859474 | M32: 0.859731 | N32: 0.858608 | O32: 0.85844 | P32: 0.858822 | Q32: 0.859353 | R32: 0.859809 | S32: 0.859885 | T32: 0.859738 | U32: 0.860021 | V32: 0.859443 | W32: 0.859103 | X32: 0.858913 | Y32: 0.858327 | Z32: 0.85773 | AA32: 0.857758 | AB32: 0.857841 | AC32: 0.858308 | AD32: 0.85899 | AE32: 0.859497 | AF32: 0.86051 | AG32: 0.000534
A33: QUA000:da_NaturalGas | B33: Natural Gas | C33: 3.481153 | D33: 3.618408 | E33: 3.562652 | F33: 3.568658 | G33: 3.578824 | H33: 3.577957 | I33: 3.593081 | J33: 3.596354 | K33: 3.591724 | L33: 3.587628 | M33: 3.588656 | N33: 3.586138 | O33: 3.582798 | P33: 3.583007 | Q33: 3.588976 | R33: 3.5977 | S33: 3.603375 | T33: 3.605938 | U33: 3.606794 | V33: 3.608207 | W33: 3.608019 | X33: 3.610833 | Y33: 3.616942 | Z33: 3.623439 | AA33: 3.630058 | AB33: 3.635484 | AC33: 3.639474 | AD33: 3.642248 | AE33: 3.642725 | AF33: 3.642333 | AG33: 0.001562
A34: QUA000:da_Coal | B34: Coal | C34: 0.01575 | D34: 0.01449 | E34: 0.015575 | F34: 0.015605 | G34: 0.015098 | H34: 0.014739 | I34: 0.014763 | J34: 0.01474 | K34: 0.014793 | L34: 0.014846 | M34: 0.015139 | N34: 0.014936 | O34: 0.015003 | P34: 0.015091 | Q34: 0.015483 | R34: 0.015631 | S34: 0.015763 | T34: 0.01586 | U34: 0.015857 | V34: 0.015841 | W34: 0.01585 | X34: 0.016514 | Y34: 0.016906 | Z34: 0.016929 | AA34: 0.016957 | AB34: 0.017001 | AC34: 0.017139 | AD34: 0.017267 | AE34: 0.017347 | AF34: 0.017454 | AG34: 0.003548
A35: QUA000:da_RenewableEner | B35: Renewable Energy 4/ | C35: 0.124386 | D35: 0.124386 | E35: 0.124386 | F35: 0.124386 | G35: 0.124386 | H35: 0.124386 | I35: 0.124386 | J35: 0.124386 | K35: 0.124386 | L35: 0.124386 | M35: 0.124386 | N35: 0.124386 | O35: 0.124386 | P35: 0.124386 | Q35: 0.124386 | R35: 0.124386 | S35: 0.124386 | T35: 0.124386 | U35: 0.124386 | V35: 0.124386 | W35: 0.124386 | X35: 0.124386 | Y35: 0.124386 | Z35: 0.124386 | AA35: 0.124386 | AB35: 0.124386 | AC35: 0.124386 | AD35: 0.124386 | AE35: 0.124386 | AF35: 0.124386 | AG35: 0
A36: QUA000:da_Electricity | B36: Purchased Electricity | C36: 4.499543 | D36: 4.539952 | E36: 4.572258 | F36: 4.560517 | G36: 4.554118 | H36: 4.53431 | I36: 4.538095 | J36: 4.54117 | K36: 4.545389 | L36: 4.54625 | M36: 4.552204 | N36: 4.561535 | O36: 4.571701 | P36: 4.585947 | Q36: 4.610533 | R36: 4.635308 | S36: 4.658102 | T36: 4.685641 | U36: 4.712861 | V36: 4.733045 | W36: 4.75976 | X36: 4.785551 | Y36: 4.817082 | Z36: 4.851602 | AA36: 4.885552 | AB36: 4.92259 | AC36: 4.962389 | AD36: 5.003931 | AE36: 5.045875 | AF36: 5.093176 | AG36: 0.004282
A37: QUA000:da_DeliveredEner | B37: Delivered Energy | C37: 8.968122 | D37: 9.164577 | E37: 9.142294 | F37: 9.132156 | G37: 9.131854 | H37: 9.107158 | I37: 9.128462 | J37: 9.135776 | K37: 9.135661 | L37: 9.132584 | M37: 9.140117 | N37: 9.145603 | O37: 9.152327 | P37: 9.167253 | Q37: 9.198732 | R37: 9.232837 | S37: 9.261511 | T37: 9.291564 | U37: 9.31992 | V37: 9.340922 | W37: 9.367119 | X37: 9.396197 | Y37: 9.433643 | Z37: 9.474088 | AA37: 9.514711 | AB37: 9.557301 | AC37: 9.601694 | AD37: 9.64682 | AE37: 9.689831 | AF37: 9.737859 | AG37: 0.002843
A38: QUA000:da_ElectricityRe | B38: Electricity Related Losses | C38: 8.297687 | D38: 8.369306 | E38: 8.347835 | F38: 8.15524 | G38: 8.007833 | H38: 7.883806 | I38: 7.806182 | J38: 7.709332 | K38: 7.675239 | L38: 7.643247 | M38: 7.628137 | N38: 7.614562 | O38: 7.564417 | P38: 7.549934 | Q38: 7.547693 | R38: 7.556566 | S38: 7.561472 | T38: 7.570962 | U38: 7.592642 | V38: 7.603622 | W38: 7.626137 | X38: 7.642853 | Y38: 7.663895 | Z38: 7.694386 | AA38: 7.723289 | AB38: 7.746513 | AC38: 7.778818 | AD38: 7.822142 | AE38: 7.860735 | AF38: 7.915395 | AG38: -0.001625
A39: QUA000:da_Total | B39: Total | C39: 17.265808 | D39: 17.533882 | E39: 17.490128 | F39: 17.287395 | G39: 17.139687 | H39: 16.990963 | I39: 16.934645 | J39: 16.845108 | K39: 16.8109 | L39: 16.775831 | M39: 16.768253 | N39: 16.760166 | O39: 16.716743 | P39: 16.717186 | Q39: 16.746426 | R39: 16.789402 | S39: 16.822983 | T39: 16.862526 | U39: 16.912561 | V39: 16.944546 | W39: 16.993256 | X39: 17.039051 | Y39: 17.097538 | Z39: 17.168474 | AA39: 17.238001 | AB39: 17.303814 | AC39: 17.380512 | AD39: 17.468962 | AE39: 17.550566 | AF39: 17.653254 | AG39: 0.000766
B41: Industrial 5/
A42: QUA000:ea_LiquefiedPetr | B42: Liquefied Petroleum Gases and Other 6/ | C42: 3.525503 | D42: 3.659933 | E42: 3.826037 | F42: 3.807156 | G42: 3.885298 | H42: 3.954717 | I42: 3.994848 | J42: 4.020617 | K42: 4.024005 | L42: 4.03884 | M42: 4.080049 | N42: 4.155496 | O42: 4.201034 | P42: 4.221895 | Q42: 4.242743 | R42: 4.270905 | S42: 4.30229 | T42: 4.326283 | U42: 4.35443 | V42: 4.366281 | W42: 4.383568 | X42: 4.407776 | Y42: 4.446388 | Z42: 4.447725 | AA42: 4.455647 | AB42: 4.511288 | AC42: 4.532683 | AD42: 4.502203 | AE42: 4.504282 | AF42: 4.568481 | AG42: 0.008977
A43: QUA000:ea_MotorGasoline | B43: Motor Gasoline 3/ | C43: 0.251457 | D43: 0.245233 | E43: 0.245962 | F43: 0.24949 | G43: 0.252653 | H43: 0.254981 | I43: 0.256543 | J43: 0.259321 | K43: 0.261791 | L43: 0.263735 | M43: 0.265413 | N43: 0.269782 | O43: 0.273194 | P43: 0.27352 | Q43: 0.273713 | R43: 0.274228 | S43: 0.276022 | T43: 0.278566 | U43: 0.281453 | V43: 0.283822 | W43: 0.285497 | X43: 0.287173 | Y43: 0.288766 | Z43: 0.290012 | AA43: 0.29119 | AB43: 0.292838 | AC43: 0.294271 | AD43: 0.29565 | AE43: 0.297591 | AF43: 0.300178 | AG43: 0.006126
A44: QUA000:ea_DistillateFue | B44: Distillate Fuel Oil | C44: 1.155744 | D44: 1.128442 | E44: 1.126598 | F44: 1.131399 | G44: 1.139035 | H44: 1.144452 | I44: 1.146798 | J44: 1.154044 | K44: 1.160566 | L44: 1.165561 | M44: 1.170175 | N44: 1.185123 | O44: 1.196447 | P44: 1.196179 | Q44: 1.195582 | R44: 1.196565 | S44: 1.202659 | T44: 1.211916 | U44: 1.22198 | V44: 1.229472 | W44: 1.235178 | X44: 1.241056 | Y44: 1.246023 | Z44: 1.249249 | AA44: 1.252306 | AB44: 1.25728 | AC44: 1.261749 | AD44: 1.266001 | AE44: 1.272091 | AF44: 1.281459 | AG44: 0.003567
A45: QUA000:ea_ResidualFuel | B45: Residual Fuel Oil | C45: 0.041609 | D45: 0.038239 | E45: 0.038356 | F45: 0.035517 | G45: 0.034044 | H45: 0.034206 | I45: 0.034337 | J45: 0.035531 | K45: 0.036764 | L45: 0.037789 | M45: 0.038746 | N45: 0.039363 | O45: 0.040495 | P45: 0.04097 | Q45: 0.041007 | R45: 0.041183 | S45: 0.041764 | T45: 0.042273 | U45: 0.043174 | V45: 0.042564 | W45: 0.04309 | X45: 0.043467 | Y45: 0.042769 | Z45: 0.042051 | AA45: 0.041564 | AB45: 0.041169 | AC45: 0.041241 | AD45: 0.041506 | AE45: 0.041357 | AF45: 0.041823 | AG45: 0.000177
A46: QUA000:ea_Petrochemical | B46: Petrochemical Feedstocks | C46: 0.583656 | D46: 0.563777 | E46: 0.6309 | F46: 0.55 | G46: 0.55 | H46: 0.55 | I46: 0.55 | J46: 0.55 | K46: 0.55 | L46: 0.55 | M46: 0.55 | N46: 0.55 | O46: 0.55 | P46: 0.55 | Q46: 0.55 | R46: 0.55 | S46: 0.55 | T46: 0.55 | U46: 0.55 | V46: 0.55 | W46: 0.55 | X46: 0.55 | Y46: 0.55 | Z46: 0.55 | AA46: 0.55 | AB46: 0.55 | AC46: 0.55 | AD46: 0.55 | AE46: 0.55 | AF46: 0.55 | AG46: -0.002046
A47: QUA000:ea_OtherPetroleu | B47: Other Petroleum 7/ | C47: 3.089952 | D47: 3.017606 | E47: 3.081593 | F47: 3.141184 | G47: 3.155158 | H47: 3.15898 | I47: 3.158485 | J47: 3.200037 | K47: 3.228584 | L47: 3.254435 | M47: 3.261669 | N47: 3.294676 | O47: 3.307526 | P47: 3.313891 | Q47: 3.314744 | R47: 3.3215 | S47: 3.347294 | T47: 3.353019 | U47: 3.365184 | V47: 3.332521 | W47: 3.34125 | X47: 3.334323 | Y47: 3.319442 | Z47: 3.314479 | AA47: 3.296336 | AB47: 3.288291 | AC47: 3.277879 | AD47: 3.292141 | AE47: 3.303919 | AF47: 3.302853 | AG47: 0.0023
A48: QUA000:ea_PetroleumSubt | B48: Petroleum and Other Liquids Subtotal | C48: 8.647922 | D48: 8.653232 | E48: 8.949446 | F48: 8.914747 | G48: 9.016188 | H48: 9.097336 | I48: 9.141014 | J48: 9.219549 | K48: 9.26171 | L48: 9.310361 | M48: 9.366053 | N48: 9.49444 | O48: 9.568695 | P48: 9.596455 | Q48: 9.61779 | R48: 9.654383 | S48: 9.720029 | T48: 9.762056 | U48: 9.81622 | V48: 9.80466 | W48: 9.838586 | X48: 9.863794 | Y48: 9.893388 | Z48: 9.893517 | AA48: 9.887041 | AB48: 9.940866 | AC48: 9.957825 | AD48: 9.947502 | AE48: 9.96924 | AF48: 10.044793 | AG48: 0.005177
A49: QUA000:ea_NaturalGas | B49: Natural Gas | C49: 8.579823 | D49: 8.652846 | E49: 8.529872 | F49: 8.556461 | G49: 8.618968 | H49: 8.680298 | I49: 8.681594 | J49: 8.674828 | K49: 8.657163 | L49: 8.653091 | M49: 8.654345 | N49: 8.637673 | O49: 8.640001 | P49: 8.657419 | Q49: 8.666124 | R49: 8.717266 | S49: 8.740398 | T49: 8.775434 | U49: 8.80256 | V49: 8.827866 | W49: 8.845437 | X49: 8.885086 | Y49: 8.943855 | Z49: 8.979114 | AA49: 9.010438 | AB49: 9.078405 | AC49: 9.137057 | AD49: 9.158196 | AE49: 9.191376 | AF49: 9.280467 | AG49: 0.00271
A50: QUA000:ea_NGastoLiquids | B50: Natural-Gas-to-Liquids Heat and Power | C50: 0 | D50: 0 | E50: 0 | F50: 0 | G50: 0 | H50: 0 | I50: 0 | J50: 0 | K50: 0 | L50: 0 | M50: 0 | N50: 0 | O50: 0 | P50: 0 | Q50: 0 | R50: 0 | S50: 0 | T50: 0 | U50: 0 | V50: 0 | W50: 0 | X50: 0 | Y50: 0 | Z50: 0 | AA50: 0 | AB50: 0 | AC50: 0 | AD50: 0 | AE50: 0 | AF50: 0 | AG50: --
A51: QUA000:ea_LeaseandPlant | B51: Lease and Plant Fuel 8/ | C51: 1.908455 | D51: 1.977932 | E51: 1.988711 | F51: 2.014221 | G51: 2.046336 | H51: 2.050896 | I51: 2.051069 | J51: 2.089817 | K51: 2.104321 | L51: 2.128522 | M51: 2.144954 | N51: 2.172365 | O51: 2.193179 | P51: 2.183699 | Q51: 2.184837 | R51: 2.178093 | S51: 2.172917 | T51: 2.177195 | U51: 2.195431 | V51: 2.213282 | W51: 2.209525 | X51: 2.21719 | Y51: 2.245676 | Z51: 2.259835 | AA51: 2.285115 | AB51: 2.300184 | AC51: 2.311478 | AD51: 2.324327 | AE51: 2.328741 | AF51: 2.372455 | AG51: 0.007533
A52: QUA000:ea_liquefactexp | B52: Natural Gas to Liquefy Gas for Export 9/ | C52: 0.300655 | D52: 0.352409 | E52: 0.372659 | F52: 0.376397 | G52: 0.39067 | H52: 0.391683 | I52: 0.400083 | J52: 0.417955 | K52: 0.433681 | L52: 0.450481 | M52: 0.46728 | N52: 0.485153 | O52: 0.492479 | P52: 0.492479 | Q52: 0.492479 | R52: 0.493552 | S52: 0.492479 | T52: 0.492479 | U52: 0.492479 | V52: 0.493552 | W52: 0.492479 | X52: 0.492479 | Y52: 0.492479 | Z52: 0.493552 | AA52: 0.492479 | AB52: 0.492479 | AC52: 0.492479 | AD52: 0.493552 | AE52: 0.492479 | AF52: 0.492479 | AG52: 0.017162
A53: QUA000:ea_NaturalGasSub | B53: Natural Gas Subtotal | C53: 10.788933 | D53: 10.983188 | E53: 10.891241 | F53: 10.94708 | G53: 11.055974 | H53: 11.122876 | I53: 11.132745 | J53: 11.1826 | K53: 11.195166 | L53: 11.232094 | M53: 11.266579 | N53: 11.295191 | O53: 11.32566 | P53: 11.333597 | Q53: 11.343441 | R53: 11.388911 | S53: 11.405794 | T53: 11.445107 | U53: 11.49047 | V53: 11.534699 | W53: 11.547441 | X53: 11.594755 | Y53: 11.682011 | Z53: 11.732501 | AA53: 11.788033 | AB53: 11.871068 | AC53: 11.941014 | AD53: 11.976075 | AE53: 12.012596 | AF53: 12.145401 | AG53: 0.004092
A54: QUA000:ea_Metallurgical | B54: Metallurgical Coal | C54: 0.47798 | D54: 0.477421 | E54: 0.495445 | F54: 0.481281 | G54: 0.477819 | H54: 0.491973 | I54: 0.487908 | J54: 0.484226 | K54: 0.471012 | L54: 0.462356 | M54: 0.454044 | N54: 0.45062 | O54: 0.445499 | P54: 0.444959 | Q54: 0.444015 | R54: 0.443062 | S54: 0.440091 | T54: 0.437403 | U54: 0.430178 | V54: 0.425549 | W54: 0.423099 | X54: 0.425421 | Y54: 0.429525 | Z54: 0.427211 | AA54: 0.424524 | AB54: 0.427489 | AC54: 0.425762 | AD54: 0.41617 | AE54: 0.409004 | AF54: 0.407861 | AG54: -0.005455
A55: QUA000:ea_SteamCoal | B55: Other Industrial Coal | C55: 0.485475 | D55: 0.484966 | E55: 0.462736 | F55: 0.462616 | G55: 0.462634 | H55: 0.463906 | I55: 0.463932 | J55: 0.46378 | K55: 0.462814 | L55: 0.461726 | M55: 0.460244 | N55: 0.458652 | O55: 0.457124 | P55: 0.454781 | Q55: 0.456137 | R55: 0.456703 | S55: 0.458158 | T55: 0.459741 | U55: 0.468179 | V55: 0.465954 | W55: 0.47075 | X55: 0.469374 | Y55: 0.46797 | Z55: 0.46615 | AA55: 0.464385 | AB55: 0.463206 | AC55: 0.461884 | AD55: 0.46007 | AE55: 0.458324 | AF55: 0.457233 | AG55: -0.002065
A56: QUA000:ea_CoaltoLiquids | B56: Coal-to-Liquids Heat and Power | C56: 0 | D56: 0 | E56: 0 | F56: 0 | G56: 0 | H56: 0 | I56: 0 | J56: 0 | K56: 0 | L56: 0 | M56: 0 | N56: 0 | O56: 0 | P56: 0 | Q56: 0 | R56: 0 | S56: 0 | T56: 0 | U56: 0 | V56: 0 | W56: 0 | X56: 0 | Y56: 0 | Z56: 0 | AA56: 0 | AB56: 0 | AC56: 0 | AD56: 0 | AE56: 0 | AF56: 0 | AG56: --
A57: QUA000:ea_NetCoalCokeIm | B57: Net Coal Coke Imports | C57: -0.035229 | D57: -0.023674 | E57: -0.027069 | F57: -0.025735 | G57: -0.026459 | H57: -0.026123 | I57: -0.026431 | J57: -0.026412 | K57: -0.026503 | L57: -0.026544 | M57: -0.026676 | N57: -0.026707 | O57: -0.026813 | P57: -0.026804 | Q57: -0.026705 | R57: -0.026698 | S57: -0.026697 | T57: -0.02665 | U57: -0.026722 | V57: -0.026782 | W57: -0.026614 | X57: -0.026412 | Y57: -0.026201 | Z57: -0.026257 | AA57: -0.026216 | AB57: -0.025939 | AC57: -0.0259 | AD57: -0.026205 | AE57: -0.026248 | AF57: -0.025964 | AG57: -0.010468
A58: QUA000:ea_CoalSubtotal | B58: Coal Subtotal | C58: 0.928225 | D58: 0.938712 | E58: 0.931112 | F58: 0.918162 | G58: 0.913994 | H58: 0.929756 | I58: 0.925408 | J58: 0.921594 | K58: 0.907323 | L58: 0.897539 | M58: 0.887612 | N58: 0.882565 | O58: 0.875809 | P58: 0.872935 | Q58: 0.873447 | R58: 0.873067 | S58: 0.871553 | T58: 0.870494 | U58: 0.871635 | V58: 0.864721 | W58: 0.867235 | X58: 0.868383 | Y58: 0.871295 | Z58: 0.867105 | AA58: 0.862693 | AB58: 0.864757 | AC58: 0.861746 | AD58: 0.850034 | AE58: 0.84108 | AF58: 0.83913 | AG58: -0.003474
A59: QUA000:ea_BiofuelsHeat | B59: Biofuels Heat and Coproducts | C59: 0.941453 | D59: 0.933549 | E59: 0.902314 | F59: 0.902289 | G59: 0.910224 | H59: 0.911726 | I59: 0.911999 | J59: 0.912429 | K59: 0.91952 | L59: 0.922166 | M59: 0.925975 | N59: 0.929158 | O59: 0.931774 | P59: 0.935223 | Q59: 0.940831 | R59: 0.944629 | S59: 0.949544 | T59: 0.954958 | U59: 0.969474 | V59: 0.969957 | W59: 0.978944 | X59: 0.984904 | Y59: 0.992837 | Z59: 1.009661 | AA59: 1.01937 | AB59: 1.030285 | AC59: 1.042042 | AD59: 1.054141 | AE59: 1.066841 | AF59: 1.083 | AG59: 0.004842
A60: QUA000:ea_RenewableEner | B60: Renewable Energy 10/ | C60: 1.556454 | D60: 1.566203 | E60: 1.560416 | F60: 1.565939 | G60: 1.569506 | H60: 1.558802 | I60: 1.545385 | J60: 1.532728 | K60: 1.523405 | L60: 1.517226 | M60: 1.504802 | N60: 1.49559 | O60: 1.483831 | P60: 1.472542 | Q60: 1.463529 | R60: 1.455971 | S60: 1.446149 | T60: 1.437351 | U60: 1.432416 | V60: 1.428148 | W60: 1.425063 | X60: 1.424716 | Y60: 1.423608 | Z60: 1.414471 | AA60: 1.408166 | AB60: 1.408697 | AC60: 1.41018 | AD60: 1.413463 | AE60: 1.408047 | AF60: 1.416329 | AG60: -0.003248
A61: QUA000:ea_Electricity | B61: Purchased Electricity | C61: 3.347698 | D61: 3.356424 | E61: 3.375865 | F61: 3.371822 | G61: 3.383329 | H61: 3.388169 | I61: 3.384229 | J61: 3.390302 | K61: 3.388705 | L61: 3.389802 | M61: 3.390174 | N61: 3.408104 | O61: 3.414217 | P61: 3.409991 | Q61: 3.411038 | R61: 3.417303 | S61: 3.426809 | T61: 3.436683 | U61: 3.448714 | V61: 3.45439 | W61: 3.464697 | X61: 3.479925 | Y61: 3.499164 | Z61: 3.505566 | AA61: 3.512586 | AB61: 3.536303 | AC61: 3.552395 | AD61: 3.55617 | AE61: 3.564416 | AF61: 3.590322 | AG61: 0.002416
A62: QUA000:ea_DeliveredEner | B62: Delivered Energy | C62: 26.210688 | D62: 26.431309 | E62: 26.61039 | F62: 26.620039 | G62: 26.849215 | H62: 27.008667 | I62: 27.040783 | J62: 27.159203 | K62: 27.195827 | L62: 27.269186 | M62: 27.341192 | N62: 27.505047 | O62: 27.599985 | P62: 27.620741 | Q62: 27.650078 | R62: 27.734261 | S62: 27.819878 | T62: 27.906652 | U62: 28.028929 | V62: 28.056576 | W62: 28.121964 | X62: 28.216476 | Y62: 28.362297 | Z62: 28.422821 | AA62: 28.477886 | AB62: 28.651974 | AC62: 28.765202 | AD62: 28.797384 | AE62: 28.862219 | AF62: 29.118975 | AG62: 0.003635
A63: QUA000:ea_ElectricityRe | B63: Electricity Related Losses | C63: 6.173548 | D63: 6.187497 | E63: 6.16351 | F63: 6.029583 | G63: 5.949151 | H63: 5.89101 | I63: 5.821366 | J63: 5.755558 | K63: 5.722089 | L63: 5.699003 | M63: 5.680921 | N63: 5.689142 | O63: 5.649225 | P63: 5.613934 | Q63: 5.584054 | R63: 5.570951 | S63: 5.562721 | T63: 5.552922 | U63: 5.556041 | V63: 5.549467 | W63: 5.551173 | X63: 5.557679 | Y63: 5.567109 | Z63: 5.559643 | AA63: 5.552845 | AB63: 5.564961 | AC63: 5.568575 | AD63: 5.559003 | AE63: 5.552838 | AF63: 5.579782 | AG63: -0.003481
A64: QUA000:ea_Total | B64: Total | C64: 32.384235 | D64: 32.618805 | E64: 32.773899 | F64: 32.64962 | G64: 32.798367 | H64: 32.899677 | I64: 32.862148 | J64: 32.914761 | K64: 32.917915 | L64: 32.968189 | M64: 33.022114 | N64: 33.194187 | O64: 33.24921 | P64: 33.234676 | Q64: 33.234131 | R64: 33.305214 | S64: 33.382599 | T64: 33.459576 | U64: 33.584969 | V64: 33.606041 | W64: 33.673138 | X64: 33.774155 | Y64: 33.929405 | Z64: 33.982464 | AA64: 34.030731 | AB64: 34.216934 | AC64: 34.333778 | AD64: 34.356388 | AE64: 34.415058 | AF64: 34.698757 | AG64: 0.002383
B67: Transportation
A68: QUA000:fa_LiquefiedPetr | B68: Propane | C68: 0.006869 | D68: 0.007989 | E68: 0.008609 | F68: 0.008875 | G68: 0.0092 | H68: 0.009477 | I68: 0.009714 | J68: 0.009727 | K68: 0.009917 | L68: 0.010134 | M68: 0.01034 | N68: 0.010567 | O68: 0.010793 | P68: 0.011016 | Q68: 0.01124 | R68: 0.011473 | S68: 0.011724 | T68: 0.01198 | U68: 0.012231 | V68: 0.012499 | W68: 0.012771 | X68: 0.013055 | Y68: 0.013347 | Z68: 0.013625 | AA68: 0.013923 | AB68: 0.014258 | AC68: 0.014598 | AD68: 0.014932 | AE68: 0.015285 | AF68: 0.015689 | AG68: 0.028887
A69: QUA000:fa_MotorGasoline | B69: Motor Gasoline 3/ | C69: 15.466408 | D69: 15.768945 | E69: 15.988935 | F69: 15.909855 | G69: 15.798645 | H69: 15.663221 | I69: 15.508991 | J69: 15.360925 | K69: 15.222957 | L69: 15.114703 | M69: 15.031124 | N69: 14.936218 | O69: 14.865545 | P69: 14.787169 | Q69: 14.703329 | R69: 14.63151 | S69: 14.578344 | T69: 14.538388 | U69: 14.52211 | V69: 14.519249 | W69: 14.521601 | X69: 14.534111 | Y69: 14.551273 | Z69: 14.581889 | AA69: 14.627379 | AB69: 14.698816 | AC69: 14.781537 | AD69: 14.86446 | AE69: 14.956556 | AF69: 15.074851 | AG69: -0.000884
A70: QUA000:fa_RenewableEner | B70: of which: E85 11/ | C70: 0.030771 | D70: 0.033197 | E70: 0.034623 | F70: 0.034328 | G70: 0.033801 | H70: 0.032973 | I70: 0.031905 | J70: 0.030835 | K70: 0.029769 | L70: 0.028677 | M70: 0.027671 | N70: 0.026621 | O70: 0.025746 | P70: 0.024923 | Q70: 0.02422 | R70: 0.023651 | S70: 0.023205 | T70: 0.022872 | U70: 0.022807 | V70: 0.022678 | W70: 0.022692 | X70: 0.022463 | Y70: 0.022592 | Z70: 0.023056 | AA70: 0.023304 | AB70: 0.023588 | AC70: 0.023895 | AD70: 0.024275 | AE70: 0.024635 | AF70: 0.025124 | AG70: -0.006967
A71: QUA000:fa_JetFuel | B71: Jet Fuel 12/ | C71: 2.669782 | D71: 3.110748 | E71: 3.450699 | F71: 3.522604 | G71: 3.584247 | H71: 3.626195 | I71: 3.652925 | J71: 3.68663 | K71: 3.716202 | L71: 3.75194 | M71: 3.775125 | N71: 3.803998 | O71: 3.818869 | P71: 3.81458 | Q71: 3.824051 | R71: 3.835392 | S71: 3.854807 | T71: 3.873541 | U71: 3.900975 | V71: 3.931522 | W71: 3.954494 | X71: 3.982706 | Y71: 4.012361 | Z71: 4.03763 | AA71: 4.071923 | AB71: 4.107882 | AC71: 4.141226 | AD71: 4.172148 | AE71: 4.206087 | AF71: 4.252439 | AG71: 0.016181
A72: QUA000:fa_DistillateFue | B72: Distillate Fuel Oil 13/ | C72: 6.491702 | D72: 6.422758 | E72: 6.490077 | F72: 6.397579 | G72: 6.344406 | H72: 6.280037 | I72: 6.196609 | J72: 6.131257 | K72: 6.049854 | L72: 5.976546 | M72: 5.901943 | N72: 5.838669 | O72: 5.778304 | P72: 5.709261 | Q72: 5.652218 | R72: 5.601161 | S72: 5.555239 | T72: 5.516709 | U72: 5.485267 | V72: 5.461822 | W72: 5.436196 | X72: 5.418772 | Y72: 5.405413 | Z72: 5.381793 | AA72: 5.360053 | AB72: 5.355654 | AC72: 5.341472 | AD72: 5.315172 | AE72: 5.292819 | AF72: 5.29156 | AG72: -0.007024
A73: QUA000:fa_ResidualFuel | B73: Residual Fuel Oil | C73: 0.553924 | D73: 0.7434 | E73: 0.518151 | F73: 0.520411 | G73: 0.525172 | H73: 0.519545 | I73: 0.508518 | J73: 0.503362 | K73: 0.501809 | L73: 0.498949 | M73: 0.497462 | N73: 0.505378 | O73: 0.504007 | P73: 0.502638 | Q73: 0.503666 | R73: 0.503674 | S73: 0.504193 | T73: 0.503816 | U73: 0.505268 | V73: 0.486345 | W73: 0.483732 | X73: 0.484013 | Y73: 0.477022 | Z73: 0.470191 | AA73: 0.468358 | AB73: 0.462141 | AC73: 0.461203 | AD73: 0.461032 | AE73: 0.459237 | AF73: 0.459974 | AG73: -0.006388
A74: QUA000:fa_OtherPetroleu | B74: Other Petroleum 14/ | C74: 0.147469 | D74: 0.148755 | E74: 0.149462 | F74: 0.14997 | G74: 0.150235 | H74: 0.150497 | I74: 0.150514 | J74: 0.150549 | K74: 0.150579 | L74: 0.150567 | M74: 0.150531 | N74: 0.150533 | O74: 0.150556 | P74: 0.150453 | Q74: 0.150276 | R74: 0.150111 | S74: 0.149992 | T74: 0.149944 | U74: 0.149962 | V74: 0.15 | W74: 0.150023 | X74: 0.150019 | Y74: 0.150003 | Z74: 0.149973 | AA74: 0.149918 | AB74: 0.149907 | AC74: 0.149898 | AD74: 0.149869 | AE74: 0.149883 | AF74: 0.149888 | AG74: 0.000561
A75: QUA000:fa_PetroleumSubt | B75: Petroleum and Other Liquids Subtotal | C75: 25.336157 | D75: 26.202593 | E75: 26.605936 | F75: 26.509295 | G75: 26.411901 | H75: 26.248972 | I75: 26.027267 | J75: 25.842445 | K75: 25.65132 | L75: 25.502836 | M75: 25.366524 | N75: 25.245361 | O75: 25.128075 | P75: 24.975117 | Q75: 24.844778 | R75: 24.733322 | S75: 24.654299 | T75: 24.594381 | U75: 24.575813 | V75: 24.561436 | W75: 24.558819 | X75: 24.582678 | Y75: 24.609419 | Z75: 24.635098 | AA75: 24.691553 | AB75: 24.788658 | AC75: 24.889936 | AD75: 24.977613 | AE75: 25.07987 | AF75: 25.2444 | AG75: -0.000125
A76: QUA000:fa_PipelineFuelN | B76: Pipeline and Distribution Fuel Natural Gas | C76: 0.747916 | D76: 0.699222 | E76: 0.679983 | F76: 0.663084 | G76: 0.651879 | H76: 0.638845 | I76: 0.622078 | J76: 0.627267 | K76: 0.621322 | L76: 0.611935 | M76: 0.608225 | N76: 0.611033 | O76: 0.61315 | P76: 0.603666 | Q76: 0.601211 | R76: 0.602072 | S76: 0.608083 | T76: 0.614808 | U76: 0.62078 | V76: 0.626373 | W76: 0.629804 | X76: 0.635453 | Y76: 0.639786 | Z76: 0.646995 | AA76: 0.645089 | AB76: 0.648412 | AC76: 0.656764 | AD76: 0.665 | AE76: 0.672356 | AF76: 0.677732 | AG76: -0.003392
A77: QUA000:fa_CompressedNat | B77: Compressed / Liquefied Natural Gas | C77: 0.110155 | D77: 0.09911 | E77: 0.116707 | F77: 0.123152 | G77: 0.129577 | H77: 0.139689 | I77: 0.150944 | J77: 0.159019 | K77: 0.16684 | L77: 0.175736 | M77: 0.184773 | N77: 0.188349 | O77: 0.196062 | P77: 0.203691 | Q77: 0.210901 | R77: 0.21866 | S77: 0.22709 | T77: 0.236284 | U77: 0.24384 | V77: 0.258586 | W77: 0.268262 | X77: 0.277377 | Y77: 0.290159 | Z77: 0.303625 | AA77: 0.314409 | AB77: 0.327593 | AC77: 0.338196 | AD77: 0.346843 | AE77: 0.356809 | AF77: 0.366318 | AG77: 0.042305
A78: QUA000:fa_LiquidHydroge | B78: Hydrogen | C78: 0.000451 | D78: 0.000576 | E78: 0.000704 | F78: 0.000826 | G78: 0.000955 | H78: 0.00109 | I78: 0.00123 | J78: 0.001381 | K78: 0.00154 | L78: 0.001707 | M78: 0.001881 | N78: 0.002057 | O78: 0.002238 | P78: 0.002415 | Q78: 0.002588 | R78: 0.002752 | S78: 0.002909 | T78: 0.003064 | U78: 0.003218 | V78: 0.003369 | W78: 0.003516 | X78: 0.003664 | Y78: 0.003808 | Z78: 0.003945 | AA78: 0.004087 | AB78: 0.004229 | AC78: 0.004371 | AD78: 0.004508 | AE78: 0.004643 | AF78: 0.004777 | AG78: 0.084798
A79: QUA000:fa_Electricity | B79: Purchased Electricity | C79: 0.043551 | D79: 0.053865 | E79: 0.065191 | F79: 0.07679 | G79: 0.088609 | H79: 0.100552 | I79: 0.112385 | J79: 0.124169 | K79: 0.135952 | L79: 0.147944 | M79: 0.159949 | N79: 0.172204 | O79: 0.184458 | P79: 0.196517 | Q79: 0.208417 | R79: 0.220291 | S79: 0.232314 | T79: 0.244538 | U79: 0.25707 | V79: 0.269937 | W79: 0.282798 | X79: 0.295816 | Y79: 0.309226 | Z79: 0.323126 | AA79: 0.337216 | AB79: 0.351319 | AC79: 0.365929 | AD79: 0.380844 | AE79: 0.396425 | AF79: 0.413046 | AG79: 0.080662
... A82: QUA000:fa_Total | B82: Total | C82: 26.318542 | D82: 27.154667 | E82: 27.587545 | F82: 27.510464 | G82: 27.438728 | H82: 27.303976 | I82: 27.107222 | J82: 26.965076 | K82: 26.806538 | L82: 26.688883 | M82: 26.589376 | N82: 26.506466 | O82: 26.429188 | P82: 26.304937 | Q82: 26.209085 | R82: 26.136221 | S82: 26.101809 | T82: 26.088194 | U82: 26.114872 | V82: 26.153355 | W82: 26.196301 | X82: 26.267424 | Y82: 26.344372 | Z82: 26.425249 | AA82: 26.52544 | AB82: 26.673073 | AC82: 26.828812 | AD82: 26.970144 | AE82: 27.127676 | AF82: 27.348196 | AG82: 0.001324
B84: Unspecified Sector 15/
A85: QUA000:un_Total | B85: Total | C85: 0.192583 | D85: -0.005713 | E85: -0.247958 | F85: -0.247566 | G85: -0.247589 | H85: -0.246891 | I85: -0.24544 | J85: -0.244502 | K85: -0.243203 | L85: -0.242283 | M85: -0.241136 | N85: -0.240294 | O85: -0.23927 | P85: -0.237635 | Q85: -0.236514 | R85: -0.235584 | S85: -0.234987 | T85: -0.234553 | U85: -0.234519 | V85: -0.234745 | W85: -0.234779 | X85: -0.235115 | Y85: -0.235573 | Z85: -0.235781 | AA85: -0.23627 | AB85: -0.237204 | AC85: -0.237929 | AD85: -0.238373 | AE85: -0.238986 | AF85: -0.240352 | AG85: --
B87: Delivered Energy Consumption, All Sectors
A88: QUA000:ga_LiquefiedPetr | B88: Liquefied Petroleum Gases and Other 6/ | C88: 4.18965 | D88: 4.338455 | E88: 4.485513 | F88: 4.461042 | G88: 4.534525 | H88: 4.599054 | I88: 4.637942 | J88: 4.661957 | K88: 4.663677 | L88: 4.677134 | M88: 4.717023 | N88: 4.791105 | O88: 4.835604 | P88: 4.855873 | Q88: 4.876571 | R88: 4.904921 | S88: 4.936522 | T88: 4.960772 | U88: 4.989331 | V88: 5.001596 | W88: 5.019331 | X88: 5.044017 | Y88: 5.082983 | Z88: 5.084746 | AA88: 5.093513 | AB88: 5.150496 | AC88: 5.173552 | AD88: 5.144804 | AE88: 5.148603 | AF88: 5.2147 | AG88: 0.007576
A89: QUA000:ga_MotorGasoline | B89: Motor Gasoline 3/ | C89: 16.197784 | D89: 16.40741 | E89: 16.53927 | F89: 16.464457 | G89: 16.357529 | H89: 16.225603 | I89: 16.074091 | J89: 15.929655 | K89: 15.795033 | L89: 15.689336 | M89: 15.608176 | N89: 15.517878 | O89: 15.451266 | P89: 15.373913 | Q89: 15.290965 | R89: 15.220361 | S89: 15.169581 | T89: 15.132666 | U89: 15.11986 | V89: 15.119605 | W89: 15.123998 | X89: 15.138477 | Y89: 15.157466 | Z89: 15.189621 | AA89: 15.236579 | AB89: 15.30983 | AC89: 15.394181 | AD89: 15.478707 | AE89: 15.572911 | AF89: 15.6941 | AG89: -0.001089
A90: QUA000:ga_E85 | B90: of which: E85 11/ | C90: 0.030771 | D90: 0.033197 | E90: 0.034623 | F90: 0.034328 | G90: 0.033801 | H90: 0.032973 | I90: 0.031905 | J90: 0.030835 | K90: 0.029769 | L90: 0.028677 | M90: 0.027671 | N90: 0.026621 | O90: 0.025746 | P90: 0.024923 | Q90: 0.02422 | R90: 0.023651 | S90: 0.023205 | T90: 0.022872 | U90: 0.022807 | V90: 0.022678 | W90: 0.022692 | X90: 0.022463 | Y90: 0.022592 | Z90: 0.023056 | AA90: 0.023304 | AB90: 0.023588 | AC90: 0.023895 | AD90: 0.024275 | AE90: 0.024635 | AF90: 0.025124 | AG90: -0.006967
A91: QUA000:ga_JetFuel | B91: Jet Fuel 12/ | C91: 2.855396 | D91: 3.184402 | E91: 3.374199 | F91: 3.444509 | G91: 3.504787 | H91: 3.545804 | I91: 3.571942 | J91: 3.604899 | K91: 3.633816 | L91: 3.668761 | M91: 3.691433 | N91: 3.719665 | O91: 3.734207 | P91: 3.730013 | Q91: 3.739274 | R91: 3.750364 | S91: 3.769349 | T91: 3.787667 | U91: 3.814492 | V91: 3.844363 | W91: 3.866826 | X91: 3.894412 | Y91: 3.923409 | Z91: 3.948118 | AA91: 3.981651 | AB91: 4.016813 | AC91: 4.049418 | AD91: 4.079654 | AE91: 4.11284 | AF91: 4.158165 | AG91: 0.013045
A92: QUA000:ga_Kerosene | B92: Kerosene 16/ | C92: 0.003274 | D92: 0.003164 | E92: 0.003717 | F92: 0.003418 | G92: 0.003319 | H92: 0.003204 | I92: 0.003155 | J92: 0.003118 | K92: 0.003094 | L92: 0.0031 | M92: 0.003049 | N92: 0.002955 | O92: 0.002947 | P92: 0.002941 | Q92: 0.002931 | R92: 0.002918 | S92: 0.002888 | T92: 0.002867 | U92: 0.00286 | V92: 0.002821 | W92: 0.002795 | X92: 0.002784 | Y92: 0.002748 | Z92: 0.002713 | AA92: 0.00271 | AB92: 0.002689 | AC92: 0.002691 | AD92: 0.002695 | AE92: 0.002684 | AF92: 0.002695 | AG92: -0.006689
A93: QUA000:ga_DistillateFue | B93: Distillate Fuel Oil 1/ | C93: 8.258992 | D93: 8.195849 | E93: 8.231738 | F93: 8.133506 | G93: 8.076631 | H93: 8.006885 | I93: 7.918554 | J93: 7.852912 | K93: 7.770899 | L93: 7.696064 | M93: 7.619589 | N93: 7.563928 | O93: 7.507926 | P93: 7.432593 | Q93: 7.369003 | R93: 7.312884 | S93: 7.266734 | T93: 7.230989 | U93: 7.203312 | V93: 7.180647 | W93: 7.154062 | X93: 7.13596 | Y93: 7.120589 | Z93: 7.093189 | AA93: 7.068066 | AB93: 7.061945 | AC93: 7.046124 | AD93: 7.018533 | AE93: 6.996561 | AF93: 6.998849 | AG93: -0.005693
A94: QUA000:ga_ResidualFuel | B94: Residual Fuel Oil | C94: 0.597433 | D94: 0.783538 | E94: 0.558883 | F94: 0.558127 | G94: 0.561554 | H94: 0.556268 | I94: 0.54522 | J94: 0.541257 | K94: 0.54095 | L94: 0.539114 | M94: 0.538591 | N94: 0.547114 | O94: 0.546886 | P94: 0.545998 | Q94: 0.547093 | R94: 0.547297 | S94: 0.548424 | T94: 0.548565 | U94: 0.550963 | V94: 0.531347 | W94: 0.529263 | X94: 0.529941 | Y94: 0.522234 | Z94: 0.514668 | AA94: 0.512369 | AB94: 0.505756 | AC94: 0.504912 | AD94: 0.50504 | AE94: 0.503111 | AF94: 0.504363 | AG94: -0.005823
A95: QUA000:ga_Petrochemical | B95: Petrochemical Feedstocks | C95: 0.583656 | D95: 0.563777 | E95: 0.6309 | F95: 0.55 | G95: 0.55 | H95: 0.55 | I95: 0.55 | J95: 0.55 | K95: 0.55 | L95: 0.55 | M95: 0.55 | N95: 0.55 | O95: 0.55 | P95: 0.55 | Q95: 0.55 | R95: 0.55 | S95: 0.55 | T95: 0.55 | U95: 0.55 | V95: 0.55 | W95: 0.55 | X95: 0.55 | Y95: 0.55 | Z95: 0.55 | AA95: 0.55 | AB95: 0.55 | AC95: 0.55 | AD95: 0.55 | AE95: 0.55 | AF95: 0.55 | AG95: -0.002046
A96: QUA000:ga_OtherPetroleu | B96: Other Petroleum 17/ | C96: 3.235998 | D96: 3.164937 | E96: 3.229631 | F96: 3.28973 | G96: 3.303969 | H96: 3.308053 | I96: 3.307575 | J96: 3.349161 | K96: 3.377739 | L96: 3.403579 | M96: 3.410776 | N96: 3.443785 | O96: 3.456658 | P96: 3.46292 | Q96: 3.463597 | R96: 3.470187 | S96: 3.495862 | T96: 3.501539 | U96: 3.513722 | V96: 3.481097 | W96: 3.489849 | X96: 3.482918 | Y96: 3.468021 | Z96: 3.463028 | AA96: 3.44483 | AB96: 3.436774 | AC96: 3.426353 | AD96: 3.440587 | AE96: 3.452377 | AF96: 3.451317 | AG96: 0.002224
A97: QUA000:ga_PetroleumSubt | B97: Petroleum and Other Liquids Subtotal | C97: 35.92218 | D97: 36.641533 | E97: 37.053852 | F97: 36.904789 | G97: 36.892315 | H97: 36.794865 | I97: 36.608479 | J97: 36.492958 | K97: 36.335209 | L97: 36.227089 | M97: 36.138638 | N97: 36.136429 | O97: 36.085491 | P97: 35.95425 | Q97: 35.839432 | R97: 35.758934 | S97: 35.739361 | T97: 35.715061 | U97: 35.744541 | V97: 35.711475 | W97: 35.736122 | X97: 35.778507 | Y97: 35.82745 | Z97: 35.846081 | AA97: 35.889717 | AB97: 36.034302 | AC97: 36.147232 | AD97: 36.220016 | AE97: 36.339088 | AF97: 36.574188 | AG97: 0.00062
A98: QUA000:ga_NaturalGas | B98: Natural Gas | C98: 17.178505 | D98: 17.440561 | E98: 17.200001 | F98: 17.25214 | G98: 17.346048 | H98: 17.42202 | I98: 17.449314 | J98: 17.444603 | K98: 17.414623 | L98: 17.399984 | M98: 17.396873 | N98: 17.363729 | O98: 17.353024 | P98: 17.364279 | Q98: 17.377035 | R98: 17.437874 | S98: 17.46744 | T98: 17.505899 | U98: 17.532627 | V98: 17.56661 | W98: 17.584719 | X98: 17.628685 | Y98: 17.70083 | Z98: 17.751511 | AA98: 17.79562 | AB98: 17.876865 | AC98: 17.943802 | AD98: 17.96913 | AE98: 18.004023 | AF98: 18.092625 | AG98: 0.001789
A99: QUA000:ga_NGastoLiquids | B99: Natural-Gas-to-Liquids Heat and Power | C99: 0 | D99: 0 | E99: 0 | F99: 0 | G99: 0 | H99: 0 | I99: 0 | J99: 0 | K99: 0 | L99: 0 | M99: 0 | N99: 0 | O99: 0 | P99: 0 | Q99: 0 | R99: 0 | S99: 0 | T99: 0 | U99: 0 | V99: 0 | W99: 0 | X99: 0 | Y99: 0 | Z99: 0 | AA99: 0 | AB99: 0 | AC99: 0 | AD99: 0 | AE99: 0 | AF99: 0 | AG99: --
A100: QUA000:ga_LeaseandPlant | B100: Lease and Plant Fuel 8/ | C100: 1.908455 | D100: 1.977932 | E100: 1.988711 | F100: 2.014221 | G100: 2.046336 | H100: 2.050896 | I100: 2.051069 | J100: 2.089817 | K100: 2.104321 | L100: 2.128522 | M100: 2.144954 | N100: 2.172365 | O100: 2.193179 | P100: 2.183699 | Q100: 2.184837 | R100: 2.178093 | S100: 2.172917 | T100: 2.177195 | U100: 2.195431 | V100: 2.213282 | W100: 2.209525 | X100: 2.21719 | Y100: 2.245676 | Z100: 2.259835 | AA100: 2.285115 | AB100: 2.300184 | AC100: 2.311478 | AD100: 2.324327 | AE100: 2.328741 | AF100: 2.372455 | AG100: 0.007533
A101: QUA000:qa_liquefactexp | B101: Natural Gas to Liquefy Gas for Export 9/ | C101: 0.300655 | D101: 0.352409 | E101: 0.372659 | F101: 0.376397 | G101: 0.39067 | H101: 0.391683 | I101: 0.400083 | J101: 0.417955 | K101: 0.433681 | L101: 0.450481 | M101: 0.46728 | N101: 0.485153 | O101: 0.492479 | P101: 0.492479 | Q101: 0.492479 | R101: 0.493552 | S101: 0.492479 | T101: 0.492479 | U101: 0.492479 | V101: 0.493552 | W101: 0.492479 | X101: 0.492479 | Y101: 0.492479 | Z101: 0.493552 | AA101: 0.492479 | AB101: 0.492479 | AC101: 0.492479 | AD101: 0.493552 | AE101: 0.492479 | AF101: 0.492479 | AG101: 0.017162
A102: QUA000:ga_PipelineNatur | B102: Pipeline and Distribution Fuel Natural Gas | C102: 0.747916 | D102: 0.699222 | E102: 0.679983 | F102: 0.663084 | G102: 0.651879 | H102: 0.638845 | I102: 0.622078 | J102: 0.627267 | K102: 0.621322 | L102: 0.611935 | M102: 0.608225 | N102: 0.611033 | O102: 0.61315 | P102: 0.603666 | Q102: 0.601211 | R102: 0.602072 | S102: 0.608083 | T102: 0.614808 | U102: 0.62078 | V102: 0.626373 | W102: 0.629804 | X102: 0.635453 | Y102: 0.639786 | Z102: 0.646995 | AA102: 0.645089 | AB102: 0.648412 | AC102: 0.656764 | AD102: 0.665 | AE102: 0.672356 | AF102: 0.677732 | AG102: -0.003392
A103: QUA000:ga_NaturalGasSub | B103: Natural Gas Subtotal | C103: 20.13553 | D103: 20.470125 | E103: 20.241354 | F103: 20.305841 | G103: 20.434933 | H103: 20.503445 | I103: 20.522543 | J103: 20.579643 | K103: 20.573948 | L103: 20.590923 | M103: 20.617331 | N103: 20.632282 | O103: 20.651833 | P103: 20.644123 | Q103: 20.655563 | R103: 20.711592 | S103: 20.740917 | T103: 20.790382 | U103: 20.841316 | V103: 20.899818 | W103: 20.916527 | X103: 20.973806 | Y103: 21.078772 | Z103: 21.151894 | AA103: 21.218304 | AB103: 21.317942 | AC103: 21.404524 | AD103: 21.452011 | AE103: 21.497599 | AF103: 21.635292 | AG103: 0.00248
A104: QUA000:ga_Metallurgical | B104: Metallurgical Coal | C104: 0.47798 | D104: 0.477421 | E104: 0.495445 | F104: 0.481281 | G104: 0.477819 | H104: 0.491973 | I104: 0.487908 | J104: 0.484226 | K104: 0.471012 | L104: 0.462356 | M104: 0.454044 | N104: 0.45062 | O104: 0.445499 | P104: 0.444959 | Q104: 0.444015 | R104: 0.443062 | S104: 0.440091 | T104: 0.437403 | U104: 0.430178 | V104: 0.425549 | W104: 0.423099 | X104: 0.425421 | Y104: 0.429525 | Z104: 0.427211 | AA104: 0.424524 | AB104: 0.427489 | AC104: 0.425762 | AD104: 0.41617 | AE104: 0.409004 | AF104: 0.407861 | AG104: -0.005455
A105: QUA000:ga_SteamCoal | B105: Other Coal | C105: 0.501224 | D105: 0.499458 | E105: 0.478311 | F105: 0.478221 | G105: 0.477733 | H105: 0.478645 | I105: 0.478695 | J105: 0.478521 | K105: 0.477607 | L105: 0.476572 | M105: 0.475382 | N105: 0.473588 | O105: 0.472126 | P105: 0.469872 | Q105: 0.47162 | R105: 0.472335 | S105: 0.473922 | T105: 0.475602 | U105: 0.484036 | V105: 0.481796 | W105: 0.4866 | X105: 0.485888 | Y105: 0.484875 | Z105: 0.48308 | AA105: 0.481341 | AB105: 0.480208 | AC105: 0.479022 | AD105: 0.477338 | AE105: 0.475671 | AF105: 0.474686 | AG105: -0.001874
A106: QUA000:ga_CoaltoLiquids | B106: Coal-to-Liquids Heat and Power | C106: 0 | D106: 0 | E106: 0 | F106: 0 | G106: 0 | H106: 0 | I106: 0 | J106: 0 | K106: 0 | L106: 0 | M106: 0 | N106: 0 | O106: 0 | P106: 0 | Q106: 0 | R106: 0 | S106: 0 | T106: 0 | U106: 0 | V106: 0 | W106: 0 | X106: 0 | Y106: 0 | Z106: 0 | AA106: 0 | AB106: 0 | AC106: 0 | AD106: 0 | AE106: 0 | AF106: 0 | AG106: --
A107: QUA000:ga_NetCoalCokeIm | B107: Net Coal Coke Imports | C107: -0.035229 | D107: -0.023674 | E107: -0.027069 | F107: -0.025735 | G107: -0.026459 | H107: -0.026123 | I107: -0.026431 | J107: -0.026412 | K107: -0.026503 | L107: -0.026544 | M107: -0.026676 | N107: -0.026707 | O107: -0.026813 | P107: -0.026804 | Q107: -0.026705 | R107: -0.026698 | S107: -0.026697 | T107: -0.02665 | U107: -0.026722 | V107: -0.026782 | W107: -0.026614 | X107: -0.026412 | Y107: -0.026201 | Z107: -0.026257 | AA107: -0.026216 | AB107: -0.025939 | AC107: -0.0259 | AD107: -0.026205 | AE107: -0.026248 | AF107: -0.025964 | AG107: -0.010468
A108: QUA000:ga_CoalSubtotal | B108: Coal Subtotal | C108: 0.943975 | D108: 0.953204 | E108: 0.946687 | F108: 0.933767 | G108: 0.929092 | H108: 0.944495 | I108: 0.940172 | J108: 0.936335 | K108: 0.922116 | L108: 0.912385 | M108: 0.90275 | N108: 0.8975 | O108: 0.890812 | P108: 0.888026 | Q108: 0.88893 | R108: 0.888698 | S108: 0.887316 | T108: 0.886355 | U108: 0.887492 | V108: 0.880563 | W108: 0.883085 | X108: 0.884897 | Y108: 0.8882 | Z108: 0.884034 | AA108: 0.879649 | AB108: 0.881758 | AC108: 0.878885 | AD108: 0.867302 | AE108: 0.858427 | AF108: 0.856583 | AG108: -0.003344
A109: QUA000:ga_BiofuelsHeat | B109: Biofuels Heat and Coproducts | C109: 0.941453 | D109: 0.933549 | E109: 0.902314 | F109: 0.902289 | G109: 0.910224 | H109: 0.911726 | I109: 0.911999 | J109: 0.912429 | K109: 0.91952 | L109: 0.922166 | M109: 0.925975 | N109: 0.929158 | O109: 0.931774 | P109: 0.935223 | Q109: 0.940831 | R109: 0.944629 | S109: 0.949544 | T109: 0.954958 | U109: 0.969474 | V109: 0.969957 | W109: 0.978944 | X109: 0.984904 | Y109: 0.992837 | Z109: 1.009661 | AA109: 1.01937 | AB109: 1.030285 | AC109: 1.042042 | AD109: 1.054141 | AE109: 1.066841 | AF109: 1.083 | AG109: 0.004842
A110: QUA000:ga_RenewableEner | B110: Renewable Energy 18/ | C110: 2.144595 | D110: 2.174059 | E110: 2.135367 | F110: 2.13597 | G110: 2.136519 | H110: 2.123153 | I110: 2.106174 | J110: 2.088475 | K110: 2.072822 | L110: 2.058813 | M110: 2.039143 | N110: 2.023129 | O110: 2.004169 | P110: 1.985061 | Q110: 1.96801 | R110: 1.952555 | S110: 1.935684 | T110: 1.920397 | U110: 1.908851 | V110: 1.898798 | W110: 1.890442 | X110: 1.884943 | Y110: 1.879447 | Z110: 1.866643 | AA110: 1.856323 | AB110: 1.85316 | AC110: 1.850444 | AD110: 1.849096 | AE110: 1.839255 | AF110: 1.842774 | AG110: -0.005217
A111: QUA000:ga_LiquidHydroge | B111: Hydrogen | C111: 0.000451 | D111: 0.000576 | E111: 0.000704 | F111: 0.000826 | G111: 0.000955 | H111: 0.00109 | I111: 0.00123 | J111: 0.001381 | K111: 0.00154 | L111: 0.001707 | M111: 0.001881 | N111: 0.002057 | O111: 0.002238 | P111: 0.002415 | Q111: 0.002588 | R111: 0.002752 | S111: 0.002909 | T111: 0.003064 | U111: 0.003218 | V111: 0.003369 | W111: 0.003516 | X111: 0.003664 | Y111: 0.003808 | Z111: 0.003945 | AA111: 0.004087 | AB111: 0.004229 | AC111: 0.004371 | AD111: 0.004508 | AE111: 0.004643 | AF111: 0.004777 | AG111: 0.084798
A112: QUA000:ga_Electricity | B112: Purchased Electricity | C112: 12.975903 | D112: 12.938816 | E112: 13.115175 | F112: 13.145205 | G112: 13.193958 | H112: 13.213648 | I112: 13.241747 | J112: 13.283731 | K112: 13.319623 | L112: 13.354419 | M112: 13.39419 | N112: 13.458882 | O112: 13.514409 | P112: 13.563329 | Q112: 13.636465 | R112: 13.721497 | S112: 13.811511 | T112: 13.907131 | U112: 14.005589 | V112: 14.085065 | W112: 14.175823 | X112: 14.27175 | Y112: 14.381081 | Z112: 14.483742 | AA112: 14.586221 | AB112: 14.71384 | AC112: 14.836473 | AD112: 14.950056 | AE112: 15.070522 | AF112: 15.221416 | AG112: 0.005519
A113: QUA000:ga_DeliveredEner | B113: Delivered Energy | C113: 73.064087 | D113: 74.111862 | E113: 74.395447 | F113: 74.32869 | G113: 74.498001 | H113: 74.492416 | I113: 74.332336 | J113: 74.294952 | K113: 74.144775 | L113: 74.067505 | M113: 74.019905 | N113: 74.079437 | O113: 74.080727 | P113: 73.972427 | Q113: 73.931824 | R113: 73.980659 | S113: 74.067245 | T113: 74.177353 | U113: 74.360481 | V113: 74.449043 | W113: 74.584457 | X113: 74.782471 | Y113: 75.05159 | Z113: 75.246002 | AA113: 75.453674 | AB113: 75.83551 | AC113: 76.163971 | AD113: 76.397133 | AE113: 76.676376 | AF113: 77.218033 | AG113: 0.001909
...

Sheet AEO 2021 2
B1: ref2021.d113020a | C1: 2020 | D1: 2021 | E1: 2022 | F1: 2023 | G1: 2024 | H1: 2025 | I1: 2026 | J1: 2027 | K1: 2028 | L1: 2029 | M1: 2030 | N1: 2031 | O1: 2032 | P1: 2033 | Q1: 2034 | R1: 2035 | S1: 2036 | T1: 2037 | U1: 2038 | V1: 2039 | W1: 2040 | X1: 2041 | Y1: 2042 | Z1: 2043 | AA1: 2044 | AB1: 2045 | AC1: 2046 | AD1: 2047 | AE1: 2048 | AF1: 2049 | AG1: 2050
C3: Report | D3: Annual Energy Outlook 2021
C4: Scenario | D4: ref2021 | G4: Reference case
C5: Datekey | D5: d113020a
C6: Release Date | E6: January 2021
A10: QUA000 | B10: 2. Energy Consumption by Sector and Source | AH10: Compound
B11: (quadrillion Btu, unless otherwise noted) | AH11: Growth
AH12: 2020-2050
B13: Sector and Source | C13: 2020 | D13: 2021 | E13: 2022 | F13: 2023 | G13: 2024 | H13: 2025 | I13: 2026 | J13: 2027 | K13: 2028 | L13: 2029 | M13: 2030 | N13: 2031 | O13: 2032 | P13: 2033 | Q13: 2034 | R13: 2035 | S13: 2036 | T13: 2037 | U13: 2038 | V13: 2039 | W13: 2040 | X13: 2041 | Y13: 2042 | Z13: 2043 | AA13: 2044 | AB13: 2045 | AC13: 2046 | AD13: 2047 | AE13: 2048 | AF13: 2049 | AG13: 2050 | AH13: (percent)
B15: Residential
A16: QUA000:ca_LiquefiedPetr | B16: Propane | C16: 0.45518 | D16: 0.474045 | E16: 0.470818 | F16: 0.46705 | G16: 0.463122 | H16: 0.45916 | I16: 0.455288 | J16: 0.451774 | K16: 0.448461 | L16: 0.445483 | M16: 0.442539 | N16: 0.439852 | O16: 0.437278 | P16: 0.434946 | Q16: 0.432862 | R16: 0.431117 | S16: 0.429486 | T16: 0.42797 | U16: 0.426517 | V16: 0.425173 | W16: 0.423932 | X16: 0.422732 | Y16: 0.421615 | Z16: 0.420587 | AA16: 0.419687 | AB16: 0.419045 | AC16: 0.418424 | AD16: 0.417723 | AE16: 0.417084 | AF16: 0.41658 | AG16: 0.416192 | AH16: -0.00298
A17: QUA000:ca_DistillateFue | B17: Distillate Fuel Oil 1/ | C17: 0.429274 | D17: 0.454966 | E17: 0.452338 | F17: 0.438593 | G17: 0.425681 | H17: 0.414456 | I17: 0.404474 | J17: 0.396042 | K17: 0.388227 | L17: 0.381239 | M17: 0.374649 | N17: 0.36844 | O17: 0.362362 | P17: 0.356616 | Q17: 0.351066 | R17: 0.345831 | S17: 0.340664 | T17: 0.335491 | U17: 0.330365 | V17: 0.325589 | W17: 0.320742 | X17: 0.315938 | Y17: 0.311213 | Z17: 0.306462 | AA17: 0.301972 | AB17: 0.297575 | AC17: 0.29301 | AD17: 0.288385 | AE17: 0.283959 | AF17: 0.279589 | AG17: 0.275341 | AH17: -0.014694
A18: QUA000:ca_PetroleumSubt | B18: Petroleum and Other Liquids Subtotal | C18: 0.884454 | D18: 0.929011 | E18: 0.923157 | F18: 0.905643 | G18: 0.888803 | H18: 0.873616 | I18: 0.859762 | J18: 0.847816 | K18: 0.836689 | L18: 0.826722 | M18: 0.817188 | N18: 0.808292 | O18: 0.79964 | P18: 0.791562 | Q18: 0.783928 | R18: 0.776948 | S18: 0.77015 | T18: 0.763461 | U18: 0.756881 | V18: 0.750762 | W18: 0.744674 | X18: 0.738671 | Y18: 0.732828 | Z18: 0.727049 | AA18: 0.72166 | AB18: 0.71662 | AC18: 0.711434 | AD18: 0.706107 | AE18: 0.701044 | AF18: 0.696169 | AG18: 0.691533 | AH18: -0.008168
A19: QUA000:ca_NaturalGas | B19: Natural Gas | C19: 4.96935 | D19: 4.841384 | E19: 4.978416 | F19: 4.970707 | G19: 4.97238 | H19: 4.968029 | I19: 4.956164 | J19: 4.942776 | K19: 4.931273 | L19: 4.920139 | M19: 4.903756 | N19: 4.891912 | O19: 4.883052 | P19: 4.874524 | Q19: 4.866061 | R19: 4.860207 | S19: 4.8556 | T19: 4.851071 | U19: 4.846893 | V19: 4.843016 | W19: 4.840974 | X19: 4.838866 | Y19: 4.837218 | Z19: 4.83576 | AA19: 4.835349 | AB19: 4.834342 | AC19: 4.833664 | AD19: 4.832069 | AE19: 4.83002 | AF19: 4.82676 | AG19: 4.82341 | AH19: -0.000993
A20: QUA000:ca_RenewableEner | B20: Renewable Energy 2/ | C20: 0.457512 | D20: 0.454333 | E20: 0.443909 | F20: 0.448911 | G20: 0.454326 | H20: 0.456317 | I20: 0.45534 | J20: 0.451821 | K20: 0.448893 | L20: 0.444799 | M20: 0.440398 | N20: 0.435099 | O20: 0.429791 | P20: 0.423655 | Q20: 0.416962 | R20: 0.409784 | S20: 0.40251 | T20: 0.396165 | U20: 0.3906 | V20: 0.384448 | W20: 0.379422 | X20: 0.37479 | Y20: 0.370205 | Z20: 0.366157 | AA20: 0.361594 | AB20: 0.357145 | AC20: 0.353832 | AD20: 0.35059 | AE20: 0.346575 | AF20: 0.34247 | AG20: 0.338111 | AH20: -0.01003
A21: QUA000:ca_Electricity | B21: Purchased Electricity | C21: 5.052733 | D21: 5.085547 | E21: 5.091327 | F21: 5.10172 | G21: 5.115735 | H21: 5.131444 | I21: 5.153737 | J21: 5.175787 | K21: 5.20145 | L21: 5.229 | M21: 5.257937 | N21: 5.29014 | O21: 5.326302 | P21: 5.36082 | Q21: 5.40049 | R21: 5.442099 | S21: 5.487025 | T21: 5.534366 | U21: 5.582504 | V21: 5.630486 | W21: 5.674673 | X21: 5.718518 | Y21: 5.763376 | Z21: 5.812753 | AA21: 5.862584 | AB21: 5.912036 | AC21: 5.963373 | AD21: 6.013557 | AE21: 6.065495 | AF21: 6.119937 | AG21: 6.177919 | AH21: 0.006724
A22: QUA000:ca_DeliveredEner | B22: Delivered Energy | C22: 11.364052 | D22: 11.310277 | E22: 11.43681 | F22: 11.426983 | G22: 11.431243 | H22: 11.429406 | I22: 11.425002 | J22: 11.418199 | K22: 11.418305 | L22: 11.42066 | M22: 11.419279 | N22: 11.425442 | O22: 11.438783 | P22: 11.450561 | Q22: 11.46744 | R22: 11.489039 | S22: 11.515284 | T22: 11.545061 | U22: 11.576879 | V22: 11.608712 | W22: 11.639742 | X22: 11.670846 | Y22: 11.703629 | Z22: 11.741718 | AA22: 11.781187 | AB22: 11.820144 | AC22: 11.862303 | AD22: 11.902324 | AE22: 11.943133 | AF22: 11.985336 | AG22: 12.030972 | AH22: 0.001903
A23: QUA000:ca_ElectricityRe | B23: Electricity Related Losses | C23: 9.417956 | D23: 9.469259 | E23: 9.523586 | F23: 9.353558 | G23: 9.192634 | H23: 8.961144 | I23: 8.754603 | J23: 8.691695 | K23: 8.686027 | L23: 8.699572 | M23: 8.728955 | N23: 8.761385 | O23: 8.769801 | P23: 8.792642 | Q23: 8.811792 | R23: 8.85434 | S23: 8.896054 | T23: 8.943662 | U23: 8.971651 | V23: 9.00147 | W23: 9.030401 | X23: 9.071213 | Y23: 9.114241 | Z23: 9.156261 | AA23: 9.196094 | AB23: 9.234004 | AC23: 9.281438 | AD23: 9.33171 | AE23: 9.396441 | AF23: 9.454361 | AG23: 9.504673 | AH23: 0.000306
A24: QUA000:ca_Total | B24: Total | C24: 20.782009 | D24: 20.779537 | E24: 20.960396 | F24: 20.78054 | G24: 20.623877 | H24: 20.390551 | I24: 20.179605 | J24: 20.109894 | K24: 20.104332 | L24: 20.120232 | M24: 20.148235 | N24: 20.186827 | O24: 20.208584 | P24: 20.243202 | Q24: 20.279232 | R24: 20.34338 | S24: 20.411339 | T24: 20.488724 | U24: 20.548531 | V24: 20.610182 | W24: 20.670143 | X24: 20.742058 | Y24: 20.817871 | Z24: 20.89798 | AA24: 20.97728 | AB24: 21.054148 | AC24: 21.143742 | AD24: 21.234034 | AE24: 21.339573 | AF24: 21.439697 | AG24: 21.535645 | AH24: 0.001188
B26: Commercial
A27: QUA000:da_LiquefiedPetr | B27: Propane | C27: 0.16909 | D27: 0.17043 | E27: 0.171078 | F27: 0.172316 | G27: 0.173561 | H27: 0.174816 | I27: 0.176343 | J27: 0.177955 | K27: 0.179406 | L27: 0.18099 | M27: 0.182417 | N27: 0.184083 | O27: 0.185733 | P27: 0.187505 | Q27: 0.189335 | R27: 0.191154 | S27: 0.192913 | T27: 0.194645 | U27: 0.196334 | V27: 0.19808 | W27: 0.199782 | X27: 0.201515 | Y27: 0.203344 | Z27: 0.20515 | AA27: 0.207034 | AB27: 0.209041 | AC27: 0.210896 | AD27: 0.212778 | AE27: 0.214758 | AF27: 0.216768 | AG27: 0.218797 | AH27: 0.008627
A28: QUA000:da_MotorGasoline | B28: Motor Gasoline 3/ | C28: 0.32368 | D28: 0.35236 | E28: 0.356357 | F28: 0.360291 | G28: 0.364608 | H28: 0.368727 | I28: 0.369102 | J28: 0.369501 | K28: 0.369535 | L28: 0.369811 | M28: 0.369612 | N28: 0.370091 | O28: 0.370272 | P28: 0.370693 | Q28: 0.371042 | R28: 0.371446 | S28: 0.371816 | T28: 0.372163 | U28: 0.372466 | V28: 0.372967 | W28: 0.373217 | X28: 0.373596 | Y28: 0.37404 | Z28: 0.374493 | AA28: 0.37501 | AB28: 0.375614 | AC28: 0.375965 | AD28: 0.37649 | AE28: 0.376973 | AF28: 0.377576 | AG28: 0.378132 | AH28: 0.005196
A29: QUA000:da_Kerosene | B29: Kerosene | C29: 0.00133 | D29: 0.0015 | E29: 0.001517 | F29: 0.001596 | G29: 0.001578 | H29: 0.001647 | I29: 0.001544 | J29: 0.0015 | K29: 0.001387 | L29: 0.001341 | M29: 0.001233 | N29: 0.001191 | O29: 0.001136 | P29: 0.001107 | Q29: 0.001085 | R29: 0.001068 | S29: 0.001046 | T29: 0.001009 | U29: 0.000971 | V29: 0.000967 | W29: 0.000917 | X29: 0.000886 | Y29: 0.000865 | Z29: 0.000823 | AA29: 0.00082 | AB29: 0.000808 | AC29: 0.000776 | AD29: 0.000762 | AE29: 0.000766 | AF29: 0.000754 | AG29: 0.00075 | AH29: -0.018902
A30: QUA000:da_DistillateFue | B30: Distillate Fuel Oil | C30: 0.30937 | D30: 0.32117 | E30: 0.332396 | F30: 0.330707 | G30: 0.329671 | H30: 0.329941 | I30: 0.329299 | J30: 0.327888 | K30: 0.324954 | L30: 0.322151 | M30: 0.318692 | N30: 0.315975 | O30: 0.313346 | P30: 0.311243 | Q30: 0.309302 | R30: 0.307546 | S30: 0.305769 | T30: 0.303689 | U30: 0.30142 | V30: 0.299543 | W30: 0.297205 | X30: 0.294907 | Y30: 0.292766 | Z30: 0.290603 | AA30: 0.288871 | AB30: 0.287173 | AC30: 0.28523 | AD30: 0.283208 | AE30: 0.281544 | AF30: 0.279879 | AG30: 0.278342 | AH30: -0.003517
A31: QUA000:da_ResidualFuel | B31: Residual Fuel Oil | C31: 0.00229 | D31: 0.00229 | E31: 0.002156 | F31: 0.002281 | G31: 0.002835 | H31: 0.003581 | I31: 0.003333 | J31: 0.003306 | K31: 0.003205 | L31: 0.003171 | M31: 0.003097 | N31: 0.003083 | O31: 0.00305 | P31: 0.003053 | Q31: 0.003059 | R31: 0.003065 | S31: 0.003088 | T31: 0.003121 | U31: 0.003099 | V31: 0.003131 | W31: 0.002992 | X31: 0.002971 | Y31: 0.002982 | Z31: 0.003004 | AA31: 0.003021 | AB31: 0.003044 | AC31: 0.003045 | AD31: 0.003054 | AE31: 0.003072 | AF31: 0.003086 | AG31: 0.003102 | AH31: 0.010163
A32: QUA000:da_PetroleumSubt | B32: Petroleum and Other Liquids Subtotal | C32: 0.80576 | D32: 0.84775 | E32: 0.863505 | F32: 0.867191 | G32: 0.872253 | H32: 0.878713 | I32: 0.87962 | J32: 0.880149 | K32: 0.878488 | L32: 0.877464 | M32: 0.875051 | N32: 0.874424 | O32: 0.873537 | P32: 0.873601 | Q32: 0.873823 | R32: 0.874279 | S32: 0.874631 | T32: 0.874627 | U32: 0.874291 | V32: 0.874688 | W32: 0.874114 | X32: 0.873877 | Y32: 0.873997 | Z32: 0.874072 | AA32: 0.874756 | AB32: 0.875681 | AC32: 0.875912 | AD32: 0.876292 | AE32: 0.877114 | AF32: 0.878064 | AG32: 0.879122 | AH32: 0.002909
A33: QUA000:da_NaturalGas | B33: Natural Gas | C33: 3.313039 | D33: 3.422087 | E33: 3.39352 | F33: 3.503651 | G33: 3.569261 | H33: 3.628121 | I33: 3.634718 | J33: 3.636774 | K33: 3.637975 | L33: 3.636573 | M33: 3.628168 | N33: 3.629257 | O33: 3.634456 | P33: 3.639338 | Q33: 3.643619 | R33: 3.65011 | S33: 3.65797 | T33: 3.665039 | U33: 3.671028 | V33: 3.676408 | W33: 3.682669 | X33: 3.689942 | Y33: 3.697488 | Z33: 3.704461 | AA33: 3.711992 | AB33: 3.717591 | AC33: 3.722889 | AD33: 3.726569 | AE33: 3.728961 | AF33: 3.729583 | AG33: 3.729169 | AH33: 0.003952
A34: QUA000:da_Coal | B34: Coal | C34: 0.01723 | D34: 0.01564 | E34: 0.014035 | F34: 0.015413 | G34: 0.015117 | H34: 0.014992 | I34: 0.014925 | J34: 0.014909 | K34: 0.014822 | L34: 0.014695 | M34: 0.014566 | N34: 0.014422 | O34: 0.014271 | P34: 0.014132 | Q34: 0.014 | R34: 0.013848 | S34: 0.013664 | T34: 0.013565 | U34: 0.01348 | V34: 0.013432 | W34: 0.013331 | X34: 0.013255 | Y34: 0.013177 | Z34: 0.013076 | AA34: 0.012991 | AB34: 0.012942 | AC34: 0.012859 | AD34: 0.012784 | AE34: 0.012731 | AF34: 0.01263 | AG34: 0.012529 | AH34: -0.010563
A35: QUA000:da_RenewableEner | B35: Renewable Energy 4/ | C35: 0.131216 | D35: 0.131216 | E35: 0.131216 | F35: 0.131216 | G35: 0.131216 | H35: 0.131216 | I35: 0.131216 | J35: 0.131216 | K35: 0.131216 | L35: 0.131216 | M35: 0.131216 | N35: 0.131216 | O35: 0.131216 | P35: 0.131216 | Q35: 0.131216 | R35: 0.131216 | S35: 0.131216 | T35: 0.131216 | U35: 0.131216 | V35: 0.131216 | W35: 0.131216 | X35: 0.131216 | Y35: 0.131216 | Z35: 0.131216 | AA35: 0.131216 | AB35: 0.131216 | AC35: 0.131216 | AD35: 0.131216 | AE35: 0.131216 | AF35: 0.131216 | AG35: 0.131216 | AH35: 0
A36: QUA000:da_Electricity | B36: Purchased Electricity | C36: 4.33543 | D36: 4.395605 | E36: 4.490564 | F36: 4.557985 | G36: 4.63273 | H36: 4.705483 | I36: 4.714942 | J36: 4.72438 | K36: 4.737476 | L36: 4.750947 | M36: 4.759401 | N36: 4.772419 | O36: 4.796052 | P36: 4.814938 | Q36: 4.841106 | R36: 4.865653 | S36: 4.893783 | T36: 4.927176 | U36: 4.963278 | V36: 5.001215 | W36: 5.036965 | X36: 5.077383 | Y36: 5.118773 | Z36: 5.172633 | AA36: 5.224681 | AB36: 5.280979 | AC36: 5.340222 | AD36: 5.40219 | AE36: 5.469254 | AF36: 5.544512 | AG36: 5.624819 | AH36: 0.008717
A37: QUA000:da_DeliveredEner | B37: Delivered Energy | C37: 8.602675 | D37: 8.812298 | E37: 8.89284 | F37: 9.075455 | G37: 9.220575 | H37: 9.358524 | I37: 9.375421 | J37: 9.387427 | K37: 9.399977 | L37: 9.410897 | M37: 9.408401 | N37: 9.421737 | O37: 9.449532 | P37: 9.473225 | Q37: 9.503764 | R37: 9.535106 | S37: 9.571264 | T37: 9.611625 | U37: 9.653292 | V37: 9.696959 | W37: 9.738296 | X37: 9.785672 | Y37: 9.834651 | Z37: 9.895458 | AA37: 9.955635 | AB37: 10.018408 | AC37: 10.083097 | AD37: 10.149053 | AE37: 10.219275 | AF37: 10.296005 | AG37: 10.376855 | AH37: 0.00627
A38: QUA000:da_ElectricityRe | B38: Electricity Related Losses | C38: 8.080952 | D38: 8.184591 | E38: 8.399828 | F38: 8.356667 | G38: 8.324706 | H38: 8.21728 | I38: 8.009226 | J38: 7.933647 | K38: 7.911225 | L38: 7.904228 | M38: 7.901311 | N38: 7.903949 | O38: 7.89674 | P38: 7.897304 | Q38: 7.899065 | R38: 7.916457 | S38: 7.934237 | T38: 7.96243 | U38: 7.976492 | V38: 7.995452 | W38: 8.015583 | X38: 8.054189 | Y38: 8.094862 | Z38: 8.147943 | AA38: 8.195475 | AB38: 8.248356 | AC38: 8.311562 | AD38: 8.383004 | AE38: 8.472766 | AF38: 8.565417 | AG38: 8.653732 | AH38: 0.002285
A39: QUA000:da_Total | B39: Total | C39: 16.683628 | D39: 16.996889 | E39: 17.292667 | F39: 17.432121 | G39: 17.54528 | H39: 17.575806 | I39: 17.384647 | J39: 17.321075 | K39: 17.311203 | L39: 17.315125 | M39: 17.309711 | N39: 17.325686 | O39: 17.346272 | P39: 17.370529 | Q39: 17.402828 | R39: 17.451563 | S39: 17.505501 | T39: 17.574055 | U39: 17.629784 | V39: 17.69241 | W39: 17.75388 | X39: 17.839861 | Y39: 17.929512 | Z39: 18.0434 | AA39: 18.15111 | AB39: 18.266764 | AC39: 18.394659 | AD39: 18.532057 | AE39: 18.692041 | AF39: 18.861423 | AG39: 19.030586 | AH39: 0.004397
B41: Industrial 5/
A42: QUA000:ea_LiquefiedPetr | B42: Liquefied Petroleum Gases and Other 6/ | C42: 3.129955 | D42: 3.386781 | E42: 3.651851 | F42: 3.776361 | G42: 3.892941 | H42: 3.994641 | I42: 4.05975 | J42: 4.108074 | K42: 4.165377 | L42: 4.227348 | M42: 4.304934 | N42: 4.376987 | O42: 4.428152 | P42: 4.487323 | Q42: 4.555828 | R42: 4.623542 | S42: 4.666788 | T42: 4.718928 | U42: 4.768962 | V42: 4.79539 | W42: 4.804048 | X42: 4.828106 | Y42: 4.879942 | Z42: 4.921879 | AA42: 4.944526 | AB42: 4.980334 | AC42: 5.011189 | AD42: 5.043888 | AE42: 5.077971 | AF42: 5.142419 | AG42: 5.197212 | AH42: 0.017047
A43: QUA000:ea_MotorGasoline | B43: Motor Gasoline 3/ | C43: 0.238015 | D43: 0.259103 | E43: 0.266313 | F43: 0.273278 | G43: 0.279129 | H43: 0.285328 | I43: 0.290397 | J43: 0.294377 | K43: 0.297677 | L43: 0.301024 | M43: 0.304527 | N43: 0.3083 | O43: 0.311921 | P43: 0.315286 | Q43: 0.318999 | R43: 0.322577 | S43: 0.325664 | T43: 0.328823 | U43: 0.332402 | V43: 0.336007 | W43: 0.339763 | X43: 0.343731 | Y43: 0.347987 | Z43: 0.352715 | AA43: 0.357547 | AB43: 0.362092 | AC43: 0.36676 | AD43: 0.371305 | AE43: 0.376088 | AF43: 0.381094 | AG43: 0.386148 | AH43: 0.01626
A44: QUA000:ea_DistillateFue | B44: Distillate Fuel Oil | C44: 1.134867 | D44: 1.194101 | E44: 1.218216 | F44: 1.238876 | G44: 1.261172 | H44: 1.287802 | I44: 1.311676 | J44: 1.330589 | K44: 1.345493 | L44: 1.361019 | M44: 1.378233 | N44: 1.397494 | O44: 1.415234 | P44: 1.431922 | Q44: 1.450262 | R44: 1.469061 | S44: 1.484862 | T44: 1.500089 | U44: 1.517681 | V44: 1.535302 | W44: 1.552948 | X44: 1.573038 | Y44: 1.594831 | Z44: 1.6189 | AA44: 1.643961 | AB44: 1.668322 | AC44: 1.692229 | AD44: 1.715713 | AE44: 1.741043 | AF44: 1.768589 | AG44: 1.796802 | AH44: 0.015434
A45: QUA000:ea_ResidualFuel | B45: Residual Fuel Oil | C45: 0.03048 | D45: 0.034245 | E45: 0.034751 | F45: 0.034203 | G45: 0.033767 | H45: 0.034162 | I45: 0.03461 | J45: 0.035264 | K45: 0.035738 | L45: 0.036353 | M45: 0.036902 | N45: 0.037473 | O45: 0.037624 | P45: 0.038008 | Q45: 0.03837 | R45: 0.038572 | S45: 0.038748 | T45: 0.039002 | U45: 0.039153 | V45: 0.039356 | W45: 0.039151 | X45: 0.039204 | Y45: 0.039436 | Z45: 0.039724 | AA45: 0.03995 | AB45: 0.04008 | AC45: 0.040254 | AD45: 0.040476 | AE45: 0.040728 | AF45: 0.041022 | AG45: 0.041235 | AH45: 0.010125
A46: QUA000:ea_Petrochemical | B46: Petrochemical Feedstocks | C46: 0.580925 | D46: 0.607373 | E46: 0.641193 | F46: 0.642074 | G46: 0.644202 | H46: 0.64596 | I46: 0.647049 | J46: 0.647831 | K46: 0.648769 | L46: 0.649764 | M46: 0.650996 | N46: 0.652113 | O46: 0.652873 | P46: 0.653758 | Q46: 0.654771 | R46: 0.655756 | S46: 0.656368 | T46: 0.657105 | U46: 0.657801 | V46: 0.658146 | W46: 0.658242 | X46: 0.658551 | Y46: 0.659253 | Z46: 0.659804 | AA46: 0.660075 | AB46: 0.660527 | AC46: 0.660914 | AD46: 0.661325 | AE46: 0.661748 | AF46: 0.662582 | AG46: 0.663274 | AH46: 0.004429
A47: QUA000:ea_OtherPetroleu | B47: Other Petroleum 7/ | C47: 3.211545 | D47: 3.275826 | E47: 3.277059 | F47: 3.284837 | G47: 3.264796 | H47: 3.294298 | I47: 3.313754 | J47: 3.340309 | K47: 3.368908 | L47: 3.400828 | M47: 3.418661 | N47: 3.443216 | O47: 3.464936 | P47: 3.480493 | Q47: 3.514555 | R47: 3.53166 | S47: 3.563787 | T47: 3.596627 | U47: 3.609115 | V47: 3.623469 | W47: 3.624057 | X47: 3.63597 | Y47: 3.646353 | Z47: 3.645204 | AA47: 3.659037 | AB47: 3.687069 | AC47: 3.693583 | AD47: 3.721316 | AE47: 3.758235 | AF47: 3.781746 | AG47: 3.822744 | AH47: 0.005824
A48: QUA000:ea_PetroleumSubt | B48: Petroleum and Other Liquids Subtotal | C48: 8.325787 | D48: 8.757428 | E48: 9.089382 | F48: 9.249629 | G48: 9.376008 | H48: 9.54219 | I48: 9.657236 | J48: 9.756444 | K48: 9.86196 | L48: 9.976336 | M48: 10.094254 | N48: 10.215582 | O48: 10.31074 | P48: 10.406791 | Q48: 10.532785 | R48: 10.641168 | S48: 10.736217 | T48: 10.840574 | U48: 10.925114 | V48: 10.987669 | W48: 11.01821 | X48: 11.0786 | Y48: 11.167805 | Z48: 11.238226 | AA48: 11.305096 | AB48: 11.398424 | AC48: 11.464931 | AD48: 11.554022 | AE48: 11.655814 | AF48: 11.777452 | AG48: 11.907414 | AH48: 0.011998
A49: QUA000:ea_NaturalGas | B49: Natural Gas | C49: 8.480199 | D49: 8.420031 | E49: 8.457843 | F49: 8.690195 | G49: 8.9474 | H49: 9.116912 | I49: 9.232755 | J49: 9.247999 | K49: 9.299183 | L49: 9.350673 | M49: 9.370773 | N49: 9.429444 | O49: 9.470813 | P49: 9.509675 | Q49: 9.590447 | R49: 9.675095 | S49: 9.755727 | T49: 9.840727 | U49: 9.936915 | V49: 10.038279 | W49: 10.120502 | X49: 10.204603 | Y49: 10.333222 | Z49: 10.464765 | AA49: 10.556852 | AB49: 10.630715 | AC49: 10.75218 | AD49: 10.858983 | AE49: 10.957294 | AF49: 11.081191 | AG49: 11.218058 | AH49: 0.00937
A50: QUA000:ea_NGastoLiquids | B50: Natural-Gas-to-Liquids Heat and Power | C50: 0 | D50: 0 | E50: 0 | F50: 0 | G50: 0 | H50: 0 | I50: 0 | J50: 0 | K50: 0 | L50: 0 | M50: 0 | N50: 0 | O50: 0 | P50: 0 | Q50: 0 | R50: 0 | S50: 0 | T50: 0 | U50: 0 | V50: 0 | W50: 0 | X50: 0 | Y50: 0 | Z50: 0 | AA50: 0 | AB50: 0 | AC50: 0 | AD50: 0 | AE50: 0 | AF50: 0 | AG50: 0 | AH50: --
A51: QUA000:ea_LeaseandPlant | B51: Lease and Plant Fuel 8/ | C51: 1.865005 | D51: 1.807725 | E51: 1.880965 | F51: 1.940857 | G51: 1.956549 | H51: 2.009153 | I51: 2.04349 | J51: 2.058817 | K51: 2.077655 | L51: 2.095453 | M51: 2.127038 | N51: 2.153266 | O51: 2.173402 | P51: 2.209553 | Q51: 2.233982 | R51: 2.235243 | S51: 2.236099 | T51: 2.244938 | U51: 2.252317 | V51: 2.270945 | W51: 2.291956 | X51: 2.306597 | Y51: 2.334318 | Z51: 2.374781 | AA51: 2.395294 | AB51: 2.395426 | AC51: 2.4162 | AD51: 2.424982 | AE51: 2.436641 | AF51: 2.43786 | AG51: 2.440809 | AH51: 0.009009
A52: QUA000:ea_liquefactexp | B52: Natural Gas to Liquefy Gas for Export 9/ | C52: 0.359971 | D52: 0.495002 | E52: 0.486455 | F52: 0.492486 | G52: 0.55065 | H52: 0.637189 | I52: 0.688292 | J52: 0.688292 | K52: 0.705733 | L52: 0.734957 | M52: 0.766067 | N52: 0.781622 | O52: 0.783508 | P52: 0.781622 | Q52: 0.781622 | R52: 0.781622 | S52: 0.783508 | T52: 0.781622 | U52: 0.781622 | V52: 0.781622 | W52: 0.783508 | X52: 0.781622 | Y52: 0.781622 | Z52: 0.781622 | AA52: 0.783508 | AB52: 0.781622 | AC52: 0.781622 | AD52: 0.781622 | AE52: 0.783508 | AF52: 0.781622 | AG52: 0.781622 | AH52: 0.026182
A53: QUA000:ea_NaturalGasSub | B53: Natural Gas Subtotal | C53: 10.705174 | D53: 10.722757 | E53: 10.825262 | F53: 11.123538 | G53: 11.454599 | H53: 11.763254 | I53: 11.964538 | J53: 11.995109 | K53: 12.082572 | L53: 12.181083 | M53: 12.263879 | N53: 12.364332 | O53: 12.427723 | P53: 12.500851 | Q53: 12.606051 | R53: 12.691959 | S53: 12.775334 | T53: 12.867287 | U53: 12.970854 | V53: 13.090845 | W53: 13.195967 | X53: 13.292822 | Y53: 13.449162 | Z53: 13.621167 | AA53: 13.735655 | AB53: 13.807764 | AC53: 13.950003 | AD53: 14.065587 | AE53: 14.177443 | AF53: 14.300673 | AG53: 14.440489 | AH53: 0.010027
A54: QUA000:ea_Metallurgical | B54: Metallurgical Coal | C54: 0.472651 | D54: 0.396053 | E54: 0.409342 | F54: 0.497934 | G54: 0.487983 | H54: 0.459444 | I54: 0.45658 | J54: 0.445446 | K54: 0.427121 | L54: 0.410139 | M54: 0.409786 | N54: 0.409278 | O54: 0.403979 | P54: 0.397242 | Q54: 0.397948 | R54: 0.399241 | S54: 0.395988 | T54: 0.396254 | U54: 0.399368 | V54: 0.400639 | W54: 0.394742 | X54: 0.39587 | Y54: 0.404704 | Z54: 0.411097 | AA54: 0.408085 | AB54: 0.407256 | AC54: 0.406142 | AD54: 0.404236 | AE54: 0.406292 | AF54: 0.404858 | AG54: 0.410491 | AH54: -0.004689
A55: QUA000:ea_SteamCoal | B55: Other Industrial Coal | C55: 0.485064 | D55: 0.479342 | E55: 0.467267 | F55: 0.469155 | G55: 0.467591 | H55: 0.465023 | I55: 0.461107 | J55: 0.456313 | K55: 0.450373 | L55: 0.445088 | M55: 0.441326 | N55: 0.437861 | O55: 0.432432 | P55: 0.427447 | Q55: 0.422371 | R55: 0.422474 | S55: 0.422044 | T55: 0.421923 | U55: 0.422352 | V55: 0.422344 | W55: 0.422031 | X55: 0.422672 | Y55: 0.429467 | Z55: 0.437536 | AA55: 0.445413 | AB55: 0.456858 | AC55: 0.459755 | AD55: 0.46111 | AE55: 0.462832 | AF55: 0.465246 | AG55: 0.467751 | AH55: -0.001211
A56: QUA000:ea_CoaltoLiquids | B56: Coal-to-Liquids Heat and Power | C56: 0 | D56: 0 | E56: 0 | F56: 0 | G56: 0 | H56: 0 | I56: 0 | J56: 0 | K56: 0 | L56: 0 | M56: 0 | N56: 0 | O56: 0 | P56: 0 | Q56: 0 | R56: 0 | S56: 0 | T56: 0 | U56: 0 | V56: 0 | W56: 0 | X56: 0 | Y56: 0 | Z56: 0 | AA56: 0 | AB56: 0 | AC56: 0 | AD56: 0 | AE56: 0 | AF56: 0 | AG56: 0 | AH56: --
A57: QUA000:ea_NetCoalCokeIm | B57: Net Coal Coke Imports | C57: -0.024547 | D57: -0.024835 | E57: -0.02554 | F57: -0.031742 | G57: -0.024374 | H57: -0.023582 | I57: -0.023761 | J57: -0.023548 | K57: -0.023507 | L57: -0.02326 | M57: -0.022973 | N57: -0.022726 | O57: -0.022679 | P57: -0.022606 | Q57: -0.022517 | R57: -0.022372 | S57: -0.022432 | T57: -0.02229 | U57: -0.021985 | V57: -0.021855 | W57: -0.022059 | X57: -0.021782 | Y57: -0.021339 | Z57: -0.021006 | AA57: -0.021162 | AB57: -0.020932 | AC57: -0.020872 | AD57: -0.020801 | AE57: -0.020572 | AF57: -0.020467 | AG57: -0.019972 | AH57: -0.006852
A58: QUA000:ea_CoalSubtotal | B58: Coal Subtotal | C58: 0.933168 | D58: 0.85056 | E58: 0.85107 | F58: 0.935347 | G58: 0.931199 | H58: 0.900886 | I58: 0.893926 | J58: 0.878211 | K58: 0.853987 | L58: 0.831967 | M58: 0.82814 | N58: 0.824412 | O58: 0.813731 | P58: 0.802082 | Q58: 0.797802 | R58: 0.799344 | S58: 0.7956 | T58: 0.795887 | U58: 0.799736 | V58: 0.801128 | W58: 0.794715 | X58: 0.79676 | Y58: 0.812832 | Z58: 0.827626 | AA58: 0.832335 | AB58: 0.843183 | AC58: 0.845025 | AD58: 0.844545 | AE58: 0.848552 | AF58: 0.849637 | AG58: 0.858271 | AH58: -0.002785
A59: QUA000:ea_BiofuelsHeat | B59: Biofuels Heat and Coproducts | C59: 0.90481 | D59: 0.881071 | E59: 0.870692 | F59: 0.876051 | G59: 0.879 | H59: 0.885424 | I59: 0.888249 | J59: 0.890477 | K59: 0.892773 | L59: 0.895172 | M59: 0.899613 | N59: 0.909264 | O59: 0.912554 | P59: 0.917705 | Q59: 0.923903 | R59: 0.92998 | S59: 0.934801 | T59: 0.940007 | U59: 0.945402 | V59: 0.951611 | W59: 0.958427 | X59: 0.965089 | Y59: 0.973151 | Z59: 0.982176 | AA59: 0.991481 | AB59: 1.005407 | AC59: 1.010229 | AD59: 1.027637 | AE59: 1.037398 | AF59: 1.047914 | AG59: 1.058575 | AH59: 0.005246
A60: QUA000:ea_RenewableEner | B60: Renewable Energy 10/ | C60: 1.530173 | D60: 1.529323 | E60: 1.571694 | F60: 1.578229 | G60: 1.587089 | H60: 1.598157 | I60: 1.605324 | J60: 1.610516 | K60: 1.611536 | L60: 1.614317 | M60: 1.622251 | N60: 1.631606 | O60: 1.635719 | P60: 1.636937 | Q60: 1.636499 | R60: 1.643351 | S60: 1.648714 | T60: 1.655263 | U60: 1.666488 | V60: 1.67628 | W60: 1.685027 | X60: 1.698678 | Y60: 1.71467 | Z60: 1.732558 | AA60: 1.749739 | AB60: 1.767995 | AC60: 1.786321 | AD60: 1.806981 | AE60: 1.826772 | AF60: 1.849088 | AG60: 1.871858 | AH60: 0.006741
A61: QUA000:ea_Electricity | B61: Purchased Electricity | C61: 3.066925 | D61: 3.033747 | E61: 3.155422 | F61: 3.228214 | G61: 3.287128 | H61: 3.356304 | I61: 3.400323 | J61: 3.434094 | K61: 3.457919 | L61: 3.482108 | M61: 3.514578 | N61: 3.54587 | O61: 3.563427 | P61: 3.580147 | Q61: 3.605359 | R61: 3.626855 | S61: 3.646274 | T61: 3.665415 | U61: 3.689911 | V61: 3.713287 | W61: 3.727647 | X61: 3.752251 | Y61: 3.789032 | Z61: 3.827358 | AA61: 3.855139 | AB61: 3.881232 | AC61: 3.907388 | AD61: 3.931267 | AE61: 3.957234 | AF61: 3.987281 | AG61: 4.019121 | AH61: 0.009054
A62: QUA000:ea_DeliveredEner | B62: Delivered Energy | C62: 25.466036 | D62: 25.774887 | E62: 26.363525 | F62: 26.991009 | G62: 27.515024 | H62: 28.046213 | I62: 28.409595 | J62: 28.56485 | K62: 28.760748 | L62: 28.980982 | M62: 29.22271 | N62: 29.491066 | O62: 29.663893 | P62: 29.844513 | Q62: 30.1024 | R62: 30.332661 | S62: 30.53694 | T62: 30.764433 | U62: 30.997509 | V62: 31.220823 | W62: 31.379993 | X62: 31.5842 | Y62: 31.906652 | Z62: 32.229111 | AA62: 32.469444 | AB62: 32.704002 | AC62: 32.963894 | AD62: 33.230042 | AE62: 33.503212 | AF62: 33.812042 | AG62: 34.155727 | AH62: 0.009834
A63: QUA000:ea_ElectricityRe | B63: Electricity Related Losses | C63: 5.716542 | D63: 5.648819 | E63: 5.902377 | F63: 5.918647 | G63: 5.906751 | H63: 5.861182 | I63: 5.776096 | J63: 5.766871 | K63: 5.774463 | L63: 5.79324 | M63: 5.834721 | N63: 5.872573 | O63: 5.867213 | P63: 5.872041 | Q63: 5.882739 | R63: 5.900922 | S63: 5.911664 | T63: 5.923395 | U63: 5.930063 | V63: 5.93644 | W63: 5.931997 | X63: 5.952148 | Y63: 5.992001 | Z63: 6.028862 | AA63: 6.047199 | AB63: 6.062092 | AC63: 6.081488 | AD63: 6.100457 | AE63: 6.130401 | AF63: 6.159736 | AG63: 6.183382 | AH63: 0.00262
A64: QUA000:ea_Total | B64: Total | C64: 31.182579 | D64: 31.423706 | E64: 32.265903 | F64: 32.909657 | G64: 33.421776 | H64: 33.907394 | I64: 34.185692 | J64: 34.331722 | K64: 34.53521 | L64: 34.774223 | M64: 35.05743 | N64: 35.36364 | O64: 35.531105 | P64: 35.716553 | Q64: 35.985138 | R64: 36.233582 | S64: 36.448605 | T64: 36.687828 | U64: 36.92757 | V64: 37.157265 | W64: 37.311989 | X64: 37.536346 | Y64: 37.898651 | Z64: 38.257973 | AA64: 38.516644 | AB64: 38.766094 | AC64: 39.04538 | AD64: 39.330498 | AE64: 39.633614 | AF64: 39.971779 | AG64: 40.339108 | AH64: 0.008619
B67: Transportation
A68: QUA000:fa_LiquefiedPetr | B68: Propane | C68: 0.005676 | D68: 0.006142 | E68: 0.00644 | F68: 0.006643 | G68: 0.006731 | H68: 0.006854 | I68: 0.006891 | J68: 0.006942 | K68: 0.00701 | L68: 0.007066 | M68: 0.007171 | N68: 0.007233 | O68: 0.00733 | P68: 0.007418 | Q68: 0.007571 | R68: 0.00773 | S68: 0.007899 | T68: 0.008083 | U68: 0.008295 | V68: 0.008501 | W68: 0.008739 | X68: 0.008987 | Y68: 0.009254 | Z68: 0.009545 | AA68: 0.009837 | AB68: 0.01014 | AC68: 0.010475 | AD68: 0.010807 | AE68: 0.011172 | AF68: 0.011541 | AG68: 0.011937 | AH68: 0.025087
A69: QUA000:fa_MotorGasoline | B69: Motor Gasoline 3/ | C69: 14.825628 | D69: 15.479929 | E69: 15.47694 | F69: 15.473867 | G69: 15.415546 | H69: 15.333024 | I69: 15.227326 | J69: 15.118141 | K69: 15.013564 | L69: 14.89942 | M69: 14.799495 | N69: 14.704511 | O69: 14.617435 | P69: 14.553504 | Q69: 14.504936 | R69: 14.464999 | S69: 14.423914 | T69: 14.385998 | U69: 14.354929 | V69: 14.33661 | W69: 14.325787 | X69: 14.319191 | Y69: 14.328247 | Z69: 14.348844 | AA69: 14.373186 | AB69: 14.395925 | AC69: 14.422081 | AD69: 14.451188 | AE69: 14.487656 | AF69: 14.531824 | AG69: 14.57723 | AH69: -0.000563
A70: QUA000:fa_RenewableEner | B70: of which: E85 11/ | C70: 0.031355 | D70: 0.032398 | E70: 0.030669 | F70: 0.031647 | G70: 0.031379 | H70: 0.030842 | I70: 0.030282 | J70: 0.029645 | K70: 0.028837 | L70: 0.028178 | M70: 0.027454 | N70: 0.02699 | O70: 0.026454 | P70: 0.026108 | Q70: 0.025822 | R70: 0.02565 | S70: 0.025522 | T70: 0.02546 | U70: 0.025423 | V70: 0.025565 | W70: 0.025641 | X70: 0.025805 | Y70: 0.026045 | Z70: 0.026329 | AA70: 0.026668 | AB70: 0.027073 | AC70: 0.027345 | AD70: 0.027734 | AE70: 0.02813 | AF70: 0.028612 | AG70: 0.029113 | AH70: -0.002469
A71: QUA000:fa_JetFuel | B71: Jet Fuel 12/ | C71: 2.239766 | D71: 2.94322 | E71: 3.260282 | F71: 3.387979 | G71: 3.453038 | H71: 3.512743 | I71: 3.531354 | J71: 3.547649 | K71: 3.577601 | L71: 3.599448 | M71: 3.629601 | N71: 3.668208 | O71: 3.716035 | P71: 3.766056 | Q71: 3.816435 | R71: 3.865948 | S71: 3.904417 | T71: 3.938256 | U71: 3.976514 | V71: 4.016325 | W71: 4.063426 | X71: 4.109544 | Y71: 4.161732 | Z71: 4.215767 | AA71: 4.272788 | AB71: 4.325967 | AC71: 4.376675 | AD71: 4.422455 | AE71: 4.464754 | AF71: 4.503581 | AG71: 4.542726 | AH71: 0.023852
A72: QUA000:fa_DistillateFue | B72: Distillate Fuel Oil 13/ | C72: 6.148733 | D72: 6.264378 | E72: 6.317327 | F72: 6.337851 | G72: 6.365721 | H72: 6.43081 | I72: 6.413516 | J72: 6.390213 | K72: 6.350393 | L72: 6.306296 | M72: 6.242887 | N72: 6.220007 | O72: 6.174397 | P72: 6.137257 | Q72: 6.110685 | R72: 6.089855 | S72: 6.066423 | T72: 6.043742 | U72: 6.034866 | V72: 6.027445 | W72: 6.020275 | X72: 6.014647 | Y72: 6.045271 | Z72: 6.068172 | AA72: 6.094205 | AB72: 6.106401 | AC72: 6.127822 | AD72: 6.144786 | AE72: 6.165811 | AF72: 6.187714 | AG72: 6.212294 | AH72: 0.000343
A73: QUA000:fa_ResidualFuel | B73: Residual Fuel Oil | C73: 0.431201 | D73: 0.492962 | E73: 0.718001 | F73: 0.710785 | G73: 0.694213 | H73: 0.607188 | I73: 0.606914 | J73: 0.575014 | K73: 0.568901 | L73: 0.562858 | M73: 0.606374 | N73: 0.566538 | O73: 0.563786 | P73: 0.560095 | Q73: 0.556752 | R73: 0.553026 | S73: 0.550134 | T73: 0.553125 | U73: 0.545776 | V73: 0.54537 | W73: 0.521423 | X73: 0.537779 | Y73: 0.509859 | Z73: 0.508648 | AA73: 0.491502 | AB73: 0.502033 | AC73: 0.487508 | AD73: 0.478976 | AE73: 0.476321 | AF73: 0.475107 | AG73: 0.471498 | AH73: 0.002982
A74: QUA000:fa_OtherPetroleu | B74: Other Petroleum 14/ | C74: 0.143681 | D74: 0.145848 | E74: 0.14723 | F74: 0.14822 | G74: 0.148819 | H74: 0.149117 | I74: 0.149257 | J74: 0.148913 | K74: 0.148653 | L74: 0.148444 | M74: 0.148233 | N74: 0.148058 | O74: 0.147877 | P74: 0.147735 | Q74: 0.147676 | R74: 0.147568 | S74: 0.147412 | T74: 0.14727 | U74: 0.14716 | V74: 0.147041 | W74: 0.146913 | X74: 0.146835 | Y74: 0.146809 | Z74: 0.146738 | AA74: 0.146733 | AB74: 0.146809 | AC74: 0.14688 | AD74: 0.146925 | AE74: 0.146953 | AF74: 0.146928 | AG74: 0.146861 | AH74: 0.00073
A75: QUA000:fa_PetroleumSubt | B75: Petroleum and Other Liquids Subtotal | C75: 23.794685 | D75: 25.332483 | E75: 25.92622 | F75: 26.065344 | G75: 26.084072 | H75: 26.039738 | I75: 25.935257 | J75: 25.786875 | K75: 25.666121 | L75: 25.523537 | M75: 25.433762 | N75: 25.314556 | O75: 25.226858 | P75: 25.172064 | Q75: 25.144058 | R75: 25.129128 | S75: 25.100199 | T75: 25.076475 | U75: 25.067543 | V75: 25.081297 | W75: 25.086563 | X75: 25.136986 | Y75: 25.201174 | Z75: 25.297714 | AA75: 25.388252 | AB75: 25.487274 | AC75: 25.571445 | AD75: 25.655134 | AE75: 25.752668 | AF75: 25.856693 | AG75: 25.962549 | AH75: 0.002911
A76: QUA000:fa_PipelineFuelN | B76: Pipeline and Distribution Fuel Natural Gas | C76: 0.706279 | D76: 0.761893 | E76: 0.756583 | F76: 0.717939 | G76: 0.680358 | H76: 0.664904 | I76: 0.623404 | J76: 0.617932 | K76: 0.616836 | L76: 0.61629 | M76: 0.611481 | N76: 0.612707 | O76: 0.617871 | P76: 0.620412 | Q76: 0.622577 | R76: 0.627443 | S76: 0.630636 | T76: 0.634875 | U76: 0.63971 | V76: 0.643975 | W76: 0.650736 | X76: 0.654636 | Y76: 0.660259 | Z76: 0.668154 | AA76: 0.676052 | AB76: 0.681385 | AC76: 0.689326 | AD76: 0.693736 | AE76: 0.699616 | AF76: 0.706647 | AG76: 0.714589 | AH76: 0.00039
A77: QUA000:fa_CompressedNat | B77: Compressed / Liquefied Natural Gas | C77: 0.087413 | D77: 0.112686 | E77: 0.098007 | F77: 0.106604 | G77: 0.114226 | H77: 0.12744 | I77: 0.133401 | J77: 0.142133 | K77: 0.151514 | L77: 0.160446 | M77: 0.162399 | N77: 0.177616 | O77: 0.188904 | P77: 0.199357 | Q77: 0.210642 | R77: 0.222094 | S77: 0.232523 | T77: 0.242866 | U77: 0.256325 | V77: 0.266904 | W77: 0.289371 | X77: 0.301611 | Y77: 0.321344 | Z77: 0.337135 | AA77: 0.354106 | AB77: 0.365278 | AC77: 0.384663 | AD77: 0.401669 | AE77: 0.416112 | AF77: 0.431513 | AG77: 0.448153 | AH77: 0.055995
A78: QUA000:fa_LiquidHydroge | B78: Hydrogen | C78: 0.000382 | D78: 0.000481 | E78: 0.000581 | F78: 0.000679 | G78: 0.000776 | H78: 0.000874 | I78: 0.000966 | J78: 0.001057 | K78: 0.001148 | L78: 0.00124 | M78: 0.001336 | N78: 0.001432 | O78: 0.001528 | P78: 0.001625 | Q78: 0.001726 | R78: 0.001833 | S78: 0.001943 | T78: 0.00206 | U78: 0.002185 | V78: 0.002314 | W78: 0.002449 | X78: 0.00259 | Y78: 0.002743 | Z78: 0.002921 | AA78: 0.003075 | AB78: 0.003233 | AC78: 0.003397 | AD78: 0.003567 | AE78: 0.003746 | AF78: 0.003933 | AG78: 0.004129 | AH78: 0.082608
A79: QUA000:fa_Electricity | B79: Purchased Electricity | C79: 0.035472 | D79: 0.042675 | E79: 0.048665 | F79: 0.054239 | G79: 0.059386 | H79: 0.064576 | I79: 0.070818 | J79: 0.077282 | K79: 0.083912 | L79: 0.090831 | M79: 0.098704 | N79: 0.107215 | O79: 0.116773 | P79: 0.127278 | Q79: 0.138795 | R79: 0.151226 | S79: 0.164454 | T79: 0.178519 | U79: 0.193546 | V79: 0.209349 | W79: 0.22616 | X79: 0.243207 | Y79: 0.260836 | Z79: 0.278866 | AA79: 0.297652 | AB79: 0.315934 | AC79: 0.334685 | AD79: 0.353799 | AE79: 0.373428 | AF79: 0.393617 | AG79: 0.413887 | AH79: 0.085342
... A82: QUA000:fa_Total | B82: Total | C82: 24.690348 | D82: 26.329678 | E82: 26.921087 | F82: 27.044247 | G82: 27.04553 | H82: 27.0103 | I82: 26.884146 | J82: 26.755058 | K82: 26.659658 | L82: 26.543461 | M82: 26.471546 | N82: 26.391092 | O82: 26.3442 | P82: 26.329494 | Q82: 26.344267 | R82: 26.377769 | S82: 26.396383 | T82: 26.423286 | U82: 26.470358 | V82: 26.538525 | W82: 26.615179 | X82: 26.724829 | Y82: 26.858843 | Z82: 27.024063 | AA82: 27.186035 | AB82: 27.34656 | AC82: 27.504423 | AD82: 27.656923 | AE82: 27.824072 | AF82: 28.000483 | AG82: 28.180067 | AH82: 0.004416
B84: Unspecified Sector 15/
A85: QUA000:un_Total | B85: Total | C85: -0.414346 | D85: -0.427999 | E85: -0.431125 | F85: -0.432314 | G85: -0.433061 | H85: -0.435084 | I85: -0.433334 | J85: -0.431295 | K85: -0.428662 | L85: -0.425727 | M85: -0.422166 | N85: -0.420356 | O85: -0.417715 | P85: -0.41567 | Q85: -0.41422 | R85: -0.413094 | S85: -0.411815 | T85: -0.410586 | U85: -0.410011 | V85: -0.409633 | W85: -0.409364 | X85: -0.409199 | Y85: -0.410713 | Z85: -0.412032 | AA85: -0.413529 | AB85: -0.414424 | AC85: -0.41573 | AD85: -0.416866 | AE85: -0.418236 | AF85: -0.419711 | AG85: -0.42131 | AH85: 0.000556
B87: Delivered Energy Consumption, All Sectors
A88: QUA000:ga_LiquefiedPetr | B88: Liquefied Petroleum Gases and Other 6/ | C88: 3.759901 | D88: 4.037397 | E88: 4.300187 | F88: 4.422371 | G88: 4.536355 | H88: 4.635471 | I88: 4.698272 | J88: 4.744745 | K88: 4.800252 | L88: 4.860888 | M88: 4.93706 | N88: 5.008153 | O88: 5.058493 | P88: 5.117192 | Q88: 5.185595 | R88: 5.253543 | S88: 5.297086 | T88: 5.349627 | U88: 5.400108 | V88: 5.427143 | W88: 5.4365 | X88: 5.46134 | Y88: 5.514156 | Z88: 5.55716 | AA88: 5.581083 | AB88: 5.618559 | AC88: 5.650984 | AD88: 5.685195 | AE88: 5.720985 | AF88: 5.787308 | AG88: 5.844136 | AH88: 0.01481
A89: QUA000:ga_MotorGasoline | B89: Motor Gasoline 3/ | C89: 15.234125 | D89: 15.931428 | E89: 15.93966 | F89: 15.947531 | G89: 15.899977 | H89: 15.828622 | I89: 15.729457 | J89: 15.625776 | K89: 15.525605 | L89: 15.41626 | M89: 15.320666 | N89: 15.230912 | O89: 15.148534 | P89: 15.089048 | Q89: 15.045041 | R89: 15.0095 | S89: 14.972295 | T89: 14.938276 | U89: 14.911413 | V89: 14.89739 | W89: 14.890686 | X89: 14.888508 | Y89: 14.90217 | Z89: 14.927738 | AA89: 14.957181 | AB89: 14.984839 | AC89: 15.015745 | AD89: 15.049625 | AE89: 15.090983 | AF89: 15.14031 | AG89: 15.190861 | AH89: -9.5e-05
A90: QUA000:ga_E85 | B90: of which: E85 11/ | C90: 0.031355 | D90: 0.032398 | E90: 0.030669 | F90: 0.031647 | G90: 0.031379 | H90: 0.030842 | I90: 0.030282 | J90: 0.029645 | K90: 0.028837 | L90: 0.028178 | M90: 0.027454 | N90: 0.02699 | O90: 0.026454 | P90: 0.026108 | Q90: 0.025822 | R90: 0.02565 | S90: 0.025522 | T90: 0.02546 | U90: 0.025423 | V90: 0.025565 | W90: 0.025641 | X90: 0.025805 | Y90: 0.026045 | Z90: 0.026329 | AA90: 0.026668 | AB90: 0.027073 | AC90: 0.027345 | AD90: 0.027734 | AE90: 0.02813 | AF90: 0.028612 | AG90: 0.029113 | AH90: -0.002469
A91: QUA000:ga_JetFuel | B91: Jet Fuel 12/ | C91: 2.233072 | D91: 2.934424 | E91: 3.250538 | F91: 3.377854 | G91: 3.442719 | H91: 3.502245 | I91: 3.5208 | J91: 3.537047 | K91: 3.566909 | L91: 3.588691 | M91: 3.618754 | N91: 3.657245 | O91: 3.704929 | P91: 3.754801 | Q91: 3.80503 | R91: 3.854394 | S91: 3.892748 | T91: 3.926486 | U91: 3.96463 | V91: 4.004322 | W91: 4.051283 | X91: 4.097263 | Y91: 4.149295 | Z91: 4.203168 | AA91: 4.260019 | AB91: 4.313039 | AC91: 4.363595 | AD91: 4.409238 | AE91: 4.451411 | AF91: 4.490122 | AG91: 4.52915 | AH91: 0.023852
A92: QUA000:ga_Kerosene | B92: Kerosene 16/ | C92: 0.002953 | D92: 0.003123 | E92: 0.00314 | F92: 0.003219 | G92: 0.003201 | H92: 0.00327 | I92: 0.003167 | J92: 0.003123 | K92: 0.00301 | L92: 0.002964 | M92: 0.002856 | N92: 0.002814 | O92: 0.002759 | P92: 0.00273 | Q92: 0.002708 | R92: 0.002691 | S92: 0.002669 | T92: 0.002632 | U92: 0.002594 | V92: 0.00259 | W92: 0.00254 | X92: 0.002509 | Y92: 0.002488 | Z92: 0.002446 | AA92: 0.002443 | AB92: 0.002431 | AC92: 0.002399 | AD92: 0.002385 | AE92: 0.002389 | AF92: 0.002377 | AG92: 0.002373 | AH92: -0.007259
A93: QUA000:ga_DistillateFue | B93: Distillate Fuel Oil 1/ | C93: 7.767789 | D93: 7.975375 | E93: 8.058846 | F93: 8.083745 | G93: 8.118811 | H93: 8.196881 | I93: 8.193554 | J93: 8.180285 | K93: 8.146268 | L93: 8.10973 | M93: 8.056109 | N93: 8.044512 | O93: 8.009823 | P93: 7.983059 | Q93: 7.968435 | R93: 7.960275 | S93: 7.94667 | T93: 7.932901 | U93: 7.934589 | V93: 7.938445 | W93: 7.942032 | X93: 7.949625 | Y93: 7.993906 | Z93: 8.033015 | AA93: 8.076812 | AB93: 8.106768 | AC93: 8.144701 | AD93: 8.177801 | AE93: 8.217196 | AF93: 8.259703 | AG93: 8.305693 | AH93: 0.002234
A94: QUA000:ga_ResidualFuel | B94: Residual Fuel Oil | C94: 0.463971 | D94: 0.529496 | E94: 0.754909 | F94: 0.747268 | G94: 0.730815 | H94: 0.644931 | I94: 0.644857 | J94: 0.613583 | K94: 0.607844 | L94: 0.602382 | M94: 0.646373 | N94: 0.607094 | O94: 0.604461 | P94: 0.601156 | Q94: 0.598182 | R94: 0.594664 | S94: 0.59197 | T94: 0.595249 | U94: 0.588028 | V94: 0.587857 | W94: 0.563566 | X94: 0.579954 | Y94: 0.552277 | Z94: 0.551376 | AA94: 0.534473 | AB94: 0.545157 | AC94: 0.530807 | AD94: 0.522506 | AE94: 0.520122 | AF94: 0.519215 | AG94: 0.515835 | AH94: 0.003538
A95: QUA000:ga_Petrochemical | B95: Petrochemical Feedstocks | C95: 0.580925 | D95: 0.607373 | E95: 0.641193 | F95: 0.642074 | G95: 0.644202 | H95: 0.64596 | I95: 0.647049 | J95: 0.647831 | K95: 0.648769 | L95: 0.649764 | M95: 0.650996 | N95: 0.652113 | O95: 0.652873 | P95: 0.653758 | Q95: 0.654771 | R95: 0.655756 | S95: 0.656368 | T95: 0.657105 | U95: 0.657801 | V95: 0.658146 | W95: 0.658242 | X95: 0.658551 | Y95: 0.659253 | Z95: 0.659804 | AA95: 0.660075 | AB95: 0.660527 | AC95: 0.660914 | AD95: 0.661325 | AE95: 0.661748 | AF95: 0.662582 | AG95: 0.663274 | AH95: 0.004429
A96: QUA000:ga_OtherPetroleu | B96: Other Petroleum 17/ | C96: 3.353603 | D96: 3.420051 | E96: 3.422667 | F96: 3.431434 | G96: 3.411993 | H96: 3.441791 | I96: 3.461388 | J96: 3.487599 | K96: 3.515938 | L96: 3.547649 | M96: 3.565271 | N96: 3.589651 | O96: 3.61119 | P96: 3.626605 | Q96: 3.660608 | R96: 3.677605 | S96: 3.709575 | T96: 3.742274 | U96: 3.754652 | V96: 3.768887 | W96: 3.769348 | X96: 3.781182 | Y96: 3.791539 | Z96: 3.790318 | AA96: 3.804147 | AB96: 3.832256 | AC96: 3.838841 | AD96: 3.866618 | AE96: 3.903566 | AF96: 3.927051 | AG96: 3.967982 | AH96: 0.005623
A97: QUA000:ga_PetroleumSubt | B97: Petroleum and Other Liquids Subtotal | C97: 33.396339 | D97: 35.438667 | E97: 36.37114 | F97: 36.655495 | G97: 36.788071 | H97: 36.899174 | I97: 36.89854 | J97: 36.839989 | K97: 36.814598 | L97: 36.778328 | M97: 36.798084 | N97: 36.792492 | O97: 36.793064 | P97: 36.82835 | Q97: 36.920372 | R97: 37.008427 | S97: 37.069382 | T97: 37.144554 | U97: 37.213814 | V97: 37.284779 | W97: 37.314198 | X97: 37.41893 | Y97: 37.565083 | Z97: 37.725025 | AA97: 37.876232 | AB97: 38.06358 | AC97: 38.207985 | AD97: 38.374695 | AE97: 38.568401 | AF97: 38.788666 | AG97: 39.019306 | AH97: 0.005201
A98: QUA000:ga_NaturalGas | B98: Natural Gas | C98: 16.849998 | D98: 16.796188 | E98: 16.927792 | F98: 17.271154 | G98: 17.603264 | H98: 17.840502 | I98: 17.957037 | J98: 17.969683 | K98: 18.019943 | L98: 18.067831 | M98: 18.065098 | N98: 18.128229 | O98: 18.177223 | P98: 18.222895 | Q98: 18.31077 | R98: 18.407507 | S98: 18.50182 | T98: 18.599699 | U98: 18.711161 | V98: 18.824608 | W98: 18.933517 | X98: 19.035021 | Y98: 19.189274 | Z98: 19.342119 | AA98: 19.458303 | AB98: 19.547926 | AC98: 19.693399 | AD98: 19.819292 | AE98: 19.93239 | AF98: 20.06905 | AG98: 20.218792 | AH98: 0.006094
A99: QUA000:ga_NGastoLiquids | B99: Natural-Gas-to-Liquids Heat and Power | C99: 0 | D99: 0 | E99: 0 | F99: 0 | G99: 0 | H99: 0 | I99: 0 | J99: 0 | K99: 0 | L99: 0 | M99: 0 | N99: 0 | O99: 0 | P99: 0 | Q99: 0 | R99: 0 | S99: 0 | T99: 0 | U99: 0 | V99: 0 | W99: 0 | X99: 0 | Y99: 0 | Z99: 0 | AA99: 0 | AB99: 0 | AC99: 0 | AD99: 0 | AE99: 0 | AF99: 0 | AG99: 0 | AH99: --
A100: QUA000:ga_LeaseandPlant | B100: Lease and Plant Fuel 8/ | C100: 1.865005 | D100: 1.807725 | E100: 1.880965 | F100: 1.940857 | G100: 1.956549 | H100: 2.009153 | I100: 2.04349 | J100: 2.058817 | K100: 2.077655 | L100: 2.095453 | M100: 2.127038 | N100: 2.153266 | O100: 2.173402 | P100: 2.209553 | Q100: 2.233982 | R100: 2.235243 | S100: 2.236099 | T100: 2.244938 | U100: 2.252317 | V100: 2.270945 | W100: 2.291956 | X100: 2.306597 | Y100: 2.334318 | Z100: 2.374781 | AA100: 2.395294 | AB100: 2.395426 | AC100: 2.4162 | AD100: 2.424982 | AE100: 2.436641 | AF100: 2.43786 | AG100: 2.440809 | AH100: 0.009009
A101: QUA000:qa_liquefactexp | B101: Natural Gas to Liquefy Gas for Export 9/ | C101: 0.359971 | D101: 0.495002 | E101: 0.486455 | F101: 0.492486 | G101: 0.55065 | H101: 0.637189 | I101: 0.688292 | J101: 0.688292 | K101: 0.705733 | L101: 0.734957 | M101: 0.766067 | N101: 0.781622 | O101: 0.783508 | P101: 0.781622 | Q101: 0.781622 | R101: 0.781622 | S101: 0.783508 | T101: 0.781622 | U101: 0.781622 | V101: 0.781622 | W101: 0.783508 | X101: 0.781622 | Y101: 0.781622 | Z101: 0.781622 | AA101: 0.783508 | AB101: 0.781622 | AC101: 0.781622 | AD101: 0.781622 | AE101: 0.783508 | AF101: 0.781622 | AG101: 0.781622 | AH101: 0.026182
A102: QUA000:ga_PipelineNatur | B102: Pipeline and Distribution Fuel Natural Gas | C102: 0.706279 | D102: 0.761893 | E102: 0.756583 | F102: 0.717939 | G102: 0.680358 | H102: 0.664904 | I102: 0.623404 | J102: 0.617932 | K102: 0.616836 | L102: 0.61629 | M102: 0.611481 | N102: 0.612707 | O102: 0.617871 | P102: 0.620412 | Q102: 0.622577 | R102: 0.627443 | S102: 0.630636 | T102: 0.634875 | U102: 0.63971 | V102: 0.643975 | W102: 0.650736 | X102: 0.654636 | Y102: 0.660259 | Z102: 0.668154 | AA102: 0.676052 | AB102: 0.681385 | AC102: 0.689326 | AD102: 0.693736 | AE102: 0.699616 | AF102: 0.706647 | AG102: 0.714589 | AH102: 0.00039
A103: QUA000:ga_NaturalGasSub | B103: Natural Gas Subtotal | C103: 19.781252 | D103: 19.860807 | E103: 20.051792 | F103: 20.422438 | G103: 20.790821 | H103: 21.151749 | I103: 21.312222 | J103: 21.334723 | K103: 21.420168 | L103: 21.51453 | M103: 21.569683 | N103: 21.675825 | O103: 21.752005 | P103: 21.83448 | Q103: 21.948952 | R103: 22.051815 | S103: 22.152063 | T103: 22.261135 | U103: 22.384809 | V103: 22.521149 | W103: 22.659718 | X103: 22.777876 | Y103: 22.965473 | Z103: 23.166676 | AA103: 23.313158 | AB103: 23.406359 | AC103: 23.580547 | AD103: 23.719633 | AE103: 23.852156 | AF103: 23.99518 | AG103: 24.155813 | AH103: 0.006682
A104: QUA000:ga_Metallurgical | B104: Metallurgical Coal | C104: 0.472651 | D104: 0.396053 | E104: 0.409342 | F104: 0.497934 | G104: 0.487983 | H104: 0.459444 | I104: 0.45658 | J104: 0.445446 | K104: 0.427121 | L104: 0.410139 | M104: 0.409786 | N104: 0.409278 | O104: 0.403979 | P104: 0.397242 | Q104: 0.397948 | R104: 0.399241 | S104: 0.395988 | T104: 0.396254 | U104: 0.399368 | V104: 0.400639 | W104: 0.394742 | X104: 0.39587 | Y104: 0.404704 | Z104: 0.411097 | AA104: 0.408085 | AB104: 0.407256 | AC104: 0.406142 | AD104: 0.404236 | AE104: 0.406292 | AF104: 0.404858 | AG104: 0.410491 | AH104: -0.004689
A105: QUA000:ga_SteamCoal | B105: Other Coal | C105: 0.502295 | D105: 0.494981 | E105: 0.481302 | F105: 0.484568 | G105: 0.482708 | H105: 0.480016 | I105: 0.476032 | J105: 0.471221 | K105: 0.465195 | L105: 0.459783 | M105: 0.455892 | N105: 0.452283 | O105: 0.446702 | P105: 0.44158 | Q105: 0.436371 | R105: 0.436323 | S105: 0.435707 | T105: 0.435488 | U105: 0.435832 | V105: 0.435777 | W105: 0.435362 | X105: 0.435926 | Y105: 0.442644 | Z105: 0.450612 | AA105: 0.458404 | AB105: 0.469799 | AC105: 0.472613 | AD105: 0.473893 | AE105: 0.475563 | AF105: 0.477876 | AG105: 0.480282 | AH105: -0.001493
A106: QUA000:ga_CoaltoLiquids | B106: Coal-to-Liquids Heat and Power | C106: 0 | D106: 0 | E106: 0 | F106: 0 | G106: 0 | H106: 0 | I106: 0 | J106: 0 | K106: 0 | L106: 0 | M106: 0 | N106: 0 | O106: 0 | P106: 0 | Q106: 0 | R106: 0 | S106: 0 | T106: 0 | U106: 0 | V106: 0 | W106: 0 | X106: 0 | Y106: 0 | Z106: 0 | AA106: 0 | AB106: 0 | AC106: 0 | AD106: 0 | AE106: 0 | AF106: 0 | AG106: 0 | AH106: --
A107: QUA000:ga_NetCoalCokeIm | B107: Net Coal Coke Imports | C107: -0.024547 | D107: -0.024835 | E107: -0.02554 | F107: -0.031742 | G107: -0.024374 | H107: -0.023582 | I107: -0.023761 | J107: -0.023548 | K107: -0.023507 | L107: -0.02326 | M107: -0.022973 | N107: -0.022726 | O107: -0.022679 | P107: -0.022606 | Q107: -0.022517 | R107: -0.022372 | S107: -0.022432 | T107: -0.02229 | U107: -0.021985 | V107: -0.021855 | W107: -0.022059 | X107: -0.021782 | Y107: -0.021339 | Z107: -0.021006 | AA107: -0.021162 | AB107: -0.020932 | AC107: -0.020872 | AD107: -0.020801 | AE107: -0.020572 | AF107: -0.020467 | AG107: -0.019972 | AH107: -0.006852
A108: QUA000:ga_CoalSubtotal | B108: Coal Subtotal | C108: 0.9504 | D108: 0.866199 | E108: 0.865104 | F108: 0.95076 | G108: 0.946316 | H108: 0.915878 | I108: 0.908851 | J108: 0.893119 | K108: 0.86881 | L108: 0.846662 | M108: 0.842706 | N108: 0.838835 | O108: 0.828002 | P108: 0.816215 | Q108: 0.811802 | R108: 0.813192 | S108: 0.809263 | T108: 0.809452 | U108: 0.813215 | V108: 0.814561 | W108: 0.808045 | X108: 0.810014 | Y108: 0.826009 | Z108: 0.840702 | AA108: 0.845327 | AB108: 0.856124 | AC108: 0.857883 | AD108: 0.857328 | AE108: 0.861283 | AF108: 0.862267 | AG108: 0.870801 | AH108: -0.002911
A109: QUA000:ga_BiofuelsHeat | B109: Biofuels Heat and Coproducts | C109: 0.90481 | D109: 0.881071 | E109: 0.870692 | F109: 0.876051 | G109: 0.879 | H109: 0.885424 | I109: 0.888249 | J109: 0.890477 | K109: 0.892773 | L109: 0.895172 | M109: 0.899613 | N109: 0.909264 | O109: 0.912554 | P109: 0.917705 | Q109: 0.923903 | R109: 0.92998 | S109: 0.934801 | T109: 0.940007 | U109: 0.945402 | V109: 0.951611 | W109: 0.958427 | X109: 0.965089 | Y109: 0.973151 | Z109: 0.982176 | AA109: 0.991481 | AB109: 1.005407 | AC109: 1.010229 | AD109: 1.027637 | AE109: 1.037398 | AF109: 1.047914 | AG109: 1.058575 | AH109: 0.005246
A110: QUA000:ga_RenewableEner | B110: Renewable Energy 18/ | C110: 2.118901 | D110: 2.114872 | E110: 2.14682 | F110: 2.158356 | G110: 2.172631 | H110: 2.18569 | I110: 2.19188 | J110: 2.193553 | K110: 2.191645 | L110: 2.190332 | M110: 2.193865 | N110: 2.19792 | O110: 2.196725 | P110: 2.191808 | Q110: 2.184678 | R110: 2.184351 | S110: 2.18244 | T110: 2.182643 | U110: 2.188304 | V110: 2.191944 | W110: 2.195666 | X110: 2.204685 | Y110: 2.216091 | Z110: 2.229931 | AA110: 2.242549 | AB110: 2.256356 | AC110: 2.271369 | AD110: 2.288787 | AE110: 2.304563 | AF110: 2.322775 | AG110: 2.341185 | AH110: 0.003331
A111: QUA000:ga_LiquidHydroge | B111: Hydrogen | C111: 0.000382 | D111: 0.000481 | E111: 0.000581 | F111: 0.000679 | G111: 0.000776 | H111: 0.000874 | I111: 0.000966 | J111: 0.001057 | K111: 0.001148 | L111: 0.00124 | M111: 0.001336 | N111: 0.001432 | O111: 0.001528 | P111: 0.001625 | Q111: 0.001726 | R111: 0.001833 | S111: 0.001943 | T111: 0.00206 | U111: 0.002185 | V111: 0.002314 | W111: 0.002449 | X111: 0.00259 | Y111: 0.002743 | Z111: 0.002921 | AA111: 0.003075 | AB111: 0.003233 | AC111: 0.003397 | AD111: 0.003567 | AE111: 0.003746 | AF111: 0.003933 | AG111: 0.004129 | AH111: 0.082608
A112: QUA000:ga_Electricity | B112: Purchased Electricity | C112: 12.490561 | D112: 12.557576 | E112: 12.785978 | F112: 12.942157 | G112: 13.094978 | H112: 13.257808 | I112: 13.339819 | J112: 13.411543 | K112: 13.480756 | L112: 13.552886 | M112: 13.630619 | N112: 13.715644 | O112: 13.802553 | P112: 13.883183 | Q112: 13.98575 | R112: 14.085832 | S112: 14.191536 | T112: 14.305477 | U112: 14.429239 | V112: 14.554337 | W112: 14.665446 | X112: 14.79136 | Y112: 14.932018 | Z112: 15.091609 | AA112: 15.240055 | AB112: 15.390182 | AC112: 15.545669 | AD112: 15.700813 | AE112: 15.865412 | AF112: 16.045347 | AG112: 16.235746 | AH112: 0.00878
A113: QUA000:ga_DeliveredEner | B113: Delivered Energy | C113: 69.642639 | D113: 71.719673 | E113: 73.09211 | F113: 74.005936 | G113: 74.672592 | H113: 75.2966 | I113: 75.540527 | J113: 75.564461 | K113: 75.669899 | L113: 75.779152 | M113: 75.935905 | N113: 76.131409 | O113: 76.28643 | P113: 76.473366 | Q113: 76.777184 | R113: 77.075432 | S113: 77.341431 | T113: 77.645325 | U113: 77.976974 | V113: 78.320694 | W113: 78.603951 | X113: 78.970551 | Y113: 79.480568 | Z113: 80.03904 | AA113: 80.511879 | AB113: 80.981239 | AC113: 81.477081 | AD113: 81.972458 | AE113: 82.492958 | AF113: 83.066078 | AG113: 83.685555 | AH113: 0.006142
...

Sheet Gas Futures
A1: MONTH | B1: OPTIONS | C1: CHART | D1: LAST | E1: CHANGE | F1: PRIOR | G1: OPEN | H1: HIGH | I1: LOW | J1: VOLUME | K1: UPDATED | L1: Month.year
F2: SETTLE
A3: 44743 | B3: OPT | D3: 8.735 | E3: -0.160 (-1.80%) | F3: 8.895 | G3: 8.811 | H3: 8.895 | I3: 8.285 | J3: 102769 | K3: 15:10:18 CT | L3: =CONCATENATE(MONTH(A3),".",YEAR(A3)) -> 7.2022
A4: NGN2 | K4: 44708 | L4: =CONCATENATE(MONTH(A4),".",YEAR(A4)) -> #VALUE!
A5: 44774 | B5: OPT | D5: 8.715 | E5: -0.165 (-1.86%) | F5: 8.88 | G5: 8.797 | H5: 8.875 | I5: 8.275 | J5: 22123 | K5: 15:10:18 CT | L5: =CONCATENATE(MONTH(A5),".",YEAR(A5)) -> 8.2022
A6: NGQ2 | K6: 44708 | L6: =CONCATENATE(MONTH(A6),".",YEAR(A6)) -> #VALUE!
A7: 44805 | B7: OPT | D7: 8.673 | E7: -0.164 (-1.86%) | F7: 8.837 | G7: 8.733 | H7: 8.832 | I7: 8.243 | J7: 18084 | K7: 15:10:18 CT | L7: =CONCATENATE(MONTH(A7),".",YEAR(A7)) -> 9.2022
A8: NGU2 | K8: 44708 | L8: =CONCATENATE(MONTH(A8),".",YEAR(A8)) -> #VALUE!
A9: 44835 | B9: OPT | D9: 8.643 | E9: -0.159 (-1.81%) | F9: 8.802 | G9: 8.731 | H9: 8.801 | I9: 8.211 | J9: 17486 | K9: 15:05:43 CT | L9: =CONCATENATE(MONTH(A9),".",YEAR(A9)) -> 10.2022
A10: NGV2 | K10: 44708 | L10: =CONCATENATE(MONTH(A10),".",YEAR(A10)) -> #VALUE!
A11: 44866 | B11: OPT | D11: 8.688 | E11: -0.146 (-1.65%) | F11: 8.834 | G11: 8.791 | H11: 8.826 | I11: 8.263 | J11: 9758 | K11: 15:05:00 CT | L11: =CONCATENATE(MONTH(A11),".",YEAR(A11)) -> 11.2022
A12: NGX2 | K12: 44708 | L12: =CONCATENATE(MONTH(A12),".",YEAR(A12)) -> #VALUE!
A13: 44896 | B13: OPT | D13: 8.737 | E13: -0.168 (-1.89%) | F13: 8.905 | G13: 8.863 | H13: 8.888 | I13: 8.322 | J13: 9744 | K13: 15:06:17 CT | L13: =CONCATENATE(MONTH(A13),".",YEAR(A13)) -> 12.2022
A14: NGZ2 | K14: 44708 | L14: =CONCATENATE(MONTH(A14),".",YEAR(A14)) -> #VALUE!
A15: 44927 | B15: OPT | D15: 8.809 | E15: -0.174 (-1.94%) | F15: 8.983 | G15: 8.923 | H15: 8.968 | I15: 8.409 | J15: 13637 | K15: 15:07:08 CT | L15: =CONCATENATE(MONTH(A15),".",YEAR(A15)) -> 1.2023
A16: NGF3 | K16: 44708 | L16: =CONCATENATE(MONTH(A16),".",YEAR(A16)) -> #VALUE!
A17: 44958 | B17: OPT | D17: 8.457 | E17: -0.168 (-1.95%) | F17: 8.625 | G17: 8.594 | H17: 8.594 | I17: 8.078 | J17: 6250 | K17: 15:07:08 CT | L17: =CONCATENATE(MONTH(A17),".",YEAR(A17)) -> 2.2023
A18: NGG3 | K18: 44708 | L18: =CONCATENATE(MONTH(A18),".",YEAR(A18)) -> #VALUE!
A19: 44986 | B19: OPT | D19: 7.081 | E19: -0.088 (-1.23%) | F19: 7.169 | G19: 7.11 | H19: 7.159 | I19: 6.827 | J19: 7959 | K19: 15:04:58 CT | L19: =CONCATENATE(MONTH(A19),".",YEAR(A19)) -> 3.2023
A20: NGH3 | K20: 44708 | L20: =CONCATENATE(MONTH(A20),".",YEAR(A20)) -> #VALUE!
A21: 45017 | B21: OPT | D21: 5.157 | E21: -0.016 (-0.31%) | F21: 5.173 | G21: 5.15 | H21: 5.216 | I21: 5.016 | J21: 7588 | K21: 14:59:59 CT | L21: =CONCATENATE(MONTH(A21),".",YEAR(A21)) -> 4.2023
A22: NGJ3 | K22: 44708 | L22: =CONCATENATE(MONTH(A22),".",YEAR(A22)) -> #VALUE!
A23: 45047 | B23: OPT | D23: 4.955 | E23: -0.012 (-0.24%) | F23: 4.967 | G23: 4.93 | H23: 5.016 | I23: 4.829 | J23: 2909 | K23: 14:59:55 CT | L23: =CONCATENATE(MONTH(A23),".",YEAR(A23)) -> 5.2023
A24: NGK3 | K24: 44708 | L24: =CONCATENATE(MONTH(A24),".",YEAR(A24)) -> #VALUE!
A25: 45078 | B25: OPT | D25: 5.036 | E25: +0.015 (+0.30%) | F25: 5.021 | G25: 5.003 | H25: 5.067 | I25: 4.887 | J25: 1958 | K25: 14:57:29 CT | L25: =CONCATENATE(MONTH(A25),".",YEAR(A25)) -> 6.2023
A26: NGM3 | K26: 44708 | L26: =CONCATENATE(MONTH(A26),".",YEAR(A26)) -> #VALUE!
A27: 45108 | B27: OPT | D27: 5.05 | E27: -0.010 (-0.20%) | F27: 5.06 | G27: 5.063 | H27: 5.09 | I27: 4.931 | J27: 1206 | K27: 15:03:53 CT | L27: =CONCATENATE(MONTH(A27),".",YEAR(A27)) -> 7.2023
A28: NGN3 | K28: 44708 | L28: =CONCATENATE(MONTH(A28),".",YEAR(A28)) -> #VALUE!
A29: 45139 | B29: OPT | D29: 5.054 | E29: +0.012 (+0.24%) | F29: 5.042 | G29: 4.943 | H29: 5.058 | I29: 4.912 | J29: 1526 | K29: 15:06:17 CT | L29: =CONCATENATE(MONTH(A29),".",YEAR(A29)) -> 8.2023
A30: NGQ3 | K30: 44708 | L30: =CONCATENATE(MONTH(A30),".",YEAR(A30)) -> #VALUE!
A31: 45170 | B31: OPT | D31: 4.983 | E31: -0.025 (-0.50%) | F31: 5.008 | G31: 5.012 | H31: 5.031 | I31: 4.876 | J31: 899 | K31: 15:03:53 CT | L31: =CONCATENATE(MONTH(A31),".",YEAR(A31)) -> 9.2023
A32: NGU3 | K32: 44708 | L32: =CONCATENATE(MONTH(A32),".",YEAR(A32)) -> #VALUE!
A33: 45200 | B33: OPT | D33: 5.063 | E33: -0.006 (-0.12%) | F33: 5.069 | G33: 5.041 | H33: 5.098 | I33: 4.94 | J33: 1847 | K33: 14:52:52 CT | L33: =CONCATENATE(MONTH(A33),".",YEAR(A33)) -> 10.2023
A34: NGV3 | K34: 44708 | L34: =CONCATENATE(MONTH(A34),".",YEAR(A34)) -> #VALUE!
A35: 45231 | B35: OPT | D35: 5.21 | E35: -0.009 (-0.17%) | F35: 5.219 | G35: 5.091 | H35: 5.238 | I35: 5.091 | J35: 787 | K35: 14:52:52 CT | L35: =CONCATENATE(MONTH(A35),".",YEAR(A35)) -> 11.2023
A36: NGX3 | K36: 44708 | L36: =CONCATENATE(MONTH(A36),".",YEAR(A36)) -> #VALUE!
A37: 45261 | B37: OPT | D37: 5.493 | E37: +0.001 (+0.02%) | F37: 5.492 | G37: 5.465 | H37: 5.522 | I37: 5.36 | J37: 783 | K37: 13:59:44 CT | L37: =CONCATENATE(MONTH(A37),".",YEAR(A37)) -> 12.2023
A38: NGZ3 | K38: 44708 | L38: =CONCATENATE(MONTH(A38),".",YEAR(A38)) -> #VALUE!
A39: 45292 | B39: OPT | D39: 5.62 | E39: -0.008 (-0.14%) | F39: 5.628 | G39: 5.62 | H39: 5.635 | I39: 5.51 | J39: 550 | K39: 13:59:44 CT | L39: =CONCATENATE(MONTH(A39),".",YEAR(A39)) -> 1.2024
A40: NGF4 | K40: 44708 | L40: =CONCATENATE(MONTH(A40),".",YEAR(A40)) -> #VALUE!
A41: 45323 | B41: OPT | D41: 5.442 | E41: +0.010 (+0.18%) | F41: 5.432 | G41: 5.33 | H41: 5.442 | I41: 5.33 | J41: 87 | K41: 14:22:10 CT | L41: =CONCATENATE(MONTH(A41),".",YEAR(A41)) -> 2.2024
A42: NGG4 | K42: 44708 | L42: =CONCATENATE(MONTH(A42),".",YEAR(A42)) -> #VALUE!
A43: 45352 | B43: OPT | D43: 4.996 | E43: UNCH (UNCH) | F43: 4.996 | G43: 4.996 | H43: 4.996 | I43: 4.996 | J43: 111 | K43: 14:22:10 CT | L43: =CONCATENATE(MONTH(A43),".",YEAR(A43)) -> 3.2024
A44: NGH4 | K44: 44708 | L44: =CONCATENATE(MONTH(A44),".",YEAR(A44)) -> #VALUE!
A45: 45383 | B45: OPT | D45: 4.228 | E45: +0.037 (+0.88%) | F45: 4.191 | G45: 4.174 | H45: 4.228 | I45: 4.15 | J45: 173 | K45: 13:59:44 CT | L45: =CONCATENATE(MONTH(A45),".",YEAR(A45)) -> 4.2024
A46: NGJ4 | K46: 44708 | L46: =CONCATENATE(MONTH(A46),".",YEAR(A46)) -> #VALUE!
A47: 45413 | B47: OPT | D47: 4.141 | E47: +0.027 (+0.66%) | F47: 4.114 | G47: 4.111 | H47: 4.159 | I47: 4.11 | J47: 35 | K47: 14:16:16 CT | L47: =CONCATENATE(MONTH(A47),".",YEAR(A47)) -> 5.2024
A48: NGK4 | K48: 44708 | L48: =CONCATENATE(MONTH(A48),".",YEAR(A48)) -> #VALUE!
A49: 45444 | B49: OPT | D49: 4.172 | E49: UNCH (UNCH) | F49: 4.172 | G49: 4.172 | H49: 4.172 | I49: 4.172 | J49: 38 | K49: 13:59:44 CT | L49: =CONCATENATE(MONTH(A49),".",YEAR(A49)) -> 6.2024
A50: NGM4 | K50: 44708 | L50: =CONCATENATE(MONTH(A50),".",YEAR(A50)) -> #VALUE!
A51: 45474 | B51: OPT | D51: - | E51: - | F51: 4.229 | G51: - | H51: - | I51: - | J51: 37 | K51: 13:59:44 CT | L51: =CONCATENATE(MONTH(A51),".",YEAR(A51)) -> 7.2024
A52: NGN4 | K52: 44708 | L52: =CONCATENATE(MONTH(A52),".",YEAR(A52)) -> #VALUE!
A53: 45505 | B53: OPT | D53: - | E53: - | F53: 4.24 | G53: - | H53: - | I53: - | J53: 0 | K53: 13:59:44 CT | L53: =CONCATENATE(MONTH(A53),".",YEAR(A53)) -> 8.2024
A54: NGQ4 | K54: 44708 | L54: =CONCATENATE(MONTH(A54),".",YEAR(A54)) -> #VALUE!
A55: 45536 | B55: OPT | D55: - | E55: - | F55: 4.222 | G55: - | H55: - | I55: - | J55: 1 | K55: 13:59:44 CT | L55: =CONCATENATE(MONTH(A55),".",YEAR(A55)) -> 9.2024
A56: NGU4 | K56: 44708 | L56: =CONCATENATE(MONTH(A56),".",YEAR(A56)) -> #VALUE!
A57: 45566 | B57: OPT | D57: 4.26 | E57: -0.018 (-0.42%) | F57: 4.278 | G57: 4.26 | H57: 4.26 | I57: 4.26 | J57: 2 | K57: 13:59:44 CT | L57: =CONCATENATE(MONTH(A57),".",YEAR(A57)) -> 10.2024
A58: NGV4 | K58: 44708 | L58: =CONCATENATE(MONTH(A58),".",YEAR(A58)) -> #VALUE!
A59: 45597 | B59: OPT | D59: - | E59: - | F59: 4.455 | G59: - | H59: - | I59: - | J59: 130 | K59: 13:59:44 CT | L59: =CONCATENATE(MONTH(A59),".",YEAR(A59)) -> 11.2024
A60: NGX4 | K60: 44708 | L60: =CONCATENATE(MONTH(A60),".",YEAR(A60)) -> #VALUE!
A61: 45627 | B61: OPT | D61: 4.81 | E61: -0.001 (-0.02%) | F61: 4.811 | G61: 4.81 | H61: 4.81 | I61: 4.81 | J61: 135 | K61: 13:59:44 CT | L61: =CONCATENATE(MONTH(A61),".",YEAR(A61)) -> 12.2024
A62: NGZ4 | K62: 44708 | L62: =CONCATENATE(MONTH(A62),".",YEAR(A62)) -> #VALUE!
A63: 45658 | B63: OPT | D63: - | E63: - | F63: 4.977 | G63: - | H63: - | I63: - | J63: 9 | K63: 13:59:44 CT | L63: =CONCATENATE(MONTH(A63),".",YEAR(A63)) -> 1.2025
A64: NGF5 | K64: 44708 | L64: =CONCATENATE(MONTH(A64),".",YEAR(A64)) -> #VALUE!
A65: 45689 | B65: OPT | D65: - | E65: - | F65: 4.844 | G65: - | H65: - | I65: - | J65: 0 | K65: 13:59:44 CT | L65: =CONCATENATE(MONTH(A65),".",YEAR(A65)) -> 2.2025
A66: NGG5 | K66: 44708 | L66: =CONCATENATE(MONTH(A66),".",YEAR(A66)) -> #VALUE!
A67: 45717 | B67: OPT | D67: - | E67: - | F67: 4.522 | G67: - | H67: - | I67: - | J67: 6 | K67: 13:59:44 CT | L67: =CONCATENATE(MONTH(A67),".",YEAR(A67)) -> 3.2025
A68: NGH5 | K68: 44708 | L68: =CONCATENATE(MONTH(A68),".",YEAR(A68)) -> #VALUE!
A69: 45748 | B69: OPT | D69: 3.97 | E69: +0.038 (+0.97%) | F69: 3.932 | G69: 3.97 | H69: 3.97 | I69: 3.97 | J69: 9 | K69: 13:59:44 CT | L69: =CONCATENATE(MONTH(A69),".",YEAR(A69)) -> 4.2025
A70: NGJ5 | K70: 44708 | L70: =CONCATENATE(MONTH(A70),".",YEAR(A70)) -> #VALUE!
A71: 45778 | B71: OPT | D71: - | E71: - | F71: 3.892 | G71: - | H71: - | I71: - | J71: 2 | K71: 13:59:44 CT | L71: =CONCATENATE(MONTH(A71),".",YEAR(A71)) -> 5.2025
A72: NGK5 | K72: 44708 | L72: =CONCATENATE(MONTH(A72),".",YEAR(A72)) -> #VALUE!
A73: 45809 | B73: OPT | D73: - | E73: - | F73: 3.952 | G73: - | H73: - | I73: - | J73: 1 | K73: 13:59:44 CT | L73: =CONCATENATE(MONTH(A73),".",YEAR(A73)) -> 6.2025
A74: NGM5 | K74: 44708 | L74: =CONCATENATE(MONTH(A74),".",YEAR(A74)) -> #VALUE!
A75: 45839 | B75: OPT | D75: - | E75: - | F75: 4.006 | G75: - | H75: - | I75: - | J75: 0 | K75: 13:59:44 CT | L75: =CONCATENATE(MONTH(A75),".",YEAR(A75)) -> 7.2025
A76: NGN25 | K76: 44708 | L76: =CONCATENATE(MONTH(A76),".",YEAR(A76)) -> #VALUE!
A77: 45870 | B77: OPT | D77: - | E77: - | F77: 4.031 | G77: - | H77: - | I77: - | J77: 0 | K77: 13:59:44 CT | L77: =CONCATENATE(MONTH(A77),".",YEAR(A77)) -> 8.2025
A78: NGQ25 | K78: 44708 | L78: =CONCATENATE(MONTH(A78),".",YEAR(A78)) -> #VALUE!
A79: 45901 | B79: OPT | D79: - | E79: - | F79: 4.021 | G79: - | H79: - | I79: - | J79: 0 | K79: 13:59:44 CT | L79: =CONCATENATE(MONTH(A79),".",YEAR(A79)) -> 9.2025
A80: NGU25 | K80: 44708 | L80: =CONCATENATE(MONTH(A80),".",YEAR(A80)) -> #VALUE!
A81: 45931 | B81: OPT | D81: - | E81: - | F81: 4.088 | G81: - | H81: - | I81: - | J81: 0 | K81: 13:59:44 CT | L81: =CONCATENATE(MONTH(A81),".",YEAR(A81)) -> 10.2025
A82: NGV25 | K82: 44708 | L82: =CONCATENATE(MONTH(A82),".",YEAR(A82)) -> #VALUE!
A83: 45962 | B83: OPT | D83: - | E83: - | F83: 4.274 | G83: - | H83: - | I83: - | J83: 0 | K83: 13:59:44 CT | L83: =CONCATENATE(MONTH(A83),".",YEAR(A83)) -> 11.2025
A84: NGX25 | K84: 44708 | L84: =CONCATENATE(MONTH(A84),".",YEAR(A84)) -> #VALUE!
A85: 45992 | B85: OPT | D85: - | E85: - | F85: 4.641 | G85: - | H85: - | I85: - | J85: 0 | K85: 13:59:44 CT | L85: =CONCATENATE(MONTH(A85),".",YEAR(A85)) -> 12.2025
A86: NGZ25 | K86: 44708 | L86: =CONCATENATE(MONTH(A86),".",YEAR(A86)) -> #VALUE!
A87: 46023 | B87: OPT | D87: - | E87: - | F87: 4.829 | G87: - | H87: - | I87: - | J87: 0 | K87: 13:59:44 CT | L87: =CONCATENATE(MONTH(A87),".",YEAR(A87)) -> 1.2026
A88: NGF26 | K88: 44708 | L88: =CONCATENATE(MONTH(A88),".",YEAR(A88)) -> #VALUE!
A89: 46054 | B89: OPT | D89: 4.69 | E89: -0.018 (-0.38%) | F89: 4.708 | G89: 4.69 | H89: 4.69 | I89: 4.69 | J89: 5 | K89: 13:59:44 CT | L89: =CONCATENATE(MONTH(A89),".",YEAR(A89)) -> 2.2026
A90: NGG26 | K90: 44708 | L90: =CONCATENATE(MONTH(A90),".",YEAR(A90)) -> #VALUE!
A91: 46082 | B91: OPT | D91: - | E91: - | F91: 4.441 | G91: - | H91: - | I91: - | J91: 0 | K91: 13:59:44 CT | L91: =CONCATENATE(MONTH(A91),".",YEAR(A91)) -> 3.2026
A92: NGH26 | K92: 44708 | L92: =CONCATENATE(MONTH(A92),".",YEAR(A92)) -> #VALUE!
A93: 46113 | B93: OPT | D93: - | E93: - | F93: 3.971 | G93: - | H93: - | I93: - | J93: 0 | K93: 13:59:44 CT | L93: =CONCATENATE(MONTH(A93),".",YEAR(A93)) -> 4.2026
A94: NGJ26 | K94: 44708 | L94: =CONCATENATE(MONTH(A94),".",YEAR(A94)) -> #VALUE!
A95: 46143 | B95: OPT | D95: - | E95: - | F95: 3.957 | G95: - | H95: - | I95: - | J95: 0 | K95: 13:59:44 CT | L95: =CONCATENATE(MONTH(A95),".",YEAR(A95)) -> 5.2026
A96: NGK26 | K96: 44708 | L96: =CONCATENATE(MONTH(A96),".",YEAR(A96)) -> #VALUE!
A97: 46174 | B97: OPT | D97: - | E97: - | F97: 4.027 | G97: - | H97: - | I97: - | J97: 0 | K97: 13:59:44 CT | L97: =CONCATENATE(MONTH(A97),".",YEAR(A97)) -> 6.2026
A98: NGM26 | K98: 44708 | L98: =CONCATENATE(MONTH(A98),".",YEAR(A98)) -> #VALUE!
A99: 46204 | B99: OPT | D99: - | E99: - | F99: 4.092 | G99: - | H99: - | I99: - | J99: 0 | K99: 13:59:44 CT | L99: =CONCATENATE(MONTH(A99),".",YEAR(A99)) -> 7.2026
A100: NGN26 | K100: 44708 | L100: =CONCATENATE(MONTH(A100),".",YEAR(A100)) -> #VALUE!
...

Sheet Henry Hub Historicals
A1: Back to Contents | B1: Data 1: Spot Price
A2: Sourcekey | B2: RNGWHHD
A3: Date | B3: Henry Hub Natural Gas Spot Price (Dollars per Million Btu) | C3: Month.year
A4: 35445 | B4: 3.45 | C4: =CONCATENATE(MONTH(A4),".",YEAR(A4)) -> 1.1997
A5: 35476 | B5: 2.15 | C5: =CONCATENATE(MONTH(A5),".",YEAR(A5)) -> 2.1997
A6: 35504 | B6: 1.89 | C6: =CONCATENATE(MONTH(A6),".",YEAR(A6)) -> 3.1997
A7: 35535 | B7: 2.03 | C7: =CONCATENATE(MONTH(A7),".",YEAR(A7)) -> 4.1997
A8: 35565 | B8: 2.25 | C8: =CONCATENATE(MONTH(A8),".",YEAR(A8)) -> 5.1997
A9: 35596 | B9: 2.2 | C9: =CONCATENATE(MONTH(A9),".",YEAR(A9)) -> 6.1997
A10: 35626 | B10: 2.19 | C10: =CONCATENATE(MONTH(A10),".",YEAR(A10)) -> 7.1997
A11: 35657 | B11: 2.49 | C11: =CONCATENATE(MONTH(A11),".",YEAR(A11)) -> 8.1997
A12: 35688 | B12: 2.88 | C12: =CONCATENATE(MONTH(A12),".",YEAR(A12)) -> 9.1997
A13: 35718 | B13: 3.07 | C13: =CONCATENATE(MONTH(A13),".",YEAR(A13)) -> 10.1997
A14: 35749 | B14: 3.01 | C14: =CONCATENATE(MONTH(A14),".",YEAR(A14)) -> 11.1997
A15: 35779 | B15: 2.35 | C15: =CONCATENATE(MONTH(A15),".",YEAR(A15)) -> 12.1997
... A307: 44666 | B307: 6.6 | C307: =CONCATENATE(MONTH(A307),".",YEAR(A307)) -> 4.2022
A309: Back to Contents | B309: Data 1: Spot Price
A310: Sourcekey | B310: RNGWHHD
A311: Date | B311: Henry Hub Natural Gas Spot Price (Dollars per Million Btu)
A312: 35611 | B312: 2.49 | C312: 1997
A313: 35976 | B313: 2.09 | C313: 1998
A314: 36341 | B314: 2.27 | C314: 1999
A315: 36707 | B315: 4.31 | C315: 2000
A316: 37072 | B316: 3.96 | C316: 2001
A317: 37437 | B317: 3.38 | C317: 2002
A318: 37802 | B318: 5.47 | C318: 2003
A319: 38168 | B319: 5.89 | C319: 2004
A320: 38533 | B320: 8.69 | C320: 2005
A321: 38898 | B321: 6.73 | C321: 2006
A322: 39263 | B322: 6.97 | C322: 2007
A323: 39629 | B323: 8.86 | C323: 2008
... A336: 44377 | B336: 3.89 | C336: 2021

Sheet NG Sector Price Historicals
A1: Back to Contents | B1: Data 1: U.S. Natural Gas Prices
A2: Sourcekey | B2: N9190US3 | C2: N9100US3 | D2: N9102US3 | E2: N9103US3 | F2: N9130US3 | G2: N9132US3 | H2: N9133US3 | I2: NA1480_NUS_3 | J2: N3050US3 | K2: N3010US3 | L2: NA1504_NUS_4 | M2: N3020US3 | N2: N3020US4 | O2: N3035US3 | P2: N3035US4 | Q2: NA1570_NUS_3 | R2: N3045US3
A3: Date | B3: U.S. Natural Gas Wellhead Price (Dollars per Thousand Cubic Feet) | C3: Price of U.S. Natural Gas Imports (Dollars per Thousand Cubic Feet) | D3: U.S. Natural Gas Pipeline Imports Price (Dollars per Thousand Cubic Feet) | E3: Price of U.S. Natural Gas LNG Imports (Dollars per Thousand Cubic Feet) | F3: Price of U.S. Natural Gas Exports (Dollars per Thousand Cubic Feet) | G3: Price of U.S. Natural Gas Pipeline Exports (Dollars per Thousand Cubic Feet) | H3: Price of Liquefied U.S. Natural Gas Exports (Dollars per Thousand Cubic Feet) | I3: U.S. Natural Gas Pipeline and Distribution Use Price (Dollars per Thousand Cubic Feet) | J3: U.S. Natural Gas Citygate Price (Dollars per Thousand Cubic Feet) | K3: U.S. Price of Natural Gas Delivered to Residential Consumers (Dollars per Thousand Cubic Feet) | L3: U.S. Natural Gas % of Total Residential - Sales (%) | M3: U.S. Price of Natural Gas Sold to Commercial Consumers (Dollars per Thousand Cubic Feet) | N3: Percent of Commercial Natural Gas Deliveries in U.S. Total Represented by the Price (%) | O3: United States Natural Gas Industrial Price (Dollars per Thousand Cubic Feet) | P3: Percent of Industrial Natural Gas Deliveries in U.S. Total Represented by the Price (%) | Q3: U.S. Natural Gas Vehicle Fuel Price (Dollars per Thousand Cubic Feet) | R3: U.S. Natural Gas Electric Power Price (Dollars per Thousand Cubic Feet) | S3: Year
A4: 8217 | B4: 0.11 | S4: =YEAR(A4) -> 1922
A5: 8582 | B5: 0.1 | S5: =YEAR(A5) -> 1923
A6: 8948 | B6: 0.09 | S6: =YEAR(A6) -> 1924
A7: 9313 | B7: 0.09 | S7: =YEAR(A7) -> 1925
A8: 9678 | B8: 0.1 | S8: =YEAR(A8) -> 1926
A9: 10043 | B9: 0.09 | S9: =YEAR(A9) -> 1927
A10: 10409 | B10: 0.09 | S10: =YEAR(A10) -> 1928
A11: 10774 | B11: 0.08 | S11: =YEAR(A11) -> 1929
A12: 11139 | B12: 0.08 | S12: =YEAR(A12) -> 1930
A13: 11504 | B13: 0.07 | S13: =YEAR(A13) -> 1931
A14: 11870 | B14: 0.06 | S14: =YEAR(A14) -> 1932
A15: 12235 | B15: 0.06 | S15: =YEAR(A15) -> 1933
... A48: 24288 | B48: 0.16 | S48: =YEAR(A48) -> 1966
A49: 24653 | B49: 0.16 | I49: 0.2 | K49: 1.04 | M49: 0.74 | S49: =YEAR(A49) -> 1967
A50: 25019 | B50: 0.16 | I50: 0.2 | K50: 1.04 | M50: 0.73 | S50: =YEAR(A50) -> 1968
A51: 25384 | B51: 0.17 | I51: 0.21 | K51: 1.05 | M51: 0.74 | S51: =YEAR(A51) -> 1969
A52: 25749 | B52: 0.17 | I52: 0.21 | K52: 1.09 | M52: 0.77 | S52: =YEAR(A52) -> 1970
A53: 26114 | B53: 0.18 | I53: 0.22 | K53: 1.15 | M53: 0.82 | S53: =YEAR(A53) -> 1971
A54: 26480 | B54: 0.19 | I54: 0.23 | K54: 1.21 | M54: 0.88 | S54: =YEAR(A54) -> 1972
A55: 26845 | B55: 0.22 | I55: 0.25 | K55: 1.29 | M55: 0.94 | S55: =YEAR(A55) -> 1973
A56: 27210 | B56: 0.3 | I56: 0.3 | K56: 1.43 | M56: 1.07 | S56: =YEAR(A56) -> 1974
A57: 27575 | B57: 0.44 | I57: 0.4 | K57: 1.71 | M57: 1.35 | S57: =YEAR(A57) -> 1975
A58: 27941 | B58: 0.58 | I58: 0.51 | K58: 1.98 | M58: 1.64 | S58: =YEAR(A58) -> 1976
A59: 28306 | B59: 0.79 | I59: 0.77 | K59: 2.35 | M59: 2.04 | S59: =YEAR(A59) -> 1977
A60: 28671 | B60: 0.91 | I60: 0.9 | K60: 2.56 | M60: 2.23 | S60: =YEAR(A60) -> 1978
... A65: 30497 | B65: 2.59 | I65: 3.15 | K65: 6.06 | M65: 5.59 | S65: =YEAR(A65) -> 1983
A66: 30863 | B66: 2.66 | I66: 3.04 | J66: 3.95 | K66: 6.12 | M66: 5.55 | S66: =YEAR(A66) -> 1984
A67: 31228 | B67: 2.51 | C67: 3.21 | D67: 3.17 | E67: 4.6 | F67: 4.77 | G67: 3.92 | H67: 4.81 | I67: 2.92 | J67: 3.75 | K67: 6.12 | M67: 5.5 | S67: =YEAR(A67) -> 1985
A68: 31593 | B68: 1.94 | C68: 2.43 | D68: 2.42 | E68: 4.62 | F68: 2.81 | G68: 2.35 | H68: 2.91 | I68: 2.52 | J68: 3.22 | K68: 5.83 | M68: 5.08 | S68: =YEAR(A68) -> 1986
A69: 31958 | B69: 1.67 | C69: 1.95 | D69: 1.95 | F69: 3.07 | G69: 2.35 | H69: 3.15 | I69: 2.17 | J69: 2.87 | K69: 5.54 | M69: 4.77 | N69: 93.1 | S69: =YEAR(A69) -> 1987
A70: 32324 | B70: 1.69 | C70: 1.84 | D70: 1.83 | E70: 2.71 | F70: 2.74 | G70: 2.14 | H70: 2.98 | I70: 2.1 | J70: 2.92 | K70: 5.47 | M70: 4.63 | N70: 90.8 | S70: =YEAR(A70) -> 1988
A71: 32689 | B71: 1.69 | C71: 1.82 | D71: 1.81 | E71: 2.22 | F71: 2.51 | G71: 2.05 | H71: 3.01 | I71: 2.01 | J71: 3.01 | K71: 5.64 | L71: 99.9 | M71: 4.74 | N71: 89.1 | Q71: 4.17 | S71: =YEAR(A71) -> 1989
A72: 33054 | B72: 1.71 | C72: 1.94 | D72: 1.91 | E72: 2.47 | F72: 3.1 | G72: 2.31 | H72: 3.59 | I72: 1.95 | J72: 3.03 | K72: 5.8 | L72: 99.2 | M72: 4.83 | N72: 86.6 | Q72: 3.39 | S72: =YEAR(A72) -> 1990
A73: 33419 | B73: 1.64 | C73: 1.83 | D73: 1.81 | E73: 2.36 | F73: 2.59 | G73: 1.79 | H73: 3.71 | I73: 1.87 | J73: 2.9 | K73: 5.82 | L73: 99.2 | M73: 4.81 | N73: 85.1 | Q73: 3.96 | S73: =YEAR(A73) -> 1991
A74: 33785 | B74: 1.74 | C74: 1.85 | D74: 1.84 | E74: 2.54 | F74: 2.25 | G74: 1.88 | H74: 3.43 | I74: 2.07 | J74: 3.01 | K74: 5.89 | L74: 99.1 | M74: 4.88 | N74: 83.2 | Q74: 4.05 | S74: =YEAR(A74) -> 1992
A75: 34150 | B75: 2.04 | C75: 2.03 | D75: 2.02 | E75: 2.2 | F75: 2.59 | G75: 2.08 | H75: 3.34 | I75: 1.97 | J75: 3.21 | K75: 6.16 | L75: 99.1 | M75: 5.22 | N75: 83.9 | Q75: 4.27 | S75: =YEAR(A75) -> 1993
A76: 34515 | B76: 1.85 | C76: 1.87 | D76: 1.86 | E76: 2.28 | F76: 2.5 | G76: 2.08 | H76: 3.18 | I76: 1.7 | J76: 3.07 | K76: 6.41 | L76: 99.1 | M76: 5.44 | N76: 79.3 | Q76: 4.11 | S76: =YEAR(A76) -> 1994
A77: 34880 | B77: 1.55 | C77: 1.49 | D77: 1.48 | E77: 2.3 | F77: 2.39 | G77: 1.64 | H77: 3.41 | I77: 1.49 | J77: 2.78 | K77: 6.06 | L77: 99 | M77: 5.05 | N77: 76.7 | Q77: 3.98 | S77: =YEAR(A77) -> 1995
A78: 35246 | B78: 2.17 | C78: 1.97 | D78: 1.96 | E78: 2.8 | F78: 2.97 | G78: 2.45 | H78: 3.65 | I78: 2.27 | J78: 3.27 | K78: 6.34 | L78: 99 | M78: 5.4 | N78: 77.6 | Q78: 4.34 | S78: =YEAR(A78) -> 1996
A79: 35611 | B79: 2.32 | C79: 2.17 | D79: 2.15 | E79: 2.74 | F79: 3.02 | G79: 2.49 | H79: 3.83 | I79: 2.29 | J79: 3.66 | K79: 6.94 | L79: 98.8 | M79: 5.8 | N79: 70.8 | O79: 3.59 | P79: 18.1 | Q79: 4.44 | R79: 2.78 | S79: =YEAR(A79) -> 1997
A80: 35976 | B80: 1.96 | C80: 1.97 | D80: 1.95 | E80: 2.63 | F80: 2.45 | G80: 2.13 | H80: 2.91 | I80: 2.01 | J80: 3.07 | K80: 6.82 | L80: 97.7 | M80: 5.48 | N80: 67 | O80: 3.14 | P80: 16.1 | Q80: 4.59 | R80: 2.4 | S80: =YEAR(A80) -> 1998
A81: 36341 | B81: 2.19 | C81: 2.24 | D81: 2.23 | E81: 2.47 | F81: 2.61 | G81: 2.3 | H81: 3.1 | I81: 1.88 | J81: 3.1 | K81: 6.69 | L81: 95.2 | M81: 5.33 | N81: 66.1 | O81: 3.12 | P81: 18.8 | Q81: 4.34 | R81: 2.62 | S81: =YEAR(A81) -> 1999
A82: 36707 | B82: 3.68 | C82: 3.95 | D82: 3.98 | E82: 3.5 | F82: 4.1 | G82: 4.02 | H82: 4.32 | I82: 2.97 | J82: 4.62 | K82: 7.76 | L82: 92.6 | M82: 6.59 | N82: 63.9 | O82: 4.45 | P82: 19.8 | Q82: 5.54 | R82: 4.38 | S82: =YEAR(A82) -> 2000
A83: 37072 | B83: 4 | C83: 4.43 | D83: 4.44 | E83: 4.35 | F83: 4.19 | G83: 4.14 | H83: 4.4 | I83: 3.55 | J83: 5.72 | K83: 9.63 | L83: 92.4 | M83: 8.43 | N83: 66 | O83: 5.24 | P83: 20.8 | Q83: 6.6 | R83: 4.61 | S83: =YEAR(A83) -> 2001
A84: 37437 | B84: 2.95 | C84: 3.15 | D84: 3.13 | E84: 3.41 | F84: 3.41 | G84: 3.32 | H84: 4.08 | J84: 4.12 | K84: 7.89 | L84: 97.9 | M84: 6.63 | N84: 77.4 | O84: 4.02 | P84: 22.7 | Q84: 5.1 | R84: 3.68 | S84: =YEAR(A84) -> 2002
A85: 37802 | B85: 4.88 | C85: 5.17 | D85: 5.23 | E85: 4.79 | F85: 5.54 | G85: 5.66 | H85: 4.47 | J85: 5.85 | K85: 9.63 | L85: 97.5 | M85: 8.4 | N85: 78.2 | O85: 5.89 | P85: 22.1 | Q85: 6.19 | R85: 5.57 | S85: =YEAR(A85) -> 2003
A86: 38168 | B86: 5.46 | C86: 5.81 | D86: 5.8 | E86: 5.82 | F86: 6.09 | G86: 6.18 | H86: 4.96 | J86: 6.65 | K86: 10.75 | L86: 97.7 | M86: 9.43 | N86: 78 | O86: 6.53 | P86: 23.6 | Q86: 7.16 | R86: 6.11 | S86: =YEAR(A86) -> 2004
A87: 38533 | B87: 7.33 | C87: 8.12 | D87: 8.09 | E87: 8.26 | F87: 7.59 | G87: 7.77 | H87: 5.79 | J87: 8.67 | K87: 12.7 | L87: 98.1 | M87: 11.34 | N87: 82.1 | O87: 8.56 | P87: 24 | Q87: 9.14 | R87: 8.47 | S87: =YEAR(A87) -> 2005
A88: 38898 | B88: 6.39 | C88: 6.88 | D88: 6.83 | E88: 7.19 | F88: 6.83 | G88: 6.9 | H88: 6.02 | J88: 8.61 | K88: 13.73 | L88: 98.1 | M88: 12 | N88: 80.8 | O88: 7.87 | P88: 23.4 | Q88: 8.72 | R88: 7.11 | S88: =YEAR(A88) -> 2006
A89: 39263 | B89: 6.25 | C89: 6.87 | D89: 6.83 | E89: 7.07 | F89: 6.92 | G89: 6.96 | H89: 6.23 | J89: 8.16 | K89: 13.08 | L89: 98 | M89: 11.34 | N89: 80.4 | O89: 7.68 | P89: 22.2 | Q89: 8.5 | R89: 7.31 | S89: =YEAR(A89) -> 2007
A90: 39629 | B90: 7.97 | C90: 8.7 | D90: 8.57 | E90: 10.03 | F90: 8.58 | G90: 8.62 | H90: 7.69 | J90: 9.18 | K90: 13.89 | L90: 97.5 | M90: 12.23 | N90: 79.7 | O90: 9.65 | P90: 20.4 | Q90: 11.75 | R90: 9.26 | S90: =YEAR(A90) -> 2008
A91: 39994 | B91: 3.67 | C91: 4.19 | D91: 4.13 | E91: 4.59 | F91: 4.47 | G91: 4.34 | H91: 8.4 | J91: 6.48 | K91: 12.14 | L91: 97.4 | M91: 10.06 | N91: 77.8 | O91: 5.33 | P91: 18.8 | Q91: 8.13 | R91: 4.93 | S91: =YEAR(A91) -> 2009
A92: 40359 | B92: 4.48 | C92: 4.52 | D92: 4.46 | E92: 4.94 | F92: 5.02 | G92: 4.75 | H92: 9.53 | J92: 6.18 | K92: 11.39 | L92: 97.4 | M92: 9.47 | N92: 77.5 | O92: 5.49 | P92: 18 | Q92: 6.25 | R92: 5.27 | S92: =YEAR(A92) -> 2010
A93: 40724 | B93: 3.95 | C93: 4.24 | D93: 4.09 | E93: 5.63 | F93: 4.64 | G93: 4.35 | H93: 10.54 | J93: 5.63 | K93: 11.03 | L93: 96.3 | M93: 8.91 | N93: 67.3 | O93: 5.13 | P93: 16.3 | Q93: 7.48 | R93: 4.89 | S93: =YEAR(A93) -> 2011
A94: 41090 | B94: 2.66 | C94: 2.88 | D94: 2.79 | E94: 4.27 | F94: 3.25 | G94: 3.08 | H94: 12.82 | J94: 4.73 | K94: 10.65 | L94: 95.8 | M94: 8.1 | N94: 65.2 | O94: 3.88 | P94: 16.2 | Q94: 8.04 | R94: 3.54 | S94: =YEAR(A94) -> 2012
A95: 41455 | C95: 3.83 | D95: 3.73 | E95: 6.8 | F95: 4.08 | G95: 4.06 | H95: 13.36 | J95: 4.88 | K95: 10.32 | L95: 95.7 | M95: 8.08 | N95: 65.8 | O95: 4.64 | P95: 16.6 | R95: 4.49 | S95: =YEAR(A95) -> 2013
A96: 41820 | C96: 5.3 | D96: 5.21 | E96: 8.85 | F96: 5.51 | G96: 5.4 | H96: 15.66 | J96: 5.71 | K96: 10.97 | L96: 95.5 | M96: 8.9 | N96: 65.8 | O96: 5.62 | P96: 15.9 | R96: 5.19 | S96: =YEAR(A96) -> 2014
A97: 42185 | C97: 2.99 | D97: 2.84 | E97: 7.37 | F97: 3.07 | G97: 2.95 | H97: 10.92 | J97: 4.26 | K97: 10.38 | L97: 95.6 | M97: 7.91 | N97: 65.7 | O97: 3.93 | P97: 14.8 | R97: 3.38 | S97: =YEAR(A97) -> 2015
A98: 42551 | C98: 2.24 | D98: 2.18 | E98: 4.07 | F98: 2.79 | G98: 2.63 | H98: 4.71 | J98: 3.71 | K98: 10.05 | L98: 95.8 | M98: 7.28 | N98: 64.8 | O98: 3.51 | P98: 14.9 | R98: 2.99 | S98: =YEAR(A98) -> 2016
A99: 42916 | C99: 2.6 | D99: 2.55 | E99: 4.58 | F99: 3.54 | G99: 3.2 | H99: 4.69 | J99: 4.16 | K99: 10.91 | L99: 95.9 | M99: 7.88 | N99: 65.4 | O99: 4.08 | P99: 14.8 | R99: 3.51 | S99: =YEAR(A99) -> 2017
A100: 43281 | C100: 2.69 | D100: 2.58 | E100: 6.56 | F100: 3.89 | G100: 3.34 | H100: 5.2 | J100: 4.23 | K100: 10.5 | L100: 96 | M100: 7.79 | N100: 65.8 | O100: 4.19 | P100: 14.5 | R100: 3.68 | S100: =YEAR(A100) -> 2018
A101: 43646 | C101: 2.55 | D101: 2.46 | E101: 7.44 | F101: 3.64 | G101: 2.64 | H101: 5.21 | J101: 3.81 | K101: 10.51 | L101: 96.2 | M101: 7.61 | N101: 65.5 | O101: 3.9 | P101: 13 | R101: 2.99 | S101: =YEAR(A101) -> 2019
A102: 44012 | C102: 2.07 | D102: 2.02 | E102: 4.6 | F102: 3.7 | G102: 2.1 | H102: 5.64 | J102: 3.43 | K102: 10.78 | L102: 96.3 | M102: 7.49 | N102: 64.6 | O102: 3.32 | P102: 13.2 | R102: 2.48 | S102: =YEAR(A102) -> 2020
A103: 44377 | C103: 3.78 | D103: 3.72 | E103: 12.21 | F103: 6.38 | G103: 4.94 | H103: 7.62 | J103: 6.11 | K103: 12.24 | L103: 96.6 | M103: 8.78 | N103: 65.1 | O103: 5.5 | P103: 13.4 | R103: 5.16 | S103: =YEAR(A103) -> 2021

Sheet Historical Monthly Gas Cons
A1: Back to Contents | B1: Data 1: Natural Gas Delivered to Consumers in the U.S. (MMcf)
A2: Sourcekey | B2: N3060US2
A3: Date | B3: Natural Gas Delivered to Consumers in the U.S. (MMcf)
A4: 36906 | B4: 2505011 | C4: =MONTH(A4) -> 1 | D4: =YEAR(A4) -> 2001
A5: 36937 | B5: 2156873 | C5: =MONTH(A5) -> 2 | D5: =YEAR(A5) -> 2001
A6: 36965 | B6: 2086568 | C6: =MONTH(A6) -> 3 | D6: =YEAR(A6) -> 2001
A7: 36996 | B7: 1663832 | C7: =MONTH(A7) -> 4 | D7: =YEAR(A7) -> 2001
A8: 37026 | B8: 1385163 | C8: =MONTH(A8) -> 5 | D8: =YEAR(A8) -> 2001
A9: 37057 | B9: 1313119 | C9: =MONTH(A9) -> 6 | D9: =YEAR(A9) -> 2001
A10: 37087 | B10: 1459919 | C10: =MONTH(A10) -> 7 | D10: =YEAR(A10) -> 2001
A11: 37118 | B11: 1528483 | C11: =MONTH(A11) -> 8 | D11: =YEAR(A11) -> 2001
A12: 37149 | B12: 1360871 | C12: =MONTH(A12) -> 9 | D12: =YEAR(A12) -> 2001
A13: 37179 | B13: 1507428 | C13: =MONTH(A13) -> 10 | D13: =YEAR(A13) -> 2001
A14: 37210 | B14: 1561970 | C14: =MONTH(A14) -> 11 | D14: =YEAR(A14) -> 2001
A15: 37240 | B15: 1965873 | C15: =MONTH(A15) -> 12 | D15: =YEAR(A15) -> 2001
... A257: 44607 | B257: 2797164 | C257: =MONTH(A257) -> 2 | D257: =YEAR(A257) -> 2022

Sheet NG Calcs
A1: Historical Monthly Consumption Average
A2: 1 | B2: {=SUMPRODUCT(IF('Historical Monthly Gas Cons'!$C$4:$C$257='NG Calcs'!A2,IF('Historical Monthly Gas Cons'!$D$4:$D$257>2015,'Historical Monthly Gas Cons'!$B$4:$B$257))/SUMPRODUCT(IF('Historical Monthly Gas Cons'!$D$4:$D$257>2015,'Historical Monthly Gas Cons'!$B$4:$B$257)))} -> 0.12704635
A3: 2 | B3: {=SUMPRODUCT(IF('Historical Monthly Gas Cons'!$C$4:$C$257='NG Calcs'!A3,IF('Historical Monthly Gas Cons'!$D$4:$D$257>2015,'Historical Monthly Gas Cons'!$B$4:$B$257))/SUMPRODUCT(IF('Historical Monthly Gas Cons'!$D$4:$D$257>2015,'Historical Monthly Gas Cons'!$B$4:$B$257)))} -> 0.10957724
A4: 3 | B4: {=SUMPRODUCT(IF('Historical Monthly Gas Cons'!$C$4:$C$257='NG Calcs'!A4,IF('Historical Monthly Gas Cons'!$D$4:$D$257>2015,'Historical Monthly Gas Cons'!$B$4:$B$257))/SUMPRODUCT(IF('Historical Monthly Gas Cons'!$D$4:$D$257>2015,'Historical Monthly Gas Cons'!$B$4:$B$257)))} -> 0.08724036
A5: 4 | B5: {=SUMPRODUCT(IF('Historical Monthly Gas Cons'!$C$4:$C$257='NG Calcs'!A5,IF('Historical Monthly Gas Cons'!$D$4:$D$257>2015,'Historical Monthly Gas Cons'!$B$4:$B$257))/SUMPRODUCT(IF('Historical Monthly Gas Cons'!$D$4:$D$257>2015,'Historical Monthly Gas Cons'!$B$4:$B$257)))} -> 0.070786697
A6: 5 | B6: {=SUMPRODUCT(IF('Historical Monthly Gas Cons'!$C$4:$C$257='NG Calcs'!A6,IF('Historical Monthly Gas Cons'!$D$4:$D$257>2015,'Historical Monthly Gas Cons'!$B$4:$B$257))/SUMPRODUCT(IF('Historical Monthly Gas Cons'!$D$4:$D$257>2015,'Historical Monthly Gas Cons'!$B$4:$B$257)))} -> 0.065746454
A7: 6 | B7: {=SUMPRODUCT(IF('Historical Monthly Gas Cons'!$C$4:$C$257='NG Calcs'!A7,IF('Historical Monthly Gas Cons'!$D$4:$D$257>2015,'Historical Monthly Gas Cons'!$B$4:$B$257))/SUMPRODUCT(IF('Historical Monthly Gas Cons'!$D$4:$D$257>2015,'Historical Monthly Gas Cons'!$B$4:$B$257)))} -> 0.067228772
A8: 7 | B8: {=SUMPRODUCT(IF('Historical Monthly Gas Cons'!$C$4:$C$257='NG Calcs'!A8,IF('Historical Monthly Gas Cons'!$D$4:$D$257>2015,'Historical Monthly Gas Cons'!$B$4:$B$257))/SUMPRODUCT(IF('Historical Monthly Gas Cons'!$D$4:$D$257>2015,'Historical Monthly Gas Cons'!$B$4:$B$257)))} -> 0.075765383
A9: 8 | B9: {=SUMPRODUCT(IF('Historical Monthly Gas Cons'!$C$4:$C$257='NG Calcs'!A9,IF('Historical Monthly Gas Cons'!$D$4:$D$257>2015,'Historical Monthly Gas Cons'!$B$4:$B$257))/SUMPRODUCT(IF('Historical Monthly Gas Cons'!$D$4:$D$257>2015,'Historical Monthly Gas Cons'!$B$4:$B$257)))} -> 0.075220401
A10: 9 | B10: {=SUMPRODUCT(IF('Historical Monthly Gas Cons'!$C$4:$C$257='NG Calcs'!A10,IF('Historical Monthly Gas Cons'!$D$4:$D$257>2015,'Historical Monthly Gas Cons'!$B$4:$B$257))/SUMPRODUCT(IF('Historical Monthly Gas Cons'!$D$4:$D$257>2015,'Historical Monthly Gas Cons'!$B$4:$B$257)))} -> 0.067544195
A11: 10 | B11: {=SUMPRODUCT(IF('Historical Monthly Gas Cons'!$C$4:$C$257='NG Calcs'!A11,IF('Historical Monthly Gas Cons'!$D$4:$D$257>2015,'Historical Monthly Gas Cons'!$B$4:$B$257))/SUMPRODUCT(IF('Historical Monthly Gas Cons'!$D$4:$D$257>2015,'Historical Monthly Gas Cons'!$B$4:$B$257)))} -> 0.070774681
A12: 11 | B12: {=SUMPRODUCT(IF('Historical Monthly Gas Cons'!$C$4:$C$257='NG Calcs'!A12,IF('Historical Monthly Gas Cons'!$D$4:$D$257>2015,'Historical Monthly Gas Cons'!$B$4:$B$257))/SUMPRODUCT(IF('Historical Monthly Gas Cons'!$D$4:$D$257>2015,'Historical Monthly Gas Cons'!$B$4:$B$257)))} -> 0.082458275
A13: 12 | B13: {=SUMPRODUCT(IF('Historical Monthly Gas Cons'!$C$4:$C$257='NG Calcs'!A13,IF('Historical Monthly Gas Cons'!$D$4:$D$257>2015,'Historical Monthly Gas Cons'!$B$4:$B$257))/SUMPRODUCT(IF('Historical Monthly Gas Cons'!$D$4:$D$257>2015,'Historical Monthly Gas Cons'!$B$4:$B$257)))} -> 0.1006112
A15: Future Prices | B15: 2021 | C15: 2022 | D15: 2023 | E15: 2024 | F15: 2025
A16: 1 | B16: =INDEX('Henry Hub Historicals'!$B$4:$B$307,MATCH(CONCATENATE('NG Calcs'!$A16,".",'NG Calcs'!B$15),'Henry Hub Historicals'!$C$4:$C$307,0),1) -> 2.71 | C16: =IFERROR(IF(AND($A16<7,C$15<2023),INDEX('Henry Hub Historicals'!$B$4:$B$307,MATCH(CONCATENATE('NG Calcs'!$A16,".",'NG Calcs'!C$15),'Henry Hub Historicals'!$C$4:$C$307,0),1),INDEX('Gas Futures'!$F:$F,MATCH(CONCATENATE('NG Calcs'!$A16,".",'NG Calcs'!C$15),'Gas Futures'!$L:$L,0),1)),"") -> 4.38 | D16: =IFERROR(IF(AND($A16<4,D$15<2022),INDEX('Henry Hub Historicals'!$B$4:$B$307,MATCH(CONCATENATE('NG Calcs'!$A16,".",'NG Calcs'!D$15),'Henry Hub Historicals'!$C$4:$C$307,0),1),INDEX('Gas Futures'!$F:$F,MATCH(CONCATENATE('NG Calcs'!$A16,".",'NG Calcs'!D$15),'Gas Futures'!$L:$L,0),1)),"") -> 8.983 | E16: =IFERROR(IF(AND($A16<4,E$15<2022),INDEX('Henry Hub Historicals'!$B$4:$B$307,MATCH(CONCATENATE('NG Calcs'!$A16,".",'NG Calcs'!E$15),'Henry Hub Historicals'!$C$4:$C$307,0),1),INDEX('Gas Futures'!$F:$F,MATCH(CONCATENATE('NG Calcs'!$A16,".",'NG Calcs'!E$15),'Gas Futures'!$L:$L,0),1)),"") -> 5.628 | F16: =IFERROR(IF(AND($A16<4,F$15<2022),INDEX('Henry Hub Historicals'!$B$4:$B$307,MATCH(CONCATENATE('NG Calcs'!$A16,".",'NG Calcs'!F$15),'Henry Hub Historicals'!$C$4:$C$307,0),1),INDEX('Gas Futures'!$F:$F,MATCH(CONCATENATE('NG Calcs'!$A16,".",'NG Calcs'!F$15),'Gas Futures'!$L:$L,0),1)),"") -> 4.977
A17: 2 | B17: =INDEX('Henry Hub Historicals'!$B$4:$B$307,MATCH(CONCATENATE('NG Calcs'!$A17,".",'NG Calcs'!B$15),'Henry Hub Historicals'!$C$4:$C$307,0),1) -> 5.35 | C17: =IFERROR(IF(AND($A17<7,C$15<2023),INDEX('Henry Hub Historicals'!$B$4:$B$307,MATCH(CONCATENATE('NG Calcs'!$A17,".",'NG Calcs'!C$15),'Henry Hub Historicals'!$C$4:$C$307,0),1),INDEX('Gas Futures'!$F:$F,MATCH(CONCATENATE('NG Calcs'!$A17,".",'NG Calcs'!C$15),'Gas Futures'!$L:$L,0),1)),"") -> 4.69 | D17: =IFERROR(IF(AND($A17<4,D$15<2022),INDEX('Henry Hub Historicals'!$B$4:$B$307,MATCH(CONCATENATE('NG Calcs'!$A17,".",'NG Calcs'!D$15),'Henry Hub Historicals'!$C$4:$C$307,0),1),INDEX('Gas Futures'!$F:$F,MATCH(CONCATENATE('NG Calcs'!$A17,".",'NG Calcs'!D$15),'Gas Futures'!$L:$L,0),1)),"") -> 8.625 | E17: =IFERROR(IF(AND($A17<4,E$15<2022),INDEX('Henry Hub Historicals'!$B$4:$B$307,MATCH(CONCATENATE('NG Calcs'!$A17,".",'NG Calcs'!E$15),'Henry Hub Historicals'!$C$4:$C$307,0),1),INDEX('Gas Futures'!$F:$F,MATCH(CONCATENATE('NG Calcs'!$A17,".",'NG Calcs'!E$15),'Gas Futures'!$L:$L,0),1)),"") -> 5.432 | F17: =IFERROR(IF(AND($A17<4,F$15<2022),INDEX('Henry Hub Historicals'!$B$4:$B$307,MATCH(CONCATENATE('NG Calcs'!$A17,".",'NG Calcs'!F$15),'Henry Hub Historicals'!$C$4:$C$307,0),1),INDEX('Gas Futures'!$F:$F,MATCH(CONCATENATE('NG Calcs'!$A17,".",'NG Calcs'!F$15),'Gas Futures'!$L:$L,0),1)),"") -> 4.844
A18: 3 | B18: =INDEX('Henry Hub Historicals'!$B$4:$B$307,MATCH(CONCATENATE('NG Calcs'!$A18,".",'NG Calcs'!B$15),'Henry Hub Historicals'!$C$4:$C$307,0),1) -> 2.62 | C18: =IFERROR(IF(AND($A18<7,C$15<2023),INDEX('Henry Hub Historicals'!$B$4:$B$307,MATCH(CONCATENATE('NG Calcs'!$A18,".",'NG Calcs'!C$15),'Henry Hub Historicals'!$C$4:$C$307,0),1),INDEX('Gas Futures'!$F:$F,MATCH(CONCATENATE('NG Calcs'!$A18,".",'NG Calcs'!C$15),'Gas Futures'!$L:$L,0),1)),"") -> 4.9 | D18: =IFERROR(IF(AND($A18<4,D$15<2022),INDEX('Henry Hub Historicals'!$B$4:$B$307,MATCH(CONCATENATE('NG Calcs'!$A18,".",'NG Calcs'!D$15),'Henry Hub Historicals'!$C$4:$C$307,0),1),INDEX('Gas Futures'!$F:$F,MATCH(CONCATENATE('NG Calcs'!$A18,".",'NG Calcs'!D$15),'Gas Futures'!$L:$L,0),1)),"") -> 7.169 | E18: =IFERROR(IF(AND($A18<4,E$15<2022),INDEX('Henry Hub Historicals'!$B$4:$B$307,MATCH(CONCATENATE('NG Calcs'!$A18,".",'NG Calcs'!E$15),'Henry Hub Historicals'!$C$4:$C$307,0),1),INDEX('Gas Futures'!$F:$F,MATCH(CONCATENATE('NG Calcs'!$A18,".",'NG Calcs'!E$15),'Gas Futures'!$L:$L,0),1)),"") -> 4.996 | F18: =IFERROR(IF(AND($A18<4,F$15<2022),INDEX('Henry Hub Historicals'!$B$4:$B$307,MATCH(CONCATENATE('NG Calcs'!$A18,".",'NG Calcs'!F$15),'Henry Hub Historicals'!$C$4:$C$307,0),1),INDEX('Gas Futures'!$F:$F,MATCH(CONCATENATE('NG Calcs'!$A18,".",'NG Calcs'!F$15),'Gas Futures'!$L:$L,0),1)),"") -> 4.522
A19: 4 | B19: =INDEX('Henry Hub Historicals'!$B$4:$B$307,MATCH(CONCATENATE('NG Calcs'!$A19,".",'NG Calcs'!B$15),'Henry Hub Historicals'!$C$4:$C$307,0),1) -> 2.66 | C19: =IFERROR(IF(AND($A19<7,C$15<2023),INDEX('Henry Hub Historicals'!$B$4:$B$307,MATCH(CONCATENATE('NG Calcs'!$A19,".",'NG Calcs'!C$15),'Henry Hub Historicals'!$C$4:$C$307,0),1),INDEX('Gas Futures'!$F:$F,MATCH(CONCATENATE('NG Calcs'!$A19,".",'NG Calcs'!C$15),'Gas Futures'!$L:$L,0),1)),"") -> 6.6 | D19: =IFERROR(IF(AND($A19<4,D$15<2022),INDEX('Henry Hub Historicals'!$B$4:$B$307,MATCH(CONCATENATE('NG Calcs'!$A19,".",'NG Calcs'!D$15),'Henry Hub Historicals'!$C$4:$C$307,0),1),INDEX('Gas Futures'!$F:$F,MATCH(CONCATENATE('NG Calcs'!$A19,".",'NG Calcs'!D$15),'Gas Futures'!$L:$L,0),1)),"") -> 5.173 | E19: =IFERROR(IF(AND($A19<4,E$15<2022),INDEX('Henry Hub Historicals'!$B$4:$B$307,MATCH(CONCATENATE('NG Calcs'!$A19,".",'NG Calcs'!E$15),'Henry Hub Historicals'!$C$4:$C$307,0),1),INDEX('Gas Futures'!$F:$F,MATCH(CONCATENATE('NG Calcs'!$A19,".",'NG Calcs'!E$15),'Gas Futures'!$L:$L,0),1)),"") -> 4.191 | F19: =IFERROR(IF(AND($A19<4,F$15<2022),INDEX('Henry Hub Historicals'!$B$4:$B$307,MATCH(CONCATENATE('NG Calcs'!$A19,".",'NG Calcs'!F$15),'Henry Hub Historicals'!$C$4:$C$307,0),1),INDEX('Gas Futures'!$F:$F,MATCH(CONCATENATE('NG Calcs'!$A19,".",'NG Calcs'!F$15),'Gas Futures'!$L:$L,0),1)),"") -> 3.932
A20: 5 | B20: =INDEX('Henry Hub Historicals'!$B$4:$B$307,MATCH(CONCATENATE('NG Calcs'!$A20,".",'NG Calcs'!B$15),'Henry Hub Historicals'!$C$4:$C$307,0),1) -> 2.91 | C20: =($C$22-$C$19)/3+C19 -> 7.365 | D20: =IFERROR(IF(AND($A20<4,D$15<2022),INDEX('Henry Hub Historicals'!$B$4:$B$307,MATCH(CONCATENATE('NG Calcs'!$A20,".",'NG Calcs'!D$15),'Henry Hub Historicals'!$C$4:$C$307,0),1),INDEX('Gas Futures'!$F:$F,MATCH(CONCATENATE('NG Calcs'!$A20,".",'NG Calcs'!D$15),'Gas Futures'!$L:$L,0),1)),"") -> 4.967 | E20: =IFERROR(IF(AND($A20<4,E$15<2022),INDEX('Henry Hub Historicals'!$B$4:$B$307,MATCH(CONCATENATE('NG Calcs'!$A20,".",'NG Calcs'!E$15),'Henry Hub Historicals'!$C$4:$C$307,0),1),INDEX('Gas Futures'!$F:$F,MATCH(CONCATENATE('NG Calcs'!$A20,".",'NG Calcs'!E$15),'Gas Futures'!$L:$L,0),1)),"") -> 4.114 | F20: =IFERROR(IF(AND($A20<4,F$15<2022),INDEX('Henry Hub Historicals'!$B$4:$B$307,MATCH(CONCATENATE('NG Calcs'!$A20,".",'NG Calcs'!F$15),'Henry Hub Historicals'!$C$4:$C$307,0),1),INDEX('Gas Futures'!$F:$F,MATCH(CONCATENATE('NG Calcs'!$A20,".",'NG Calcs'!F$15),'Gas Futures'!$L:$L,0),1)),"") -> 3.892
A21: 6 | B21: =INDEX('Henry Hub Historicals'!$B$4:$B$307,MATCH(CONCATENATE('NG Calcs'!$A21,".",'NG Calcs'!B$15),'Henry Hub Historicals'!$C$4:$C$307,0),1) -> 3.26 | C21: =($C$22-$C$19)/3+C20 -> 8.13 | D21: =IFERROR(IF(AND($A21<4,D$15<2022),INDEX('Henry Hub Historicals'!$B$4:$B$307,MATCH(CONCATENATE('NG Calcs'!$A21,".",'NG Calcs'!D$15),'Henry Hub Historicals'!$C$4:$C$307,0),1),INDEX('Gas Futures'!$F:$F,MATCH(CONCATENATE('NG Calcs'!$A21,".",'NG Calcs'!D$15),'Gas Futures'!$L:$L,0),1)),"") -> 5.021 | E21: =IFERROR(IF(AND($A21<4,E$15<2022),INDEX('Henry Hub Historicals'!$B$4:$B$307,MATCH(CONCATENATE('NG Calcs'!$A21,".",'NG Calcs'!E$15),'Henry Hub Historicals'!$C$4:$C$307,0),1),INDEX('Gas Futures'!$F:$F,MATCH(CONCATENATE('NG Calcs'!$A21,".",'NG Calcs'!E$15),'Gas Futures'!$L:$L,0),1)),"") -> 4.172 | F21: =IFERROR(IF(AND($A21<4,F$15<2022),INDEX('Henry Hub Historicals'!$B$4:$B$307,MATCH(CONCATENATE('NG Calcs'!$A21,".",'NG Calcs'!F$15),'Henry Hub Historicals'!$C$4:$C$307,0),1),INDEX('Gas Futures'!$F:$F,MATCH(CONCATENATE('NG Calcs'!$A21,".",'NG Calcs'!F$15),'Gas Futures'!$L:$L,0),1)),"") -> 3.952
A22: 7 | B22: =INDEX('Henry Hub Historicals'!$B$4:$B$307,MATCH(CONCATENATE('NG Calcs'!$A22,".",'NG Calcs'!B$15),'Henry Hub Historicals'!$C$4:$C$307,0),1) -> 3.84 | C22: =IFERROR(IF(AND($A22<7,C$15<2023),INDEX('Henry Hub Historicals'!$B$4:$B$307,MATCH(CONCATENATE('NG Calcs'!$A22,".",'NG Calcs'!C$15),'Henry Hub Historicals'!$C$4:$C$307,0),1),INDEX('Gas Futures'!$F:$F,MATCH(CONCATENATE('NG Calcs'!$A22,".",'NG Calcs'!C$15),'Gas Futures'!$L:$L,0),1)),"") -> 8.895 | D22: =IFERROR(IF(AND($A22<4,D$15<2022),INDEX('Henry Hub Historicals'!$B$4:$B$307,MATCH(CONCATENATE('NG Calcs'!$A22,".",'NG Calcs'!D$15),'Henry Hub Historicals'!$C$4:$C$307,0),1),INDEX('Gas Futures'!$F:$F,MATCH(CONCATENATE('NG Calcs'!$A22,".",'NG Calcs'!D$15),'Gas Futures'!$L:$L,0),1)),"") -> 5.06 | E22: =IFERROR(IF(AND($A22<4,E$15<2022),INDEX('Henry Hub Historicals'!$B$4:$B$307,MATCH(CONCATENATE('NG Calcs'!$A22,".",'NG Calcs'!E$15),'Henry Hub Historicals'!$C$4:$C$307,0),1),INDEX('Gas Futures'!$F:$F,MATCH(CONCATENATE('NG Calcs'!$A22,".",'NG Calcs'!E$15),'Gas Futures'!$L:$L,0),1)),"") -> 4.229 | F22: =IFERROR(IF(AND($A22<4,F$15<2022),INDEX('Henry Hub Historicals'!$B$4:$B$307,MATCH(CONCATENATE('NG Calcs'!$A22,".",'NG Calcs'!F$15),'Henry Hub Historicals'!$C$4:$C$307,0),1),INDEX('Gas Futures'!$F:$F,MATCH(CONCATENATE('NG Calcs'!$A22,".",'NG Calcs'!F$15),'Gas Futures'!$L:$L,0),1)),"") -> 4.006
A23: 8 | B23: =INDEX('Henry Hub Historicals'!$B$4:$B$307,MATCH(CONCATENATE('NG Calcs'!$A23,".",'NG Calcs'!B$15),'Henry Hub Historicals'!$C$4:$C$307,0),1) -> 4.07 | C23: =IFERROR(IF(AND($A23<4,C$15<2022),INDEX('Henry Hub Historicals'!$B$4:$B$307,MATCH(CONCATENATE('NG Calcs'!$A23,".",'NG Calcs'!C$15),'Henry Hub Historicals'!$C$4:$C$307,0),1),INDEX('Gas Futures'!$F:$F,MATCH(CONCATENATE('NG Calcs'!$A23,".",'NG Calcs'!C$15),'Gas Futures'!$L:$L,0),1)),"") -> 8.88 | D23: =IFERROR(IF(AND($A23<4,D$15<2022),INDEX('Henry Hub Historicals'!$B$4:$B$307,MATCH(CONCATENATE('NG Calcs'!$A23,".",'NG Calcs'!D$15),'Henry Hub Historicals'!$C$4:$C$307,0),1),INDEX('Gas Futures'!$F:$F,MATCH(CONCATENATE('NG Calcs'!$A23,".",'NG Calcs'!D$15),'Gas Futures'!$L:$L,0),1)),"") -> 5.042 | E23: =IFERROR(IF(AND($A23<4,E$15<2022),INDEX('Henry Hub Historicals'!$B$4:$B$307,MATCH(CONCATENATE('NG Calcs'!$A23,".",'NG Calcs'!E$15),'Henry Hub Historicals'!$C$4:$C$307,0),1),INDEX('Gas Futures'!$F:$F,MATCH(CONCATENATE('NG Calcs'!$A23,".",'NG Calcs'!E$15),'Gas Futures'!$L:$L,0),1)),"") -> 4.24 | F23: =IFERROR(IF(AND($A23<4,F$15<2022),INDEX('Henry Hub Historicals'!$B$4:$B$307,MATCH(CONCATENATE('NG Calcs'!$A23,".",'NG Calcs'!F$15),'Henry Hub Historicals'!$C$4:$C$307,0),1),INDEX('Gas Futures'!$F:$F,MATCH(CONCATENATE('NG Calcs'!$A23,".",'NG Calcs'!F$15),'Gas Futures'!$L:$L,0),1)),"") -> 4.031
A24: 9 | B24: =INDEX('Henry Hub Historicals'!$B$4:$B$307,MATCH(CONCATENATE('NG Calcs'!$A24,".",'NG Calcs'!B$15),'Henry Hub Historicals'!$C$4:$C$307,0),1) -> 5.16 | C24: =IFERROR(IF(AND($A24<4,C$15<2022),INDEX('Henry Hub Historicals'!$B$4:$B$307,MATCH(CONCATENATE('NG Calcs'!$A24,".",'NG Calcs'!C$15),'Henry Hub Historicals'!$C$4:$C$307,0),1),INDEX('Gas Futures'!$F:$F,MATCH(CONCATENATE('NG Calcs'!$A24,".",'NG Calcs'!C$15),'Gas Futures'!$L:$L,0),1)),"") -> 8.837 | D24: =IFERROR(IF(AND($A24<4,D$15<2022),INDEX('Henry Hub Historicals'!$B$4:$B$307,MATCH(CONCATENATE('NG Calcs'!$A24,".",'NG Calcs'!D$15),'Henry Hub Historicals'!$C$4:$C$307,0),1),INDEX('Gas Futures'!$F:$F,MATCH(CONCATENATE('NG Calcs'!$A24,".",'NG Calcs'!D$15),'Gas Futures'!$L:$L,0),1)),"") -> 5.008 | E24: =IFERROR(IF(AND($A24<4,E$15<2022),INDEX('Henry Hub Historicals'!$B$4:$B$307,MATCH(CONCATENATE('NG Calcs'!$A24,".",'NG Calcs'!E$15),'Henry Hub Historicals'!$C$4:$C$307,0),1),INDEX('Gas Futures'!$F:$F,MATCH(CONCATENATE('NG Calcs'!$A24,".",'NG Calcs'!E$15),'Gas Futures'!$L:$L,0),1)),"") -> 4.222 | F24: =IFERROR(IF(AND($A24<4,F$15<2022),INDEX('Henry Hub Historicals'!$B$4:$B$307,MATCH(CONCATENATE('NG Calcs'!$A24,".",'NG Calcs'!F$15),'Henry Hub Historicals'!$C$4:$C$307,0),1),INDEX('Gas Futures'!$F:$F,MATCH(CONCATENATE('NG Calcs'!$A24,".",'NG Calcs'!F$15),'Gas Futures'!$L:$L,0),1)),"") -> 4.021
A25: 10 | B25: =INDEX('Henry Hub Historicals'!$B$4:$B$307,MATCH(CONCATENATE('NG Calcs'!$A25,".",'NG Calcs'!B$15),'Henry Hub Historicals'!$C$4:$C$307,0),1) -> 5.51 | C25: =IFERROR(IF(AND($A25<4,C$15<2022),INDEX('Henry Hub Historicals'!$B$4:$B$307,MATCH(CONCATENATE('NG Calcs'!$A25,".",'NG Calcs'!C$15),'Henry Hub Historicals'!$C$4:$C$307,0),1),INDEX('Gas Futures'!$F:$F,MATCH(CONCATENATE('NG Calcs'!$A25,".",'NG Calcs'!C$15),'Gas Futures'!$L:$L,0),1)),"") -> 8.802 | D25: =IFERROR(IF(AND($A25<4,D$15<2022),INDEX('Henry Hub Historicals'!$B$4:$B$307,MATCH(CONCATENATE('NG Calcs'!$A25,".",'NG Calcs'!D$15),'Henry Hub Historicals'!$C$4:$C$307,0),1),INDEX('Gas Futures'!$F:$F,MATCH(CONCATENATE('NG Calcs'!$A25,".",'NG Calcs'!D$15),'Gas Futures'!$L:$L,0),1)),"") -> 5.069 | E25: =IFERROR(IF(AND($A25<4,E$15<2022),INDEX('Henry Hub Historicals'!$B$4:$B$307,MATCH(CONCATENATE('NG Calcs'!$A25,".",'NG Calcs'!E$15),'Henry Hub Historicals'!$C$4:$C$307,0),1),INDEX('Gas Futures'!$F:$F,MATCH(CONCATENATE('NG Calcs'!$A25,".",'NG Calcs'!E$15),'Gas Futures'!$L:$L,0),1)),"") -> 4.278 | F25: =IFERROR(IF(AND($A25<4,F$15<2022),INDEX('Henry Hub Historicals'!$B$4:$B$307,MATCH(CONCATENATE('NG Calcs'!$A25,".",'NG Calcs'!F$15),'Henry Hub Historicals'!$C$4:$C$307,0),1),INDEX('Gas Futures'!$F:$F,MATCH(CONCATENATE('NG Calcs'!$A25,".",'NG Calcs'!F$15),'Gas Futures'!$L:$L,0),1)),"") -> 4.088
A26: 11 | B26: =INDEX('Henry Hub Historicals'!$B$4:$B$307,MATCH(CONCATENATE('NG Calcs'!$A26,".",'NG Calcs'!B$15),'Henry Hub Historicals'!$C$4:$C$307,0),1) -> 5.05 | C26: =IFERROR(IF(AND($A26<4,C$15<2022),INDEX('Henry Hub Historicals'!$B$4:$B$307,MATCH(CONCATENATE('NG Calcs'!$A26,".",'NG Calcs'!C$15),'Henry Hub Historicals'!$C$4:$C$307,0),1),INDEX('Gas Futures'!$F:$F,MATCH(CONCATENATE('NG Calcs'!$A26,".",'NG Calcs'!C$15),'Gas Futures'!$L:$L,0),1)),"") -> 8.834 | D26: =IFERROR(IF(AND($A26<4,D$15<2022),INDEX('Henry Hub Historicals'!$B$4:$B$307,MATCH(CONCATENATE('NG Calcs'!$A26,".",'NG Calcs'!D$15),'Henry Hub Historicals'!$C$4:$C$307,0),1),INDEX('Gas Futures'!$F:$F,MATCH(CONCATENATE('NG Calcs'!$A26,".",'NG Calcs'!D$15),'Gas Futures'!$L:$L,0),1)),"") -> 5.219 | E26: =IFERROR(IF(AND($A26<4,E$15<2022),INDEX('Henry Hub Historicals'!$B$4:$B$307,MATCH(CONCATENATE('NG Calcs'!$A26,".",'NG Calcs'!E$15),'Henry Hub Historicals'!$C$4:$C$307,0),1),INDEX('Gas Futures'!$F:$F,MATCH(CONCATENATE('NG Calcs'!$A26,".",'NG Calcs'!E$15),'Gas Futures'!$L:$L,0),1)),"") -> 4.455 | F26: =IFERROR(IF(AND($A26<4,F$15<2022),INDEX('Henry Hub Historicals'!$B$4:$B$307,MATCH(CONCATENATE('NG Calcs'!$A26,".",'NG Calcs'!F$15),'Henry Hub Historicals'!$C$4:$C$307,0),1),INDEX('Gas Futures'!$F:$F,MATCH(CONCATENATE('NG Calcs'!$A26,".",'NG Calcs'!F$15),'Gas Futures'!$L:$L,0),1)),"") -> 4.274
A27: 12 | B27: =INDEX('Henry Hub Historicals'!$B$4:$B$307,MATCH(CONCATENATE('NG Calcs'!$A27,".",'NG Calcs'!B$15),'Henry Hub Historicals'!$C$4:$C$307,0),1) -> 3.76 | C27: =IFERROR(IF(AND($A27<4,C$15<2022),INDEX('Henry Hub Historicals'!$B$4:$B$307,MATCH(CONCATENATE('NG Calcs'!$A27,".",'NG Calcs'!C$15),'Henry Hub Historicals'!$C$4:$C$307,0),1),INDEX('Gas Futures'!$F:$F,MATCH(CONCATENATE('NG Calcs'!$A27,".",'NG Calcs'!C$15),'Gas Futures'!$L:$L,0),1)),"") -> 8.905 | D27: =IFERROR(IF(AND($A27<4,D$15<2022),INDEX('Henry Hub Historicals'!$B$4:$B$307,MATCH(CONCATENATE('NG Calcs'!$A27,".",'NG Calcs'!D$15),'Henry Hub Historicals'!$C$4:$C$307,0),1),INDEX('Gas Futures'!$F:$F,MATCH(CONCATENATE('NG Calcs'!$A27,".",'NG Calcs'!D$15),'Gas Futures'!$L:$L,0),1)),"") -> 5.492 | E27: =IFERROR(IF(AND($A27<4,E$15<2022),INDEX('Henry Hub Historicals'!$B$4:$B$307,MATCH(CONCATENATE('NG Calcs'!$A27,".",'NG Calcs'!E$15),'Henry Hub Historicals'!$C$4:$C$307,0),1),INDEX('Gas Futures'!$F:$F,MATCH(CONCATENATE('NG Calcs'!$A27,".",'NG Calcs'!E$15),'Gas Futures'!$L:$L,0),1)),"") -> 4.811 | F27: =IFERROR(IF(AND($A27<4,F$15<2022),INDEX('Henry Hub Historicals'!$B$4:$B$307,MATCH(CONCATENATE('NG Calcs'!$A27,".",'NG Calcs'!F$15),'Henry Hub Historicals'!$C$4:$C$307,0),1),INDEX('Gas Futures'!$F:$F,MATCH(CONCATENATE('NG Calcs'!$A27,".",'NG Calcs'!F$15),'Gas Futures'!$L:$L,0),1)),"") -> 4.641
A30: Annual Average | B30: 2021 | C30: 2022 | D30: 2023 | E30: 2024 | F30: 2025
B31: =SUMPRODUCT(B16:B27,$B$2:$B$13) -> 3.8881792 | C31: =SUMPRODUCT(C16:C27,$B$2:$B$13) -> 7.1819589 | D31: =SUMPRODUCT(D16:D27,$B$2:$B$13) -> 6.1846438 | E31: =SUMPRODUCT(E16:E27,$B$2:$B$13) -> 4.6724037 | F31: =SUMPRODUCT(F16:F27,$B$2:$B$13) -> 4.3445242
A33: Henry Hub: Sector Price Ratio | B33: 2010 | C33: 2011 | D33: 2012 | E33: 2013 | F33: 2014 | G33: 2015 | H33: 2016 | I33: 2017 | J33: 2018 | K33: 2019 | L33: 2020
A34: Residential | B34: =INDEX('NG Sector Price Historicals'!$K$4:$K$103,MATCH('NG Calcs'!B$33,'NG Sector Price Historicals'!$S$4:$S$103,0),1)/INDEX('Henry Hub Historicals'!$B$312:$B$336,MATCH('NG Calcs'!B$33,'Henry Hub Historicals'!$C$312:$C$336,0),1)/1.037 -> 2.5134111 | C34: =INDEX('NG Sector Price Historicals'!$K$4:$K$103,MATCH('NG Calcs'!C$33,'NG Sector Price Historicals'!$S$4:$S$103,0),1)/INDEX('Henry Hub Historicals'!$B$312:$B$336,MATCH('NG Calcs'!C$33,'Henry Hub Historicals'!$C$312:$C$336,0),1)/1.037 -> 2.6591128 | D34: =INDEX('NG Sector Price Historicals'!$K$4:$K$103,MATCH('NG Calcs'!D$33,'NG Sector Price Historicals'!$S$4:$S$103,0),1)/INDEX('Henry Hub Historicals'!$B$312:$B$336,MATCH('NG Calcs'!D$33,'Henry Hub Historicals'!$C$312:$C$336,0),1)/1.037 -> 3.734549 | E34: =INDEX('NG Sector Price Historicals'!$K$4:$K$103,MATCH('NG Calcs'!E$33,'NG Sector Price Historicals'!$S$4:$S$103,0),1)/INDEX('Henry Hub Historicals'!$B$312:$B$336,MATCH('NG Calcs'!E$33,'Henry Hub Historicals'!$C$312:$C$336,0),1)/1.037 -> 2.6680386 | F34: =INDEX('NG Sector Price Historicals'!$K$4:$K$103,MATCH('NG Calcs'!F$33,'NG Sector Price Historicals'!$S$4:$S$103,0),1)/INDEX('Henry Hub Historicals'!$B$312:$B$336,MATCH('NG Calcs'!F$33,'Henry Hub Historicals'!$C$312:$C$336,0),1)/1.037 -> 2.4207305 | G34: =INDEX('NG Sector Price Historicals'!$K$4:$K$103,MATCH('NG Calcs'!G$33,'NG Sector Price Historicals'!$S$4:$S$103,0),1)/INDEX('Henry Hub Historicals'!$B$312:$B$336,MATCH('NG Calcs'!G$33,'Henry Hub Historicals'!$C$312:$C$336,0),1)/1.037 -> 3.8204745 | H34: =INDEX('NG Sector Price Historicals'!$K$4:$K$103,MATCH('NG Calcs'!H$33,'NG Sector Price Historicals'!$S$4:$S$103,0),1)/INDEX('Henry Hub Historicals'!$B$312:$B$336,MATCH('NG Calcs'!H$33,'Henry Hub Historicals'!$C$312:$C$336,0),1)/1.037 -> 3.8458006 | I34: =INDEX('NG Sector Price Historicals'!$K$4:$K$103,MATCH('NG Calcs'!I$33,'NG Sector Price Historicals'!$S$4:$S$103,0),1)/INDEX('Henry Hub Historicals'!$B$312:$B$336,MATCH('NG Calcs'!I$33,'Henry Hub Historicals'!$C$312:$C$336,0),1)/1.037 -> 3.5186398 | ... L34: =INDEX('NG Sector Price Historicals'!$K$4:$K$103,MATCH('NG Calcs'!L$33,'NG Sector Price Historicals'!$S$4:$S$103,0),1)/INDEX('Henry Hub Historicals'!$B$312:$B$336,MATCH('NG Calcs'!L$33,'Henry Hub Historicals'!$C$312:$C$336,0),1)/1.037 -> 5.1208725
A35: Commercial | B35: =INDEX('NG Sector Price Historicals'!$M$4:$M$102,MATCH('NG Calcs'!B$33,'NG Sector Price Historicals'!$S$4:$S$102,0),1)/INDEX('Henry Hub Historicals'!$B$312:$B$336,MATCH('NG Calcs'!B$33,'Henry Hub Historicals'!$C$312:$C$336,0),1)/1.037 -> 2.0897281 | C35: =INDEX('NG Sector Price Historicals'!$M$4:$M$102,MATCH('NG Calcs'!C$33,'NG Sector Price Historicals'!$S$4:$S$102,0),1)/INDEX('Henry Hub Historicals'!$B$312:$B$336,MATCH('NG Calcs'!C$33,'Henry Hub Historicals'!$C$312:$C$336,0),1)/1.037 -> 2.1480231 | D35: =INDEX('NG Sector Price Historicals'!$M$4:$M$102,MATCH('NG Calcs'!D$33,'NG Sector Price Historicals'!$S$4:$S$102,0),1)/INDEX('Henry Hub Historicals'!$B$312:$B$336,MATCH('NG Calcs'!D$33,'Henry Hub Historicals'!$C$312:$C$336,0),1)/1.037 -> 2.8403612 | E35: =INDEX('NG Sector Price Historicals'!$M$4:$M$102,MATCH('NG Calcs'!E$33,'NG Sector Price Historicals'!$S$4:$S$102,0),1)/INDEX('Henry Hub Historicals'!$B$312:$B$336,MATCH('NG Calcs'!E$33,'Henry Hub Historicals'!$C$312:$C$336,0),1)/1.037 -> 2.0889294 | F35: =INDEX('NG Sector Price Historicals'!$M$4:$M$102,MATCH('NG Calcs'!F$33,'NG Sector Price Historicals'!$S$4:$S$102,0),1)/INDEX('Henry Hub Historicals'!$B$312:$B$336,MATCH('NG Calcs'!F$33,'Henry Hub Historicals'!$C$312:$C$336,0),1)/1.037 -> 1.9639472 | G35: =INDEX('NG Sector Price Historicals'!$M$4:$M$102,MATCH('NG Calcs'!G$33,'NG Sector Price Historicals'!$S$4:$S$102,0),1)/INDEX('Henry Hub Historicals'!$B$312:$B$336,MATCH('NG Calcs'!G$33,'Henry Hub Historicals'!$C$312:$C$336,0),1)/1.037 -> 2.9113635 | H35: =INDEX('NG Sector Price Historicals'!$M$4:$M$102,MATCH('NG Calcs'!H$33,'NG Sector Price Historicals'!$S$4:$S$102,0),1)/INDEX('Henry Hub Historicals'!$B$312:$B$336,MATCH('NG Calcs'!H$33,'Henry Hub Historicals'!$C$312:$C$336,0),1)/1.037 -> 2.7858138 | I35: =INDEX('NG Sector Price Historicals'!$M$4:$M$102,MATCH('NG Calcs'!I$33,'NG Sector Price Historicals'!$S$4:$S$102,0),1)/INDEX('Henry Hub Historicals'!$B$312:$B$336,MATCH('NG Calcs'!I$33,'Henry Hub Historicals'!$C$312:$C$336,0),1)/1.037 -> 2.541419 | ... L35: =INDEX('NG Sector Price Historicals'!$M$4:$M$102,MATCH('NG Calcs'!L$33,'NG Sector Price Historicals'!$S$4:$S$102,0),1)/INDEX('Henry Hub Historicals'!$B$312:$B$336,MATCH('NG Calcs'!L$33,'Henry Hub Historicals'!$C$312:$C$336,0),1)/1.037 -> 3.5580088
A36: Industry | B36: =INDEX('NG Sector Price Historicals'!$O$4:$O$102,MATCH('NG Calcs'!B$33,'NG Sector Price Historicals'!$S$4:$S$102,0),1)/INDEX('Henry Hub Historicals'!$B$312:$B$336,MATCH('NG Calcs'!B$33,'Henry Hub Historicals'!$C$312:$C$336,0),1)/1.037 -> 1.2114686 | C36: =INDEX('NG Sector Price Historicals'!$O$4:$O$102,MATCH('NG Calcs'!C$33,'NG Sector Price Historicals'!$S$4:$S$102,0),1)/INDEX('Henry Hub Historicals'!$B$312:$B$336,MATCH('NG Calcs'!C$33,'Henry Hub Historicals'!$C$312:$C$336,0),1)/1.037 -> 1.2367406 | D36: =INDEX('NG Sector Price Historicals'!$O$4:$O$102,MATCH('NG Calcs'!D$33,'NG Sector Price Historicals'!$S$4:$S$102,0),1)/INDEX('Henry Hub Historicals'!$B$312:$B$336,MATCH('NG Calcs'!D$33,'Henry Hub Historicals'!$C$312:$C$336,0),1)/1.037 -> 1.3605681 | E36: =INDEX('NG Sector Price Historicals'!$O$4:$O$102,MATCH('NG Calcs'!E$33,'NG Sector Price Historicals'!$S$4:$S$102,0),1)/INDEX('Henry Hub Historicals'!$B$312:$B$336,MATCH('NG Calcs'!E$33,'Henry Hub Historicals'!$C$312:$C$336,0),1)/1.037 -> 1.1995832 | F36: =INDEX('NG Sector Price Historicals'!$O$4:$O$102,MATCH('NG Calcs'!F$33,'NG Sector Price Historicals'!$S$4:$S$102,0),1)/INDEX('Henry Hub Historicals'!$B$312:$B$336,MATCH('NG Calcs'!F$33,'Henry Hub Historicals'!$C$312:$C$336,0),1)/1.037 -> 1.2401554 | G36: =INDEX('NG Sector Price Historicals'!$O$4:$O$102,MATCH('NG Calcs'!G$33,'NG Sector Price Historicals'!$S$4:$S$102,0),1)/INDEX('Henry Hub Historicals'!$B$312:$B$336,MATCH('NG Calcs'!G$33,'Henry Hub Historicals'!$C$312:$C$336,0),1)/1.037 -> 1.4464802 | H36: =INDEX('NG Sector Price Historicals'!$O$4:$O$102,MATCH('NG Calcs'!H$33,'NG Sector Price Historicals'!$S$4:$S$102,0),1)/INDEX('Henry Hub Historicals'!$B$312:$B$336,MATCH('NG Calcs'!H$33,'Henry Hub Historicals'!$C$312:$C$336,0),1)/1.037 -> 1.3431602 | I36: =INDEX('NG Sector Price Historicals'!$O$4:$O$102,MATCH('NG Calcs'!I$33,'NG Sector Price Historicals'!$S$4:$S$102,0),1)/INDEX('Henry Hub Historicals'!$B$312:$B$336,MATCH('NG Calcs'!I$33,'Henry Hub Historicals'!$C$312:$C$336,0),1)/1.037 -> 1.3158616 | ... L36: =INDEX('NG Sector Price Historicals'!$O$4:$O$102,MATCH('NG Calcs'!L$33,'NG Sector Price Historicals'!$S$4:$S$102,0),1)/INDEX('Henry Hub Historicals'!$B$312:$B$336,MATCH('NG Calcs'!L$33,'Henry Hub Historicals'!$C$312:$C$336,0),1)/1.037 -> 1.5771147
A37: Electricity | B37: =INDEX('NG Sector Price Historicals'!$R$4:$R$102,MATCH('NG Calcs'!B$33,'NG Sector Price Historicals'!$S$4:$S$102,0),1)/INDEX('Henry Hub Historicals'!$B$312:$B$336,MATCH('NG Calcs'!B$33,'Henry Hub Historicals'!$C$312:$C$336,0),1)/1.037 -> 1.1629216 | C37: =INDEX('NG Sector Price Historicals'!$R$4:$R$102,MATCH('NG Calcs'!C$33,'NG Sector Price Historicals'!$S$4:$S$102,0),1)/INDEX('Henry Hub Historicals'!$B$312:$B$336,MATCH('NG Calcs'!C$33,'Henry Hub Historicals'!$C$312:$C$336,0),1)/1.037 -> 1.1788814 | D37: =INDEX('NG Sector Price Historicals'!$R$4:$R$102,MATCH('NG Calcs'!D$33,'NG Sector Price Historicals'!$S$4:$S$102,0),1)/INDEX('Henry Hub Historicals'!$B$312:$B$336,MATCH('NG Calcs'!D$33,'Henry Hub Historicals'!$C$312:$C$336,0),1)/1.037 -> 1.241343 | E37: =INDEX('NG Sector Price Historicals'!$R$4:$R$102,MATCH('NG Calcs'!E$33,'NG Sector Price Historicals'!$S$4:$S$102,0),1)/INDEX('Henry Hub Historicals'!$B$312:$B$336,MATCH('NG Calcs'!E$33,'Henry Hub Historicals'!$C$312:$C$336,0),1)/1.037 -> 1.1608036 | F37: =INDEX('NG Sector Price Historicals'!$R$4:$R$102,MATCH('NG Calcs'!F$33,'NG Sector Price Historicals'!$S$4:$S$102,0),1)/INDEX('Henry Hub Historicals'!$B$312:$B$336,MATCH('NG Calcs'!F$33,'Henry Hub Historicals'!$C$312:$C$336,0),1)/1.037 -> 1.1452681 | G37: =INDEX('NG Sector Price Historicals'!$R$4:$R$102,MATCH('NG Calcs'!G$33,'NG Sector Price Historicals'!$S$4:$S$102,0),1)/INDEX('Henry Hub Historicals'!$B$312:$B$336,MATCH('NG Calcs'!G$33,'Henry Hub Historicals'!$C$312:$C$336,0),1)/1.037 -> 1.2440466 | H37: =INDEX('NG Sector Price Historicals'!$R$4:$R$102,MATCH('NG Calcs'!H$33,'NG Sector Price Historicals'!$S$4:$S$102,0),1)/INDEX('Henry Hub Historicals'!$B$312:$B$336,MATCH('NG Calcs'!H$33,'Henry Hub Historicals'!$C$312:$C$336,0),1)/1.037 -> 1.1441735 | I37: =INDEX('NG Sector Price Historicals'!$R$4:$R$102,MATCH('NG Calcs'!I$33,'NG Sector Price Historicals'!$S$4:$S$102,0),1)/INDEX('Henry Hub Historicals'!$B$312:$B$336,MATCH('NG Calcs'!I$33,'Henry Hub Historicals'!$C$312:$C$336,0),1)/1.037 -> 1.132028 | ... L37: =INDEX('NG Sector Price Historicals'!$R$4:$R$102,MATCH('NG Calcs'!L$33,'NG Sector Price Historicals'!$S$4:$S$102,0),1)/INDEX('Henry Hub Historicals'!$B$312:$B$336,MATCH('NG Calcs'!L$33,'Henry Hub Historicals'!$C$312:$C$336,0),1)/1.037 -> 1.1780857
A38: Transportation | B38: =INDEX('NG Sector Price Historicals'!$K$4:$K$102,MATCH('NG Calcs'!B$33,'NG Sector Price Historicals'!$S$4:$S$102,0),1)/INDEX('Henry Hub Historicals'!$B$312:$B$336,MATCH('NG Calcs'!B$33,'Henry Hub Historicals'!$C$312:$C$336,0),1)/1.037 -> 2.5134111 | C38: =INDEX('NG Sector Price Historicals'!$K$4:$K$102,MATCH('NG Calcs'!C$33,'NG Sector Price Historicals'!$S$4:$S$102,0),1)/INDEX('Henry Hub Historicals'!$B$312:$B$336,MATCH('NG Calcs'!C$33,'Henry Hub Historicals'!$C$312:$C$336,0),1)/1.037 -> 2.6591128 | D38: =INDEX('NG Sector Price Historicals'!$K$4:$K$102,MATCH('NG Calcs'!D$33,'NG Sector Price Historicals'!$S$4:$S$102,0),1)/INDEX('Henry Hub Historicals'!$B$312:$B$336,MATCH('NG Calcs'!D$33,'Henry Hub Historicals'!$C$312:$C$336,0),1)/1.037 -> 3.734549 | E38: =INDEX('NG Sector Price Historicals'!$K$4:$K$102,MATCH('NG Calcs'!E$33,'NG Sector Price Historicals'!$S$4:$S$102,0),1)/INDEX('Henry Hub Historicals'!$B$312:$B$336,MATCH('NG Calcs'!E$33,'Henry Hub Historicals'!$C$312:$C$336,0),1)/1.037 -> 2.6680386 | F38: =INDEX('NG Sector Price Historicals'!$K$4:$K$102,MATCH('NG Calcs'!F$33,'NG Sector Price Historicals'!$S$4:$S$102,0),1)/INDEX('Henry Hub Historicals'!$B$312:$B$336,MATCH('NG Calcs'!F$33,'Henry Hub Historicals'!$C$312:$C$336,0),1)/1.037 -> 2.4207305 | G38: =INDEX('NG Sector Price Historicals'!$K$4:$K$102,MATCH('NG Calcs'!G$33,'NG Sector Price Historicals'!$S$4:$S$102,0),1)/INDEX('Henry Hub Historicals'!$B$312:$B$336,MATCH('NG Calcs'!G$33,'Henry Hub Historicals'!$C$312:$C$336,0),1)/1.037 -> 3.8204745 | H38: =INDEX('NG Sector Price Historicals'!$K$4:$K$102,MATCH('NG Calcs'!H$33,'NG Sector Price Historicals'!$S$4:$S$102,0),1)/INDEX('Henry Hub Historicals'!$B$312:$B$336,MATCH('NG Calcs'!H$33,'Henry Hub Historicals'!$C$312:$C$336,0),1)/1.037 -> 3.8458006 | I38: =INDEX('NG Sector Price Historicals'!$K$4:$K$102,MATCH('NG Calcs'!I$33,'NG Sector Price Historicals'!$S$4:$S$102,0),1)/INDEX('Henry Hub Historicals'!$B$312:$B$336,MATCH('NG Calcs'!I$33,'Henry Hub Historicals'!$C$312:$C$336,0),1)/1.037 -> 3.5186398 | ... L38: =INDEX('NG Sector Price Historicals'!$K$4:$K$102,MATCH('NG Calcs'!L$33,'NG Sector Price Historicals'!$S$4:$S$102,0),1)/INDEX('Henry Hub Historicals'!$B$312:$B$336,MATCH('NG Calcs'!L$33,'Henry Hub Historicals'!$C$312:$C$336,0),1)/1.037 -> 5.1208725 | M38: <-uses residential price
A40: Future Prices by Sector | B40: 2021 | C40: 2022 | D40: 2023 | E40: 2024 | F40: 2025
A41: Residential | B41: =AVERAGE($G34:$K34)*B$31 -> 14.276073 | C41: =AVERAGE($G34:$K34)*C$31 -> 26.369714 | D41: =AVERAGE($G34:$K34)*D$31 -> 22.707911 | E41: =AVERAGE($G34:$K34)*E$31 -> 17.155479 | F41: =AVERAGE($G34:$K34)*F$31 -> 15.951617
A42: Commercial | B42: =AVERAGE($G35:$K35)*B$31 -> 10.490282 | C42: =AVERAGE($G35:$K35)*C$31 -> 19.376879 | D42: =AVERAGE($G35:$K35)*D$31 -> 16.686129 | E42: =AVERAGE($G35:$K35)*E$31 -> 12.606115 | F42: =AVERAGE($G35:$K35)*F$31 -> 11.721498
A43: Industry | B43: =AVERAGE($G36:$K36)*B$31 -> 5.3324686 | C43: =AVERAGE($G36:$K36)*C$31 -> 9.8497441 | D43: =AVERAGE($G36:$K36)*D$31 -> 8.4819698 | E43: =AVERAGE($G36:$K36)*E$31 -> 6.4079983 | F43: =AVERAGE($G36:$K36)*F$31 -> 5.9583259
A44: Electricity | B44: =AVERAGE($G37:$K37)*B$31 -> 4.489381 | C44: =AVERAGE($G37:$K37)*C$31 -> 8.2924546 | D44: =AVERAGE($G37:$K37)*D$31 -> 7.1409317 | E44: =AVERAGE($G37:$K37)*E$31 -> 5.3948646 | F44: =AVERAGE($G37:$K37)*F$31 -> 5.0162874
A45: Transportation | B45: =AVERAGE($G38:$K38)*B$31 -> 14.276073 | C45: =AVERAGE($G38:$K38)*C$31 -> 26.369714 | D45: =AVERAGE($G38:$K38)*D$31 -> 22.707911 | E45: =AVERAGE($G38:$K38)*E$31 -> 17.155479 | F45: =AVERAGE($G38:$K38)*F$31 -> 15.951617

Sheet AEO 2022 3
B1: ref2022.d011222a | C1: 2021 | D1: 2022 | E1: 2023 | F1: 2024 | G1: 2025 | H1: 2026 | I1: 2027 | J1: 2028 | K1: 2029 | L1: 2030 | M1: 2031 | N1: 2032 | O1: 2033 | P1: 2034 | Q1: 2035 | R1: 2036 | S1: 2037 | T1: 2038 | U1: 2039 | V1: 2040 | W1: 2041 | X1: 2042 | Y1: 2043 | Z1: 2044 | AA1: 2045 | AB1: 2046 | AC1: 2047 | AD1: 2048 | AE1: 2049 | AF1: 2050
C3: Report | D3: Annual Energy Outlook 2022
C4: Scenario | D4: ref2022 | G4: Reference
C5: Datekey | D5: d011222a
C6: Release Date | E6: March 2022
A10: PRC000 | B10: 3. Energy Prices by Sector and Source | AG10: Average
B11: (2021 dollars per million Btu, unless otherwise noted) | AG11: Annual
AG12: Change
B13: Sector and Source | C13: 2021 | D13: 2022 | E13: 2023 | F13: 2024 | G13: 2025 | H13: 2026 | I13: 2027 | J13: 2028 | K13: 2029 | L13: 2030 | M13: 2031 | N13: 2032 | O13: 2033 | P13: 2034 | Q13: 2035 | R13: 2036 | S13: 2037 | T13: 2038 | U13: 2039 | V13: 2040 | W13: 2041 | X13: 2042 | Y13: 2043 | Z13: 2044 | AA13: 2045 | AB13: 2046 | AC13: 2047 | AD13: 2048 | AE13: 2049 | AF13: 2050 | AG13: 2021–2050
B15: Residential
A16: PRC000:ba_LiquefiedPetr | B16: Propane | C16: 21.519539 | D16: 23.171989 | E16: 22.882879 | F16: 22.879547 | G16: 22.81468 | H16: 22.860277 | I16: 23.090302 | J16: 23.526861 | K16: 24.041061 | L16: 24.518085 | M16: 24.986616 | N16: 25.594236 | O16: 26.029459 | P16: 26.333237 | Q16: 26.526838 | R16: 26.637016 | S16: 26.823605 | T16: 27.044893 | U16: 27.215189 | V16: 27.495535 | W16: 27.787014 | X16: 28.060249 | Y16: 28.415535 | Z16: 28.739542 | AA16: 28.873835 | AB16: 28.852163 | AC16: 28.765711 | AD16: 28.699755 | AE16: 28.682411 | AF16: 28.628248 | AG16: 0.009891
A17: PRC000:ba_DistillateFue | B17: Distillate Fuel Oil | C17: 21.74482 | D17: 22.068129 | E17: 21.495361 | F17: 22.810974 | G17: 23.416267 | H17: 23.953699 | I17: 24.605654 | J17: 24.700975 | K17: 24.801643 | L17: 24.726501 | M17: 24.89443 | N17: 25.006918 | O17: 25.06778 | P17: 25.021008 | Q17: 25.012953 | R17: 25.030716 | S17: 25.173168 | T17: 25.266403 | U17: 25.26918 | V17: 25.488142 | W17: 25.65202 | X17: 25.722313 | Y17: 25.994267 | Z17: 26.257401 | AA17: 26.239376 | AB17: 26.421463 | AC17: 26.39146 | AD17: 26.301579 | AE17: 26.37286 | AF17: 26.23348 | AG17: 0.006492
A18: PRC000:ba_NaturalGas | B18: Natural Gas | C18: 11.714767 | D18: 12.151939 | E18: 11.530189 | F18: 11.049291 | G18: 10.738748 | H18: 10.557094 | I18: 10.430874 | J18: 10.569336 | K18: 10.733542 | L18: 10.824615 | M18: 10.916719 | N18: 11.249624 | O18: 11.388998 | P18: 11.442094 | Q18: 11.442281 | R18: 11.411037 | S18: 11.449186 | T18: 11.482208 | U18: 11.520953 | V18: 11.549916 | W18: 11.630534 | X18: 11.626328 | Y18: 11.591697 | Z18: 11.577318 | AA18: 11.548356 | AB18: 11.546086 | AC18: 11.550601 | AD18: 11.556095 | AE18: 11.593725 | AF18: 11.616578 | AG18: -0.00029
A19: PRC000:ba_Electricity | B19: Electricity | C19: 38.76239 | D19: 38.520023 | E19: 38.213291 | F19: 37.571396 | G19: 37.389545 | H19: 37.544312 | I19: 37.608688 | J19: 37.67712 | K19: 37.800606 | L19: 37.826485 | M19: 37.95697 | N19: 38.120724 | O19: 38.280704 | P19: 38.361744 | Q19: 38.052212 | R19: 37.810265 | S19: 37.659115 | T19: 37.508751 | U19: 37.363533 | V19: 37.418816 | W19: 37.32682 | X19: 37.339638 | Y19: 37.170746 | Z19: 37.042542 | AA19: 37.059158 | AB19: 36.817814 | AC19: 36.777477 | AD19: 36.656681 | AE19: 36.538506 | AF19: 36.290455 | AG19: -0.00227
B21: Commercial
A22: PRC000:ca_LiquefiedGas | B22: Propane | C22: 18.82229 | D22: 19.715876 | E22: 18.120464 | F22: 18.024939 | G22: 17.919872 | H22: 18.009079 | I22: 18.3034 | J22: 18.778172 | K22: 19.233488 | L22: 19.571339 | M22: 19.902462 | N22: 20.432222 | O22: 20.743967 | P22: 20.877277 | Q22: 20.929077 | R22: 20.949825 | S22: 21.118494 | T22: 21.305202 | U22: 21.400408 | V22: 21.663759 | W22: 21.891474 | X22: 22.078979 | Y22: 22.382664 | Z22: 22.604012 | AA22: 22.578735 | AB22: 22.440573 | AC22: 22.312597 | AD22: 22.263029 | AE22: 22.278421 | AF22: 22.221497 | AG22: 0.005741
A23: PRC000:ca_DistillateFue | B23: Distillate Fuel Oil | C23: 21.823187 | D23: 22.151241 | E23: 20.410337 | F23: 20.680359 | G23: 20.203226 | H23: 19.669413 | I23: 19.257957 | J23: 19.355928 | K23: 19.454554 | L23: 19.407745 | M23: 19.577158 | N23: 20.015388 | O23: 20.072495 | P23: 20.03583 | Q23: 20.077394 | R23: 20.092907 | S23: 20.242428 | T23: 20.340593 | U23: 20.341209 | V23: 20.574266 | W23: 20.738567 | X23: 20.811586 | Y23: 21.077398 | Z23: 21.340584 | AA23: 21.334831 | AB23: 21.519756 | AC23: 21.496529 | AD23: 21.407711 | AE23: 21.483562 | AF23: 21.350731 | AG23: -0.000754
A24: PRC000:ca_ResidualFuel | B24: Residual Fuel Oil | C24: 6.510058 | D24: 7.557132 | E24: 7.507626 | F24: 8.768214 | G24: 9.385942 | H24: 9.938887 | I24: 10.723703 | J24: 10.872849 | K24: 10.957002 | L24: 11.106604 | M24: 11.208329 | N24: 11.39804 | O24: 11.494227 | P24: 11.57103 | Q24: 11.59597 | R24: 11.640589 | S24: 11.60836 | T24: 11.717171 | U24: 11.650704 | V24: 12.228127 | W24: 12.351459 | X24: 12.376053 | Y24: 12.620767 | Z24: 12.870325 | AA24: 12.911318 | AB24: 13.078762 | AC24: 13.098419 | AD24: 13.071736 | AE24: 13.146095 | AF24: 13.070272 | AG24: 0.024325
A25: PRC000:ca_NaturalGas | B25: Natural Gas | C25: 8.442578 | D25: 8.81864 | E25: 8.497001 | F25: 8.180623 | G25: 8.017892 | H25: 7.970574 | I25: 7.962804 | J25: 8.083815 | K25: 8.223901 | L25: 8.293325 | M25: 8.363929 | N25: 8.57109 | O25: 8.670591 | P25: 8.698514 | Q25: 8.671237 | R25: 8.627092 | S25: 8.651712 | T25: 8.673417 | U25: 8.701211 | V25: 8.720324 | W25: 8.789293 | X25: 8.774185 | Y25: 8.728896 | Z25: 8.705806 | AA25: 8.668962 | AB25: 8.657973 | AC25: 8.654889 | AD25: 8.653486 | AE25: 8.683637 | AF25: 8.700233 | AG25: 0.001037
A26: PRC000:ca_Electricity | B26: Electricity | C26: 33.23053 | D26: 32.918514 | E26: 32.008312 | F26: 31.329121 | G26: 31.108648 | H26: 31.226942 | I26: 31.192585 | J26: 31.205448 | K26: 31.239994 | L26: 31.164198 | M26: 31.207338 | N26: 31.252337 | O26: 31.384094 | P26: 31.392914 | Q26: 31.002916 | R26: 30.702438 | S26: 30.551657 | T26: 30.342772 | U26: 30.176033 | V26: 30.204935 | W26: 30.056618 | X26: 30.057528 | Y26: 29.873531 | Z26: 29.691975 | AA26: 29.655783 | AB26: 29.391348 | AC26: 29.304863 | AD26: 29.157902 | AE26: 29.036934 | AF26: 28.768715 | AG26: -0.004959
B28: Industrial 1/
A29: PRC000:da_LiquefiedPetr | B29: Propane | C29: 13.663833 | D29: 14.357594 | E29: 12.540752 | F29: 12.504602 | G29: 12.409207 | H29: 12.512104 | I29: 12.822186 | J29: 13.316794 | K29: 13.784143 | L29: 14.126072 | M29: 14.469291 | N29: 14.76237 | O29: 15.093699 | P29: 15.225082 | Q29: 15.235613 | R29: 15.257844 | S29: 15.447799 | T29: 15.651039 | U29: 15.74879 | V29: 16.04315 | W29: 16.289669 | X29: 16.49139 | Y29: 16.830481 | Z29: 17.069897 | AA29: 17.026379 | AB29: 16.866844 | AC29: 16.727716 | AD29: 16.679976 | AE29: 16.703079 | AF29: 16.638475 | AG29: 0.006815
A30: PRC000:da_DistillateFue | B30: Distillate Fuel Oil | C30: 21.75238 | D30: 22.07209 | E30: 20.410429 | F30: 20.646559 | G30: 20.162947 | H30: 19.615082 | I30: 19.183277 | J30: 19.286734 | K30: 19.397879 | L30: 19.367228 | M30: 19.537781 | N30: 19.664978 | O30: 19.740728 | P30: 19.7083 | Q30: 19.713743 | R30: 19.732658 | S30: 19.883741 | T30: 19.985138 | U30: 19.992161 | V30: 20.237799 | W30: 20.408806 | X30: 20.488091 | Y30: 20.759394 | Z30: 21.023619 | AA30: 21.028748 | AB30: 21.221027 | AC30: 21.206429 | AD30: 21.123951 | AE30: 21.206486 | AF30: 21.081644 | AG30: -0.001079
A31: PRC000:da_ResidualFuel | B31: Residual Fuel Oil | C31: 7.09223 | D31: 8.293962 | E31: 8.453308 | F31: 9.941956 | G31: 10.752403 | H31: 11.551449 | I31: 12.545612 | J31: 12.71112 | K31: 12.829576 | L31: 12.988939 | M31: 13.118169 | N31: 13.329255 | O31: 13.446094 | P31: 13.510265 | Q31: 13.572783 | R31: 13.618667 | S31: 13.563599 | T31: 13.682616 | U31: 13.633999 | V31: 14.207245 | W31: 14.34065 | X31: 14.376684 | Y31: 14.61781 | Z31: 14.86674 | AA31: 14.907736 | AB31: 15.082319 | AC31: 15.10018 | AD31: 15.080288 | AE31: 15.156901 | AF31: 15.086491 | AG31: 0.026369
A32: PRC000:da_NaturalGas | B32: Natural Gas 2/ | C32: 5.071276 | D32: 4.843464 | E32: 4.512031 | F32: 4.155407 | G32: 3.980554 | H32: 3.926305 | I32: 3.957039 | J32: 4.114555 | K32: 4.261919 | L32: 4.348165 | M32: 4.405538 | N32: 4.405082 | O32: 4.501796 | P32: 4.506782 | Q32: 4.436007 | R32: 4.385244 | S32: 4.383933 | T32: 4.405835 | U32: 4.426479 | V32: 4.448872 | W32: 4.503239 | X32: 4.510521 | Y32: 4.447511 | Z32: 4.412628 | AA32: 4.339705 | AB32: 4.309629 | AC32: 4.291151 | AD32: 4.285682 | AE32: 4.295768 | AF32: 4.30372 | AG32: -0.005643
A33: PRC000:da_Metallurgical | B33: Metallurgical Coal | C33: 3.927859 | D33: 3.518811 | E33: 3.347698 | F33: 3.188333 | G33: 3.098164 | H33: 3.037497 | I33: 3.009427 | J33: 3.004971 | K33: 3.016198 | L33: 3.040812 | M33: 3.063208 | N33: 3.094111 | O33: 3.112654 | P33: 3.12921 | Q33: 3.151268 | R33: 3.173285 | S33: 3.199473 | T33: 3.221655 | U33: 3.243439 | V33: 3.268032 | W33: 3.287717 | X33: 3.306536 | Y33: 3.33003 | Z33: 3.356462 | AA33: 3.383151 | AB33: 3.410095 | AC33: 3.436724 | AD33: 3.458919 | AE33: 3.483504 | AF33: 3.508619 | AG33: -0.003885
A34: PRC000:da_SteamCoal | B34: Other Industrial Coal | C34: 2.729489 | D34: 2.681275 | E34: 2.690543 | F34: 2.694087 | G34: 2.695647 | H34: 2.689396 | I34: 2.677643 | J34: 2.675602 | K34: 2.675394 | L34: 2.676888 | M34: 2.677192 | N34: 2.681719 | O34: 2.687179 | P34: 2.68689 | Q34: 2.675991 | R34: 2.671342 | S34: 2.666051 | T34: 2.66399 | U34: 2.670385 | V34: 2.672748 | W34: 2.678431 | X34: 2.677164 | Y34: 2.67528 | Z34: 2.679811 | AA34: 2.682535 | AB34: 2.685032 | AC34: 2.684788 | AD34: 2.68338 | AE34: 2.684288 | AF34: 2.68431 | AG34: -0.000575
A35: PRC000:da_CoaltoLiquids | B35: Coal to Liquids | C35: -- | D35: -- | E35: -- | F35: -- | G35: -- | H35: -- | I35: -- | J35: -- | K35: -- | L35: -- | M35: -- | N35: -- | O35: -- | P35: -- | Q35: -- | R35: -- | S35: -- | T35: -- | U35: -- | V35: -- | W35: -- | X35: -- | Y35: -- | Z35: -- | AA35: -- | AB35: -- | AC35: -- | AD35: -- | AE35: -- | AF35: -- | AG35: --
A36: PRC000:da_Electricity | B36: Electricity | C36: 21.954327 | D36: 21.585382 | E36: 20.592312 | F36: 19.991262 | G36: 19.767326 | H36: 19.610733 | I36: 19.56032 | J36: 19.572056 | K36: 19.607359 | L36: 19.590822 | M36: 19.607412 | N36: 19.627659 | O36: 19.631359 | P36: 19.629396 | Q36: 19.42919 | R36: 19.290569 | S36: 19.131826 | T36: 19.040081 | U36: 18.93644 | V36: 18.923027 | W36: 18.863256 | X36: 18.807621 | Y36: 18.641674 | Z36: 18.541803 | AA36: 18.475939 | AB36: 18.302622 | AC36: 18.235422 | AD36: 18.142365 | AE36: 18.062515 | AF36: 17.956863 | AG36: -0.006907
B38: Transportation
A39: PRC000:ea_LiquefiedPetr | B39: Propane | C39: 17.771591 | D39: 18.268835 | E39: 16.727415 | F39: 16.714048 | G39: 16.63475 | H39: 16.724779 | I39: 16.989109 | J39: 17.403635 | K39: 17.787142 | L39: 18.062943 | M39: 18.338911 | N39: 18.912962 | O39: 19.174692 | P39: 19.274258 | Q39: 19.327059 | R39: 19.342785 | S39: 19.492384 | T39: 19.649984 | U39: 19.722977 | V39: 19.951733 | W39: 20.139431 | X39: 20.291405 | Y39: 20.549433 | Z39: 20.727776 | AA39: 20.689186 | AB39: 20.564272 | AC39: 20.45661 | AD39: 20.419739 | AE39: 20.436655 | AF39: 20.384317 | AG39: 0.004741
A40: PRC000:ea_Ethanol(E85) | B40: E85 3/ | C40: 25.787903 | D40: 25.761244 | E40: 25.495865 | F40: 25.212345 | G40: 24.975626 | H40: 25.043127 | I40: 25.355228 | J40: 25.594719 | K40: 25.777565 | L40: 26.200195 | M40: 26.276876 | N40: 27.198093 | O40: 27.413271 | P40: 27.550776 | Q40: 27.680271 | R40: 27.711462 | S40: 27.855463 | T40: 28.059765 | U40: 28.008661 | V40: 28.442335 | W40: 28.682402 | X40: 28.964655 | Y40: 29.315157 | Z40: 29.494404 | AA40: 29.595737 | AB40: 29.879946 | AC40: 29.952457 | AD40: 30.036066 | AE40: 30.150232 | AF40: 29.900158 | AG40: 0.005115
A41: PRC000:ea_MotorGasoline | B41: Motor Gasoline 4/ | C41: 25.885534 | D41: 24.823555 | E41: 21.931265 | F41: 21.752617 | G41: 21.573097 | H41: 21.630323 | I41: 21.882795 | J41: 22.068708 | K41: 22.206301 | L41: 22.537537 | M41: 22.59231 | N41: 23.553766 | O41: 23.718866 | P41: 23.814569 | Q41: 23.936171 | R41: 23.943441 | S41: 24.047487 | T41: 24.204655 | U41: 24.154181 | V41: 24.491938 | W41: 24.685377 | X41: 24.854437 | Y41: 25.146194 | Z41: 25.343546 | AA41: 25.424524 | AB41: 25.671301 | AC41: 25.718651 | AD41: 25.792084 | AE41: 25.879534 | AF41: 25.666084 | AG41: -0.000294
A42: PRC000:ea_JetFuel | B42: Jet Fuel 5/ | C42: 14.720805 | D42: 15.38822 | E42: 14.073745 | F42: 15.179766 | G42: 15.292542 | H42: 15.463751 | I42: 15.70466 | J42: 15.898726 | K42: 16.05232 | L42: 16.046509 | M42: 16.330721 | N42: 16.697517 | O42: 16.757906 | P42: 16.780107 | Q42: 16.810595 | R42: 16.876972 | S42: 17.097425 | T42: 17.235626 | U42: 17.279207 | V42: 17.533007 | W42: 17.728834 | X42: 17.813095 | Y42: 18.115818 | Z42: 18.40634 | AA42: 18.427332 | AB42: 18.612141 | AC42: 18.622166 | AD42: 18.579237 | AE42: 18.690105 | AF42: 18.608126 | AG42: 0.008113
A43: PRC000:ea_DistillateFue | B43: Diesel Fuel (distillate fuel oil) 6/ | C43: 23.750263 | D43: 22.843327 | E43: 21.93634 | F43: 22.651623 | G43: 22.721119 | H43: 22.675623 | I43: 22.731689 | J43: 22.822958 | K43: 22.936224 | L43: 22.910614 | M43: 23.069981 | N43: 23.535149 | O43: 23.617865 | P43: 23.558996 | Q43: 23.605259 | R43: 23.598024 | S43: 23.764229 | T43: 23.864792 | U43: 23.869284 | V43: 24.107859 | W43: 24.278906 | X43: 24.369808 | Y43: 24.638464 | Z43: 24.907894 | AA43: 24.912159 | AB43: 25.116587 | AC43: 25.106068 | AD43: 25.002657 | AE43: 25.088144 | AF43: 24.951025 | AG43: 0.001702
A44: PRC000:ea_ResidualFuel | B44: Residual Fuel Oil | C44: 12.357966 | D44: 10.441763 | E44: 12.662357 | F44: 13.544412 | G44: 13.756763 | H44: 13.919001 | I44: 14.270379 | J44: 14.384391 | K44: 14.458046 | L44: 14.603832 | M44: 14.679204 | N44: 14.933182 | O44: 15.015419 | P44: 15.044872 | Q44: 15.107331 | R44: 15.142351 | S44: 15.144779 | T44: 15.235153 | U44: 15.196106 | V44: 15.646362 | W44: 15.738945 | X44: 15.785649 | Y44: 15.987934 | Z44: 16.203949 | AA44: 16.243937 | AB44: 16.391148 | AC44: 16.410231 | AD44: 16.386232 | AE44: 16.43816 | AF44: 16.369478 | AG44: 0.009741
A45: PRC000:ea_NaturalGas | B45: Natural Gas 7/ | C45: 14.654003 | D45: 14.619699 | E45: 13.872672 | F45: 13.306766 | G45: 12.89931 | H45: 12.541728 | I45: 12.263359 | J45: 12.130099 | K45: 12.005839 | L45: 11.846902 | M45: 11.685585 | N45: 12.332364 | O45: 12.244666 | P45: 12.103299 | Q45: 11.998527 | R45: 11.817566 | S45: 11.702035 | T45: 11.61793 | U45: 11.537097 | V45: 11.515666 | W45: 11.50357 | X45: 11.440135 | Y45: 11.341637 | Z45: 11.270406 | AA45: 11.16805 | AB45: 11.113301 | AC45: 11.064749 | AD45: 11.018502 | AE45: 10.993929 | AF45: 10.952426 | AG45: -0.00999
A46: PRC000:ea_Electricity | B46: Electricity | C46: 39.115726 | D46: 39.616028 | E46: 38.115593 | F46: 37.093182 | G46: 37.086498 | H46: 37.542118 | I46: 37.558929 | J46: 37.560974 | K46: 37.509598 | L46: 37.302563 | M46: 37.30394 | N46: 37.330086 | O46: 37.461796 | P46: 37.336975 | Q46: 36.881054 | R46: 36.467251 | S46: 36.202427 | T46: 35.905403 | U46: 35.639503 | V46: 35.46138 | W46: 35.281731 | X46: 35.079762 | Y46: 34.771469 | Z46: 34.571163 | AA46: 34.483639 | AB46: 34.241879 | AC46: 34.021767 | AD46: 33.821972 | AE46: 33.614403 | AF46: 33.397739 | AG46: -0.005435
B48: Electric Power 8/
A49: PRC000:ga_DistillateFue | B49: Distillate Fuel Oil | C49: 21.749472 | D49: 22.063303 | E49: 20.153975 | F49: 20.553831 | G49: 19.961508 | H49: 19.321976 | I49: 18.867052 | J49: 18.963041 | K49: 19.071278 | L49: 19.038746 | M49: 19.098368 | N49: 19.294424 | O49: 19.321995 | P49: 19.367441 | Q49: 19.355671 | R49: 19.394863 | S49: 19.574009 | T49: 19.640402 | U49: 19.645767 | V49: 19.901247 | W49: 20.06513 | X49: 20.117165 | Y49: 20.384939 | Z49: 20.628145 | AA49: 20.629406 | AB49: 20.826429 | AC49: 20.826172 | AD49: 20.740261 | AE49: 20.844084 | AF49: 20.736099 | AG49: -0.001644
A50: PRC000:ga_ResidualFuel | B50: Residual Fuel Oil | C50: 13.006465 | D50: 13.345431 | E50: 12.638397 | F50: 13.540524 | G50: 13.744135 | H50: 13.901823 | I50: 14.324615 | J50: 14.413228 | K50: 14.473246 | L50: 14.597926 | M50: 14.66163 | N50: 14.952104 | O50: 15.023062 | P50: 15.028744 | Q50: 15.100775 | R50: 15.121873 | S50: 15.147896 | T50: 15.209865 | U50: 15.144525 | V50: 15.53472 | W50: 15.481628 | X50: 15.415256 | Y50: 15.467604 | Z50: 15.479861 | AA50: 15.233349 | AB50: 15.422539 | AC50: 15.494015 | AD50: 15.477424 | AE50: 15.574907 | AF50: 15.574647 | AG50: 0.006233
A51: PRC000:ga_NaturalGas | B51: Natural Gas | C51: 5.157501 | D51: 4.041245 | E51: 3.758129 | F51: 3.430388 | G51: 3.266725 | H51: 3.232515 | I51: 3.270525 | J51: 3.439616 | K51: 3.567562 | L51: 3.640071 | M51: 3.682663 | N51: 3.699922 | O51: 3.792077 | P51: 3.7758 | Q51: 3.673566 | R51: 3.626955 | S51: 3.621633 | T51: 3.644042 | U51: 3.668771 | V51: 3.703752 | W51: 3.75456 | X51: 3.753616 | Y51: 3.678001 | Z51: 3.641202 | AA51: 3.570948 | AB51: 3.545763 | AC51: 3.530404 | AD51: 3.534259 | AE51: 3.53999 | AF51: 3.56578 | AG51: -0.012646
A52: PRC000:ga_SteamCoal | B52: Steam Coal | C52: 2.11768 | D52: 2.002686 | E52: 2.003769 | F52: 2.008078 | G52: 1.956206 | H52: 1.931614 | I52: 1.916737 | J52: 1.908257 | K52: 1.920629 | L52: 1.917488 | M52: 1.911739 | N52: 1.90225 | O52: 1.895574 | P52: 1.892647 | Q52: 1.86805 | R52: 1.856108 | S52: 1.853899 | T52: 1.847783 | U52: 1.844928 | V52: 1.844842 | W52: 1.846852 | X52: 1.828859 | Y52: 1.824401 | Z52: 1.81727 | AA52: 1.811768 | AB52: 1.808238 | AC52: 1.797737 | AD52: 1.78178 | AE52: 1.777986 | AF52: 1.775739 | AG52: -0.006054
A53: PRC000:ga_uranium | B53: Uranium | C53: 0.717811 | D53: 0.718863 | E53: 0.720964 | F53: 0.722015 | G53: 0.724117 | H53: 0.725168 | I53: 0.72727 | J53: 0.728321 | K53: 0.730423 | L53: 0.732525 | M53: 0.733576 | N53: 0.735678 | O53: 0.73778 | P53: 0.738831 | Q53: 0.740933 | R53: 0.743035 | S53: 0.744086 | T53: 0.746188 | U53: 0.74829 | V53: 0.750391 | W53: 0.752494 | X53: 0.754595 | Y53: 0.756697 | Z53: 0.758799 | AA53: 0.760901 | AB53: 0.763003 | AC53: 0.765105 | AD53: 0.767207 | AE53: 0.769309 | AF53: 0.771411 | AG53: 0.002486
B56: Average Price to All Users 9/
A57: PRC000:ha_LiquefiedPetr | B57: Propane | C57: 19.520824 | D57: 20.92996 | E57: 20.082417 | F57: 20.050674 | G57: 19.965826 | H57: 20.02533 | I57: 20.268194 | J57: 20.706121 | K57: 21.177542 | L57: 21.577402 | M57: 21.969906 | N57: 22.476595 | O57: 22.83824 | P57: 23.050047 | Q57: 23.159853 | R57: 23.215166 | S57: 23.376358 | T57: 23.562716 | U57: 23.67705 | V57: 23.936489 | W57: 24.185408 | X57: 24.404106 | Y57: 24.725622 | Z57: 24.990145 | AA57: 25.032494 | AB57: 24.937096 | AC57: 24.814219 | AD57: 24.741323 | AE57: 24.724777 | AF57: 24.650307 | AG57: 0.008078
A58: PRC000:ha_Ethanol(E85) | B58: E85 3/ | C58: 25.787903 | D58: 25.761244 | E58: 25.495865 | F58: 25.212345 | G58: 24.975626 | H58: 25.043127 | I58: 25.355228 | J58: 25.594719 | K58: 25.777565 | L58: 26.200195 | M58: 26.276876 | N58: 27.198093 | O58: 27.413271 | P58: 27.550776 | Q58: 27.680271 | R58: 27.711462 | S58: 27.855463 | T58: 28.059765 | U58: 28.008661 | V58: 28.442335 | W58: 28.682402 | X58: 28.964655 | Y58: 29.315157 | Z58: 29.494404 | AA58: 29.595737 | AB58: 29.879946 | AC58: 29.952457 | AD58: 30.036066 | AE58: 30.150232 | AF58: 29.900158 | AG58: 0.005115
A59: PRC000:ha_MotorGasoline | B59: Motor Gasoline 4/ | C59: 25.875973 | D59: 24.818628 | E59: 21.957455 | F59: 21.790281 | G59: 21.608536 | H59: 21.654921 | I59: 21.892027 | J59: 22.07807 | K59: 22.215803 | L59: 22.54702 | M59: 22.602013 | N59: 23.561117 | O59: 23.726307 | P59: 23.822149 | Q59: 23.943626 | R59: 23.951033 | S59: 24.055145 | T59: 24.212412 | U59: 24.161999 | V59: 24.499897 | W59: 24.693489 | X59: 24.862711 | Y59: 25.154669 | Z59: 25.352127 | AA59: 25.433323 | AB59: 25.680344 | AC59: 25.727892 | AD59: 25.801403 | AE59: 25.888937 | AF59: 25.675623 | AG59: -0.000268
A60: PRC000:ha_JetFuel | B60: Jet Fuel 5/ | C60: 14.720805 | D60: 15.38822 | E60: 14.073745 | F60: 15.179766 | G60: 15.292542 | H60: 15.463751 | I60: 15.70466 | J60: 15.898726 | K60: 16.05232 | L60: 16.046509 | M60: 16.330721 | N60: 16.697517 | O60: 16.757906 | P60: 16.780107 | Q60: 16.810595 | R60: 16.876972 | S60: 17.097425 | T60: 17.235626 | U60: 17.279207 | V60: 17.533007 | W60: 17.728834 | X60: 17.813095 | Y60: 18.115818 | Z60: 18.40634 | AA60: 18.427332 | AB60: 18.612141 | AC60: 18.622166 | AD60: 18.579237 | AE60: 18.690105 | AF60: 18.608126 | AG60: 0.008113
A61: PRC000:ha_DistillateFue | B61: Distillate Fuel Oil | C61: 23.276806 | D61: 22.657784 | E61: 21.509951 | F61: 22.159214 | G61: 22.12748 | H61: 22.01108 | I61: 22.010616 | J61: 22.090155 | K61: 22.191229 | L61: 22.147449 | M61: 22.299383 | N61: 22.668865 | O61: 22.730412 | P61: 22.678328 | Q61: 22.711632 | R61: 22.719547 | S61: 22.852823 | T61: 22.942526 | U61: 22.941147 | V61: 23.172098 | W61: 23.334955 | X61: 23.412827 | Y61: 23.677961 | Z61: 23.933039 | AA61: 23.931978 | AB61: 24.119179 | AC61: 24.097599 | AD61: 24.005205 | AE61: 24.077518 | AF61: 23.943972 | AG61: 0.000975
A62: PRC000:ha_ResidualFuel | B62: Residual Fuel Oil | C62: 12.032716 | D62: 10.461782 | E62: 12.369011 | F62: 13.310703 | G62: 13.567265 | H62: 13.763799 | I62: 14.156386 | J62: 14.267786 | K62: 14.339729 | L62: 14.481854 | M62: 14.557441 | N62: 14.810274 | O62: 14.891078 | P62: 14.92039 | Q62: 14.983093 | R62: 15.017566 | S62: 15.015263 | T62: 15.104892 | U62: 15.061521 | V62: 15.516302 | W62: 15.603861 | X62: 15.644531 | Y62: 15.845129 | Z62: 16.058098 | AA62: 16.091763 | AB62: 16.24157 | AC62: 16.261566 | AD62: 16.237041 | AE62: 16.292362 | AF62: 16.22451 | AG62: 0.01036
A63: PRC000:ha_NaturalGas | B63: Natural Gas | C63: 6.727046 | D63: 6.398545 | E63: 6.007559 | F63: 5.653534 | G63: 5.487725 | H63: 5.429889 | I63: 5.454965 | J63: 5.59216 | K63: 5.741125 | L63: 5.837134 | M63: 5.907144 | N63: 6.005502 | O63: 6.090653 | P63: 6.117626 | Q63: 6.076823 | R63: 6.04059 | S63: 6.036061 | T63: 6.044491 | U63: 6.054013 | V63: 6.068184 | W63: 6.11861 | X63: 6.106076 | Y63: 6.030046 | Z63: 5.991965 | AA63: 5.9233 | AB63: 5.887187 | AC63: 5.860796 | AD63: 5.847686 | AE63: 5.85101 | AF63: 5.847811 | AG63: -0.004818
A64: PRC000:ha_Metallugical | B64: Metallurgical Coal | C64: 3.927859 | D64: 3.518811 | E64: 3.347698 | F64: 3.188333 | G64: 3.098164 | H64: 3.037497 | I64: 3.009427 | J64: 3.004971 | K64: 3.016198 | L64: 3.040812 | M64: 3.063208 | N64: 3.094111 | O64: 3.112654 | P64: 3.12921 | Q64: 3.151268 | R64: 3.173285 | S64: 3.199473 | T64: 3.221655 | U64: 3.243439 | V64: 3.268032 | W64: 3.287717 | X64: 3.306536 | Y64: 3.33003 | Z64: 3.356462 | AA64: 3.383151 | AB64: 3.410095 | AC64: 3.436724 | AD64: 3.458919 | AE64: 3.483504 | AF64: 3.508619 | AG64: -0.003885
A65: PRC000:ha_Coal | B65: Other Coal | C65: 2.151859 | D65: 2.041804 | E65: 2.044459 | F65: 2.05539 | G65: 2.009318 | H65: 1.987594 | I65: 1.974667 | J65: 1.966878 | K65: 1.978533 | L65: 1.976764 | M65: 1.971833 | N65: 1.964469 | O65: 1.958048 | P65: 1.957809 | Q65: 1.937612 | R65: 1.927672 | S65: 1.926794 | T65: 1.921452 | U65: 1.920618 | V65: 1.921497 | W65: 1.924581 | X65: 1.908737 | Y65: 1.905591 | Z65: 1.900162 | AA65: 1.896935 | AB65: 1.894529 | AC65: 1.886219 | AD65: 1.872889 | AE65: 1.869953 | AF65: 1.866915 | AG65: -0.004886
A66: PRC000:ha_CoaltoLiquids | B66: Coal to Liquids | C66: -- | D66: -- | E66: -- | F66: -- | G66: -- | H66: -- | I66: -- | J66: -- | K66: -- | L66: -- | M66: -- | N66: -- | O66: -- | P66: -- | Q66: -- | R66: -- | S66: -- | T66: -- | U66: -- | V66: -- | W66: -- | X66: -- | Y66: -- | Z66: -- | AA66: -- | AB66: -- | AC66: -- | AD66: -- | AE66: -- | AF66: -- | AG66: --
A67: PRC000:ha_Electricity | B67: Electricity | C67: 32.508968 | D67: 32.166168 | E67: 31.513943 | F67: 30.893538 | G67: 30.700684 | H67: 30.778042 | I67: 30.796724 | J67: 30.842819 | K67: 30.930162 | L67: 30.923807 | M67: 31.010801 | N67: 31.099874 | O67: 31.225035 | P67: 31.281097 | Q67: 30.992538 | R67: 30.775299 | S67: 30.640684 | T67: 30.502256 | U67: 30.375847 | V67: 30.421076 | W67: 30.332275 | X67: 30.332272 | Y67: 30.166447 | Z67: 30.047379 | AA67: 30.044783 | AB67: 29.821831 | AC67: 29.770481 | AD67: 29.670555 | AE67: 29.580069 | AF67: 29.370739 | AG67: -0.003494
B69: Non-Renewable Energy Expenditures by Sector
B70: (billion 2021 dollars)
A71: PRC000:ia_Residential | B71: Residential | C71: 275.19543 | D71: 274.69827 | E71: 272.04227 | F71: 268.02911 | G71: 266.8042 | H71: 267.53424 | I71: 267.90832 | J71: 269.61636 | K71: 271.74518 | L71: 272.91385 | M71: 274.75326 | N71: 278.11163 | O71: 280.4754 | P71: 281.95062 | Q71: 281.42996 | R71: 281.35779 | S71: 282.30389 | T71: 283.22006 | U71: 284.15469 | V71: 286.06439 | W71: 287.36847 | X71: 288.87006 | Y71: 289.41064 | Z71: 290.36166 | AA71: 291.91492 | AB71: 292.26712 | AC71: 293.7171 | AD71: 294.71783 | AE71: 295.96994 | AF71: 296.49973 | AG71: 0.002575
A72: PRC000:ia_Commercial | B72: Commercial | C72: 198.23921 | D72: 201.05307 | E72: 194.74181 | F72: 190.23673 | G72: 188.21303 | H72: 187.65823 | I72: 187.63826 | J72: 188.45783 | K72: 189.38261 | L72: 189.44869 | M72: 190.23714 | N72: 192.08362 | O72: 193.46835 | P72: 194.11852 | Q72: 193.13898 | R72: 192.45633 | S72: 192.71271 | T72: 192.80084 | U72: 192.95999 | V72: 194.02557 | W72: 194.53627 | X72: 195.41013 | Y72: 195.60156 | Z72: 195.9108 | AA72: 196.69556 | AB72: 196.62048 | AC72: 197.383 | AD72: 197.89435 | AE72: 198.69301 | AF72: 198.65846 | AG72: 7.3e-05
A73: PRC000:ia_Industrial | B73: Industrial 1/ | C73: 208.20412 | D73: 210.05396 | E73: 199.0141 | F73: 195.01041 | G73: 193.97601 | H73: 194.498 | I73: 196.37509 | J73: 201.22051 | K73: 205.68648 | L73: 208.69907 | M73: 212.24527 | N73: 216.80934 | O73: 221.01056 | P73: 221.60986 | Q73: 220.98859 | R73: 220.6508 | S73: 222.12486 | T73: 224.47987 | U73: 225.4944 | V73: 228.34744 | W73: 231.27826 | X73: 233.87386 | Y73: 235.76959 | Z73: 236.9698 | AA73: 236.51178 | AB73: 237.4744 | AC73: 237.51184 | AD73: 236.39203 | AE73: 236.96558 | AF73: 238.35934 | AG73: 0.004675
A74: PRC000:ia_Transportatio | B74: Transportation | C74: 609.53595 | D74: 598.28845 | E74: 547.89264 | F74: 551.61621 | G74: 547.54291 | H74: 545.69781 | I74: 546.7984 | J74: 547.26239 | K74: 546.77887 | L74: 548.69134 | M74: 548.89294 | N74: 565.02356 | O74: 565.95117 | P74: 564.18976 | Q74: 563.7074 | R74: 561.88098 | S74: 563.49658 | T74: 565.8255 | U74: 565.11725 | V74: 572.72223 | W74: 577.58527 | X74: 581.76526 | Y74: 589.78558 | Z74: 596.39648 | AA74: 599.4906 | AB74: 607.73554 | AC74: 611.27429 | AD74: 614.31207 | AE74: 619.45441 | AF74: 619.66425 | AG74: 0.000568
A75: PRC000:ia_TotalNon-Rene | B75: Total Non-Renewable Expenditures | C75: 1291.1747 | D75: 1284.0938 | E75: 1213.6908 | F75: 1204.8925 | G75: 1196.5361 | H75: 1195.3883 | I75: 1198.72 | J75: 1206.5571 | K75: 1213.5931 | L75: 1219.7529 | M75: 1226.1287 | N75: 1252.0281 | O75: 1260.9055 | P75: 1261.8688 | Q75: 1259.2649 | R75: 1256.3459 | S75: 1260.6381 | T75: 1266.3263 | U75: 1267.7263 | V75: 1281.1597 | W75: 1290.7683 | X75: 1299.9193 | Y75: 1310.5674 | Z75: 1319.6387 | AA75: 1324.6128 | AB75: 1334.0975 | AC75: 1339.8862 | AD75: 1343.3163 | AE75: 1351.083 | AF75: 1353.1819 | AG75: 0.001619
A76: PRC000:ja_Transportatio | B76: Transportation Renewable Expenditures | C76: 0.793518 | D76: 0.855206 | E76: 0.882733 | F76: 0.86548 | G76: 0.844213 | H76: 0.825758 | I76: 0.80896 | J76: 0.789201 | K76: 0.767372 | L76: 0.751337 | M76: 0.727102 | N76: 0.724035 | O76: 0.705781 | P76: 0.686639 | Q76: 0.670417 | R76: 0.655405 | S76: 0.646374 | T76: 0.641782 | U76: 0.638807 | V76: 0.645006 | W76: 0.650856 | X76: 0.650637 | Y76: 0.662279 | Z76: 0.680016 | AA76: 0.689701 | AB76: 0.704812 | AC76: 0.715713 | AD76: 0.729132 | AE76: 0.742763 | AF76: 0.751202 | AG76: -0.001888
A77: PRC000:ja_TotalExpendit | B77: Total Expenditures | C77: 1291.9681 | D77: 1284.949 | E77: 1214.5735 | F77: 1205.7579 | G77: 1197.3804 | H77: 1196.2141 | I77: 1199.5289 | J77: 1207.3463 | K77: 1214.3605 | L77: 1220.5043 | M77: 1226.8557 | N77: 1252.7521 | O77: 1261.6113 | P77: 1262.5554 | Q77: 1259.9353 | R77: 1257.0013 | S77: 1261.2844 | T77: 1266.968 | U77: 1268.3651 | V77: 1281.8047 | W77: 1291.4192 | X77: 1300.5699 | Y77: 1311.2296 | Z77: 1320.3187 | AA77: 1325.3025 | AB77: 1334.8024 | AC77: 1340.6019 | AD77: 1344.0454 | AE77: 1351.8258 | AF77: 1353.9331 | AG77: 0.001617
B80: Prices in Nominal Dollars
B81: Residential
A82: PRC000:nom_R_LiquefiedP | B82: Propane | C82: 21.519539 | D82: 23.918144 | E82: 24.217051 | F82: 24.935791 | G82: 25.653114 | H82: 26.580561 | I82: 27.797075 | J82: 29.328686 | K82: 31.014244 | L82: 32.694023 | M82: 34.429127 | N82: 36.408802 | O82: 38.23621 | P82: 39.975243 | Q82: 41.643776 | R82: 43.255379 | S82: 45.06881 | T82: 47.014851 | U82: 48.922707 | V82: 51.130653 | W82: 53.447807 | X82: 55.830475 | Y82: 58.463219 | Z82: 61.121395 | AA82: 63.463867 | AB82: 65.540504 | AC82: 67.531944 | AD82: 69.613518 | AE82: 71.843872 | AF82: 74.008057 | AG82: 0.043514
A83: PRC000:nom_R_Distillate | B83: Distillate Fuel Oil | C83: 21.74482 | D83: 22.778738 | E83: 22.748636 | F83: 24.861053 | G83: 26.329546 | H83: 27.851925 | I83: 29.621317 | J83: 30.792341 | K83: 31.995436 | L83: 32.971935 | M83: 34.302105 | N83: 35.573318 | O83: 36.823544 | P83: 37.983208 | Q83: 39.267166 | R83: 40.646938 | S83: 42.295757 | T83: 43.923122 | U83: 45.424511 | V83: 47.397709 | W83: 49.341187 | X83: 51.178768 | Y83: 53.481609 | Z83: 55.842537 | AA83: 57.673405 | AB83: 60.018929 | AC83: 61.958023 | AD83: 63.796551 | AE83: 66.058899 | AF83: 67.817245 | AG83: 0.040001
A84: PRC000:nom_R_NaturalGas | B84: Natural Gas | C84: 11.714767 | D84: 12.543241 | E84: 12.202449 | F84: 12.042318 | G84: 12.074784 | H84: 12.275156 | I84: 12.557124 | J84: 13.175778 | K84: 13.846839 | L84: 14.43425 | M84: 15.042178 | N84: 16.003031 | O84: 16.729973 | P84: 17.369701 | Q84: 17.962931 | R84: 18.53018 | S84: 19.236832 | T84: 19.960674 | U84: 20.710352 | V84: 21.478207 | W84: 22.371119 | X84: 23.13249 | Y84: 23.849205 | Z84: 24.621889 | AA84: 25.382959 | AB84: 26.228062 | AC84: 27.116817 | AD84: 28.030218 | AE84: 29.04003 | AF84: 30.030491 | AG84: 0.032993
A85: PRC000:nom_R_Electricit | B85: Electricity | C85: 38.76239 | D85: 39.760395 | E85: 40.441296 | F85: 40.948036 | G85: 42.041279 | H85: 43.654278 | I85: 45.274918 | J85: 46.968456 | K85: 48.764786 | L85: 50.440311 | M85: 52.301014 | N85: 54.228222 | O85: 56.232788 | P85: 58.235149 | Q85: 59.737148 | R85: 61.399422 | S85: 63.274548 | T85: 65.205223 | U85: 67.165619 | V85: 69.583977 | W85: 71.797447 | X85: 74.293343 | Y85: 76.476524 | Z85: 78.779671 | AA85: 81.454979 | AB85: 83.635262 | AC85: 86.340797 | AD85: 88.913673 | AE85: 91.521866 | AF85: 93.815933 | AG85: 0.030948
B87: Commercial
A88: PRC000:nom_C_LiquefiedG | B88: Propane | C88: 18.82229 | D88: 20.35074 | E88: 19.176968 | F88: 19.644886 | G88: 20.149332 | H88: 20.939877 | I88: 22.034401 | J88: 23.408949 | K88: 24.81222 | L88: 26.097706 | M88: 27.423658 | N88: 29.065638 | O88: 30.472038 | P88: 31.692806 | Q88: 32.855999 | R88: 34.02005 | S88: 35.483128 | T88: 37.036972 | U88: 38.469906 | V88: 40.285892 | W88: 42.107845 | X88: 43.92976 | Y88: 46.050961 | Z88: 48.072746 | AA88: 49.627422 | AB88: 50.975948 | AC88: 52.382263 | AD88: 54.000732 | AE88: 55.80312 | AF88: 57.445702 | AG88: 0.039226
A89: PRC000:nom_C_Distillate | B89: Distillate Fuel Oil | C89: 21.823187 | D89: 22.864527 | E89: 21.600349 | F89: 22.538956 | G89: 22.716763 | H89: 22.870413 | I89: 23.183537 | J89: 24.129183 | K89: 25.097404 | L89: 25.879559 | M89: 26.97542 | N89: 28.472673 | O89: 29.485674 | P89: 30.415445 | Q89: 31.518965 | R89: 32.628517 | S89: 34.011166 | T89: 35.360092 | U89: 36.565868 | V89: 38.259872 | W89: 39.890251 | X89: 41.40807 | Y89: 43.365456 | Z89: 45.385769 | AA89: 46.893353 | AB89: 48.884224 | AC89: 50.466415 | AD89: 51.926086 | AE89: 53.812157 | AF89: 55.194649 | AG89: 0.032514
A90: PRC000:nom_C_ResidualFu | B90: Residual Fuel Oil | C90: 6.510058 | D90: 7.800477 | E90: 7.945353 | F90: 9.556235 | G90: 10.553672 | H90: 11.556342 | I90: 12.909644 | J90: 13.55414 | K90: 14.135114 | L90: 14.810273 | M90: 15.443988 | N90: 16.214159 | O90: 16.88455 | P90: 17.565434 | Q90: 18.204203 | R90: 18.902946 | S90: 19.504274 | T90: 20.369133 | U90: 20.943598 | V90: 22.739405 | W90: 23.757801 | X90: 24.624191 | Y90: 25.966454 | Z90: 27.371773 | AA90: 28.37871 | AB90: 29.709684 | AC90: 30.750561 | AD90: 31.706526 | AE90: 32.928417 | AF90: 33.788494 | AG90: 0.058429
A91: PRC000:nom_C_NaturalGas | B91: Natural Gas | C91: 8.442578 | D91: 9.102607 | E91: 8.992414 | F91: 8.915836 | G91: 9.015419 | H91: 9.267706 | I91: 9.585958 | J91: 10.077318 | K91: 10.609268 | L91: 11.058864 | M91: 11.524681 | N91: 12.192711 | O91: 12.736744 | P91: 13.204803 | Q91: 13.612744 | R91: 14.009382 | S91: 14.536539 | T91: 15.07787 | U91: 15.641514 | V91: 16.216299 | W91: 16.906044 | X91: 17.457684 | Y91: 17.959169 | Z91: 18.514944 | AA91: 19.054134 | AB91: 19.667431 | AC91: 20.318686 | AD91: 20.989712 | AE91: 21.750826 | AF91: 22.491329 | AG91: 0.034365
A92: PRC000:nom_C_Electricit | B92: Electricity | C92: 33.23053 | D92: 33.978516 | E92: 33.874538 | F92: 34.144749 | G92: 34.978958 | H92: 36.308815 | I92: 37.550941 | J92: 38.900845 | K92: 40.301247 | L92: 41.556381 | M92: 43.000675 | N92: 44.457672 | O92: 46.101952 | P92: 47.656097 | Q92: 48.67065 | R92: 49.857143 | S92: 51.332649 | T92: 52.747883 | U92: 54.245193 | V92: 56.169052 | W92: 57.813347 | X92: 59.804386 | Y92: 61.462963 | Z92: 63.146969 | AA92: 65.182571 | AB92: 66.765312 | AC92: 68.797684 | AD92: 70.724792 | AE92: 72.73188 | AF92: 74.371185 | AG92: 0.028169
B94: Industrial 1/
A95: PRC000:nom_I_LiquefiedP | B95: Propane | C95: 13.663833 | D95: 14.819919 | E95: 13.271934 | F95: 13.628423 | G95: 13.95307 | H95: 14.548325 | I95: 15.435884 | J95: 16.600773 | K95: 17.782276 | L95: 18.83663 | M95: 19.937275 | N95: 21.00005 | O95: 22.172026 | P95: 23.112478 | Q95: 23.917982 | R95: 24.776943 | S95: 25.955269 | T95: 27.207771 | U95: 28.310419 | V95: 29.833817 | W95: 31.332878 | X95: 32.812332 | Y95: 34.627686 | Z95: 36.30315 | AA95: 37.4235 | AB95: 38.314682 | AC95: 39.270897 | AD95: 40.458591 | AE95: 41.837971 | AF95: 43.012806 | AG95: 0.040335
A96: PRC000:nom_I_Distillate | B96: Distillate Fuel Oil | C96: 21.75238 | D96: 22.782827 | E96: 21.600447 | F96: 22.502117 | G96: 22.671473 | H96: 22.807241 | I96: 23.093634 | J96: 24.042925 | K96: 25.024292 | L96: 25.825529 | M96: 26.921162 | N96: 27.974201 | O96: 28.998323 | P96: 29.918238 | Q96: 30.948078 | R96: 32.043514 | S96: 33.408504 | T96: 34.742168 | U96: 35.938408 | V96: 37.634182 | W96: 39.255959 | X96: 40.764423 | Y96: 42.711178 | Z96: 44.71167 | AA96: 46.220592 | AB96: 48.205631 | AC96: 49.785362 | AD96: 51.237804 | AE96: 53.11813 | AF96: 54.499023 | AG96: 0.032178
