Workbook

Sheet About
A1: FoISaGPbE Fraction of Goods Purchased by Entity
A2: FoISaGPbE Nonenergy Inputs by Supplying Entity as Share of Gross Output
A4: Sources: | B4: All Data
B5: Organisation for Economic Co-operation and Development | C5: Organisation for Economic Co-operation and Development
B6: 2019 | C6: 2021 ed.
B7: Interactive Data Tables: OECD.Stat | C7: Interactive Data Tables: OECD Stat
B8: https://stats.oecd.org | C8: https://stats.oecd.org/Index.aspx?QueryId=109612
B9: Input Output Database: Input-Output Tables (IOTs) ISIC Rev. 4 | C9: Input Output Tables (IOTS) 2021ed.
B10: TTL : Total; VAL: Value Added, DOMIMP: Domestic output and imports | C10: DOMIMP (Domestic output and imports0
A13: Notes
A15: Explanation
A16: When industrial production declines in response to a policy package, the effect is not only
A17: to reduce industry revenue. Industry also buys less services from suppliers, and pays less
A18: income and other taxes to government. This variable helps us calculate the cash flows associated
A19: both with lost revenue (reduced purchases of industrial goods) and reduced spending by
A20: industry.
A22: Fraction of Goods Purchased by Entity is used to allocate money for reduced sales of industrial
A23: outputs. Values for all industries (except Waste Management) are calculated, but only the values
A24: for non-energy industries are actually used in Vensim (in EPS 1.5.0), since the cash flows associated
A25: with reduced sales of energy are already handled in the various demand sectors, with cash flows
A26: assigned to the relevant energy supply industry, as well as to the users of the energy, who buy less.
... A82: to imperceptible levels.

Sheet OECD Crosswalk
A1: OECD Name | B1: Fraction of Good Purchased Category | C1: Industry Category | E1: government | H1: Cement and other carbonate use
A2: TTL_01T03: Agriculture, forestry and fishing | B2: nonenergy industries | C2: agriculture | E2: nonenergy industries | H2: Natural gas and petroleum systems
A3: TTL_05T06: Mining and extraction of energy producing products | B3: natural gas and petroleum suppliers | C3: other industries | E3: labor and consumers | H3: Iron and steel
A4: TTL_07T08: Mining and quarrying of non-energy producing products | B4: nonenergy industries | C4: other industries | E4: foreign entities | H4: Chemicals
A5: TTL_09: Mining support service activities | B5: nonenergy industries | C5: other industries | E5: electricity suppliers | H5: Coal mining
A6: TTL_10T12: Food products, beverages and tobacco | B6: nonenergy industries | C6: other industries | E6: coal suppliers | H6: Waste management
A7: TTL_13T15: Textiles, wearing apparel, leather and related products | B7: nonenergy industries | C7: other industries | E7: natural gas and petroleum suppliers | H7: Agriculture
A8: TTL_16: Wood and of products of wood and cork (except furniture) | B8: nonenergy industries | C8: other industries | E8: biomass and biofuel suppliers | H8: Other industries
A9: TTL_17T18: Paper products and printing | B9: nonenergy industries | C9: other industries | E9: other energy suppliers
A10: TTL_19: Coke and refined petroleum products | B10: natural gas and petroleum suppliers | C10: natural gas and petroleum systems
A11: TTL_20T21: Chemicals and pharmaceutical products | B11: nonenergy industries | C11: chemicals
A12: TTL_22: Rubber and plastics products | B12: nonenergy industries | C12: other industries
A13: TTL_23: Other non-metallic mineral products | B13: nonenergy industries | C13: Cement and other carbonate use
A14: TTL_24: Manufacture of basic metals | B14: nonenergy industries | C14: iron and steel
A15: TTL_25: Fabricated metal products, except machinery and equipment | B15: nonenergy industries | C15: other industries
A16: TTL_26: Computer, electronic and optical products | B16: nonenergy industries | C16: other industries
A17: TTL_27: Electrical equipment | B17: nonenergy industries | C17: other industries
A18: TTL_28: Machinery and equipment n.e.c. | B18: nonenergy industries | C18: other industries
A19: TTL_29: Motor vehicles, trailers and semi-trailers | B19: nonenergy industries | C19: other industries
A20: TTL_30: Other transport equipment | B20: nonenergy industries | C20: other industries
A21: TTL_31T33: Other manufacturing; repair and installation of machinery and equipment | B21: nonenergy industries | C21: other industries
A22: TTL_35T39: Electricity, gas, water supply, sewerage, waste and remediation services | B22: energy suppliers | C22: energy suppliers
A23: TTL_41T43: Construction | B23: nonenergy industries
A24: TTL_45T47: Wholesale and retail trade; repair of motor vehicles | B24: nonenergy industries
A25: TTL_49T53: Transportation and storage | B25: nonenergy industries
A26: TTL_55T56: Accomodation and food services | B26: nonenergy industries
A27: TTL_58T60: Publishing, audiovisual and broadcasting activities | B27: nonenergy industries
A28: TTL_61: Telecommunications | B28: nonenergy industries
A29: TTL_62T63: IT and other information services | B29: nonenergy industries
A30: TTL_64T66: Financial and insurance activities | B30: nonenergy industries
A31: TTL_68: Real estate activities | B31: nonenergy industries
A32: TTL_69T82: Other business sector services | B32: nonenergy industries
A33: TTL_84: Public administration and defence; compulsory social security | B33: government
A34: TTL_85: Education | B34: nonenergy industries
... A42: OUTPUT: Output at basic prices | B42: output
A43: D01T03: Agriculture, forestry and fishing | B43: nonenergy industries | C43: agriculture
A44: D05T06: Mining and extraction of energy producing products | B44: natural gas and petroleum suppliers | C44: other industries
A45: D07T08: Mining and quarrying of non-energy producing products | B45: nonenergy industries | C45: other industries
A46: D09: Mining support service activities | B46: nonenergy industries | C46: other industries
A47: D10T12: Food products, beverages and tobacco | B47: nonenergy industries | C47: other industries
A48: D13T15: Textiles, wearing apparel, leather and related products | B48: nonenergy industries | C48: other industries
A49: D16: Wood and products of wood and cork | B49: nonenergy industries | C49: other industries
A50: D17T18: Paper products and printing | B50: nonenergy industries | C50: other industries
A51: D19: Coke and refined petroleum products | B51: natural gas and petroleum suppliers | C51: natural gas and petroleum systems
A52: D20T21: Chemicals and pharmaceutical products | B52: nonenergy industries | C52: chemicals
A53: D22: Rubber and plastic products | B53: nonenergy industries | C53: other industries
A54: D23: Other non-metallic mineral products | B54: nonenergy industries | C54: Cement and other carbonate use
... A63: D35T39: Electricity, gas, water supply, sewerage, waste and remediation services | B63: energy suppliers | C63: energy suppliers
A64: D41T43: Construction | B64: nonenergy industries
A65: D45T47: Wholesale and retail trade; repair of motor vehicles | B65: nonenergy industries
A66: D49T53: Transportation and storage | B66: nonenergy industries
A67: D55T56: Accomodation and food services | B67: nonenergy industries
A68: D58T60: Publishing, audiovisual and broadcasting activities | B68: nonenergy industries
A69: D61: Telecommunications | B69: nonenergy industries
A70: D62T63: IT and other information services | B70: nonenergy industries
A71: D64T66: Financial and insurance activities | B71: nonenergy industries
A72: D68: Real estate activities | B72: nonenergy industries
A73: D69T82: Other business sector services | B73: nonenergy industries
A74: D84: Public admin. and defence; compulsory social security | B74: government
A75: D85: Education | B75: nonenergy industries
... A90: GOPS: Gross operating surplus and mixed income | B90: other

Sheet OECD Data IO Table - Total (HKD
A1: =DotStatQuery(#REF!) -> #NAME?
A2: To Sector | B2: =INDEX('OECD Crosswalk'!$B$2:$B$90,MATCH('OECD Data IO Table - Total (USD'!B8,'OECD Crosswalk'!$A$2:$A$90,0),1) -> #N/A | C2: =INDEX('OECD Crosswalk'!$B$2:$B$90,MATCH('OECD Data IO Table - Total (USD'!C8,'OECD Crosswalk'!$A$2:$A$90,0),1) -> #N/A | D2: =INDEX('OECD Crosswalk'!$B$2:$B$90,MATCH('OECD Data IO Table - Total (USD'!D8,'OECD Crosswalk'!$A$2:$A$90,0),1) -> #N/A | E2: =INDEX('OECD Crosswalk'!$B$2:$B$90,MATCH('OECD Data IO Table - Total (USD'!E8,'OECD Crosswalk'!$A$2:$A$90,0),1) -> nonenergy industries | F2: =INDEX('OECD Crosswalk'!$B$2:$B$90,MATCH('OECD Data IO Table - Total (USD'!F8,'OECD Crosswalk'!$A$2:$A$90,0),1) -> natural gas and petroleum suppliers | G2: =INDEX('OECD Crosswalk'!$B$2:$B$90,MATCH('OECD Data IO Table - Total (USD'!G8,'OECD Crosswalk'!$A$2:$A$90,0),1) -> nonenergy industries | H2: =INDEX('OECD Crosswalk'!$B$2:$B$90,MATCH('OECD Data IO Table - Total (USD'!H8,'OECD Crosswalk'!$A$2:$A$90,0),1) -> nonenergy industries | I2: =INDEX('OECD Crosswalk'!$B$2:$B$90,MATCH('OECD Data IO Table - Total (USD'!I8,'OECD Crosswalk'!$A$2:$A$90,0),1) -> nonenergy industries | ... AT2: =INDEX('OECD Crosswalk'!$B$2:$B$90,MATCH('OECD Data IO Table - Total (USD'!AT8,'OECD Crosswalk'!$A$2:$A$90,0),1) -> imports
A3: From Sector | B3: =INDEX('OECD Crosswalk'!$C$2:$C$90,MATCH('OECD Data IO Table - Total (USD'!B8,'OECD Crosswalk'!$A$2:$A$90,0),1) -> #N/A | C3: =INDEX('OECD Crosswalk'!$C$2:$C$90,MATCH('OECD Data IO Table - Total (USD'!C8,'OECD Crosswalk'!$A$2:$A$90,0),1) -> #N/A | D3: =INDEX('OECD Crosswalk'!$C$2:$C$90,MATCH('OECD Data IO Table - Total (USD'!D8,'OECD Crosswalk'!$A$2:$A$90,0),1) -> #N/A | E3: =INDEX('OECD Crosswalk'!$C$2:$C$90,MATCH('OECD Data IO Table - Total (USD'!E8,'OECD Crosswalk'!$A$2:$A$90,0),1) -> agriculture | F3: =INDEX('OECD Crosswalk'!$C$2:$C$90,MATCH('OECD Data IO Table - Total (USD'!F8,'OECD Crosswalk'!$A$2:$A$90,0),1) -> other industries | G3: =INDEX('OECD Crosswalk'!$C$2:$C$90,MATCH('OECD Data IO Table - Total (USD'!G8,'OECD Crosswalk'!$A$2:$A$90,0),1) -> other industries | H3: =INDEX('OECD Crosswalk'!$C$2:$C$90,MATCH('OECD Data IO Table - Total (USD'!H8,'OECD Crosswalk'!$A$2:$A$90,0),1) -> other industries | I3: =INDEX('OECD Crosswalk'!$C$2:$C$90,MATCH('OECD Data IO Table - Total (USD'!I8,'OECD Crosswalk'!$A$2:$A$90,0),1) -> other industries | ... AT3: =INDEX('OECD Crosswalk'!$C$2:$C$90,MATCH('OECD Data IO Table - Total (USD'!AT8,'OECD Crosswalk'!$A$2:$A$90,0),1) -> 0
A4: Variable | B4: TTL: Total
A5: Country | B5: HKG: Hong Kong, China
A6: Time | B6: 2021
A7: Unit | B7: HK Dollar, Millions
A8: To: (sector in column) | B8: D01T03: Agriculture, forestry and fishing | C8: D05T06: Mining and extraction of energy producing products | D8: D07T08: Mining and quarrying of non-energy producing products | E8: D09: Mining support service activities | F8: D10T12: Food products, beverages and tobacco | G8: D13T15: Textiles, wearing apparel, leather and related products | H8: D16: Wood and products of wood and cork | I8: D17T18: Paper products and printing | J8: D19: Coke and refined petroleum products | K8: D20T21: Chemicals and pharmaceutical products | L8: D22: Rubber and plastic products | M8: D23: Other non-metallic mineral products | N8: D24: Basic metals | O8: D25: Fabricated metal products | P8: D26: Computer, electronic and optical products | Q8: D27: Electrical equipment | R8: D28: Machinery and equipment, nec | S8: D29: Motor vehicles, trailers and semi-trailers | T8: D30: Other transport equipment | U8: D31T33: Other manufacturing; repair and installation of machinery and equipment | V8: D35T39: Electricity, gas, water supply, sewerage, waste and remediation services | W8: D41T43: Construction | X8: D45T47: Wholesale and retail trade; repair of motor vehicles | Y8: D49T53: Transportation and storage | Z8: D55T56: Accomodation and food services | AA8: D58T60: Publishing, audiovisual and broadcasting activities | AB8: D61: Telecommunications | AC8: D62T63: IT and other information services | AD8: D64T66: Financial and insurance activities | AE8: D68: Real estate activities | AF8: D69T82: Other business sector services | AG8: D84: Public admin. and defence; compulsory social security | AH8: D85: Education | AI8: D86T88: Human health and social work | AJ8: D90T96: Arts, entertainment, recreation and other service activities | AK8: D97T98: Private households with employed persons | AL8: HFCE: Final consumption expenditure of households | AM8: NPISH: Final consumption expenditure of non-profit institutions serving households | AN8: GGFC: Final consumption expenditure of general government | AO8: GFCF: Gross Fixed Capital Formation | AP8: INVNT: Changes in inventories | AQ8: CONS_ABR: Direct purchases abroad by residents (imports) | AR8: CONS_NONRES: Direct purchases by non-residents (exports) | AS8: EXPO: Exports (cross border) | AT8: IMPO: Imports (cross border) | AU8: Totals
A9: From: (sector in row)
A10: TTL_01T03: Agriculture, forestry and fishing | B10: =0.9+0.1+0.1 -> 1.1 | C10: 0 | D10: 0 | E10: 0.0012333592 | F10: =154.9+4.4 -> 159.3 | G10: =1.6+0.2 -> 1.8 | H10: =0.5+0.1 -> 0.6 | I10: =2.5+0.6 -> 3.1 | J10: 0 | K10: =0.3+0.2 -> 0.5 | L10: 0 | M10: 0.1 | N10: 0.4 | O10: 0 | P10: 0.1 | Q10: 0.1 | R10: 0.1 | S10: 0.1 | T10: 1.6348852e-05 | U10: 0 | V10: =43.7+16.7+5.3+2.2 -> 67.9 | W10: =7.9+1.3 -> 9.2 | X10: =44.4+3.5 -> 47.9 | Y10: =34.6+141.9+255+6.8+4+4.4+37.6+62.6+1.3+1.1 -> 549.3 | Z10: =453.1+91.4 -> 544.5 | AA10: =3.6+1 -> 4.6 | AB10: =8.3+1.8 -> 10.1 | AC10: 0.2 | AD10: =8.6+1.5 -> 10.1 | AE10: =2.9+0.4 -> 3.3 | AF10: =2+5.2+0.3+0.6 -> 8.1 | AG10: =7.1+0.7 -> 7.8 | AH10: =11.8+1.3 -> 13.1 | AI10: =19.4+1.6 -> 21 | AJ10: =13+2.4+19.7+3.5 -> 38.6 | AK10: 0 | AL10: =4367.1+711.7 -> 5078.8 | AM10: 0.1 | AN10: 0 | AO10: =3.2+0.3 -> 3.5 | AP10: =10.3+0.3 -> 10.6 | AQ10: =33.6+2.6 -> 36.2 | AR10: =1.1+2.5 -> 3.6 | AS10: =4.5+7.5 -> 12 | AT10: =-5242.7+-891.3 -> -6134 | AU10: =SUM(B10:AN10) -> 6581.9012
A11: TTL_05T06: Mining and extraction of energy producing products | B11: =15.7+1.5 -> 17.2 | C11: 0 | D11: 0 | E11: 169.3 | F11: 167.3 | G11: 136.5 | H11: 8.7 | I11: 91.6 | J11: 18.1 | K11: =0.6+0.1 -> 0.7 | L11: 0 | M11: 1.4 | N11: 43.7 | O11: 2.2 | P11: 4.1 | Q11: 11.9 | R11: 8.1 | S11: 2.6 | T11: 1.7 | U11: 9.7 | V11: =54.1+30.2 -> 84.3 | W11: 3.8 | X11: 22.3 | Y11: =129.4+1.9+39.4+1601.3+9.5 -> 1781.5 | Z11: 6 | AA11: 3.2 | AB11: 12.7 | AC11: 4.1 | AD11: 44.4 | AE11: 11.6 | AF11: =27.1+84.5 -> 111.6 | AG11: 7.7 | AH11: 30.2 | AI11: 16.2 | AJ11: =14.1+22.3 -> 36.4 | AK11: 0 | AL11: 37.1 | AM11: 0.6 | AN11: 0 | AO11: 3.7 | AP11: 31.4 | AQ11: 0.4 | AR11: 0 | AS11: 0 | AT11: -2952.4 | AU11: =SUM(B11:AN11) -> 2908.5
A12: TTL_07T08: Mining and quarrying of non-energy producing products | B12: =3.1+0.4 -> 3.5 | C12: 0 | D12: 0 | E12: 38.7 | F12: 20.2 | G12: 17.4 | H12: 1.3 | I12: 9.9 | J12: 0.5 | K12: =0.2+0.1 -> 0.3 | L12: 0 | M12: 0.9 | N12: 10.1 | O12: 0.6 | P12: 0.7 | Q12: 2.4 | R12: 1.6 | S12: 0.4 | T12: 0.3 | U12: 1.7 | V12: =4.2+4 -> 8.2 | W12: 2.1 | X12: 3.7 | Y12: =18.8+0.2+4.8+288.2+0.9 -> 312.9 | Z12: 0.8 | AA12: 800.1 | AB12: 1.6 | AC12: 0.5 | AD12: 4.7 | AE12: 1.8 | AF12: =5.7+10.8 -> 16.5 | AG12: 1.3 | AH12: 3.1 | AI12: 1.7 | AJ12: =1.9+3 -> 4.9 | AK12: 0 | AL12: 6.1 | AM12: 0 | AN12: 0 | AO12: 1 | AP12: 1.1 | AQ12: 0.4 | AR12: 0 | AS12: 0 | AT12: -481.4 | AU12: =SUM(B12:AN12) -> 1280.5
A13: TTL_09: Mining support service activities | B13: =61.5+20.9 -> 82.4 | C13: 0 | D13: 0 | E13: 6150 | F13: 152.1 | G13: 30.3 | H13: 37.1 | I13: 141.9 | J13: 2.4 | K13: =0.5 -> 0.5 | L13: 0 | M13: 1.1 | N13: 131.8 | O13: 6.1 | P13: 2 | Q13: 5.3 | R13: 22.1 | S13: 2 | T13: 1.1 | U13: 0.2 | V13: =52.3+30.2 -> 82.5 | W13: 10.6 | X13: 26.6 | Y13: =317.8+2.7+174+48.2+55.1 -> 597.8 | Z13: 3.5 | AA13: 3.2 | AB13: 0 | AC13: 1.6 | AD13: 190.1 | AE13: 50.8 | AF13: =120.1+41.2 -> 161.3 | AG13: 20.2 | AH13: 83.8 | AI13: 0.6 | AJ13: =6.4+18 -> 24.4 | AK13: 0 | AL13: 6.2 | AM13: 0 | AN13: 0 | AO13: 1.2 | AP13: 1.1 | AQ13: 0.1 | AR13: 0 | AS13: 73.2 | AT13: -14.6 | AU13: =SUM(B13:AN13) -> 8031.6
A14: TTL_10T12: Food products, beverages and tobacco | B14: =11.3+0.9 -> 12.2 | C14: 0 | D14: 0 | E14: 0.1 | F14: 539.2 | G14: 78.2 | H14: 53.8 | I14: 396.1 | J14: 2.8 | K14: =19.7+10.5 -> 30.2 | L14: 0 | M14: 3.2 | N14: 20.7 | O14: 1.7 | P14: 2.8 | Q14: 4.8 | R14: 3.2 | S14: 1.5 | T14: 0.6 | U14: 0.5 | V14: =255.9+134.1 -> 390 | W14: 848.3 | X14: 801 | Y14: =295.2+974+907.2+327.5+153.3 -> 2657.2 | Z14: 1390.5 | AA14: 800.1 | AB14: 197.8 | AC14: 9.7 | AD14: 595.1 | AE14: 216.6 | AF14: =66.2+113.4 -> 179.6 | AG14: 75.2 | AH14: 93.8 | AI14: 418.3 | AJ14: =106.5+249.3 -> 355.8 | AK14: 0 | AL14: 11837.5 | AM14: 0 | AN14: 0 | AO14: 244.1 | AP14: 3599.6 | AQ14: 148.6 | AR14: 219.5 | AS14: 380.6 | AT14: -17148.7 | AU14: =SUM(B14:AN14) -> 22018.1
A15: TTL_13T15: Textiles, wearing apparel, leather and related products | B15: =0.5+0.1 -> 0.6 | C15: 0 | D15: 0 | E15: 0.2 | F15: 22.7 | G15: 642.5 | H15: 2.8 | I15: 30.9 | J15: 0.1 | K15: =0.7+0.3 -> 1 | L15: 0 | M15: 0.6 | N15: 2.5 | O15: 0.3 | P15: 0.3 | Q15: 0.6 | R15: 0.4 | S15: 0.8 | T15: 0.2 | U15: 0.7 | V15: =13.3+21 -> 34.3 | W15: 15.2 | X15: 320.4 | Y15: =129+151.7+110.9+152.1+80.8 -> 624.5 | Z15: 11.8 | AA15: 3.2 | AB15: 86.1 | AC15: 3.9 | AD15: 312.3 | AE15: 117.6 | AF15: =28.7+60.6 -> 89.3 | AG15: 35.2 | AH15: 23.1 | AI15: 32.3 | AJ15: =20+106.4 -> 126.4 | AK15: 0 | AL15: 9666.4 | AM15: 0 | AN15: 0 | AO15: 62.4 | AP15: 1918.5 | AQ15: 94 | AR15: 19.7 | AS15: 389.1 | AT15: -11723.4 | AU15: =SUM(B15:AN15) -> 12209.2
A16: TTL_16: Wood and of products of wood and cork (except furniture) | B16: =2+0.1 -> 2.1 | C16: 0 | D16: 0 | E16: 0.1 | F16: 25.5 | G16: 0.2 | H16: 0 | I16: 0.2 | J16: 0 | K16: 0.1 | L16: 0 | M16: 0.1 | N16: 0.9 | O16: 0.1 | P16: 0.1 | Q16: 0.2 | R16: 0.1 | S16: 0.2 | T16: 0.1 | U16: 0.1 | V16: =1.8+1.9 -> 3.7 | W16: 113.8 | X16: 12.2 | Y16: =19.9+83.6+12.7+34.4+3.1 -> 153.7 | Z16: 1.4 | AA16: 800.1 | AB16: 4.7 | AC16: 0 | AD16: 10.6 | AE16: 3.1 | AF16: =0.9+1.2 -> 2.1 | AG16: 1.1 | AH16: 1.3 | AI16: 28.4 | AJ16: =2.3+3.6 -> 5.9 | AK16: 0 | AL16: 565.3 | AM16: 0 | AN16: 0 | AO16: 66.4 | AP16: 334.4 | AQ16: 6.2 | AR16: 0.2 | AS16: 26 | AT16: -626.1 | AU16: =SUM(B16:AN16) -> 1737.5
A17: TTL_17T18: Paper products and printing | B17: =9.6+1 -> 10.6 | C17: 0 | D17: 0 | E17: 0.1 | F17: 751.4 | G17: 175.7 | H17: 5.3 | I17: 796.5 | J17: 0.3 | K17: =3.2+2.7 -> 5.9 | L17: 0 | M17: 10 | N17: 6 | O17: 0.8 | P17: 4.5 | Q17: 10 | R17: 3.4 | S17: 1.3 | T17: 0.3 | U17: 3.3 | V17: =16.3+20.7 -> 37 | W17: 449.8 | X17: 427.7 | Y17: =117.7+176.3+82.9+171.8+54.5 -> 603.2 | Z17: 5.2 | AA17: 3.2 | AB17: 59.7 | AC17: 2.7 | AD17: 351.9 | AE17: 89.7 | AF17: =24.6+29.4 -> 54 | AG17: 16.4 | AH17: 39.5 | AI17: 334 | AJ17: =24+41.4 -> 65.4 | AK17: 0 | AL17: 1557.3 | AM17: 0 | AN17: 0 | AO17: 18.8 | AP17: 234 | AQ17: 17 | AR17: 74.7 | AS17: 124.2 | AT17: -1724.9 | AU17: =SUM(B17:AN17) -> 5882.1
A18: TTL_19: Coke and refined petroleum products | B18: =1+0.1 -> 1.1 | C18: 0 | D18: 0 | E18: 15.7 | F18: 11.7 | G18: 3.1 | H18: 2.1 | I18: 11.4 | J18: 74.9 | K18: =119.6+20.8 -> 140.4 | L18: 0 | M18: 52.8 | N18: 667.4 | O18: 48.7 | P18: 4.8 | Q18: 15.9 | R18: 9.3 | S18: 10.4 | T18: 3.5 | U18: 6.1 | V18: =84.7+55.8 -> 140.5 | W18: 4 | X18: 4405.8 | Y18: =293.6+671.7+606.3+737.5+45.6 -> 2354.7 | Z18: 15 | AA18: 800.1 | AB18: 40.7 | AC18: 3.9 | AD18: 535 | AE18: 134.4 | AF18: =23.7+97.7 -> 121.4 | AG18: 253.3 | AH18: 116.1 | AI18: 20.1 | AJ18: =29.2+62.4 -> 91.6 | AK18: 0 | AL18: 3345.6 | AM18: 0 | AN18: 0 | AO18: 12.6 | AP18: 1096.6 | AQ18: 63.2 | AR18: 69 | AS18: 33.1 | AT18: -13543.9 | AU18: =SUM(B18:AN18) -> 13461.5
A19: TTL_20T21: Chemicals and pharmaceutical products | B19: =2.1+0.1+0.1 -> 2.3 | C19: 0 | D19: 0 | E19: =11.5+0.1 -> 11.6 | F19: =32.9+2.4 -> 35.3 | G19: =3.1+22 -> 25.1 | H19: =11.5+0.4 -> 11.9 | I19: =93.6+2.1 -> 95.7 | J19: =27.4+0.7 -> 28.1 | K19: =289.4+68.9+7.7+55.8 -> 421.8 | L19: 0 | M19: =76.4+1.6 -> 78 | N19: =197.6+667.4 -> 865 | O19: =18.5+0.5 -> 19 | P19: =37+1.5 -> 38.5 | Q19: =106.2+2.1 -> 108.3 | R19: =28.2+0.9 -> 29.1 | S19: =20.4+0.5 -> 20.9 | T19: =6.1+0.2 -> 6.3 | U19: =12.1+0.2 -> 12.3 | V19: =12.5+158.3+0.6+4.8 -> 176.2 | W19: =7+0.8 -> 7.8 | X19: =764.3+51 -> 815.3 | Y19: =16.8+34.7+30.3+104+13+0.9+2.9+2.9+4.9+1.1 -> 211.5 | Z19: =23.4+2 -> 25.4 | AA19: =68.6+1.7 -> 70.3 | AB19: =21.5+2 -> 23.5 | AC19: =1.7+0.1 -> 1.8 | AD19: =125.9+9.8 -> 135.7 | AE19: =54+2.7 -> 56.7 | AF19: =19.7+46.6+2.8+1.7 -> 70.8 | AG19: =78+14.6 -> 92.6 | AH19: =202.3+21.7 -> 224 | AI19: =87.8+75.7 -> 163.5 | AJ19: =79.1+9.8+267.1+12.6 -> 368.6 | AK19: 0 | AL19: =3025.1+1373.4 -> 4398.5 | AM19: 0 | AN19: =0.2+0.2 -> 0.4 | AO19: =127.2+30.4 -> 157.6 | AP19: =899.5+349.2 -> 1248.7 | AQ19: =23.6+18.4 -> 42 | AR19: =6.1+44.5 -> 50.6 | AS19: =333.9+161.6 -> 495.5 | AT19: =-6496.9-1813.5 -> -8310.4 | AU19: =SUM(B19:AN19) -> 8651.8
A20: TTL_22: Rubber and plastics products | B20: 0.2 | C20: 0 | D20: 0 | E20: 1.4 | F20: 49.5 | G20: 5.7 | H20: 1.7 | I20: 21.7 | J20: 2.3 | K20: =19.8+12.8 -> 32.6 | L20: 0 | M20: 15.7 | N20: 41.9 | O20: 7.3 | P20: 28.6 | Q20: 83.7 | R20: 30.4 | S20: 82.5 | T20: 15.9 | U20: 10.9 | V20: =2.4+34 -> 36.4 | W20: 2.4 | X20: 2002.7 | Y20: =17.9+2.3+2.4+14.1+3.3 -> 40 | Z20: 7 | AA20: 14.4 | AB20: 5 | AC20: 0.2 | AD20: 14.1 | AE20: 29.8 | AF20: =1.6+3.5 -> 5.1 | AG20: 6.7 | AH20: 2.1 | AI20: 2.2 | AJ20: =15.1+38.2 -> 53.3 | AK20: 0 | AL20: 326 | AM20: 0 | AN20: 0.1 | AO20: 43.5 | AP20: 40.4 | AQ20: 0.5 | AR20: 0 | AS20: 0 | AT20: -3064 | AU20: =SUM(B20:AN20) -> 2979.5
A21: TTL_23: Other non-metallic mineral products | B21: 0.1 | C21: 0 | D21: 0 | E21: 4.4 | F21: 41.4 | G21: 1.6 | H21: 1.4 | I21: 5.3 | J21: 14 | K21: =11.9+8.7 -> 20.6 | L21: 0 | M21: 402.6 | N21: 451.1 | O21: 42.1 | P21: 36.3 | Q21: 98.8 | R21: 19.8 | S21: 61.1 | T21: 18.4 | U21: 6 | V21: =5.3+32 -> 37.3 | W21: 58.7 | X21: 183.1 | Y21: =2.6+2.7+5+26+13.2 -> 49.5 | Z21: 3.2 | AA21: 12.2 | AB21: 35.8 | AC21: 0.4 | AD21: 61.3 | AE21: 22 | AF21: =3.9+7.9 -> 11.8 | AG21: 115.8 | AH21: 81.2 | AI21: 4.6 | AJ21: =18.4+43.1 -> 61.5 | AK21: 0 | AL21: 672.5 | AM21: 0 | AN21: 0 | AO21: 49.4 | AP21: 165.7 | AQ21: 0.3 | AR21: 0 | AS21: 108.8 | AT21: -1681.9 | AU21: =SUM(B21:AN21) -> 2635.9
A22: TTL_24: Manufacture of basic metals | B22: 0.1 | C22: 0 | D22: 0 | E22: 5.3 | F22: 10.3 | G22: 0.9 | H22: 1.7 | I22: 8.7 | J22: 5 | K22: =14.7+3.7 -> 18.4 | L22: 0 | M22: 31.6 | N22: 5839.2 | O22: 476 | P22: 110.9 | Q22: 489.7 | R22: 157.6 | S22: 52.9 | T22: 10.1 | U22: 37.9 | V22: =6.5+87.6 -> 94.1 | W22: 8.3 | X22: 5508.3 | Y22: =5.3+13.1+10.3+50.1+2.9 -> 81.7 | Z22: 1.7 | AA22: 12.2 | AB22: 8.3 | AC22: 0.7 | AD22: 62 | AE22: 41 | AF22: =7.7+5.2 -> 12.9 | AG22: 13.7 | AH22: 14.6 | AI22: 2.3 | AJ22: =15.4+24.7 -> 40.1 | AK22: 0 | AL22: 158.6 | AM22: 0 | AN22: 0.1 | AO22: 263.3 | AP22: 295.4 | AQ22: 0.7 | AR22: 0 | AS22: 8466.3 | AT22: -10834.1 | AU22: =SUM(B22:AN22) -> 13316.9
A23: TTL_25: Fabricated metal products, except machinery and equipment | B23: 0.1 | C23: 0 | D23: 0 | E23: 3.9 | F23: 4.7 | G23: 0.9 | H23: 1.4 | I23: 3.2 | J23: 2.6 | K23: =4+1.7 -> 5.7 | L23: 0 | M23: 13 | N23: 275.8 | O23: 75.6 | P23: 24.8 | Q23: 81.6 | R23: 58.2 | S23: 32.3 | T23: 10.7 | U23: 10 | V23: =3.1+16.3 -> 19.4 | W23: 6.2 | X23: 2351.6 | Y23: =2.6+5+3.3+30+1.7 -> 42.6 | Z23: 1.6 | AA23: 6.1 | AB23: 6.9 | AC23: 0.6 | AD23: 32.2 | AE23: 31.1 | AF23: =4.4+10.3 -> 14.7 | AG23: 13.6 | AH23: 13.1 | AI23: 1.8 | AJ23: =9.7+14.1 -> 23.8 | AK23: 0 | AL23: 390.5 | AM23: 0 | AN23: 0 | AO23: 631.1 | AP23: 230.1 | AQ23: 0.5 | AR23: 0 | AS23: 335.3 | AT23: -3551.3 | AU23: =SUM(B23:AN23) -> 3560.3
A24: TTL_26: Computer, electronic and optical products | B24: 0.1 | C24: 0 | D24: 0 | E24: 2 | F24: 3.9 | G24: 1.3 | H24: 0.4 | I24: 3.9 | J24: 2.9 | K24: =4.7+2.9 -> 7.6 | L24: 0 | M24: 3.9 | N24: 20 | O24: 4.4 | P24: 384.8 | Q24: 160.8 | R24: 52.9 | S24: 26 | T24: 11.7 | U24: 9.6 | V24: =47.7+63 -> 110.7 | W24: 2.8 | X24: 11206.1 | Y24: =4.2+12.5+10.6+21.6+111.8 -> 160.7 | Z24: 3.3 | AA24: 134.7 | AB24: 1136.7 | AC24: 18.3 | AD24: 167.9 | AE24: 62.2 | AF24: =35.9+44.9 -> 80.8 | AG24: 72.9 | AH24: 101.3 | AI24: 7.3 | AJ24: =99.7+241.4 -> 341.1 | AK24: 0 | AL24: 9641.6 | AM24: 0 | AN24: 0.2 | AO24: 6253.5 | AP24: 29295.1 | AQ24: 28 | AR24: 0.1 | AS24: 1379.5 | AT24: -59402.6 | AU24: =SUM(B24:AN24) -> 23944.8
A25: TTL_27: Electrical equipment | B25: 0 | C25: 0 | D25: 0 | E25: 1.8 | F25: 3.2 | G25: 0.7 | H25: 0.5 | I25: 2.5 | J25: 2.5 | K25: =3.2+1.6 -> 4.8 | L25: 0 | M25: 5.3 | N25: 42.3 | O25: 5.7 | P25: 127.1 | Q25: 580.4 | R25: 102.4 | S25: 48.3 | T25: 14.3 | U25: 13.2 | V25: =75.6+61 -> 136.6 | W25: 6.7 | X25: 8164.4 | Y25: =5.2+11.2+6+17.1+62.9 -> 102.4 | Z25: 2.3 | AA25: 75 | AB25: 538.9 | AC25: 5 | AD25: 75.2 | AE25: 91 | AF25: =22.9+42.5 -> 65.4 | AG25: 37 | AH25: 46.3 | AI25: 3.2 | AJ25: =64.3+163.9 -> 228.2 | AK25: 0 | AL25: 4056.2 | AM25: 0 | AN25: 0.1 | AO25: 2029.2 | AP25: 1058.9 | AQ25: 11.8 | AR25: 2.4 | AS25: 342.1 | AT25: -15322.5 | AU25: =SUM(B25:AN25) -> 14588.9
A26: TTL_28: Machinery and equipment n.e.c. | B26: 0.3 | C26: 0 | D26: 0 | E26: 15.2 | F26: 14.4 | G26: 3.6 | H26: 2.6 | I26: 12.8 | J26: 5.9 | K26: =9.5+5.3 -> 14.8 | L26: 0 | M26: 29.5 | N26: 232.2 | O26: 39.9 | P26: 26.2 | Q26: 71.3 | R26: 237.1 | S26: 115.8 | T26: 39.9 | U26: 22.1 | V26: =12.3+20.7 -> 33 | W26: 3.2 | X26: 724.6 | Y26: =8.3+69.5+100.1+171.4+16.1 -> 365.4 | Z26: 3.7 | AA26: 10 | AB26: 34.5 | AC26: 0.4 | AD26: 251.5 | AE26: 61.5 | AF26: =2.8+8.4 -> 11.2 | AG26: 14 | AH26: 18.9 | AI26: 31.4 | AJ26: =13.1+20.5 -> 33.6 | AK26: 0 | AL26: 465.5 | AM26: 0 | AN26: 0.2 | AO26: 7163.9 | AP26: 1027.4 | AQ26: 0.8 | AR26: 0 | AS26: 912.5 | AT26: -10813.8 | AU26: =SUM(B26:AN26) -> 2946.2
A27: TTL_29: Motor vehicles, trailers and semi-trailers | B27: 0 | C27: 0 | D27: 0 | E27: 0.3 | F27: 0.6 | G27: 0.3 | H27: 0.1 | I27: 0.6 | J27: 0.2 | K27: =0.4+0.2 -> 0.6 | L27: 0 | M27: 1.5 | N27: 6.9 | O27: 1.1 | P27: 2.2 | Q27: 6.3 | R27: 9.4 | S27: 186.9 | T27: 7.3 | U27: 1.3 | V27: =0.9+26.3 -> 27.2 | W27: 0.3 | X27: 468 | Y27: =24.1+24+17.4+5.7+17.8 -> 89 | Z27: 1 | AA27: 13.7 | AB27: 19.5 | AC27: 0.4 | AD27: 36 | AE27: 5.3 | AF27: =2.6+11.3 -> 13.9 | AG27: 40.8 | AH27: 1.6 | AI27: 1 | AJ27: =23.9+32.8 -> 56.7 | AK27: 0 | AL27: 1598 | AM27: 0 | AN27: 0.1 | AO27: 2196.8 | AP27: 701.9 | AQ27: 13.1 | AR27: 4.1 | AS27: 45 | AT27: -4090.8 | AU27: =SUM(B27:AN27) -> 2598.1
A28: TTL_30: Other transport equipment | B28: 0 | C28: 0 | D28: 0 | E28: 0.1 | F28: 0.4 | G28: 0.1 | H28: 0.1 | I28: 0.5 | J28: 0.2 | K28: =0.3+0.2 -> 0.5 | L28: 0 | M28: 1.1 | N28: 5.5 | O28: 0.6 | P28: 1.1 | Q28: 2.2 | R28: 4.7 | S28: 199.1 | T28: 127.4 | U28: 4.6 | V28: =0.3+21.1 -> 21.4 | W28: 0.2 | X28: 475.7 | Y28: =17.1+53.5+83.6+5.8+13.3 -> 173.3 | Z28: 0.8 | AA28: 21.1 | AB28: 10.4 | AC28: 0.3 | AD28: 52.1 | AE28: 4 | AF28: =4.4+8 -> 12.4 | AG28: 91.9 | AH28: 1.1 | AI28: 0.7 | AJ28: =27.3+40.4 -> 67.7 | AK28: 0 | AL28: 916.2 | AM28: 0 | AN28: 0 | AO28: 4989.8 | AP28: 1071.4 | AQ28: 0.3 | AR28: 0 | AS28: 30.6 | AT28: -7770.4 | AU28: =SUM(B28:AN28) -> 2197.5
A29: TTL_31T33: Other manufacturing; repair and installation of machinery and equipment | B29: =0.3+0.1 -> 0.4 | C29: 0 | D29: 0 | E29: 1.2 | F29: 9.5 | G29: 2.4 | H29: 1.4 | I29: 12.9 | J29: 0.3 | K29: =0.8+0.7 -> 1.5 | L29: 0 | M29: 1.6 | N29: 31.2 | O29: 4.8 | P29: 2.7 | Q29: 4.2 | R29: 2.9 | S29: 5.5 | T29: 2.9 | U29: 3.1 | V29: =13.8+16.7 -> 30.5 | W29: 27.5 | X29: 362.7 | Y29: =33.7+59.1+91.5+52.2+10 -> 246.5 | Z29: 9.8 | AA29: 11.1 | AB29: 31.8 | AC29: 1.1 | AD29: 342.2 | AE29: 93.4 | AF29: =5.9+26 -> 31.9 | AG29: 42.3 | AH29: 37.9 | AI29: 17.6 | AJ29: =29.7+22.7 -> 52.4 | AK29: 0 | AL29: 1011.7 | AM29: 0 | AN29: 0.1 | AO29: 353.7 | AP29: 8436.5 | AQ29: 82.2 | AR29: 0 | AS29: 317.4 | AT29: -10821.1 | AU29: =SUM(B29:AN29) -> 2439
A30: TTL_35T39: Electricity, gas, water supply, sewerage, waste and remediation services | B30: =0.8+0.8+0.1 -> 1.7 | C30: 0 | D30: 0 | E30: =0.9+0.1 -> 1 | F30: =101.8+46.8 -> 148.6 | G30: =13.8+8.9 -> 22.7 | H30: =9.4+6.5 -> 15.9 | I30: =75.2+60.3 -> 135.5 | J30: =0.2+0.1 -> 0.3 | K30: =0.7+0.2+0.3+0.1 -> 1.3 | L30: 0 | M30: =0.7+0.3 -> 1 | N30: =7.2+7.3 -> 14.5 | O30: =0.4+0.4 -> 0.8 | P30: =0.2+0.2 -> 0.4 | Q30: =0.5+0.4 -> 0.9 | R30: =0.3+0.3 -> 0.6 | S30: =0.2+0.3 -> 0.5 | T30: =0.1+0.1 -> 0.2 | U30: =0.4+0.1 -> 0.5 | V30: =309.3+91.3+68.3+324.7 -> 793.6 | W30: =41+54.5 -> 95.5 | X30: =392.8+637.4 -> 1030.2 | Y30: =127.5+49.2+72.4+374.1+17.8+64.4+58.5+53.5+159.9+51.6 -> 1028.9 | Z30: =396.2+147.3 -> 543.5 | AA30: =68.5+27 -> 95.5 | AB30: =102.3+95.6 -> 197.9 | AC30: =3.9+5.8 -> 9.7 | AD30: =492.5+512.9 -> 1005.4 | AE30: =1271.9+1084 -> 2355.9 | AF30: =23.1+25.5+32.5+67.5 -> 148.6 | AG30: =154.8+97.2 -> 252 | AH30: =127.8+62.5 -> 190.3 | AI30: =202.9+80.2 -> 283.1 | AJ30: =115.3+120.8+55.8+107.4 -> 399.3 | AK30: 0 | AL30: =1356.2+1142.3 -> 2498.5 | AM30: =2.4+29.9 -> 32.3 | AN30: 0 | AO30: =2.2+108.1 -> 110.3 | AP30: =3.8+8.5 -> 12.3 | AQ30: =0.4+0.2 -> 0.6 | AR30: 0 | AS30: =39.5 -> 39.5 | AT30: =-915.6+-26.6 -> -942.2 | AU30: =SUM(B30:AN30) -> 11306.6
A31: TTL_41T43: Construction | B31: 0.8 | C31: 0 | D31: 0 | E31: 0.5 | F31: 7.4 | G31: 0.6 | H31: 0.4 | I31: 2.3 | J31: 0 | K31: =0.1+0.1 -> 0.2 | L31: 0 | M31: 0.4 | N31: 2.1 | O31: 0.2 | P31: 0.2 | Q31: 0.4 | R31: 0.2 | S31: 0.2 | T31: 0.1 | U31: 0.1 | V31: =5+5.5 -> 10.5 | W31: 6417 | X31: 31.4 | Y31: =22.1+14.8+63.3+24.6+3.4 -> 128.2 | Z31: 10.7 | AA31: 3.2 | AB31: 11.3 | AC31: 0.3 | AD31: 32.5 | AE31: 325.9 | AF31: =2.6+2.8 -> 5.4 | AG31: 352.5 | AH31: 22.6 | AI31: 23 | AJ31: =5.8+8.4 -> 14.2 | AK31: 0 | AL31: 13.2 | AM31: 0 | AN31: 0 | AO31: 20315.1 | AP31: 9.7 | AQ31: 1.6 | AR31: 0 | AS31: 0 | AT31: -55 | AU31: =SUM(B31:AN31) -> 7418
A32: TTL_45T47: Wholesale and retail trade; repair of motor vehicles | B32: =130.8+6.8 -> 137.6 | C32: 0 | D32: 0 | E32: 1505.9 | F32: 2412.7 | G32: 1050.7 | H32: 192.3 | I32: 1563.4 | J32: 172.2 | K32: =544.1+216.9 -> 761 | L32: 0 | M32: 461.7 | N32: 2750.3 | O32: 317 | P32: 521.1 | Q32: 757.5 | R32: 357.4 | S32: 470.6 | T32: 189.1 | U32: 529.4 | V32: =1129.9+873.3 -> 2003.2 | W32: 2384.2 | X32: 31331.2 | Y32: =1651.4+3322.3+3587.6+4514.6+589.3 -> 13665.2 | Z32: 3055.2 | AA32: 800.1 | AB32: 1862.5 | AC32: 71.6 | AD32: 4045.9 | AE32: 1503.6 | AF32: =376.4+934.6 -> 1311 | AG32: 985.7 | AH32: 1037.5 | AI32: 1582.7 | AJ32: =721.8+1395.5 -> 2117.3 | AK32: 0 | AL32: 60617 | AM32: 1.7 | AN32: 0.5 | AO32: 16654.3 | AP32: 5580.1 | AQ32: 108.4 | AR32: 467.9 | AS32: 37109.9 | AT32: -23738.3 | AU32: =SUM(B32:AN32) -> 142526
A33: TTL_49T53: Transportation and storage | B33: =4.8+0.4+1.1+0.1+1+0.1+2.6+0.2+0.3 -> 10.6 | C33: 0 | D33: 0 | E33: =28+6.5+5.1+15.3+0.1 -> 55 | F33: =120.7+89.2+59.6+57.8+33.8 -> 361.1 | G33: =60.7+27.5+20.2+28.1+9.1 -> 145.6 | H33: =7.7+9.6+5.4+3.8+4 -> 30.5 | I33: =11.6+2.3+2.1+6.5 -> 22.5 | J33: =11.6+2.3+2.1+6.5 -> 22.5 | K33: =33.8+12.3+6.6+2.3+6+2.1+18.7+6.6+0.1+0.1 -> 88.6 | L33: 0 | M33: =45.3+8.2+7.4+23.2+0.1 -> 84.2 | N33: =260.9+44.3+37.7+121.5+0.4 -> 464.8 | O33: =30.3+5.3+4.6+14.7+0.1 -> 55 | P33: =41.9+7.6+7+21.6+0.1 -> 78.2 | Q33: =69.7+11.4+10.3+32.4+0.2 -> 124 | R33: =31.7+5.4+4.8+14.9+0.2 -> 57 | S33: =33.3+5.9+5.3+16.4+0.1 -> 61 | T33: =14.4+2.6+2.4+7.3 -> 26.7 | U33: =7.6+1.6+1+3.8 -> 14 | V33: =50.8+52+14.2+24.8+11.6+13.7+26.4+25.6+8.2+18.6 -> 245.9 | W33: =82.1+84.9+61.7+43.9+17.7 -> 290.3 | X33: =1955.1+2124.8+1373.8+966.9+723.7 -> 7144.3 | Y33: =234.5+231.6+186.9+479.2+43.7+85.8+3781.7+1973.5+1578.4+647.4+56+2183+1169+551.6+397.6+44.5+93.7+96.4+244.7+20.4+32.2+417.1+55.5+73.2+736.5 -> 15414.1 | Z33: =188.3+59.4+44.5+90.6+22.1 -> 404.9 | AA33: =41.3+22.6+23.8+20.5+34.4 -> 142.6 | AB33: =135.5+599.9+351.4+69.2+459.7 -> 1615.7 | AC33: =4.5+9+7.1+1.9+7.6 -> 30.1 | AD33: =292.9+1034.6+547.4+102.6+992.6 -> 2970.1 | AE33: =84.7+73.1+46.8+38.1+205.7 -> 448.4 | AF33: =25+57.2+49.8+151.2+36.3+83.7+10.4+24.7+40.6+67 -> 545.9 | AG33: =63.3+40.3+28.1+32.7+60.3 -> 224.7 | AH33: =63.3+35.8+25+32.3+30.2 -> 186.6 | AI33: =70.8+44.9+31.4+34.2+34.3 -> 215.6 | AJ33: =40.9+95.6+30+120.9+20.5+65.2+20+45.1+30.9+76.8 -> 545.9 | AK33: 0 | AL33: =3927.6+1996.7+1249+1753+279.6 -> 9205.9 | AM33: =0.3+0.1+0.1+0.2+7.1 -> 7.8 | AN33: 0.1 | AO33: =1191.2+231+202.6+598.2+308.9 -> 2531.9 | AP33: =-1034+276.2+332.1+654.1+87.6 -> 316 | AQ33: =374.1+68.8+181+6.8+5.4 -> 636.1 | AR33: =4706.2+1724.6+1965.7+14.2+67.5 -> 8478.2 | AS33: =2393.5+2708.3+11912.4+13749.2+1316.9 -> 32080.3 | AT33: =-4656.3+-1227.2+-1495+-1421.5+-1087 -> -9887 | AU33: =SUM(B33:AN33) -> 41340.2
A34: TTL_55T56: Accomodation and food services | B34: 0.2 | C34: 0 | D34: 0 | E34: 0.1 | F34: 9.7 | G34: 2.7 | H34: 1.3 | I34: 5.5 | J34: 0 | K34: 0.1 | L34: 0 | M34: 0.1 | N34: 0.2 | O34: 0 | P34: 0 | Q34: 0.1 | R34: 0.1 | S34: 0 | T34: 0 | U34: 0.1 | V34: =4.9+7.3 -> 12.2 | W34: 11.7 | X34: 129.3 | Y34: =16.5+44.3+11.1+33.1+10.7 -> 115.7 | Z34: 72.5 | AA34: 16.9 | AB34: 32.9 | AC34: 2.5 | AD34: 214.8 | AE34: 96.2 | AF34: =10.3+16.5 -> 26.8 | AG34: 14 | AH34: 33.1 | AI34: 19.9 | AJ34: 00=8.4+24.4 | AK34: 0 | AL34: 4944.9 | AM34: 0 | AN34: 0 | AO34: 25.5 | AP34: 4.6 | AQ34: 1302.9 | AR34: 14832.2 | AS34: 0 | AT34: -1329.3 | AU34: =SUM(B34:AN34) -> 5763.6
A35: TTL_58T60: Publishing, audiovisual and broadcasting activities | B35: =2.1+0.2 -> 2.3 | C35: 0 | D35: 0 | E35: 0.1 | F35: 56.1 | G35: 15.6 | H35: 1.4 | I35: 21.5 | J35: 0.2 | K35: =0.6+0.3 -> 0.9 | L35: 0 | M35: 0.8 | N35: 2.2 | O35: 0.2 | P35: 1 | Q35: 1.6 | R35: 0.7 | S35: 0.4 | T35: 0.1 | U35: 0.3 | V35: =12.2+7.8 -> 20 | W35: 78 | X35: 430.3 | Y35: =44.5+66.3+69.3+70.6+19.6 -> 270.3 | Z35: 28.3 | AA35: 431.7 | AB35: 136.5 | AC35: 4.6 | AD35: 460.8 | AE35: 258.3 | AF35: =62.1+21.2 -> 83.3 | AG35: 22.2 | AH35: 37.5 | AI35: 111 | AJ35: =74.7+36.6 -> 111.3 | AK35: 0 | AL35: 1190.7 | AM35: 4.1 | AN35: 0.1 | AO35: 194.9 | AP35: 12.9 | AQ35: 21.7 | AR35: 114.3 | AS35: 3613.2 | AT35: -1908.6 | AU35: =SUM(B35:AN35) -> 3784.4
A36: TTL_61: Telecommunications | B36: =0.7+0.1 -> 0.8 | C36: 0 | D36: 0 | E36: 0.1 | F36: 68.7 | G36: 20.4 | H36: 9.9 | I36: 40.1 | J36: 0 | K36: =0.2+0.2 -> 0.4 | L36: 0 | M36: 0.2 | N36: 1.4 | O36: 0.2 | P36: 0.4 | Q36: 0.5 | R36: 0.4 | S36: 0.2 | T36: 0.1 | U36: 0.1 | V36: =16.5+38.6 -> 55.1 | W36: 62.8 | X36: 1284.1 | Y36: =84.6+1281+185.3+159.5+60.6 -> 1771 | Z36: 95.1 | AA36: 134.6 | AB36: 1340.8 | AC36: 31.5 | AD36: 2217.2 | AE36: 567.7 | AF36: =104.5+145.6 -> 250.1 | AG36: 119.1 | AH36: 76.9 | AI36: 111 | AJ36: =87.3+149.7 -> 237 | AK36: 0 | AL36: 1842.2 | AM36: 7.9 | AN36: 0 | AO36: 306.2 | AP36: 161.7 | AQ36: 84.7 | AR36: 1251 | AS36: 4880.9 | AT36: -352.5 | AU36: =SUM(B36:AN36) -> 10348
A37: TTL_62T63: IT and other information services | B37: 0.4 | C37: 0 | D37: 0 | E37: 0.1 | F37: 35.2 | G37: 12.2 | H37: 4.7 | I37: 26.1 | J37: 0 | K37: =0.3+0.2 -> 0.5 | L37: 0 | M37: 0.2 | N37: 2.6 | O37: 0.2 | P37: 0.5 | Q37: 0.7 | R37: 0.3 | S37: 0.4 | T37: 0.2 | U37: 0.1 | V37: =8.3+10.2 -> 18.5 | W37: 24 | X37: 567.6 | Y37: =43.7+37.6+70+84.4+37.7 -> 273.4 | Z37: 34.8 | AA37: 42.4 | AB37: 217.3 | AC37: 25.1 | AD37: 966.5 | AE37: 233.6 | AF37: =24.4+17.6 -> 42 | AG37: 79.8 | AH37: 42 | AI37: 35.1 | AJ37: =23.9+34.1 -> 58 | AK37: 0 | AL37: 98.2 | AM37: 0 | AN37: 0.1 | AO37: 408.3 | AP37: 70.1 | AQ37: 1.9 | AR37: 15.6 | AS37: 2128.6 | AT37: -921.1 | AU37: =SUM(B37:AN37) -> 2842.8
A38: TTL_64T66: Financial and insurance activities | B38: =1.1+0.1 -> 1.2 | C38: 0 | D38: 0 | E38: 0.1 | F38: 421.4 | G38: 108.9 | H38: 45.3 | I38: 350.3 | J38: 0.4 | K38: =1.1+0.6 -> 1.7 | L38: 0 | M38: 1.3 | N38: 12 | O38: 1.2 | P38: 1 | Q38: 2 | R38: 1.2 | S38: 0.8 | T38: 0.3 | U38: 0.6 | V38: =286.1+238.2 -> 524.3 | W38: 253.9 | X38: 6839.4 | Y38: =629.2+920.9+301+1126+208.2 -> 3185.3 | Z38: 434.6 | AA38: 258.3 | AB38: 654.5 | AC38: 66.3 | AD38: 25577.6 | AE38: 12634.4 | AF38: =355.7+731.7 -> 1087.4 | AG38: 176.8 | AH38: 466.3 | AI38: 330.2 | AJ38: =328.9+836.1 -> 1165 | AK38: 0 | AL38: 22484.8 | AM38: 0 | AN38: 371.8 | AO38: 497.7 | AP38: 4729.6 | AQ38: 70.5 | AR38: 1071.6 | AS38: 41690.4 | AT38: -2972.6 | AU38: =SUM(B38:AN38) -> 77460.6
A39: TTL_68: Real estate activities | B39: =1.2+0.1 -> 1.3 | C39: 0 | D39: 0 | E39: 0.1 | F39: 90.6 | G39: 44 | H39: 13.3 | I39: 76 | J39: 0.1 | K39: =0.2+0.1 -> 0.3 | L39: 0 | M39: 0.6 | N39: 4.2 | O39: 0.6 | P39: 0.7 | Q39: 1.2 | R39: 0.8 | S39: 0.6 | T39: 0.2 | U39: 0.4 | V39: =95.1+305.7 -> 400.8 | W39: 185.2 | X39: 6898.8 | Y39: =278.5+170+219.5+2384+104.5 -> 3156.5 | Z39: 1391.8 | AA39: 403 | AB39: 392.3 | AC39: 58.3 | AD39: 4381.8 | AE39: 4338.3 | AF39: =281.5+509.8 -> 791.3 | AG39: 77.7 | AH39: 303.2 | AI39: 524.7 | AJ39: =616.5+1577.2 -> 2193.7 | AK39: 0 | AL39: 45769.3 | AM39: 0 | AN39: 0.1 | AO39: 6134.7 | AP39: 4.7 | AQ39: 229.3 | AR39: 3510.3 | AS39: 41.9 | AT39: -395.1 | AU39: =SUM(B39:AN39) -> 71501.8
A40: TTL_69T82: Other business sector services | B40: =3.1+0.3+1.1+0.1 -> 4.6 | C40: 0 | D40: 0 | E40: =4.6+1.4 -> 6 | F40: =207.4+63.2 -> 270.6 | G40: =58.1+17.2 -> 75.3 | H40: =36.2+13.2 -> 49.4 | I40: =183.2+59.5 -> 242.7 | J40: =0.2+0.1 -> 0.3 | K40: =1+1.2+0.3+0.2 -> 2.7 | L40: 0 | M40: =0.6+0.2 -> 0.8 | N40: =4.4+1.9 -> 6.3 | O40: =0.5+0.2 -> 0.7 | P40: =1.4+0.3 -> 1.7 | Q40: =2.7+0.6 -> 3.3 | R40: =1.7+0.4 -> 2.1 | S40: =1.8+0.4 -> 2.2 | T40: =0.6+0.1 -> 0.7 | U40: =1.1+0.8 -> 1.9 | V40: =45.7+82.8+14.6+37.6 -> 180.7 | W40: =238.6+62 -> 300.6 | X40: =3920.9+1506.9 -> 5427.8 | Y40: =220.2+208.5+279.9+399.6+112.8+167.2+212+252.5+245.6+113.4 -> 2211.7 | Z40: =210.5+86.1 -> 296.6 | AA40: =169.2+122.1 -> 291.3 | AB40: =599.6+346.7 -> 946.3 | AC40: =46.3+16.6 -> 62.9 | AD40: =3109.4+1132.7 -> 4242.1 | AE40: =1710+694.3 -> 2404.3 | AF40: =488.7+96.2 -> 584.9 | AG40: =409.8+124.8 -> 534.6 | AH40: =209.1+95.6 -> 304.7 | AI40: =301.4+152.1 -> 453.5 | AJ40: =167.1+235+87.6+88 -> 577.7 | AK40: 0 | AL40: =525.5+187.8 -> 713.3 | AM40: =7.8 -> 7.8 | AN40: =348.2+0.1 -> 348.3 | AO40: =2565+91 -> 2656 | AP40: =97.9+59.5 -> 157.4 | AQ40: =32.9+73 -> 105.9 | AR40: =541.9+1088.8 -> 1630.7 | AS40: =2254.3+1482.5 -> 3736.8 | AT40: =-967+-91.6 -> -1058.6 | AU40: =SUM(B40:AN40) -> 20560.4
A41: TTL_84: Public administration and defence; compulsory social security | B41: 0.1 | C41: 0 | D41: 0 | E41: 0.1 | F41: 14 | G41: 3.3 | H41: 2 | I41: 7.1 | J41: 0 | K41: =0.2+0.1 -> 0.3 | L41: 0 | M41: 0.1 | N41: 2.1 | O41: 0.2 | P41: 0.2 | Q41: 0.4 | R41: 0.2 | S41: 0.2 | T41: 0.1 | U41: 0.1 | V41: =6.2+13.4 -> 19.6 | W41: 67.7 | X41: 297.9 | Y41: =25.8+40.5+196.3+101.2+14.3 -> 378.1 | Z41: 42.9 | AA41: 17.6 | AB41: 38.9 | AC41: 2.7 | AD41: 310.4 | AE41: 91 | AF41: =19.3+28.4 -> 47.7 | AG41: 309.8 | AH41: 31.6 | AI41: 25.1 | AJ41: =23.3+40.8 -> 64.1 | AK41: 0 | AL41: 2023.7 | AM41: 0 | AN41: 21947.8 | AO41: 47.4 | AP41: 12 | AQ41: 4.7 | AR41: 0 | AS41: 0 | AT41: -91.6 | AU41: =SUM(B41:AN41) -> 25747.1
A42: TTL_85: Education | B42: 0.5 | C42: 0 | D42: 0 | E42: 0 | F42: 38.1 | G42: 9.3 | H42: 6.1 | I42: 34 | J42: 0 | K42: =0.1+0.1 -> 0.2 | L42: 0 | M42: 0.2 | N42: 1.2 | O42: 0.1 | P42: 0.1 | Q42: 0.2 | R42: 0.2 | S42: 0.2 | T42: 0.1 | U42: 0.1 | V42: =12.8+20.4 -> 33.2 | W42: 45.6 | X42: 627.7 | Y42: =57.7+62.4+67.9+123.9+31.9 -> 343.8 | Z42: 46.8 | AA42: 30.5 | AB42: 128.9 | AC42: 13.9 | AD42: 711.7 | AE42: 301.3 | AF42: =57.6+63.5 -> 121.1 | AG42: 163.3 | AH42: 469.4 | AI42: 89.2 | AJ42: =34.4+87.7 -> 122.1 | AK42: 0 | AL42: 2924.9 | AM42: 9128.7 | AN42: 2620.8 | AO42: 233 | AP42: 5.3 | AQ42: 135.5 | AR42: 1707.7 | AS42: 0 | AT42: -157 | AU42: =SUM(B42:AN42) -> 18013.5
A43: TTL_86T88: Human health and social work | B43: 0 | C43: 0 | D43: 0 | E43: 0.1 | F43: 8.4 | G43: 4.2 | H43: 1 | I43: 4.1 | J43: 0.1 | K43: =0.2+0.1 -> 0.3 | L43: 0 | M43: 0.1 | N43: 0.8 | O43: 0.1 | P43: 0.2 | Q43: 0.3 | R43: 0.1 | S43: 0.1 | T43: 0 | U43: 0 | V43: =4.1+5.7 -> 9.8 | W43: 10.2 | X43: 141.1 | Y43: =17+48.8+8+41.2+8.8 -> 123.8 | Z43: 17.1 | AA43: 5 | AB43: 17.1 | AC43: 1.2 | AD43: 218.2 | AE43: 86.8 | AF43: =11.2+18.8 -> 30 | AG43: 9 | AH43: 35.4 | AI43: 258.2 | AJ43: =15.8+25.5 -> 41.3 | AK43: 0 | AL43: 6137.2 | AM43: 1571 | AN43: 10648 | AO43: 29.8 | AP43: 17.1 | AQ43: 58.1 | AR43: 843.7 | AS43: 0 | AT43: -117.5 | AU43: =SUM(B43:AN43) -> 19380.3
A44: TTL_90T96: Arts, entertainment, recreation and other service activities | B44: =0.5+0.1+3.5+0.5 -> 4.6 | C44: 0 | D44: 0 | E44: =0.2 -> 0.2 | F44: =18.8+146.4 -> 165.2 | G44: =3+53.2 -> 56.2 | H44: =1.2+16.1 -> 17.3 | I44: =12.6+96 -> 108.6 | J44: =1 -> 1 | K44: =0.1+0.1+3+2.3 -> 5.5 | L44: 0 | M44: =2.6 -> 2.6 | N44: =0.4+19.2 -> 19.6 | O44: =2.5 -> 2.5 | P44: =0.1+4 -> 4.1 | Q44: =0.1+6.7 -> 6.8 | R44: =0.1+3.8 -> 3.9 | S44: =0.1+9.9 -> 10 | T44: 3.4 | U44: 0.5 | V44: =7.3+11.1+65.7+72.1 -> 156.2 | W44: =14.6+121.8 -> 136.4 | X44: =250.6+1184 -> 1434.6 | Y44: =24.2502+42.6+58.3+28.2+126.7+137.8+220.3+176.9+78 -> 893.0502 | Z44: =22.7+208.2 -> 230.9 | AA44: =169.2+122.1 -> 291.3 | AB44: =73.2+175.1 -> 248.3 | AC44: =3.3+14 -> 17.3 | AD44: =499.7+1244 -> 1743.7 | AE44: =360.9+773.1 -> 1134 | AF44: =43.7+57.6+90.1+133.1 -> 324.5 | AG44: =32.5+87.7 -> 120.2 | AH44: =45.2+80.8 -> 126 | AI44: =36.9+163.7 -> 200.6 | AJ44: =766.6+114.1+163.2+499.5 -> 1543.4 | AK44: 0 | AL44: =1641.3+4507.2 -> 6148.5 | AM44: =62.3+346 -> 408.3 | AN44: 0 | AO44: =167+611.6 -> 778.6 | AP44: =-0.9+19.3 -> 18.4 | AQ44: =132.4+78.3 -> 210.7 | AR44: =2089.6+1116.4 -> 3206 | AS44: 318 | AT44: =-337.8+-150.2 -> -488 | AU44: =SUM(B44:AN44) -> 15569.25
A45: TTL_97T98: Private households with employed persons | B45: 0 | C45: 0 | D45: 0 | E45: 0 | F45: 0 | G45: 0 | H45: 0 | I45: 0 | J45: 0 | K45: 0 | L45: 0 | M45: 0 | N45: 0 | O45: 0 | P45: 0 | Q45: 0 | R45: 0 | S45: 0 | T45: 0 | U45: 0 | V45: 0 | W45: 0 | X45: 0 | Y45: 0 | Z45: 0 | AA45: 0 | AB45: 0 | AC45: 0 | AD45: 0 | AE45: 0 | AF45: 0 | AG45: 0 | AH45: 0 | AI45: 0 | AJ45: 0 | AK45: 0 | AL45: 4665 | AM45: 0 | AN45: 0 | AO45: 0 | AP45: 0 | AQ45: 0 | AR45: 0 | AS45: 0 | AT45: 0 | AU45: =SUM(B45:AN45) -> 4665
A46: TXS_IMP_FNL: Taxes less subsidies on intermediate and final products (paid in foreign countries) | B46: 0 | C46: 0 | D46: 0 | E46: 0 | F46: 0 | G46: 0 | H46: 0 | I46: 0 | J46: 0 | K46: 0 | L46: 0 | M46: 0 | N46: 0 | O46: 0 | P46: 0 | Q46: 0 | R46: 0 | S46: 0 | T46: 0 | U46: 0 | V46: 0 | W46: 0 | X46: 0 | Y46: =-0.1 -> -0.1 | Z46: -0.1 | AA46: 0 | AB46: 0 | AC46: 0 | AD46: 0 | AE46: 0 | AF46: 0 | AG46: 0 | AH46: 0 | AI46: 0 | AJ46: 0 | AK46: 0 | AL46: 0 | AM46: 0 | AN46: 0 | AO46: 0 | AP46: 0 | AQ46: 57.3 | AR46: 0 | AS46: 0 | AT46: -57.1 | AU46: =SUM(B46:AN46) -> -0.2
A47: TXS_INT_FNL: Taxes less subsidies on intermediate and final products (paid in domestic agencies, includes duty on imported products) | B47: =2.8+0.2 -> 3 | C47: 0 | D47: 0 | E47: 35.8 | F47: 64.3 | G47: 31.4 | H47: 7 | I47: 47.9 | J47: 17.5 | K47: =30.7+8.5 -> 39.2 | L47: 0 | M47: 20 | N47: 162.7 | O47: 14.4 | P47: 34.1 | Q47: 27.1 | R47: 12.1 | S47: 26.6 | T47: 4.8 | U47: 13.7 | V47: =55.6+61.1 -> 116.7 | W47: 231.5 | X47: 2799.5 | Y47: =104.9+350.7+239.3+392.1+67.7 -> 1154.7 | Z47: 117.8 | AA47: 84.1 | AB47: 263 | AC47: 10.4 | AD47: 1344.4 | AE47: 635.3 | AF47: =51.8+99.6 -> 151.4 | AG47: 123.1 | AH47: 94.8 | AI47: 77.1 | AJ47: =113.3+162.8 -> 276.1 | AK47: 0 | AL47: 3739.1 | AM47: 29.6 | AN47: -29.4 | AO47: 1750.4 | AP47: 0 | AQ47: 0 | AR47: -42.9 | AS47: 0 | AT47: 0 | AU47: =SUM(B47:AN47) -> 11780.8
A48: TTL_INT_FNL: Total intermediate consumption at purchasers’ prices | B48: =269.5+34.7 -> 304.2 | C48: 0 | D48: 0 | E48: 8028.3 | F48: 6194.7 | G48: 2727.5 | H48: 532.4 | I48: 4555.6 | J48: 377.9 | K48: =1159.8+452 -> 1611.8 | L48: 0 | M48: 1228.3 | N48: 11480.1 | O48: 1130.6 | P48: 1446.5 | Q48: 2665.6 | R48: 1189.9 | S48: 1424.9 | T48: 499 | U48: 715.8 | V48: =2971.3+3200.1 -> 6171.4 | W48: 12195.5 | X48: 104745.4 | Y48: =5658.2+16315.8+12040.1+17264.4+4079.3 -> 55357.8 | Z48: 8861.7 | AA48: 3649.8 | AB48: 10369.2 | AC48: 464.7 | AD48: 53727.3 | AE48: 28542.2 | AF48: =2707.8+4500.8 -> 7208.6 | AG48: 4524.5 | AH48: 4403.8 | AI48: 5448 | AJ48: =4177.3+7398.2 -> 11575.5 | AK48: 0 | AL48: 230751.9 | AM48: 11199.9 | AN48: 35909.8 | AO48: 77220.9 | AP48: 61910.2 | AQ48: 3576.1 | AR48: 37530.2 | AS48: 139110.7 | AT48: -235559.1 | AU48: =SUM(B48:AN48) -> 641220.1
A49: VALU: Value added at basic prices | B49: =179.8+30.3 -> 210.1 | C49: 0 | D49: 0 | E49: 76.3 | F49: 2573.5 | G49: 265.2 | H49: 213.6 | I49: 133.1 | J49: 35.3 | K49: =38+22.9 -> 60.9 | L49: 0 | M49: 50 | N49: 28.2 | O49: 75.6 | P49: 51.7 | Q49: 45.3 | R49: 47.2 | S49: 43.4 | T49: 20.4 | U49: 92 | V49: =2341.9+2023.8 -> 4365.7 | W49: 15493.8 | X49: 73962.9 | Y49: =6622.9+2366.9+9657.3+606.9+1122.7 -> 20376.7 | Z49: 11770.9 | AA49: 2182.6 | AB49: 6311.7 | AC49: 4091.6 | AD49: 68821.6 | AE49: 52485.6 | AF49: =16474.7+3558.1 -> 20032.8 | AG49: 21195.1 | AH49: 15533.9 | AI49: 14763.2 | AJ49: =2644.6+5442.6 -> 8087.2 | AK49: 4665 | AL49: 0 | AM49: 0 | AN49: 0 | AO49: 0 | AP49: 0 | AQ49: 0 | AR49: 0 | AS49: 0 | AT49: 0 | AU49: =SUM(B49:AN49) -> 348162.1
A50: OUTPUT: Output at basic prices | B50: =449.3+65 -> 514.3 | C50: 0 | D50: 0 | E50: 8104.5 | F50: 8768.1 | G50: 2992.7 | H50: 746 | I50: 4688.8 | J50: 413.2 | K50: =1197+474.8 -> 1671.8 | L50: 0 | M50: 1278.3 | N50: 11508.3 | O50: 1206.2 | P50: 1498.2 | Q50: 2710.9 | R50: 1237.1 | S50: 1468.2 | T50: 519.5 | U50: 807.8 | V50: =5313.3+5223.9 -> 10537.2 | W50: 27689.4 | X50: 178708.3 | Y50: =12281.1+18682.6+21697.4+17871.3+5202 -> 75734.4 | Z50: 20632.5 | AA50: 5832.4 | AB50: 16680.9 | AC50: 4556.3 | AD50: 122548.9 | AE50: 81027.8 | AF50: =19182.5+8058.9 -> 27241.4 | AG50: 25719.6 | AH50: 19937.7 | AI50: 20211.2 | AJ50: =6821.9+12840.8 -> 19662.7 | AK50: 4665 | AL50: 0 | AM50: 0 | AN50: 0 | AO50: 0 | AP50: 0 | AQ50: 0 | AR50: 0 | AS50: 0 | AT50: 0 | AU50: =SUM(B50:AN50) -> 711519.6
A51: Data extracted on 4 Sept 2023 10:13 UTC (GMT) from OECD.Stat | AU51: =SUM(B51:AN51) -> 0

Sheet OECD Data IO Table - Total (USD
D1: =DotStatQuery(#REF!) -> #NAME?
D2: To Sector | E2: =INDEX('OECD Crosswalk'!$B$2:$B$90,MATCH('OECD Data IO Table - Total (USD'!E8,'OECD Crosswalk'!$A$2:$A$90,0),1) -> nonenergy industries | F2: =INDEX('OECD Crosswalk'!$B$2:$B$90,MATCH('OECD Data IO Table - Total (USD'!F8,'OECD Crosswalk'!$A$2:$A$90,0),1) -> natural gas and petroleum suppliers | G2: =INDEX('OECD Crosswalk'!$B$2:$B$90,MATCH('OECD Data IO Table - Total (USD'!G8,'OECD Crosswalk'!$A$2:$A$90,0),1) -> nonenergy industries | H2: =INDEX('OECD Crosswalk'!$B$2:$B$90,MATCH('OECD Data IO Table - Total (USD'!H8,'OECD Crosswalk'!$A$2:$A$90,0),1) -> nonenergy industries | I2: =INDEX('OECD Crosswalk'!$B$2:$B$90,MATCH('OECD Data IO Table - Total (USD'!I8,'OECD Crosswalk'!$A$2:$A$90,0),1) -> nonenergy industries | J2: =INDEX('OECD Crosswalk'!$B$2:$B$90,MATCH('OECD Data IO Table - Total (USD'!J8,'OECD Crosswalk'!$A$2:$A$90,0),1) -> nonenergy industries | K2: =INDEX('OECD Crosswalk'!$B$2:$B$90,MATCH('OECD Data IO Table - Total (USD'!K8,'OECD Crosswalk'!$A$2:$A$90,0),1) -> nonenergy industries | L2: =INDEX('OECD Crosswalk'!$B$2:$B$90,MATCH('OECD Data IO Table - Total (USD'!L8,'OECD Crosswalk'!$A$2:$A$90,0),1) -> nonenergy industries | ... AW2: =INDEX('OECD Crosswalk'!$B$2:$B$90,MATCH('OECD Data IO Table - Total (USD'!AW8,'OECD Crosswalk'!$A$2:$A$90,0),1) -> imports
D3: From Sector | E3: =INDEX('OECD Crosswalk'!$C$2:$C$90,MATCH('OECD Data IO Table - Total (USD'!E8,'OECD Crosswalk'!$A$2:$A$90,0),1) -> agriculture | F3: =INDEX('OECD Crosswalk'!$C$2:$C$90,MATCH('OECD Data IO Table - Total (USD'!F8,'OECD Crosswalk'!$A$2:$A$90,0),1) -> other industries | G3: =INDEX('OECD Crosswalk'!$C$2:$C$90,MATCH('OECD Data IO Table - Total (USD'!G8,'OECD Crosswalk'!$A$2:$A$90,0),1) -> other industries | H3: =INDEX('OECD Crosswalk'!$C$2:$C$90,MATCH('OECD Data IO Table - Total (USD'!H8,'OECD Crosswalk'!$A$2:$A$90,0),1) -> other industries | I3: =INDEX('OECD Crosswalk'!$C$2:$C$90,MATCH('OECD Data IO Table - Total (USD'!I8,'OECD Crosswalk'!$A$2:$A$90,0),1) -> other industries | J3: =INDEX('OECD Crosswalk'!$C$2:$C$90,MATCH('OECD Data IO Table - Total (USD'!J8,'OECD Crosswalk'!$A$2:$A$90,0),1) -> other industries | K3: =INDEX('OECD Crosswalk'!$C$2:$C$90,MATCH('OECD Data IO Table - Total (USD'!K8,'OECD Crosswalk'!$A$2:$A$90,0),1) -> other industries | L3: =INDEX('OECD Crosswalk'!$C$2:$C$90,MATCH('OECD Data IO Table - Total (USD'!L8,'OECD Crosswalk'!$A$2:$A$90,0),1) -> other industries | ... AW3: =INDEX('OECD Crosswalk'!$C$2:$C$90,MATCH('OECD Data IO Table - Total (USD'!AW8,'OECD Crosswalk'!$A$2:$A$90,0),1) -> 0
D4: Variable | E4: TTL: Total
D5: Country | E5: HKG: Hong Kong, China
D6: Time | E6: 2021
D7: Unit | E7: US Dollar, Millions
D8: To: (sector in column) | E8: D01T03: Agriculture, forestry and fishing | F8: D05T06: Mining and extraction of energy producing products | G8: D07T08: Mining and quarrying of non-energy producing products | H8: D09: Mining support service activities | I8: D10T12: Food products, beverages and tobacco | J8: D13T15: Textiles, wearing apparel, leather and related products | K8: D16: Wood and products of wood and cork | L8: D17T18: Paper products and printing | M8: D19: Coke and refined petroleum products | N8: D20T21: Chemicals and pharmaceutical products | O8: D22: Rubber and plastic products | P8: D23: Other non-metallic mineral products | Q8: D24: Basic metals | R8: D25: Fabricated metal products | S8: D26: Computer, electronic and optical products | T8: D27: Electrical equipment | U8: D28: Machinery and equipment, nec | V8: D29: Motor vehicles, trailers and semi-trailers | W8: D30: Other transport equipment | X8: D31T33: Other manufacturing; repair and installation of machinery and equipment | Y8: D35T39: Electricity, gas, water supply, sewerage, waste and remediation services | Z8: D41T43: Construction | AA8: D45T47: Wholesale and retail trade; repair of motor vehicles | AB8: D49T53: Transportation and storage | AC8: D55T56: Accomodation and food services | AD8: D58T60: Publishing, audiovisual and broadcasting activities | AE8: D61: Telecommunications | AF8: D62T63: IT and other information services | AG8: D64T66: Financial and insurance activities | AH8: D68: Real estate activities | AI8: D69T82: Other business sector services | AJ8: D84: Public admin. and defence; compulsory social security | AK8: D85: Education | AL8: D86T88: Human health and social work | AM8: D90T96: Arts, entertainment, recreation and other service activities | AN8: D97T98: Private households with employed persons | AO8: HFCE: Final consumption expenditure of households | AP8: NPISH: Final consumption expenditure of non-profit institutions serving households | AQ8: GGFC: Final consumption expenditure of general government | AR8: GFCF: Gross Fixed Capital Formation | AS8: INVNT: Changes in inventories | AT8: CONS_ABR: Direct purchases abroad by residents (imports) | AU8: CONS_NONRES: Direct purchases by non-residents (exports) | AV8: EXPO: Exports (cross border) | AW8: IMPO: Imports (cross border) | AX8: Totals
A9: From Sector | B9: To Sector | D9: From: (sector in row)
A10: =INDEX('OECD Crosswalk'!$C$2:$C$90,MATCH('OECD Data IO Table - Total (USD'!D10,'OECD Crosswalk'!$A$2:$A$90,0),1) -> agriculture | B10: =INDEX('OECD Crosswalk'!$B$2:$B$90,MATCH('OECD Data IO Table - Total (USD'!D10,'OECD Crosswalk'!$A$2:$A$90,0),1) -> nonenergy industries | D10: TTL_01T03: Agriculture, forestry and fishing | E10: =0.9+0.1+0.1 -> 1.1 | F10: 0 | G10: 0 | H10: 0.0012333592 | I10: =154.9+4.4 -> 159.3 | J10: =1.6+0.2 -> 1.8 | K10: =0.5+0.1 -> 0.6 | L10: =2.5+0.6 -> 3.1 | M10: 0 | N10: =0.3+0.2 -> 0.5 | O10: 0 | P10: 0.1 | Q10: 0.4 | R10: 0 | S10: 0.1 | T10: 0.1 | U10: 0.1 | V10: 0.1 | W10: 1.6348852e-05 | X10: 0 | Y10: =43.7+16.7+5.3+2.2 -> 67.9 | Z10: =7.9+1.3 -> 9.2 | AA10: =44.4+3.5 -> 47.9 | AB10: =34.6+141.9+255+6.8+4+4.4+37.6+62.6+1.3+1.1 -> 549.3 | AC10: =453.1+91.4 -> 544.5 | AD10: =3.6+1 -> 4.6 | AE10: =8.3+1.8 -> 10.1 | AF10: 0.2 | AG10: =8.6+1.5 -> 10.1 | AH10: =2.9+0.4 -> 3.3 | AI10: =2+5.2+0.3+0.6 -> 8.1 | AJ10: =7.1+0.7 -> 7.8 | AK10: =11.8+1.3 -> 13.1 | AL10: =19.4+1.6 -> 21 | AM10: =13+2.4+19.7+3.5 -> 38.6 | AN10: 0 | AO10: =4367.1+711.7 -> 5078.8 | AP10: 0.1 | AQ10: 0 | AR10: =3.2+0.3 -> 3.5 | AS10: =10.3+0.3 -> 10.6 | AT10: =33.6+2.6 -> 36.2 | AU10: =1.1+2.5 -> 3.6 | AV10: =4.5+7.5 -> 12 | AW10: =-5242.7+-891.3 -> -6134 | AX10: =SUM(E10:AQ10) -> 6581.9012
A11: =INDEX('OECD Crosswalk'!$C$2:$C$90,MATCH('OECD Data IO Table - Total (USD'!D11,'OECD Crosswalk'!$A$2:$A$90,0),1) -> other industries | B11: =INDEX('OECD Crosswalk'!$B$2:$B$90,MATCH('OECD Data IO Table - Total (USD'!D11,'OECD Crosswalk'!$A$2:$A$90,0),1) -> natural gas and petroleum suppliers | D11: TTL_05T06: Mining and extraction of energy producing products | E11: =15.7+1.5 -> 17.2 | F11: 0 | G11: 0 | H11: 169.3 | I11: 167.3 | J11: 136.5 | K11: 8.7 | L11: 91.6 | M11: 18.1 | N11: =0.6+0.1 -> 0.7 | O11: 0 | P11: 1.4 | Q11: 43.7 | R11: 2.2 | S11: 4.1 | T11: 11.9 | U11: 8.1 | V11: 2.6 | W11: 1.7 | X11: 9.7 | Y11: =54.1+30.2 -> 84.3 | Z11: 3.8 | AA11: 22.3 | AB11: =129.4+1.9+39.4+1601.3+9.5 -> 1781.5 | AC11: 6 | AD11: 3.2 | AE11: 12.7 | AF11: 4.1 | AG11: 44.4 | AH11: 11.6 | AI11: =27.1+84.5 -> 111.6 | AJ11: 7.7 | AK11: 30.2 | AL11: 16.2 | AM11: =14.1+22.3 -> 36.4 | AN11: 0 | AO11: 37.1 | AP11: 0.6 | AQ11: 0 | AR11: 3.7 | AS11: 31.4 | AT11: 0.4 | AU11: 0 | AV11: 0 | AW11: -2952.4 | AX11: =SUM(E11:AQ11) -> 2908.5
A12: =INDEX('OECD Crosswalk'!$C$2:$C$90,MATCH('OECD Data IO Table - Total (USD'!D12,'OECD Crosswalk'!$A$2:$A$90,0),1) -> other industries | B12: =INDEX('OECD Crosswalk'!$B$2:$B$90,MATCH('OECD Data IO Table - Total (USD'!D12,'OECD Crosswalk'!$A$2:$A$90,0),1) -> nonenergy industries | D12: TTL_07T08: Mining and quarrying of non-energy producing products | E12: =3.1+0.4 -> 3.5 | F12: 0 | G12: 0 | H12: 38.7 | I12: 20.2 | J12: 17.4 | K12: 1.3 | L12: 9.9 | M12: 0.5 | N12: =0.2+0.1 -> 0.3 | O12: 0 | P12: 0.9 | Q12: 10.1 | R12: 0.6 | S12: 0.7 | T12: 2.4 | U12: 1.6 | V12: 0.4 | W12: 0.3 | X12: 1.7 | Y12: =4.2+4 -> 8.2 | Z12: 2.1 | AA12: 3.7 | AB12: =18.8+0.2+4.8+288.2+0.9 -> 312.9 | AC12: 0.8 | AD12: 800.1 | AE12: 1.6 | AF12: 0.5 | AG12: 4.7 | AH12: 1.8 | AI12: =5.7+10.8 -> 16.5 | AJ12: 1.3 | AK12: 3.1 | AL12: 1.7 | AM12: =1.9+3 -> 4.9 | AN12: 0 | AO12: 6.1 | AP12: 0 | AQ12: 0 | AR12: 1 | AS12: 1.1 | AT12: 0.4 | AU12: 0 | AV12: 0 | AW12: -481.4 | AX12: =SUM(E12:AQ12) -> 1280.5
A13: =INDEX('OECD Crosswalk'!$C$2:$C$90,MATCH('OECD Data IO Table - Total (USD'!D13,'OECD Crosswalk'!$A$2:$A$90,0),1) -> other industries | B13: =INDEX('OECD Crosswalk'!$B$2:$B$90,MATCH('OECD Data IO Table - Total (USD'!D13,'OECD Crosswalk'!$A$2:$A$90,0),1) -> nonenergy industries | D13: TTL_09: Mining support service activities | E13: =61.5+20.9 -> 82.4 | F13: 0 | G13: 0 | H13: 6150 | I13: 152.1 | J13: 30.3 | K13: 37.1 | L13: 141.9 | M13: 2.4 | N13: =0.5 -> 0.5 | O13: 0 | P13: 1.1 | Q13: 131.8 | R13: 6.1 | S13: 2 | T13: 5.3 | U13: 22.1 | V13: 2 | W13: 1.1 | X13: 0.2 | Y13: =52.3+30.2 -> 82.5 | Z13: 10.6 | AA13: 26.6 | AB13: =317.8+2.7+174+48.2+55.1 -> 597.8 | AC13: 3.5 | AD13: 3.2 | AE13: 0 | AF13: 1.6 | AG13: 190.1 | AH13: 50.8 | AI13: =120.1+41.2 -> 161.3 | AJ13: 20.2 | AK13: 83.8 | AL13: 0.6 | AM13: =6.4+18 -> 24.4 | AN13: 0 | AO13: 6.2 | AP13: 0 | AQ13: 0 | AR13: 1.2 | AS13: 1.1 | AT13: 0.1 | AU13: 0 | AV13: 73.2 | AW13: -14.6 | AX13: =SUM(E13:AQ13) -> 8031.6
A14: =INDEX('OECD Crosswalk'!$C$2:$C$90,MATCH('OECD Data IO Table - Total (USD'!D14,'OECD Crosswalk'!$A$2:$A$90,0),1) -> other industries | B14: =INDEX('OECD Crosswalk'!$B$2:$B$90,MATCH('OECD Data IO Table - Total (USD'!D14,'OECD Crosswalk'!$A$2:$A$90,0),1) -> nonenergy industries | D14: TTL_10T12: Food products, beverages and tobacco | E14: =11.3+0.9 -> 12.2 | F14: 0 | G14: 0 | H14: 0.1 | I14: 539.2 | J14: 78.2 | K14: 53.8 | L14: 396.1 | M14: 2.8 | N14: =19.7+10.5 -> 30.2 | O14: 0 | P14: 3.2 | Q14: 20.7 | R14: 1.7 | S14: 2.8 | T14: 4.8 | U14: 3.2 | V14: 1.5 | W14: 0.6 | X14: 0.5 | Y14: =255.9+134.1 -> 390 | Z14: 848.3 | AA14: 801 | AB14: =295.2+974+907.2+327.5+153.3 -> 2657.2 | AC14: 1390.5 | AD14: 800.1 | AE14: 197.8 | AF14: 9.7 | AG14: 595.1 | AH14: 216.6 | AI14: =66.2+113.4 -> 179.6 | AJ14: 75.2 | AK14: 93.8 | AL14: 418.3 | AM14: =106.5+249.3 -> 355.8 | AN14: 0 | AO14: 11837.5 | AP14: 0 | AQ14: 0 | AR14: 244.1 | AS14: 3599.6 | AT14: 148.6 | AU14: 219.5 | AV14: 380.6 | AW14: -17148.7 | AX14: =SUM(E14:AQ14) -> 22018.1
A15: =INDEX('OECD Crosswalk'!$C$2:$C$90,MATCH('OECD Data IO Table - Total (USD'!D15,'OECD Crosswalk'!$A$2:$A$90,0),1) -> other industries | B15: =INDEX('OECD Crosswalk'!$B$2:$B$90,MATCH('OECD Data IO Table - Total (USD'!D15,'OECD Crosswalk'!$A$2:$A$90,0),1) -> nonenergy industries | D15: TTL_13T15: Textiles, wearing apparel, leather and related products | E15: =0.5+0.1 -> 0.6 | F15: 0 | G15: 0 | H15: 0.2 | I15: 22.7 | J15: 642.5 | K15: 2.8 | L15: 30.9 | M15: 0.1 | N15: =0.7+0.3 -> 1 | O15: 0 | P15: 0.6 | Q15: 2.5 | R15: 0.3 | S15: 0.3 | T15: 0.6 | U15: 0.4 | V15: 0.8 | W15: 0.2 | X15: 0.7 | Y15: =13.3+21 -> 34.3 | Z15: 15.2 | AA15: 320.4 | AB15: =129+151.7+110.9+152.1+80.8 -> 624.5 | AC15: 11.8 | AD15: 3.2 | AE15: 86.1 | AF15: 3.9 | AG15: 312.3 | AH15: 117.6 | AI15: =28.7+60.6 -> 89.3 | AJ15: 35.2 | AK15: 23.1 | AL15: 32.3 | AM15: =20+106.4 -> 126.4 | AN15: 0 | AO15: 9666.4 | AP15: 0 | AQ15: 0 | AR15: 62.4 | AS15: 1918.5 | AT15: 94 | AU15: 19.7 | AV15: 389.1 | AW15: -11723.4 | AX15: =SUM(E15:AQ15) -> 12209.2
A16: =INDEX('OECD Crosswalk'!$C$2:$C$90,MATCH('OECD Data IO Table - Total (USD'!D16,'OECD Crosswalk'!$A$2:$A$90,0),1) -> other industries | B16: =INDEX('OECD Crosswalk'!$B$2:$B$90,MATCH('OECD Data IO Table - Total (USD'!D16,'OECD Crosswalk'!$A$2:$A$90,0),1) -> nonenergy industries | D16: TTL_16: Wood and of products of wood and cork (except furniture) | E16: =2+0.1 -> 2.1 | F16: 0 | G16: 0 | H16: 0.1 | I16: 25.5 | J16: 0.2 | K16: 0 | L16: 0.2 | M16: 0 | N16: 0.1 | O16: 0 | P16: 0.1 | Q16: 0.9 | R16: 0.1 | S16: 0.1 | T16: 0.2 | U16: 0.1 | V16: 0.2 | W16: 0.1 | X16: 0.1 | Y16: =1.8+1.9 -> 3.7 | Z16: 113.8 | AA16: 12.2 | AB16: =19.9+83.6+12.7+34.4+3.1 -> 153.7 | AC16: 1.4 | AD16: 800.1 | AE16: 4.7 | AF16: 0 | AG16: 10.6 | AH16: 3.1 | AI16: =0.9+1.2 -> 2.1 | AJ16: 1.1 | AK16: 1.3 | AL16: 28.4 | AM16: =2.3+3.6 -> 5.9 | AN16: 0 | AO16: 565.3 | AP16: 0 | AQ16: 0 | AR16: 66.4 | AS16: 334.4 | AT16: 6.2 | AU16: 0.2 | AV16: 26 | AW16: -626.1 | AX16: =SUM(E16:AQ16) -> 1737.5
A17: =INDEX('OECD Crosswalk'!$C$2:$C$90,MATCH('OECD Data IO Table - Total (USD'!D17,'OECD Crosswalk'!$A$2:$A$90,0),1) -> other industries | B17: =INDEX('OECD Crosswalk'!$B$2:$B$90,MATCH('OECD Data IO Table - Total (USD'!D17,'OECD Crosswalk'!$A$2:$A$90,0),1) -> nonenergy industries | D17: TTL_17T18: Paper products and printing | E17: =9.6+1 -> 10.6 | F17: 0 | G17: 0 | H17: 0.1 | I17: 751.4 | J17: 175.7 | K17: 5.3 | L17: 796.5 | M17: 0.3 | N17: =3.2+2.7 -> 5.9 | O17: 0 | P17: 10 | Q17: 6 | R17: 0.8 | S17: 4.5 | T17: 10 | U17: 3.4 | V17: 1.3 | W17: 0.3 | X17: 3.3 | Y17: =16.3+20.7 -> 37 | Z17: 449.8 | AA17: 427.7 | AB17: =117.7+176.3+82.9+171.8+54.5 -> 603.2 | AC17: 5.2 | AD17: 3.2 | AE17: 59.7 | AF17: 2.7 | AG17: 351.9 | AH17: 89.7 | AI17: =24.6+29.4 -> 54 | AJ17: 16.4 | AK17: 39.5 | AL17: 334 | AM17: =24+41.4 -> 65.4 | AN17: 0 | AO17: 1557.3 | AP17: 0 | AQ17: 0 | AR17: 18.8 | AS17: 234 | AT17: 17 | AU17: 74.7 | AV17: 124.2 | AW17: -1724.9 | AX17: =SUM(E17:AQ17) -> 5882.1
A18: =INDEX('OECD Crosswalk'!$C$2:$C$90,MATCH('OECD Data IO Table - Total (USD'!D18,'OECD Crosswalk'!$A$2:$A$90,0),1) -> natural gas and petroleum systems | B18: =INDEX('OECD Crosswalk'!$B$2:$B$90,MATCH('OECD Data IO Table - Total (USD'!D18,'OECD Crosswalk'!$A$2:$A$90,0),1) -> natural gas and petroleum suppliers | D18: TTL_19: Coke and refined petroleum products | E18: =1+0.1 -> 1.1 | F18: 0 | G18: 0 | H18: 15.7 | I18: 11.7 | J18: 3.1 | K18: 2.1 | L18: 11.4 | M18: 74.9 | N18: =119.6+20.8 -> 140.4 | O18: 0 | P18: 52.8 | Q18: 667.4 | R18: 48.7 | S18: 4.8 | T18: 15.9 | U18: 9.3 | V18: 10.4 | W18: 3.5 | X18: 6.1 | Y18: =84.7+55.8 -> 140.5 | Z18: 4 | AA18: 4405.8 | AB18: =293.6+671.7+606.3+737.5+45.6 -> 2354.7 | AC18: 15 | AD18: 800.1 | AE18: 40.7 | AF18: 3.9 | AG18: 535 | AH18: 134.4 | AI18: =23.7+97.7 -> 121.4 | AJ18: 253.3 | AK18: 116.1 | AL18: 20.1 | AM18: =29.2+62.4 -> 91.6 | AN18: 0 | AO18: 3345.6 | AP18: 0 | AQ18: 0 | AR18: 12.6 | AS18: 1096.6 | AT18: 63.2 | AU18: 69 | AV18: 33.1 | AW18: -13543.9 | AX18: =SUM(E18:AQ18) -> 13461.5
A19: =INDEX('OECD Crosswalk'!$C$2:$C$90,MATCH('OECD Data IO Table - Total (USD'!D19,'OECD Crosswalk'!$A$2:$A$90,0),1) -> chemicals | B19: =INDEX('OECD Crosswalk'!$B$2:$B$90,MATCH('OECD Data IO Table - Total (USD'!D19,'OECD Crosswalk'!$A$2:$A$90,0),1) -> nonenergy industries | D19: TTL_20T21: Chemicals and pharmaceutical products | E19: =2.1+0.1+0.1 -> 2.3 | F19: 0 | G19: 0 | H19: =11.5+0.1 -> 11.6 | I19: =32.9+2.4 -> 35.3 | J19: =3.1+22 -> 25.1 | K19: =11.5+0.4 -> 11.9 | L19: =93.6+2.1 -> 95.7 | M19: =27.4+0.7 -> 28.1 | N19: =289.4+68.9+7.7+55.8 -> 421.8 | O19: 0 | P19: =76.4+1.6 -> 78 | Q19: =197.6+667.4 -> 865 | R19: =18.5+0.5 -> 19 | S19: =37+1.5 -> 38.5 | T19: =106.2+2.1 -> 108.3 | U19: =28.2+0.9 -> 29.1 | V19: =20.4+0.5 -> 20.9 | W19: =6.1+0.2 -> 6.3 | X19: =12.1+0.2 -> 12.3 | Y19: =12.5+158.3+0.6+4.8 -> 176.2 | Z19: =7+0.8 -> 7.8 | AA19: =764.3+51 -> 815.3 | AB19: =16.8+34.7+30.3+104+13+0.9+2.9+2.9+4.9+1.1 -> 211.5 | AC19: =23.4+2 -> 25.4 | AD19: =68.6+1.7 -> 70.3 | AE19: =21.5+2 -> 23.5 | AF19: =1.7+0.1 -> 1.8 | AG19: =125.9+9.8 -> 135.7 | AH19: =54+2.7 -> 56.7 | AI19: =19.7+46.6+2.8+1.7 -> 70.8 | AJ19: =78+14.6 -> 92.6 | AK19: =202.3+21.7 -> 224 | AL19: =87.8+75.7 -> 163.5 | AM19: =79.1+9.8+267.1+12.6 -> 368.6 | AN19: 0 | AO19: =3025.1+1373.4 -> 4398.5 | AP19: 0 | AQ19: =0.2+0.2 -> 0.4 | AR19: =127.2+30.4 -> 157.6 | AS19: =899.5+349.2 -> 1248.7 | AT19: =23.6+18.4 -> 42 | AU19: =6.1+44.5 -> 50.6 | AV19: =333.9+161.6 -> 495.5 | AW19: =-6496.9-1813.5 -> -8310.4 | AX19: =SUM(E19:AQ19) -> 8651.8
A20: =INDEX('OECD Crosswalk'!$C$2:$C$90,MATCH('OECD Data IO Table - Total (USD'!D20,'OECD Crosswalk'!$A$2:$A$90,0),1) -> other industries | B20: =INDEX('OECD Crosswalk'!$B$2:$B$90,MATCH('OECD Data IO Table - Total (USD'!D20,'OECD Crosswalk'!$A$2:$A$90,0),1) -> nonenergy industries | D20: TTL_22: Rubber and plastics products | E20: 0.2 | F20: 0 | G20: 0 | H20: 1.4 | I20: 49.5 | J20: 5.7 | K20: 1.7 | L20: 21.7 | M20: 2.3 | N20: =19.8+12.8 -> 32.6 | O20: 0 | P20: 15.7 | Q20: 41.9 | R20: 7.3 | S20: 28.6 | T20: 83.7 | U20: 30.4 | V20: 82.5 | W20: 15.9 | X20: 10.9 | Y20: =2.4+34 -> 36.4 | Z20: 2.4 | AA20: 2002.7 | AB20: =17.9+2.3+2.4+14.1+3.3 -> 40 | AC20: 7 | AD20: 14.4 | AE20: 5 | AF20: 0.2 | AG20: 14.1 | AH20: 29.8 | AI20: =1.6+3.5 -> 5.1 | AJ20: 6.7 | AK20: 2.1 | AL20: 2.2 | AM20: =15.1+38.2 -> 53.3 | AN20: 0 | AO20: 326 | AP20: 0 | AQ20: 0.1 | AR20: 43.5 | AS20: 40.4 | AT20: 0.5 | AU20: 0 | AV20: 0 | AW20: -3064 | AX20: =SUM(E20:AQ20) -> 2979.5
A21: =INDEX('OECD Crosswalk'!$C$2:$C$90,MATCH('OECD Data IO Table - Total (USD'!D21,'OECD Crosswalk'!$A$2:$A$90,0),1) -> Cement and other carbonate use | B21: =INDEX('OECD Crosswalk'!$B$2:$B$90,MATCH('OECD Data IO Table - Total (USD'!D21,'OECD Crosswalk'!$A$2:$A$90,0),1) -> nonenergy industries | D21: TTL_23: Other non-metallic mineral products | E21: 0.1 | F21: 0 | G21: 0 | H21: 4.4 | I21: 41.4 | J21: 1.6 | K21: 1.4 | L21: 5.3 | M21: 14 | N21: =11.9+8.7 -> 20.6 | O21: 0 | P21: 402.6 | Q21: 451.1 | R21: 42.1 | S21: 36.3 | T21: 98.8 | U21: 19.8 | V21: 61.1 | W21: 18.4 | X21: 6 | Y21: =5.3+32 -> 37.3 | Z21: 58.7 | AA21: 183.1 | AB21: =2.6+2.7+5+26+13.2 -> 49.5 | AC21: 3.2 | AD21: 12.2 | AE21: 35.8 | AF21: 0.4 | AG21: 61.3 | AH21: 22 | AI21: =3.9+7.9 -> 11.8 | AJ21: 115.8 | AK21: 81.2 | AL21: 4.6 | AM21: =18.4+43.1 -> 61.5 | AN21: 0 | AO21: 672.5 | AP21: 0 | AQ21: 0 | AR21: 49.4 | AS21: 165.7 | AT21: 0.3 | AU21: 0 | AV21: 108.8 | AW21: -1681.9 | AX21: =SUM(E21:AQ21) -> 2635.9
A22: =INDEX('OECD Crosswalk'!$C$2:$C$90,MATCH('OECD Data IO Table - Total (USD'!D22,'OECD Crosswalk'!$A$2:$A$90,0),1) -> iron and steel | B22: =INDEX('OECD Crosswalk'!$B$2:$B$90,MATCH('OECD Data IO Table - Total (USD'!D22,'OECD Crosswalk'!$A$2:$A$90,0),1) -> nonenergy industries | D22: TTL_24: Manufacture of basic metals | E22: 0.1 | F22: 0 | G22: 0 | H22: 5.3 | I22: 10.3 | J22: 0.9 | K22: 1.7 | L22: 8.7 | M22: 5 | N22: =14.7+3.7 -> 18.4 | O22: 0 | P22: 31.6 | Q22: 5839.2 | R22: 476 | S22: 110.9 | T22: 489.7 | U22: 157.6 | V22: 52.9 | W22: 10.1 | X22: 37.9 | Y22: =6.5+87.6 -> 94.1 | Z22: 8.3 | AA22: 5508.3 | AB22: =5.3+13.1+10.3+50.1+2.9 -> 81.7 | AC22: 1.7 | AD22: 12.2 | AE22: 8.3 | AF22: 0.7 | AG22: 62 | AH22: 41 | AI22: =7.7+5.2 -> 12.9 | AJ22: 13.7 | AK22: 14.6 | AL22: 2.3 | AM22: =15.4+24.7 -> 40.1 | AN22: 0 | AO22: 158.6 | AP22: 0 | AQ22: 0.1 | AR22: 263.3 | AS22: 295.4 | AT22: 0.7 | AU22: 0 | AV22: 8466.3 | AW22: -10834.1 | AX22: =SUM(E22:AQ22) -> 13316.9
A23: =INDEX('OECD Crosswalk'!$C$2:$C$90,MATCH('OECD Data IO Table - Total (USD'!D23,'OECD Crosswalk'!$A$2:$A$90,0),1) -> other industries | B23: =INDEX('OECD Crosswalk'!$B$2:$B$90,MATCH('OECD Data IO Table - Total (USD'!D23,'OECD Crosswalk'!$A$2:$A$90,0),1) -> nonenergy industries | D23: TTL_25: Fabricated metal products, except machinery and equipment | E23: 0.1 | F23: 0 | G23: 0 | H23: 3.9 | I23: 4.7 | J23: 0.9 | K23: 1.4 | L23: 3.2 | M23: 2.6 | N23: =4+1.7 -> 5.7 | O23: 0 | P23: 13 | Q23: 275.8 | R23: 75.6 | S23: 24.8 | T23: 81.6 | U23: 58.2 | V23: 32.3 | W23: 10.7 | X23: 10 | Y23: =3.1+16.3 -> 19.4 | Z23: 6.2 | AA23: 2351.6 | AB23: =2.6+5+3.3+30+1.7 -> 42.6 | AC23: 1.6 | AD23: 6.1 | AE23: 6.9 | AF23: 0.6 | AG23: 32.2 | AH23: 31.1 | AI23: =4.4+10.3 -> 14.7 | AJ23: 13.6 | AK23: 13.1 | AL23: 1.8 | AM23: =9.7+14.1 -> 23.8 | AN23: 0 | AO23: 390.5 | AP23: 0 | AQ23: 0 | AR23: 631.1 | AS23: 230.1 | AT23: 0.5 | AU23: 0 | AV23: 335.3 | AW23: -3551.3 | AX23: =SUM(E23:AQ23) -> 3560.3
A24: =INDEX('OECD Crosswalk'!$C$2:$C$90,MATCH('OECD Data IO Table - Total (USD'!D24,'OECD Crosswalk'!$A$2:$A$90,0),1) -> other industries | B24: =INDEX('OECD Crosswalk'!$B$2:$B$90,MATCH('OECD Data IO Table - Total (USD'!D24,'OECD Crosswalk'!$A$2:$A$90,0),1) -> nonenergy industries | D24: TTL_26: Computer, electronic and optical products | E24: 0.1 | F24: 0 | G24: 0 | H24: 2 | I24: 3.9 | J24: 1.3 | K24: 0.4 | L24: 3.9 | M24: 2.9 | N24: =4.7+2.9 -> 7.6 | O24: 0 | P24: 3.9 | Q24: 20 | R24: 4.4 | S24: 384.8 | T24: 160.8 | U24: 52.9 | V24: 26 | W24: 11.7 | X24: 9.6 | Y24: =47.7+63 -> 110.7 | Z24: 2.8 | AA24: 11206.1 | AB24: =4.2+12.5+10.6+21.6+111.8 -> 160.7 | AC24: 3.3 | AD24: 134.7 | AE24: 1136.7 | AF24: 18.3 | AG24: 167.9 | AH24: 62.2 | AI24: =35.9+44.9 -> 80.8 | AJ24: 72.9 | AK24: 101.3 | AL24: 7.3 | AM24: =99.7+241.4 -> 341.1 | AN24: 0 | AO24: 9641.6 | AP24: 0 | AQ24: 0.2 | AR24: 6253.5 | AS24: 29295.1 | AT24: 28 | AU24: 0.1 | AV24: 1379.5 | AW24: -59402.6 | AX24: =SUM(E24:AQ24) -> 23944.8
A25: =INDEX('OECD Crosswalk'!$C$2:$C$90,MATCH('OECD Data IO Table - Total (USD'!D25,'OECD Crosswalk'!$A$2:$A$90,0),1) -> other industries | B25: =INDEX('OECD Crosswalk'!$B$2:$B$90,MATCH('OECD Data IO Table - Total (USD'!D25,'OECD Crosswalk'!$A$2:$A$90,0),1) -> nonenergy industries | D25: TTL_27: Electrical equipment | E25: 0 | F25: 0 | G25: 0 | H25: 1.8 | I25: 3.2 | J25: 0.7 | K25: 0.5 | L25: 2.5 | M25: 2.5 | N25: =3.2+1.6 -> 4.8 | O25: 0 | P25: 5.3 | Q25: 42.3 | R25: 5.7 | S25: 127.1 | T25: 580.4 | U25: 102.4 | V25: 48.3 | W25: 14.3 | X25: 13.2 | Y25: =75.6+61 -> 136.6 | Z25: 6.7 | AA25: 8164.4 | AB25: =5.2+11.2+6+17.1+62.9 -> 102.4 | AC25: 2.3 | AD25: 75 | AE25: 538.9 | AF25: 5 | AG25: 75.2 | AH25: 91 | AI25: =22.9+42.5 -> 65.4 | AJ25: 37 | AK25: 46.3 | AL25: 3.2 | AM25: =64.3+163.9 -> 228.2 | AN25: 0 | AO25: 4056.2 | AP25: 0 | AQ25: 0.1 | AR25: 2029.2 | AS25: 1058.9 | AT25: 11.8 | AU25: 2.4 | AV25: 342.1 | AW25: -15322.5 | AX25: =SUM(E25:AQ25) -> 14588.9
A26: =INDEX('OECD Crosswalk'!$C$2:$C$90,MATCH('OECD Data IO Table - Total (USD'!D26,'OECD Crosswalk'!$A$2:$A$90,0),1) -> other industries | B26: =INDEX('OECD Crosswalk'!$B$2:$B$90,MATCH('OECD Data IO Table - Total (USD'!D26,'OECD Crosswalk'!$A$2:$A$90,0),1) -> nonenergy industries | D26: TTL_28: Machinery and equipment n.e.c. | E26: 0.3 | F26: 0 | G26: 0 | H26: 15.2 | I26: 14.4 | J26: 3.6 | K26: 2.6 | L26: 12.8 | M26: 5.9 | N26: =9.5+5.3 -> 14.8 | O26: 0 | P26: 29.5 | Q26: 232.2 | R26: 39.9 | S26: 26.2 | T26: 71.3 | U26: 237.1 | V26: 115.8 | W26: 39.9 | X26: 22.1 | Y26: =12.3+20.7 -> 33 | Z26: 3.2 | AA26: 724.6 | AB26: =8.3+69.5+100.1+171.4+16.1 -> 365.4 | AC26: 3.7 | AD26: 10 | AE26: 34.5 | AF26: 0.4 | AG26: 251.5 | AH26: 61.5 | AI26: =2.8+8.4 -> 11.2 | AJ26: 14 | AK26: 18.9 | AL26: 31.4 | AM26: =13.1+20.5 -> 33.6 | AN26: 0 | AO26: 465.5 | AP26: 0 | AQ26: 0.2 | AR26: 7163.9 | AS26: 1027.4 | AT26: 0.8 | AU26: 0 | AV26: 912.5 | AW26: -10813.8 | AX26: =SUM(E26:AQ26) -> 2946.2
A27: =INDEX('OECD Crosswalk'!$C$2:$C$90,MATCH('OECD Data IO Table - Total (USD'!D27,'OECD Crosswalk'!$A$2:$A$90,0),1) -> other industries | B27: =INDEX('OECD Crosswalk'!$B$2:$B$90,MATCH('OECD Data IO Table - Total (USD'!D27,'OECD Crosswalk'!$A$2:$A$90,0),1) -> nonenergy industries | D27: TTL_29: Motor vehicles, trailers and semi-trailers | E27: 0 | F27: 0 | G27: 0 | H27: 0.3 | I27: 0.6 | J27: 0.3 | K27: 0.1 | L27: 0.6 | M27: 0.2 | N27: =0.4+0.2 -> 0.6 | O27: 0 | P27: 1.5 | Q27: 6.9 | R27: 1.1 | S27: 2.2 | T27: 6.3 | U27: 9.4 | V27: 186.9 | W27: 7.3 | X27: 1.3 | Y27: =0.9+26.3 -> 27.2 | Z27: 0.3 | AA27: 468 | AB27: =24.1+24+17.4+5.7+17.8 -> 89 | AC27: 1 | AD27: 13.7 | AE27: 19.5 | AF27: 0.4 | AG27: 36 | AH27: 5.3 | AI27: =2.6+11.3 -> 13.9 | AJ27: 40.8 | AK27: 1.6 | AL27: 1 | AM27: =23.9+32.8 -> 56.7 | AN27: 0 | AO27: 1598 | AP27: 0 | AQ27: 0.1 | AR27: 2196.8 | AS27: 701.9 | AT27: 13.1 | AU27: 4.1 | AV27: 45 | AW27: -4090.8 | AX27: =SUM(E27:AQ27) -> 2598.1
A28: =INDEX('OECD Crosswalk'!$C$2:$C$90,MATCH('OECD Data IO Table - Total (USD'!D28,'OECD Crosswalk'!$A$2:$A$90,0),1) -> other industries | B28: =INDEX('OECD Crosswalk'!$B$2:$B$90,MATCH('OECD Data IO Table - Total (USD'!D28,'OECD Crosswalk'!$A$2:$A$90,0),1) -> nonenergy industries | D28: TTL_30: Other transport equipment | E28: 0 | F28: 0 | G28: 0 | H28: 0.1 | I28: 0.4 | J28: 0.1 | K28: 0.1 | L28: 0.5 | M28: 0.2 | N28: =0.3+0.2 -> 0.5 | O28: 0 | P28: 1.1 | Q28: 5.5 | R28: 0.6 | S28: 1.1 | T28: 2.2 | U28: 4.7 | V28: 199.1 | W28: 127.4 | X28: 4.6 | Y28: =0.3+21.1 -> 21.4 | Z28: 0.2 | AA28: 475.7 | AB28: =17.1+53.5+83.6+5.8+13.3 -> 173.3 | AC28: 0.8 | AD28: 21.1 | AE28: 10.4 | AF28: 0.3 | AG28: 52.1 | AH28: 4 | AI28: =4.4+8 -> 12.4 | AJ28: 91.9 | AK28: 1.1 | AL28: 0.7 | AM28: =27.3+40.4 -> 67.7 | AN28: 0 | AO28: 916.2 | AP28: 0 | AQ28: 0 | AR28: 4989.8 | AS28: 1071.4 | AT28: 0.3 | AU28: 0 | AV28: 30.6 | AW28: -7770.4 | AX28: =SUM(E28:AQ28) -> 2197.5
A29: =INDEX('OECD Crosswalk'!$C$2:$C$90,MATCH('OECD Data IO Table - Total (USD'!D29,'OECD Crosswalk'!$A$2:$A$90,0),1) -> other industries | B29: =INDEX('OECD Crosswalk'!$B$2:$B$90,MATCH('OECD Data IO Table - Total (USD'!D29,'OECD Crosswalk'!$A$2:$A$90,0),1) -> nonenergy industries | D29: TTL_31T33: Other manufacturing; repair and installation of machinery and equipment | E29: =0.3+0.1 -> 0.4 | F29: 0 | G29: 0 | H29: 1.2 | I29: 9.5 | J29: 2.4 | K29: 1.4 | L29: 12.9 | M29: 0.3 | N29: =0.8+0.7 -> 1.5 | O29: 0 | P29: 1.6 | Q29: 31.2 | R29: 4.8 | S29: 2.7 | T29: 4.2 | U29: 2.9 | V29: 5.5 | W29: 2.9 | X29: 3.1 | Y29: =13.8+16.7 -> 30.5 | Z29: 27.5 | AA29: 362.7 | AB29: =33.7+59.1+91.5+52.2+10 -> 246.5 | AC29: 9.8 | AD29: 11.1 | AE29: 31.8 | AF29: 1.1 | AG29: 342.2 | AH29: 93.4 | AI29: =5.9+26 -> 31.9 | AJ29: 42.3 | AK29: 37.9 | AL29: 17.6 | AM29: =29.7+22.7 -> 52.4 | AN29: 0 | AO29: 1011.7 | AP29: 0 | AQ29: 0.1 | AR29: 353.7 | AS29: 8436.5 | AT29: 82.2 | AU29: 0 | AV29: 317.4 | AW29: -10821.1 | AX29: =SUM(E29:AQ29) -> 2439
A30: =INDEX('OECD Crosswalk'!$C$2:$C$90,MATCH('OECD Data IO Table - Total (USD'!D30,'OECD Crosswalk'!$A$2:$A$90,0),1) -> energy suppliers | B30: =INDEX('OECD Crosswalk'!$B$2:$B$90,MATCH('OECD Data IO Table - Total (USD'!D30,'OECD Crosswalk'!$A$2:$A$90,0),1) -> energy suppliers | D30: TTL_35T39: Electricity, gas, water supply, sewerage, waste and remediation services | E30: =0.8+0.8+0.1 -> 1.7 | F30: 0 | G30: 0 | H30: =0.9+0.1 -> 1 | I30: =101.8+46.8 -> 148.6 | J30: =13.8+8.9 -> 22.7 | K30: =9.4+6.5 -> 15.9 | L30: =75.2+60.3 -> 135.5 | M30: =0.2+0.1 -> 0.3 | N30: =0.7+0.2+0.3+0.1 -> 1.3 | O30: 0 | P30: =0.7+0.3 -> 1 | Q30: =7.2+7.3 -> 14.5 | R30: =0.4+0.4 -> 0.8 | S30: =0.2+0.2 -> 0.4 | T30: =0.5+0.4 -> 0.9 | U30: =0.3+0.3 -> 0.6 | V30: =0.2+0.3 -> 0.5 | W30: =0.1+0.1 -> 0.2 | X30: =0.4+0.1 -> 0.5 | Y30: =309.3+91.3+68.3+324.7 -> 793.6 | Z30: =41+54.5 -> 95.5 | AA30: =392.8+637.4 -> 1030.2 | AB30: =127.5+49.2+72.4+374.1+17.8+64.4+58.5+53.5+159.9+51.6 -> 1028.9 | AC30: =396.2+147.3 -> 543.5 | AD30: =68.5+27 -> 95.5 | AE30: =102.3+95.6 -> 197.9 | AF30: =3.9+5.8 -> 9.7 | AG30: =492.5+512.9 -> 1005.4 | AH30: =1271.9+1084 -> 2355.9 | AI30: =23.1+25.5+32.5+67.5 -> 148.6 | AJ30: =154.8+97.2 -> 252 | AK30: =127.8+62.5 -> 190.3 | AL30: =202.9+80.2 -> 283.1 | AM30: =115.3+120.8+55.8+107.4 -> 399.3 | AN30: 0 | AO30: =1356.2+1142.3 -> 2498.5 | AP30: =2.4+29.9 -> 32.3 | AQ30: 0 | AR30: =2.2+108.1 -> 110.3 | AS30: =3.8+8.5 -> 12.3 | AT30: =0.4+0.2 -> 0.6 | AU30: 0 | AV30: =39.5 -> 39.5 | AW30: =-915.6+-26.6 -> -942.2 | AX30: =SUM(E30:AQ30) -> 11306.6
A31: =INDEX('OECD Crosswalk'!$C$2:$C$90,MATCH('OECD Data IO Table - Total (USD'!D31,'OECD Crosswalk'!$A$2:$A$90,0),1) -> 0 | B31: =INDEX('OECD Crosswalk'!$B$2:$B$90,MATCH('OECD Data IO Table - Total (USD'!D31,'OECD Crosswalk'!$A$2:$A$90,0),1) -> nonenergy industries | D31: TTL_41T43: Construction | E31: 0.8 | F31: 0 | G31: 0 | H31: 0.5 | I31: 7.4 | J31: 0.6 | K31: 0.4 | L31: 2.3 | M31: 0 | N31: =0.1+0.1 -> 0.2 | O31: 0 | P31: 0.4 | Q31: 2.1 | R31: 0.2 | S31: 0.2 | T31: 0.4 | U31: 0.2 | V31: 0.2 | W31: 0.1 | X31: 0.1 | Y31: =5+5.5 -> 10.5 | Z31: 6417 | AA31: 31.4 | AB31: =22.1+14.8+63.3+24.6+3.4 -> 128.2 | AC31: 10.7 | AD31: 3.2 | AE31: 11.3 | AF31: 0.3 | AG31: 32.5 | AH31: 325.9 | AI31: =2.6+2.8 -> 5.4 | AJ31: 352.5 | AK31: 22.6 | AL31: 23 | AM31: =5.8+8.4 -> 14.2 | AN31: 0 | AO31: 13.2 | AP31: 0 | AQ31: 0 | AR31: 20315.1 | AS31: 9.7 | AT31: 1.6 | AU31: 0 | AV31: 0 | AW31: -55 | AX31: =SUM(E31:AQ31) -> 7418
A32: =INDEX('OECD Crosswalk'!$C$2:$C$90,MATCH('OECD Data IO Table - Total (USD'!D32,'OECD Crosswalk'!$A$2:$A$90,0),1) -> 0 | B32: =INDEX('OECD Crosswalk'!$B$2:$B$90,MATCH('OECD Data IO Table - Total (USD'!D32,'OECD Crosswalk'!$A$2:$A$90,0),1) -> nonenergy industries | D32: TTL_45T47: Wholesale and retail trade; repair of motor vehicles | E32: =130.8+6.8 -> 137.6 | F32: 0 | G32: 0 | H32: 1505.9 | I32: 2412.7 | J32: 1050.7 | K32: 192.3 | L32: 1563.4 | M32: 172.2 | N32: =544.1+216.9 -> 761 | O32: 0 | P32: 461.7 | Q32: 2750.3 | R32: 317 | S32: 521.1 | T32: 757.5 | U32: 357.4 | V32: 470.6 | W32: 189.1 | X32: 529.4 | Y32: =1129.9+873.3 -> 2003.2 | Z32: 2384.2 | AA32: 31331.2 | AB32: =1651.4+3322.3+3587.6+4514.6+589.3 -> 13665.2 | AC32: 3055.2 | AD32: 800.1 | AE32: 1862.5 | AF32: 71.6 | AG32: 4045.9 | AH32: 1503.6 | AI32: =376.4+934.6 -> 1311 | AJ32: 985.7 | AK32: 1037.5 | AL32: 1582.7 | AM32: =721.8+1395.5 -> 2117.3 | AN32: 0 | AO32: 60617 | AP32: 1.7 | AQ32: 0.5 | AR32: 16654.3 | AS32: 5580.1 | AT32: 108.4 | AU32: 467.9 | AV32: 37109.9 | AW32: -23738.3 | AX32: =SUM(E32:AQ32) -> 142526
A33: =INDEX('OECD Crosswalk'!$C$2:$C$90,MATCH('OECD Data IO Table - Total (USD'!D33,'OECD Crosswalk'!$A$2:$A$90,0),1) -> 0 | B33: =INDEX('OECD Crosswalk'!$B$2:$B$90,MATCH('OECD Data IO Table - Total (USD'!D33,'OECD Crosswalk'!$A$2:$A$90,0),1) -> nonenergy industries | D33: TTL_49T53: Transportation and storage | E33: =4.8+0.4+1.1+0.1+1+0.1+2.6+0.2+0.3 -> 10.6 | F33: 0 | G33: 0 | H33: =28+6.5+5.1+15.3+0.1 -> 55 | I33: =120.7+89.2+59.6+57.8+33.8 -> 361.1 | J33: =60.7+27.5+20.2+28.1+9.1 -> 145.6 | K33: =7.7+9.6+5.4+3.8+4 -> 30.5 | L33: =11.6+2.3+2.1+6.5 -> 22.5 | M33: =11.6+2.3+2.1+6.5 -> 22.5 | N33: =33.8+12.3+6.6+2.3+6+2.1+18.7+6.6+0.1+0.1 -> 88.6 | O33: 0 | P33: =45.3+8.2+7.4+23.2+0.1 -> 84.2 | Q33: =260.9+44.3+37.7+121.5+0.4 -> 464.8 | R33: =30.3+5.3+4.6+14.7+0.1 -> 55 | S33: =41.9+7.6+7+21.6+0.1 -> 78.2 | T33: =69.7+11.4+10.3+32.4+0.2 -> 124 | U33: =31.7+5.4+4.8+14.9+0.2 -> 57 | V33: =33.3+5.9+5.3+16.4+0.1 -> 61 | W33: =14.4+2.6+2.4+7.3 -> 26.7 | X33: =7.6+1.6+1+3.8 -> 14 | Y33: =50.8+52+14.2+24.8+11.6+13.7+26.4+25.6+8.2+18.6 -> 245.9 | Z33: =82.1+84.9+61.7+43.9+17.7 -> 290.3 | AA33: =1955.1+2124.8+1373.8+966.9+723.7 -> 7144.3 | AB33: =234.5+231.6+186.9+479.2+43.7+85.8+3781.7+1973.5+1578.4+647.4+56+2183+1169+551.6+397.6+44.5+93.7+96.4+244.7+20.4+32.2+417.1+55.5+73.2+736.5 -> 15414.1 | AC33: =188.3+59.4+44.5+90.6+22.1 -> 404.9 | AD33: =41.3+22.6+23.8+20.5+34.4 -> 142.6 | AE33: =135.5+599.9+351.4+69.2+459.7 -> 1615.7 | AF33: =4.5+9+7.1+1.9+7.6 -> 30.1 | AG33: =292.9+1034.6+547.4+102.6+992.6 -> 2970.1 | AH33: =84.7+73.1+46.8+38.1+205.7 -> 448.4 | AI33: =25+57.2+49.8+151.2+36.3+83.7+10.4+24.7+40.6+67 -> 545.9 | AJ33: =63.3+40.3+28.1+32.7+60.3 -> 224.7 | AK33: =63.3+35.8+25+32.3+30.2 -> 186.6 | AL33: =70.8+44.9+31.4+34.2+34.3 -> 215.6 | AM33: =40.9+95.6+30+120.9+20.5+65.2+20+45.1+30.9+76.8 -> 545.9 | AN33: 0 | AO33: =3927.6+1996.7+1249+1753+279.6 -> 9205.9 | AP33: =0.3+0.1+0.1+0.2+7.1 -> 7.8 | AQ33: 0.1 | AR33: =1191.2+231+202.6+598.2+308.9 -> 2531.9 | AS33: =-1034+276.2+332.1+654.1+87.6 -> 316 | AT33: =374.1+68.8+181+6.8+5.4 -> 636.1 | AU33: =4706.2+1724.6+1965.7+14.2+67.5 -> 8478.2 | AV33: =2393.5+2708.3+11912.4+13749.2+1316.9 -> 32080.3 | AW33: =-4656.3+-1227.2+-1495+-1421.5+-1087 -> -9887 | AX33: =SUM(E33:AQ33) -> 41340.2
A34: =INDEX('OECD Crosswalk'!$C$2:$C$90,MATCH('OECD Data IO Table - Total (USD'!D34,'OECD Crosswalk'!$A$2:$A$90,0),1) -> 0 | B34: =INDEX('OECD Crosswalk'!$B$2:$B$90,MATCH('OECD Data IO Table - Total (USD'!D34,'OECD Crosswalk'!$A$2:$A$90,0),1) -> nonenergy industries | D34: TTL_55T56: Accomodation and food services | E34: 0.2 | F34: 0 | G34: 0 | H34: 0.1 | I34: 9.7 | J34: 2.7 | K34: 1.3 | L34: 5.5 | M34: 0 | N34: 0.1 | O34: 0 | P34: 0.1 | Q34: 0.2 | R34: 0 | S34: 0 | T34: 0.1 | U34: 0.1 | V34: 0 | W34: 0 | X34: 0.1 | Y34: =4.9+7.3 -> 12.2 | Z34: 11.7 | AA34: 129.3 | AB34: =16.5+44.3+11.1+33.1+10.7 -> 115.7 | AC34: 72.5 | AD34: 16.9 | AE34: 32.9 | AF34: 2.5 | AG34: 214.8 | AH34: 96.2 | AI34: =10.3+16.5 -> 26.8 | AJ34: 14 | AK34: 33.1 | AL34: 19.9 | AM34: 00=8.4+24.4 | AN34: 0 | AO34: 4944.9 | AP34: 0 | AQ34: 0 | AR34: 25.5 | AS34: 4.6 | AT34: 1302.9 | AU34: 14832.2 | AV34: 0 | AW34: -1329.3 | AX34: =SUM(E34:AQ34) -> 5763.6
A35: =INDEX('OECD Crosswalk'!$C$2:$C$90,MATCH('OECD Data IO Table - Total (USD'!D35,'OECD Crosswalk'!$A$2:$A$90,0),1) -> 0 | B35: =INDEX('OECD Crosswalk'!$B$2:$B$90,MATCH('OECD Data IO Table - Total (USD'!D35,'OECD Crosswalk'!$A$2:$A$90,0),1) -> nonenergy industries | D35: TTL_58T60: Publishing, audiovisual and broadcasting activities | E35: =2.1+0.2 -> 2.3 | F35: 0 | G35: 0 | H35: 0.1 | I35: 56.1 | J35: 15.6 | K35: 1.4 | L35: 21.5 | M35: 0.2 | N35: =0.6+0.3 -> 0.9 | O35: 0 | P35: 0.8 | Q35: 2.2 | R35: 0.2 | S35: 1 | T35: 1.6 | U35: 0.7 | V35: 0.4 | W35: 0.1 | X35: 0.3 | Y35: =12.2+7.8 -> 20 | Z35: 78 | AA35: 430.3 | AB35: =44.5+66.3+69.3+70.6+19.6 -> 270.3 | AC35: 28.3 | AD35: 431.7 | AE35: 136.5 | AF35: 4.6 | AG35: 460.8 | AH35: 258.3 | AI35: =62.1+21.2 -> 83.3 | AJ35: 22.2 | AK35: 37.5 | AL35: 111 | AM35: =74.7+36.6 -> 111.3 | AN35: 0 | AO35: 1190.7 | AP35: 4.1 | AQ35: 0.1 | AR35: 194.9 | AS35: 12.9 | AT35: 21.7 | AU35: 114.3 | AV35: 3613.2 | AW35: -1908.6 | AX35: =SUM(E35:AQ35) -> 3784.4
A36: =INDEX('OECD Crosswalk'!$C$2:$C$90,MATCH('OECD Data IO Table - Total (USD'!D36,'OECD Crosswalk'!$A$2:$A$90,0),1) -> 0 | B36: =INDEX('OECD Crosswalk'!$B$2:$B$90,MATCH('OECD Data IO Table - Total (USD'!D36,'OECD Crosswalk'!$A$2:$A$90,0),1) -> nonenergy industries | D36: TTL_61: Telecommunications | E36: =0.7+0.1 -> 0.8 | F36: 0 | G36: 0 | H36: 0.1 | I36: 68.7 | J36: 20.4 | K36: 9.9 | L36: 40.1 | M36: 0 | N36: =0.2+0.2 -> 0.4 | O36: 0 | P36: 0.2 | Q36: 1.4 | R36: 0.2 | S36: 0.4 | T36: 0.5 | U36: 0.4 | V36: 0.2 | W36: 0.1 | X36: 0.1 | Y36: =16.5+38.6 -> 55.1 | Z36: 62.8 | AA36: 1284.1 | AB36: =84.6+1281+185.3+159.5+60.6 -> 1771 | AC36: 95.1 | AD36: 134.6 | AE36: 1340.8 | AF36: 31.5 | AG36: 2217.2 | AH36: 567.7 | AI36: =104.5+145.6 -> 250.1 | AJ36: 119.1 | AK36: 76.9 | AL36: 111 | AM36: =87.3+149.7 -> 237 | AN36: 0 | AO36: 1842.2 | AP36: 7.9 | AQ36: 0 | AR36: 306.2 | AS36: 161.7 | AT36: 84.7 | AU36: 1251 | AV36: 4880.9 | AW36: -352.5 | AX36: =SUM(E36:AQ36) -> 10348
A37: =INDEX('OECD Crosswalk'!$C$2:$C$90,MATCH('OECD Data IO Table - Total (USD'!D37,'OECD Crosswalk'!$A$2:$A$90,0),1) -> 0 | B37: =INDEX('OECD Crosswalk'!$B$2:$B$90,MATCH('OECD Data IO Table - Total (USD'!D37,'OECD Crosswalk'!$A$2:$A$90,0),1) -> nonenergy industries | D37: TTL_62T63: IT and other information services | E37: 0.4 | F37: 0 | G37: 0 | H37: 0.1 | I37: 35.2 | J37: 12.2 | K37: 4.7 | L37: 26.1 | M37: 0 | N37: =0.3+0.2 -> 0.5 | O37: 0 | P37: 0.2 | Q37: 2.6 | R37: 0.2 | S37: 0.5 | T37: 0.7 | U37: 0.3 | V37: 0.4 | W37: 0.2 | X37: 0.1 | Y37: =8.3+10.2 -> 18.5 | Z37: 24 | AA37: 567.6 | AB37: =43.7+37.6+70+84.4+37.7 -> 273.4 | AC37: 34.8 | AD37: 42.4 | AE37: 217.3 | AF37: 25.1 | AG37: 966.5 | AH37: 233.6 | AI37: =24.4+17.6 -> 42 | AJ37: 79.8 | AK37: 42 | AL37: 35.1 | AM37: =23.9+34.1 -> 58 | AN37: 0 | AO37: 98.2 | AP37: 0 | AQ37: 0.1 | AR37: 408.3 | AS37: 70.1 | AT37: 1.9 | AU37: 15.6 | AV37: 2128.6 | AW37: -921.1 | AX37: =SUM(E37:AQ37) -> 2842.8
A38: =INDEX('OECD Crosswalk'!$C$2:$C$90,MATCH('OECD Data IO Table - Total (USD'!D38,'OECD Crosswalk'!$A$2:$A$90,0),1) -> 0 | B38: =INDEX('OECD Crosswalk'!$B$2:$B$90,MATCH('OECD Data IO Table - Total (USD'!D38,'OECD Crosswalk'!$A$2:$A$90,0),1) -> nonenergy industries | D38: TTL_64T66: Financial and insurance activities | E38: =1.1+0.1 -> 1.2 | F38: 0 | G38: 0 | H38: 0.1 | I38: 421.4 | J38: 108.9 | K38: 45.3 | L38: 350.3 | M38: 0.4 | N38: =1.1+0.6 -> 1.7 | O38: 0 | P38: 1.3 | Q38: 12 | R38: 1.2 | S38: 1 | T38: 2 | U38: 1.2 | V38: 0.8 | W38: 0.3 | X38: 0.6 | Y38: =286.1+238.2 -> 524.3 | Z38: 253.9 | AA38: 6839.4 | AB38: =629.2+920.9+301+1126+208.2 -> 3185.3 | AC38: 434.6 | AD38: 258.3 | AE38: 654.5 | AF38: 66.3 | AG38: 25577.6 | AH38: 12634.4 | AI38: =355.7+731.7 -> 1087.4 | AJ38: 176.8 | AK38: 466.3 | AL38: 330.2 | AM38: =328.9+836.1 -> 1165 | AN38: 0 | AO38: 22484.8 | AP38: 0 | AQ38: 371.8 | AR38: 497.7 | AS38: 4729.6 | AT38: 70.5 | AU38: 1071.6 | AV38: 41690.4 | AW38: -2972.6 | AX38: =SUM(E38:AQ38) -> 77460.6
A39: =INDEX('OECD Crosswalk'!$C$2:$C$90,MATCH('OECD Data IO Table - Total (USD'!D39,'OECD Crosswalk'!$A$2:$A$90,0),1) -> 0 | B39: =INDEX('OECD Crosswalk'!$B$2:$B$90,MATCH('OECD Data IO Table - Total (USD'!D39,'OECD Crosswalk'!$A$2:$A$90,0),1) -> nonenergy industries | D39: TTL_68: Real estate activities | E39: =1.2+0.1 -> 1.3 | F39: 0 | G39: 0 | H39: 0.1 | I39: 90.6 | J39: 44 | K39: 13.3 | L39: 76 | M39: 0.1 | N39: =0.2+0.1 -> 0.3 | O39: 0 | P39: 0.6 | Q39: 4.2 | R39: 0.6 | S39: 0.7 | T39: 1.2 | U39: 0.8 | V39: 0.6 | W39: 0.2 | X39: 0.4 | Y39: =95.1+305.7 -> 400.8 | Z39: 185.2 | AA39: 6898.8 | AB39: =278.5+170+219.5+2384+104.5 -> 3156.5 | AC39: 1391.8 | AD39: 403 | AE39: 392.3 | AF39: 58.3 | AG39: 4381.8 | AH39: 4338.3 | AI39: =281.5+509.8 -> 791.3 | AJ39: 77.7 | AK39: 303.2 | AL39: 524.7 | AM39: =616.5+1577.2 -> 2193.7 | AN39: 0 | AO39: 45769.3 | AP39: 0 | AQ39: 0.1 | AR39: 6134.7 | AS39: 4.7 | AT39: 229.3 | AU39: 3510.3 | AV39: 41.9 | AW39: -395.1 | AX39: =SUM(E39:AQ39) -> 71501.8
A40: =INDEX('OECD Crosswalk'!$C$2:$C$90,MATCH('OECD Data IO Table - Total (USD'!D40,'OECD Crosswalk'!$A$2:$A$90,0),1) -> 0 | B40: =INDEX('OECD Crosswalk'!$B$2:$B$90,MATCH('OECD Data IO Table - Total (USD'!D40,'OECD Crosswalk'!$A$2:$A$90,0),1) -> nonenergy industries | D40: TTL_69T82: Other business sector services | E40: =3.1+0.3+1.1+0.1 -> 4.6 | F40: 0 | G40: 0 | H40: =4.6+1.4 -> 6 | I40: =207.4+63.2 -> 270.6 | J40: =58.1+17.2 -> 75.3 | K40: =36.2+13.2 -> 49.4 | L40: =183.2+59.5 -> 242.7 | M40: =0.2+0.1 -> 0.3 | N40: =1+1.2+0.3+0.2 -> 2.7 | O40: 0 | P40: =0.6+0.2 -> 0.8 | Q40: =4.4+1.9 -> 6.3 | R40: =0.5+0.2 -> 0.7 | S40: =1.4+0.3 -> 1.7 | T40: =2.7+0.6 -> 3.3 | U40: =1.7+0.4 -> 2.1 | V40: =1.8+0.4 -> 2.2 | W40: =0.6+0.1 -> 0.7 | X40: =1.1+0.8 -> 1.9 | Y40: =45.7+82.8+14.6+37.6 -> 180.7 | Z40: =238.6+62 -> 300.6 | AA40: =3920.9+1506.9 -> 5427.8 | AB40: =220.2+208.5+279.9+399.6+112.8+167.2+212+252.5+245.6+113.4 -> 2211.7 | AC40: =210.5+86.1 -> 296.6 | AD40: =169.2+122.1 -> 291.3 | AE40: =599.6+346.7 -> 946.3 | AF40: =46.3+16.6 -> 62.9 | AG40: =3109.4+1132.7 -> 4242.1 | AH40: =1710+694.3 -> 2404.3 | AI40: =488.7+96.2 -> 584.9 | AJ40: =409.8+124.8 -> 534.6 | AK40: =209.1+95.6 -> 304.7 | AL40: =301.4+152.1 -> 453.5 | AM40: =167.1+235+87.6+88 -> 577.7 | AN40: 0 | AO40: =525.5+187.8 -> 713.3 | AP40: =7.8 -> 7.8 | AQ40: =348.2+0.1 -> 348.3 | AR40: =2565+91 -> 2656 | AS40: =97.9+59.5 -> 157.4 | AT40: =32.9+73 -> 105.9 | AU40: =541.9+1088.8 -> 1630.7 | AV40: =2254.3+1482.5 -> 3736.8 | AW40: =-967+-91.6 -> -1058.6 | AX40: =SUM(E40:AQ40) -> 20560.4
A41: =INDEX('OECD Crosswalk'!$C$2:$C$90,MATCH('OECD Data IO Table - Total (USD'!D41,'OECD Crosswalk'!$A$2:$A$90,0),1) -> 0 | B41: =INDEX('OECD Crosswalk'!$B$2:$B$90,MATCH('OECD Data IO Table - Total (USD'!D41,'OECD Crosswalk'!$A$2:$A$90,0),1) -> government | D41: TTL_84: Public administration and defence; compulsory social security | E41: 0.1 | F41: 0 | G41: 0 | H41: 0.1 | I41: 14 | J41: 3.3 | K41: 2 | L41: 7.1 | M41: 0 | N41: =0.2+0.1 -> 0.3 | O41: 0 | P41: 0.1 | Q41: 2.1 | R41: 0.2 | S41: 0.2 | T41: 0.4 | U41: 0.2 | V41: 0.2 | W41: 0.1 | X41: 0.1 | Y41: =6.2+13.4 -> 19.6 | Z41: 67.7 | AA41: 297.9 | AB41: =25.8+40.5+196.3+101.2+14.3 -> 378.1 | AC41: 42.9 | AD41: 17.6 | AE41: 38.9 | AF41: 2.7 | AG41: 310.4 | AH41: 91 | AI41: =19.3+28.4 -> 47.7 | AJ41: 309.8 | AK41: 31.6 | AL41: 25.1 | AM41: =23.3+40.8 -> 64.1 | AN41: 0 | AO41: 2023.7 | AP41: 0 | AQ41: 21947.8 | AR41: 47.4 | AS41: 12 | AT41: 4.7 | AU41: 0 | AV41: 0 | AW41: -91.6 | AX41: =SUM(E41:AQ41) -> 25747.1
A42: =INDEX('OECD Crosswalk'!$C$2:$C$90,MATCH('OECD Data IO Table - Total (USD'!D42,'OECD Crosswalk'!$A$2:$A$90,0),1) -> 0 | B42: =INDEX('OECD Crosswalk'!$B$2:$B$90,MATCH('OECD Data IO Table - Total (USD'!D42,'OECD Crosswalk'!$A$2:$A$90,0),1) -> nonenergy industries | D42: TTL_85: Education | E42: 0.5 | F42: 0 | G42: 0 | H42: 0 | I42: 38.1 | J42: 9.3 | K42: 6.1 | L42: 34 | M42: 0 | N42: =0.1+0.1 -> 0.2 | O42: 0 | P42: 0.2 | Q42: 1.2 | R42: 0.1 | S42: 0.1 | T42: 0.2 | U42: 0.2 | V42: 0.2 | W42: 0.1 | X42: 0.1 | Y42: =12.8+20.4 -> 33.2 | Z42: 45.6 | AA42: 627.7 | AB42: =57.7+62.4+67.9+123.9+31.9 -> 343.8 | AC42: 46.8 | AD42: 30.5 | AE42: 128.9 | AF42: 13.9 | AG42: 711.7 | AH42: 301.3 | AI42: =57.6+63.5 -> 121.1 | AJ42: 163.3 | AK42: 469.4 | AL42: 89.2 | AM42: =34.4+87.7 -> 122.1 | AN42: 0 | AO42: 2924.9 | AP42: 9128.7 | AQ42: 2620.8 | AR42: 233 | AS42: 5.3 | AT42: 135.5 | AU42: 1707.7 | AV42: 0 | AW42: -157 | AX42: =SUM(E42:AQ42) -> 18013.5
A43: =INDEX('OECD Crosswalk'!$C$2:$C$90,MATCH('OECD Data IO Table - Total (USD'!D43,'OECD Crosswalk'!$A$2:$A$90,0),1) -> 0 | B43: =INDEX('OECD Crosswalk'!$B$2:$B$90,MATCH('OECD Data IO Table - Total (USD'!D43,'OECD Crosswalk'!$A$2:$A$90,0),1) -> nonenergy industries | D43: TTL_86T88: Human health and social work | E43: 0 | F43: 0 | G43: 0 | H43: 0.1 | I43: 8.4 | J43: 4.2 | K43: 1 | L43: 4.1 | M43: 0.1 | N43: =0.2+0.1 -> 0.3 | O43: 0 | P43: 0.1 | Q43: 0.8 | R43: 0.1 | S43: 0.2 | T43: 0.3 | U43: 0.1 | V43: 0.1 | W43: 0 | X43: 0 | Y43: =4.1+5.7 -> 9.8 | Z43: 10.2 | AA43: 141.1 | AB43: =17+48.8+8+41.2+8.8 -> 123.8 | AC43: 17.1 | AD43: 5 | AE43: 17.1 | AF43: 1.2 | AG43: 218.2 | AH43: 86.8 | AI43: =11.2+18.8 -> 30 | AJ43: 9 | AK43: 35.4 | AL43: 258.2 | AM43: =15.8+25.5 -> 41.3 | AN43: 0 | AO43: 6137.2 | AP43: 1571 | AQ43: 10648 | AR43: 29.8 | AS43: 17.1 | AT43: 58.1 | AU43: 843.7 | AV43: 0 | AW43: -117.5 | AX43: =SUM(E43:AQ43) -> 19380.3
A44: =INDEX('OECD Crosswalk'!$C$2:$C$90,MATCH('OECD Data IO Table - Total (USD'!D44,'OECD Crosswalk'!$A$2:$A$90,0),1) -> 0 | B44: =INDEX('OECD Crosswalk'!$B$2:$B$90,MATCH('OECD Data IO Table - Total (USD'!D44,'OECD Crosswalk'!$A$2:$A$90,0),1) -> nonenergy industries | D44: TTL_90T96: Arts, entertainment, recreation and other service activities | E44: =0.5+0.1+3.5+0.5 -> 4.6 | F44: 0 | G44: 0 | H44: =0.2 -> 0.2 | I44: =18.8+146.4 -> 165.2 | J44: =3+53.2 -> 56.2 | K44: =1.2+16.1 -> 17.3 | L44: =12.6+96 -> 108.6 | M44: =1 -> 1 | N44: =0.1+0.1+3+2.3 -> 5.5 | O44: 0 | P44: =2.6 -> 2.6 | Q44: =0.4+19.2 -> 19.6 | R44: =2.5 -> 2.5 | S44: =0.1+4 -> 4.1 | T44: =0.1+6.7 -> 6.8 | U44: =0.1+3.8 -> 3.9 | V44: =0.1+9.9 -> 10 | W44: 3.4 | X44: 0.5 | Y44: =7.3+11.1+65.7+72.1 -> 156.2 | Z44: =14.6+121.8 -> 136.4 | AA44: =250.6+1184 -> 1434.6 | AB44: =24.2502+42.6+58.3+28.2+126.7+137.8+220.3+176.9+78 -> 893.0502 | AC44: =22.7+208.2 -> 230.9 | AD44: =169.2+122.1 -> 291.3 | AE44: =73.2+175.1 -> 248.3 | AF44: =3.3+14 -> 17.3 | AG44: =499.7+1244 -> 1743.7 | AH44: =360.9+773.1 -> 1134 | AI44: =43.7+57.6+90.1+133.1 -> 324.5 | AJ44: =32.5+87.7 -> 120.2 | AK44: =45.2+80.8 -> 126 | AL44: =36.9+163.7 -> 200.6 | AM44: =766.6+114.1+163.2+499.5 -> 1543.4 | AN44: 0 | AO44: =1641.3+4507.2 -> 6148.5 | AP44: =62.3+346 -> 408.3 | AQ44: 0 | AR44: =167+611.6 -> 778.6 | AS44: =-0.9+19.3 -> 18.4 | AT44: =132.4+78.3 -> 210.7 | AU44: =2089.6+1116.4 -> 3206 | AV44: 318 | AW44: =-337.8+-150.2 -> -488 | AX44: =SUM(E44:AQ44) -> 15569.25
A45: =INDEX('OECD Crosswalk'!$C$2:$C$90,MATCH('OECD Data IO Table - Total (USD'!D45,'OECD Crosswalk'!$A$2:$A$90,0),1) -> 0 | B45: =INDEX('OECD Crosswalk'!$B$2:$B$90,MATCH('OECD Data IO Table - Total (USD'!D45,'OECD Crosswalk'!$A$2:$A$90,0),1) -> labor and consumers | D45: TTL_97T98: Private households with employed persons | E45: 0 | F45: 0 | G45: 0 | H45: 0 | I45: 0 | J45: 0 | K45: 0 | L45: 0 | M45: 0 | N45: 0 | O45: 0 | P45: 0 | Q45: 0 | R45: 0 | S45: 0 | T45: 0 | U45: 0 | V45: 0 | W45: 0 | X45: 0 | Y45: 0 | Z45: 0 | AA45: 0 | AB45: 0 | AC45: 0 | AD45: 0 | AE45: 0 | AF45: 0 | AG45: 0 | AH45: 0 | AI45: 0 | AJ45: 0 | AK45: 0 | AL45: 0 | AM45: 0 | AN45: 0 | AO45: 4665 | AP45: 0 | AQ45: 0 | AR45: 0 | AS45: 0 | AT45: 0 | AU45: 0 | AV45: 0 | AW45: 0 | AX45: =SUM(E45:AQ45) -> 4665
A46: =INDEX('OECD Crosswalk'!$C$2:$C$90,MATCH('OECD Data IO Table - Total (USD'!D46,'OECD Crosswalk'!$A$2:$A$90,0),1) -> 0 | B46: =INDEX('OECD Crosswalk'!$B$2:$B$90,MATCH('OECD Data IO Table - Total (USD'!D46,'OECD Crosswalk'!$A$2:$A$90,0),1) -> government | D46: TXS_IMP_FNL: Taxes less subsidies on intermediate and final products (paid in foreign countries) | E46: 0 | F46: 0 | G46: 0 | H46: 0 | I46: 0 | J46: 0 | K46: 0 | L46: 0 | M46: 0 | N46: 0 | O46: 0 | P46: 0 | Q46: 0 | R46: 0 | S46: 0 | T46: 0 | U46: 0 | V46: 0 | W46: 0 | X46: 0 | Y46: 0 | Z46: 0 | AA46: 0 | AB46: =-0.1 -> -0.1 | AC46: -0.1 | AD46: 0 | AE46: 0 | AF46: 0 | AG46: 0 | AH46: 0 | AI46: 0 | AJ46: 0 | AK46: 0 | AL46: 0 | AM46: 0 | AN46: 0 | AO46: 0 | AP46: 0 | AQ46: 0 | AR46: 0 | AS46: 0 | AT46: 57.3 | AU46: 0 | AV46: 0 | AW46: -57.1 | AX46: =SUM(E46:AQ46) -> -0.2
A47: =INDEX('OECD Crosswalk'!$C$2:$C$90,MATCH('OECD Data IO Table - Total (USD'!D47,'OECD Crosswalk'!$A$2:$A$90,0),1) -> 0 | B47: =INDEX('OECD Crosswalk'!$B$2:$B$90,MATCH('OECD Data IO Table - Total (USD'!D47,'OECD Crosswalk'!$A$2:$A$90,0),1) -> government | D47: TXS_INT_FNL: Taxes less subsidies on intermediate and final products (paid in domestic agencies, includes duty on imported products) | E47: =2.8+0.2 -> 3 | F47: 0 | G47: 0 | H47: 35.8 | I47: 64.3 | J47: 31.4 | K47: 7 | L47: 47.9 | M47: 17.5 | N47: =30.7+8.5 -> 39.2 | O47: 0 | P47: 20 | Q47: 162.7 | R47: 14.4 | S47: 34.1 | T47: 27.1 | U47: 12.1 | V47: 26.6 | W47: 4.8 | X47: 13.7 | Y47: =55.6+61.1 -> 116.7 | Z47: 231.5 | AA47: 2799.5 | AB47: =104.9+350.7+239.3+392.1+67.7 -> 1154.7 | AC47: 117.8 | AD47: 84.1 | AE47: 263 | AF47: 10.4 | AG47: 1344.4 | AH47: 635.3 | AI47: =51.8+99.6 -> 151.4 | AJ47: 123.1 | AK47: 94.8 | AL47: 77.1 | AM47: =113.3+162.8 -> 276.1 | AN47: 0 | AO47: 3739.1 | AP47: 29.6 | AQ47: -29.4 | AR47: 1750.4 | AS47: 0 | AT47: 0 | AU47: -42.9 | AV47: 0 | AW47: 0 | AX47: =SUM(E47:AQ47) -> 11780.8
A48: =INDEX('OECD Crosswalk'!$C$2:$C$90,MATCH('OECD Data IO Table - Total (USD'!D48,'OECD Crosswalk'!$A$2:$A$90,0),1) -> 0 | B48: =INDEX('OECD Crosswalk'!$B$2:$B$90,MATCH('OECD Data IO Table - Total (USD'!D48,'OECD Crosswalk'!$A$2:$A$90,0),1) -> total | D48: TTL_INT_FNL: Total intermediate consumption at purchasers’ prices | E48: =269.5+34.7 -> 304.2 | F48: 0 | G48: 0 | H48: 8028.3 | I48: 6194.7 | J48: 2727.5 | K48: 532.4 | L48: 4555.6 | M48: 377.9 | N48: =1159.8+452 -> 1611.8 | O48: 0 | P48: 1228.3 | Q48: 11480.1 | R48: 1130.6 | S48: 1446.5 | T48: 2665.6 | U48: 1189.9 | V48: 1424.9 | W48: 499 | X48: 715.8 | Y48: =2971.3+3200.1 -> 6171.4 | Z48: 12195.5 | AA48: 104745.4 | AB48: =5658.2+16315.8+12040.1+17264.4+4079.3 -> 55357.8 | AC48: 8861.7 | AD48: 3649.8 | AE48: 10369.2 | AF48: 464.7 | AG48: 53727.3 | AH48: 28542.2 | AI48: =2707.8+4500.8 -> 7208.6 | AJ48: 4524.5 | AK48: 4403.8 | AL48: 5448 | AM48: =4177.3+7398.2 -> 11575.5 | AN48: 0 | AO48: 230751.9 | AP48: 11199.9 | AQ48: 35909.8 | AR48: 77220.9 | AS48: 61910.2 | AT48: 3576.1 | AU48: 37530.2 | AV48: 139110.7 | AW48: -235559.1 | AX48: =SUM(E48:AQ48) -> 641220.1
A49: =INDEX('OECD Crosswalk'!$C$2:$C$90,MATCH('OECD Data IO Table - Total (USD'!D49,'OECD Crosswalk'!$A$2:$A$90,0),1) -> 0 | B49: =INDEX('OECD Crosswalk'!$B$2:$B$90,MATCH('OECD Data IO Table - Total (USD'!D49,'OECD Crosswalk'!$A$2:$A$90,0),1) -> value add | D49: VALU: Value added at basic prices | E49: =179.8+30.3 -> 210.1 | F49: 0 | G49: 0 | H49: 76.3 | I49: 2573.5 | J49: 265.2 | K49: 213.6 | L49: 133.1 | M49: 35.3 | N49: =38+22.9 -> 60.9 | O49: 0 | P49: 50 | Q49: 28.2 | R49: 75.6 | S49: 51.7 | T49: 45.3 | U49: 47.2 | V49: 43.4 | W49: 20.4 | X49: 92 | Y49: =2341.9+2023.8 -> 4365.7 | Z49: 15493.8 | AA49: 73962.9 | AB49: =6622.9+2366.9+9657.3+606.9+1122.7 -> 20376.7 | AC49: 11770.9 | AD49: 2182.6 | AE49: 6311.7 | AF49: 4091.6 | AG49: 68821.6 | AH49: 52485.6 | AI49: =16474.7+3558.1 -> 20032.8 | AJ49: 21195.1 | AK49: 15533.9 | AL49: 14763.2 | AM49: =2644.6+5442.6 -> 8087.2 | AN49: 4665 | AO49: 0 | AP49: 0 | AQ49: 0 | AR49: 0 | AS49: 0 | AT49: 0 | AU49: 0 | AV49: 0 | AW49: 0 | AX49: =SUM(E49:AQ49) -> 348162.1
A50: =INDEX('OECD Crosswalk'!$C$2:$C$90,MATCH('OECD Data IO Table - Total (USD'!D50,'OECD Crosswalk'!$A$2:$A$90,0),1) -> 0 | B50: =INDEX('OECD Crosswalk'!$B$2:$B$90,MATCH('OECD Data IO Table - Total (USD'!D50,'OECD Crosswalk'!$A$2:$A$90,0),1) -> output | D50: OUTPUT: Output at basic prices | E50: =449.3+65 -> 514.3 | F50: 0 | G50: 0 | H50: 8104.5 | I50: 8768.1 | J50: 2992.7 | K50: 746 | L50: 4688.8 | M50: 413.2 | N50: =1197+474.8 -> 1671.8 | O50: 0 | P50: 1278.3 | Q50: 11508.3 | R50: 1206.2 | S50: 1498.2 | T50: 2710.9 | U50: 1237.1 | V50: 1468.2 | W50: 519.5 | X50: 807.8 | Y50: =5313.3+5223.9 -> 10537.2 | Z50: 27689.4 | AA50: 178708.3 | AB50: =12281.1+18682.6+21697.4+17871.3+5202 -> 75734.4 | AC50: 20632.5 | AD50: 5832.4 | AE50: 16680.9 | AF50: 4556.3 | AG50: 122548.9 | AH50: 81027.8 | AI50: =19182.5+8058.9 -> 27241.4 | AJ50: 25719.6 | AK50: 19937.7 | AL50: 20211.2 | AM50: =6821.9+12840.8 -> 19662.7 | AN50: 4665 | AO50: 0 | AP50: 0 | AQ50: 0 | AR50: 0 | AS50: 0 | AT50: 0 | AU50: 0 | AV50: 0 | AW50: 0 | AX50: =SUM(E50:AQ50) -> 711519.6
D51: Data extracted on 4 Sept 2023 10:13 UTC (GMT) from OECD.Stat | AX51: =SUM(E51:AQ51) -> 0

Sheet OECD Data IO Table - Value HKD
E1: =DotStatQuery(F1) -> #NAME? | F1: Sorry, the query is too large to fit into the Excel cell. You will not be able to update your table with the .Stat Populator.
D2: To Sector | E2: =INDEX('OECD Crosswalk'!$B$2:$B$90,MATCH('OECD Data IO Table - Value HKD'!E8,'OECD Crosswalk'!$A$2:$A$90,0),1) -> nonenergy industries | F2: =INDEX('OECD Crosswalk'!$B$2:$B$90,MATCH('OECD Data IO Table - Value HKD'!F8,'OECD Crosswalk'!$A$2:$A$90,0),1) -> natural gas and petroleum suppliers | G2: =INDEX('OECD Crosswalk'!$B$2:$B$90,MATCH('OECD Data IO Table - Value HKD'!G8,'OECD Crosswalk'!$A$2:$A$90,0),1) -> nonenergy industries | H2: =INDEX('OECD Crosswalk'!$B$2:$B$90,MATCH('OECD Data IO Table - Value HKD'!H8,'OECD Crosswalk'!$A$2:$A$90,0),1) -> nonenergy industries | I2: =INDEX('OECD Crosswalk'!$B$2:$B$90,MATCH('OECD Data IO Table - Value HKD'!I8,'OECD Crosswalk'!$A$2:$A$90,0),1) -> nonenergy industries | J2: =INDEX('OECD Crosswalk'!$B$2:$B$90,MATCH('OECD Data IO Table - Value HKD'!J8,'OECD Crosswalk'!$A$2:$A$90,0),1) -> nonenergy industries | K2: =INDEX('OECD Crosswalk'!$B$2:$B$90,MATCH('OECD Data IO Table - Value HKD'!K8,'OECD Crosswalk'!$A$2:$A$90,0),1) -> nonenergy industries | L2: =INDEX('OECD Crosswalk'!$B$2:$B$90,MATCH('OECD Data IO Table - Value HKD'!L8,'OECD Crosswalk'!$A$2:$A$90,0),1) -> nonenergy industries | ... AN2: =INDEX('OECD Crosswalk'!$B$2:$B$90,MATCH('OECD Data IO Table - Value HKD'!AN8,'OECD Crosswalk'!$A$2:$A$90,0),1) -> labor and consumers
D3: From Sector | E3: =INDEX('OECD Crosswalk'!$C$2:$C$90,MATCH('OECD Data IO Table - Value HKD'!E8,'OECD Crosswalk'!$A$2:$A$90,0),1) -> agriculture | F3: =INDEX('OECD Crosswalk'!$C$2:$C$90,MATCH('OECD Data IO Table - Value HKD'!F8,'OECD Crosswalk'!$A$2:$A$90,0),1) -> other industries | G3: =INDEX('OECD Crosswalk'!$C$2:$C$90,MATCH('OECD Data IO Table - Value HKD'!G8,'OECD Crosswalk'!$A$2:$A$90,0),1) -> other industries | H3: =INDEX('OECD Crosswalk'!$C$2:$C$90,MATCH('OECD Data IO Table - Value HKD'!H8,'OECD Crosswalk'!$A$2:$A$90,0),1) -> other industries | I3: =INDEX('OECD Crosswalk'!$C$2:$C$90,MATCH('OECD Data IO Table - Value HKD'!I8,'OECD Crosswalk'!$A$2:$A$90,0),1) -> other industries | J3: =INDEX('OECD Crosswalk'!$C$2:$C$90,MATCH('OECD Data IO Table - Value HKD'!J8,'OECD Crosswalk'!$A$2:$A$90,0),1) -> other industries | K3: =INDEX('OECD Crosswalk'!$C$2:$C$90,MATCH('OECD Data IO Table - Value HKD'!K8,'OECD Crosswalk'!$A$2:$A$90,0),1) -> other industries | L3: =INDEX('OECD Crosswalk'!$C$2:$C$90,MATCH('OECD Data IO Table - Value HKD'!L8,'OECD Crosswalk'!$A$2:$A$90,0),1) -> other industries | ... AN3: =INDEX('OECD Crosswalk'!$C$2:$C$90,MATCH('OECD Data IO Table - Value HKD'!AN8,'OECD Crosswalk'!$A$2:$A$90,0),1) -> 0
D4: Variable | E4: VAL: Value added
D5: Country | E5: HKG: Hong Kong, China
D6: Time | E6: 2021
D7: Unit | E7: HK Dollar, Millions
D8: To: (sector in column) | E8: D01T03: Agriculture, forestry and fishing | F8: D05T06: Mining and extraction of energy producing products | G8: D07T08: Mining and quarrying of non-energy producing products | H8: D09: Mining support service activities | I8: D10T12: Food products, beverages and tobacco | J8: D13T15: Textiles, wearing apparel, leather and related products | K8: D16: Wood and products of wood and cork | L8: D17T18: Paper products and printing | M8: D19: Coke and refined petroleum products | N8: D20T21: Chemicals and pharmaceutical products | O8: D22: Rubber and plastic products | P8: D23: Other non-metallic mineral products | Q8: D24: Basic metals | R8: D25: Fabricated metal products | S8: D26: Computer, electronic and optical products | T8: D27: Electrical equipment | U8: D28: Machinery and equipment, nec | V8: D29: Motor vehicles, trailers and semi-trailers | W8: D30: Other transport equipment | X8: D31T33: Other manufacturing; repair and installation of machinery and equipment | Y8: D35T39: Electricity, gas, water supply, sewerage, waste and remediation services | Z8: D41T43: Construction | AA8: D45T47: Wholesale and retail trade; repair of motor vehicles | AB8: D49T53: Transportation and storage | AC8: D55T56: Accomodation and food services | AD8: D58T60: Publishing, audiovisual and broadcasting activities | AE8: D61: Telecommunications | AF8: D62T63: IT and other information services | AG8: D64T66: Financial and insurance activities | AH8: D68: Real estate activities | AI8: D69T82: Other business sector services | AJ8: D84: Public admin. and defence; compulsory social security | AK8: D85: Education | AL8: D86T88: Human health and social work | AM8: D90T96: Arts, entertainment, recreation and other service activities | AN8: D97T98: Private households with employed persons
C9: To Sector | D9: From: (sector in row)
B10: CPI | C10: ='OECD Crosswalk'!E3 -> labor and consumers | D10: LABR: Compensation of employees | E10: =(485.39*$E$15)*7.8 -> 3609.1241 | F10: =5.207*E15*7.8 -> 38.716721 | G10: =35.95*E15*7.8 -> 267.30673 | H10: =2.604*E15*7.8 -> 19.362079 | I10: =7930.575*E15*7.8 -> 58967.902 | J10: =3867.448*E15*7.8 -> 28756.464 | K10: =14.159*E15*7.8 -> 105.27944 | L10: =327.372*E15*7.8 -> 2434.1791 | M10: =184.586*E15*7.8 -> 1372.4918 | N10: =759.663*E15*7.8 -> 5648.4849 | O10: =388.617*E15*7.8 -> 2889.5672 | P10: =139.822*E15*7.8 -> 1039.6484 | Q10: =145.694*E15*7.8 -> 1083.3098 | R10: =237.032*E15*7.8 -> 1762.4548 | S10: =1271.075*E15*7.8 -> 9451.096 | T10: =1745.943*E15*7.8 -> 12981.984 | U10: =447.443*E15*7.8 -> 3326.9687 | V10: =1434.696*E15*7.8 -> 10667.702 | W10: =310.318*E15*7.8 -> 2307.3738 | X10: =1121.006*E15*7.8 -> 8335.2558 | Y10: =1197.347*E15*7.8 -> 8902.8904 | Z10: =7616.261*E15*7.8 -> 56630.815 | AA10: =26217.189*E15*7.8 -> 194938.28 | AB10: =10211.047*E15*7.8 -> 75924.383 | AC10: =7168.008*E15*7.8 -> 53297.824 | AD10: =1892.131*E15*7.8 -> 14068.967 | AE10: =1047.095*E15*7.8 -> 7785.6896 | AF10: =2436.061*E15*7.8 -> 18113.366 | AG10: =20356.82*E15*7.8 -> 151363.42 | AH10: =2166.938*E15*7.8 -> 16112.298 | AI10: =13370.42*E15*7.8 -> 99415.945 | AJ10: =11151.01*E15*7.8 -> 82913.491 | AK10: =10020.707*E15*7.8 -> 74509.107 | AL10: =6593.354*E15*7.8 -> 49024.976 | AM10: =5936.281*E15*7.8 -> 44139.301 | AN10: =32915.5*E15*7.8 -> 244743.66
B11: GDP | C11: ='OECD Crosswalk'!E1 -> government | D11: OTXS: Other taxes less subsidies on production | E11: =8.906*E16*7.8 -> 68.926472 | F11: =1.544*E16*7.8 -> 11.949525 | G11: =6.101*E16*7.8 -> 47.217652 | H11: =0.323*E16*7.8 -> 2.4998035 | I11: =140.56*E16*7.8 -> 1087.8402 | J11: =70.66*E16*7.8 -> 546.86105 | K11: =0.825*E16*7.8 -> 6.3849471 | L11: =7.965*E16*7.8 -> 61.643762 | M11: =102.816*E16*7.8 -> 795.72694 | N11: =47.888*E16*7.8 -> 370.62103 | O11: =20.416*E16*7.8 -> 158.00616 | P11: =9.577*E16*7.8 -> 74.119562 | Q11: =2.798*E16*7.8 -> 21.654645 | R11: =14.054*E16*7.8 -> 108.76854 | S11: =65.644*E16*7.8 -> 508.04057 | T11: =105.603*E16*7.8 -> 817.29645 | U11: =24.244*E16*7.8 -> 187.63231 | V11: =105.421*E16*7.8 -> 815.88789 | W11: =12.201*E16*7.8 -> 94.427564 | X11: =73.612*E16*7.8 -> 569.70755 | Y11: =56.642*E16*7.8 -> 438.37112 | Z11: =100.948*E16*7.8 -> 781.26987 | AA11: =816.859*E16*7.8 -> 6321.9413 | AB11: =543.644*E16*7.8 -> 4207.4402 | AC11: =194.749*E16*7.8 -> 1507.2268 | AD11: =104.108*E16*7.8 -> 805.72615 | AE11: =107.92*E16*7.8 -> 835.22848 | AF11: =93.092*E16*7.8 -> 720.4697 | AG11: =253.117*E16*7.8 -> 1958.956 | AH11: =823.642*E16*7.8 -> 6374.4371 | AI11: =183.502*E16*7.8 -> 1420.1825 | AJ11: =7.697*E16*7.8 -> 59.569622 | AK11: =24.492*E16*7.8 -> 189.55167 | AL11: =29.505*E16*7.8 -> 228.34893 | AM11: =99.423*E16*7.8 -> 769.46739 | AN11: =0*E16*7.8 -> 0
B12: GDP | D12: GOPS: Gross operating surplus and mixed income | E12: =826.404*E16*7.8 -> 6395.8132 | F12: =15.249*E16*7.8 -> 118.01704 | G12: =66.649*E16*7.8 -> 515.8186 | H12: =2.573*E16*7.8 -> 19.913296 | I12: =4261.665*E16*7.8 -> 32982.431 | J12: =203.292*E16*7.8 -> 1573.3438 | K12: =11.116*E16*7.8 -> 86.030391 | L12: =161.363*E16*7.8 -> 1248.8415 | M12: =584.797*E16*7.8 -> 4525.9369 | N12: =988.148*E16*7.8 -> 7647.6033 | O12: =242.867*E16*7.8 -> 1879.6278 | P12: =126.402*E16*7.8 -> 978.26677 | Q12: =87.508*E16*7.8 -> 677.25328 | R12: =116.814*E16*7.8 -> 904.06208 | S12: =1146.081*E16*7.8 -> 8869.8989 | T12: =990.154*E16*7.8 -> 7663.1284 | U12: =274.013*E16*7.8 -> 2120.677 | V12: =927.583*E16*7.8 -> 7178.8708 | W12: =134.082*E16*7.8 -> 1037.7048 | X12: =766.082*E16*7.8 -> 5928.9613 | Y12: =5118.112*E16*7.8 -> 39610.757 | Z12: =1743.891*E16*7.8 -> 13496.548 | AA12: =36269.952*E16*7.8 -> 280705.12 | AB12: =8819.309*E16*7.8 -> 68255.542 | AC12: =3493.943*E16*7.8 -> 27040.777 | AD12: =1460.761*E16*7.8 -> 11305.311 | AE12: =2269.685*E16*7.8 -> 17565.841 | AF12: =1213.348*E16*7.8 -> 9390.5004 | AG12: =11415.863*E16*7.8 -> 88351.13 | AH12: =20694.82*E16*7.8 -> 160164.04 | AI12: =2676.278*E16*7.8 -> 20712.598 | AJ12: =3351.593*E16*7.8 -> 25939.084 | AK12: =1172.201*E16*7.8 -> 9072.0502 | AL12: =1815.241*E16*7.8 -> 14048.749 | AM12: =1129.596*E16*7.8 -> 8742.3161 | AN12: =0*E16*7.8 -> 0
D13: Data extracted on 05 Oct 2019 17:23 UTC (GMT) from OECD.Stat
D15: CPI change (2018-2021) | E15: =102/107 -> 0.95327103
D16: GDP Change (2018-2021) | E16: =2845317/2867622 -> 0.99222178
D18: WRI (14/11/21) | E18: change the currency to HKD and then change it to year using GDP
E19: using a CPI (Consumer Price Index) | F19: more on the price rather than the product
E20: use the exchange rate to change to HKD GDP and then CPI to change 2018 datasheet to 2021
E21: GDP becomes a multiplier to calculate the differences
E24: USD--> HKD --->
E25: * CPI = value to input above

Sheet OECD Data IO Table - Value USD
E1: =DotStatQuery(F1) -> #NAME? | F1: Sorry, the query is too large to fit into the Excel cell. You will not be able to update your table with the .Stat Populator.
D2: To Sector | E2: =INDEX('OECD Crosswalk'!$B$2:$B$90,MATCH('OECD Data IO Table - Value USD'!E8,'OECD Crosswalk'!$A$2:$A$90,0),1) -> nonenergy industries | F2: =INDEX('OECD Crosswalk'!$B$2:$B$90,MATCH('OECD Data IO Table - Value USD'!F8,'OECD Crosswalk'!$A$2:$A$90,0),1) -> natural gas and petroleum suppliers | G2: =INDEX('OECD Crosswalk'!$B$2:$B$90,MATCH('OECD Data IO Table - Value USD'!G8,'OECD Crosswalk'!$A$2:$A$90,0),1) -> nonenergy industries | H2: =INDEX('OECD Crosswalk'!$B$2:$B$90,MATCH('OECD Data IO Table - Value USD'!H8,'OECD Crosswalk'!$A$2:$A$90,0),1) -> nonenergy industries | I2: =INDEX('OECD Crosswalk'!$B$2:$B$90,MATCH('OECD Data IO Table - Value USD'!I8,'OECD Crosswalk'!$A$2:$A$90,0),1) -> nonenergy industries | J2: =INDEX('OECD Crosswalk'!$B$2:$B$90,MATCH('OECD Data IO Table - Value USD'!J8,'OECD Crosswalk'!$A$2:$A$90,0),1) -> nonenergy industries | K2: =INDEX('OECD Crosswalk'!$B$2:$B$90,MATCH('OECD Data IO Table - Value USD'!K8,'OECD Crosswalk'!$A$2:$A$90,0),1) -> nonenergy industries | L2: =INDEX('OECD Crosswalk'!$B$2:$B$90,MATCH('OECD Data IO Table - Value USD'!L8,'OECD Crosswalk'!$A$2:$A$90,0),1) -> nonenergy industries | ... AN2: =INDEX('OECD Crosswalk'!$B$2:$B$90,MATCH('OECD Data IO Table - Value USD'!AN8,'OECD Crosswalk'!$A$2:$A$90,0),1) -> labor and consumers
D3: From Sector | E3: =INDEX('OECD Crosswalk'!$C$2:$C$90,MATCH('OECD Data IO Table - Value USD'!E8,'OECD Crosswalk'!$A$2:$A$90,0),1) -> agriculture | F3: =INDEX('OECD Crosswalk'!$C$2:$C$90,MATCH('OECD Data IO Table - Value USD'!F8,'OECD Crosswalk'!$A$2:$A$90,0),1) -> other industries | G3: =INDEX('OECD Crosswalk'!$C$2:$C$90,MATCH('OECD Data IO Table - Value USD'!G8,'OECD Crosswalk'!$A$2:$A$90,0),1) -> other industries | H3: =INDEX('OECD Crosswalk'!$C$2:$C$90,MATCH('OECD Data IO Table - Value USD'!H8,'OECD Crosswalk'!$A$2:$A$90,0),1) -> other industries | I3: =INDEX('OECD Crosswalk'!$C$2:$C$90,MATCH('OECD Data IO Table - Value USD'!I8,'OECD Crosswalk'!$A$2:$A$90,0),1) -> other industries | J3: =INDEX('OECD Crosswalk'!$C$2:$C$90,MATCH('OECD Data IO Table - Value USD'!J8,'OECD Crosswalk'!$A$2:$A$90,0),1) -> other industries | K3: =INDEX('OECD Crosswalk'!$C$2:$C$90,MATCH('OECD Data IO Table - Value USD'!K8,'OECD Crosswalk'!$A$2:$A$90,0),1) -> other industries | L3: =INDEX('OECD Crosswalk'!$C$2:$C$90,MATCH('OECD Data IO Table - Value USD'!L8,'OECD Crosswalk'!$A$2:$A$90,0),1) -> other industries | ... AN3: =INDEX('OECD Crosswalk'!$C$2:$C$90,MATCH('OECD Data IO Table - Value USD'!AN8,'OECD Crosswalk'!$A$2:$A$90,0),1) -> 0
D4: Variable | E4: VAL: Value added
D5: Country | E5: HKG: Hong Kong, China
D6: Time | E6: 2021
D7: Unit | E7: US Dollar, Millions
D8: To: (sector in column) | E8: D01T03: Agriculture, forestry and fishing | F8: D05T06: Mining and extraction of energy producing products | G8: D07T08: Mining and quarrying of non-energy producing products | H8: D09: Mining support service activities | I8: D10T12: Food products, beverages and tobacco | J8: D13T15: Textiles, wearing apparel, leather and related products | K8: D16: Wood and products of wood and cork | L8: D17T18: Paper products and printing | M8: D19: Coke and refined petroleum products | N8: D20T21: Chemicals and pharmaceutical products | O8: D22: Rubber and plastic products | P8: D23: Other non-metallic mineral products | Q8: D24: Basic metals | R8: D25: Fabricated metal products | S8: D26: Computer, electronic and optical products | T8: D27: Electrical equipment | U8: D28: Machinery and equipment, nec | V8: D29: Motor vehicles, trailers and semi-trailers | W8: D30: Other transport equipment | X8: D31T33: Other manufacturing; repair and installation of machinery and equipment | Y8: D35T39: Electricity, gas, water supply, sewerage, waste and remediation services | Z8: D41T43: Construction | AA8: D45T47: Wholesale and retail trade; repair of motor vehicles | AB8: D49T53: Transportation and storage | AC8: D55T56: Accomodation and food services | AD8: D58T60: Publishing, audiovisual and broadcasting activities | AE8: D61: Telecommunications | AF8: D62T63: IT and other information services | AG8: D64T66: Financial and insurance activities | AH8: D68: Real estate activities | AI8: D69T82: Other business sector services | AJ8: D84: Public admin. and defence; compulsory social security | AK8: D85: Education | AL8: D86T88: Human health and social work | AM8: D90T96: Arts, entertainment, recreation and other service activities | AN8: D97T98: Private households with employed persons
C9: To Sector | D9: From: (sector in row)
B10: CPI | C10: ='OECD Crosswalk'!E3 -> labor and consumers | D10: LABR: Compensation of employees | E10: =485.39*$E$15 -> 462.70822 | F10: =5.207*E15 -> 4.9636822 | G10: =35.95*E15 -> 34.270093 | H10: =2.604*E15 -> 2.4823178 | I10: =7930.575*E15 -> 7559.9874 | J10: =3867.448*E15 -> 3686.7261 | K10: =14.159*E15 -> 13.497364 | L10: =327.372*E15 -> 312.07424 | M10: =184.586*E15 -> 175.96049 | N10: =759.663*E15 -> 724.16473 | O10: =388.617*E15 -> 370.45733 | P10: =139.822*E15 -> 133.28826 | Q10: =145.694*E15 -> 138.88587 | R10: =237.032*E15 -> 225.95574 | S10: =1271.075*E15 -> 1211.679 | T10: =1745.943*E15 -> 1664.3569 | U10: =447.443*E15 -> 426.53445 | V10: =1434.696*E15 -> 1367.6541 | W10: =310.318*E15 -> 295.81716 | X10: =1121.006*E15 -> 1068.6225 | Y10: =1197.347*E15 -> 1141.3962 | Z10: =7616.261*E15 -> 7260.361 | AA10: =26217.189*E15 -> 24992.087 | AB10: =10211.047*E15 -> 9733.8953 | AC10: =7168.008*E15 -> 6833.0544 | AD10: =1892.131*E15 -> 1803.7137 | AE10: =1047.095*E15 -> 998.16533 | AF10: =2436.061*E15 -> 2322.2264 | AG10: =20356.82*E15 -> 19405.567 | AH10: =2166.938*E15 -> 2065.6792 | AI10: =13370.42*E15 -> 12745.634 | AJ10: =11151.01*E15 -> 10629.935 | AK10: =10020.707*E15 -> 9552.4497 | AL10: =6593.354*E15 -> 6285.2533 | AM10: =5936.281*E15 -> 5658.8847 | AN10: =32915.5*E15 -> 31377.393
B11: GDP | C11: ='OECD Crosswalk'!E1 -> government | D11: OTXS: Other taxes less subsidies on production | E11: =8.906*E16 -> 8.8367272 | F11: =1.544*E16 -> 1.5319904 | G11: =6.101*E16 -> 6.0535451 | H11: =0.323*E16 -> 0.32048763 | I11: =140.56*E16 -> 139.46669 | J11: =70.66*E16 -> 70.110391 | K11: =0.825*E16 -> 0.81858297 | L11: =7.965*E16 -> 7.9030465 | M11: =102.816*E16 -> 102.01627 | N11: =47.888*E16 -> 47.515517 | O11: =20.416*E16 -> 20.2572 | P11: =9.577*E16 -> 9.502508 | Q11: =2.798*E16 -> 2.7762365 | R11: =14.054*E16 -> 13.944685 | S11: =65.644*E16 -> 65.133406 | T11: =105.603*E16 -> 104.7816 | U11: =24.244*E16 -> 24.055425 | V11: =105.421*E16 -> 104.60101 | W11: =12.201*E16 -> 12.106098 | X11: =73.612*E16 -> 73.03943 | Y11: =56.642*E16 -> 56.201426 | Z11: =100.948*E16 -> 100.1628 | AA11: =816.859*E16 -> 810.50529 | AB11: =543.644*E16 -> 539.41542 | AC11: =194.749*E16 -> 193.2342 | AD11: =104.108*E16 -> 103.29822 | AE11: =107.92*E16 -> 107.08057 | AF11: =93.092*E16 -> 92.36791 | AG11: =253.117*E16 -> 251.1482 | AH11: =823.642*E16 -> 817.23553 | AI11: =183.502*E16 -> 182.07468 | AJ11: =7.697*E16 -> 7.637131 | AK11: =24.492*E16 -> 24.301496 | AL11: =29.505*E16 -> 29.275504 | AM11: =99.423*E16 -> 98.649666 | AN11: =0*E16 -> 0
B12: GDP | D12: GOPS: Gross operating surplus and mixed income | E12: =826.404*E16 -> 819.97605 | F12: =15.249*E16 -> 15.13039 | G12: =66.649*E15 -> 63.534561 | H12: =2.573*E16 -> 2.5529866 | I12: =4261.665*E16 -> 4228.5168 | J12: =203.292*E16 -> 201.71075 | K12: =11.116*E16 -> 11.029537 | L12: =161.363*E16 -> 160.10788 | M12: =584.797*E16 -> 580.24832 | N12: =988.148*E16 -> 980.46197 | O12: =242.867*E16 -> 240.97793 | P12: =126.402*E16 -> 125.41882 | Q12: =87.508*E16 -> 86.827343 | R12: =116.814*E16 -> 115.90539 | S12: =1146.081*E16 -> 1137.1665 | T12: =990.154*E16 -> 982.45236 | U12: =274.013*E16 -> 271.88167 | V12: =927.583*E15 -> 884.238 | W12: =134.082*E16 -> 133.03908 | X12: =766.082*E16 -> 760.12324 | Y12: =5118.112*E16 -> 5078.3022 | Z12: =1743.891*E16 -> 1730.3266 | AA12: =36269.952*E16 -> 35987.836 | AB12: =8819.309*E16 -> 8750.7105 | AC12: =3493.943*E16 -> 3466.7663 | AD12: =1460.761*E16 -> 1449.3989 | AE12: =2269.685*E16 -> 2252.0309 | AF12: =1213.348*E16 -> 1203.9103 | AG12: =11415.863*E16 -> 11327.068 | AH12: =20694.82*E16 -> 20533.851 | AI12: =2676.278*E16 -> 2655.4613 | AJ12: =3351.593*E16 -> 3325.5236 | AK12: =1172.201*E16 -> 1163.0834 | AL12: =1815.241*E16 -> 1801.1217 | AM12: =1129.596*E16 -> 1120.8098 | AN12: =0*E16 -> 0
D13: Data extracted on 05 Oct 2019 17:23 UTC (GMT) from OECD.Stat | G13: =66.649*E16 -> 66.130589
F14: https://www.censtatd.gov.hk/en/data/stat_report/product/B1060002/att/B10600022018AN18B0100.pdf
D15: CPI change (2018-2021) | E15: =102/107 -> 0.95327103 | F15: https://www.censtatd.gov.hk/en/data/stat_report/product/B1060002/att/B10600022021AN21B0100.pdf
D16: GDP Change (2018-2021) | E16: =2845317/2867622 -> 0.99222178 | F16: https://www.censtatd.gov.hk/en/web_table.html?id=31
F17: https://www.statistics.gov.hk/pub/B10300022018AN18E0100.pdf
D18: WRI (14/11/21) | E18: change the currency to HKD and then change it to year using GDP
E19: using a CPI (Consumer Price Index) | F19: more on the price rather than the product
E20: use the exchange rate to change to HKD GDP and then CPI to change 2018 datasheet to 2021
E21: GDP becomes a multiplier to calculate the differences
E24: USD--> HKD --->
E25: * CPI = value to input above

Sheet OECD Data IO Table - Imports
E2: From Sector | F2: =INDEX('OECD Crosswalk'!$C$2:$C$90,MATCH('OECD Data IO Table - Imports'!F7,'OECD Crosswalk'!$A$2:$A$90,0),1) -> agriculture | G2: =INDEX('OECD Crosswalk'!$C$2:$C$90,MATCH('OECD Data IO Table - Imports'!G7,'OECD Crosswalk'!$A$2:$A$90,0),1) -> other industries | H2: =INDEX('OECD Crosswalk'!$C$2:$C$90,MATCH('OECD Data IO Table - Imports'!H7,'OECD Crosswalk'!$A$2:$A$90,0),1) -> other industries | I2: =INDEX('OECD Crosswalk'!$C$2:$C$90,MATCH('OECD Data IO Table - Imports'!I7,'OECD Crosswalk'!$A$2:$A$90,0),1) -> other industries | J2: =INDEX('OECD Crosswalk'!$C$2:$C$90,MATCH('OECD Data IO Table - Imports'!J7,'OECD Crosswalk'!$A$2:$A$90,0),1) -> other industries | K2: =INDEX('OECD Crosswalk'!$C$2:$C$90,MATCH('OECD Data IO Table - Imports'!K7,'OECD Crosswalk'!$A$2:$A$90,0),1) -> other industries | L2: =INDEX('OECD Crosswalk'!$C$2:$C$90,MATCH('OECD Data IO Table - Imports'!L7,'OECD Crosswalk'!$A$2:$A$90,0),1) -> other industries | M2: =INDEX('OECD Crosswalk'!$C$2:$C$90,MATCH('OECD Data IO Table - Imports'!M7,'OECD Crosswalk'!$A$2:$A$90,0),1) -> other industries | ... AY2: =INDEX('OECD Crosswalk'!$C$2:$C$90,MATCH('OECD Data IO Table - Imports'!AY7,'OECD Crosswalk'!$A$2:$A$90,0),1) -> #N/A
D3: Variable | F3: DOMIMP: Domestic output and imports
D4: Country | F4: HKG: Hong Kong, China
D5: Time | F5: 2021
D6: Unit | F6: US Dollar, Millions
D7: To: (sector in column) | F7: D01T03: Agriculture, forestry and fishing | G7: D05T06: Mining and extraction of energy producing products | H7: D07T08: Mining and quarrying of non-energy producing products | I7: D09: Mining support service activities | J7: D10T12: Food products, beverages and tobacco | K7: D13T15: Textiles, wearing apparel, leather and related products | L7: D16: Wood and products of wood and cork | M7: D17T18: Paper products and printing | N7: D19: Coke and refined petroleum products | O7: D20T21: Chemicals and pharmaceutical products | P7: D22: Rubber and plastic products | Q7: D23: Other non-metallic mineral products | R7: D24: Basic metals | S7: D25: Fabricated metal products | T7: D26: Computer, electronic and optical products | U7: D27: Electrical equipment | V7: D28: Machinery and equipment, nec | W7: D29: Motor vehicles, trailers and semi-trailers | X7: D30: Other transport equipment | Y7: D31T33: Other manufacturing; repair and installation of machinery and equipment | Z7: D35T39: Electricity, gas, water supply, sewerage, waste and remediation services | AA7: D41T43: Construction | AB7: D45T47: Wholesale and retail trade; repair of motor vehicles | AC7: D49T53: Transportation and storage | AD7: D55T56: Accomodation and food services | AE7: D58T60: Publishing, audiovisual and broadcasting activities | AF7: D61: Telecommunications | AG7: D62T63: IT and other information services | AH7: D64T66: Financial and insurance activities | AI7: D68: Real estate activities | AJ7: D69T82: Other business sector services | AK7: D84: Public admin. and defence; compulsory social security | AL7: D85: Education | AM7: D86T88: Human health and social work | AN7: D90T96: Arts, entertainment, recreation and other service activities | AO7: D97T98: Private households with employed persons | AP7: HFCE: Final consumption expenditure of households | AQ7: NPISH: Final consumption expenditure of non-profit institutions serving households | AR7: GGFC: Final consumption expenditure of general government | AS7: GFCF: Gross Fixed Capital Formation | AT7: INVNT: Changes in inventories | AU7: CONS_ABR: Direct purchases abroad by residents (imports) | AV7: CONS_NONRES: Direct purchases by non-residents (exports) | AW7: EXPO: Exports (cross border) | AX7: IMPO: Imports (cross border) | AY7: TOTAL: Total
D8: From: (sector in row)
C9: Domestic | D9: DOM_01T03: Agriculture, forestry and fishing | F9: =0.2 -> 0.2 | G9: 0 | H9: 0 | I9: 0 | J9: =11+0.2 -> 11.2 | K9: 0.1 | L9: 0.2 | M9: 0.2 | N9: 0 | O9: 0 | P9: 0 | Q9: 0 | R9: 0 | S9: 0 | T9: 0 | U9: 0 | V9: 0 | W9: 0 | X9: 0 | Y9: 0 | Z9: =7.4+1.9+0.3+0.1 -> 9.7 | AA9: 0.9 | AB9: 4.2 | AC9: =5+19+24.2+0.7+0.6+0.2+2.4+3.8+0.1+0.1 -> 56.1 | AD9: =30.8+5.1 -> 35.9 | AE9: 0.4 | AF9: 1.1 | AG9: 0 | AH9: 0.9 | AI9: 0.3 | AJ9: =0.8 -> 0.8 | AK9: =0.7 -> 0.7 | AL9: 1.2 | AM9: 1.5 | AN9: =1.3+2.2+0.1+0.2 -> 3.8 | AO9: 0 | AP9: =327.5+41.8 -> 369.3 | AQ9: 0 | AR9: 0 | AS9: 0 | AT9: -0.1 | AU9: 0 | AV9: =1.1+2.5 -> 3.6 | AW9: =4.5+7.5 -> 12 | AX9: 0 | AY9: =449.3+65 -> 514.3
C10: Domestic | D10: DOM_05T06: Mining and extraction of energy producing products | F10: 0 | G10: 0 | H10: 0 | I10: 0 | J10: 0 | K10: 0 | L10: 0 | M10: 0 | N10: 0 | O10: 0 | P10: 0 | Q10: 0 | R10: 0 | S10: 0 | T10: 0 | U10: 0 | V10: 0 | W10: 0 | X10: 0 | Y10: 0 | Z10: 0 | AA10: 0 | AB10: 0 | AC10: 0 | AD10: 0 | AE10: 0 | AF10: 0 | AG10: 0 | AH10: 0 | AI10: 0 | AJ10: 0 | AK10: 0 | AL10: 0 | AM10: 0 | AN10: 0 | AO10: 0 | AP10: 0 | AQ10: 0 | AR10: 0 | AS10: 0 | AT10: 0 | AU10: 0 | AV10: 0 | AW10: 0 | AX10: 0 | AY10: 0
C11: Domestic | D11: DOM_07T08: Mining and quarrying of non-energy producing products | F11: 0 | G11: 0 | H11: 0 | I11: 0 | J11: 0 | K11: 0 | L11: 0 | M11: 0 | N11: 0 | O11: 2 | P11: 0 | Q11: 0 | R11: 0 | S11: 0 | T11: 0 | U11: 0 | V11: 0 | W11: 0 | X11: 0 | Y11: 0 | Z11: 0 | AA11: 0 | AB11: 0 | AC11: 0 | AD11: 0 | AE11: 0 | AF11: 0 | AG11: 0 | AH11: 0 | AI11: 0 | AJ11: 0 | AK11: 0 | AL11: 0 | AM11: 0 | AN11: 0 | AO11: 0 | AP11: 0 | AQ11: 0 | AR11: 0 | AS11: 0 | AT11: 0 | AU11: 0 | AV11: 0 | AW11: 0 | AX11: 0 | AY11: 0
C12: Domestic | D12: DOM_09: Mining support service activities | F12: =31.4+20.8 -> 52.2 | G12: 0 | H12: 0 | I12: 6141.3 | J12: 151.8 | K12: 30.3 | L12: 37.1 | M12: 141.7 | N12: 2.4 | O12: 0.5 | P12: 0 | Q12: 1.1 | R12: 131.3 | S12: 6.1 | T12: 2 | U12: 5.3 | V12: 22 | W12: 2 | X12: 1.1 | Y12: 0.2 | Z12: =52.2+30.1 -> 82.3 | AA12: 10.5 | AB12: 26 | AC12: =317.3+2.7+173.7+46.1+55.1 -> 594.9 | AD12: 3.5 | AE12: 17.2 | AF12: 0 | AG12: 1.6 | AH12: 189.7 | AI12: 50.7 | AJ12: =119.9+41.1 -> 161 | AK12: 20.2 | AL12: 83.6 | AM12: 0.6 | AN12: =6.4+18 -> 24.4 | AO12: 0 | AP12: 5.4 | AQ12: 0 | AR12: 0 | AS12: 0.9 | AT12: 0.7 | AU12: 0 | AV12: 0 | AW12: 73.2 | AX12: 0 | AY12: 8104.5
C13: Domestic | D13: DOM_10T12: Food products, beverages and tobacco | F13: =2.6+0.2 -> 2.8 | G13: 0 | H13: 0 | I13: 0 | J13: 112.7 | K13: 17.1 | L13: 11.7 | M13: 85.8 | N13: 0.6 | O13: =4.3+2.3 -> 6.6 | P13: 0 | Q13: 0.6 | R13: 3.7 | S13: 0.3 | T13: 0.5 | U13: 0.8 | V13: 0.6 | W13: 0.2 | X13: 0.1 | Y13: 0.1 | Z13: =54.3+28.2 -> 82.5 | AA13: 172.8 | AB13: 170.8 | AC13: =63.7+221.9+186.3+74.9+34 -> 580.8 | AD13: 305.8 | AE13: 22 | AF13: 41.6 | AG13: 2.1 | AH13: 127.9 | AI13: 50.8 | AJ13: =14.6+24.8 -> 39.4 | AK13: 16.8 | AL13: 20.8 | AM13: 93 | AN13: =22.7+54.3 -> 77 | AO13: 0 | AP13: 2495.4 | AQ13: 0 | AR13: 0 | AS13: 53.7 | AT13: 3570.7 | AU13: 0 | AV13: 219.5 | AW13: 380.6 | AX13: 0 | AY13: 8768.1
C14: Domestic | D14: DOM_13T15: Textiles, wearing apparel, leather and related products | F14: 0 | G14: 0 | H14: 0 | I14: 0 | J14: 2.2 | K14: 67.8 | L14: 0.3 | M14: 3.3 | N14: 0 | O14: 0 | P14: 0 | Q14: 0 | R14: 0.1 | S14: 0 | T14: 0 | U14: 0 | V14: 0 | W14: 0 | X14: 0 | Y14: 0.1 | Z14: =1.2+1.9 -> 3.1 | AA14: 1.4 | AB14: 32 | AC14: =12.2+15.9+10+15.5+7.9 -> 61.5 | AD14: 1.1 | AE14: 2.5 | AF14: 7.5 | AG14: 0.4 | AH14: 32.4 | AI14: 12.4 | AJ14: =2.8+5.6 -> 8.4 | AK14: 3.1 | AL14: 2.1 | AM14: 3 | AN14: =1.8+10.6 -> 12.4 | AO14: 0 | AP14: 627 | AQ14: 0 | AR14: 0 | AS14: 5.3 | AT14: 1694.3 | AU14: 0 | AV14: 19.7 | AW14: 389.1 | AX14: 0 | AY14: 2992.7
C15: Domestic | D15: DOM_16: Wood and of products of wood and cork (except furniture) | F15: =1.3+0.1 -> 1.4 | G15: 0 | H15: 0 | I15: 0.1 | J15: 16.4 | K15: 0 | L15: 0 | M15: 0 | N15: 0 | O15: 0 | P15: 0 | Q15: 0 | R15: 0 | S15: 0 | T15: 0 | U15: 0 | V15: 0 | W15: 0 | X15: 0 | Y15: 0 | Z15: =1.1+1.1 -> 2.2 | AA15: 73.3 | AB15: 1.5 | AC15: =13.1+56+8.3+22.8+2 -> 102.2 | AD15: 0.8 | AE15: 0.6 | AF15: 2.8 | AG15: 0 | AH15: 2.2 | AI15: 1.2 | AJ15: =0.5+0.7 -> 1.2 | AK15: 0.2 | AL15: 0.3 | AM15: 18.3 | AN15: =1.1+2 -> 3.1 | AO15: 0 | AP15: 350.3 | AQ15: 0 | AR15: 0 | AS15: 37.6 | AT15: 104.1 | AU15: 0 | AV15: 0.2 | AW15: 26 | AX15: 0 | AY15: 746
C16: Domestic | D16: DOM_17T18: Paper products and printing | F16: =7+0.7 -> 7.7 | G16: 0 | H16: 0 | I16: 0 | J16: 539.1 | K16: 125.9 | L16: 3.8 | M16: 572 | N16: 0.2 | O16: =2.2+1.9 -> 4.1 | P16: 0 | Q16: 7.1 | R16: 3.4 | S16: 0.5 | T16: 3.1 | U16: 6.8 | V16: 2.3 | W16: 0.8 | X16: 0.2 | Y16: 2.4 | Z16: =11.6+14.6 -> 26.2 | AA16: 320.7 | AB16: 299.8 | AC16: =85.3+129.4+59.9+125.7+39.6 -> 439.9 | AD16: 3.3 | AE16: 46.8 | AF16: 42.3 | AG16: 1.9 | AH16: 257.5 | AI16: 65.8 | AJ16: =17.7+21.2 -> 38.9 | AK16: 11.7 | AL16: 28.2 | AM16: 238.4 | AN16: =17+29.3 -> 46.3 | AO16: 0 | AP16: 1114.8 | AQ16: 0 | AR16: 0 | AS16: 10.9 | AT16: 217.1 | AU16: 0 | AV16: 74.7 | AW16: 124.2 | AX16: 0 | AY16: 4688.8
C17: Domestic | D17: DOM_19: Coke and refined petroleum products | F17: 0 | G17: 0 | H17: 0 | I17: 0.5 | J17: 0.3 | K17: 0.1 | L17: 0.1 | M17: 0.3 | N17: 2.5 | O17: =3.5+0.6 -> 4.1 | P17: 0 | Q17: 1.6 | R17: 20.2 | S17: 1.5 | T17: 0.1 | U17: 0.4 | V17: 0.3 | W17: 0.3 | X17: 0.1 | Y17: 0.2 | Z17: =2.6+1.6 -> 4.2 | AA17: 0.1 | AB17: 136.6 | AC17: =9.6+22.9+19.9+24.8+1.5 -> 78.7 | AD17: 0.4 | AE17: 0.6 | AF17: 1.2 | AG17: 0.1 | AH17: 18.2 | AI17: 4.6 | AJ17: =0.7+3.1 -> 3.8 | AK17: 8.1 | AL17: 3.5 | AM17: 0.5 | AN17: =0.8+1.7 -> 2.5 | AO17: 0 | AP17: 152.5 | AQ17: 0 | AR17: 0 | AS17: 0.2 | AT17: -137.5 | AU17: 0 | AV17: 69 | AW17: 33.1 | AX17: 0 | AY17: 413.2
C18: Domestic | D18: DOM_20T21: Chemicals and pharmaceutical products | F18: 0 | G18: 0 | H18: 0 | I18: 0 | J18: =0.1+0.1 -> 0.2 | K18: 0.1 | L18: 0 | M18: =0.3+0.1 -> 0.4 | N18: 0.1 | O18: =0.9+0.2+0.5+3.7 -> 5.3 | P18: 0 | Q18: =0.2+0.1 -> 0.3 | R18: =0.6+0.3 -> 0.9 | S18: 0.1 | T18: =0.1+0.1 -> 0.2 | U18: 0.4 | V18: 0.1 | W18: 0.1 | X18: 0 | Y18: 0 | Z18: 0.8 | AA18: 0 | AB18: 2.6 | AC18: =0.1+0.1+0.3+0.1+0.1+0.3+0.1 -> 1.1 | AD18: 0.1 | AE18: 0.3 | AF18: 0.2 | AG18: 0 | AH18: 1 | AI18: 0.3 | AJ18: =0.1+0.1+0.2+0.1 -> 0.5 | AK18: =1.2 -> 1.2 | AL18: 1.2 | AM18: =0.3+4.9 -> 5.2 | AN18: =0.2+0.8+0.6+0.8 -> 2.4 | AO18: 0 | AP18: =9.4+90.9 -> 100.3 | AQ18: 0 | AR18: 0 | AS18: =0.4+1.7 -> 2.1 | AT18: =838.1+157.7 -> 995.8 | AU18: 0 | AV18: =6.1+44.5 -> 50.6 | AW18: =333.9+161.6 -> 495.5 | AX18: 0 | AY18: =1197.8+474.8 -> 1672.6
C19: Domestic | D19: DOM_22: Rubber and plastics products | F19: 0 | G19: 0 | H19: 0 | I19: 0 | J19: 0 | K19: 0 | L19: 0 | M19: 36 | N19: 0 | O19: 0 | P19: 0 | Q19: 0 | R19: 0 | S19: 0 | T19: 0 | U19: 0 | V19: 0 | W19: 0 | X19: 0 | Y19: 0 | Z19: 0 | AA19: 0 | AB19: 0 | AC19: 0 | AD19: 0 | AE19: 0 | AF19: 0 | AG19: 0 | AH19: 30.6 | AI19: 0 | AJ19: 0 | AK19: 0 | AL19: 0 | AM19: 0 | AN19: 0 | AO19: 0 | AP19: 0 | AQ19: 0 | AR19: 0 | AS19: 0 | AT19: 0 | AU19: 0 | AV19: 0 | AW19: 0 | AX19: 0 | AY19: 0
C20: Domestic | D20: DOM_23: Other non-metallic mineral products | F20: 0 | G20: 0 | H20: 0 | I20: 1.7 | J20: 15.7 | K20: 0.5 | L20: 0.5 | M20: 1.9 | N20: 5.6 | O20: =4.5+3.3 -> 7.8 | P20: 0 | Q20: 155.5 | R20: 171.4 | S20: 16 | T20: 13.8 | U20: 37.4 | V20: 7.4 | W20: 23.5 | X20: 7.1 | Y20: 2.3 | Z20: =2+12.3 -> 14.3 | AA20: 22.3 | AB20: 67.3 | AC20: =0.9+0.9+1.8+9.8+5.2 -> 18.6 | AD20: 1.1 | AE20: 4.7 | AF20: 13.7 | AG20: 0.2 | AH20: 3648.1 | AI20: 8.9 | AJ20: =1.5+3.1 -> 4.6 | AK20: 45.7 | AL20: 31.6 | AM20: 1.7 | AN20: =7.1+16.5 -> 23.6 | AO20: 0 | AP20: 259.1 | AQ20: 0 | AR20: 0 | AS20: 16.6 | AT20: 142.6 | AU20: 0 | AV20: 0 | AW20: 108.8 | AX20: 0 | AY20: 1278.3
C21: Domestic | D21: DOM_24: Manufacture of basic metals | F21: 0 | G21: 0 | H21: 0 | I21: 1 | J21: 2.3 | K21: 0.1 | L21: 0.4 | M21: 1.9 | N21: 1 | O21: =3.2+0.8 -> 4 | P21: 0 | Q21: 6.1 | R21: 1407.2 | S21: 102.6 | T21: 25.9 | U21: 112.5 | V21: 31.2 | W21: 10.6 | X21: 1.9 | Y21: 8.5 | Z21: =1.2+20.1 -> 21.3 | AA21: 1.4 | AB21: 1217 | AC21: =0.6+1.7+1.2+10+0.5 -> 14 | AD21: 0.3 | AE21: 2.5 | AF21: 1.5 | AG21: 0.1 | AH21: 30.6 | AI21: 8.7 | AJ21: =1.5+0.8 -> 2.3 | AK21: 2.2 | AL21: 2.4 | AM21: 0.4 | AN21: =3.2+4.9 -> 8.1 | AO21: 0 | AP21: 18.2 | AQ21: 0 | AR21: 0 | AS21: 52.4 | AT21: -39.1 | AU21: 0 | AV21: 0 | AW21: 8466.3 | AX21: 0 | AY21: 11508.3
C22: Domestic | D22: DOM_25: Fabricated metal products, except machinery and equipment | F22: 0 | G22: 0 | H22: 0 | I22: 0.7 | J22: 0.7 | K22: 0.1 | L22: 0.2 | M22: 0.5 | N22: 0.4 | O22: =0.7+0.3 -> 1 | P22: 0 | Q22: 2.2 | R22: 86.4 | S22: 15.9 | T22: 4.4 | U22: 15.7 | V22: 10 | W22: 5 | X22: 1.6 | Y22: 1.8 | Z22: =0.5+3.1 -> 3.6 | AA22: 0.9 | AB22: 389.1 | AC22: =0.4+0.7+0.4+4.9+0.2 -> 6.6 | AD22: 0.1 | AE22: 0.9 | AF22: 0.7 | AG22: 0.1 | AH22: 3648.1 | AI22: 5.2 | AJ22: =0.7+1.6 -> 2.3 | AK22: 2 | AL22: 2 | AM22: 0.2 | AN22: =1.5+2.1 -> 3.6 | AO22: 0 | AP22: 52.6 | AQ22: 0 | AR22: 0 | AS22: 86.6 | AT22: 162.9 | AU22: 0 | AV22: 0 | AW22: 335.3 | AX22: 0 | AY22: 1206.2
C23: Domestic | D23: DOM_26: Computer, electronic and optical products | F23: 0 | G23: 0 | H23: 0 | I23: 0 | J23: 0 | K23: 0 | L23: 0 | M23: 0 | N23: 0 | O23: 0 | P23: 0 | Q23: 0 | R23: 0 | S23: 0 | T23: 1 | U23: 0.4 | V23: 0.1 | W23: 0.1 | X23: 0 | Y23: 0 | Z23: 0.3 | AA23: 0 | AB23: 28.7 | AC23: 0.4 | AD23: 0 | AE23: 0.3 | AF23: 3 | AG23: 0 | AH23: 30.6 | AI23: 0.2 | AJ23: 0.2 | AK23: 0.2 | AL23: 0.3 | AM23: 0 | AN23: 0.9 | AO23: 0 | AP23: 498 | AQ23: 0 | AR23: 0 | AS23: 321.8 | AT23: -737.8 | AU23: 0 | AV23: 0.1 | AW23: 1379.5 | AX23: 0 | AY23: 1498.2
C24: Domestic | D24: DOM_27: Electrical equipment | F24: 0 | G24: 0 | H24: 0 | I24: 0.2 | J24: 0.2 | K24: 0 | L24: 0 | M24: 0.2 | N24: 0.2 | O24: =0.2+0.1 -> 0.3 | P24: 0 | Q24: 0.4 | R24: 2.7 | S24: 0.4 | T24: 10.5 | U24: 47.9 | V24: 8.3 | W24: 3.9 | X24: 1.2 | Y24: 1.1 | Z24: =6.4+5.1 -> 11.5 | AA24: 0.5 | AB24: 689.1 | AC24: =0.4+0.9+0.4+1.4+5.6 -> 8.7 | AD24: 0.1 | AE24: 6.3 | AF24: 45.9 | AG24: 0.4 | AH24: 3648.1 | AI24: 8.4 | AJ24: =2+3.7 -> 5.7 | AK24: 3.2 | AL24: 3.9 | AM24: 0.2 | AN24: =5.4+13.9 -> 19.3 | AO24: 0 | AP24: 349.1 | AQ24: 0 | AR24: 0 | AS24: 169.5 | AT24: 960 | AU24: 0 | AV24: 2.4 | AW24: 342.1 | AX24: 0 | AY24: 2710.9
C25: Domestic | D25: DOM_28: Machinery and equipment n.e.c. | F25: 0 | G25: 0 | H25: 0 | I25: 1 | J25: 0.8 | K25: 0.2 | L25: 0.1 | M25: 0.7 | N25: 0.4 | O25: =0.5+0.3 -> 0.8 | P25: 0 | Q25: 1.7 | R25: 13 | S25: 2.3 | T25: 1.4 | U25: 3.9 | V25: 13.9 | W25: 6.7 | X25: 2.4 | Y25: 1.3 | Z25: =0.7+1.1 -> 1.8 | AA25: 0.1 | AB25: 36.6 | AC25: =0.4+4.4+6.2+11+0.9 -> 22.9 | AD25: 0.1 | AE25: 0.5 | AF25: 1.6 | AG25: 0 | AH25: 30.6 | AI25: 3.9 | AJ25: =0.1+0.5 -> 0.6 | AK25: 0.7 | AL25: 1.1 | AM25: 1.8 | AN25: =0.7+1.1 -> 1.8 | AO25: 0 | AP25: 22.8 | AQ25: 0 | AR25: 0 | AS25: 437.2 | AT25: -276.2 | AU25: 0 | AV25: 0 | AW25: 912.5 | AX25: 0 | AY25: 1237.1
C26: Domestic | D26: DOM_29: Motor vehicles, trailers and semi-trailers | F26: 0 | G26: 0 | H26: 0 | I26: 0 | J26: 0 | K26: 0 | L26: 0 | M26: 0 | N26: 0 | O26: =0 -> 0 | P26: 0 | Q26: 0.2 | R26: 0.4 | S26: 0.1 | T26: 0.1 | U26: 0.2 | V26: 1 | W26: 29.5 | X26: 3 | Y26: 0.2 | Z26: 4 | AA26: 0 | AB26: 62 | AC26: =3.8+4.8+3.7+0.7+2.8 -> 15.8 | AD26: 0.1 | AE26: 2.2 | AF26: 2.2 | AG26: 0.1 | AH26: 3648.1 | AI26: 0.6 | AJ26: =0.4+1.7 -> 2.1 | AK26: 7.4 | AL26: 0.1 | AM26: 0.1 | AN26: =3.8+5.1 -> 8.9 | AO26: 0 | AP26: 241.5 | AQ26: 0 | AR26: 0 | AS26: 391.6 | AT26: 640 | AU26: 0 | AV26: 4.1 | AW26: 45 | AX26: 0 | AY26: 1468.2
C27: Domestic | D27: DOM_30: Other transport equipment | F27: 0 | G27: 0 | H27: 0 | I27: 0 | J27: 0 | K27: 0 | L27: 0 | M27: 0 | N27: 0 | O27: =0 -> 0 | P27: 0 | Q27: 0 | R27: 0 | S27: 0 | T27: 0 | U27: 0 | V27: 0.2 | W27: 9.5 | X27: 6.6 | Y27: 0.2 | Z27: 0.9 | AA27: 0 | AB27: 20.5 | AC27: =0.8+4.2+3.9+0.3+0.6 -> 9.8 | AD27: 0 | AE27: 1 | AF27: 0.4 | AG27: 0 | AH27: 30.6 | AI27: 0.2 | AJ27: =0.2+0.4 -> 0.6 | AK27: 4.5 | AL27: 0 | AM27: 0 | AN27: =1.3+1.9 -> 3.2 | AO27: 0 | AP27: 43.2 | AQ27: 0 | AR27: 0 | AS27: 258.2 | AT27: 127.1 | AU27: 0 | AV27: 0 | AW27: 30.6 | AX27: 0 | AY27: 519.5
C28: Domestic | D28: DOM_31T33: Other manufacturing; repair and installation of machinery and equipment | F28: 0.3 | G28: 0 | H28: 0 | I28: 0.3 | J28: 6.6 | K28: 1.1 | L28: 1 | M28: 8 | N28: 0 | O28: =0.2+0.1 -> 0.3 | P28: 0 | Q28: 0.2 | R28: 0.9 | S28: 0.2 | T28: 0.1 | U28: 0.4 | V28: 0.4 | W28: 0.3 | X28: 0.2 | Y28: 0.3 | Z28: =10.7+8.9 -> 19.6 | AA28: 21.7 | AB28: 51.8 | AC28: =26.6+47.5+73.5+37.4+5.1 -> 190.1 | AD28: 6.9 | AE28: 3.1 | AF28: 18.7 | AG28: 0.7 | AH28: 3648.1 | AI28: 36.5 | AJ28: =3.1+18.7 -> 21.8 | AK28: 10.8 | AL28: 4.8 | AM28: 13.3 | AN28: =6.9+6.5 -> 13.4 | AO28: 0 | AP28: 52.9 | AQ28: 0 | AR28: 0 | AS28: 14.5 | AT28: -57.9 | AU28: 0 | AV28: 0 | AW28: 317.4 | AX28: 0 | AY28: 807.8
C29: Domestic | D29: DOM_35T39: Electricity, gas, water supply, sewerage, waste and remediation services | F29: =0.8+0.7+0.1 -> 1.6 | G29: 0 | H29: 0 | I29: =0.8+0.1 -> 0.9 | J29: =86.3+46.4 -> 132.7 | K29: =11.7+8.8 -> 20.5 | L29: =7.9+6.4 -> 14.3 | M29: =63.8+60 -> 123.8 | N29: =63.8+60 -> 123.8 | O29: =0.6+0.2+0.2+0.1 -> 1.1 | P29: 0 | Q29: =0.6+0.3 -> 0.9 | R29: =5.6+6.1 -> 11.7 | S29: =0.3+0.3 -> 0.6 | T29: 0.2 | U29: 0.4 | V29: 0.4 | W29: 0.3 | X29: 0.1 | Y29: 0.4 | Z29: =283+77.5+68.2+324.5 -> 753.2 | AA29: =34.6+54.1 -> 88.7 | AB29: =331.5+634.1 -> 965.6 | AC29: =108.9+42+61.7+321.3+15.2+64.2+57.9+53+159.6+51.5 -> 935.3 | AD29: =335.2+146.5 -> 481.7 | AE29: =58.1+26.9 -> 85 | AF29: =86.6+95.4 -> 182 | AG29: =3.3+5.7 -> 9 | AH29: =442+491.8 -> 933.8 | AI29: =1097.7+1083.7 -> 2181.4 | AJ29: =19.7+30.3+32.4+67.4 -> 149.8 | AK29: =132.1+97.1 -> 229.2 | AL29: =132.1+97.1 -> 229.2 | AM29: =172+79.9 -> 251.9 | AN29: =98+102.6+55.7+107.2 -> 363.5 | AO29: 0 | AP29: =1150.3+1133.7 -> 2284 | AQ29: =2.1+29.2 -> 31.3 | AR29: 0 | AS29: 105.2 | AT29: =-0.5+5.2 -> 4.7 | AU29: 0 | AV29: 0 | AW29: 39.4 | AX29: 0 | AY29: =5313.3+5223.9 -> 10537.2
C30: Domestic | D30: DOM_41T43: Construction | F30: 0.8 | G30: 0 | H30: 0 | I30: 0.5 | J30: 7.1 | K30: 0.4 | L30: 0.3 | M30: 2 | N30: 0 | O30: 0 | P30: 0 | Q30: 0 | R30: 0.1 | S30: 0 | T30: 0 | U30: 0 | V30: 0 | W30: 0 | X30: 0 | Y30: 0.1 | Z30: =4.8+5.2 -> 10 | AA30: 6416.4 | AB30: 22 | AC30: =21.7+14.1+62.5+23.8+3.2 -> 125.3 | AD30: 10.2 | AE30: 3 | AF30: 10.5 | AG30: 0.3 | AH30: 30.6 | AI30: 324.6 | AJ30: =2.4+2.5 -> 4.9 | AK30: 352 | AL30: 22.2 | AM30: 22.6 | AN30: =5.5+7.9 -> 13.4 | AO30: 0 | AP30: 0.8 | AQ30: 0 | AR30: 0 | AS30: 20309.2 | AT30: 0 | AU30: 0 | AV30: 0 | AW30: 0 | AX30: 0 | AY30: 27689.4
C31: Domestic | D31: DOM_45T47: Wholesale and retail trade; repair of motor vehicles | F31: =126.8+6.4 -> 133.2 | G31: 0 | H31: 0 | I31: 1495.6 | J31: 2232.7 | K31: 927.3 | L31: 177.9 | M31: 1432 | N31: 156.8 | O31: =475+186.5 -> 661.5 | P31: 0 | Q31: 413 | R31: 2226.7 | S31: 269.5 | T31: 451.8 | U31: 617.9 | V31: 297.5 | W31: 400.1 | X31: 169.8 | Y31: 517.2 | Z31: =1043.4+778.2 -> 1821.6 | AA31: 2181.4 | AB31: 27943.2 | AC31: =1515.8+2987.4+3256.3+4252.8+512.1 -> 12524.4 | AD31: 2702.9 | AE31: 723.8 | AF31: 1630.7 | AG31: 65.6 | AH31: 3648.1 | AI31: 1369.8 | AJ31: =341.5+867.3 -> 1208.8 | AK31: 885.8 | AL31: 932.5 | AM31: 1431 | AN31: =646+1218.5 -> 1864.5 | AO31: 0 | AP31: 52574.8 | AQ31: 1.6 | AR31: 0.1 | AS31: 14530.6 | AT31: 508.6 | AU31: 0 | AV31: 467.9 | AW31: 37109.9 | AX31: 0 | AY31: 178708.3
C32: Domestic | D32: DOM_49T53: Transportation and storage | F32: =3.7+0.3+1+0.1+0.9+0.1+2.3+0.2+0.2 -> 8.8 | G32: 0 | H32: 0 | I32: =2232.7+81.6 -> 2314.3 | J32: =81.6+82.2+51.2+46.9+25.8 -> 287.7 | K32: =37.7+24.9+17.2+22.6+7 -> 109.4 | L32: =5.5+8.9+4.6+2.9+3 -> 24.9 | M32: =52.1+64.2+32.5+29.9+17 -> 195.7 | N32: =52.1+64.2+32.5+29.9+17 -> 195.7 | O32: =24.41+8.4+5.5+1.9+5.1+1.8+15.4+5.4+0.1+0.1 -> 68.11 | P32: 0 | Q32: =30.7+7+6.4+19.7+0.1 -> 63.9 | R32: =133.6+31.7+28+85.4+0.2 -> 278.9 | S32: =17.8+4.1+3.7+11.3 -> 36.9 | T32: =28.1+6.3+5.9+18+0.1 -> 58.4 | U32: =38.3+8.7+8.1+24.5+0.1 -> 79.7 | V32: =17.6+4+3.8+11.3+0.1 -> 36.8 | W32: =20.6+4.8+4.4+13.1 -> 42.9 | X32: =9.5+2.2+2+6.1 -> 19.8 | Y32: =4.7+1.3+1.1+2.6 -> 9.7 | Z32: =35.7+35.2+12.7+22.3+10.1+11.6+22.3+20.5+6.3+14.3 -> 191 | AA32: =63.7+87.9+52.8+34.8+13.4 -> 252.6 | AB32: =1280.7+1948.6+1166.2+738.1+555.7 -> 5689.3 | AC32: =175.9+166.1+127.4+371.6+29.6+79.4+3565.3+1854.5+1484.4+609+48.2+1890.3+1008.6+479.8+342.4+35.6+4.1+31.4+161.6+0.8+24.9+326.9+42.9+57.1+573.4 -> 13491.2 | AD32: =122.7+53.5+38.3+74.9+16.7 -> 306.1 | AE32: =28+20.5+20.3+16.7+26.4 -> 111.9 | AF32: =93.1+560.7+300.4+44+353.5 -> 1351.7 | AG32: =3.3+8.4+6.1+1.4+5.9 -> 25.1 | AH32: =210.1+972.2+473.6+59.7+779.4 -> 2495 | AI32: =60.8+67.8+404.4+30.2+161.6 -> 724.8 | AJ32: =17.9+41.8+16.5+141.7+31.2+72.3+7.6+17.4+31.5+51.9 -> 429.8 | AK32: =45.2+36.7+24+26.7+46.6 -> 179.2 | AL32: =44.9+32.6+21.4+26.5+23.2 -> 148.6 | AM32: =48.7+41.1+26.9+27.6+26.2 -> 170.5 | AN32: =28.1+65.5+27.5+111.9+17.5+55.6+16.4+35.6+23.8+59 -> 440.9 | AO32: 0 | AP32: =2572.2+1813.8+1065.9+1434.5+213.2 -> 7099.6 | AQ32: =0.2+0.1+5.5 -> 5.8 | AR32: 0 | AS32: =768.5+189.1+168.2+486.4+237.9 -> 1850.1 | AT32: =-1801+194.9+265.6+417.2+86.6 -> -836.7 | AU32: 0 | AV32: =4706.2+1724.6+1965.7+14.2+67.5 -> 8478.2 | AW32: =2393.5+2708.3+11912.4+13749.2+1316.9 -> 32080.3 | AX32: 0 | AY32: =12281.1+18682.6+21697.4+17871.3+5202 -> 75734.4
C33: Domestic | D33: DOM_55T56: Accomodation and food services | F33: 0.2 | G33: 0 | H33: 0 | I33: 0.1 | J33: 0.3 | K33: 2.6 | L33: 1.2 | M33: 5.2 | N33: 0 | O33: 0 | P33: 0 | Q33: 0 | R33: 0 | S33: 0 | T33: 0 | U33: 0 | V33: 0 | W33: 0 | X33: =9.5+2.2+2+6.1 -> 19.8 | Y33: 0.1 | Z33: =4.7+7.2 -> 11.9 | AA33: 11.2 | AB33: 127 | AC33: =16.3+43.6+10.5+32.8+10.5 -> 113.7 | AD33: 71.7 | AE33: 16.8 | AF33: 32.6 | AG33: 2.5 | AH33: 214 | AI33: 95.9 | AJ33: =10.2+16.4 -> 26.6 | AK33: 13.9 | AL33: 33 | AM33: 19.6 | AN33: =8.3+24.2 -> 32.5 | AO33: 0 | AP33: 4934.2 | AQ33: 0 | AR33: 0 | AS33: 24.3 | AT33: 0 | AU33: 0 | AV33: 14832.2 | AW33: 0 | AX33: 0 | AY33: 20632.5
C34: Domestic | D34: DOM_58T60: Publishing, audiovisual and broadcasting activities | F34: 0.6 | G34: 0 | H34: 0 | I34: 0 | J34: 36.3 | K34: 5.6 | L34: 0.8 | M34: 8.7 | N34: 0 | O34: =0.1+0.1 -> 0.2 | P34: 0 | Q34: 0.2 | R34: 0.2 | S34: 0 | T34: 0.2 | U34: 0.3 | V34: 0.1 | W34: 0.1 | X34: 0 | Y34: 0.1 | Z34: =5.5+3.2 -> 8.7 | AA34: 22.4 | AB34: 240.5 | AC34: =16.5+21.9+29.2+28.1+9.8 -> 105.5 | AD34: 18.6 | AE34: 283.9 | AF34: 81.2 | AG34: 2.6 | AH34: 261.6 | AI34: 172.7 | AJ34: =38.2+11 -> 49.2 | AK34: 12 | AL34: 16.2 | AM34: 29.7 | AN34: =45.1+18.9 -> 64 | AO34: 0 | AP34: 575.3 | AQ34: 2.9 | AR34: 0 | AS34: 127.1 | AT34: -6.1 | AU34: 0 | AV34: 114.3 | AW34: 3613.2 | AX34: 0 | AY34: 5832.4
C35: Domestic | D35: DOM_61: Telecommunications | F35: =0.7+0.1 -> 0.8 | G35: 0 | H35: 0 | I35: 0.1 | J35: 1.8 | K35: 19.8 | L35: 9.7 | M35: 39 | N35: 0 | O35: =0.2+0.1 -> 0.3 | P35: 0 | Q35: 0.2 | R35: 0.5 | S35: 0.1 | T35: 0.2 | U35: 0.3 | V35: 0.3 | W35: 0.1 | X35: 0 | Y35: 0 | Z35: =18+37.6 -> 55.6 | AA35: 61.1 | AB35: 1248.2 | AC35: =82.6+1255.9+181+155.8+57.2 -> 1732.5 | AD35: 92.5 | AE35: 130.8 | AF35: 1310.7 | AG35: 30.8 | AH35: 2170.4 | AI35: 555.5 | AJ35: =102.1+142.3 -> 244.4 | AK35: 116.3 | AL35: 75.1 | AM35: 108.3 | AN35: =85.1+146.1 -> 231.2 | AO35: 0 | AP35: 1794 | AQ35: 7.7 | AR35: 0 | AS35: 295 | AT35: 152.5 | AU35: 0 | AV35: 1251 | AW35: 4880.9 | AX35: 0 | AY35: 16680.9
C36: Domestic | D36: DOM_62T63: IT and other information services | F36: 0.2 | G36: 0 | H36: 0 | I36: 0.1 | J36: 10.5 | K36: 8.7 | L36: 3.4 | M36: 18.7 | N36: 0 | O36: 0.1 | P36: 0 | Q36: 0 | R36: 0.2 | S36: 0 | T36: 0.1 | U36: 0.1 | V36: 0.1 | W36: 0.1 | X36: 0 | Y36: 0.1 | Z36: =5.8+7.2 -> 13 | AA36: 15.8 | AB36: 405.5 | AC36: =31.7+26.7+50.8+62.3+28 -> 199.5 | AD36: 24.9 | AE36: 30.3 | AF36: 159.6 | AG36: 18.8 | AH36: 730.6 | AI36: 176.3 | AJ36: =17.7+20.1 -> 37.8 | AK36: 59.2 | AL36: 30.6 | AM36: 23.3 | AN36: =17.1+24.5 -> 41.6 | AO36: 0 | AP36: 47 | AQ36: 0 | AR36: 0 | AS36: 296.4 | AT36: 45.2 | AU36: 0 | AV36: 15.6 | AW36: 2128.6 | AX36: 0 | AY36: 4556.3
C37: Domestic | D37: DOM_64T66: Financial and insurance activities | F37: =1+0.1 -> 1.1 | G37: 0 | H37: 0 | I37: 1.4 | J37: 13 | K37: 105.2 | L37: 43.8 | M37: 338.3 | N37: 0.4 | O37: =1+0.6 -> 1.6 | P37: 0 | Q37: 1.2 | R37: 11.5 | S37: 1.2 | T37: 0.9 | U37: 1.9 | V37: 1.1 | W37: 0.7 | X37: 0.2 | Y37: 0.1 | Z37: =276.5+2302.4 -> 2578.9 | AA37: 245.3 | AB37: 6604.3 | AC37: =612.3+894+290.7+1091.8+201.7 -> 3090.5 | AD37: 420.5 | AE37: 248.8 | AF37: 630.4 | AG37: 64 | AH37: 24290.4 | AI37: 12276.5 | AJ37: =343.3+708.1 -> 1051.4 | AK37: 170.4 | AL37: 451.6 | AM37: 318.8 | AN37: =317.7+806.3 -> 1124 | AO37: 0 | AP37: 21823 | AQ37: 0 | AR37: 357.8 | AS37: 465.8 | AT37: 4727 | AU37: 0 | AV37: 1071.6 | AW37: 41690.4 | AX37: 0 | AY37: 122548.9
C38: Domestic | D38: DOM_68: Real estate activities | F38: =1.2+0.1 -> 1.3 | G38: 0 | H38: 0 | I38: 0.1 | J38: 0.5 | K38: 43.8 | L38: 13.3 | M38: 75.6 | N38: 0.1 | O38: =0.2+0.1 -> 0.3 | P38: 0 | Q38: 0.6 | R38: 3.9 | S38: 0.6 | T38: 0.6 | U38: 1.1 | V38: 0.8 | W38: 0.5 | X38: 0.2 | Y38: 0 | Z38: =94.7+304.4 -> 399.1 | AA38: 184.3 | AB38: 6868.2 | AC38: =277.2+168.6+218.1+2374.6+103.9 -> 3142.4 | AD38: 1385.9 | AE38: 401.2 | AF38: 390.3 | AG38: 58.1 | AH38: 4363.2 | AI38: 4322 | AJ38: =280.3+507.6 -> 787.9 | AK38: 77.2 | AL38: 301.9 | AM38: 522.4 | AN38: =613.9+1570.6 -> 2184.5 | AO38: 0 | AP38: 45744.2 | AQ38: 0 | AR38: 0 | AS38: 6108.7 | AT38: 0.6 | AU38: 0 | AV38: 3510.3 | AW38: 41.9 | AX38: 0 | AY38: 81027.8
C39: Domestic | D39: DOM_69T82: Other business sector services | F39: =2.9+0.3+1+0.1 -> 4.3 | G39: 0 | H39: 0 | I39: =195.7+54.2 -> 249.9 | J39: =195.7+54.2 -> 249.9 | K39: =52.6+14.7 -> 67.3 | L39: =33.8+11.6 -> 45.4 | M39: =171.9+51.8 -> 223.7 | N39: =171.9+51.8 -> 223.7 | O39: =0.7+1+0.2+0.2 -> 2.1 | P39: 0 | Q39: =0.4+0.1 -> 0.5 | R39: =2+0.6 -> 2.6 | S39: =0.3+0.1 -> 0.4 | T39: =0.9+0.2 -> 1.1 | U39: =1.6+0.4 -> 2 | V39: 1.2 | W39: 1.2 | X39: 0.4 | Y39: 1.5 | Z39: =42.6+77+12.7+33 -> 165.3 | AA39: =222.2+52.6 -> 274.8 | AB39: =3636.8+1305.3 -> 4942.1 | AC39: =205.9+195.3+263+371.8+103.4+146.3+138.3+194.2+214.4+95.9 -> 1928.5 | AD39: =197.4+74.8 -> 272.2 | AE39: =171.2+64.1 -> 235.3 | AF39: =556.7+296.8 -> 853.5 | AG39: =43.5+14.6 -> 58.1 | AH39: =2916.5+1002.8 -> 3919.3 | AI39: =1606+622.8 -> 2228.8 | AJ39: =461.1+267.2+85.2+244.6 -> 1058.1 | AK39: =387.7+110.3 -> 498 | AL39: =198.1+94.6 -> 292.7 | AM39: =283.9+134.6 -> 418.5 | AN39: =155.4+218.3+77.4+76.3 -> 527.4 | AO39: 0 | AP39: =447.2+141.4 -> 588.6 | AQ39: 6.7 | AR39: 303.1 | AS39: =2495.7+75.2 -> 2570.9 | AT39: =80.9+52 -> 132.9 | AU39: 0 | AV39: =541.9+1088.8 -> 1630.7 | AW39: =2254.3+1482.5 -> 3736.8 | AX39: 0 | AY39: =19182.5+8058.9 -> 27241.4
C40: Domestic | D40: DOM_84: Public administration and defence; compulsory social security | F40: 0.1 | G40: 0 | H40: 0 | I40: 0.1 | J40: 0.9 | K40: 3.1 | L40: 1.9 | M40: 6.6 | N40: 0 | O40: 0 | P40: 0 | Q40: 0 | R40: 0.3 | S40: 0 | T40: 0 | U40: 0.1 | V40: 0 | W40: 0.1 | X40: 0.1 | Y40: 0.1 | Z40: =5.8+13 -> 18.8 | AA40: 66.9 | AB40: 289.4 | AC40: =25.2+38.1+193.7+99.6+13.9 -> 370.5 | AD40: 39.9 | AE40: 17.3 | AF40: 38 | AG40: 2.7 | AH40: 307.1 | AI40: 89.7 | AJ40: =19.1+28.1 -> 47.2 | AK40: 309.3 | AL40: 31.1 | AM40: 24.3 | AN40: =22.9+40.1 -> 63 | AO40: 0 | AP40: 1988.1 | AQ40: 0 | AR40: 21947.6 | AS40: 43 | AT40: 0 | AU40: 0 | AV40: 0 | AW40: 0 | AX40: 0 | AY40: 25719.6
C41: Domestic | D41: DOM_85: Education | F41: 0.5 | G41: 0 | H41: 0 | I41: 0 | J41: 0.2 | K41: 9.3 | L41: 6.1 | M41: 33.8 | N41: 0 | O41: =0.1+0.1 -> 0.2 | P41: 0 | Q41: 0.1 | R41: 1 | S41: 0.1 | T41: 0.1 | U41: 0.1 | V41: 0.2 | W41: 0.2 | X41: 0.1 | Y41: 0.1 | Z41: =12.8+20.3 -> 33.1 | AA41: 45.4 | AB41: 625.5 | AC41: =57.5+61.8+67.5+123.5+31.8 -> 342.1 | AD41: 46.6 | AE41: 30.3 | AF41: 128.5 | AG41: 13.9 | AH41: 710.2 | AI41: 300.8 | AJ41: =57.7+63.3 -> 121 | AK41: 163.1 | AL41: 469.2 | AM41: 89 | AN41: =34.3+87.5 -> 121.8 | AO41: 0 | AP41: 2918.9 | AQ41: 9128.7 | AR41: 2620.7 | AS41: 231.7 | AT41: 0 | AU41: 0 | AV41: 1707.7 | AW41: 0 | AX41: 0 | AY41: 19937.7
C42: Domestic | D42: DOM_86T88: Human health and social work | F42: 0 | G42: 0 | H42: 0 | I42: 0 | J42: 0.5 | K42: 3.9 | L42: 0.9 | M42: 3.8 | N42: 0 | O42: 0 | P42: 0 | Q42: 0 | R42: 0.1 | S42: 0 | T42: 0 | U42: 0 | V42: 0 | W42: 0 | X42: 0 | Y42: 0 | Z42: =3.9+5.5 -> 9.4 | AA42: 9.7 | AB42: 133.6 | AC42: =16.7+47.8+7.1+40.6+8.6 -> 120.8 | AD42: 16.1 | AE42: 4.7 | AF42: 16.4 | AG42: 1.1 | AH42: 216.6 | AI42: 86.3 | AJ42: =11.1+18.6 -> 29.7 | AK42: 8.7 | AL42: 35.1 | AM42: 257.7 | AN42: =15.6+25 -> 40.6 | AO42: 0 | AP42: 6118.6 | AQ42: 1570.9 | AR42: 10648 | AS42: 26.4 | AT42: 0 | AU42: 0 | AV42: 843.7 | AW42: 0 | AX42: 0 | AY42: 20211.2
C43: Domestic | D43: DOM_90T96: Arts, entertainment, recreation and other service activities | F43: =0.4+0.1+3.5+0.5 -> 4.5 | G43: 0 | H43: 0 | I43: =17.8+145.8 -> 163.6 | J43: =17.8+145.8 -> 163.6 | K43: =2.7+52.9 -> 55.6 | L43: =1.2+16.1 -> 17.3 | M43: =11.8+95.6 -> 107.4 | N43: =11.8+95.6 -> 107.4 | O43: =2.7+2.2 -> 4.9 | P43: 0 | Q43: 2.5 | R43: =0.2+18 -> 18.2 | S43: 2.4 | T43: 3.7 | U43: 6.4 | V43: 0 | W43: 9.8 | X43: 3.3 | Y43: 0.5 | Z43: =7+10.8+65.5+71.8 -> 155.1 | AA43: =13.7+121.3 -> 135 | AB43: =237.9+1173.7 -> 1411.6 | AC43: =23+46.9+39.9+55.7+27.1+126.3+136.9+219.5+176.1+77.7 -> 929.1 | AD43: =21.3+207.4 -> 228.7 | AE43: =160.6+121.8 -> 282.4 | AF43: =70.2+174.3 -> 244.5 | AG43: =3.2+13.9 -> 17.1 | AH43: =480.7+1242.6 -> 1723.3 | AI43: =347.9+772.6 -> 1120.5 | AJ43: =55+132.9 -> 187.9 | AK43: =31+87.3 -> 118.3 | AL43: =43.3+80.4 -> 123.7 | AM43: =34.9+163.3 -> 198.2 | AN43: =732.5+110.2+162.9+498.9 -> 1504.5 | AO43: 0 | AP43: =1574.7+4484.5 -> 6059.2 | AQ43: =61+346 -> 407 | AR43: 0 | AS43: =155.1+606.3 -> 761.4 | AT43: =-5.5 -> -5.5 | AU43: 0 | AV43: =2089.6+1116.4 -> 3206 | AW43: 318 | AX43: 0 | AY43: =6821.9+12840.8 -> 19662.7
C44: Domestic | D44: DOM_97T98: Private households with employed persons | F44: 0 | G44: 0 | H44: 0 | I44: 0 | J44: 0 | K44: 0 | L44: 0 | M44: 0 | N44: 0 | O44: 0 | P44: 0 | Q44: 0 | R44: 0 | S44: 0 | T44: 0 | U44: 0 | V44: 0 | W44: 0 | X44: 0 | Y44: 0 | Z44: 0 | AA44: 0 | AB44: 0 | AC44: 0 | AD44: 0 | AE44: 0 | AF44: 0 | AG44: 0 | AH44: 0 | AI44: 0 | AJ44: 0 | AK44: 0 | AL44: 0 | AM44: 0 | AN44: 0 | AO44: 0 | AP44: 4665 | AQ44: 0 | AR44: 0 | AS44: 0 | AT44: 0 | AU44: 0 | AV44: 0 | AW44: 0 | AX44: 0 | AY44: 4665
C45: Imports | D45: IMP_01T03: Agriculture, forestry and fishing | F45: =0.8+0.1+0.1 -> 1 | G45: 0 | H45: 0 | I45: 0 | J45: =143.9+4.2 -> 148.1 | K45: =1.5+0.2 -> 1.7 | L45: 0.4 | M45: 2.7 | N45: 0 | O45: =0.3+0.2 -> 0.5 | P45: 0 | Q45: 0.1 | R45: 0.4 | S45: 0 | T45: 0.1 | U45: 0.1 | V45: 0.1 | W45: 0.1 | X45: 0 | Y45: 0 | Z45: =36.3+5+14.8+2.1 -> 58.2 | AA45: 8.3 | AB45: 43.8 | AC45: ='[1]OECD.Stat export'!$BD$54+'[1]OECD.Stat export'!$BF$54+'[1]OECD.Stat export'!$BH$54+'[1]OECD.Stat export'!$BJ$54+'[1]OECD.Stat export'!$BL$54+'[1]OECD.Stat export'!$BD$55+'[1]OECD.Stat export'!$BF$55+'[1]OECD.Stat export'!$BH$55+'[1]OECD.Stat export'!$BJ$55+'[1]OECD.Stat export'!$BL$55 -> 493.1 | AD45: =422.3+86.3 -> 508.6 | AE45: =3.3+1 -> 4.3 | AF45: =7.3+1.7 -> 9 | AG45: 0.2 | AH45: =7.7+1.4 -> 9.1 | AI45: =2.7+0.4 -> 3.1 | AJ45: =1.8+0.3+4.6+0.5 -> 7.2 | AK45: =6.4+0.7 -> 7.1 | AL45: =10.8+1.2 -> 12 | AM45: =18+1.6 -> 19.6 | AN45: =11.8+2.3+17.5+3.3 -> 34.9 | AO45: 0 | AP45: =4039.6+669.9 -> 4709.5 | AQ45: 0.1 | AR45: 0 | AS45: 3.5 | AT45: 10.6 | AU45: =33.6+2.6 -> 36.2 | AV45: 0 | AW45: 0 | AX45: =5242.7+891.3 -> 6134 | AY45: 0
C46: Imports | D46: IMP_05T06: Mining and extraction of energy producing products | F46: =15.7+1.5 -> 17.2 | G46: 0 | H46: 0 | I46: 169.3 | J46: 167.3 | K46: 136.5 | L46: 8.7 | M46: 91.6 | N46: 18.1 | O46: =0.7 -> 0.7 | P46: 0 | Q46: 1.4 | R46: 43.7 | S46: 2.2 | T46: 4.1 | U46: 11.9 | V46: 8.1 | W46: 2.6 | X46: 1.7 | Y46: 9.7 | Z46: =54.1+30.2 -> 84.3 | AA46: 3.8 | AB46: 22.3 | AC46: =129.4+1.9+39.4+1601.3+9.5 -> 1781.5 | AD46: 6 | AE46: 11.8 | AF46: 12.7 | AG46: 4.1 | AH46: 44.4 | AI46: 11.6 | AJ46: =27.1+84.5 -> 111.6 | AK46: 7.7 | AL46: 30.2 | AM46: 16.2 | AN46: =14.1+22.3 -> 36.4 | AO46: 0 | AP46: 37.1 | AQ46: 0.6 | AR46: 0 | AS46: 3.7 | AT46: 31.4 | AU46: 0.4 | AV46: 0 | AW46: 0 | AX46: 2952.4 | AY46: 0
C47: Imports | D47: IMP_07T08: Mining and quarrying of non-energy producing products | F47: =3.1+0.4 -> 3.5 | G47: 0 | H47: 0 | I47: 38.7 | J47: 20.2 | K47: 17.4 | L47: 1.3 | M47: 9.9 | N47: 0.5 | O47: 0.3 | P47: 0 | Q47: 0.9 | R47: 10.1 | S47: 0.6 | T47: 0.7 | U47: 2.4 | V47: 1.6 | W47: 0.4 | X47: 0.3 | Y47: 1.7 | Z47: 8.2 | AA47: 2.1 | AB47: 3.7 | AC47: =18.6+0.2+4.8+286.2+0.9 -> 310.7 | AD47: 0.8 | AE47: 0.8 | AF47: 1.6 | AG47: 0.5 | AH47: 4.7 | AI47: 1.8 | AJ47: =5.7+10.8 -> 16.5 | AK47: 1.3 | AL47: 3.1 | AM47: 1.7 | AN47: =1.9+3 -> 4.9 | AO47: 0 | AP47: 6.1 | AQ47: 0 | AR47: 0 | AS47: 1 | AT47: 1.1 | AU47: 0.4 | AV47: 0 | AW47: 0 | AX47: 481.4 | AY47: 0
C48: Imports | D48: IMP_09: Mining support service activities | F48: 0.1 | G48: 0 | H48: 0 | I48: 8.8 | J48: 0.3 | K48: 0.1 | L48: 0.1 | M48: 0.2 | N48: 0 | O48: 0 | P48: 0 | Q48: 0 | R48: 0.4 | S48: 0 | T48: 0 | U48: 0 | V48: 0 | W48: 0 | X48: 0 | Y48: 0 | Z48: 0.2 | AA48: 0 | AB48: 0.5 | AC48: =0.5+0.1+0.3+0.1+0.1 -> 1.1 | AD48: 0.1 | AE48: 0 | AF48: 0 | AG48: 0 | AH48: 0.3 | AI48: 0.1 | AJ48: 0.3 | AK48: 0 | AL48: 0.1 | AM48: 0 | AN48: 0 | AO48: 0 | AP48: 0.7 | AQ48: 0 | AR48: 0 | AS48: 0.3 | AT48: 0.3 | AU48: 0.1 | AV48: 0 | AW48: 0 | AX48: 14.6 | AY48: 0
C49: Imports | D49: IMP_10T12: Food products, beverages and tobacco | F49: =8.7+0.7 -> 9.4 | G49: 0 | H49: 0 | I49: 0.1 | J49: 426.5 | K49: 61.1 | L49: 42.1 | M49: 310.3 | N49: 2.2 | O49: =15.4+8.2 -> 23.6 | P49: 0 | Q49: 2.6 | R49: 17.1 | S49: 1.4 | T49: 2.3 | U49: 4 | V49: 2.6 | W49: 1.3 | X49: 0.5 | Y49: 0.4 | Z49: =201.6+106 -> 307.6 | AA49: 675.5 | AB49: 630.2 | AC49: =231.5+752.1+720.9+252.7+119.3 -> 2076.5 | AD49: 1084.7 | AE49: 84.2 | AF49: 156.2 | AG49: 7.6 | AH49: 467.1 | AI49: 165.8 | AJ49: =51.6+88.6 -> 140.2 | AK49: 58.5 | AL49: 73 | AM49: 325.3 | AN49: =83.8+195.1 -> 278.9 | AO49: 0 | AP49: 9342.1 | AQ49: 0 | AR49: 0 | AS49: 190.5 | AT49: 28.9 | AU49: 148.6 | AV49: 0 | AW49: 0 | AX49: 17148.7 | AY49: 0
C50: Imports | D50: IMP_13T15: Textiles, wearing apparel, leather and related products | F50: 0.6 | G50: 0 | H50: 0 | I50: 0.2 | J50: 20.5 | K50: 574.8 | L50: 2.5 | M50: 27.7 | N50: 0.1 | O50: 1 | P50: 0 | Q50: 0.6 | R50: 2.4 | S50: 0.3 | T50: 0.3 | U50: 0.6 | V50: 0.4 | W50: 0.7 | X50: 0.2 | Y50: 0.7 | Z50: =12.1+19 -> 31.1 | AA50: 13.8 | AB50: 288.5 | AC50: =117.2+135.9+100.9+136.6+73 -> 563.6 | AD50: 10.6 | AE50: 23.1 | AF50: 78.6 | AG50: 3.6 | AH50: 279.9 | AI50: 105.2 | AJ50: =25.8+55 -> 80.8 | AK50: 32.1 | AL50: 21 | AM50: 29.3 | AN50: =18.2+95.8 -> 114 | AO50: 0 | AP50: 9039.4 | AQ50: 0 | AR50: 0 | AS50: 57.1 | AT50: 224.2 | AU50: 94 | AV50: 0 | AW50: 0 | AX50: 11723.4 | AY50: 0
C51: Imports | D51: IMP_16: Wood and of products of wood and cork (except furniture) | F51: 0.7 | G51: 0 | H51: 0 | I51: 0.1 | J51: 9.1 | K51: 0.2 | L51: 0 | M51: 0.2 | N51: 0 | O51: 0.1 | P51: 0 | Q51: 0.1 | R51: 0.9 | S51: 0.1 | T51: 0.1 | U51: 0.2 | V51: 0.1 | W51: 0.2 | X51: 0.1 | Y51: 0.1 | Z51: =0.7+0.8 -> 1.5 | AA51: 40.5 | AB51: 10.7 | AC51: =6.8+27.6+4.4+11.6+1.2 -> 51.6 | AD51: 0.6 | AE51: 0.6 | AF51: 1.8 | AG51: 0 | AH51: 8.5 | AI51: 1.9 | AJ51: 0.8 | AK51: 0.9 | AL51: 1 | AM51: 10.1 | AN51: 2.8 | AO51: 0 | AP51: 214.9 | AQ51: 0 | AR51: 0 | AS51: 28.8 | AT51: 230.3 | AU51: 6.2 | AV51: 0 | AW51: 0 | AX51: 626.1 | AY51: 0
C52: Imports | D52: IMP_17T18: Paper products and printing | F52: =2.7+0.3 -> 3 | G52: 0 | H52: 0 | I52: 0 | J52: 212.3 | K52: 49.8 | L52: 1.5 | M52: 224.4 | N52: 0.1 | O52: 1.8 | P52: 0 | Q52: 2.9 | R52: 2.6 | S52: 0.3 | T52: 1.4 | U52: 3.2 | V52: 1.1 | W52: 0.5 | X52: 0.1 | Y52: 1 | Z52: =4.7+6 -> 10.7 | AA52: 129.1 | AB52: 127.9 | AC52: =32.4+47+23.1+46.2+14.9 -> 163.6 | AD52: 1.9 | AE52: 19.1 | AF52: 17.4 | AG52: 0.8 | AH52: 94.5 | AI52: 23.9 | AJ52: =6.9+8.2 -> 15.1 | AK52: 4.7 | AL52: 11.3 | AM52: 95.6 | AN52: =7+12.1 -> 19.1 | AO52: 0 | AP52: 442.5 | AQ52: 0 | AR52: 0 | AS52: 7.9 | AT52: 16.9 | AU52: 17 | AV52: 0 | AW52: 0 | AX52: 1724.9 | AY52: 0
C53: Imports | D53: IMP_19: Coke and refined petroleum products | F53: 1.1 | G53: 0 | H53: 0 | I53: 15.2 | J53: 11.4 | K53: 3.1 | L53: 2 | M53: 11.2 | N53: 72.4 | O53: =116.1+20.2 -> 136.3 | P53: 0 | Q53: 51.2 | R53: 647.2 | S53: 47.2 | T53: 4.7 | U53: 15.5 | V53: 9.1 | W53: 10.1 | X53: 3.4 | Y53: 5.9 | Z53: =82+54.2 -> 136.2 | AA53: 3.9 | AB53: 4269.3 | AC53: =284+348.7+586.4+712.7+44 -> 1975.8 | AD53: 14.6 | AE53: 20.4 | AF53: 39.4 | AG53: 3.7 | AH53: 516.7 | AI53: 129.8 | AJ53: =23+94.5 -> 117.5 | AK53: 245.2 | AL53: 112.6 | AM53: 19.6 | AN53: =28.4+60.7 -> 89.1 | AO53: 0 | AP53: 3193.1 | AQ53: 0 | AR53: 0 | AS53: 12.3 | AT53: 1234 | AU53: 63.2 | AV53: 0 | AW53: 0 | AX53: 13543.9 | AY53: 0
C54: Imports | D54: IMP_20T21: Chemicals and pharmaceutical products | F54: =2.1+0.1+0.1 -> 2.3 | G54: 0 | H54: 0 | I54: ='[1]OECD.Stat export'!L$64+'[1]OECD.Stat export'!L$65 -> 11.6 | J54: ='[1]OECD.Stat export'!N$64+'[1]OECD.Stat export'!N$65 -> 35.1 | K54: ='[1]OECD.Stat export'!P$64+'[1]OECD.Stat export'!P$65 -> 22.7 | L54: ='[1]OECD.Stat export'!R$64+'[1]OECD.Stat export'!R$65 -> 11.9 | M54: ='[1]OECD.Stat export'!T$64+'[1]OECD.Stat export'!T$65 -> 95.3 | N54: ='[1]OECD.Stat export'!V$64+'[1]OECD.Stat export'!V$65 -> 28 | O54: ='[1]OECD.Stat export'!$X$64+'[1]OECD.Stat export'!$Z$64+'[1]OECD.Stat export'!$X$65+'[1]OECD.Stat export'!$Z$65 -> 416.6 | P54: 0 | Q54: ='[1]OECD.Stat export'!AD$64+'[1]OECD.Stat export'!AD$65 -> 77.7 | R54: ='[1]OECD.Stat export'!AF$64+'[1]OECD.Stat export'!AF$65 -> 202.7 | S54: ='[1]OECD.Stat export'!AH$64+'[1]OECD.Stat export'!AH$65 -> 19 | T54: ='[1]OECD.Stat export'!AJ$64+'[1]OECD.Stat export'!AJ$65 -> 38.3 | U54: ='[1]OECD.Stat export'!AL$64+'[1]OECD.Stat export'!AL$65 -> 107.9 | V54: ='[1]OECD.Stat export'!AN$64+'[1]OECD.Stat export'!AN$65 -> 28.9 | W54: ='[1]OECD.Stat export'!AP$64+'[1]OECD.Stat export'!AP$65 -> 20.8 | X54: ='[1]OECD.Stat export'!AR$64+'[1]OECD.Stat export'!AR$65 -> 6.3 | Y54: ='[1]OECD.Stat export'!AT$64+'[1]OECD.Stat export'!AT$65 -> 12.2 | Z54: ='[1]OECD.Stat export'!$AV$64+'[1]OECD.Stat export'!$AX$64+'[1]OECD.Stat export'!$AV$65+'[1]OECD.Stat export'!$AX$65 -> 175.4 | AA54: ='[1]OECD.Stat export'!$BB$64+'[1]OECD.Stat export'!$BB$65 -> 810.5 | AB54: ='[1]OECD.Stat export'!$AZ$64+'[1]OECD.Stat export'!$AZ$65 -> 7.8 | AC54: ='[1]OECD.Stat export'!$BD$64+'[1]OECD.Stat export'!$BF$64+'[1]OECD.Stat export'!$BH$64+'[1]OECD.Stat export'!$BJ$64+'[1]OECD.Stat export'!$BL$64+'[1]OECD.Stat export'!$BL$65+'[1]OECD.Stat export'!$BJ$65+'[1]OECD.Stat export'!$BH$65+'[1]OECD.Stat export'!$BF$65+'[1]OECD.Stat export'!$BD$65 -> 210.1 | AD54: ='[1]OECD.Stat export'!$BN$64+'[1]OECD.Stat export'!$BN$65 -> 25.3 | AE54: ='[1]OECD.Stat export'!$BP$64+'[1]OECD.Stat export'!$BP$65 -> 69.9 | AF54: ='[1]OECD.Stat export'!$BR$64+'[1]OECD.Stat export'!$BR$65 -> 23.4 | AG54: ='[1]OECD.Stat export'!$BT$64+'[1]OECD.Stat export'!$BT$65 -> 1.8 | AH54: ='[1]OECD.Stat export'!$BV$64+'[1]OECD.Stat export'!$BV$65 -> 134.8 | AI54: ='[1]OECD.Stat export'!$BX$64+'[1]OECD.Stat export'!$BX$65 -> 56.4 | AJ54: ='[1]OECD.Stat export'!$BZ$64+'[1]OECD.Stat export'!$CB$64+'[1]OECD.Stat export'!$BZ$65+'[1]OECD.Stat export'!$CB$65 -> 70.4 | AK54: ='[1]OECD.Stat export'!$CD$64+'[1]OECD.Stat export'!$CD$65 -> 92.1 | AL54: ='[1]OECD.Stat export'!$CF$64+'[1]OECD.Stat export'!$CF$65 -> 222 | AM54: ='[1]OECD.Stat export'!$CH$64+'[1]OECD.Stat export'!$CH$65 -> 158.3 | AN54: ='[1]OECD.Stat export'!$CJ$64+'[1]OECD.Stat export'!$CL$64+'[1]OECD.Stat export'!$CJ$65+'[1]OECD.Stat export'!$CL$65 -> 366.1 | AO54: 0 | AP54: ='[1]OECD.Stat export'!$CP$64+'[1]OECD.Stat export'!$CP$65 -> 4298.3 | AQ54: 0 | AR54: 0.4 | AS54: ='[1]OECD.Stat export'!$CV$64+'[1]OECD.Stat export'!$CV$65 -> 155.5 | AT54: ='[1]OECD.Stat export'!$CX$64+'[1]OECD.Stat export'!$CX$65 -> 253 | AU54: ='[1]OECD.Stat export'!$CZ$64+'[1]OECD.Stat export'!$CZ$65 -> 42 | AV54: 0 | AW54: 0 | AX54: ='[1]OECD.Stat export'!$DF$64+'[1]OECD.Stat export'!$DF$65 -> 8310.4 | AY54: 0
C55: Imports | D55: IMP_22: Rubber and plastics products | F55: 0.2 | G55: 0 | H55: 0 | I55: 1.4 | J55: 49.5 | K55: # | L55: 1.7 | M55: 21.7 | N55: 2.3 | O55: =12.8 -> 12.8 | P55: 0 | Q55: 15.7 | R55: 41.9 | S55: 7.3 | T55: 28.6 | U55: 83.7 | V55: 30.4 | W55: 82.5 | X55: 15.9 | Y55: 10.9 | Z55: =2.4+34.1 -> 36.5 | AA55: 2.4 | AB55: 2002.7 | AC55: =17.9+2.3+2.4+14.1+3.3 -> 40 | AD55: 7 | AE55: 14.4 | AF55: 5 | AG55: # | AH55: 14.1 | AI55: 29.8 | AJ55: =1.6+3.5 -> 5.1 | AK55: 6.7 | AL55: 2.1 | AM55: 2.2 | AN55: =15.1+38.2 -> 53.3 | AO55: 0 | AP55: 326 | AQ55: 0 | AR55: 0.1 | AS55: 43.5 | AT55: 40.4 | AU55: 0.5 | AV55: 0 | AW55: 0 | AX55: 3064 | AY55: 0
C56: Imports | D56: IMP_23: Other non-metallic mineral products | F56: 0.1 | G56: 0 | H56: 0 | I56: 2.7 | J56: 25.6 | K56: 1.2 | L56: 0.9 | M56: 3.4 | N56: 8.4 | O56: 5.4 | P56: 0 | Q56: 247.1 | R56: 279.7 | S56: 26.1 | T56: 22.5 | U56: 61.5 | V56: 12.4 | W56: 37.7 | X56: 11.3 | Y56: 3.7 | Z56: =3.3+19.7 -> 23 | AA56: 36.3 | AB56: 115.8 | AC56: =1.7+1.7+3.2+16.2+7.9 -> 30.7 | AD56: 2.1 | AE56: 7.6 | AF56: 22 | AG56: 0.3 | AH56: 36.6 | AI56: 13.1 | AJ56: =2.4+4.9 -> 7.3 | AK56: 70.1 | AL56: 49.5 | AM56: 2.9 | AN56: =11.3+26.6 -> 37.9 | AO56: 0 | AP56: 413.4 | AQ56: 0 | AR56: 0 | AS56: 32.8 | AT56: 23.1 | AU56: 0.3 | AV56: 0 | AW56: 0 | AX56: 1681.9 | AY56: 0
C57: Imports | D57: IMP_24: Manufacture of basic metals | F57: 0.1 | G57: 0 | H57: 0 | I57: 4.2 | J57: 8 | K57: 0.7 | L57: 1.4 | M57: 6.9 | N57: 4 | O57: 2.9 | P57: 0 | Q57: 25.5 | R57: 4432 | S57: 373.4 | T57: 85.1 | U57: 377.3 | V57: 126.4 | W57: 42.3 | X57: 8.2 | Y57: 29.4 | Z57: =5.4+67.6 -> 73 | AA57: 6.8 | AB57: 4291.4 | AC57: =4.7+11.4+9+40.1+2.3 -> 67.5 | AD57: 1.5 | AE57: 9.7 | AF57: 6.9 | AG57: 0.6 | AH57: 50.6 | AI57: 32.4 | AJ57: =6.2+4.4 -> 10.6 | AK57: 11.4 | AL57: 12.1 | AM57: 1.9 | AN57: =12.2+19.9 -> 32.1 | AO57: 0 | AP57: 140.4 | AQ57: 0 | AR57: 0.1 | AS57: 210.9 | AT57: 334.5 | AU57: 0.7 | AV57: 0 | AW57: 0 | AX57: 10834.1 | AY57: 0
C58: Imports | D58: IMP_25: Fabricated metal products, except machinery and equipment | F58: 0.1 | G58: 0 | H58: 0 | I58: 3.2 | J58: 4 | K58: 0.8 | L58: 1.2 | M58: 2.8 | N58: 2.2 | O58: 1.5 | P58: 0 | Q58: 10.7 | R58: 189.4 | S58: 59.7 | T58: 20.5 | U58: 65.9 | V58: 48.2 | W58: 27.3 | X58: 9.1 | Y58: 8.2 | Z58: =2.6+13.2 -> 15.8 | AA58: 5.3 | AB58: 1962.5 | AC58: =2.2+4.3+3+25.1+1.5 -> 36.1 | AD58: 1.4 | AE58: 5.2 | AF58: 6.2 | AG58: 0.5 | AH58: 27.2 | AI58: 25.9 | AJ58: =3.7+8.8 -> 12.5 | AK58: 11.6 | AL58: 11.1 | AM58: 1.6 | AN58: =8.2+12 -> 20.2 | AO58: 0 | AP58: 337.9 | AQ58: 0 | AR58: 0 | AS58: 544.5 | AT58: 67.2 | AU58: 0.5 | AV58: 0 | AW58: 0 | AX58: 3551.3 | AY58: 0
C59: Imports | D59: IMP_26: Computer, electronic and optical products | F59: 0.1 | G59: 0 | H59: 0 | I59: 2 | J59: 3.9 | K59: 1.3 | L59: 0.4 | M59: 3.9 | N59: 2.9 | O59: 2.9 | P59: 0 | Q59: 3.8 | R59: 20 | S59: 4.4 | T59: 383.9 | U59: 160.4 | V59: 52.7 | W59: 26 | X59: 11.7 | Y59: 9.6 | Z59: =47.6+62.9 -> 110.5 | AA59: 2.8 | AB59: 11177.4 | AC59: =4.2+12.5+10.6+21.5+111.5 -> 160.3 | AD59: 3.3 | AE59: 134.3 | AF59: 1133.8 | AG59: 18.2 | AH59: 167.4 | AI59: 62 | AJ59: =35.8+44.8 -> 80.6 | AK59: 72.7 | AL59: 101 | AM59: 7.2 | AN59: =99.4+240.8 -> 340.2 | AO59: 0 | AP59: 9143.6 | AQ59: 0 | AR59: 0.2 | AS59: 5931.7 | AT59: 30032.9 | AU59: 28 | AV59: 0 | AW59: 0 | AX59: 59402.6 | AY59: 0
C60: Imports | D60: IMP_27: Electrical equipment | F60: 0 | G60: 0 | H60: 0 | I60: 1.7 | J60: 3 | K60: 0.6 | L60: 0.4 | M60: 2.3 | N60: 2.3 | O60: 1.4 | P60: 0 | Q60: 4.9 | R60: 39.6 | S60: 5.3 | T60: 116.7 | U60: 532.5 | V60: 94.1 | W60: 44.3 | X60: 13.2 | Y60: 12.1 | Z60: =69.2+55.9 -> 125.1 | AA60: 6.2 | AB60: 7475.3 | AC60: =4.8+10.3+5.6+15.7+57.3 -> 93.7 | AD60: 2.1 | AE60: 68.7 | AF60: 493 | AG60: 4.6 | AH60: 68.6 | AI60: 82.6 | AJ60: =20.9+38.7 -> 59.6 | AK60: 33.8 | AL60: 42.4 | AM60: 3 | AN60: =58.8+150 -> 208.8 | AO60: 0 | AP60: 3707 | AQ60: 0 | AR60: 0.1 | AS60: 1859.7 | AT60: 98.9 | AU60: 11.8 | AV60: 0 | AW60: 0 | AX60: 15322.5 | AY60: 0
C61: Imports | D61: IMP_28: Machinery and equipment n.e.c. | F61: 0.3 | G61: 0 | H61: 0 | I61: 14.2 | J61: 13.6 | K61: 3.4 | L61: 2.4 | M61: 12.1 | N61: 5.6 | O61: 5 | P61: 0 | Q61: 27.8 | R61: 219.2 | S61: 37.6 | T61: 24.8 | U61: 67.4 | V61: 223.3 | W61: 109 | X61: 37.5 | Y61: 20.8 | Z61: =116+19.5 -> 135.5 | AA61: 3.1 | AB61: 687.9 | AC61: =7.9+65.1+93.9+160.4+15.1 -> 342.4 | AD61: 3.6 | AE61: 9.5 | AF61: 32.8 | AG61: 0.4 | AH61: 235.2 | AI61: 57.6 | AJ61: =2.7+8 -> 10.7 | AK61: 13.3 | AL61: 17.8 | AM61: 29.6 | AN61: =12.4+19.5 -> 31.9 | AO61: 0 | AP61: 442.6 | AQ61: 0 | AR61: 0.2 | AS61: 6726.7 | AT61: 1303.6 | AU61: 0.8 | AV61: 0 | AW61: 0 | AX61: 10813.8 | AY61: 0
C62: Imports | D62: IMP_29: Motor vehicles, trailers and semi-trailers | F62: 0 | G62: 0 | H62: 0 | I62: 0.3 | J62: 0.6 | K62: 0.3 | L62: 0.1 | M62: 0.5 | N62: 0.2 | O62: 0.2 | P62: 0 | Q62: 1.4 | R62: 6.5 | S62: 1.1 | T62: 2.1 | U62: 6.1 | V62: 8.5 | W62: 157.4 | X62: 4.3 | Y62: 1.1 | Z62: =0.9+22.4 -> 23.3 | AA62: 0.3 | AB62: 406.1 | AC62: =20.3+19.1+13.7+5+15 -> 73.1 | AD62: 0.9 | AE62: 11.5 | AF62: 17.4 | AG62: 0.4 | AH62: 30.2 | AI62: 4.7 | AJ62: =2.2+9.6 -> 11.8 | AK62: 33.5 | AL62: 1.5 | AM62: 0.9 | AN62: =20.1+27.7 -> 47.8 | AO62: 0 | AP62: 1356.5 | AQ62: 0 | AR62: 0.1 | AS62: 1805.2 | AT62: 62 | AU62: 13.1 | AV62: 0 | AW62: 0 | AX62: 4090.8 | AY62: 0
C63: Imports | D63: IMP_30: Other transport equipment | F63: 0 | G63: 0 | H63: 0 | I63: 0.1 | J63: 0.4 | K63: 0.1 | L63: 0.1 | M63: 0.5 | N63: 0.1 | O63: 0.2 | P63: 0 | Q63: 1.1 | R63: 5.4 | S63: 0.6 | T63: 1.1 | U63: 2.2 | V63: 4.5 | W63: 189.6 | X63: 120.9 | Y63: 4.4 | Z63: =0.3+20.1 -> 20.4 | AA63: 0.2 | AB63: 455.2 | AC63: =16.4+49.3+79.6+5.5+12.8 -> 163.6 | AD63: 0.8 | AE63: 20.1 | AF63: 10.1 | AG63: 0.3 | AH63: 49.6 | AI63: 3.8 | AJ63: =4.2+7.6 -> 11.8 | AK63: 87.5 | AL63: 1 | AM63: 0.7 | AN63: =26+38.5 -> 64.5 | AO63: 0 | AP63: 873 | AQ63: 0 | AR63: 0 | AS63: 4731.6 | AT63: 944.3 | AU63: 0.3 | AV63: 0 | AW63: 0 | AX63: 7770.4 | AY63: 0
C64: Imports | D64: IMP_31T33: Other manufacturing; repair and installation of machinery and equipment | F64: 0.1 | G64: 0 | H64: 0 | I64: 1 | J64: 2.9 | K64: 1.3 | L64: 0.4 | M64: 4.9 | N64: 0.2 | O64: 0.6 | P64: 0 | Q64: 1.4 | R64: 30.3 | S64: 4.6 | T64: 2.6 | U64: 3.8 | V64: 2.5 | W64: 5.2 | X64: 2.8 | Y64: 2.8 | Z64: =3.1+7.8 -> 10.9 | AA64: 5.8 | AB64: 310.8 | AC64: =7.1+11.6+18+4.8+4.9 -> 46.4 | AD64: 2.9 | AE64: 7.9 | AF64: 13 | AG64: 0.4 | AH64: 294.8 | AI64: 56.9 | AJ64: =2.8+7.3 -> 10.1 | AK64: 31.5 | AL64: 33.1 | AM64: 4.3 | AN64: =22.9+16.2 -> 39.1 | AO64: 0 | AP64: 958.8 | AQ64: 0 | AR64: 0.1 | AS64: 339.2 | AT64: 8494.4 | AU64: 82.2 | AV64: 0 | AW64: 0 | AX64: 10821.1 | AY64: 0
C65: Imports | D65: IMP_35T39: Electricity, gas, water supply, sewerage, waste and remediation services | F65: 0.1 | G65: 0 | H65: 0 | I65: ='[1]OECD.Stat export'!$L$76+'[1]OECD.Stat export'!$L$77 -> 0.1 | J65: ='[1]OECD.Stat export'!$N$76+'[1]OECD.Stat export'!$N$77 -> 15.8 | K65: ='[1]OECD.Stat export'!$P$76+'[1]OECD.Stat export'!$P$77 -> 2.2 | L65: ='[1]OECD.Stat export'!$R$76+'[1]OECD.Stat export'!$R$77 -> 1.4 | M65: ='[1]OECD.Stat export'!$T$76+'[1]OECD.Stat export'!$T$77 -> 11.7 | N65: ='[1]OECD.Stat export'!$V$76+'[1]OECD.Stat export'!$V$77 -> 0.1 | O65: ='[1]OECD.Stat export'!$X$76+'[1]OECD.Stat export'!$Z$76+'[1]OECD.Stat export'!$X$77+'[1]OECD.Stat export'!$Z$77 -> 0.4 | P65: 0 | Q65: ='[1]OECD.Stat export'!$AD$76+'[1]OECD.Stat export'!$AD$77 -> 0.2 | R65: ='[1]OECD.Stat export'!$AF$76+'[1]OECD.Stat export'!$AF$77 -> 2.7 | S65: ='[1]OECD.Stat export'!$AH$76+'[1]OECD.Stat export'!$AH$77 -> 0.2 | T65: ='[1]OECD.Stat export'!$AJ$76+'[1]OECD.Stat export'!$AJ$77 -> 0.2 | U65: ='[1]OECD.Stat export'!$AL$76+'[1]OECD.Stat export'!$AL$77 -> 0.4 | V65: ='[1]OECD.Stat export'!$AN$76+'[1]OECD.Stat export'!$AN$77 -> 0.2 | W65: ='[1]OECD.Stat export'!$AP$76+'[1]OECD.Stat export'!$AP$77 -> 0.2 | X65: ='[1]OECD.Stat export'!$AR$76+'[1]OECD.Stat export'!$AR$77 -> 0.1 | Y65: ='[1]OECD.Stat export'!$AT$76+'[1]OECD.Stat export'!$AT$77 -> 0.1 | Z65: ='[1]OECD.Stat export'!$AV$76+'[1]OECD.Stat export'!$AX$76+'[1]OECD.Stat export'!$AV$77+'[1]OECD.Stat export'!$AX$77 -> 60.4 | AA65: ='[1]OECD.Stat export'!$AZ$76+'[1]OECD.Stat export'!$AZ$77 -> 6.9 | AB65: ='[1]OECD.Stat export'!$BB$76+'[1]OECD.Stat export'!$BB$77 -> 64.5 | AC65: ='[1]OECD.Stat export'!$BD$76+'[1]OECD.Stat export'!$BF$76+'[1]OECD.Stat export'!$BH$76+'[1]OECD.Stat export'!$BJ$76+'[1]OECD.Stat export'!$BL$76+'[1]OECD.Stat export'!$BD$77+'[1]OECD.Stat export'!$BF$77+'[1]OECD.Stat export'!$BH$77+'[1]OECD.Stat export'!$BJ$77+'[1]OECD.Stat export'!$BL$77 -> 93.6 | AD65: ='[1]OECD.Stat export'!$BN$76+'[1]OECD.Stat export'!$BN$77 -> 61.8 | AE65: ='[1]OECD.Stat export'!$BP$76+'[1]OECD.Stat export'!$BP$77 -> 10.4 | AF65: ='[1]OECD.Stat export'!$BR$76+'[1]OECD.Stat export'!$BR$77 -> 15.7 | AG65: ='[1]OECD.Stat export'!$BT$76+'[1]OECD.Stat export'!$BT$77 -> 0.6 | AH65: ='[1]OECD.Stat export'!$BV$76+'[1]OECD.Stat export'!$BV$77 -> 71.5 | AI65: ='[1]OECD.Stat export'!$BX$76+'[1]OECD.Stat export'!$BX$77 -> 174.6 | AJ65: ='[1]OECD.Stat export'!$BZ$76+'[1]OECD.Stat export'!$CB$76+'[1]OECD.Stat export'!$BZ$77+'[1]OECD.Stat export'!$CB$77 -> 8.8 | AK65: ='[1]OECD.Stat export'!CD$76+'[1]OECD.Stat export'!CD$77 -> 22.8 | AL65: ='[1]OECD.Stat export'!CF$76+'[1]OECD.Stat export'!CF$77 -> 19.1 | AM65: ='[1]OECD.Stat export'!CH$76+'[1]OECD.Stat export'!CH$77 -> 31.2 | AN65: ='[1]OECD.Stat export'!$CJ$76+'[1]OECD.Stat export'!$CL$76+'[1]OECD.Stat export'!$CJ$77+'[1]OECD.Stat export'!$CL$77 -> 36 | AO65: 0 | AP65: ='[1]OECD.Stat export'!CP$76+'[1]OECD.Stat export'!CP$77 -> 214.4 | AQ65: ='[1]OECD.Stat export'!CR$76+'[1]OECD.Stat export'!CR$77 -> 0.4 | AR65: ='[1]OECD.Stat export'!CT$76+'[1]OECD.Stat export'!CT$77 -> 0 | AS65: ='[1]OECD.Stat export'!CV$76+'[1]OECD.Stat export'!CV$77 -> 5.1 | AT65: ='[1]OECD.Stat export'!CX$76+'[1]OECD.Stat export'!CX$77 -> 7.6 | AU65: ='[1]OECD.Stat export'!CZ$76+'[1]OECD.Stat export'!CZ$77 -> 0.6 | AV65: ='[1]OECD.Stat export'!DB$76+'[1]OECD.Stat export'!DB$77 -> 0 | AW65: 0 | AX65: ='[1]OECD.Stat export'!$DF$76+'[1]OECD.Stat export'!$DF$77 -> 942.2 | AY65: 0
C66: Imports | D66: IMP_41T43: Construction | F66: 0 | G66: 0 | H66: 0 | I66: 0 | J66: 0.4 | K66: 0.2 | L66: 0 | M66: 0.3 | N66: 0 | O66: 0.2 | P66: 0 | Q66: 0.3 | R66: 2 | S66: 0.2 | T66: 0.2 | U66: 0.4 | V66: 0.2 | W66: 0.2 | X66: 0.1 | Y66: 0 | Z66: =0.2+0.2 -> 0.4 | AA66: 0.6 | AB66: 9.3 | AC66: =0.4+0.7+0.8+0.8+0.2 -> 2.9 | AD66: 0.5 | AE66: 0.2 | AF66: 0.8 | AG66: 0 | AH66: 2 | AI66: 1.3 | AJ66: =0.3+0.3 -> 0.6 | AK66: 0.5 | AL66: 0.3 | AM66: 0.4 | AN66: 0.6 | AO66: 0 | AP66: 12.4 | AQ66: 0 | AR66: 0 | AS66: 6 | AT66: 9.7 | AU66: 1.6 | AV66: 0 | AW66: 0 | AX66: 55 | AY66: 0
C67: Imports | D67: IMP_45T47: Wholesale and retail trade; repair of motor vehicles | F67: 4.3 | G67: 0 | H67: 0 | I67: 10.3 | J67: 180 | K67: 123.4 | L67: 14.4 | M67: 131.4 | N67: 15.4 | O67: =69+30.3 -> 99.3 | P67: 0 | Q67: 48.6 | R67: 523.6 | S67: 47.5 | T67: 69.3 | U67: 139.6 | V67: 59.8 | W67: 70.5 | X67: 19.3 | Y67: 12.2 | Z67: =86.5+95.1 -> 181.6 | AA67: 202.8 | AB67: 3388 | AC67: =135.6+334.9+331.4+261.8+77.2 -> 1140.9 | AD67: 352.3 | AE67: 76.4 | AF67: 231.8 | AG67: 6.1 | AH67: 397.8 | AI67: 133.8 | AJ67: =34.9+67.3 -> 102.2 | AK67: 99.9 | AL67: 105 | AM67: 151.6 | AN67: =75.8+177 -> 252.8 | AO67: 0 | AP67: 8042.2 | AQ67: 0.1 | AR67: 0.4 | AS67: 2123.7 | AT67: 5071.5 | AU67: 108.4 | AV67: 0 | AW67: 0 | AX67: 23738.3 | AY67: 0
C68: Imports | D68: IMP_49T53: Transportation and storage | F68: =1.2+0.1+0.1+0.1+0.3+0.1 -> 1.9 | G68: 0 | H68: 0 | I68: ='[1]OECD.Stat export'!$L$80+'[1]OECD.Stat export'!$L$81+'[1]OECD.Stat export'!$L$82+'[1]OECD.Stat export'!$L$83+'[1]OECD.Stat export'!$L$84 -> 10.1 | J68: ='[1]OECD.Stat export'!$L$80+'[1]OECD.Stat export'!$L$81+'[1]OECD.Stat export'!$L$82+'[1]OECD.Stat export'!$L$83+'[1]OECD.Stat export'!$L$84 -> 10.1 | K68: ='[1]OECD.Stat export'!$L$80+'[1]OECD.Stat export'!$L$81+'[1]OECD.Stat export'!$L$82+'[1]OECD.Stat export'!$L$83+'[1]OECD.Stat export'!$L$84 -> 10.1 | L68: ='[1]OECD.Stat export'!$L$80+'[1]OECD.Stat export'!$L$81+'[1]OECD.Stat export'!$L$82+'[1]OECD.Stat export'!$L$83+'[1]OECD.Stat export'!$L$84 -> 10.1 | M68: ='[1]OECD.Stat export'!$L$80+'[1]OECD.Stat export'!$L$81+'[1]OECD.Stat export'!$L$82+'[1]OECD.Stat export'!$L$83+'[1]OECD.Stat export'!$L$84 -> 10.1 | N68: ='[1]OECD.Stat export'!$L$80+'[1]OECD.Stat export'!$L$81+'[1]OECD.Stat export'!$L$82+'[1]OECD.Stat export'!$L$83+'[1]OECD.Stat export'!$L$84 -> 10.1 | O68: ='[1]OECD.Stat export'!$X$80+'[1]OECD.Stat export'!$Z$80+'[1]OECD.Stat export'!$X$81+'[1]OECD.Stat export'!$Z$81+'[1]OECD.Stat export'!$X$82+'[1]OECD.Stat export'!$Z$82+'[1]OECD.Stat export'!$X$83+'[1]OECD.Stat export'!$Z$83+'[1]OECD.Stat export'!$X$84+'[1]OECD.Stat export'!$Z$84 -> 20.9 | P68: 0 | Q68: ='[1]OECD.Stat export'!$AD$80+'[1]OECD.Stat export'!$AD$81+'[1]OECD.Stat export'!$AD$82+'[1]OECD.Stat export'!$AD$83+'[1]OECD.Stat export'!$AD$84 -> 20.3 | R68: ='[1]OECD.Stat export'!$AF$80+'[1]OECD.Stat export'!$AF$81+'[1]OECD.Stat export'!$AF$82+'[1]OECD.Stat export'!$AF$83+'[1]OECD.Stat export'!$AF$84 -> 186 | S68: ='[1]OECD.Stat export'!AH$80+'[1]OECD.Stat export'!AH$81+'[1]OECD.Stat export'!AH$82+'[1]OECD.Stat export'!AH$83+'[1]OECD.Stat export'!AH$84 -> 18.1 | T68: ='[1]OECD.Stat export'!AJ$80+'[1]OECD.Stat export'!AJ$81+'[1]OECD.Stat export'!AJ$82+'[1]OECD.Stat export'!AJ$83+'[1]OECD.Stat export'!AJ$84 -> 19.9 | U68: ='[1]OECD.Stat export'!AL$80+'[1]OECD.Stat export'!AL$81+'[1]OECD.Stat export'!AL$82+'[1]OECD.Stat export'!AL$83+'[1]OECD.Stat export'!AL$84 -> 44.4 | V68: ='[1]OECD.Stat export'!AN$80+'[1]OECD.Stat export'!AN$81+'[1]OECD.Stat export'!AN$82+'[1]OECD.Stat export'!AN$83+'[1]OECD.Stat export'!AN$84 -> 20.1 | W68: ='[1]OECD.Stat export'!AP$80+'[1]OECD.Stat export'!AP$81+'[1]OECD.Stat export'!AP$82+'[1]OECD.Stat export'!AP$83+'[1]OECD.Stat export'!AP$84 -> 18.1 | X68: ='[1]OECD.Stat export'!AR$80+'[1]OECD.Stat export'!AR$81+'[1]OECD.Stat export'!AR$82+'[1]OECD.Stat export'!AR$83+'[1]OECD.Stat export'!AR$84 -> 6.9 | Y68: ='[1]OECD.Stat export'!AT$80+'[1]OECD.Stat export'!AT$81+'[1]OECD.Stat export'!AT$82+'[1]OECD.Stat export'!AT$83+'[1]OECD.Stat export'!AT$84 -> 4.6 | Z68: ='[1]OECD.Stat export'!$AV$80+'[1]OECD.Stat export'!$AX$80+'[1]OECD.Stat export'!$AV$81+'[1]OECD.Stat export'!$AX$82+'[1]OECD.Stat export'!$AX$81+'[1]OECD.Stat export'!$AV$82+'[1]OECD.Stat export'!$AV$83+'[1]OECD.Stat export'!$AX$83+'[1]OECD.Stat export'!$AV$84+'[1]OECD.Stat export'!$AX$84 -> 54.8 | AA68: ='[1]OECD.Stat export'!$AZ$80+'[1]OECD.Stat export'!$AZ$81+'[1]OECD.Stat export'!$AZ$82+'[1]OECD.Stat export'!$AZ$83+'[1]OECD.Stat export'!$AZ$84 -> 57.6 | AB68: ='[1]OECD.Stat export'!$BB$80+'[1]OECD.Stat export'!$BB$81+'[1]OECD.Stat export'!$BB$82+'[1]OECD.Stat export'!$AZ$83+'[1]OECD.Stat export'!$BB$84 -> 1235.1 | AC68: ='[1]OECD.Stat export'!$BD$80+'[1]OECD.Stat export'!$BF$80+'[1]OECD.Stat export'!$BH$80+'[1]OECD.Stat export'!$BJ$80+'[1]OECD.Stat export'!$BL$80+'[1]OECD.Stat export'!$BD$81+'[1]OECD.Stat export'!$BF$81+'[1]OECD.Stat export'!$BH$81+'[1]OECD.Stat export'!$BJ$81+'[1]OECD.Stat export'!$BL$81+'[1]OECD.Stat export'!$BD$82+'[1]OECD.Stat export'!$BF$82+'[1]OECD.Stat export'!$BH$82+'[1]OECD.Stat export'!$BJ$82+'[1]OECD.Stat export'!$BL$82+'[1]OECD.Stat export'!$BD$83+'[1]OECD.Stat export'!$BF$83+'[1]OECD.Stat export'!$BH$83+'[1]OECD.Stat export'!$BJ$83+'[1]OECD.Stat export'!$BL$83+'[1]OECD.Stat export'!$BD$84+'[1]OECD.Stat export'!$BF$84+'[1]OECD.Stat export'!$BH$84+'[1]OECD.Stat export'!$BJ$84+'[1]OECD.Stat export'!$BL$84 -> 1924.7 | AD68: ='[1]OECD.Stat export'!BN$80+'[1]OECD.Stat export'!BN$81+'[1]OECD.Stat export'!BN$82+'[1]OECD.Stat export'!BN$83+'[1]OECD.Stat export'!BN$84 -> 98.8 | AE68: ='[1]OECD.Stat export'!BP$80+'[1]OECD.Stat export'!BP$81+'[1]OECD.Stat export'!BP$82+'[1]OECD.Stat export'!BP$83+'[1]OECD.Stat export'!BP$84 -> 29.8 | AF68: ='[1]OECD.Stat export'!BR$80+'[1]OECD.Stat export'!BR$81+'[1]OECD.Stat export'!BR$82+'[1]OECD.Stat export'!BR$83+'[1]OECD.Stat export'!BR$84 -> 264.1 | AG68: ='[1]OECD.Stat export'!BT$80+'[1]OECD.Stat export'!BT$81+'[1]OECD.Stat export'!BT$82+'[1]OECD.Stat export'!BT$83+'[1]OECD.Stat export'!BT$84 -> 5.1 | AH68: ='[1]OECD.Stat export'!BV$80+'[1]OECD.Stat export'!BV$81+'[1]OECD.Stat export'!BV$82+'[1]OECD.Stat export'!BV$83+'[1]OECD.Stat export'!BV$84 -> 475 | AI68: ='[1]OECD.Stat export'!BX$80+'[1]OECD.Stat export'!BX$81+'[1]OECD.Stat export'!BX$82+'[1]OECD.Stat export'!BX$83+'[1]OECD.Stat export'!BX$84 -> 87.6 | AJ68: ='[1]OECD.Stat export'!$BZ$80+'[1]OECD.Stat export'!$CB$80+'[1]OECD.Stat export'!$BZ$81+'[1]OECD.Stat export'!$CB$82+'[1]OECD.Stat export'!$CB$81+'[1]OECD.Stat export'!$BZ$82+'[1]OECD.Stat export'!$BZ$83+'[1]OECD.Stat export'!$CB$83+'[1]OECD.Stat export'!$BZ$84+'[1]OECD.Stat export'!$CB$84 -> 86.3 | AK68: ='[1]OECD.Stat export'!CD$80+'[1]OECD.Stat export'!CD$81+'[1]OECD.Stat export'!CD$82+'[1]OECD.Stat export'!CD$83+'[1]OECD.Stat export'!CD$84 -> 45.3 | AL68: ='[1]OECD.Stat export'!CF$80+'[1]OECD.Stat export'!CF$81+'[1]OECD.Stat export'!CF$82+'[1]OECD.Stat export'!CF$83+'[1]OECD.Stat export'!CF$84 -> 37.9 | AM68: ='[1]OECD.Stat export'!CH$80+'[1]OECD.Stat export'!CH$81+'[1]OECD.Stat export'!CH$82+'[1]OECD.Stat export'!CH$83+'[1]OECD.Stat export'!CH$84 -> 45.1 | AN68: ='[1]OECD.Stat export'!$CJ$80+'[1]OECD.Stat export'!$CL$80+'[1]OECD.Stat export'!$CJ$81+'[1]OECD.Stat export'!$CL$81+'[1]OECD.Stat export'!$CJ$82+'[1]OECD.Stat export'!$CL$82+'[1]OECD.Stat export'!$CJ$83+'[1]OECD.Stat export'!$CL$83+'[1]OECD.Stat export'!$CJ$84+'[1]OECD.Stat export'!$CL$84 -> 105.1 | AO68: 0 | AP68: ='[1]OECD.Stat export'!CP$80+'[1]OECD.Stat export'!CP$81+'[1]OECD.Stat export'!CP$82+'[1]OECD.Stat export'!CP$83+'[1]OECD.Stat export'!CP$84 -> 2106.2 | AQ68: ='[1]OECD.Stat export'!CR$80+'[1]OECD.Stat export'!CR$81+'[1]OECD.Stat export'!CR$82+'[1]OECD.Stat export'!CR$83+'[1]OECD.Stat export'!CR$84 -> 1.7 | AR68: ='[1]OECD.Stat export'!CT$80+'[1]OECD.Stat export'!CT$81+'[1]OECD.Stat export'!CT$82+'[1]OECD.Stat export'!CT$83+'[1]OECD.Stat export'!CT$84 -> 0.1 | AS68: ='[1]OECD.Stat export'!CV$80+'[1]OECD.Stat export'!CV$81+'[1]OECD.Stat export'!CV$82+'[1]OECD.Stat export'!CV$83+'[1]OECD.Stat export'!CV$84 -> 682 | AT68: ='[1]OECD.Stat export'!CX$80+'[1]OECD.Stat export'!CX$81+'[1]OECD.Stat export'!CX$82+'[1]OECD.Stat export'!CX$83+'[1]OECD.Stat export'!CX$84 -> 1152.3 | AU68: ='[1]OECD.Stat export'!CZ$80+'[1]OECD.Stat export'!CZ$81+'[1]OECD.Stat export'!CZ$82+'[1]OECD.Stat export'!CZ$83+'[1]OECD.Stat export'!CZ$84 -> 636.1 | AV68: ='[1]OECD.Stat export'!DB$80+'[1]OECD.Stat export'!DB$81+'[1]OECD.Stat export'!DB$82+'[1]OECD.Stat export'!DB$83+'[1]OECD.Stat export'!DB$84 -> 0 | AW68: 0 | AX68: ='[1]OECD.Stat export'!DF$80+'[1]OECD.Stat export'!DF$81+'[1]OECD.Stat export'!DF$82+'[1]OECD.Stat export'!DF$83+'[1]OECD.Stat export'!DF$84 -> 9887 | AY68: 0
C69: Imports | D69: IMP_55T56: Accomodation and food services | F69: 0 | G69: 0 | H69: 0 | I69: 0 | J69: 0.3 | K69: 0.1 | L69: 0 | M69: 0.2 | N69: 0 | O69: 0 | P69: 0 | Q69: 0 | R69: 0.2 | S69: 0 | T69: 0 | U69: 0.1 | V69: 0 | W69: 0 | X69: 0 | Y69: 0 | Z69: 0.2 | AA69: 0.5 | AB69: 2.3 | AC69: =0.2+0.7+0.6+0.3+0.2 -> 2 | AD69: 0.8 | AE69: 0.1 | AF69: 0.3 | AG69: 0 | AH69: 0.9 | AI69: 0.3 | AJ69: 0.2 | AK69: 0.1 | AL69: 0.1 | AM69: 0.3 | AN69: =0.2+0.2 -> 0.4 | AO69: 0 | AP69: 10.7 | AQ69: 0 | AR69: 0 | AS69: 1.2 | AT69: 4.6 | AU69: 1302.9 | AV69: 0 | AW69: 0 | AX69: 1329.3 | AY69: 0
C70: Imports | D70: IMP_58T60: Publishing, audiovisual and broadcasting activities | F70: 1.6 | G70: 0 | H70: 0 | I70: 0 | J70: 36.3 | K70: 10 | L70: 0.6 | M70: 12.8 | N70: 0.2 | O70: 0.3 | P70: 0 | Q70: 0.6 | R70: 2 | S70: 0.2 | T70: 0.9 | U70: 1.3 | V70: 0.5 | W70: 0.3 | X70: 0.1 | Y70: 0.2 | Z70: =6.8+4.6 -> 11.4 | AA70: 55.6 | AB70: 189.8 | AC70: =28+44.4+40+42.5+9.8 -> 164.7 | AD70: 9.7 | AE70: 147.8 | AF70: 55.3 | AG70: 2 | AH70: 199.2 | AI70: 85.6 | AJ70: =23.9+10.2 -> 34.1 | AK70: 10.2 | AL70: 21.3 | AM70: 81.2 | AN70: =29.6+17.7 -> 47.3 | AO70: 0 | AP70: 615.4 | AQ70: 1.2 | AR70: 0.1 | AS70: 67.8 | AT70: 19 | AU70: 21.7 | AV70: 0 | AW70: 0 | AX70: 1908.6 | AY70: 0
C71: Imports | D71: IMP_61: Telecommunications | F71: 0 | G71: 0 | H71: 0 | I71: 0 | J71: 1.8 | K71: 0.6 | L71: 0.2 | M71: 1.1 | N71: 0 | O71: 0 | P71: 0 | Q71: 0 | R71: 0.8 | S71: 0.1 | T71: 0.2 | U71: 0.2 | V71: 0.1 | W71: 0.1 | X71: 0 | Y71: 0 | Z71: 1.5 | AA71: 1.7 | AB71: 36 | AC71: =2+25.9+4.4+3.7+3.4 -> 39.4 | AD71: 2.6 | AE71: 3.8 | AF71: 30.1 | AG71: 0.7 | AH71: 46.8 | AI71: 12.2 | AJ71: =2.4+3.3 -> 5.7 | AK71: 2.8 | AL71: 1.9 | AM71: 2.7 | AN71: =2.2+3.7 -> 5.9 | AO71: 0 | AP71: 48.2 | AQ71: 0.2 | AR71: 0 | AS71: 11.2 | AT71: 9.2 | AU71: 84.7 | AV71: 0 | AW71: 0 | AX71: 352.5 | AY71: 0
C72: Imports | D72: IMP_62T63: IT and other information services | F72: 0.1 | G72: 0 | H72: 0 | I72: 0 | J72: 10.5 | K72: 3.5 | L72: 1.3 | M72: 7.4 | N72: 0 | O72: 0.1 | P72: 0 | Q72: 0.1 | R72: 2.4 | S72: 0.2 | T72: 0.4 | U72: 0.6 | V72: 0.2 | W72: 0.4 | X72: 0.1 | Y72: 0.1 | Z72: 5.4 | AA72: 8.2 | AB72: 162.1 | AC72: =12+10.9+19.1+22.1+9.8 -> 73.9 | AD72: 10 | AE72: 12.1 | AF72: 57.6 | AG72: 6.3 | AH72: 235.9 | AI72: 57.3 | AJ72: =6.7+7.5 -> 14.2 | AK72: 20.6 | AL72: 11.5 | AM72: 11.7 | AN72: =6.8+9.6 -> 16.4 | AO72: 0 | AP72: 51.1 | AQ72: 0 | AR72: 0.1 | AS72: 111.9 | AT72: 24.9 | AU72: 1.9 | AV72: 0 | AW72: 0 | AX72: 921.1 | AY72: 0
C73: Imports | D73: IMP_64T66: Financial and insurance activities | F73: 0 | G73: 0 | H73: 0 | I73: 0.1 | J73: 13 | K73: 3.8 | L73: 1.5 | M73: 12 | N73: 0 | O73: 0 | P73: 0 | Q73: 0.1 | R73: 0.6 | S73: 0.1 | T73: 0.1 | U73: 0.1 | V73: 0.1 | W73: 0.1 | X73: 0 | Y73: 0 | Z73: =9.6+7.8 -> 17.4 | AA73: 8.5 | AB73: 235 | AC73: =16.8+26.9+10.3+34.2+6.5 -> 94.7 | AD73: 14 | AE73: 9.5 | AF73: 24.1 | AG73: 2.3 | AH73: 1287.2 | AI73: 357.9 | AJ73: =12.4+23.6 -> 36 | AK73: 6.4 | AL73: 14.7 | AM73: 11.4 | AN73: =11.2+29.8 -> 41 | AO73: 0 | AP73: 661.8 | AQ73: 0 | AR73: 14 | AS73: 31.9 | AT73: 2.6 | AU73: 70.5 | AV73: 0 | AW73: 0 | AX73: 2972.6 | AY73: 0
C74: Imports | D74: IMP_68: Real estate activities | F74: 0 | G74: 0 | H74: 0 | I74: 0 | J74: 0.5 | K74: 0.2 | L74: 0.1 | M74: 0.4 | N74: 0 | O74: 0 | P74: 0 | Q74: 0 | R74: 0.2 | S74: 0 | T74: 0.1 | U74: 0.1 | V74: 0 | W74: 0 | X74: 0 | Y74: 0 | Z74: =0.4+1.3 -> 1.7 | AA74: 0.9 | AB74: 30.6 | AC74: =1.2+1.4+1.4+9.4+0.6 -> 14 | AD74: 5.9 | AE74: 1.8 | AF74: 2.1 | AG74: 0.2 | AH74: 18.6 | AI74: 16.3 | AJ74: =1.2+2.1 -> 3.3 | AK74: 0.5 | AL74: 1.3 | AM74: 2.3 | AN74: =2.6+6.5 -> 9.1 | AO74: 0 | AP74: 25 | AQ74: 0 | AR74: 0.1 | AS74: 26 | AT74: 4.1 | AU74: 229.3 | AV74: 0 | AW74: 0 | AX74: 395.1 | AY74: 0
C75: Imports | D75: IMP_69T82: Other business sector services | F75: =0.2+0.1 -> 0.3 | G75: 0 | H75: 0 | I75: ='[1]OECD.Stat export'!L$91+'[1]OECD.Stat export'!L$92 -> 0.7 | J75: ='[1]OECD.Stat export'!N$91+'[1]OECD.Stat export'!N$92 -> 20.7 | K75: ='[1]OECD.Stat export'!P$91+'[1]OECD.Stat export'!P$92 -> 6 | L75: ='[1]OECD.Stat export'!R$91+'[1]OECD.Stat export'!R$92 -> 4.1 | M75: ='[1]OECD.Stat export'!T$91+'[1]OECD.Stat export'!T$92 -> 19.2 | N75: ='[1]OECD.Stat export'!V$91+'[1]OECD.Stat export'!V$92 -> 0.1 | O75: ='[1]OECD.Stat export'!$X$91+'[1]OECD.Stat export'!$Z$91+'[1]OECD.Stat export'!$X$92+'[1]OECD.Stat export'!$Z$92 -> 0.7 | P75: 0 | Q75: ='[1]OECD.Stat export'!AD$91+'[1]OECD.Stat export'!AD$92 -> 0.3 | R75: ='[1]OECD.Stat export'!AF$91+'[1]OECD.Stat export'!AF$92 -> 3.6 | S75: ='[1]OECD.Stat export'!AH$91+'[1]OECD.Stat export'!AH$92 -> 0.3 | T75: ='[1]OECD.Stat export'!AJ$91+'[1]OECD.Stat export'!AJ$92 -> 0.6 | U75: ='[1]OECD.Stat export'!AL$91+'[1]OECD.Stat export'!AL$92 -> 1.4 | V75: ='[1]OECD.Stat export'!AN$91+'[1]OECD.Stat export'!AN$92 -> 0.9 | W75: ='[1]OECD.Stat export'!AP$91+'[1]OECD.Stat export'!AP$92 -> 1 | X75: ='[1]OECD.Stat export'!AR$91+'[1]OECD.Stat export'!AR$92 -> 0.4 | Y75: ='[1]OECD.Stat export'!AT$91+'[1]OECD.Stat export'!AT$92 -> 0.4 | Z75: ='[1]OECD.Stat export'!$AV$91+'[1]OECD.Stat export'!$AX$91+'[1]OECD.Stat export'!$AV$92+'[1]OECD.Stat export'!$AX$92 -> 15.4 | AA75: ='[1]OECD.Stat export'!AZ$91+'[1]OECD.Stat export'!AZ$92 -> 25.7 | AB75: ='[1]OECD.Stat export'!BB$91+'[1]OECD.Stat export'!BB$92 -> 485.7 | AC75: ='[1]OECD.Stat export'!$BD$91+'[1]OECD.Stat export'!$BF$91+'[1]OECD.Stat export'!$BH$91+'[1]OECD.Stat export'!$BJ$91+'[1]OECD.Stat export'!$BL$91+'[1]OECD.Stat export'!$BL$92+'[1]OECD.Stat export'!$BJ$92+'[1]OECD.Stat export'!$BH$92+'[1]OECD.Stat export'!$BF$92+'[1]OECD.Stat export'!$BD$92 -> 283 | AD75: ='[1]OECD.Stat export'!BP$91+'[1]OECD.Stat export'!BN$92 -> 24.7 | AE75: ='[1]OECD.Stat export'!BP$91+'[1]OECD.Stat export'!BP$92 -> 22.6 | AF75: ='[1]OECD.Stat export'!BR$91+'[1]OECD.Stat export'!BR$92 -> 92.8 | AG75: ='[1]OECD.Stat export'!BT$91+'[1]OECD.Stat export'!BT$92 -> 4.8 | AH75: ='[1]OECD.Stat export'!BV$91+'[1]OECD.Stat export'!BV$92 -> 322.9 | AI75: ='[1]OECD.Stat export'!BX$91+'[1]OECD.Stat export'!BX$92 -> 175.6 | AJ75: ='[1]OECD.Stat export'!$BZ$91+'[1]OECD.Stat export'!$CB$91+'[1]OECD.Stat export'!$BZ$92+'[1]OECD.Stat export'!$CB$92 -> 89 | AK75: ='[1]OECD.Stat export'!CD$91+'[1]OECD.Stat export'!CD$92 -> 36.6 | AL75: ='[1]OECD.Stat export'!CF$91+'[1]OECD.Stat export'!CF$92 -> 22 | AM75: ='[1]OECD.Stat export'!CH$91+'[1]OECD.Stat export'!CH$92 -> 35 | AN75: ='[1]OECD.Stat export'!CJ$91+'[1]OECD.Stat export'!CJ$92+'[1]OECD.Stat export'!$CL$91+'[1]OECD.Stat export'!$CL$92 -> 50.3 | AO75: 0 | AP75: ='[1]OECD.Stat export'!CP$91+'[1]OECD.Stat export'!CP$92 -> 124.7 | AQ75: ='[1]OECD.Stat export'!CR$91+'[1]OECD.Stat export'!CR$92 -> 1 | AR75: ='[1]OECD.Stat export'!CT$91+'[1]OECD.Stat export'!CT$92 -> 45.2 | AS75: ='[1]OECD.Stat export'!CV$91+'[1]OECD.Stat export'!CV$92 -> 86.1 | AT75: ='[1]OECD.Stat export'!CX$91+'[1]OECD.Stat export'!CX$92 -> 24.7 | AU75: ='[1]OECD.Stat export'!CZ$91+'[1]OECD.Stat export'!CZ$92 -> 105.9 | AV75: ='[1]OECD.Stat export'!DB$91+'[1]OECD.Stat export'!DB$92 -> 0 | AW75: 0 | AX75: ='[1]OECD.Stat export'!DF$91+'[1]OECD.Stat export'!DF$92 -> 2133.9 | AY75: 0
C76: Imports | D76: IMP_84: Public administration and defence; compulsory social security | F76: 0 | G76: 0 | H76: 0 | I76: 0 | J76: 0.9 | K76: 0.2 | L76: 0.1 | M76: 0.5 | N76: 0 | O76: 0.3 | P76: 0 | Q76: 0.1 | R76: 1.7 | S76: 0.1 | T76: 0.1 | U76: 0 | V76: 0.1 | W76: 0.1 | X76: 0 | Y76: 0 | Z76: 0.7 | AA76: 0.8 | AB76: 8.5 | AC76: =0.6+2.4+2.6+1.6+0.4 -> 7.6 | AD76: 3 | AE76: 0.4 | AF76: 1 | AG76: 0 | AH76: 3.2 | AI76: 1.2 | AJ76: 0.7 | AK76: 0.4 | AL76: 0.4 | AM76: 0.8 | AN76: 1 | AO76: 0 | AP76: 35.7 | AQ76: 0 | AR76: 0.2 | AS76: 4.4 | AT76: 12 | AU76: 4.7 | AV76: 0 | AW76: 0 | AX76: 91.6 | AY76: 0
C77: Imports | D77: IMP_85: Education | F77: 0 | G77: 0 | H77: 0 | I77: 0 | J77: 0.2 | K77: 0.1 | L77: 0 | M77: 0.1 | N77: 0 | O77: 0 | P77: 0 | Q77: 0 | R77: 0.1 | S77: 0 | T77: 0 | U77: 0.2 | V77: 0 | W77: 0 | X77: 0 | Y77: 0 | Z77: 0.1 | AA77: 0.2 | AB77: 2.2 | AC77: =0.2+0.5+0.4+0.4+0.1 -> 1.6 | AD77: 0.2 | AE77: 0.1 | AF77: 0.4 | AG77: 0 | AH77: 1.5 | AI77: 0.6 | AJ77: 0.3 | AK77: 0.2 | AL77: 0.1 | AM77: 0.2 | AN77: 0.3 | AO77: 0 | AP77: 6 | AQ77: 0 | AR77: 0.1 | AS77: 1.4 | AT77: 5.3 | AU77: 135.5 | AV77: 0 | AW77: 0 | AX77: 157 | AY77: 0
C78: Imports | D78: IMP_86T88: Human health and social work | F78: 0 | G78: 0 | H78: 0 | I78: 0 | J78: 0.5 | K78: 0.3 | L78: 0 | M78: 0.3 | N78: 0 | O78: 0.3 | P78: 0 | Q78: 0.1 | R78: 0.6 | S78: 0.1 | T78: 0.1 | U78: 0.1 | V78: 0.1 | W78: 0.1 | X78: 0 | Y78: 0 | Z78: 0.4 | AA78: 0.5 | AB78: 7.5 | AC78: =0.4+1+0.9+0.7+2 -> 5 | AD78: 1 | AE78: 0.2 | AF78: 0.7 | AG78: 0 | AH78: 1.5 | AI78: 0.5 | AJ78: 0.3 | AK78: 0.3 | AL78: 0.3 | AM78: 0.5 | AN78: 0.6 | AO78: 0 | AP78: 18.6 | AQ78: 0 | AR78: 0 | AS78: 3.4 | AT78: 17.1 | AU78: 58.1 | AV78: 0 | AW78: 0 | AX78: 117.5 | AY78: 0
C79: Imports | D79: IMP_90T96: Arts, entertainment, recreation and other service activities | F79: 0 | G79: 0 | H79: 0 | I79: ='[1]OECD.Stat export'!L$96+'[1]OECD.Stat export'!L$97 -> 0 | J79: ='[1]OECD.Stat export'!N$96+'[1]OECD.Stat export'!N$97 -> 1.5 | K79: ='[1]OECD.Stat export'!P$96+'[1]OECD.Stat export'!P$97 -> 0.4 | L79: ='[1]OECD.Stat export'!R$96+'[1]OECD.Stat export'!R$97 -> 0.1 | M79: ='[1]OECD.Stat export'!T$96+'[1]OECD.Stat export'!T$97 -> 1.1 | N79: ='[1]OECD.Stat export'!V$96+'[1]OECD.Stat export'!V$97 -> 0.1 | O79: ='[1]OECD.Stat export'!$X$96+'[1]OECD.Stat export'!$Z$96+'[1]OECD.Stat export'!$X$97+'[1]OECD.Stat export'!$Z$97 -> 0.5 | P79: 0 | Q79: ='[1]OECD.Stat export'!AD$96+'[1]OECD.Stat export'!AD$97 -> 0.2 | R79: ='[1]OECD.Stat export'!AF$96+'[1]OECD.Stat export'!AF$97 -> 1.3 | S79: ='[1]OECD.Stat export'!AH$96+'[1]OECD.Stat export'!AH$97 -> 0.1 | T79: ='[1]OECD.Stat export'!AJ$96+'[1]OECD.Stat export'!AJ$97 -> 0.2 | U79: ='[1]OECD.Stat export'!AL$96+'[1]OECD.Stat export'!AL$97 -> 0.5 | V79: ='[1]OECD.Stat export'!AN$96+'[1]OECD.Stat export'!AN$97 -> 0.1 | W79: ='[1]OECD.Stat export'!AP$96+'[1]OECD.Stat export'!AP$97 -> 0.2 | X79: ='[1]OECD.Stat export'!AR$96+'[1]OECD.Stat export'!AR$97 -> 0 | Y79: ='[1]OECD.Stat export'!AT$96+'[1]OECD.Stat export'!AT$97 -> 0 | Z79: ='[1]OECD.Stat export'!$AV$96+'[1]OECD.Stat export'!$AX$96+'[1]OECD.Stat export'!$AV$97+'[1]OECD.Stat export'!$AX$97 -> 1.1 | AA79: ='[1]OECD.Stat export'!AZ$96+'[1]OECD.Stat export'!AZ$97 -> 1.4 | AB79: ='[1]OECD.Stat export'!BB$96+'[1]OECD.Stat export'!BB$97 -> 23 | AC79: ='[1]OECD.Stat export'!$BD$96+'[1]OECD.Stat export'!$BF$96+'[1]OECD.Stat export'!$BH$96+'[1]OECD.Stat export'!$BJ$96+'[1]OECD.Stat export'!$BL$96+'[1]OECD.Stat export'!$BL$97+'[1]OECD.Stat export'!$BJ$97+'[1]OECD.Stat export'!$BH$97+'[1]OECD.Stat export'!$BF$97+'[1]OECD.Stat export'!$BD$97 -> 14.2 | AD79: ='[1]OECD.Stat export'!BN$96+'[1]OECD.Stat export'!BN$97 -> 2 | AE79: ='[1]OECD.Stat export'!BP$96+'[1]OECD.Stat export'!BP$97 -> 8.9 | AF79: ='[1]OECD.Stat export'!BR$96+'[1]OECD.Stat export'!BR$97 -> 3.8 | AG79: ='[1]OECD.Stat export'!BT$96+'[1]OECD.Stat export'!BT$97 -> 0.1 | AH79: ='[1]OECD.Stat export'!BV$96+'[1]OECD.Stat export'!BV$97 -> 20.5 | AI79: ='[1]OECD.Stat export'!BX$96+'[1]OECD.Stat export'!BX$97 -> 13.5 | AJ79: ='[1]OECD.Stat export'!$BZ$96+'[1]OECD.Stat export'!$CB$96+'[1]OECD.Stat export'!$BZ$97+'[1]OECD.Stat export'!$CB$97 -> 5 | AK79: ='[1]OECD.Stat export'!CD$96+'[1]OECD.Stat export'!CD$97 -> 1.7 | AL79: ='[1]OECD.Stat export'!CF$96+'[1]OECD.Stat export'!CF$97 -> 2.3 | AM79: ='[1]OECD.Stat export'!CH$96+'[1]OECD.Stat export'!CH$97 -> 2.4 | AN79: ='[1]OECD.Stat export'!$CJ$96+'[1]OECD.Stat export'!$CL$96+'[1]OECD.Stat export'!$CJ$97+'[1]OECD.Stat export'!$CL$97 -> 38.9 | AO79: 0 | AP79: ='[1]OECD.Stat export'!CP$96+'[1]OECD.Stat export'!CP$97 -> 89.3 | AQ79: ='[1]OECD.Stat export'!CR$96+'[1]OECD.Stat export'!CR$97 -> 1.3 | AR79: ='[1]OECD.Stat export'!CT$96+'[1]OECD.Stat export'!CT$97 -> 0 | AS79: ='[1]OECD.Stat export'!CV$96+'[1]OECD.Stat export'!CV$97 -> 17.2 | AT79: ='[1]OECD.Stat export'!CX$96+'[1]OECD.Stat export'!CX$97 -> 23.8 | AU79: ='[1]OECD.Stat export'!CZ$96+'[1]OECD.Stat export'!CZ$97 -> 210.7 | AV79: ='[1]OECD.Stat export'!DB$96+'[1]OECD.Stat export'!DB97 -> 0 | AW79: 0 | AX79: ='[1]OECD.Stat export'!DF$96+'[1]OECD.Stat export'!DF$97 -> 488 | AY79: 0
C80: Imports | D80: IMP_97T98: Private households with employed persons | F80: 0 | G80: 0 | H80: 0 | I80: 0 | J80: 0 | K80: 0 | L80: 0 | M80: 0 | N80: 0 | O80: 0 | P80: 0 | Q80: 0 | R80: 0 | S80: 0 | T80: 0 | U80: 0 | V80: 0 | W80: 0 | X80: 0 | Y80: 0 | Z80: 0 | AA80: 0 | AB80: 0 | AC80: 0 | AD80: 0 | AE80: 0 | AF80: 0 | AG80: 0 | AH80: 0 | AI80: 0 | AJ80: 0 | AK80: 0 | AL80: 0 | AM80: 0 | AN80: 0 | AO80: 0 | AP80: 0 | AQ80: 0 | AR80: 0 | AS80: 0 | AT80: 0 | AU80: 0 | AV80: 0 | AW80: 0 | AX80: 0 | AY80: 0
D81: TXS_IMP_FNL: Taxes less subsidies on intermediate and final products (paid in foreign countries) | F81: 0 | G81: 0 | H81: 0 | I81: 0 | J81: 0 | K81: 0 | L81: 0 | M81: 0 | N81: 0 | O81: 0 | P81: 0 | Q81: 0 | R81: 0 | S81: 0 | T81: 0 | U81: 0 | V81: 0 | W81: 0 | X81: 0 | Y81: 0 | Z81: 0 | AA81: 0 | AB81: 0 | AC81: -0.1 | AD81: -0.1 | AE81: 0 | AF81: 0 | AG81: 0 | AH81: 0 | AI81: 0 | AJ81: 0 | AK81: 0 | AL81: 0 | AM81: 0 | AN81: 0 | AO81: 0 | AP81: 0 | AQ81: 0 | AR81: 0 | AS81: 0 | AT81: 0 | AU81: 57.3 | AV81: 0 | AW81: 0 | AX81: 57.1 | AY81: 0
D82: TXS_INT_FNL: Taxes less subsidies on intermediate and final products (paid in domestic agencies, includes duty on imported products) | F82: =2.8+0.2 -> 3 | G82: 0 | H82: 0 | I82: 35.8 | J82: 64.3 | K82: 31.4 | L82: 7 | M82: 47.9 | N82: 17.5 | O82: =30.7+8.5 -> 39.2 | P82: 0 | Q82: 20 | R82: 162.7 | S82: 14.4 | T82: 34.1 | U82: 27.1 | V82: 12.1 | W82: 26.6 | X82: 4.8 | Y82: 13.7 | Z82: =55.6+61.1 -> 116.7 | AA82: 231.5 | AB82: 2799.5 | AC82: =104.9+350.7+239.3+392.1+67.7 -> 1154.7 | AD82: 117.8 | AE82: 84.1 | AF82: 263 | AG82: 10.4 | AH82: 1344.4 | AI82: 635.3 | AJ82: =51.8+99.6 -> 151.4 | AK82: 123.1 | AL82: 94.8 | AM82: 77.1 | AN82: =113.3+162.8 -> 276.1 | AO82: 0 | AP82: 3739.1 | AQ82: 29.6 | AR82: -29.4 | AS82: 1750.4 | AT82: 0 | AU82: 0 | AV82: -42.9 | AW82: 0 | AX82: 0 | AY82: 13488.4
D83: TTL_INT_FNL: Total intermediate consumption at purchasers’ prices | F83: =269.5+34.7 -> 304.2 | G83: 0 | H83: 0 | I83: 8028.3 | J83: 6194.7 | K83: 2727.5 | L83: 532.4 | M83: 4555.6 | N83: 377.9 | O83: =1159.8+452 -> 1611.8 | P83: 0 | Q83: 1228.3 | R83: 11480.1 | S83: 1130.6 | T83: 1446.5 | U83: 2665.6 | V83: 1189.9 | W83: 1424.9 | X83: 499 | Y83: 715.8 | Z83: =2971.3+3200.1 -> 6171.4 | AA83: 12195.5 | AB83: 104745.4 | AC83: =5658.2+16315.8+12040.1+17264+4079.3 -> 55357.4 | AD83: 8861.7 | AE83: 3649.8 | AF83: 10369.2 | AG83: 464.7 | AH83: 53727.3 | AI83: 28542.2 | AJ83: =2707.8+4500.8 -> 7208.6 | AK83: 4524.5 | AL83: 4403.8 | AM83: 5448 | AN83: =4177.3+7398.2 -> 11575.5 | AO83: 0 | AP83: 230751.9 | AQ83: 11199.9 | AR83: 35909.8 | AS83: 77220.9 | AT83: 61910.2 | AU83: 3576.1 | AV83: 37530.2 | AW83: 139110.7 | AX83: 235559.1 | AY83: 1196127.2
D84: VALU: Value added at basic prices | F84: =179.8+30.3 -> 210.1 | G84: 0 | H84: 0 | I84: 76.3 | J84: 2573.5 | K84: 265.2 | L84: 213.6 | M84: 133.1 | N84: 35.3 | O84: =38+22.9 -> 60.9 | P84: 0 | Q84: 50 | R84: 28.2 | S84: 75.6 | T84: 51.7 | U84: 45.3 | V84: 47.2 | W84: 43.4 | X84: 20.4 | Y84: 92 | Z84: =2341.9+2023.8 -> 4365.7 | AA84: 15493.8 | AB84: 73962.9 | AC84: =6622.9+2366.9+9657.3+606.9+1122.7 -> 20376.7 | AD84: 11770.9 | AE84: 2182.6 | AF84: 6311.7 | AG84: 4091.6 | AH84: 68821.6 | AI84: 52485.6 | AJ84: =16474.7+3558.1 -> 20032.8 | AK84: 21195.1 | AL84: 15533.9 | AM84: 14763.2 | AN84: =2644.6+5442.6 -> 8087.2 | AO84: 4665 | AP84: 0 | AQ84: 0 | AR84: 0 | AS84: 0 | AT84: 0 | AU84: 0 | AV84: 0 | AW84: 0 | AX84: 0 | AY84: 348162.1
D85: OUTPUT: Output at basic prices | F85: =449.3+65 -> 514.3 | G85: 0 | H85: 0 | I85: 8104.5 | J85: 8768.1 | K85: 2992.7 | L85: 746 | M85: 4688.8 | N85: 413.2 | O85: =1197.8+474.8 -> 1672.6 | P85: 0 | Q85: 1278.3 | R85: 11508.3 | S85: 1206.2 | T85: 1498.2 | U85: 2710.9 | V85: 1237.1 | W85: 1468.2 | X85: 519.5 | Y85: 807.8 | Z85: =5313.3+5223.9 -> 10537.2 | AA85: 27689.4 | AB85: 178708.3 | AC85: =12281.1+18682.6+21697.4+17871.3+5202 -> 75734.4 | AD85: 20632.5 | AE85: 5832.4 | AF85: 16680.9 | AG85: 4556.3 | AH85: 122548.9 | AI85: 81027.8 | AJ85: =19182.5+8058.9 -> 27241.4 | AK85: 25719.6 | AL85: 19937.7 | AM85: 20211.2 | AN85: =6821.9+12840.8 -> 19662.7 | AO85: 4665 | AP85: 0 | AQ85: 0 | AR85: 0 | AS85: 0 | AT85: 0 | AU85: 0 | AV85: 0 | AW85: 0 | AX85: 0 | AY85: 711520.5
D86: Data extracted on 6 Sept 2023 17:23 UTC (GMT) from OECD.Stat
CV125: 0

Sheet Calculations
A1: Estimating Fraction of Goods Purchased by Entity
A2: Consolidating Industry Sectors
B3: ='OECD Data IO Table - Total (USD'!E8 -> D01T03: Agriculture, forestry and fishing | C3: ='OECD Data IO Table - Total (USD'!F8 -> D05T06: Mining and extraction of energy producing products | D3: ='OECD Data IO Table - Total (USD'!G8 -> D07T08: Mining and quarrying of non-energy producing products | E3: ='OECD Data IO Table - Total (USD'!H8 -> D09: Mining support service activities | F3: ='OECD Data IO Table - Total (USD'!I8 -> D10T12: Food products, beverages and tobacco | G3: ='OECD Data IO Table - Total (USD'!J8 -> D13T15: Textiles, wearing apparel, leather and related products | H3: ='OECD Data IO Table - Total (USD'!K8 -> D16: Wood and products of wood and cork | I3: ='OECD Data IO Table - Total (USD'!L8 -> D17T18: Paper products and printing | ... AT3: ='OECD Data IO Table - Total (USD'!AW8 -> IMPO: Imports (cross border)
B4: ='OECD Data IO Table - Total (USD'!E2 -> nonenergy industries | C4: ='OECD Data IO Table - Total (USD'!F2 -> natural gas and petroleum suppliers | D4: ='OECD Data IO Table - Total (USD'!G2 -> nonenergy industries | E4: ='OECD Data IO Table - Total (USD'!H2 -> nonenergy industries | F4: ='OECD Data IO Table - Total (USD'!I2 -> nonenergy industries | G4: ='OECD Data IO Table - Total (USD'!J2 -> nonenergy industries | H4: ='OECD Data IO Table - Total (USD'!K2 -> nonenergy industries | I4: ='OECD Data IO Table - Total (USD'!L2 -> nonenergy industries | ... AT4: ='OECD Data IO Table - Total (USD'!AW2 -> imports
A5: Cement and other carbonate use | B5: =SUMIF('OECD Data IO Table - Total (USD'!$A$10:$A$50,Calculations!$A5,'OECD Data IO Table - Total (USD'!E$10:E$50) -> 0.1 | C5: =SUMIF('OECD Data IO Table - Total (USD'!$A$10:$A$50,Calculations!$A5,'OECD Data IO Table - Total (USD'!F$10:F$50) -> 0 | D5: =SUMIF('OECD Data IO Table - Total (USD'!$A$10:$A$50,Calculations!$A5,'OECD Data IO Table - Total (USD'!G$10:G$50) -> 0 | E5: =SUMIF('OECD Data IO Table - Total (USD'!$A$10:$A$50,Calculations!$A5,'OECD Data IO Table - Total (USD'!H$10:H$50) -> 4.4 | F5: =SUMIF('OECD Data IO Table - Total (USD'!$A$10:$A$50,Calculations!$A5,'OECD Data IO Table - Total (USD'!I$10:I$50) -> 41.4 | G5: =SUMIF('OECD Data IO Table - Total (USD'!$A$10:$A$50,Calculations!$A5,'OECD Data IO Table - Total (USD'!J$10:J$50) -> 1.6 | H5: =SUMIF('OECD Data IO Table - Total (USD'!$A$10:$A$50,Calculations!$A5,'OECD Data IO Table - Total (USD'!K$10:K$50) -> 1.4 | I5: =SUMIF('OECD Data IO Table - Total (USD'!$A$10:$A$50,Calculations!$A5,'OECD Data IO Table - Total (USD'!L$10:L$50) -> 5.3 | ... AT5: =SUMIF('OECD Data IO Table - Total (USD'!$A$10:$A$50,Calculations!$A5,'OECD Data IO Table - Total (USD'!AW$10:AW$50) -> -1681.9
A6: Natural gas and petroleum systems | B6: =SUMIF('OECD Data IO Table - Total (USD'!$A$10:$A$50,Calculations!$A6,'OECD Data IO Table - Total (USD'!E$10:E$50) -> 1.1 | C6: =SUMIF('OECD Data IO Table - Total (USD'!$A$10:$A$50,Calculations!$A6,'OECD Data IO Table - Total (USD'!F$10:F$50) -> 0 | D6: =SUMIF('OECD Data IO Table - Total (USD'!$A$10:$A$50,Calculations!$A6,'OECD Data IO Table - Total (USD'!G$10:G$50) -> 0 | E6: =SUMIF('OECD Data IO Table - Total (USD'!$A$10:$A$50,Calculations!$A6,'OECD Data IO Table - Total (USD'!H$10:H$50) -> 15.7 | F6: =SUMIF('OECD Data IO Table - Total (USD'!$A$10:$A$50,Calculations!$A6,'OECD Data IO Table - Total (USD'!I$10:I$50) -> 11.7 | G6: =SUMIF('OECD Data IO Table - Total (USD'!$A$10:$A$50,Calculations!$A6,'OECD Data IO Table - Total (USD'!J$10:J$50) -> 3.1 | H6: =SUMIF('OECD Data IO Table - Total (USD'!$A$10:$A$50,Calculations!$A6,'OECD Data IO Table - Total (USD'!K$10:K$50) -> 2.1 | I6: =SUMIF('OECD Data IO Table - Total (USD'!$A$10:$A$50,Calculations!$A6,'OECD Data IO Table - Total (USD'!L$10:L$50) -> 11.4 | ... AT6: =SUMIF('OECD Data IO Table - Total (USD'!$A$10:$A$50,Calculations!$A6,'OECD Data IO Table - Total (USD'!AW$10:AW$50) -> -13543.9
A7: Iron and steel | B7: =SUMIF('OECD Data IO Table - Total (USD'!$A$10:$A$50,Calculations!$A7,'OECD Data IO Table - Total (USD'!E$10:E$50) -> 0.1 | C7: =SUMIF('OECD Data IO Table - Total (USD'!$A$10:$A$50,Calculations!$A7,'OECD Data IO Table - Total (USD'!F$10:F$50) -> 0 | D7: =SUMIF('OECD Data IO Table - Total (USD'!$A$10:$A$50,Calculations!$A7,'OECD Data IO Table - Total (USD'!G$10:G$50) -> 0 | E7: =SUMIF('OECD Data IO Table - Total (USD'!$A$10:$A$50,Calculations!$A7,'OECD Data IO Table - Total (USD'!H$10:H$50) -> 5.3 | F7: =SUMIF('OECD Data IO Table - Total (USD'!$A$10:$A$50,Calculations!$A7,'OECD Data IO Table - Total (USD'!I$10:I$50) -> 10.3 | G7: =SUMIF('OECD Data IO Table - Total (USD'!$A$10:$A$50,Calculations!$A7,'OECD Data IO Table - Total (USD'!J$10:J$50) -> 0.9 | H7: =SUMIF('OECD Data IO Table - Total (USD'!$A$10:$A$50,Calculations!$A7,'OECD Data IO Table - Total (USD'!K$10:K$50) -> 1.7 | I7: =SUMIF('OECD Data IO Table - Total (USD'!$A$10:$A$50,Calculations!$A7,'OECD Data IO Table - Total (USD'!L$10:L$50) -> 8.7 | ... AT7: =SUMIF('OECD Data IO Table - Total (USD'!$A$10:$A$50,Calculations!$A7,'OECD Data IO Table - Total (USD'!AW$10:AW$50) -> -10834.1
A8: Chemicals | B8: =SUMIF('OECD Data IO Table - Total (USD'!$A$10:$A$50,Calculations!$A8,'OECD Data IO Table - Total (USD'!E$10:E$50) -> 2.3 | C8: =SUMIF('OECD Data IO Table - Total (USD'!$A$10:$A$50,Calculations!$A8,'OECD Data IO Table - Total (USD'!F$10:F$50) -> 0 | D8: =SUMIF('OECD Data IO Table - Total (USD'!$A$10:$A$50,Calculations!$A8,'OECD Data IO Table - Total (USD'!G$10:G$50) -> 0 | E8: =SUMIF('OECD Data IO Table - Total (USD'!$A$10:$A$50,Calculations!$A8,'OECD Data IO Table - Total (USD'!H$10:H$50) -> 11.6 | F8: =SUMIF('OECD Data IO Table - Total (USD'!$A$10:$A$50,Calculations!$A8,'OECD Data IO Table - Total (USD'!I$10:I$50) -> 35.3 | G8: =SUMIF('OECD Data IO Table - Total (USD'!$A$10:$A$50,Calculations!$A8,'OECD Data IO Table - Total (USD'!J$10:J$50) -> 25.1 | H8: =SUMIF('OECD Data IO Table - Total (USD'!$A$10:$A$50,Calculations!$A8,'OECD Data IO Table - Total (USD'!K$10:K$50) -> 11.9 | I8: =SUMIF('OECD Data IO Table - Total (USD'!$A$10:$A$50,Calculations!$A8,'OECD Data IO Table - Total (USD'!L$10:L$50) -> 95.7 | ... AT8: =SUMIF('OECD Data IO Table - Total (USD'!$A$10:$A$50,Calculations!$A8,'OECD Data IO Table - Total (USD'!AW$10:AW$50) -> -8310.4
A9: Coal mining | B9: =SUMIF('OECD Data IO Table - Total (USD'!$A$10:$A$50,Calculations!$A9,'OECD Data IO Table - Total (USD'!E$10:E$50) -> 0 | C9: =SUMIF('OECD Data IO Table - Total (USD'!$A$10:$A$50,Calculations!$A9,'OECD Data IO Table - Total (USD'!F$10:F$50) -> 0 | D9: =SUMIF('OECD Data IO Table - Total (USD'!$A$10:$A$50,Calculations!$A9,'OECD Data IO Table - Total (USD'!G$10:G$50) -> 0 | E9: =SUMIF('OECD Data IO Table - Total (USD'!$A$10:$A$50,Calculations!$A9,'OECD Data IO Table - Total (USD'!H$10:H$50) -> 0 | F9: =SUMIF('OECD Data IO Table - Total (USD'!$A$10:$A$50,Calculations!$A9,'OECD Data IO Table - Total (USD'!I$10:I$50) -> 0 | G9: =SUMIF('OECD Data IO Table - Total (USD'!$A$10:$A$50,Calculations!$A9,'OECD Data IO Table - Total (USD'!J$10:J$50) -> 0 | H9: =SUMIF('OECD Data IO Table - Total (USD'!$A$10:$A$50,Calculations!$A9,'OECD Data IO Table - Total (USD'!K$10:K$50) -> 0 | I9: =SUMIF('OECD Data IO Table - Total (USD'!$A$10:$A$50,Calculations!$A9,'OECD Data IO Table - Total (USD'!L$10:L$50) -> 0 | ... AT9: =SUMIF('OECD Data IO Table - Total (USD'!$A$10:$A$50,Calculations!$A9,'OECD Data IO Table - Total (USD'!AW$10:AW$50) -> 0
A10: Waste management | B10: =SUMIF('OECD Data IO Table - Total (USD'!$A$10:$A$50,Calculations!$A10,'OECD Data IO Table - Total (USD'!E$10:E$50) -> 0 | C10: =SUMIF('OECD Data IO Table - Total (USD'!$A$10:$A$50,Calculations!$A10,'OECD Data IO Table - Total (USD'!F$10:F$50) -> 0 | D10: =SUMIF('OECD Data IO Table - Total (USD'!$A$10:$A$50,Calculations!$A10,'OECD Data IO Table - Total (USD'!G$10:G$50) -> 0 | E10: =SUMIF('OECD Data IO Table - Total (USD'!$A$10:$A$50,Calculations!$A10,'OECD Data IO Table - Total (USD'!H$10:H$50) -> 0 | F10: =SUMIF('OECD Data IO Table - Total (USD'!$A$10:$A$50,Calculations!$A10,'OECD Data IO Table - Total (USD'!I$10:I$50) -> 0 | G10: =SUMIF('OECD Data IO Table - Total (USD'!$A$10:$A$50,Calculations!$A10,'OECD Data IO Table - Total (USD'!J$10:J$50) -> 0 | H10: =SUMIF('OECD Data IO Table - Total (USD'!$A$10:$A$50,Calculations!$A10,'OECD Data IO Table - Total (USD'!K$10:K$50) -> 0 | I10: =SUMIF('OECD Data IO Table - Total (USD'!$A$10:$A$50,Calculations!$A10,'OECD Data IO Table - Total (USD'!L$10:L$50) -> 0 | ... AT10: =SUMIF('OECD Data IO Table - Total (USD'!$A$10:$A$50,Calculations!$A10,'OECD Data IO Table - Total (USD'!AW$10:AW$50) -> 0
