Workbook
Name Average_emission_factor: '[1]Electricity emissions'!$H$38
Name footnote500011: FloorAreaPer!$A$170

Sheet About
A1: Sources:
B2: EMSD Energy End-use Data | C2: (Sheets:Energy8Sec, Residential8Fuel, Commercial8Fuel, Residential8EndUse, Commertial8EndUse)
B3: Hong Kong Energy End-use Data
B4: 2013-2018
B5: https://www.emsd.gov.hk/en/energy_efficiency/energy_end_use_data_and_consumption_indicators/hong_kong_energy_end_use_data/data/index.html
B6: Sheets:"Energy8Sec","Residential8Fuel","Commercial8Fuel","Residential8EndUse" and "Commercial8EndUse" are all from this data source.
B8: HK 2030 Report | F8: HK 2030: Baseline Review
B9: HK Development Bureau, HK Planning Department | F9: HK Development Bureau, HK Planning Department
B10: 2017 | F10: 2017
B11: Final Report | F11: Baseline Review: Population, Housing, Economy and Spatial Development Pattern
B12: https://www.pland.gov.hk/pland_en/p_study/comp_s/hk2030/eng/finalreport/ | F12: https://www.hk2030plus.hk/document/Baseline%20Review%20-%20Population_Housing_Economy%20and%20Spatial%20Development%20Pattern_Eng.pdf
B14: Household History Data(Sheet: Household_Histo) | F14: Household Prediction Data(Sheet: Household_Pred)
B15: Census and Statistics Department, HK | F15: Census and Statistics Department, HK
B16: 2019 | F16: 2019
B17: Table 005 : Statistics on Domestic Households | F17: Table E485 : Hong Kong Domestic Household Projections
B18: https://www.censtatd.gov.hk/hkstat/sub/sp150.jsp?tableID=005&ID=0&productType=8 | F18: https://www.censtatd.gov.hk/hkstat/sub/sp190.jsp?productCode=D5320185
B20: Floor Area Per capita (Sheet: FloorAreaPer)
B21: Population By-census
B22: 2017
B23: Table E129c: Median Per Capita Floor Area of Accommodation by Area of Residence, Household Size, Year and Type of Housing
B24: https://www.bycensus2016.gov.hk/en/bc-mt.html?search=E129c
B26: Building 2016 Data
B27: From Xiaoqian Jiang
B28: 2017
B29: From Excel "Copy of HK 2016 end use energy consumption rough 20190226 (added the building waste) revised2 lawrence.xlsx", Sheet"Building"
A32: Edition Log (WU Yazhen)
A33: 20190301_v1
A34: This part of data collection has not been finished.
A35: Next step: | B35: 1.Found Household Unit Composition to separate urban/rural residential
B36: 2.Use historical and predicted data of :Population, GDP, total residential area, total commercial arer, average number of people per household, average residential area per household
C37: to make linear or non-linear regression to predict future total energy consumption of residential/commercial sector of each fuel type.
C38: Then assuming the end-use composition stay unchanged throught the years, and the already-annouced building energy saving goal achieved.
C39: To predict future BAU End-use Data
A40: 20190304_v2
A41: Finished: | B41: 1.Found household history and prediction data.
B42: 2.Found Commercial AreaUse relative prediction ( average living area per household, household number; average living area per person, population) to predict residential area.
B43: 3.Done regression for estimating future residential energy consumption and
A44: 20190305_v3
A45: Finished: | B45: 1.Finished 1st version of Future Energy (End-use) Share Prediction.
B46: 2.Finished all calculation and got the final results, with TJ been converted to BTU.
A47: 20190306_v4
A48: Finished: | B48: 1. Change future household prediction data (from using"HK 2030 Baseline.pdf" as source, to using the HK C&SD predictions in sheet"Household_Pred").
B49: 2. The End-use "cooking" category has been put into "Appliance", not "Others".
B50: 3. The breakdown of rural/urban residential is finished.
B51: 4. The final data sheets are in the same format as the EPS US model inputdata sheets'.
A52: 20190404_v5
A53: Revised: | B53: 1. The missing final sheets for commercial have been added.
B54: 2. The data form in the sheets colored blue is adjust to be the same with the US model(start year from 2014).
B55: 3. Limit the use of coal&oil, and also gas, to be only in the appliance, not for lighting and other end-use sectors.
B56: (Adjustments are mainly made in the sheet "Future Energy share", on the breakdown of oil&coal (or gas) among different end-use types.
A58: 20190906_v6
A59: Revised: | B59: 1. Change the method of predicting total private/public/commercial building's energy demand: first predict future trend of per capita/per area energy consumption,
B60: and multiply them with population/area projections, than to directly predict total energy consumption by regression.
B61: 2. No longer divide the house as urban/rural residential, but divide them as private/public residential (and mark private as urban, residential as rural in the dark-blue final input sheets)

Sheet Note
A1: Method
A2: Step1: Predict Future Total Energy Consumption by Segments using socioeconomic and energy intensity data
B3: predict per capita/per area energy consumption and then multiply it with population/area projections. Not directly predict total energy consumption by regression.
A4: Step2: Predict Future Energy Type Share by using trend function.
A5: Step3: Predict Future End-use share of different(electricity/non-electricity) type in residential energy use
A8: Assumptions & Classicification
A9: 1. "Coal and oil"(in statistics: energy consumption by fuel) is made up of 50% coal, 50% oil. And "Town gas &Oil gas" equals to natural gas
A10: 2. The end-use "Hot water" are categorized as "Appliance", not as part of the "Heating".
A11: 3. No energy consumption in "Heating"(In EPS model note, the "Heating" means distributed heating, which HK does not have), and thus
A12: 4. The end-use "Appliance" includes "Hot water &Refrigeration", "Office equipment" and "Cooking", while the category "Others" includes "Others" in the Residential/Commercial sector segment statistic.
A13: 5. The share of end-uses in all different non-electricity energy types are the same.
A15: Future considerations
A16: 1.The fact that older peole' energy demand is different and the HK population structure is changing
A17: 2. Classification of end-use categories. E.g. perhaps "Cooking" should be grouped into "Appliance" category, not "Others"?
A18: 3. Refer to BEC (HK Energy-saving Report)?
... A51: 10. Sheet "Future Energy Share", data in row 64-65 is currently not yet supported by valid material; they are assumed by me.

Sheet InternalLink
A2: About
A3: InternalLink
A4: Household_Histo
A5: Household_Pred
A6: Energy8Sec
A7: Residential8Fuel
A8: Commercial8Fuel
A9: Residential8EndUse
A10: Commercial8EndUse
A11: Commercial
A12: Residential
A13: Future Pred
... A18: Note

Sheet Household_Histo
A1: Table005: Statistics on Domestic Households
A3: Period | C3: Number of domestic households ('000) | D3: Average domestic household size | E3: Owner-occupiers as a proportion of total number of domestic households (%) | F3: Owner-occupiers in public sector housing as a proportion of total number of domestic households in public sector housing (%) | G3: Owner-occupiers in private sector housing as a proportion of total number of domestic households in private sector housing (%)
A4: 1982 | C4: 1311.6 | D4: 3.9 | E4: 28.7 | F4: N.A. | G4: N.A.
A5: 1983 | C5: 1334.3 | D5: 3.9 | E5: 30.7 | F5: N.A. | G5: N.A.
A6: 1984 | C6: 1378.7 | D6: 3.7 | E6: 31.2 | F6: N.A. | G6: N.A.
A7: 1985 | C7: 1417.7 | D7: 3.7 | E7: 32.8 | F7: 6.6 | G7: 51.8
A8: 1986 | C8: 1473.1 | D8: 3.6 | E8: 34.9 | F8: 9.1 | G8: 53.9
A9: 1987 | C9: 1496.1 | D9: 3.6 | E9: 37.9 | F9: 10.1 | G9: 59.1
A10: 1988 | C10: 1532.6 | D10: 3.6 | E10: 39.4 | F10: 11.9 | G10: 60.8
A11: 1989 | C11: 1549 | D11: 3.6 | E11: 41.6 | F11: 12.9 | G11: 64.5
A12: 1990 | C12: 1559 | D12: 3.5 | E12: 42.6 | F12: 14.2 | G12: 66.3
A13: 1991 | C13: 1601.9 | D13: 3.5 | E13: 43.1 | F13: 15.8 | G13: 66.5
A14: 1992 | C14: 1633.5 | D14: 3.4 | E14: 43.5 | F14: 16.3 | G14: 68
A15: 1993 | C15: 1677.7 | D15: 3.5 | E15: 44.6 | F15: 18.2 | G15: 68.6
A16: 1994 | C16: 1729.1 | D16: 3.4 | E16: 45.1 | F16: 20.5 | G16: 67.8
A17: 1995 | C17: 1783 | D17: 3.4 | E17: 45.2 | F17: 21.6 | G17: 67.3
A18: 1996 | C18: 1864.5 | D18: 3.4 | E18: 45.9 | F18: 21.9 | G18: 67.1
... A39: 2017 | C39: 2534.7 | D39: 2.8 | E39: 49.2 | F39: 31.8 | G39: 63.8
A40: 10/1981 - 12/1981 | C40: 1297.7 | D40: 3.8 | E40: 28.7 | F40: N.A. | G40: N.A.
A41: 1/1982 - 3/1982 | C41: 1297.4 | D41: 3.9 | E41: 28.3 | F41: N.A. | G41: N.A.
A42: 4/1982 - 6/1982 | C42: 1317.5 | D42: 3.9 | E42: 28.5 | F42: N.A. | G42: N.A.
A43: 7/1982 - 9/1982 | C43: 1312.3 | D43: 3.9 | E43: 29 | F43: N.A. | G43: N.A.
A44: 10/1982 - 12/1982 | C44: 1319.3 | D44: 3.9 | E44: 29 | F44: N.A. | G44: N.A.
A45: 1/1983 - 3/1983 | C45: 1320.1 | D45: 3.9 | E45: 31.1 | F45: N.A. | G45: N.A.
A46: 4/1983 - 6/1983 | C46: 1330.5 | D46: 3.9 | E46: 30.9 | F46: N.A. | G46: N.A.
A47: 7/1983 - 9/1983 | C47: 1336.9 | D47: 3.8 | E47: 30.3 | F47: N.A. | G47: N.A.
A48: 10/1983 - 12/1983 | C48: 1349.9 | D48: 3.8 | E48: 30.3 | F48: N.A. | G48: N.A.
A49: 1/1984 - 3/1984 | C49: 1345.4 | D49: 3.8 | E49: 30.9 | F49: N.A. | G49: N.A.
A50: 4/1984 - 6/1984 | C50: 1378.1 | D50: 3.8 | E50: 30.9 | F50: N.A. | G50: N.A.
A51: 7/1984 - 9/1984 | C51: 1386.3 | D51: 3.7 | E51: 31.8 | F51: N.A. | G51: N.A.
A52: 10/1984 - 12/1984 | C52: 1405 | D52: 3.7 | E52: 31.3 | F52: N.A. | G52: N.A.
A53: 1/1985 - 3/1985 | C53: 1402.9 | D53: 3.7 | E53: 31.4 | F53: 5.9 | G53: 50.2
A54: 4/1985 - 6/1985 | C54: 1416.7 | D54: 3.7 | E54: 32.8 | F54: 6.3 | G54: 51.6
A55: 7/1985 - 9/1985 | C55: 1416.5 | D55: 3.7 | E55: 33.9 | F55: 6.9 | G55: 53.6
A56: 10/1985 - 12/1985 | C56: 1434.7 | D56: 3.7 | E56: 33.2 | F56: 7.3 | G56: 51.8
A57: 1/1986 - 3/1986 | C57: 1453 | D57: 3.7 | E57: 32.9 | F57: 7.9 | G57: 50.6
A58: 4/1986 - 6/1986 | C58: 1469.7 | D58: 3.6 | E58: 34 | F58: 9 | G58: 52
A59: 7/1986 - 9/1986 | C59: 1481.4 | D59: 3.6 | E59: 36 | F59: 9.5 | G59: 56.4
A60: 10/1986 - 12/1986 | C60: 1488.2 | D60: 3.6 | E60: 36.5 | F60: 9.9 | G60: 56.9
A61: 1/1987 - 3/1987 | C61: 1478.3 | D61: 3.6 | E61: 37.1 | F61: 9.9 | G61: 57.7
A62: 4/1987 - 6/1987 | C62: 1494.3 | D62: 3.6 | E62: 37.3 | F62: 10.3 | G62: 57.9
A63: 7/1987 - 9/1987 | C63: 1496.7 | D63: 3.6 | E63: 38.5 | F63: 10.2 | G63: 60.3
A64: 10/1987 - 12/1987 | C64: 1514.9 | D64: 3.6 | E64: 38.7 | F64: 9.9 | G64: 60.4
... A394: 10/2018 - 12/2018 | C394: 2573.9 | D394: 2.8 | E394: 49.1 | F394: 32 | G394: 63.8
A396: Notes : | B396: Starting from 2001, annual figures are compiled based on data collected in the General Household Survey from January to December of the year concerned as well as the mid-year population estimates.
B397: Owner-occupiers refer to the domestic households which own the quarters they occupy.
B398: Public sector housing includes public rental flats and interim housing flats provided by Housing Authority (HA); and public rental flats and Senior Citizen Residences Scheme flats provided by the Housing Society (HS); subsidized sale flats provided by HA under the Home Ownership Scheme (HOS), Private Sector Participation Scheme (PSPS), Tenants Purchase Scheme (TPS), Buy or Rent Option Scheme (BRO), Green Form Subsidised Home Owership Pilot Scheme (GSH), Mortgage Subsidy Scheme (MSS) and Middle Income Housing Scheme (MIH); and flats provided by HS under the Flat-For-Sale Scheme (FFSS), Sandwich Class Housing Scheme (SCHS) and Subsidised Sale Flats Scheme (SSFS); and flats in Urban Renewal Authority Subsidised Sale Flats Scheme; and Public Temporary housing. As from Q1 2002, subsidized sale flats that can be traded in open market are excluded.
B399: Private sector housing includes private housing blocks, flats built under the Urban Improvement Scheme of the Hong Kong Housing Society, villas/bungalows/modern village houses, simple stone structures, quarters in non-residential buildings and private temporary housing. As from Q1 2002, subsidized sale flats that can be traded in open market are also put under this category.
B400: N.A. | C400: Not available.
A401: Source : | B401: Household Statistics Analysis Section, Census and Statistics Department (Enquiry telephone no. : 2887 5508 Enquiry e-mail : ghs@censtatd.gov.hk)
A403: Last revision date: 21 February, 2019

Sheet Household_Pred
A1: 表 1 | B1: 家庭住戶數目及平均住戶人數
A2: Table 1 | B2: Number of domestic households and average household size
A4: 年份 | B4: 家庭住戶數目 | C4: 前五年內平均每年增幅 | D4: 平均住戶人數
A5: Year | B5: Number of domestic households | C5: Average annual growth over the past 5 years | D5: Average household size
A7: 1981 | B7: 1244700 | C7: - | D7: 3.9
A8: 1986 | B8: 1452600 | C8: 41600 | D8: 3.7
A9: 1991 | B9: 1582200 | C9: 25900 | D9: 3.4
A10: 1996 | B10: 1855600 | C10: 54700 | D10: 3.3
A11: 2001 | B11: 2053400 | C11: 39600 | D11: 3.1
A12: 2006 | B12: 2226500 | C12: 34600 | D12: 3
A13: 2011 | B13: 2368800 | C13: 28500 | D13: 2.9
A14: 2016 | B14: 2509700 | C14: 28200 | D14: 2.8
A15: 2021 | B15: 2657000 | C15: 29400 | D15: 2.8
A16: 2026 | B16: 2768900 | C16: 22400 | D16: 2.7
A17: 2031 | B17: 2854500 | C17: 17100 | D17: 2.7
A18: 2036 | B18: 2920200 | C18: 13100 | D18: 2.7
A19: 2041 | B19: 2961400 | C19: 8200 | D19: 2.7
... A21: 2051 | B21: 2949500 | C21: -4500 | D21: 2.7
A23: 註釋： | B23: 虛線以下的數字是推算數字。
B24: 推算結果反映若過往有關生育、死亡、人口遷移及戶主率的人口趨勢仍延續，未來的整體趨勢情況。要注意的是由於未來可能會發生現階段不能預見及預測的情況，因此，有關未來趨勢的假設亦受制於這些不確定因素的發展。
A26: Notes : | B26: Figures below the broken lines are based on projections.
B27: The projection results aim at illustrating what would happen if the past demographic trends on fertility, mortality, movement and headship rates continue into the future. It should however be noted that the assumptions of future trends are subject to uncertainties arising from unforeseeable and unpredictable future events.

Sheet History Type Share
A1: Residential Energy Use by Fuel
A2: Source: | B2: EMSD End-use Data report 2023
A3: 住宅 Residential
A4: 年份 Year | B4: 煤氣及石油氣* Town Gas & Liquefied Petroleum Gas* | D4: 油及煤產品 Oil & Coal Products | F4: 電力 Electricity | H4: 總計 Total
A5: 2006 | B5: 18476 | C5: 0.34 | D5: 79 | E5: 0 | F5: 35428 | G5: 0.66 | H5: 53982
A6: 2007 | B6: 18238 | C6: 0.33 | D6: 57 | E6: 0 | F6: 36422 | G6: 0.67 | H6: 54717
A7: 2008 | B7: 18708 | C7: 0.33 | D7: 41 | E7: 0 | F7: 37100 | G7: 0.66 | H7: 55849
A8: 2009 | B8: 18736 | C8: 0.32 | D8: 23 | E8: 0 | F8: 38972 | G8: 0.68 | H8: 57731
A9: 2010 | B9: 19038 | C9: 0.33 | D9: 13 | E9: 0 | F9: 39344 | G9: 0.67 | H9: 58396
A10: 2011 | B10: 18977 | C10: 0.32 | D10: 8 | E10: 0 | F10: 39872 | G10: 0.68 | H10: 58857
A11: 2012 | B11: 18841 | C11: 0.31 | D11: 8 | E11: 0 | F11: 41189 | G11: 0.69 | H11: 60037
A12: 2013 | B12: 18635 | C12: 0.32 | D12: 7 | E12: 0 | F12: 39941 | G12: 0.68 | H12: 58582
A13: 2014 | B13: 18681 | C13: 0.3 | D13: 7 | E13: 0 | F13: 43415 | G13: 0.7 | H13: 62103
A14: 2015 | B14: 18063 | C14: 0.3 | D14: 8 | E14: 0 | F14: 42368 | G14: 0.7 | H14: 60439
A15: 2016 | B15: 18574 | C15: 0.3 | D15: 10 | E15: 0 | F15: 43120 | G15: 0.7 | H15: 61704
A16: 2017 | B16: 18335 | C16: 0.3 | D16: 14 | E16: 0 | F16: 42127 | G16: 0.7 | H16: 60476
... A20: 2021 | B20: 19242 | C20: 0.29 | D20: 15 | E20: 0 | F20: 47464 | G20: 0.7 | H20: 66721
A23: Commercial Energy Use by Fuel
A24: Source: | B24: EMSD End-use Data report 2022#
A25: 商业 Commercial
A26: 年份 Year | B26: 煤氣及石油氣* Town Gas & Liquefied Petroleum Gas* | D26: 油及煤產品 Oil & Coal Products | F26: 電力 Electricity | H26: 總計 Total
A27: 2006 | B27: 13631 | C27: 0.12 | D27: 4936 | E27: 0.04 | F27: 93317 | G27: 0.83 | H27: 111884
A28: 2007 | B28: 13888 | C28: 0.12 | D28: 4975 | E28: 0.04 | F28: 95051 | G28: 0.83 | H28: 113914
A29: 2008 | B29: 13471 | C29: 0.12 | D29: 4739 | E29: 0.04 | F29: 95543 | G29: 0.84 | H29: 113753
A30: 2009 | B30: 12815 | C30: 0.11 | D30: 4753 | E30: 0.04 | F30: 96728 | G30: 0.85 | H30: 114297
A31: 2010 | B31: 13971 | C31: 0.12 | D31: 4526 | E31: 0.04 | F31: 97894 | G31: 0.84 | H31: 116391
A32: 2011 | B32: 14129 | C32: 0.12 | D32: 1979 | E32: 0.02 | F32: 99905 | G32: 0.86 | H32: 116013
A33: 2012 | B33: 14280 | C33: 0.12 | D33: 1696 | E33: 0.01 | F33: 102353 | G33: 0.86 | H33: 118330
A34: 2013 | B34: 14512 | C34: 0.12 | D34: 1477 | E34: 0.01 | F34: 102221 | G34: 0.86 | H34: 118209
A35: 2014 | B35: 14713 | C35: 0.12 | D35: 1431 | E35: 0.01 | F35: 103471 | G35: 0.87 | H35: 119615
A36: 2015 | B36: 14535 | C36: 0.12 | D36: 1235 | E36: 0.01 | F36: 104647 | G36: 0.87 | H36: 120417
A37: 2016 | B37: 14601 | C37: 0.12 | D37: 1019 | E37: 0.01 | F37: 104839 | G37: 0.87 | H37: 120458
A38: 2017 | B38: 14908 | C38: 0.12 | D38: 830 | E38: 0.01 | F38: 104669 | G38: 0.87 | H38: 120408
... A42: 2021 | B42: 12353 | C42: 0.1 | D42: 490 | E42: 0 | F42: 107240 | G42: 0.89 | H42: 120083

Sheet Commercial8Fuel
A1: Commercial Energy Use by Fuel
A2: Source: | B2: EMSD End-use Data report 2023
A3: 商业 Commercial
A4: 年份 Year | B4: 煤氣及石油氣* Town Gas & Liquefied Petroleum Gas* | D4: 油及煤產品 Oil & Coal Products | F4: 電力 Electricity | H4: 總計 Total
A5: 2006 | B5: 13631 | C5: 0.12 | D5: 4936 | E5: 0.04 | F5: 93317 | G5: 0.86 | H5: 111884
A6: 2007 | B6: 13888 | C6: 0.12 | D6: 4975 | E6: 0.04 | F6: 95051 | G6: 0.86 | H6: 113914
A7: 2008 | B7: 13471 | C7: 0.12 | D7: 4739 | E7: 0.04 | F7: 95543 | G7: 0.86 | H7: 113753
A8: 2009 | B8: 12815 | C8: 0.11 | D8: 4753 | E8: 0.04 | F8: 96728 | G8: 0.87 | H8: 114297
A9: 2010 | B9: 13971 | C9: 0.12 | D9: 4526 | E9: 0.04 | F9: 97894 | G9: 0.87 | H9: 116391
A10: 2011 | B10: 14129 | C10: 0.12 | D10: 1979 | E10: 0.02 | F10: 99905 | G10: 0.87 | H10: 116013
A11: 2012 | B11: 14280 | C11: 0.12 | D11: 1696 | E11: 0.01 | F11: 102353 | G11: 0.87 | H11: 118330
A12: 2013 | B12: 14512 | C12: 0.12 | D12: 1477 | E12: 0.01 | F12: 102221 | G12: 0.87 | H12: 118209
A13: 2014 | B13: 14713 | C13: 0.12 | D13: 1431 | E13: 0.01 | F13: 103471 | G13: 0.87 | H13: 119615
A14: 2015 | B14: 14535 | C14: 0.12 | D14: 1235 | E14: 0.01 | F14: 104647 | G14: 0.87 | H14: 120417
A15: 2016 | B15: 14601 | C15: 0.12 | D15: 1019 | E15: 0.01 | F15: 104839 | G15: 0.87 | H15: 120458
A16: 2017 | B16: 14908 | C16: 0.12 | D16: 830 | E16: 0.01 | F16: 104669 | G16: 0.87 | H16: 120408
... A20: 2021 | B20: 12353 | C20: 0.1 | D20: 490 | E20: 0 | F20: 107240 | G20: 0.89 | H20: 120083

Sheet Energy8Sec
A1: All Energy/Electricity Consumption by Sector
A2: Source: | B2: EMSD End-use Data report 2018
A3: P23
A5: 终端能源使用All Energy Consumption By Sectors | F5: Unit:Terajoule | H5: Sectors Energy Consumption Percentage
A6: Year | B6: 住宅 Residential | C6: 商业 Commercial | D6: 工业 Industrial | E6: 运输 Transport | F6: 总计 Total | H6: Year | I6: 住宅 Residential | J6: 商业 Commercial | K6: 工业 Industrial | L6: 运输 Transport | M6: 总计 Total
A7: 2006 | B7: 53982 | C7: 111884 | D7: 18934 | E7: 96404 | F7: =SUM(B7:E7) -> 281204 | H7: 2006 | I7: =B7/$F7 -> 0.1919674 | J7: =C7/$F7 -> 0.39787485 | K7: =D7/$F7 -> 0.067331901 | L7: =E7/$F7 -> 0.34282585 | M7: =F7/$F7 -> 1
A8: 2007 | B8: 54717 | C8: 113914 | D8: 17645 | E8: 96165 | F8: =SUM(B8:E8) -> 282441 | H8: 2007 | I8: =B8/$F8 -> 0.19372896 | J8: =C8/$F8 -> 0.40331963 | K8: =D8/$F8 -> 0.062473224 | L8: =E8/$F8 -> 0.34047819 | M8: =F8/$F8 -> 1
A9: 2008 | B9: 55849 | C9: 113753 | D9: 17332 | E9: 94504 | F9: =SUM(B9:E9) -> 281438 | H9: 2008 | I9: =B9/$F9 -> 0.19844158 | J9: =C9/$F9 -> 0.40418494 | K9: =D9/$F9 -> 0.061583724 | L9: =E9/$F9 -> 0.33578977 | M9: =F9/$F9 -> 1
A10: 2009 | B10: 57731 | C10: 114297 | D10: 16129 | E10: 90643 | F10: =SUM(B10:E10) -> 278800 | H10: 2009 | I10: =B10/$F10 -> 0.20706958 | J10: =C10/$F10 -> 0.40996055 | K10: =D10/$F10 -> 0.057851506 | L10: =E10/$F10 -> 0.32511836 | M10: =F10/$F10 -> 1
A11: 2010 | B11: 58396 | C11: 116391 | D11: 16053 | E11: 90889 | F11: =SUM(B11:E11) -> 281729 | H11: 2010 | I11: =B11/$F11 -> 0.20727721 | J11: =C11/$F11 -> 0.41313106 | K11: =D11/$F11 -> 0.05698029 | L11: =E11/$F11 -> 0.32261145 | M11: =F11/$F11 -> 1
A12: 2011 | B12: 58826 | C12: 118558 | D12: 14732 | E12: 90774 | F12: =SUM(B12:E12) -> 282890 | H12: 2011 | I12: =B12/$F12 -> 0.20794655 | J12: =C12/$F12 -> 0.41909576 | K12: =D12/$F12 -> 0.052076779 | L12: =E12/$F12 -> 0.32088091 | M12: =F12/$F12 -> 1
A13: 2012 | B13: 59932 | C13: 120970 | D13: 14723 | E13: 90423 | F13: =SUM(B13:E13) -> 286048 | H13: 2012 | I13: =B13/$F13 -> 0.20951728 | J13: =C13/$F13 -> 0.42290105 | K13: =D13/$F13 -> 0.051470383 | L13: =E13/$F13 -> 0.31611128 | M13: =F13/$F13 -> 1
A14: 2013 | B14: 58394 | C14: 121215 | D14: 14583 | E14: 90198 | F14: =SUM(B14:E14) -> 284390 | H14: 2013 | I14: =B14/$F14 -> 0.20533071 | J14: =C14/$F14 -> 0.42622807 | K14: =D14/$F14 -> 0.051278174 | L14: =E14/$F14 -> 0.31716305 | M14: =F14/$F14 -> 1
A15: 2014 | B15: 61910 | C15: 122711 | D15: 14718 | E15: 89999 | F15: =SUM(B15:E15) -> 289338 | H15: 2014 | I15: =B15/$F15 -> 0.2139712 | J15: =C15/$F15 -> 0.42410952 | K15: =D15/$F15 -> 0.050867843 | L15: =E15/$F15 -> 0.31105143 | M15: =F15/$F15 -> 1
A16: 2015 | B16: 60214 | C16: 123674 | D16: 14853 | E16: 89245 | F16: =SUM(B16:E16) -> 287986 | H16: 2015 | I16: =B16/$F16 -> 0.20908655 | J16: =C16/$F16 -> 0.42944449 | K16: =D16/$F16 -> 0.051575424 | L16: =E16/$F16 -> 0.30989354 | M16: =F16/$F16 -> 1
A17: 2016 | B17: 61439 | C17: 123969 | D17: 13992 | E17: 89819 | F17: =SUM(B17:E17) -> 289219 | H17: 2016 | I17: =B17/$F17 -> 0.21243072 | J17: =C17/$F17 -> 0.42863367 | K17: =D17/$F17 -> 0.048378564 | L17: =E17/$F17 -> 0.31055705 | M17: =F17/$F17 -> 1
A18: 2017 | B18: 60476 | C18: 120408 | D18: 12722 | E18: 86557 | F18: 280162 | H18: 2017 | I18: =B18/$F18 -> 0.21586082 | J18: =C18/$F18 -> 0.42977991 | K18: =D18/$F18 -> 0.045409442 | L18: =E18/$F18 -> 0.30895339 | M18: =F18/$F18 -> 1
A19: 2018 | B19: 61556 | C19: 122220 | D19: 12829 | E19: 85054 | F19: 281659 | H19: 2018 | I19: =B19/$F19 -> 0.21854796 | J19: =C19/$F19 -> 0.43392897 | K19: =D19/$F19 -> 0.045547985 | L19: =E19/$F19 -> 0.30197508 | M19: =F19/$F19 -> 1
A20: 2019 | B20: 61021 | C20: 123001 | D20: 12274 | E20: 85877 | F20: 282174 | H20: 2019 | I20: =B20/$F20 -> 0.21625309 | J20: =C20/$F20 -> 0.4359048 | K20: =D20/$F20 -> 0.043497984 | L20: =E20/$F20 -> 0.30434058 | M20: =F20/$F20 -> 1
A21: 2020 | B21: 66413 | C21: 114512 | D21: 12161 | E21: 78514 | F21: 271600 | H21: 2020 | I21: =B21/$F21 -> 0.24452504 | J21: =C21/$F21 -> 0.42162003 | K21: =D21/$F21 -> 0.044775405 | L21: =E21/$F21 -> 0.28907953 | M21: =F21/$F21 -> 1
A22: 2021 | B22: 66721 | C22: 120083 | D22: 11945 | E22: 81158 | F22: 279907 | H22: 2021 | I22: =B22/$F22 -> 0.23836846 | J22: =C22/$F22 -> 0.42901035 | K22: =D22/$F22 -> 0.042674888 | L22: =E22/$F22 -> 0.2899463 | M22: =F22/$F22 -> 1
A25: 电力使用 Electricity Consuption By Sectors | H25: Sectors Electricity Consumption Percentage
A26: Year | B26: 住宅 Residential | C26: 商业 Commercial | D26: 工业 Industrial | E26: 运输 Transport | F26: 总计 Total | H26: Year | I26: 住宅 Residential | J26: 商业 Commercial | K26: 工业 Industrial | L26: 运输 Transport | M26: 总计 Total | O26: Check
A27: 2006 | B27: 35428 | C27: 93317 | D27: 14015 | E27: 2444 | F27: =SUM(B27:E27) -> 145204 | H27: 2006 | I27: =B27/$F27 -> 0.24398777 | J27: =C27/$F27 -> 0.64266136 | K27: =D27/$F27 -> 0.09651938 | L27: =E27/$F27 -> 0.016831492 | M27: =F27/$F27 -> 1 | O27: =B7*'History Type Share'!G5 -> 35628.12
A28: 2007 | B28: 36422 | C28: 95051 | D28: 13104 | E28: 2495 | F28: =SUM(B28:E28) -> 147072 | H28: 2007 | I28: =B28/$F28 -> 0.24764741 | J28: =C28/$F28 -> 0.64628889 | K28: =D28/$F28 -> 0.089099217 | L28: =E28/$F28 -> 0.01696448 | M28: =F28/$F28 -> 1 | O28: =B8*'History Type Share'!G6 -> 36660.39
A29: 2008 | B29: 37100 | C29: 95543 | D29: 12182 | E29: 2520 | F29: =SUM(B29:E29) -> 147345 | H29: 2008 | I29: =B29/$F29 -> 0.25179002 | J29: =C29/$F29 -> 0.64843055 | K29: =D29/$F29 -> 0.082676711 | L29: =E29/$F29 -> 0.017102718 | M29: =F29/$F29 -> 1 | O29: =B9*'History Type Share'!G7 -> 36860.34
A30: 2009 | B30: 38972 | C30: 96728 | D30: 11143 | E30: 2523 | F30: =SUM(B30:E30) -> 149366 | H30: 2009 | I30: =B30/$F30 -> 0.26091614 | J30: =C30/$F30 -> 0.64759048 | K30: =D30/$F30 -> 0.074601984 | L30: =E30/$F30 -> 0.016891394 | M30: =F30/$F30 -> 1 | O30: =B10*'History Type Share'!G8 -> 39257.08
A31: 2010 | B31: 39344 | C31: 97894 | D31: 11082 | E31: 2540 | F31: =SUM(B31:E31) -> 150860 | H31: 2010 | I31: =B31/$F31 -> 0.26079809 | J31: =C31/$F31 -> 0.64890627 | K31: =D31/$F31 -> 0.073458836 | L31: =E31/$F31 -> 0.016836802 | M31: =F31/$F31 -> 1 | O31: =B11*'History Type Share'!G9 -> 39125.32
A32: 2011 | B32: 39872 | C32: 99594 | D32: 9530 | E32: 2609 | F32: =SUM(B32:E32) -> 151605 | H32: 2011 | I32: =B32/$F32 -> 0.26299924 | J32: =C32/$F32 -> 0.65693084 | K32: =D32/$F32 -> 0.062860724 | L32: =E32/$F32 -> 0.017209195 | M32: =F32/$F32 -> 1 | O32: =B12*'History Type Share'!G10 -> 40001.68
A33: 2012 | B33: 41189 | C33: 101813 | D33: 9356 | E33: 2722 | F33: =SUM(B33:E33) -> 155080 | H33: 2012 | I33: =B33/$F33 -> 0.2655984 | J33: =C33/$F33 -> 0.65651922 | K33: =D33/$F33 -> 0.060330152 | L33: =E33/$F33 -> 0.017552231 | M33: =F33/$F33 -> 1 | O33: =B13*'History Type Share'!G11 -> 41353.08
A34: 2013 | B34: 39941 | C34: 101480 | D34: 9144 | E34: 2796 | F34: =SUM(B34:E34) -> 153361 | H34: 2013 | I34: =B34/$F34 -> 0.26043779 | J34: =C34/$F34 -> 0.66170669 | K34: =D34/$F34 -> 0.059624024 | L34: =E34/$F34 -> 0.018231493 | M34: =F34/$F34 -> 1 | O34: =B14*'History Type Share'!G12 -> 39707.92
A35: 2014 | B35: 43415 | C35: 102627 | D35: 9230 | E35: 2875 | F35: =SUM(B35:E35) -> 158147 | H35: 2014 | I35: =B35/$F35 -> 0.27452307 | J35: =C35/$F35 -> 0.64893422 | K35: =D35/$F35 -> 0.058363421 | L35: =E35/$F35 -> 0.018179289 | M35: =F35/$F35 -> 1 | O35: =B15*'History Type Share'!G13 -> 43337
A36: 2015 | B36: 42368 | C36: 103693 | D36: 9242 | E36: 2972 | F36: =SUM(B36:E36) -> 158275 | H36: 2015 | I36: =B36/$F36 -> 0.26768599 | J36: =C36/$F36 -> 0.65514453 | K36: =D36/$F36 -> 0.058392039 | L36: =E36/$F36 -> 0.018777444 | M36: =F36/$F36 -> 1 | O36: =B16*'History Type Share'!G14 -> 42149.8
A37: 2016 | B37: 43120 | C37: 103881 | D37: 8709 | E37: 2951 | F37: =SUM(B37:E37) -> 158661 | H37: 2016 | I37: =B37/$F37 -> 0.27177441 | J37: =C37/$F37 -> 0.65473557 | K37: =D37/$F37 -> 0.054890616 | L37: =E37/$F37 -> 0.018599404 | M37: =F37/$F37 -> 1 | O37: =B17*'History Type Share'!G15 -> 43007.3
A38: 2017 | B38: 42127 | C38: 104669 | D38: 7963 | E38: 3218 | F38: =SUM(B38:E38) -> 157977 | H38: 2017 | I38: =B38/$F38 -> 0.2666654 | J38: =C38/$F38 -> 0.66255847 | K38: =D38/$F38 -> 0.050406072 | L38: =E38/$F38 -> 0.020370054 | M38: =F38/$F38 -> 1 | O38: =B18*'History Type Share'!G16 -> 42333.2
... A42: 2021 | B42: 47464 | C42: 107240 | D42: 7222 | E42: 3002 | F42: =SUM(B42:E42) -> 164928 | H42: 2021 | I42: =B42/$F42 -> 0.28778619 | J42: =C42/$F42 -> 0.65022313 | K42: =D42/$F42 -> 0.043788805 | L42: =E42/$F42 -> 0.018201882 | M42: =F42/$F42 -> 1 | O42: =B22*'History Type Share'!G20 -> 46704.7
A44: Year | B44: Residential (Unit : Terajoule) | C44: Commercial (Unit : Terajoule) | D44: Industrial (Unit : Terajoule) | E44: Transport (Unit : Terajoule) | F44: 总计 Total | H44: Year | I44: Residential Percentage (%) | J44: Commercial Percentage (%) | K44: Industrial Percentage (%) | L44: Transport Percentage (%) | M44: 总计 Total
A45: 2011 | B45: 8 | C45: 1979 | D45: 3978 | E45: 72383 | F45: =SUM(B45:E45) -> 78348 | H45: 2011 | I45: 0 | J45: 0.03 | K45: 0.05 | L45: 0.92 | M45: =SUM(I45:L45) -> 1
A46: 2012 | B46: 8 | C46: 1696 | D46: 3728 | E46: 71927 | F46: =SUM(B46:E46) -> 77359 | H46: 2012 | I46: 0 | J46: 0.02 | K46: 0.05 | L46: 0.93 | M46: =SUM(I46:L46) -> 1
A47: 2013 | B47: 7 | C47: 1477 | D47: 3571 | E47: 71449 | F47: =SUM(B47:E47) -> 76504 | H47: 2013 | I47: 0 | J47: 0.02 | K47: 0.05 | L47: 0.93 | M47: =SUM(I47:L47) -> 1
A48: 2014 | B48: 7 | C48: 1431 | D48: 3389 | E48: 69206 | F48: =SUM(B48:E48) -> 74033 | H48: 2014 | I48: 0 | J48: 0.02 | K48: 0.05 | L48: 0.93 | M48: =SUM(I48:L48) -> 1
A49: 2015 | B49: 8 | C49: 1235 | D49: 3386 | E49: 70251 | F49: =SUM(B49:E49) -> 74880 | H49: 2015 | I49: 0 | J49: 0.02 | K49: 0.05 | L49: 0.94 | M49: =SUM(I49:L49) -> 1.01
A50: 2016 | B50: 10 | C50: 1019 | D50: 3190 | E50: 70374 | F50: =SUM(B50:E50) -> 74593 | H50: 2016 | I50: 0 | J50: 0.01 | K50: 0.04 | L50: 0.94 | M50: =SUM(I50:L50) -> 0.99
A51: 2017 | B51: 14 | C51: 830 | D51: 3442 | E51: 69991 | F51: =SUM(B51:E51) -> 74277 | H51: 2017 | I51: 0 | J51: 0.01 | K51: 0.05 | L51: 0.94 | M51: =SUM(I51:L51) -> 1
A52: 2018 | B52: 14 | C52: 675 | D52: 3443 | E52: 69492 | F52: =SUM(B52:E52) -> 73624 | H52: 2018 | I52: 0 | J52: 0.01 | K52: 0.05 | L52: 0.94 | M52: =SUM(I52:L52) -> 1
A53: 2019 | B53: 15 | C53: 574 | D53: 3177 | E53: 69401 | F53: =SUM(B53:E53) -> 73167 | H53: 2019 | I53: 0 | J53: 0.01 | K53: 0.04 | L53: 0.95 | M53: =SUM(I53:L53) -> 1
A54: 2020 | B54: 15 | C54: 498 | D54: 3309 | E54: 64484 | F54: =SUM(B54:E54) -> 68306 | H54: 2020 | I54: 0 | J54: 0.01 | K54: 0.05 | L54: 0.94 | M54: =SUM(I54:L54) -> 1
A55: 2021 | B55: 15 | C55: 490 | D55: 3237 | E55: 67145 | F55: =SUM(B55:E55) -> 70887 | H55: 2021 | I55: 0 | J55: 0.01 | K55: 0.05 | L55: 0.95 | M55: =SUM(I55:L55) -> 1.01

Sheet Private,Public8EndUse
A1: Private/Public Residential Energy Consumption by End-use | K1: Air Conditioning | L1: Hot Water | M1: Lighting | N1: Refrigeration | O1: Office Equipment | P1: Cooking | Q1: Others | R1: Sum
A2: Source: | C2: Chapter : By Sectors&Segments | G2: EMSD End-use Data report
A3: Energy
A4: 所有住宅All Residential | K4: 私人住宅Private Housing Segment | V4: 公共住宅 Public Housing | AG4: 房委会资助出售单位组别 Housing Authority Subsidized Sale Flats Segment | AR4: Total Energy Consumption in Other Housing Segment by End-use | BC4: 重新加总Private+Public | BM4: Private = Urban defination in the EPS | BW4: Public = Rural defination in the EPS
A5: 年份 Year | B5: 空氣調節 Air Conditioning | C5: 熱水 Hot Water | D5: 照明 Lighting | E5: 冷凍 Refrigeration | F5: 辦公室設備 Office Equipment | G5: 煮食 Cooking | H5: 其他 1 Others 1 | I5: 總計 Total | K5: 年份 Year | L5: Cooking (Unit : Terajoule) | M5: Air Conditioning (Unit : Terajoule) | N5: Hot Water (Unit : Terajoule) | O5: Lighting (Unit : Terajoule) | P5: Refrigeration (Unit : Terajoule) | Q5: Office Equipment (Unit : Terajoule) | R5: Laundry (Unit : Terajoule) | S5: Others (Unit : Terajoule) | T5: 總計 Total | V5: 年份 Year | W5: Cooking (Unit : Terajoule) | X5: Air Conditioning (Unit : Terajoule) | Y5: Hot Water (Unit : Terajoule) | Z5: Lighting (Unit : Terajoule) | AA5: Refrigeration (Unit : Terajoule) | AB5: Office Equipment (Unit : Terajoule) | AC5: Laundry (Unit : Terajoule) | AD5: Others (Unit : Terajoule) | AE5: 總計 Total | AG5: 年份 Year | AH5: Cooking (Unit : Terajoule) | AI5: Air Conditioning (Unit : Terajoule) | AJ5: Hot Water (Unit : Terajoule) | AK5: Lighting (Unit : Terajoule) | AL5: Refrigeration (Unit : Terajoule) | AM5: Office Equipment (Unit : Terajoule) | AN5: Laundry (Unit : Terajoule) | AO5: Others (Unit : Terajoule) | AP5: 總計 Total | AR5: Year | AS5: Cooking (Unit : Terajoule) | AT5: Air Conditioning (Unit : Terajoule) | AU5: Hot Water (Unit : Terajoule) | AV5: Lighting (Unit : Terajoule) | AW5: Refrigeration (Unit : Terajoule) | AX5: Office Equipment (Unit : Terajoule) | AY5: Laundry (Unit : Terajoule) | AZ5: Others (Unit : Terajoule) | BA5: 總計 Total | BC5: 年份 Year | BD5: 煮食 Cooking | BE5: 空氣調節 Air Conditioning | BF5: 熱水 Hot Water | BG5: 照明 Lighting | BH5: 冷凍 Refrigeration | BI5: 辦公室設備 Office Equipment | BJ5: 其他 1 Others 1 | BK5: 總計 Total | BM5: 年份 Year | BN5: 煮食 Cooking | BO5: 空氣調節 Air Conditioning | BP5: 熱水 Hot Water | BQ5: 照明 Lighting | BR5: 冷凍 Refrigeration | BS5: 辦公室設備 Office Equipment | BT5: 其他 1 Others 1 | BU5: 總計 Total | BW5: 年份 Year | BX5: 煮食 Cooking | BY5: 空氣調節 Air Conditioning | BZ5: 熱水 Hot Water | CA5: 照明 Lighting | CB5: 冷凍 Refrigeration | CC5: 辦公室設備 Office Equipment | CD5: 其他 1 Others 1 | CE5: 總計 Total
A6: 2006 | B6: =BE6 -> 13285 | C6: =BF6 -> 12535 | D6: =BG6 -> 4633 | E6: =BH6 -> 6372 | F6: =BI6 -> 5366 | G6: =BD6 -> 16232 | H6: =BJ6 -> 2231 | I6: =BK6 -> 60654 | K6: 2006 | L6: 6828 | M6: 6122 | N6: 5074 | O6: 2148 | P6: 2830 | Q6: 2311 | R6: 0 | S6: 898 | T6: 26211 | V6: 2006 | W6: =G139+AH6 -> 6900 | X6: =B139+AI6 -> 5006 | Y6: =C139+AJ6 -> 5485 | Z6: =D139+AK6 -> 1760 | AA6: =E139+AL6 -> 2656 | AB6: =F139+AM6 -> 2211 | AD6: =H139+AO6 -> 948 | AE6: =I139+AP6 -> 24967 | AG6: 2006 | AH6: 2504 | AI6: 2157 | AJ6: 1976 | AK6: 725 | AL6: 886 | AM6: 844 | AN6: 0 | AO6: 385 | AP6: 9478 | AR6: 2006 | BA6: 0 | BC6: 2006 | BD6: =L6+W6+AH6+AS6 -> 16232 | BE6: =M6+X6+AI6+AT6 -> 13285 | BF6: =N6+Y6+AJ6+AU6 -> 12535 | BG6: =O6+Z6+AK6+AV6 -> 4633 | BH6: =P6+AA6+AL6+AW6 -> 6372 | BI6: =Q6+AB6+AM6+AX6 -> 5366 | BJ6: =R6+AC6+AN6+AY6+S6+AD6+AO6+AZ6 -> 2231 | BK6: =SUM(BD6:BJ6) -> 60654 | BM6: 2006 | BN6: =L6+AH6+AS6 -> 9332 | BO6: =M6+AI6+AT6 -> 8279 | BP6: =N6+AJ6+AU6 -> 7050 | BQ6: =O6+AK6+AV6 -> 2873 | BR6: =P6+AL6+AW6 -> 3716 | BS6: =Q6+AM6+AX6 -> 3155 | BT6: =R6+AY6+AN6+S6+AZ6+AO6 -> 1283 | BU6: =SUM(BN6:BT6) -> 35688 | BW6: 2006 | BX6: =W6 -> 6900 | BY6: =X6 -> 5006 | BZ6: =Y6 -> 5485 | CA6: =Z6 -> 1760 | CB6: =AA6 -> 2656 | CC6: =AB6 -> 2211 | CD6: =AC6+AD6 -> 948 | CE6: =SUM(BX6:CD6) -> 24966
A7: 2007 | B7: =BE7 -> 13329 | C7: =BF7 -> 12467 | D7: =BG7 -> 4509 | E7: =BH7 -> 6618 | F7: =BI7 -> 5701 | G7: =BD7 -> 16618 | H7: =BJ7 -> 2339 | I7: =BK7 -> 61581 | K7: 2007 | L7: 6974 | M7: 6176 | N7: 5104 | O7: 2100 | P7: 2962 | Q7: 2469 | R7: 0 | S7: 948 | T7: 26733 | V7: 2007 | W7: =G140+AH7 -> 7023 | X7: =B140+AI7 -> 4963 | Y7: =C140+AJ7 -> 5436 | Z7: =D140+AK7 -> 1709 | AA7: =E140+AL7 -> 2741 | AB7: =F140+AM7 -> 2323 | AD7: =H140+AO7 -> 990 | AE7: =I140+AP7 -> 25185 | AG7: 2007 | AH7: 2621 | AI7: 2190 | AJ7: 1927 | AK7: 700 | AL7: 915 | AM7: 909 | AN7: 0 | AO7: 401 | AP7: 9664 | AR7: 2007 | BA7: 0 | BC7: 2007 | BD7: =L7+W7+AH7+AS7 -> 16618 | BE7: =M7+X7+AI7+AT7 -> 13329 | BF7: =N7+Y7+AJ7+AU7 -> 12467 | BG7: =O7+Z7+AK7+AV7 -> 4509 | BH7: =P7+AA7+AL7+AW7 -> 6618 | BI7: =Q7+AB7+AM7+AX7 -> 5701 | BJ7: =R7+AC7+AN7+AY7+S7+AD7+AO7+AZ7 -> 2339 | BK7: =SUM(BD7:BJ7) -> 61581 | BM7: 2007 | BN7: =L7+AH7+AS7 -> 9595 | BO7: =M7+AI7+AT7 -> 8366 | BP7: =N7+AJ7+AU7 -> 7031 | BQ7: =O7+AK7+AV7 -> 2800 | BR7: =P7+AL7+AW7 -> 3877 | BS7: =Q7+AM7+AX7 -> 3378 | BT7: =R7+AY7+AN7+S7+AZ7+AO7 -> 1349 | BU7: =SUM(BN7:BT7) -> 36396 | BW7: 2007 | BX7: =W7 -> 7023 | BY7: =X7 -> 4963 | BZ7: =Y7 -> 5436 | CA7: =Z7 -> 1709 | CB7: =AA7 -> 2741 | CC7: =AB7 -> 2323 | CD7: =AC7+AD7 -> 990 | CE7: =SUM(BX7:CD7) -> 25185
A8: 2008 | B8: =BE8 -> 13292 | C8: =BF8 -> 12874 | D8: =BG8 -> 4353 | E8: =BH8 -> 6806 | F8: =BI8 -> 6021 | G8: =BD8 -> 17535 | H8: =BJ8 -> 2437 | I8: =BK8 -> 63318 | K8: 2008 | L8: 7334 | M8: 6240 | N8: 5323 | O8: 2055 | P8: 3101 | Q8: 2646 | R8: 0 | S8: 1002 | T8: 27701 | V8: 2008 | W8: =G141+AH8 -> 7334 | X8: =B141+AI8 -> 4836 | Y8: =C141+AJ8 -> 5559 | Z8: =D141+AK8 -> 1625 | AA8: =E141+AL8 -> 2765 | AB8: =F141+AM8 -> 2398 | AD8: =H141+AO8 -> 1017 | AE8: =I141+AP8 -> 25533 | AG8: 2008 | AH8: 2867 | AI8: 2216 | AJ8: 1992 | AK8: 673 | AL8: 940 | AM8: 977 | AN8: 0 | AO8: 418 | AP8: 10082 | AR8: 2008 | BA8: 0 | BC8: 2008 | BD8: =L8+W8+AH8+AS8 -> 17535 | BE8: =M8+X8+AI8+AT8 -> 13292 | BF8: =N8+Y8+AJ8+AU8 -> 12874 | BG8: =O8+Z8+AK8+AV8 -> 4353 | BH8: =P8+AA8+AL8+AW8 -> 6806 | BI8: =Q8+AB8+AM8+AX8 -> 6021 | BJ8: =R8+AC8+AN8+AY8+S8+AD8+AO8+AZ8 -> 2437 | BK8: =SUM(BD8:BJ8) -> 63318 | BM8: 2008 | BN8: =L8+AH8+AS8 -> 10201 | BO8: =M8+AI8+AT8 -> 8456 | BP8: =N8+AJ8+AU8 -> 7315 | BQ8: =O8+AK8+AV8 -> 2728 | BR8: =P8+AL8+AW8 -> 4041 | BS8: =Q8+AM8+AX8 -> 3623 | BT8: =R8+AY8+AN8+S8+AZ8+AO8 -> 1420 | BU8: =SUM(BN8:BT8) -> 37784 | BW8: 2008 | BX8: =W8 -> 7334 | BY8: =X8 -> 4836 | BZ8: =Y8 -> 5559 | CA8: =Z8 -> 1625 | CB8: =AA8 -> 2765 | CC8: =AB8 -> 2398 | CD8: =AC8+AD8 -> 1017 | CE8: =SUM(BX8:CD8) -> 25534
A9: 2009 | B9: =BE9 -> 14145 | C9: =BF9 -> 12864 | D9: =BG9 -> 4482 | E9: =BH9 -> 6907 | F9: =BI9 -> 6297 | G9: =BD9 -> 17300 | H9: =BJ9 -> 2771 | I9: =BK9 -> 64766 | K9: 2009 | L9: 7232 | M9: 6740 | N9: 5344 | O9: 2167 | P9: 3134 | Q9: 2764 | R9: 0 | S9: 1164 | T9: 28544 | V9: 2009 | W9: =G142+AH9 -> 7307 | X9: =B142+AI9 -> 5103 | Y9: =C142+AJ9 -> 5543 | Z9: =D142+AK9 -> 1639 | AA9: =E142+AL9 -> 2818 | AB9: =F142+AM9 -> 2519 | AD9: =H142+AO9 -> 1139 | AE9: =I142+AP9 -> 26068 | AG9: 2009 | AH9: 2761 | AI9: 2302 | AJ9: 1977 | AK9: 676 | AL9: 955 | AM9: 1014 | AN9: 0 | AO9: 468 | AP9: 10153 | AR9: 2009 | BA9: 0 | BC9: 2009 | BD9: =L9+W9+AH9+AS9 -> 17300 | BE9: =M9+X9+AI9+AT9 -> 14145 | BF9: =N9+Y9+AJ9+AU9 -> 12864 | BG9: =O9+Z9+AK9+AV9 -> 4482 | BH9: =P9+AA9+AL9+AW9 -> 6907 | BI9: =Q9+AB9+AM9+AX9 -> 6297 | BJ9: =R9+AC9+AN9+AY9+S9+AD9+AO9+AZ9 -> 2771 | BK9: =SUM(BD9:BJ9) -> 64766 | BM9: 2009 | BN9: =L9+AH9+AS9 -> 9993 | BO9: =M9+AI9+AT9 -> 9042 | BP9: =N9+AJ9+AU9 -> 7321 | BQ9: =O9+AK9+AV9 -> 2843 | BR9: =P9+AL9+AW9 -> 4089 | BS9: =Q9+AM9+AX9 -> 3778 | BT9: =R9+AY9+AN9+S9+AZ9+AO9 -> 1632 | BU9: =SUM(BN9:BT9) -> 38698 | BW9: 2009 | BX9: =W9 -> 7307 | BY9: =X9 -> 5103 | BZ9: =Y9 -> 5543 | CA9: =Z9 -> 1639 | CB9: =AA9 -> 2818 | CC9: =AB9 -> 2519 | CD9: =AC9+AD9 -> 1139 | CE9: =SUM(BX9:CD9) -> 26068
A10: 2010 | B10: =BE10 -> 12104 | C10: =BF10 -> 10831 | D10: =BG10 -> 3770 | E10: =BH10 -> 5747 | F10: =BI10 -> 5402 | G10: =BD10 -> 14518 | H10: =BJ10 -> 2594 | I10: =BK10 -> 54966 | K10: 2010 | L10: 7172 | M10: 6949 | N10: 5279 | O10: 2178 | P10: 3003 | Q10: 2815 | R10: 0 | S10: 1333 | T10: 28730 | V10: 2010 | W10: 4661 | X10: 2870 | Y10: 3557 | Z10: 947 | AA10: 1818 | AB10: 1558 | AD10: 742 | AE10: 16152 | AG10: 2010 | AH10: 2685 | AI10: 2285 | AJ10: 1995 | AK10: 645 | AL10: 926 | AM10: 1029 | AN10: 0 | AO10: 519 | AP10: 10084 | AR10: 2010 | BA10: 0 | BC10: 2010 | BD10: =L10+W10+AH10+AS10 -> 14518 | BE10: =M10+X10+AI10+AT10 -> 12104 | BF10: =N10+Y10+AJ10+AU10 -> 10831 | BG10: =O10+Z10+AK10+AV10 -> 3770 | BH10: =P10+AA10+AL10+AW10 -> 5747 | BI10: =Q10+AB10+AM10+AX10 -> 5402 | BJ10: =R10+AC10+AN10+AY10+S10+AD10+AO10+AZ10 -> 2594 | BK10: =SUM(BD10:BJ10) -> 54966 | BM10: 2010 | BN10: =L10+AH10+AS10 -> 9857 | BO10: =M10+AI10+AT10 -> 9234 | BP10: =N10+AJ10+AU10 -> 7274 | BQ10: =O10+AK10+AV10 -> 2823 | BR10: =P10+AL10+AW10 -> 3929 | BS10: =Q10+AM10+AX10 -> 3844 | BT10: =R10+AY10+AN10+S10+AZ10+AO10 -> 1852 | BU10: =SUM(BN10:BT10) -> 38813 | BW10: 2010 | BX10: =W10 -> 4661 | BY10: =X10 -> 2870 | BZ10: =Y10 -> 3557 | CA10: =Z10 -> 947 | CB10: =AA10 -> 1818 | CC10: =AB10 -> 1558 | CD10: =AC10+AD10 -> 742 | CE10: =SUM(BX10:CD10) -> 16153
A11: 2011 | B11: =BE11 -> 13423 | C11: =BF11 -> 11329 | D11: =BG11 -> 4042 | E11: =BH11 -> 5858 | F11: =BI11 -> 5908 | G11: =BD11 -> 15071 | H11: =BJ11 -> 3224 | I11: =BK11 -> 58855 | K11: 2011 | L11: 7028 | M11: 7201 | N11: 5259 | O11: 2204 | P11: 2891 | Q11: 2945 | R11: 0 | S11: 1606 | T11: =SUM(L11:S11) -> 29134 | V11: 2011 | W11: 4740 | X11: 2931 | Y11: 3565 | Z11: 942 | AA11: 1763 | AB11: 1642 | AD11: 841 | AE11: =SUM(W11:AD11) -> 16424 | AG11: 2011 | AH11: 2517 | AI11: 2163 | AJ11: 1950 | AK11: 585 | AL11: 857 | AM11: 1025 | AN11: 0 | AO11: 567 | AP11: =SUM(AH11:AO11) -> 9664 | AR11: 2011 | AS11: 786 | AT11: 1128 | AU11: 555 | AV11: 311 | AW11: 347 | AX11: 296 | AY11: 0 | AZ11: 210 | BA11: =SUM(AS11:AZ11) -> 3633 | BC11: 2011 | BD11: =L11+W11+AH11+AS11 -> 15071 | BE11: =M11+X11+AI11+AT11 -> 13423 | BF11: =N11+Y11+AJ11+AU11 -> 11329 | BG11: =O11+Z11+AK11+AV11 -> 4042 | BH11: =P11+AA11+AL11+AW11 -> 5858 | BI11: =Q11+AB11+AM11+AX11 -> 5908 | BJ11: =R11+AC11+AN11+AY11+S11+AD11+AO11+AZ11 -> 3224 | BK11: =SUM(BD11:BJ11) -> 58855 | BM11: 2011 | BN11: =L11+AH11+AS11 -> 10331 | BO11: =M11+AI11+AT11 -> 10492 | BP11: =N11+AJ11+AU11 -> 7764 | BQ11: =O11+AK11+AV11 -> 3100 | BR11: =P11+AL11+AW11 -> 4095 | BS11: =Q11+AM11+AX11 -> 4266 | BT11: =R11+AY11+AN11+S11+AZ11+AO11 -> 2383 | BU11: =SUM(BN11:BT11) -> 42431 | BW11: 2011 | BX11: =W11 -> 4740 | BY11: =X11 -> 2931 | BZ11: =Y11 -> 3565 | CA11: =Z11 -> 942 | CB11: =AA11 -> 1763 | CC11: =AB11 -> 1642 | CD11: =AC11+AD11 -> 841 | CE11: =SUM(BX11:CD11) -> 16424
A12: 2012 | B12: =BE12 -> 13846 | C12: =BF12 -> 11214 | D12: =BG12 -> 4086 | E12: =BH12 -> 5665 | F12: =BI12 -> 6357 | G12: =BD12 -> 14920 | H12: =BJ12 -> 3947 | I12: =BK12 -> 60035 | K12: 2012 | L12: 6788 | M12: 7364 | N12: 5113 | O12: 2208 | P12: 2743 | Q12: 3099 | R12: 0 | S12: 2008 | T12: =SUM(L12:S12) -> 29323 | V12: 2012 | W12: 4804 | X12: 3029 | Y12: 3549 | Z12: 970 | AA12: 1725 | AB12: 1794 | AD12: 995 | AE12: =SUM(W12:AD12) -> 16866 | AG12: 2012 | AH12: 2464 | AI12: 2162 | AJ12: 1982 | AK12: 561 | AL12: 838 | AM12: 1127 | AN12: 0 | AO12: 678 | AP12: =SUM(AH12:AO12) -> 9812 | AR12: 2012 | AS12: 864 | AT12: 1291 | AU12: 570 | AV12: 347 | AW12: 359 | AX12: 337 | AY12: 0 | AZ12: 266 | BA12: =SUM(AS12:AZ12) -> 4034 | BC12: 2012 | BD12: =L12+W12+AH12+AS12 -> 14920 | BE12: =M12+X12+AI12+AT12 -> 13846 | BF12: =N12+Y12+AJ12+AU12 -> 11214 | BG12: =O12+Z12+AK12+AV12 -> 4086 | BH12: =P12+AA12+AL12+AW12 -> 5665 | BI12: =Q12+AB12+AM12+AX12 -> 6357 | BJ12: =R12+AC12+AN12+AY12+S12+AD12+AO12+AZ12 -> 3947 | BK12: =SUM(BD12:BJ12) -> 60035 | BM12: 2012 | BN12: =L12+AH12+AS12 -> 10116 | BO12: =M12+AI12+AT12 -> 10817 | BP12: =N12+AJ12+AU12 -> 7665 | BQ12: =O12+AK12+AV12 -> 3116 | BR12: =P12+AL12+AW12 -> 3940 | BS12: =Q12+AM12+AX12 -> 4563 | BT12: =R12+AY12+AN12+S12+AZ12+AO12 -> 2952 | BU12: =SUM(BN12:BT12) -> 43169 | BW12: 2012 | BX12: =W12 -> 4804 | BY12: =X12 -> 3029 | BZ12: =Y12 -> 3549 | CA12: =Z12 -> 970 | CB12: =AA12 -> 1725 | CC12: =AB12 -> 1794 | CD12: =AC12+AD12 -> 995 | CE12: =SUM(BX12:CD12) -> 16866
A13: 2013 | B13: =BE13 -> 13078 | C13: =BF13 -> 11791 | D13: =BG13 -> 3469 | E13: =BH13 -> 5000 | F13: =BI13 -> 5319 | G13: =BD13 -> 15898 | H13: =BJ13 -> 4030 | I13: =BK13 -> 58585 | K13: 2013 | L13: 7301 | M13: 6914 | N13: 5450 | O13: 1874 | P13: 2404 | Q13: 2505 | R13: 0 | S13: 2042 | T13: =SUM(L13:S13) -> 28490 | V13: 2013 | W13: 5085 | X13: 2883 | Y13: 3661 | Z13: 823 | AA13: 1544 | AB13: 1573 | AD13: 1035 | AE13: =SUM(W13:AD13) -> 16604 | AG13: 2013 | AH13: 2515 | AI13: 2075 | AJ13: 2049 | AK13: 480 | AL13: 741 | AM13: 945 | AN13: 0 | AO13: 664 | AP13: =SUM(AH13:AO13) -> 9469 | AR13: 2013 | AS13: 997 | AT13: 1206 | AU13: 631 | AV13: 292 | AW13: 311 | AX13: 296 | AY13: 0 | AZ13: 289 | BA13: =SUM(AS13:AZ13) -> 4022 | BC13: 2013 | BD13: =L13+W13+AH13+AS13 -> 15898 | BE13: =M13+X13+AI13+AT13 -> 13078 | BF13: =N13+Y13+AJ13+AU13 -> 11791 | BG13: =O13+Z13+AK13+AV13 -> 3469 | BH13: =P13+AA13+AL13+AW13 -> 5000 | BI13: =Q13+AB13+AM13+AX13 -> 5319 | BJ13: =R13+AC13+AN13+AY13+S13+AD13+AO13+AZ13 -> 4030 | BK13: =SUM(BD13:BJ13) -> 58585 | BM13: 2013 | BN13: =L13+AH13+AS13 -> 10813 | BO13: =M13+AI13+AT13 -> 10195 | BP13: =N13+AJ13+AU13 -> 8130 | BQ13: =O13+AK13+AV13 -> 2646 | BR13: =P13+AL13+AW13 -> 3456 | BS13: =Q13+AM13+AX13 -> 3746 | BT13: =R13+AY13+AN13+S13+AZ13+AO13 -> 2995 | BU13: =SUM(BN13:BT13) -> 41981 | BW13: 2013 | BX13: =W13 -> 5085 | BY13: =X13 -> 2883 | BZ13: =Y13 -> 3661 | CA13: =Z13 -> 823 | CB13: =AA13 -> 1544 | CC13: =AB13 -> 1573 | CD13: =AC13+AD13 -> 1035 | CE13: =SUM(BX13:CD13) -> 16604
A14: 2014 | B14: =BE14 -> 15738 | C14: =BF14 -> 12772 | D14: =BG14 -> 3239 | E14: =BH14 -> 4778 | F14: =BI14 -> 4986 | G14: =BD14 -> 16114 | H14: =BJ14 -> 4479 | I14: =BK14 -> 62106 | K14: 2014 | L14: 7499 | M14: 8322 | N14: 6055 | O14: 1752 | P14: 2292 | Q14: 2357 | R14: 0 | S14: 2271 | T14: =SUM(L14:S14) -> 30548 | V14: 2014 | W14: 5083 | X14: 3496 | Y14: 3866 | Z14: 775 | AA14: 1495 | AB14: 1489 | AD14: 1168 | AE14: =SUM(W14:AD14) -> 17372 | AG14: 2014 | AH14: 2491 | AI14: 2565 | AJ14: 2167 | AK14: 454 | AL14: 715 | AM14: 873 | AN14: 0 | AO14: 718 | AP14: =SUM(AH14:AO14) -> 9983 | AR14: 2014 | AS14: 1041 | AT14: 1355 | AU14: 684 | AV14: 258 | AW14: 276 | AX14: 267 | AY14: 0 | AZ14: 322 | BA14: =SUM(AS14:AZ14) -> 4203 | BC14: 2014 | BD14: =L14+W14+AH14+AS14 -> 16114 | BE14: =M14+X14+AI14+AT14 -> 15738 | BF14: =N14+Y14+AJ14+AU14 -> 12772 | BG14: =O14+Z14+AK14+AV14 -> 3239 | BH14: =P14+AA14+AL14+AW14 -> 4778 | BI14: =Q14+AB14+AM14+AX14 -> 4986 | BJ14: =R14+AC14+AN14+AY14+S14+AD14+AO14+AZ14 -> 4479 | BK14: =SUM(BD14:BJ14) -> 62106 | BM14: 2014 | BN14: =L14+AH14+AS14 -> 11031 | BO14: =M14+AI14+AT14 -> 12242 | BP14: =N14+AJ14+AU14 -> 8906 | BQ14: =O14+AK14+AV14 -> 2464 | BR14: =P14+AL14+AW14 -> 3283 | BS14: =Q14+AM14+AX14 -> 3497 | BT14: =R14+AY14+AN14+S14+AZ14+AO14 -> 3311 | BU14: =SUM(BN14:BT14) -> 44734 | BW14: 2014 | BX14: =W14 -> 5083 | BY14: =X14 -> 3496 | BZ14: =Y14 -> 3866 | CA14: =Z14 -> 775 | CB14: =AA14 -> 1495 | CC14: =AB14 -> 1489 | CD14: =AC14+AD14 -> 1168 | CE14: =SUM(BX14:CD14) -> 17372
A15: 2015 | B15: =BE15 -> 15662 | C15: =BF15 -> 12957 | D15: =BG15 -> 2840 | E15: =BH15 -> 4213 | F15: =BI15 -> 4404 | G15: =BD15 -> 15727 | H15: =BJ15 -> 4636 | I15: =BK15 -> 60439 | K15: 2015 | L15: 7243 | M15: 8046 | N15: 6136 | O15: 1500 | P15: 1972 | Q15: 2047 | R15: 0 | S15: 2296 | T15: =SUM(L15:S15) -> 29240 | V15: 2015 | W15: 4912 | X15: 3580 | Y15: 3866 | Z15: 691 | AA15: 1349 | AB15: 1338 | AD15: 1235 | AE15: =SUM(W15:AD15) -> 16971 | AG15: 2015 | AH15: 2350 | AI15: 2605 | AJ15: 2177 | AK15: 400 | AL15: 632 | AM15: 758 | AN15: 0 | AO15: 718 | AP15: =SUM(AH15:AO15) -> 9640 | AR15: 2015 | AS15: 1222 | AT15: 1431 | AU15: 778 | AV15: 249 | AW15: 260 | AX15: 261 | AY15: 0 | AZ15: 387 | BA15: =SUM(AS15:AZ15) -> 4588 | BC15: 2015 | BD15: =L15+W15+AH15+AS15 -> 15727 | BE15: =M15+X15+AI15+AT15 -> 15662 | BF15: =N15+Y15+AJ15+AU15 -> 12957 | BG15: =O15+Z15+AK15+AV15 -> 2840 | BH15: =P15+AA15+AL15+AW15 -> 4213 | BI15: =Q15+AB15+AM15+AX15 -> 4404 | BJ15: =R15+AC15+AN15+AY15+S15+AD15+AO15+AZ15 -> 4636 | BK15: =SUM(BD15:BJ15) -> 60439 | BM15: 2015 | BN15: =L15+AH15+AS15 -> 10815 | BO15: =M15+AI15+AT15 -> 12082 | BP15: =N15+AJ15+AU15 -> 9091 | BQ15: =O15+AK15+AV15 -> 2149 | BR15: =P15+AL15+AW15 -> 2864 | BS15: =Q15+AM15+AX15 -> 3066 | BT15: =R15+AY15+AN15+S15+AZ15+AO15 -> 3401 | BU15: =SUM(BN15:BT15) -> 43468 | BW15: 2015 | BX15: =W15 -> 4912 | BY15: =X15 -> 3580 | BZ15: =Y15 -> 3866 | CA15: =Z15 -> 691 | CB15: =AA15 -> 1349 | CC15: =AB15 -> 1338 | CD15: =AC15+AD15 -> 1235 | CE15: =SUM(BX15:CD15) -> 16971
A16: 2016 | B16: =BE16 -> 16082 | C16: =BF16 -> 14095 | D16: =BG16 -> 2581 | E16: =BH16 -> 3783 | F16: =BI16 -> 4017 | G16: =BD16 -> 16236 | H16: =BJ16 -> 4908 | I16: =BK16 -> 61702 | K16: 2016 | L16: 7706 | M16: 8323 | N16: 6933 | O16: 1379 | P16: 1789 | Q16: 1893 | R16: 0 | S16: 2465 | T16: =SUM(L16:S16) -> 30488 | V16: 2016 | W16: 4942 | X16: 3758 | Y16: 4079 | Z16: 633 | AA16: 1226 | AB16: 1231 | AD16: 1320 | AE16: =SUM(W16:AD16) -> 17189 | AG16: 2016 | AH16: 2298 | AI16: 2676 | AJ16: 2278 | AK16: 359 | AL16: 560 | AM16: 674 | AN16: 0 | AO16: 726 | AP16: =SUM(AH16:AO16) -> 9571 | AR16: 2016 | AS16: 1290 | AT16: 1325 | AU16: 805 | AV16: 210 | AW16: 208 | AX16: 219 | AY16: 0 | AZ16: 397 | BA16: =SUM(AS16:AZ16) -> 4454 | BC16: 2016 | BD16: =L16+W16+AH16+AS16 -> 16236 | BE16: =M16+X16+AI16+AT16 -> 16082 | BF16: =N16+Y16+AJ16+AU16 -> 14095 | BG16: =O16+Z16+AK16+AV16 -> 2581 | BH16: =P16+AA16+AL16+AW16 -> 3783 | BI16: =Q16+AB16+AM16+AX16 -> 4017 | BJ16: =R16+AC16+AN16+AY16+S16+AD16+AO16+AZ16 -> 4908 | BK16: =SUM(BD16:BJ16) -> 61702 | BM16: 2016 | BN16: =L16+AH16+AS16 -> 11294 | BO16: =M16+AI16+AT16 -> 12324 | BP16: =N16+AJ16+AU16 -> 10016 | BQ16: =O16+AK16+AV16 -> 1948 | BR16: =P16+AL16+AW16 -> 2557 | BS16: =Q16+AM16+AX16 -> 2786 | BT16: =R16+AY16+AN16+S16+AZ16+AO16 -> 3588 | BU16: =SUM(BN16:BT16) -> 44513 | BW16: 2016 | BX16: =W16 -> 4942 | BY16: =X16 -> 3758 | BZ16: =Y16 -> 4079 | CA16: =Z16 -> 633 | CB16: =AA16 -> 1226 | CC16: =AB16 -> 1231 | CD16: =AC16+AD16 -> 1320 | CE16: =SUM(BX16:CD16) -> 17189
A17: 2017 | B17: =BE17 -> 15926 | C17: =BF17 -> 14376 | D17: =BG17 -> 2286 | E17: =BH17 -> 3214 | F17: =BI17 -> 3495 | G17: =BD17 -> 16227 | H17: =BJ17 -> 4949 | I17: =BK17 -> 60473 | K17: 2017 | L17: 7887 | M17: 8202 | N17: 7241 | O17: 1220 | P17: 1522 | Q17: 1652 | R17: 1465 | S17: 1036 | T17: =SUM(L17:S17) -> 30225 | V17: 2017 | W17: 4777 | X17: 3821 | Y17: 4041 | Z17: 570 | AA17: 1053 | AB17: 1080 | AC17: 790 | AD17: 549 | AE17: =SUM(W17:AD17) -> 16681 | AG17: 2017 | AH17: 2190 | AI17: 2703 | AJ17: 2306 | AK17: 318 | AL17: 477 | AM17: 582 | AN17: 475 | AO17: 234 | AP17: =SUM(AH17:AO17) -> 9285 | AR17: 2017 | AS17: 1373 | AT17: 1200 | AU17: 788 | AV17: 178 | AW17: 162 | AX17: 181 | AY17: 144 | AZ17: 256 | BA17: =SUM(AS17:AZ17) -> 4282 | BC17: 2017 | BD17: =L17+W17+AH17+AS17 -> 16227 | BE17: =M17+X17+AI17+AT17 -> 15926 | BF17: =N17+Y17+AJ17+AU17 -> 14376 | BG17: =O17+Z17+AK17+AV17 -> 2286 | BH17: =P17+AA17+AL17+AW17 -> 3214 | BI17: =Q17+AB17+AM17+AX17 -> 3495 | BJ17: =R17+AC17+AN17+AY17+S17+AD17+AO17+AZ17 -> 4949 | BK17: =SUM(BD17:BJ17) -> 60473 | BM17: 2017 | BN17: =L17+AH17+AS17 -> 11450 | BO17: =M17+AI17+AT17 -> 12105 | BP17: =N17+AJ17+AU17 -> 10335 | BQ17: =O17+AK17+AV17 -> 1716 | BR17: =P17+AL17+AW17 -> 2161 | BS17: =Q17+AM17+AX17 -> 2415 | BT17: =R17+AY17+AN17+S17+AZ17+AO17 -> 3610 | BU17: =SUM(BN17:BT17) -> 43792 | BW17: 2017 | BX17: =W17 -> 4777 | BY17: =X17 -> 3821 | BZ17: =Y17 -> 4041 | CA17: =Z17 -> 570 | CB17: =AA17 -> 1053 | CC17: =AB17 -> 1080 | CD17: =AC17+AD17 -> 1339 | CE17: =SUM(BX17:CD17) -> 16681
A18: 2018 | B18: =BE18 -> 15765 | C18: =BF18 -> 14692 | D18: =BG18 -> 2286 | E18: =BH18 -> 3211 | F18: =BI18 -> 3489 | G18: =BD18 -> 17159 | H18: =BJ18 -> 4955 | I18: =BK18 -> 61557 | K18: 2018 | L18: 8210 | M18: 8000 | N18: 7212 | O18: 1202 | P18: 1502 | Q18: 1628 | R18: 1445 | S18: 1021 | T18: =SUM(L18:S18) -> 30220 | V18: 2018 | W18: 4941 | X18: 3767 | Y18: 4124 | Z18: 568 | AA18: 1050 | AB18: 1076 | AC18: 787 | AD18: 547 | AE18: =SUM(W18:AD18) -> 16860 | AG18: 2018 | AH18: 2269 | AI18: 2678 | AJ18: 2431 | AK18: 318 | AL18: 478 | AM18: 583 | AN18: 475 | AO18: 234 | AP18: =SUM(AH18:AO18) -> 9466 | AR18: 2018 | AS18: 1739 | AT18: 1320 | AU18: 925 | AV18: 198 | AW18: 181 | AX18: 202 | AY18: 161 | AZ18: 285 | BA18: =SUM(AS18:AZ18) -> 5011 | BC18: 2018 | BD18: =L18+W18+AH18+AS18 -> 17159 | BE18: =M18+X18+AI18+AT18 -> 15765 | BF18: =N18+Y18+AJ18+AU18 -> 14692 | BG18: =O18+Z18+AK18+AV18 -> 2286 | BH18: =P18+AA18+AL18+AW18 -> 3211 | BI18: =Q18+AB18+AM18+AX18 -> 3489 | BJ18: =R18+AC18+AN18+AY18+S18+AD18+AO18+AZ18 -> 4955 | BK18: =SUM(BD18:BJ18) -> 61557 | BM18: 2018 | BN18: =L18+AH18+AS18 -> 12218 | BO18: =M18+AI18+AT18 -> 11998 | BP18: =N18+AJ18+AU18 -> 10568 | BQ18: =O18+AK18+AV18 -> 1718 | BR18: =P18+AL18+AW18 -> 2161 | BS18: =Q18+AM18+AX18 -> 2413 | BT18: =R18+AY18+AN18+S18+AZ18+AO18 -> 3621 | BU18: =SUM(BN18:BT18) -> 44697 | BW18: 2018 | BX18: =W18 -> 4941 | BY18: =X18 -> 3767 | BZ18: =Y18 -> 4124 | CA18: =Z18 -> 568 | CB18: =AA18 -> 1050 | CC18: =AB18 -> 1076 | CD18: =AC18+AD18 -> 1334 | CE18: =SUM(BX18:CD18) -> 16860
A19: 2019 | B19: =BE19 -> 16113 | C19: =BF19 -> 14147 | D19: =BG19 -> 2354 | E19: =BH19 -> 3349 | F19: =BI19 -> 3594 | G19: =BD19 -> 16365 | H19: =BJ19 -> 5099 | I19: =BK19 -> 61021 | K19: 2019 | L19: 7851 | M19: 8203 | N19: 7037 | O19: 1239 | P19: 1567 | Q19: 1678 | R19: 1487 | S19: 1053 | T19: =SUM(L19:S19) -> 30115 | V19: 2019 | W19: 4768 | X19: 3819 | Y19: 3961 | Z19: 584 | AA19: 1093 | AB19: 1106 | AC19: 808 | AD19: 563 | AE19: =SUM(W19:AD19) -> 16702 | AG19: 2019 | AH19: 2225 | AI19: 2778 | AJ19: 2301 | AK19: 331 | AL19: 504 | AM19: 606 | AN19: 494 | AO19: 244 | AP19: =SUM(AH19:AO19) -> 9483 | AR19: 2019 | AS19: 1521 | AT19: 1313 | AU19: 848 | AV19: 200 | AW19: 185 | AX19: 204 | AY19: 162 | AZ19: 288 | BA19: =SUM(AS19:AZ19) -> 4721 | BC19: 2019 | BD19: =L19+W19+AH19+AS19 -> 16365 | BE19: =M19+X19+AI19+AT19 -> 16113 | BF19: =N19+Y19+AJ19+AU19 -> 14147 | BG19: =O19+Z19+AK19+AV19 -> 2354 | BH19: =P19+AA19+AL19+AW19 -> 3349 | BI19: =Q19+AB19+AM19+AX19 -> 3594 | BJ19: =R19+AC19+AN19+AY19+S19+AD19+AO19+AZ19 -> 5099 | BK19: =SUM(BD19:BJ19) -> 61021 | BM19: 2019 | BN19: =L19+AH19+AS19 -> 11597 | BO19: =M19+AI19+AT19 -> 12294 | BP19: =N19+AJ19+AU19 -> 10186 | BQ19: =O19+AK19+AV19 -> 1770 | BR19: =P19+AL19+AW19 -> 2256 | BS19: =Q19+AM19+AX19 -> 2488 | BT19: =R19+AY19+AN19+S19+AZ19+AO19 -> 3728 | BU19: =SUM(BN19:BT19) -> 44319 | BW19: 2019 | BX19: =W19 -> 4768 | BY19: =X19 -> 3819 | BZ19: =Y19 -> 3961 | CA19: =Z19 -> 584 | CB19: =AA19 -> 1093 | CC19: =AB19 -> 1106 | CD19: =AC19+AD19 -> 1371 | CE19: =SUM(BX19:CD19) -> 16702
A20: 2020 | B20: =BE20 -> 18137 | C20: =BF20 -> 15449 | D20: =BG20 -> 2501 | E20: =BH20 -> 3550 | F20: =BI20 -> 3819 | G20: =BD20 -> 17535 | H20: =BJ20 -> 5421 | I20: =BK20 -> 66412 | K20: 2020 | L20: 8417 | M20: 9247 | N20: 7710 | O20: 1320 | P20: 1666 | Q20: 1788 | R20: 1586 | S20: 1121 | T20: =SUM(L20:S20) -> 32855 | V20: 2020 | W20: 5131 | X20: 4280 | Y20: 4318 | Z20: 617 | AA20: 1153 | AB20: 1169 | AC20: 855 | AD20: 595 | AE20: =SUM(W20:AD20) -> 18118 | AG20: 2020 | AH20: 2413 | AI20: 3131 | AJ20: 2524 | AK20: 352 | AL20: 535 | AM20: 646 | AN20: 526 | AO20: 260 | AP20: =SUM(AH20:AO20) -> 10387 | AR20: 2020 | AS20: 1574 | AT20: 1479 | AU20: 897 | AV20: 212 | AW20: 196 | AX20: 216 | AY20: 172 | AZ20: 306 | BA20: =SUM(AS20:AZ20) -> 5052 | BC20: 2020 | BD20: =L20+W20+AH20+AS20 -> 17535 | BE20: =M20+X20+AI20+AT20 -> 18137 | BF20: =N20+Y20+AJ20+AU20 -> 15449 | BG20: =O20+Z20+AK20+AV20 -> 2501 | BH20: =P20+AA20+AL20+AW20 -> 3550 | BI20: =Q20+AB20+AM20+AX20 -> 3819 | BJ20: =R20+AC20+AN20+AY20+S20+AD20+AO20+AZ20 -> 5421 | BK20: =SUM(BD20:BJ20) -> 66412 | BM20: 2020 | BN20: =L20+AH20+AS20 -> 12404 | BO20: =M20+AI20+AT20 -> 13857 | BP20: =N20+AJ20+AU20 -> 11131 | BQ20: =O20+AK20+AV20 -> 1884 | BR20: =P20+AL20+AW20 -> 2397 | BS20: =Q20+AM20+AX20 -> 2650 | BT20: =R20+AY20+AN20+S20+AZ20+AO20 -> 3971 | BU20: =SUM(BN20:BT20) -> 48294 | BW20: 2020 | BX20: =W20 -> 5131 | BY20: =X20 -> 4280 | BZ20: =Y20 -> 4318 | CA20: =Z20 -> 617 | CB20: =AA20 -> 1153 | CC20: =AB20 -> 1169 | CD20: =AC20+AD20 -> 1450 | CE20: =SUM(BX20:CD20) -> 18118
A21: 2021 | B21: =BE21 -> 18697 | C21: =BF21 -> 15074 | D21: =BG21 -> 2526 | E21: =BH21 -> 3603 | F21: =BI21 -> 3855 | G21: =BD21 -> 17493 | H21: =BJ21 -> 5475 | I21: =BK21 -> 66723 | K21: 2021 | L21: 8198 | M21: 9309 | N21: 7349 | O21: 1301 | P21: 1651 | Q21: 1762 | R21: 1561 | S21: 1105 | T21: =SUM(L21:S21) -> 32236 | V21: 2021 | W21: 5121 | X21: 4446 | Y21: 4249 | Z21: 630 | AA21: 1183 | AB21: 1193 | AC21: 871 | AD21: 607 | AE21: =SUM(W21:AD21) -> 18300 | AG21: 2021 | AH21: 2426 | AI21: 3288 | AJ21: 2501 | AK21: 362 | AL21: 553 | AM21: 663 | AN21: 540 | AO21: 267 | AP21: =SUM(AH21:AO21) -> 10600 | AR21: 2021 | AS21: 1748 | AT21: 1654 | AU21: 975 | AV21: 233 | AW21: 216 | AX21: 237 | AY21: 189 | AZ21: 335 | BA21: =SUM(AS21:AZ21) -> 5587 | BC21: 2021 | BD21: =L21+W21+AH21+AS21 -> 17493 | BE21: =M21+X21+AI21+AT21 -> 18697 | BF21: =N21+Y21+AJ21+AU21 -> 15074 | BG21: =O21+Z21+AK21+AV21 -> 2526 | BH21: =P21+AA21+AL21+AW21 -> 3603 | BI21: =Q21+AB21+AM21+AX21 -> 3855 | BJ21: =R21+AC21+AN21+AY21+S21+AD21+AO21+AZ21 -> 5475 | BK21: =SUM(BD21:BJ21) -> 66723 | BM21: 2021 | BN21: =L21+AH21+AS21 -> 12372 | BO21: =M21+AI21+AT21 -> 14251 | BP21: =N21+AJ21+AU21 -> 10825 | BQ21: =O21+AK21+AV21 -> 1896 | BR21: =P21+AL21+AW21 -> 2420 | BS21: =Q21+AM21+AX21 -> 2662 | BT21: =R21+AY21+AN21+S21+AZ21+AO21 -> 3997 | BU21: =SUM(BN21:BT21) -> 48423 | BW21: 2021 | BX21: =W21 -> 5121 | BY21: =X21 -> 4446 | BZ21: =Y21 -> 4249 | CA21: =Z21 -> 630 | CB21: =AA21 -> 1183 | CC21: =AB21 -> 1193 | CD21: =AC21+AD21 -> 1478 | CE21: =SUM(BX21:CD21) -> 18300
A23: 转换为百分比Change to percentage
A24: Year | B24: Hot Water | C24: Lighting | D24: Refrigeration | E24: Office Equipment | F24: Cooking | G24: Air Conditioning | H24: Others | I24: Sum | K24: 私人住宅Private Housing Segment | V24: 公共住宅 Public Housing | AG24: 房委会资助出售单位组别 Housing Authority Subsidized Sale Flats Segment | AR24: Total Energy Consumption in Other Housing Segment by End-use | BC24: 重新加总Private+Public | BM24: Private = Urban defination in the EPS | BW24: Public = Rural defination in the EPS
A25: 年份 Year | B25: =BE25 -> 空氣調節 Air Conditioning | C25: =BF25 -> 熱水 Hot Water | D25: =BG25 -> 照明 Lighting | E25: =BH25 -> 冷凍 Refrigeration | F25: =BI25 -> 辦公室設備 Office Equipment | G25: =BD25 -> 煮食 Cooking | H25: =BJ25 -> 其他 1 Others 1 | I25: =BK25 -> 總計 Total | K25: 年份 Year | L25: 煮食 Cooking | M25: 空氣調節 Air Conditioning | N25: 熱水 Hot Water | O25: 照明 Lighting | P25: 冷凍 Refrigeration | Q25: 辦公室設備 Office Equipment | R25: Laundry (Unit : Terajoule) | S25: 其他 1 Others 1 | T25: 總計 Total | V25: 年份 Year | W25: 煮食 Cooking | X25: 空氣調節 Air Conditioning | Y25: 熱水 Hot Water | Z25: 照明 Lighting | AA25: 冷凍 Refrigeration | AB25: 辦公室設備 Office Equipment | AC25: Laundry (Unit : Terajoule) | AD25: 其他 1 Others 1 | AE25: 總計 Total | AG25: 年份 Year | AH25: 煮食 Cooking | AI25: 空氣調節 Air Conditioning | AJ25: 熱水 Hot Water | AK25: 照明 Lighting | AL25: 冷凍 Refrigeration | AM25: 辦公室設備 Office Equipment | AN25: Laundry (Unit : Terajoule) | AO25: 其他 1 Others 1 | AP25: 總計 Total | AR25: 年份 Year | AS25: 煮食 Cooking | AT25: 空氣調節 Air Conditioning | AU25: 熱水 Hot Water | AV25: 照明 Lighting | AW25: 冷凍 Refrigeration | AX25: 辦公室設備 Office Equipment | AY25: Laundry (Unit : Terajoule) | AZ25: 其他 1 Others 1 | BA25: 總計 Total | BC25: 年份 Year | BD25: 煮食 Cooking | BE25: 空氣調節 Air Conditioning | BF25: 熱水 Hot Water | BG25: 照明 Lighting | BH25: 冷凍 Refrigeration | BI25: 辦公室設備 Office Equipment | BJ25: 其他 1 Others 1 | BK25: 總計 Total | BM25: 年份 Year | BN25: 煮食 Cooking | BO25: 空氣調節 Air Conditioning | BP25: 熱水 Hot Water | BQ25: 照明 Lighting | BR25: 冷凍 Refrigeration | BS25: 辦公室設備 Office Equipment | BT25: 其他 1 Others 1 | BU25: 總計 Total | BW25: 年份 Year | BX25: 煮食 Cooking | BY25: 空氣調節 Air Conditioning | BZ25: 熱水 Hot Water | CA25: 照明 Lighting | CB25: 冷凍 Refrigeration | CC25: 辦公室設備 Office Equipment | CD25: 其他 1 Others 1 | CE25: 總計 Total
A26: 2006 | B26: =BE26 -> 0.21902925 | C26: =BF26 -> 0.20666403 | D26: =BG26 -> 0.07638408 | E26: =BH26 -> 0.1050549 | F26: =BI26 -> 0.088469021 | G26: =BD26 -> 0.26761632 | H26: =BJ26 -> 0.036782405 | I26: =BK26 -> 1 | K26: 2006 | L26: =L6/$T6 -> 0.26050132 | M26: =M6/$T6 -> 0.23356606 | N26: =N6/$T6 -> 0.19358285 | O26: =O6/$T6 -> 0.081950326 | P26: =P6/$T6 -> 0.10796994 | Q26: =Q6/$T6 -> 0.088169089 | R26: =R6/$T6 -> 0 | S26: =S6/$T6 -> 0.034260425 | T26: =T6/$T6 -> 1 | V26: 2006 | W26: =W6/$AE6 -> 0.2763648 | X26: =X6/$AE6 -> 0.20050467 | Y26: =Y6/$AE6 -> 0.21968999 | Z26: =Z6/$AE6 -> 0.070493051 | AA26: =AA6/$AE6 -> 0.10638042 | AB26: =AB6/$AE6 -> 0.088556895 | AC26: =AC6/$AE6 -> 0 | AD26: =AD6/$AE6 -> 0.037970121 | AE26: =AE6/$AE6 -> 1 | AG26: 2006 | AH26: =AH6/$AP6 -> 0.26419076 | AI26: =AI6/$AP6 -> 0.22757966 | AJ26: =AJ6/$AP6 -> 0.2084828 | AK26: =AK6/$AP6 -> 0.076492931 | AL26: =AL6/$AP6 -> 0.093479637 | AM26: =AM6/$AP6 -> 0.089048322 | AN26: =AN6/$AP6 -> 0 | AO26: =AO6/$AP6 -> 0.040620384 | AP26: =AP6/$AE6 -> 0.3796211 | AR26: 2006 | AS26: =IFERROR(AS6/$BA6,0) -> 0 | AT26: =IFERROR(AT6/$BA6,0) -> 0 | AU26: =IFERROR(AU6/$BA6,0) -> 0 | AV26: =IFERROR(AV6/$BA6,0) -> 0 | AW26: =IFERROR(AW6/$BA6,0) -> 0 | AX26: =IFERROR(AX6/$BA6,0) -> 0 | AY26: =IFERROR(AY6/$BA6,0) -> 0 | AZ26: =AZ6/$AP6 -> 0 | BA26: =BA6/$AE6 -> 0 | BC26: 2006 | BD26: =(L26*$T6+W26*$AE6+AH26*$AP6+AS26*$BA6)/$I6 -> 0.26761632 | BE26: =(M26*$T6+X26*$AE6+AI26*$AP6+AT26*$BA6)/$I6 -> 0.21902925 | BF26: =(N26*$T6+Y26*$AE6+AJ26*$AP6+AU26*$BA6)/$I6 -> 0.20666403 | BG26: =(O26*$T6+Z26*$AE6+AK26*$AP6+AV26*$BA6)/$I6 -> 0.07638408 | BH26: =(P26*$T6+AA26*$AE6+AL26*$AP6+AW26*$BA6)/$I6 -> 0.1050549 | BI26: =(Q26*$T6+AB26*$AE6+AM26*$AP6+AX26*$BA6)/$I6 -> 0.088469021 | BJ26: =((R26+S26)*$T6+(AC26+AD26)*$AE6+(AN26+AO26)*$AP6+(AZ26+AY26)*$BA6)/$I6 -> 0.036782405 | BK26: =SUM(BD26:BJ26) -> 1 | BM26: 2006 | BN26: =BN6/$BU6 -> 0.26148846 | BO26: =BO6/$BU6 -> 0.23198274 | BP26: =BP6/$BU6 -> 0.19754539 | BQ26: =BQ6/$BU6 -> 0.08050325 | BR26: =BR6/$BU6 -> 0.10412464 | BS26: =BS6/$BU6 -> 0.088405066 | BT26: =BT6/$BU6 -> 0.03595046 | BU26: =SUM(BN26:BT26) -> 1 | BW26: 2006 | BX26: =IFERROR(BX6/$CE6,0) -> 0.27637587 | BY26: =IFERROR(BY6/$CE6,0) -> 0.2005127 | BZ26: =IFERROR(BZ6/$CE6,0) -> 0.21969879 | CA26: =IFERROR(CA6/$CE6,0) -> 0.070495874 | CB26: =IFERROR(CB6/$CE6,0) -> 0.10638468 | CC26: =IFERROR(CC6/$CE6,0) -> 0.088560442 | CD26: =IFERROR(CD6/$CE6,0) -> 0.037971641 | CE26: =SUM(BX26:CD26) -> 1
A27: 2007 | B27: =BE27 -> 0.21644663 | C27: =BF27 -> 0.20244881 | D27: =BG27 -> 0.073220636 | E27: =BH27 -> 0.10746821 | F27: =BI27 -> 0.092577256 | G27: =BD27 -> 0.26985596 | H27: =BJ27 -> 0.037982495 | I27: =BK27 -> 1 | K27: 2007 | L27: =L7/$T7 -> 0.26087607 | M27: =M7/$T7 -> 0.23102532 | N27: =N7/$T7 -> 0.19092507 | O27: =O7/$T7 -> 0.078554595 | P27: =P7/$T7 -> 0.11079939 | Q27: =Q7/$T7 -> 0.09235776 | R27: =R7/$T7 -> 0 | S27: =S7/$T7 -> 0.035461789 | T27: =T7/$T7 -> 1 | V27: 2007 | W27: =W7/$AE7 -> 0.27885646 | X27: =X7/$AE7 -> 0.19706174 | Y27: =Y7/$AE7 -> 0.21584276 | Z27: =Z7/$AE7 -> 0.067857852 | AA27: =AA7/$AE7 -> 0.10883462 | AB27: =AB7/$AE7 -> 0.092237443 | AC27: =AC7/$AE7 -> 0 | AD27: =AD7/$AE7 -> 0.039309113 | AE27: =AE7/$AE7 -> 1 | AG27: 2007 | AH27: =AH7/$AP7 -> 0.27121275 | AI27: =AI7/$AP7 -> 0.22661424 | AJ27: =AJ7/$AP7 -> 0.19939983 | AK27: =AK7/$AP7 -> 0.072433775 | AL27: =AL7/$AP7 -> 0.094681291 | AM27: =AM7/$AP7 -> 0.09406043 | AN27: =AN7/$AP7 -> 0 | AO27: =AO7/$AP7 -> 0.041494205 | AP27: =AP7/$AE7 -> 0.38372047 | AR27: 2007 | AS27: =IFERROR(AS7/$BA7,0) -> 0 | AT27: =IFERROR(AT7/$BA7,0) -> 0 | AU27: =IFERROR(AU7/$BA7,0) -> 0 | AV27: =IFERROR(AV7/$BA7,0) -> 0 | AW27: =IFERROR(AW7/$BA7,0) -> 0 | AX27: =IFERROR(AX7/$BA7,0) -> 0 | AY27: =IFERROR(AY7/$BA7,0) -> 0 | AZ27: =AZ7/$AP7 -> 0 | BA27: =BA7/$AE7 -> 0 | BC27: 2007 | BD27: =(L27*$T7+W27*$AE7+AH27*$AP7+AS27*$BA7)/$I7 -> 0.26985596 | BE27: =(M27*$T7+X27*$AE7+AI27*$AP7+AT27*$BA7)/$I7 -> 0.21644663 | BF27: =(N27*$T7+Y27*$AE7+AJ27*$AP7+AU27*$BA7)/$I7 -> 0.20244881 | BG27: =(O27*$T7+Z27*$AE7+AK27*$AP7+AV27*$BA7)/$I7 -> 0.073220636 | BH27: =(P27*$T7+AA27*$AE7+AL27*$AP7+AW27*$BA7)/$I7 -> 0.10746821 | BI27: =(Q27*$T7+AB27*$AE7+AM27*$AP7+AX27*$BA7)/$I7 -> 0.092577256 | BJ27: =((R27+S27)*$T7+(AC27+AD27)*$AE7+(AN27+AO27)*$AP7+(AZ27+AY27)*$BA7)/$I7 -> 0.037982495 | BK27: =SUM(BD27:BJ27) -> 1 | BM27: 2007 | BN27: =BN7/$BU7 -> 0.26362787 | BO27: =BO7/$BU7 -> 0.22986042 | BP27: =BP7/$BU7 -> 0.19318057 | BQ27: =BQ7/$BU7 -> 0.076931531 | BR27: =BR7/$BU7 -> 0.10652269 | BS27: =BS7/$BU7 -> 0.092812397 | BT27: =BT7/$BU7 -> 0.037064513 | BU27: =SUM(BN27:BT27) -> 1 | BW27: 2007 | BX27: =IFERROR(BX7/$CE7,0) -> 0.27885646 | BY27: =IFERROR(BY7/$CE7,0) -> 0.19706174 | BZ27: =IFERROR(BZ7/$CE7,0) -> 0.21584276 | CA27: =IFERROR(CA7/$CE7,0) -> 0.067857852 | CB27: =IFERROR(CB7/$CE7,0) -> 0.10883462 | CC27: =IFERROR(CC7/$CE7,0) -> 0.092237443 | CD27: =IFERROR(CD7/$CE7,0) -> 0.039309113 | CE27: =SUM(BX27:CD27) -> 1
A28: 2008 | B28: =BE28 -> 0.20992451 | C28: =BF28 -> 0.20332291 | D28: =BG28 -> 0.068748223 | E28: =BH28 -> 0.10748918 | F28: =BI28 -> 0.095091443 | G28: =BD28 -> 0.27693547 | H28: =BJ28 -> 0.038488266 | I28: =BK28 -> 1 | K28: 2008 | L28: =L8/$T8 -> 0.26475578 | M28: =M8/$T8 -> 0.22526263 | N28: =N8/$T8 -> 0.19215913 | O28: =O8/$T8 -> 0.074185047 | P28: =P8/$T8 -> 0.11194542 | Q28: =Q8/$T8 -> 0.095520017 | R28: =R8/$T8 -> 0 | S28: =S8/$T8 -> 0.036171979 | T28: =T8/$T8 -> 1 | V28: 2008 | W28: =W8/$AE8 -> 0.28723613 | X28: =X8/$AE8 -> 0.18940195 | Y28: =Y8/$AE8 -> 0.21771825 | Z28: =Z8/$AE8 -> 0.063643129 | AA28: =AA8/$AE8 -> 0.10829123 | AB28: =AB8/$AE8 -> 0.093917675 | AC28: =AC8/$AE8 -> 0 | AD28: =AD8/$AE8 -> 0.039830807 | AE28: =AE8/$AE8 -> 1 | AG28: 2008 | AH28: =AH8/$AP8 -> 0.28436818 | AI28: =AI8/$AP8 -> 0.21979766 | AJ28: =AJ8/$AP8 -> 0.19757985 | AK28: =AK8/$AP8 -> 0.066752628 | AL28: =AL8/$AP8 -> 0.093235469 | AM28: =AM8/$AP8 -> 0.096905376 | AN28: =AN8/$AP8 -> 0 | AO28: =AO8/$AP8 -> 0.041460028 | AP28: =AP8/$AE8 -> 0.39486155 | AR28: 2008 | AS28: =IFERROR(AS8/$BA8,0) -> 0 | AT28: =IFERROR(AT8/$BA8,0) -> 0 | AU28: =IFERROR(AU8/$BA8,0) -> 0 | AV28: =IFERROR(AV8/$BA8,0) -> 0 | AW28: =IFERROR(AW8/$BA8,0) -> 0 | AX28: =IFERROR(AX8/$BA8,0) -> 0 | AY28: =IFERROR(AY8/$BA8,0) -> 0 | AZ28: =AZ8/$AP8 -> 0 | BA28: =BA8/$AE8 -> 0 | BC28: 2008 | BD28: =(L28*$T8+W28*$AE8+AH28*$AP8+AS28*$BA8)/$I8 -> 0.27693547 | BE28: =(M28*$T8+X28*$AE8+AI28*$AP8+AT28*$BA8)/$I8 -> 0.20992451 | BF28: =(N28*$T8+Y28*$AE8+AJ28*$AP8+AU28*$BA8)/$I8 -> 0.20332291 | BG28: =(O28*$T8+Z28*$AE8+AK28*$AP8+AV28*$BA8)/$I8 -> 0.068748223 | BH28: =(P28*$T8+AA28*$AE8+AL28*$AP8+AW28*$BA8)/$I8 -> 0.10748918 | BI28: =(Q28*$T8+AB28*$AE8+AM28*$AP8+AX28*$BA8)/$I8 -> 0.095091443 | BJ28: =((R28+S28)*$T8+(AC28+AD28)*$AE8+(AN28+AO28)*$AP8+(AZ28+AY28)*$BA8)/$I8 -> 0.038488266 | BK28: =SUM(BD28:BJ28) -> 1 | BM28: 2008 | BN28: =BN8/$BU8 -> 0.269982 | BO28: =BO8/$BU8 -> 0.22379843 | BP28: =BP8/$BU8 -> 0.19360047 | BQ28: =BQ8/$BU8 -> 0.072199873 | BR28: =BR8/$BU8 -> 0.10695003 | BS28: =BS8/$BU8 -> 0.095887148 | BT28: =BT8/$BU8 -> 0.037582045 | BU28: =SUM(BN28:BT28) -> 1 | BW28: 2008 | BX28: =IFERROR(BX8/$CE8,0) -> 0.28722488 | BY28: =IFERROR(BY8/$CE8,0) -> 0.18939453 | BZ28: =IFERROR(BZ8/$CE8,0) -> 0.21770972 | CA28: =IFERROR(CA8/$CE8,0) -> 0.063640636 | CB28: =IFERROR(CB8/$CE8,0) -> 0.10828699 | CC28: =IFERROR(CC8/$CE8,0) -> 0.093913997 | CD28: =IFERROR(CD8/$CE8,0) -> 0.039829247 | CE28: =SUM(BX28:CD28) -> 1
A29: 2009 | B29: =BE29 -> 0.21840163 | C29: =BF29 -> 0.19862273 | D29: =BG29 -> 0.069202977 | E29: =BH29 -> 0.10664546 | F29: =BI29 -> 0.09722694 | G29: =BD29 -> 0.26711546 | H29: =BJ29 -> 0.042784794 | I29: =BK29 -> 1 | K29: 2009 | L29: =L9/$T9 -> 0.25336323 | M29: =M9/$T9 -> 0.23612668 | N29: =N9/$T9 -> 0.18721973 | O29: =O9/$T9 -> 0.075917881 | P29: =P9/$T9 -> 0.1097954 | Q29: =Q9/$T9 -> 0.09683296 | R29: =R9/$T9 -> 0 | S29: =S9/$T9 -> 0.040779148 | T29: =T9/$T9 -> 1 | V29: 2009 | W29: =W9/$AE9 -> 0.28030536 | X29: =X9/$AE9 -> 0.19575725 | Y29: =Y9/$AE9 -> 0.21263618 | Z29: =Z9/$AE9 -> 0.062874022 | AA29: =AA9/$AE9 -> 0.10810189 | AB29: =AB9/$AE9 -> 0.096631886 | AC29: =AC9/$AE9 -> 0 | AD29: =AD9/$AE9 -> 0.043693417 | AE29: =AE9/$AE9 -> 1 | AG29: 2009 | AH29: =AH9/$AP9 -> 0.27193933 | AI29: =AI9/$AP9 -> 0.22673102 | AJ29: =AJ9/$AP9 -> 0.19472077 | AK29: =AK9/$AP9 -> 0.066581306 | AL29: =AL9/$AP9 -> 0.094060869 | AM29: =AM9/$AP9 -> 0.099871959 | AN29: =AN9/$AP9 -> 0 | AO29: =AO9/$AP9 -> 0.04609475 | AP29: =AP9/$AE9 -> 0.38948136 | AR29: 2009 | AS29: =IFERROR(AS9/$BA9,0) -> 0 | AT29: =IFERROR(AT9/$BA9,0) -> 0 | AU29: =IFERROR(AU9/$BA9,0) -> 0 | AV29: =IFERROR(AV9/$BA9,0) -> 0 | AW29: =IFERROR(AW9/$BA9,0) -> 0 | AX29: =IFERROR(AX9/$BA9,0) -> 0 | AY29: =IFERROR(AY9/$BA9,0) -> 0 | AZ29: =AZ9/$AP9 -> 0 | BA29: =BA9/$AE9 -> 0 | BC29: 2009 | BD29: =(L29*$T9+W29*$AE9+AH29*$AP9+AS29*$BA9)/$I9 -> 0.26711546 | BE29: =(M29*$T9+X29*$AE9+AI29*$AP9+AT29*$BA9)/$I9 -> 0.21840163 | BF29: =(N29*$T9+Y29*$AE9+AJ29*$AP9+AU29*$BA9)/$I9 -> 0.19862273 | BG29: =(O29*$T9+Z29*$AE9+AK29*$AP9+AV29*$BA9)/$I9 -> 0.069202977 | BH29: =(P29*$T9+AA29*$AE9+AL29*$AP9+AW29*$BA9)/$I9 -> 0.10664546 | BI29: =(Q29*$T9+AB29*$AE9+AM29*$AP9+AX29*$BA9)/$I9 -> 0.09722694 | BJ29: =((R29+S29)*$T9+(AC29+AD29)*$AE9+(AN29+AO29)*$AP9+(AZ29+AY29)*$BA9)/$I9 -> 0.042784794 | BK29: =SUM(BD29:BJ29) -> 1 | BM29: 2009 | BN29: =BN9/$BU9 -> 0.2582304 | BO29: =BO9/$BU9 -> 0.23365549 | BP29: =BP9/$BU9 -> 0.1891829 | BQ29: =BQ9/$BU9 -> 0.073466329 | BR29: =BR9/$BU9 -> 0.10566438 | BS29: =BS9/$BU9 -> 0.097627784 | BT29: =BT9/$BU9 -> 0.042172722 | BU29: =SUM(BN29:BT29) -> 1 | BW29: 2009 | BX29: =IFERROR(BX9/$CE9,0) -> 0.28030536 | BY29: =IFERROR(BY9/$CE9,0) -> 0.19575725 | BZ29: =IFERROR(BZ9/$CE9,0) -> 0.21263618 | CA29: =IFERROR(CA9/$CE9,0) -> 0.062874022 | CB29: =IFERROR(CB9/$CE9,0) -> 0.10810189 | CC29: =IFERROR(CC9/$CE9,0) -> 0.096631886 | CD29: =IFERROR(CD9/$CE9,0) -> 0.043693417 | CE29: =SUM(BX29:CD29) -> 1
A30: 2010 | B30: =BE30 -> 0.22020886 | C30: =BF30 -> 0.19704908 | D30: =BG30 -> 0.068587854 | E30: =BH30 -> 0.10455554 | F30: =BI30 -> 0.098278936 | G30: =BD30 -> 0.26412691 | H30: =BJ30 -> 0.04719281 | I30: =BK30 -> 1 | K30: 2010 | L30: =L10/$T10 -> 0.24963453 | M30: =M10/$T10 -> 0.24187261 | N30: =N10/$T10 -> 0.18374521 | O30: =O10/$T10 -> 0.075809259 | P30: =P10/$T10 -> 0.10452489 | Q30: =Q10/$T10 -> 0.097981204 | R30: =R10/$T10 -> 0 | S30: =S10/$T10 -> 0.046397494 | T30: =T10/$T10 -> 1 | V30: 2010 | W30: =W10/$AE10 -> 0.28857107 | X30: =X10/$AE10 -> 0.17768697 | Y30: =Y10/$AE10 -> 0.22022041 | Z30: =Z10/$AE10 -> 0.05863051 | AA30: =AA10/$AE10 -> 0.11255572 | AB30: =AB10/$AE10 -> 0.096458643 | AC30: =AC10/$AE10 -> 0 | AD30: =AD10/$AE10 -> 0.045938583 | AE30: =AE10/$AE10 -> 1 | AG30: 2010 | AH30: =AH10/$AP10 -> 0.26626339 | AI30: =AI10/$AP10 -> 0.22659659 | AJ30: =AJ10/$AP10 -> 0.19783816 | AK30: =AK10/$AP10 -> 0.063962713 | AL30: =AL10/$AP10 -> 0.091828639 | AM30: =AM10/$AP10 -> 0.10204284 | AN30: =AN10/$AP10 -> 0 | AO30: =AO10/$AP10 -> 0.051467672 | AP30: =AP10/$AE10 -> 0.62431897 | AR30: 2010 | AS30: =IFERROR(AS10/$BA10,0) -> 0 | AT30: =IFERROR(AT10/$BA10,0) -> 0 | AU30: =IFERROR(AU10/$BA10,0) -> 0 | AV30: =IFERROR(AV10/$BA10,0) -> 0 | AW30: =IFERROR(AW10/$BA10,0) -> 0 | AX30: =IFERROR(AX10/$BA10,0) -> 0 | AY30: =IFERROR(AY10/$BA10,0) -> 0 | AZ30: =AZ10/$AP10 -> 0 | BA30: =BA10/$AE10 -> 0 | BC30: 2010 | BD30: =(L30*$T10+W30*$AE10+AH30*$AP10+AS30*$BA10)/$I10 -> 0.26412691 | BE30: =(M30*$T10+X30*$AE10+AI30*$AP10+AT30*$BA10)/$I10 -> 0.22020886 | BF30: =(N30*$T10+Y30*$AE10+AJ30*$AP10+AU30*$BA10)/$I10 -> 0.19704908 | BG30: =(O30*$T10+Z30*$AE10+AK30*$AP10+AV30*$BA10)/$I10 -> 0.068587854 | BH30: =(P30*$T10+AA30*$AE10+AL30*$AP10+AW30*$BA10)/$I10 -> 0.10455554 | BI30: =(Q30*$T10+AB30*$AE10+AM30*$AP10+AX30*$BA10)/$I10 -> 0.098278936 | BJ30: =((R30+S30)*$T10+(AC30+AD30)*$AE10+(AN30+AO30)*$AP10+(AZ30+AY30)*$BA10)/$I10 -> 0.04719281 | BK30: =SUM(BD30:BJ30) -> 1 | BM30: 2010 | BN30: =BN10/$BU10 -> 0.2539613 | BO30: =BO10/$BU10 -> 0.23790998 | BP30: =BP10/$BU10 -> 0.18741143 | BQ30: =BQ10/$BU10 -> 0.072733363 | BR30: =BR10/$BU10 -> 0.10122897 | BS30: =BS10/$BU10 -> 0.099038982 | BT30: =BT10/$BU10 -> 0.047715971 | BU30: =SUM(BN30:BT30) -> 1 | BW30: 2010 | BX30: =IFERROR(BX10/$CE10,0) -> 0.28855321 | BY30: =IFERROR(BY10/$CE10,0) -> 0.17767597 | BZ30: =IFERROR(BZ10/$CE10,0) -> 0.22020677 | CA30: =IFERROR(CA10/$CE10,0) -> 0.05862688 | CB30: =IFERROR(CB10/$CE10,0) -> 0.11254875 | CC30: =IFERROR(CC10/$CE10,0) -> 0.096452671 | CD30: =IFERROR(CD10/$CE10,0) -> 0.045935739 | CE30: =SUM(BX30:CD30) -> 1
A31: 2011 | B31: =BE31 -> 0.22806898 | C31: =BF31 -> 0.19249002 | D31: =BG31 -> 0.068677258 | E31: =BH31 -> 0.09953275 | F31: =BI31 -> 0.1003823 | G31: =BD31 -> 0.25607 | H31: =BJ31 -> 0.054778693 | I31: =BK31 -> 1 | K31: 2011 | L31: =L11/$T11 -> 0.24123018 | M31: =M11/$T11 -> 0.24716826 | N31: =N11/$T11 -> 0.18051074 | O31: =O11/$T11 -> 0.075650443 | P31: =P11/$T11 -> 0.099231139 | Q31: =Q11/$T11 -> 0.10108464 | R31: =R11/$T11 -> 0 | S31: =S11/$T11 -> 0.055124597 | T31: =T11/$T11 -> 1 | V31: 2011 | W31: =W11/$AE11 -> 0.28860205 | X31: =X11/$AE11 -> 0.17845835 | Y31: =Y11/$AE11 -> 0.2170604 | Z31: =Z11/$AE11 -> 0.05735509 | AA31: =AA11/$AE11 -> 0.10734291 | AB31: =AB11/$AE11 -> 0.099975645 | AC31: =AC11/$AE11 -> 0 | AD31: =AD11/$AE11 -> 0.051205553 | AE31: =AE11/$AE11 -> 1 | AG31: 2011 | AH31: =AH11/$AP11 -> 0.26045116 | AI31: =AI11/$AP11 -> 0.22382036 | AJ31: =AJ11/$AP11 -> 0.2017798 | AK31: =AK11/$AP11 -> 0.06053394 | AL31: =AL11/$AP11 -> 0.088679636 | AM31: =AM11/$AP11 -> 0.10606374 | AN31: =AN11/$AP11 -> 0 | AO31: =AO11/$AP11 -> 0.058671358 | AP31: =AP11/$AE11 -> 0.58840721 | AR31: 2011 | AS31: =IFERROR(AS11/$BA11,0) -> 0.21635012 | AT31: =IFERROR(AT11/$BA11,0) -> 0.3104872 | AU31: =IFERROR(AU11/$BA11,0) -> 0.15276631 | AV31: =IFERROR(AV11/$BA11,0) -> 0.085604184 | AW31: =IFERROR(AW11/$BA11,0) -> 0.09551335 | AX31: =IFERROR(AX11/$BA11,0) -> 0.081475365 | AY31: =IFERROR(AY11/$BA11,0) -> 0 | AZ31: =AZ11/$BA11 -> 0.057803468 | BA31: =BA11/$AE11 -> 0.22120068 | BC31: 2011 | BD31: =(L31*$T11+W31*$AE11+AH31*$AP11+AS31*$BA11)/$I11 -> 0.25607 | BE31: =(M31*$T11+X31*$AE11+AI31*$AP11+AT31*$BA11)/$I11 -> 0.22806898 | BF31: =(N31*$T11+Y31*$AE11+AJ31*$AP11+AU31*$BA11)/$I11 -> 0.19249002 | BG31: =(O31*$T11+Z31*$AE11+AK31*$AP11+AV31*$BA11)/$I11 -> 0.068677258 | BH31: =(P31*$T11+AA31*$AE11+AL31*$AP11+AW31*$BA11)/$I11 -> 0.09953275 | BI31: =(Q31*$T11+AB31*$AE11+AM31*$AP11+AX31*$BA11)/$I11 -> 0.1003823 | BJ31: =((R31+S31)*$T11+(AC31+AD31)*$AE11+(AN31+AO31)*$AP11+(AZ31+AY31)*$BA11)/$I11 -> 0.054778693 | BK31: =SUM(BD31:BJ31) -> 1 | BM31: 2011 | BN31: =BN11/$BU11 -> 0.24347765 | BO31: =BO11/$BU11 -> 0.24727204 | BP31: =BP11/$BU11 -> 0.18297943 | BQ31: =BQ11/$BU11 -> 0.073059791 | BR31: =BR11/$BU11 -> 0.096509627 | BS31: =BS11/$BU11 -> 0.1005397 | BT31: =BT11/$BU11 -> 0.056161769 | BU31: =SUM(BN31:BT31) -> 1 | BW31: 2011 | BX31: =IFERROR(BX11/$CE11,0) -> 0.28860205 | BY31: =IFERROR(BY11/$CE11,0) -> 0.17845835 | BZ31: =IFERROR(BZ11/$CE11,0) -> 0.2170604 | CA31: =IFERROR(CA11/$CE11,0) -> 0.05735509 | CB31: =IFERROR(CB11/$CE11,0) -> 0.10734291 | CC31: =IFERROR(CC11/$CE11,0) -> 0.099975645 | CD31: =IFERROR(CD11/$CE11,0) -> 0.051205553 | CE31: =SUM(BX31:CD31) -> 1
A32: 2012 | B32: =BE32 -> 0.23063213 | C32: =BF32 -> 0.18679104 | D32: =BG32 -> 0.068060298 | E32: =BH32 -> 0.094361622 | F32: =BI32 -> 0.10588823 | G32: =BD32 -> 0.2485217 | H32: =BJ32 -> 0.065744982 | I32: =BK32 -> 1 | K32: 2012 | L32: =L12/$T12 -> 0.23149064 | M32: =M12/$T12 -> 0.25113392 | N32: =N12/$T12 -> 0.17436824 | O32: =O12/$T12 -> 0.075299253 | P32: =P12/$T12 -> 0.093544317 | Q32: =Q12/$T12 -> 0.10568496 | R32: =R12/$T12 -> 0 | S32: =S12/$T12 -> 0.068478669 | T32: =T12/$T12 -> 1 | V32: 2012 | W32: =W12/$AE12 -> 0.28483339 | X32: =X12/$AE12 -> 0.17959208 | Y32: =Y12/$AE12 -> 0.21042334 | Z32: =Z12/$AE12 -> 0.057512155 | AA32: =AA12/$AE12 -> 0.10227677 | AB32: =AB12/$AE12 -> 0.10636784 | AC32: =AC12/$AE12 -> 0 | AD32: =AD12/$AE12 -> 0.058994427 | AE32: =AE12/$AE12 -> 1 | AG32: 2012 | AH32: =AH12/$AP12 -> 0.25112108 | AI32: =AI12/$AP12 -> 0.22034244 | AJ32: =AJ12/$AP12 -> 0.20199755 | AK32: =AK12/$AP12 -> 0.057174888 | AL32: =AL12/$AP12 -> 0.085405626 | AM32: =AM12/$AP12 -> 0.11485936 | AN32: =AN12/$AP12 -> 0 | AO32: =AO12/$AP12 -> 0.069099062 | AP32: =AP12/$AE12 -> 0.58176212 | AR32: 2012 | AS32: =AS12/$BA12 -> 0.21417947 | AT32: =AT12/$BA12 -> 0.32002975 | AU32: =AU12/$BA12 -> 0.14129896 | AV32: =AV12/$BA12 -> 0.08601884 | AW32: =AW12/$BA12 -> 0.088993555 | AX32: =AX12/$BA12 -> 0.083539911 | AY32: =AY12/$BA12 -> 0 | AZ32: =AZ12/$BA12 -> 0.065939514 | BA32: =BA12/$AE12 -> 0.23917941 | BC32: 2012 | BD32: =(L32*$T12+W32*$AE12+AH32*$AP12+AS32*$BA12)/$I12 -> 0.2485217 | BE32: =(M32*$T12+X32*$AE12+AI32*$AP12+AT32*$BA12)/$I12 -> 0.23063213 | BF32: =(N32*$T12+Y32*$AE12+AJ32*$AP12+AU32*$BA12)/$I12 -> 0.18679104 | BG32: =(O32*$T12+Z32*$AE12+AK32*$AP12+AV32*$BA12)/$I12 -> 0.068060298 | BH32: =(P32*$T12+AA32*$AE12+AL32*$AP12+AW32*$BA12)/$I12 -> 0.094361622 | BI32: =(Q32*$T12+AB32*$AE12+AM32*$AP12+AX32*$BA12)/$I12 -> 0.10588823 | BJ32: =((R32+S32)*$T12+(AC32+AD32)*$AE12+(AN32+AO32)*$AP12+(AZ32+AY32)*$BA12)/$I12 -> 0.065744982 | BK32: =SUM(BD32:BJ32) -> 1 | BM32: 2012 | BN32: =BN12/$BU12 -> 0.23433482 | BO32: =BO12/$BU12 -> 0.25057333 | BP32: =BP12/$BU12 -> 0.17755797 | BQ32: =BQ12/$BU12 -> 0.072181426 | BR32: =BR12/$BU12 -> 0.091269198 | BS32: =BS12/$BU12 -> 0.10570085 | BT32: =BT12/$BU12 -> 0.068382404 | BU32: =SUM(BN32:BT32) -> 1 | BW32: 2012 | BX32: =IFERROR(BX12/$CE12,0) -> 0.28483339 | BY32: =IFERROR(BY12/$CE12,0) -> 0.17959208 | BZ32: =IFERROR(BZ12/$CE12,0) -> 0.21042334 | CA32: =IFERROR(CA12/$CE12,0) -> 0.057512155 | CB32: =IFERROR(CB12/$CE12,0) -> 0.10227677 | CC32: =IFERROR(CC12/$CE12,0) -> 0.10636784 | CD32: =IFERROR(CD12/$CE12,0) -> 0.058994427 | CE32: =SUM(BX32:CD32) -> 1
A33: 2013 | B33: =BE33 -> 0.2232312 | C33: =BF33 -> 0.20126312 | D33: =BG33 -> 0.059213109 | E33: =BH33 -> 0.085346078 | F33: =BI33 -> 0.090791158 | G33: =BD33 -> 0.27136639 | H33: =BJ33 -> 0.068788939 | I33: =BK33 -> 1 | K33: 2013 | L33: =L13/$T13 -> 0.25626536 | M33: =M13/$T13 -> 0.24268164 | N33: =N13/$T13 -> 0.19129519 | O33: =O13/$T13 -> 0.065777466 | P33: =P13/$T13 -> 0.084380484 | Q33: =Q13/$T13 -> 0.087925588 | R33: =R13/$T13 -> 0 | S33: =S13/$T13 -> 0.071674272 | T33: =T13/$T13 -> 1 | V33: 2013 | W33: =W13/$AE13 -> 0.30625151 | X33: =X13/$AE13 -> 0.17363286 | Y33: =Y13/$AE13 -> 0.22048904 | Z33: =Z13/$AE13 -> 0.04956637 | AA33: =AA13/$AE13 -> 0.092989641 | AB33: =AB13/$AE13 -> 0.094736208 | AC33: =AC13/$AE13 -> 0 | AD33: =AD13/$AE13 -> 0.062334377 | AE33: =AE13/$AE13 -> 1 | AG33: 2013 | AH33: =AH13/$AP13 -> 0.26560355 | AI33: =AI13/$AP13 -> 0.21913613 | AJ33: =AJ13/$AP13 -> 0.21639033 | AK33: =AK13/$AP13 -> 0.050691731 | AL33: =AL13/$AP13 -> 0.07825536 | AM33: =AM13/$AP13 -> 0.099799345 | AN33: =AN13/$AP13 -> 0 | AO33: =AO13/$AP13 -> 0.070123561 | AP33: =AP13/$AE13 -> 0.57028427 | AR33: 2013 | AS33: =AS13/$BA13 -> 0.24788662 | AT33: =AT13/$BA13 -> 0.29985082 | AU33: =AU13/$BA13 -> 0.15688712 | AV33: =AV13/$BA13 -> 0.072600696 | AW33: =AW13/$BA13 -> 0.077324714 | AX33: =AX13/$BA13 -> 0.073595226 | AY33: =AY13/$BA13 -> 0 | AZ33: =AZ13/$BA13 -> 0.071854799 | BA33: =BA13/$AE13 -> 0.24223079 | BC33: 2013 | BD33: =(L33*$T13+W33*$AE13+AH33*$AP13+AS33*$BA13)/$I13 -> 0.27136639 | BE33: =(M33*$T13+X33*$AE13+AI33*$AP13+AT33*$BA13)/$I13 -> 0.2232312 | BF33: =(N33*$T13+Y33*$AE13+AJ33*$AP13+AU33*$BA13)/$I13 -> 0.20126312 | BG33: =(O33*$T13+Z33*$AE13+AK33*$AP13+AV33*$BA13)/$I13 -> 0.059213109 | BH33: =(P33*$T13+AA33*$AE13+AL33*$AP13+AW33*$BA13)/$I13 -> 0.085346078 | BI33: =(Q33*$T13+AB33*$AE13+AM33*$AP13+AX33*$BA13)/$I13 -> 0.090791158 | BJ33: =((R33+S33)*$T13+(AC33+AD33)*$AE13+(AN33+AO33)*$AP13+(AZ33+AY33)*$BA13)/$I13 -> 0.068788939 | BK33: =SUM(BD33:BJ33) -> 1 | BM33: 2013 | BN33: =BN13/$BU13 -> 0.2575689 | BO33: =BO13/$BU13 -> 0.24284796 | BP33: =BP13/$BU13 -> 0.19365904 | BQ33: =BQ13/$BU13 -> 0.063028513 | BR33: =BR13/$BU13 -> 0.082322956 | BS33: =BS13/$BU13 -> 0.089230843 | BT33: =BT13/$BU13 -> 0.071341797 | BU33: =SUM(BN33:BT33) -> 1 | BW33: 2013 | BX33: =IFERROR(BX13/$CE13,0) -> 0.30625151 | BY33: =IFERROR(BY13/$CE13,0) -> 0.17363286 | BZ33: =IFERROR(BZ13/$CE13,0) -> 0.22048904 | CA33: =IFERROR(CA13/$CE13,0) -> 0.04956637 | CB33: =IFERROR(CB13/$CE13,0) -> 0.092989641 | CC33: =IFERROR(CC13/$CE13,0) -> 0.094736208 | CD33: =IFERROR(CD13/$CE13,0) -> 0.062334377 | CE33: =SUM(BX33:CD33) -> 1
A34: 2014 | B34: =BE34 -> 0.25340547 | C34: =BF34 -> 0.20564841 | D34: =BG34 -> 0.052152771 | E34: =BH34 -> 0.076932986 | F34: =BI34 -> 0.080282098 | G34: =BD34 -> 0.25945963 | H34: =BJ34 -> 0.072118636 | I34: =BK34 -> 1 | K34: 2014 | L34: =L14/$T14 -> 0.24548252 | M34: =M14/$T14 -> 0.27242373 | N34: =N14/$T14 -> 0.19821265 | O34: =O14/$T14 -> 0.057352363 | P34: =P14/$T14 -> 0.075029462 | Q34: =Q14/$T14 -> 0.077157261 | R34: =R14/$T14 -> 0 | S34: =S14/$T14 -> 0.074342019 | T34: =T14/$T14 -> 1 | V34: 2014 | W34: =W14/$AE14 -> 0.29259728 | X34: =X14/$AE14 -> 0.20124338 | Y34: =Y14/$AE14 -> 0.22254202 | Z34: =Z14/$AE14 -> 0.044612019 | AA34: =AA14/$AE14 -> 0.086058024 | AB34: =AB14/$AE14 -> 0.085712641 | AC34: =AC14/$AE14 -> 0 | AD34: =AD14/$AE14 -> 0.06723463 | AE34: =AE14/$AE14 -> 1 | AG34: 2014 | AH34: =AH14/$AP14 -> 0.24952419 | AI34: =AI14/$AP14 -> 0.25693679 | AJ34: =AJ14/$AP14 -> 0.21706902 | AK34: =AK14/$AP14 -> 0.045477311 | AL34: =AL14/$AP14 -> 0.071621757 | AM34: =AM14/$AP14 -> 0.087448663 | AN34: =AN14/$AP14 -> 0 | AO34: =AO14/$AP14 -> 0.071922268 | AP34: =AP14/$AE14 -> 0.57466037 | AR34: 2014 | AS34: =AS14/$BA14 -> 0.24768023 | AT34: =AT14/$BA14 -> 0.32238877 | AU34: =AU14/$BA14 -> 0.1627409 | AV34: =AV14/$BA14 -> 0.061384725 | AW34: =AW14/$BA14 -> 0.06566738 | AX34: =AX14/$BA14 -> 0.063526053 | AY34: =AY14/$BA14 -> 0 | AZ34: =AZ14/$BA14 -> 0.076611944 | BA34: =BA14/$AE14 -> 0.24194105 | BC34: 2014 | BD34: =(L34*$T14+W34*$AE14+AH34*$AP14+AS34*$BA14)/$I14 -> 0.25945963 | BE34: =(M34*$T14+X34*$AE14+AI34*$AP14+AT34*$BA14)/$I14 -> 0.25340547 | BF34: =(N34*$T14+Y34*$AE14+AJ34*$AP14+AU34*$BA14)/$I14 -> 0.20564841 | BG34: =(O34*$T14+Z34*$AE14+AK34*$AP14+AV34*$BA14)/$I14 -> 0.052152771 | BH34: =(P34*$T14+AA34*$AE14+AL34*$AP14+AW34*$BA14)/$I14 -> 0.076932986 | BI34: =(Q34*$T14+AB34*$AE14+AM34*$AP14+AX34*$BA14)/$I14 -> 0.080282098 | BJ34: =((R34+S34)*$T14+(AC34+AD34)*$AE14+(AN34+AO34)*$AP14+(AZ34+AY34)*$BA14)/$I14 -> 0.072118636 | BK34: =SUM(BD34:BJ34) -> 1 | BM34: 2014 | BN34: =BN14/$BU14 -> 0.24659096 | BO34: =BO14/$BU14 -> 0.27366209 | BP34: =BP14/$BU14 -> 0.19908794 | BQ34: =BQ14/$BU14 -> 0.055081146 | BR34: =BR14/$BU14 -> 0.073389368 | BS34: =BS14/$BU14 -> 0.078173202 | BT34: =BT14/$BU14 -> 0.07401529 | BU34: =SUM(BN34:BT34) -> 1 | BW34: 2014 | BX34: =IFERROR(BX14/$CE14,0) -> 0.29259728 | BY34: =IFERROR(BY14/$CE14,0) -> 0.20124338 | BZ34: =IFERROR(BZ14/$CE14,0) -> 0.22254202 | CA34: =IFERROR(CA14/$CE14,0) -> 0.044612019 | CB34: =IFERROR(CB14/$CE14,0) -> 0.086058024 | CC34: =IFERROR(CC14/$CE14,0) -> 0.085712641 | CD34: =IFERROR(CD14/$CE14,0) -> 0.06723463 | CE34: =SUM(BX34:CD34) -> 1
A35: 2015 | B35: =BE35 -> 0.25913731 | C35: =BF35 -> 0.21438144 | D35: =BG35 -> 0.046989527 | E35: =BH35 -> 0.069706646 | F35: =BI35 -> 0.072866857 | G35: =BD35 -> 0.26021278 | H35: =BJ35 -> 0.076705439 | I35: =BK35 -> 1 | K35: 2015 | L35: =L15/$T15 -> 0.24770862 | M35: =M15/$T15 -> 0.275171 | N35: =N15/$T15 -> 0.20984952 | O35: =O15/$T15 -> 0.05129959 | P35: =P15/$T15 -> 0.06744186 | Q35: =Q15/$T15 -> 0.07000684 | R35: =R15/$T15 -> 0 | S35: =S15/$T15 -> 0.078522572 | T35: =T15/$T15 -> 1 | V35: 2015 | W35: =W15/$AE15 -> 0.28943492 | X35: =X15/$AE15 -> 0.21094809 | Y35: =Y15/$AE15 -> 0.22780037 | Z35: =Z15/$AE15 -> 0.040716516 | AA35: =AA15/$AE15 -> 0.079488539 | AB35: =AB15/$AE15 -> 0.078840375 | AC35: =AC15/$AE15 -> 0 | AD35: =AD15/$AE15 -> 0.072771198 | AE35: =AE15/$AE15 -> 1 | AG35: 2015 | AH35: =AH15/$AP15 -> 0.24377593 | AI35: =AI15/$AP15 -> 0.27022822 | AJ35: =AJ15/$AP15 -> 0.22582988 | AK35: =AK15/$AP15 -> 0.041493776 | AL35: =AL15/$AP15 -> 0.065560166 | AM35: =AM15/$AP15 -> 0.078630705 | AN35: =AN15/$AP15 -> 0 | AO35: =AO15/$AP15 -> 0.074481328 | AP35: =AP15/$AE15 -> 0.56802781 | AR35: 2015 | AS35: =AS15/$BA15 -> 0.26634699 | AT35: =AT15/$BA15 -> 0.31190061 | AU35: =AU15/$BA15 -> 0.1695728 | AV35: =AV15/$BA15 -> 0.054272014 | AW35: =AW15/$BA15 -> 0.056669573 | AX35: =AX15/$BA15 -> 0.056887533 | AY35: =AY15/$BA15 -> 0 | AZ35: =AZ15/$BA15 -> 0.08435048 | BA35: =BA15/$AE15 -> 0.27034353 | BC35: 2015 | BD35: =(L35*$T15+W35*$AE15+AH35*$AP15+AS35*$BA15)/$I15 -> 0.26021278 | BE35: =(M35*$T15+X35*$AE15+AI35*$AP15+AT35*$BA15)/$I15 -> 0.25913731 | BF35: =(N35*$T15+Y35*$AE15+AJ35*$AP15+AU35*$BA15)/$I15 -> 0.21438144 | BG35: =(O35*$T15+Z35*$AE15+AK35*$AP15+AV35*$BA15)/$I15 -> 0.046989527 | BH35: =(P35*$T15+AA35*$AE15+AL35*$AP15+AW35*$BA15)/$I15 -> 0.069706646 | BI35: =(Q35*$T15+AB35*$AE15+AM35*$AP15+AX35*$BA15)/$I15 -> 0.072866857 | BJ35: =((R35+S35)*$T15+(AC35+AD35)*$AE15+(AN35+AO35)*$AP15+(AZ35+AY35)*$BA15)/$I15 -> 0.076705439 | BK35: =SUM(BD35:BJ35) -> 1 | BM35: 2015 | BN35: =BN15/$BU15 -> 0.24880372 | BO35: =BO15/$BU15 -> 0.2779516 | BP35: =BP15/$BU15 -> 0.20914236 | BQ35: =BQ15/$BU15 -> 0.049438668 | BR35: =BR15/$BU15 -> 0.065887549 | BS35: =BS15/$BU15 -> 0.070534646 | BT35: =BT15/$BU15 -> 0.078241465 | BU35: =SUM(BN35:BT35) -> 1 | BW35: 2015 | BX35: =IFERROR(BX15/$CE15,0) -> 0.28943492 | BY35: =IFERROR(BY15/$CE15,0) -> 0.21094809 | BZ35: =IFERROR(BZ15/$CE15,0) -> 0.22780037 | CA35: =IFERROR(CA15/$CE15,0) -> 0.040716516 | CB35: =IFERROR(CB15/$CE15,0) -> 0.079488539 | CC35: =IFERROR(CC15/$CE15,0) -> 0.078840375 | CD35: =IFERROR(CD15/$CE15,0) -> 0.072771198 | CE35: =SUM(BX35:CD35) -> 1
A36: 2016 | B36: =BE36 -> 0.26063985 | C36: =BF36 -> 0.22843668 | D36: =BG36 -> 0.041830087 | E36: =BH36 -> 0.061310817 | F36: =BI36 -> 0.065103238 | G36: =BD36 -> 0.26313572 | H36: =BJ36 -> 0.079543613 | I36: =BK36 -> 1 | K36: 2016 | L36: =L16/$T16 -> 0.25275518 | M36: =M16/$T16 -> 0.27299265 | N36: =N16/$T16 -> 0.22740094 | O36: =O16/$T16 -> 0.045230911 | P36: =P16/$T16 -> 0.058678824 | Q36: =Q16/$T16 -> 0.062090003 | R36: =R16/$T16 -> 0 | S36: =S16/$T16 -> 0.080851483 | T36: =T16/$T16 -> 1 | V36: 2016 | W36: =W16/$AE16 -> 0.28750945 | X36: =X16/$AE16 -> 0.21862819 | Y36: =Y16/$AE16 -> 0.23730293 | Z36: =Z16/$AE16 -> 0.036825877 | AA36: =AA16/$AE16 -> 0.071324684 | AB36: =AB16/$AE16 -> 0.071615568 | AC36: =AC16/$AE16 -> 0 | AD36: =AD16/$AE16 -> 0.076793298 | AE36: =AE16/$AE16 -> 1 | AG36: 2016 | AH36: =AH16/$AP16 -> 0.2401003 | AI36: =AI16/$AP16 -> 0.27959461 | AJ36: =AJ16/$AP16 -> 0.23801066 | AK36: =AK16/$AP16 -> 0.037509142 | AL36: =AL16/$AP16 -> 0.058510083 | AM36: =AM16/$AP16 -> 0.070421064 | AN36: =AN16/$AP16 -> 0 | AO36: =AO16/$AP16 -> 0.075854143 | AP36: =AP16/$AE16 -> 0.55680959 | AR36: 2016 | AS36: =AS16/$BA16 -> 0.2896273 | AT36: =AT16/$BA16 -> 0.29748541 | AU36: =AU16/$BA16 -> 0.18073642 | AV36: =AV16/$BA16 -> 0.04714863 | AW36: =AW16/$BA16 -> 0.046699596 | AX36: =AX16/$BA16 -> 0.049169286 | AY36: =AY16/$BA16 -> 0 | AZ36: =AZ16/$BA16 -> 0.089133363 | BA36: =BA16/$AE16 -> 0.2591192 | BC36: 2016 | BD36: =(L36*$T16+W36*$AE16+AH36*$AP16+AS36*$BA16)/$I16 -> 0.26313572 | BE36: =(M36*$T16+X36*$AE16+AI36*$AP16+AT36*$BA16)/$I16 -> 0.26063985 | BF36: =(N36*$T16+Y36*$AE16+AJ36*$AP16+AU36*$BA16)/$I16 -> 0.22843668 | BG36: =(O36*$T16+Z36*$AE16+AK36*$AP16+AV36*$BA16)/$I16 -> 0.041830087 | BH36: =(P36*$T16+AA36*$AE16+AL36*$AP16+AW36*$BA16)/$I16 -> 0.061310817 | BI36: =(Q36*$T16+AB36*$AE16+AM36*$AP16+AX36*$BA16)/$I16 -> 0.065103238 | BJ36: =((R36+S36)*$T16+(AC36+AD36)*$AE16+(AN36+AO36)*$AP16+(AZ36+AY36)*$BA16)/$I16 -> 0.079543613 | BK36: =SUM(BD36:BJ36) -> 1 | BM36: 2016 | BN36: =BN16/$BU16 -> 0.25372363 | BO36: =BO16/$BU16 -> 0.27686294 | BP36: =BP16/$BU16 -> 0.22501292 | BQ36: =BQ16/$BU16 -> 0.043762496 | BR36: =BR16/$BU16 -> 0.057443893 | BS36: =BS16/$BU16 -> 0.062588457 | BT36: =BT16/$BU16 -> 0.080605666 | BU36: =SUM(BN36:BT36) -> 1 | BW36: 2016 | BX36: =IFERROR(BX16/$CE16,0) -> 0.28750945 | BY36: =IFERROR(BY16/$CE16,0) -> 0.21862819 | BZ36: =IFERROR(BZ16/$CE16,0) -> 0.23730293 | CA36: =IFERROR(CA16/$CE16,0) -> 0.036825877 | CB36: =IFERROR(CB16/$CE16,0) -> 0.071324684 | CC36: =IFERROR(CC16/$CE16,0) -> 0.071615568 | CD36: =IFERROR(CD16/$CE16,0) -> 0.076793298 | CE36: =SUM(BX36:CD36) -> 1
A37: 2017 | B37: =BE37 -> 0.2633572 | C37: =BF37 -> 0.23772593 | D37: =BG37 -> 0.037801994 | E37: =BH37 -> 0.053147686 | F37: =BI37 -> 0.057794388 | G37: =BD37 -> 0.26833463 | H37: =BJ37 -> 0.081838176 | I37: =BK37 -> 1 | K37: 2017 | L37: =L17/$T17 -> 0.26094293 | M37: =M17/$T17 -> 0.27136476 | N37: =N17/$T17 -> 0.23956989 | O37: =O17/$T17 -> 0.040363937 | P37: =P17/$T17 -> 0.050355666 | Q37: =Q17/$T17 -> 0.054656741 | R37: =R17/$T17 -> 0.04846981 | S37: =S17/$T17 -> 0.034276261 | T37: =T17/$T17 -> 1 | V37: 2017 | W37: =W17/$AE17 -> 0.28637372 | X37: =X17/$AE17 -> 0.22906301 | Y37: =Y17/$AE17 -> 0.24225166 | Z37: =Z17/$AE17 -> 0.034170613 | AA37: =AA17/$AE17 -> 0.063125712 | AB37: =AB17/$AE17 -> 0.06474432 | AC37: =AC17/$AE17 -> 0.047359271 | AD37: =AD17/$AE17 -> 0.032911696 | AE37: =AE17/$AE17 -> 1 | AG37: 2017 | AH37: =AH17/$AP17 -> 0.2358643 | AI37: =AI17/$AP17 -> 0.2911147 | AJ37: =AJ17/$AP17 -> 0.24835757 | AK37: =AK17/$AP17 -> 0.034248788 | AL37: =AL17/$AP17 -> 0.051373183 | AM37: =AM17/$AP17 -> 0.062681745 | AN37: =AN17/$AP17 -> 0.051157781 | AO37: =AO17/$AP17 -> 0.025201939 | AP37: =AP17/$AE17 -> 0.55662131 | AR37: 2017 | AS37: =AS17/$BA17 -> 0.32064456 | AT37: =AT17/$BA17 -> 0.28024288 | AU37: =AU17/$BA17 -> 0.18402616 | AV37: =AV17/$BA17 -> 0.04156936 | AW37: =AW17/$BA17 -> 0.037832788 | AX37: =AX17/$BA17 -> 0.042269967 | AY37: =AY17/$BA17 -> 0.033629145 | AZ37: =AZ17/$BA17 -> 0.059785147 | BA37: =BA17/$AE17 -> 0.25669924 | BC37: 2017 | BD37: =(L37*$T17+W37*$AE17+AH37*$AP17+AS37*$BA17)/$I17 -> 0.26833463 | BE37: =(M37*$T17+X37*$AE17+AI37*$AP17+AT37*$BA17)/$I17 -> 0.2633572 | BF37: =(N37*$T17+Y37*$AE17+AJ37*$AP17+AU37*$BA17)/$I17 -> 0.23772593 | BG37: =(O37*$T17+Z37*$AE17+AK37*$AP17+AV37*$BA17)/$I17 -> 0.037801994 | BH37: =(P37*$T17+AA37*$AE17+AL37*$AP17+AW37*$BA17)/$I17 -> 0.053147686 | BI37: =(Q37*$T17+AB37*$AE17+AM37*$AP17+AX37*$BA17)/$I17 -> 0.057794388 | BJ37: =((R37+S37)*$T17+(AC37+AD37)*$AE17+(AN37+AO37)*$AP17+(AZ37+AY37)*$BA17)/$I17 -> 0.081838176 | BK37: =SUM(BD37:BJ37) -> 1 | BM37: 2017 | BN37: =BN17/$BU17 -> 0.26146328 | BO37: =BO17/$BU17 -> 0.27642035 | BP37: =BP17/$BU17 -> 0.23600201 | BQ37: =BQ17/$BU17 -> 0.039185239 | BR37: =BR17/$BU17 -> 0.049346913 | BS37: =BS17/$BU17 -> 0.055147059 | BT37: =BT17/$BU17 -> 0.082435148 | BU37: =SUM(BN37:BT37) -> 1 | BW37: 2017 | BX37: =IFERROR(BX17/$CE17,0) -> 0.28637372 | BY37: =IFERROR(BY17/$CE17,0) -> 0.22906301 | BZ37: =IFERROR(BZ17/$CE17,0) -> 0.24225166 | CA37: =IFERROR(CA17/$CE17,0) -> 0.034170613 | CB37: =IFERROR(CB17/$CE17,0) -> 0.063125712 | CC37: =IFERROR(CC17/$CE17,0) -> 0.06474432 | CD37: =IFERROR(CD17/$CE17,0) -> 0.080270967 | CE37: =SUM(BX37:CD37) -> 1
A38: 2018 | B38: =BE38 -> 0.2561041 | C38: =BF38 -> 0.2386731 | D38: =BG38 -> 0.037136313 | E38: =BH38 -> 0.052163036 | F38: =BI38 -> 0.056679175 | G38: =BD38 -> 0.27874978 | H38: =BJ38 -> 0.080494501 | I38: =BK38 -> 1 | K38: 2018 | L38: =L18/$T18 -> 0.27167439 | M38: =M18/$T18 -> 0.26472535 | N38: =N18/$T18 -> 0.2386499 | O38: =O18/$T18 -> 0.039774983 | P38: =P18/$T18 -> 0.049702184 | Q38: =Q18/$T18 -> 0.053871608 | R38: =R18/$T18 -> 0.047816016 | S38: =S18/$T18 -> 0.033785572 | T38: =T18/$T18 -> 1 | V38: 2018 | W38: =W18/$AE18 -> 0.2930605 | X38: =X18/$AE18 -> 0.22342823 | Y38: =Y18/$AE18 -> 0.24460261 | Z38: =Z18/$AE18 -> 0.033689205 | AA38: =AA18/$AE18 -> 0.06227758 | AB38: =AB18/$AE18 -> 0.063819692 | AC38: =AC18/$AE18 -> 0.046678529 | AD38: =AD18/$AE18 -> 0.032443654 | AE38: =AE18/$AE18 -> 1 | AG38: 2018 | AH38: =AH18/$AP18 -> 0.23969998 | AI38: =AI18/$AP18 -> 0.28290725 | AJ38: =AJ18/$AP18 -> 0.25681386 | AK38: =AK18/$AP18 -> 0.033593915 | AL38: =AL18/$AP18 -> 0.050496514 | AM38: =AM18/$AP18 -> 0.061588844 | AN38: =AN18/$AP18 -> 0.05017959 | AO38: =AO18/$AP18 -> 0.024720051 | AP38: =AP18/$AE18 -> 0.56144721 | AR38: 2018 | AS38: =AS18/$BA18 -> 0.34703652 | AT38: =AT18/$BA18 -> 0.26342047 | AU38: =AU18/$BA18 -> 0.18459389 | AV38: =AV18/$BA18 -> 0.039513071 | AW38: =AW18/$BA18 -> 0.036120535 | AX38: =AX18/$BA18 -> 0.040311315 | AY38: =AY18/$BA18 -> 0.032129316 | AZ38: =AZ18/$BA18 -> 0.056874875 | BA38: =BA18/$AE18 -> 0.29721234 | BC38: 2018 | BD38: =(L38*$T18+W38*$AE18+AH38*$AP18+AS38*$BA18)/$I18 -> 0.27874978 | BE38: =(M38*$T18+X38*$AE18+AI38*$AP18+AT38*$BA18)/$I18 -> 0.2561041 | BF38: =(N38*$T18+Y38*$AE18+AJ38*$AP18+AU38*$BA18)/$I18 -> 0.2386731 | BG38: =(O38*$T18+Z38*$AE18+AK38*$AP18+AV38*$BA18)/$I18 -> 0.037136313 | BH38: =(P38*$T18+AA38*$AE18+AL38*$AP18+AW38*$BA18)/$I18 -> 0.052163036 | BI38: =(Q38*$T18+AB38*$AE18+AM38*$AP18+AX38*$BA18)/$I18 -> 0.056679175 | BJ38: =((R38+S38)*$T18+(AC38+AD38)*$AE18+(AN38+AO38)*$AP18+(AZ38+AY38)*$BA18)/$I18 -> 0.080494501 | BK38: =SUM(BD38:BJ38) -> 1 | BM38: 2018 | BN38: =BN18/$BU18 -> 0.27335168 | BO38: =BO18/$BU18 -> 0.26842965 | BP38: =BP18/$BU18 -> 0.23643645 | BQ38: =BQ18/$BU18 -> 0.038436584 | BR38: =BR18/$BU18 -> 0.048347764 | BS38: =BS18/$BU18 -> 0.053985726 | BT38: =BT18/$BU18 -> 0.081012148 | BU38: =SUM(BN38:BT38) -> 1 | BW38: 2018 | BX38: =IFERROR(BX18/$CE18,0) -> 0.2930605 | BY38: =IFERROR(BY18/$CE18,0) -> 0.22342823 | BZ38: =IFERROR(BZ18/$CE18,0) -> 0.24460261 | CA38: =IFERROR(CA18/$CE18,0) -> 0.033689205 | CB38: =IFERROR(CB18/$CE18,0) -> 0.06227758 | CC38: =IFERROR(CC18/$CE18,0) -> 0.063819692 | CD38: =IFERROR(CD18/$CE18,0) -> 0.079122183 | CE38: =SUM(BX38:CD38) -> 1
A39: 2019 | B39: =BE39 -> 0.26405664 | C39: =BF39 -> 0.23183822 | D39: =BG39 -> 0.038576883 | E39: =BH39 -> 0.054882745 | F39: =BI39 -> 0.058897757 | G39: =BD39 -> 0.26818636 | H39: =BJ39 -> 0.083561397 | I39: =BK39 -> 1 | K39: 2019 | L39: =L19/$T19 -> 0.26070065 | M39: =M19/$T19 -> 0.27238917 | N39: =N19/$T19 -> 0.23367093 | O39: =O19/$T19 -> 0.041142288 | P39: =P19/$T19 -> 0.05203387 | Q39: =Q19/$T19 -> 0.055719741 | R39: =R19/$T19 -> 0.049377387 | S39: =S19/$T19 -> 0.034965964 | T39: =T19/$T19 -> 1 | V39: 2019 | W39: =W19/$AE19 -> 0.28547479 | X39: =X19/$AE19 -> 0.22865525 | Y39: =Y19/$AE19 -> 0.23715723 | Z39: =Z19/$AE19 -> 0.034965872 | AA39: =AA19/$AE19 -> 0.065441265 | AB39: =AB19/$AE19 -> 0.066219614 | AC39: =AC19/$AE19 -> 0.04837744 | AD39: =AD19/$AE19 -> 0.033708538 | AE39: =AE19/$AE19 -> 1 | AG39: 2019 | AH39: =AH19/$AP19 -> 0.23463039 | AI39: =AI19/$AP19 -> 0.29294527 | AJ39: =AJ19/$AP19 -> 0.24264473 | AK39: =AK19/$AP19 -> 0.034904566 | AL39: =AL19/$AP19 -> 0.053147738 | AM39: =AM19/$AP19 -> 0.063903828 | AN39: =AN19/$AP19 -> 0.052093219 | AO39: =AO19/$AP19 -> 0.025730254 | AP39: =AP19/$AE19 -> 0.56777631 | AR39: 2019 | AS39: =AS19/$BA19 -> 0.3221775 | AT39: =AT19/$BA19 -> 0.27811904 | AU39: =AU19/$BA19 -> 0.17962296 | AV39: =AV19/$BA19 -> 0.042363906 | AW39: =AW19/$BA19 -> 0.039186613 | AX39: =AX19/$BA19 -> 0.043211184 | AY39: =AY19/$BA19 -> 0.034314764 | AZ39: =AZ19/$BA19 -> 0.061004025 | BA39: =BA19/$AE19 -> 0.28266076 | BC39: 2019 | BD39: =(L39*$T19+W39*$AE19+AH39*$AP19+AS39*$BA19)/$I19 -> 0.26818636 | BE39: =(M39*$T19+X39*$AE19+AI39*$AP19+AT39*$BA19)/$I19 -> 0.26405664 | BF39: =(N39*$T19+Y39*$AE19+AJ39*$AP19+AU39*$BA19)/$I19 -> 0.23183822 | BG39: =(O39*$T19+Z39*$AE19+AK39*$AP19+AV39*$BA19)/$I19 -> 0.038576883 | BH39: =(P39*$T19+AA39*$AE19+AL39*$AP19+AW39*$BA19)/$I19 -> 0.054882745 | BI39: =(Q39*$T19+AB39*$AE19+AM39*$AP19+AX39*$BA19)/$I19 -> 0.058897757 | BJ39: =((R39+S39)*$T19+(AC39+AD39)*$AE19+(AN39+AO39)*$AP19+(AZ39+AY39)*$BA19)/$I19 -> 0.083561397 | BK39: =SUM(BD39:BJ39) -> 1 | BM39: 2019 | BN39: =BN19/$BU19 -> 0.26167107 | BO39: =BO19/$BU19 -> 0.27739796 | BP39: =BP19/$BU19 -> 0.22983371 | BQ39: =BQ19/$BU19 -> 0.039937724 | BR39: =BR19/$BU19 -> 0.050903676 | BS39: =BS19/$BU19 -> 0.056138451 | BT39: =BT19/$BU19 -> 0.084117421 | BU39: =SUM(BN39:BT39) -> 1 | BW39: 2019 | BX39: =IFERROR(BX19/$CE19,0) -> 0.28547479 | BY39: =IFERROR(BY19/$CE19,0) -> 0.22865525 | BZ39: =IFERROR(BZ19/$CE19,0) -> 0.23715723 | CA39: =IFERROR(CA19/$CE19,0) -> 0.034965872 | CB39: =IFERROR(CB19/$CE19,0) -> 0.065441265 | CC39: =IFERROR(CC19/$CE19,0) -> 0.066219614 | CD39: =IFERROR(CD19/$CE19,0) -> 0.082085978 | CE39: =SUM(BX39:CD39) -> 1
A40: 2020 | B40: =BE40 -> 0.27309824 | C40: =BF40 -> 0.23262362 | D40: =BG40 -> 0.037658857 | E40: =BH40 -> 0.053454195 | F40: =BI40 -> 0.057504668 | G40: =BD40 -> 0.26403361 | H40: =BJ40 -> 0.081626814 | I40: =BK40 -> 1 | K40: 2020 | L40: =L20/$T20 -> 0.25618627 | M40: =M20/$T20 -> 0.28144879 | N40: =N20/$T20 -> 0.23466748 | O40: =O20/$T20 -> 0.040176533 | P40: =P20/$T20 -> 0.050707655 | Q40: =Q20/$T20 -> 0.05442094 | R40: =R20/$T20 -> 0.048272713 | S40: =S20/$T20 -> 0.034119616 | T40: =T20/$T20 -> 1 | V40: 2020 | W40: =W20/$AE20 -> 0.28319903 | X40: =X20/$AE20 -> 0.23622916 | Y40: =Y20/$AE20 -> 0.23832653 | Z40: =Z20/$AE20 -> 0.034054531 | AA40: =AA20/$AE20 -> 0.063638371 | AB40: =AB20/$AE20 -> 0.06452147 | AC40: =AC20/$AE20 -> 0.047190639 | AD40: =AD20/$AE20 -> 0.032840269 | AE40: =AE20/$AE20 -> 1 | AG40: 2020 | AH40: =AH20/$AP20 -> 0.23230962 | AI40: =AI20/$AP20 -> 0.30143449 | AJ40: =AJ20/$AP20 -> 0.24299605 | AK40: =AK20/$AP20 -> 0.033888514 | AL40: =AL20/$AP20 -> 0.051506691 | AM40: =AM20/$AP20 -> 0.062193126 | AN40: =AN20/$AP20 -> 0.050640223 | AO40: =AO20/$AP20 -> 0.025031289 | AP40: =AP20/$AE20 -> 0.57329727 | AR40: 2020 | AS40: =AS20/$BA20 -> 0.31155978 | AT40: =AT20/$BA20 -> 0.29275534 | AU40: =AU20/$BA20 -> 0.17755344 | AV40: =AV20/$BA20 -> 0.041963579 | AW40: =AW20/$BA20 -> 0.038796516 | AX40: =AX20/$BA20 -> 0.042755344 | AY40: =AY20/$BA20 -> 0.034045922 | AZ40: =AZ20/$BA20 -> 0.060570071 | BA40: =BA20/$AE20 -> 0.27883872 | BC40: 2020 | BD40: =(L40*$T20+W40*$AE20+AH40*$AP20+AS40*$BA20)/$I20 -> 0.26403361 | BE40: =(M40*$T20+X40*$AE20+AI40*$AP20+AT40*$BA20)/$I20 -> 0.27309824 | BF40: =(N40*$T20+Y40*$AE20+AJ40*$AP20+AU40*$BA20)/$I20 -> 0.23262362 | BG40: =(O40*$T20+Z40*$AE20+AK40*$AP20+AV40*$BA20)/$I20 -> 0.037658857 | BH40: =(P40*$T20+AA40*$AE20+AL40*$AP20+AW40*$BA20)/$I20 -> 0.053454195 | BI40: =(Q40*$T20+AB40*$AE20+AM40*$AP20+AX40*$BA20)/$I20 -> 0.057504668 | BJ40: =((R40+S40)*$T20+(AC40+AD40)*$AE20+(AN40+AO40)*$AP20+(AZ40+AY40)*$BA20)/$I20 -> 0.081626814 | BK40: =SUM(BD40:BJ40) -> 1 | BM40: 2020 | BN40: =BN20/$BU20 -> 0.2568435 | BO40: =BO20/$BU20 -> 0.28693005 | BP40: =BP20/$BU20 -> 0.23048412 | BQ40: =BQ20/$BU20 -> 0.039011057 | BR40: =BR20/$BU20 -> 0.049633495 | BS40: =BS20/$BU20 -> 0.054872241 | BT40: =BT20/$BU20 -> 0.082225535 | BU40: =SUM(BN40:BT40) -> 1 | BW40: 2020 | BX40: =IFERROR(BX20/$CE20,0) -> 0.28319903 | BY40: =IFERROR(BY20/$CE20,0) -> 0.23622916 | BZ40: =IFERROR(BZ20/$CE20,0) -> 0.23832653 | CA40: =IFERROR(CA20/$CE20,0) -> 0.034054531 | CB40: =IFERROR(CB20/$CE20,0) -> 0.063638371 | CC40: =IFERROR(CC20/$CE20,0) -> 0.06452147 | CD40: =IFERROR(CD20/$CE20,0) -> 0.080030908 | CE40: =SUM(BX40:CD40) -> 1
A41: 2021 | B41: =BE41 -> 0.28021822 | C41: =BF41 -> 0.2259191 | D41: =BG41 -> 0.03785801 | E41: =BH41 -> 0.053999371 | F41: =BI41 -> 0.057776179 | G41: =BD41 -> 0.26217346 | H41: =BJ41 -> 0.082055663 | I41: =BK41 -> 1 | K41: 2021 | L41: =L21/$T21 -> 0.25431195 | M41: =M21/$T21 -> 0.28877652 | N41: =N21/$T21 -> 0.22797493 | O41: =O21/$T21 -> 0.040358605 | P41: =P21/$T21 -> 0.051216032 | Q41: =Q21/$T21 -> 0.054659387 | R41: =R21/$T21 -> 0.048424122 | S41: =S21/$T21 -> 0.034278446 | T41: =T21/$T21 -> 1 | V41: 2021 | W41: =W21/$AE21 -> 0.27983607 | X41: =X21/$AE21 -> 0.24295082 | Y41: =Y21/$AE21 -> 0.23218579 | Z41: =Z21/$AE21 -> 0.03442623 | AA41: =AA21/$AE21 -> 0.064644809 | AB41: =AB21/$AE21 -> 0.065191257 | AC41: =AC21/$AE21 -> 0.047595628 | AD41: =AD21/$AE21 -> 0.033169399 | AE41: =AE21/$AE21 -> 1 | AG41: 2021 | AH41: =AH21/$AP21 -> 0.22886792 | AI41: =AI21/$AP21 -> 0.31018868 | AJ41: =AJ21/$AP21 -> 0.2359434 | AK41: =AK21/$AP21 -> 0.034150943 | AL41: =AL21/$AP21 -> 0.052169811 | AM41: =AM21/$AP21 -> 0.06254717 | AN41: =AN21/$AP21 -> 0.050943396 | AO41: =AO21/$AP21 -> 0.025188679 | AP41: =AP21/$AE21 -> 0.57923497 | AR41: 2021 | AS41: =AS21/$BA21 -> 0.31286916 | AT41: =AT21/$BA21 -> 0.29604439 | AU41: =AU21/$BA21 -> 0.17451226 | AV41: =AV21/$BA21 -> 0.041703956 | AW41: =AW21/$BA21 -> 0.038661178 | AX41: =AX21/$BA21 -> 0.042419903 | AY41: =AY21/$BA21 -> 0.033828531 | AZ41: =AZ21/$BA21 -> 0.059960623 | BA41: =BA21/$AE21 -> 0.30530055 | BC41: 2021 | BD41: =(L41*$T21+W41*$AE21+AH41*$AP21+AS41*$BA21)/$I21 -> 0.26217346 | BE41: =(M41*$T21+X41*$AE21+AI41*$AP21+AT41*$BA21)/$I21 -> 0.28021822 | BF41: =(N41*$T21+Y41*$AE21+AJ41*$AP21+AU41*$BA21)/$I21 -> 0.2259191 | BG41: =(O41*$T21+Z41*$AE21+AK41*$AP21+AV41*$BA21)/$I21 -> 0.03785801 | BH41: =(P41*$T21+AA41*$AE21+AL41*$AP21+AW41*$BA21)/$I21 -> 0.053999371 | BI41: =(Q41*$T21+AB41*$AE21+AM41*$AP21+AX41*$BA21)/$I21 -> 0.057776179 | BJ41: =((R41+S41)*$T21+(AC41+AD41)*$AE21+(AN41+AO41)*$AP21+(AZ41+AY41)*$BA21)/$I21 -> 0.082055663 | BK41: =SUM(BD41:BJ41) -> 1 | BM41: 2021 | BN41: =BN21/$BU21 -> 0.25549842 | BO41: =BO21/$BU21 -> 0.29430229 | BP41: =BP21/$BU21 -> 0.22355079 | BQ41: =BQ21/$BU21 -> 0.039154947 | BR41: =BR21/$BU21 -> 0.049976251 | BS41: =BS21/$BU21 -> 0.054973876 | BT41: =BT21/$BU21 -> 0.082543419 | BU41: =SUM(BN41:BT41) -> 1 | BW41: 2021 | BX41: =IFERROR(BX21/$CE21,0) -> 0.27983607 | BY41: =IFERROR(BY21/$CE21,0) -> 0.24295082 | BZ41: =IFERROR(BZ21/$CE21,0) -> 0.23218579 | CA41: =IFERROR(CA21/$CE21,0) -> 0.03442623 | CB41: =IFERROR(CB21/$CE21,0) -> 0.064644809 | CC41: =IFERROR(CC21/$CE21,0) -> 0.065191257 | CD41: =IFERROR(CD21/$CE21,0) -> 0.080765027 | CE41: =SUM(BX41:CD41) -> 1
A43: Electricity
A44: 所有住宅All Residential | K44: 私人住宅Private Housing Segment | V44: 公共住宅 Public Housing | AG44: 房委会资助出售单位组别 Housing Authority Subsidized Sale Flats Segment | AR44: Total ElecConsumption in Other Housing Segment by End-use | BC44: 重新加总Private+Public | BM44: Private = Urban defination in the EPS | BW44: Public = Rural defination in the EPS
A45: 年份 Year | B45: 空氣調節 Air Conditioning | C45: 熱水 Hot Water | D45: 照明 Lighting | E45: 冷凍 Refrigeration | F45: 辦公室設備 Office Equipment | G45: 煮食 Cooking | H45: 其他 1 Others 1 | I45: 總計 Total | K45: 年份 Year | L45: 煮食 Cooking | M45: 空氣調節 Air Conditioning | N45: 熱水 Hot Water | O45: 照明 Lighting | P45: 冷凍 Refrigeration | Q45: 辦公室設備 Office Equipment | R45: Laundry (Unit : Terajoule) | S45: 其他 1 Others 1 | T45: 總計 Total | V45: 年份 Year | W45: 煮食 Cooking | X45: 空氣調節 Air Conditioning | Y45: 熱水 Hot Water | Z45: 照明 Lighting | AA45: 冷凍 Refrigeration | AB45: 辦公室設備 Office Equipment | AC45: Laundry (Unit : Terajoule) | AD45: 其他 1 Others 1 | AE45: 總計 Total | AG45: 年份 Year | AH45: 煮食 Cooking | AI45: 空氣調節 Air Conditioning | AJ45: 熱水 Hot Water | AK45: 照明 Lighting | AL45: 冷凍 Refrigeration | AM45: 辦公室設備 Office Equipment | AN45: Laundry (Unit : Terajoule) | AO45: 其他 1 Others 1 | AP45: 總計 Total | AR45: Year | AS45: Cooking (Unit : Terajoule) | AT45: Air Conditioning (Unit : Terajoule) | AU45: Hot Water (Unit : Terajoule) | AV45: Lighting (Unit : Terajoule) | AW45: Refrigeration (Unit : Terajoule) | AX45: Office Equipment (Unit : Terajoule) | AY45: Laundry (Unit : Terajoule) | AZ45: Others (Unit : Terajoule) | BA45: 總計 Total | BC45: 年份 Year | BD45: 煮食 Cooking | BE45: 空氣調節 Air Conditioning | BF45: 熱水 Hot Water | BG45: 照明 Lighting | BH45: 冷凍 Refrigeration | BI45: 辦公室設備 Office Equipment | BJ45: 其他 1 Others 1 | BK45: 總計 Total | BM45: 年份 Year | BN45: 煮食 Cooking | BO45: 空氣調節 Air Conditioning | BP45: 熱水 Hot Water | BQ45: 照明 Lighting | BR45: 冷凍 Refrigeration | BS45: 辦公室設備 Office Equipment | BT45: 其他 1 Others 1 | BU45: 總計 Total | BW45: 年份 Year | BX45: 煮食 Cooking | BY45: 空氣調節 Air Conditioning | BZ45: 熱水 Hot Water | CA45: 照明 Lighting | CB45: 冷凍 Refrigeration | CC45: 辦公室設備 Office Equipment | CD45: 其他 1 Others 1 | CE45: 總計 Total
A46: 2006 | B46: =BE46 -> 13285 | C46: =BF46 -> 3535 | D46: =BG46 -> 4633 | E46: =BH46 -> 6372 | F46: =BI46 -> 5366 | G46: =BD46 -> 3579 | H46: =BJ46 -> 2157 | I46: =BK46 -> 38927 | K46: 2006 | L46: 1592 | M46: 6122 | N46: 2123 | O46: 2148 | P46: 2830 | Q46: 2311 | S46: 890 | T46: =SUM(L46:S46) -> 18016 | V46: 2006 | W46: =G159+AH46 -> 1400 | X46: =B159+AI46 -> 5006 | Y46: =C159+AJ46 -> 1241 | Z46: =D159+AK46 -> 1760 | AA46: =E159+AL46 -> 2656 | AB46: =F159+AM46 -> 2211 | AD46: =H159+AO46 -> 903 | AE46: =SUM(W46:AD46) -> 15177 | AG46: 2006 | AH46: 587 | AI46: 2157 | AJ46: 171 | AK46: 725 | AL46: 886 | AM46: 844 | AO46: 364 | AP46: =SUM(AH46:AO46) -> 5734 | AR46: 2006 | BA46: 0 | BC46: 2006 | BD46: =L46+W46+AH46+AS46 -> 3579 | BE46: =M46+X46+AI46+AT46 -> 13285 | BF46: =N46+Y46+AJ46+AU46 -> 3535 | BG46: =O46+Z46+AK46+AV46 -> 4633 | BH46: =P46+AA46+AL46+AW46 -> 6372 | BI46: =Q46+AB46+AM46+AX46 -> 5366 | BJ46: =R46+AC46+AN46+AY46+S46+AD46+AO46+AZ46 -> 2157 | BK46: =SUM(BD46:BJ46) -> 38927 | BM46: 2006 | BN46: =L46+AH46+AS46 -> 2179 | BO46: =M46+AI46+AT46 -> 8279 | BP46: =N46+AJ46+AU46 -> 2294 | BQ46: =O46+AK46+AV46 -> 2873 | BR46: =P46+AL46+AW46 -> 3716 | BS46: =Q46+AM46+AX46 -> 3155 | BT46: =R46+AY46+AN46+S46+AZ46+AO46 -> 1254 | BU46: =SUM(BN46:BT46) -> 23750 | BW46: 2006 | BX46: =W46 -> 1400 | BY46: =X46 -> 5006 | BZ46: =Y46 -> 1241 | CA46: =Z46 -> 1760 | CB46: =AA46 -> 2656 | CC46: =AB46 -> 2211 | CD46: =AC46+AD46 -> 903 | CE46: =SUM(BX46:CD46) -> 15177
A47: 2007 | B47: =BE47 -> 13329 | C47: =BF47 -> 3888 | D47: =BG47 -> 4509 | E47: =BH47 -> 6618 | F47: =BI47 -> 5701 | G47: =BD47 -> 3866 | H47: =BJ47 -> 2262 | I47: =BK47 -> 40173 | K47: 2007 | L47: 1698 | M47: 6176 | N47: 2271 | O47: 2100 | P47: 2962 | Q47: 2469 | S47: 939 | T47: =SUM(L47:S47) -> 18615 | V47: 2007 | W47: =G160+AH47 -> 1509 | X47: =B160+AI47 -> 4963 | Y47: =C160+AJ47 -> 1399 | Z47: =D160+AK47 -> 1709 | AA47: =E160+AL47 -> 2741 | AB47: =F160+AM47 -> 2323 | AD47: =H160+AO47 -> 943 | AE47: =SUM(W47:AD47) -> 15587 | AG47: 2007 | AH47: 659 | AI47: 2190 | AJ47: 218 | AK47: 700 | AL47: 915 | AM47: 909 | AO47: 380 | AP47: =SUM(AH47:AO47) -> 5971 | AR47: 2007 | BA47: 0 | BC47: 2007 | BD47: =L47+W47+AH47+AS47 -> 3866 | BE47: =M47+X47+AI47+AT47 -> 13329 | BF47: =N47+Y47+AJ47+AU47 -> 3888 | BG47: =O47+Z47+AK47+AV47 -> 4509 | BH47: =P47+AA47+AL47+AW47 -> 6618 | BI47: =Q47+AB47+AM47+AX47 -> 5701 | BJ47: =R47+AC47+AN47+AY47+S47+AD47+AO47+AZ47 -> 2262 | BK47: =SUM(BD47:BJ47) -> 40173 | BM47: 2007 | BN47: =L47+AH47+AS47 -> 2357 | BO47: =M47+AI47+AT47 -> 8366 | BP47: =N47+AJ47+AU47 -> 2489 | BQ47: =O47+AK47+AV47 -> 2800 | BR47: =P47+AL47+AW47 -> 3877 | BS47: =Q47+AM47+AX47 -> 3378 | BT47: =R47+AY47+AN47+S47+AZ47+AO47 -> 1319 | BU47: =SUM(BN47:BT47) -> 24586 | BW47: 2007 | BX47: =W47 -> 1509 | BY47: =X47 -> 4963 | BZ47: =Y47 -> 1399 | CA47: =Z47 -> 1709 | CB47: =AA47 -> 2741 | CC47: =AB47 -> 2323 | CD47: =AC47+AD47 -> 943 | CE47: =SUM(BX47:CD47) -> 15587
A48: 2008 | B48: =BE48 -> 13292 | C48: =BF48 -> 4249 | D48: =BG48 -> 4353 | E48: =BH48 -> 6806 | F48: =BI48 -> 6021 | G48: =BD48 -> 4162 | H48: =BJ48 -> 2352 | I48: =BK48 -> 41235 | K48: 2008 | L48: 1812 | M48: 6240 | N48: 2431 | O48: 2055 | P48: 3101 | Q48: 2646 | S48: 992 | T48: =SUM(L48:S48) -> 19277 | V48: 2008 | W48: =G161+AH48 -> 1606 | X48: =B161+AI48 -> 4836 | Y48: =C161+AJ48 -> 1541 | Z48: =D161+AK48 -> 1625 | AA48: =E161+AL48 -> 2765 | AB48: =F161+AM48 -> 2398 | AD48: =H161+AO48 -> 965 | AE48: =SUM(W48:AD48) -> 15736 | AG48: 2008 | AH48: 744 | AI48: 2216 | AJ48: 277 | AK48: 673 | AL48: 940 | AM48: 977 | AO48: 395 | AP48: =SUM(AH48:AO48) -> 6222 | AR48: 2008 | BA48: 0 | BC48: 2008 | BD48: =L48+W48+AH48+AS48 -> 4162 | BE48: =M48+X48+AI48+AT48 -> 13292 | BF48: =N48+Y48+AJ48+AU48 -> 4249 | BG48: =O48+Z48+AK48+AV48 -> 4353 | BH48: =P48+AA48+AL48+AW48 -> 6806 | BI48: =Q48+AB48+AM48+AX48 -> 6021 | BJ48: =R48+AC48+AN48+AY48+S48+AD48+AO48+AZ48 -> 2352 | BK48: =SUM(BD48:BJ48) -> 41235 | BM48: 2008 | BN48: =L48+AH48+AS48 -> 2556 | BO48: =M48+AI48+AT48 -> 8456 | BP48: =N48+AJ48+AU48 -> 2708 | BQ48: =O48+AK48+AV48 -> 2728 | BR48: =P48+AL48+AW48 -> 4041 | BS48: =Q48+AM48+AX48 -> 3623 | BT48: =R48+AY48+AN48+S48+AZ48+AO48 -> 1387 | BU48: =SUM(BN48:BT48) -> 25499 | BW48: 2008 | BX48: =W48 -> 1606 | BY48: =X48 -> 4836 | BZ48: =Y48 -> 1541 | CA48: =Z48 -> 1625 | CB48: =AA48 -> 2765 | CC48: =AB48 -> 2398 | CD48: =AC48+AD48 -> 965 | CE48: =SUM(BX48:CD48) -> 15736
A49: 2009 | B49: =BE49 -> 14145 | C49: =BF49 -> 4095 | D49: =BG49 -> 4482 | E49: =BH49 -> 6907 | F49: =BI49 -> 6297 | G49: =BD49 -> 4176 | H49: =BJ49 -> 2702 | I49: =BK49 -> 42804 | K49: 2009 | L49: 1807 | M49: 6740 | N49: 2389 | O49: 2167 | P49: 3134 | Q49: 2764 | S49: 1158 | T49: =SUM(L49:S49) -> 20159 | V49: 2009 | W49: =G162+AH49 -> 1660 | X49: =B162+AI49 -> 5103 | Y49: =C162+AJ49 -> 1479 | Z49: =D162+AK49 -> 1639 | AA49: =E162+AL49 -> 2818 | AB49: =F162+AM49 -> 2519 | AD49: =H162+AO49 -> 1094 | AE49: =SUM(W49:AD49) -> 16312 | AG49: 2009 | AH49: 709 | AI49: 2302 | AJ49: 227 | AK49: 676 | AL49: 955 | AM49: 1014 | AO49: 450 | AP49: =SUM(AH49:AO49) -> 6333 | AR49: 2009 | BA49: 0 | BC49: 2009 | BD49: =L49+W49+AH49+AS49 -> 4176 | BE49: =M49+X49+AI49+AT49 -> 14145 | BF49: =N49+Y49+AJ49+AU49 -> 4095 | BG49: =O49+Z49+AK49+AV49 -> 4482 | BH49: =P49+AA49+AL49+AW49 -> 6907 | BI49: =Q49+AB49+AM49+AX49 -> 6297 | BJ49: =R49+AC49+AN49+AY49+S49+AD49+AO49+AZ49 -> 2702 | BK49: =SUM(BD49:BJ49) -> 42804 | BM49: 2009 | BN49: =L49+AH49+AS49 -> 2516 | BO49: =M49+AI49+AT49 -> 9042 | BP49: =N49+AJ49+AU49 -> 2616 | BQ49: =O49+AK49+AV49 -> 2843 | BR49: =P49+AL49+AW49 -> 4089 | BS49: =Q49+AM49+AX49 -> 3778 | BT49: =R49+AY49+AN49+S49+AZ49+AO49 -> 1608 | BU49: =SUM(BN49:BT49) -> 26492 | BW49: 2009 | BX49: =W49 -> 1660 | BY49: =X49 -> 5103 | BZ49: =Y49 -> 1479 | CA49: =Z49 -> 1639 | CB49: =AA49 -> 2818 | CC49: =AB49 -> 2519 | CD49: =AC49+AD49 -> 1094 | CE49: =SUM(BX49:CD49) -> 16312
A50: 2010 | B50: =BE50 -> 12104 | C50: =BF50 -> 3353 | D50: =BG50 -> 3770 | E50: =BH50 -> 5747 | F50: =BI50 -> 5412 | G50: =BD50 -> 3450 | H50: =BJ50 -> 2551 | I50: =BK50 -> 36387 | K50: 2010 | L50: 1779 | M50: 6949 | N50: 2228 | O50: 2178 | P50: 3003 | Q50: 2815 | S50: 1330 | T50: =SUM(L50:S50) -> 20282 | V50: 2010 | W50: 1004 | X50: 2870 | Y50: 947 | Z50: 947 | AA50: 1818 | AB50: 1588 | AD50: 717 | AE50: =SUM(W50:AD50) -> 9891 | AG50: 2010 | AH50: 667 | AI50: 2285 | AJ50: 178 | AK50: 645 | AL50: 926 | AM50: 1009 | AO50: 504 | AP50: =SUM(AH50:AO50) -> 6214 | AR50: 2010 | BA50: 0 | BC50: 2010 | BD50: =L50+W50+AH50+AS50 -> 3450 | BE50: =M50+X50+AI50+AT50 -> 12104 | BF50: =N50+Y50+AJ50+AU50 -> 3353 | BG50: =O50+Z50+AK50+AV50 -> 3770 | BH50: =P50+AA50+AL50+AW50 -> 5747 | BI50: =Q50+AB50+AM50+AX50 -> 5412 | BJ50: =R50+AC50+AN50+AY50+S50+AD50+AO50+AZ50 -> 2551 | BK50: =SUM(BD50:BJ50) -> 36387 | BM50: 2010 | BN50: =L50+AH50+AS50 -> 2446 | BO50: =M50+AI50+AT50 -> 9234 | BP50: =N50+AJ50+AU50 -> 2406 | BQ50: =O50+AK50+AV50 -> 2823 | BR50: =P50+AL50+AW50 -> 3929 | BS50: =Q50+AM50+AX50 -> 3824 | BT50: =R50+AY50+AN50+S50+AZ50+AO50 -> 1834 | BU50: =SUM(BN50:BT50) -> 26496 | BW50: 2010 | BX50: =W50 -> 1004 | BY50: =X50 -> 2870 | BZ50: =Y50 -> 947 | CA50: =Z50 -> 947 | CB50: =AA50 -> 1818 | CC50: =AB50 -> 1588 | CD50: =AC50+AD50 -> 717 | CE50: =SUM(BX50:CD50) -> 9891
A51: 2011 | B51: =BE51 -> 13423 | C51: =BF51 -> 3710 | D51: =BG51 -> 4042 | E51: =BH51 -> 5858 | F51: =BI51 -> 5908 | G51: =BD51 -> 3743 | H51: =BJ51 -> 3187 | I51: =BK51 -> 39871 | K51: 2011 | L51: 1808 | M51: 7201 | N51: 2086 | O51: 2204 | P51: 2891 | Q51: 2945 | S51: 1604 | T51: =SUM(L51:S51) -> 20739 | V51: 2011 | W51: 1055 | X51: 2931 | Y51: 1118 | Z51: 942 | AA51: 1763 | AB51: 1642 | AD51: 817 | AE51: =SUM(W51:AD51) -> 10268 | AG51: 2011 | AH51: 613 | AI51: 2163 | AJ51: 133 | AK51: 585 | AL51: 857 | AM51: 1025 | AO51: 556 | AP51: =SUM(AH51:AO51) -> 5932 | AR51: 2011 | AS51: 267 | AT51: 1128 | AU51: 373 | AV51: 311 | AW51: 347 | AX51: 296 | AZ51: 210 | BA51: =SUM(AS51:AZ51) -> 2932 | BC51: 2011 | BD51: =L51+W51+AH51+AS51 -> 3743 | BE51: =M51+X51+AI51+AT51 -> 13423 | BF51: =N51+Y51+AJ51+AU51 -> 3710 | BG51: =O51+Z51+AK51+AV51 -> 4042 | BH51: =P51+AA51+AL51+AW51 -> 5858 | BI51: =Q51+AB51+AM51+AX51 -> 5908 | BJ51: =R51+AC51+AN51+AY51+S51+AD51+AO51+AZ51 -> 3187 | BK51: =SUM(BD51:BJ51) -> 39871 | BM51: 2011 | BN51: =L51+AH51+AS51 -> 2688 | BO51: =M51+AI51+AT51 -> 10492 | BP51: =N51+AJ51+AU51 -> 2592 | BQ51: =O51+AK51+AV51 -> 3100 | BR51: =P51+AL51+AW51 -> 4095 | BS51: =Q51+AM51+AX51 -> 4266 | BT51: =R51+AY51+AN51+S51+AZ51+AO51 -> 2370 | BU51: =SUM(BN51:BT51) -> 29603 | BW51: 2011 | BX51: =W51 -> 1055 | BY51: =X51 -> 2931 | BZ51: =Y51 -> 1118 | CA51: =Z51 -> 942 | CB51: =AA51 -> 1763 | CC51: =AB51 -> 1642 | CD51: =AC51+AD51 -> 817 | CE51: =SUM(BX51:CD51) -> 10268
A52: 2012 | B52: =BE52 -> 13846 | C52: =BF52 -> 3441 | D52: =BG52 -> 4086 | E52: =BH52 -> 5665 | F52: =BI52 -> 6357 | G52: =BD52 -> 3876 | H52: =BJ52 -> 3916 | I52: =BK52 -> 41187 | K52: 2012 | L52: 1847 | M52: 7364 | N52: 1925 | O52: 2208 | P52: 2743 | Q52: 3099 | S52: 2007 | T52: =SUM(L52:S52) -> 21193 | V52: 2012 | W52: 1120 | X52: 3029 | Y52: 1062 | Z52: 970 | AA52: 1725 | AB52: 1794 | AD52: 974 | AE52: =SUM(W52:AD52) -> 10674 | AG52: 2012 | AH52: 605 | AI52: 2162 | AJ52: 105 | AK52: 561 | AL52: 838 | AM52: 1127 | AO52: 669 | AP52: =SUM(AH52:AO52) -> 6067 | AR52: 2012 | AS52: 304 | AT52: 1291 | AU52: 349 | AV52: 347 | AW52: 359 | AX52: 337 | AZ52: 266 | BA52: =SUM(AS52:AZ52) -> 3253 | BC52: 2012 | BD52: =L52+W52+AH52+AS52 -> 3876 | BE52: =M52+X52+AI52+AT52 -> 13846 | BF52: =N52+Y52+AJ52+AU52 -> 3441 | BG52: =O52+Z52+AK52+AV52 -> 4086 | BH52: =P52+AA52+AL52+AW52 -> 5665 | BI52: =Q52+AB52+AM52+AX52 -> 6357 | BJ52: =R52+AC52+AN52+AY52+S52+AD52+AO52+AZ52 -> 3916 | BK52: =SUM(BD52:BJ52) -> 41187 | BM52: 2012 | BN52: =L52+AH52+AS52 -> 2756 | BO52: =M52+AI52+AT52 -> 10817 | BP52: =N52+AJ52+AU52 -> 2379 | BQ52: =O52+AK52+AV52 -> 3116 | BR52: =P52+AL52+AW52 -> 3940 | BS52: =Q52+AM52+AX52 -> 4563 | BT52: =R52+AY52+AN52+S52+AZ52+AO52 -> 2942 | BU52: =SUM(BN52:BT52) -> 30513 | BW52: 2012 | BX52: =W52 -> 1120 | BY52: =X52 -> 3029 | BZ52: =Y52 -> 1062 | CA52: =Z52 -> 970 | CB52: =AA52 -> 1725 | CC52: =AB52 -> 1794 | CD52: =AC52+AD52 -> 974 | CE52: =SUM(BX52:CD52) -> 10674
A53: 2013 | B53: =BE53 -> 13078 | C53: =BF53 -> 3722 | D53: =BG53 -> 3469 | E53: =BH53 -> 5000 | F53: =BI53 -> 5319 | G53: =BD53 -> 5358 | H53: =BJ53 -> 3996 | I53: =BK53 -> 39942 | K53: 2013 | L53: 2566 | M53: 6914 | N53: 2128 | O53: 1874 | P53: 2404 | Q53: 2505 | S53: 2040 | T53: =SUM(L53:S53) -> 20431 | V53: 2013 | W53: 1587 | X53: 2883 | Y53: 1072 | Z53: 823 | AA53: 1544 | AB53: 1573 | AD53: 1013 | AE53: =SUM(W53:AD53) -> 10495 | AG53: 2013 | AH53: 789 | AI53: 2075 | AJ53: 120 | AK53: 480 | AL53: 741 | AM53: 945 | AO53: 654 | AP53: =SUM(AH53:AO53) -> 5804 | AR53: 2013 | AS53: 416 | AT53: 1206 | AU53: 402 | AV53: 292 | AW53: 311 | AX53: 296 | AZ53: 289 | BA53: =SUM(AS53:AZ53) -> 3212 | BC53: 2013 | BD53: =L53+W53+AH53+AS53 -> 5358 | BE53: =M53+X53+AI53+AT53 -> 13078 | BF53: =N53+Y53+AJ53+AU53 -> 3722 | BG53: =O53+Z53+AK53+AV53 -> 3469 | BH53: =P53+AA53+AL53+AW53 -> 5000 | BI53: =Q53+AB53+AM53+AX53 -> 5319 | BJ53: =R53+AC53+AN53+AY53+S53+AD53+AO53+AZ53 -> 3996 | BK53: =SUM(BD53:BJ53) -> 39942 | BM53: 2013 | BN53: =L53+AH53+AS53 -> 3771 | BO53: =M53+AI53+AT53 -> 10195 | BP53: =N53+AJ53+AU53 -> 2650 | BQ53: =O53+AK53+AV53 -> 2646 | BR53: =P53+AL53+AW53 -> 3456 | BS53: =Q53+AM53+AX53 -> 3746 | BT53: =R53+AY53+AN53+S53+AZ53+AO53 -> 2983 | BU53: =SUM(BN53:BT53) -> 29447 | BW53: 2013 | BX53: =W53 -> 1587 | BY53: =X53 -> 2883 | BZ53: =Y53 -> 1072 | CA53: =Z53 -> 823 | CB53: =AA53 -> 1544 | CC53: =AB53 -> 1573 | CD53: =AC53+AD53 -> 1013 | CE53: =SUM(BX53:CD53) -> 10495
A54: 2014 | B54: =BE54 -> 15738 | C54: =BF54 -> 4263 | D54: =BG54 -> 3239 | E54: =BH54 -> 4778 | F54: =BI54 -> 4986 | G54: =BD54 -> 5974 | H54: =BJ54 -> 4440 | I54: =BK54 -> 43418 | K54: 2014 | L54: 2920 | M54: 8322 | N54: 2508 | O54: 1752 | P54: 2292 | Q54: 2357 | S54: 2267 | T54: =SUM(L54:S54) -> 22418 | V54: 2014 | W54: 1728 | X54: 3496 | Y54: 1146 | Z54: 775 | AA54: 1495 | AB54: 1489 | AD54: 1145 | AE54: =SUM(W54:AD54) -> 11274 | AG54: 2014 | AH54: 855 | AI54: 2565 | AJ54: 144 | AK54: 454 | AL54: 715 | AM54: 873 | AO54: 706 | AP54: =SUM(AH54:AO54) -> 6312 | AR54: 2014 | AS54: 471 | AT54: 1355 | AU54: 465 | AV54: 258 | AW54: 276 | AX54: 267 | AZ54: 322 | BA54: =SUM(AS54:AZ54) -> 3414 | BC54: 2014 | BD54: =L54+W54+AH54+AS54 -> 5974 | BE54: =M54+X54+AI54+AT54 -> 15738 | BF54: =N54+Y54+AJ54+AU54 -> 4263 | BG54: =O54+Z54+AK54+AV54 -> 3239 | BH54: =P54+AA54+AL54+AW54 -> 4778 | BI54: =Q54+AB54+AM54+AX54 -> 4986 | BJ54: =R54+AC54+AN54+AY54+S54+AD54+AO54+AZ54 -> 4440 | BK54: =SUM(BD54:BJ54) -> 43418 | BM54: 2014 | BN54: =L54+AH54+AS54 -> 4246 | BO54: =M54+AI54+AT54 -> 12242 | BP54: =N54+AJ54+AU54 -> 3117 | BQ54: =O54+AK54+AV54 -> 2464 | BR54: =P54+AL54+AW54 -> 3283 | BS54: =Q54+AM54+AX54 -> 3497 | BT54: =R54+AY54+AN54+S54+AZ54+AO54 -> 3295 | BU54: =SUM(BN54:BT54) -> 32144 | BW54: 2014 | BX54: =W54 -> 1728 | BY54: =X54 -> 3496 | BZ54: =Y54 -> 1146 | CA54: =Z54 -> 775 | CB54: =AA54 -> 1495 | CC54: =AB54 -> 1489 | CD54: =AC54+AD54 -> 1145 | CE54: =SUM(BX54:CD54) -> 11274
A55: 2015 | B55: =BE55 -> 15662 | C55: =BF55 -> 4335 | D55: =BG55 -> 2840 | E55: =BH55 -> 4213 | F55: =BI55 -> 4404 | G55: =BD55 -> 6320 | H55: =BJ55 -> 4592 | I55: =BK55 -> 42366 | K55: 2015 | L55: 3083 | M55: 8046 | N55: 2547 | O55: 1500 | P55: 1972 | Q55: 2047 | S55: 2287 | T55: =SUM(L55:S55) -> 21482 | V55: 2015 | W55: 1773 | X55: 3580 | Y55: 1090 | Z55: 691 | AA55: 1349 | AB55: 1338 | AD55: 1212 | AE55: =SUM(W55:AD55) -> 11033 | AG55: 2015 | AH55: 865 | AI55: 2605 | AJ55: 151 | AK55: 400 | AL55: 632 | AM55: 758 | AO55: 706 | AP55: =SUM(AH55:AO55) -> 6117 | AR55: 2015 | AS55: 599 | AT55: 1431 | AU55: 547 | AV55: 249 | AW55: 260 | AX55: 261 | AZ55: 387 | BA55: =SUM(AS55:AZ55) -> 3734 | BC55: 2015 | BD55: =L55+W55+AH55+AS55 -> 6320 | BE55: =M55+X55+AI55+AT55 -> 15662 | BF55: =N55+Y55+AJ55+AU55 -> 4335 | BG55: =O55+Z55+AK55+AV55 -> 2840 | BH55: =P55+AA55+AL55+AW55 -> 4213 | BI55: =Q55+AB55+AM55+AX55 -> 4404 | BJ55: =R55+AC55+AN55+AY55+S55+AD55+AO55+AZ55 -> 4592 | BK55: =SUM(BD55:BJ55) -> 42366 | BM55: 2015 | BN55: =L55+AH55+AS55 -> 4547 | BO55: =M55+AI55+AT55 -> 12082 | BP55: =N55+AJ55+AU55 -> 3245 | BQ55: =O55+AK55+AV55 -> 2149 | BR55: =P55+AL55+AW55 -> 2864 | BS55: =Q55+AM55+AX55 -> 3066 | BT55: =R55+AY55+AN55+S55+AZ55+AO55 -> 3380 | BU55: =SUM(BN55:BT55) -> 31333 | BW55: 2015 | BX55: =W55 -> 1773 | BY55: =X55 -> 3580 | BZ55: =Y55 -> 1090 | CA55: =Z55 -> 691 | CB55: =AA55 -> 1349 | CC55: =AB55 -> 1338 | CD55: =AC55+AD55 -> 1212 | CE55: =SUM(BX55:CD55) -> 11033
A56: 2016 | B56: =BE56 -> 16082 | C56: =BF56 -> 4839 | D56: =BG56 -> 2581 | E56: =BH56 -> 3783 | F56: =BI56 -> 4017 | G56: =BD56 -> 6963 | H56: =BJ56 -> 4853 | I56: =BK56 -> 43118 | K56: 2016 | L56: 3539 | M56: 8323 | N56: 2948 | O56: 1379 | P56: 1789 | Q56: 1893 | S56: 2446 | T56: =SUM(L56:S56) -> 22317 | V56: 2016 | W56: 1856 | X56: 3758 | Y56: 1130 | Z56: 633 | AA56: 1226 | AB56: 1231 | AD56: 1297 | AE56: =SUM(W56:AD56) -> 11131 | AG56: 2016 | AH56: 895 | AI56: 2676 | AJ56: 171 | AK56: 359 | AL56: 560 | AM56: 674 | AO56: 713 | AP56: =SUM(AH56:AO56) -> 6048 | AR56: 2016 | AS56: 673 | AT56: 1325 | AU56: 590 | AV56: 210 | AW56: 208 | AX56: 219 | AZ56: 397 | BA56: =SUM(AS56:AZ56) -> 3622 | BC56: 2016 | BD56: =L56+W56+AH56+AS56 -> 6963 | BE56: =M56+X56+AI56+AT56 -> 16082 | BF56: =N56+Y56+AJ56+AU56 -> 4839 | BG56: =O56+Z56+AK56+AV56 -> 2581 | BH56: =P56+AA56+AL56+AW56 -> 3783 | BI56: =Q56+AB56+AM56+AX56 -> 4017 | BJ56: =R56+AC56+AN56+AY56+S56+AD56+AO56+AZ56 -> 4853 | BK56: =SUM(BD56:BJ56) -> 43118 | BM56: 2016 | BN56: =L56+AH56+AS56 -> 5107 | BO56: =M56+AI56+AT56 -> 12324 | BP56: =N56+AJ56+AU56 -> 3709 | BQ56: =O56+AK56+AV56 -> 1948 | BR56: =P56+AL56+AW56 -> 2557 | BS56: =Q56+AM56+AX56 -> 2786 | BT56: =R56+AY56+AN56+S56+AZ56+AO56 -> 3556 | BU56: =SUM(BN56:BT56) -> 31987 | BW56: 2016 | BX56: =W56 -> 1856 | BY56: =X56 -> 3758 | BZ56: =Y56 -> 1130 | CA56: =Z56 -> 633 | CB56: =AA56 -> 1226 | CC56: =AB56 -> 1231 | CD56: =AC56+AD56 -> 1297 | CE56: =SUM(BX56:CD56) -> 11131
A57: 2017 | B57: =BE57 -> 15926 | C57: =BF57 -> 4858 | D57: =BG57 -> 2286 | E57: =BH57 -> 3214 | F57: =BI57 -> 3495 | G57: =BD57 -> 7470 | H57: =BJ57 -> 4874 | I57: =BK57 -> 42123 | K57: 2017 | L57: 3934 | M57: 8202 | N57: 3038 | O57: 1220 | P57: 1522 | Q57: 1652 | R57: 1428 | S57: 1036 | T57: =SUM(L57:S57) -> 22032 | V57: 2017 | W57: 1862 | X57: 3821 | Y57: 1051 | Z57: 570 | AA57: 1053 | AB57: 1080 | AC57: 766 | AD57: 549 | AE57: =SUM(W57:AD57) -> 10752 | AG57: 2017 | AH57: 907 | AI57: 2703 | AJ57: 178 | AK57: 318 | AL57: 477 | AM57: 582 | AN57: 461 | AO57: 234 | AP57: =SUM(AH57:AO57) -> 5860 | AR57: 2017 | AS57: 767 | AT57: 1200 | AU57: 591 | AV57: 178 | AW57: 162 | AX57: 181 | AY57: 144 | AZ57: 256 | BA57: =SUM(AS57:AZ57) -> 3479 | BC57: 2017 | BD57: =L57+W57+AH57+AS57 -> 7470 | BE57: =M57+X57+AI57+AT57 -> 15926 | BF57: =N57+Y57+AJ57+AU57 -> 4858 | BG57: =O57+Z57+AK57+AV57 -> 2286 | BH57: =P57+AA57+AL57+AW57 -> 3214 | BI57: =Q57+AB57+AM57+AX57 -> 3495 | BJ57: =R57+AC57+AN57+AY57+S57+AD57+AO57+AZ57 -> 4874 | BK57: =SUM(BD57:BJ57) -> 42123 | BM57: 2017 | BN57: =L57+AH57+AS57 -> 5608 | BO57: =M57+AI57+AT57 -> 12105 | BP57: =N57+AJ57+AU57 -> 3807 | BQ57: =O57+AK57+AV57 -> 1716 | BR57: =P57+AL57+AW57 -> 2161 | BS57: =Q57+AM57+AX57 -> 2415 | BT57: =R57+AY57+AN57+S57+AZ57+AO57 -> 3559 | BU57: =SUM(BN57:BT57) -> 31371 | BW57: 2017 | BX57: =W57 -> 1862 | BY57: =X57 -> 3821 | BZ57: =Y57 -> 1051 | CA57: =Z57 -> 570 | CB57: =AA57 -> 1053 | CC57: =AB57 -> 1080 | CD57: =AC57+AD57 -> 1315 | CE57: =SUM(BX57:CD57) -> 10752
A58: 2018 | B58: =BE58 -> 15765 | C58: =BF58 -> 4840 | D58: =BG58 -> 2286 | E58: =BH58 -> 3211 | F58: =BI58 -> 3489 | G58: =BD58 -> 7494 | H58: =BJ58 -> 4879 | I58: =BK58 -> 41964 | K58: 2018 | L58: 3877 | M58: 8000 | N58: 2971 | O58: 1202 | P58: 1502 | Q58: 1628 | R58: 1407 | S58: 1021 | T58: =SUM(L58:S58) -> 21608 | V58: 2018 | W58: 1855 | X58: 3767 | Y58: 1039 | Z58: 568 | AA58: 1050 | AB58: 1076 | AC58: 763 | AD58: 547 | AE58: =SUM(W58:AD58) -> 10665 | AG58: 2018 | AH58: 908 | AI58: 2678 | AJ58: 177 | AK58: 318 | AL58: 478 | AM58: 583 | AN58: 461 | AO58: 234 | AP58: =SUM(AH58:AO58) -> 5837 | AR58: 2018 | AS58: 854 | AT58: 1320 | AU58: 653 | AV58: 198 | AW58: 181 | AX58: 202 | AY58: 161 | AZ58: 285 | BA58: =SUM(AS58:AZ58) -> 3854 | BC58: 2018 | BD58: =L58+W58+AH58+AS58 -> 7494 | BE58: =M58+X58+AI58+AT58 -> 15765 | BF58: =N58+Y58+AJ58+AU58 -> 4840 | BG58: =O58+Z58+AK58+AV58 -> 2286 | BH58: =P58+AA58+AL58+AW58 -> 3211 | BI58: =Q58+AB58+AM58+AX58 -> 3489 | BJ58: =R58+AC58+AN58+AY58+S58+AD58+AO58+AZ58 -> 4879 | BK58: =SUM(BD58:BJ58) -> 41964 | BM58: 2018 | BN58: =L58+AH58+AS58 -> 5639 | BO58: =M58+AI58+AT58 -> 11998 | BP58: =N58+AJ58+AU58 -> 3801 | BQ58: =O58+AK58+AV58 -> 1718 | BR58: =P58+AL58+AW58 -> 2161 | BS58: =Q58+AM58+AX58 -> 2413 | BT58: =R58+AY58+AN58+S58+AZ58+AO58 -> 3569 | BU58: =SUM(BN58:BT58) -> 31299 | BW58: 2018 | BX58: =W58 -> 1855 | BY58: =X58 -> 3767 | BZ58: =Y58 -> 1039 | CA58: =Z58 -> 568 | CB58: =AA58 -> 1050 | CC58: =AB58 -> 1076 | CD58: =AC58+AD58 -> 1310 | CE58: =SUM(BX58:CD58) -> 10665
A59: 2019 | B59: =BE59 -> 16113 | C59: =BF59 -> 4790 | D59: =BG59 -> 2354 | E59: =BH59 -> 3349 | F59: =BI59 -> 3594 | G59: =BD59 -> 7712 | H59: =BJ59 -> 5025 | I59: =BK59 -> 42937 | K59: 2019 | L59: 3997 | M59: 8203 | N59: 2949 | O59: 1239 | P59: 1567 | Q59: 1678 | R59: 1450 | S59: 1053 | T59: =SUM(L59:S59) -> 22136 | V59: 2019 | W59: 1907 | X59: 3819 | Y59: 1028 | Z59: 584 | AA59: 1093 | AB59: 1106 | AC59: 785 | AD59: 563 | AE59: =SUM(W59:AD59) -> 10885 | AG59: 2019 | AH59: 945 | AI59: 2778 | AJ59: 177 | AK59: 331 | AL59: 504 | AM59: 606 | AN59: 480 | AO59: 244 | AP59: =SUM(AH59:AO59) -> 6065 | AR59: 2019 | AS59: 863 | AT59: 1313 | AU59: 636 | AV59: 200 | AW59: 185 | AX59: 204 | AY59: 162 | AZ59: 288 | BA59: =SUM(AS59:AZ59) -> 3851 | BC59: 2019 | BD59: =L59+W59+AH59+AS59 -> 7712 | BE59: =M59+X59+AI59+AT59 -> 16113 | BF59: =N59+Y59+AJ59+AU59 -> 4790 | BG59: =O59+Z59+AK59+AV59 -> 2354 | BH59: =P59+AA59+AL59+AW59 -> 3349 | BI59: =Q59+AB59+AM59+AX59 -> 3594 | BJ59: =R59+AC59+AN59+AY59+S59+AD59+AO59+AZ59 -> 5025 | BK59: =SUM(BD59:BJ59) -> 42937 | BM59: 2019 | BN59: =L59+AH59+AS59 -> 5805 | BO59: =M59+AI59+AT59 -> 12294 | BP59: =N59+AJ59+AU59 -> 3762 | BQ59: =O59+AK59+AV59 -> 1770 | BR59: =P59+AL59+AW59 -> 2256 | BS59: =Q59+AM59+AX59 -> 2488 | BT59: =R59+AY59+AN59+S59+AZ59+AO59 -> 3677 | BU59: =SUM(BN59:BT59) -> 32052 | BW59: 2019 | BX59: =W59 -> 1907 | BY59: =X59 -> 3819 | BZ59: =Y59 -> 1028 | CA59: =Z59 -> 584 | CB59: =AA59 -> 1093 | CC59: =AB59 -> 1106 | CD59: =AC59+AD59 -> 1348 | CE59: =SUM(BX59:CD59) -> 10885
A60: 2020 | B60: =BE60 -> 18137 | C60: =BF60 -> 5133 | D60: =BG60 -> 2501 | E60: =BH60 -> 3550 | F60: =BI60 -> 3819 | G60: =BD60 -> 8194 | H60: =BJ60 -> 5340 | I60: =BK60 -> 46674 | K60: 2020 | L60: 4258 | M60: 9247 | N60: 3168 | O60: 1320 | P60: 1666 | Q60: 1788 | R60: 1545 | S60: 1121 | T60: =SUM(L60:S60) -> 24113 | V60: 2020 | W60: 2016 | X60: 4280 | Y60: 1096 | Z60: 617 | AA60: 1153 | AB60: 1169 | AC60: 830 | AD60: 595 | AE60: =SUM(W60:AD60) -> 11756 | AG60: 2020 | AH60: 1006 | AI60: 3131 | AJ60: 190 | AK60: 352 | AL60: 535 | AM60: 646 | AN60: 511 | AO60: 260 | AP60: =SUM(AH60:AO60) -> 6631 | AR60: 2020 | AS60: 914 | AT60: 1479 | AU60: 679 | AV60: 212 | AW60: 196 | AX60: 216 | AY60: 172 | AZ60: 306 | BA60: =SUM(AS60:AZ60) -> 4174 | BC60: 2020 | BD60: =L60+W60+AH60+AS60 -> 8194 | BE60: =M60+X60+AI60+AT60 -> 18137 | BF60: =N60+Y60+AJ60+AU60 -> 5133 | BG60: =O60+Z60+AK60+AV60 -> 2501 | BH60: =P60+AA60+AL60+AW60 -> 3550 | BI60: =Q60+AB60+AM60+AX60 -> 3819 | BJ60: =R60+AC60+AN60+AY60+S60+AD60+AO60+AZ60 -> 5340 | BK60: =SUM(BD60:BJ60) -> 46674 | BM60: 2020 | BN60: =L60+AH60+AS60 -> 6178 | BO60: =M60+AI60+AT60 -> 13857 | BP60: =N60+AJ60+AU60 -> 4037 | BQ60: =O60+AK60+AV60 -> 1884 | BR60: =P60+AL60+AW60 -> 2397 | BS60: =Q60+AM60+AX60 -> 2650 | BT60: =R60+AY60+AN60+S60+AZ60+AO60 -> 3915 | BU60: =SUM(BN60:BT60) -> 34918 | BW60: 2020 | BX60: =W60 -> 2016 | BY60: =X60 -> 4280 | BZ60: =Y60 -> 1096 | CA60: =Z60 -> 617 | CB60: =AA60 -> 1153 | CC60: =AB60 -> 1169 | CD60: =AC60+AD60 -> 1425 | CE60: =SUM(BX60:CD60) -> 11756
A61: 2021 | B61: =BE61 -> 18697 | C61: =BF61 -> 5099 | D61: =BG61 -> 2526 | E61: =BH61 -> 3603 | F61: =BI61 -> 3855 | G61: =BD61 -> 8289 | H61: =BJ61 -> 5396 | I61: =BK61 -> 47465 | K61: 2021 | L61: 4196 | M61: 9309 | N61: 3073 | O61: 1301 | P61: 1651 | Q61: 1762 | R61: 1522 | S61: 1105 | T61: =SUM(L61:S61) -> 23919 | V61: 2021 | W61: 2056 | X61: 4446 | Y61: 1100 | Z61: 630 | AA61: 1183 | AB61: 1193 | AC61: 846 | AD61: 607 | AE61: =SUM(W61:AD61) -> 12061 | AG61: 2021 | AH61: 1033 | AI61: 3288 | AJ61: 192 | AK61: 362 | AL61: 553 | AM61: 663 | AN61: 525 | AO61: 267 | AP61: =SUM(AH61:AO61) -> 6883 | AR61: 2021 | AS61: 1004 | AT61: 1654 | AU61: 734 | AV61: 233 | AW61: 216 | AX61: 237 | AY61: 189 | AZ61: 335 | BA61: =SUM(AS61:AZ61) -> 4602 | BC61: 2021 | BD61: =L61+W61+AH61+AS61 -> 8289 | BE61: =M61+X61+AI61+AT61 -> 18697 | BF61: =N61+Y61+AJ61+AU61 -> 5099 | BG61: =O61+Z61+AK61+AV61 -> 2526 | BH61: =P61+AA61+AL61+AW61 -> 3603 | BI61: =Q61+AB61+AM61+AX61 -> 3855 | BJ61: =R61+AC61+AN61+AY61+S61+AD61+AO61+AZ61 -> 5396 | BK61: =SUM(BD61:BJ61) -> 47465 | BM61: 2021 | BN61: =L61+AH61+AS61 -> 6233 | BO61: =M61+AI61+AT61 -> 14251 | BP61: =N61+AJ61+AU61 -> 3999 | BQ61: =O61+AK61+AV61 -> 1896 | BR61: =P61+AL61+AW61 -> 2420 | BS61: =Q61+AM61+AX61 -> 2662 | BT61: =R61+AY61+AN61+S61+AZ61+AO61 -> 3943 | BU61: =SUM(BN61:BT61) -> 35404 | BW61: 2021 | BX61: =W61 -> 2056 | BY61: =X61 -> 4446 | BZ61: =Y61 -> 1100 | CA61: =Z61 -> 630 | CB61: =AA61 -> 1183 | CC61: =AB61 -> 1193 | CD61: =AC61+AD61 -> 1453 | CE61: =SUM(BX61:CD61) -> 12061
A63: 转换为百分比Change to percentage
K64: 私人住宅Private Housing Segment | V64: 公共住宅 Public Housing | AG64: 房委会资助出售单位组别 Housing Authority Subsidized Sale Flats Segment | AR64: Total Energy Consumption in Other Housing Segment by End-use | BC64: 重新加总Private+Public | BM64: Private = Urban defination in the EPS | BW64: Public = Rural defination in the EPS
A65: 年份 Year | B65: =BE65 -> 空氣調節 Air Conditioning | C65: =BF65 -> 熱水 Hot Water | D65: =BG65 -> 照明 Lighting | E65: =BH65 -> 冷凍 Refrigeration | F65: =BI65 -> 辦公室設備 Office Equipment | G65: =BD65 -> 煮食 Cooking | H65: =BJ65 -> 其他 1 Others 1 | I65: =BK65 -> 總計 Total | K65: 年份 Year | L65: 煮食 Cooking | M65: 空氣調節 Air Conditioning | N65: 熱水 Hot Water | O65: 照明 Lighting | P65: 冷凍 Refrigeration | Q65: 辦公室設備 Office Equipment | R65: Laundry (Unit : Terajoule) | S65: 其他 1 Others 1 | T65: 總計 Total | V65: 年份 Year | W65: 煮食 Cooking | X65: 空氣調節 Air Conditioning | Y65: 熱水 Hot Water | Z65: 照明 Lighting | AA65: 冷凍 Refrigeration | AB65: 辦公室設備 Office Equipment | AC65: Laundry (Unit : Terajoule) | AD65: 其他 1 Others 1 | AE65: 總計 Total | AG65: 年份 Year | AH65: 煮食 Cooking | AI65: 空氣調節 Air Conditioning | AJ65: 熱水 Hot Water | AK65: 照明 Lighting | AL65: 冷凍 Refrigeration | AM65: 辦公室設備 Office Equipment | AN65: Laundry (Unit : Terajoule) | AO65: 其他 1 Others 1 | AP65: 總計 Total | AR65: 年份 Year | AS65: 煮食 Cooking | AT65: 空氣調節 Air Conditioning | AU65: 熱水 Hot Water | AV65: 照明 Lighting | AW65: 冷凍 Refrigeration | AX65: 辦公室設備 Office Equipment | AY65: Laundry (Unit : Terajoule) | AZ65: 其他 1 Others 1 | BA65: 總計 Total | BC65: 年份 Year | BD65: 煮食 Cooking | BE65: 空氣調節 Air Conditioning | BF65: 熱水 Hot Water | BG65: 照明 Lighting | BH65: 冷凍 Refrigeration | BI65: 辦公室設備 Office Equipment | BJ65: 其他 1 Others 1 | BK65: 總計 Total | BM65: 年份 Year | BN65: 煮食 Cooking | BO65: 空氣調節 Air Conditioning | BP65: 熱水 Hot Water | BQ65: 照明 Lighting | BR65: 冷凍 Refrigeration | BS65: 辦公室設備 Office Equipment | BT65: 其他 1 Others 1 | BU65: 總計 Total | BW65: 年份 Year | BX65: 煮食 Cooking | BY65: 空氣調節 Air Conditioning | BZ65: 熱水 Hot Water | CA65: 照明 Lighting | CB65: 冷凍 Refrigeration | CC65: 辦公室設備 Office Equipment | CD65: 其他 1 Others 1 | CE65: 總計 Total
A66: 2006 | B66: =BE66 -> 0.34127983 | C66: =BF66 -> 0.090811005 | D66: =BG66 -> 0.11901765 | E66: =BH66 -> 0.16369101 | F66: =BI66 -> 0.13784777 | G66: =BD66 -> 0.091941326 | H66: =BJ66 -> 0.055411411 | I66: =BK66 -> 1 | K66: 2006 | L66: =L46/$T46 -> 0.088365897 | M66: =M46/$T46 -> 0.33980906 | N66: =N46/$T46 -> 0.1178397 | O66: =O46/$T46 -> 0.11922735 | P66: =P46/$T46 -> 0.15708259 | Q66: =Q46/$T46 -> 0.12827487 | R66: =R46/$T46 -> 0 | S66: =S46/$T46 -> 0.049400533 | T66: =T46/$T46 -> 1 | V66: 2006 | W66: =W46/$AE46 -> 0.092244844 | X66: =X46/$AE46 -> 0.32984121 | Y66: =Y46/$AE46 -> 0.081768465 | Z66: =Z46/$AE46 -> 0.11596495 | AA66: =AA46/$AE46 -> 0.17500165 | AB66: =AB46/$AE46 -> 0.14568096 | AC66: =AC46/$AE46 -> 0 | AD66: =AD46/$AE46 -> 0.059497924 | AE66: =SUM(W66:AD66) -> 1 | AG66: 2006 | AH66: =AH46/$AP46 -> 0.10237182 | AI66: =AI46/$AP46 -> 0.37617719 | AJ66: =AJ46/$AP46 -> 0.029822114 | AK66: =AK46/$AP46 -> 0.12643879 | AL66: =AL46/$AP46 -> 0.15451692 | AM66: =AM46/$AP46 -> 0.14719219 | AN66: =AN46/$AP46 -> 0 | AO66: =AO46/$AP46 -> 0.063480991 | AP66: =SUM(AH66:AO66) -> 1 | AR66: 2006 | AS66: =IFERROR(AS46/$BA46,0) -> 0 | AT66: =IFERROR(AT46/$BA46,0) -> 0 | AU66: =IFERROR(AU46/$BA46,0) -> 0 | AV66: =IFERROR(AV46/$BA46,0) -> 0 | AW66: =IFERROR(AW46/$BA46,0) -> 0 | AX66: =IFERROR(AX46/$BA46,0) -> 0 | AY66: =IFERROR(AY46/$BA46,0) -> 0 | AZ66: =AZ46/$AP46 -> 0 | BA66: =SUM(AS66:AZ66) -> 0 | BC66: 2006 | BD66: =(L66*$T46+W66*$AE46+AH66*$AP46+AS66*$BA46)/$I46 -> 0.091941326 | BE66: =(M66*$T46+X66*$AE46+AI66*$AP46+AT66*$BA46)/$I46 -> 0.34127983 | BF66: =(N66*$T46+Y66*$AE46+AJ66*$AP46+AU66*$BA46)/$I46 -> 0.090811005 | BG66: =(O66*$T46+Z66*$AE46+AK66*$AP46+AV66*$BA46)/$I46 -> 0.11901765 | BH66: =(P66*$T46+AA66*$AE46+AL66*$AP46+AW66*$BA46)/$I46 -> 0.16369101 | BI66: =(Q66*$T46+AB66*$AE46+AM66*$AP46+AX66*$BA46)/$I46 -> 0.13784777 | BJ66: =((R66+S66)*$T46+(AC66+AD66)*$AE46+(AN66+AO66)*$AP46+(AZ66+AY66)*$BA46)/$I46 -> 0.055411411 | BK66: =SUM(BD66:BJ66) -> 1 | BM66: 2006 | BN66: =BN46/$BU46 -> 0.091747368 | BO66: =BO46/$BU46 -> 0.34858947 | BP66: =BP46/$BU46 -> 0.096589474 | BQ66: =BQ46/$BU46 -> 0.12096842 | BR66: =BR46/$BU46 -> 0.15646316 | BS66: =BS46/$BU46 -> 0.13284211 | BT66: =BT46/$BU46 -> 0.0528 | BU66: =SUM(BN66:BT66) -> 1 | BW66: 2006 | BX66: =IFERROR(BX46/$CE46,0) -> 0.092244844 | BY66: =IFERROR(BY46/$CE46,0) -> 0.32984121 | BZ66: =IFERROR(BZ46/$CE46,0) -> 0.081768465 | CA66: =IFERROR(CA46/$CE46,0) -> 0.11596495 | CB66: =IFERROR(CB46/$CE46,0) -> 0.17500165 | CC66: =IFERROR(CC46/$CE46,0) -> 0.14568096 | CD66: =IFERROR(CD46/$CE46,0) -> 0.059497924 | CE66: =SUM(BX66:CD66) -> 1
A67: 2007 | B67: =BE67 -> 0.33179001 | C67: =BF67 -> 0.09678142 | D67: =BG67 -> 0.11223956 | E67: =BH67 -> 0.16473751 | F67: =BI67 -> 0.14191123 | G67: =BD67 -> 0.096233789 | H67: =BJ67 -> 0.056306474 | I67: =BK67 -> 1 | K67: 2007 | L67: =L47/$T47 -> 0.091216761 | M67: =M47/$T47 -> 0.33177545 | N67: =N47/$T47 -> 0.12199839 | O67: =O47/$T47 -> 0.11281225 | P67: =P47/$T47 -> 0.15911899 | Q67: =Q47/$T47 -> 0.13263497 | R67: =R47/$T47 -> 0 | S67: =S47/$T47 -> 0.050443191 | T67: =T47/$T47 -> 1 | V67: 2007 | W67: =W47/$AE47 -> 0.096811445 | X67: =X47/$AE47 -> 0.31840636 | Y67: =Y47/$AE47 -> 0.089754282 | Z67: =Z47/$AE47 -> 0.10964265 | AA67: =AA47/$AE47 -> 0.17585167 | AB67: =AB47/$AE47 -> 0.14903445 | AC67: =AC47/$AE47 -> 0 | AD67: =AD47/$AE47 -> 0.060499134 | AE67: =SUM(W67:AD67) -> 1 | AG67: 2007 | AH67: =AH47/$AP47 -> 0.11036677 | AI67: =AI47/$AP47 -> 0.36677273 | AJ67: =AJ47/$AP47 -> 0.036509797 | AK67: =AK47/$AP47 -> 0.11723329 | AL67: =AL47/$AP47 -> 0.15324066 | AM67: =AM47/$AP47 -> 0.15223581 | AN67: =AN47/$AP47 -> 0 | AO67: =AO47/$AP47 -> 0.063640931 | AP67: =SUM(AH67:AO67) -> 1 | AR67: 2007 | AS67: =IFERROR(AS47/$BA47,0) -> 0 | AT67: =IFERROR(AT47/$BA47,0) -> 0 | AU67: =IFERROR(AU47/$BA47,0) -> 0 | AV67: =IFERROR(AV47/$BA47,0) -> 0 | AW67: =IFERROR(AW47/$BA47,0) -> 0 | AX67: =IFERROR(AX47/$BA47,0) -> 0 | AY67: =IFERROR(AY47/$BA47,0) -> 0 | AZ67: =AZ47/$AP47 -> 0 | BA67: =SUM(AS67:AZ67) -> 0 | BC67: 2007 | BD67: =(L67*$T47+W67*$AE47+AH67*$AP47+AS67*$BA47)/$I47 -> 0.096233789 | BE67: =(M67*$T47+X67*$AE47+AI67*$AP47+AT67*$BA47)/$I47 -> 0.33179001 | BF67: =(N67*$T47+Y67*$AE47+AJ67*$AP47+AU67*$BA47)/$I47 -> 0.09678142 | BG67: =(O67*$T47+Z67*$AE47+AK67*$AP47+AV67*$BA47)/$I47 -> 0.11223956 | BH67: =(P67*$T47+AA67*$AE47+AL67*$AP47+AW67*$BA47)/$I47 -> 0.16473751 | BI67: =(Q67*$T47+AB67*$AE47+AM67*$AP47+AX67*$BA47)/$I47 -> 0.14191123 | BJ67: =((R67+S67)*$T47+(AC67+AD67)*$AE47+(AN67+AO67)*$AP47+(AZ67+AY67)*$BA47)/$I47 -> 0.056306474 | BK67: =SUM(BD67:BJ67) -> 1 | BM67: 2007 | BN67: =BN47/$BU47 -> 0.095867567 | BO67: =BO47/$BU47 -> 0.34027495 | BP67: =BP47/$BU47 -> 0.10123648 | BQ67: =BQ47/$BU47 -> 0.11388595 | BR67: =BR47/$BU47 -> 0.15769137 | BS67: =BS47/$BU47 -> 0.13739527 | BT67: =BT47/$BU47 -> 0.053648418 | BU67: =SUM(BN67:BT67) -> 1 | BW67: 2007 | BX67: =IFERROR(BX47/$CE47,0) -> 0.096811445 | BY67: =IFERROR(BY47/$CE47,0) -> 0.31840636 | BZ67: =IFERROR(BZ47/$CE47,0) -> 0.089754282 | CA67: =IFERROR(CA47/$CE47,0) -> 0.10964265 | CB67: =IFERROR(CB47/$CE47,0) -> 0.17585167 | CC67: =IFERROR(CC47/$CE47,0) -> 0.14903445 | CD67: =IFERROR(CD47/$CE47,0) -> 0.060499134 | CE67: =SUM(BX67:CD67) -> 1
A68: 2008 | B68: =BE68 -> 0.32234752 | C68: =BF68 -> 0.10304353 | D68: =BG68 -> 0.10556566 | E68: =BH68 -> 0.16505396 | F68: =BI68 -> 0.14601673 | G68: =BD68 -> 0.10093367 | H68: =BJ68 -> 0.057038923 | I68: =BK68 -> 1 | K68: 2008 | L68: =L48/$T48 -> 0.093998029 | M68: =M48/$T48 -> 0.32370182 | N68: =N48/$T48 -> 0.12610883 | O68: =O48/$T48 -> 0.10660372 | P68: =P48/$T48 -> 0.16086528 | Q68: =Q48/$T48 -> 0.13726202 | R68: =R48/$T48 -> 0 | S68: =S48/$T48 -> 0.051460289 | T68: =T48/$T48 -> 1 | V68: 2008 | W68: =W48/$AE48 -> 0.10205897 | X68: =X48/$AE48 -> 0.30732079 | Y68: =Y48/$AE48 -> 0.097928317 | Z68: =Z48/$AE48 -> 0.1032664 | AA68: =AA48/$AE48 -> 0.17571174 | AB68: =AB48/$AE48 -> 0.15238943 | AC68: =AC48/$AE48 -> 0 | AD68: =AD48/$AE48 -> 0.061324352 | AE68: =SUM(W68:AD68) -> 1 | AG68: 2008 | AH68: =AH48/$AP48 -> 0.1195757 | AI68: =AI48/$AP48 -> 0.35615558 | AJ68: =AJ48/$AP48 -> 0.044519447 | AK68: =AK48/$AP48 -> 0.10816458 | AL68: =AL48/$AP48 -> 0.15107682 | AM68: =AM48/$AP48 -> 0.15702347 | AN68: =AN48/$AP48 -> 0 | AO68: =AO48/$AP48 -> 0.06348441 | AP68: =SUM(AH68:AO68) -> 1 | AR68: 2008 | AS68: =IFERROR(AS48/$BA48,0) -> 0 | AT68: =IFERROR(AT48/$BA48,0) -> 0 | AU68: =IFERROR(AU48/$BA48,0) -> 0 | AV68: =IFERROR(AV48/$BA48,0) -> 0 | AW68: =IFERROR(AW48/$BA48,0) -> 0 | AX68: =IFERROR(AX48/$BA48,0) -> 0 | AY68: =IFERROR(AY48/$BA48,0) -> 0 | AZ68: =AZ48/$AP48 -> 0 | BA68: =SUM(AS68:AZ68) -> 0 | BC68: 2008 | BD68: =(L68*$T48+W68*$AE48+AH68*$AP48+AS68*$BA48)/$I48 -> 0.10093367 | BE68: =(M68*$T48+X68*$AE48+AI68*$AP48+AT68*$BA48)/$I48 -> 0.32234752 | BF68: =(N68*$T48+Y68*$AE48+AJ68*$AP48+AU68*$BA48)/$I48 -> 0.10304353 | BG68: =(O68*$T48+Z68*$AE48+AK68*$AP48+AV68*$BA48)/$I48 -> 0.10556566 | BH68: =(P68*$T48+AA68*$AE48+AL68*$AP48+AW68*$BA48)/$I48 -> 0.16505396 | BI68: =(Q68*$T48+AB68*$AE48+AM68*$AP48+AX68*$BA48)/$I48 -> 0.14601673 | BJ68: =((R68+S68)*$T48+(AC68+AD68)*$AE48+(AN68+AO68)*$AP48+(AZ68+AY68)*$BA48)/$I48 -> 0.057038923 | BK68: =SUM(BD68:BJ68) -> 1 | BM68: 2008 | BN68: =BN48/$BU48 -> 0.10023923 | BO68: =BO48/$BU48 -> 0.33162085 | BP68: =BP48/$BU48 -> 0.10620024 | BQ68: =BQ48/$BU48 -> 0.10698459 | BR68: =BR48/$BU48 -> 0.1584768 | BS68: =BS48/$BU48 -> 0.142084 | BT68: =BT48/$BU48 -> 0.05439429 | BU68: =SUM(BN68:BT68) -> 1 | BW68: 2008 | BX68: =IFERROR(BX48/$CE48,0) -> 0.10205897 | BY68: =IFERROR(BY48/$CE48,0) -> 0.30732079 | BZ68: =IFERROR(BZ48/$CE48,0) -> 0.097928317 | CA68: =IFERROR(CA48/$CE48,0) -> 0.1032664 | CB68: =IFERROR(CB48/$CE48,0) -> 0.17571174 | CC68: =IFERROR(CC48/$CE48,0) -> 0.15238943 | CD68: =IFERROR(CD48/$CE48,0) -> 0.061324352 | CE68: =SUM(BX68:CD68) -> 1
A69: 2009 | B69: =BE69 -> 0.33045977 | C69: =BF69 -> 0.095668629 | D69: =BG69 -> 0.10470984 | E69: =BH69 -> 0.16136342 | F69: =BI69 -> 0.14711242 | G69: =BD69 -> 0.097560976 | H69: =BJ69 -> 0.063124942 | I69: =BK69 -> 1 | K69: 2009 | L69: =L49/$T49 -> 0.089637383 | M69: =M49/$T49 -> 0.33434198 | N69: =N49/$T49 -> 0.11850786 | O69: =O49/$T49 -> 0.10749541 | P69: =P49/$T49 -> 0.15546406 | Q69: =Q49/$T49 -> 0.13710998 | R69: =R49/$T49 -> 0 | S69: =S49/$T49 -> 0.057443326 | T69: =T49/$T49 -> 1 | V69: 2009 | W69: =W49/$AE49 -> 0.10176557 | X69: =X49/$AE49 -> 0.31283718 | Y69: =Y49/$AE49 -> 0.090669446 | Z69: =Z49/$AE49 -> 0.10047818 | AA69: =AA49/$AE49 -> 0.17275625 | AB69: =AB49/$AE49 -> 0.15442619 | AC69: =AC49/$AE49 -> 0 | AD69: =AD49/$AE49 -> 0.06706719 | AE69: =SUM(W69:AD69) -> 1 | AG69: 2009 | AH69: =AH49/$AP49 -> 0.11195326 | AI69: =AI49/$AP49 -> 0.36349282 | AJ69: =AJ49/$AP49 -> 0.035843992 | AK69: =AK49/$AP49 -> 0.10674246 | AL69: =AL49/$AP49 -> 0.15079741 | AM69: =AM49/$AP49 -> 0.16011369 | AN69: =AN49/$AP49 -> 0 | AO69: =AO49/$AP49 -> 0.071056371 | AP69: =SUM(AH69:AO69) -> 1 | AR69: 2009 | AS69: =IFERROR(AS49/$BA49,0) -> 0 | AT69: =IFERROR(AT49/$BA49,0) -> 0 | AU69: =IFERROR(AU49/$BA49,0) -> 0 | AV69: =IFERROR(AV49/$BA49,0) -> 0 | AW69: =IFERROR(AW49/$BA49,0) -> 0 | AX69: =IFERROR(AX49/$BA49,0) -> 0 | AY69: =IFERROR(AY49/$BA49,0) -> 0 | AZ69: =AZ49/$AP49 -> 0 | BA69: =SUM(AS69:AZ69) -> 0 | BC69: 2009 | BD69: =(L69*$T49+W69*$AE49+AH69*$AP49+AS69*$BA49)/$I49 -> 0.097560976 | BE69: =(M69*$T49+X69*$AE49+AI69*$AP49+AT69*$BA49)/$I49 -> 0.33045977 | BF69: =(N69*$T49+Y69*$AE49+AJ69*$AP49+AU69*$BA49)/$I49 -> 0.095668629 | BG69: =(O69*$T49+Z69*$AE49+AK69*$AP49+AV69*$BA49)/$I49 -> 0.10470984 | BH69: =(P69*$T49+AA69*$AE49+AL69*$AP49+AW69*$BA49)/$I49 -> 0.16136342 | BI69: =(Q69*$T49+AB69*$AE49+AM69*$AP49+AX69*$BA49)/$I49 -> 0.14711242 | BJ69: =((R69+S69)*$T49+(AC69+AD69)*$AE49+(AN69+AO69)*$AP49+(AZ69+AY69)*$BA49)/$I49 -> 0.063124942 | BK69: =SUM(BD69:BJ69) -> 1 | BM69: 2009 | BN69: =BN49/$BU49 -> 0.094972067 | BO69: =BO49/$BU49 -> 0.34131058 | BP69: =BP49/$BU49 -> 0.098746791 | BQ69: =BQ49/$BU49 -> 0.10731542 | BR69: =BR49/$BU49 -> 0.15434848 | BS69: =BS49/$BU49 -> 0.14260909 | BT69: =BT49/$BU49 -> 0.060697569 | BU69: =SUM(BN69:BT69) -> 1 | BW69: 2009 | BX69: =IFERROR(BX49/$CE49,0) -> 0.10176557 | BY69: =IFERROR(BY49/$CE49,0) -> 0.31283718 | BZ69: =IFERROR(BZ49/$CE49,0) -> 0.090669446 | CA69: =IFERROR(CA49/$CE49,0) -> 0.10047818 | CB69: =IFERROR(CB49/$CE49,0) -> 0.17275625 | CC69: =IFERROR(CC49/$CE49,0) -> 0.15442619 | CD69: =IFERROR(CD49/$CE49,0) -> 0.06706719 | CE69: =SUM(BX69:CD69) -> 1
A70: 2010 | B70: =BE70 -> 0.33264627 | C70: =BF70 -> 0.092148295 | D70: =BG70 -> 0.10360843 | E70: =BH70 -> 0.15794102 | F70: =BI70 -> 0.14873444 | G70: =BD70 -> 0.094814082 | H70: =BJ70 -> 0.070107456 | I70: =BK70 -> 1 | K70: 2010 | L70: =L50/$T50 -> 0.087713243 | M70: =M50/$T50 -> 0.34261907 | N70: =N50/$T50 -> 0.1098511 | O70: =O50/$T50 -> 0.10738586 | P70: =P50/$T50 -> 0.14806232 | Q70: =Q50/$T50 -> 0.13879302 | R70: =R50/$T50 -> 0 | S70: =S50/$T50 -> 0.065575387 | T70: =T50/$T50 -> 1 | V70: 2010 | W70: =W50/$AE50 -> 0.10150642 | X70: =X50/$AE50 -> 0.29016277 | Y70: =Y50/$AE50 -> 0.095743605 | Z70: =Z50/$AE50 -> 0.095743605 | AA70: =AA50/$AE50 -> 0.18380346 | AB70: =AB50/$AE50 -> 0.16054999 | AC70: =AC50/$AE50 -> 0 | AD70: =AD50/$AE50 -> 0.072490143 | AE70: =SUM(W70:AD70) -> 1 | AG70: 2010 | AH70: =AH50/$AP50 -> 0.10733827 | AI70: =AI50/$AP50 -> 0.36771806 | AJ70: =AJ50/$AP50 -> 0.028644995 | AK70: =AK50/$AP50 -> 0.10379788 | AL70: =AL50/$AP50 -> 0.14901835 | AM70: =AM50/$AP50 -> 0.16237528 | AN70: =AN50/$AP50 -> 0 | AO70: =AO50/$AP50 -> 0.081107177 | AP70: =SUM(AH70:AO70) -> 1 | AR70: 2010 | AS70: =IFERROR(AS50/$BA50,0) -> 0 | AT70: =IFERROR(AT50/$BA50,0) -> 0 | AU70: =IFERROR(AU50/$BA50,0) -> 0 | AV70: =IFERROR(AV50/$BA50,0) -> 0 | AW70: =IFERROR(AW50/$BA50,0) -> 0 | AX70: =IFERROR(AX50/$BA50,0) -> 0 | AY70: =IFERROR(AY50/$BA50,0) -> 0 | AZ70: =AZ50/$AP50 -> 0 | BA70: =SUM(AS70:AZ70) -> 0 | BC70: 2010 | BD70: =(L70*$T50+W70*$AE50+AH70*$AP50+AS70*$BA50)/$I50 -> 0.094814082 | BE70: =(M70*$T50+X70*$AE50+AI70*$AP50+AT70*$BA50)/$I50 -> 0.33264627 | BF70: =(N70*$T50+Y70*$AE50+AJ70*$AP50+AU70*$BA50)/$I50 -> 0.092148295 | BG70: =(O70*$T50+Z70*$AE50+AK70*$AP50+AV70*$BA50)/$I50 -> 0.10360843 | BH70: =(P70*$T50+AA70*$AE50+AL70*$AP50+AW70*$BA50)/$I50 -> 0.15794102 | BI70: =(Q70*$T50+AB70*$AE50+AM70*$AP50+AX70*$BA50)/$I50 -> 0.14873444 | BJ70: =((R70+S70)*$T50+(AC70+AD70)*$AE50+(AN70+AO70)*$AP50+(AZ70+AY70)*$BA50)/$I50 -> 0.070107456 | BK70: =SUM(BD70:BJ70) -> 1 | BM70: 2010 | BN70: =BN50/$BU50 -> 0.092315821 | BO70: =BO50/$BU50 -> 0.34850543 | BP70: =BP50/$BU50 -> 0.090806159 | BQ70: =BQ50/$BU50 -> 0.10654438 | BR70: =BR50/$BU50 -> 0.14828653 | BS70: =BS50/$BU50 -> 0.14432367 | BT70: =BT50/$BU50 -> 0.069217995 | BU70: =SUM(BN70:BT70) -> 1 | BW70: 2010 | BX70: =IFERROR(BX50/$CE50,0) -> 0.10150642 | BY70: =IFERROR(BY50/$CE50,0) -> 0.29016277 | BZ70: =IFERROR(BZ50/$CE50,0) -> 0.095743605 | CA70: =IFERROR(CA50/$CE50,0) -> 0.095743605 | CB70: =IFERROR(CB50/$CE50,0) -> 0.18380346 | CC70: =IFERROR(CC50/$CE50,0) -> 0.16054999 | CD70: =IFERROR(CD50/$CE50,0) -> 0.072490143 | CE70: =SUM(BX70:CD70) -> 1
A71: 2011 | B71: =BE71 -> 0.33666073 | C71: =BF71 -> 0.093050087 | D71: =BG71 -> 0.10137694 | E71: =BH71 -> 0.14692383 | F71: =BI71 -> 0.14817787 | G71: =BD71 -> 0.093877756 | H71: =BJ71 -> 0.079932783 | I71: =BK71 -> 1 | K71: 2011 | L71: =L51/$T51 -> 0.087178745 | M71: =M51/$T51 -> 0.34722021 | N71: =N51/$T51 -> 0.10058344 | O71: =O51/$T51 -> 0.10627321 | P71: =P51/$T51 -> 0.1393992 | Q71: =Q51/$T51 -> 0.14200299 | R71: =R51/$T51 -> 0 | S71: =S51/$T51 -> 0.077342206 | T71: =T51/$T51 -> 1 | V71: 2011 | W71: =W51/$AE51 -> 0.1027464 | X71: =X51/$AE51 -> 0.28544994 | Y71: =Y51/$AE51 -> 0.10888196 | Z71: =Z51/$AE51 -> 0.091741332 | AA71: =AA51/$AE51 -> 0.17169848 | AB71: =AB51/$AE51 -> 0.1599143 | AC71: =AC51/$AE51 -> 0 | AD71: =AD51/$AE51 -> 0.079567589 | AE71: =SUM(W71:AD71) -> 1 | AG71: 2011 | AH71: =AH51/$AP51 -> 0.10333783 | AI71: =AI51/$AP51 -> 0.3646325 | AJ71: =AJ51/$AP51 -> 0.022420769 | AK71: =AK51/$AP51 -> 0.098617667 | AL71: =AL51/$AP51 -> 0.14447067 | AM71: =AM51/$AP51 -> 0.17279164 | AN71: =AN51/$AP51 -> 0 | AO71: =AO51/$AP51 -> 0.093728928 | AP71: =SUM(AH71:AO71) -> 1 | AR71: 2011 | AS71: =IFERROR(AS51/$BA51,0) -> 0.09106412 | AT71: =IFERROR(AT51/$BA51,0) -> 0.38472033 | AU71: =IFERROR(AU51/$BA51,0) -> 0.12721692 | AV71: =IFERROR(AV51/$BA51,0) -> 0.10607094 | AW71: =IFERROR(AW51/$BA51,0) -> 0.11834925 | AX71: =IFERROR(AX51/$BA51,0) -> 0.10095498 | AY71: =IFERROR(AY51/$BA51,0) -> 0 | AZ71: =AZ51/$BA51 -> 0.071623465 | BA71: =SUM(AS71:AZ71) -> 1 | BC71: 2011 | BD71: =(L71*$T51+W71*$AE51+AH71*$AP51+AS71*$BA51)/$I51 -> 0.093877756 | BE71: =(M71*$T51+X71*$AE51+AI71*$AP51+AT71*$BA51)/$I51 -> 0.33666073 | BF71: =(N71*$T51+Y71*$AE51+AJ71*$AP51+AU71*$BA51)/$I51 -> 0.093050087 | BG71: =(O71*$T51+Z71*$AE51+AK71*$AP51+AV71*$BA51)/$I51 -> 0.10137694 | BH71: =(P71*$T51+AA71*$AE51+AL71*$AP51+AW71*$BA51)/$I51 -> 0.14692383 | BI71: =(Q71*$T51+AB71*$AE51+AM71*$AP51+AX71*$BA51)/$I51 -> 0.14817787 | BJ71: =((R71+S71)*$T51+(AC71+AD71)*$AE51+(AN71+AO71)*$AP51+(AZ71+AY71)*$BA51)/$I51 -> 0.079932783 | BK71: =SUM(BD71:BJ71) -> 1 | BM71: 2011 | BN71: =BN51/$BU51 -> 0.090801608 | BO71: =BO51/$BU51 -> 0.35442354 | BP71: =BP51/$BU51 -> 0.087558693 | BQ71: =BQ51/$BU51 -> 0.10471912 | BR71: =BR51/$BU51 -> 0.13833057 | BS71: =BS51/$BU51 -> 0.14410702 | BT71: =BT51/$BU51 -> 0.080059453 | BU71: =SUM(BN71:BT71) -> 1 | BW71: 2011 | BX71: =IFERROR(BX51/$CE51,0) -> 0.1027464 | BY71: =IFERROR(BY51/$CE51,0) -> 0.28544994 | BZ71: =IFERROR(BZ51/$CE51,0) -> 0.10888196 | CA71: =IFERROR(CA51/$CE51,0) -> 0.091741332 | CB71: =IFERROR(CB51/$CE51,0) -> 0.17169848 | CC71: =IFERROR(CC51/$CE51,0) -> 0.1599143 | CD71: =IFERROR(CD51/$CE51,0) -> 0.079567589 | CE71: =SUM(BX71:CD71) -> 1
A72: 2012 | B72: =BE72 -> 0.33617404 | C72: =BF72 -> 0.083545779 | D72: =BG72 -> 0.09920606 | E72: =BH72 -> 0.1375434 | F72: =BI72 -> 0.15434482 | G72: =BD72 -> 0.094107364 | H72: =BJ72 -> 0.095078544 | I72: =BK72 -> 1 | K72: 2012 | L72: =L52/$T52 -> 0.087151418 | M72: =M52/$T52 -> 0.34747322 | N72: =N52/$T52 -> 0.090831878 | O72: =O52/$T52 -> 0.10418534 | P72: =P52/$T52 -> 0.12942953 | Q72: =Q52/$T52 -> 0.14622753 | R72: =R52/$T52 -> 0 | S72: =S52/$T52 -> 0.094701081 | T72: =T52/$T52 -> 1 | V72: 2012 | W72: =W52/$AE52 -> 0.10492786 | X72: =X52/$AE52 -> 0.28377366 | Y72: =Y52/$AE52 -> 0.099494098 | Z72: =Z52/$AE52 -> 0.090875023 | AA72: =AA52/$AE52 -> 0.16160764 | AB72: =AB52/$AE52 -> 0.16807195 | AC72: =AC52/$AE52 -> 0 | AD72: =AD52/$AE52 -> 0.091249766 | AE72: =SUM(W72:AD72) -> 1 | AG72: 2012 | AH72: =AH52/$AP52 -> 0.099719796 | AI72: =AI52/$AP52 -> 0.35635405 | AJ72: =AJ52/$AP52 -> 0.017306741 | AK72: =AK52/$AP52 -> 0.092467447 | AL72: =AL52/$AP52 -> 0.13812428 | AM72: =AM52/$AP52 -> 0.18575902 | AN72: =AN52/$AP52 -> 0 | AO72: =AO52/$AP52 -> 0.11026867 | AP72: =SUM(AH72:AO72) -> 1 | AR72: 2012 | AS72: =AS52/$BA52 -> 0.093452198 | AT72: =AT52/$BA52 -> 0.39686443 | AU72: =AU52/$BA52 -> 0.10728558 | AV72: =AV52/$BA52 -> 0.10667077 | AW72: =AW52/$BA52 -> 0.11035967 | AX72: =AX52/$BA52 -> 0.10359668 | AY72: =AY52/$BA52 -> 0 | AZ72: =AZ52/$BA52 -> 0.081770673 | BA72: =SUM(AS72:AZ72) -> 1 | BC72: 2012 | BD72: =(L72*$T52+W72*$AE52+AH72*$AP52+AS72*$BA52)/$I52 -> 0.094107364 | BE72: =(M72*$T52+X72*$AE52+AI72*$AP52+AT72*$BA52)/$I52 -> 0.33617404 | BF72: =(N72*$T52+Y72*$AE52+AJ72*$AP52+AU72*$BA52)/$I52 -> 0.083545779 | BG72: =(O72*$T52+Z72*$AE52+AK72*$AP52+AV72*$BA52)/$I52 -> 0.09920606 | BH72: =(P72*$T52+AA72*$AE52+AL72*$AP52+AW72*$BA52)/$I52 -> 0.1375434 | BI72: =(Q72*$T52+AB72*$AE52+AM72*$AP52+AX72*$BA52)/$I52 -> 0.15434482 | BJ72: =((R72+S72)*$T52+(AC72+AD72)*$AE52+(AN72+AO72)*$AP52+(AZ72+AY72)*$BA52)/$I52 -> 0.095078544 | BK72: =SUM(BD72:BJ72) -> 1 | BM72: 2012 | BN72: =BN52/$BU52 -> 0.090322158 | BO72: =BO52/$BU52 -> 0.35450464 | BP72: =BP52/$BU52 -> 0.077966768 | BQ72: =BQ52/$BU52 -> 0.10212041 | BR72: =BR52/$BU52 -> 0.12912529 | BS72: =BS52/$BU52 -> 0.14954282 | BT72: =BT52/$BU52 -> 0.09641792 | BU72: =SUM(BN72:BT72) -> 1 | BW72: 2012 | BX72: =IFERROR(BX52/$CE52,0) -> 0.10492786 | BY72: =IFERROR(BY52/$CE52,0) -> 0.28377366 | BZ72: =IFERROR(BZ52/$CE52,0) -> 0.099494098 | CA72: =IFERROR(CA52/$CE52,0) -> 0.090875023 | CB72: =IFERROR(CB52/$CE52,0) -> 0.16160764 | CC72: =IFERROR(CC52/$CE52,0) -> 0.16807195 | CD72: =IFERROR(CD52/$CE52,0) -> 0.091249766 | CE72: =SUM(BX72:CD72) -> 1
A73: 2013 | B73: =BE73 -> 0.32742477 | C73: =BF73 -> 0.093185118 | D73: =BG73 -> 0.086850934 | E73: =BH73 -> 0.12518151 | F73: =BI73 -> 0.13316809 | G73: =BD73 -> 0.13414451 | H73: =BJ73 -> 0.10004507 | I73: =BK73 -> 1 | K73: 2013 | L73: =L53/$T53 -> 0.12559346 | M73: =M53/$T53 -> 0.33840732 | N73: =N53/$T53 -> 0.10415545 | O73: =O53/$T53 -> 0.091723362 | P73: =P53/$T53 -> 0.11766433 | Q73: =Q53/$T53 -> 0.1226078 | R73: =R53/$T53 -> 0 | S73: =S53/$T53 -> 0.09984827 | T73: =T53/$T53 -> 1 | V73: 2013 | W73: =W53/$AE53 -> 0.15121486 | X73: =X53/$AE53 -> 0.27470224 | Y73: =Y53/$AE53 -> 0.10214388 | Z73: =Z53/$AE53 -> 0.078418294 | AA73: =AA53/$AE53 -> 0.14711768 | AB73: =AB53/$AE53 -> 0.1498809 | AC73: =AC53/$AE53 -> 0 | AD73: =AD53/$AE53 -> 0.096522153 | AE73: =SUM(W73:AD73) -> 1 | AG73: 2013 | AH73: =AH53/$AP53 -> 0.13594073 | AI73: =AI53/$AP53 -> 0.35751206 | AJ73: =AJ53/$AP53 -> 0.020675396 | AK73: =AK53/$AP53 -> 0.082701585 | AL73: =AL53/$AP53 -> 0.12767057 | AM73: =AM53/$AP53 -> 0.16281875 | AN73: =AN53/$AP53 -> 0 | AO73: =AO53/$AP53 -> 0.11268091 | AP73: =SUM(AH73:AO73) -> 1 | AR73: 2013 | AS73: =AS53/$BA53 -> 0.12951432 | AT73: =AT53/$BA53 -> 0.375467 | AU73: =AU53/$BA53 -> 0.12515567 | AV73: =AV53/$BA53 -> 0.090909091 | AW73: =AW53/$BA53 -> 0.096824408 | AX73: =AX53/$BA53 -> 0.092154421 | AY73: =AY53/$BA53 -> 0 | AZ73: =AZ53/$BA53 -> 0.089975093 | BA73: =SUM(AS73:AZ73) -> 1 | BC73: 2013 | BD73: =(L73*$T53+W73*$AE53+AH73*$AP53+AS73*$BA53)/$I53 -> 0.13414451 | BE73: =(M73*$T53+X73*$AE53+AI73*$AP53+AT73*$BA53)/$I53 -> 0.32742477 | BF73: =(N73*$T53+Y73*$AE53+AJ73*$AP53+AU73*$BA53)/$I53 -> 0.093185118 | BG73: =(O73*$T53+Z73*$AE53+AK73*$AP53+AV73*$BA53)/$I53 -> 0.086850934 | BH73: =(P73*$T53+AA73*$AE53+AL73*$AP53+AW73*$BA53)/$I53 -> 0.12518151 | BI73: =(Q73*$T53+AB73*$AE53+AM73*$AP53+AX73*$BA53)/$I53 -> 0.13316809 | BJ73: =((R73+S73)*$T53+(AC73+AD73)*$AE53+(AN73+AO73)*$AP53+(AZ73+AY73)*$BA53)/$I53 -> 0.10004507 | BK73: =SUM(BD73:BJ73) -> 1 | BM73: 2013 | BN73: =BN53/$BU53 -> 0.12806058 | BO73: =BO53/$BU53 -> 0.34621523 | BP73: =BP53/$BU53 -> 0.089992189 | BQ73: =BQ53/$BU53 -> 0.089856352 | BR73: =BR53/$BU53 -> 0.1173634 | BS73: =BS53/$BU53 -> 0.1272116 | BT73: =BT53/$BU53 -> 0.10130064 | BU73: =SUM(BN73:BT73) -> 1 | BW73: 2013 | BX73: =IFERROR(BX53/$CE53,0) -> 0.15121486 | BY73: =IFERROR(BY53/$CE53,0) -> 0.27470224 | BZ73: =IFERROR(BZ53/$CE53,0) -> 0.10214388 | CA73: =IFERROR(CA53/$CE53,0) -> 0.078418294 | CB73: =IFERROR(CB53/$CE53,0) -> 0.14711768 | CC73: =IFERROR(CC53/$CE53,0) -> 0.1498809 | CD73: =IFERROR(CD53/$CE53,0) -> 0.096522153 | CE73: =SUM(BX73:CD73) -> 1
A74: 2014 | B74: =BE74 -> 0.36247639 | C74: =BF74 -> 0.098185085 | D74: =BG74 -> 0.074600396 | E74: =BH74 -> 0.11004652 | F74: =BI74 -> 0.11483716 | G74: =BD74 -> 0.1375927 | H74: =BJ74 -> 0.10226173 | I74: =BK74 -> 1 | K74: 2014 | L74: =L54/$T54 -> 0.13025248 | M74: =M54/$T54 -> 0.37121956 | N74: =N54/$T54 -> 0.11187439 | O74: =O54/$T54 -> 0.078151485 | P74: =P54/$T54 -> 0.10223927 | Q74: =Q54/$T54 -> 0.10513873 | R74: =R54/$T54 -> 0 | S74: =S54/$T54 -> 0.1011241 | T74: =T54/$T54 -> 1 | V74: 2014 | W74: =W54/$AE54 -> 0.15327302 | X74: =X54/$AE54 -> 0.31009402 | Y74: =Y54/$AE54 -> 0.10164981 | Z74: =Z54/$AE54 -> 0.068742239 | AA74: =AA54/$AE54 -> 0.132606 | AB74: =AB54/$AE54 -> 0.1320738 | AC74: =AC54/$AE54 -> 0 | AD74: =AD54/$AE54 -> 0.10156111 | AE74: =SUM(W74:AD74) -> 1 | AG74: 2014 | AH74: =AH54/$AP54 -> 0.13545627 | AI74: =AI54/$AP54 -> 0.40636882 | AJ74: =AJ54/$AP54 -> 0.022813688 | AK74: =AK54/$AP54 -> 0.071926489 | AL74: =AL54/$AP54 -> 0.1132763 | AM74: =AM54/$AP54 -> 0.13830798 | AN74: =AN54/$AP54 -> 0 | AO74: =AO54/$AP54 -> 0.11185044 | AP74: =SUM(AH74:AO74) -> 1 | AR74: 2014 | AS74: =AS54/$BA54 -> 0.13796134 | AT74: =AT54/$BA54 -> 0.39689514 | AU74: =AU54/$BA54 -> 0.13620387 | AV74: =AV54/$BA54 -> 0.075571178 | AW74: =AW54/$BA54 -> 0.080843585 | AX74: =AX54/$BA54 -> 0.078207381 | AY74: =AY54/$BA54 -> 0 | AZ74: =AZ54/$BA54 -> 0.094317516 | BA74: =SUM(AS74:AZ74) -> 1 | BC74: 2014 | BD74: =(L74*$T54+W74*$AE54+AH74*$AP54+AS74*$BA54)/$I54 -> 0.1375927 | BE74: =(M74*$T54+X74*$AE54+AI74*$AP54+AT74*$BA54)/$I54 -> 0.36247639 | BF74: =(N74*$T54+Y74*$AE54+AJ74*$AP54+AU74*$BA54)/$I54 -> 0.098185085 | BG74: =(O74*$T54+Z74*$AE54+AK74*$AP54+AV74*$BA54)/$I54 -> 0.074600396 | BH74: =(P74*$T54+AA74*$AE54+AL74*$AP54+AW74*$BA54)/$I54 -> 0.11004652 | BI74: =(Q74*$T54+AB74*$AE54+AM74*$AP54+AX74*$BA54)/$I54 -> 0.11483716 | BJ74: =((R74+S74)*$T54+(AC74+AD74)*$AE54+(AN74+AO74)*$AP54+(AZ74+AY74)*$BA54)/$I54 -> 0.10226173 | BK74: =SUM(BD74:BJ74) -> 1 | BM74: 2014 | BN74: =BN54/$BU54 -> 0.13209308 | BO74: =BO54/$BU54 -> 0.38084868 | BP74: =BP54/$BU54 -> 0.096969886 | BQ74: =BQ54/$BU54 -> 0.076655052 | BR74: =BR54/$BU54 -> 0.10213415 | BS74: =BS54/$BU54 -> 0.10879169 | BT74: =BT54/$BU54 -> 0.10250747 | BU74: =SUM(BN74:BT74) -> 1 | BW74: 2014 | BX74: =IFERROR(BX54/$CE54,0) -> 0.15327302 | BY74: =IFERROR(BY54/$CE54,0) -> 0.31009402 | BZ74: =IFERROR(BZ54/$CE54,0) -> 0.10164981 | CA74: =IFERROR(CA54/$CE54,0) -> 0.068742239 | CB74: =IFERROR(CB54/$CE54,0) -> 0.132606 | CC74: =IFERROR(CC54/$CE54,0) -> 0.1320738 | CD74: =IFERROR(CD54/$CE54,0) -> 0.10156111 | CE74: =SUM(BX74:CD74) -> 1
A75: 2015 | B75: =BE75 -> 0.36968324 | C75: =BF75 -> 0.10232262 | D75: =BG75 -> 0.067034886 | E75: =BH75 -> 0.09944295 | F75: =BI75 -> 0.10395128 | G75: =BD75 -> 0.14917623 | H75: =BJ75 -> 0.1083888 | I75: =BK75 -> 1 | K75: 2015 | L75: =L55/$T55 -> 0.1435155 | M75: =M55/$T55 -> 0.37454613 | N75: =N55/$T55 -> 0.11856438 | O75: =O55/$T55 -> 0.069825901 | P75: =P55/$T55 -> 0.091797784 | Q75: =Q55/$T55 -> 0.095289079 | R75: =R55/$T55 -> 0 | S75: =S55/$T55 -> 0.10646122 | T75: =T55/$T55 -> 1 | V75: 2015 | W75: =W55/$AE55 -> 0.16069972 | X75: =X55/$AE55 -> 0.3244811 | Y75: =Y55/$AE55 -> 0.098794526 | Z75: =Z55/$AE55 -> 0.062630291 | AA75: =AA55/$AE55 -> 0.12226955 | AB75: =AB55/$AE55 -> 0.12127255 | AC75: =AC55/$AE55 -> 0 | AD75: =AD55/$AE55 -> 0.10985226 | AE75: =SUM(W75:AD75) -> 1 | AG75: 2015 | AH75: =AH55/$AP55 -> 0.14140919 | AI75: =AI55/$AP55 -> 0.42586235 | AJ75: =AJ55/$AP55 -> 0.024685303 | AK75: =AK55/$AP55 -> 0.065391532 | AL75: =AL55/$AP55 -> 0.10331862 | AM75: =AM55/$AP55 -> 0.12391695 | AN75: =AN55/$AP55 -> 0 | AO75: =AO55/$AP55 -> 0.11541605 | AP75: =SUM(AH75:AO75) -> 1 | AR75: 2015 | AS75: =AS55/$BA55 -> 0.16041778 | AT75: =AT55/$BA55 -> 0.38323514 | AU75: =AU55/$BA55 -> 0.1464917 | AV75: =AV55/$BA55 -> 0.066684521 | AW75: =AW55/$BA55 -> 0.069630423 | AX75: =AX55/$BA55 -> 0.069898232 | AY75: =AY55/$BA55 -> 0 | AZ75: =AZ55/$BA55 -> 0.10364221 | BA75: =SUM(AS75:AZ75) -> 1 | BC75: 2015 | BD75: =(L75*$T55+W75*$AE55+AH75*$AP55+AS75*$BA55)/$I55 -> 0.14917623 | BE75: =(M75*$T55+X75*$AE55+AI75*$AP55+AT75*$BA55)/$I55 -> 0.36968324 | BF75: =(N75*$T55+Y75*$AE55+AJ75*$AP55+AU75*$BA55)/$I55 -> 0.10232262 | BG75: =(O75*$T55+Z75*$AE55+AK75*$AP55+AV75*$BA55)/$I55 -> 0.067034886 | BH75: =(P75*$T55+AA75*$AE55+AL75*$AP55+AW75*$BA55)/$I55 -> 0.09944295 | BI75: =(Q75*$T55+AB75*$AE55+AM75*$AP55+AX75*$BA55)/$I55 -> 0.10395128 | BJ75: =((R75+S75)*$T55+(AC75+AD75)*$AE55+(AN75+AO75)*$AP55+(AZ75+AY75)*$BA55)/$I55 -> 0.1083888 | BK75: =SUM(BD75:BJ75) -> 1 | BM75: 2015 | BN75: =BN55/$BU55 -> 0.14511857 | BO75: =BO55/$BU55 -> 0.38559985 | BP75: =BP55/$BU55 -> 0.10356493 | BQ75: =BQ55/$BU55 -> 0.068585836 | BR75: =BR55/$BU55 -> 0.091405228 | BS75: =BS55/$BU55 -> 0.097852105 | BT75: =BT55/$BU55 -> 0.10787349 | BU75: =SUM(BN75:BT75) -> 1 | BW75: 2015 | BX75: =IFERROR(BX55/$CE55,0) -> 0.16069972 | BY75: =IFERROR(BY55/$CE55,0) -> 0.3244811 | BZ75: =IFERROR(BZ55/$CE55,0) -> 0.098794526 | CA75: =IFERROR(CA55/$CE55,0) -> 0.062630291 | CB75: =IFERROR(CB55/$CE55,0) -> 0.12226955 | CC75: =IFERROR(CC55/$CE55,0) -> 0.12127255 | CD75: =IFERROR(CD55/$CE55,0) -> 0.10985226 | CE75: =SUM(BX75:CD75) -> 1
A76: 2016 | B76: =BE76 -> 0.37297648 | C76: =BF76 -> 0.11222691 | D76: =BG76 -> 0.059858992 | E76: =BH76 -> 0.08773598 | F76: =BI76 -> 0.093162948 | G76: =BD76 -> 0.16148708 | H76: =BJ76 -> 0.1125516 | I76: =BK76 -> 1 | K76: 2016 | L76: =L56/$T56 -> 0.15857866 | M76: =M56/$T56 -> 0.37294439 | N76: =N56/$T56 -> 0.13209661 | O76: =O56/$T56 -> 0.061791459 | P76: =P56/$T56 -> 0.080163104 | Q76: =Q56/$T56 -> 0.084823229 | R76: =R56/$T56 -> 0 | S76: =S56/$T56 -> 0.10960255 | T76: =T56/$T56 -> 1 | V76: 2016 | W76: =W56/$AE56 -> 0.16674153 | X76: =X56/$AE56 -> 0.33761567 | Y76: =Y56/$AE56 -> 0.10151828 | Z76: =Z56/$AE56 -> 0.056868206 | AA76: =AA56/$AE56 -> 0.11014284 | AB76: =AB56/$AE56 -> 0.11059204 | AC76: =AC56/$AE56 -> 0 | AD76: =AD56/$AE56 -> 0.11652143 | AE76: =SUM(W76:AD76) -> 1 | AG76: 2016 | AH76: =AH56/$AP56 -> 0.1479828 | AI76: =AI56/$AP56 -> 0.44246032 | AJ76: =AJ56/$AP56 -> 0.02827381 | AK76: =AK56/$AP56 -> 0.059358466 | AL76: =AL56/$AP56 -> 0.092592593 | AM76: =AM56/$AP56 -> 0.1114418 | AN76: =AN56/$AP56 -> 0 | AO76: =AO56/$AP56 -> 0.11789021 | AP76: =SUM(AH76:AO76) -> 1 | AR76: 2016 | AS76: =AS56/$BA56 -> 0.18580895 | AT76: =AT56/$BA56 -> 0.36581999 | AU76: =AU56/$BA56 -> 0.16289343 | AV76: =AV56/$BA56 -> 0.057979017 | AW76: =AW56/$BA56 -> 0.057426836 | AX76: =AX56/$BA56 -> 0.060463832 | AY76: =AY56/$BA56 -> 0 | AZ76: =AZ56/$BA56 -> 0.10960795 | BA76: =SUM(AS76:AZ76) -> 1 | BC76: 2016 | BD76: =(L76*$T56+W76*$AE56+AH76*$AP56+AS76*$BA56)/$I56 -> 0.16148708 | BE76: =(M76*$T56+X76*$AE56+AI76*$AP56+AT76*$BA56)/$I56 -> 0.37297648 | BF76: =(N76*$T56+Y76*$AE56+AJ76*$AP56+AU76*$BA56)/$I56 -> 0.11222691 | BG76: =(O76*$T56+Z76*$AE56+AK76*$AP56+AV76*$BA56)/$I56 -> 0.059858992 | BH76: =(P76*$T56+AA76*$AE56+AL76*$AP56+AW76*$BA56)/$I56 -> 0.08773598 | BI76: =(Q76*$T56+AB76*$AE56+AM76*$AP56+AX76*$BA56)/$I56 -> 0.093162948 | BJ76: =((R76+S76)*$T56+(AC76+AD76)*$AE56+(AN76+AO76)*$AP56+(AZ76+AY76)*$BA56)/$I56 -> 0.1125516 | BK76: =SUM(BD76:BJ76) -> 1 | BM76: 2016 | BN76: =BN56/$BU56 -> 0.15965861 | BO76: =BO56/$BU56 -> 0.38528152 | BP76: =BP56/$BU56 -> 0.11595336 | BQ76: =BQ56/$BU56 -> 0.060899741 | BR76: =BR56/$BU56 -> 0.079938725 | BS76: =BS56/$BU56 -> 0.087097884 | BT76: =BT56/$BU56 -> 0.11117016 | BU76: =SUM(BN76:BT76) -> 1 | BW76: 2016 | BX76: =IFERROR(BX56/$CE56,0) -> 0.16674153 | BY76: =IFERROR(BY56/$CE56,0) -> 0.33761567 | BZ76: =IFERROR(BZ56/$CE56,0) -> 0.10151828 | CA76: =IFERROR(CA56/$CE56,0) -> 0.056868206 | CB76: =IFERROR(CB56/$CE56,0) -> 0.11014284 | CC76: =IFERROR(CC56/$CE56,0) -> 0.11059204 | CD76: =IFERROR(CD56/$CE56,0) -> 0.11652143 | CE76: =SUM(BX76:CD76) -> 1
A77: 2017 | B77: =BE77 -> 0.37808323 | C77: =BF77 -> 0.11532892 | D77: =BG77 -> 0.054269639 | E77: =BH77 -> 0.076300358 | F77: =BI77 -> 0.082971298 | G77: =BD77 -> 0.1773378 | H77: =BJ77 -> 0.11570876 | I77: =BK77 -> 1 | K77: 2017 | L77: =L57/$T57 -> 0.17855846 | M77: =M57/$T57 -> 0.37227669 | N77: =N57/$T57 -> 0.13789034 | O77: =O57/$T57 -> 0.055374001 | P77: =P57/$T57 -> 0.069081336 | Q77: =Q57/$T57 -> 0.074981845 | R77: =R57/$T57 -> 0.064814815 | S77: =S57/$T57 -> 0.047022513 | T77: =T57/$T57 -> 1 | V77: 2017 | W77: =W57/$AE57 -> 0.17317708 | X77: =X57/$AE57 -> 0.35537574 | Y77: =Y57/$AE57 -> 0.097749256 | Z77: =Z57/$AE57 -> 0.053013393 | AA77: =AA57/$AE57 -> 0.097935268 | AB77: =AB57/$AE57 -> 0.10044643 | AC77: =AC57/$AE57 -> 0.07124256 | AD77: =AD57/$AE57 -> 0.051060268 | AE77: =SUM(W77:AD77) -> 1 | AG77: 2017 | AH77: =AH57/$AP57 -> 0.15477816 | AI77: =AI57/$AP57 -> 0.4612628 | AJ77: =AJ57/$AP57 -> 0.030375427 | AK77: =AK57/$AP57 -> 0.054266212 | AL77: =AL57/$AP57 -> 0.081399317 | AM77: =AM57/$AP57 -> 0.099317406 | AN77: =AN57/$AP57 -> 0.078668942 | AO77: =AO57/$AP57 -> 0.039931741 | AP77: =SUM(AH77:AO77) -> 1 | AR77: 2017 | AS77: =AS57/$BA57 -> 0.22046565 | AT77: =AT57/$BA57 -> 0.3449267 | AU77: =AU57/$BA57 -> 0.1698764 | AV77: =AV57/$BA57 -> 0.051164128 | AW77: =AW57/$BA57 -> 0.046565105 | AX77: =AX57/$BA57 -> 0.052026444 | AY77: =AY57/$BA57 -> 0.041391204 | AZ77: =AZ57/$BA57 -> 0.073584363 | BA77: =SUM(AS77:AZ77) -> 1 | BC77: 2017 | BD77: =(L77*$T57+W77*$AE57+AH77*$AP57+AS77*$BA57)/$I57 -> 0.1773378 | BE77: =(M77*$T57+X77*$AE57+AI77*$AP57+AT77*$BA57)/$I57 -> 0.37808323 | BF77: =(N77*$T57+Y77*$AE57+AJ77*$AP57+AU77*$BA57)/$I57 -> 0.11532892 | BG77: =(O77*$T57+Z77*$AE57+AK77*$AP57+AV77*$BA57)/$I57 -> 0.054269639 | BH77: =(P77*$T57+AA77*$AE57+AL77*$AP57+AW77*$BA57)/$I57 -> 0.076300358 | BI77: =(Q77*$T57+AB77*$AE57+AM77*$AP57+AX77*$BA57)/$I57 -> 0.082971298 | BJ77: =((R77+S77)*$T57+(AC77+AD77)*$AE57+(AN77+AO77)*$AP57+(AZ77+AY77)*$BA57)/$I57 -> 0.11570876 | BK77: =SUM(BD77:BJ77) -> 1 | BM77: 2017 | BN77: =BN57/$BU57 -> 0.17876383 | BO77: =BO57/$BU57 -> 0.38586593 | BP77: =BP57/$BU57 -> 0.12135412 | BQ77: =BQ57/$BU57 -> 0.054700201 | BR77: =BR57/$BU57 -> 0.068885276 | BS77: =BS57/$BU57 -> 0.076981926 | BT77: =BT57/$BU57 -> 0.11344873 | BU77: =SUM(BN77:BT77) -> 1 | BW77: 2017 | BX77: =IFERROR(BX57/$CE57,0) -> 0.17317708 | BY77: =IFERROR(BY57/$CE57,0) -> 0.35537574 | BZ77: =IFERROR(BZ57/$CE57,0) -> 0.097749256 | CA77: =IFERROR(CA57/$CE57,0) -> 0.053013393 | CB77: =IFERROR(CB57/$CE57,0) -> 0.097935268 | CC77: =IFERROR(CC57/$CE57,0) -> 0.10044643 | CD77: =IFERROR(CD57/$CE57,0) -> 0.12230283 | CE77: =SUM(BX77:CD77) -> 1
A78: 2018 | B78: =BE78 -> 0.37567915 | C78: =BF78 -> 0.11533696 | D78: =BG78 -> 0.054475265 | E78: =BH78 -> 0.076517968 | F78: =BI78 -> 0.083142694 | G78: =BD78 -> 0.17858164 | H78: =BJ78 -> 0.11626632 | I78: =BK78 -> 1 | K78: 2018 | L78: =L58/$T58 -> 0.17942429 | M78: =M58/$T58 -> 0.37023325 | N78: =N58/$T58 -> 0.13749537 | O78: =O58/$T58 -> 0.055627545 | P78: =P58/$T58 -> 0.069511292 | Q78: =Q58/$T58 -> 0.075342466 | R78: =R58/$T58 -> 0.065114772 | S78: =S58/$T58 -> 0.047251018 | T78: =T58/$T58 -> 1 | V78: 2018 | W78: =W58/$AE58 -> 0.17393343 | X78: =X58/$AE58 -> 0.35321144 | Y78: =Y58/$AE58 -> 0.097421472 | Z78: =Z58/$AE58 -> 0.053258322 | AA78: =AA58/$AE58 -> 0.098452883 | AB78: =AB58/$AE58 -> 0.10089076 | AC78: =AC58/$AE58 -> 0.071542429 | AD78: =AD58/$AE58 -> 0.051289264 | AE78: =SUM(W78:AD78) -> 1 | AG78: 2018 | AH78: =AH58/$AP58 -> 0.15555936 | AI78: =AI58/$AP58 -> 0.45879733 | AJ78: =AJ58/$AP58 -> 0.030323796 | AK78: =AK58/$AP58 -> 0.054480041 | AL78: =AL58/$AP58 -> 0.081891383 | AM78: =AM58/$AP58 -> 0.099880075 | AN78: =AN58/$AP58 -> 0.078978928 | AO78: =AO58/$AP58 -> 0.040089087 | AP78: =SUM(AH78:AO78) -> 1 | AR78: 2018 | AS78: =AS58/$BA58 -> 0.22158796 | AT78: =AT58/$BA58 -> 0.3425013 | AU78: =AU58/$BA58 -> 0.16943435 | AV78: =AV58/$BA58 -> 0.051375195 | AW78: =AW58/$BA58 -> 0.046964193 | AX78: =AX58/$BA58 -> 0.052413077 | AY78: =AY58/$BA58 -> 0.041774779 | AZ78: =AZ58/$BA58 -> 0.073949144 | BA78: =SUM(AS78:AZ78) -> 1 | BC78: 2018 | BD78: =(L78*$T58+W78*$AE58+AH78*$AP58+AS78*$BA58)/$I58 -> 0.17858164 | BE78: =(M78*$T58+X78*$AE58+AI78*$AP58+AT78*$BA58)/$I58 -> 0.37567915 | BF78: =(N78*$T58+Y78*$AE58+AJ78*$AP58+AU78*$BA58)/$I58 -> 0.11533696 | BG78: =(O78*$T58+Z78*$AE58+AK78*$AP58+AV78*$BA58)/$I58 -> 0.054475265 | BH78: =(P78*$T58+AA78*$AE58+AL78*$AP58+AW78*$BA58)/$I58 -> 0.076517968 | BI78: =(Q78*$T58+AB78*$AE58+AM78*$AP58+AX78*$BA58)/$I58 -> 0.083142694 | BJ78: =((R78+S78)*$T58+(AC78+AD78)*$AE58+(AN78+AO78)*$AP58+(AZ78+AY78)*$BA58)/$I58 -> 0.11626632 | BK78: =SUM(BD78:BJ78) -> 1 | BM78: 2018 | BN78: =BN58/$BU58 -> 0.1801655 | BO78: =BO58/$BU58 -> 0.38333493 | BP78: =BP58/$BU58 -> 0.12144158 | BQ78: =BQ58/$BU58 -> 0.054889933 | BR78: =BR58/$BU58 -> 0.069043739 | BS78: =BS58/$BU58 -> 0.077095115 | BT78: =BT58/$BU58 -> 0.1140292 | BU78: =SUM(BN78:BT78) -> 1 | BW78: 2018 | BX78: =IFERROR(BX58/$CE58,0) -> 0.17393343 | BY78: =IFERROR(BY58/$CE58,0) -> 0.35321144 | BZ78: =IFERROR(BZ58/$CE58,0) -> 0.097421472 | CA78: =IFERROR(CA58/$CE58,0) -> 0.053258322 | CB78: =IFERROR(CB58/$CE58,0) -> 0.098452883 | CC78: =IFERROR(CC58/$CE58,0) -> 0.10089076 | CD78: =IFERROR(CD58/$CE58,0) -> 0.12283169 | CE78: =SUM(BX78:CD78) -> 1
A79: 2019 | B79: =BE79 -> 0.37527075 | C79: =BF79 -> 0.1115588 | D79: =BG79 -> 0.05482451 | E79: =BH79 -> 0.077997997 | F79: =BI79 -> 0.083704031 | G79: =BD79 -> 0.17961199 | H79: =BJ79 -> 0.11703193 | I79: =BK79 -> 1 | K79: 2019 | L79: =L59/$T59 -> 0.18056559 | M79: =M59/$T59 -> 0.37057282 | N79: =N59/$T59 -> 0.1332219 | O79: =O59/$T59 -> 0.055972172 | P79: =P59/$T59 -> 0.070789664 | Q79: =Q59/$T59 -> 0.07580412 | R79: =R59/$T59 -> 0.065504156 | S79: =S59/$T59 -> 0.04756957 | T79: =T59/$T59 -> 1 | V79: 2019 | W79: =W59/$AE59 -> 0.17519522 | X79: =X59/$AE59 -> 0.35084979 | Y79: =Y59/$AE59 -> 0.094441893 | Z79: =Z59/$AE59 -> 0.053651814 | AA79: =AA59/$AE59 -> 0.10041341 | AB79: =AB59/$AE59 -> 0.10160772 | AC79: =AC59/$AE59 -> 0.072117593 | AD79: =AD59/$AE59 -> 0.051722554 | AE79: =SUM(W79:AD79) -> 1 | AG79: 2019 | AH79: =AH59/$AP59 -> 0.15581204 | AI79: =AI59/$AP59 -> 0.45803792 | AJ79: =AJ59/$AP59 -> 0.029183842 | AK79: =AK59/$AP59 -> 0.054575433 | AL79: =AL59/$AP59 -> 0.083099753 | AM79: =AM59/$AP59 -> 0.09991756 | AN79: =AN59/$AP59 -> 0.079142622 | AO79: =AO59/$AP59 -> 0.040230833 | AP79: =SUM(AH79:AO79) -> 1 | AR79: 2019 | AS79: =AS59/$BA59 -> 0.22409764 | AT79: =AT59/$BA59 -> 0.3409504 | AU79: =AU59/$BA59 -> 0.16515191 | AV79: =AV59/$BA59 -> 0.051934562 | AW79: =AW59/$BA59 -> 0.04803947 | AX79: =AX59/$BA59 -> 0.052973254 | AY79: =AY59/$BA59 -> 0.042066996 | AZ79: =AZ59/$BA59 -> 0.07478577 | BA79: =SUM(AS79:AZ79) -> 1 | BC79: 2019 | BD79: =(L79*$T59+W79*$AE59+AH79*$AP59+AS79*$BA59)/$I59 -> 0.17961199 | BE79: =(M79*$T59+X79*$AE59+AI79*$AP59+AT79*$BA59)/$I59 -> 0.37527075 | BF79: =(N79*$T59+Y79*$AE59+AJ79*$AP59+AU79*$BA59)/$I59 -> 0.1115588 | BG79: =(O79*$T59+Z79*$AE59+AK79*$AP59+AV79*$BA59)/$I59 -> 0.05482451 | BH79: =(P79*$T59+AA79*$AE59+AL79*$AP59+AW79*$BA59)/$I59 -> 0.077997997 | BI79: =(Q79*$T59+AB79*$AE59+AM79*$AP59+AX79*$BA59)/$I59 -> 0.083704031 | BJ79: =((R79+S79)*$T59+(AC79+AD79)*$AE59+(AN79+AO79)*$AP59+(AZ79+AY79)*$BA59)/$I59 -> 0.11703193 | BK79: =SUM(BD79:BJ79) -> 1 | BM79: 2019 | BN79: =BN59/$BU59 -> 0.18111194 | BO79: =BO59/$BU59 -> 0.38356421 | BP79: =BP59/$BU59 -> 0.11737177 | BQ79: =BQ59/$BU59 -> 0.055222763 | BR79: =BR59/$BU59 -> 0.070385623 | BS79: =BS59/$BU59 -> 0.077623861 | BT79: =BT59/$BU59 -> 0.11471983 | BU79: =SUM(BN79:BT79) -> 1 | BW79: 2019 | BX79: =IFERROR(BX59/$CE59,0) -> 0.17519522 | BY79: =IFERROR(BY59/$CE59,0) -> 0.35084979 | BZ79: =IFERROR(BZ59/$CE59,0) -> 0.094441893 | CA79: =IFERROR(CA59/$CE59,0) -> 0.053651814 | CB79: =IFERROR(CB59/$CE59,0) -> 0.10041341 | CC79: =IFERROR(CC59/$CE59,0) -> 0.10160772 | CD79: =IFERROR(CD59/$CE59,0) -> 0.12384015 | CE79: =SUM(BX79:CD79) -> 1
A80: 2020 | B80: =BE80 -> 0.38858894 | C80: =BF80 -> 0.10997558 | D80: =BG80 -> 0.053584437 | E80: =BH80 -> 0.076059476 | F80: =BI80 -> 0.081822856 | G80: =BD80 -> 0.17555813 | H80: =BJ80 -> 0.11441059 | I80: =BK80 -> 1 | K80: 2020 | L80: =L60/$T60 -> 0.17658524 | M80: =M60/$T60 -> 0.38348609 | N80: =N60/$T60 -> 0.13138141 | O80: =O60/$T60 -> 0.054742255 | P80: =P60/$T60 -> 0.069091362 | Q80: =Q60/$T60 -> 0.074150873 | R80: =R60/$T60 -> 0.064073321 | S80: =S60/$T60 -> 0.046489446 | T80: =T60/$T60 -> 1 | V80: 2020 | W80: =W60/$AE60 -> 0.1714869 | X80: =X60/$AE60 -> 0.36406941 | Y80: =Y60/$AE60 -> 0.093228989 | Z80: =Z60/$AE60 -> 0.052483838 | AA80: =AA60/$AE60 -> 0.098077577 | AB80: =AB60/$AE60 -> 0.099438585 | AC80: =AC60/$AE60 -> 0.070602246 | AD80: =AD60/$AE60 -> 0.050612453 | AE80: =SUM(W80:AD80) -> 1 | AG80: 2020 | AH80: =AH60/$AP60 -> 0.15171166 | AI80: =AI60/$AP60 -> 0.47217614 | AJ80: =AJ60/$AP60 -> 0.028653295 | AK80: =AK60/$AP60 -> 0.053083999 | AL80: =AL60/$AP60 -> 0.080681647 | AM80: =AM60/$AP60 -> 0.097421203 | AN80: =AN60/$AP60 -> 0.077062283 | AO80: =AO60/$AP60 -> 0.039209772 | AP80: =SUM(AH80:AO80) -> 1 | AR80: 2020 | AS80: =AS60/$BA60 -> 0.2189746 | AT80: =AT60/$BA60 -> 0.35433637 | AU80: =AU60/$BA60 -> 0.16267369 | AV80: =AV60/$BA60 -> 0.050790609 | AW80: =AW60/$BA60 -> 0.046957355 | AX80: =AX60/$BA60 -> 0.051748922 | AY80: =AY60/$BA60 -> 0.041207475 | AZ80: =AZ60/$BA60 -> 0.073310973 | BA80: =SUM(AS80:AZ80) -> 1 | BC80: 2020 | BD80: =(L80*$T60+W80*$AE60+AH80*$AP60+AS80*$BA60)/$I60 -> 0.17555813 | BE80: =(M80*$T60+X80*$AE60+AI80*$AP60+AT80*$BA60)/$I60 -> 0.38858894 | BF80: =(N80*$T60+Y80*$AE60+AJ80*$AP60+AU80*$BA60)/$I60 -> 0.10997558 | BG80: =(O80*$T60+Z80*$AE60+AK80*$AP60+AV80*$BA60)/$I60 -> 0.053584437 | BH80: =(P80*$T60+AA80*$AE60+AL80*$AP60+AW80*$BA60)/$I60 -> 0.076059476 | BI80: =(Q80*$T60+AB80*$AE60+AM80*$AP60+AX80*$BA60)/$I60 -> 0.081822856 | BJ80: =((R80+S80)*$T60+(AC80+AD80)*$AE60+(AN80+AO80)*$AP60+(AZ80+AY80)*$BA60)/$I60 -> 0.11441059 | BK80: =SUM(BD80:BJ80) -> 1 | BM80: 2020 | BN80: =BN60/$BU60 -> 0.1769288 | BO80: =BO60/$BU60 -> 0.39684403 | BP80: =BP60/$BU60 -> 0.11561372 | BQ80: =BQ60/$BU60 -> 0.05395498 | BR80: =BR60/$BU60 -> 0.068646543 | BS80: =BS60/$BU60 -> 0.07589209 | BT80: =BT60/$BU60 -> 0.11211982 | BU80: =SUM(BN80:BT80) -> 1 | BW80: 2020 | BX80: =IFERROR(BX60/$CE60,0) -> 0.1714869 | BY80: =IFERROR(BY60/$CE60,0) -> 0.36406941 | BZ80: =IFERROR(BZ60/$CE60,0) -> 0.093228989 | CA80: =IFERROR(CA60/$CE60,0) -> 0.052483838 | CB80: =IFERROR(CB60/$CE60,0) -> 0.098077577 | CC80: =IFERROR(CC60/$CE60,0) -> 0.099438585 | CD80: =IFERROR(CD60/$CE60,0) -> 0.1212147 | CE80: =SUM(BX80:CD80) -> 1
A81: 2021 | B81: =BE81 -> 0.3939113 | C81: =BF81 -> 0.10742652 | D81: =BG81 -> 0.053218161 | E81: =BH81 -> 0.075908564 | F81: =BI81 -> 0.081217739 | G81: =BD81 -> 0.17463394 | H81: =BJ81 -> 0.11368377 | I81: =BK81 -> 1 | K81: 2021 | L81: =L61/$T61 -> 0.17542539 | M81: =M61/$T61 -> 0.38918851 | N81: =N61/$T61 -> 0.12847527 | O81: =O61/$T61 -> 0.054391906 | P81: =P61/$T61 -> 0.069024625 | Q81: =Q61/$T61 -> 0.073665287 | R81: =R61/$T61 -> 0.063631423 | S81: =S61/$T61 -> 0.046197584 | T81: =T61/$T61 -> 1 | V81: 2021 | W81: =W61/$AE61 -> 0.17046679 | X81: =X61/$AE61 -> 0.36862615 | Y81: =Y61/$AE61 -> 0.091203051 | Z81: =Z61/$AE61 -> 0.052234475 | AA81: =AA61/$AE61 -> 0.098084736 | AB81: =AB61/$AE61 -> 0.098913855 | AC81: =AC61/$AE61 -> 0.070143438 | AD81: =AD61/$AE61 -> 0.050327502 | AE81: =SUM(W81:AD81) -> 1 | AG81: 2021 | AH81: =AH61/$AP61 -> 0.15007991 | AI81: =AI61/$AP61 -> 0.47769868 | AJ81: =AJ61/$AP61 -> 0.027894813 | AK81: =AK61/$AP61 -> 0.052593346 | AL81: =AL61/$AP61 -> 0.080342874 | AM81: =AM61/$AP61 -> 0.096324277 | AN81: =AN61/$AP61 -> 0.07627488 | AO81: =AO61/$AP61 -> 0.038791225 | AP81: =SUM(AH81:AO81) -> 1 | AR81: 2021 | AS81: =AS61/$BA61 -> 0.21816601 | AT81: =AT61/$BA61 -> 0.35940895 | AU81: =AU61/$BA61 -> 0.15949587 | AV81: =AV61/$BA61 -> 0.050630161 | AW81: =AW61/$BA61 -> 0.046936115 | AX81: =AX61/$BA61 -> 0.051499348 | AY81: =AY61/$BA61 -> 0.0410691 | AZ81: =AZ61/$BA61 -> 0.072794437 | BA81: =SUM(AS81:AZ81) -> 1 | BC81: 2021 | BD81: =(L81*$T61+W81*$AE61+AH81*$AP61+AS81*$BA61)/$I61 -> 0.17463394 | BE81: =(M81*$T61+X81*$AE61+AI81*$AP61+AT81*$BA61)/$I61 -> 0.3939113 | BF81: =(N81*$T61+Y81*$AE61+AJ81*$AP61+AU81*$BA61)/$I61 -> 0.10742652 | BG81: =(O81*$T61+Z81*$AE61+AK81*$AP61+AV81*$BA61)/$I61 -> 0.053218161 | BH81: =(P81*$T61+AA81*$AE61+AL81*$AP61+AW81*$BA61)/$I61 -> 0.075908564 | BI81: =(Q81*$T61+AB81*$AE61+AM81*$AP61+AX81*$BA61)/$I61 -> 0.081217739 | BJ81: =((R81+S81)*$T61+(AC81+AD81)*$AE61+(AN81+AO81)*$AP61+(AZ81+AY81)*$BA61)/$I61 -> 0.11368377 | BK81: =SUM(BD81:BJ81) -> 1 | BM81: 2021 | BN81: =BN61/$BU61 -> 0.17605355 | BO81: =BO61/$BU61 -> 0.40252514 | BP81: =BP61/$BU61 -> 0.11295334 | BQ81: =BQ61/$BU61 -> 0.053553271 | BR81: =BR61/$BU61 -> 0.068353858 | BS81: =BS61/$BU61 -> 0.075189244 | BT81: =BT61/$BU61 -> 0.1113716 | BU81: =SUM(BN81:BT81) -> 1 | BW81: 2021 | BX81: =IFERROR(BX61/$CE61,0) -> 0.17046679 | BY81: =IFERROR(BY61/$CE61,0) -> 0.36862615 | BZ81: =IFERROR(BZ61/$CE61,0) -> 0.091203051 | CA81: =IFERROR(CA61/$CE61,0) -> 0.052234475 | CB81: =IFERROR(CB61/$CE61,0) -> 0.098084736 | CC81: =IFERROR(CC61/$CE61,0) -> 0.098913855 | CD81: =IFERROR(CD61/$CE61,0) -> 0.12047094 | CE81: =SUM(BX81:CD81) -> 1
A83: Non-Electricity Energy
A84: Solve first-order equation by using data above(total energy, electricity)
A85: Method: for a certain category(e.g. air conditioning), assuming the fraction of non-elec energy consumption of this category, is x
G86: Because the total energy consumption in the air-conditioning category in 2005 can be expressed in two ways in the following equation, we can solve the value of X:
G87: 23%*Total energy consumption of private/public house=34%*electricity consumption of private/public house+x*non-elec energy consumption of private/public house
G88: So x=((23%*Total energy consumption of private/public house)-(4%*electricity consumption of private/public house))/(Total Energy-Total Electricity)
A89: 所有住宅All Residential | K89: 私人住宅Private Housing Segment | V89: 公共住宅 Public Housing | AG89: 房委会资助出售单位组别 Housing Authority Subsidized Sale Flats Segment | AR89: Total Energy Consumption in Other Housing Segment by End-use | BC89: 重新加总Private+Public | BM89: Private = Urban defination in the EPS | BW89: Public = Rural defination in the EPS
A90: 年份 Year | B90: 空氣調節 Air Conditioning | C90: 熱水 Hot Water | D90: 照明 Lighting | E90: 冷凍 Refrigeration | F90: 辦公室設備 Office Equipment | G90: 煮食 Cooking | H90: 其他 1 Others 1 | I90: 總計 Total | K90: 年份 Year | L90: Cooking (Unit : Terajoule) | M90: Air Conditioning (Unit : Terajoule) | N90: Hot Water (Unit : Terajoule) | O90: Lighting (Unit : Terajoule) | P90: Refrigeration (Unit : Terajoule) | Q90: Office Equipment (Unit : Terajoule) | R90: Laundry (Unit : Terajoule) | S90: Others (Unit : Terajoule) | T90: 總計 Total | V90: 年份 Year | W90: Cooking (Unit : Terajoule) | X90: Air Conditioning (Unit : Terajoule) | Y90: Hot Water (Unit : Terajoule) | Z90: Lighting (Unit : Terajoule) | AA90: Refrigeration (Unit : Terajoule) | AB90: Office Equipment (Unit : Terajoule) | AC90: Laundry (Unit : Terajoule) | AD90: Others (Unit : Terajoule) | AE90: 總計 Total | AG90: 年份 Year | AH90: Cooking (Unit : Terajoule) | AI90: Air Conditioning (Unit : Terajoule) | AJ90: Hot Water (Unit : Terajoule) | AK90: Lighting (Unit : Terajoule) | AL90: Refrigeration (Unit : Terajoule) | AM90: Office Equipment (Unit : Terajoule) | AN90: Laundry (Unit : Terajoule) | AO90: Others (Unit : Terajoule) | AP90: 總計 Total | AR90: Year | AS90: Cooking (Unit : Terajoule) | AT90: Air Conditioning (Unit : Terajoule) | AU90: Hot Water (Unit : Terajoule) | AV90: Lighting (Unit : Terajoule) | AW90: Refrigeration (Unit : Terajoule) | AX90: Office Equipment (Unit : Terajoule) | AY90: Laundry (Unit : Terajoule) | AZ90: Others (Unit : Terajoule) | BA90: 總計 Total | BC90: 年份 Year | BD90: 煮食 Cooking | BE90: 空氣調節 Air Conditioning | BF90: 熱水 Hot Water | BG90: 照明 Lighting | BH90: 冷凍 Refrigeration | BI90: 辦公室設備 Office Equipment | BJ90: 其他 1 Others 1 | BK90: 總計 Total | BM90: 年份 Year | BN90: 煮食 Cooking | BO90: 空氣調節 Air Conditioning | BP90: 熱水 Hot Water | BQ90: 照明 Lighting | BR90: 冷凍 Refrigeration | BS90: 辦公室設備 Office Equipment | BT90: 其他 1 Others 1 | BU90: 總計 Total | BW90: 年份 Year | BX90: 煮食 Cooking | BY90: 空氣調節 Air Conditioning | BZ90: 熱水 Hot Water | CA90: 照明 Lighting | CB90: 冷凍 Refrigeration | CC90: 辦公室設備 Office Equipment | CD90: 其他 1 Others 1 | CE90: 總計 Total
A91: 2006 | B91: =B6-B46 -> 0 | C91: =C6-C46 -> 9000 | D91: =D6-D46 -> 0 | E91: =E6-E46 -> 0 | F91: =F6-F46 -> 0 | G91: =G6-G46 -> 12653 | H91: =H6-H46 -> 74 | I91: =SUM(C91:H91) -> 21727 | K91: 2006 | L91: =L6-L46 -> 5236 | M91: =M6-M46 -> 0 | N91: =N6-N46 -> 2951 | O91: =O6-O46 -> 0 | P91: =P6-P46 -> 0 | Q91: =Q6-Q46 -> 0 | R91: =R6-R46 -> 0 | S91: =S6-S46 -> 8 | T91: =SUM(L91:S91) -> 8195 | V91: 2006 | W91: =W6-W46 -> 5500 | X91: =X6-X46 -> 0 | Y91: =Y6-Y46 -> 4244 | Z91: =Z6-Z46 -> 0 | AA91: =AA6-AA46 -> 0 | AB91: =AB6-AB46 -> 0 | AC91: =AC6-AC46 -> 0 | AD91: =AD6-AD46 -> 45 | AE91: =SUM(W91:AD91) -> 9789 | AG91: 2006 | AH91: =AH6-AH46 -> 1917 | AI91: =AI6-AI46 -> 0 | AJ91: =AJ6-AJ46 -> 1805 | AK91: =AK6-AK46 -> 0 | AL91: =AL6-AL46 -> 0 | AM91: =AM6-AM46 -> 0 | AN91: =AN6-AN46 -> 0 | AO91: =AO6-AO46 -> 21 | AP91: =SUM(AH91:AO91) -> 3743 | AR91: 2006 | AS91: =AS6-AS46 -> 0 | AT91: =AT6-AT46 -> 0 | AU91: =AU6-AU46 -> 0 | AV91: =AV6-AV46 -> 0 | AW91: =AW6-AW46 -> 0 | AX91: =AX6-AX46 -> 0 | AY91: =AY6-AY46 -> 0 | AZ91: =AZ6-AZ46 -> 0 | BA91: 0 | BC91: 2006 | BD91: =L91+W91+AH91+AS91 -> 12653 | BE91: =M91+X91+AI91+AT91 -> 0 | BF91: =N91+Y91+AJ91+AU91 -> 9000 | BG91: =O91+Z91+AK91+AV91 -> 0 | BH91: =P91+AA91+AL91+AW91 -> 0 | BI91: =Q91+AB91+AM91+AX91 -> 0 | BJ91: =R91+AC91+AN91+AY91+S91+AD91+AO91+AZ91 -> 74 | BK91: =SUM(BD91:BJ91) -> 21727 | BM91: 2006 | BN91: =L91+AH91+AS91 -> 7153 | BO91: =M91+AI91+AT91 -> 0 | BP91: =N91+AJ91+AU91 -> 4756 | BQ91: =O91+AK91+AV91 -> 0 | BR91: =P91+AL91+AW91 -> 0 | BS91: =Q91+AM91+AX91 -> 0 | BT91: =R91+AY91+AN91+S91+AZ91+AO91 -> 29 | BU91: =SUM(BN91:BT91) -> 11938 | BW91: 2006 | BX91: =W91 -> 5500 | BY91: =X91 -> 0 | BZ91: =Y91 -> 4244 | CA91: =Z91 -> 0 | CB91: =AA91 -> 0 | CC91: =AB91 -> 0 | CD91: =AC91+AD91 -> 45 | CE91: =SUM(BX91:CD91) -> 9789
A92: 2007 | B92: =B7-B47 -> 0 | C92: =C7-C47 -> 8579 | D92: =D7-D47 -> 0 | E92: =E7-E47 -> 0 | F92: =F7-F47 -> 0 | G92: =G7-G47 -> 12752 | H92: =H7-H47 -> 77 | I92: =SUM(C92:H92) -> 21408 | K92: 2007 | L92: =L7-L47 -> 5276 | M92: =M7-M47 -> 0 | N92: =N7-N47 -> 2833 | O92: =O7-O47 -> 0 | P92: =P7-P47 -> 0 | Q92: =Q7-Q47 -> 0 | R92: =R7-R47 -> 0 | S92: =S7-S47 -> 9 | T92: =SUM(L92:S92) -> 8118 | V92: 2007 | W92: =W7-W47 -> 5514 | X92: =X7-X47 -> 0 | Y92: =Y7-Y47 -> 4037 | Z92: =Z7-Z47 -> 0 | AA92: =AA7-AA47 -> 0 | AB92: =AB7-AB47 -> 0 | AC92: =AC7-AC47 -> 0 | AD92: =AD7-AD47 -> 47 | AE92: =SUM(W92:AD92) -> 9598 | AG92: 2007 | AH92: =AH7-AH47 -> 1962 | AI92: =AI7-AI47 -> 0 | AJ92: =AJ7-AJ47 -> 1709 | AK92: =AK7-AK47 -> 0 | AL92: =AL7-AL47 -> 0 | AM92: =AM7-AM47 -> 0 | AN92: =AN7-AN47 -> 0 | AO92: =AO7-AO47 -> 21 | AP92: =SUM(AH92:AO92) -> 3692 | AR92: 2007 | AS92: =AS7-AS47 -> 0 | AT92: =AT7-AT47 -> 0 | AU92: =AU7-AU47 -> 0 | AV92: =AV7-AV47 -> 0 | AW92: =AW7-AW47 -> 0 | AX92: =AX7-AX47 -> 0 | AY92: =AY7-AY47 -> 0 | AZ92: =AZ7-AZ47 -> 0 | BA92: 0 | BC92: 2007 | BD92: =L92+W92+AH92+AS92 -> 12752 | BE92: =M92+X92+AI92+AT92 -> 0 | BF92: =N92+Y92+AJ92+AU92 -> 8579 | BG92: =O92+Z92+AK92+AV92 -> 0 | BH92: =P92+AA92+AL92+AW92 -> 0 | BI92: =Q92+AB92+AM92+AX92 -> 0 | BJ92: =R92+AC92+AN92+AY92+S92+AD92+AO92+AZ92 -> 77 | BK92: =SUM(BD92:BJ92) -> 21408 | BM92: 2007 | BN92: =L92+AH92+AS92 -> 7238 | BO92: =M92+AI92+AT92 -> 0 | BP92: =N92+AJ92+AU92 -> 4542 | BQ92: =O92+AK92+AV92 -> 0 | BR92: =P92+AL92+AW92 -> 0 | BS92: =Q92+AM92+AX92 -> 0 | BT92: =R92+AY92+AN92+S92+AZ92+AO92 -> 30 | BU92: =SUM(BN92:BT92) -> 11810 | BW92: 2007 | BX92: =W92 -> 5514 | BY92: =X92 -> 0 | BZ92: =Y92 -> 4037 | CA92: =Z92 -> 0 | CB92: =AA92 -> 0 | CC92: =AB92 -> 0 | CD92: =AC92+AD92 -> 47 | CE92: =SUM(BX92:CD92) -> 9598
A93: 2008 | B93: =B8-B48 -> 0 | C93: =C8-C48 -> 8625 | D93: =D8-D48 -> 0 | E93: =E8-E48 -> 0 | F93: =F8-F48 -> 0 | G93: =G8-G48 -> 13373 | H93: =H8-H48 -> 85 | I93: =SUM(C93:H93) -> 22083 | K93: 2008 | L93: =L8-L48 -> 5522 | M93: =M8-M48 -> 0 | N93: =N8-N48 -> 2892 | O93: =O8-O48 -> 0 | P93: =P8-P48 -> 0 | Q93: =Q8-Q48 -> 0 | R93: =R8-R48 -> 0 | S93: =S8-S48 -> 10 | T93: =SUM(L93:S93) -> 8424 | V93: 2008 | W93: =W8-W48 -> 5728 | X93: =X8-X48 -> 0 | Y93: =Y8-Y48 -> 4018 | Z93: =Z8-Z48 -> 0 | AA93: =AA8-AA48 -> 0 | AB93: =AB8-AB48 -> 0 | AC93: =AC8-AC48 -> 0 | AD93: =AD8-AD48 -> 52 | AE93: =SUM(W93:AD93) -> 9798 | AG93: 2008 | AH93: =AH8-AH48 -> 2123 | AI93: =AI8-AI48 -> 0 | AJ93: =AJ8-AJ48 -> 1715 | AK93: =AK8-AK48 -> 0 | AL93: =AL8-AL48 -> 0 | AM93: =AM8-AM48 -> 0 | AN93: =AN8-AN48 -> 0 | AO93: =AO8-AO48 -> 23 | AP93: =SUM(AH93:AO93) -> 3861 | AR93: 2008 | AS93: =AS8-AS48 -> 0 | AT93: =AT8-AT48 -> 0 | AU93: =AU8-AU48 -> 0 | AV93: =AV8-AV48 -> 0 | AW93: =AW8-AW48 -> 0 | AX93: =AX8-AX48 -> 0 | AY93: =AY8-AY48 -> 0 | AZ93: =AZ8-AZ48 -> 0 | BA93: 0 | BC93: 2008 | BD93: =L93+W93+AH93+AS93 -> 13373 | BE93: =M93+X93+AI93+AT93 -> 0 | BF93: =N93+Y93+AJ93+AU93 -> 8625 | BG93: =O93+Z93+AK93+AV93 -> 0 | BH93: =P93+AA93+AL93+AW93 -> 0 | BI93: =Q93+AB93+AM93+AX93 -> 0 | BJ93: =R93+AC93+AN93+AY93+S93+AD93+AO93+AZ93 -> 85 | BK93: =SUM(BD93:BJ93) -> 22083 | BM93: 2008 | BN93: =L93+AH93+AS93 -> 7645 | BO93: =M93+AI93+AT93 -> 0 | BP93: =N93+AJ93+AU93 -> 4607 | BQ93: =O93+AK93+AV93 -> 0 | BR93: =P93+AL93+AW93 -> 0 | BS93: =Q93+AM93+AX93 -> 0 | BT93: =R93+AY93+AN93+S93+AZ93+AO93 -> 33 | BU93: =SUM(BN93:BT93) -> 12285 | BW93: 2008 | BX93: =W93 -> 5728 | BY93: =X93 -> 0 | BZ93: =Y93 -> 4018 | CA93: =Z93 -> 0 | CB93: =AA93 -> 0 | CC93: =AB93 -> 0 | CD93: =AC93+AD93 -> 52 | CE93: =SUM(BX93:CD93) -> 9798
A94: 2009 | B94: =B9-B49 -> 0 | C94: =C9-C49 -> 8769 | D94: =D9-D49 -> 0 | E94: =E9-E49 -> 0 | F94: =F9-F49 -> 0 | G94: =G9-G49 -> 13124 | H94: =H9-H49 -> 69 | I94: =SUM(C94:H94) -> 21962 | K94: 2009 | L94: =L9-L49 -> 5425 | M94: =M9-M49 -> 0 | N94: =N9-N49 -> 2955 | O94: =O9-O49 -> 0 | P94: =P9-P49 -> 0 | Q94: =Q9-Q49 -> 0 | R94: =R9-R49 -> 0 | S94: =S9-S49 -> 6 | T94: =SUM(L94:S94) -> 8386 | V94: 2009 | W94: =W9-W49 -> 5647 | X94: =X9-X49 -> 0 | Y94: =Y9-Y49 -> 4064 | Z94: =Z9-Z49 -> 0 | AA94: =AA9-AA49 -> 0 | AB94: =AB9-AB49 -> 0 | AC94: =AC9-AC49 -> 0 | AD94: =AD9-AD49 -> 45 | AE94: =SUM(W94:AD94) -> 9756 | AG94: 2009 | AH94: =AH9-AH49 -> 2052 | AI94: =AI9-AI49 -> 0 | AJ94: =AJ9-AJ49 -> 1750 | AK94: =AK9-AK49 -> 0 | AL94: =AL9-AL49 -> 0 | AM94: =AM9-AM49 -> 0 | AN94: =AN9-AN49 -> 0 | AO94: =AO9-AO49 -> 18 | AP94: =SUM(AH94:AO94) -> 3820 | AR94: 2009 | AS94: =AS9-AS49 -> 0 | AT94: =AT9-AT49 -> 0 | AU94: =AU9-AU49 -> 0 | AV94: =AV9-AV49 -> 0 | AW94: =AW9-AW49 -> 0 | AX94: =AX9-AX49 -> 0 | AY94: =AY9-AY49 -> 0 | AZ94: =AZ9-AZ49 -> 0 | BA94: 0 | BC94: 2009 | BD94: =L94+W94+AH94+AS94 -> 13124 | BE94: =M94+X94+AI94+AT94 -> 0 | BF94: =N94+Y94+AJ94+AU94 -> 8769 | BG94: =O94+Z94+AK94+AV94 -> 0 | BH94: =P94+AA94+AL94+AW94 -> 0 | BI94: =Q94+AB94+AM94+AX94 -> 0 | BJ94: =R94+AC94+AN94+AY94+S94+AD94+AO94+AZ94 -> 69 | BK94: =SUM(BD94:BJ94) -> 21962 | BM94: 2009 | BN94: =L94+AH94+AS94 -> 7477 | BO94: =M94+AI94+AT94 -> 0 | BP94: =N94+AJ94+AU94 -> 4705 | BQ94: =O94+AK94+AV94 -> 0 | BR94: =P94+AL94+AW94 -> 0 | BS94: =Q94+AM94+AX94 -> 0 | BT94: =R94+AY94+AN94+S94+AZ94+AO94 -> 24 | BU94: =SUM(BN94:BT94) -> 12206 | BW94: 2009 | BX94: =W94 -> 5647 | BY94: =X94 -> 0 | BZ94: =Y94 -> 4064 | CA94: =Z94 -> 0 | CB94: =AA94 -> 0 | CC94: =AB94 -> 0 | CD94: =AC94+AD94 -> 45 | CE94: =SUM(BX94:CD94) -> 9756
A95: 2010 | B95: =B10-B50 -> 0 | C95: =C10-C50 -> 7478 | D95: =D10-D50 -> 0 | E95: =E10-E50 -> 0 | F95: 0 | G95: =G10-G50 -> 11068 | H95: =H10-H50 -> 43 | I95: =SUM(C95:H95) -> 18589 | K95: 2010 | L95: =L10-L50 -> 5393 | M95: =M10-M50 -> 0 | N95: =N10-N50 -> 3051 | O95: =O10-O50 -> 0 | P95: =P10-P50 -> 0 | Q95: =Q10-Q50 -> 0 | R95: =R10-R50 -> 0 | S95: =S10-S50 -> 3 | T95: =SUM(L95:S95) -> 8447 | V95: 2010 | W95: =W10-W50 -> 3657 | X95: =X10-X50 -> 0 | Y95: =Y10-Y50 -> 2610 | Z95: =Z10-Z50 -> 0 | AA95: =AA10-AA50 -> 0 | AB95: =AB10-AB50 -> -30 | AC95: =AC10-AC50 -> 0 | AD95: =AD10-AD50 -> 25 | AE95: =SUM(W95:AD95) -> 6262 | AG95: 2010 | AH95: =AH10-AH50 -> 2018 | AI95: =AI10-AI50 -> 0 | AJ95: =AJ10-AJ50 -> 1817 | AK95: =AK10-AK50 -> 0 | AL95: =AL10-AL50 -> 0 | AM95: =AM10-AM50 -> 20 | AN95: =AN10-AN50 -> 0 | AO95: =AO10-AO50 -> 15 | AP95: =SUM(AH95:AO95) -> 3870 | AR95: 2010 | AS95: =AS10-AS50 -> 0 | AT95: =AT10-AT50 -> 0 | AU95: =AU10-AU50 -> 0 | AV95: =AV10-AV50 -> 0 | AW95: =AW10-AW50 -> 0 | AX95: =AX10-AX50 -> 0 | AY95: =AY10-AY50 -> 0 | AZ95: =AZ10-AZ50 -> 0 | BA95: 0 | BC95: 2010 | BD95: =L95+W95+AH95+AS95 -> 11068 | BE95: =M95+X95+AI95+AT95 -> 0 | BF95: =N95+Y95+AJ95+AU95 -> 7478 | BG95: =O95+Z95+AK95+AV95 -> 0 | BH95: =P95+AA95+AL95+AW95 -> 0 | BI95: =Q95+AB95+AM95+AX95 -> -10 | BJ95: =R95+AC95+AN95+AY95+S95+AD95+AO95+AZ95 -> 43 | BK95: =SUM(BD95:BJ95) -> 18579 | BM95: 2010 | BN95: =L95+AH95+AS95 -> 7411 | BO95: =M95+AI95+AT95 -> 0 | BP95: =N95+AJ95+AU95 -> 4868 | BQ95: =O95+AK95+AV95 -> 0 | BR95: =P95+AL95+AW95 -> 0 | BS95: =Q95+AM95+AX95 -> 20 | BT95: =R95+AY95+AN95+S95+AZ95+AO95 -> 18 | BU95: =SUM(BN95:BT95) -> 12317 | BW95: 2010 | BX95: =W95 -> 3657 | BY95: =X95 -> 0 | BZ95: =Y95 -> 2610 | CA95: =Z95 -> 0 | CB95: =AA95 -> 0 | CC95: =AB95 -> -30 | CD95: =AC95+AD95 -> 25 | CE95: =SUM(BX95:CD95) -> 6262
A96: 2011 | B96: =B11-B51 -> 0 | C96: =C11-C51 -> 7619 | D96: =D11-D51 -> 0 | E96: =E11-E51 -> 0 | F96: =F11-F51 -> 0 | G96: =G11-G51 -> 11328 | H96: =H11-H51 -> 37 | I96: =SUM(C96:H96) -> 18984 | K96: 2011 | L96: =L11-L51 -> 5220 | M96: =M11-M51 -> 0 | N96: =N11-N51 -> 3173 | O96: =O11-O51 -> 0 | P96: =P11-P51 -> 0 | Q96: =Q11-Q51 -> 0 | R96: =R11-R51 -> 0 | S96: =S11-S51 -> 2 | T96: =SUM(L96:S96) -> 8395 | V96: 2011 | W96: =W11-W51 -> 3685 | X96: =X11-X51 -> 0 | Y96: =Y11-Y51 -> 2447 | Z96: =Z11-Z51 -> 0 | AA96: =AA11-AA51 -> 0 | AB96: =AB11-AB51 -> 0 | AC96: =AC11-AC51 -> 0 | AD96: =AD11-AD51 -> 24 | AE96: =SUM(W96:AD96) -> 6156 | AG96: 2011 | AH96: =AH11-AH51 -> 1904 | AI96: =AI11-AI51 -> 0 | AJ96: =AJ11-AJ51 -> 1817 | AK96: =AK11-AK51 -> 0 | AL96: =AL11-AL51 -> 0 | AM96: =AM11-AM51 -> 0 | AN96: =AN11-AN51 -> 0 | AO96: =AO11-AO51 -> 11 | AP96: =SUM(AH96:AO96) -> 3732 | AR96: 2011 | AS96: =AS11-AS51 -> 519 | AT96: =AT11-AT51 -> 0 | AU96: =AU11-AU51 -> 182 | AV96: =AV11-AV51 -> 0 | AW96: =AW11-AW51 -> 0 | AX96: =AX11-AX51 -> 0 | AY96: =AY11-AY51 -> 0 | AZ96: =AZ11-AZ51 -> 0 | BA96: =SUM(AS96:AZ96) -> 701 | BC96: 2011 | BD96: =L96+W96+AH96+AS96 -> 11328 | BE96: =M96+X96+AI96+AT96 -> 0 | BF96: =N96+Y96+AJ96+AU96 -> 7619 | BG96: =O96+Z96+AK96+AV96 -> 0 | BH96: =P96+AA96+AL96+AW96 -> 0 | BI96: =Q96+AB96+AM96+AX96 -> 0 | BJ96: =R96+AC96+AN96+AY96+S96+AD96+AO96+AZ96 -> 37 | BK96: =SUM(BD96:BJ96) -> 18984 | BM96: 2011 | BN96: =L96+AH96+AS96 -> 7643 | BO96: =M96+AI96+AT96 -> 0 | BP96: =N96+AJ96+AU96 -> 5172 | BQ96: =O96+AK96+AV96 -> 0 | BR96: =P96+AL96+AW96 -> 0 | BS96: =Q96+AM96+AX96 -> 0 | BT96: =R96+AY96+AN96+S96+AZ96+AO96 -> 13 | BU96: =SUM(BN96:BT96) -> 12828 | BW96: 2011 | BX96: =W96 -> 3685 | BY96: =X96 -> 0 | BZ96: =Y96 -> 2447 | CA96: =Z96 -> 0 | CB96: =AA96 -> 0 | CC96: =AB96 -> 0 | CD96: =AC96+AD96 -> 24 | CE96: =SUM(BX96:CD96) -> 6156
A97: 2012 | B97: =B12-B52 -> 0 | C97: =C12-C52 -> 7773 | D97: =D12-D52 -> 0 | E97: =E12-E52 -> 0 | F97: =F12-F52 -> 0 | G97: =G12-G52 -> 11044 | H97: =H12-H52 -> 31 | I97: =SUM(C97:H97) -> 18848 | K97: 2012 | L97: =L12-L52 -> 4941 | M97: =M12-M52 -> 0 | N97: =N12-N52 -> 3188 | O97: =O12-O52 -> 0 | P97: =P12-P52 -> 0 | Q97: =Q12-Q52 -> 0 | R97: =R12-R52 -> 0 | S97: =S12-S52 -> 1 | T97: =SUM(L97:S97) -> 8130 | V97: 2012 | W97: =W12-W52 -> 3684 | X97: =X12-X52 -> 0 | Y97: =Y12-Y52 -> 2487 | Z97: =Z12-Z52 -> 0 | AA97: =AA12-AA52 -> 0 | AB97: =AB12-AB52 -> 0 | AC97: =AC12-AC52 -> 0 | AD97: =AD12-AD52 -> 21 | AE97: =SUM(W97:AD97) -> 6192 | AG97: 2012 | AH97: =AH12-AH52 -> 1859 | AI97: =AI12-AI52 -> 0 | AJ97: =AJ12-AJ52 -> 1877 | AK97: =AK12-AK52 -> 0 | AL97: =AL12-AL52 -> 0 | AM97: =AM12-AM52 -> 0 | AN97: =AN12-AN52 -> 0 | AO97: =AO12-AO52 -> 9 | AP97: =SUM(AH97:AO97) -> 3745 | AR97: 2012 | AS97: =AS12-AS52 -> 560 | AT97: =AT12-AT52 -> 0 | AU97: =AU12-AU52 -> 221 | AV97: =AV12-AV52 -> 0 | AW97: =AW12-AW52 -> 0 | AX97: =AX12-AX52 -> 0 | AY97: =AY12-AY52 -> 0 | AZ97: =AZ12-AZ52 -> 0 | BA97: =SUM(AS97:AZ97) -> 781 | BC97: 2012 | BD97: =L97+W97+AH97+AS97 -> 11044 | BE97: =M97+X97+AI97+AT97 -> 0 | BF97: =N97+Y97+AJ97+AU97 -> 7773 | BG97: =O97+Z97+AK97+AV97 -> 0 | BH97: =P97+AA97+AL97+AW97 -> 0 | BI97: =Q97+AB97+AM97+AX97 -> 0 | BJ97: =R97+AC97+AN97+AY97+S97+AD97+AO97+AZ97 -> 31 | BK97: =SUM(BD97:BJ97) -> 18848 | BM97: 2012 | BN97: =L97+AH97+AS97 -> 7360 | BO97: =M97+AI97+AT97 -> 0 | BP97: =N97+AJ97+AU97 -> 5286 | BQ97: =O97+AK97+AV97 -> 0 | BR97: =P97+AL97+AW97 -> 0 | BS97: =Q97+AM97+AX97 -> 0 | BT97: =R97+AY97+AN97+S97+AZ97+AO97 -> 10 | BU97: =SUM(BN97:BT97) -> 12656 | BW97: 2012 | BX97: =W97 -> 3684 | BY97: =X97 -> 0 | BZ97: =Y97 -> 2487 | CA97: =Z97 -> 0 | CB97: =AA97 -> 0 | CC97: =AB97 -> 0 | CD97: =AC97+AD97 -> 21 | CE97: =SUM(BX97:CD97) -> 6192
A98: 2013 | B98: =B13-B53 -> 0 | C98: =C13-C53 -> 8069 | D98: =D13-D53 -> 0 | E98: =E13-E53 -> 0 | F98: =F13-F53 -> 0 | G98: =G13-G53 -> 10540 | H98: =H13-H53 -> 34 | I98: =SUM(C98:H98) -> 18643 | K98: 2013 | L98: =L13-L53 -> 4735 | M98: =M13-M53 -> 0 | N98: =N13-N53 -> 3322 | O98: =O13-O53 -> 0 | P98: =P13-P53 -> 0 | Q98: =Q13-Q53 -> 0 | R98: =R13-R53 -> 0 | S98: =S13-S53 -> 2 | T98: =SUM(L98:S98) -> 8059 | V98: 2013 | W98: =W13-W53 -> 3498 | X98: =X13-X53 -> 0 | Y98: =Y13-Y53 -> 2589 | Z98: =Z13-Z53 -> 0 | AA98: =AA13-AA53 -> 0 | AB98: =AB13-AB53 -> 0 | AC98: =AC13-AC53 -> 0 | AD98: =AD13-AD53 -> 22 | AE98: =SUM(W98:AD98) -> 6109 | AG98: 2013 | AH98: =AH13-AH53 -> 1726 | AI98: =AI13-AI53 -> 0 | AJ98: =AJ13-AJ53 -> 1929 | AK98: =AK13-AK53 -> 0 | AL98: =AL13-AL53 -> 0 | AM98: =AM13-AM53 -> 0 | AN98: =AN13-AN53 -> 0 | AO98: =AO13-AO53 -> 10 | AP98: =SUM(AH98:AO98) -> 3665 | AR98: 2013 | AS98: =AS13-AS53 -> 581 | AT98: =AT13-AT53 -> 0 | AU98: =AU13-AU53 -> 229 | AV98: =AV13-AV53 -> 0 | AW98: =AW13-AW53 -> 0 | AX98: =AX13-AX53 -> 0 | AY98: =AY13-AY53 -> 0 | AZ98: =AZ13-AZ53 -> 0 | BA98: =SUM(AS98:AZ98) -> 810 | BC98: 2013 | BD98: =L98+W98+AH98+AS98 -> 10540 | BE98: =M98+X98+AI98+AT98 -> 0 | BF98: =N98+Y98+AJ98+AU98 -> 8069 | BG98: =O98+Z98+AK98+AV98 -> 0 | BH98: =P98+AA98+AL98+AW98 -> 0 | BI98: =Q98+AB98+AM98+AX98 -> 0 | BJ98: =R98+AC98+AN98+AY98+S98+AD98+AO98+AZ98 -> 34 | BK98: =SUM(BD98:BJ98) -> 18643 | BM98: 2013 | BN98: =L98+AH98+AS98 -> 7042 | BO98: =M98+AI98+AT98 -> 0 | BP98: =N98+AJ98+AU98 -> 5480 | BQ98: =O98+AK98+AV98 -> 0 | BR98: =P98+AL98+AW98 -> 0 | BS98: =Q98+AM98+AX98 -> 0 | BT98: =R98+AY98+AN98+S98+AZ98+AO98 -> 12 | BU98: =SUM(BN98:BT98) -> 12534 | BW98: 2013 | BX98: =W98 -> 3498 | BY98: =X98 -> 0 | BZ98: =Y98 -> 2589 | CA98: =Z98 -> 0 | CB98: =AA98 -> 0 | CC98: =AB98 -> 0 | CD98: =AC98+AD98 -> 22 | CE98: =SUM(BX98:CD98) -> 6109
A99: 2014 | B99: =B14-B54 -> 0 | C99: =C14-C54 -> 8509 | D99: =D14-D54 -> 0 | E99: =E14-E54 -> 0 | F99: =F14-F54 -> 0 | G99: =G14-G54 -> 10140 | H99: =H14-H54 -> 39 | I99: =SUM(C99:H99) -> 18688 | K99: 2014 | L99: =L14-L54 -> 4579 | M99: =M14-M54 -> 0 | N99: =N14-N54 -> 3547 | O99: =O14-O54 -> 0 | P99: =P14-P54 -> 0 | Q99: =Q14-Q54 -> 0 | R99: =R14-R54 -> 0 | S99: =S14-S54 -> 4 | T99: =SUM(L99:S99) -> 8130 | V99: 2014 | W99: =W14-W54 -> 3355 | X99: =X14-X54 -> 0 | Y99: =Y14-Y54 -> 2720 | Z99: =Z14-Z54 -> 0 | AA99: =AA14-AA54 -> 0 | AB99: =AB14-AB54 -> 0 | AC99: =AC14-AC54 -> 0 | AD99: =AD14-AD54 -> 23 | AE99: =SUM(W99:AD99) -> 6098 | AG99: 2014 | AH99: =AH14-AH54 -> 1636 | AI99: =AI14-AI54 -> 0 | AJ99: =AJ14-AJ54 -> 2023 | AK99: =AK14-AK54 -> 0 | AL99: =AL14-AL54 -> 0 | AM99: =AM14-AM54 -> 0 | AN99: =AN14-AN54 -> 0 | AO99: =AO14-AO54 -> 12 | AP99: =SUM(AH99:AO99) -> 3671 | AR99: 2014 | AS99: =AS14-AS54 -> 570 | AT99: =AT14-AT54 -> 0 | AU99: =AU14-AU54 -> 219 | AV99: =AV14-AV54 -> 0 | AW99: =AW14-AW54 -> 0 | AX99: =AX14-AX54 -> 0 | AY99: =AY14-AY54 -> 0 | AZ99: =AZ14-AZ54 -> 0 | BA99: =SUM(AS99:AZ99) -> 789 | BC99: 2014 | BD99: =L99+W99+AH99+AS99 -> 10140 | BE99: =M99+X99+AI99+AT99 -> 0 | BF99: =N99+Y99+AJ99+AU99 -> 8509 | BG99: =O99+Z99+AK99+AV99 -> 0 | BH99: =P99+AA99+AL99+AW99 -> 0 | BI99: =Q99+AB99+AM99+AX99 -> 0 | BJ99: =R99+AC99+AN99+AY99+S99+AD99+AO99+AZ99 -> 39 | BK99: =SUM(BD99:BJ99) -> 18688 | BM99: 2014 | BN99: =L99+AH99+AS99 -> 6785 | BO99: =M99+AI99+AT99 -> 0 | BP99: =N99+AJ99+AU99 -> 5789 | BQ99: =O99+AK99+AV99 -> 0 | BR99: =P99+AL99+AW99 -> 0 | BS99: =Q99+AM99+AX99 -> 0 | BT99: =R99+AY99+AN99+S99+AZ99+AO99 -> 16 | BU99: =SUM(BN99:BT99) -> 12590 | BW99: 2014 | BX99: =W99 -> 3355 | BY99: =X99 -> 0 | BZ99: =Y99 -> 2720 | CA99: =Z99 -> 0 | CB99: =AA99 -> 0 | CC99: =AB99 -> 0 | CD99: =AC99+AD99 -> 23 | CE99: =SUM(BX99:CD99) -> 6098
A100: 2015 | B100: =B15-B55 -> 0 | C100: =C15-C55 -> 8622 | D100: =D15-D55 -> 0 | E100: =E15-E55 -> 0 | F100: =F15-F55 -> 0 | G100: =G15-G55 -> 9407 | H100: =H15-H55 -> 44 | I100: =SUM(C100:H100) -> 18073 | K100: 2015 | L100: =L15-L55 -> 4160 | M100: =M15-M55 -> 0 | N100: =N15-N55 -> 3589 | O100: =O15-O55 -> 0 | P100: =P15-P55 -> 0 | Q100: =Q15-Q55 -> 0 | R100: =R15-R55 -> 0 | S100: =S15-S55 -> 9 | T100: =SUM(L100:S100) -> 7758 | V100: 2015 | W100: =W15-W55 -> 3139 | X100: =X15-X55 -> 0 | Y100: =Y15-Y55 -> 2776 | Z100: =Z15-Z55 -> 0 | AA100: =AA15-AA55 -> 0 | AB100: =AB15-AB55 -> 0 | AC100: =AC15-AC55 -> 0 | AD100: =AD15-AD55 -> 23 | AE100: =SUM(W100:AD100) -> 5938 | AG100: 2015 | AH100: =AH15-AH55 -> 1485 | AI100: =AI15-AI55 -> 0 | AJ100: =AJ15-AJ55 -> 2026 | AK100: =AK15-AK55 -> 0 | AL100: =AL15-AL55 -> 0 | AM100: =AM15-AM55 -> 0 | AN100: =AN15-AN55 -> 0 | AO100: =AO15-AO55 -> 12 | AP100: =SUM(AH100:AO100) -> 3523 | AR100: 2015 | AS100: =AS15-AS55 -> 623 | AT100: =AT15-AT55 -> 0 | AU100: =AU15-AU55 -> 231 | AV100: =AV15-AV55 -> 0 | AW100: =AW15-AW55 -> 0 | AX100: =AX15-AX55 -> 0 | AY100: =AY15-AY55 -> 0 | AZ100: =AZ15-AZ55 -> 0 | BA100: =SUM(AS100:AZ100) -> 854 | BC100: 2015 | BD100: =L100+W100+AH100+AS100 -> 9407 | BE100: =M100+X100+AI100+AT100 -> 0 | BF100: =N100+Y100+AJ100+AU100 -> 8622 | BG100: =O100+Z100+AK100+AV100 -> 0 | BH100: =P100+AA100+AL100+AW100 -> 0 | BI100: =Q100+AB100+AM100+AX100 -> 0 | BJ100: =R100+AC100+AN100+AY100+S100+AD100+AO100+AZ100 -> 44 | BK100: =SUM(BD100:BJ100) -> 18073 | BM100: 2015 | BN100: =L100+AH100+AS100 -> 6268 | BO100: =M100+AI100+AT100 -> 0 | BP100: =N100+AJ100+AU100 -> 5846 | BQ100: =O100+AK100+AV100 -> 0 | BR100: =P100+AL100+AW100 -> 0 | BS100: =Q100+AM100+AX100 -> 0 | BT100: =R100+AY100+AN100+S100+AZ100+AO100 -> 21 | BU100: =SUM(BN100:BT100) -> 12135 | BW100: 2015 | BX100: =W100 -> 3139 | BY100: =X100 -> 0 | BZ100: =Y100 -> 2776 | CA100: =Z100 -> 0 | CB100: =AA100 -> 0 | CC100: =AB100 -> 0 | CD100: =AC100+AD100 -> 23 | CE100: =SUM(BX100:CD100) -> 5938
A101: 2016 | B101: =B16-B56 -> 0 | C101: =C16-C56 -> 9256 | D101: =D16-D56 -> 0 | E101: =E16-E56 -> 0 | F101: =F16-F56 -> 0 | G101: =G16-G56 -> 9273 | H101: =H16-H56 -> 55 | I101: =SUM(C101:H101) -> 18584 | K101: 2016 | L101: =L16-L56 -> 4167 | M101: =M16-M56 -> 0 | N101: =N16-N56 -> 3985 | O101: =O16-O56 -> 0 | P101: =P16-P56 -> 0 | Q101: =Q16-Q56 -> 0 | R101: =R16-R56 -> 0 | S101: =S16-S56 -> 19 | T101: =SUM(L101:S101) -> 8171 | V101: 2016 | W101: =W16-W56 -> 3086 | X101: =X16-X56 -> 0 | Y101: =Y16-Y56 -> 2949 | Z101: =Z16-Z56 -> 0 | AA101: =AA16-AA56 -> 0 | AB101: =AB16-AB56 -> 0 | AC101: =AC16-AC56 -> 0 | AD101: =AD16-AD56 -> 23 | AE101: =SUM(W101:AD101) -> 6058 | AG101: 2016 | AH101: =AH16-AH56 -> 1403 | AI101: =AI16-AI56 -> 0 | AJ101: =AJ16-AJ56 -> 2107 | AK101: =AK16-AK56 -> 0 | AL101: =AL16-AL56 -> 0 | AM101: =AM16-AM56 -> 0 | AN101: =AN16-AN56 -> 0 | AO101: =AO16-AO56 -> 13 | AP101: =SUM(AH101:AO101) -> 3523 | AR101: 2016 | AS101: =AS16-AS56 -> 617 | AT101: =AT16-AT56 -> 0 | AU101: =AU16-AU56 -> 215 | AV101: =AV16-AV56 -> 0 | AW101: =AW16-AW56 -> 0 | AX101: =AX16-AX56 -> 0 | AY101: =AY16-AY56 -> 0 | AZ101: =AZ16-AZ56 -> 0 | BA101: =SUM(AS101:AZ101) -> 832 | BC101: 2016 | BD101: =L101+W101+AH101+AS101 -> 9273 | BE101: =M101+X101+AI101+AT101 -> 0 | BF101: =N101+Y101+AJ101+AU101 -> 9256 | BG101: =O101+Z101+AK101+AV101 -> 0 | BH101: =P101+AA101+AL101+AW101 -> 0 | BI101: =Q101+AB101+AM101+AX101 -> 0 | BJ101: =R101+AC101+AN101+AY101+S101+AD101+AO101+AZ101 -> 55 | BK101: =SUM(BD101:BJ101) -> 18584 | BM101: 2016 | BN101: =L101+AH101+AS101 -> 6187 | BO101: =M101+AI101+AT101 -> 0 | BP101: =N101+AJ101+AU101 -> 6307 | BQ101: =O101+AK101+AV101 -> 0 | BR101: =P101+AL101+AW101 -> 0 | BS101: =Q101+AM101+AX101 -> 0 | BT101: =R101+AY101+AN101+S101+AZ101+AO101 -> 32 | BU101: =SUM(BN101:BT101) -> 12526 | BW101: 2016 | BX101: =W101 -> 3086 | BY101: =X101 -> 0 | BZ101: =Y101 -> 2949 | CA101: =Z101 -> 0 | CB101: =AA101 -> 0 | CC101: =AB101 -> 0 | CD101: =AC101+AD101 -> 23 | CE101: =SUM(BX101:CD101) -> 6058
A102: 2017 | B102: =B17-B57 -> 0 | C102: =C17-C57 -> 9518 | D102: =D17-D57 -> 0 | E102: =E17-E57 -> 0 | F102: =F17-F57 -> 0 | G102: =G17-G57 -> 8757 | H102: =H17-H57 -> 75 | I102: =SUM(C102:H102) -> 18350 | K102: 2017 | L102: =L17-L57 -> 3953 | M102: =M17-M57 -> 0 | N102: =N17-N57 -> 4203 | O102: =O17-O57 -> 0 | P102: =P17-P57 -> 0 | Q102: =Q17-Q57 -> 0 | R102: =R17-R57 -> 37 | S102: =S17-S57 -> 0 | T102: =SUM(L102:S102) -> 8193 | V102: 2017 | W102: =W17-W57 -> 2915 | X102: =X17-X57 -> 0 | Y102: =Y17-Y57 -> 2990 | Z102: =Z17-Z57 -> 0 | AA102: =AA17-AA57 -> 0 | AB102: =AB17-AB57 -> 0 | AC102: =AC17-AC57 -> 24 | AD102: =AD17-AD57 -> 0 | AE102: =SUM(W102:AD102) -> 5929 | AG102: 2017 | AH102: =AH17-AH57 -> 1283 | AI102: =AI17-AI57 -> 0 | AJ102: =AJ17-AJ57 -> 2128 | AK102: =AK17-AK57 -> 0 | AL102: =AL17-AL57 -> 0 | AM102: =AM17-AM57 -> 0 | AN102: =AN17-AN57 -> 14 | AO102: =AO17-AO57 -> 0 | AP102: =SUM(AH102:AO102) -> 3425 | AR102: 2017 | AS102: =AS17-AS57 -> 606 | AT102: =AT17-AT57 -> 0 | AU102: =AU17-AU57 -> 197 | AV102: =AV17-AV57 -> 0 | AW102: =AW17-AW57 -> 0 | AX102: =AX17-AX57 -> 0 | AY102: =AY17-AY57 -> 0 | AZ102: =AZ17-AZ57 -> 0 | BA102: =SUM(AS102:AZ102) -> 803 | BC102: 2017 | BD102: =L102+W102+AH102+AS102 -> 8757 | BE102: =M102+X102+AI102+AT102 -> 0 | BF102: =N102+Y102+AJ102+AU102 -> 9518 | BG102: =O102+Z102+AK102+AV102 -> 0 | BH102: =P102+AA102+AL102+AW102 -> 0 | BI102: =Q102+AB102+AM102+AX102 -> 0 | BJ102: =R102+AC102+AN102+AY102+S102+AD102+AO102+AZ102 -> 75 | BK102: =SUM(BD102:BJ102) -> 18350 | BM102: 2017 | BN102: =L102+AH102+AS102 -> 5842 | BO102: =M102+AI102+AT102 -> 0 | BP102: =N102+AJ102+AU102 -> 6528 | BQ102: =O102+AK102+AV102 -> 0 | BR102: =P102+AL102+AW102 -> 0 | BS102: =Q102+AM102+AX102 -> 0 | BT102: =R102+AY102+AN102+S102+AZ102+AO102 -> 51 | BU102: =SUM(BN102:BT102) -> 12421 | BW102: 2017 | BX102: =W102 -> 2915 | BY102: =X102 -> 0 | BZ102: =Y102 -> 2990 | CA102: =Z102 -> 0 | CB102: =AA102 -> 0 | CC102: =AB102 -> 0 | CD102: =AC102+AD102 -> 24 | CE102: =SUM(BX102:CD102) -> 5929
A103: 2018 | B103: =B18-B58 -> 0 | C103: =C18-C58 -> 9852 | D103: =D18-D58 -> 0 | E103: =E18-E58 -> 0 | F103: =F18-F58 -> 0 | G103: =G18-G58 -> 9665 | H103: =H18-H58 -> 76 | I103: =SUM(C103:H103) -> 19593 | K103: 2018 | L103: =L18-L58 -> 4333 | M103: =M18-M58 -> 0 | N103: =N18-N58 -> 4241 | O103: =O18-O58 -> 0 | P103: =P18-P58 -> 0 | Q103: =Q18-Q58 -> 0 | R103: =R18-R58 -> 38 | S103: =S18-S58 -> 0 | T103: =SUM(L103:S103) -> 8612 | V103: 2018 | W103: =W18-W58 -> 3086 | X103: =X18-X58 -> 0 | Y103: =Y18-Y58 -> 3085 | Z103: =Z18-Z58 -> 0 | AA103: =AA18-AA58 -> 0 | AB103: =AB18-AB58 -> 0 | AC103: =AC18-AC58 -> 24 | AD103: =AD18-AD58 -> 0 | AE103: =SUM(W103:AD103) -> 6195 | AG103: 2018 | AH103: =AH18-AH58 -> 1361 | AI103: =AI18-AI58 -> 0 | AJ103: =AJ18-AJ58 -> 2254 | AK103: =AK18-AK58 -> 0 | AL103: =AL18-AL58 -> 0 | AM103: =AM18-AM58 -> 0 | AN103: =AN18-AN58 -> 14 | AO103: =AO18-AO58 -> 0 | AP103: =SUM(AH103:AO103) -> 3629 | AR103: 2018 | AS103: =AS18-AS58 -> 885 | AT103: =AT18-AT58 -> 0 | AU103: =AU18-AU58 -> 272 | AV103: =AV18-AV58 -> 0 | AW103: =AW18-AW58 -> 0 | AX103: =AX18-AX58 -> 0 | AY103: =AY18-AY58 -> 0 | AZ103: =AZ18-AZ58 -> 0 | BA103: =SUM(AS103:AZ103) -> 1157 | BC103: 2018 | BD103: =L103+W103+AH103+AS103 -> 9665 | BE103: =M103+X103+AI103+AT103 -> 0 | BF103: =N103+Y103+AJ103+AU103 -> 9852 | BG103: =O103+Z103+AK103+AV103 -> 0 | BH103: =P103+AA103+AL103+AW103 -> 0 | BI103: =Q103+AB103+AM103+AX103 -> 0 | BJ103: =R103+AC103+AN103+AY103+S103+AD103+AO103+AZ103 -> 76 | BK103: =SUM(BD103:BJ103) -> 19593 | BM103: 2018 | BN103: =L103+AH103+AS103 -> 6579 | BO103: =M103+AI103+AT103 -> 0 | BP103: =N103+AJ103+AU103 -> 6767 | BQ103: =O103+AK103+AV103 -> 0 | BR103: =P103+AL103+AW103 -> 0 | BS103: =Q103+AM103+AX103 -> 0 | BT103: =R103+AY103+AN103+S103+AZ103+AO103 -> 52 | BU103: =SUM(BN103:BT103) -> 13398 | BW103: 2018 | BX103: =W103 -> 3086 | BY103: =X103 -> 0 | BZ103: =Y103 -> 3085 | CA103: =Z103 -> 0 | CB103: =AA103 -> 0 | CC103: =AB103 -> 0 | CD103: =AC103+AD103 -> 24 | CE103: =SUM(BX103:CD103) -> 6195
A104: 2019 | B104: =B19-B59 -> 0 | C104: =C19-C59 -> 9357 | D104: =D19-D59 -> 0 | E104: =E19-E59 -> 0 | F104: =F19-F59 -> 0 | G104: =G19-G59 -> 8653 | H104: =H19-H59 -> 74 | I104: =SUM(C104:H104) -> 18084 | K104: 2019 | L104: =L19-L59 -> 3854 | M104: =M19-M59 -> 0 | N104: =N19-N59 -> 4088 | O104: =O19-O59 -> 0 | P104: =P19-P59 -> 0 | Q104: =Q19-Q59 -> 0 | R104: =R19-R59 -> 37 | S104: =S19-S59 -> 0 | T104: =SUM(L104:S104) -> 7979 | V104: 2019 | W104: =W19-W59 -> 2861 | X104: =X19-X59 -> 0 | Y104: =Y19-Y59 -> 2933 | Z104: =Z19-Z59 -> 0 | AA104: =AA19-AA59 -> 0 | AB104: =AB19-AB59 -> 0 | AC104: =AC19-AC59 -> 23 | AD104: =AD19-AD59 -> 0 | AE104: =SUM(W104:AD104) -> 5817 | AG104: 2019 | AH104: =AH19-AH59 -> 1280 | AI104: =AI19-AI59 -> 0 | AJ104: =AJ19-AJ59 -> 2124 | AK104: =AK19-AK59 -> 0 | AL104: =AL19-AL59 -> 0 | AM104: =AM19-AM59 -> 0 | AN104: =AN19-AN59 -> 14 | AO104: =AO19-AO59 -> 0 | AP104: =SUM(AH104:AO104) -> 3418 | AR104: 2019 | AS104: =AS19-AS59 -> 658 | AT104: =AT19-AT59 -> 0 | AU104: =AU19-AU59 -> 212 | AV104: =AV19-AV59 -> 0 | AW104: =AW19-AW59 -> 0 | AX104: =AX19-AX59 -> 0 | AY104: =AY19-AY59 -> 0 | AZ104: =AZ19-AZ59 -> 0 | BA104: =SUM(AS104:AZ104) -> 870 | BC104: 2019 | BD104: =L104+W104+AH104+AS104 -> 8653 | BE104: =M104+X104+AI104+AT104 -> 0 | BF104: =N104+Y104+AJ104+AU104 -> 9357 | BG104: =O104+Z104+AK104+AV104 -> 0 | BH104: =P104+AA104+AL104+AW104 -> 0 | BI104: =Q104+AB104+AM104+AX104 -> 0 | BJ104: =R104+AC104+AN104+AY104+S104+AD104+AO104+AZ104 -> 74 | BK104: =SUM(BD104:BJ104) -> 18084 | BM104: 2019 | BN104: =L104+AH104+AS104 -> 5792 | BO104: =M104+AI104+AT104 -> 0 | BP104: =N104+AJ104+AU104 -> 6424 | BQ104: =O104+AK104+AV104 -> 0 | BR104: =P104+AL104+AW104 -> 0 | BS104: =Q104+AM104+AX104 -> 0 | BT104: =R104+AY104+AN104+S104+AZ104+AO104 -> 51 | BU104: =SUM(BN104:BT104) -> 12267 | BW104: 2019 | BX104: =W104 -> 2861 | BY104: =X104 -> 0 | BZ104: =Y104 -> 2933 | CA104: =Z104 -> 0 | CB104: =AA104 -> 0 | CC104: =AB104 -> 0 | CD104: =AC104+AD104 -> 23 | CE104: =SUM(BX104:CD104) -> 5817
...

Sheet FloorAreaPer
A1: Median Per Capita Floor Area of Accommodation by Area of Residence, Household Size, Year and Type of Housing | J1: source:Population By-census, 2016
D2: Median Per Capita Floor Area of Accommodation(1)
D3: Square Metres
A4: Year | D4: 2016
A5: Type of Housing | D5: Public rental housing | E5: Subsidised home ownership housing | F5: Private permanent housing | G5: Others | H5: Overall
A6: Area of Residence | C6: Household Size
A7: Central and Western | C7: 1 | D7: 25 | E7: - | F7: 35 | G7: 19 | H7: 34
