Workbook
Name Average_emission_factor: '[1]Electricity emissions'!$H$38
Name footnote500011: FloorAreaPer!$A$170

Sheet About
A1: Sources:
B2: EMSD Energy End-use Data | C2: (Sheets:Energy8Sec, Residential8Fuel, Commercial8Fuel, Residential8EndUse, Commertial8EndUse)
B3: Hong Kong Energy End-use Data
B4: 2013-2018
B5: https://www.emsd.gov.hk/en/energy_efficiency/energy_end_use_data_and_consumption_indicators/hong_kong_energy_end_use_data/data/index.html
B6: Sheets:"Energy8Sec","Residential8Fuel","Commercial8Fuel","Residential8EndUse" and "Commercial8EndUse" are all from this data source.
B8: HK 2030 Report | F8: HK 2030: Baseline Review
B9: HK Development Bureau, HK Planning Department | F9: HK Development Bureau, HK Planning Department
B10: 2017 | F10: 2017
B11: Final Report | F11: Baseline Review: Population, Housing, Economy and Spatial Development Pattern
B12: https://www.pland.gov.hk/pland_en/p_study/comp_s/hk2030/eng/finalreport/ | F12: https://www.hk2030plus.hk/document/Baseline%20Review%20-%20Population_Housing_Economy%20and%20Spatial%20Development%20Pattern_Eng.pdf
B14: Household History Data(Sheet: Household_Histo) | F14: Household Prediction Data(Sheet: Household_Pred)
B15: Census and Statistics Department, HK | F15: Census and Statistics Department, HK
B16: 2019 | F16: 2019
B17: Table 005 : Statistics on Domestic Households | F17: Table E485 : Hong Kong Domestic Household Projections
B18: https://www.censtatd.gov.hk/hkstat/sub/sp150.jsp?tableID=005&ID=0&productType=8 | F18: https://www.censtatd.gov.hk/hkstat/sub/sp190.jsp?productCode=D5320185
B20: Floor Area Per capita (Sheet: FloorAreaPer)
B21: Population By-census
B22: 2017
B23: Table E129c: Median Per Capita Floor Area of Accommodation by Area of Residence, Household Size, Year and Type of Housing
B24: https://www.bycensus2016.gov.hk/en/bc-mt.html?search=E129c
B26: Building 2016 Data
B27: From Xiaoqian Jiang
B28: 2017
B29: From Excel "Copy of HK 2016 end use energy consumption rough 20190226 (added the building waste) revised2 lawrence.xlsx", Sheet"Building"
A32: Edition Log (WU Yazhen)
A33: 20190301_v1
A34: This part of data collection has not been finished.
A35: Next step: | B35: 1.Found Household Unit Composition to separate urban/rural residential
B36: 2.Use historical and predicted data of :Population, GDP, total residential area, total commercial arer, average number of people per household, average residential area per household
C37: to make linear or non-linear regression to predict future total energy consumption of residential/commercial sector of each fuel type.
C38: Then assuming the end-use composition stay unchanged throught the years, and the already-annouced building energy saving goal achieved.
C39: To predict future BAU End-use Data
A40: 20190304_v2
A41: Finished: | B41: 1.Found household history and prediction data.
B42: 2.Found Commercial AreaUse relative prediction ( average living area per household, household number; average living area per person, population) to predict residential area.
B43: 3.Done regression for estimating future residential energy consumption and
A44: 20190305_v3
A45: Finished: | B45: 1.Finished 1st version of Future Energy (End-use) Share Prediction.
B46: 2.Finished all calculation and got the final results, with TJ been converted to BTU.
A47: 20190306_v4
A48: Finished: | B48: 1. Change future household prediction data (from using"HK 2030 Baseline.pdf" as source, to using the HK C&SD predictions in sheet"Household_Pred").
B49: 2. The End-use "cooking" category has been put into "Appliance", not "Others".
B50: 3. The breakdown of rural/urban residential is finished.
B51: 4. The final data sheets are in the same format as the EPS US model inputdata sheets'.
A52: 20190404_v5
A53: Revised: | B53: 1. The missing final sheets for commercial have been added.
B54: 2. The data form in the sheets colored blue is adjust to be the same with the US model(start year from 2014).
B55: 3. Limit the use of coal&oil, and also gas, to be only in the appliance, not for lighting and other end-use sectors.
B56: (Adjustments are mainly made in the sheet "Future Energy share", on the breakdown of oil&coal (or gas) among different end-use types.
A58: 20190906_v6
A59: Revised: | B59: 1. Change the method of predicting total private/public/commercial building's energy demand: first predict future trend of per capita/per area energy consumption,
B60: and multiply them with population/area projections, than to directly predict total energy consumption by regression.
B61: 2. No longer divide the house as urban/rural residential, but divide them as private/public residential (and mark private as urban, residential as rural in the dark-blue final input sheets)

Sheet Note
A1: Method
A2: Step1: Predict Future Total Energy Consumption by Segments using socioeconomic and energy intensity data
B3: predict per capita/per area energy consumption and then multiply it with population/area projections. Not directly predict total energy consumption by regression.
A4: Step2: Predict Future Energy Type Share by using trend function.
A5: Step3: Predict Future End-use share of different(electricity/non-electricity) type in residential energy use
A8: Assumptions & Classicification
A9: 1. "Coal and oil"(in statistics: energy consumption by fuel) is made up of 50% coal, 50% oil. And "Town gas &Oil gas" equals to natural gas
A10: 2. The end-use "Hot water" are categorized as "Appliance", not as part of the "Heating".
A11: 3. No energy consumption in "Heating"(In EPS model note, the "Heating" means distributed heating, which HK does not have), and thus
A12: 4. The end-use "Appliance" includes "Hot water &Refrigeration", "Office equipment" and "Cooking", while the category "Others" includes "Others" in the Residential/Commercial sector segment statistic.
A13: 5. The share of end-uses in all different non-electricity energy types are the same.
A15: Future considerations
A16: 1.The fact that older peole' energy demand is different and the HK population structure is changing
A17: 2. Classification of end-use categories. E.g. perhaps "Cooking" should be grouped into "Appliance" category, not "Others"?
A18: 3. Refer to BEC (HK Energy-saving Report)?
... A51: 10. Sheet "Future Energy Share", data in row 64-65 is currently not yet supported by valid material; they are assumed by me.

Sheet InternalLink
A2: About
A3: InternalLink
A4: Household_Histo
A5: Household_Pred
A6: Energy8Sec
A7: Residential8Fuel
A8: Commercial8Fuel
A9: Residential8EndUse
A10: Commercial8EndUse
A11: Commercial
A12: Residential
A13: Future Pred
... A18: Note

Sheet Household_Histo
A1: Table005: Statistics on Domestic Households
A3: Period | C3: Number of domestic households ('000) | D3: Average domestic household size | E3: Owner-occupiers as a proportion of total number of domestic households (%) | F3: Owner-occupiers in public sector housing as a proportion of total number of domestic households in public sector housing (%) | G3: Owner-occupiers in private sector housing as a proportion of total number of domestic households in private sector housing (%)
A4: 1982 | C4: 1311.6 | D4: 3.9 | E4: 28.7 | F4: N.A. | G4: N.A.
A5: 1983 | C5: 1334.3 | D5: 3.9 | E5: 30.7 | F5: N.A. | G5: N.A.
A6: 1984 | C6: 1378.7 | D6: 3.7 | E6: 31.2 | F6: N.A. | G6: N.A.
A7: 1985 | C7: 1417.7 | D7: 3.7 | E7: 32.8 | F7: 6.6 | G7: 51.8
A8: 1986 | C8: 1473.1 | D8: 3.6 | E8: 34.9 | F8: 9.1 | G8: 53.9
A9: 1987 | C9: 1496.1 | D9: 3.6 | E9: 37.9 | F9: 10.1 | G9: 59.1
A10: 1988 | C10: 1532.6 | D10: 3.6 | E10: 39.4 | F10: 11.9 | G10: 60.8
A11: 1989 | C11: 1549 | D11: 3.6 | E11: 41.6 | F11: 12.9 | G11: 64.5
A12: 1990 | C12: 1559 | D12: 3.5 | E12: 42.6 | F12: 14.2 | G12: 66.3
A13: 1991 | C13: 1601.9 | D13: 3.5 | E13: 43.1 | F13: 15.8 | G13: 66.5
A14: 1992 | C14: 1633.5 | D14: 3.4 | E14: 43.5 | F14: 16.3 | G14: 68
A15: 1993 | C15: 1677.7 | D15: 3.5 | E15: 44.6 | F15: 18.2 | G15: 68.6
A16: 1994 | C16: 1729.1 | D16: 3.4 | E16: 45.1 | F16: 20.5 | G16: 67.8
A17: 1995 | C17: 1783 | D17: 3.4 | E17: 45.2 | F17: 21.6 | G17: 67.3
A18: 1996 | C18: 1864.5 | D18: 3.4 | E18: 45.9 | F18: 21.9 | G18: 67.1
... A39: 2017 | C39: 2534.7 | D39: 2.8 | E39: 49.2 | F39: 31.8 | G39: 63.8
A40: 10/1981 - 12/1981 | C40: 1297.7 | D40: 3.8 | E40: 28.7 | F40: N.A. | G40: N.A.
A41: 1/1982 - 3/1982 | C41: 1297.4 | D41: 3.9 | E41: 28.3 | F41: N.A. | G41: N.A.
A42: 4/1982 - 6/1982 | C42: 1317.5 | D42: 3.9 | E42: 28.5 | F42: N.A. | G42: N.A.
A43: 7/1982 - 9/1982 | C43: 1312.3 | D43: 3.9 | E43: 29 | F43: N.A. | G43: N.A.
A44: 10/1982 - 12/1982 | C44: 1319.3 | D44: 3.9 | E44: 29 | F44: N.A. | G44: N.A.
A45: 1/1983 - 3/1983 | C45: 1320.1 | D45: 3.9 | E45: 31.1 | F45: N.A. | G45: N.A.
A46: 4/1983 - 6/1983 | C46: 1330.5 | D46: 3.9 | E46: 30.9 | F46: N.A. | G46: N.A.
A47: 7/1983 - 9/1983 | C47: 1336.9 | D47: 3.8 | E47: 30.3 | F47: N.A. | G47: N.A.
A48: 10/1983 - 12/1983 | C48: 1349.9 | D48: 3.8 | E48: 30.3 | F48: N.A. | G48: N.A.
A49: 1/1984 - 3/1984 | C49: 1345.4 | D49: 3.8 | E49: 30.9 | F49: N.A. | G49: N.A.
A50: 4/1984 - 6/1984 | C50: 1378.1 | D50: 3.8 | E50: 30.9 | F50: N.A. | G50: N.A.
A51: 7/1984 - 9/1984 | C51: 1386.3 | D51: 3.7 | E51: 31.8 | F51: N.A. | G51: N.A.
A52: 10/1984 - 12/1984 | C52: 1405 | D52: 3.7 | E52: 31.3 | F52: N.A. | G52: N.A.
A53: 1/1985 - 3/1985 | C53: 1402.9 | D53: 3.7 | E53: 31.4 | F53: 5.9 | G53: 50.2
A54: 4/1985 - 6/1985 | C54: 1416.7 | D54: 3.7 | E54: 32.8 | F54: 6.3 | G54: 51.6
A55: 7/1985 - 9/1985 | C55: 1416.5 | D55: 3.7 | E55: 33.9 | F55: 6.9 | G55: 53.6
A56: 10/1985 - 12/1985 | C56: 1434.7 | D56: 3.7 | E56: 33.2 | F56: 7.3 | G56: 51.8
A57: 1/1986 - 3/1986 | C57: 1453 | D57: 3.7 | E57: 32.9 | F57: 7.9 | G57: 50.6
A58: 4/1986 - 6/1986 | C58: 1469.7 | D58: 3.6 | E58: 34 | F58: 9 | G58: 52
A59: 7/1986 - 9/1986 | C59: 1481.4 | D59: 3.6 | E59: 36 | F59: 9.5 | G59: 56.4
A60: 10/1986 - 12/1986 | C60: 1488.2 | D60: 3.6 | E60: 36.5 | F60: 9.9 | G60: 56.9
A61: 1/1987 - 3/1987 | C61: 1478.3 | D61: 3.6 | E61: 37.1 | F61: 9.9 | G61: 57.7
A62: 4/1987 - 6/1987 | C62: 1494.3 | D62: 3.6 | E62: 37.3 | F62: 10.3 | G62: 57.9
A63: 7/1987 - 9/1987 | C63: 1496.7 | D63: 3.6 | E63: 38.5 | F63: 10.2 | G63: 60.3
A64: 10/1987 - 12/1987 | C64: 1514.9 | D64: 3.6 | E64: 38.7 | F64: 9.9 | G64: 60.4
... A394: 10/2018 - 12/2018 | C394: 2573.9 | D394: 2.8 | E394: 49.1 | F394: 32 | G394: 63.8
A396: Notes : | B396: Starting from 2001, annual figures are compiled based on data collected in the General Household Survey from January to December of the year concerned as well as the mid-year population estimates.
B397: Owner-occupiers refer to the domestic households which own the quarters they occupy.
B398: Public sector housing includes public rental flats and interim housing flats provided by Housing Authority (HA); and public rental flats and Senior Citizen Residences Scheme flats provided by the Housing Society (HS); subsidized sale flats provided by HA under the Home Ownership Scheme (HOS), Private Sector Participation Scheme (PSPS), Tenants Purchase Scheme (TPS), Buy or Rent Option Scheme (BRO), Green Form Subsidised Home Owership Pilot Scheme (GSH), Mortgage Subsidy Scheme (MSS) and Middle Income Housing Scheme (MIH); and flats provided by HS under the Flat-For-Sale Scheme (FFSS), Sandwich Class Housing Scheme (SCHS) and Subsidised Sale Flats Scheme (SSFS); and flats in Urban Renewal Authority Subsidised Sale Flats Scheme; and Public Temporary housing. As from Q1 2002, subsidized sale flats that can be traded in open market are excluded.
B399: Private sector housing includes private housing blocks, flats built under the Urban Improvement Scheme of the Hong Kong Housing Society, villas/bungalows/modern village houses, simple stone structures, quarters in non-residential buildings and private temporary housing. As from Q1 2002, subsidized sale flats that can be traded in open market are also put under this category.
B400: N.A. | C400: Not available.
A401: Source : | B401: Household Statistics Analysis Section, Census and Statistics Department (Enquiry telephone no. : 2887 5508 Enquiry e-mail : ghs@censtatd.gov.hk)
A403: Last revision date: 21 February, 2019

Sheet Household_Pred
A1: 表 1 | B1: 家庭住戶數目及平均住戶人數
A2: Table 1 | B2: Number of domestic households and average household size
A4: 年份 | B4: 家庭住戶數目 | C4: 前五年內平均每年增幅 | D4: 平均住戶人數
A5: Year | B5: Number of domestic households | C5: Average annual growth over the past 5 years | D5: Average household size
A7: 1981 | B7: 1244700 | C7: - | D7: 3.9
A8: 1986 | B8: 1452600 | C8: 41600 | D8: 3.7
A9: 1991 | B9: 1582200 | C9: 25900 | D9: 3.4
A10: 1996 | B10: 1855600 | C10: 54700 | D10: 3.3
A11: 2001 | B11: 2053400 | C11: 39600 | D11: 3.1
A12: 2006 | B12: 2226500 | C12: 34600 | D12: 3
A13: 2011 | B13: 2368800 | C13: 28500 | D13: 2.9
A14: 2016 | B14: 2509700 | C14: 28200 | D14: 2.8
A15: 2021 | B15: 2657000 | C15: 29400 | D15: 2.8
A16: 2026 | B16: 2768900 | C16: 22400 | D16: 2.7
A17: 2031 | B17: 2854500 | C17: 17100 | D17: 2.7
A18: 2036 | B18: 2920200 | C18: 13100 | D18: 2.7
A19: 2041 | B19: 2961400 | C19: 8200 | D19: 2.7
... A21: 2051 | B21: 2949500 | C21: -4500 | D21: 2.7
A23: 註釋： | B23: 虛線以下的數字是推算數字。
B24: 推算結果反映若過往有關生育、死亡、人口遷移及戶主率的人口趨勢仍延續，未來的整體趨勢情況。要注意的是由於未來可能會發生現階段不能預見及預測的情況，因此，有關未來趨勢的假設亦受制於這些不確定因素的發展。
A26: Notes : | B26: Figures below the broken lines are based on projections.
B27: The projection results aim at illustrating what would happen if the past demographic trends on fertility, mortality, movement and headship rates continue into the future. It should however be noted that the assumptions of future trends are subject to uncertainties arising from unforeseeable and unpredictable future events.

Sheet History Type Share
A1: Residential Energy Use by Fuel
A2: Source: | B2: EMSD End-use Data report 2023
A3: 住宅 Residential
A4: 年份 Year | B4: 煤氣及石油氣* Town Gas & Liquefied Petroleum Gas* | D4: 油及煤產品 Oil & Coal Products | F4: 電力 Electricity | H4: 總計 Total
A5: 2006 | B5: 18476 | C5: 0.34 | D5: 79 | E5: 0 | F5: 35428 | G5: 0.66 | H5: 53982
A6: 2007 | B6: 18238 | C6: 0.33 | D6: 57 | E6: 0 | F6: 36422 | G6: 0.67 | H6: 54717
A7: 2008 | B7: 18708 | C7: 0.33 | D7: 41 | E7: 0 | F7: 37100 | G7: 0.66 | H7: 55849
A8: 2009 | B8: 18736 | C8: 0.32 | D8: 23 | E8: 0 | F8: 38972 | G8: 0.68 | H8: 57731
A9: 2010 | B9: 19038 | C9: 0.33 | D9: 13 | E9: 0 | F9: 39344 | G9: 0.67 | H9: 58396
A10: 2011 | B10: 18977 | C10: 0.32 | D10: 8 | E10: 0 | F10: 39872 | G10: 0.68 | H10: 58857
A11: 2012 | B11: 18841 | C11: 0.31 | D11: 8 | E11: 0 | F11: 41189 | G11: 0.69 | H11: 60037
A12: 2013 | B12: 18635 | C12: 0.32 | D12: 7 | E12: 0 | F12: 39941 | G12: 0.68 | H12: 58582
A13: 2014 | B13: 18681 | C13: 0.3 | D13: 7 | E13: 0 | F13: 43415 | G13: 0.7 | H13: 62103
A14: 2015 | B14: 18063 | C14: 0.3 | D14: 8 | E14: 0 | F14: 42368 | G14: 0.7 | H14: 60439
A15: 2016 | B15: 18574 | C15: 0.3 | D15: 10 | E15: 0 | F15: 43120 | G15: 0.7 | H15: 61704
A16: 2017 | B16: 18335 | C16: 0.3 | D16: 14 | E16: 0 | F16: 42127 | G16: 0.7 | H16: 60476
... A20: 2021 | B20: 19242 | C20: 0.29 | D20: 15 | E20: 0 | F20: 47464 | G20: 0.7 | H20: 66721
A23: Commercial Energy Use by Fuel
A24: Source: | B24: EMSD End-use Data report 2022#
A25: 商业 Commercial
A26: 年份 Year | B26: 煤氣及石油氣* Town Gas & Liquefied Petroleum Gas* | D26: 油及煤產品 Oil & Coal Products | F26: 電力 Electricity | H26: 總計 Total
A27: 2006 | B27: 13631 | C27: 0.12 | D27: 4936 | E27: 0.04 | F27: 93317 | G27: 0.83 | H27: 111884
A28: 2007 | B28: 13888 | C28: 0.12 | D28: 4975 | E28: 0.04 | F28: 95051 | G28: 0.83 | H28: 113914
A29: 2008 | B29: 13471 | C29: 0.12 | D29: 4739 | E29: 0.04 | F29: 95543 | G29: 0.84 | H29: 113753
A30: 2009 | B30: 12815 | C30: 0.11 | D30: 4753 | E30: 0.04 | F30: 96728 | G30: 0.85 | H30: 114297
A31: 2010 | B31: 13971 | C31: 0.12 | D31: 4526 | E31: 0.04 | F31: 97894 | G31: 0.84 | H31: 116391
A32: 2011 | B32: 14129 | C32: 0.12 | D32: 1979 | E32: 0.02 | F32: 99905 | G32: 0.86 | H32: 116013
A33: 2012 | B33: 14280 | C33: 0.12 | D33: 1696 | E33: 0.01 | F33: 102353 | G33: 0.86 | H33: 118330
A34: 2013 | B34: 14512 | C34: 0.12 | D34: 1477 | E34: 0.01 | F34: 102221 | G34: 0.86 | H34: 118209
A35: 2014 | B35: 14713 | C35: 0.12 | D35: 1431 | E35: 0.01 | F35: 103471 | G35: 0.87 | H35: 119615
A36: 2015 | B36: 14535 | C36: 0.12 | D36: 1235 | E36: 0.01 | F36: 104647 | G36: 0.87 | H36: 120417
A37: 2016 | B37: 14601 | C37: 0.12 | D37: 1019 | E37: 0.01 | F37: 104839 | G37: 0.87 | H37: 120458
A38: 2017 | B38: 14908 | C38: 0.12 | D38: 830 | E38: 0.01 | F38: 104669 | G38: 0.87 | H38: 120408
... A42: 2021 | B42: 12353 | C42: 0.1 | D42: 490 | E42: 0 | F42: 107240 | G42: 0.89 | H42: 120083

Sheet Commercial8Fuel
A1: Commercial Energy Use by Fuel
A2: Source: | B2: EMSD End-use Data report 2023
A3: 商业 Commercial
A4: 年份 Year | B4: 煤氣及石油氣* Town Gas & Liquefied Petroleum Gas* | D4: 油及煤產品 Oil & Coal Products | F4: 電力 Electricity | H4: 總計 Total
A5: 2006 | B5: 13631 | C5: 0.12 | D5: 4936 | E5: 0.04 | F5: 93317 | G5: 0.86 | H5: 111884
A6: 2007 | B6: 13888 | C6: 0.12 | D6: 4975 | E6: 0.04 | F6: 95051 | G6: 0.86 | H6: 113914
A7: 2008 | B7: 13471 | C7: 0.12 | D7: 4739 | E7: 0.04 | F7: 95543 | G7: 0.86 | H7: 113753
A8: 2009 | B8: 12815 | C8: 0.11 | D8: 4753 | E8: 0.04 | F8: 96728 | G8: 0.87 | H8: 114297
A9: 2010 | B9: 13971 | C9: 0.12 | D9: 4526 | E9: 0.04 | F9: 97894 | G9: 0.87 | H9: 116391
A10: 2011 | B10: 14129 | C10: 0.12 | D10: 1979 | E10: 0.02 | F10: 99905 | G10: 0.87 | H10: 116013
A11: 2012 | B11: 14280 | C11: 0.12 | D11: 1696 | E11: 0.01 | F11: 102353 | G11: 0.87 | H11: 118330
A12: 2013 | B12: 14512 | C12: 0.12 | D12: 1477 | E12: 0.01 | F12: 102221 | G12: 0.87 | H12: 118209
A13: 2014 | B13: 14713 | C13: 0.12 | D13: 1431 | E13: 0.01 | F13: 103471 | G13: 0.87 | H13: 119615
A14: 2015 | B14: 14535 | C14: 0.12 | D14: 1235 | E14: 0.01 | F14: 104647 | G14: 0.87 | H14: 120417
A15: 2016 | B15: 14601 | C15: 0.12 | D15: 1019 | E15: 0.01 | F15: 104839 | G15: 0.87 | H15: 120458
A16: 2017 | B16: 14908 | C16: 0.12 | D16: 830 | E16: 0.01 | F16: 104669 | G16: 0.87 | H16: 120408
... A20: 2021 | B20: 12353 | C20: 0.1 | D20: 490 | E20: 0 | F20: 107240 | G20: 0.89 | H20: 120083

Sheet Residential8EndUse
A1: Residential Sector Energy Consumption by End-use
A2: Source: | B2: EMSD End-use Data report | D2: Chapter : By Sectors&Segments
B4: Data from END-use data report 2023 | G4: Data from END-use data report 2013-2018
B5: Energy | G5: Energy
D6: 2016 | E6: 2021 | H6: Air Conditioning | I6: Hot Water | J6: Lighting | K6: Refrigeration | L6: Office Equipment | M6: Cooking | N6: Others | O6: Sum
B7: 空气调节 | C7: Air Conditioning | D7: 0.25 | E7: 0.28 | G7: 2005 | H7: 0.23 | I7: 0.21 | J7: 0.08 | K7: 0.11 | L7: 0.08 | M7: 0.26 | N7: 0.03 | O7: =SUM(H7:N7) -> 1
B8: 热水 | C8: Hot Water | D8: 0.18 | E8: 0.23 | G8: 2006 | H8: 0.22 | I8: 0.2 | J8: 0.08 | K8: 0.11 | L8: 0.09 | M8: 0.26 | N8: 0.04 | O8: =SUM(H8:N8) -> 1
B9: 照明 | C9: Lighting | D9: 0.06 | E9: 0.04 | G9: 2007 | H9: The Categories are different in End-use Datas which reporting the end-use data
B10: 冷冻 | C10: Refrigeration | D10: 0.09 | E10: 0.05 | G10: 2008 | H10: between 2007 and 2010
B11: 办公设备 | C11: Office Equipment | D11: 0.11 | E11: 0.06 | G11: 2009
B12: 煮食 | C12: Cooking | D12: 0.24 | E12: 0.26 | G12: 2010
B13: 其他 | C13: Others | D13: 0.07 | E13: 0.08 | G13: 2011 | H13: 0.23 | I13: 0.19 | J13: 0.07 | K13: 0.1 | L13: 0.1 | M13: 0.25 | N13: 0.06 | O13: =SUM(H13:N13) -> 1
B14: Sum | D14: =SUM(D7:D13) -> 1 | E14: =SUM(E7:E13) -> 1 | G14: 2012 | H14: 0.23 | I14: 0.19 | J14: 0.07 | K14: 0.09 | L14: 0.1 | M14: 0.26 | N14: 0.06 | O14: =SUM(H14:N14) -> 1
G15: 2013 | H15: 0.21 | I15: 0.19 | J15: 0.07 | K15: 0.09 | L15: 0.11 | M15: 0.26 | N15: 0.07 | O15: =SUM(H15:N15) -> 1
G16: 2014 | H16: 0.25 | I16: 0.18 | J16: 0.06 | K16: 0.09 | L16: 0.1 | M16: 0.25 | N16: 0.07 | O16: =SUM(H16:N16) -> 1
G17: 2015 | H17: 0.25 | I17: 0.18 | J17: 0.06 | K17: 0.1 | L17: 0.1 | M17: 0.24 | N17: 0.07 | O17: =SUM(H17:N17) -> 1
G18: 2016 | H18: 0.27 | I18: 0.24 | J18: 0.04 | K18: 0.05 | L18: 0.06 | M18: 0.26 | N18: 0.08 | O18: =SUM(H18:N18) -> 1
G19: 2017 | H19: 0.26 | I19: 0.24 | J19: 0.04 | K19: 0.05 | L19: 0.06 | M19: 0.27 | N19: 0.08 | O19: =SUM(H19:N19) -> 1
G20: 2018 | H20: 0.26 | I20: 0.24 | J20: 0.04 | K20: 0.05 | L20: 0.06 | M20: 0.27 | N20: 0.08 | O20: =SUM(H20:N20) -> 1
G21: 2019 | H21: 0.26 | I21: 0.23 | J21: 0.04 | K21: 0.05 | L21: 0.06 | M21: 0.27 | N21: 0.09 | O21: =SUM(H21:N21) -> 1
G22: 2020 | H22: 0.27 | I22: 0.23 | J22: 0.04 | K22: 0.05 | L22: 0.06 | M22: 0.26 | N22: 0.08 | O22: =SUM(H22:N22) -> 0.99
G23: 2021 | H23: 0.28 | I23: 0.23 | J23: 0.04 | K23: 0.05 | L23: 0.06 | M23: 0.26 | N23: 0.08 | O23: =SUM(H23:N23) -> 1
G25: Electricity
B26: Electricity | H26: Air Conditioning | I26: Hot Water | J26: Lighting | K26: Refrigeration | L26: Office Equipment | M26: Cooking | N26: Others | O26: Sum
D27: 2016 | E27: 2021 | G27: 2005 | H27: 0.35 | I27: 0.1 | J27: 0.12 | K27: 0.16 | L27: 0.13 | M27: 0.09 | N27: 0.05 | O27: =SUM(H27:N27) -> 1
B28: 空气调节 | C28: Air Conditioning | D28: 0.35 | E28: 0.39 | G28: 2006 | H28: 0.34 | I28: 0.11 | J28: 0.12 | K28: 0.16 | L28: 0.13 | M28: 0.09 | N28: 0.05 | O28: =SUM(H28:N28) -> 1
B29: 热水 | C29: Hot Water | D29: 0.08 | E29: 0.11 | G29: 2007 | H29: No data about electricity demand decomposition between 2007-2011
B30: 照明 | C30: Lighting | D30: 0.09 | E30: 0.05 | G30: 2008
B31: 冷冻 | C31: Refrigeration | D31: 0.14 | E31: 0.08 | G31: 2009
B32: 办公设备 | C32: Office Equipment | D32: 0.15 | E32: 0.08 | G32: 2010
B33: 煮食 | C33: Cooking | D33: 0.09 | E33: 0.17 | G33: 2011
B34: 其他 | C34: Others | D34: 0.1 | E34: 0.11 | G34: 2012 | H34: 0.34 | I34: 0.08 | J34: 0.1 | K34: 0.14 | L34: 0.15 | M34: 0.09 | N34: 0.1 | O34: =SUM(H34:N34) -> 1
B35: Sum | D35: =SUM(D28:D34) -> 1 | E35: =SUM(E28:E34) -> 0.99 | G35: 2013 | H35: 0.31 | I35: 0.09 | J35: 0.1 | K35: 0.14 | L35: 0.16 | M35: 0.1 | N35: 0.1 | O35: =SUM(H35:N35) -> 1
G36: 2014 | H36: 0.36 | I36: 0.08 | J36: 0.09 | K36: 0.13 | L36: 0.15 | M36: 0.09 | N36: 0.1 | O36: =SUM(H36:N36) -> 1
G37: 2015 | H37: 0.36 | I37: 0.08 | J37: 0.09 | K37: 0.14 | L37: 0.15 | M37: 0.09 | N37: 0.09 | O37: =SUM(H37:N37) -> 1
G38: 2016 | H38: 0.35 | I38: 0.08 | J38: 0.09 | K38: 0.14 | L38: 0.15 | M38: 0.09 | N38: 0.1 | O38: =SUM(H38:N38) -> 1
G39: 2017 | H39: 0.38 | I39: 0.12 | J39: 0.05 | K39: 0.08 | L39: 0.08 | M39: 0.18 | N39: 0.12 | O39: =SUM(H39:N39) -> 1.01
G40: 2018 | H40: 0.38 | I40: 0.12 | J40: 0.05 | K40: 0.08 | L40: 0.08 | M40: 0.18 | N40: 0.12 | O40: =SUM(H40:N40) -> 1.01
G41: 2019 | H41: 0.38 | I41: 0.11 | J41: 0.05 | K41: 0.08 | L41: 0.08 | M41: 0.18 | N41: 0.12 | O41: =SUM(H41:N41) -> 1
G42: 2020 | H42: 0.39 | I42: 0.11 | J42: 0.05 | K42: 0.08 | L42: 0.08 | M42: 0.18 | N42: 0.12 | O42: =SUM(H42:N42) -> 1.01
G43: 2021 | H43: 0.39 | I43: 0.11 | J43: 0.05 | K43: 0.08 | L43: 0.08 | M43: 0.17 | N43: 0.11 | O43: =SUM(H43:N43) -> 0.99
G45: Calculating the decomposition of energy other than electricity | V45: 可以解方程解出除电力外(另外两种能源平均）的能源使用占比
G46: Equation: for a certain category(e.g. air conditioning), assuming the fraction of energy consumption, other than electricity consumption, of this category, is x | V46: x*能源用量+35%*电力用量=25%*总能源用量
H47: Then, the total consumption in 2005 in the residential sector in air-conditioning category is
H48: 23%*Total energy consumption in redidential sector=35%*electricity consumption+x*other energy consumption
H50: Therefore, x=(23%*Total energy consumption in redidential sector-35%*electricity consumption)/(other energy consumption)
G51: Calculating Results:
G52: Energy Except Electricity (Town gas, oil&coal) | R52: Energy Except Electricity (Town gas, oil&coal)
H53: Air Conditioning | I53: Hot Water | J53: Lighting | K53: Refrigeration | L53: Office Equipment | M53: Cooking | N53: Others | O53: Sum | P53: 1.Replace negative | S53: Air Conditioning | T53: Hot Water | U53: Lighting | V53: Refrigeration | W53: Office Equipment | X53: Cooking | Y53: Others | Z53: Sum
G54: 2006 | H54: =(Residential8EndUse!H8*Energy8Sec!$B7-Residential8EndUse!H28*Energy8Sec!$B27)/(Energy8Sec!$B7-Energy8Sec!$B27) -> -0.0091344185 | I54: =(Residential8EndUse!I8*Energy8Sec!$B7-Residential8EndUse!I28*Energy8Sec!$B27)/(Energy8Sec!$B7-Energy8Sec!$B27) -> 0.37185081 | J54: =(Residential8EndUse!J8*Energy8Sec!$B7-Residential8EndUse!J28*Energy8Sec!$B27)/(Energy8Sec!$B7-Energy8Sec!$B27) -> 0.0036218605 | K54: =(Residential8EndUse!K8*Energy8Sec!$B7-Residential8EndUse!K28*Energy8Sec!$B27)/(Energy8Sec!$B7-Energy8Sec!$B27) -> 0.014527326 | L54: =(Residential8EndUse!L8*Energy8Sec!$B7-Residential8EndUse!L28*Energy8Sec!$B27)/(Energy8Sec!$B7-Energy8Sec!$B27) -> 0.013621861 | M54: =(Residential8EndUse!M8*Energy8Sec!$B7-Residential8EndUse!M28*Energy8Sec!$B27)/(Energy8Sec!$B7-Energy8Sec!$B27) -> 0.58460709 | N54: =(Residential8EndUse!N8*Energy8Sec!$B7-Residential8EndUse!N28*Energy8Sec!$B27)/(Energy8Sec!$B7-Energy8Sec!$B27) -> 0.020905465 | O54: =(Residential8EndUse!O8*Energy8Sec!$B7-Residential8EndUse!O28*Energy8Sec!$B27)/(Energy8Sec!$B7-Energy8Sec!$B27) -> 1 | P54: value with 0； | R54: 2006 | S54: 0 | T54: 0.37185081 | U54: 0.0036218605 | V54: 0 | W54: 0.013621861 | X54: =1-S54-T54-U54-V54-Y54-W54 -> 0.59 | Y54: 0.020905465 | Z54: 1
G55: 2007 | R55: 2007
G56: 2008 | P56: 2.Adjust "Cooking" to make | R56: 2008
G57: 2009 | P57: sum=100% | R57: 2009
G58: 2010 | R58: 2010
G59: 2011 | R59: 2011
G60: 2012 | H60: =(Residential8EndUse!H14*Energy8Sec!$B13-Residential8EndUse!H34*Energy8Sec!$B33)/(Energy8Sec!$B13-Energy8Sec!$B33) -> -0.01173238 | I60: =(Residential8EndUse!I14*Energy8Sec!$B13-Residential8EndUse!I34*Energy8Sec!$B33)/(Energy8Sec!$B13-Energy8Sec!$B33) -> 0.43173238 | J60: =(Residential8EndUse!J14*Energy8Sec!$B13-Residential8EndUse!J34*Energy8Sec!$B33)/(Energy8Sec!$B13-Energy8Sec!$B33) -> 0.0040729872 | K60: =(Residential8EndUse!K14*Energy8Sec!$B13-Residential8EndUse!K34*Energy8Sec!$B33)/(Energy8Sec!$B13-Energy8Sec!$B33) -> -0.019878355 | L60: =(Residential8EndUse!L14*Energy8Sec!$B13-Residential8EndUse!L34*Energy8Sec!$B33)/(Energy8Sec!$B13-Energy8Sec!$B33) -> -0.0098783546 | M60: =(Residential8EndUse!M14*Energy8Sec!$B13-Residential8EndUse!M34*Energy8Sec!$B33)/(Energy8Sec!$B13-Energy8Sec!$B33) -> 0.63358641 | N60: =(Residential8EndUse!N14*Energy8Sec!$B13-Residential8EndUse!N34*Energy8Sec!$B33)/(Energy8Sec!$B13-Energy8Sec!$B33) -> -0.027902684 | O60: =(Residential8EndUse!O14*Energy8Sec!$B13-Residential8EndUse!O34*Energy8Sec!$B33)/(Energy8Sec!$B13-Energy8Sec!$B33) -> 1 | R60: 2012 | S60: 0 | T60: 0.43173238 | U60: 0.0040729872 | V60: 0 | W60: 0 | X60: =1-S60-T60-U60-V60-Y60-W60 -> 0.56419463 | Y60: 0 | Z60: 1
G61: 2013 | H61: =(Residential8EndUse!H15*Energy8Sec!$B14-Residential8EndUse!H35*Energy8Sec!$B34)/(Energy8Sec!$B14-Energy8Sec!$B34) -> -0.0064471902 | I61: =(Residential8EndUse!I15*Energy8Sec!$B14-Residential8EndUse!I35*Energy8Sec!$B34)/(Energy8Sec!$B14-Energy8Sec!$B34) -> 0.40644719 | J61: =(Residential8EndUse!J15*Energy8Sec!$B14-Residential8EndUse!J35*Energy8Sec!$B34)/(Energy8Sec!$B14-Energy8Sec!$B34) -> 0.005065843 | K61: =(Residential8EndUse!K15*Energy8Sec!$B14-Residential8EndUse!K35*Energy8Sec!$B34)/(Energy8Sec!$B14-Energy8Sec!$B34) -> -0.018223595 | L61: =(Residential8EndUse!L15*Energy8Sec!$B14-Residential8EndUse!L35*Energy8Sec!$B34)/(Energy8Sec!$B14-Energy8Sec!$B34) -> 0.0017764049 | M61: =(Residential8EndUse!M15*Energy8Sec!$B14-Residential8EndUse!M35*Energy8Sec!$B34)/(Energy8Sec!$B14-Energy8Sec!$B34) -> 0.6063155 | N61: =(Residential8EndUse!N15*Energy8Sec!$B14-Residential8EndUse!N35*Energy8Sec!$B34)/(Energy8Sec!$B14-Energy8Sec!$B34) -> 0.005065843 | O61: =(Residential8EndUse!O15*Energy8Sec!$B14-Residential8EndUse!O35*Energy8Sec!$B34)/(Energy8Sec!$B14-Energy8Sec!$B34) -> 1 | R61: 2013 | S61: 0 | T61: 0.40644719 | U61: 0.005065843 | V61: 0 | W61: 0.0017764049 | X61: =1-S61-T61-U61-V61-Y61-W61 -> 0.58164472 | Y61: 0.005065843 | Z61: 1
G62: 2014 | H62: =(Residential8EndUse!H16*Energy8Sec!$B15-Residential8EndUse!H36*Energy8Sec!$B35)/(Energy8Sec!$B15-Energy8Sec!$B35) -> -0.0082130305 | I62: =(Residential8EndUse!I16*Energy8Sec!$B15-Residential8EndUse!I36*Energy8Sec!$B35)/(Energy8Sec!$B15-Energy8Sec!$B35) -> 0.41473912 | J62: =(Residential8EndUse!J16*Energy8Sec!$B15-Residential8EndUse!J36*Energy8Sec!$B35)/(Energy8Sec!$B15-Energy8Sec!$B35) -> -0.010421736 | K62: =(Residential8EndUse!K16*Energy8Sec!$B15-Residential8EndUse!K36*Energy8Sec!$B35)/(Energy8Sec!$B15-Energy8Sec!$B35) -> -0.0038956475 | L62: =(Residential8EndUse!L16*Energy8Sec!$B15-Residential8EndUse!L36*Energy8Sec!$B35)/(Energy8Sec!$B15-Energy8Sec!$B35) -> -0.017369559 | M62: =(Residential8EndUse!M16*Energy8Sec!$B15-Residential8EndUse!M36*Energy8Sec!$B35)/(Energy8Sec!$B15-Energy8Sec!$B35) -> 0.62558259 | N62: =(Residential8EndUse!N16*Energy8Sec!$B15-Residential8EndUse!N36*Energy8Sec!$B35)/(Energy8Sec!$B15-Energy8Sec!$B35) -> -0.0004217356 | O62: =(Residential8EndUse!O16*Energy8Sec!$B15-Residential8EndUse!O36*Energy8Sec!$B35)/(Energy8Sec!$B15-Energy8Sec!$B35) -> 1 | R62: 2014 | S62: 0 | T62: 0.41473912 | U62: 0 | V62: 0 | W62: 0 | X62: =1-S62-T62-U62-V62-Y62-W62 -> 0.58526088 | Y62: 0 | Z62: 1
G63: 2015 | H63: =(Residential8EndUse!H17*Energy8Sec!$B16-Residential8EndUse!H37*Energy8Sec!$B36)/(Energy8Sec!$B16-Energy8Sec!$B36) -> -0.011149837 | I63: =(Residential8EndUse!I17*Energy8Sec!$B16-Residential8EndUse!I37*Energy8Sec!$B36)/(Energy8Sec!$B16-Energy8Sec!$B36) -> 0.41740894 | J63: =(Residential8EndUse!J17*Energy8Sec!$B16-Residential8EndUse!J37*Energy8Sec!$B36)/(Energy8Sec!$B16-Energy8Sec!$B36) -> -0.011222683 | K63: =(Residential8EndUse!K17*Energy8Sec!$B16-Residential8EndUse!K37*Energy8Sec!$B36)/(Energy8Sec!$B16-Energy8Sec!$B36) -> 0.0050364227 | L63: =(Residential8EndUse!L17*Energy8Sec!$B16-Residential8EndUse!L37*Energy8Sec!$B36)/(Energy8Sec!$B16-Energy8Sec!$B36) -> -0.018704472 | M63: =(Residential8EndUse!M17*Energy8Sec!$B16-Residential8EndUse!M37*Energy8Sec!$B36)/(Energy8Sec!$B16-Energy8Sec!$B36) -> 0.59611341 | N63: =(Residential8EndUse!N17*Energy8Sec!$B16-Residential8EndUse!N37*Energy8Sec!$B36)/(Energy8Sec!$B16-Energy8Sec!$B36) -> 0.022518211 | O63: =(Residential8EndUse!O17*Energy8Sec!$B16-Residential8EndUse!O37*Energy8Sec!$B36)/(Energy8Sec!$B16-Energy8Sec!$B36) -> 1 | R63: 2015 | S63: 0 | T63: 0.41740894 | U63: 0 | V63: 0 | W63: 0 | X63: =1-S63-T63-U63-V63-Y63-W63 -> 0.56007285 | Y63: 0.022518211 | Z63: 1
G64: 2016 | H64: =(Residential8EndUse!H18*Energy8Sec!$B17-Residential8EndUse!H38*Energy8Sec!$B37)/(Energy8Sec!$B17-Energy8Sec!$B37) -> 0.081692778 | I64: =(Residential8EndUse!I18*Energy8Sec!$B17-Residential8EndUse!I38*Energy8Sec!$B37)/(Energy8Sec!$B17-Energy8Sec!$B37) -> 0.61661444 | J64: =(Residential8EndUse!J18*Energy8Sec!$B17-Residential8EndUse!J38*Energy8Sec!$B37)/(Energy8Sec!$B17-Energy8Sec!$B37) -> -0.077692014 | K64: =(Residential8EndUse!K18*Energy8Sec!$B17-Residential8EndUse!K38*Energy8Sec!$B37)/(Energy8Sec!$B17-Energy8Sec!$B37) -> -0.16184562 | L64: =(Residential8EndUse!L18*Energy8Sec!$B17-Residential8EndUse!L38*Energy8Sec!$B37)/(Energy8Sec!$B17-Energy8Sec!$B37) -> -0.15184562 | M64: =(Residential8EndUse!M18*Energy8Sec!$B17-Residential8EndUse!M38*Energy8Sec!$B37)/(Energy8Sec!$B17-Energy8Sec!$B37) -> 0.66015285 | N64: =(Residential8EndUse!N18*Energy8Sec!$B17-Residential8EndUse!N38*Energy8Sec!$B37)/(Energy8Sec!$B17-Energy8Sec!$B37) -> 0.032923194 | O64: =(Residential8EndUse!O18*Energy8Sec!$B17-Residential8EndUse!O38*Energy8Sec!$B37)/(Energy8Sec!$B17-Energy8Sec!$B37) -> 1 | R64: 2016 | S64: 0 | T64: 0.41538403 | U64: 0 | V64: 0 | W64: 0.015846389 | X64: =1-S64-T64-U64-V64-Y64-W64 -> 0.56876958 | Y64: 0 | Z64: 1
G65: 2017 | H65: =(Residential8EndUse!H19*Energy8Sec!$B18-Residential8EndUse!H39*Energy8Sec!$B38)/(Energy8Sec!$B18-Energy8Sec!$B38) -> -0.015504932 | I65: =(Residential8EndUse!I19*Energy8Sec!$B18-Residential8EndUse!I39*Energy8Sec!$B38)/(Energy8Sec!$B18-Energy8Sec!$B38) -> 0.51550493 | J65: =(Residential8EndUse!J19*Energy8Sec!$B18-Residential8EndUse!J39*Energy8Sec!$B38)/(Energy8Sec!$B18-Energy8Sec!$B38) -> 0.017041256 | K65: =(Residential8EndUse!K19*Energy8Sec!$B18-Residential8EndUse!K39*Energy8Sec!$B38)/(Energy8Sec!$B18-Energy8Sec!$B38) -> -0.018876233 | L65: =(Residential8EndUse!L19*Energy8Sec!$B18-Residential8EndUse!L39*Energy8Sec!$B38)/(Energy8Sec!$B18-Energy8Sec!$B38) -> 0.014082511 | M65: =(Residential8EndUse!M19*Energy8Sec!$B18-Residential8EndUse!M39*Energy8Sec!$B38)/(Energy8Sec!$B18-Energy8Sec!$B38) -> 0.4766287 | N65: =(Residential8EndUse!N19*Energy8Sec!$B18-Residential8EndUse!N39*Energy8Sec!$B38)/(Energy8Sec!$B18-Energy8Sec!$B38) -> -0.011834977 | O65: =(Residential8EndUse!O19*Energy8Sec!$B18-Residential8EndUse!O39*Energy8Sec!$B38)/(Energy8Sec!$B18-Energy8Sec!$B38) -> 0.97704126 | R65: 2017
G66: 2018 | H66: =(Residential8EndUse!H20*Energy8Sec!$B19-Residential8EndUse!H40*Energy8Sec!$B39)/(Energy8Sec!$B19-Energy8Sec!$B39) -> 0.002953397 | I66: =(Residential8EndUse!I20*Energy8Sec!$B19-Residential8EndUse!I40*Energy8Sec!$B39)/(Energy8Sec!$B19-Energy8Sec!$B39) -> 0.4970466 | J66: =(Residential8EndUse!J20*Energy8Sec!$B19-Residential8EndUse!J40*Energy8Sec!$B39)/(Energy8Sec!$B19-Energy8Sec!$B39) -> 0.01857945 | K66: =(Residential8EndUse!K20*Energy8Sec!$B19-Residential8EndUse!K40*Energy8Sec!$B39)/(Energy8Sec!$B19-Energy8Sec!$B39) -> -0.014261651 | L66: =(Residential8EndUse!L20*Energy8Sec!$B19-Residential8EndUse!L40*Energy8Sec!$B39)/(Energy8Sec!$B19-Energy8Sec!$B39) -> 0.017158899 | M66: =(Residential8EndUse!M20*Energy8Sec!$B19-Residential8EndUse!M40*Energy8Sec!$B39)/(Energy8Sec!$B19-Energy8Sec!$B39) -> 0.46278495 | N66: =(Residential8EndUse!N20*Energy8Sec!$B19-Residential8EndUse!N40*Energy8Sec!$B39)/(Energy8Sec!$B19-Energy8Sec!$B39) -> -0.005682201 | O66: =(Residential8EndUse!O20*Energy8Sec!$B19-Residential8EndUse!O40*Energy8Sec!$B39)/(Energy8Sec!$B19-Energy8Sec!$B39) -> 0.97857945 | R66: 2018
G67: 2019 | H67: =(Residential8EndUse!H21*Energy8Sec!$B20-Residential8EndUse!H41*Energy8Sec!$B40)/(Energy8Sec!$B20-Energy8Sec!$B40) -> -0.024917054 | I67: =(Residential8EndUse!I21*Energy8Sec!$B20-Residential8EndUse!I41*Energy8Sec!$B40)/(Energy8Sec!$B20-Energy8Sec!$B40) -> 0.51491705 | J67: =(Residential8EndUse!J21*Energy8Sec!$B20-Residential8EndUse!J41*Energy8Sec!$B40)/(Energy8Sec!$B20-Energy8Sec!$B40) -> 0.016256912 | K67: =(Residential8EndUse!K21*Energy8Sec!$B20-Residential8EndUse!K41*Energy8Sec!$B40)/(Energy8Sec!$B20-Energy8Sec!$B40) -> -0.021229263 | L67: =(Residential8EndUse!L21*Energy8Sec!$B20-Residential8EndUse!L41*Energy8Sec!$B40)/(Energy8Sec!$B20-Energy8Sec!$B40) -> 0.012513824 | M67: =(Residential8EndUse!M21*Energy8Sec!$B20-Residential8EndUse!M41*Energy8Sec!$B40)/(Energy8Sec!$B20-Energy8Sec!$B40) -> 0.48368779 | N67: =(Residential8EndUse!N21*Energy8Sec!$B20-Residential8EndUse!N41*Energy8Sec!$B40)/(Energy8Sec!$B20-Energy8Sec!$B40) -> 0.018770737 | O67: =(Residential8EndUse!O21*Energy8Sec!$B20-Residential8EndUse!O41*Energy8Sec!$B40)/(Energy8Sec!$B20-Energy8Sec!$B40) -> 1 | R67: 2019
G68: 2020 | H68: =(Residential8EndUse!H22*Energy8Sec!$B21-Residential8EndUse!H42*Energy8Sec!$B41)/(Energy8Sec!$B21-Energy8Sec!$B41) -> -0.013767352 | I68: =(Residential8EndUse!I22*Energy8Sec!$B21-Residential8EndUse!I42*Energy8Sec!$B41)/(Energy8Sec!$B21-Energy8Sec!$B41) -> 0.51376735 | J68: =(Residential8EndUse!J22*Energy8Sec!$B21-Residential8EndUse!J42*Energy8Sec!$B41)/(Energy8Sec!$B21-Energy8Sec!$B41) -> 0.016352721 | K68: =(Residential8EndUse!K22*Energy8Sec!$B21-Residential8EndUse!K42*Energy8Sec!$B41)/(Energy8Sec!$B21-Energy8Sec!$B41) -> -0.020941838 | L68: =(Residential8EndUse!L22*Energy8Sec!$B21-Residential8EndUse!L42*Energy8Sec!$B41)/(Energy8Sec!$B21-Energy8Sec!$B41) -> 0.012705441 | M68: =(Residential8EndUse!M22*Energy8Sec!$B21-Residential8EndUse!M42*Energy8Sec!$B41)/(Energy8Sec!$B21-Energy8Sec!$B41) -> 0.44917823 | N68: =(Residential8EndUse!N22*Energy8Sec!$B21-Residential8EndUse!N42*Energy8Sec!$B41)/(Energy8Sec!$B21-Energy8Sec!$B41) -> -0.014589117 | O68: =(Residential8EndUse!O22*Energy8Sec!$B21-Residential8EndUse!O42*Energy8Sec!$B41)/(Energy8Sec!$B21-Energy8Sec!$B41) -> 0.94270544 | R68: 2020
G69: 2021 | H69: =(Residential8EndUse!H23*Energy8Sec!$B22-Residential8EndUse!H43*Energy8Sec!$B42)/(Energy8Sec!$B22-Energy8Sec!$B42) -> 0.0088757335 | I69: =(Residential8EndUse!I23*Energy8Sec!$B22-Residential8EndUse!I43*Energy8Sec!$B42)/(Energy8Sec!$B22-Energy8Sec!$B42) -> 0.52577193 | J69: =(Residential8EndUse!J23*Energy8Sec!$B22-Residential8EndUse!J43*Energy8Sec!$B42)/(Energy8Sec!$B22-Energy8Sec!$B42) -> 0.015352339 | K69: =(Residential8EndUse!K23*Energy8Sec!$B22-Residential8EndUse!K43*Energy8Sec!$B42)/(Energy8Sec!$B22-Energy8Sec!$B42) -> -0.023942982 | L69: =(Residential8EndUse!L23*Energy8Sec!$B22-Residential8EndUse!L43*Energy8Sec!$B42)/(Energy8Sec!$B22-Energy8Sec!$B42) -> 0.010704679 | M69: =(Residential8EndUse!M23*Energy8Sec!$B22-Residential8EndUse!M43*Energy8Sec!$B42)/(Energy8Sec!$B22-Energy8Sec!$B42) -> 0.48182895 | N69: =(Residential8EndUse!N23*Energy8Sec!$B22-Residential8EndUse!N43*Energy8Sec!$B42)/(Energy8Sec!$B22-Energy8Sec!$B42) -> 0.0060570182 | O69: =(Residential8EndUse!O23*Energy8Sec!$B22-Residential8EndUse!O43*Energy8Sec!$B42)/(Energy8Sec!$B22-Energy8Sec!$B42) -> 1.0246477 | R69: 2021

Sheet Energy8Sec
A1: All Energy/Electricity Consumption by Sector
A2: Source: | B2: EMSD End-use Data report 2018
A3: P23
A5: 终端能源使用All Energy Consumption By Sectors | F5: Unit:Terajoule | H5: Sectors Energy Consumption Percentage
A6: Year | B6: 住宅 Residential | C6: 商业 Commercial | D6: 工业 Industrial | E6: 运输 Transport | F6: 总计 Total | H6: Year | I6: 住宅 Residential | J6: 商业 Commercial | K6: 工业 Industrial | L6: 运输 Transport | M6: 总计 Total
A7: 2006 | B7: 53982 | C7: 111884 | D7: 18934 | E7: 96404 | F7: =SUM(B7:E7) -> 281204 | H7: 2006 | I7: =B7/$F7 -> 0.1919674 | J7: =C7/$F7 -> 0.39787485 | K7: =D7/$F7 -> 0.067331901 | L7: =E7/$F7 -> 0.34282585 | M7: =F7/$F7 -> 1
A8: 2007 | B8: 54717 | C8: 113914 | D8: 17645 | E8: 96165 | F8: =SUM(B8:E8) -> 282441 | H8: 2007 | I8: =B8/$F8 -> 0.19372896 | J8: =C8/$F8 -> 0.40331963 | K8: =D8/$F8 -> 0.062473224 | L8: =E8/$F8 -> 0.34047819 | M8: =F8/$F8 -> 1
A9: 2008 | B9: 55849 | C9: 113753 | D9: 17332 | E9: 94504 | F9: =SUM(B9:E9) -> 281438 | H9: 2008 | I9: =B9/$F9 -> 0.19844158 | J9: =C9/$F9 -> 0.40418494 | K9: =D9/$F9 -> 0.061583724 | L9: =E9/$F9 -> 0.33578977 | M9: =F9/$F9 -> 1
A10: 2009 | B10: 57731 | C10: 114297 | D10: 16129 | E10: 90643 | F10: =SUM(B10:E10) -> 278800 | H10: 2009 | I10: =B10/$F10 -> 0.20706958 | J10: =C10/$F10 -> 0.40996055 | K10: =D10/$F10 -> 0.057851506 | L10: =E10/$F10 -> 0.32511836 | M10: =F10/$F10 -> 1
A11: 2010 | B11: 58396 | C11: 116391 | D11: 16053 | E11: 90889 | F11: =SUM(B11:E11) -> 281729 | H11: 2010 | I11: =B11/$F11 -> 0.20727721 | J11: =C11/$F11 -> 0.41313106 | K11: =D11/$F11 -> 0.05698029 | L11: =E11/$F11 -> 0.32261145 | M11: =F11/$F11 -> 1
A12: 2011 | B12: 58826 | C12: 118558 | D12: 14732 | E12: 90774 | F12: =SUM(B12:E12) -> 282890 | H12: 2011 | I12: =B12/$F12 -> 0.20794655 | J12: =C12/$F12 -> 0.41909576 | K12: =D12/$F12 -> 0.052076779 | L12: =E12/$F12 -> 0.32088091 | M12: =F12/$F12 -> 1
A13: 2012 | B13: 59932 | C13: 120970 | D13: 14723 | E13: 90423 | F13: =SUM(B13:E13) -> 286048 | H13: 2012 | I13: =B13/$F13 -> 0.20951728 | J13: =C13/$F13 -> 0.42290105 | K13: =D13/$F13 -> 0.051470383 | L13: =E13/$F13 -> 0.31611128 | M13: =F13/$F13 -> 1
A14: 2013 | B14: 58394 | C14: 121215 | D14: 14583 | E14: 90198 | F14: =SUM(B14:E14) -> 284390 | H14: 2013 | I14: =B14/$F14 -> 0.20533071 | J14: =C14/$F14 -> 0.42622807 | K14: =D14/$F14 -> 0.051278174 | L14: =E14/$F14 -> 0.31716305 | M14: =F14/$F14 -> 1
A15: 2014 | B15: 61910 | C15: 122711 | D15: 14718 | E15: 89999 | F15: =SUM(B15:E15) -> 289338 | H15: 2014 | I15: =B15/$F15 -> 0.2139712 | J15: =C15/$F15 -> 0.42410952 | K15: =D15/$F15 -> 0.050867843 | L15: =E15/$F15 -> 0.31105143 | M15: =F15/$F15 -> 1
A16: 2015 | B16: 60214 | C16: 123674 | D16: 14853 | E16: 89245 | F16: =SUM(B16:E16) -> 287986 | H16: 2015 | I16: =B16/$F16 -> 0.20908655 | J16: =C16/$F16 -> 0.42944449 | K16: =D16/$F16 -> 0.051575424 | L16: =E16/$F16 -> 0.30989354 | M16: =F16/$F16 -> 1
A17: 2016 | B17: 61439 | C17: 123969 | D17: 13992 | E17: 89819 | F17: =SUM(B17:E17) -> 289219 | H17: 2016 | I17: =B17/$F17 -> 0.21243072 | J17: =C17/$F17 -> 0.42863367 | K17: =D17/$F17 -> 0.048378564 | L17: =E17/$F17 -> 0.31055705 | M17: =F17/$F17 -> 1
A18: 2017 | B18: 60476 | C18: 120408 | D18: 12722 | E18: 86557 | F18: 280162 | H18: 2017 | I18: =B18/$F18 -> 0.21586082 | J18: =C18/$F18 -> 0.42977991 | K18: =D18/$F18 -> 0.045409442 | L18: =E18/$F18 -> 0.30895339 | M18: =F18/$F18 -> 1
A19: 2018 | B19: 61556 | C19: 122220 | D19: 12829 | E19: 85054 | F19: 281659 | H19: 2018 | I19: =B19/$F19 -> 0.21854796 | J19: =C19/$F19 -> 0.43392897 | K19: =D19/$F19 -> 0.045547985 | L19: =E19/$F19 -> 0.30197508 | M19: =F19/$F19 -> 1
A20: 2019 | B20: 61021 | C20: 123001 | D20: 12274 | E20: 85877 | F20: 282174 | H20: 2019 | I20: =B20/$F20 -> 0.21625309 | J20: =C20/$F20 -> 0.4359048 | K20: =D20/$F20 -> 0.043497984 | L20: =E20/$F20 -> 0.30434058 | M20: =F20/$F20 -> 1
A21: 2020 | B21: 66413 | C21: 114512 | D21: 12161 | E21: 78514 | F21: 271600 | H21: 2020 | I21: =B21/$F21 -> 0.24452504 | J21: =C21/$F21 -> 0.42162003 | K21: =D21/$F21 -> 0.044775405 | L21: =E21/$F21 -> 0.28907953 | M21: =F21/$F21 -> 1
A22: 2021 | B22: 66721 | C22: 120083 | D22: 11945 | E22: 81158 | F22: 279907 | H22: 2021 | I22: =B22/$F22 -> 0.23836846 | J22: =C22/$F22 -> 0.42901035 | K22: =D22/$F22 -> 0.042674888 | L22: =E22/$F22 -> 0.2899463 | M22: =F22/$F22 -> 1
A25: 电力使用 Electricity Consuption By Sectors | H25: Sectors Electricity Consumption Percentage
A26: Year | B26: 住宅 Residential | C26: 商业 Commercial | D26: 工业 Industrial | E26: 运输 Transport | F26: 总计 Total | H26: Year | I26: 住宅 Residential | J26: 商业 Commercial | K26: 工业 Industrial | L26: 运输 Transport | M26: 总计 Total | O26: Check
A27: 2006 | B27: 35428 | C27: 93317 | D27: 14015 | E27: 2444 | F27: =SUM(B27:E27) -> 145204 | H27: 2006 | I27: =B27/$F27 -> 0.24398777 | J27: =C27/$F27 -> 0.64266136 | K27: =D27/$F27 -> 0.09651938 | L27: =E27/$F27 -> 0.016831492 | M27: =F27/$F27 -> 1 | O27: =B7*'History Type Share'!G5 -> 35628.12
A28: 2007 | B28: 36422 | C28: 95051 | D28: 13104 | E28: 2495 | F28: =SUM(B28:E28) -> 147072 | H28: 2007 | I28: =B28/$F28 -> 0.24764741 | J28: =C28/$F28 -> 0.64628889 | K28: =D28/$F28 -> 0.089099217 | L28: =E28/$F28 -> 0.01696448 | M28: =F28/$F28 -> 1 | O28: =B8*'History Type Share'!G6 -> 36660.39
A29: 2008 | B29: 37100 | C29: 95543 | D29: 12182 | E29: 2520 | F29: =SUM(B29:E29) -> 147345 | H29: 2008 | I29: =B29/$F29 -> 0.25179002 | J29: =C29/$F29 -> 0.64843055 | K29: =D29/$F29 -> 0.082676711 | L29: =E29/$F29 -> 0.017102718 | M29: =F29/$F29 -> 1 | O29: =B9*'History Type Share'!G7 -> 36860.34
A30: 2009 | B30: 38972 | C30: 96728 | D30: 11143 | E30: 2523 | F30: =SUM(B30:E30) -> 149366 | H30: 2009 | I30: =B30/$F30 -> 0.26091614 | J30: =C30/$F30 -> 0.64759048 | K30: =D30/$F30 -> 0.074601984 | L30: =E30/$F30 -> 0.016891394 | M30: =F30/$F30 -> 1 | O30: =B10*'History Type Share'!G8 -> 39257.08
A31: 2010 | B31: 39344 | C31: 97894 | D31: 11082 | E31: 2540 | F31: =SUM(B31:E31) -> 150860 | H31: 2010 | I31: =B31/$F31 -> 0.26079809 | J31: =C31/$F31 -> 0.64890627 | K31: =D31/$F31 -> 0.073458836 | L31: =E31/$F31 -> 0.016836802 | M31: =F31/$F31 -> 1 | O31: =B11*'History Type Share'!G9 -> 39125.32
A32: 2011 | B32: 39872 | C32: 99594 | D32: 9530 | E32: 2609 | F32: =SUM(B32:E32) -> 151605 | H32: 2011 | I32: =B32/$F32 -> 0.26299924 | J32: =C32/$F32 -> 0.65693084 | K32: =D32/$F32 -> 0.062860724 | L32: =E32/$F32 -> 0.017209195 | M32: =F32/$F32 -> 1 | O32: =B12*'History Type Share'!G10 -> 40001.68
A33: 2012 | B33: 41189 | C33: 101813 | D33: 9356 | E33: 2722 | F33: =SUM(B33:E33) -> 155080 | H33: 2012 | I33: =B33/$F33 -> 0.2655984 | J33: =C33/$F33 -> 0.65651922 | K33: =D33/$F33 -> 0.060330152 | L33: =E33/$F33 -> 0.017552231 | M33: =F33/$F33 -> 1 | O33: =B13*'History Type Share'!G11 -> 41353.08
A34: 2013 | B34: 39941 | C34: 101480 | D34: 9144 | E34: 2796 | F34: =SUM(B34:E34) -> 153361 | H34: 2013 | I34: =B34/$F34 -> 0.26043779 | J34: =C34/$F34 -> 0.66170669 | K34: =D34/$F34 -> 0.059624024 | L34: =E34/$F34 -> 0.018231493 | M34: =F34/$F34 -> 1 | O34: =B14*'History Type Share'!G12 -> 39707.92
A35: 2014 | B35: 43415 | C35: 102627 | D35: 9230 | E35: 2875 | F35: =SUM(B35:E35) -> 158147 | H35: 2014 | I35: =B35/$F35 -> 0.27452307 | J35: =C35/$F35 -> 0.64893422 | K35: =D35/$F35 -> 0.058363421 | L35: =E35/$F35 -> 0.018179289 | M35: =F35/$F35 -> 1 | O35: =B15*'History Type Share'!G13 -> 43337
A36: 2015 | B36: 42368 | C36: 103693 | D36: 9242 | E36: 2972 | F36: =SUM(B36:E36) -> 158275 | H36: 2015 | I36: =B36/$F36 -> 0.26768599 | J36: =C36/$F36 -> 0.65514453 | K36: =D36/$F36 -> 0.058392039 | L36: =E36/$F36 -> 0.018777444 | M36: =F36/$F36 -> 1 | O36: =B16*'History Type Share'!G14 -> 42149.8
A37: 2016 | B37: 43120 | C37: 103881 | D37: 8709 | E37: 2951 | F37: =SUM(B37:E37) -> 158661 | H37: 2016 | I37: =B37/$F37 -> 0.27177441 | J37: =C37/$F37 -> 0.65473557 | K37: =D37/$F37 -> 0.054890616 | L37: =E37/$F37 -> 0.018599404 | M37: =F37/$F37 -> 1 | O37: =B17*'History Type Share'!G15 -> 43007.3
A38: 2017 | B38: 42127 | C38: 104669 | D38: 7963 | E38: 3218 | F38: =SUM(B38:E38) -> 157977 | H38: 2017 | I38: =B38/$F38 -> 0.2666654 | J38: =C38/$F38 -> 0.66255847 | K38: =D38/$F38 -> 0.050406072 | L38: =E38/$F38 -> 0.020370054 | M38: =F38/$F38 -> 1 | O38: =B18*'History Type Share'!G16 -> 42333.2
... A42: 2021 | B42: 47464 | C42: 107240 | D42: 7222 | E42: 3002 | F42: =SUM(B42:E42) -> 164928 | H42: 2021 | I42: =B42/$F42 -> 0.28778619 | J42: =C42/$F42 -> 0.65022313 | K42: =D42/$F42 -> 0.043788805 | L42: =E42/$F42 -> 0.018201882 | M42: =F42/$F42 -> 1 | O42: =B22*'History Type Share'!G20 -> 46704.7

Sheet Private,Public8EndUse
A1: Private/Public Residential Energy Consumption by End-use
A2: Source: | B2: EMSD End-use Data report | D2: Chapter : By Sectors&Segments
A3: Energy
A4: 所有住宅All Residential | K4: 私人住宅Private Housing Segment | U4: 公共住宅 Public Housing | AE4: 重新加总Private+Public
A5: (缺少原始数据 No raw data) | I5: 總計 Total | K5: 年份 Year | L5: 煮食 Cooking | M5: 空氣調節 Air Conditioning | N5: 熱水 Hot Water | O5: 照明 Lighting | P5: 冷凍 Refrigeration | Q5: 辦公室設備 Office Equipment | R5: 其他 1 Others 1 | S5: 總計 Total | U5: 年份 Year | V5: 煮食 Cooking | W5: 空氣調節 Air Conditioning | X5: 熱水 Hot Water | Y5: 照明 Lighting | Z5: 冷凍 Refrigeration | AA5: 辦公室設備 Office Equipment | AB5: 其他 1 Others 1 | AC5: 總計 Total | AE5: 年份 Year | AF5: 煮食 Cooking | AG5: 空氣調節 Air Conditioning | AH5: 熱水 Hot Water | AI5: 照明 Lighting | AJ5: 冷凍 Refrigeration | AK5: 辦公室設備 Office Equipment | AL5: 其他 1 Others 1 | AM5: 總計 Total
I6: 53982 | K6: 2006 | L6: 6828 | M6: 6122 | N6: 5074 | O6: 2148 | P6: 2830 | Q6: 2311 | R6: 898 | S6: 26211 | U6: 2006 | V6: =B120+L120 -> 6900 | W6: =C120+M120 -> 5006 | X6: =D120+N120 -> 5485 | Y6: =E120+O120 -> 1760 | Z6: =F120+P120 -> 2656 | AA6: =G120+Q120 -> 2211 | AB6: =H120+R120 -> 948 | AC6: =I120+S120 -> 24967 | AE6: 2006 | AF6: =L6+V6 -> 13728 | AG6: =M6+W6 -> 11128 | AH6: =N6+X6 -> 10559 | AI6: =O6+Y6 -> 3908 | AJ6: =P6+Z6 -> 5486 | AK6: =Q6+AA6 -> 4522 | AL6: =R6+AB6 -> 1846 | AM6: =S6+AC6 -> 51178
I7: 54717 | K7: 2007 | L7: 6974 | M7: 6176 | N7: 5104 | O7: 2100 | P7: 2962 | Q7: 2469 | R7: 948 | S7: 26733 | U7: 2007 | V7: =B121+L121 -> 7023 | W7: =C121+M121 -> 4963 | X7: =D121+N121 -> 5436 | Y7: =E121+O121 -> 1709 | Z7: =F121+P121 -> 2741 | AA7: =G121+Q121 -> 2323 | AB7: =H121+R121 -> 990 | AC7: =I121+S121 -> 25185 | AE7: 2007 | AF7: =L7+V7 -> 13997 | AG7: =M7+W7 -> 11139 | AH7: =N7+X7 -> 10540 | AI7: =O7+Y7 -> 3809 | AJ7: =P7+Z7 -> 5703 | AK7: =Q7+AA7 -> 4792 | AL7: =R7+AB7 -> 1938 | AM7: =S7+AC7 -> 51918
I8: 55849 | K8: 2008 | L8: 7334 | M8: 6240 | N8: 5323 | O8: 2055 | P8: 3101 | Q8: 2646 | R8: 1002 | S8: 27701 | U8: 2008 | V8: =B122+L122 -> 7334 | W8: =C122+M122 -> 4836 | X8: =D122+N122 -> 5559 | Y8: =E122+O122 -> 1625 | Z8: =F122+P122 -> 2765 | AA8: =G122+Q122 -> 2398 | AB8: =H122+R122 -> 1017 | AC8: =I122+S122 -> 25533 | AE8: 2008 | AF8: =L8+V8 -> 14668 | AG8: =M8+W8 -> 11076 | AH8: =N8+X8 -> 10882 | AI8: =O8+Y8 -> 3680 | AJ8: =P8+Z8 -> 5866 | AK8: =Q8+AA8 -> 5044 | AL8: =R8+AB8 -> 2019 | AM8: =S8+AC8 -> 53234
I9: 57731 | K9: 2009 | L9: 7232 | M9: 6740 | N9: 5344 | O9: 2167 | P9: 3134 | Q9: 2764 | R9: 1164 | S9: 28544 | U9: 2009 | V9: =B123+L123 -> 7307 | W9: =C123+M123 -> 5103 | X9: =D123+N123 -> 5543 | Y9: =E123+O123 -> 1639 | Z9: =F123+P123 -> 2818 | AA9: =G123+Q123 -> 2519 | AB9: =H123+R123 -> 1139 | AC9: =I123+S123 -> 26068 | AE9: 2009 | AF9: =L9+V9 -> 14539 | AG9: =M9+W9 -> 11843 | AH9: =N9+X9 -> 10887 | AI9: =O9+Y9 -> 3806 | AJ9: =P9+Z9 -> 5952 | AK9: =Q9+AA9 -> 5283 | AL9: =R9+AB9 -> 2303 | AM9: =S9+AC9 -> 54612
I10: 58396 | K10: 2010 | L10: 7172 | M10: 6949 | N10: 5279 | O10: 2178 | P10: 3003 | Q10: 2815 | R10: 1333 | S10: 28730 | U10: 2010 | V10: 4661 | W10: 2870 | X10: 3557 | Y10: 947 | Z10: 1818 | AA10: 1558 | AB10: 742 | AC10: 16152 | AE10: 2010 | AF10: =L10+V10 -> 11833 | AG10: =M10+W10 -> 9819 | AH10: =N10+X10 -> 8836 | AI10: =O10+Y10 -> 3125 | AJ10: =P10+Z10 -> 4821 | AK10: =Q10+AA10 -> 4373 | AL10: =R10+AB10 -> 2075 | AM10: =S10+AC10 -> 44882
I11: 58826 | K11: 2011 | L11: 7028 | M11: 7201 | N11: 5259 | O11: 2204 | P11: 2891 | Q11: 2945 | R11: 1606 | S11: 29134 | U11: 2011 | V11: 4740 | W11: 2931 | X11: 3565 | Y11: 942 | Z11: 1763 | AA11: 1642 | AB11: 841 | AC11: 16425 | AE11: 2011 | AF11: =L11+V11 -> 11768 | AG11: =M11+W11 -> 10132 | AH11: =N11+X11 -> 8824 | AI11: =O11+Y11 -> 3146 | AJ11: =P11+Z11 -> 4654 | AK11: =Q11+AA11 -> 4587 | AL11: =R11+AB11 -> 2447 | AM11: =S11+AC11 -> 45559
I12: 59932 | K12: 2012 | L12: 6788 | M12: 7364 | N12: 5113 | O12: 2208 | P12: 2743 | Q12: 3099 | R12: 2008 | S12: 29324 | U12: 2012 | V12: 4804 | W12: 3029 | X12: 3549 | Y12: 970 | Z12: 1725 | AA12: 1794 | AB12: 995 | AC12: 16866 | AE12: 2012 | AF12: =L12+V12 -> 11592 | AG12: =M12+W12 -> 10393 | AH12: =N12+X12 -> 8662 | AI12: =O12+Y12 -> 3178 | AJ12: =P12+Z12 -> 4468 | AK12: =Q12+AA12 -> 4893 | AL12: =R12+AB12 -> 3003 | AM12: =S12+AC12 -> 46190
I13: 58394 | K13: 2013 | L13: 7301 | M13: 6914 | N13: 5450 | O13: 1874 | P13: 2404 | Q13: 2505 | R13: 2042 | S13: 28489 | U13: 2013 | V13: 5085 | W13: 2883 | X13: 3661 | Y13: 823 | Z13: 1544 | AA13: 1573 | AB13: 1035 | AC13: 16604 | AE13: 2013 | AF13: =L13+V13 -> 12386 | AG13: =M13+W13 -> 9797 | AH13: =N13+X13 -> 9111 | AI13: =O13+Y13 -> 2697 | AJ13: =P13+Z13 -> 3948 | AK13: =Q13+AA13 -> 4078 | AL13: =R13+AB13 -> 3077 | AM13: =S13+AC13 -> 45093
I14: 61910 | K14: 2014 | L14: 7499 | M14: 8322 | N14: 6055 | O14: 1752 | P14: 2292 | Q14: 2357 | R14: 2271 | S14: 30548 | U14: 2014 | V14: 5083 | W14: 3496 | X14: 3866 | Y14: 775 | Z14: 1495 | AA14: 1489 | AB14: 1168 | AC14: 17371 | AE14: 2014 | AF14: =L14+V14 -> 12582 | AG14: =M14+W14 -> 11818 | AH14: =N14+X14 -> 9921 | AI14: =O14+Y14 -> 2527 | AJ14: =P14+Z14 -> 3787 | AK14: =Q14+AA14 -> 3846 | AL14: =R14+AB14 -> 3439 | AM14: =S14+AC14 -> 47919
I15: 60214 | K15: 2015 | L15: 7243 | M15: 8046 | N15: 6136 | O15: 1500 | P15: 1972 | Q15: 2047 | R15: 2296 | S15: 29241 | U15: 2015 | V15: 4912 | W15: 3580 | X15: 3866 | Y15: 691 | Z15: 1349 | AA15: 1338 | AB15: 1235 | AC15: 16970 | AE15: 2015 | AF15: =L15+V15 -> 12155 | AG15: =M15+W15 -> 11626 | AH15: =N15+X15 -> 10002 | AI15: =O15+Y15 -> 2191 | AJ15: =P15+Z15 -> 3321 | AK15: =Q15+AA15 -> 3385 | AL15: =R15+AB15 -> 3531 | AM15: =S15+AC15 -> 46211
I16: 61439 | K16: 2016 | L16: 7706 | M16: 8323 | N16: 6933 | O16: 1379 | P16: 1789 | Q16: 1893 | R16: 2465 | S16: 30489 | U16: 2016 | V16: 4942 | W16: 3758 | X16: 4079 | Y16: 633 | Z16: 1226 | AA16: 1231 | AB16: 1320 | AC16: 17190 | AE16: 2016 | AF16: =L16+V16 -> 12648 | AG16: =M16+W16 -> 12081 | AH16: =N16+X16 -> 11012 | AI16: =O16+Y16 -> 2012 | AJ16: =P16+Z16 -> 3015 | AK16: =Q16+AA16 -> 3124 | AL16: =R16+AB16 -> 3785 | AM16: =S16+AC16 -> 47679
I17: 59992 | K17: 2017 | L17: 7888 | M17: 8203 | N17: 7242 | O17: 1220 | P17: 1523 | Q17: 1652 | R17: 1036 | S17: 30231 | U17: 2017 | V17: 4786 | W17: 3829 | X17: 4048 | Y17: 571 | Z17: 1055 | AA17: 1082 | AB17: 550 | AC17: 16713 | AE17: 2017 | AF17: =L17+V17 -> 12674 | AG17: =M17+W17 -> 12032 | AH17: =N17+X17 -> 11290 | AI17: =O17+Y17 -> 1791 | AJ17: =P17+Z17 -> 2578 | AK17: =Q17+AA17 -> 2734 | AL17: =R17+AB17 -> 1586 | AM17: =S17+AC17 -> 46944
I18: 60793 | K18: 2018 | L18: 8216 | M18: 8009 | N18: 7215 | O18: 1203 | P18: 1502 | Q18: 1629 | R18: 1022 | S18: 30241 | U18: 2018 | V18: 4960 | W18: 3783 | X18: 4139 | Y18: 570 | Z18: 1054 | AA18: 1080 | AB18: 549 | AC18: 16925 | AE18: 2018 | AF18: =L18+V18 -> 13176 | AG18: =M18+W18 -> 11792 | AH18: =N18+X18 -> 11354 | AI18: =O18+Y18 -> 1773 | AJ18: =P18+Z18 -> 2556 | AK18: =Q18+AA18 -> 2709 | AL18: =R18+AB18 -> 1571 | AM18: =S18+AC18 -> 47166
I19: 61025 | K19: 2019 | L19: 7850 | M19: 8206 | N19: 7035 | O19: 1239 | P19: 1567 | Q19: 1678 | R19: 1052 | S19: 30115 | U19: 2019 | V19: 4792 | W19: 3839 | X19: 3980 | Y19: 587 | Z19: 1098 | AA19: 1111 | AB19: 565 | AC19: 16785 | AE19: 2019 | AF19: =L19+V19 -> 12642 | AG19: =M19+W19 -> 12045 | AH19: =N19+X19 -> 11015 | AI19: =O19+Y19 -> 1826 | AJ19: =P19+Z19 -> 2665 | AK19: =Q19+AA19 -> 2789 | AL19: =R19+AB19 -> 1617 | AM19: =S19+AC19 -> 46900
I20: 66416 | K20: 2020 | L20: 8417 | M20: 9257 | N20: 7711 | O20: 1320 | P20: 1667 | Q20: 1788 | R20: 1122 | S20: 32856 | U20: 2020 | V20: 5131 | W20: 4280 | X20: 4318 | Y20: 617 | Z20: 1153 | AA20: 1169 | AB20: 595 | AC20: 18119 | AE20: 2020 | AF20: =L20+V20 -> 13548 | AG20: =M20+W20 -> 13537 | AH20: =N20+X20 -> 12029 | AI20: =O20+Y20 -> 1937 | AJ20: =P20+Z20 -> 2820 | AK20: =Q20+AA20 -> 2957 | AL20: =R20+AB20 -> 1717 | AM20: =S20+AC20 -> 50975
I21: 66721 | K21: 2021 | L21: 8198 | M21: 9309 | N21: 7349 | O21: 1301 | P21: 1651 | Q21: 1762 | R21: 1105 | S21: 32236 | U21: 2021 | V21: 5121 | W21: 4466 | X21: 4249 | Y21: 630 | Z21: 1183 | AA21: 1193 | AB21: 607 | AC21: 18298 | AE21: 2021 | AF21: =L21+V21 -> 13319 | AG21: =M21+W21 -> 13775 | AH21: =N21+X21 -> 11598 | AI21: =O21+Y21 -> 1931 | AJ21: =P21+Z21 -> 2834 | AK21: =Q21+AA21 -> 2955 | AL21: =R21+AB21 -> 1712 | AM21: =S21+AC21 -> 50534
A23: 转换为百分比Change to percentage
A24: Year | B24: Air Conditioning | C24: Hot Water | D24: Lighting | E24: Refrigeration | F24: Office Equipment | G24: Cooking | H24: Others | I24: Sum | K24: 私人住宅Private Housing Segment | U24: 公共住宅 Public Housing | AE24: 重新加总Private+Public
A25: 2005 | B25: 0.23 | C25: 0.21 | D25: 0.08 | E25: 0.11 | F25: 0.08 | G25: 0.26 | H25: 0.03 | I25: =SUM(B25:H25) -> 1 | K25: 年份 Year | L25: 煮食 Cooking | M25: 空氣調節 Air Conditioning | N25: 熱水 Hot Water | O25: 照明 Lighting | P25: 冷凍 Refrigeration | Q25: 辦公室設備 Office Equipment | R25: 其他 1 Others 1 | S25: 總計 Total | U25: 年份 Year | V25: 煮食 Cooking | W25: 空氣調節 Air Conditioning | X25: 熱水 Hot Water | Y25: 照明 Lighting | Z25: 冷凍 Refrigeration | AA25: 辦公室設備 Office Equipment | AB25: 其他 1 Others 1 | AC25: 總計 Total | AE25: 年份 Year | AF25: 煮食 Cooking | AG25: 空氣調節 Air Conditioning | AH25: 熱水 Hot Water | AI25: 照明 Lighting | AJ25: 冷凍 Refrigeration | AK25: 辦公室設備 Office Equipment | AL25: 其他 1 Others 1 | AM25: 總計 Total
A26: 2006 | B26: 0.22 | C26: 0.2 | D26: 0.08 | E26: 0.11 | F26: 0.09 | G26: 0.26 | H26: 0.04 | I26: =SUM(B26:H26) -> 1 | K26: 2006 | L26: =L6/$S6 -> 0.26050132 | M26: =M6/$S6 -> 0.23356606 | N26: =N6/$S6 -> 0.19358285 | O26: =O6/$S6 -> 0.081950326 | P26: =P6/$S6 -> 0.10796994 | Q26: =Q6/$S6 -> 0.088169089 | R26: =R6/$S6 -> 0.034260425 | S26: =S6/$S6 -> 1 | U26: 2006 | V26: =V6/$AC6 -> 0.2763648 | W26: =W6/$AC6 -> 0.20050467 | X26: =X6/$AC6 -> 0.21968999 | Y26: =Y6/$AC6 -> 0.070493051 | Z26: =Z6/$AC6 -> 0.10638042 | AA26: =AA6/$AC6 -> 0.088556895 | AB26: =AB6/$AC6 -> 0.037970121 | AC26: =AC6/$AC6 -> 1 | AE26: 2006 | AF26: =(L26*$S6+V26*$AC6)/$I6 -> 0.25430699 | AG26: =(M26*$S6+W26*$AC6)/$I6 -> 0.20614279 | AH26: =(N26*$S6+X26*$AC6)/$I6 -> 0.19560224 | AI26: =(O26*$S6+Y26*$AC6)/$I6 -> 0.072394502 | AJ26: =(P26*$S6+Z26*$AC6)/$I6 -> 0.10162647 | AK26: =(Q26*$S6+AA26*$AC6)/$I6 -> 0.083768664 | AL26: =(R26*$S6+AB26*$AC6)/$I6 -> 0.034196584 | AM26: =(S26*$S6+AC26*$AC6)/$I6 -> 0.94805676
A27: 2007 | B27: The Categories are different in End-use Datas which reporting the end-use data | K27: 2007 | L27: =L7/$S7 -> 0.26087607 | M27: =M7/$S7 -> 0.23102532 | N27: =N7/$S7 -> 0.19092507 | O27: =O7/$S7 -> 0.078554595 | P27: =P7/$S7 -> 0.11079939 | Q27: =Q7/$S7 -> 0.09235776 | R27: =R7/$S7 -> 0.035461789 | S27: =S7/$S7 -> 1 | U27: 2007 | V27: =V7/$AC7 -> 0.27885646 | W27: =W7/$AC7 -> 0.19706174 | X27: =X7/$AC7 -> 0.21584276 | Y27: =Y7/$AC7 -> 0.067857852 | Z27: =Z7/$AC7 -> 0.10883462 | AA27: =AA7/$AC7 -> 0.092237443 | AB27: =AB7/$AC7 -> 0.039309113 | AC27: =AC7/$AC7 -> 1 | AE27: 2007 | AF27: =(L27*$S7+V27*$AC7)/$I7 -> 0.25580715 | AG27: =(M27*$S7+W27*$AC7)/$I7 -> 0.20357476 | AH27: =(N27*$S7+X27*$AC7)/$I7 -> 0.19262752 | AI27: =(O27*$S7+Y27*$AC7)/$I7 -> 0.069612735 | AJ27: =(P27*$S7+Z27*$AC7)/$I7 -> 0.10422721 | AK27: =(Q27*$S7+AA27*$AC7)/$I7 -> 0.087577901 | AL27: =(R27*$S7+AB27*$AC7)/$I7 -> 0.035418608 | AM27: =(S27*$S7+AC27*$AC7)/$I7 -> 0.94884588
A28: 2008 | B28: between 2007 and 2010 | K28: 2008 | L28: =L8/$S8 -> 0.26475578 | M28: =M8/$S8 -> 0.22526263 | N28: =N8/$S8 -> 0.19215913 | O28: =O8/$S8 -> 0.074185047 | P28: =P8/$S8 -> 0.11194542 | Q28: =Q8/$S8 -> 0.095520017 | R28: =R8/$S8 -> 0.036171979 | S28: =S8/$S8 -> 1 | U28: 2008 | V28: =V8/$AC8 -> 0.28723613 | W28: =W8/$AC8 -> 0.18940195 | X28: =X8/$AC8 -> 0.21771825 | Y28: =Y8/$AC8 -> 0.063643129 | Z28: =Z8/$AC8 -> 0.10829123 | AA28: =AA8/$AC8 -> 0.093917675 | AB28: =AB8/$AC8 -> 0.039830807 | AC28: =AC8/$AC8 -> 1 | AE28: 2008 | AF28: =(L28*$S8+V28*$AC8)/$I8 -> 0.26263675 | AG28: =(M28*$S8+W28*$AC8)/$I8 -> 0.19832047 | AH28: =(N28*$S8+X28*$AC8)/$I8 -> 0.19484682 | AI28: =(O28*$S8+Y28*$AC8)/$I8 -> 0.065891959 | AJ28: =(P28*$S8+Z28*$AC8)/$I8 -> 0.10503321 | AK28: =(Q28*$S8+AA28*$AC8)/$I8 -> 0.090314956 | AL28: =(R28*$S8+AB28*$AC8)/$I8 -> 0.03615105 | AM28: =(S28*$S8+AC28*$AC8)/$I8 -> 0.95317732
A29: 2009 | K29: 2009 | L29: =L9/$S9 -> 0.25336323 | M29: =M9/$S9 -> 0.23612668 | N29: =N9/$S9 -> 0.18721973 | O29: =O9/$S9 -> 0.075917881 | P29: =P9/$S9 -> 0.1097954 | Q29: =Q9/$S9 -> 0.09683296 | R29: =R9/$S9 -> 0.040779148 | S29: =S9/$S9 -> 1 | U29: 2009 | V29: =V9/$AC9 -> 0.28030536 | W29: =W9/$AC9 -> 0.19575725 | X29: =X9/$AC9 -> 0.21263618 | Y29: =Y9/$AC9 -> 0.062874022 | Z29: =Z9/$AC9 -> 0.10810189 | AA29: =AA9/$AC9 -> 0.096631886 | AB29: =AB9/$AC9 -> 0.043693417 | AC29: =AC9/$AC9 -> 1 | AE29: 2009 | AF29: =(L29*$S9+V29*$AC9)/$I9 -> 0.25184043 | AG29: =(M29*$S9+W29*$AC9)/$I9 -> 0.20514109 | AH29: =(N29*$S9+X29*$AC9)/$I9 -> 0.18858152 | AI29: =(O29*$S9+Y29*$AC9)/$I9 -> 0.065926452 | AJ29: =(P29*$S9+Z29*$AC9)/$I9 -> 0.10309886 | AK29: =(Q29*$S9+AA29*$AC9)/$I9 -> 0.091510627 | AL29: =(R29*$S9+AB29*$AC9)/$I9 -> 0.039891912 | AM29: =(S29*$S9+AC29*$AC9)/$I9 -> 0.94597357
A30: 2010 | K30: 2010 | L30: =L10/$S10 -> 0.24963453 | M30: =M10/$S10 -> 0.24187261 | N30: =N10/$S10 -> 0.18374521 | O30: =O10/$S10 -> 0.075809259 | P30: =P10/$S10 -> 0.10452489 | Q30: =Q10/$S10 -> 0.097981204 | R30: =R10/$S10 -> 0.046397494 | S30: =S10/$S10 -> 1 | U30: 2010 | V30: =V10/$AC10 -> 0.28857107 | W30: =W10/$AC10 -> 0.17768697 | X30: =X10/$AC10 -> 0.22022041 | Y30: =Y10/$AC10 -> 0.05863051 | Z30: =Z10/$AC10 -> 0.11255572 | AA30: =AA10/$AC10 -> 0.096458643 | AB30: =AB10/$AC10 -> 0.045938583 | AC30: =AC10/$AC10 -> 1 | AE30: 2010 | AF30: =(L30*$S10+V30*$AC10)/$I10 -> 0.20263374 | AG30: =(M30*$S10+W30*$AC10)/$I10 -> 0.16814508 | AH30: =(N30*$S10+X30*$AC10)/$I10 -> 0.15131173 | AI30: =(O30*$S10+Y30*$AC10)/$I10 -> 0.053513939 | AJ30: =(P30*$S10+Z30*$AC10)/$I10 -> 0.082557024 | AK30: =(Q30*$S10+AA30*$AC10)/$I10 -> 0.074885266 | AL30: =(R30*$S10+AB30*$AC10)/$I10 -> 0.035533256 | AM30: =(S30*$S10+AC30*$AC10)/$I10 -> 0.76858004
A31: 2011 | B31: 0.23 | C31: 0.19 | D31: 0.07 | E31: 0.1 | F31: 0.1 | G31: 0.25 | H31: 0.06 | I31: =SUM(B31:H31) -> 1 | K31: 2011 | L31: =L11/$S11 -> 0.24123018 | M31: =M11/$S11 -> 0.24716826 | N31: =N11/$S11 -> 0.18051074 | O31: =O11/$S11 -> 0.075650443 | P31: =P11/$S11 -> 0.099231139 | Q31: =Q11/$S11 -> 0.10108464 | R31: =R11/$S11 -> 0.055124597 | S31: =S11/$S11 -> 1 | U31: 2011 | V31: =V11/$AC11 -> 0.28858447 | W31: =W11/$AC11 -> 0.17844749 | X31: =X11/$AC11 -> 0.21704718 | Y31: =Y11/$AC11 -> 0.057351598 | Z31: =Z11/$AC11 -> 0.10733638 | AA31: =AA11/$AC11 -> 0.099969559 | AB31: =AB11/$AC11 -> 0.051202435 | AC31: =AC11/$AC11 -> 1 | AE31: 2011 | AF31: =(L31*$S11+V31*$AC11)/$I11 -> 0.2000476 | AG31: =(M31*$S11+W31*$AC11)/$I11 -> 0.17223677 | AH31: =(N31*$S11+X31*$AC11)/$I11 -> 0.1500017 | AI31: =(O31*$S11+Y31*$AC11)/$I11 -> 0.053479754 | AJ31: =(P31*$S11+Z31*$AC11)/$I11 -> 0.079114677 | AK31: =(Q31*$S11+AA31*$AC11)/$I11 -> 0.077975725 | AL31: =(R31*$S11+AB31*$AC11)/$I11 -> 0.041597253 | AM31: =(S31*$S11+AC31*$AC11)/$I11 -> 0.77447047
A32: 2012 | B32: 0.23 | C32: 0.19 | D32: 0.07 | E32: 0.09 | F32: 0.1 | G32: 0.26 | H32: 0.06 | I32: =SUM(B32:H32) -> 1 | K32: 2012 | L32: =L12/$S12 -> 0.23148274 | M32: =M12/$S12 -> 0.25112536 | N32: =N12/$S12 -> 0.1743623 | O32: =O12/$S12 -> 0.075296685 | P32: =P12/$S12 -> 0.093541127 | Q32: =Q12/$S12 -> 0.10568135 | R32: =R12/$S12 -> 0.068476333 | S32: =S12/$S12 -> 1 | U32: 2012 | V32: =V12/$AC12 -> 0.28483339 | W32: =W12/$AC12 -> 0.17959208 | X32: =X12/$AC12 -> 0.21042334 | Y32: =Y12/$AC12 -> 0.057512155 | Z32: =Z12/$AC12 -> 0.10227677 | AA32: =AA12/$AC12 -> 0.10636784 | AB32: =AB12/$AC12 -> 0.058994427 | AC32: =AC12/$AC12 -> 1 | AE32: 2012 | AF32: =(L32*$S12+V32*$AC12)/$I12 -> 0.19341921 | AG32: =(M32*$S12+W32*$AC12)/$I12 -> 0.1734132 | AH32: =(N32*$S12+X32*$AC12)/$I12 -> 0.14453047 | AI32: =(O32*$S12+Y32*$AC12)/$I12 -> 0.053026764 | AJ32: =(P32*$S12+Z32*$AC12)/$I12 -> 0.074551158 | AK32: =(Q32*$S12+AA32*$AC12)/$I12 -> 0.081642528 | AL32: =(R32*$S12+AB32*$AC12)/$I12 -> 0.050106788 | AM32: =(S32*$S12+AC32*$AC12)/$I12 -> 0.7707068
A33: 2013 | B33: 0.21 | C33: 0.19 | D33: 0.07 | E33: 0.09 | F33: 0.11 | G33: 0.26 | H33: 0.07 | I33: =SUM(B33:H33) -> 1 | K33: 2013 | L33: =L13/$S13 -> 0.25627435 | M33: =M13/$S13 -> 0.24269016 | N33: =N13/$S13 -> 0.19130191 | O33: =O13/$S13 -> 0.065779775 | P33: =P13/$S13 -> 0.084383446 | Q33: =Q13/$S13 -> 0.087928674 | R33: =R13/$S13 -> 0.071676788 | S33: =S13/$S13 -> 1 | U33: 2013 | V33: =V13/$AC13 -> 0.30625151 | W33: =W17/$AC17 -> 0.22910309 | X33: =X13/$AC13 -> 0.22048904 | Y33: =Y13/$AC13 -> 0.04956637 | Z33: =Z13/$AC13 -> 0.092989641 | AA33: =AA13/$AC13 -> 0.094736208 | AB33: =AB13/$AC13 -> 0.062334377 | AC33: =AC13/$AC13 -> 1 | AE33: 2013 | AF33: =(L33*$S13+V33*$AC13)/$I13 -> 0.21211083 | AG33: =(M33*$S13+W33*$AC13)/$I13 -> 0.18354673 | AH33: =(N33*$S13+X33*$AC13)/$I13 -> 0.1560263 | AI33: =(O33*$S13+Y33*$AC13)/$I13 -> 0.046186252 | AJ33: =(P33*$S13+Z33*$AC13)/$I13 -> 0.067609686 | AK33: =(Q33*$S13+AA33*$AC13)/$I13 -> 0.069835942 | AL33: =(R33*$S13+AB33*$AC13)/$I13 -> 0.05269377 | AM33: =(S33*$S13+AC33*$AC13)/$I13 -> 0.77221975
A34: 2014 | B34: 0.25 | C34: 0.18 | D34: 0.06 | E34: 0.09 | F34: 0.1 | G34: 0.25 | H34: 0.07 | I34: =SUM(B34:H34) -> 1 | K34: 2014 | L34: =L14/$S14 -> 0.24548252 | M34: =M14/$S14 -> 0.27242373 | N34: =N14/$S14 -> 0.19821265 | O34: =O14/$S14 -> 0.057352363 | P34: =P14/$S14 -> 0.075029462 | Q34: =Q14/$S14 -> 0.077157261 | R34: =R14/$S14 -> 0.074342019 | S34: =S14/$S14 -> 1 | U34: 2014 | V34: =V14/$AC14 -> 0.29261413 | W34: =W13/$AC13 -> 0.17363286 | X34: =X14/$AC14 -> 0.22255483 | Y34: =Y14/$AC14 -> 0.044614588 | Z34: =Z14/$AC14 -> 0.086062979 | AA34: =AA14/$AC14 -> 0.085717575 | AB34: =AB14/$AC14 -> 0.067238501 | AC34: =AC14/$AC14 -> 1 | AE34: 2014 | AF34: =(L34*$S14+V34*$AC14)/$I14 -> 0.2032305 | AG34: =(M34*$S14+W34*$AC14)/$I14 -> 0.18313966 | AH34: =(N34*$S14+X34*$AC14)/$I14 -> 0.16024875 | AI34: =(O34*$S14+Y34*$AC14)/$I14 -> 0.040817315 | AJ34: =(P34*$S14+Z34*$AC14)/$I14 -> 0.06116944 | AK34: =(Q34*$S14+AA34*$AC14)/$I14 -> 0.062122436 | AL34: =(R34*$S14+AB34*$AC14)/$I14 -> 0.055548377 | AM34: =(S34*$S14+AC34*$AC14)/$I14 -> 0.77401066
A35: 2015 | K35: 2015 | L35: =L15/$S15 -> 0.24770015 | M35: =M15/$S15 -> 0.27516159 | N35: =N15/$S15 -> 0.20984234 | O35: =O15/$S15 -> 0.051297835 | P35: =P15/$S15 -> 0.067439554 | Q35: =Q15/$S15 -> 0.070004446 | R35: =R15/$S15 -> 0.078519886 | S35: =S15/$S15 -> 1 | U35: 2015 | V35: =V15/$AC15 -> 0.28945197 | W35: =W14/$AC14 -> 0.20125497 | X35: =X15/$AC15 -> 0.22781379 | Y35: =Y15/$AC15 -> 0.040718916 | Z35: =Z15/$AC15 -> 0.079493223 | AA35: =AA15/$AC15 -> 0.078845021 | AB35: =AB15/$AC15 -> 0.072775486 | AC35: =AC15/$AC15 -> 1 | AE35: 2015 | AF35: =(L35*$S15+V35*$AC15)/$I15 -> 0.20186335 | AG35: =(M35*$S15+W35*$AC15)/$I15 -> 0.19034272 | AH35: =(N35*$S15+X35*$AC15)/$I15 -> 0.16610755 | AI35: =(O35*$S15+Y35*$AC15)/$I15 -> 0.036386887 | AJ35: =(P35*$S15+Z35*$AC15)/$I15 -> 0.055153287 | AK35: =(Q35*$S15+AA35*$AC15)/$I15 -> 0.056216162 | AL35: =(R35*$S15+AB35*$AC15)/$I15 -> 0.058640848 | AM35: =(S35*$S15+AC35*$AC15)/$I15 -> 0.76744611
A36: 2016 | K36: 2016 | L36: =L16/$S16 -> 0.25274689 | M36: =M16/$S16 -> 0.2729837 | N36: =N16/$S16 -> 0.22739349 | O36: =O16/$S16 -> 0.045229427 | P36: =P16/$S16 -> 0.0586769 | Q36: =Q16/$S16 -> 0.062087966 | R36: =R16/$S16 -> 0.080848831 | S36: =S16/$S16 -> 1 | U36: 2016 | V36: =V16/$AC16 -> 0.28749273 | W36: =W15/$AC15 -> 0.21096052 | X36: =X16/$AC16 -> 0.23728912 | Y36: =Y16/$AC16 -> 0.036823735 | Z36: =Z16/$AC16 -> 0.071320535 | AA36: =AA16/$AC16 -> 0.071611402 | AB36: =AB16/$AC16 -> 0.076788831 | AC36: =AC16/$AC16 -> 1 | AE36: 2016 | AF36: =(L36*$S16+V36*$AC16)/$I16 -> 0.20586273 | AG36: =(M36*$S16+W36*$AC16)/$I16 -> 0.19449228 | AH36: =(N36*$S16+X36*$AC16)/$I16 -> 0.17923469 | AI36: =(O36*$S16+Y36*$AC16)/$I16 -> 0.032747929 | AJ36: =(P36*$S16+Z36*$AC16)/$I16 -> 0.049073064 | AK36: =(Q36*$S16+AA36*$AC16)/$I16 -> 0.050847182 | AL36: =(R36*$S16+AB36*$AC16)/$I16 -> 0.06160582 | AM36: =(S36*$S16+AC36*$AC16)/$I16 -> 0.77603802
A37: 2017 | K37: 2017 | L37: =L17/$S17 -> 0.26092422 | M37: =M17/$S17 -> 0.27134398 | N37: =N17/$S17 -> 0.23955542 | O37: =O17/$S17 -> 0.040355926 | P37: =P17/$S17 -> 0.05037875 | Q37: =Q17/$S17 -> 0.054645893 | R37: =R17/$S17 -> 0.034269459 | S37: =S17/$S17 -> 1 | U37: 2017 | V37: =V17/$AC17 -> 0.28636391 | W37: =W16/$AC16 -> 0.21861547 | X37: =X17/$AC17 -> 0.24220667 | Y37: =Y17/$AC17 -> 0.034165021 | Z37: =Z17/$AC17 -> 0.063124514 | AA37: =AA17/$AC17 -> 0.064740023 | AB37: =AB17/$AC17 -> 0.032908514 | AC37: =AC17/$AC17 -> 1 | AE37: 2017 | AF37: =(L37*$S17+V37*$AC17)/$I17 -> 0.2112615 | AG37: =(M37*$S17+W37*$AC17)/$I17 -> 0.19763836 | AH37: =(N37*$S17+X37*$AC17)/$I17 -> 0.18819176 | AI37: =(O37*$S17+Y37*$AC17)/$I17 -> 0.029853981 | AJ37: =(P37*$S17+Z37*$AC17)/$I17 -> 0.042972396 | AK37: =(Q37*$S17+AA37*$AC17)/$I17 -> 0.045572743 | AL37: =(R37*$S17+AB37*$AC17)/$I17 -> 0.026436858 | AM37: =(S37*$S17+AC37*$AC17)/$I17 -> 0.78250433
A38: 2018 | K38: 2018 | L38: =L18/$S18 -> 0.27168414 | M38: =M18/$S18 -> 0.26483913 | N38: =N18/$S18 -> 0.23858338 | O38: =O18/$S18 -> 0.039780431 | P38: =P18/$S18 -> 0.04966767 | Q38: =Q18/$S18 -> 0.053867266 | R38: =R18/$S18 -> 0.033795179 | S38: =S18/$S18 -> 1 | U38: 2018 | V38: =V18/$AC18 -> 0.29305761 | W38: =W17/$AC17 -> 0.22910309 | X38: =X18/$AC18 -> 0.24454948 | Y38: =Y18/$AC18 -> 0.033677991 | Z38: =Z18/$AC18 -> 0.062274742 | AA38: =AA18/$AC18 -> 0.063810931 | AB38: =AB18/$AC18 -> 0.032437223 | AC38: =AC18/$AC18 -> 1 | AE38: 2018 | AF38: =(L38*$S18+V38*$AC18)/$I18 -> 0.21673548 | AG38: =(M38*$S18+W38*$AC18)/$I18 -> 0.1955253 | AH38: =(N38*$S18+X38*$AC18)/$I18 -> 0.18676492 | AI38: =(O38*$S18+Y38*$AC18)/$I18 -> 0.029164542 | AJ38: =(P38*$S18+Z38*$AC18)/$I18 -> 0.042044314 | AK38: =(Q38*$S18+AA38*$AC18)/$I18 -> 0.044561051 | AL38: =(R38*$S18+AB38*$AC18)/$I18 -> 0.025841791 | AM38: =(S38*$S18+AC38*$AC18)/$I18 -> 0.7758459
A39: 2019 | K39: 2019 | L39: =L19/$S19 -> 0.26066744 | M39: =M19/$S19 -> 0.27248879 | N39: =N19/$S19 -> 0.23360452 | O39: =O19/$S19 -> 0.041142288 | P39: =P19/$S19 -> 0.05203387 | Q39: =Q19/$S19 -> 0.055719741 | R39: =R19/$S19 -> 0.034932758 | S39: =S19/$S19 -> 1 | U39: 2019 | V39: =V19/$AC19 -> 0.285493 | W39: =W18/$AC18 -> 0.22351551 | X39: =X19/$AC19 -> 0.23711647 | Y39: =Y19/$AC19 -> 0.034971701 | Z39: =Z19/$AC19 -> 0.06541555 | AA39: =AA19/$AC19 -> 0.066190051 | AB39: =AB19/$AC19 -> 0.033661007 | AC39: =AC19/$AC19 -> 1 | AE39: 2019 | AF39: =(L39*$S19+V39*$AC19)/$I19 -> 0.207161 | AG39: =(M39*$S19+W39*$AC19)/$I19 -> 0.19594769 | AH39: =(N39*$S19+X39*$AC19)/$I19 -> 0.1804998 | AI39: =(O39*$S19+Y39*$AC19)/$I19 -> 0.029922163 | AJ39: =(P39*$S19+Z39*$AC19)/$I19 -> 0.043670627 | AK39: =(Q39*$S19+AA39*$AC19)/$I19 -> 0.045702581 | AL39: =(R39*$S19+AB39*$AC19)/$I19 -> 0.026497337 | AM39: =(S39*$S19+AC39*$AC19)/$I19 -> 0.76853748
A40: 2020 | K40: 2020 | L40: =L20/$S20 -> 0.25617848 | M40: =M20/$S20 -> 0.28174458 | N40: =N20/$S20 -> 0.23469077 | O40: =O20/$S20 -> 0.04017531 | P40: =P20/$S20 -> 0.050736547 | Q40: =Q20/$S20 -> 0.054419284 | R40: =R20/$S20 -> 0.034149014 | S40: =S20/$S20 -> 1 | U40: 2020 | V40: =V20/$AC20 -> 0.2831834 | W40: =W19/$AC19 -> 0.22871612 | X40: =X20/$AC20 -> 0.23831337 | Y40: =Y20/$AC20 -> 0.034052652 | Z40: =Z20/$AC20 -> 0.063634858 | AA40: =AA20/$AC20 -> 0.064517909 | AB40: =AB20/$AC20 -> 0.032838457 | AC40: =AC20/$AC20 -> 1 | AE40: 2020 | AF40: =(L40*$S20+V40*$AC20)/$I20 -> 0.20398699 | AG40: =(M40*$S20+W40*$AC20)/$I20 -> 0.20177528 | AH40: =(N40*$S20+X40*$AC20)/$I20 -> 0.181116 | AI40: =(O40*$S20+Y40*$AC20)/$I20 -> 0.029164659 | AJ40: =(P40*$S20+Z40*$AC20)/$I20 -> 0.042459648 | AK40: =(Q40*$S20+AA40*$AC20)/$I20 -> 0.044522404 | AL40: =(R40*$S20+AB40*$AC20)/$I20 -> 0.025852204 | AM40: =(S40*$S20+AC40*$AC20)/$I20 -> 0.76751084
A41: 2021 | K41: 2021 | L41: =L21/$S21 -> 0.25431195 | M41: =M21/$S21 -> 0.28877652 | N41: =N21/$S21 -> 0.22797493 | O41: =O21/$S21 -> 0.040358605 | P41: =P21/$S21 -> 0.051216032 | Q41: =Q21/$S21 -> 0.054659387 | R41: =R21/$S21 -> 0.034278446 | S41: =S21/$S21 -> 1 | U41: 2021 | V41: =V21/$AC21 -> 0.27986665 | W41: =W20/$AC20 -> 0.23621613 | X41: =X21/$AC21 -> 0.23221117 | Y41: =Y21/$AC21 -> 0.034429992 | Z41: =Z21/$AC21 -> 0.064651875 | AA41: =AA21/$AC21 -> 0.065198382 | AB41: =AB21/$AC21 -> 0.033173024 | AC41: =AC21/$AC21 -> 1 | AE41: 2021 | AF41: =(L41*$S21+V41*$AC21)/$I21 -> 0.19962231 | AG41: =(M41*$S21+W41*$AC21)/$I21 -> 0.20430273 | AH41: =(N41*$S21+X41*$AC21)/$I21 -> 0.17382833 | AI41: =(O41*$S21+Y41*$AC21)/$I21 -> 0.028941413 | AJ41: =(P41*$S21+Z41*$AC21)/$I21 -> 0.042475383 | AK41: =(Q41*$S21+AA41*$AC21)/$I21 -> 0.044288905 | AL41: =(R41*$S21+AB41*$AC21)/$I21 -> 0.025659088 | AM41: =(S41*$S21+AC41*$AC21)/$I21 -> 0.75739272
A43: Electricity
A44: 所有住宅All Residential | K44: 私人住宅Private Housing Segment | U44: 公共住宅 Public Housing | AE44: 重新加总Private+Public
A45: (缺少原始数据 No raw data) | I45: 總計 Total | K45: 年份 Year | L45: 煮食 Cooking | M45: 空氣調節 Air Conditioning | N45: 熱水 Hot Water | O45: 照明 Lighting | P45: 冷凍 Refrigeration | Q45: 辦公室設備 Office Equipment | R45: 其他 1 Others 1 | S45: 總計 Total | U45: 年份 Year | V45: 煮食 Cooking | W45: 空氣調節 Air Conditioning | X45: 熱水 Hot Water | Y45: 照明 Lighting | Z45: 冷凍 Refrigeration | AA45: 辦公室設備 Office Equipment | AB45: 其他 1 Others 1 | AC45: 總計 Total | AE45: 年份 Year | AF45: 煮食 Cooking | AG45: 空氣調節 Air Conditioning | AH45: 熱水 Hot Water | AI45: 照明 Lighting | AJ45: 冷凍 Refrigeration | AK45: 辦公室設備 Office Equipment | AL45: 其他 1 Others 1 | AM45: 總計 Total
I46: 35428 | K46: 2006 | L46: 1592 | M46: 6122 | N46: 2123 | O46: 2148 | P46: 2830 | Q46: 2311 | R46: 890 | S46: 18016 | U46: 2006 | V46: =B140+L140 -> 1400 | W46: =C140+M140 -> 5006 | X46: =D140+N140 -> 1241 | Y46: =E140+O140 -> 1760 | Z46: =F140+P140 -> 2656 | AA46: =G140+Q140 -> 2211 | AB46: =H140+R140 -> 903 | AC46: =I140+S140 -> 15175 | AE46: 2006 | AF46: =L46+V46 -> 2992 | AG46: =M46+W46 -> 11128 | AH46: =N46+X46 -> 3364 | AI46: =O46+Y46 -> 3908 | AJ46: =P46+Z46 -> 5486 | AK46: =Q46+AA46 -> 4522 | AL46: =R46+AB46 -> 1793 | AM46: =S46+AC46 -> 33191
I47: 36422 | K47: 2007 | L47: 1698 | M47: 6176 | N47: 2271 | O47: 2100 | P47: 2962 | Q47: 2469 | R47: 939 | S47: 18615 | U47: 2007 | V47: =B141+L141 -> 1509 | W47: =C141+M141 -> 4963 | X47: =D141+N141 -> 1399 | Y47: =E141+O141 -> 1709 | Z47: =F141+P141 -> 2741 | AA47: =G141+Q141 -> 2323 | AB47: =H141+R141 -> 943 | AC47: =I141+S141 -> 15587 | AE47: 2007 | AF47: =L47+V47 -> 3207 | AG47: =M47+W47 -> 11139 | AH47: =N47+X47 -> 3670 | AI47: =O47+Y47 -> 3809 | AJ47: =P47+Z47 -> 5703 | AK47: =Q47+AA47 -> 4792 | AL47: =R47+AB47 -> 1882 | AM47: =S47+AC47 -> 34202
I48: 37100 | K48: 2008 | L48: 1812 | M48: 6240 | N48: 2431 | O48: 2055 | P48: 3101 | Q48: 2646 | R48: 992 | S48: 19277 | U48: 2008 | V48: =B142+L142 -> 1606 | W48: =C142+M142 -> 4836 | X48: =D142+N142 -> 1541 | Y48: =E142+O142 -> 1625 | Z48: =F142+P142 -> 2765 | AA48: =G142+Q142 -> 2398 | AB48: =H142+R142 -> 965 | AC48: =I142+S142 -> 15736 | AE48: 2008 | AF48: =L48+V48 -> 3418 | AG48: =M48+W48 -> 11076 | AH48: =N48+X48 -> 3972 | AI48: =O48+Y48 -> 3680 | AJ48: =P48+Z48 -> 5866 | AK48: =Q48+AA48 -> 5044 | AL48: =R48+AB48 -> 1957 | AM48: =S48+AC48 -> 35013
I49: 38972 | K49: 2009 | L49: 1807 | M49: 6740 | N49: 2389 | O49: 2167 | P49: 3134 | Q49: 2764 | R49: 1158 | S49: 20160 | U49: 2009 | V49: =B143+L143 -> 1660 | W49: =C143+M143 -> 5103 | X49: =D143+N143 -> 1479 | Y49: =E143+O143 -> 1639 | Z49: =F143+P143 -> 2818 | AA49: =G143+Q143 -> 2519 | AB49: =H143+R143 -> 1094 | AC49: =I143+S143 -> 16312 | AE49: 2009 | AF49: =L49+V49 -> 3467 | AG49: =M49+W49 -> 11843 | AH49: =N49+X49 -> 3868 | AI49: =O49+Y49 -> 3806 | AJ49: =P49+Z49 -> 5952 | AK49: =Q49+AA49 -> 5283 | AL49: =R49+AB49 -> 2252 | AM49: =S49+AC49 -> 36472
I50: 39344 | K50: 2010 | L50: 1779 | M50: 6949 | N50: 2228 | O50: 2178 | P50: 3003 | Q50: 2815 | R50: 1330 | S50: 20282 | U50: 2010 | V50: 1004 | W50: 2870 | X50: 947 | Y50: 947 | Z50: 1818 | AA50: 1588 | AB50: 717 | AC50: 10100 | AE50: 2010 | AF50: =L50+V50 -> 2783 | AG50: =M50+W50 -> 9819 | AH50: =N50+X50 -> 3175 | AI50: =O50+Y50 -> 3125 | AJ50: =P50+Z50 -> 4821 | AK50: =Q50+AA50 -> 4403 | AL50: =R50+AB50 -> 2047 | AM50: =S50+AC50 -> 30382
I51: 39872 | K51: 2011 | L51: 1808 | M51: 7201 | N51: 2086 | O51: 2204 | P51: 2891 | Q51: 2945 | R51: 1604 | S51: 20739 | U51: 2011 | V51: 1055 | W51: 2931 | X51: 1118 | Y51: 42 | Z51: 1763 | AA51: 1642 | AB51: 817 | AC51: 10269 | AE51: 2011 | AF51: =L51+V51 -> 2863 | AG51: =M51+W51 -> 10132 | AH51: =N51+X51 -> 3204 | AI51: =O51+Y51 -> 2246 | AJ51: =P51+Z51 -> 4654 | AK51: =Q51+AA51 -> 4587 | AL51: =R51+AB51 -> 2421 | AM51: =S51+AC51 -> 31008
I52: 41189 | K52: 2012 | L52: 1847 | M52: 7364 | N52: 1925 | O52: 2208 | P52: 2743 | Q52: 3099 | R52: 2007 | S52: 21195 | U52: 2012 | V52: 1120 | W52: 3029 | X52: 1062 | Y52: 970 | Z52: 1725 | AA52: 1794 | AB52: 974 | AC52: 10674 | AE52: 2012 | AF52: =L52+V52 -> 2967 | AG52: =M52+W52 -> 10393 | AH52: =N52+X52 -> 2987 | AI52: =O52+Y52 -> 3178 | AJ52: =P52+Z52 -> 4468 | AK52: =Q52+AA52 -> 4893 | AL52: =R52+AB52 -> 2981 | AM52: =S52+AC52 -> 31869
I53: 39941 | K53: 2013 | L53: 2566 | M53: 6914 | N53: 2128 | O53: 1874 | P53: 2404 | Q53: 2505 | R53: 2040 | S53: 20430 | U53: 2013 | V53: 1587 | W53: 2883 | X53: 1072 | Y53: 823 | Z53: 1544 | AA53: 1573 | AB53: 1013 | AC53: 10496 | AE53: 2013 | AF53: =L53+V53 -> 4153 | AG53: =M53+W53 -> 9797 | AH53: =N53+X53 -> 3200 | AI53: =O53+Y53 -> 2697 | AJ53: =P53+Z53 -> 3948 | AK53: =Q53+AA53 -> 4078 | AL53: =R53+AB53 -> 3053 | AM53: =S53+AC53 -> 30926
I54: 43415 | K54: 2014 | L54: 2920 | M54: 8322 | N54: 2508 | O54: 1752 | P54: 2292 | Q54: 2357 | R54: 2267 | S54: 22417 | U54: 2014 | V54: 1728 | W54: 3496 | X54: 1146 | Y54: 775 | Z54: 1495 | AA54: 1489 | AB54: 1145 | AC54: 11272 | AE54: 2014 | AF54: =L54+V54 -> 4648 | AG54: =M54+W54 -> 11818 | AH54: =N54+X54 -> 3654 | AI54: =O54+Y54 -> 2527 | AJ54: =P54+Z54 -> 3787 | AK54: =Q54+AA54 -> 3846 | AL54: =R54+AB54 -> 3412 | AM54: =S54+AC54 -> 33689
I55: 42368 | K55: 2015 | L55: 3083 | M55: 8046 | N55: 2547 | O55: 1500 | P55: 1972 | Q55: 2047 | R55: 2287 | S55: 21483 | U55: 2015 | V55: 1773 | W55: 3580 | X55: 1090 | Y55: 691 | Z55: 1349 | AA55: 1338 | AB55: 1212 | AC55: 11033 | AE55: 2015 | AF55: =L55+V55 -> 4856 | AG55: =M55+W55 -> 11626 | AH55: =N55+X55 -> 3637 | AI55: =O55+Y55 -> 2191 | AJ55: =P55+Z55 -> 3321 | AK55: =Q55+AA55 -> 3385 | AL55: =R55+AB55 -> 3499 | AM55: =S55+AC55 -> 32516
I56: 43120 | K56: 2016 | L56: 3539 | M56: 8323 | N56: 2948 | O56: 1379 | P56: 1789 | Q56: 1893 | R56: 2446 | S56: 22318 | U56: 2016 | V56: 1856 | W56: 3758 | X56: 1130 | Y56: 633 | Z56: 1226 | AA56: 1231 | AB56: 1297 | AC56: 11131 | AE56: 2016 | AF56: =L56+V56 -> 5395 | AG56: =M56+W56 -> 12081 | AH56: =N56+X56 -> 4078 | AI56: =O56+Y56 -> 2012 | AJ56: =P56+Z56 -> 3015 | AK56: =Q56+AA56 -> 3124 | AL56: =R56+AB56 -> 3743 | AM56: =S56+AC56 -> 33449
I57: 42157 | K57: 2017 | L57: 3935 | M57: 8203 | N57: 3038 | O57: 1220 | P57: 1523 | Q57: 1652 | R57: 1036 | S57: 22036 | U57: 2017 | V57: 1862 | W57: 3821 | X57: 1051 | Y57: 570 | Z57: 1053 | AA57: 1080 | AB57: 549 | AC57: 10774 | AE57: 2017 | AF57: =L57+V57 -> 5797 | AG57: =M57+W57 -> 12024 | AH57: =N57+X57 -> 4089 | AI57: =O57+Y57 -> 1790 | AJ57: =P57+Z57 -> 2576 | AK57: =Q57+AA57 -> 2732 | AL57: =R57+AB57 -> 1585 | AM57: =S57+AC57 -> 32810
I58: 41965 | K58: 2018 | L58: 3879 | M58: 8009 | N58: 2972 | O58: 1203 | P58: 1502 | Q58: 1629 | R58: 1022 | S58: 21624 | U58: 2018 | V58: 1855 | W58: 3767 | X58: 1039 | Y58: 568 | Z58: 1050 | AA58: 1076 | AB58: 547 | AC58: 10706 | AE58: 2018 | AF58: =L58+V58 -> 5734 | AG58: =M58+W58 -> 11776 | AH58: =N58+X58 -> 4011 | AI58: =O58+Y58 -> 1771 | AJ58: =P58+Z58 -> 2552 | AK58: =Q58+AA58 -> 2705 | AL58: =R58+AB58 -> 1569 | AM58: =S58+AC58 -> 32330
I59: 42937 | K59: 2019 | L59: 3996 | M59: 8206 | N59: 2948 | O59: 1239 | P59: 1567 | Q59: 1678 | R59: 1052 | S59: 22136 | U59: 2019 | V59: 1907 | W59: 3819 | X59: 1028 | Y59: 584 | Z59: 1093 | AA59: 1106 | AB59: 563 | AC59: 10939 | AE59: 2019 | AF59: =L59+V59 -> 5903 | AG59: =M59+W59 -> 12025 | AH59: =N59+X59 -> 3976 | AI59: =O59+Y59 -> 1823 | AJ59: =P59+Z59 -> 2660 | AK59: =Q59+AA59 -> 2784 | AL59: =R59+AB59 -> 1615 | AM59: =S59+AC59 -> 33075
I60: 46676 | K60: 2020 | L60: 4259 | M60: 9257 | N60: 3168 | O60: 1320 | P60: 1667 | Q60: 1788 | R60: 1122 | S60: 24126 | U60: 2020 | V60: 2016 | W60: 4280 | X60: 1096 | Y60: 617 | Z60: 1153 | AA60: 1169 | AB60: 595 | AC60: 11825 | AE60: 2020 | AF60: =L60+V60 -> 6275 | AG60: =M60+W60 -> 13537 | AH60: =N60+X60 -> 4264 | AI60: =O60+Y60 -> 1937 | AJ60: =P60+Z60 -> 2820 | AK60: =Q60+AA60 -> 2957 | AL60: =R60+AB60 -> 1717 | AM60: =S60+AC60 -> 35951
I61: 47465 | K61: 2021 | L61: 4196 | M61: 9309 | N61: 3073 | O61: 1301 | P61: 1651 | Q61: 1762 | R61: 1105 | S61: 23919 | U61: 2021 | V61: 2056 | W61: 4446 | X61: 1100 | Y61: 630 | Z61: 1183 | AA61: 1193 | AB61: 607 | AC61: 12061 | AE61: 2021 | AF61: =L61+V61 -> 6252 | AG61: =M61+W61 -> 13755 | AH61: =N61+X61 -> 4173 | AI61: =O61+Y61 -> 1931 | AJ61: =P61+Z61 -> 2834 | AK61: =Q61+AA61 -> 2955 | AL61: =R61+AB61 -> 1712 | AM61: =S61+AC61 -> 35980
A63: 转换为百分比Change to percentage
B64: Air Conditioning | C64: Hot Water | D64: Lighting | E64: Refrigeration | F64: Office Equipment | G64: Cooking | H64: Others | I64: Sum | K64: 私人住宅Private Housing Segment | U64: 公共住宅 Public Housing | AE64: 重新加总Private+Public
A65: 2005 | B65: 0.35 | C65: 0.1 | D65: 0.12 | E65: 0.16 | F65: 0.13 | G65: 0.09 | H65: 0.05 | I65: =SUM(B65:H65) -> 1 | K65: 年份 Year | L65: 煮食 Cooking | M65: 空氣調節 Air Conditioning | N65: 熱水 Hot Water | O65: 照明 Lighting | P65: 冷凍 Refrigeration | Q65: 辦公室設備 Office Equipment | R65: 其他 1 Others 1 | S65: 總計 Total | U65: 年份 Year | V65: 煮食 Cooking | W65: 空氣調節 Air Conditioning | X65: 熱水 Hot Water | Y65: 照明 Lighting | Z65: 冷凍 Refrigeration | AA65: 辦公室設備 Office Equipment | AB65: 其他 1 Others 1 | AC65: 總計 Total | AE65: 年份 Year | AF65: 煮食 Cooking | AG65: 空氣調節 Air Conditioning | AH65: 熱水 Hot Water | AI65: 照明 Lighting | AJ65: 冷凍 Refrigeration | AK65: 辦公室設備 Office Equipment | AL65: 其他 1 Others 1 | AM65: 總計 Total
A66: 2006 | B66: 0.34 | C66: 0.11 | D66: 0.12 | E66: 0.16 | F66: 0.13 | G66: 0.09 | H66: 0.05 | I66: =SUM(B66:H66) -> 1 | K66: 2006 | L66: =L46/$S46 -> 0.088365897 | M66: =M46/$S46 -> 0.33980906 | N66: =N46/$S46 -> 0.1178397 | O66: =O46/$S46 -> 0.11922735 | P66: =P46/$S46 -> 0.15708259 | Q66: =Q46/$S46 -> 0.12827487 | R66: =R46/$S46 -> 0.049400533 | S66: =S46/$S46 -> 1 | U66: 2006 | V66: =V46/$AC46 -> 0.092257002 | W66: =W46/$AC46 -> 0.32988468 | X66: =X46/$AC46 -> 0.081779242 | Y66: =Y46/$AC46 -> 0.11598023 | Z66: =Z46/$AC46 -> 0.17502471 | AA66: =AA46/$AC46 -> 0.14570016 | AB66: =AB46/$AC46 -> 0.059505766 | AC66: =AC46/$AC46 -> 1 | AE66: 2006 | AF66: =(L66*$S46+V66*$AC46)/$I46 -> 0.084452975 | AG66: =(M66*$S46+W66*$AC46)/$I46 -> 0.31410184 | AH66: =(N66*$S46+X66*$AC46)/$I46 -> 0.094953144 | AI66: =(O66*$S46+Y66*$AC46)/$I46 -> 0.11030823 | AJ66: =(P66*$S46+Z66*$AC46)/$I46 -> 0.15484927 | AK66: =(Q66*$S46+AA66*$AC46)/$I46 -> 0.12763916 | AL66: =(R66*$S46+AB66*$AC46)/$I46 -> 0.050609687 | AM66: =(S66*$S46+AC66*$AC46)/$I46 -> 0.93685785
A67: 2007 | B67: No data about electricity demand decomposition between 2007-2011 | K67: 2007 | L67: =L47/$S47 -> 0.091216761 | M67: =M47/$S47 -> 0.33177545 | N67: =N47/$S47 -> 0.12199839 | O67: =O47/$S47 -> 0.11281225 | P67: =P47/$S47 -> 0.15911899 | Q67: =Q47/$S47 -> 0.13263497 | R67: =R47/$S47 -> 0.050443191 | S67: =S47/$S47 -> 1 | U67: 2007 | V67: =V47/$AC47 -> 0.096811445 | W67: =W47/$AC47 -> 0.31840636 | X67: =X47/$AC47 -> 0.089754282 | Y67: =Y47/$AC47 -> 0.10964265 | Z67: =Z47/$AC47 -> 0.17585167 | AA67: =AA47/$AC47 -> 0.14903445 | AB67: =AB47/$AC47 -> 0.060499134 | AC67: =AC47/$AC47 -> 1 | AE67: 2007 | AF67: =(L67*$S47+V67*$AC47)/$I47 -> 0.088051178 | AG67: =(M67*$S47+W67*$AC47)/$I47 -> 0.30583164 | AH67: =(N67*$S47+X67*$AC47)/$I47 -> 0.10076327 | AI67: =(O67*$S47+Y67*$AC47)/$I47 -> 0.10457965 | AJ67: =(P67*$S47+Z67*$AC47)/$I47 -> 0.15658119 | AK67: =(Q67*$S47+AA67*$AC47)/$I47 -> 0.13156883 | AL67: =(R67*$S47+AB67*$AC47)/$I47 -> 0.051672066 | AM67: =(S67*$S47+AC67*$AC47)/$I47 -> 0.93904783
A68: 2008 | K68: 2008 | L68: =L48/$S48 -> 0.093998029 | M68: =M48/$S48 -> 0.32370182 | N68: =N48/$S48 -> 0.12610883 | O68: =O48/$S48 -> 0.10660372 | P68: =P48/$S48 -> 0.16086528 | Q68: =Q48/$S48 -> 0.13726202 | R68: =R48/$S48 -> 0.051460289 | S68: =S48/$S48 -> 1 | U68: 2008 | V68: =V48/$AC48 -> 0.10205897 | W68: =W48/$AC48 -> 0.30732079 | X68: =X48/$AC48 -> 0.097928317 | Y68: =Y48/$AC48 -> 0.1032664 | Z68: =Z48/$AC48 -> 0.17571174 | AA68: =AA48/$AC48 -> 0.15238943 | AB68: =AB48/$AC48 -> 0.061324352 | AC68: =AC48/$AC48 -> 1 | AE68: 2008 | AF68: =(L68*$S48+V68*$AC48)/$I48 -> 0.09212938 | AG68: =(M68*$S48+W68*$AC48)/$I48 -> 0.29854447 | AH68: =(N68*$S48+X68*$AC48)/$I48 -> 0.10706199 | AI68: =(O68*$S48+Y68*$AC48)/$I48 -> 0.099191375 | AJ68: =(P68*$S48+Z68*$AC48)/$I48 -> 0.15811321 | AK68: =(Q68*$S48+AA68*$AC48)/$I48 -> 0.13595687 | AL68: =(R68*$S48+AB68*$AC48)/$I48 -> 0.052749326 | AM68: =(S68*$S48+AC68*$AC48)/$I48 -> 0.94374663
A69: 2009 | K69: 2009 | L69: =L49/$S49 -> 0.089632937 | M69: =M49/$S49 -> 0.3343254 | N69: =N49/$S49 -> 0.11850198 | O69: =O49/$S49 -> 0.10749008 | P69: =P49/$S49 -> 0.15545635 | Q69: =Q49/$S49 -> 0.13710317 | R69: =R49/$S49 -> 0.057440476 | S69: =S49/$S49 -> 1 | U69: 2009 | V69: =V49/$AC49 -> 0.10176557 | W69: =W49/$AC49 -> 0.31283718 | X69: =X49/$AC49 -> 0.090669446 | Y69: =Y49/$AC49 -> 0.10047818 | Z69: =Z49/$AC49 -> 0.17275625 | AA69: =AA49/$AC49 -> 0.15442619 | AB69: =AB49/$AC49 -> 0.06706719 | AC69: =AC49/$AC49 -> 1 | AE69: 2009 | AF69: =(L69*$S49+V69*$AC49)/$I49 -> 0.088961306 | AG69: =(M69*$S49+W69*$AC49)/$I49 -> 0.30388484 | AH69: =(N69*$S49+X69*$AC49)/$I49 -> 0.099250744 | AI69: =(O69*$S49+Y69*$AC49)/$I49 -> 0.097659858 | AJ69: =(P69*$S49+Z69*$AC49)/$I49 -> 0.15272503 | AK69: =(Q69*$S49+AA69*$AC49)/$I49 -> 0.13555886 | AL69: =(R69*$S49+AB69*$AC49)/$I49 -> 0.057785076 | AM69: =(S69*$S49+AC69*$AC49)/$I49 -> 0.93585138
A70: 2010 | K70: 2010 | L70: =L50/$S50 -> 0.087713243 | M70: =M50/$S50 -> 0.34261907 | N70: =N50/$S50 -> 0.1098511 | O70: =O50/$S50 -> 0.10738586 | P70: =P50/$S50 -> 0.14806232 | Q70: =Q50/$S50 -> 0.13879302 | R70: =R50/$S50 -> 0.065575387 | S70: =S50/$S50 -> 1 | U70: 2010 | V70: =V50/$AC50 -> 0.099405941 | W70: =W50/$AC50 -> 0.28415842 | X70: =X50/$AC50 -> 0.093762376 | Y70: =Y50/$AC50 -> 0.093762376 | Z70: =Z50/$AC50 -> 0.18 | AA70: =AA50/$AC50 -> 0.15722772 | AB70: =AB50/$AC50 -> 0.070990099 | AC70: =AC50/$AC50 -> 1 | AE70: 2010 | AF70: =(L70*$S50+V70*$AC50)/$I50 -> 0.070735055 | AG70: =(M70*$S50+W70*$AC50)/$I50 -> 0.24956791 | AH70: =(N70*$S50+X70*$AC50)/$I50 -> 0.080698455 | AI70: =(O70*$S50+Y70*$AC50)/$I50 -> 0.079427613 | AJ70: =(P70*$S50+Z70*$AC50)/$I50 -> 0.12253457 | AK70: =(Q70*$S50+AA70*$AC50)/$I50 -> 0.11191033 | AL70: =(R70*$S50+AB70*$AC50)/$I50 -> 0.052028264 | AM70: =(S70*$S50+AC70*$AC50)/$I50 -> 0.77221431
A71: 2011 | K71: 2011 | L71: =L51/$S51 -> 0.087178745 | M71: =M51/$S51 -> 0.34722021 | N71: =N51/$S51 -> 0.10058344 | O71: =O51/$S51 -> 0.10627321 | P71: =P51/$S51 -> 0.1393992 | Q71: =Q51/$S51 -> 0.14200299 | R71: =R51/$S51 -> 0.077342206 | S71: =S51/$S51 -> 1 | U71: 2011 | V71: =V51/$AC51 -> 0.10273639 | W71: =W51/$AC51 -> 0.28542214 | X71: =X51/$AC51 -> 0.10887136 | Y71: =Y51/$AC51 -> 0.0040899796 | Z71: =Z51/$AC51 -> 0.17168176 | AA71: =AA51/$AC51 -> 0.15989872 | AB71: =AB51/$AC51 -> 0.07955984 | AC71: =AC51/$AC51 -> 1 | AE71: 2011 | AF71: =(L71*$S51+V71*$AC51)/$I51 -> 0.071804775 | AG71: =(M71*$S51+W71*$AC51)/$I51 -> 0.25411316 | AH71: =(N71*$S51+X71*$AC51)/$I51 -> 0.080357143 | AI71: =(O71*$S51+Y71*$AC51)/$I51 -> 0.056330257 | AJ71: =(P71*$S51+Z71*$AC51)/$I51 -> 0.11672352 | AK71: =(Q71*$S51+AA71*$AC51)/$I51 -> 0.11504314 | AL71: =(R71*$S51+AB71*$AC51)/$I51 -> 0.060719302 | AM71: =(S71*$S51+AC71*$AC51)/$I51 -> 0.7776886
A72: 2012 | B72: 0.34 | C72: 0.08 | D72: 0.1 | E72: 0.14 | F72: 0.15 | G72: 0.09 | H72: 0.1 | I72: =SUM(B72:H72) -> 1 | K72: 2012 | L72: =L52/$S52 -> 0.087143194 | M72: =M52/$S52 -> 0.34744043 | N72: =N52/$S52 -> 0.090823307 | O72: =O52/$S52 -> 0.10417551 | P72: =P52/$S52 -> 0.12941732 | Q72: =Q52/$S52 -> 0.14621373 | R72: =R52/$S52 -> 0.094692144 | S72: =S52/$S52 -> 1 | U72: 2012 | V72: =V52/$AC52 -> 0.10492786 | W72: =W52/$AC52 -> 0.28377366 | X72: =X52/$AC52 -> 0.099494098 | Y72: =Y52/$AC52 -> 0.090875023 | Z72: =Z52/$AC52 -> 0.16160764 | AA72: =AA52/$AC52 -> 0.16807195 | AB72: =AB52/$AC52 -> 0.091249766 | AC72: =AC52/$AC52 -> 1 | AE72: 2012 | AF72: =(L72*$S52+V72*$AC52)/$I52 -> 0.072033795 | AG72: =(M72*$S52+W72*$AC52)/$I52 -> 0.25232465 | AH72: =(N72*$S52+X72*$AC52)/$I52 -> 0.072519362 | AI72: =(O72*$S52+Y72*$AC52)/$I52 -> 0.077156522 | AJ72: =(P72*$S52+Z72*$AC52)/$I52 -> 0.10847556 | AK72: =(Q72*$S52+AA72*$AC52)/$I52 -> 0.11879385 | AL72: =(R72*$S52+AB72*$AC52)/$I52 -> 0.072373692 | AM72: =(S72*$S52+AC72*$AC52)/$I52 -> 0.77372599
A73: 2013 | B73: 0.31 | C73: 0.09 | D73: 0.1 | E73: 0.14 | F73: 0.16 | G73: 0.1 | H73: 0.1 | I73: =SUM(B73:H73) -> 1 | K73: 2013 | L73: =L53/$S53 -> 0.12559961 | M73: =M53/$S53 -> 0.33842389 | N73: =N53/$S53 -> 0.10416055 | O73: =O53/$S53 -> 0.091727851 | P73: =P53/$S53 -> 0.11767009 | Q73: =Q53/$S53 -> 0.1226138 | R73: =R53/$S53 -> 0.099853157 | S73: =S53/$S53 -> 1 | U73: 2013 | V73: =V53/$AC53 -> 0.15120046 | W73: =W53/$AC53 -> 0.27467607 | X73: =X53/$AC53 -> 0.10213415 | Y73: =Y53/$AC53 -> 0.078410823 | Z73: =Z53/$AC53 -> 0.14710366 | AA73: =AA53/$AC53 -> 0.14986662 | AB73: =AB53/$AC53 -> 0.096512957 | AC73: =AC53/$AC53 -> 1 | AE73: 2013 | AF73: =(L73*$S53+V73*$AC53)/$I53 -> 0.10397837 | AG73: =(M73*$S53+W73*$AC53)/$I53 -> 0.2452868 | AH73: =(N73*$S53+X73*$AC53)/$I53 -> 0.080118174 | AI73: =(O73*$S53+Y73*$AC53)/$I53 -> 0.067524599 | AJ73: =(P73*$S53+Z73*$AC53)/$I53 -> 0.098845798 | AK73: =(Q73*$S53+AA73*$AC53)/$I53 -> 0.1021006 | AL73: =(R73*$S53+AB73*$AC53)/$I53 -> 0.076437746 | AM73: =(S73*$S53+AC73*$AC53)/$I53 -> 0.77429208
A74: 2014 | B74: 0.36 | C74: 0.08 | D74: 0.09 | E74: 0.13 | F74: 0.15 | G74: 0.09 | H74: 0.1 | I74: =SUM(B74:H74) -> 1 | K74: 2014 | L74: =L54/$S54 -> 0.13025829 | M74: =M54/$S54 -> 0.37123612 | N74: =N54/$S54 -> 0.11187938 | O74: =O54/$S54 -> 0.078154972 | P74: =P54/$S54 -> 0.10224383 | Q74: =Q54/$S54 -> 0.10514342 | R74: =R54/$S54 -> 0.10112861 | S74: =S54/$S54 -> 1 | U74: 2014 | V74: =V54/$AC54 -> 0.15330021 | W74: =W54/$AC54 -> 0.31014904 | X74: =X54/$AC54 -> 0.10166785 | Y74: =Y54/$AC54 -> 0.068754436 | Z74: =Z54/$AC54 -> 0.13262952 | AA74: =AA54/$AC54 -> 0.13209723 | AB74: =AB54/$AC54 -> 0.10157913 | AC74: =AC54/$AC54 -> 1 | AE74: 2014 | AF74: =(L74*$S54+V74*$AC54)/$I54 -> 0.10705977 | AG74: =(M74*$S54+W74*$AC54)/$I54 -> 0.27221007 | AH74: =(N74*$S54+X74*$AC54)/$I54 -> 0.084164459 | AI74: =(O74*$S54+Y74*$AC54)/$I54 -> 0.058205689 | AJ74: =(P74*$S54+Z74*$AC54)/$I54 -> 0.087227917 | AK74: =(Q74*$S54+AA74*$AC54)/$I54 -> 0.088586894 | AL74: =(R74*$S54+AB74*$AC54)/$I54 -> 0.078590349 | AM74: =(S74*$S54+AC74*$AC54)/$I54 -> 0.77597605
A75: 2015 | B75: 0.36 | C75: 0.08 | D75: 0.09 | E75: 0.14 | F75: 0.15 | G75: 0.09 | H75: 0.09 | I75: =SUM(B75:H75) -> 1 | K75: 2015 | L75: =L55/$S55 -> 0.14350882 | M75: =M55/$S55 -> 0.3745287 | N75: =N55/$S55 -> 0.11855886 | O75: =O55/$S55 -> 0.06982265 | P75: =P55/$S55 -> 0.091793511 | Q75: =Q55/$S55 -> 0.095284644 | R75: =R55/$S55 -> 0.10645627 | S75: =S55/$S55 -> 1 | U75: 2015 | V75: =V55/$AC55 -> 0.16069972 | W75: =W55/$AC55 -> 0.3244811 | X75: =X55/$AC55 -> 0.098794526 | Y75: =Y55/$AC55 -> 0.062630291 | Z75: =Z55/$AC55 -> 0.12226955 | AA75: =AA55/$AC55 -> 0.12127255 | AB75: =AB55/$AC55 -> 0.10985226 | AC75: =AC55/$AC55 -> 1 | AE75: 2015 | AF75: =(L75*$S55+V75*$AC55)/$I55 -> 0.1146148 | AG75: =(M75*$S55+W75*$AC55)/$I55 -> 0.27440521 | AH75: =(N75*$S55+X75*$AC55)/$I55 -> 0.085843089 | AI75: =(O75*$S55+Y75*$AC55)/$I55 -> 0.051713557 | AJ75: =(P75*$S55+Z75*$AC55)/$I55 -> 0.07838463 | AK75: =(Q75*$S55+AA75*$AC55)/$I55 -> 0.079895204 | AL75: =(R75*$S55+AB75*$AC55)/$I55 -> 0.082585914 | AM75: =(S75*$S55+AC75*$AC55)/$I55 -> 0.76746601
A76: 2016 | B76: 0.35 | C76: 0.08 | D76: 0.09 | E76: 0.14 | F76: 0.15 | G76: 0.09 | H76: 0.1 | I76: =SUM(B76:H76) -> 1 | K76: 2016 | L76: =L56/$S56 -> 0.15857156 | M76: =M56/$S56 -> 0.37292768 | N76: =N56/$S56 -> 0.13209069 | O76: =O56/$S56 -> 0.061788691 | P76: =P56/$S56 -> 0.080159513 | Q76: =Q56/$S56 -> 0.084819428 | R76: =R56/$S56 -> 0.10959763 | S76: =S56/$S56 -> 1 | U76: 2016 | V76: =V56/$AC56 -> 0.16674153 | W76: =W56/$AC56 -> 0.33761567 | X76: =X56/$AC56 -> 0.10151828 | Y76: =Y56/$AC56 -> 0.056868206 | Z76: =Z56/$AC56 -> 0.11014284 | AA76: =AA56/$AC56 -> 0.11059204 | AB76: =AB56/$AC56 -> 0.11652143 | AC76: =AC56/$AC56 -> 1 | AE76: 2016 | AF76: =(L76*$S56+V76*$AC56)/$I56 -> 0.12511596 | AG76: =(M76*$S56+W76*$AC56)/$I56 -> 0.28017161 | AH76: =(N76*$S56+X76*$AC56)/$I56 -> 0.094573284 | AI76: =(O76*$S56+Y76*$AC56)/$I56 -> 0.046660482 | AJ76: =(P76*$S56+Z76*$AC56)/$I56 -> 0.06992115 | AK76: =(Q76*$S56+AA76*$AC56)/$I56 -> 0.07244898 | AL76: =(R76*$S56+AB76*$AC56)/$I56 -> 0.086804267 | AM76: =(S76*$S56+AC76*$AC56)/$I56 -> 0.77571892
A77: 2017 | K77: 2017 | L77: =L57/$S57 -> 0.17857143 | M77: =M57/$S57 -> 0.37225449 | N77: =N57/$S57 -> 0.13786531 | O77: =O57/$S57 -> 0.05536395 | P77: =P57/$S57 -> 0.069114177 | Q77: =Q57/$S57 -> 0.074968234 | R77: =R57/$S57 -> 0.047013977 | S77: =S57/$S57 -> 1 | U77: 2017 | V77: =V57/$AC57 -> 0.17282346 | W77: =W57/$AC57 -> 0.35465008 | X77: =X57/$AC57 -> 0.097549657 | Y77: =Y57/$AC57 -> 0.052905142 | Z77: =Z57/$AC57 -> 0.097735289 | AA77: =AA57/$AC57 -> 0.10024132 | AB77: =AB57/$AC57 -> 0.050956005 | AC77: =AC57/$AC57 -> 1 | AE77: 2017 | AF77: =(L77*$S57+V77*$AC57)/$I57 -> 0.13750978 | AG77: =(M77*$S57+W77*$AC57)/$I57 -> 0.28521954 | AH77: =(N77*$S57+X77*$AC57)/$I57 -> 0.096994568 | AI77: =(O77*$S57+Y77*$AC57)/$I57 -> 0.042460327 | AJ77: =(P77*$S57+Z77*$AC57)/$I57 -> 0.061104917 | AK77: =(Q77*$S57+AA77*$AC57)/$I57 -> 0.06480537 | AL77: =(R77*$S57+AB77*$AC57)/$I57 -> 0.037597552 | AM77: =(S77*$S57+AC77*$AC57)/$I57 -> 0.77828119
A78: 2018 | K78: 2018 | L78: =L58/$S58 -> 0.17938402 | M78: =M58/$S58 -> 0.37037551 | N78: =N58/$S58 -> 0.13743988 | O78: =O58/$S58 -> 0.05563263 | P78: =P58/$S58 -> 0.069459859 | Q78: =Q58/$S58 -> 0.075332963 | R78: =R58/$S58 -> 0.047262301 | S78: =S58/$S58 -> 1 | U78: 2018 | V78: =V58/$AC58 -> 0.17326733 | W78: =W58/$AC58 -> 0.35185877 | X78: =X58/$AC58 -> 0.097048384 | Y78: =Y58/$AC58 -> 0.053054362 | Z78: =Z58/$AC58 -> 0.098075845 | AA78: =AA58/$AC58 -> 0.10050439 | AB78: =AB58/$AC58 -> 0.051092845 | AC78: =AC58/$AC58 -> 1 | AE78: 2018 | AF78: =(L78*$S58+V78*$AC58)/$I58 -> 0.13663767 | AG78: =(M78*$S58+W78*$AC58)/$I58 -> 0.2806148 | AH78: =(N78*$S58+X78*$AC58)/$I58 -> 0.09557965 | AI78: =(O78*$S58+Y78*$AC58)/$I58 -> 0.042201835 | AJ78: =(P78*$S58+Z78*$AC58)/$I58 -> 0.060812582 | AK78: =(Q78*$S58+AA78*$AC58)/$I58 -> 0.064458477 | AL78: =(R78*$S58+AB78*$AC58)/$I58 -> 0.0373883 | AM78: =(S78*$S58+AC78*$AC58)/$I58 -> 0.77040391
A79: 2019 | K79: 2019 | L79: =L59/$S59 -> 0.18052042 | M79: =M59/$S59 -> 0.37070835 | N79: =N59/$S59 -> 0.13317673 | O79: =O59/$S59 -> 0.055972172 | P79: =P59/$S59 -> 0.070789664 | Q79: =Q59/$S59 -> 0.07580412 | R79: =R59/$S59 -> 0.047524395 | S79: =S59/$S59 -> 1 | U79: 2019 | V79: =V59/$AC59 -> 0.17433038 | W79: =W59/$AC59 -> 0.34911784 | X79: =X59/$AC59 -> 0.093975683 | Y79: =Y59/$AC59 -> 0.053386964 | Z79: =Z59/$AC59 -> 0.099917726 | AA79: =AA59/$AC59 -> 0.10110613 | AB79: =AB59/$AC59 -> 0.051467227 | AC79: =AC59/$AC59 -> 1 | AE79: 2019 | AF79: =(L79*$S59+V79*$AC59)/$I59 -> 0.13748049 | AG79: =(M79*$S59+W79*$AC59)/$I59 -> 0.28006149 | AH79: =(N79*$S59+X79*$AC59)/$I59 -> 0.092600787 | AI79: =(O79*$S59+Y79*$AC59)/$I59 -> 0.042457554 | AJ79: =(P79*$S59+Z79*$AC59)/$I59 -> 0.061951231 | AK79: =(Q79*$S59+AA79*$AC59)/$I59 -> 0.064839183 | AL79: =(R79*$S59+AB79*$AC59)/$I59 -> 0.037613247 | AM79: =(S79*$S59+AC79*$AC59)/$I59 -> 0.77031465
A80: 2020 | K80: 2020 | L80: =L60/$S60 -> 0.17653154 | M80: =M60/$S60 -> 0.38369394 | N80: =N60/$S60 -> 0.13131062 | O80: =O60/$S60 -> 0.054712758 | P80: =P60/$S60 -> 0.069095582 | Q80: =Q60/$S60 -> 0.074110918 | R80: =R60/$S60 -> 0.046505844 | S80: =S60/$S60 -> 1 | U80: 2020 | V80: =V60/$AC60 -> 0.17048626 | W80: =W60/$AC60 -> 0.36194503 | X80: =X60/$AC60 -> 0.092684989 | Y80: =Y60/$AC60 -> 0.05217759 | Z80: =Z60/$AC60 -> 0.097505285 | AA80: =AA60/$AC60 -> 0.098858351 | AB80: =AB60/$AC60 -> 0.050317125 | AC80: =AC60/$AC60 -> 1 | AE80: 2020 | AF80: =(L80*$S60+V80*$AC60)/$I60 -> 0.1344374 | AG80: =(M80*$S60+W80*$AC60)/$I60 -> 0.29002057 | AH80: =(N80*$S60+X80*$AC60)/$I60 -> 0.091353158 | AI80: =(O80*$S60+Y80*$AC60)/$I60 -> 0.041498843 | AJ80: =(P80*$S60+Z80*$AC60)/$I60 -> 0.060416488 | AK80: =(Q80*$S60+AA80*$AC60)/$I60 -> 0.063351615 | AL80: =(R80*$S60+AB80*$AC60)/$I60 -> 0.0367855 | AM80: =(S80*$S60+AC80*$AC60)/$I60 -> 0.77022453
A81: 2021 | K81: 2021 | L81: =L61/$S61 -> 0.17542539 | M81: =M61/$S61 -> 0.38918851 | N81: =N61/$S61 -> 0.12847527 | O81: =O61/$S61 -> 0.054391906 | P81: =P61/$S61 -> 0.069024625 | Q81: =Q61/$S61 -> 0.073665287 | R81: =R61/$S61 -> 0.046197584 | S81: =S61/$S61 -> 1 | U81: 2021 | V81: =V61/$AC61 -> 0.17046679 | W81: =W61/$AC61 -> 0.36862615 | X81: =X61/$AC61 -> 0.091203051 | Y81: =Y61/$AC61 -> 0.052234475 | Z81: =Z61/$AC61 -> 0.098084736 | AA81: =AA61/$AC61 -> 0.098913855 | AB81: =AB61/$AC61 -> 0.050327502 | AC81: =AC61/$AC61 -> 1 | AE81: 2021 | AF81: =(L81*$S61+V81*$AC61)/$I61 -> 0.13171811 | AG81: =(M81*$S61+W81*$AC61)/$I61 -> 0.28979248 | AH81: =(N81*$S61+X81*$AC61)/$I61 -> 0.087917413 | AI81: =(O81*$S61+Y81*$AC61)/$I61 -> 0.040682608 | AJ81: =(P81*$S61+Z81*$AC61)/$I61 -> 0.059707153 | AK81: =(Q81*$S61+AA81*$AC61)/$I61 -> 0.062256399 | AL81: =(R81*$S61+AB81*$AC61)/$I61 -> 0.036068682 | AM81: =(S81*$S61+AC81*$AC61)/$I61 -> 0.75803223
A83: Non-Electricity Energy
A84: Solve first-order equation by using data above(total energy, electricity)
A85: Method: for a certain category(e.g. air conditioning), assuming the fraction of non-elec energy consumption of this category, is x
B86: Because the total energy consumption in the air-conditioning category in 2005 can be expressed in two ways in the following equation, we can solve the value of X:
B87: 23%*Total energy consumption of private/public house=34%*electricity consumption of private/public house+x*non-elec energy consumption of private/public house
B88: So x=((23%*Total energy consumption of private/public house)-(4%*electricity consumption of private/public house))/(Total Energy-Total Electricity)
K89: 私人住宅Private Housing Segment | U89: 公共住宅 Public Housing
I90: 總計 Total | K90: 年份 Year | L90: 煮食 Cooking | M90: 空氣調節 Air Conditioning | N90: 熱水 Hot Water | O90: 照明 Lighting | P90: 冷凍 Refrigeration | Q90: 辦公室設備 Office Equipment | R90: 其他 1 Others 1 | S90: 總計 Total | U90: 年份 Year | V90: 煮食 Cooking | W90: 空氣調節 Air Conditioning | X90: 熱水 Hot Water | Y90: 照明 Lighting | Z90: 冷凍 Refrigeration | AA90: 辦公室設備 Office Equipment | AB90: 其他 1 Others 1 | AC90: 總計 Total
I91: =I6-I46 -> 18554 | K91: 2006 | L91: =(L6-L46)/($S6-$S46) -> 0.63892617 | M91: =(M6-M46)/($S6-$S46) -> 0 | N91: =(N6-N46)/($S6-$S46) -> 0.36009762 | O91: =(O6-O46)/($S6-$S46) -> 0 | P91: =(P6-P46)/($S6-$S46) -> 0 | Q91: =(Q6-Q46)/($S6-$S46) -> 0 | R91: =(R6-R46)/($S6-$S46) -> 0.000976205 | S91: =(S6-S46)/($S6-$S46) -> 1 | U91: 2006 | V91: =(V6-V46)/($AC6-$AC46) -> 0.56168301 | W91: =(W6-W46)/($AC6-$AC46) -> 0 | X91: =(X6-X46)/($AC6-$AC46) -> 0.43341503 | Y91: =(Y6-Y46)/($AC6-$AC46) -> 0 | Z91: =(Z6-Z46)/($AC6-$AC46) -> 0 | AA91: =(AA6-AA46)/($AC6-$AC46) -> 0 | AB91: =(AB6-AB46)/($AC6-$AC46) -> 0.0045955882 | AC91: =(AC6-AC46)/($AC6-$AC46) -> 1
I92: =I7-I47 -> 18295 | K92: 2007 | L92: =(L7-L47)/($S7-$S47) -> 0.64991377 | M92: =(M7-M47)/($S7-$S47) -> 0 | N92: =(N7-N47)/($S7-$S47) -> 0.34897758 | O92: =(O7-O47)/($S7-$S47) -> 0 | P92: =(P7-P47)/($S7-$S47) -> 0 | Q92: =(Q7-Q47)/($S7-$S47) -> 0 | R92: =(R7-R47)/($S7-$S47) -> 0.0011086475 | S92: =(S7-S47)/($S7-$S47) -> 1 | U92: 2007 | V92: =(V7-V47)/($AC7-$AC47) -> 0.57449469 | W92: =(W7-W47)/($AC7-$AC47) -> 0 | X92: =(X7-X47)/($AC7-$AC47) -> 0.42060846 | Y92: =(Y7-Y47)/($AC7-$AC47) -> 0 | Z92: =(Z7-Z47)/($AC7-$AC47) -> 0 | AA92: =(AA7-AA47)/($AC7-$AC47) -> 0 | AB92: =(AB7-AB47)/($AC7-$AC47) -> 0.0048968535 | AC92: =(AC7-AC47)/($AC7-$AC47) -> 1
I93: =I8-I48 -> 18749 | K93: 2008 | L93: =(L8-L48)/($S8-$S48) -> 0.65550807 | M93: =(M8-M48)/($S8-$S48) -> 0 | N93: =(N8-N48)/($S8-$S48) -> 0.34330484 | O93: =(O8-O48)/($S8-$S48) -> 0 | P93: =(P8-P48)/($S8-$S48) -> 0 | Q93: =(Q8-Q48)/($S8-$S48) -> 0 | R93: =(R8-R48)/($S8-$S48) -> 0.0011870845 | S93: =(S8-S48)/($S8-$S48) -> 1 | U93: 2008 | V93: =(V8-V48)/($AC8-$AC48) -> 0.58466878 | W93: =(W8-W48)/($AC8-$AC48) -> 0 | X93: =(X8-X48)/($AC8-$AC48) -> 0.41012555 | Y93: =(Y8-Y48)/($AC8-$AC48) -> 0 | Z93: =(Z8-Z48)/($AC8-$AC48) -> 0 | AA93: =(AA8-AA48)/($AC8-$AC48) -> 0 | AB93: =(AB8-AB48)/($AC8-$AC48) -> 0.0053077473 | AC93: =(AC8-AC48)/($AC8-$AC48) -> 1
I94: =I9-I49 -> 18759 | K94: 2009 | L94: =(L9-L49)/($S9-$S49) -> 0.64706584 | M94: =(M9-M49)/($S9-$S49) -> 0 | N94: =(N9-N49)/($S9-$S49) -> 0.35245706 | O94: =(O9-O49)/($S9-$S49) -> 0 | P94: =(P9-P49)/($S9-$S49) -> 0 | Q94: =(Q9-Q49)/($S9-$S49) -> 0 | R94: =(R9-R49)/($S9-$S49) -> 0.00071564885 | S94: =(S9-S49)/($S9-$S49) -> 1 | U94: 2009 | V94: =(V9-V49)/($AC9-$AC49) -> 0.57882329 | W94: =(W9-W49)/($AC9-$AC49) -> 0 | X94: =(X9-X49)/($AC9-$AC49) -> 0.41656417 | Y94: =(Y9-Y49)/($AC9-$AC49) -> 0 | Z94: =(Z9-Z49)/($AC9-$AC49) -> 0 | AA94: =(AA9-AA49)/($AC9-$AC49) -> 0 | AB94: =(AB9-AB49)/($AC9-$AC49) -> 0.0046125461 | AC94: =(AC9-AC49)/($AC9-$AC49) -> 1
I95: =I10-I50 -> 19052 | K95: 2010 | L95: =(L10-L50)/($S10-$S50) -> 0.63837595 | M95: =(M10-M50)/($S10-$S50) -> 0 | N95: =(N10-N50)/($S10-$S50) -> 0.36115057 | O95: =(O10-O50)/($S10-$S50) -> 0 | P95: =(P10-P50)/($S10-$S50) -> 0 | Q95: =(Q10-Q50)/($S10-$S50) -> 0 | R95: =(R10-R50)/($S10-$S50) -> 0.00035511364 | S95: =(S10-S50)/($S10-$S50) -> 1 | U95: 2010 | V95: =(V10-V50)/($AC10-$AC50) -> 0.60426305 | W95: =(W10-W50)/($AC10-$AC50) -> 0 | X95: =(X10-X50)/($AC10-$AC50) -> 0.43126239 | Y95: =(Y10-Y50)/($AC10-$AC50) -> 0 | Z95: =(Z10-Z50)/($AC10-$AC50) -> 0 | AA95: =(AA10-AA50)/($AC10-$AC50) -> -0.004957039 | AB95: =(AB10-AB50)/($AC10-$AC50) -> 0.0041308658 | AC95: =(AC10-AC50)/($AC10-$AC50) -> 1
I96: =I11-I51 -> 18954 | K96: 2011 | L96: =(L11-L51)/($S11-$S51) -> 0.62179869 | M96: =(M11-M51)/($S11-$S51) -> 0 | N96: =(N11-N51)/($S11-$S51) -> 0.37796307 | O96: =(O11-O51)/($S11-$S51) -> 0 | P96: =(P11-P51)/($S11-$S51) -> 0 | Q96: =(Q11-Q51)/($S11-$S51) -> 0 | R96: =(R11-R51)/($S11-$S51) -> 0.00023823705 | S96: =(S11-S51)/($S11-$S51) -> 1 | U96: 2011 | V96: =(V11-V51)/($AC11-$AC51) -> 0.59860299 | W96: =(W11-W51)/($AC11-$AC51) -> 0 | X96: =(X11-X51)/($AC11-$AC51) -> 0.39749838 | Y96: =(Y11-Y51)/($AC11-$AC51) -> 0.14619883 | Z96: =(Z11-Z51)/($AC11-$AC51) -> 0 | AA96: =(AA11-AA51)/($AC11-$AC51) -> 0 | AB96: =(AB11-AB51)/($AC11-$AC51) -> 0.0038986355 | AC96: =(AC11-AC51)/($AC11-$AC51) -> 1
I97: =I12-I52 -> 18743 | K97: 2012 | L97: =(L12-L52)/($S12-$S52) -> 0.60782384 | M97: =(M12-M52)/($S12-$S52) -> 0 | N97: =(N12-N52)/($S12-$S52) -> 0.39217616 | O97: =(O12-O52)/($S12-$S52) -> 0 | P97: =(P12-P52)/($S12-$S52) -> 0 | Q97: =(Q12-Q52)/($S12-$S52) -> 0 | R97: =(R12-R52)/($S12-$S52) -> 0.00012301636 | S97: =(S12-S52)/($S12-$S52) -> 1 | U97: 2012 | V97: =(V12-V52)/($AC12-$AC52) -> 0.59496124 | W97: =(W12-W52)/($AC12-$AC52) -> 0 | X97: =(X12-X52)/($AC12-$AC52) -> 0.40164729 | Y97: =(Y12-Y52)/($AC12-$AC52) -> 0 | Z97: =(Z12-Z52)/($AC12-$AC52) -> 0 | AA97: =(AA12-AA52)/($AC12-$AC52) -> 0 | AB97: =(AB12-AB52)/($AC12-$AC52) -> 0.0033914729 | AC97: =(AC12-AC52)/($AC12-$AC52) -> 1
I98: =I17-I53 -> 20051 | K98: 2013 | L98: =(L13-L53)/($S13-$S53) -> 0.58754188 | M98: =(M13-M53)/($S13-$S53) -> 0 | N98: =(N13-N53)/($S13-$S53) -> 0.41220995 | O98: =(O13-O53)/($S13-$S53) -> 0 | P98: =(P13-P53)/($S13-$S53) -> 0 | Q98: =(Q13-Q53)/($S13-$S53) -> 0 | R98: =(R13-R53)/($S13-$S53) -> 0.00024816975 | S98: =(S13-S53)/($S13-$S53) -> 1 | U98: 2013 | V98: =(V13-V53)/($AC13-$AC53) -> 0.57269155 | W98: =(W13-W53)/($AC13-$AC53) -> 0 | X98: =(X13-X53)/($AC13-$AC53) -> 0.42387033 | Y98: =(Y13-Y53)/($AC13-$AC53) -> 0 | Z98: =(Z13-Z53)/($AC13-$AC53) -> 0 | AA98: =(AA13-AA53)/($AC13-$AC53) -> 0 | AB98: =(AB13-AB53)/($AC13-$AC53) -> 0.0036018337 | AC98: =(AC13-AC53)/($AC13-$AC53) -> 1
I99: =I18-I54 -> 17378 | K99: 2014 | L99: =(L14-L54)/($S14-$S54) -> 0.56315336 | M99: =(M14-M54)/($S14-$S54) -> 0 | N99: =(N14-N54)/($S14-$S54) -> 0.43623171 | O99: =(O14-O54)/($S14-$S54) -> 0 | P99: =(P14-P54)/($S14-$S54) -> 0 | Q99: =(Q14-Q54)/($S14-$S54) -> 0 | R99: =(R14-R54)/($S14-$S54) -> 0.00049194441 | S99: =(S14-S54)/($S14-$S54) -> 1 | U99: 2014 | V99: =(V14-V54)/($AC14-$AC54) -> 0.55009018 | W99: =(W14-W54)/($AC14-$AC54) -> 0 | X99: =(X14-X54)/($AC14-$AC54) -> 0.44597475 | Y99: =(Y14-Y54)/($AC14-$AC54) -> 0 | Z99: =(Z14-Z54)/($AC14-$AC54) -> 0 | AA99: =(AA14-AA54)/($AC14-$AC54) -> 0 | AB99: =(AB14-AB54)/($AC14-$AC54) -> 0.00377111 | AC99: =(AC14-AC54)/($AC14-$AC54) -> 1
I100: =I19-I55 -> 18657 | K100: 2015 | L100: =(L15-L55)/($S15-$S55) -> 0.53622068 | M100: =(M15-M55)/($S15-$S55) -> 0 | N100: =(N15-N55)/($S15-$S55) -> 0.46261923 | O100: =(O15-O55)/($S15-$S55) -> 0 | P100: =(P15-P55)/($S15-$S55) -> 0 | Q100: =(Q15-Q55)/($S15-$S55) -> 0 | R100: =(R15-R55)/($S15-$S55) -> 0.0011600928 | S100: =(S15-S55)/($S15-$S55) -> 1 | U100: 2015 | V100: =(V15-V55)/($AC15-$AC55) -> 0.52871821 | W100: =(W15-W55)/($AC15-$AC55) -> 0 | X100: =(X15-X55)/($AC15-$AC55) -> 0.46757622 | Y100: =(Y15-Y55)/($AC15-$AC55) -> 0 | Z100: =(Z15-Z55)/($AC15-$AC55) -> 0 | AA100: =(AA15-AA55)/($AC15-$AC55) -> 0 | AB100: =(AB15-AB55)/($AC15-$AC55) -> 0.0038740104 | AC100: =(AC15-AC55)/($AC15-$AC55) -> 1
I101: =I21-I56 -> 23601 | K101: 2016 | L101: =(L16-L56)/($S16-$S56) -> 0.5099743 | M101: =(M16-M56)/($S16-$S56) -> 0 | N101: =(N16-N56)/($S16-$S56) -> 0.4877004 | O101: =(O16-O56)/($S16-$S56) -> 0 | P101: =(P16-P56)/($S16-$S56) -> 0 | Q101: =(Q16-Q56)/($S16-$S56) -> 0 | R101: =(R16-R56)/($S16-$S56) -> 0.0023252968 | S101: =(S16-S56)/($S16-$S56) -> 1 | U101: 2016 | V101: =(V16-V56)/($AC16-$AC56) -> 0.50932497 | W101: =(W16-W56)/($AC16-$AC56) -> 0 | X101: =(X16-X56)/($AC16-$AC56) -> 0.48671398 | Y101: =(Y16-Y56)/($AC16-$AC56) -> 0 | Z101: =(Z16-Z56)/($AC16-$AC56) -> 0 | AA101: =(AA16-AA56)/($AC16-$AC56) -> 0 | AB101: =(AB16-AB56)/($AC16-$AC56) -> 0.0037960059 | AC101: =(AC16-AC56)/($AC16-$AC56) -> 1
K102: 2017 | L102: =(L17-L57)/($S17-$S57) -> 0.4823673 | M102: =(M17-M57)/($S17-$S57) -> 0 | N102: =(N17-N57)/($S17-$S57) -> 0.51299573 | O102: =(O17-O57)/($S17-$S57) -> 0 | P102: =(P17-P57)/($S17-$S57) -> 0 | Q102: =(Q17-Q57)/($S17-$S57) -> 0 | R102: =(R17-R57)/($S17-$S57) -> 0 | S102: =(S17-S57)/($S17-$S57) -> 1 | U102: 2017 | V102: =(V17-V57)/($AC17-$AC57) -> 0.49233878 | W102: =(W17-W57)/($AC17-$AC57) -> 0.0013470281 | X102: =(X17-X57)/($AC17-$AC57) -> 0.50463041 | Y102: =(Y17-Y57)/($AC17-$AC57) -> 0.00016837851 | Z102: =(Z17-Z57)/($AC17-$AC57) -> 0.00033675703 | AA102: =(AA17-AA57)/($AC17-$AC57) -> 0.00033675703 | AB102: =(AB17-AB57)/($AC17-$AC57) -> 0.00016837851 | AC102: =(AC17-AC57)/($AC17-$AC57) -> 1
K103: 2018 | L103: =(L18-L58)/($S18-$S58) -> 0.50330742 | M103: =(M18-M58)/($S18-$S58) -> 0 | N103: =(N18-N58)/($S18-$S58) -> 0.49239875 | O103: =(O18-O58)/($S18-$S58) -> 0 | P103: =(P18-P58)/($S18-$S58) -> 0 | Q103: =(Q18-Q58)/($S18-$S58) -> 0 | R103: =(R18-R58)/($S18-$S58) -> 0 | S103: =(S18-S58)/($S18-$S58) -> 1 | U103: 2018 | V103: =(V18-V58)/($AC18-$AC58) -> 0.49927641 | W103: =(W18-W58)/($AC18-$AC58) -> 0.0025727609 | X103: =(X18-X58)/($AC18-$AC58) -> 0.49847242 | Y103: =(Y18-Y58)/($AC18-$AC58) -> 0.00032159511 | Z103: =(Z18-Z58)/($AC18-$AC58) -> 0.00064319022 | AA103: =(AA18-AA58)/($AC18-$AC58) -> 0.00064319022 | AB103: =(AB18-AB58)/($AC18-$AC58) -> 0.00032159511 | AC103: =(AC18-AC58)/($AC18-$AC58) -> 1
K104: 2019 | L104: =(L19-L59)/($S19-$S59) -> 0.48301792 | M104: =(M19-M59)/($S19-$S59) -> 0 | N104: =(N19-N59)/($S19-$S59) -> 0.51221958 | O104: =(O19-O59)/($S19-$S59) -> 0 | P104: =(P19-P59)/($S19-$S59) -> 0 | Q104: =(Q19-Q59)/($S19-$S59) -> 0 | R104: =(R19-R59)/($S19-$S59) -> 0 | S104: =(S19-S59)/($S19-$S59) -> 1 | U104: 2019 | V104: =(V19-V59)/($AC19-$AC59) -> 0.49349983 | W104: =(W19-W59)/($AC19-$AC59) -> 0.0034211427 | X104: =(X19-X59)/($AC19-$AC59) -> 0.50496066 | Y104: =(Y19-Y59)/($AC19-$AC59) -> 0.0005131714 | Z104: =(Z19-Z59)/($AC19-$AC59) -> 0.00085528567 | AA104: =(AA19-AA59)/($AC19-$AC59) -> 0.00085528567 | AB104: =(AB19-AB59)/($AC19-$AC59) -> 0.00034211427 | AC104: =(AC19-AC59)/($AC19-$AC59) -> 1
...

Sheet Commercial8EndUse
A1: Commercial Sector Energy Consumption by End-use
A2: Source: | B2: EMSD End Use 2023 | G2: NOTE --> from 2017 - 2021, referred to the corresponding ESMD End use report since there was no singular graph that showed total energy/ electiricty consumption by commercial end use with multiple years :. Had to refer to many previous iterations
B4: Energy | G4: Energy
D5: 2021 | E5: 2016 | H5: Air Conditioning | I5: Hot Water & Refrigeration | J5: Lighting | K5: Office Equipment | L5: Cooking | M5: Others | N5: Sum | O5: NOTE --> Others include vertical transport
G6: 2005 | H6: 0.28 | I6: 0.07 | J6: 0.16 | K6: 0.05 | L6: 0.15 | M6: 0.29 | N6: =SUM(H6:M6) -> 1
B7: 空气调节 | C7: Air Conditioning | D7: 0.25 | E7: 0.24 | G7: 2006 | H7: 0.27 | I7: 0.08 | J7: 0.15 | K7: 0.05 | L7: 0.15 | M7: 0.3 | N7: =SUM(H7:M7) -> 1
B8: 热水及冷冻 | C8: Hot Water & Refrigeration | D8: 0.09 | E8: 0.12 | G8: 2007 | H8: 0.27 | I8: 0.06 | J8: 0.15 | K8: 0.04 | L8: 0.11 | M8: 0.37 | N8: =SUM(H8:M8) -> 1
B9: 照明 | C9: Lighting | D9: 0.11 | E9: 0.12 | G9: 2008 | H9: 0.24 | I9: 0.1 | J9: 0.1 | K9: 0.05 | L9: 0.13 | M9: 0.38 | N9: =SUM(H9:M9) -> 1
B10: 办公设备 | C10: Office Equipment | D10: 0.05 | E10: 0.05 | G10: 2009 | H10: 0.24 | I10: 0.1 | J10: 0.1 | K10: 0.05 | L10: 0.13 | M10: 0.38 | N10: =SUM(H10:M10) -> 1
B11: 煮食 | C11: Cooking | D11: 0.11 | E11: 0.14 | G11: 2010 | H11: 0.25 | I11: 0.1 | J11: 0.12 | K11: 0.05 | L11: 0.13 | M11: 0.35 | N11: =SUM(H11:M11) -> 1 | Q11: Taken from EMSD Total Energy Consumption by End-Use
B12: 其他 | C12: Others | D12: 0.32 | E12: 0.33 | G12: 2011 | H12: 0.26 | I12: 0.12 | J12: 0.13 | K12: 0.05 | L12: 0.13 | M12: 0.31 | N12: =SUM(H12:M12) -> 1 | Q12: 116013
B13: Sum | E13: =SUM(E7:E12) -> 1 | G13: 2012 | H13: 0.25 | I13: 0.12 | J13: 0.13 | K13: 0.05 | L13: 0.14 | M13: 0.31 | N13: =SUM(H13:M13) -> 1 | Q13: 118330
G14: 2013 | H14: 0.26 | I14: 0.12 | J14: 0.13 | K14: 0.05 | L14: 0.14 | M14: 0.3 | N14: =SUM(H14:M14) -> 1 | Q14: 118209
G15: 2014 | H15: 0.26 | I15: 0.12 | J15: 0.13 | K15: 0.05 | L15: 0.14 | M15: 0.3 | N15: =SUM(H15:M15) -> 1 | Q15: 119615
G16: 2015 | H16: 0.25 | I16: 0.12 | J16: 0.12 | K16: 0.05 | L16: 0.14 | M16: 0.32 | N16: =SUM(H16:M16) -> 1 | Q16: 120417
G17: 2016 | H17: 0.24 | I17: 0.12 | J17: 0.12 | K17: 0.05 | L17: 0.14 | M17: 0.33 | N17: =SUM(H17:M17) -> 1 | Q17: 120458
G18: 2017 | H18: 0.25 | I18: 0.12 | J18: 0.12 | K18: 0.05 | L18: 0.13 | M18: 0.33 | N18: =SUM(H18:M18) -> 1 | Q18: 120408
G19: 2018 | H19: 0.26 | I19: 0.12 | J19: 0.12 | K19: 0.05 | L19: 0.14 | M19: 0.32 | N19: =SUM(H19:M19) -> 1.01 | Q19: 122220
G20: 2019 | H20: 0.22 | I20: 0.1 | J20: 0.1 | K20: 0.05 | L20: 0.13 | M20: 0.39 | N20: =SUM(H20:M20) -> 0.99 | Q20: 123001
G21: 2020 | H21: 0.25 | I21: 0.09 | J21: 0.11 | K21: 0.06 | L21: 0.1 | M21: 0.39 | N21: =SUM(H21:M21) -> 1 | Q21: 114512
G22: 2021 | H22: 0.25 | I22: 0.09 | J22: 0.11 | K22: 0.05 | L22: 0.11 | M22: 0.39 | N22: =SUM(H22:M22) -> 1 | Q22: 120083
B25: Electricity | G25: Electricity
D26: 2021 | E26: 2016 | H26: Air Conditioning | I26: Hot Water & Refrigeration | J26: Lighting | K26: Office Equipment | L26: Cooking | M26: Others | N26: Sum
B27: 空气调节 | C27: Air Conditioning | D27: 0.28 | E27: 0.29 | G27: 2005 | H27: 0.34 | I27: 0.03 | J27: 0.19 | K27: 0.07 | L27: 0.05 | M27: 0.32 | N27: =SUM(H27:M27) -> 1
B28: 热水及冷冻 | C28: Hot Water & Refrigeration | D28: 0.06 | E28: 0.08 | G28: 2006 | H28: 0.33 | I28: 0.05 | J28: 0.17 | K28: 0.06 | L28: 0.06 | M28: 0.33 | N28: =SUM(H28:M28) -> 1
B29: 照明 | C29: Lighting | D29: 0.12 | E29: 0.15 | G29: 2007 | H29: No data about electricity demand decomposition between 2007-2011
B30: 办公设备 | C30: Office Equipment | D30: 0.06 | E30: 0.06 | G30: 2008
B31: 煮食 | C31: Cooking | D31: 0.06 | E31: 0.07 | G31: 2009
B32: 其他 | C32: Others | D32: 0.34 | E32: 0.35 | G32: 2010
B33: Sum | E33: =SUM(E27:E32) -> 1 | G33: 2011
G34: 2012 | H34: 0.3 | I34: 0.08 | J34: 0.15 | K34: 0.06 | L34: 0.08 | M34: 0.33 | N34: =SUM(H34:M34) -> 1
G35: 2013 | H35: 0.3 | I35: 0.08 | J35: 0.16 | K35: 0.06 | L35: 0.08 | M35: 0.32 | N35: =SUM(H35:M35) -> 1
G36: 2014 | H36: 0.31 | I36: 0.08 | J36: 0.15 | K36: 0.06 | L36: 0.08 | M36: 0.32 | N36: =SUM(H36:M36) -> 1
G37: 2015 | H37: 0.29 | I37: 0.08 | J37: 0.15 | K37: 0.06 | L37: 0.07 | M37: 0.35 | N37: =SUM(H37:M37) -> 1
G38: 2016 | H38: 0.29 | I38: 0.08 | J38: 0.15 | K38: 0.06 | L38: 0.07 | M38: 0.35 | N38: =SUM(H38:M38) -> 1
G39: 2017 | H39: 0.3 | I39: 0.09 | J39: 0.14 | K39: 0.06 | L39: 0.07 | M39: 0.34 | N39: =SUM(H39:M39) -> 1
G40: 2018 | H40: 0.31 | I40: 0.09 | J40: 0.14 | K40: 0.06 | L40: 0.07 | M40: 0.34 | N40: =SUM(H40:M40) -> 1.01
G41: 2019 | H41: 0.25 | I41: 0.07 | J41: 0.12 | K41: 0.06 | L41: 0.07 | M41: 0.43 | N41: =SUM(H41:M41) -> 1
G42: 2020 | H42: 0.28 | I42: 0.06 | J42: 0.12 | K42: 0.06 | L42: 0.05 | M42: 0.42 | N42: =SUM(H42:M42) -> 0.99
G43: 2021 | H43: 0.28 | I43: 0.06 | J43: 0.12 | K43: 0.06 | L43: 0.06 | M43: 0.42 | N43: =SUM(H43:M43) -> 1
G45: Calculating the decomposition of energy other than electricity
G46: Equation: for a certain category(e.g. air conditioning), assuming the fraction of energy consumption, other than electricity consumption, of this category, is x
H47: Then, the total consumption in 2005 in the commercial sector in air-conditioning category is
H48: 23%*Total energy consumption in commercial sector=35%*electricity consumption+x*other energy consumption
H50: Therefore, x=(23%*Total energy consumption in commercial sector-35%*electricity consumption)/(other energy consumption)
G51: Calculating Results:
G52: Energy Except Electricity (Town gas, oil&coal) | R52: Energy Except Electricity (Town gas, oil&coal)
H53: Air Conditioning | I53: Hot Water & Refrigeration | J53: Lighting | K53: Office Equipment | L53: Cooking | M53: Others | N53: Sum | S53: Air Conditioning | T53: Hot Water & Refrigeration | U53: Lighting | V53: Office Equipment | W53: Cooking | X53: Others | Y53: Sum
G54: 2006 | H54: =(H7*Energy8Sec!$C7-Commercial8EndUse!H28*Energy8Sec!$C27)/(Energy8Sec!$C7-Energy8Sec!$C27) -> -0.031557602 | I54: =(I7*Energy8Sec!$C7-Commercial8EndUse!I28*Energy8Sec!$C27)/(Energy8Sec!$C7-Energy8Sec!$C27) -> 0.2307788 | J54: =(J7*Energy8Sec!$C7-Commercial8EndUse!J28*Energy8Sec!$C27)/(Energy8Sec!$C7-Energy8Sec!$C27) -> 0.049480799 | K54: =(K7*Energy8Sec!$C7-Commercial8EndUse!K28*Energy8Sec!$C27)/(Energy8Sec!$C7-Energy8Sec!$C27) -> -0.00025960037 | L54: =(L7*Energy8Sec!$C7-Commercial8EndUse!L28*Energy8Sec!$C27)/(Energy8Sec!$C7-Energy8Sec!$C27) -> 0.6023364 | M54: =(M7*Energy8Sec!$C7-Commercial8EndUse!M28*Energy8Sec!$C27)/(Energy8Sec!$C7-Energy8Sec!$C27) -> 0.1492212 | N54: =(N7*Energy8Sec!$C7-Commercial8EndUse!N28*Energy8Sec!$C27)/(Energy8Sec!$C7-Energy8Sec!$C27) -> 1 | R54: 2006 | S54: 0 | T54: 0.2307788 | U54: 0.049480799 | V54: -0.00025960037 | W54: 0.6023364 | X54: =Y54-SUM(S54:W54) -> 0.1176636 | Y54: 1
G55: 2007 | H55: No data | P55: 1.Replace negative | R55: 2007 | S55: No data
G56: 2008 | P56: value with 0； | R56: 2008
G57: 2009 | R57: 2009
G58: 2010 | P58: 2.Adjust "other" to make | R58: 2010
G59: 2011 | P59: sum=100% | R59: 2011
G60: 2012 | H60: =(H13*Energy8Sec!$C13-Commercial8EndUse!H34*Energy8Sec!$C33)/(Energy8Sec!$C13-Energy8Sec!$C33) -> -0.015733152 | I60: =(I13*Energy8Sec!$C13-Commercial8EndUse!I34*Energy8Sec!$C33)/(Energy8Sec!$C13-Energy8Sec!$C33) -> 0.33258652 | J60: =(J13*Energy8Sec!$C13-Commercial8EndUse!J34*Energy8Sec!$C33)/(Energy8Sec!$C13-Energy8Sec!$C33) -> 0.023706739 | K60: =(K13*Energy8Sec!$C13-Commercial8EndUse!K34*Energy8Sec!$C33)/(Energy8Sec!$C13-Energy8Sec!$C33) -> -0.0031466305 | L60: =(L13*Energy8Sec!$C13-Commercial8EndUse!L34*Energy8Sec!$C33)/(Energy8Sec!$C13-Energy8Sec!$C33) -> 0.45887978 | M60: =(M13*Energy8Sec!$C13-Commercial8EndUse!M34*Energy8Sec!$C33)/(Energy8Sec!$C13-Energy8Sec!$C33) -> 0.20370674 | N60: =(N13*Energy8Sec!$C13-Commercial8EndUse!N34*Energy8Sec!$C33)/(Energy8Sec!$C13-Energy8Sec!$C33) -> 1 | R60: 2012 | S60: 0 | T60: 0.33258652 | U60: 0.023706739 | V60: 0 | W60: 0.45887978 | X60: =Y60-SUM(S60:W60) -> 0.18482696 | Y60: 1
G61: 2013 | H61: =(H14*Energy8Sec!$C14-Commercial8EndUse!H35*Energy8Sec!$C34)/(Energy8Sec!$C14-Energy8Sec!$C34) -> 0.054314669 | I61: =(I14*Energy8Sec!$C14-Commercial8EndUse!I35*Energy8Sec!$C34)/(Energy8Sec!$C14-Energy8Sec!$C34) -> 0.32568533 | J61: =(J14*Energy8Sec!$C14-Commercial8EndUse!J35*Energy8Sec!$C34)/(Energy8Sec!$C14-Energy8Sec!$C34) -> -0.024263998 | K61: =(K14*Energy8Sec!$C14-Commercial8EndUse!K35*Energy8Sec!$C34)/(Energy8Sec!$C14-Energy8Sec!$C34) -> -0.0014213327 | L61: =(L14*Energy8Sec!$C14-Commercial8EndUse!L35*Energy8Sec!$C34)/(Energy8Sec!$C14-Energy8Sec!$C34) -> 0.448528 | M61: =(M14*Energy8Sec!$C14-Commercial8EndUse!M35*Energy8Sec!$C34)/(Energy8Sec!$C14-Energy8Sec!$C34) -> 0.19715733 | N61: =(N14*Energy8Sec!$C14-Commercial8EndUse!N35*Energy8Sec!$C34)/(Energy8Sec!$C14-Energy8Sec!$C34) -> 1 | R61: 2013 | S61: 0 | T61: 0.32568533 | U61: 0 | V61: 0 | W61: 0.448528 | X61: =Y61-SUM(S61:W61) -> 0.22578667 | Y61: 1
G62: 2014 | H62: =(H15*Energy8Sec!$C15-Commercial8EndUse!H36*Energy8Sec!$C35)/(Energy8Sec!$C15-Energy8Sec!$C35) -> 0.0045055766 | I62: =(I15*Energy8Sec!$C15-Commercial8EndUse!I36*Energy8Sec!$C35)/(Energy8Sec!$C15-Energy8Sec!$C35) -> 0.32439554 | J62: =(J15*Energy8Sec!$C15-Commercial8EndUse!J36*Energy8Sec!$C35)/(Energy8Sec!$C15-Energy8Sec!$C35) -> 0.027802231 | K62: =(K15*Energy8Sec!$C15-Commercial8EndUse!K36*Energy8Sec!$C35)/(Energy8Sec!$C15-Energy8Sec!$C35) -> -0.0010988847 | L62: =(L15*Energy8Sec!$C15-Commercial8EndUse!L36*Energy8Sec!$C35)/(Energy8Sec!$C15-Energy8Sec!$C35) -> 0.44659331 | M62: =(M15*Energy8Sec!$C15-Commercial8EndUse!M36*Energy8Sec!$C35)/(Energy8Sec!$C15-Energy8Sec!$C35) -> 0.19780223 | N62: =(N15*Energy8Sec!$C15-Commercial8EndUse!N36*Energy8Sec!$C35)/(Energy8Sec!$C15-Energy8Sec!$C35) -> 1 | R62: 2014 | S62: 0 | T62: 0.32439554 | U62: 0.027802231 | V62: 0 | W62: 0.44659331 | X62: =Y62-SUM(S62:W62) -> 0.20120892 | Y62: 1
G63: 2015 | H63: =(H16*Energy8Sec!$C16-Commercial8EndUse!H37*Energy8Sec!$C36)/(Energy8Sec!$C16-Energy8Sec!$C36) -> 0.042416796 | I63: =(I16*Energy8Sec!$C16-Commercial8EndUse!I37*Energy8Sec!$C36)/(Energy8Sec!$C16-Energy8Sec!$C36) -> 0.3275832 | J63: =(J16*Energy8Sec!$C16-Commercial8EndUse!J37*Energy8Sec!$C36)/(Energy8Sec!$C16-Energy8Sec!$C36) -> -0.035687403 | K63: =(K16*Energy8Sec!$C16-Commercial8EndUse!K37*Energy8Sec!$C36)/(Energy8Sec!$C16-Energy8Sec!$C36) -> -0.001895801 | L63: =(L16*Energy8Sec!$C16-Commercial8EndUse!L37*Energy8Sec!$C36)/(Energy8Sec!$C16-Energy8Sec!$C36) -> 0.50327061 | M63: =(M16*Energy8Sec!$C16-Commercial8EndUse!M37*Energy8Sec!$C36)/(Energy8Sec!$C16-Energy8Sec!$C36) -> 0.1643126 | N63: =(N16*Energy8Sec!$C16-Commercial8EndUse!N37*Energy8Sec!$C36)/(Energy8Sec!$C16-Energy8Sec!$C36) -> 1 | R63: 2015 | S63: 0 | T63: 0.3275832 | U63: 0 | V63: 0 | W63: 0.50327061 | X63: =Y63-SUM(S63:W63) -> 0.16914619 | Y63: 1
G64: 2016 | H64: =(H17*Energy8Sec!$C17-Commercial8EndUse!H38*Energy8Sec!$C37)/(Energy8Sec!$C17-Energy8Sec!$C37) -> -0.018564815 | I64: =(I17*Energy8Sec!$C17-Commercial8EndUse!I38*Energy8Sec!$C37)/(Energy8Sec!$C17-Energy8Sec!$C37) -> 0.32685185 | J64: =(J17*Energy8Sec!$C17-Commercial8EndUse!J38*Energy8Sec!$C37)/(Energy8Sec!$C17-Energy8Sec!$C37) -> -0.035138889 | K64: =(K17*Energy8Sec!$C17-Commercial8EndUse!K38*Energy8Sec!$C37)/(Energy8Sec!$C17-Energy8Sec!$C37) -> -0.001712963 | L64: =(L17*Energy8Sec!$C17-Commercial8EndUse!L38*Energy8Sec!$C37)/(Energy8Sec!$C17-Energy8Sec!$C37) -> 0.50199074 | M64: =(M17*Energy8Sec!$C17-Commercial8EndUse!M38*Energy8Sec!$C37)/(Energy8Sec!$C17-Energy8Sec!$C37) -> 0.22657407 | N64: =(N17*Energy8Sec!$C17-Commercial8EndUse!N38*Energy8Sec!$C37)/(Energy8Sec!$C17-Energy8Sec!$C37) -> 1 | R64: 2016 | S64: 0 | T64: 0.32685185 | U64: 0 | V64: 0 | W64: 0.50199074 | X64: =$Y64-SUM($S64:$W64) -> 0.17115741 | Y64: 1
G65: 2017 | H65: =(H18*Energy8Sec!$C18-Commercial8EndUse!H39*Energy8Sec!$C38)/(Energy8Sec!$C18-Energy8Sec!$C38) -> -0.082514772 | I65: =(I18*Energy8Sec!$C18-Commercial8EndUse!I39*Energy8Sec!$C38)/(Energy8Sec!$C18-Energy8Sec!$C38) -> 0.31950886 | J65: =(J18*Energy8Sec!$C18-Commercial8EndUse!J39*Energy8Sec!$C38)/(Energy8Sec!$C18-Energy8Sec!$C38) -> -0.013005909 | K65: =(K18*Energy8Sec!$C18-Commercial8EndUse!K39*Energy8Sec!$C38)/(Energy8Sec!$C18-Energy8Sec!$C38) -> -0.016502954 | L65: =(L18*Energy8Sec!$C18-Commercial8EndUse!L39*Energy8Sec!$C38)/(Energy8Sec!$C18-Energy8Sec!$C38) -> 0.52901773 | M65: =(M18*Energy8Sec!$C18-Commercial8EndUse!M39*Energy8Sec!$C38)/(Energy8Sec!$C18-Energy8Sec!$C38) -> 0.26349705 | N65: =(N18*Energy8Sec!$C18-Commercial8EndUse!N39*Energy8Sec!$C38)/(Energy8Sec!$C18-Energy8Sec!$C38) -> 1 | R65: 2017 | S65: 0 | T65: 0.32 | U65: 0 | V65: 0 | W65: 0.529 | X65: =$Y65-SUM($S65:$W65) -> 0.151 | Y65: 1
G66: 2018 | H66: =(H19*Energy8Sec!$C19-Commercial8EndUse!H40*Energy8Sec!$C39)/(Energy8Sec!$C19-Energy8Sec!$C39) -> -0.073639902 | I66: =(I19*Energy8Sec!$C19-Commercial8EndUse!I40*Energy8Sec!$C39)/(Energy8Sec!$C19-Energy8Sec!$C39) -> 0.32018394 | J66: =(J19*Energy8Sec!$C19-Commercial8EndUse!J40*Energy8Sec!$C39)/(Energy8Sec!$C19-Energy8Sec!$C39) -> -0.013455961 | K66: =(K19*Energy8Sec!$C19-Commercial8EndUse!K40*Energy8Sec!$C39)/(Energy8Sec!$C19-Energy8Sec!$C39) -> -0.01672798 | L66: =(L19*Energy8Sec!$C19-Commercial8EndUse!L40*Energy8Sec!$C39)/(Energy8Sec!$C19-Energy8Sec!$C39) -> 0.60709586 | M66: =(M19*Energy8Sec!$C19-Commercial8EndUse!M40*Energy8Sec!$C39)/(Energy8Sec!$C19-Energy8Sec!$C39) -> 0.18654404 | N66: =(N19*Energy8Sec!$C19-Commercial8EndUse!N40*Energy8Sec!$C39)/(Energy8Sec!$C19-Energy8Sec!$C39) -> 1.01 | R66: 2018 | S66: 0 | T66: 0.32 | U66: 0 | V66: 0 | W66: 0.607 | X66: =$Y66-SUM($S66:$W66) -> 0.073 | Y66: 1
G67: 2019 | H67: =(H20*Energy8Sec!$C20-Commercial8EndUse!H41*Energy8Sec!$C40)/(Energy8Sec!$C20-Energy8Sec!$C40) -> 0.0042110171 | I67: =(I20*Energy8Sec!$C20-Commercial8EndUse!I41*Energy8Sec!$C40)/(Energy8Sec!$C20-Energy8Sec!$C40) -> 0.31578898 | J67: =(J20*Energy8Sec!$C20-Commercial8EndUse!J41*Energy8Sec!$C40)/(Energy8Sec!$C20-Energy8Sec!$C40) -> -0.043859322 | K67: =(K20*Energy8Sec!$C20-Commercial8EndUse!K41*Energy8Sec!$C40)/(Energy8Sec!$C20-Energy8Sec!$C40) -> -0.021929661 | L67: =(L20*Energy8Sec!$C20-Commercial8EndUse!L41*Energy8Sec!$C40)/(Energy8Sec!$C20-Energy8Sec!$C40) -> 0.56157797 | M67: =(M20*Energy8Sec!$C20-Commercial8EndUse!M41*Energy8Sec!$C40)/(Energy8Sec!$C20-Energy8Sec!$C40) -> 0.10228136 | N67: =(N20*Energy8Sec!$C20-Commercial8EndUse!N41*Energy8Sec!$C40)/(Energy8Sec!$C20-Energy8Sec!$C40) -> 0.91807034 | R67: 2019 | S67: 0.004 | T67: 0.316 | U67: 0 | V67: 0 | W67: 0.562 | X67: =$Y67-SUM($S67:$W67) -> 0.118 | Y67: 1
G68: 2020 | H68: =(H21*Energy8Sec!$C21-Commercial8EndUse!H42*Energy8Sec!$C41)/(Energy8Sec!$C21-Energy8Sec!$C41) -> 0.0017205346 | I68: =(I21*Energy8Sec!$C21-Commercial8EndUse!I42*Energy8Sec!$C41)/(Energy8Sec!$C21-Energy8Sec!$C41) -> 0.33827947 | J68: =(J21*Energy8Sec!$C21-Commercial8EndUse!J42*Energy8Sec!$C41)/(Energy8Sec!$C21-Energy8Sec!$C41) -> 0.027240178 | K68: =(K21*Energy8Sec!$C21-Commercial8EndUse!K42*Energy8Sec!$C41)/(Energy8Sec!$C21-Energy8Sec!$C41) -> 0.06 | L68: =(L21*Energy8Sec!$C21-Commercial8EndUse!L42*Energy8Sec!$C41)/(Energy8Sec!$C21-Energy8Sec!$C41) -> 0.51379911 | M68: =(M21*Energy8Sec!$C21-Commercial8EndUse!M42*Energy8Sec!$C41)/(Energy8Sec!$C21-Energy8Sec!$C41) -> 0.14172053 | N68: =(N21*Energy8Sec!$C21-Commercial8EndUse!N42*Energy8Sec!$C41)/(Energy8Sec!$C21-Energy8Sec!$C41) -> 1.0827598 | R68: 2020 | S68: 0.002 | T68: 0.3385 | U68: 0.027 | V68: 0.06 | W68: 0.514 | X68: =$Y68-SUM($S68:$W68) -> 0.0585 | Y68: 1
G69: 2021 | H69: =(H22*Energy8Sec!$C22-Commercial8EndUse!H43*Energy8Sec!$C42)/(Energy8Sec!$C22-Energy8Sec!$C42) -> -0.00050221911 | I69: =(I22*Energy8Sec!$C22-Commercial8EndUse!I43*Energy8Sec!$C42)/(Energy8Sec!$C22-Energy8Sec!$C42) -> 0.34050222 | J69: =(J22*Energy8Sec!$C22-Commercial8EndUse!J43*Energy8Sec!$C42)/(Energy8Sec!$C22-Energy8Sec!$C42) -> 0.02649926 | K69: =(K22*Energy8Sec!$C22-Commercial8EndUse!K43*Energy8Sec!$C42)/(Energy8Sec!$C22-Energy8Sec!$C42) -> -0.03350074 | L69: =(L22*Energy8Sec!$C22-Commercial8EndUse!L43*Energy8Sec!$C42)/(Energy8Sec!$C22-Energy8Sec!$C42) -> 0.5275037 | M69: =(M22*Energy8Sec!$C22-Commercial8EndUse!M43*Energy8Sec!$C42)/(Energy8Sec!$C22-Energy8Sec!$C42) -> 0.13949778 | N69: =(N22*Energy8Sec!$C22-Commercial8EndUse!N43*Energy8Sec!$C42)/(Energy8Sec!$C22-Energy8Sec!$C42) -> 1 | R69: 2021 | S69: 0 | T69: 0.341 | U69: 0.026 | V69: 0 | W69: 0.528 | X69: =$Y69-SUM($S69:$W69) -> 0.105 | Y69: 1
G72: Main Finding from the above data
G73: 1.There exist differences in the composition of different end-use among different energy types
G74: 2.The demand composition of different end-use of a certain type of energy is almost stable throughout tht years

Sheet FloorAreaPer
A1: Median Per Capita Floor Area of Accommodation by Area of Residence, Household Size, Year and Type of Housing | J1: source:Population By-census, 2016
D2: Median Per Capita Floor Area of Accommodation(1)
D3: Square Metres
A4: Year | D4: 2016
A5: Type of Housing | D5: Public rental housing | E5: Subsidised home ownership housing | F5: Private permanent housing | G5: Others | H5: Overall
A6: Area of Residence | C6: Household Size
A7: Central and Western | C7: 1 | D7: 25 | E7: - | F7: 35 | G7: 19 | H7: 34
C8: 2 | D8: 13.5 | E8: - | F8: 20 | G8: 21.5 | H8: 19.5
C9: 3 | D9: 11.3 | E9: - | F9: 14.3 | G9: 12 | H9: 14.3
C10: 4 | D10: 8.8 | E10: - | F10: 12.3 | G10: 13.5 | H10: 11.8
C11: 5 | D11: 7.2 | E11: - | F11: 14 | G11: 14.8 | H11: 13.2
C12: 6 and over | D12: 5.7 | E12: - | F12: 17.3 | G12: 23.3 | H12: 16.7
C13: Sub-Total | D13: 11.5 | E13: - | F13: 20.5 | G13: 18.6 | H13: 20
A14: Wan Chai | C14: 1 | D14: 28 | E14: - | F14: 38 | G14: 15 | H14: 37
C15: 2 | D15: 14 | E15: - | F15: 22.5 | G15: 8.5 | H15: 21.5
C16: 3 | D16: 10.7 | E16: - | F16: 17 | G16: 11.3 | H16: 16.7
C17: 4 | D17: 8.5 | E17: - | F17: 15 | G17: 11.5 | H17: 14.5
C18: 5 | D18: 6.8 | E18: - | F18: 18 | G18: 11.2 | H18: 17.6
C19: 6 and over | D19: 6.5 | E19: - | F19: 16.1 | G19: 9.3 | H19: 15.7
C20: Sub-Total | D20: 12.5 | E20: - | F20: 23.3 | G20: 11.3 | H20: 22.4
A21: Eastern | C21: 1 | D21: 22 | E21: 45 | F21: 37 | G21: 21 | H21: 35
C22: 2 | D22: 15.5 | E22: 25 | F22: 22.5 | G22: 9.5 | H22: 21
C23: 3 | D23: 11.3 | E23: 16.7 | F23: 16.3 | G23: 18.7 | H23: 15
C24: 4 | D24: 8.8 | E24: 13 | F24: 13.5 | G24: 9.5 | H24: 12.3
C25: 5 | D25: 8 | E25: 10.8 | F25: 12.2 | G25: 3 | H25: 11
C26: 6 and over | D26: 7.2 | E26: 8.7 | F26: 10.7 | G26: 5.4 | H26: 9.2
C27: Sub-Total | D27: 11.5 | E27: 17.3 | F27: 17.7 | G27: 11.5 | H27: 16
A28: Southern | C28: 1 | D28: 24 | E28: 38 | F28: 46 | G28: 25 | H28: 35
C29: 2 | D29: 15 | E29: 19.5 | F29: 25.5 | G29: 16.5 | H29: 19
C30: 3 | D30: 11 | E30: 13 | F30: 18.3 | G30: 11.3 | H30: 13
C31: 4 | D31: 8.8 | E31: 11 | F31: 14.3 | G31: 13.8 | H31: 10.8
C32: 5 | D32: 7.2 | E32: 9.2 | F32: 13.8 | G32: 3.6 | H32: 11
C33: 6 and over | D33: 6 | E33: 7.7 | F33: 20.8 | G33: 12.1 | H33: 14
C34: Sub-Total | D34: 11.5 | E34: 14.7 | F34: 20.5 | G34: 16.8 | H34: 16
A35: Yau Tsim Mong | C35: 1 | D35: 19 | E35: 45 | F35: 33 | G35: 46 | H35: 34
C36: 2 | D36: 11.5 | E36: 24.8 | F36: 18.5 | G36: 23 | H36: 19
C37: 3 | D37: 11.3 | E37: 18.3 | F37: 13.3 | G37: 18.3 | H37: 13.3
C38: 4 | D38: 10 | E38: 13.8 | F38: 11 | G38: 11.3 | H38: 11
C39: 5 | D39: 8 | E39: 11 | F39: 11.2 | G39: 2.4 | H39: 11
C40: 6 and over | D40: 7.2 | E40: 7.9 | F40: 10.2 | G40: 29.8 | H40: 9.7
C41: Sub-Total | D41: 11.3 | E41: 18.3 | F41: 16 | G41: 26 | H41: 16
A42: Sham Shui Po | C42: 1 | D42: 18 | E42: 40 | F42: 30 | G42: 10 | H42: 23
C43: 2 | D43: 13 | E43: 20.5 | F43: 20.5 | G43: 7 | H43: 17
C44: 3 | D44: 11.3 | E44: 13.7 | F44: 14 | G44: 9.3 | H44: 11.7
C45: 4 | D45: 9.5 | E45: 10.8 | F45: 12 | G45: 4.8 | H45: 10.8
C46: 5 | D46: 7.8 | E46: 9.2 | F46: 11.4 | G46: 3.8 | H46: 9.2
C47: 6 and over | D47: 7.2 | E47: 8.7 | F47: 9.7 | G47: 3 | H47: 8
C48: Sub-Total | D48: 11.5 | E48: 16.3 | F48: 15.5 | G48: 9 | H48: 14
A49: Kowloon City | C49: 1 | D49: 18 | E49: 40 | F49: 37 | G49: 37 | H49: 31
C50: 2 | D50: 13 | E50: 22.5 | F50: 21.5 | G50: 14 | H50: 17
C51: 3 | D51: 10 | E51: 17 | F51: 15.7 | G51: 26.3 | H51: 13
C52: 4 | D52: 8.5 | E52: 13.8 | F52: 13.8 | G52: 6.3 | H52: 12.3
C53: 5 | D53: 7.4 | E53: 11 | F53: 13.2 | G53: 11.2 | H53: 12
C54: 6 and over | D54: 6.5 | E54: 8.2 | F54: 12.9 | G54: 26.7 | H54: 11.8
C55: Sub-Total | D55: 11 | E55: 20 | F55: 18 | G55: 25 | H55: 15.5
A56: Wong Tai Sin | C56: 1 | D56: 22 | E56: 40 | F56: 36 | G56: 14 | H56: 31
C57: 2 | D57: 16.5 | E57: 20.5 | F57: 19.5 | G57: 5.5 | H57: 18
C58: 3 | D58: 11.3 | E58: 13.7 | F58: 14 | G58: 5 | H58: 12.7
C59: 4 | D59: 9 | E59: 11.3 | F59: 11.8 | G59: 3 | H59: 10.3
C60: 5 | D60: 8 | E60: 10.4 | F60: 11 | G60: 17 | H60: 8.8
C61: 6 and over | D61: 7.2 | E61: 7.8 | F61: 9.4 | G61: 12.1 | H61: 7.3
C62: Sub-Total | D62: 11.7 | E62: 15.7 | F62: 15.3 | G62: 8 | H62: 13.7
A63: Kwun Tong | C63: 1 | D63: 18 | E63: 41 | F63: 37 | G63: 8 | H63: 23
C64: 2 | D64: 14 | E64: 20.5 | F64: 20.5 | G64: 4.5 | H64: 16.5
C65: 3 | D65: 10.7 | E65: 14.3 | F65: 15 | G65: 4.7 | H65: 11.7
C66: 4 | D66: 9.5 | E66: 11.5 | F66: 12.3 | G66: 3.8 | H66: 10
C67: 5 | D67: 7.8 | E67: 10.2 | F67: 10.2 | G67: 6.8 | H67: 8.8
C68: 6 and over | D68: 7.3 | E68: 8.3 | F68: 8.2 | G68: 17 | H68: 7.7
C69: Sub-Total | D69: 11.3 | E69: 16.3 | F69: 15.3 | G69: 8 | H69: 13
A70: Sai Kung (Tseung Kwan O) | C70: 1 | D70: 17 | E70: 41 | F70: 46 | G70: 23 | H70: 36
C71: 2 | D71: 15 | E71: 22.5 | F71: 23 | G71: 35 | H71: 22
C72: 3 | D72: 10.7 | E72: 15 | F72: 16.7 | G72: - | H72: 14.7
C73: 4 | D73: 9.4 | E73: 11.8 | F73: 14.5 | G73: 13.8 | H73: 12
C74: 5 | D74: 8.6 | E74: 10.4 | F74: 12 | G74: - | H74: 10.4
C75: 6 and over | D75: 7 | E75: 8.2 | F75: 10 | G75: - | H75: 8.2
C76: Sub-Total | D76: 11 | E76: 15 | F76: 17.8 | G76: 23 | H76: 15
A77: Tsuen Wan (New town) | C77: 1 | D77: 23 | E77: 43 | F77: 42 | G77: 19 | H77: 35
C78: 2 | D78: 14.5 | E78: 22.5 | F78: 22.5 | G78: 15.5 | H78: 20
C79: 3 | D79: 10.7 | E79: 15 | F79: 16 | G79: 4.7 | H79: 14.3
C80: 4 | D80: 8.8 | E80: 13.8 | F80: 12.8 | G80: 5.8 | H80: 11.5
C81: 5 | D81: 7.6 | E81: 9.2 | F81: 11.4 | G81: 7.4 | H81: 10.4
C82: 6 and over | D82: 7.1 | E82: 8 | F82: 9.5 | G82: 21.7 | H82: 9
C83: Sub-Total | D83: 11.7 | E83: 15.5 | F83: 17 | G83: 15 | H83: 16
A84: Tuen Mun (New town) | C84: 1 | D84: 23 | E84: 41 | F84: 42 | G84: 37 | H84: 31
C85: 2 | D85: 12.5 | E85: 22 | F85: 22.5 | G85: 23 | H85: 19
C86: 3 | D86: 10.3 | E86: 15 | F86: 15.7 | G86: 12.3 | H86: 13.3
C87: 4 | D87: 8.8 | E87: 11.3 | F87: 12.5 | G87: 9.5 | H87: 10.8
C88: 5 | D88: 7.4 | E88: 10.4 | F88: 11 | G88: 11 | H88: 10.4
C89: 6 and over | D89: 6.5 | E89: 8.3 | F89: 10.3 | G89: 12.1 | H89: 8.7
C90: Sub-Total | D90: 11.7 | E90: 15 | F90: 18 | G90: 17 | H90: 15
A91: Yuen Long (New town) | C91: 1 | D91: 29 | E91: 33 | F91: 36 | G91: 42 | H91: 34
C92: 2 | D92: 15 | E92: 17.5 | F92: 20.5 | G92: 18.5 | H92: 19.5
C93: 3 | D93: 10 | E93: 11.7 | F93: 14.3 | G93: 9.3 | H93: 13.3
C94: 4 | D94: 8.5 | E94: 9.8 | F94: 11.8 | G94: 9.5 | H94: 10.8
C95: 5 | D95: 7 | E95: 8.2 | F95: 11.2 | G95: 3.7 | H95: 10.6
C96: 6 and over | D96: 5.8 | E96: 7.7 | F96: 8.5 | G96: 10.8 | H96: 8
C97: Sub-Total | D97: 11.5 | E97: 13 | F97: 16.5 | G97: 14 | H97: 15.4
A98: Yuen Long (Tin Shui Wai) | C98: 1 | D98: 17 | E98: 49 | F98: 51 | G98: 38 | H98: 22
C99: 2 | D99: 17 | E99: 28 | F99: 25.5 | G99: 16 | H99: 21
C100: 3 | D100: 11.7 | E100: 19.7 | F100: 17 | G100: - | H100: 14.3
...

Sheet DataSum
A1: Data Summary
A2: About the backgroud color: | B2: History data | C2: Prejection from reports
A3: Note (about data in this sheet): | B3: The Population&GDP data is from another prediction datafile "HK population and GDP_190227_v3.xlsx";
B4: Domestic Household and Average no. of people per household data are from the below "HK 2030 Baseline Review.pdf"(source of this report can be fund on the "About" sheet;
B5: Residential and Commercial Building Area data are from the below "HK 2030 Final Report.pdf"(source of this report can also be fund on the "About" sheet).
A7: X (independent variables in regression) | B7: Unit | C7: 2005 | D7: 2006 | E7: 2007 | F7: 2008 | G7: 2009 | H7: 2010 | I7: 2011 | J7: 2012 | K7: 2013 | L7: 2014 | M7: 2015 | N7: 2016 | O7: 2017 | P7: 2018 | Q7: 2019 | R7: 2020 | S7: 2021 | T7: 2022 | U7: 2023 | V7: 2024 | W7: 2025 | X7: 2026 | Y7: 2027 | Z7: 2028 | AA7: 2029 | AB7: 2030 | AC7: 2031 | AD7: 2032 | AE7: 2033 | AF7: 2034 | AG7: 2035 | AH7: 2036 | AI7: 2037 | AJ7: 2038 | AK7: 2039 | AL7: 2040 | AM7: 2041 | AN7: 2042 | AO7: 2043 | AP7: 2044 | AQ7: 2045 | AR7: 2046 | AS7: 2047 | AT7: 2048 | AU7: 2049 | AV7: 2050 | AW7: 2051
A8: Population(HK Gov Census) | B8: ×10^3 people | C8: 6813.2 | D8: 6857.1 | E8: 6916.3 | F8: 6957.8 | G8: 6972.8 | H8: 7024.2 | I8: 7071.6 | J8: 7150.1 | K8: 7178.9 | L8: 7229.5 | M8: 7291.3 | N8: 7336.6 | O8: 7391.7 | P8: 7451 | Q8: 7502.6 | R8: 7558.1 | S8: 7608.4 | T8: 7657.7 | U8: 7705.4 | V8: 7748.4 | W8: 7788.7 | X8: 7825.2 | Y8: 7859.6 | Z8: 7895.2 | AA8: 7930.5 | AB8: 7963.8 | AC8: 7996.2 | AD8: 8028 | AE8: 8060 | AF8: 8090.2 | AG8: 8117.2 | AH8: 8141.7 | AI8: 8163.5 | AJ8: 8182 | AK8: 8196.2 | AL8: 8207 | AM8: 8213.8 | AN8: 8217.1 | AO8: 8218.5 | AP8: 8217.6 | AQ8: 8213.7 | AR8: 8207.2 | AS8: 8197.1 | AT8: 8185 | AU8: 8170 | AV8: 8152.3
A9: GDP(2018 onward: from extrapolation) | B9: bil.USD2012 | C9: 196.28291 | D9: 210.08695 | E9: 223.66873 | F9: 228.42826 | G9: 222.8111 | H9: 237.89025 | I9: 249.34392 | J9: 253.58353 | K9: 261.4484 | L9: 268.67069 | M9: 275.08613 | N9: 281.03604 | O9: 291.69109 | P9: 301.90028 | Q9: 310.65539 | R9: 319.97505 | S9: 329.89428 | T9: 340.121 | U9: 350.66475 | V9: 359.74897 | W9: 369.95294 | X9: 380.05923 | Y9: 390.01401 | Z9: 399.87872 | AA9: 409.75023 | AB9: 419.87453 | AC9: 429.77617 | AD9: 439.69593 | AE9: 449.65422 | AF9: 459.63326 | AG9: 469.59812 | AH9: 479.52013 | AI9: 489.48684 | AJ9: 499.4498 | AK9: 509.40313 | AL9: 519.35232 | AM9: 529.30668 | AN9: 539.26807 | AO9: 549.22041 | AP9: 559.17362 | AQ9: 569.12919 | AR9: 579.08546 | AS9: 589.04028 | AT9: 598.99402 | AU9: 608.9496 | AV9: 618.90495
A10: GDP per capita | B10: kUSD2012 | C10: =C9/C8*1000 -> 28.80921 | D10: =D9/D8*1000 -> 30.637872 | E10: =E9/E8*1000 -> 32.339362 | F10: =F9/F8*1000 -> 32.83053 | G10: =G9/G8*1000 -> 31.954323 | H10: =H9/H8*1000 -> 33.867237 | I10: =I9/I8*1000 -> 35.259902 | J10: =J9/J8*1000 -> 35.465732 | ... AV10: =AV9/AV8*1000 -> 75.917833
A11: No. of Domestic Household (2030 Baseline Pred) | B11: Million | C11: =Household_Histo!C27/1000 -> 2.1971 | D11: =Household_Histo!C28/1000 -> 2.2209 | E11: =Household_Histo!C29/1000 -> 2.2499 | F11: =Household_Histo!C30/1000 -> 2.2791 | G11: =Household_Histo!C31/1000 -> 2.2972 | H11: =Household_Histo!C32/1000 -> 2.3251 | I11: =Household_Histo!C33/1000 -> 2.3593 | J11: =Household_Histo!C34/1000 -> 2.3862 | K11: =Household_Histo!C35/1000 -> 2.4073 | L11: =Household_Histo!C36/1000 -> 2.4324 | M11: =Household_Histo!C37/1000 -> 2.4711 | N11: =Household_Histo!C38/1000 -> 2.4989 | O11: =Household_Histo!C39/1000 -> 2.5347 | P11: =TREND($V$33:$V$34,$U$33:$U$34,P7) -> 2.5493407 | Q11: =TREND($V$33:$V$34,$U$33:$U$34,Q7) -> 2.5639815 | R11: =TREND($V$33:$V$34,$U$33:$U$34,R7) -> 2.5786222 | S11: =TREND($V$33:$V$34,$U$33:$U$34,S7) -> 2.593263 | T11: =TREND($V$33:$V$34,$U$33:$U$34,T7) -> 2.6079037 | U11: =TREND($V$33:$V$34,$U$33:$U$34,U7) -> 2.6225444 | V11: =TREND($V$33:$V$34,$U$33:$U$34,V7) -> 2.6371852 | W11: =TREND($V$33:$V$34,$U$33:$U$34,W7) -> 2.6518259 | ... AO11: =TREND($V$33:$V$34,$U$33:$U$34,AO7) -> 2.9153593 | AP11: 2.93 | AQ11: =TREND($V$34:$V$35,$U$34:$U$35,AQ7) -> 2.926 | AR11: =TREND($V$34:$V$35,$U$34:$U$35,AR7) -> 2.922 | AS11: =TREND($V$34:$V$35,$U$34:$U$35,AS7) -> 2.918 | AT11: =TREND($V$34:$V$35,$U$34:$U$35,AT7) -> 2.914 | AU11: 2.91 | AV11: =TREND($V$34:$V$35,$U$34:$U$35,AV7) -> 2.906
A12: No. of Domestic Household (HK C&SD Pred) | B12: Million | C12: =C11 -> 2.1971 | D12: =D11 -> 2.2209 | E12: =E11 -> 2.2499 | F12: =F11 -> 2.2791 | G12: =G11 -> 2.2972 | H12: =H11 -> 2.3251 | I12: =I11 -> 2.3593 | J12: =J11 -> 2.3862 | ... O12: =O11 -> 2.5347 | P12: =-0.00040693*P7*P7+1.6681351*P7-1706.5786 -> 2.5672265 | Q12: =-0.00040693*Q7*Q7+1.6681351*Q7-1706.5786 -> 2.5925852 | R12: =-0.00040693*R7*R7+1.6681351*R7-1706.5786 -> 2.61713 | S12: =-0.00040693*S7*S7+1.6681351*S7-1706.5786 -> 2.640861 | T12: =-0.00040693*T7*T7+1.6681351*T7-1706.5786 -> 2.6637781 | U12: =-0.00040693*U7*U7+1.6681351*U7-1706.5786 -> 2.6858813 | V12: =-0.00040693*V7*V7+1.6681351*V7-1706.5786 -> 2.7071707 | W12: =-0.00040693*W7*W7+1.6681351*W7-1706.5786 -> 2.7276462 | ... AV12: =-0.00040693*AV7*AV7+1.6681351*AV7-1706.5786 -> 2.97503 | AW12: =Household_Pred!B21/10^6 -> 2.9495
A13: Note: Fitting Curve for Domestic Household | B13: Y=-0.00040693*X2+1.6681351*X-1706.5786 | F13: For more information about the fitting, see sheet"FittingHH"
A14: Average no. of people per household, by my estimation | B14: - | C14: =TREND($AA$48:$AA$50,$T$48:$T$50,C7) -> 3.1823115 | D14: =TREND($AA$48:$AA$50,$T$48:$T$50,D7) -> 3.1695082 | E14: =TREND($AA$48:$AA$50,$T$48:$T$50,E7) -> 3.1567049 | F14: =TREND($AA$48:$AA$50,$T$48:$T$50,F7) -> 3.1439016 | G14: =TREND($AA$48:$AA$50,$T$48:$T$50,G7) -> 3.1310984 | H14: =TREND($AA$48:$AA$50,$T$48:$T$50,H7) -> 3.1182951 | I14: =TREND($AA$48:$AA$50,$T$48:$T$50,I7) -> 3.1054918 | J14: =TREND($AA$48:$AA$50,$T$48:$T$50,J7) -> 3.0926885 | ... AV14: =TREND($AA$48:$AA$50,$T$48:$T$50,AV7) -> 2.6061639
A15: Average no. of people per household, by division1 | B15: - | C15: =C8/C11/1000 -> 3.1009968 | D15: =D8/D11/1000 -> 3.0875321 | E15: =E8/E11/1000 -> 3.0740477 | F15: =F8/F11/1000 -> 3.0528717 | G15: =G8/G11/1000 -> 3.0353474 | H15: =H8/H11/1000 -> 3.0210314 | I15: =I8/I11/1000 -> 2.9973297 | J15: =J8/J11/1000 -> 2.9964379 | ... AV15: =AV8/AV11/1000 -> 2.8053338
A16: Average no. of people per household, by division2 | B16: - | C16: =C8/C12/1000 -> 3.1009968 | D16: =D8/D12/1000 -> 3.0875321 | E16: =E8/E12/1000 -> 3.0740477 | F16: =F8/F12/1000 -> 3.0528717 | G16: =G8/G12/1000 -> 3.0353474 | H16: =H8/H12/1000 -> 3.0210314 | I16: =I8/I12/1000 -> 2.9973297 | J16: =J8/J12/1000 -> 2.9964379 | ... AV16: =AV8/AV12/1000 -> 2.7402413
A17: Residential Building Area 1 | B17: Mil m2 | C17: =C11*$R$105 -> 95.57385 | D17: =D11*$R$105 -> 96.60915 | E17: =E11*$R$105 -> 97.87065 | F17: =F11*$R$105 -> 99.14085 | G17: =G11*$R$105 -> 99.9282 | H17: =H11*$R$105 -> 101.14185 | I17: =I11*$R$105 -> 102.62955 | J17: =J11*$R$105 -> 103.7997 | ... AV17: =AV11*$R$105 -> 126.411
A18: Residential Building Area 2 | B18: Mil m2 | C18: =C8*$R$106/1000 -> 102.198 | D18: =D8*$R$106/1000 -> 102.8565 | E18: =E8*$R$106/1000 -> 103.7445 | F18: =F8*$R$106/1000 -> 104.367 | G18: =G8*$R$106/1000 -> 104.592 | H18: =H8*$R$106/1000 -> 105.363 | I18: =I8*$R$106/1000 -> 106.074 | J18: =J8*$R$106/1000 -> 107.2515 | ... AV18: =AV8*$R$106/1000 -> 122.2845
A19: Commercial Building Area | B19: Mil m2 in GFA | C19: =N74 -> 42.557143 | D19: =O74 -> 43.285714 | E19: =P74 -> 44.014286 | F19: =Q74 -> 44.742857 | G19: =R74 -> 45.471429 | H19: =S74 -> 46.2 | I19: =T74 -> 46.37 | J19: =U74 -> 46.54 | ... AV19: =BG74 -> 59
A21: Y (dependent variables in regression) | B21: Unit | C21: 2005 | D21: 2006 | E21: 2007 | F21: 2008 | G21: 2009 | H21: 2010 | I21: 2011 | J21: 2012 | K21: 2013 | L21: 2014 | M21: 2015 | N21: 2016 | O21: 2017 | P21: 2018 | Q21: 2019 | R21: 2020 | S21: 2021 | T21: 2022 | U21: 2023 | V21: 2024 | W21: 2025 | X21: 2026 | Y21: 2027 | Z21: 2028 | AA21: 2029 | AB21: 2030 | AC21: 2031 | AD21: 2032 | AE21: 2033 | AF21: 2034 | AG21: 2035 | AH21: 2036 | AI21: 2037 | AJ21: 2038 | AK21: 2039 | AL21: 2040 | AM21: 2041 | AN21: 2042 | AO21: 2043 | AP21: 2044 | AQ21: 2045 | AR21: 2046 | AS21: 2047 | AT21: 2048 | AU21: 2049 | AV21: 2050
A22: Residential Energy Consumption | B22: TJ | D22: 53982 | E22: 54717 | F22: 55849 | G22: 57731 | H22: 58396 | I22: 58826 | J22: 59932 | K22: 58394 | L22: 61910 | M22: 60214 | N22: 61439
A23: Commercial Energy Consumption | B23: TJ | D23: 111884 | E23: 113914 | F23: 113753 | G23: 114297 | H23: 116391 | I23: 118558 | J23: 120970 | K23: 121215 | L23: 122711 | M23: 123674 | N23: 123969
A27: Raw data for data used in this sheet are shown below:
U31: Domestic Household Projection
U32: Year | V32: Household number(Million)
U33: 2017 | V33: 2.5347
U34: 2044 | V34: 2.93
U35: 2049 | V35: 2.91
T46: Percentages of Domestiv Households by Size | Z46: Suppose the average no. of people in household 5+ is 7
U47: 1 | V47: 2 | W47: 3 | X47: 4 | Y47: 5+ | Z47: 7 | AA47: Average
T48: 2014 | U48: 0.173 | V48: 0.263 | W48: 0.244 | X48: 0.201 | Y48: 0.119 | Z48: =Y48 -> 0.119 | AA48: =U$47*U48+V$47*V48+W$47*W48+X$47*X48+Z$47*Z48 -> 3.068
T49: 2019 | U49: 0.181 | V49: 0.274 | W49: 0.244 | X49: 0.189 | Y49: 0.112 | Z49: =Y49 -> 0.112 | AA49: =U$47*U49+V$47*V49+W$47*W49+X$47*X49+Z$47*Z49 -> 3.001
T50: 2023 | U50: 0.186 | V50: 0.286 | W50: 0.241 | X50: 0.179 | Y50: 0.108 | Z50: =Y50 -> 0.108 | AA50: =U$47*U50+V$47*V50+W$47*W50+X$47*X50+Z$47*Z50 -> 2.953
T52: trend:
W53: 2005 | X53: 2006 | Y53: 2007 | Z53: 2008 | AA53: 2009 | AB53: 2010 | AC53: 2011 | AD53: 2012 | AE53: 2013 | AF53: 2014 | AG53: 2015 | AH53: 2016 | AI53: 2017 | AJ53: 2018 | AK53: 2019 | AL53: 2020 | AM53: 2021 | AN53: 2022 | AO53: 2023 | AP53: 2024 | AQ53: 2025 | AR53: 2026 | AS53: 2027 | AT53: 2028 | AU53: 2029 | AV53: 2030 | AW53: 2031 | AX53: 2032 | AY53: 2033 | AZ53: 2034 | BA53: 2035 | BB53: 2036 | BC53: 2037 | BD53: 2038 | BE53: 2039 | BF53: 2040 | BG53: 2041 | BH53: 2042 | BI53: 2043 | BJ53: 2044 | BK53: 2045 | BL53: 2046 | BM53: 2047 | BN53: 2048 | BO53: 2049 | BP53: 2050
W54: =TREND($AA$48:$AA$50,$T$48:$T$50,W53) -> 3.1823115 | X54: =TREND($AA$48:$AA$50,$T$48:$T$50,X53) -> 3.1695082 | Y54: =TREND($AA$48:$AA$50,$T$48:$T$50,Y53) -> 3.1567049 | Z54: =TREND($AA$48:$AA$50,$T$48:$T$50,Z53) -> 3.1439016 | AA54: =TREND($AA$48:$AA$50,$T$48:$T$50,AA53) -> 3.1310984 | AB54: =TREND($AA$48:$AA$50,$T$48:$T$50,AB53) -> 3.1182951 | AC54: =TREND($AA$48:$AA$50,$T$48:$T$50,AC53) -> 3.1054918 | AD54: =TREND($AA$48:$AA$50,$T$48:$T$50,AD53) -> 3.0926885 | ... BP54: =TREND($AA$48:$AA$50,$T$48:$T$50,BP53) -> 2.6061639
M59: Employment use floorspace
M61: year | N61: mil. m2 in GFA
M62: 2003 | N62: 41.1
M63: 2010 | N63: 46.2
M64: 2020 | N64: 47.9
M65: 2030 | N65: 51.6
M72: trend
N73: 2005 | O73: 2006 | P73: 2007 | Q73: 2008 | R73: 2009 | S73: 2010 | T73: 2011 | U73: 2012 | V73: 2013 | W73: 2014 | X73: 2015 | Y73: 2016 | Z73: 2017 | AA73: 2018 | AB73: 2019 | AC73: 2020 | AD73: 2021 | AE73: 2022 | AF73: 2023 | AG73: 2024 | AH73: 2025 | AI73: 2026 | AJ73: 2027 | AK73: 2028 | AL73: 2029 | AM73: 2030 | AN73: 2031 | AO73: 2032 | AP73: 2033 | AQ73: 2034 | AR73: 2035 | AS73: 2036 | AT73: 2037 | AU73: 2038 | AV73: 2039 | AW73: 2040 | AX73: 2041 | AY73: 2042 | AZ73: 2043 | BA73: 2044 | BB73: 2045 | BC73: 2046 | BD73: 2047 | BE73: 2048 | BF73: 2049 | BG73: 2050
L74: mil. m2 in GFA | M74: area | N74: =TREND($N$62:$N$63,$M$62:$M$63,N73) -> 42.557143 | O74: =TREND($N$62:$N$63,$M$62:$M$63,O73) -> 43.285714 | P74: =TREND($N$62:$N$63,$M$62:$M$63,P73) -> 44.014286 | Q74: =TREND($N$62:$N$63,$M$62:$M$63,Q73) -> 44.742857 | R74: =TREND($N$62:$N$63,$M$62:$M$63,R73) -> 45.471429 | S74: =TREND($N$62:$N$63,$M$62:$M$63,S73) -> 46.2 | T74: =TREND($N$63:$N$64,$M$63:$M$64,T73) -> 46.37 | U74: =TREND($N$63:$N$64,$M$63:$M$64,U73) -> 46.54 | V74: =TREND($N$63:$N$64,$M$63:$M$64,V73) -> 46.71 | W74: =TREND($N$63:$N$64,$M$63:$M$64,W73) -> 46.88 | X74: =TREND($N$63:$N$64,$M$63:$M$64,X73) -> 47.05 | Y74: =TREND($N$63:$N$64,$M$63:$M$64,Y73) -> 47.22 | Z74: =TREND($N$63:$N$64,$M$63:$M$64,Z73) -> 47.39 | AA74: =TREND($N$63:$N$64,$M$63:$M$64,AA73) -> 47.56 | ... AC74: =TREND($N$63:$N$64,$M$63:$M$64,AC73) -> 47.9 | AD74: =TREND($N$64:$N$65,$M$64:$M$65,AD73) -> 48.27 | AE74: =TREND($N$64:$N$65,$M$64:$M$65,AE73) -> 48.64 | AF74: =TREND($N$64:$N$65,$M$64:$M$65,AF73) -> 49.01 | AG74: =TREND($N$64:$N$65,$M$64:$M$65,AG73) -> 49.38 | AH74: =TREND($N$64:$N$65,$M$64:$M$65,AH73) -> 49.75 | AI74: =TREND($N$64:$N$65,$M$64:$M$65,AI73) -> 50.12 | AJ74: =TREND($N$64:$N$65,$M$64:$M$65,AJ73) -> 50.49 | AK74: =TREND($N$64:$N$65,$M$64:$M$65,AK73) -> 50.86 | ... BG74: =TREND($N$64:$N$65,$M$64:$M$65,BG73) -> 59
O104: HONG KONG | R104: m2
O105: Average floor area per dwelling | R105: 43.5
O106: Average floor area per person | R106: 15
O107: Also,from Sheet"Floor Area Per" | R107: =FloorAreaPer!H167 -> 15

Sheet Building
A1: Buildings & Industrial | E1: Updated: | F1: =+[2]FRAMEWORK!$B$2 -> 43599 | G1: Scenario: | H1: =+[2]FRAMEWORK!$D$2 -> Core higher population | J1: Color code | K1: Fixed data Input | L1: Parameter input | M1: Parameter rpt item | N1: Clear: calculated | X1: Page 1 or 2 | Y1: Buildings & Industrial | AB1: Updated: | AC1: =+[2]FRAMEWORK!$B$2 -> 43599 | AD1: Scenario: | AE1: =+[2]FRAMEWORK!$D$2 -> Core higher population | AG1: Color code | AH1: Data Input | AI1: Clear = calculated. | AN1: Page 2 of 2
A2: Buildings Input | B2: Share of population in 2050 | C2: Floor area per capita in 2050 m2 ^1 | D2: Energy efficiency improvement --electricity (%) ^2 | M2: Energy efficiency improvement -- gas (%) | R2: Electrification rate (share of cooking, hot water & Ref) | V2: Summary of results
D3: Industrial equipment | E3: Cooking | F3: A.C. | G3: District cooling | H3: Hot Water & Refrigeration | I3: Lighting | J3: Office Equipment | K3: Others | L3: Total | M3: Indust'l equip | N3: Cooking | O3: Hot Water | P3: Others | Q3: Total | W3: Emissions ('000 t CO2)
A4: Residential | W4: 2016 | X4: 2050
A5: Private | B5: ='[2]Key parameters rpt'!O25 -> 0.4 | C5: ='[2]Key parameters rpt'!O27 -> 2174901.2 | E5: ='[2]Key parameters rpt'!O36 -> 0.55 | F5: ='[2]Key parameters rpt'!$O$33 -> 0.1 | H5: ='[2]Key parameters rpt'!$O$34 -> 0.5 | I5: ='[2]Key parameters rpt'!$O$35 -> 0.35 | J5: ='[2]Key parameters rpt'!$O$37 -> 0.08 | K5: =AVERAGE(E5:J5) -> 0.316 | N5: ='[2]Key parameters rpt'!$O$36 -> 0.55 | O5: ='[2]Key parameters rpt'!O34 -> 0.5 | P5: =AVERAGE(N5:O5) -> 0.525 | R5: ='[2]Key parameters rpt'!$O$41 -> 0 | V5: Residential | W5: =Y30 -> #VALUE! | X5: =Y51 -> 138.12678
A6: Public | B6: ='[2]Key parameters rpt'!O26 -> 0.6 | C6: ='[2]Key parameters rpt'!O28 -> 2121852.2 | E6: ='[2]Key parameters rpt'!O36 -> 0.55 | F6: ='[2]Key parameters rpt'!$O$33 -> 0.1 | H6: ='[2]Key parameters rpt'!$O$34 -> 0.5 | I6: ='[2]Key parameters rpt'!$O$35 -> 0.35 | J6: ='[2]Key parameters rpt'!$O$37 -> 0.08 | K6: =AVERAGE(E6:J6) -> 0.316 | N6: ='[2]Key parameters rpt'!$O$36 -> 0.55 | O6: ='[2]Key parameters rpt'!O35 -> 0.35 | P6: =AVERAGE(N6:O6) -> 0.45 | R6: ='[2]Key parameters rpt'!$O$41 -> 0 | V6: Commercial | W6: =Y33 -> #VALUE! | X6: =Y54 -> 209.223
A7: Commercial | C7: ='[2]Key parameters rpt'!O30 -> 5.9026996 | E7: ='[2]Key parameters rpt'!O36 -> 0.55 | F7: ='[2]Key parameters rpt'!$O$33 -> 0.1 | H7: ='[2]Key parameters rpt'!$O$34 -> 0.5 | I7: ='[2]Key parameters rpt'!$O$35 -> 0.35 | J7: ='[2]Key parameters rpt'!$O$37 -> 0.08 | K7: =AVERAGE(E7:J7) -> 0.316 | N7: ='[2]Key parameters rpt'!$O$36 -> 0.55 | O7: ='[2]Key parameters rpt'!O36 -> 0.55 | P7: =AVERAGE(N7:O7) -> 0.55 | R7: ='[2]Key parameters rpt'!$O$41 -> 0 | V7: Industrial | W7: =Y41 -> #VALUE! | X7: =Y62 -> 28.11812
A8: Industrial | C8: ='[2]Key parameters rpt'!O31 -> 3.6728616 | D8: ='[2]Key parameters rpt'!O38 -> 0.15 | F8: ='[2]Key parameters rpt'!$O$33 -> 0.1 | I8: ='[2]Key parameters rpt'!$O$35 -> 0.35 | K8: =AVERAGE(E8:J8) -> 0.225 | M8: ='[2]Key parameters rpt'!$O$37 -> 0.08 | P8: =AVERAGE(M8:O8) -> 0.08 | V8: Total | W8: =SUM(W5:W7) -> #VALUE! | X8: =SUM(X5:X7) -> 375.4679
A10: 1. Flat size: Source of information | D10: 2. Energy efficiency. Source of information | G10: IEA, Energy Efficiency 2018
K11: Emission factors: | N11: 2016 | O11: 2050
K12: Electricity | L12: Kg CO2/KWh | O12: =[2]Electricity!$K$6 -> 0.008765039
K13: Gas | L13: Kg CO2/TJ | N13: 65437.5 | O13: 65437.5
K15: Source for electricity: Electricity page.
K16: Source for electricity: EF-1 page page.
Z19: Impact of using District Cooling: And Freshwater cooling towers:
Z20: Saving %per EMSD Energy Saving wesite
Z21: https://www.emsd.gov.hk/energyland/en/building/district_cooling_sys/dcs_benefits.html
AC22: Normal A/C | AD22: District cooling | AE22: Fresh water cooling | AF22: Total | AG22: Energy Saving (TJ) | AH22: Energy Saving (GWh)
Z23: Energy saving compare with traditional air-cooled air-conditioning systems^1 | AD23: 0.35 | AE23: 0.2
Z24: Floor area installed (million m2) | AC24: =AF24-AE24-AD24 -> 48.741485 | AD24: ='[2]Key parameters rpt'!O39*1000000/1000000 -> 2.21 | AE24: =($C$54-'[2]Key parameters rpt'!O39*1000000)*('[2]Key parameters rpt'!O40)/1000000 -> 2.5653413 | AF24: =C54/1000000 -> 53.516826 | AG24: =C54*AC54*'[2]EF-1'!$R$5/1000000000000-(SUM(H54:J54)) -> 745.54649 | AH24: =AG24/3.6 -> 207.09625
A27: 2016 | B27: Floor area calculation | F27: Electricity consumption | P27: Gas Consumption | U27: Emission factor | W27: Emissions | Z27: 2016 | AA27: Energy efficiency -- Electricity | AK27: Energy efficiency -- Gas | AP27: Electrification (share of cooking, hot water & Refridgeration)
B28: No. of Flats | C28: Floor area | D28: Population | E28: Floor area per capita | F28: Industrial equipment | G28: Cooking | H28: A.C. | I28: District cooling | J28: Fresh water cooling | K28: Hot Water & Refrigeration | L28: Lighting | M28: Office Equipment | N28: Others | O28: Total | P28: Industrial equipment | Q28: Cooking | R28: Hot Water | S28: Others | T28: Total | U28: Electricity | V28: Gas | W28: Electricity | X28: Gas | Y28: Total | AA28: Industrial equipment | AB28: Cooking | AC28: A.C. | AD28: District cooling | AE28: Fresh water cooling | AF28: Hot Water & Refrigeration | AG28: Lighting | AH28: Office Equipment | AI28: Others | AJ28: Total | AK28: Industrial equipment | AL28: Cooking | AM28: Hot Water | AN28: Others | AO28: Total
C29: m2 | D29: 1000 people | E29: m2 | F29: TJ | G29: TJ | H29: TJ | I29: TJ | J29: TJ | K29: TJ | L29: TJ | M29: TJ | N29: TJ | O29: TJ | P29: TJ | Q29: TJ | R29: TJ | S29: TJ | T29: TJ | U29: Kg CO2/KWh | V29: Kg CO2/TJ | W29: kt | X29: kt | Y29: kt | AA29: KWh per Flat or m2 | AB29: KWh per Flat or m2 | AC29: KWh per Flat or m2 | AD29: KWh per Flat or m2 | AE29: KWh per Flat or m2 | AF29: KWh per Flat or m2 | AG29: KWh per Flat or m2 | AH29: KWh per Flat or m2 | AI29: KWh per Flat or m2 | AJ29: KWh per Flat or m2 | AK29: KWh per Flat or m2 | AL29: KWh per Flat or m2 | AM29: KWh per Flat or m2 | AN29: KWh per Flat or m2 | AO29: KWh per Flat or m2 | AP29: %
A30: Residential | B30: =SUM(B31:B32) -> 2384228 | C30: =SUM(C31:C32) -> 86277952 | D30: ='[2]Population and GDP'!E6/1000 -> 7116.8 | E30: =C30/D30/1000 -> 12.123138 | G30: =SUM(G31:G32) -> 3926 | H30: =SUM(H31:H32) -> 15237 | K30: =SUM(K31:K32) -> 9329 | L30: =SUM(L31:L32) -> 3879 | M30: =SUM(M31:M32) -> 6590 | N30: =SUM(N31:N32) -> 4160 | O30: =SUM(O31:O32) -> 43121 | Q30: =SUM(Q31:Q32) -> 10684 | R30: =SUM(R31:R32) -> 7633 | S30: =SUM(S31:S32) -> 31 | T30: =SUM(T31:T32) -> 18348 | U30: =+$N$12 | V30: =+$N$13 -> 65437.5 | W30: =SUM(W31:W32) -> #VALUE! | X30: =SUM(X31:X32) -> 1200.6472 | Y30: =SUM(Y31:Y32) -> #VALUE! | Z30: Residential
A31: Private Residential | B31: =1174628+24000 -> 1198628 | C31: =50509004+1032000 -> 51541004 | D31: 0.546 | E31: =C31/(D31*D30)/1000 -> 13.264029 | G31: =1882+311 -> 2193 | H31: =8197+1408 -> 9605 | K31: =1965+2848+357+375 -> 5545 | L31: =2107+318 -> 2425 | M31: =3229+350 -> 3579 | N31: =2166+272 -> 2438 | O31: =SUM(G31:N31) -> 25785 | Q31: =4760+515 -> 5275 | R31: =3129+172 -> 3301 | S31: 1 | T31: =SUM(Q31:S31) -> 8577 | U31: =+$N$12 | V31: =+$N$13 -> 65437.5 | W31: =O31/3.6*1000000*U31/1000000 -> #VALUE! | X31: =T31*V31/1000000 -> 561.25744 | Y31: =W31+X31 -> #VALUE! | Z31: Private Residential | AB31: =G31*1000000000000/'[2]EF-1'!$R$5/$B$31 -> 508.21995 | AC31: =H31*1000000000000/'[2]EF-1'!$R$5/$B$31 -> 2225.9246 | AD31: =I31*1000000000000/'[2]EF-1'!$R$5/$B$31 -> 0 | AE31: =J31*1000000000000/'[2]EF-1'!$R$5/$B$31 -> 0 | AF31: =K31*1000000000000/'[2]EF-1'!$R$5/$B$31 -> 1285.034 | AG31: =L31*1000000000000/'[2]EF-1'!$R$5/$B$31 -> 561.98513 | AH31: =M31*1000000000000/'[2]EF-1'!$R$5/$B$31 -> 829.42053 | AI31: =N31*1000000000000/'[2]EF-1'!$R$5/$B$31 -> 564.99783 | AJ31: =SUM(AB31:AI31) -> 5975.5821 | AL31: =Q31*1000000000000/'[2]EF-1'!$R$5/$B$31 -> 1222.4625 | AM31: =R31*1000000000000/'[2]EF-1'!$R$5/$B$31 -> 764.99501 | AN31: =S31*1000000000000/'[2]EF-1'!$R$5/$B$31 -> 0.23174644 | AO31: =SUM(AL31:AN31) -> 1987.6893 | AP31: =(G31+K31)/((G31+K31)+(Q31+R31)) -> 0.47431654
A32: Public Residential | B32: =1185.6*1000 -> 1185600 | C32: 34736948 | D32: =44.8% -> 0.448 | E32: =C32/(D32*D30)/1000 -> 10.895041 | G32: 1733 | H32: 5632 | K32: 3784 | L32: 1454 | M32: 3011 | N32: 1722 | O32: =SUM(G32:N32) -> 17336 | Q32: 5409 | R32: 4332 | S32: 30 | T32: =SUM(Q32:S32) -> 9771 | U32: =+$N$12 | V32: =+$N$13 -> 65437.5 | W32: =O32/3.6*1000000*U32/1000000 -> #VALUE! | X32: =T32*V32/1000000 -> 639.38981 | Y32: =W32+X32 -> #VALUE! | Z32: Public Residential | AB32: =G32*1000000000000/'[2]EF-1'!$R$5/$B$31 -> 401.61659 | AC32: =H32*1000000000000/'[2]EF-1'!$R$5/$B$31 -> 1305.196 | AD32: =I32*1000000000000/'[2]EF-1'!$R$5/$B$31 -> 0 | AE32: =J32*1000000000000/'[2]EF-1'!$R$5/$B$31 -> 0 | AF32: =K32*1000000000000/'[2]EF-1'!$R$5/$B$31 -> 876.92855 | AG32: =L32*1000000000000/'[2]EF-1'!$R$5/$B$31 -> 336.95933 | AH32: =M32*1000000000000/'[2]EF-1'!$R$5/$B$31 -> 697.78855 | AI32: =N32*1000000000000/'[2]EF-1'!$R$5/$B$31 -> 399.06738 | AJ32: =SUM(AB32:AI32) -> 4017.5564 | AL32: =Q32*1000000000000/'[2]EF-1'!$R$5/$B$31 -> 1253.5165 | AM32: =R32*1000000000000/'[2]EF-1'!$R$5/$B$31 -> 1003.9256 | AN32: =S32*1000000000000/'[2]EF-1'!$R$5/$B$31 -> 6.9523933 | AO32: =SUM(AL32:AN32) -> 2264.3945 | AP32: =(G32+K32)/((G32+K32)+(Q32+R32)) -> 0.36158081
A33: Commercial | C33: =SUM('[2]Commerical demand'!D46:D51) -> 47054400 | D33: =D30 -> 7116.8 | E33: =C33/D33/1000 -> 6.6117356 | G33: =SUM(G34:G40) -> 4039 | H33: =SUM(H34:H40) -> 30297 | I33: =SUM(I34:I40) -> 0 | K33: =SUM(K34:K40) -> 5340 | L33: =SUM(L34:L40) -> 15095 | M33: =SUM(M34:M40) -> 4464 | N33: =SUM(N34:N40) -> 44646 | O33: =SUM(G33:N33) -> 103881 | Q33: =SUM(Q34:Q40) -> 8319 | R33: =SUM(R34:R40) -> 6240 | S33: =SUM(S34:S40) -> 5531 | T33: =SUM(T34:T40) -> 20090 | U33: =+$N$12 | V33: =+$N$13 -> 65437.5 | W33: =O33/3.6*1000000*U33/1000000 -> #VALUE! | X33: =T33*V33/1000000 -> 1314.6394 | Y33: =W33+X33 -> #VALUE! | Z33: Commercial | AB33: =G33/$C$33*1000000000000*'[2]EF-1'!$R$6 -> 23.843561 | AC33: =H33/$C$33*1000000000000*'[2]EF-1'!$R$6 -> 178.85327 | AD33: =AC33*(1-$AD$23) -> 116.25463 | AE33: =AC33*(1-$AE$23) -> 143.08262 | AF33: =K33/$C$33*1000000000000*'[2]EF-1'!$R$6 -> 31.523797 | AG33: =L33/$C$33*1000000000000*'[2]EF-1'!$R$6 -> 89.110807 | AH33: =M33/$C$33*1000000000000*'[2]EF-1'!$R$6 -> 26.352477 | AI33: =N33/$C$33*1000000000000*'[2]EF-1'!$R$6 -> 263.56019 | AJ33: =SUM(AB33:AI33) -> 872.58135 | AL33: =Q33/$C$33*1000000000000*'[2]EF-1'!$R$8 -> 4.9678366 | AM33: =R33/$C$33*1000000000000*'[2]EF-1'!$R$8 -> 3.7263253 | AN33: =S33/$C$33*1000000000000*'[2]EF-1'!$R$8 -> 3.3029336 | AO33: =SUM(AL33:AN33) -> 11.997095 | AP33: =(G33+K33)/((G33+K33)+(Q33+R33)) -> 0.39180383
A34: Office | C34: 11838200 | D34: =$D$30 -> 7116.8 | E34: =C34/D34/1000 -> 1.6634161 | H34: 7158 | K34: 0 | L34: 1862 | M34: 1646 | N34: 2517 | O34: =SUM(G34:N34) -> 13183 | R34: 0 | S34: 0 | T34: =SUM(P34:S34) -> 0 | U34: =+$N$12 | V34: =+$N$13 -> 65437.5 | Z34: Office | AD34: =AC34*(1-$AD$23) -> 0 | AE34: =AC34*(1-$AE$23) -> 0 | AJ34: =SUM(AB34:AI34) -> 0 | AO34: =SUM(AL34:AN34) -> 0 | AP34: =(G34+K34)/((G34+K34)+(Q34+R34)) -> #DIV/0!
A35: Restaurant | C35: 11274200 | D35: =$D$30 -> 7116.8 | E35: =C35/D34/1000 -> 1.584167 | G35: 4039 | H35: 5402 | K35: 1595 | L35: 819 | N35: 474 | O35: =SUM(G35:N35) -> 12329 | Q35: 8319 | R35: 459 | S35: 56 | T35: =SUM(P35:S35) -> 8834 | U35: =+$N$12 | V35: =+$N$13 -> 65437.5 | Z35: Restaurant | AD35: =AC35*(1-$AD$23) -> 0 | AE35: =AC35*(1-$AE$23) -> 0 | AJ35: =SUM(AB35:AI35) -> 0 | AO35: =SUM(AL35:AN35) -> 0 | AP35: =(G35+K35)/((G35+K35)+(Q35+R35)) -> 0.39092423
A36: Accommodation | H36: 3855 | K36: 1527 | L36: 1645 | M36: 697 | N36: 4381 | O36: =SUM(G36:N36) -> 12105 | R36: 3798 | S36: 550 | T36: =SUM(P36:S36) -> 4348 | U36: =+$N$12 | V36: =+$N$13 -> 65437.5 | Z36: Accommodation | AD36: =AC36*(1-$AD$23) -> 0 | AE36: =AC36*(1-$AE$23) -> 0 | AJ36: =SUM(AB36:AI36) -> 0 | AO36: =SUM(AL36:AN36) -> 0 | AP36: =(G36+K36)/((G36+K36)+(Q36+R36)) -> 0.28676056
A37: Retail | H37: 5582 | L37: 4189 | N37: 6535 | O37: =SUM(G37:N37) -> 16306 | R37: 0 | S37: 1037 | T37: =SUM(P37:S37) -> 1037 | U37: =+$N$12 | V37: =+$N$13 -> 65437.5 | Z37: Retail | AD37: =AC37*(1-$AD$23) -> 0 | AE37: =AC37*(1-$AE$23) -> 0 | AJ37: =SUM(AB37:AI37) -> 0 | AO37: =SUM(AL37:AN37) -> 0 | AP37: =(G37+K37)/((G37+K37)+(Q37+R37)) -> #DIV/0!
A38: Human Health | H38: 1257 | K38: 316 | L38: 303 | M38: 298 | N38: 1363 | O38: =SUM(G38:N38) -> 3537 | R38: 1902 | S38: 529 | T38: =SUM(P38:S38) -> 2431 | U38: =+$N$12 | V38: =+$N$13 -> 65437.5 | Z38: Human Health | AD38: =AC38*(1-$AD$23) -> 0 | AE38: =AC38*(1-$AE$23) -> 0 | AJ38: =SUM(AB38:AI38) -> 0 | AO38: =SUM(AL38:AN38) -> 0 | AP38: =(G38+K38)/((G38+K38)+(Q38+R38)) -> 0.14247069
A39: Education | H39: 1613 | K39: 95 | L39: 681 | M39: 337 | N39: 472 | O39: =SUM(G39:N39) -> 3198 | R39: 43 | S39: 84 | T39: =SUM(P39:S39) -> 127 | U39: =+$N$12 | V39: =+$N$13 -> 65437.5 | Z39: Education | AD39: =AC39*(1-$AD$23) -> 0 | AE39: =AC39*(1-$AE$23) -> 0 | AJ39: =SUM(AB39:AI39) -> 0 | AO39: =SUM(AL39:AN39) -> 0 | AP39: =(G39+K39)/((G39+K39)+(Q39+R39)) -> 0.6884058
A40: Other Commercial Segments | H40: 5430 | K40: 1807 | L40: 5596 | M40: 1486 | N40: 28904 | O40: =SUM(G40:N40) -> 43223 | R40: 38 | S40: 3275 | T40: =SUM(P40:S40) -> 3313 | U40: =+$N$12 | V40: =+$N$13 -> 65437.5 | Z40: Other Commercial Segments | AD40: =AC40*(1-$AD$23) -> 0 | AE40: =AC40*(1-$AE$23) -> 0 | AJ40: =SUM(AB40:AI40) -> 0 | AO40: =SUM(AL40:AN40) -> 0 | AP40: =(G40+K40)/((G40+K40)+(Q40+R40)) -> 0.97940379
A41: Industrial | C41: ='[2]Commerical demand'!D52 -> 22305467 | D41: =D30 -> 7116.8 | E41: =C41/D41/1000 -> 3.1341989 | F41: 3555 | H41: 2404 | L41: 864 | N41: 1885 | O41: =SUM(F41:N41) -> 8708 | P41: 3959 | S41: 1326 | T41: =SUM(P41:S41) -> 5285 | U41: =+$N$12 | V41: =+$N$13 -> 65437.5 | W41: =O41/3.6*1000000*U41/1000000 -> #VALUE! | X41: =T41*V41/1000000 -> 345.83719 | Y41: =W41+X41 -> #VALUE! | Z41: Industrial | AA41: =F41/$C$41*1000000000000*'[2]EF-1'!$R$6 -> 44.271658 | AC41: =H41/$C$41*1000000000000*'[2]EF-1'!$R$6 -> 29.937853 | AD41: =AC41*(1-$AD$23) -> 19.459604 | AE41: =AC41*(1-$AE$23) -> 23.950282 | AG41: =L41/$C$41*1000000000000*'[2]EF-1'!$R$6 -> 10.759694 | AI41: =N41/$C$41*1000000000000*'[2]EF-1'!$R$6 -> 23.474564 | AJ41: =SUM(AB41:AI41) -> 107.582 | AK41: =P41/$C$41*1000000000000*'[2]EF-1'!$R$8 -> 4.9873587 | AN41: =S41/$C$41*1000000000000*'[2]EF-1'!$R$8 -> 1.6704313 | AO41: =SUM(AK41:AN41) -> 6.6577901
A42: Industrial Land | C42: 16525600 | Z42: Industrial Land | AP42: =(G42+K42)/(G42+K42+Q42+R42) -> #DIV/0!
A43: Industrial Estates | Z43: Industrial Estates | AP43: =(G43+K43)/(G43+K43+Q43+R43) -> #DIV/0!
A44: Warehouse and Open Storage | C44: 3810700 | Z44: Warehouse & Open Storage
A45: TOTAL | B45: =(B30+B33+B41) -> 2384228 | C45: =(C30+C33+C41) -> 1.5563782e+08 | E45: =(E30+E33+E41) -> 21.869073 | F45: =(F30+F33+F41) -> 3555 | G45: =(G30+G33+G41) -> 7965 | H45: =(H30+H33+H41) -> 47938 | K45: =(K30+K33+K41) -> 14669 | L45: =(L30+L33+L41) -> 19838 | M45: =(M30+M33+M41) -> 11054 | N45: =(N30+N33+N41) -> 50691 | O45: =(O30+O33+O41) -> 155710 | P45: =(P30+P33+P41) -> 3959 | Q45: =(Q30+Q33+Q41) -> 19003 | R45: =(R30+R33+R41) -> 13873 | ... T45: =(T30+T33+T41) -> 43723 | W45: =(W30+W33+W41) -> #VALUE! | X45: =(X30+X33+X41) -> 2861.1238 | Y45: =(Y30+Y33+Y41) -> #VALUE! | Z45: TOTAL
A48: 2050 | B48: Floor area | F48: Electricity consumption | P48: Gas Consumption | U48: emission factor | W48: Emissions | Z48: 2050 | AA48: Energy efficiency -- Electricity | AK48: Energy efficiency -- Gas | AP48: Electrification (share of cooking, hot water & Ref)
B49: No. of Flats | C49: Floor area | D49: Population | E49: Floor area per capita | F49: Industrial equipment | G49: Cooking | H49: A.C. | I49: District cooling | J49: Fresh water cooling | K49: Hot Water & Refrigeration | L49: Lighting | M49: Office Equipment | N49: Others | O49: Total | P49: Industrial equipment | Q49: Cooking | R49: Hot Water | S49: Others | T49: Total | U49: Electricity | V49: Gas | W49: Electricity | X49: Gas | Y49: Total | AA49: Industrial equipment | AB49: Cooking | AC49: A.C. | AD49: District cooling | AE49: Fresh water cooling | AF49: Hot Water & Refrigeration | AG49: Lighting | AH49: Office Equipment | AI49: Others | AJ49: Total | AK49: Industrial equipment | AL49: Cooking | AM49: Hot Water | AN49: Others | AO49: Total
C50: m2 | D50: 1000 people | E50: m2 | F50: TJ | G50: TJ | H50: TJ | I50: TJ | J50: TJ | K50: TJ | L50: TJ | M50: TJ | N50: TJ | O50: TJ | P50: TJ | Q50: TJ | R50: TJ | S50: TJ | T50: TJ | U50: Kg CO2/KWh | V50: Kg CO2/TJ | W50: kt | X50: kt | Y50: kt | AA50: KWh per Flat or m2 | AB50: KWh per Flat or m2 | AC50: KWh per Flat or m2 | AD50: KWh per Flat or m2 | AE50: KWh per Flat or m2 | AF50: KWh per Flat or m2 | AG50: KWh per Flat or m2 | AH50: KWh per Flat or m2 | AI50: KWh per Flat or m2 | AJ50: KWh per Flat or m2 | AK50: m3 per capita | AL50: m3 per capita | AM50: m3 per capita | AN50: m3 per capita | AO50: m3 per capita
A51: Residential | B51: =SUM(B52:B53) -> 4296753.4 | C51: =SUM(C52:C53) -> 1.943016e+10 | D51: ='[2]Population and GDP'!E41/1000 -> 9066.5 | E51: =C51/D51/1000 -> 2143.0718 | G51: =SUM(G52:G53) -> 3171.1488 | H51: =SUM(H52:H53) -> 24658.341 | K51: =SUM(K52:K53) -> 8379.9627 | L51: =SUM(L52:L53) -> 4533.1417 | M51: =SUM(M52:M53) -> 10878.303 | N51: =SUM(N52:N53) -> 5110.8995 | O51: =SUM(O52:O53) -> 56731.797 | Q51: =SUM(Q52:Q53) -> 8723.7159 | R51: =SUM(R52:R53) -> 8104.0668 | S51: =SUM(S52:S53) -> 30.801006 | T51: =SUM(T52:T53)*(1-'[2]Key parameters rpt'!O42) -> 0 | U51: =+O12 -> 0.008765039 | V51: =+O13 -> 65437.5 | W51: =SUM(W52:W53) -> 138.12678 | X51: =SUM(X52:X53) -> 0 | Y51: =W51+X51 -> 138.12678 | Z51: Residential
A52: Private Residential | B52: ='[2]Key parameters rpt'!O27 -> 2174901.2 | C52: =D52*D51*E52 -> 7.8874968e+09 | D52: =B5 -> 0.4 | E52: =C5 -> 2174901.2 | G52: =$B$52*AB52*'[2]EF-1'!$R$5/1000000000000 -> 1790.6317 | H52: =$B$52*AC52*'[2]EF-1'!$R$5/1000000000000 -> 15685.378 | I52: 0 | K52: =$B$52*AF52*'[2]EF-1'!$R$5/1000000000000 -> 5030.6798 | L52: =$B$52*AG52*'[2]EF-1'!$R$5/1000000000000 -> 2860.0934 | M52: =$B$52*AH52*'[2]EF-1'!$R$5/1000000000000 -> 5974.5424 | N52: =$B$52*AI52*'[2]EF-1'!$R$5/1000000000000 -> 3025.8328 | O52: =SUM(F52:N52) -> 34367.159 | Q52: =$B$52*AL52*'[2]EF-1'!$R$5/1000000000000 -> 4307.151 | R52: =$B$52*AM52*'[2]EF-1'!$R$5/1000000000000 -> 2994.8195 | S52: =$B$52*AN52*'[2]EF-1'!$R$5/1000000000000 -> 0.86188383 | T52: =SUM(Q52:S52)*(1-'[2]Key parameters rpt'!O42)-('[2]Key parameters rpt'!O43/4) -> 0 | U52: =[2]Electricity!$K$6 -> 0.008765039 | V52: =O13 -> 65437.5 | W52: =O52*1000000000000*'[2]EF-1'!R6*U52/1000000 -> 83.674857 | X52: =T52*V52/1000000 -> 0 | Y52: =W52+X52 -> 83.674857 | Z52: Private Residential | AB52: =AB31*(1-E5)+AL31*(1-N5)*R5 -> 228.69898 | AC52: =AC31*(1-F5) -> 2003.3321 | AF52: =AF31*(1-H5)+AM31*(1-O5)*R5 -> 642.51702 | AG52: =AG31*(1-I5) -> 365.29033 | AH52: =AH31*(1-J5) -> 763.06688 | AI52: =AI31*(1-K5) -> 386.45852 | AJ52: =SUM(AA52:AI52) -> 4389.3639 | AL52: =AL31*(1-N5)*(1-R5) -> 550.10812 | AM52: =AM31*(1-O5)*(1-R5) -> 382.49751 | AN52: =AN31*(1-P5) -> 0.11007956 | AO52: =SUM(AK52:AN52) -> 932.71571 | AP52: =(G52+K52)/((G52+K52)+(Q52+R52)) -> 0.48298345
A53: Public Residential | B53: ='[2]Key parameters rpt'!O28 -> 2121852.2 | C53: =D53*D51*E53 -> 1.1542664e+10 | D53: =B6 -> 0.6 | E53: =C6 -> 2121852.2 | G53: =$B$53*AB53*'[2]EF-1'!$R$5/1000000000000 -> 1380.5171 | H53: =$B$53*AC53*'[2]EF-1'!$R$5/1000000000000 -> 8972.9626 | I53: 0 | K53: =$B$53*AF53*'[2]EF-1'!$R$5/1000000000000 -> 3349.2829 | L53: =$B$53*AG53*'[2]EF-1'!$R$5/1000000000000 -> 1673.0482 | M53: =$B$53*AH53*'[2]EF-1'!$R$5/1000000000000 -> 4903.7609 | N53: =$B$53*AI53*'[2]EF-1'!$R$5/1000000000000 -> 2085.0667 | O53: =SUM(F53:N53) -> 22364.638 | Q53: =$B$52*AL53*'[2]EF-1'!$R$5/1000000000000 -> 4416.5649 | R53: =$B$52*AM53*'[2]EF-1'!$R$5/1000000000000 -> 5109.2473 | S53: =$B$52*AN53*'[2]EF-1'!$R$5/1000000000000 -> 29.939122 | T53: =SUM(Q53:S53)*(1-'[2]Key parameters rpt'!O42)-('[2]Key parameters rpt'!O43/4) -> 0 | U53: =[2]Electricity!$K$6 -> 0.008765039 | V53: =O13 -> 65437.5 | W53: =O53*1000000000000*'[2]EF-1'!R6*U53/1000000 -> 54.451925 | X53: =T53*V53/1000000 -> 0 | Y53: =W53+X53 -> 54.451925 | Z53: Public Residential | AB53: =AB32*(1-E6)+AL32*(1-N6)*R6 -> 180.72747 | AC53: =AC32*(1-F6) -> 1174.6764 | AF53: =AF32*(1-H6)+AM32*(1-O6)*R6 -> 438.46427 | AG53: =AG32*(1-I6) -> 219.02357 | AH53: =AH32*(1-J6) -> 641.96546 | AI53: =AI32*(1-K6) -> 272.96209 | AJ53: =SUM(AA53:AI53) -> 2927.8192 | AL53: =AL32*(1-N6)*(1-R6) -> 564.08243 | AM53: =AM32*(1-O6)*(1-R6) -> 652.55164 | AN53: =AN32*(1-P6) -> 3.8238163 | AO53: =SUM(AK53:AN53) -> 1220.4579 | AP53: =(G53+K53)/((G53+K53)+(Q53+R53)) -> 0.33178512
A54: Commercial | C54: =D54*E54*1000 -> 53516826 | D54: =D51 -> 9066.5 | E54: =C7 -> 5.9026996 | G54: =$C$54*AB54*'[2]EF-1'!$R$5/1000000000000 -> 2067.1714 | H54: =AC24*1000000*AC54*'[2]EF-1'!$R$5/1000000000000 -> 28244.94 | I54: =AD54*'[2]EF-1'!$R$5/1000000000000*AD24*1000000 -> 832.42962 | J54: =AE24*1000000*AE54*'[2]EF-1'!$R$5/1000000000000 -> 1189.2606 | K54: =$C$54*AF54*'[2]EF-1'!$R$5/1000000000000 -> 3036.6964 | L54: =$C$54*AG54*'[2]EF-1'!$R$5/1000000000000 -> 11159.291 | M54: =$C$54*AH54*'[2]EF-1'!$R$5/1000000000000 -> 4670.9167 | N54: =$C$54*AI54*'[2]EF-1'!$R$5/1000000000000 -> 34731.918 | O54: =SUM(G54:N54) -> 85932.623 | Q54: =$C$54*AL54*'[2]EF-1'!$R$7/1000000000000 -> 4257.6872 | R54: =$C$54*AM54*'[2]EF-1'!$R$7/1000000000000 -> 3193.6492 | S54: =$C$54*AN54*'[2]EF-1'!$R$7/1000000000000 -> 2830.7811 | T54: =SUM(Q54:S54)*(1-'[2]Key parameters rpt'!O42)-('[2]Key parameters rpt'!O43/4) -> 0 | U54: =[2]Electricity!$K$6 -> 0.008765039 | V54: =O13 -> 65437.5 | W54: =O54*1000000000000*'[2]EF-1'!R6*U54/1000000 -> 209.223 | X54: =T54*V54/1000000 -> 0 | Y54: =W54+X54 -> 209.223 | Z54: Commercial | AB54: =AB33*(1-E7)+AL33*(1-N7)*R7 -> 10.729602 | AC54: =AC33*(1-F7) -> 160.96794 | AD54: =AC54*(1-$AD$23) -> 104.62916 | AE54: =AC54*(1-$AE$23) -> 128.77435 | AF54: =AF33*(1-H7)+AM33*(1-O7)*R7 -> 15.761898 | AG54: =AG33*(1-I7) -> 57.922025 | AH54: =AH33*(1-J7) -> 24.244279 | AI54: =AI33*(1-K7) -> 180.27517 | AJ54: =SUM(AA54:AI54) -> 683.30444 | AL54: =AL33*(1-N7)*(1-R7) -> 2.2355265 | AM54: =AM33*(1-O7)*(1-R7) -> 1.6768464 | AN54: =AN33*(1-P7) -> 1.4863201 | AO54: =SUM(AK54:AN54) -> 5.398693 | AP54: =(G54+K54)/((G54+K54)+(Q54+R54)) -> 0.40651412
A55: Office | T55: =SUM(Q55:S55) -> 0 | U55: =[2]Electricity!$K$6 -> 0.008765039 | W55: =O55*1000000000000*$AI$46*U55/1000000 -> 0 | Z55: Office | AC55: =AC34*(1-F8) -> 0 | AD55: =AC55*(1-$AD$23) -> 0 | AE55: =AC55*(1-$AE$23) -> 0 | AG55: =AG34*(1-I8) -> 0 | AI55: =AI34*(1-K8) -> 0 | AJ55: =SUM(AA55:AI55) -> 0 | AO55: =SUM(AK55:AN55) -> 0 | AP55: =(#REF!+J71)/(#REF!+J71+Q55+R55) -> #REF!
A56: Restaurant | T56: =SUM(Q56:S56) -> 0 | U56: =[2]Electricity!$K$6 -> 0.008765039 | W56: =O56*1000000000000*$AI$46*U56/1000000 -> 0 | Z56: Restaurant | AC56: =AC35*(1-#REF!) -> #REF! | AD56: =AC56*(1-$AD$23) -> #REF! | AE56: =AC56*(1-$AE$23) -> #REF! | AG56: =AG35*(1-#REF!) -> #REF! | AI56: =AI35*(1-#REF!) -> #REF! | AJ56: =SUM(AA56:AI56) -> #REF! | AO56: =SUM(AK56:AN56) -> 0 | AP56: =(#REF!+J72)/(#REF!+J72+Q56+R56) -> #REF!
A57: Accommodation | T57: =SUM(Q57:S57) -> 0 | U57: =[2]Electricity!$K$6 -> 0.008765039 | W57: =O57*1000000000000*$AI$46*U57/1000000 -> 0 | Z57: Accommodation | AC57: =AC36*(1-AC48) -> 0 | AD57: =AC57*(1-$AD$23) -> 0 | AE57: =AC57*(1-$AE$23) -> 0 | AG57: =AG36*(1-AG48) -> 0 | AI57: =AI36*(1-AI48) -> 0 | AJ57: =SUM(AA57:AI57) -> 0 | AO57: =SUM(AK57:AN57) -> 0 | AP57: =('[2]EF-1'!S20+J73)/('[2]EF-1'!S20+J73+Q57+R57) -> #VALUE!
A58: Retail | T58: =SUM(Q58:S58) -> 0 | U58: =[2]Electricity!$K$6 -> 0.008765039 | W58: =O58*1000000000000*$AI$46*U58/1000000 -> 0 | Z58: Retail | AC58: =AC37*(1-AC49) -> #VALUE! | AD58: =AC58*(1-$AD$23) -> #VALUE! | AE58: =AC58*(1-$AE$23) -> #VALUE! | AG58: =AG37*(1-AG49) -> #VALUE! | AI58: =AI37*(1-AI49) -> #VALUE! | AJ58: =SUM(AA58:AI58) -> #VALUE! | AO58: =SUM(AK58:AN58) -> 0 | AP58: =(#REF!+J74)/(#REF!+J74+Q58+R58) -> #REF!
A59: Human Health | T59: =SUM(Q59:S59) -> 0 | U59: =[2]Electricity!$K$6 -> 0.008765039 | W59: =O59*1000000000000*$AI$46*U59/1000000 -> 0 | Z59: Human Health | AC59: =AC38*(1-AC50) -> #VALUE! | AD59: =AC59*(1-$AD$23) -> #VALUE! | AE59: =AC59*(1-$AE$23) -> #VALUE! | AG59: =AG38*(1-AG50) -> #VALUE! | AI59: =AI38*(1-AI50) -> #VALUE! | AJ59: =SUM(AA59:AI59) -> #VALUE! | AO59: =SUM(AK59:AN59) -> 0 | AP59: =(#REF!+J75)/(#REF!+J75+Q59+R59) -> #REF!
A60: Education | T60: =SUM(Q60:S60) -> 0 | U60: =[2]Electricity!$K$6 -> 0.008765039 | W60: =O60*1000000000000*$AI$46*U60/1000000 -> 0 | Z60: Education | AC60: =AC39*(1-AC51) -> 0 | AD60: =AC60*(1-$AD$23) -> 0 | AE60: =AC60*(1-$AE$23) -> 0 | AG60: =AG39*(1-AG51) -> 0 | AI60: =AI39*(1-AI51) -> 0 | AJ60: =SUM(AA60:AI60) -> 0 | AO60: =SUM(AK60:AN60) -> 0 | AP60: =(#REF!+J76)/(#REF!+J76+Q60+R60) -> #REF!
A61: Other Commercial Segments | T61: =SUM(Q61:S61) -> 0 | U61: =[2]Electricity!$K$6 -> 0.008765039 | W61: =O61*1000000000000*$AI$46*U61/1000000 -> 0 | Z61: Other Commercial Segments | AC61: =AC40*(1-AC52) -> 0 | AD61: =AC61*(1-$AD$23) -> 0 | AE61: =AC61*(1-$AE$23) -> 0 | AG61: =AG40*(1-AG52) -> 0 | AI61: =AI40*(1-AI52) -> 0 | AJ61: =SUM(AA61:AI61) -> 0 | AO61: =SUM(AK61:AN61) -> 0 | AP61: =(#REF!+J77)/(#REF!+J77+Q61+R61) -> #REF!
A62: Industrial | C62: =D62*E62*1000 -> 33300000 | D62: =D51 -> 9066.5 | E62: =C8 -> 3.6728616 | F62: =$C$62*AA62*'[2]EF-1'!$R$5/1000000000000 -> 5299.3255 | G62: =$C$62*AB62*'[2]EF-1'!$R$5/1000000000000 -> 0 | H62: =$C$62*AC62*'[2]EF-1'!$R$5/1000000000000 -> 3230.0548 | K62: =$C$62*AF62*'[2]EF-1'!$R$5/1000000000000 -> 0 | L62: =$C$62*AG62*'[2]EF-1'!$R$5/1000000000000 -> 838.41689 | M62: =$C$62*AH62*'[2]EF-1'!$R$5/1000000000000 -> 0 | N62: =$C$62*AI62*'[2]EF-1'!$R$5/1000000000000 -> 2180.9513 | O62: =SUM(F62:N62) -> 11548.749 | P62: =$C$62*AK62*'[2]EF-1'!$R$7/1000000000000 -> 5437.5874 | S62: =$C$62*AN62*'[2]EF-1'!$R$7/1000000000000 -> 1821.2278 | T62: =SUM(P62:S62)*(1-'[2]Key parameters rpt'!O42)-('[2]Key parameters rpt'!O43/4) -> 0 | U62: =[2]Electricity!$K$6 -> 0.008765039 | V62: =O13 -> 65437.5 | W62: =O62*1000000000000*'[2]EF-1'!R6*U62/1000000 -> 28.11812 | X62: =T62*V62/1000000 -> 0 | Y62: =W62+X62 -> 28.11812 | Z62: Industrial | AA62: =AA41*(1-D8%) -> 44.205251 | AC62: =AC41*(1-F8) -> 26.944068 | AD62: =AC62*(1-$AD$23) -> 17.513644 | AE62: =AC62*(1-$AE$23) -> 21.555254 | AG62: =AG41*(1-I8) -> 6.9938012 | AI62: =AI41*(1-K8) -> 18.192787 | AJ62: =SUM(AA62:AI62) -> 135.4048 | AK62: =AK41*(1-M8) -> 4.58837 | AN62: =AN41*(1-P8) -> 1.5367968 | AO62: =SUM(AK62:AN62) -> 6.1251668
A63: Industrial Land | Z63: Industrial Land | AJ63: =SUM(AA63:AI63) -> 0
A64: Industrial Estates | Z64: Industrial Estates | AJ64: =SUM(AA64:AI64) -> 0
A65: Warehouse and Open Storage | Z65: Warehouse and Open Storage | AJ65: =SUM(AA65:AI65) -> 0
A66: TOTAL | B66: =(B51+B54+B62) -> 4296753.4 | C66: =(C51+C54+C62) -> 1.9516977e+10 | D66: =(D51) -> 9066.5 | E66: =(E51+E54+E62) -> 2152.6474 | F66: =(F51+F54+F62) -> 5299.3255 | G66: =(G51+G54+G62) -> 5238.3201 | H66: =(H51+H54+H62) -> 56133.336 | I66: =(I51+I54+I62) -> 832.42962 | J66: =(J51+J54+J62) -> 1189.2606 | K66: =(K51+K54+K62) -> 11416.659 | L66: =(L51+L54+L62) -> 16530.849 | ... T66: =(T51+T54+T62) -> 0 | U66: =(O12+U54+U62) -> 0.026295117 | V66: =(O13+V54+V62) -> 196312.5 | W66: =(W51+W54+W62) -> 375.4679 | X66: =(X51+X54+X62) -> 0 | Y66: =(Y51+Y54+Y62) -> 375.4679 | Z66: TOTAL

Sheet Future Total Energy
A1: year | B1: popu | C1: popu_private_raw | D1: popu_public_raw | E1: popu_private | F1: popu_public | G1: gdp | H1: gdpper | I1: hh | J1: poperhh | K1: rear | L1: cmar | N1: Explain for the abbr. of variables | T1: year | U1: History&Trend | V1: reener | W1: PHre户均 | X1: PCre人均 | Y1: private ENER | Z1: PC private ENER | AA1: public ENER | AB1: PC public ENER | AC1: comener | AD1: PAce单位面积 | AE1: Future_Prediction | AF1: origin_residential | AG1: origin_commercial | AH1: new_residential | AI1: new_commercial | AJ1: DIFF_COMMERCIAL | AL1: new_private | AM1: new_public | AN1: new_residential | AO1: new_commercial
A2: 2005 | B2: 6.8132 | C2: =TREND($C$49:$C$50,$A$49:$A$50,$A2) -> 4.2084595 | D2: =TREND($D$49:$D$50,$A$49:$A$50,$A2) -> 2.7102029 | G2: 196.28291 | H2: 28.80921 | I2: 2.1971 | J2: 3.1823115 | K2: 95.57385 | L2: 42.557143 | N2: popu | O2: population,×10^6 people | T2: 2005 | Z2: 均值6956.12; 10年均增长率2.00% 5年均增长率1.33% | AB2: 均值8592.81; 5年均增长率-0.74% 10年均增长率-0.74% | AE2: Old:direct regress total energy; New: predict intensity*popu(or area)
A3: 2006 | B3: 6.8571 | C3: =TREND($C$49:$C$50,$A$49:$A$50,$A3) -> 4.1900344 | D3: =TREND($D$49:$D$50,$A$49:$A$50,$A3) -> 2.7626205 | G3: 210.08695 | H3: 30.637872 | I3: 2.2209 | J3: 3.1695082 | K3: 96.60915 | L3: 43.285714 | N3: gdp | O3: GDP, bil.USD2012 | T3: 2006 | V3: 53982 | W3: =V3/I3/1000 -> 24.306362 | X3: =V3/B3/1000 -> 7.8724242 | Y3: ='Private,Public8EndUse'!S6 -> 26211 | Z3: =Y3/C3 -> 6255.5572 | AA3: ='Private,Public8EndUse'!AC6 -> 24967 | AB3: =AA3/D3 -> 9037.4338 | AC3: 111884 | AD3: =AC3/L3/1000 -> 2.5847789 | AF3: 53982 | AG3: 111884 | AH3: 53982 | AI3: 111884 | AJ3: =(AI3-AG3)/AG3 -> 0 | AL3: =Y3 -> 26211 | AM3: =AA3 -> 24967 | AN3: =SUM(AL3:AM3) -> 51178 | AO3: =AI3 -> 111884
A4: 2007 | B4: 6.9163 | C4: =TREND($C$49:$C$50,$A$49:$A$50,$A4) -> 4.1716093 | D4: =TREND($D$49:$D$50,$A$49:$A$50,$A4) -> 2.8150381 | G4: 223.66873 | H4: 32.339362 | I4: 2.2499 | J4: 3.1567049 | K4: 97.87065 | L4: 44.014286 | N4: gdpper | O4: GDP per capita, kUSD2012 | T4: 2007 | V4: 54717 | W4: =V4/I4/1000 -> 24.319748 | X4: =V4/B4/1000 -> 7.911311 | Y4: ='Private,Public8EndUse'!S7 -> 26733 | Z4: =Y4/C4 -> 6408.3182 | AA4: ='Private,Public8EndUse'!AC7 -> 25185 | AB4: =AA4/D4 -> 8946.5928 | AC4: 113914 | AD4: =AC4/L4/1000 -> 2.5881142 | AF4: 54717 | AG4: 113914 | AH4: 54717 | AI4: 113914 | AJ4: =(AI4-AG4)/AG4 -> 0 | AL4: =Y4 -> 26733 | AM4: =AA4 -> 25185 | AN4: =SUM(AL4:AM4) -> 51918 | AO4: =AI4 -> 113914
A5: 2008 | B5: 6.9578 | C5: =TREND($C$49:$C$50,$A$49:$A$50,$A5) -> 4.1531843 | D5: =TREND($D$49:$D$50,$A$49:$A$50,$A5) -> 2.8674558 | G5: 228.42826 | H5: 32.83053 | I5: 2.2791 | J5: 3.1439016 | K5: 99.14085 | L5: 44.742857 | N5: hh | O5: household unit, predicted according to HK 2030 Baseline report | T5: 2008 | V5: 55849 | W5: =V5/I5/1000 -> 24.504848 | X5: =V5/B5/1000 -> 8.0268188 | Y5: ='Private,Public8EndUse'!S8 -> 27701 | Z5: =Y5/C5 -> 6669.8221 | AA5: ='Private,Public8EndUse'!AC8 -> 25533 | AB5: =AA5/D5 -> 8904.4094 | AC5: 113753 | AD5: =AC5/L5/1000 -> 2.5423723 | AF5: 55849 | AG5: 113753 | AH5: 55849 | AI5: 113753 | AJ5: =(AI5-AG5)/AG5 -> 0 | AL5: =Y5 -> 27701 | AM5: =AA5 -> 25533 | AN5: =SUM(AL5:AM5) -> 53234 | AO5: =AI5 -> 113753
A6: 2009 | B6: 6.9728 | C6: =TREND($C$49:$C$50,$A$49:$A$50,$A6) -> 4.1347592 | D6: =TREND($D$49:$D$50,$A$49:$A$50,$A6) -> 2.9198734 | G6: 222.8111 | H6: 31.954323 | I6: 2.2972 | J6: 3.1310984 | K6: 99.9282 | L6: 45.471429 | N6: hhnew | O6: household unit, predicted according to HK C&SD | T6: 2009 | V6: 57731 | W6: =V6/I6/1000 -> 25.131029 | X6: =V6/B6/1000 -> 8.2794573 | Y6: ='Private,Public8EndUse'!S9 -> 28544 | Z6: =Y6/C6 -> 6903.425 | AA6: ='Private,Public8EndUse'!AC9 -> 26068 | AB6: =AA6/D6 -> 8927.7844 | AC6: 114297 | AD6: =AC6/L6/1000 -> 2.5136004 | AF6: 57731 | AG6: 114297 | AH6: 57731 | AI6: 114297 | AJ6: =(AI6-AG6)/AG6 -> 0 | AL6: =Y6 -> 28544 | AM6: =AA6 -> 26068 | AN6: =SUM(AL6:AM6) -> 54612 | AO6: =AI6 -> 114297
A7: 2010 | B7: 7.0242 | C7: =TREND($C$49:$C$50,$A$49:$A$50,$A7) -> 4.1163341 | D7: =TREND($D$49:$D$50,$A$49:$A$50,$A7) -> 2.972291 | G7: 237.89025 | H7: 33.867237 | I7: 2.3251 | J7: 3.1182951 | K7: 101.14185 | L7: 46.2 | N7: poperhh | O7: Average no. of people per household | T7: 2010 | V7: 58396 | W7: =V7/I7/1000 -> 25.115479 | X7: =V7/B7/1000 -> 8.3135446 | Y7: ='Private,Public8EndUse'!S10 -> 28730 | Z7: =Y7/C7 -> 6979.5112 | AA7: ='Private,Public8EndUse'!AC10 -> 16152 | AB7: =AA7/D7 -> 5434.192 | AC7: 116391 | AD7: =AC7/L7/1000 -> 2.5192857 | AF7: 58396 | AG7: 116391 | AH7: 58396 | AI7: 116391 | AJ7: =(AI7-AG7)/AG7 -> 0 | AL7: =Y7 -> 28730 | AM7: =AA7 -> 16152 | AN7: =SUM(AL7:AM7) -> 44882 | AO7: =AI7 -> 116391 | AR7: Final results(2019/9/5)
A8: 2011 | B8: 7.0716 | C8: =TREND($C$49:$C$50,$A$49:$A$50,$A8) -> 4.097909 | D8: =TREND($D$49:$D$50,$A$49:$A$50,$A8) -> 3.0247087 | G8: 249.34392 | H8: 35.259902 | I8: 2.3593 | J8: 3.1054918 | K8: 102.62955 | L8: 46.37 | N8: rear | O8: residential building area, Mil. M2 | T8: 2011 | V8: 58826 | W8: =V8/I8/1000 -> 24.933667 | X8: =V8/B8/1000 -> 8.3186266 | Y8: ='Private,Public8EndUse'!S11 -> 29134 | Z8: =Y8/C8 -> 7109.4795 | AA8: ='Private,Public8EndUse'!AC11 -> 16425 | AB8: =AA8/D8 -> 5430.2751 | AC8: =Commercial8EndUse!Q12 -> 116013 | AD8: =AC8/L8/1000 -> 2.5018978 | AF8: 58826 | AG8: 118558 | AH8: 58826 | AI8: 118558 | AJ8: =(AI8-AG8)/AG8 -> 0 | AL8: =Y8 -> 29134 | AM8: =AA8 -> 16425 | AN8: =SUM(AL8:AM8) -> 45559 | AO8: =AI8 -> 118558
A9: 2012 | B9: 7.1501 | C9: =TREND($C$49:$C$50,$A$49:$A$50,$A9) -> 4.0794839 | D9: =TREND($D$49:$D$50,$A$49:$A$50,$A9) -> 3.0771263 | G9: 253.58353 | H9: 35.465732 | I9: 2.3862 | J9: 3.0926885 | K9: 103.7997 | L9: 46.54 | N9: cmar | O9: commercial building area, Mil m2 in GFA | T9: 2012 | V9: 59932 | W9: =V9/I9/1000 -> 25.116084 | X9: =V9/B9/1000 -> 8.3819807 | Y9: ='Private,Public8EndUse'!S12 -> 29324 | Z9: =Y9/C9 -> 7188.1641 | AA9: ='Private,Public8EndUse'!AC12 -> 16866 | AB9: =AA9/D9 -> 5481.088 | AC9: =Commercial8EndUse!Q13 -> 118330 | AD9: =AC9/L9/1000 -> 2.542544 | AF9: 59932 | AG9: 120970 | AH9: 59932 | AI9: 120970 | AJ9: =(AI9-AG9)/AG9 -> 0 | AL9: =Y9 -> 29324 | AM9: =AA9 -> 16866 | AN9: =SUM(AL9:AM9) -> 46190 | AO9: =AI9 -> 120970
A10: 2013 | B10: 7.1789 | C10: =TREND($C$49:$C$50,$A$49:$A$50,$A10) -> 4.0610588 | D10: =TREND($D$49:$D$50,$A$49:$A$50,$A10) -> 3.1295439 | G10: 261.4484 | H10: 36.419006 | I10: 2.4073 | J10: 3.0798852 | K10: 104.71755 | L10: 46.71 | N10: re | O10: residential total energy use,TJ | T10: 2013 | V10: 58394 | W10: =V10/I10/1000 -> 24.257051 | X10: =V10/B10/1000 -> 8.1341153 | Y10: ='Private,Public8EndUse'!S13 -> 28489 | Z10: =Y10/C10 -> 7015.1655 | AA10: ='Private,Public8EndUse'!AC13 -> 16604 | AB10: =AA10/D10 -> 5305.5654 | AC10: =Commercial8EndUse!Q14 -> 118209 | AD10: =AC10/L10/1000 -> 2.5307001 | AF10: 58394 | AG10: 121215 | AH10: 58394 | AI10: 121215 | AJ10: =(AI10-AG10)/AG10 -> 0 | AL10: =Y10 -> 28489 | AM10: =AA10 -> 16604 | AN10: =SUM(AL10:AM10) -> 45093 | AO10: =AI10 -> 121215
A11: 2014 | B11: 7.2295 | C11: =TREND($C$49:$C$50,$A$49:$A$50,$A11) -> 4.0426338 | D11: =TREND($D$49:$D$50,$A$49:$A$50,$A11) -> 3.1819615 | G11: 268.67069 | H11: 37.163108 | I11: 2.4324 | J11: 3.067082 | K11: 105.8094 | L11: 46.88 | N11: cm | O11: commercial total energy use,TJ | T11: 2014 | V11: 61910 | W11: =V11/I11/1000 -> 25.452228 | X11: =V11/B11/1000 -> 8.5635244 | Y11: ='Private,Public8EndUse'!S14 -> 30548 | Z11: =Y11/C11 -> 7556.4599 | AA11: ='Private,Public8EndUse'!AC14 -> 17371 | AB11: =AA11/D11 -> 5459.2112 | AC11: =Commercial8EndUse!Q15 -> 119615 | AD11: =AC11/L11/1000 -> 2.5515145 | AF11: 61910 | AG11: 122711 | AH11: 61910 | AI11: 122711 | AJ11: =(AI11-AG11)/AG11 -> 0 | AL11: =Y11 -> 30548 | AM11: =AA11 -> 17371 | AN11: =SUM(AL11:AM11) -> 47919 | AO11: =AI11 -> 122711
A12: 2015 | B12: 7.2913 | C12: =TREND($C$49:$C$50,$A$49:$A$50,$A12) -> 4.0242087 | D12: =TREND($D$49:$D$50,$A$49:$A$50,$A12) -> 3.2343792 | G12: 275.08613 | H12: 37.727996 | I12: 2.4711 | J12: 3.0542787 | K12: 107.49285 | L12: 47.05 | T12: 2015 | V12: 60214 | W12: =V12/I12/1000 -> 24.367286 | X12: =V12/B12/1000 -> 8.2583353 | Y12: ='Private,Public8EndUse'!S15 -> 29241 | Z12: =Y12/C12 -> 7266.2733 | AA12: ='Private,Public8EndUse'!AC15 -> 16970 | AB12: =AA12/D12 -> 5246.7565 | AC12: =Commercial8EndUse!Q16 -> 120417 | AD12: =AC12/L12/1000 -> 2.5593411 | AF12: 60214 | AG12: 123674 | AH12: 60214 | AI12: 123674 | AJ12: =(AI12-AG12)/AG12 -> 0 | AL12: =Y12 -> 29241 | AM12: =AA12 -> 16970 | AN12: =SUM(AL12:AM12) -> 46211 | AO12: =AI12 -> 123674
A13: 2016 | B13: 7.3366 | C13: =B13*Building!D31 -> 4.0057836 | D13: =B13*Building!D32 -> 3.2867968 | E13: =$B13*C13/($C13+$D13) -> 4.0299634 | F13: =$B13*D13/($C13+$D13) -> 3.3066366 | G13: 281.03604 | H13: 38.306032 | I13: 2.8 | J13: 3.0414754 | K13: 108.70215 | L13: 47.22 | T13: 2016 | V13: 61439 | W13: =V13/I13/1000 -> 21.9425 | X13: =V13/B13/1000 -> 8.3743151 | Y13: ='Private,Public8EndUse'!S16 -> 30489 | Z13: =Y13/C13 -> 7611.2449 | AA13: ='Private,Public8EndUse'!AC16 -> 17190 | AB13: =AA13/D13 -> 5230.016 | AC13: =Commercial8EndUse!Q17 -> 120458 | AD13: =AC13/L13/1000 -> 2.5509953 | AF13: 61439 | AG13: 123969 | AH13: 61439 | AI13: 123969 | AJ13: =(AI13-AG13)/AG13 -> 0 | AL13: =Y13 -> 30489 | AM13: =AA13 -> 17190 | AN13: =SUM(AL13:AM13) -> 47679 | AO13: =AI13 -> 123969
A14: 2017 | B14: 7.3917 | C14: =TREND($C$49:$C$50,$A$49:$A$50,$A14) -> 3.9873585 | D14: =TREND($D$49:$D$50,$A$49:$A$50,$A14) -> 3.3392144 | E14: =$B14*C14/($C14+$D14) -> 4.0228028 | F14: =$B14*D14/($C14+$D14) -> 3.3688972 | G14: 291.69109 | H14: 39.461977 | I14: 2.8 | J14: 3.0286721 | K14: 110.25945 | L14: 47.39 | T14: 2017 | Y14: ='Private,Public8EndUse'!S17 -> 30231 | Z14: =Y14/C14 -> 7581.711 | AA14: ='Private,Public8EndUse'!AC17 -> 16713 | AB14: =AA14/D14 -> 5005.0694 | AC14: =Commercial8EndUse!Q18 -> 120408 | AD14: =AD13 -> 2.5509953 | AF14: 62377.59 | AG14: 126310.49 | AH14: =I14*$W$16*1000 -> 68586.327 | AI14: =L14*$AD$16*1000 -> 120891.67 | AJ14: =(AI14-AG14)/AG14 -> -0.042900773 | AL14: =Y14 -> 30231 | AM14: =AA14 -> 16713 | AN14: =SUM(AL14:AM14) -> 46944 | AO14: =AI14 -> 120891.67
A15: 2018 | B15: 7.451 | C15: =TREND($C$49:$C$50,$A$49:$A$50,$A15) -> 3.9689334 | D15: =TREND($D$49:$D$50,$A$49:$A$50,$A15) -> 3.3916321 | E15: =$B15*C15/($C15+$D15) -> 4.0176972 | F15: =$B15*D15/($C15+$D15) -> 3.4333028 | G15: 301.90028 | H15: 40.518089 | I15: 2.8 | J15: 3.0158689 | K15: 110.89632 | L15: 47.56 | T15: 2018 | W15: 平均值 | Y15: ='Private,Public8EndUse'!S18 -> 30241 | Z15: =Y15/C15 -> 7619.4274 | AA15: ='Private,Public8EndUse'!AC18 -> 16925 | AB15: =AA15/D15 -> 4990.2229 | AC15: =Commercial8EndUse!Q19 -> 122220 | AD15: =AD14 -> 2.5509953 | AF15: 62807.112 | AG15: 127689.15 | AH15: =I15*$W$16*1000 -> 68586.327 | AI15: =L15*$AD$16*1000 -> 121325.34 | AJ15: =(AI15-AG15)/AG15 -> -0.049838306 | AL15: =Y15 -> 30241 | AM15: =AA15 -> 16925 | AN15: =SUM(AL15:AM15) -> 47166 | AO15: =AI15 -> 121325.34 | AU15: the following is extracted from the updated Policy Concept Model | BA15: conversion for gdp | BG15: conversion for capita | BM15: conversion for population
A16: 2019 | B16: 7.5026 | C16: =TREND($C$49:$C$50,$A$49:$A$50,$A16) -> 3.9505084 | D16: =TREND($D$49:$D$50,$A$49:$A$50,$A16) -> 3.4440497 | E16: =$B16*C16/($C16+$D16) -> 4.0082293 | F16: =$B16*D16/($C16+$D16) -> 3.4943707 | G16: 310.65539 | H16: 41.406364 | I16: 2.8 | J16: 3.0030656 | K16: 111.53319 | L16: 47.73 | T16: 2019 | W16: =AVERAGE(W3:W13) -> 24.495117 | Y16: ='Private,Public8EndUse'!S19 -> 30115 | Z16: =Y16/C16 -> 7623.0696 | AA16: ='Private,Public8EndUse'!AC19 -> 16785 | AB16: =AA16/D16 -> 4873.6231 | AC16: =Commercial8EndUse!Q20 -> 123001 | AD16: =AD15 -> 2.5509953 | AF16: 63353.126 | AG16: 129082.93 | AH16: =I16*$W$16*1000 -> 68586.327 | AI16: =L16*$AD$16*1000 -> 121759.01 | AJ16: =(AI16-AG16)/AG16 -> -0.056738091 | AL16: =Y16 -> 30115 | AM16: =AA16 -> 16785 | AN16: =SUM(AL16:AM16) -> 46900 | AO16: =AI16 -> 121759.01 | AV16: GDP | AW16: Year-on-year change | AX16: GDP per capita HK$ | AY16: Usual Residents ^3 | BO16: Usual Residents ^3
A17: 2020 | B17: 7.5581 | C17: =TREND($C$49:$C$50,$A$49:$A$50,$A17) -> 3.9320833 | D17: =TREND($D$49:$D$50,$A$49:$A$50,$A17) -> 3.4964673 | E17: =$B17*C17/($C17+$D17) -> 4.0006564 | F17: =$B17*D17/($C17+$D17) -> 3.5574436 | G17: 319.97505 | H17: 42.335382 | I17: 2.7 | J17: 2.9902623 | K17: 112.17007 | L17: 47.9 | T17: 2020 | Y17: ='Private,Public8EndUse'!S20 -> 32856 | Z17: =Y17/C17 -> 8355.8759 | AA17: ='Private,Public8EndUse'!AC20 -> 18119 | AB17: =AA17/D17 -> 5182.0876 | AC17: =Commercial8EndUse!Q21 -> 114512 | AD17: =AD16 -> 2.5509953 | AF17: 63846.351 | AG17: 130491.82 | AH17: =I17*$W$16*1000 -> 66136.815 | AI17: =L17*$AD$16*1000 -> 122192.68 | AJ17: =(AI17-AG17)/AG17 -> -0.063598941 | AL17: =Y17 -> 32856 | AM17: =AA17 -> 18119 | AN17: =SUM(AL17:AM17) -> 50975 | AO17: =AI17 -> 122192.68 | AU17: gdp | AV17: HK$ million | BC17: HK$ | BD17: US$ | BE17: US$ billion | BI17: US$ | BJ17: US$ k
A18: 2021 | B18: =BO18 -> 7.3895 | C18: =TREND($C$49:$C$50,$A$49:$A$50,$A18) -> 3.9136582 | D18: =TREND($D$49:$D$50,$A$49:$A$50,$A18) -> 3.5488849 | E18: =$B18*C18/($C18+$D18) -> 3.8753514 | F18: =$B18*D18/($C18+$D18) -> 3.5141486 | G18: =BE18 -> 367.68885 | H18: =BJ18 -> 49.599872 | I18: 2.7 | J18: 2.977459 | K18: 112.80694 | L18: 48.27 | T18: 2021 | Y18: ='Private,Public8EndUse'!S21 -> 32236 | Z18: =Y18/C18 -> 8236.7949 | AA18: ='Private,Public8EndUse'!AC21 -> 18298 | AB18: =AA18/D18 -> 5155.9857 | AC18: =Commercial8EndUse!Q22 -> 120083 | AD18: =AD17 -> 2.5509953 | AF18: 64283.85 | AG18: 132413.99 | AH18: =I18*$W$16*1000 -> 66136.815 | AI18: =L18*$AD$16*1000 -> 123136.55 | AJ18: =(AI18-AG18)/AG18 -> -0.070063958 | AL18: =Y18 -> 32236 | AM18: =AA18 -> 18298 | AN18: =SUM(AL18:AM18) -> 50534 | AO18: =AI18 -> 123136.55 | AU18: 2021 | AV18: 2867973 | AW18: =(AV19-AV18)/AV18 -> -0.036807529 | AX18: 386879 | AY18: 7389500 | BC18: =AV18*1000000 -> 2867973000000 | BD18: =BC18/7.8 -> 3.6768885e+11 | BE18: =BD18/1000000000 -> 367.68885 | BI18: =AX18/7.8 -> 49599.872 | BJ18: =BI18/1000 -> 49.599872 | BO18: =AY18/1000000 -> 7.3895
A19: 2022 | B19: =BO19 -> 7.4375 | C19: =TREND($C$49:$C$50,$A$49:$A$50,$A19) -> 3.8952331 | D19: =TREND($D$49:$D$50,$A$49:$A$50,$A19) -> 3.6013026 | E19: =$B19*C19/($C19+$D19) -> 3.8645579 | F19: =$B19*D19/($C19+$D19) -> 3.5729421 | G19: =BE19 -> 354.15513 | H19: =BJ19 -> 48.21 | I19: 2.7 | J19: 2.9646557 | K19: 113.44381 | L19: 48.64 | T19: 2022 | Y19: =Z19*E19 -> 32254.931 | Z19: =Z18*(1+0.0133) -> 8346.3443 | AA19: =AB19*F19 -> 18667.051 | AB19: =AB18*(1+0.0133) -> 5224.5603 | AC19: =AC18*(1+0.0133) -> 121680.1 | AD19: =AD18 -> 2.5509953 | AF19: 64690.115 | AG19: 134424.15 | AH19: =I19*$W$16*1000 -> 66136.815 | AI19: =L19*$AD$16*1000 -> 124080.41 | AJ19: =(AI19-AG19)/AG19 -> -0.076948509 | AL19: =Y19 -> 32254.931 | AM19: =AA19 -> 18667.051 | AN19: =SUM(AL19:AM19) -> 50921.982 | AO19: =AI19 -> 124080.41 | AU19: 2022 | AV19: 2762410 | AW19: =(AV20-AV19)/AV19 -> 0.03215055 | AX19: 376038 | AY19: 7437500 | BC19: =AV19*1000000 -> 2762410000000 | BD19: =BC19/7.8 -> 3.5415513e+11 | BE19: =BD19/1000000000 -> 354.15513 | BI19: =AX19/7.8 -> 48210 | BJ19: =BI19/1000 -> 48.21 | BO19: =AY19/1000000 -> 7.4375
A20: 2023 | B20: =BO20 -> 7.4847 | C20: =TREND($C$49:$C$50,$A$49:$A$50,$A20) -> 3.876808 | D20: =TREND($D$49:$D$50,$A$49:$A$50,$A20) -> 3.6537202 | E20: =$B20*C20/($C20+$D20) -> 3.8532151 | F20: =$B20*D20/($C20+$D20) -> 3.6314849 | G20: =BE20 -> 365.54141 | H20: =BJ20 -> 48.505385 | I20: 2.7 | J20: 2.9518525 | K20: 114.08068 | L20: 49.01 | T20: 2023 | Y20: =Z20*E20 -> 32587.991 | Z20: =Z19*(1+0.0133) -> 8457.3507 | AA20: =AB20*F20 -> 19225.252 | AB20: =AB19*(1+0.0133) -> 5294.047 | AC20: =AC19*(1+0.0133) -> 123298.45 | AD20: =AD19 -> 2.5509953 | AF20: 65064.348 | AG20: 136522.29 | AH20: =I20*$W$16*1000 -> 66136.815 | AI20: =L20*$AD$16*1000 -> 125024.28 | AJ20: =(AI20-AG20)/AG20 -> -0.084220751 | AL20: =Y20 -> 32587.991 | AM20: =AA20 -> 19225.252 | AN20: =SUM(AL20:AM20) -> 51813.243 | AO20: =AI20 -> 125024.28 | AU20: 2023 | AV20: 2851223 | AW20: =(AV21-AV20)/AV20 -> 0.035 | AX20: 378342 | AY20: 7484700 | BC20: =AV20*1000000 -> 2851223000000 | BD20: =BC20/7.8 -> 3.6554141e+11 | BE20: =BD20/1000000000 -> 365.54141 | BI20: =AX20/7.8 -> 48505.385 | BJ20: =BI20/1000 -> 48.505385 | BO20: =AY20/1000000 -> 7.4847
A21: 2024 | B21: =BO21 -> 7.5268 | C21: =TREND($C$49:$C$50,$A$49:$A$50,$A21) -> 3.8583829 | D21: =TREND($D$49:$D$50,$A$49:$A$50,$A21) -> 3.7061378 | E21: =$B21*C21/($C21+$D21) -> 3.839143 | F21: =$B21*D21/($C21+$D21) -> 3.687657 | G21: =BE21 -> 378.33536 | H21: =BJ21 -> 50.265101 | I21: 2.7 | J21: 2.9390492 | K21: 114.71756 | L21: 49.38 | T21: 2024 | Y21: =Z21*E21 -> 32900.816 | Z21: =Z20*(1+0.0133) -> 8569.8335 | AA21: =AB21*F21 -> 19782.28 | AB21: =AB20*(1+0.0133) -> 5364.4578 | AC21: =AC20*(1+0.0133) -> 124938.32 | AD21: =AD20 -> 2.5509953 | AF21: 65555.531 | AG21: 138708.41 | AH21: =I21*$W$16*1000 -> 66136.815 | AI21: =L21*$AD$16*1000 -> 125968.15 | AJ21: =(AI21-AG21)/AG21 -> -0.091849254 | AL21: =Y21 -> 32900.816 | AM21: =AA21 -> 19782.28 | AN21: =SUM(AL21:AM21) -> 52683.096 | AO21: =AI21 -> 125968.15 | AU21: 2024 | AV21: =AV20*(1+0.035) -> 2951015.8 | AW21: 0.03 | AX21: =AV21*1000000/AY21 -> 392067.79 | AY21: 7526800 | BC21: =AV21*1000000 -> 2.9510158e+12 | BD21: =BC21/7.8 -> 3.7833536e+11 | BE21: =BD21/1000000000 -> 378.33536 | BI21: =AX21/7.8 -> 50265.101 | BJ21: =BI21/1000 -> 50.265101 | BO21: =AY21/1000000 -> 7.5268
A22: 2025 | B22: =BO22 -> 7.5598 | C22: =TREND($C$49:$C$50,$A$49:$A$50,$A22) -> 3.8399579 | D22: =TREND($D$49:$D$50,$A$49:$A$50,$A22) -> 3.7585555 | E22: =$B22*C22/($C22+$D22) -> 3.8203938 | F22: =$B22*D22/($C22+$D22) -> 3.7394062 | G22: =BE22 -> 389.68542 | H22: =BJ22 -> 51.547054 | I22: 2.7 | J22: 2.9262459 | K22: 115.35443 | L22: 49.75 | T22: 2025 | Y22: =Z22*E22 -> 33175.583 | Z22: =Z21*(1+0.0133) -> 8683.8123 | AA22: =AB22*F22 -> 20326.683 | AB22: =AB21*(1+0.0133) -> 5435.8051 | AC22: =AC21*(1+0.0133) -> 126600 | AD22: =AD21 -> 2.5509953 | AF22: 65947.365 | AG22: 140982.52 | AH22: =I22*$W$16*1000 -> 66136.815 | AI22: =L22*$AD$16*1000 -> 126912.02 | AJ22: =(AI22-AG22)/AG22 -> -0.099803161 | AL22: =Y22 -> 33175.583 | AM22: =AA22 -> 20326.683 | AN22: =SUM(AL22:AM22) -> 53502.266 | AO22: =AI22 -> 126912.02 | AU22: 2025 | AV22: =AV21*(1+AW21) -> 3039546.3 | AW22: 0.03 | AX22: =AV22*1000000/AY22 -> 402067.02 | AY22: 7559800 | BC22: =AV22*1000000 -> 3039546279150 | BD22: =BC22/7.8 -> 3.8968542e+11 | BE22: =BD22/1000000000 -> 389.68542 | BI22: =AX22/7.8 -> 51547.054 | BJ22: =BI22/1000 -> 51.547054 | BO22: =AY22/1000000 -> 7.5598
A23: 2026 | B23: =BO23 -> 7.5968 | C23: =TREND($C$49:$C$50,$A$49:$A$50,$A23) -> 3.8215328 | D23: =TREND($D$49:$D$50,$A$49:$A$50,$A23) -> 3.8109731 | E23: =$B23*C23/($C23+$D23) -> 3.8036551 | F23: =$B23*D23/($C23+$D23) -> 3.7931449 | G23: =BE23 -> 401.37598 | H23: =BJ23 -> 52.834876 | I23: 2.7 | J23: 2.9134426 | K23: 115.9913 | L23: 50.12 | T23: 2026 | Y23: =Z23*E23 -> 33469.529 | Z23: =Z22*(1+0.0133) -> 8799.307 | AA23: =AB23*F23 -> 20893.026 | AB23: =AB22*(1+0.0133) -> 5508.1013 | AC23: =AC22*(1+0.0133) -> 128283.78 | AD23: =AD22 -> 2.5509953 | AF23: 66341.945 | AG23: 143344.61 | AH23: =I23*$W$16*1000 -> 66136.815 | AI23: =L23*$AD$16*1000 -> 127855.89 | AJ23: =(AI23-AG23)/AG23 -> -0.10805234 | AL23: =Y23 -> 33469.529 | AM23: =AA23 -> 20893.026 | AN23: =SUM(AL23:AM23) -> 54362.555 | AO23: =AI23 -> 127855.89 | AU23: 2026 | AV23: =AV22*(1+AW22) -> 3130732.7 | AW23: 0.025 | AX23: =AV23*1000000/AY23 -> 412112.03 | AY23: 7596800 | BC23: =AV23*1000000 -> 3.1307327e+12 | BD23: =BC23/7.8 -> 4.0137598e+11 | BE23: =BD23/1000000000 -> 401.37598 | BI23: =AX23/7.8 -> 52834.876 | BJ23: =BI23/1000 -> 52.834876 | BO23: =AY23/1000000 -> 7.5968
A24: 2027 | B24: =BO24 -> 7.6387 | C24: =TREND($C$49:$C$50,$A$49:$A$50,$A24) -> 3.8031077 | D24: =TREND($D$49:$D$50,$A$49:$A$50,$A24) -> 3.8633907 | E24: =$B24*C24/($C24+$D24) -> 3.7893178 | F24: =$B24*D24/($C24+$D24) -> 3.8493822 | G24: =BE24 -> 411.41038 | H24: =BJ24 -> 53.858691 | I24: 2.7 | J24: 2.9006393 | K24: 116.62817 | L24: 50.49 | T24: 2027 | Y24: =Z24*E24 -> 33786.837 | Z24: =Z23*(1+0.0133) -> 8916.3377 | AA24: =AB24*F24 -> 21484.784 | AB24: =AB23*(1+0.0133) -> 5581.359 | AC24: =AC23*(1+0.0133) -> 129989.95 | AD24: =AD23 -> 2.5509953 | AF24: 66743.783 | AG24: 145794.68 | AH24: =I24*$W$16*1000 -> 66136.815 | AI24: =L24*$AD$16*1000 -> 128799.75 | AJ24: =(AI24-AG24)/AG24 -> -0.1165675 | AL24: =Y24 -> 33786.837 | AM24: =AA24 -> 21484.784 | AN24: =SUM(AL24:AM24) -> 55271.621 | AO24: =AI24 -> 128799.75 | AU24: 2027 | AV24: =AV23*(1+AW23) -> 3209001 | AW24: 0.025 | AX24: =AV24*1000000/AY24 -> 420097.79 | AY24: 7638700 | BC24: =AV24*1000000 -> 3.209001e+12 | BD24: =BC24/7.8 -> 4.1141038e+11 | BE24: =BD24/1000000000 -> 411.41038 | BI24: =AX24/7.8 -> 53858.691 | BJ24: =BI24/1000 -> 53.858691 | BO24: =AY24/1000000 -> 7.6387
A25: 2028 | B25: =BO25 -> 7.6845 | C25: =TREND($C$49:$C$50,$A$49:$A$50,$A25) -> 3.7846826 | D25: =TREND($D$49:$D$50,$A$49:$A$50,$A25) -> 3.9158084 | E25: =$B25*C25/($C25+$D25) -> 3.7768233 | F25: =$B25*D25/($C25+$D25) -> 3.9076767 | G25: =BE25 -> 421.69564 | H25: =BJ25 -> 54.876133 | I25: 2.7 | J25: 2.8878361 | K25: 117.26504 | L25: 50.86 | T25: 2028 | Y25: =Z25*E25 -> 34123.315 | Z25: =Z24*(1+0.0133) -> 9034.925 | AA25: =AB25*F25 -> 22100.222 | AB25: =AB24*(1+0.0133) -> 5655.5911 | AC25: =AC24*(1+0.0133) -> 131718.82 | AD25: =AD24 -> 2.5509953 | AF25: 67147.727 | AG25: 148332.73 | AH25: =I25*$W$16*1000 -> 66136.815 | AI25: =L25*$AD$16*1000 -> 129743.62 | AJ25: =(AI25-AG25)/AG25 -> -0.12532032 | AL25: =Y25 -> 34123.315 | AM25: =AA25 -> 22100.222 | AN25: =SUM(AL25:AM25) -> 56223.537 | AO25: =AI25 -> 129743.62 | AU25: 2028 | AV25: =AV24*(1+AW24) -> 3289226 | AW25: 0.025 | AX25: =AV25*1000000/AY25 -> 428033.84 | AY25: 7684500 | BC25: =AV25*1000000 -> 3.289226e+12 | BD25: =BC25/7.8 -> 4.2169564e+11 | BE25: =BD25/1000000000 -> 421.69564 | BI25: =AX25/7.8 -> 54876.133 | BJ25: =BI25/1000 -> 54.876133 | BO25: =AY25/1000000 -> 7.6845
A26: 2029 | B26: =BO26 -> 7.7311 | C26: =TREND($C$49:$C$50,$A$49:$A$50,$A26) -> 3.7662575 | D26: =TREND($D$49:$D$50,$A$49:$A$50,$A26) -> 3.968226 | E26: =$B26*C26/($C26+$D26) -> 3.7646099 | F26: =$B26*D26/($C26+$D26) -> 3.9664901 | G26: =BE26 -> 432.23803 | H26: =BJ26 -> 55.908995 | I26: 2.7 | J26: 2.8750328 | K26: 117.90192 | L26: 51.23 | T26: 2029 | Y26: =Z26*E26 -> 34465.341 | Z26: =Z25*(1+0.0133) -> 9155.0895 | AA26: =AB26*F26 -> 22731.203 | AB26: =AB25*(1+0.0133) -> 5730.8105 | AC26: =AC25*(1+0.0133) -> 133470.68 | AD26: =AD25 -> 2.5509953 | AF26: 67545.656 | AG26: 150958.76 | AH26: =I26*$W$16*1000 -> 66136.815 | AI26: =L26*$AD$16*1000 -> 130687.49 | AJ26: =(AI26-AG26)/AG26 -> -0.13428351 | AL26: =Y26 -> 34465.341 | AM26: =AA26 -> 22731.203 | AN26: =SUM(AL26:AM26) -> 57196.544 | AO26: =AI26 -> 130687.49 | AU26: 2029 | AV26: =AV25*(1+AW25) -> 3371456.7 | AW26: 0.025 | AX26: =AV26*1000000/AY26 -> 436090.16 | AY26: 7731100 | BC26: =AV26*1000000 -> 3.3714567e+12 | BD26: =BC26/7.8 -> 4.3223803e+11 | BE26: =BD26/1000000000 -> 432.23803 | BI26: =AX26/7.8 -> 55908.995 | BJ26: =BI26/1000 -> 55.908995 | BO26: =AY26/1000000 -> 7.7311
A27: 2030 | B27: =BO27 -> 7.7771 | C27: =TREND($C$49:$C$50,$A$49:$A$50,$A27) -> 3.7478324 | D27: =TREND($D$49:$D$50,$A$49:$A$50,$A27) -> 4.0206436 | E27: =$B27*C27/($C27+$D27) -> 3.751993 | F27: =$B27*D27/($C27+$D27) -> 4.025107 | G27: =BE27 -> 443.04398 | H27: =BJ27 -> 56.967762 | I27: 2.7 | J27: 2.8622295 | K27: 118.53879 | L27: 51.6 | T27: 2030 | Y27: =Z27*E27 -> 34806.685 | Z27: =Z26*(1+0.0133) -> 9276.8522 | AA27: =AB27*F27 -> 23373.918 | AB27: =AB26*(1+0.0133) -> 5807.0302 | AC27: =AC26*(1+0.0133) -> 135245.84 | AD27: =AD26 -> 2.5509953 | AF27: 67916.939 | AG27: 153672.78 | AH27: =I27*$W$16*1000 -> 66136.815 | AI27: =L27*$AD$16*1000 -> 131631.36 | AJ27: =(AI27-AG27)/AG27 -> -0.14343087 | AL27: =Y27 -> 34806.685 | AM27: =AA27 -> 23373.918 | AN27: =SUM(AL27:AM27) -> 58180.603 | AO27: =AI27 -> 131631.36 | AU27: 2030 | AV27: =AV26*(1+AW26) -> 3455743.1 | AW27: 0.025 | AX27: =AV27*1000000/AY27 -> 444348.55 | AY27: 7777100 | BC27: =AV27*1000000 -> 3.4557431e+12 | BD27: =BC27/7.8 -> 4.4304398e+11 | BE27: =BD27/1000000000 -> 443.04398 | BI27: =AX27/7.8 -> 56967.762 | BJ27: =BI27/1000 -> 56.967762 | BO27: =AY27/1000000 -> 7.7771
A28: 2031 | B28: =BO28 -> 7.8202 | C28: =TREND($C$49:$C$50,$A$49:$A$50,$A28) -> 3.7294074 | D28: =TREND($D$49:$D$50,$A$49:$A$50,$A28) -> 4.0730612 | E28: =$B28*C28/($C28+$D28) -> 3.7378826 | F28: =$B28*D28/($C28+$D28) -> 4.0823174 | G28: =BE28 -> 454.12008 | H28: =BJ28 -> 58.070137 | I28: 2.6 | J28: 2.8494262 | K28: 119.17566 | L28: 51.97 | T28: 2031 | Y28: =Z28*E28 -> 35136.972 | Z28: =Z27*(1+0.0133) -> 9400.2344 | AA28: =AB28*F28 -> 24021.432 | AB28: =AB27*(1+0.0133) -> 5884.2637 | AC28: =AC27*(1+0.0133) -> 137044.61 | AD28: =AD27 -> 2.5509953 | AF28: 68301.447 | AG28: 156474.78 | AH28: =I28*$W$16*1000 -> 63687.303 | AI28: =L28*$AD$16*1000 -> 132575.23 | AJ28: =(AI28-AG28)/AG28 -> -0.1527374 | AL28: =Y28 -> 35136.972 | AM28: =AA28 -> 24021.432 | AN28: =SUM(AL28:AM28) -> 59158.405 | AO28: =AI28 -> 132575.23 | AU28: 2031 | AV28: =AV27*(1+AW27) -> 3542136.7 | AW28: 0.025 | AX28: =AV28*1000000/AY28 -> 452947.07 | AY28: 7820200 | BC28: =AV28*1000000 -> 3.5421367e+12 | BD28: =BC28/7.8 -> 4.5412008e+11 | BE28: =BD28/1000000000 -> 454.12008 | BI28: =AX28/7.8 -> 58070.137 | BJ28: =BI28/1000 -> 58.070137 | BO28: =AY28/1000000 -> 7.8202
A29: 2032 | B29: =BO29 -> 7.8621 | C29: =TREND($C$49:$C$50,$A$49:$A$50,$A29) -> 3.7109823 | D29: =TREND($D$49:$D$50,$A$49:$A$50,$A29) -> 4.1254789 | E29: =$B29*C29/($C29+$D29) -> 3.7231236 | F29: =$B29*D29/($C29+$D29) -> 4.1389764 | G29: =BE29 -> 465.47309 | H29: =BJ29 -> 59.204676 | I29: 2.6 | J29: 2.836623 | K29: 119.81253 | L29: 52.34 | T29: 2032 | Y29: =Z29*E29 -> 35463.711 | Z29: =Z28*(1+0.0133) -> 9525.2575 | AA29: =AB29*F29 -> 24678.748 | AB29: =AB28*(1+0.0133) -> 5962.5244 | AC29: =AC28*(1+0.0133) -> 138867.3 | AD29: =AD28 -> 2.5509953 | AF29: 68678.991 | AG29: 159364.76 | AH29: =I29*$W$16*1000 -> 63687.303 | AI29: =L29*$AD$16*1000 -> 133519.1 | AJ29: =(AI29-AG29)/AG29 -> -0.1621793 | AL29: =Y29 -> 35463.711 | AM29: =AA29 -> 24678.748 | AN29: =SUM(AL29:AM29) -> 60142.459 | AO29: =AI29 -> 133519.1 | AU29: 2032 | AV29: =AV28*(1+AW28) -> 3630690.1 | AW29: 0.025 | AX29: =AV29*1000000/AY29 -> 461796.48 | AY29: 7862100 | BC29: =AV29*1000000 -> 3.6306901e+12 | BD29: =BC29/7.8 -> 4.6547309e+11 | BE29: =BD29/1000000000 -> 465.47309 | BI29: =AX29/7.8 -> 59204.676 | BJ29: =BI29/1000 -> 59.204676 | BO29: =AY29/1000000 -> 7.8621
A30: 2033 | B30: =BO30 -> 7.9036 | C30: =TREND($C$49:$C$50,$A$49:$A$50,$A30) -> 3.6925572 | D30: =TREND($D$49:$D$50,$A$49:$A$50,$A30) -> 4.1778965 | E30: =$B30*C30/($C30+$D30) -> 3.7081084 | F30: =$B30*D30/($C30+$D30) -> 4.1954916 | G30: =BE30 -> 477.10991 | H30: =BJ30 -> 60.366151 | I30: 2.6 | J30: 2.8238197 | K30: 120.44941 | L30: 52.71 | T30: 2033 | Y30: =Z30*E30 -> 35790.452 | Z30: =Z29*(1+0.0133) -> 9651.9434 | AA30: =AB30*F30 -> 25348.431 | AB30: =AB29*(1+0.0133) -> 6041.826 | AC30: =AC29*(1+0.0133) -> 140714.24 | AD30: =AD29 -> 2.5509953 | AF30: 69047.855 | AG30: 162342.73 | AH30: =I30*$W$16*1000 -> 63687.303 | AI30: =L30*$AD$16*1000 -> 134462.96 | AJ30: =(AI30-AG30)/AG30 -> -0.17173397 | AL30: =Y30 -> 35790.452 | AM30: =AA30 -> 25348.431 | AN30: =SUM(AL30:AM30) -> 61138.883 | AO30: =AI30 -> 134462.96 | AU30: 2033 | AV30: =AV29*(1+AW29) -> 3721457.3 | AW30: 0.025 | AX30: =AV30*1000000/AY30 -> 470855.98 | AY30: 7903600 | BC30: =AV30*1000000 -> 3.7214573e+12 | BD30: =BC30/7.8 -> 4.7710991e+11 | BE30: =BD30/1000000000 -> 477.10991 | BI30: =AX30/7.8 -> 60366.151 | BJ30: =BI30/1000 -> 60.366151 | BO30: =AY30/1000000 -> 7.9036
A31: 2034 | B31: =BO31 -> 7.9451 | C31: =TREND($C$49:$C$50,$A$49:$A$50,$A31) -> 3.6741321 | D31: =TREND($D$49:$D$50,$A$49:$A$50,$A31) -> 4.2303141 | E31: =$B31*C31/($C31+$D31) -> 3.6930287 | F31: =$B31*D31/($C31+$D31) -> 4.2520713 | G31: =BE31 -> 489.03766 | H31: =BJ31 -> 61.552109 | I31: 2.6 | J31: 2.8110164 | K31: 121.08628 | L31: 53.08 | T31: 2034 | Y31: =Z31*E31 -> 36118.982 | Z31: =Z30*(1+0.0133) -> 9780.3142 | AA31: =AB31*F31 -> 26031.955 | AB31: =AB30*(1+0.0133) -> 6122.1823 | AC31: =AC30*(1+0.0133) -> 142585.74 | AD31: =AD30 -> 2.5509953 | AF31: 69409.534 | AG31: 165408.67 | AH31: =I31*$W$16*1000 -> 63687.303 | AI31: =L31*$AD$16*1000 -> 135406.83 | AJ31: =(AI31-AG31)/AG31 -> -0.18138009 | AL31: =Y31 -> 36118.982 | AM31: =AA31 -> 26031.955 | AN31: =SUM(AL31:AM31) -> 62150.937 | AO31: =AI31 -> 135406.83 | AU31: 2034 | AV31: =AV30*(1+AW30) -> 3814493.8 | AW31: 0.025 | AX31: =AV31*1000000/AY31 -> 480106.45 | AY31: 7945100 | BC31: =AV31*1000000 -> 3.8144938e+12 | BD31: =BC31/7.8 -> 4.8903766e+11 | BE31: =BD31/1000000000 -> 489.03766 | BI31: =AX31/7.8 -> 61552.109 | BJ31: =BI31/1000 -> 61.552109 | BO31: =AY31/1000000 -> 7.9451
