Workbook

Sheet About
A1: DSCF Distributed Solar Capacity Factor
A3: Source: | B3: NREL
B4: 2021, 2022
B5: Annual Technology Baseline 2021, Annual Technology Baseline 2022
B6: https://atb.nrel.gov/
B7: "Solar - PV Dist. Res" tab
A9: Notes
A10: We use the ATB "Moderate" case
J14: Source (Hong Kong)
J15: 2014
J16: Solar Energy – New Development and Future Trend by Prof. Yang Hongxing
J17: http://www.energyinst.org.hk/Activity/ICE2014/2.2%20Prof%20Hongxing%20YANG.pdf
J18: Slide 33
A22: Note by Wing 300823
A23: Added J19:J23 and put 12.9% on sheet DSCF.

Sheet Solar - PV Dist. Res 2021
D1: X | G1: Future Projections
L2: Basis Year
L3: 2019 | M3: 2020 | N3: 2021 | O3: 2022 | P3: 2023 | Q3: 2024 | R3: 2025 | S3: 2026 | T3: 2027 | U3: 2028 | V3: 2029 | W3: 2030 | X3: 2031 | Y3: 2032 | Z3: 2033 | AA3: 2034 | AB3: 2035 | AC3: 2036 | AD3: 2037 | AE3: 2038 | AF3: 2039 | AG3: 2040 | AH3: 2041 | AI3: 2042 | AJ3: 2043 | AK3: 2044 | AL3: 2045 | AM3: 2046 | AN3: 2047 | AO3: 2048 | AP3: 2049 | AQ3: 2050
H4: Techno-Economic Cost and Performance Parameters | J4: Net Capacity Factor (%) | K4: Residential PV - Class 10 - Advanced | L4: 0.11966056 | M4: 0.12013139 | N4: 0.12060223 | O4: 0.12107307 | P4: 0.1215439 | Q4: 0.12201474 | R4: 0.12248557 | S4: 0.12295641 | T4: 0.12342725 | U4: 0.12389808 | V4: 0.12436892 | W4: 0.12483975 | X4: 0.12483975 | Y4: 0.12483975 | Z4: 0.12483975 | AA4: 0.12483975 | AB4: 0.12483975 | AC4: 0.12483975 | AD4: 0.12483975 | AE4: 0.12483975 | AF4: 0.12483975 | AG4: 0.12483975 | AH4: 0.12483975 | AI4: 0.12483975 | AJ4: 0.12483975 | AK4: 0.12483975 | AL4: 0.12483975 | AM4: 0.12483975 | AN4: 0.12483975 | AO4: 0.12483975 | AP4: 0.12483975 | AQ4: 0.12483975
K5: Residential PV - Class 10 - Moderate | L5: 0.11966056 | M5: 0.11984569 | N5: 0.12003083 | O5: 0.12021596 | P5: 0.1204011 | Q5: 0.12058623 | R5: 0.12077137 | S5: 0.12095651 | T5: 0.12114164 | U5: 0.12132678 | V5: 0.12151191 | W5: 0.12169705 | X5: 0.12185418 | Y5: 0.12201132 | Z5: 0.12216845 | AA5: 0.12232559 | AB5: 0.12248272 | AC5: 0.12263986 | AD5: 0.12279699 | AE5: 0.12295413 | AF5: 0.12311126 | AG5: 0.1232684 | AH5: 0.12342554 | AI5: 0.12358267 | AJ5: 0.12373981 | AK5: 0.12389694 | AL5: 0.12405408 | AM5: 0.12421121 | AN5: 0.12436835 | AO5: 0.12452548 | AP5: 0.12468262 | AQ5: 0.12483975
K6: Residential PV - Class 10 - Conservative | L6: 0.11966056 | M6: 0.11966056 | N6: 0.11966056 | O6: 0.11966056 | P6: 0.11966056 | Q6: 0.11966056 | R6: 0.11966056 | S6: 0.11966056 | T6: 0.11966056 | U6: 0.11966056 | V6: 0.11966056 | W6: 0.11966056 | X6: 0.11976238 | Y6: 0.11986421 | Z6: 0.11996603 | AA6: 0.12006786 | AB6: 0.12016968 | AC6: 0.1202715 | AD6: 0.12037333 | AE6: 0.12047515 | AF6: 0.12057698 | AG6: 0.1206788 | AH6: 0.12078063 | AI6: 0.12088245 | AJ6: 0.12098428 | AK6: 0.1210861 | AL6: 0.12118792 | AM6: 0.12128975 | AN6: 0.12139157 | AO6: 0.1214934 | AP6: 0.12159522 | AQ6: 0.12169705
K7: Residential PV - Class 9 - Advanced | L7: 0.13106905 | M7: 0.13158478 | N7: 0.13210051 | O7: 0.13261623 | P7: 0.13313196 | Q7: 0.13364768 | R7: 0.13416341 | S7: 0.13467913 | T7: 0.13519486 | U7: 0.13571059 | V7: 0.13622631 | W7: 0.13674204 | X7: 0.13674204 | Y7: 0.13674204 | Z7: 0.13674204 | AA7: 0.13674204 | AB7: 0.13674204 | AC7: 0.13674204 | AD7: 0.13674204 | AE7: 0.13674204 | AF7: 0.13674204 | AG7: 0.13674204 | AH7: 0.13674204 | AI7: 0.13674204 | AJ7: 0.13674204 | AK7: 0.13674204 | AL7: 0.13674204 | AM7: 0.13674204 | AN7: 0.13674204 | AO7: 0.13674204 | AP7: 0.13674204 | AQ7: 0.13674204
K8: Residential PV - Class 9 - Moderate | L8: 0.13106905 | M8: 0.13127184 | N8: 0.13147463 | O8: 0.13167741 | P8: 0.1318802 | Q8: 0.13208299 | R8: 0.13228577 | S8: 0.13248856 | T8: 0.13269134 | U8: 0.13289413 | V8: 0.13309692 | W8: 0.1332997 | X8: 0.13347182 | Y8: 0.13364394 | Z8: 0.13381605 | AA8: 0.13398817 | AB8: 0.13416029 | AC8: 0.1343324 | AD8: 0.13450452 | AE8: 0.13467664 | AF8: 0.13484875 | AG8: 0.13502087 | AH8: 0.13519299 | AI8: 0.1353651 | AJ8: 0.13553722 | AK8: 0.13570934 | AL8: 0.13588145 | AM8: 0.13605357 | AN8: 0.13622569 | AO8: 0.1363978 | AP8: 0.13656992 | AQ8: 0.13674204
K9: Residential PV - Class 9 - Conservative | L9: 0.13106905 | M9: 0.13106905 | N9: 0.13106905 | O9: 0.13106905 | P9: 0.13106905 | Q9: 0.13106905 | R9: 0.13106905 | S9: 0.13106905 | T9: 0.13106905 | U9: 0.13106905 | V9: 0.13106905 | W9: 0.13106905 | X9: 0.13118059 | Y9: 0.13129212 | Z9: 0.13140365 | AA9: 0.13151518 | AB9: 0.13162672 | AC9: 0.13173825 | AD9: 0.13184978 | AE9: 0.13196131 | AF9: 0.13207285 | AG9: 0.13218438 | AH9: 0.13229591 | AI9: 0.13240744 | AJ9: 0.13251898 | AK9: 0.13263051 | AL9: 0.13274204 | AM9: 0.13285357 | AN9: 0.13296511 | AO9: 0.13307664 | AP9: 0.13318817 | AQ9: 0.1332997
K10: Residential PV - Class 8 - Advanced | L10: 0.1365026 | M10: 0.13703971 | N10: 0.13757681 | O10: 0.13811392 | P10: 0.13865103 | Q10: 0.13918813 | R10: 0.13972524 | S10: 0.14026234 | T10: 0.14079945 | U10: 0.14133655 | V10: 0.14187366 | W10: 0.14241076 | X10: 0.14241076 | Y10: 0.14241076 | Z10: 0.14241076 | AA10: 0.14241076 | AB10: 0.14241076 | AC10: 0.14241076 | AD10: 0.14241076 | AE10: 0.14241076 | AF10: 0.14241076 | AG10: 0.14241076 | AH10: 0.14241076 | AI10: 0.14241076 | AJ10: 0.14241076 | AK10: 0.14241076 | AL10: 0.14241076 | AM10: 0.14241076 | AN10: 0.14241076 | AO10: 0.14241076 | AP10: 0.14241076 | AQ10: 0.14241076
K11: Residential PV - Class 8 - Moderate | L11: 0.1365026 | M11: 0.1367138 | N11: 0.13692499 | O11: 0.13713618 | P11: 0.13734738 | Q11: 0.13755857 | R11: 0.13776976 | S11: 0.13798095 | T11: 0.13819215 | U11: 0.13840334 | V11: 0.13861453 | W11: 0.13882573 | X11: 0.13900498 | Y11: 0.13918423 | Z11: 0.13936348 | AA11: 0.13954273 | AB11: 0.13972198 | AC11: 0.13990124 | AD11: 0.14008049 | AE11: 0.14025974 | AF11: 0.14043899 | AG11: 0.14061824 | AH11: 0.1407975 | AI11: 0.14097675 | AJ11: 0.141156 | AK11: 0.14133525 | AL11: 0.1415145 | AM11: 0.14169376 | AN11: 0.14187301 | AO11: 0.14205226 | AP11: 0.14223151 | AQ11: 0.14241076
K12: Residential PV - Class 8 - Conservative | L12: 0.1365026 | M12: 0.1365026 | N12: 0.1365026 | O12: 0.1365026 | P12: 0.1365026 | Q12: 0.1365026 | R12: 0.1365026 | S12: 0.1365026 | T12: 0.1365026 | U12: 0.1365026 | V12: 0.1365026 | W12: 0.1365026 | X12: 0.13661876 | Y12: 0.13673492 | Z12: 0.13685107 | AA12: 0.13696723 | AB12: 0.13708338 | AC12: 0.13719954 | AD12: 0.1373157 | AE12: 0.13743185 | AF12: 0.13754801 | AG12: 0.13766416 | AH12: 0.13778032 | AI12: 0.13789648 | AJ12: 0.13801263 | AK12: 0.13812879 | AL12: 0.13824494 | AM12: 0.1383611 | AN12: 0.13847726 | AO12: 0.13859341 | AP12: 0.13870957 | AQ12: 0.13882573
K13: Residential PV - Class 7 - Advanced | L13: 0.14329455 | M13: 0.14385838 | N13: 0.14442221 | O13: 0.14498604 | P13: 0.14554987 | Q13: 0.1461137 | R13: 0.14667753 | S13: 0.14724136 | T13: 0.14780519 | U13: 0.14836902 | V13: 0.14893285 | W13: 0.14949668 | X13: 0.14949668 | Y13: 0.14949668 | Z13: 0.14949668 | AA13: 0.14949668 | AB13: 0.14949668 | AC13: 0.14949668 | AD13: 0.14949668 | AE13: 0.14949668 | AF13: 0.14949668 | AG13: 0.14949668 | AH13: 0.14949668 | AI13: 0.14949668 | AJ13: 0.14949668 | AK13: 0.14949668 | AL13: 0.14949668 | AM13: 0.14949668 | AN13: 0.14949668 | AO13: 0.14949668 | AP13: 0.14949668 | AQ13: 0.14949668
K14: Residential PV - Class 7 - Moderate | L14: 0.14329455 | M14: 0.14351625 | N14: 0.14373795 | O14: 0.14395965 | P14: 0.14418135 | Q14: 0.14440305 | R14: 0.14462475 | S14: 0.14484645 | T14: 0.14506816 | U14: 0.14528986 | V14: 0.14551156 | W14: 0.14573326 | X14: 0.14592143 | Y14: 0.1461096 | Z14: 0.14629777 | AA14: 0.14648594 | AB14: 0.14667411 | AC14: 0.14686229 | AD14: 0.14705046 | AE14: 0.14723863 | AF14: 0.1474268 | AG14: 0.14761497 | AH14: 0.14780314 | AI14: 0.14799131 | AJ14: 0.14817948 | AK14: 0.14836765 | AL14: 0.14855582 | AM14: 0.14874399 | AN14: 0.14893217 | AO14: 0.14912034 | AP14: 0.14930851 | AQ14: 0.14949668
K15: Residential PV - Class 7 - Conservative | L15: 0.14329455 | M15: 0.14329455 | N15: 0.14329455 | O15: 0.14329455 | P15: 0.14329455 | Q15: 0.14329455 | R15: 0.14329455 | S15: 0.14329455 | T15: 0.14329455 | U15: 0.14329455 | V15: 0.14329455 | W15: 0.14329455 | X15: 0.14341648 | Y15: 0.14353842 | Z15: 0.14366035 | AA15: 0.14378229 | AB15: 0.14390422 | AC15: 0.14402616 | AD15: 0.1441481 | AE15: 0.14427003 | AF15: 0.14439197 | AG15: 0.1445139 | AH15: 0.14463584 | AI15: 0.14475777 | AJ15: 0.14487971 | AK15: 0.14500165 | AL15: 0.14512358 | AM15: 0.14524552 | AN15: 0.14536745 | AO15: 0.14548939 | AP15: 0.14561132 | AQ15: 0.14573326
K16: Residential PV - Class 6 - Advanced | L16: 0.14990328 | M16: 0.15049312 | N16: 0.15108295 | O16: 0.15167279 | P16: 0.15226262 | Q16: 0.15285245 | R16: 0.15344229 | S16: 0.15403212 | T16: 0.15462196 | U16: 0.15521179 | V16: 0.15580162 | W16: 0.15639146 | X16: 0.15639146 | Y16: 0.15639146 | Z16: 0.15639146 | AA16: 0.15639146 | AB16: 0.15639146 | AC16: 0.15639146 | AD16: 0.15639146 | AE16: 0.15639146 | AF16: 0.15639146 | AG16: 0.15639146 | AH16: 0.15639146 | AI16: 0.15639146 | AJ16: 0.15639146 | AK16: 0.15639146 | AL16: 0.15639146 | AM16: 0.15639146 | AN16: 0.15639146 | AO16: 0.15639146 | AP16: 0.15639146 | AQ16: 0.15639146
... K33: Residential PV - Class 1 - Conservative | L33: 0.18463784 | M33: 0.18463784 | N33: 0.18463784 | O33: 0.18463784 | P33: 0.18463784 | Q33: 0.18463784 | R33: 0.18463784 | S33: 0.18463784 | T33: 0.18463784 | U33: 0.18463784 | V33: 0.18463784 | W33: 0.18463784 | X33: 0.18479496 | Y33: 0.18495208 | Z33: 0.18510919 | AA33: 0.18526631 | AB33: 0.18542343 | AC33: 0.18558054 | AD33: 0.18573766 | AE33: 0.18589478 | AF33: 0.18605189 | AG33: 0.18620901 | AH33: 0.18636613 | AI33: 0.18652324 | AJ33: 0.18668036 | AK33: 0.18683748 | AL33: 0.18699459 | AM33: 0.18715171 | AN33: 0.18730882 | AO33: 0.18746594 | AP33: 0.18762306 | AQ33: 0.18778017

Sheet Solar - PV Dist. Res 2022
A1: Solar Distributed Residential PV | M1: https://atb.nrel.gov/electricity/2022/residential_pv
U2: Inputs
U3: Calculated
U4: Input from other tab
B7: X | G7: Assumptions
H9: Technology | J9: Base Year: | M9: 2020
J10: All values are given in 2020 U.S. dollars, using the Consumer Price Index (BLS, 2021) for dollar year conversions where source dollar years don't match 2020.
J11: Residential Solar Photovoltaic
J14: Representative Dist. Res system is fixed-tilt roof mounted with capacity of 7.15 kW
J15: Overnight Capital Cost, Capacity Factor, Fixed O&M, and Variable O&M costs
J16: represent $/kW DC; however LCOE reflects $/MWh AC.
J17: Capacity factors chosen here to reflect range across the continental U.S. using NREL PVWATTS.
O20: Available | P20: Available
O21: Capacity | P21: Generation
O22: (GW) | P22: (GWh)
O23: 731 | P23: 926000
M26: ATB values reflect annual average capacity factor over life of plant including estimated degradation, starting at 0.7% per year, reducing to 0.2%, 0.5%, and 0.5% annual degradation by 2050 for the advanced, moderate, and conservative scenarios, respectively.
H33: Finance | J33: Financial Assumptions:
J34: Capital Recovery Period (Years) | O34: =S35 -> 30 | Q34: Financial Case | S34: ='[2]Financial and CRP Inputs'!$B$5 -> Market
J35: Depreciation Period | O35: 5 | Q35: Capital Recovery Period | S35: =IF('[2]Financial and CRP Inputs'!$E$5="Custom",'[2]Financial and CRP Inputs'!$J$10,IF('[2]Financial and CRP Inputs'!$E$5="TechLife",'[2]Financial and CRP Inputs'!$I$10,'[2]Financial and CRP Inputs'!$E$5)) -> 30
J36: Equity Premium During Construction | O36: 0.02
J37: Construction Duration yrs | O37: 0
J38: Year | K38: Capital | L38: Percent of Leverage During Construction | M38: Percent of Equity During Construction
J39: Index | K39: Fraction
J42: 0 | K42: 1 | L42: 0.8 | M42: =1-L42 -> 0.2
J43: 1 | K43: 0 | L43: 0.8 | M43: =1-L43 -> 0.2
J44: 2 | K44: 0 | L44: 0.8 | M44: =1-L44 -> 0.2
M46: Base Year
M47: 2020 | N47: 2021 | O47: 2022 | P47: 2023 | Q47: 2024 | R47: 2025 | S47: 2026 | T47: 2027 | U47: 2028 | V47: 2029 | W47: 2030 | X47: 2031 | Y47: 2032 | Z47: 2033 | AA47: 2034 | AB47: 2035 | AC47: 2036 | AD47: 2037 | AE47: 2038 | AF47: 2039 | AG47: 2040 | AH47: 2041 | AI47: 2042 | AJ47: 2043 | AK47: 2044 | AL47: 2045 | AM47: 2046 | AN47: 2047 | AO47: 2048 | AP47: 2049 | AQ47: 2050
J48: Assumptions | K48: Inflation Rate | L48: * | M48: =IF($S$34="Market",'[2]WACC Calc'!F368,'[2]WACC Calc'!F550) -> 0.025 | N48: =IF($S$34="Market",'[2]WACC Calc'!G368,'[2]WACC Calc'!G550) -> 0.025 | O48: =IF($S$34="Market",'[2]WACC Calc'!H368,'[2]WACC Calc'!H550) -> 0.025 | P48: =IF($S$34="Market",'[2]WACC Calc'!I368,'[2]WACC Calc'!I550) -> 0.025 | Q48: =IF($S$34="Market",'[2]WACC Calc'!J368,'[2]WACC Calc'!J550) -> 0.025 | R48: =IF($S$34="Market",'[2]WACC Calc'!K368,'[2]WACC Calc'!K550) -> 0.025 | S48: =IF($S$34="Market",'[2]WACC Calc'!L368,'[2]WACC Calc'!L550) -> 0.025 | T48: =IF($S$34="Market",'[2]WACC Calc'!M368,'[2]WACC Calc'!M550) -> 0.025 | ... AQ48: =IF($S$34="Market",'[2]WACC Calc'!AJ368,'[2]WACC Calc'!AJ550) -> 0.025
K49: Interest Rate Nominal | L49: Advanced | M49: =IF($S$34="Market",'[2]WACC Calc'!F369,'[2]WACC Calc'!F551) -> 0.04 | N49: =IF($S$34="Market",'[2]WACC Calc'!G369,'[2]WACC Calc'!G551) -> 0.04 | O49: =IF($S$34="Market",'[2]WACC Calc'!H369,'[2]WACC Calc'!H551) -> 0.04 | P49: =IF($S$34="Market",'[2]WACC Calc'!I369,'[2]WACC Calc'!I551) -> 0.04 | Q49: =IF($S$34="Market",'[2]WACC Calc'!J369,'[2]WACC Calc'!J551) -> 0.04 | R49: =IF($S$34="Market",'[2]WACC Calc'!K369,'[2]WACC Calc'!K551) -> 0.04 | S49: =IF($S$34="Market",'[2]WACC Calc'!L369,'[2]WACC Calc'!L551) -> 0.042 | T49: =IF($S$34="Market",'[2]WACC Calc'!M369,'[2]WACC Calc'!M551) -> 0.044 | ... AQ49: =IF($S$34="Market",'[2]WACC Calc'!AJ369,'[2]WACC Calc'!AJ551) -> 0.05
K50: Interest Rate Nominal | L50: Moderate | M50: =IF($S$34="Market",'[2]WACC Calc'!F370,'[2]WACC Calc'!F552) -> 0.04 | N50: =IF($S$34="Market",'[2]WACC Calc'!G370,'[2]WACC Calc'!G552) -> 0.04 | O50: =IF($S$34="Market",'[2]WACC Calc'!H370,'[2]WACC Calc'!H552) -> 0.04 | P50: =IF($S$34="Market",'[2]WACC Calc'!I370,'[2]WACC Calc'!I552) -> 0.04 | Q50: =IF($S$34="Market",'[2]WACC Calc'!J370,'[2]WACC Calc'!J552) -> 0.04 | R50: =IF($S$34="Market",'[2]WACC Calc'!K370,'[2]WACC Calc'!K552) -> 0.04 | S50: =IF($S$34="Market",'[2]WACC Calc'!L370,'[2]WACC Calc'!L552) -> 0.042 | T50: =IF($S$34="Market",'[2]WACC Calc'!M370,'[2]WACC Calc'!M552) -> 0.044 | ... AQ50: =IF($S$34="Market",'[2]WACC Calc'!AJ370,'[2]WACC Calc'!AJ552) -> 0.05
K51: Interest Rate Nominal | L51: Conservative | M51: =IF($S$34="Market",'[2]WACC Calc'!F371,'[2]WACC Calc'!F553) -> 0.04 | N51: =IF($S$34="Market",'[2]WACC Calc'!G371,'[2]WACC Calc'!G553) -> 0.04 | O51: =IF($S$34="Market",'[2]WACC Calc'!H371,'[2]WACC Calc'!H553) -> 0.04 | P51: =IF($S$34="Market",'[2]WACC Calc'!I371,'[2]WACC Calc'!I553) -> 0.04 | Q51: =IF($S$34="Market",'[2]WACC Calc'!J371,'[2]WACC Calc'!J553) -> 0.04 | R51: =IF($S$34="Market",'[2]WACC Calc'!K371,'[2]WACC Calc'!K553) -> 0.04 | S51: =IF($S$34="Market",'[2]WACC Calc'!L371,'[2]WACC Calc'!L553) -> 0.042 | T51: =IF($S$34="Market",'[2]WACC Calc'!M371,'[2]WACC Calc'!M553) -> 0.044 | ... AQ51: =IF($S$34="Market",'[2]WACC Calc'!AJ371,'[2]WACC Calc'!AJ553) -> 0.05
K52: Calculated Interest Rate Real | L52: Advanced | M52: =(1+M49)/(1+M$48) - 1 -> 0.014634146 | N52: =(1+N49)/(1+N$48) - 1 -> 0.014634146 | O52: =(1+O49)/(1+O$48) - 1 -> 0.014634146 | P52: =(1+P49)/(1+P$48) - 1 -> 0.014634146 | Q52: =(1+Q49)/(1+Q$48) - 1 -> 0.014634146 | R52: =(1+R49)/(1+R$48) - 1 -> 0.014634146 | S52: =(1+S49)/(1+S$48) - 1 -> 0.016585366 | T52: =(1+T49)/(1+T$48) - 1 -> 0.018536585 | ... AQ52: =(1+AQ49)/(1+AQ$48) - 1 -> 0.024390244
K53: Calculated Interest Rate Real | L53: Moderate | M53: =(1+M50)/(1+M$48) - 1 -> 0.014634146 | N53: =(1+N50)/(1+N$48) - 1 -> 0.014634146 | O53: =(1+O50)/(1+O$48) - 1 -> 0.014634146 | P53: =(1+P50)/(1+P$48) - 1 -> 0.014634146 | Q53: =(1+Q50)/(1+Q$48) - 1 -> 0.014634146 | R53: =(1+R50)/(1+R$48) - 1 -> 0.014634146 | S53: =(1+S50)/(1+S$48) - 1 -> 0.016585366 | T53: =(1+T50)/(1+T$48) - 1 -> 0.018536585 | ... AQ53: =(1+AQ50)/(1+AQ$48) - 1 -> 0.024390244
K54: Calculated Interest Rate Real | L54: Conservative | M54: =(1+M51)/(1+M$48) - 1 -> 0.014634146 | N54: =(1+N51)/(1+N$48) - 1 -> 0.014634146 | O54: =(1+O51)/(1+O$48) - 1 -> 0.014634146 | P54: =(1+P51)/(1+P$48) - 1 -> 0.014634146 | Q54: =(1+Q51)/(1+Q$48) - 1 -> 0.014634146 | R54: =(1+R51)/(1+R$48) - 1 -> 0.014634146 | S54: =(1+S51)/(1+S$48) - 1 -> 0.016585366 | T54: =(1+T51)/(1+T$48) - 1 -> 0.018536585 | ... AQ54: =(1+AQ51)/(1+AQ$48) - 1 -> 0.024390244
K55: Interest During Construction - Nominal | L55: * | M55: =IF($S$34="Market",'[2]WACC Calc'!F375,'[2]WACC Calc'!F557) -> 0.035 | N55: =IF($S$34="Market",'[2]WACC Calc'!G375,'[2]WACC Calc'!G557) -> 0.035 | O55: =IF($S$34="Market",'[2]WACC Calc'!H375,'[2]WACC Calc'!H557) -> 0.035 | P55: =IF($S$34="Market",'[2]WACC Calc'!I375,'[2]WACC Calc'!I557) -> 0.035 | Q55: =IF($S$34="Market",'[2]WACC Calc'!J375,'[2]WACC Calc'!J557) -> 0.035 | R55: =IF($S$34="Market",'[2]WACC Calc'!K375,'[2]WACC Calc'!K557) -> 0.035 | S55: =IF($S$34="Market",'[2]WACC Calc'!L375,'[2]WACC Calc'!L557) -> 0.037 | T55: =IF($S$34="Market",'[2]WACC Calc'!M375,'[2]WACC Calc'!M557) -> 0.039 | ... AQ55: =IF($S$34="Market",'[2]WACC Calc'!AJ375,'[2]WACC Calc'!AJ557) -> 0.045
K56: Rate of Return on Equity Nominal | L56: Advanced | M56: =IF($S$34="Market",'[2]WACC Calc'!F376,'[2]WACC Calc'!F558) -> 0.088 | N56: =IF($S$34="Market",'[2]WACC Calc'!G376,'[2]WACC Calc'!G558) -> 0.088 | O56: =IF($S$34="Market",'[2]WACC Calc'!H376,'[2]WACC Calc'!H558) -> 0.088 | P56: =IF($S$34="Market",'[2]WACC Calc'!I376,'[2]WACC Calc'!I558) -> 0.088 | Q56: =IF($S$34="Market",'[2]WACC Calc'!J376,'[2]WACC Calc'!J558) -> 0.088 | R56: =IF($S$34="Market",'[2]WACC Calc'!K376,'[2]WACC Calc'!K558) -> 0.088 | S56: =IF($S$34="Market",'[2]WACC Calc'!L376,'[2]WACC Calc'!L558) -> 0.088 | T56: =IF($S$34="Market",'[2]WACC Calc'!M376,'[2]WACC Calc'!M558) -> 0.088 | ... AQ56: =IF($S$34="Market",'[2]WACC Calc'!AJ376,'[2]WACC Calc'!AJ558) -> 0.088
K57: Rate of Return on Equity Nominal | L57: Moderate | M57: =IF($S$34="Market",'[2]WACC Calc'!F377,'[2]WACC Calc'!F559) -> 0.088 | N57: =IF($S$34="Market",'[2]WACC Calc'!G377,'[2]WACC Calc'!G559) -> 0.088 | O57: =IF($S$34="Market",'[2]WACC Calc'!H377,'[2]WACC Calc'!H559) -> 0.088 | P57: =IF($S$34="Market",'[2]WACC Calc'!I377,'[2]WACC Calc'!I559) -> 0.088 | Q57: =IF($S$34="Market",'[2]WACC Calc'!J377,'[2]WACC Calc'!J559) -> 0.088 | R57: =IF($S$34="Market",'[2]WACC Calc'!K377,'[2]WACC Calc'!K559) -> 0.088 | S57: =IF($S$34="Market",'[2]WACC Calc'!L377,'[2]WACC Calc'!L559) -> 0.088 | T57: =IF($S$34="Market",'[2]WACC Calc'!M377,'[2]WACC Calc'!M559) -> 0.088 | ... AQ57: =IF($S$34="Market",'[2]WACC Calc'!AJ377,'[2]WACC Calc'!AJ559) -> 0.088
K58: Rate of Return on Equity Nominal | L58: Conservative | M58: =IF($S$34="Market",'[2]WACC Calc'!F378,'[2]WACC Calc'!F560) -> 0.088 | N58: =IF($S$34="Market",'[2]WACC Calc'!G378,'[2]WACC Calc'!G560) -> 0.088 | O58: =IF($S$34="Market",'[2]WACC Calc'!H378,'[2]WACC Calc'!H560) -> 0.088 | P58: =IF($S$34="Market",'[2]WACC Calc'!I378,'[2]WACC Calc'!I560) -> 0.088 | Q58: =IF($S$34="Market",'[2]WACC Calc'!J378,'[2]WACC Calc'!J560) -> 0.088 | R58: =IF($S$34="Market",'[2]WACC Calc'!K378,'[2]WACC Calc'!K560) -> 0.088 | S58: =IF($S$34="Market",'[2]WACC Calc'!L378,'[2]WACC Calc'!L560) -> 0.088 | T58: =IF($S$34="Market",'[2]WACC Calc'!M378,'[2]WACC Calc'!M560) -> 0.088 | ... AQ58: =IF($S$34="Market",'[2]WACC Calc'!AJ378,'[2]WACC Calc'!AJ560) -> 0.088
K59: Calculated Rate of Return on Equity Real | L59: Advanced | M59: =(1+M56)/(1+M$48) - 1 -> 0.061463415 | N59: =(1+N56)/(1+N$48) - 1 -> 0.061463415 | O59: =(1+O56)/(1+O$48) - 1 -> 0.061463415 | P59: =(1+P56)/(1+P$48) - 1 -> 0.061463415 | Q59: =(1+Q56)/(1+Q$48) - 1 -> 0.061463415 | R59: =(1+R56)/(1+R$48) - 1 -> 0.061463415 | S59: =(1+S56)/(1+S$48) - 1 -> 0.061463415 | T59: =(1+T56)/(1+T$48) - 1 -> 0.061463415 | ... AQ59: =(1+AQ56)/(1+AQ$48) - 1 -> 0.061463415
K60: Calculated Rate of Return on Equity Real | L60: Moderate | M60: =(1+M57)/(1+M$48) - 1 -> 0.061463415 | N60: =(1+N57)/(1+N$48) - 1 -> 0.061463415 | O60: =(1+O57)/(1+O$48) - 1 -> 0.061463415 | P60: =(1+P57)/(1+P$48) - 1 -> 0.061463415 | Q60: =(1+Q57)/(1+Q$48) - 1 -> 0.061463415 | R60: =(1+R57)/(1+R$48) - 1 -> 0.061463415 | S60: =(1+S57)/(1+S$48) - 1 -> 0.061463415 | T60: =(1+T57)/(1+T$48) - 1 -> 0.061463415 | ... AQ60: =(1+AQ57)/(1+AQ$48) - 1 -> 0.061463415
K61: Calculated Rate of Return on Equity Real | L61: Conservative | M61: =(1+M58)/(1+M$48) - 1 -> 0.061463415 | N61: =(1+N58)/(1+N$48) - 1 -> 0.061463415 | O61: =(1+O58)/(1+O$48) - 1 -> 0.061463415 | P61: =(1+P58)/(1+P$48) - 1 -> 0.061463415 | Q61: =(1+Q58)/(1+Q$48) - 1 -> 0.061463415 | R61: =(1+R58)/(1+R$48) - 1 -> 0.061463415 | S61: =(1+S58)/(1+S$48) - 1 -> 0.061463415 | T61: =(1+T58)/(1+T$48) - 1 -> 0.061463415 | ... AQ61: =(1+AQ58)/(1+AQ$48) - 1 -> 0.061463415
K62: Debt Fraction | L62: Advanced | M62: =IF($S$34="Market",'[2]WACC Calc'!F382,'[2]WACC Calc'!F564) -> 0.53694431 | N62: =IF($S$34="Market",'[2]WACC Calc'!G382,'[2]WACC Calc'!G564) -> 0.53694431 | O62: =IF($S$34="Market",'[2]WACC Calc'!H382,'[2]WACC Calc'!H564) -> 0.53694431 | P62: =IF($S$34="Market",'[2]WACC Calc'!I382,'[2]WACC Calc'!I564) -> 0.53694431 | Q62: =IF($S$34="Market",'[2]WACC Calc'!J382,'[2]WACC Calc'!J564) -> 0.56650043 | R62: =IF($S$34="Market",'[2]WACC Calc'!K382,'[2]WACC Calc'!K564) -> 0.56650043 | S62: =IF($S$34="Market",'[2]WACC Calc'!L382,'[2]WACC Calc'!L564) -> 0.68472492 | T62: =IF($S$34="Market",'[2]WACC Calc'!M382,'[2]WACC Calc'!M564) -> 0.68106405 | ... AQ62: =IF($S$34="Market",'[2]WACC Calc'!AJ382,'[2]WACC Calc'!AJ564) -> 0.67008143
K63: Debt Fraction | L63: Moderate | M63: =IF($S$34="Market",'[2]WACC Calc'!F383,'[2]WACC Calc'!F565) -> 0.53694431 | N63: =IF($S$34="Market",'[2]WACC Calc'!G383,'[2]WACC Calc'!G565) -> 0.53694431 | O63: =IF($S$34="Market",'[2]WACC Calc'!H383,'[2]WACC Calc'!H565) -> 0.53694431 | P63: =IF($S$34="Market",'[2]WACC Calc'!I383,'[2]WACC Calc'!I565) -> 0.53694431 | Q63: =IF($S$34="Market",'[2]WACC Calc'!J383,'[2]WACC Calc'!J565) -> 0.56650043 | R63: =IF($S$34="Market",'[2]WACC Calc'!K383,'[2]WACC Calc'!K565) -> 0.56650043 | S63: =IF($S$34="Market",'[2]WACC Calc'!L383,'[2]WACC Calc'!L565) -> 0.68472492 | T63: =IF($S$34="Market",'[2]WACC Calc'!M383,'[2]WACC Calc'!M565) -> 0.68106405 | ... AQ63: =IF($S$34="Market",'[2]WACC Calc'!AJ383,'[2]WACC Calc'!AJ565) -> 0.67008143
K64: Debt Fraction | L64: Conservative | M64: =IF($S$34="Market",'[2]WACC Calc'!F384,'[2]WACC Calc'!F566) -> 0.53694431 | N64: =IF($S$34="Market",'[2]WACC Calc'!G384,'[2]WACC Calc'!G566) -> 0.53694431 | O64: =IF($S$34="Market",'[2]WACC Calc'!H384,'[2]WACC Calc'!H566) -> 0.53694431 | P64: =IF($S$34="Market",'[2]WACC Calc'!I384,'[2]WACC Calc'!I566) -> 0.53694431 | Q64: =IF($S$34="Market",'[2]WACC Calc'!J384,'[2]WACC Calc'!J566) -> 0.56650043 | R64: =IF($S$34="Market",'[2]WACC Calc'!K384,'[2]WACC Calc'!K566) -> 0.56650043 | S64: =IF($S$34="Market",'[2]WACC Calc'!L384,'[2]WACC Calc'!L566) -> 0.68472492 | T64: =IF($S$34="Market",'[2]WACC Calc'!M384,'[2]WACC Calc'!M566) -> 0.68106405 | ... AQ64: =IF($S$34="Market",'[2]WACC Calc'!AJ384,'[2]WACC Calc'!AJ566) -> 0.67008143
K65: Tax Rate (Federal and State) | L65: * | M65: =IF($S$34="Market",'[2]WACC Calc'!F385,'[2]WACC Calc'!F567) -> 0.2574 | N65: =IF($S$34="Market",'[2]WACC Calc'!G385,'[2]WACC Calc'!G567) -> 0.2574 | O65: =IF($S$34="Market",'[2]WACC Calc'!H385,'[2]WACC Calc'!H567) -> 0.2574 | P65: =IF($S$34="Market",'[2]WACC Calc'!I385,'[2]WACC Calc'!I567) -> 0.2574 | Q65: =IF($S$34="Market",'[2]WACC Calc'!J385,'[2]WACC Calc'!J567) -> 0.2574 | R65: =IF($S$34="Market",'[2]WACC Calc'!K385,'[2]WACC Calc'!K567) -> 0.2574 | S65: =IF($S$34="Market",'[2]WACC Calc'!L385,'[2]WACC Calc'!L567) -> 0.2574 | T65: =IF($S$34="Market",'[2]WACC Calc'!M385,'[2]WACC Calc'!M567) -> 0.2574 | ... AQ65: =IF($S$34="Market",'[2]WACC Calc'!AJ385,'[2]WACC Calc'!AJ567) -> 0.2574
K66: WACC Nominal | L66: Advanced | M66: =M62*M49*(1-M$65)+(1-M62)*(M56) -> 0.056698295 | N66: =N62*N49*(1-N$65)+(1-N62)*(N56) -> 0.056698295 | O66: =O62*O49*(1-O$65)+(1-O62)*(O56) -> 0.056698295 | P66: =P62*P49*(1-P$65)+(1-P62)*(P56) -> 0.056698295 | Q66: =Q62*Q49*(1-Q$65)+(1-Q62)*(Q56) -> 0.054975291 | R66: =R62*R49*(1-R$65)+(1-R62)*(R56) -> 0.054975291 | S66: =S62*S49*(1-S$65)+(1-S62)*(S56) -> 0.04910023 | T66: =T62*T49*(1-T$65)+(1-T62)*(T56) -> 0.050319723 | ... AQ66: =AQ62*AQ49*(1-AQ$65)+(1-AQ62)*(AQ56) -> 0.053912958
K67: WACC Nominal | L67: Moderate | M67: =M63*M50*(1-M$65)+(1-M63)*(M57) -> 0.056698295 | N67: =N63*N50*(1-N$65)+(1-N63)*(N57) -> 0.056698295 | O67: =O63*O50*(1-O$65)+(1-O63)*(O57) -> 0.056698295 | P67: =P63*P50*(1-P$65)+(1-P63)*(P57) -> 0.056698295 | Q67: =Q63*Q50*(1-Q$65)+(1-Q63)*(Q57) -> 0.054975291 | R67: =R63*R50*(1-R$65)+(1-R63)*(R57) -> 0.054975291 | S67: =S63*S50*(1-S$65)+(1-S63)*(S57) -> 0.04910023 | T67: =T63*T50*(1-T$65)+(1-T63)*(T57) -> 0.050319723 | ... AQ67: =AQ63*AQ50*(1-AQ$65)+(1-AQ63)*(AQ57) -> 0.053912958
K68: WACC Nominal | L68: Conservative | M68: =M64*M51*(1-M$65)+(1-M64)*(M58) -> 0.056698295 | N68: =N64*N51*(1-N$65)+(1-N64)*(N58) -> 0.056698295 | O68: =O64*O51*(1-O$65)+(1-O64)*(O58) -> 0.056698295 | P68: =P64*P51*(1-P$65)+(1-P64)*(P58) -> 0.056698295 | Q68: =Q64*Q51*(1-Q$65)+(1-Q64)*(Q58) -> 0.054975291 | R68: =R64*R51*(1-R$65)+(1-R64)*(R58) -> 0.054975291 | S68: =S64*S51*(1-S$65)+(1-S64)*(S58) -> 0.04910023 | T68: =T64*T51*(1-T$65)+(1-T64)*(T58) -> 0.050319723 | ... AQ68: =AQ64*AQ51*(1-AQ$65)+(1-AQ64)*(AQ58) -> 0.053912958
K69: WACC Real | L69: Advanced | M69: =(1+M66)/(1+M$48) - 1 -> 0.030925165 | N69: =(1+N66)/(1+N$48) - 1 -> 0.030925165 | O69: =(1+O66)/(1+O$48) - 1 -> 0.030925165 | P69: =(1+P66)/(1+P$48) - 1 -> 0.030925165 | Q69: =(1+Q66)/(1+Q$48) - 1 -> 0.029244186 | R69: =(1+R66)/(1+R$48) - 1 -> 0.029244186 | S69: =(1+S66)/(1+S$48) - 1 -> 0.023512419 | T69: =(1+T66)/(1+T$48) - 1 -> 0.024702169 | ... AQ69: =(1+AQ66)/(1+AQ$48) - 1 -> 0.028207763
K70: WACC Real | L70: Moderate | M70: =(1+M67)/(1+M$48) - 1 -> 0.030925165 | N70: =(1+N67)/(1+N$48) - 1 -> 0.030925165 | O70: =(1+O67)/(1+O$48) - 1 -> 0.030925165 | P70: =(1+P67)/(1+P$48) - 1 -> 0.030925165 | Q70: =(1+Q67)/(1+Q$48) - 1 -> 0.029244186 | R70: =(1+R67)/(1+R$48) - 1 -> 0.029244186 | S70: =(1+S67)/(1+S$48) - 1 -> 0.023512419 | T70: =(1+T67)/(1+T$48) - 1 -> 0.024702169 | ... AQ70: =(1+AQ67)/(1+AQ$48) - 1 -> 0.028207763
K71: WACC Real | L71: Conservative | M71: =(1+M68)/(1+M$48) - 1 -> 0.030925165 | N71: =(1+N68)/(1+N$48) - 1 -> 0.030925165 | O71: =(1+O68)/(1+O$48) - 1 -> 0.030925165 | P71: =(1+P68)/(1+P$48) - 1 -> 0.030925165 | Q71: =(1+Q68)/(1+Q$48) - 1 -> 0.029244186 | R71: =(1+R68)/(1+R$48) - 1 -> 0.029244186 | S71: =(1+S68)/(1+S$48) - 1 -> 0.023512419 | T71: =(1+T68)/(1+T$48) - 1 -> 0.024702169 | ... AQ71: =(1+AQ68)/(1+AQ$48) - 1 -> 0.028207763
K72: Capital Recovery Factor (CRF) Nominal | L72: Advanced | M72: =M66 / (1 - (1 / (1 + M66)^$O$34)) -> 0.070101059 | N72: =N66 / (1 - (1 / (1 + N66)^$O$34)) -> 0.070101059 | O72: =O66 / (1 - (1 / (1 + O66)^$O$34)) -> 0.070101059 | P72: =P66 / (1 - (1 / (1 + P66)^$O$34)) -> 0.070101059 | Q72: =Q66 / (1 - (1 / (1 + Q66)^$O$34)) -> 0.068786614 | R72: =R66 / (1 - (1 / (1 + R66)^$O$34)) -> 0.068786614 | S72: =S66 / (1 - (1 / (1 + S66)^$O$34)) -> 0.064385753 | T72: =T66 / (1 - (1 / (1 + T66)^$O$34)) -> 0.065288712 | ... AQ72: =AQ66 / (1 - (1 / (1 + AQ66)^$O$34)) -> 0.067981472
K73: Capital Recovery Factor (CRF) Nominal | L73: Moderate | M73: =M67 / (1 - (1 / (1 + M67)^$O$34)) -> 0.070101059 | N73: =N67 / (1 - (1 / (1 + N67)^$O$34)) -> 0.070101059 | O73: =O67 / (1 - (1 / (1 + O67)^$O$34)) -> 0.070101059 | P73: =P67 / (1 - (1 / (1 + P67)^$O$34)) -> 0.070101059 | Q73: =Q67 / (1 - (1 / (1 + Q67)^$O$34)) -> 0.068786614 | R73: =R67 / (1 - (1 / (1 + R67)^$O$34)) -> 0.068786614 | S73: =S67 / (1 - (1 / (1 + S67)^$O$34)) -> 0.064385753 | T73: =T67 / (1 - (1 / (1 + T67)^$O$34)) -> 0.065288712 | ... AQ73: =AQ67 / (1 - (1 / (1 + AQ67)^$O$34)) -> 0.067981472
K74: Capital Recovery Factor (CRF) Nominal | L74: Conservative | M74: =M68 / (1 - (1 / (1 + M68)^$O$34)) -> 0.070101059 | N74: =N68 / (1 - (1 / (1 + N68)^$O$34)) -> 0.070101059 | O74: =O68 / (1 - (1 / (1 + O68)^$O$34)) -> 0.070101059 | P74: =P68 / (1 - (1 / (1 + P68)^$O$34)) -> 0.070101059 | Q74: =Q68 / (1 - (1 / (1 + Q68)^$O$34)) -> 0.068786614 | R74: =R68 / (1 - (1 / (1 + R68)^$O$34)) -> 0.068786614 | S74: =S68 / (1 - (1 / (1 + S68)^$O$34)) -> 0.064385753 | T74: =T68 / (1 - (1 / (1 + T68)^$O$34)) -> 0.065288712 | ... AQ74: =AQ68 / (1 - (1 / (1 + AQ68)^$O$34)) -> 0.067981472
K75: Capital Recovery Factor (CRF) Real | L75: Advanced | M75: =M69 / (1 - (1 / (1 + M69)^$O$34)) -> 0.051631284 | N75: =N69 / (1 - (1 / (1 + N69)^$O$34)) -> 0.051631284 | O75: =O69 / (1 - (1 / (1 + O69)^$O$34)) -> 0.051631284 | P75: =P69 / (1 - (1 / (1 + P69)^$O$34)) -> 0.051631284 | Q75: =Q69 / (1 - (1 / (1 + Q69)^$O$34)) -> 0.050522072 | R75: =R69 / (1 - (1 / (1 + R69)^$O$34)) -> 0.050522072 | S75: =S69 / (1 - (1 / (1 + S69)^$O$34)) -> 0.046835044 | T75: =T69 / (1 - (1 / (1 + T69)^$O$34)) -> 0.047588112 | ... AQ75: =AQ69 / (1 - (1 / (1 + AQ69)^$O$34)) -> 0.049844423
K76: Capital Recovery Factor (CRF) Real | L76: Moderate | M76: =M70 / (1 - (1 / (1 + M70)^$O$34)) -> 0.051631284 | N76: =N70 / (1 - (1 / (1 + N70)^$O$34)) -> 0.051631284 | O76: =O70 / (1 - (1 / (1 + O70)^$O$34)) -> 0.051631284 | P76: =P70 / (1 - (1 / (1 + P70)^$O$34)) -> 0.051631284 | Q76: =Q70 / (1 - (1 / (1 + Q70)^$O$34)) -> 0.050522072 | R76: =R70 / (1 - (1 / (1 + R70)^$O$34)) -> 0.050522072 | S76: =S70 / (1 - (1 / (1 + S70)^$O$34)) -> 0.046835044 | T76: =T70 / (1 - (1 / (1 + T70)^$O$34)) -> 0.047588112 | ... AQ76: =AQ70 / (1 - (1 / (1 + AQ70)^$O$34)) -> 0.049844423
K77: Capital Recovery Factor (CRF) Real | L77: Conservative | M77: =M71 / (1 - (1 / (1 + M71)^$O$34)) -> 0.051631284 | N77: =N71 / (1 - (1 / (1 + N71)^$O$34)) -> 0.051631284 | O77: =O71 / (1 - (1 / (1 + O71)^$O$34)) -> 0.051631284 | P77: =P71 / (1 - (1 / (1 + P71)^$O$34)) -> 0.051631284 | Q77: =Q71 / (1 - (1 / (1 + Q71)^$O$34)) -> 0.050522072 | R77: =R71 / (1 - (1 / (1 + R71)^$O$34)) -> 0.050522072 | S77: =S71 / (1 - (1 / (1 + S71)^$O$34)) -> 0.046835044 | T77: =T71 / (1 - (1 / (1 + T71)^$O$34)) -> 0.047588112 | ... AQ77: =AQ71 / (1 - (1 / (1 + AQ71)^$O$34)) -> 0.049844423
D82: X | G82: Future Projections
M83: Base Year
M84: 2020 | N84: 2021 | O84: 2022 | P84: 2023 | Q84: 2024 | R84: 2025 | S84: 2026 | T84: 2027 | U84: 2028 | V84: 2029 | W84: 2030 | X84: 2031 | Y84: 2032 | Z84: 2033 | AA84: 2034 | AB84: 2035 | AC84: 2036 | AD84: 2037 | AE84: 2038 | AF84: 2039 | AG84: 2040 | AH84: 2041 | AI84: 2042 | AJ84: 2043 | AK84: 2044 | AL84: 2045 | AM84: 2046 | AN84: 2047 | AO84: 2048 | AP84: 2049 | AQ84: 2050
H85: Techno-Economic Cost and Performance Parameters | J85: Net Capacity Factor (%) | K85: Residential PV - Class 10 | L85: Advanced | M85: 0.12013139 | N85: 0.12060223 | O85: 0.12107307 | P85: 0.1215439 | Q85: 0.12201474 | R85: 0.12248557 | S85: 0.12295641 | T85: 0.12342725 | U85: 0.12389808 | V85: 0.12436892 | W85: 0.12483975 | X85: 0.12483975 | Y85: 0.12483975 | Z85: 0.12483975 | AA85: 0.12483975 | AB85: 0.12483975 | AC85: 0.12483975 | AD85: 0.12483975 | AE85: 0.12483975 | AF85: 0.12483975 | AG85: 0.12483975 | AH85: 0.12483975 | AI85: 0.12483975 | AJ85: 0.12483975 | AK85: 0.12483975 | AL85: 0.12483975 | AM85: 0.12483975 | AN85: 0.12483975 | AO85: 0.12483975 | AP85: 0.12483975 | AQ85: 0.12483975
K86: Residential PV - Class 10 | L86: Moderate | M86: 0.11984569 | N86: 0.12003083 | O86: 0.12021596 | P86: 0.1204011 | Q86: 0.12058623 | R86: 0.12077137 | S86: 0.12095651 | T86: 0.12114164 | U86: 0.12132678 | V86: 0.12151191 | W86: 0.12169705 | X86: 0.12185418 | Y86: 0.12201132 | Z86: 0.12216845 | AA86: 0.12232559 | AB86: 0.12248272 | AC86: 0.12263986 | AD86: 0.12279699 | AE86: 0.12295413 | AF86: 0.12311126 | AG86: 0.1232684 | AH86: 0.12342554 | AI86: 0.12358267 | AJ86: 0.12373981 | AK86: 0.12389694 | AL86: 0.12405408 | AM86: 0.12421121 | AN86: 0.12436835 | AO86: 0.12452548 | AP86: 0.12468262 | AQ86: 0.12483975
K87: Residential PV - Class 10 | L87: Conservative | M87: 0.11966056 | N87: 0.11966056 | O87: 0.11966056 | P87: 0.11966056 | Q87: 0.11966056 | R87: 0.11966056 | S87: 0.11966056 | T87: 0.11966056 | U87: 0.11966056 | V87: 0.11966056 | W87: 0.11966056 | X87: 0.11976238 | Y87: 0.11986421 | Z87: 0.11996603 | AA87: 0.12006786 | AB87: 0.12016968 | AC87: 0.1202715 | AD87: 0.12037333 | AE87: 0.12047515 | AF87: 0.12057698 | AG87: 0.1206788 | AH87: 0.12078063 | AI87: 0.12088245 | AJ87: 0.12098428 | AK87: 0.1210861 | AL87: 0.12118792 | AM87: 0.12128975 | AN87: 0.12139157 | AO87: 0.1214934 | AP87: 0.12159522 | AQ87: 0.12169705
K88: Residential PV - Class 9 | L88: Advanced | M88: 0.13158478 | N88: 0.13210051 | O88: 0.13261623 | P88: 0.13313196 | Q88: 0.13364768 | R88: 0.13416341 | S88: 0.13467913 | T88: 0.13519486 | U88: 0.13571059 | V88: 0.13622631 | W88: 0.13674204 | X88: 0.13674204 | Y88: 0.13674204 | Z88: 0.13674204 | AA88: 0.13674204 | AB88: 0.13674204 | AC88: 0.13674204 | AD88: 0.13674204 | AE88: 0.13674204 | AF88: 0.13674204 | AG88: 0.13674204 | AH88: 0.13674204 | AI88: 0.13674204 | AJ88: 0.13674204 | AK88: 0.13674204 | AL88: 0.13674204 | AM88: 0.13674204 | AN88: 0.13674204 | AO88: 0.13674204 | AP88: 0.13674204 | AQ88: 0.13674204
K89: Residential PV - Class 9 | L89: Moderate | M89: 0.13127184 | N89: 0.13147463 | O89: 0.13167741 | P89: 0.1318802 | Q89: 0.13208299 | R89: 0.13228577 | S89: 0.13248856 | T89: 0.13269134 | U89: 0.13289413 | V89: 0.13309692 | W89: 0.1332997 | X89: 0.13347182 | Y89: 0.13364394 | Z89: 0.13381605 | AA89: 0.13398817 | AB89: 0.13416029 | AC89: 0.1343324 | AD89: 0.13450452 | AE89: 0.13467664 | AF89: 0.13484875 | AG89: 0.13502087 | AH89: 0.13519299 | AI89: 0.1353651 | AJ89: 0.13553722 | AK89: 0.13570934 | AL89: 0.13588145 | AM89: 0.13605357 | AN89: 0.13622569 | AO89: 0.1363978 | AP89: 0.13656992 | AQ89: 0.13674204
K90: Residential PV - Class 9 | L90: Conservative | M90: 0.13106905 | N90: 0.13106905 | O90: 0.13106905 | P90: 0.13106905 | Q90: 0.13106905 | R90: 0.13106905 | S90: 0.13106905 | T90: 0.13106905 | U90: 0.13106905 | V90: 0.13106905 | W90: 0.13106905 | X90: 0.13118059 | Y90: 0.13129212 | Z90: 0.13140365 | AA90: 0.13151518 | AB90: 0.13162672 | AC90: 0.13173825 | AD90: 0.13184978 | AE90: 0.13196131 | AF90: 0.13207285 | AG90: 0.13218438 | AH90: 0.13229591 | AI90: 0.13240744 | AJ90: 0.13251898 | AK90: 0.13263051 | AL90: 0.13274204 | AM90: 0.13285357 | AN90: 0.13296511 | AO90: 0.13307664 | AP90: 0.13318817 | AQ90: 0.1332997
K91: Residential PV - Class 8 | L91: Advanced | M91: 0.13703971 | N91: 0.13757681 | O91: 0.13811392 | P91: 0.13865103 | Q91: 0.13918813 | R91: 0.13972524 | S91: 0.14026234 | T91: 0.14079945 | U91: 0.14133655 | V91: 0.14187366 | W91: 0.14241076 | X91: 0.14241076 | Y91: 0.14241076 | Z91: 0.14241076 | AA91: 0.14241076 | AB91: 0.14241076 | AC91: 0.14241076 | AD91: 0.14241076 | AE91: 0.14241076 | AF91: 0.14241076 | AG91: 0.14241076 | AH91: 0.14241076 | AI91: 0.14241076 | AJ91: 0.14241076 | AK91: 0.14241076 | AL91: 0.14241076 | AM91: 0.14241076 | AN91: 0.14241076 | AO91: 0.14241076 | AP91: 0.14241076 | AQ91: 0.14241076
K92: Residential PV - Class 8 | L92: Moderate | M92: 0.1367138 | N92: 0.13692499 | O92: 0.13713618 | P92: 0.13734738 | Q92: 0.13755857 | R92: 0.13776976 | S92: 0.13798095 | T92: 0.13819215 | U92: 0.13840334 | V92: 0.13861453 | W92: 0.13882573 | X92: 0.13900498 | Y92: 0.13918423 | Z92: 0.13936348 | AA92: 0.13954273 | AB92: 0.13972198 | AC92: 0.13990124 | AD92: 0.14008049 | AE92: 0.14025974 | AF92: 0.14043899 | AG92: 0.14061824 | AH92: 0.1407975 | AI92: 0.14097675 | AJ92: 0.141156 | AK92: 0.14133525 | AL92: 0.1415145 | AM92: 0.14169376 | AN92: 0.14187301 | AO92: 0.14205226 | AP92: 0.14223151 | AQ92: 0.14241076
K93: Residential PV - Class 8 | L93: Conservative | M93: 0.1365026 | N93: 0.1365026 | O93: 0.1365026 | P93: 0.1365026 | Q93: 0.1365026 | R93: 0.1365026 | S93: 0.1365026 | T93: 0.1365026 | U93: 0.1365026 | V93: 0.1365026 | W93: 0.1365026 | X93: 0.13661876 | Y93: 0.13673492 | Z93: 0.13685107 | AA93: 0.13696723 | AB93: 0.13708338 | AC93: 0.13719954 | AD93: 0.1373157 | AE93: 0.13743185 | AF93: 0.13754801 | AG93: 0.13766416 | AH93: 0.13778032 | AI93: 0.13789648 | AJ93: 0.13801263 | AK93: 0.13812879 | AL93: 0.13824494 | AM93: 0.1383611 | AN93: 0.13847726 | AO93: 0.13859341 | AP93: 0.13870957 | AQ93: 0.13882573
K94: Residential PV - Class 7 | L94: Advanced | M94: 0.14385838 | N94: 0.14442221 | O94: 0.14498604 | P94: 0.14554987 | Q94: 0.1461137 | R94: 0.14667753 | S94: 0.14724136 | T94: 0.14780519 | U94: 0.14836902 | V94: 0.14893285 | W94: 0.14949668 | X94: 0.14949668 | Y94: 0.14949668 | Z94: 0.14949668 | AA94: 0.14949668 | AB94: 0.14949668 | AC94: 0.14949668 | AD94: 0.14949668 | AE94: 0.14949668 | AF94: 0.14949668 | AG94: 0.14949668 | AH94: 0.14949668 | AI94: 0.14949668 | AJ94: 0.14949668 | AK94: 0.14949668 | AL94: 0.14949668 | AM94: 0.14949668 | AN94: 0.14949668 | AO94: 0.14949668 | AP94: 0.14949668 | AQ94: 0.14949668
K95: Residential PV - Class 7 | L95: Moderate | M95: 0.14351625 | N95: 0.14373795 | O95: 0.14395965 | P95: 0.14418135 | Q95: 0.14440305 | R95: 0.14462475 | S95: 0.14484645 | T95: 0.14506816 | U95: 0.14528986 | V95: 0.14551156 | W95: 0.14573326 | X95: 0.14592143 | Y95: 0.1461096 | Z95: 0.14629777 | AA95: 0.14648594 | AB95: 0.14667411 | AC95: 0.14686229 | AD95: 0.14705046 | AE95: 0.14723863 | AF95: 0.1474268 | AG95: 0.14761497 | AH95: 0.14780314 | AI95: 0.14799131 | AJ95: 0.14817948 | AK95: 0.14836765 | AL95: 0.14855582 | AM95: 0.14874399 | AN95: 0.14893217 | AO95: 0.14912034 | AP95: 0.14930851 | AQ95: 0.14949668
K96: Residential PV - Class 7 | L96: Conservative | M96: 0.14329455 | N96: 0.14329455 | O96: 0.14329455 | P96: 0.14329455 | Q96: 0.14329455 | R96: 0.14329455 | S96: 0.14329455 | T96: 0.14329455 | U96: 0.14329455 | V96: 0.14329455 | W96: 0.14329455 | X96: 0.14341648 | Y96: 0.14353842 | Z96: 0.14366035 | AA96: 0.14378229 | AB96: 0.14390422 | AC96: 0.14402616 | AD96: 0.1441481 | AE96: 0.14427003 | AF96: 0.14439197 | AG96: 0.1445139 | AH96: 0.14463584 | AI96: 0.14475777 | AJ96: 0.14487971 | AK96: 0.14500165 | AL96: 0.14512358 | AM96: 0.14524552 | AN96: 0.14536745 | AO96: 0.14548939 | AP96: 0.14561132 | AQ96: 0.14573326
K97: Residential PV - Class 6 | L97: Advanced | M97: 0.15049312 | N97: 0.15108295 | O97: 0.15167279 | P97: 0.15226262 | Q97: 0.15285245 | R97: 0.15344229 | S97: 0.15403212 | T97: 0.15462196 | U97: 0.15521179 | V97: 0.15580162 | W97: 0.15639146 | X97: 0.15639146 | Y97: 0.15639146 | Z97: 0.15639146 | AA97: 0.15639146 | AB97: 0.15639146 | AC97: 0.15639146 | AD97: 0.15639146 | AE97: 0.15639146 | AF97: 0.15639146 | AG97: 0.15639146 | AH97: 0.15639146 | AI97: 0.15639146 | AJ97: 0.15639146 | AK97: 0.15639146 | AL97: 0.15639146 | AM97: 0.15639146 | AN97: 0.15639146 | AO97: 0.15639146 | AP97: 0.15639146 | AQ97: 0.15639146
... K114: Residential PV - Class 1 | L114: Conservative | M114: 0.18463784 | N114: 0.18463784 | O114: 0.18463784 | P114: 0.18463784 | Q114: 0.18463784 | R114: 0.18463784 | S114: 0.18463784 | T114: 0.18463784 | U114: 0.18463784 | V114: 0.18463784 | W114: 0.18463784 | X114: 0.18479496 | Y114: 0.18495208 | Z114: 0.18510919 | AA114: 0.18526631 | AB114: 0.18542343 | AC114: 0.18558054 | AD114: 0.18573766 | AE114: 0.18589478 | AF114: 0.18605189 | AG114: 0.18620901 | AH114: 0.18636613 | AI114: 0.18652324 | AJ114: 0.18668036 | AK114: 0.18683748 | AL114: 0.18699459 | AM114: 0.18715171 | AN114: 0.18730882 | AO114: 0.18746594 | AP114: 0.18762306 | AQ114: 0.18778017
M116: 2020 | N116: 2021 | O116: 2022 | P116: 2023 | Q116: 2024 | R116: 2025 | S116: 2026 | T116: 2027 | U116: 2028 | V116: 2029 | W116: 2030 | X116: 2031 | Y116: 2032 | Z116: 2033 | AA116: 2034 | AB116: 2035 | AC116: 2036 | AD116: 2037 | AE116: 2038 | AF116: 2039 | AG116: 2040 | AH116: 2041 | AI116: 2042 | AJ116: 2043 | AK116: 2044 | AL116: 2045 | AM116: 2046 | AN116: 2047 | AO116: 2048 | AP116: 2049 | AQ116: 2050
J117: Annual Energy Production (kWh/kW) | K117: Residential PV - Class 10 | L117: Advanced | M117: =M85*8760 -> 1052.351 | N117: =N85*8760 -> 1056.4755 | O117: =O85*8760 -> 1060.6001 | P117: =P85*8760 -> 1064.7246 | Q117: =Q85*8760 -> 1068.8491 | R117: =R85*8760 -> 1072.9736 | S117: =S85*8760 -> 1077.0981 | T117: =T85*8760 -> 1081.2227 | ... AQ117: =AQ85*8760 -> 1093.5962
K118: Residential PV - Class 10 | L118: Moderate | M118: =M86*8760 -> 1049.8483 | N118: =N86*8760 -> 1051.4701 | O118: =O86*8760 -> 1053.0918 | P118: =P86*8760 -> 1054.7136 | Q118: =Q86*8760 -> 1056.3354 | R118: =R86*8760 -> 1057.9572 | S118: =S86*8760 -> 1059.579 | T118: =T86*8760 -> 1061.2008 | ... AQ118: =AQ86*8760 -> 1093.5962
K119: Residential PV - Class 10 | L119: Conservative | M119: =M87*8760 -> 1048.2265 | N119: =N87*8760 -> 1048.2265 | O119: =O87*8760 -> 1048.2265 | P119: =P87*8760 -> 1048.2265 | Q119: =Q87*8760 -> 1048.2265 | R119: =R87*8760 -> 1048.2265 | S119: =S87*8760 -> 1048.2265 | T119: =T87*8760 -> 1048.2265 | ... AQ119: =AQ87*8760 -> 1066.0661
K120: Residential PV - Class 9 | L120: Advanced | M120: =M88*8760 -> 1152.6827 | N120: =N88*8760 -> 1157.2004 | O120: =O88*8760 -> 1161.7182 | P120: =P88*8760 -> 1166.2359 | Q120: =Q88*8760 -> 1170.7537 | R120: =R88*8760 -> 1175.2715 | S120: =S88*8760 -> 1179.7892 | T120: =T88*8760 -> 1184.307 | ... AQ120: =AQ88*8760 -> 1197.8602
K121: Residential PV - Class 9 | L121: Moderate | M121: =M89*8760 -> 1149.9413 | N121: =N89*8760 -> 1151.7177 | O121: =O89*8760 -> 1153.4941 | P121: =P89*8760 -> 1155.2705 | Q121: =Q89*8760 -> 1157.047 | R121: =R89*8760 -> 1158.8234 | S121: =S89*8760 -> 1160.5998 | T121: =T89*8760 -> 1162.3762 | ... AQ121: =AQ89*8760 -> 1197.8602
K122: Residential PV - Class 9 | L122: Conservative | M122: =M90*8760 -> 1148.1649 | N122: =N90*8760 -> 1148.1649 | O122: =O90*8760 -> 1148.1649 | P122: =P90*8760 -> 1148.1649 | Q122: =Q90*8760 -> 1148.1649 | R122: =R90*8760 -> 1148.1649 | S122: =S90*8760 -> 1148.1649 | T122: =T90*8760 -> 1148.1649 | ... AQ122: =AQ90*8760 -> 1167.7054
K123: Residential PV - Class 8 | L123: Advanced | M123: =M91*8760 -> 1200.4679 | N123: =N91*8760 -> 1205.1729 | O123: =O91*8760 -> 1209.8779 | P123: =P91*8760 -> 1214.583 | Q123: =Q91*8760 -> 1219.288 | R123: =R91*8760 -> 1223.9931 | S123: =S91*8760 -> 1228.6981 | T123: =T91*8760 -> 1233.4032 | ... AQ123: =AQ91*8760 -> 1247.5183
K124: Residential PV - Class 8 | L124: Moderate | M124: =M92*8760 -> 1197.6129 | N124: =N92*8760 -> 1199.4629 | O124: =O92*8760 -> 1201.313 | P124: =P92*8760 -> 1203.163 | Q124: =Q92*8760 -> 1205.0131 | R124: =R92*8760 -> 1206.8631 | S124: =S92*8760 -> 1208.7132 | T124: =T92*8760 -> 1210.5632 | ... AQ124: =AQ92*8760 -> 1247.5183
K125: Residential PV - Class 8 | L125: Conservative | M125: =M93*8760 -> 1195.7628 | N125: =N93*8760 -> 1195.7628 | O125: =O93*8760 -> 1195.7628 | P125: =P93*8760 -> 1195.7628 | Q125: =Q93*8760 -> 1195.7628 | R125: =R93*8760 -> 1195.7628 | S125: =S93*8760 -> 1195.7628 | T125: =T93*8760 -> 1195.7628 | ... AQ125: =AQ93*8760 -> 1216.1134
K126: Residential PV - Class 7 | L126: Advanced | M126: =M94*8760 -> 1260.1994 | N126: =N94*8760 -> 1265.1385 | O126: =O94*8760 -> 1270.0777 | P126: =P94*8760 -> 1275.0168 | Q126: =Q94*8760 -> 1279.956 | R126: =R94*8760 -> 1284.8951 | S126: =S94*8760 -> 1289.8343 | T126: =T94*8760 -> 1294.7734 | ... AQ126: =AQ94*8760 -> 1309.5909
K127: Residential PV - Class 7 | L127: Moderate | M127: =M95*8760 -> 1257.2023 | N127: =N95*8760 -> 1259.1444 | O127: =O95*8760 -> 1261.0865 | P127: =P95*8760 -> 1263.0286 | Q127: =Q95*8760 -> 1264.9707 | R127: =R95*8760 -> 1266.9128 | S127: =S95*8760 -> 1268.8549 | T127: =T95*8760 -> 1270.797 | ... AQ127: =AQ95*8760 -> 1309.5909
K128: Residential PV - Class 7 | L128: Conservative | M128: =M96*8760 -> 1255.2602 | N128: =N96*8760 -> 1255.2602 | O128: =O96*8760 -> 1255.2602 | P128: =P96*8760 -> 1255.2602 | Q128: =Q96*8760 -> 1255.2602 | R128: =R96*8760 -> 1255.2602 | S128: =S96*8760 -> 1255.2602 | T128: =T96*8760 -> 1255.2602 | ... AQ128: =AQ96*8760 -> 1276.6234
K129: Residential PV - Class 6 | L129: Advanced | M129: =M97*8760 -> 1318.3197 | N129: =N97*8760 -> 1323.4867 | O129: =O97*8760 -> 1328.6536 | P129: =P97*8760 -> 1333.8206 | Q129: =Q97*8760 -> 1338.9875 | R129: =R97*8760 -> 1344.1544 | S129: =S97*8760 -> 1349.3214 | T129: =T97*8760 -> 1354.4883 | ... AQ129: =AQ97*8760 -> 1369.9892
... K146: Residential PV - Class 1 | L146: Conservative | M146: =M114*8760 -> 1617.4275 | N146: =N114*8760 -> 1617.4275 | O146: =O114*8760 -> 1617.4275 | P146: =P114*8760 -> 1617.4275 | Q146: =Q114*8760 -> 1617.4275 | R146: =R114*8760 -> 1617.4275 | S146: =S114*8760 -> 1617.4275 | T146: =T114*8760 -> 1617.4275 | ... AQ146: =AQ114*8760 -> 1644.9543
M148: 2020 | N148: 2021 | O148: 2022 | P148: 2023 | Q148: 2024 | R148: 2025 | S148: 2026 | T148: 2027 | U148: 2028 | V148: 2029 | W148: 2030 | X148: 2031 | Y148: 2032 | Z148: 2033 | AA148: 2034 | AB148: 2035 | AC148: 2036 | AD148: 2037 | AE148: 2038 | AF148: 2039 | AG148: 2040 | AH148: 2041 | AI148: 2042 | AJ148: 2043 | AK148: 2044 | AL148: 2045 | AM148: 2046 | AN148: 2047 | AO148: 2048 | AP148: 2049 | AQ148: 2050
J149: CAPEX ($/kW) | K149: Residential PV - Class 10 | L149: Advanced | M149: =M$376*( M181+M278) -> 2743.333 | N149: =N$376*( N181+N278) -> 2650 | O149: =O$376*( O181+O278) -> 2443.4533 | P149: =P$376*( P181+P278) -> 2236.9065 | Q149: =Q$376*( Q181+Q278) -> 2030.3598 | R149: =R$376*( R181+R278) -> 1823.813 | S149: =S$376*( S181+S278) -> 1617.2663 | T149: =T$376*( T181+T278) -> 1410.7195 | ... AQ149: =AQ$376*( AQ181+AQ278) -> 550.38018
K150: Residential PV - Class 10 | L150: Moderate | M150: =M$377*( M182+M279) -> 2743.333 | N150: =N$377*( N182+N279) -> 2650 | O150: =O$377*( O182+O279) -> 2468.4921 | P150: =P$377*( P182+P279) -> 2286.9841 | Q150: =Q$377*( Q182+Q279) -> 2105.4762 | R150: =R$377*( R182+R279) -> 1923.9683 | S150: =S$377*( S182+S279) -> 1742.4603 | T150: =T$377*( T182+T279) -> 1560.9524 | ... AQ150: =AQ$377*( AQ182+AQ279) -> 791.07932
K151: Residential PV - Class 10 | L151: Conservative | M151: =M$378*( M183+M280) -> 2743.333 | N151: =N$378*( N183+N280) -> 2650 | O151: =O$378*( O183+O280) -> 2609.4919 | P151: =P$378*( P183+P280) -> 2568.9839 | Q151: =Q$378*( Q183+Q280) -> 2528.4758 | R151: =R$378*( R183+R280) -> 2487.9677 | S151: =S$378*( S183+S280) -> 2447.4596 | T151: =T$378*( T183+T280) -> 2406.9516 | ... AQ151: =AQ$378*( AQ183+AQ280) -> 1016.4286
K152: Residential PV - Class 9 | L152: Advanced | M152: =M$376*( M184+M281) -> 2743.333 | N152: =N$376*( N184+N281) -> 2650 | O152: =O$376*( O184+O281) -> 2443.4533 | P152: =P$376*( P184+P281) -> 2236.9065 | Q152: =Q$376*( Q184+Q281) -> 2030.3598 | R152: =R$376*( R184+R281) -> 1823.813 | S152: =S$376*( S184+S281) -> 1617.2663 | T152: =T$376*( T184+T281) -> 1410.7195 | ... AQ152: =AQ$376*( AQ184+AQ281) -> 550.38018
K153: Residential PV - Class 9 | L153: Moderate | M153: =M$377*( M185+M282) -> 2743.333 | N153: =N$377*( N185+N282) -> 2650 | O153: =O$377*( O185+O282) -> 2468.4921 | P153: =P$377*( P185+P282) -> 2286.9841 | Q153: =Q$377*( Q185+Q282) -> 2105.4762 | R153: =R$377*( R185+R282) -> 1923.9683 | S153: =S$377*( S185+S282) -> 1742.4603 | T153: =T$377*( T185+T282) -> 1560.9524 | ... AQ153: =AQ$377*( AQ185+AQ282) -> 791.07932
K154: Residential PV - Class 9 | L154: Conservative | M154: =M$378*( M186+M283) -> 2743.333 | N154: =N$378*( N186+N283) -> 2650 | O154: =O$378*( O186+O283) -> 2609.4919 | P154: =P$378*( P186+P283) -> 2568.9839 | Q154: =Q$378*( Q186+Q283) -> 2528.4758 | R154: =R$378*( R186+R283) -> 2487.9677 | S154: =S$378*( S186+S283) -> 2447.4596 | T154: =T$378*( T186+T283) -> 2406.9516 | ... AQ154: =AQ$378*( AQ186+AQ283) -> 1016.4286
K155: Residential PV - Class 8 | L155: Advanced | M155: =M$376*( M187+M284) -> 2743.333 | N155: =N$376*( N187+N284) -> 2650 | O155: =O$376*( O187+O284) -> 2443.4533 | P155: =P$376*( P187+P284) -> 2236.9065 | Q155: =Q$376*( Q187+Q284) -> 2030.3598 | R155: =R$376*( R187+R284) -> 1823.813 | S155: =S$376*( S187+S284) -> 1617.2663 | T155: =T$376*( T187+T284) -> 1410.7195 | ... AQ155: =AQ$376*( AQ187+AQ284) -> 550.38018
K156: Residential PV - Class 8 | L156: Moderate | M156: =M$377*( M188+M285) -> 2743.333 | N156: =N$377*( N188+N285) -> 2650 | O156: =O$377*( O188+O285) -> 2468.4921 | P156: =P$377*( P188+P285) -> 2286.9841 | Q156: =Q$377*( Q188+Q285) -> 2105.4762 | R156: =R$377*( R188+R285) -> 1923.9683 | S156: =S$377*( S188+S285) -> 1742.4603 | T156: =T$377*( T188+T285) -> 1560.9524 | ... AQ156: =AQ$377*( AQ188+AQ285) -> 791.07932
...

Sheet DSCF
B1: 2019 | C1: 2020 | D1: 2021 | E1: 2022 | F1: 2023 | G1: 2024 | H1: 2025 | I1: 2026 | J1: 2027 | K1: 2028 | L1: 2029 | M1: 2030 | N1: 2031 | O1: 2032 | P1: 2033 | Q1: 2034 | R1: 2035 | S1: 2036 | T1: 2037 | U1: 2038 | V1: 2039 | W1: 2040 | X1: 2041 | Y1: 2042 | Z1: 2043 | AA1: 2044 | AB1: 2045 | AC1: 2046 | AD1: 2047 | AE1: 2048 | AF1: 2049 | AG1: 2050
A2: Capacity Factor (dimensionless) | B2: =AVERAGE('Solar - PV Dist. Res 2021'!L5,'Solar - PV Dist. Res 2021'!L8,'Solar - PV Dist. Res 2021'!L11,'Solar - PV Dist. Res 2021'!L14,'Solar - PV Dist. Res 2021'!L17,'Solar - PV Dist. Res 2021'!L20,'Solar - PV Dist. Res 2021'!L23,'Solar - PV Dist. Res 2021'!L26,'Solar - PV Dist. Res 2021'!L29,'Solar - PV Dist. Res 2021'!L32) -> 0.15284766 | C2: =AVERAGE('Solar - PV Dist. Res 2022'!M86,'Solar - PV Dist. Res 2022'!M89,'Solar - PV Dist. Res 2022'!M92,'Solar - PV Dist. Res 2022'!M95,'Solar - PV Dist. Res 2022'!M98,'Solar - PV Dist. Res 2022'!M101,'Solar - PV Dist. Res 2022'!M104,'Solar - PV Dist. Res 2022'!M107,'Solar - PV Dist. Res 2022'!M110,'Solar - PV Dist. Res 2022'!M113) -> 0.15308415 | D2: =AVERAGE('Solar - PV Dist. Res 2022'!N86,'Solar - PV Dist. Res 2022'!N89,'Solar - PV Dist. Res 2022'!N92,'Solar - PV Dist. Res 2022'!N95,'Solar - PV Dist. Res 2022'!N98,'Solar - PV Dist. Res 2022'!N101,'Solar - PV Dist. Res 2022'!N104,'Solar - PV Dist. Res 2022'!N107,'Solar - PV Dist. Res 2022'!N110,'Solar - PV Dist. Res 2022'!N113) -> 0.15332063 | E2: =AVERAGE('Solar - PV Dist. Res 2022'!O86,'Solar - PV Dist. Res 2022'!O89,'Solar - PV Dist. Res 2022'!O92,'Solar - PV Dist. Res 2022'!O95,'Solar - PV Dist. Res 2022'!O98,'Solar - PV Dist. Res 2022'!O101,'Solar - PV Dist. Res 2022'!O104,'Solar - PV Dist. Res 2022'!O107,'Solar - PV Dist. Res 2022'!O110,'Solar - PV Dist. Res 2022'!O113) -> 0.15355711 | F2: =AVERAGE('Solar - PV Dist. Res 2022'!P86,'Solar - PV Dist. Res 2022'!P89,'Solar - PV Dist. Res 2022'!P92,'Solar - PV Dist. Res 2022'!P95,'Solar - PV Dist. Res 2022'!P98,'Solar - PV Dist. Res 2022'!P101,'Solar - PV Dist. Res 2022'!P104,'Solar - PV Dist. Res 2022'!P107,'Solar - PV Dist. Res 2022'!P110,'Solar - PV Dist. Res 2022'!P113) -> 0.15379359 | G2: =AVERAGE('Solar - PV Dist. Res 2022'!Q86,'Solar - PV Dist. Res 2022'!Q89,'Solar - PV Dist. Res 2022'!Q92,'Solar - PV Dist. Res 2022'!Q95,'Solar - PV Dist. Res 2022'!Q98,'Solar - PV Dist. Res 2022'!Q101,'Solar - PV Dist. Res 2022'!Q104,'Solar - PV Dist. Res 2022'!Q107,'Solar - PV Dist. Res 2022'!Q110,'Solar - PV Dist. Res 2022'!Q113) -> 0.15403007 | H2: =AVERAGE('Solar - PV Dist. Res 2022'!R86,'Solar - PV Dist. Res 2022'!R89,'Solar - PV Dist. Res 2022'!R92,'Solar - PV Dist. Res 2022'!R95,'Solar - PV Dist. Res 2022'!R98,'Solar - PV Dist. Res 2022'!R101,'Solar - PV Dist. Res 2022'!R104,'Solar - PV Dist. Res 2022'!R107,'Solar - PV Dist. Res 2022'!R110,'Solar - PV Dist. Res 2022'!R113) -> 0.15426655 | I2: =AVERAGE('Solar - PV Dist. Res 2022'!S86,'Solar - PV Dist. Res 2022'!S89,'Solar - PV Dist. Res 2022'!S92,'Solar - PV Dist. Res 2022'!S95,'Solar - PV Dist. Res 2022'!S98,'Solar - PV Dist. Res 2022'!S101,'Solar - PV Dist. Res 2022'!S104,'Solar - PV Dist. Res 2022'!S107,'Solar - PV Dist. Res 2022'!S110,'Solar - PV Dist. Res 2022'!S113) -> 0.15450303 | J2: =AVERAGE('Solar - PV Dist. Res 2022'!T86,'Solar - PV Dist. Res 2022'!T89,'Solar - PV Dist. Res 2022'!T92,'Solar - PV Dist. Res 2022'!T95,'Solar - PV Dist. Res 2022'!T98,'Solar - PV Dist. Res 2022'!T101,'Solar - PV Dist. Res 2022'!T104,'Solar - PV Dist. Res 2022'!T107,'Solar - PV Dist. Res 2022'!T110,'Solar - PV Dist. Res 2022'!T113) -> 0.15473952 | ... AG2: =AVERAGE('Solar - PV Dist. Res 2022'!AQ86,'Solar - PV Dist. Res 2022'!AQ89,'Solar - PV Dist. Res 2022'!AQ92,'Solar - PV Dist. Res 2022'!AQ95,'Solar - PV Dist. Res 2022'!AQ98,'Solar - PV Dist. Res 2022'!AQ101,'Solar - PV Dist. Res 2022'!AQ104,'Solar - PV Dist. Res 2022'!AQ107,'Solar - PV Dist. Res 2022'!AQ110,'Solar - PV Dist. Res 2022'!AQ113) -> 0.15946328
A3: Capacity Factor (dimensionless) | B3: 0.129 | C3: 0.129 | D3: 0.129 | E3: 0.129 | F3: 0.129 | G3: 0.129 | H3: 0.129 | I3: 0.129 | J3: 0.129 | K3: 0.129 | L3: 0.129 | M3: 0.129 | N3: 0.129 | O3: 0.129 | P3: 0.129 | Q3: 0.129 | R3: 0.129 | S3: 0.129 | T3: 0.129 | U3: 0.129 | V3: 0.129 | W3: 0.129 | X3: 0.129 | Y3: 0.129 | Z3: 0.129 | AA3: 0.129 | AB3: 0.129 | AC3: 0.129 | AD3: 0.129 | AE3: 0.129 | AF3: 0.129 | AG3: 0.129
