Workbook

Sheet About
A1: BSoFPtiT BAU Share of Fuel Price that is Tax
A3: Source: | B3: Petroleum Gasoline, Petroleum Diesel, Jet Fuel Tax
B4: Hydrocarbon Oil
B5: 2016
B6: Customs and Excise Department: The Government of the Hong Kong Special Administrative Region
B7: https://web.archive.org/web/20161006230240/http://www.customs.gov.hk/en/trade_facilitation/dutiable/types/index.html#methyl_alcohol
B9: Sales Tax
B10: Taxation and Investment in Hong Kong 2016
B11: 2016
B12: Deloitte
B13: https://www2.deloitte.com/content/dam/Deloitte/global/Documents/Tax/dttl-tax-hongkongguide-2016.pdf
B15: Fuels
B16: Value Added Tax (VAT) Rates
B17: 2019
B18: PwC
B19: http://taxsummaries.pwc.com/ID/Value-added-tax-(VAT)-rates
B21: Price Board
B22: 2019
B23: Shell
B24: https://www.shell.com.hk/en_hk/motorists/shell-fuels/price-board.html
B26: List Price Adjustment
B27: 2019
B28: Sinopec
B29: http://www.sinopechk.com/oilprice.aspx
B31: Fuel Prices
B32: 2019
B33: Caltex
B34: https://www.caltex.com/hk/en/motorists/products-and-services/fuel-prices.html
A36: Notes
A37: Tax rate projections have only been located for petroleum gasoline, petroleum diesel, and jet fuel.
A38: We assume biofuel gasoline is taxed at the same rate as petroleum gasoline and biofuel diesel
A39: is taxed at the same rate as petroleum diesel.
A40: For all other fuels, we assume the national average sales tax rate.
A41: We assume years after 2018 to be like 2018, because in the BAU case, we don't assume the expiration or change of any laws
A43: Hong Kong does not levy a sales tax on goods and services-Deloitte
A45: The tax rate for petroleum gasoline is calculated based on average petrol prices from various providers (Caltex, Shell, Sinopec) operating in Kong Kong.

Sheet Tax Rates
A2: rate= | B2: tax/(end user price-tax)
B4: HK Tax | C4: avg | D4: Sinopeck | F4: Rate
A5: Aircraft spirit | B5: 6.51 | D5: 4 | F5: =B5/D5 -> 1.6275
A6: Motor spirit (leaded petrol) | B6: 6.82
A7: Motor spirit (unleaded petrol) | B7: 6.06 | C7: =AVERAGE(B15,D15,E15) -> 21.656667 | D7: 24.19 | F7: =B7/D7 -> 0.25051674
A8: Light diesel oil | B8: 2.89 | C8: =(B16+E16+D16)/3 -> 20.926667 | D8: 22.9 | E8: marine | F8: =B8/D8 -> 0.12620087
A9: Ultra Low Sulphur diesel | B9: 2.89 | D9: 20.7 | F9: =B9/D9 -> 0.13961353
A10: Euro V diesel | B10: 0 | D10: 21.85 | F10: =B10/D10 -> 0
B13: Sinopec | D13: Caltex | E13: Shell
A14: Sino X Power | B14: 25.23 | C14: Platinum | D14: 14.15 | E14: 25.5 | F14: Shell V-Power*
A15: Sino Power | B15: 24.04 | C15: Gold | D15: 16.74 | E15: 24.19 | F15: Shell FuelSave Unleaded*
A16: Sino Diesel | B16: 22.35 | C16: Caltex Diesel | D16: 17.93 | E16: 22.5 | F16: Shell FuelSave Diesel
A17: * Inc. Government Excise Duty HK$6.06/ Litre
A19: Avg Sales Tax Rate
A20: 0

Sheet BSoFPtiT
A1: Year | B1: 2016 | C1: 2017 | D1: 2018 | E1: 2019 | F1: 2020 | G1: 2021 | H1: 2022 | I1: 2023 | J1: 2024 | K1: 2025 | L1: 2026 | M1: 2027 | N1: 2028 | O1: 2029 | P1: 2030 | Q1: 2031 | R1: 2032 | S1: 2033 | T1: 2034 | U1: 2035 | V1: 2036 | W1: 2037 | X1: 2038 | Y1: 2039 | Z1: 2040 | AA1: 2041 | AB1: 2042 | AC1: 2043 | AD1: 2044 | AE1: 2045 | AF1: 2046 | AG1: 2047 | AH1: 2048 | AI1: 2049 | AJ1: 2050
A2: electricity | B2: ='Tax Rates'!$A$20 -> 0 | C2: ='Tax Rates'!$A$20 -> 0 | D2: ='Tax Rates'!$A$20 -> 0 | E2: ='Tax Rates'!$A$20 -> 0 | F2: ='Tax Rates'!$A$20 -> 0 | G2: ='Tax Rates'!$A$20 -> 0 | H2: ='Tax Rates'!$A$20 -> 0 | I2: ='Tax Rates'!$A$20 -> 0 | ... AJ2: ='Tax Rates'!$A$20 -> 0
A3: hard coal | B3: ='Tax Rates'!$A$20 -> 0 | C3: ='Tax Rates'!$A$20 -> 0 | D3: ='Tax Rates'!$A$20 -> 0 | E3: ='Tax Rates'!$A$20 -> 0 | F3: ='Tax Rates'!$A$20 -> 0 | G3: ='Tax Rates'!$A$20 -> 0 | H3: ='Tax Rates'!$A$20 -> 0 | I3: ='Tax Rates'!$A$20 -> 0 | ... AJ3: ='Tax Rates'!$A$20 -> 0
A4: natural gas | B4: ='Tax Rates'!$A$20 -> 0 | C4: ='Tax Rates'!$A$20 -> 0 | D4: ='Tax Rates'!$A$20 -> 0 | E4: ='Tax Rates'!$A$20 -> 0 | F4: ='Tax Rates'!$A$20 -> 0 | G4: ='Tax Rates'!$A$20 -> 0 | H4: ='Tax Rates'!$A$20 -> 0 | I4: ='Tax Rates'!$A$20 -> 0 | ... AJ4: ='Tax Rates'!$A$20 -> 0
A5: nuclear | B5: ='Tax Rates'!$A$20 -> 0 | C5: ='Tax Rates'!$A$20 -> 0 | D5: ='Tax Rates'!$A$20 -> 0 | E5: ='Tax Rates'!$A$20 -> 0 | F5: ='Tax Rates'!$A$20 -> 0 | G5: ='Tax Rates'!$A$20 -> 0 | H5: ='Tax Rates'!$A$20 -> 0 | I5: ='Tax Rates'!$A$20 -> 0 | ... AJ5: ='Tax Rates'!$A$20 -> 0
A6: hydro (does not use fuel) | B6: ='Tax Rates'!$A$20 -> 0 | C6: ='Tax Rates'!$A$20 -> 0 | D6: ='Tax Rates'!$A$20 -> 0 | E6: ='Tax Rates'!$A$20 -> 0 | F6: ='Tax Rates'!$A$20 -> 0 | G6: ='Tax Rates'!$A$20 -> 0 | H6: ='Tax Rates'!$A$20 -> 0 | I6: ='Tax Rates'!$A$20 -> 0 | ... AJ6: ='Tax Rates'!$A$20 -> 0
A7: wind (does not use fuel) | B7: ='Tax Rates'!$A$20 -> 0 | C7: ='Tax Rates'!$A$20 -> 0 | D7: ='Tax Rates'!$A$20 -> 0 | E7: ='Tax Rates'!$A$20 -> 0 | F7: ='Tax Rates'!$A$20 -> 0 | G7: ='Tax Rates'!$A$20 -> 0 | H7: ='Tax Rates'!$A$20 -> 0 | I7: ='Tax Rates'!$A$20 -> 0 | ... AJ7: ='Tax Rates'!$A$20 -> 0
A8: solar (does not use fuel) | B8: ='Tax Rates'!$A$20 -> 0 | C8: ='Tax Rates'!$A$20 -> 0 | D8: ='Tax Rates'!$A$20 -> 0 | E8: ='Tax Rates'!$A$20 -> 0 | F8: ='Tax Rates'!$A$20 -> 0 | G8: ='Tax Rates'!$A$20 -> 0 | H8: ='Tax Rates'!$A$20 -> 0 | I8: ='Tax Rates'!$A$20 -> 0 | ... AJ8: ='Tax Rates'!$A$20 -> 0
A9: biomass | B9: ='Tax Rates'!$A$20 -> 0 | C9: ='Tax Rates'!$A$20 -> 0 | D9: ='Tax Rates'!$A$20 -> 0 | E9: ='Tax Rates'!$A$20 -> 0 | F9: ='Tax Rates'!$A$20 -> 0 | G9: ='Tax Rates'!$A$20 -> 0 | H9: ='Tax Rates'!$A$20 -> 0 | I9: ='Tax Rates'!$A$20 -> 0 | ... AJ9: ='Tax Rates'!$A$20 -> 0
A10: petroleum gasoline | B10: ='Tax Rates'!F7 -> 0.25051674 | C10: =$B10 -> 0.25051674 | D10: =$B10 -> 0.25051674 | E10: =$B10 -> 0.25051674 | F10: =$B10 -> 0.25051674 | G10: =$B10 -> 0.25051674 | H10: =$B10 -> 0.25051674 | I10: =$B10 -> 0.25051674 | J10: =$B10 -> 0.25051674 | ... AJ10: =$B10 -> 0.25051674
A11: petroleum diesel | B11: ='Tax Rates'!F9 -> 0.13961353 | C11: ='Tax Rates'!$F9 -> 0.13961353 | D11: ='Tax Rates'!$F9 -> 0.13961353 | E11: ='Tax Rates'!$F9 -> 0.13961353 | F11: ='Tax Rates'!$F9 -> 0.13961353 | G11: ='Tax Rates'!$F9 -> 0.13961353 | H11: ='Tax Rates'!$F9 -> 0.13961353 | I11: ='Tax Rates'!$F9 -> 0.13961353 | J11: ='Tax Rates'!$F9 -> 0.13961353 | ... AJ11: ='Tax Rates'!$F9 -> 0.13961353
A12: biofuel gasoline | B12: =B10 -> 0.25051674 | C12: =$B10 -> 0.25051674 | D12: =$B10 -> 0.25051674 | E12: =$B10 -> 0.25051674 | F12: =$B10 -> 0.25051674 | G12: =$B10 -> 0.25051674 | H12: =$B10 -> 0.25051674 | I12: =$B10 -> 0.25051674 | J12: =$B10 -> 0.25051674 | ... AJ12: =$B10 -> 0.25051674
A13: biofuel diesel | B13: =B11 -> 0.13961353 | C13: =$B11 -> 0.13961353 | D13: =$B11 -> 0.13961353 | E13: =$B11 -> 0.13961353 | F13: =$B11 -> 0.13961353 | G13: =$B11 -> 0.13961353 | H13: =$B11 -> 0.13961353 | I13: =$B11 -> 0.13961353 | J13: =$B11 -> 0.13961353 | ... AJ13: =$B11 -> 0.13961353
A14: jet fuel | B14: ='Tax Rates'!F5 -> 1.6275 | C14: ='Tax Rates'!$F5 -> 1.6275 | D14: ='Tax Rates'!$F5 -> 1.6275 | E14: ='Tax Rates'!$F5 -> 1.6275 | F14: ='Tax Rates'!$F5 -> 1.6275 | G14: ='Tax Rates'!$F5 -> 1.6275 | H14: ='Tax Rates'!$F5 -> 1.6275 | I14: ='Tax Rates'!$F5 -> 1.6275 | J14: ='Tax Rates'!$F5 -> 1.6275 | ... AJ14: ='Tax Rates'!$F5 -> 1.6275
A15: heat | B15: ='Tax Rates'!$A$20 -> 0 | C15: ='Tax Rates'!$A$20 -> 0 | D15: ='Tax Rates'!$A$20 -> 0 | E15: ='Tax Rates'!$A$20 -> 0 | F15: ='Tax Rates'!$A$20 -> 0 | G15: ='Tax Rates'!$A$20 -> 0 | H15: ='Tax Rates'!$A$20 -> 0 | I15: ='Tax Rates'!$A$20 -> 0 | ... AJ15: ='Tax Rates'!$A$20 -> 0
A16: geothermal (does not use fuel) | B16: ='Tax Rates'!$A$20 -> 0 | C16: ='Tax Rates'!$A$20 -> 0 | D16: ='Tax Rates'!$A$20 -> 0 | E16: ='Tax Rates'!$A$20 -> 0 | F16: ='Tax Rates'!$A$20 -> 0 | G16: ='Tax Rates'!$A$20 -> 0 | H16: ='Tax Rates'!$A$20 -> 0 | I16: ='Tax Rates'!$A$20 -> 0 | ... AJ16: ='Tax Rates'!$A$20 -> 0
A17: lignite | B17: ='Tax Rates'!$A$20 -> 0 | C17: ='Tax Rates'!$A$20 -> 0 | D17: ='Tax Rates'!$A$20 -> 0 | E17: ='Tax Rates'!$A$20 -> 0 | F17: ='Tax Rates'!$A$20 -> 0 | G17: ='Tax Rates'!$A$20 -> 0 | H17: ='Tax Rates'!$A$20 -> 0 | I17: ='Tax Rates'!$A$20 -> 0 | ... AJ17: ='Tax Rates'!$A$20 -> 0
A18: crude oil | B18: 0 | C18: 0 | D18: 0 | E18: 0 | F18: 0 | G18: 0 | H18: 0 | I18: 0 | J18: 0 | K18: 0 | L18: 0 | M18: 0 | N18: 0 | O18: 0 | P18: 0 | Q18: 0 | R18: 0 | S18: 0 | T18: 0 | U18: 0 | V18: 0 | W18: 0 | X18: 0 | Y18: 0 | Z18: 0 | AA18: 0 | AB18: 0 | AC18: 0 | AD18: 0 | AE18: 0 | AF18: 0 | AG18: 0 | AH18: 0 | AI18: 0 | AJ18: 0
A19: heavy fuel oil | B19: 0 | C19: 0 | D19: 0 | E19: 0 | F19: 0 | G19: 0 | H19: 0 | I19: 0 | J19: 0 | K19: 0 | L19: 0 | M19: 0 | N19: 0 | O19: 0 | P19: 0 | Q19: 0 | R19: 0 | S19: 0 | T19: 0 | U19: 0 | V19: 0 | W19: 0 | X19: 0 | Y19: 0 | Z19: 0 | AA19: 0 | AB19: 0 | AC19: 0 | AD19: 0 | AE19: 0 | AF19: 0 | AG19: 0 | AH19: 0 | AI19: 0 | AJ19: 0
A20: LPG propane or butane | B20: 0 | C20: 0 | D20: 0 | E20: 0 | F20: 0 | G20: 0 | H20: 0 | I20: 0 | J20: 0 | K20: 0 | L20: 0 | M20: 0 | N20: 0 | O20: 0 | P20: 0 | Q20: 0 | R20: 0 | S20: 0 | T20: 0 | U20: 0 | V20: 0 | W20: 0 | X20: 0 | Y20: 0 | Z20: 0 | AA20: 0 | AB20: 0 | AC20: 0 | AD20: 0 | AE20: 0 | AF20: 0 | AG20: 0 | AH20: 0 | AI20: 0 | AJ20: 0
A21: municipal solid waste | B21: 0 | C21: 0 | D21: 0 | E21: 0 | F21: 0 | G21: 0 | H21: 0 | I21: 0 | J21: 0 | K21: 0 | L21: 0 | M21: 0 | N21: 0 | O21: 0 | P21: 0 | Q21: 0 | R21: 0 | S21: 0 | T21: 0 | U21: 0 | V21: 0 | W21: 0 | X21: 0 | Y21: 0 | Z21: 0 | AA21: 0 | AB21: 0 | AC21: 0 | AD21: 0 | AE21: 0 | AF21: 0 | AG21: 0 | AH21: 0 | AI21: 0 | AJ21: 0
A22: hydrogen | B22: 0 | C22: 0 | D22: 0 | E22: 0 | F22: 0 | G22: 0 | H22: 0 | I22: 0 | J22: 0 | K22: 0 | L22: 0 | M22: 0 | N22: 0 | O22: 0 | P22: 0 | Q22: 0 | R22: 0 | S22: 0 | T22: 0 | U22: 0 | V22: 0 | W22: 0 | X22: 0 | Y22: 0 | Z22: 0 | AA22: 0 | AB22: 0 | AC22: 0 | AD22: 0 | AE22: 0 | AF22: 0 | AG22: 0 | AH22: 0 | AI22: 0 | AJ22: 0
